{
  "type": "Feature",
  "properties": {
    "gn:admin1_code":"64.0",
    "gn:asciiname":"Ban Nai Mong",
    "gn:country_code":"TH",
    "gn:dem":24,
    "gn:feature_class":"P",
    "gn:feature_code":"PPL",
    "gn:name":"Ban Nai Mong",
    "gn:population":0,
    "gn:timezone":"Asia/Bangkok",
    "iso:country":"TH",
    "name:tha_x_preferred":[
        "\u0e1a\u0e49\u0e32\u0e19\u0e43\u0e19\u0e2b\u0e21\u0e07"
    ],
    "wof:name":"Ban Nai Mong",
    "wof:placetype":"locality"
},
  "geometry": {"coordinates":[99.82449,8.49669],"type":"Point"}
}