{
  "type": "Feature",
  "properties": {
    "gn:admin1_code":"8.0",
    "gn:asciiname":"Ban Mae Khamu Noi",
    "gn:country_code":"TH",
    "gn:dem":214,
    "gn:feature_class":"P",
    "gn:feature_code":"PPL",
    "gn:name":"Ban Mae Khamu Noi",
    "gn:population":0,
    "gn:timezone":"Asia/Bangkok",
    "iso:country":"TH",
    "name:tha_x_preferred":[
        "\u0e1a\u0e49\u0e32\u0e19\u0e41\u0e21\u0e48\u0e02\u0e30\u0e21\u0e38\u0e19\u0e49\u0e2d\u0e22"
    ],
    "wof:name":"Ban Mae Khamu Noi",
    "wof:placetype":"locality"
},
  "geometry": {"coordinates":[98.3152,17.20703],"type":"Point"}
}