{
  "type": "Feature",
  "properties": {
    "gn:admin1_code":"57.0",
    "gn:asciiname":"Ban Thung Chan",
    "gn:country_code":"TH",
    "gn:dem":19,
    "gn:feature_class":"P",
    "gn:feature_code":"PPL",
    "gn:name":"Ban Thung Chan",
    "gn:population":0,
    "gn:timezone":"Asia/Bangkok",
    "iso:country":"TH",
    "name:tha_x_preferred":[
        "\u0e1a\u0e49\u0e32\u0e19\u0e17\u0e38\u0e48\u0e07\u0e08\u0e31\u0e19\u0e17\u0e23\u0e4c"
    ],
    "wof:name":"Ban Thung Chan",
    "wof:placetype":"locality"
},
  "geometry": {"coordinates":[99.43517,11.08844],"type":"Point"}
}