{
  "type": "Feature",
  "properties": {
    "gn:admin1_code":"27.0",
    "gn:asciiname":"Ban Tha Luang",
    "gn:country_code":"TH",
    "gn:dem":159,
    "gn:feature_class":"P",
    "gn:feature_code":"PPL",
    "gn:name":"Ban Tha Luang",
    "gn:population":0,
    "gn:timezone":"Asia/Bangkok",
    "iso:country":"TH",
    "name:tha_x_preferred":[
        "\u0e1a\u0e49\u0e32\u0e19\u0e17\u0e48\u0e32\u0e2b\u0e25\u0e27\u0e07"
    ],
    "name:und_x_variant":[
        "Tha Luang",
        "Ban Tha Luang"
    ],
    "wof:name":"Ban Tha Luang",
    "wof:placetype":"locality"
},
  "geometry": {"coordinates":[102.52811,15.25556],"type":"Point"}
}