{
  "type": "Feature",
  "properties": {
    "gn:admin1_code":"70.0",
    "gn:asciiname":"Ban To Thong",
    "gn:country_code":"TH",
    "gn:dem":17,
    "gn:feature_class":"P",
    "gn:feature_code":"PPL",
    "gn:name":"Ban To Thong",
    "gn:population":0,
    "gn:timezone":"Asia/Bangkok",
    "iso:country":"TH",
    "name:tha_x_preferred":[
        "\u0e1a\u0e49\u0e32\u0e19\u0e42\u0e15\u0e4a\u0e30\u0e17\u0e2d\u0e07"
    ],
    "wof:name":"Ban To Thong",
    "wof:placetype":"locality"
},
  "geometry": {"coordinates":[101.51220000000001,6.58164],"type":"Point"}
}