{
  "type": "Feature",
  "properties": {
    "gn:admin1_code":"22",
    "gn:asciiname":"Ban Bua Simma",
    "gn:country_code":"TH",
    "gn:dem":213,
    "gn:feature_class":"P",
    "gn:feature_code":"PPL",
    "gn:name":"Ban Bua Simma",
    "gn:population":0,
    "gn:timezone":"Asia/Bangkok",
    "iso:country":"TH",
    "name:tha_x_preferred":[
        "\u0e1a\u0e49\u0e32\u0e19\u0e1a\u0e31\u0e27\u0e2a\u0e34\u0e21\u0e21\u0e32"
    ],
    "wof:name":"Ban Bua Simma",
    "wof:placetype":"locality"
},
  "geometry": {"coordinates":[102.23,16.51017],"type":"Point"}
}