{
  "type": "Feature",
  "properties": {
    "gn:admin1_code":"75.0",
    "gn:asciiname":"Ban Mai Phasuk",
    "gn:country_code":"TH",
    "gn:dem":137,
    "gn:feature_class":"P",
    "gn:feature_code":"PPL",
    "gn:name":"Ban Mai Phasuk",
    "gn:population":0,
    "gn:timezone":"Asia/Bangkok",
    "iso:country":"TH",
    "name:tha_x_preferred":[
        "\u0e1a\u0e49\u0e32\u0e19\u0e43\u0e2b\u0e21\u0e48\u0e1c\u0e32\u0e2a\u0e38\u0e02"
    ],
    "wof:name":"Ban Mai Phasuk",
    "wof:placetype":"locality"
},
  "geometry": {"coordinates":[105.31264,15.12411],"type":"Point"}
}