{
  "type": "Feature",
  "properties": {
    "gn:admin1_code":"56.0",
    "gn:asciiname":"Ban Rai Makham",
    "gn:country_code":"TH",
    "gn:dem":14,
    "gn:feature_class":"P",
    "gn:feature_code":"PPL",
    "gn:name":"Ban Rai Makham",
    "gn:population":0,
    "gn:timezone":"Asia/Bangkok",
    "iso:country":"TH",
    "name:tha_x_preferred":[
        "\u0e1a\u0e49\u0e32\u0e19\u0e44\u0e23\u0e48\u0e21\u0e30\u0e02\u0e32\u0e21"
    ],
    "wof:name":"Ban Rai Makham",
    "wof:placetype":"locality"
},
  "geometry": {"coordinates":[99.94244,13.00792],"type":"Point"}
}