{
  "type": "Feature",
  "properties": {
    "gn:admin1_code":"10.0",
    "gn:asciiname":"Ban Huai Mun",
    "gn:country_code":"TH",
    "gn:dem":86,
    "gn:feature_class":"P",
    "gn:feature_code":"PPL",
    "gn:name":"Ban Huai Mun",
    "gn:population":0,
    "gn:timezone":"Asia/Bangkok",
    "iso:country":"TH",
    "name:tha_x_preferred":[
        "Ban Huai Mun"
    ],
    "name:tha_x_variant":[
        "\u0e1a\u0e49\u0e32\u0e19\u0e2b\u0e49\u0e27\u0e22\u0e21\u0e38\u0e48\u0e19"
    ],
    "wof:name":"Ban Huai Mun",
    "wof:placetype":"locality"
},
  "geometry": {"coordinates":[99.94468999999999,17.57394],"type":"Point"}
}