{
  "type": "Feature",
  "properties": {
    "gn:admin1_code":"12.0",
    "gn:asciiname":"Ban Phai Si Thong",
    "gn:country_code":"TH",
    "gn:dem":343,
    "gn:feature_class":"P",
    "gn:feature_code":"PPL",
    "gn:name":"Ban Phai Si Thong",
    "gn:population":0,
    "gn:timezone":"Asia/Bangkok",
    "iso:country":"TH",
    "name:tha_x_preferred":[
        "\u0e1a\u0e49\u0e32\u0e19\u0e44\u0e1c\u0e48\u0e2a\u0e35\u0e17\u0e2d\u0e07"
    ],
    "wof:name":"Ban Phai Si Thong",
    "wof:placetype":"locality"
},
  "geometry": {"coordinates":[100.56656,16.73503],"type":"Point"}
}