{
  "type": "Feature",
  "properties": {
    "gn:admin1_code":"2.0",
    "gn:asciiname":"Ban Mae Yui",
    "gn:country_code":"TH",
    "gn:dem":322,
    "gn:feature_class":"P",
    "gn:feature_code":"PPL",
    "gn:name":"Ban Mae Yui",
    "gn:population":0,
    "gn:timezone":"Asia/Bangkok",
    "iso:country":"TH",
    "name:tha_x_preferred":[
        "\u0e1a\u0e49\u0e32\u0e19\u0e41\u0e21\u0e48\u0e22\u0e38\u0e22"
    ],
    "wof:name":"Ban Mae Yui",
    "wof:placetype":"locality"
},
  "geometry": {"coordinates":[98.70708,18.05775],"type":"Point"}
}