{
  "type": "Feature",
  "properties": {
    "gn:admin1_code":"32.0",
    "gn:asciiname":"Ban Wong Duean",
    "gn:country_code":"TH",
    "gn:dem":23,
    "gn:feature_class":"P",
    "gn:feature_code":"PPL",
    "gn:name":"Ban Wong Duean",
    "gn:population":0,
    "gn:timezone":"Asia/Bangkok",
    "iso:country":"TH",
    "name:tha_x_preferred":[
        "\u0e1a\u0e49\u0e32\u0e19\u0e27\u0e07\u0e40\u0e14\u0e37\u0e2d\u0e19"
    ],
    "wof:name":"Ban Wong Duean",
    "wof:placetype":"locality"
},
  "geometry": {"coordinates":[100.01881,15.06647],"type":"Point"}
}