{
  "type": "Feature",
  "properties": {
    "gn:admin1_code":"23.0",
    "gn:asciiname":"Ban Saphan Hin",
    "gn:country_code":"TH",
    "gn:dem":215,
    "gn:feature_class":"P",
    "gn:feature_code":"PPL",
    "gn:name":"Ban Saphan Hin",
    "gn:population":0,
    "gn:timezone":"Asia/Bangkok",
    "iso:country":"TH",
    "name:tha_x_preferred":[
        "\u0e1a\u0e49\u0e32\u0e19\u0e2a\u0e30\u0e1e\u0e32\u0e19\u0e2b\u0e34\u0e19"
    ],
    "wof:name":"Ban Saphan Hin",
    "wof:placetype":"locality"
},
  "geometry": {"coordinates":[103.66797,16.86231],"type":"Point"}
}