{
  "type": "Feature",
  "properties": {
    "gn:admin1_code":"22",
    "gn:asciiname":"Ban Kham Pa Ko",
    "gn:country_code":"TH",
    "gn:dem":227,
    "gn:feature_class":"P",
    "gn:feature_code":"PPL",
    "gn:name":"Ban Kham Pa Ko",
    "gn:population":0,
    "gn:timezone":"Asia/Bangkok",
    "iso:country":"TH",
    "name:tha_x_preferred":[
        "\u0e1a\u0e49\u0e32\u0e19\u0e04\u0e33\u0e1b\u0e48\u0e32\u0e01\u0e48\u0e2d"
    ],
    "wof:name":"Ban Kham Pa Ko",
    "wof:placetype":"locality"
},
  "geometry": {"coordinates":[102.77403,17.01842000000001],"type":"Point"}
}