{
  "type": "Feature",
  "properties": {
    "gn:admin1_code":"31.0",
    "gn:asciiname":"Ban Pu Po Tai",
    "gn:country_code":"TH",
    "gn:dem":8,
    "gn:feature_class":"P",
    "gn:feature_code":"PPL",
    "gn:name":"Ban Pu Po Tai",
    "gn:population":0,
    "gn:timezone":"Asia/Bangkok",
    "iso:country":"TH",
    "name:tha_x_preferred":[
        "\u0e1a\u0e49\u0e32\u0e19\u0e1b\u0e39\u0e42\u0e1b\u0e4a\u0e30 (\u0e43\u0e15\u0e49)"
    ],
    "wof:name":"Ban Pu Po Tai",
    "wof:placetype":"locality"
},
  "geometry": {"coordinates":[102.03872,6.113],"type":"Point"}
}