{
  "type": "Feature",
  "properties": {
    "gn:admin1_code":"6.0",
    "gn:asciiname":"Ban Pa Miang",
    "gn:country_code":"TH",
    "gn:dem":978,
    "gn:feature_class":"P",
    "gn:feature_code":"PPL",
    "gn:name":"Ban Pa Miang",
    "gn:population":0,
    "gn:timezone":"Asia/Bangkok",
    "iso:country":"TH",
    "name:tha_x_preferred":[
        "\u0e1a\u0e49\u0e32\u0e19\u0e1b\u0e48\u0e32\u0e40\u0e21\u0e35\u0e48\u0e22\u0e07"
    ],
    "name:und_x_variant":[
        "Pa Miang",
        "Ban Pa Miang"
    ],
    "wof:lang_x_official":[
        "tha"
    ],
    "wof:lang_x_spoken":[
        "tha"
    ],
    "wof:name":"Ban Pa Miang",
    "wof:placetype":"locality"
},
  "geometry": {"coordinates":[99.77772,18.90864],"type":"Point"}
}