{
  "type": "Feature",
  "properties": {
    "gn:admin1_code":"29",
    "gn:asciiname":"Ban Phanao",
    "gn:country_code":"TH",
    "gn:dem":135,
    "gn:feature_class":"P",
    "gn:feature_code":"PPL",
    "gn:name":"Ban Phanao",
    "gn:population":0,
    "gn:timezone":"Asia/Bangkok",
    "iso:country":"TH",
    "name:tha_x_preferred":[
        "\u0e1a\u0e49\u0e32\u0e19\u0e1e\u0e30\u0e40\u0e19\u0e32"
    ],
    "wof:name":"Ban Phanao",
    "wof:placetype":"locality"
},
  "geometry": {"coordinates":[103.60881000000001,15.25042],"type":"Point"}
}