{
  "type": "Feature",
  "properties": {
    "gn:admin1_code":"17.0",
    "gn:asciiname":"Ban Khok Kai",
    "gn:country_code":"TH",
    "gn:dem":178,
    "gn:feature_class":"P",
    "gn:feature_code":"PPL",
    "gn:name":"Ban Khok Kai",
    "gn:population":0,
    "gn:timezone":"Asia/Bangkok",
    "iso:country":"TH",
    "wof:name":"Ban Khok Kai",
    "wof:placetype":"locality"
},
  "geometry": {"coordinates":[102.6675,17.64528],"type":"Point"}
}