{
  "type": "Feature",
  "properties": {
    "gn:admin1_code":"29",
    "gn:asciiname":"Ban Prue Kian",
    "gn:country_code":"TH",
    "gn:dem":157,
    "gn:feature_class":"P",
    "gn:feature_code":"PPL",
    "gn:name":"Ban Prue Kian",
    "gn:population":0,
    "gn:timezone":"Asia/Bangkok",
    "iso:country":"TH",
    "name:tha_x_preferred":[
        "\u0e1a\u0e49\u0e32\u0e19\u0e1b\u0e23\u0e37\u0e2d\u0e40\u0e01\u0e35\u0e22\u0e19"
    ],
    "wof:name":"Ban Prue Kian",
    "wof:placetype":"locality"
},
  "geometry": {"coordinates":[103.52144,14.82414],"type":"Point"}
}