{
  "type": "Feature",
  "properties": {
    "gn:admin1_code":"68.0",
    "gn:asciiname":"Ban Sala Luang Bon",
    "gn:country_code":"TH",
    "gn:dem":3,
    "gn:feature_class":"P",
    "gn:feature_code":"PPL",
    "gn:name":"Ban Sala Luang Bon",
    "gn:population":0,
    "gn:timezone":"Asia/Bangkok",
    "iso:country":"TH",
    "name:tha_x_preferred":[
        "\u0e1a\u0e49\u0e32\u0e19\u0e28\u0e32\u0e25\u0e32\u0e2b\u0e25\u0e27\u0e07\u0e1a\u0e19"
    ],
    "name:und_x_variant":[
        "Ban Sala Luang"
    ],
    "wof:name":"Ban Sala Luang Bon",
    "wof:placetype":"locality"
},
  "geometry": {"coordinates":[100.3516,7.84566],"type":"Point"}
}