{
  "type": "Feature",
  "properties": {
    "gn:admin1_code":"20.0",
    "gn:asciiname":"Ban Tan Lian",
    "gn:country_code":"TH",
    "gn:dem":170,
    "gn:feature_class":"P",
    "gn:feature_code":"PPL",
    "gn:name":"Ban Tan Lian",
    "gn:population":0,
    "gn:timezone":"Asia/Bangkok",
    "iso:country":"TH",
    "name:tha_x_preferred":[
        "\u0e1a\u0e49\u0e32\u0e19\u0e15\u0e32\u0e25\u0e40\u0e25\u0e35\u0e22\u0e19"
    ],
    "wof:name":"Ban Tan Lian",
    "wof:placetype":"locality"
},
  "geometry": {"coordinates":[103.78045,17.33383],"type":"Point"}
}