{
  "type": "Feature",
  "properties": {
    "gn:admin1_code":"16.0",
    "gn:asciiname":"Ban Kan Kheha Haeng Chat",
    "gn:country_code":"TH",
    "gn:dem":31,
    "gn:feature_class":"P",
    "gn:feature_code":"PPL",
    "gn:name":"Ban Kan Kheha Haeng Chat",
    "gn:population":0,
    "gn:timezone":"Asia/Bangkok",
    "iso:country":"TH",
    "name:tha_x_preferred":[
        "\u0e1a\u0e49\u0e32\u0e19\u0e01\u0e32\u0e23\u0e40\u0e04\u0e2b\u0e30\u0e41\u0e2b\u0e48\u0e07\u0e0a\u0e32\u0e15\u0e34"
    ],
    "wof:name":"Ban Kan Kheha Haeng Chat",
    "wof:placetype":"locality"
},
  "geometry": {"coordinates":[100.10511,15.73108],"type":"Point"}
}