{
  "type": "Feature",
  "properties": {
    "gn:admin1_code":"26.0",
    "gn:asciiname":"Ban Huai Phaknam",
    "gn:country_code":"TH",
    "gn:dem":504,
    "gn:feature_class":"P",
    "gn:feature_code":"PPL",
    "gn:name":"Ban Huai Phaknam",
    "gn:population":0,
    "gn:timezone":"Asia/Bangkok",
    "iso:country":"TH",
    "name:tha_x_preferred":[
        "\u0e1a\u0e49\u0e32\u0e19\u0e2b\u0e49\u0e27\u0e22\u0e1c\u0e31\u0e01\u0e2b\u0e19\u0e32\u0e21"
    ],
    "wof:name":"Ban Huai Phaknam",
    "wof:placetype":"locality"
},
  "geometry": {"coordinates":[102.06314,16.08708],"type":"Point"}
}