{
  "type": "Feature",
  "properties": {
    "gn:admin1_code":"27",
    "gn:asciiname":"Ban Bu Kut Chok",
    "gn:country_code":"TH",
    "gn:dem":253,
    "gn:feature_class":"P",
    "gn:feature_code":"PPL",
    "gn:name":"Ban Bu Kut Chok",
    "gn:population":0,
    "gn:timezone":"Asia/Bangkok",
    "iso:country":"TH",
    "name:tha_x_preferred":[
        "\u0e1a\u0e49\u0e32\u0e19\u0e1a\u0e38\u0e01\u0e38\u0e14\u0e08\u0e2d\u0e01"
    ],
    "wof:name":"Ban Bu Kut Chok",
    "wof:placetype":"locality"
},
  "geometry": {"coordinates":[102.31453,14.72947],"type":"Point"}
}