{
  "type": "Feature",
  "properties": {
    "gn:admin1_code":"25",
    "gn:asciiname":"Ban Nong Na La",
    "gn:country_code":"TH",
    "gn:dem":137,
    "gn:feature_class":"P",
    "gn:feature_code":"PPL",
    "gn:name":"Ban Nong Na La",
    "gn:population":0,
    "gn:timezone":"Asia/Bangkok",
    "iso:country":"TH",
    "name:tha_x_preferred":[
        "\u0e1a\u0e49\u0e32\u0e19\u0e2b\u0e19\u0e2d\u0e07\u0e19\u0e32\u0e2b\u0e25\u0e49\u0e32"
    ],
    "wof:name":"Ban Nong Na La",
    "wof:placetype":"locality"
},
  "geometry": {"coordinates":[103.82671999999999,15.89975],"type":"Point"}
}