{
  "type": "Feature",
  "properties": {
    "gn:admin1_code":"78.0",
    "gn:asciiname":"Ban Na Pho",
    "gn:country_code":"TH",
    "gn:dem":148,
    "gn:feature_class":"P",
    "gn:feature_code":"PPL",
    "gn:name":"Ban Na Pho",
    "gn:population":0,
    "gn:timezone":"Asia/Bangkok",
    "iso:country":"TH",
    "name:tha_x_preferred":[
        "\u0e1a\u0e49\u0e32\u0e19\u0e19\u0e32\u0e42\u0e1e\u0e18\u0e34\u0e4c"
    ],
    "name:und_x_variant":[
        "Ban Na Po",
        "Ban Na Pho"
    ],
    "wof:name":"Ban Na Pho",
    "wof:placetype":"locality"
},
  "geometry": {"coordinates":[104.87503,16.35311],"type":"Point"}
}