{
  "type": "Feature",
  "properties": {
    "gn:admin1_code":"30.0",
    "gn:asciiname":"Ban Nong Khaeo Chang",
    "gn:country_code":"TH",
    "gn:dem":167,
    "gn:feature_class":"P",
    "gn:feature_code":"PPL",
    "gn:name":"Ban Nong Khaeo Chang",
    "gn:population":0,
    "gn:timezone":"Asia/Bangkok",
    "iso:country":"TH",
    "name:tha_x_preferred":[
        "\u0e1a\u0e49\u0e32\u0e19\u0e2b\u0e19\u0e2d\u0e07\u0e41\u0e02\u0e49\u0e27\u0e0a\u0e49\u0e32\u0e07"
    ],
    "wof:name":"Ban Nong Khaeo Chang",
    "wof:placetype":"locality"
},
  "geometry": {"coordinates":[104.75192,14.76636],"type":"Point"}
}