{
  "type": "Feature",
  "properties": {
    "gn:admin1_code":"20.0",
    "gn:asciiname":"Ban Dong Noi",
    "gn:country_code":"TH",
    "gn:dem":158,
    "gn:feature_class":"P",
    "gn:feature_code":"PPL",
    "gn:name":"Ban Dong Noi",
    "gn:population":0,
    "gn:timezone":"Asia/Bangkok",
    "iso:country":"TH",
    "name:tha_x_preferred":[
        "\u0e1a\u0e49\u0e32\u0e19\u0e14\u0e07\u0e19\u0e49\u0e2d\u0e22"
    ],
    "wof:name":"Ban Dong Noi",
    "wof:placetype":"locality"
},
  "geometry": {"coordinates":[104.33222000000001,17.02125],"type":"Point"}
}