{
  "type": "Feature",
  "properties": {
    "gn:admin1_code":"75.0",
    "gn:asciiname":"Ban Pak Huai Tum",
    "gn:country_code":"TH",
    "gn:dem":117,
    "gn:feature_class":"P",
    "gn:feature_code":"PPL",
    "gn:name":"Ban Pak Huai Tum",
    "gn:population":0,
    "gn:timezone":"Asia/Bangkok",
    "iso:country":"TH",
    "name:tha_x_preferred":[
        "\u0e1a\u0e49\u0e32\u0e19\u0e1b\u0e32\u0e01\u0e2b\u0e49\u0e27\u0e22\u0e15\u0e39\u0e21"
    ],
    "wof:name":"Ban Pak Huai Tum",
    "wof:placetype":"locality"
},
  "geometry": {"coordinates":[105.33028,15.271],"type":"Point"}
}