{
  "type": "Feature",
  "properties": {
    "gn:admin1_code":"72.0",
    "gn:asciiname":"Ban Kok Bak",
    "gn:country_code":"TH",
    "gn:dem":177,
    "gn:feature_class":"P",
    "gn:feature_code":"PPL",
    "gn:name":"Ban Kok Bak",
    "gn:population":0,
    "gn:timezone":"Asia/Bangkok",
    "iso:country":"TH",
    "name:tha_x_preferred":[
        "\u0e1a\u0e49\u0e32\u0e19\u0e01\u0e01\u0e1a\u0e32\u0e01"
    ],
    "wof:name":"Ban Kok Bak",
    "wof:placetype":"locality"
},
  "geometry": {"coordinates":[104.26546999999999,16.08961],"type":"Point"}
}