{
  "type": "Feature",
  "properties": {
    "gn:admin1_code":"51.0",
    "gn:asciiname":"Ban Rang Khem Thong",
    "gn:country_code":"TH",
    "gn:dem":11,
    "gn:feature_class":"P",
    "gn:feature_code":"PPL",
    "gn:name":"Ban Rang Khem Thong",
    "gn:population":0,
    "gn:timezone":"Asia/Bangkok",
    "iso:country":"TH",
    "name:tha_x_preferred":[
        "\u0e1a\u0e49\u0e32\u0e19\u0e23\u0e32\u0e07\u0e40\u0e02\u0e47\u0e21\u0e17\u0e2d\u0e07"
    ],
    "wof:name":"Ban Rang Khem Thong",
    "wof:placetype":"locality"
},
  "geometry": {"coordinates":[99.89506,14.14367],"type":"Point"}
}