{
  "type": "Feature",
  "properties": {
    "gn:admin1_code":"52.0",
    "gn:asciiname":"Ban Yuan Nuea",
    "gn:country_code":"TH",
    "gn:dem":8,
    "gn:feature_class":"P",
    "gn:feature_code":"PPL",
    "gn:name":"Ban Yuan Nuea",
    "gn:population":0,
    "gn:timezone":"Asia/Bangkok",
    "iso:country":"TH",
    "name:tha_x_preferred":[
        "\u0e1a\u0e49\u0e32\u0e19\u0e0d\u0e27\u0e19\u0e40\u0e2b\u0e19\u0e37\u0e2d"
    ],
    "wof:name":"Ban Yuan Nuea",
    "wof:placetype":"locality"
},
  "geometry": {"coordinates":[99.83664,13.61678],"type":"Point"}
}