{
  "type": "Feature",
  "properties": {
    "gn:admin1_code":"34",
    "gn:asciiname":"Ban Nong Ta Biao",
    "gn:country_code":"TH",
    "gn:dem":114,
    "gn:feature_class":"P",
    "gn:feature_code":"PPL",
    "gn:name":"Ban Nong Ta Biao",
    "gn:population":0,
    "gn:timezone":"Asia/Bangkok",
    "iso:country":"TH",
    "name:tha_x_preferred":[
        "\u0e1a\u0e49\u0e32\u0e19\u0e2b\u0e19\u0e2d\u0e07\u0e15\u0e32\u0e40\u0e1a\u0e35\u0e49\u0e22\u0e27"
    ],
    "wof:name":"Ban Nong Ta Biao",
    "wof:placetype":"locality"
},
  "geometry": {"coordinates":[100.66864,15.25303],"type":"Point"}
}