{
  "type": "Feature",
  "properties": {
    "gn:country":"TH",
    "gn:fcode":"ADM3",
    "gn:pop":9234,
    "iso:country":"TH",
    "name:ceb_x_preferred":[
        "Mae Yuam"
    ],
    "name:deu_x_preferred":[
        "Mae Yuam"
    ],
    "name:eng_x_preferred":[
        "Mae Yuam subdistrict"
    ],
    "name:eng_x_variant":[
        "Mae Yuam"
    ],
    "name:fra_x_preferred":[
        "Mae Yuam"
    ],
    "name:rus_x_preferred":[
        "\u041c\u0430\u0435-\u042e\u0430\u043c"
    ],
    "name:tha_x_preferred":[
        "\u0e15\u0e33\u0e1a\u0e25\u0e41\u0e21\u0e48\u0e22\u0e27\u0e21"
    ],
    "name:tha_x_variant":[
        "\u0e41\u0e21\u0e48\u0e22\u0e27\u0e21"
    ],
    "name:unk_x_variant":[
        "Tambon Mae Yuam"
    ],
    "name:urd_x_preferred":[
        "\u0645\u0627\u0626\u06d2 \u06cc\u0648\u0627\u0645"
    ],
    "qs:name":"Mae Yuam",
    "qs:photos_9r":0,
    "qs:photos_sr":0,
    "qs:pop_sr":"5",
    "wd:wordcount":61,
    "wof:name":"Mae Yuam",
    "wof:placetype":"localadmin",
    "wof:population":9234
},
  "geometry": {"coordinates":[97.92289,18.14578],"type":"Point"}
}