{
  "type": "Feature",
  "properties": {
    "gn:admin1_code":"30.0",
    "gn:asciiname":"Ban Yang Ta Kuai",
    "gn:country_code":"TH",
    "gn:dem":164,
    "gn:feature_class":"P",
    "gn:feature_code":"PPL",
    "gn:name":"Ban Yang Ta Kuai",
    "gn:population":0,
    "gn:timezone":"Asia/Bangkok",
    "iso:country":"TH",
    "name:tha_x_preferred":[
        "\u0e1a\u0e49\u0e32\u0e19\u0e22\u0e32\u0e07\u0e15\u0e32\u0e01\u0e27\u0e22"
    ],
    "wof:name":"Ban Yang Ta Kuai",
    "wof:placetype":"locality"
},
  "geometry": {"coordinates":[104.21344000000001,14.65033],"type":"Point"}
}