{
  "type": "Feature",
  "properties": {
    "gn:admin1_code":"56.0",
    "gn:asciiname":"Ban Nong Krachok",
    "gn:country_code":"TH",
    "gn:dem":8,
    "gn:feature_class":"P",
    "gn:feature_code":"PPL",
    "gn:name":"Ban Nong Krachok",
    "gn:population":0,
    "gn:timezone":"Asia/Bangkok",
    "iso:country":"TH",
    "name:tha_x_preferred":[
        "\u0e1a\u0e49\u0e32\u0e19\u0e2b\u0e19\u0e2d\u0e07\u0e01\u0e23\u0e30\u0e08\u0e01"
    ],
    "wof:name":"Ban Nong Krachok",
    "wof:placetype":"locality"
},
  "geometry": {"coordinates":[99.98766999999999,13.01678],"type":"Point"}
}