{
  "type": "Feature",
  "properties": {
    "gn:admin1_code":"4.0",
    "gn:asciiname":"Ban Mon",
    "gn:country_code":"TH",
    "gn:dem":310,
    "gn:feature_class":"P",
    "gn:feature_code":"PPL",
    "gn:name":"Ban Mon",
    "gn:population":0,
    "gn:timezone":"Asia/Bangkok",
    "iso:country":"TH",
    "name:tha_x_preferred":[
        "\u0e1a\u0e49\u0e32\u0e19\u0e21\u0e2d\u0e0d"
    ],
    "wof:name":"Ban Mon",
    "wof:placetype":"locality"
},
  "geometry": {"coordinates":[100.87014000000001,19.41064],"type":"Point"}
}