{
  "type": "Feature",
  "properties": {
    "gn:admin1_code":"70.0",
    "gn:asciiname":"Ban Due Ri Yae Ha Yi",
    "gn:country_code":"TH",
    "gn:dem":81,
    "gn:feature_class":"P",
    "gn:feature_code":"PPL",
    "gn:name":"Ban Due Ri Yae Ha Yi",
    "gn:population":0,
    "gn:timezone":"Asia/Bangkok",
    "iso:country":"TH",
    "name:tha_x_preferred":[
        "\u0e1a\u0e49\u0e32\u0e19\u0e14\u0e37\u0e2d\u0e23\u0e34\u0e41\u0e22\u0e2e\u0e30\u0e22\u0e35"
    ],
    "wof:lang_x_official":[
        "tha"
    ],
    "wof:lang_x_spoken":[
        "tha"
    ],
    "wof:name":"Ban Due Ri Yae Ha Yi",
    "wof:placetype":"locality"
},
  "geometry": {"coordinates":[101.23442,6.287],"type":"Point"}
}