{
  "type": "Feature",
  "properties": {
    "gn:admin1_code":"65.0",
    "gn:asciiname":"Ban Bang Mak Yai",
    "gn:country_code":"TH",
    "gn:dem":13,
    "gn:feature_class":"P",
    "gn:feature_code":"PPL",
    "gn:name":"Ban Bang Mak Yai",
    "gn:population":0,
    "gn:timezone":"Asia/Bangkok",
    "iso:country":"TH",
    "name:tha_x_preferred":[
        "\u0e1a\u0e49\u0e32\u0e19\u0e1a\u0e32\u0e07\u0e2b\u0e21\u0e32\u0e01\u0e43\u0e2b\u0e0d\u0e48"
    ],
    "name:und_x_variant":[
        "Ban Bang Mak"
    ],
    "wof:lang_x_official":[
        "tha"
    ],
    "wof:lang_x_spoken":[
        "tha"
    ],
    "wof:name":"Ban Bang Mak Yai",
    "wof:placetype":"locality"
},
  "geometry": {"coordinates":[99.55558000000001,7.47503],"type":"Point"}
}