{
  "type": "Feature",
  "properties": {
    "gn:admin1_code":"8.0",
    "gn:asciiname":"Ban Ruam Thai Phatthana Sip Sam",
    "gn:country_code":"TH",
    "gn:dem":832,
    "gn:feature_class":"P",
    "gn:feature_code":"PPL",
    "gn:name":"Ban Ruam Thai Phatthana Sip Sam",
    "gn:population":0,
    "gn:timezone":"Asia/Bangkok",
    "iso:country":"TH",
    "name:tha_x_preferred":[
        "\u0e1a\u0e49\u0e32\u0e19\u0e23\u0e27\u0e21\u0e44\u0e17\u0e22\u0e1e\u0e31\u0e12\u0e19\u0e32 \u0e2a\u0e34\u0e1a\u0e2a\u0e32\u0e21"
    ],
    "name:und_x_variant":[
        "Ban Ruam Thai Phatthana 13"
    ],
    "wof:lang_x_official":[
        "tha"
    ],
    "wof:lang_x_spoken":[
        "tha"
    ],
    "wof:name":"Ban Ruam Thai Phatthana Sip Sam",
    "wof:placetype":"locality"
},
  "geometry": {"coordinates":[98.81653,16.496],"type":"Point"}
}