{
  "type": "Feature",
  "properties": {
    "gn:admin1_code":"65.0",
    "gn:asciiname":"Ban Khun Sit",
    "gn:country_code":"TH",
    "gn:dem":32,
    "gn:feature_class":"P",
    "gn:feature_code":"PPL",
    "gn:name":"Ban Khun Sit",
    "gn:population":0,
    "gn:timezone":"Asia/Bangkok",
    "iso:country":"TH",
    "name:tha_x_preferred":[
        "\u0e1a\u0e49\u0e32\u0e19\u0e02\u0e38\u0e19\u0e2a\u0e34\u0e17\u0e18\u0e34\u0e4c"
    ],
    "wof:name":"Ban Khun Sit",
    "wof:placetype":"locality"
},
  "geometry": {"coordinates":[99.65728,7.61147],"type":"Point"}
}