{
  "type": "Feature",
  "properties": {
    "gn:admin1_code":"26.0",
    "gn:asciiname":"Ban Pong Khlong Tai",
    "gn:country_code":"TH",
    "gn:dem":220,
    "gn:feature_class":"P",
    "gn:feature_code":"PPL",
    "gn:name":"Ban Pong Khlong Tai",
    "gn:population":0,
    "gn:timezone":"Asia/Bangkok",
    "iso:country":"TH",
    "name:tha_x_preferred":[
        "\u0e1a\u0e49\u0e32\u0e19\u0e42\u0e1b\u0e48\u0e07\u0e04\u0e25\u0e2d\u0e07\u0e43\u0e15\u0e49"
    ],
    "wof:name":"Ban Pong Khlong Tai",
    "wof:placetype":"locality"
},
  "geometry": {"coordinates":[101.96306,15.90025],"type":"Point"}
}