{
  "type": "Feature",
  "properties": {
    "gn:admin1_code":"39.0",
    "gn:asciiname":"Ban Bo Nam Chiao",
    "gn:country_code":"TH",
    "gn:dem":5,
    "gn:feature_class":"P",
    "gn:feature_code":"PPL",
    "gn:name":"Ban Bo Nam Chiao",
    "gn:population":0,
    "gn:timezone":"Asia/Bangkok",
    "iso:country":"TH",
    "name:tha_x_preferred":[
        "Ban Bo Nam Chiao"
    ],
    "name:tha_x_variant":[
        "\u0e1a\u0e49\u0e32\u0e19\u0e1a\u0e48\u0e2d\u0e19\u0e49\u0e33\u0e40\u0e0a\u0e35\u0e48\u0e22\u0e27"
    ],
    "wof:name":"Ban Bo Nam Chiao",
    "wof:placetype":"locality"
},
  "geometry": {"coordinates":[100.40575,14.03094],"type":"Point"}
}