{
  "type": "Feature",
  "properties": {
    "gn:admin1_code":"78.0",
    "gn:asciiname":"Ban Nong Kapat",
    "gn:country_code":"TH",
    "gn:dem":213,
    "gn:feature_class":"P",
    "gn:feature_code":"PPL",
    "gn:name":"Ban Nong Kapat",
    "gn:population":0,
    "gn:timezone":"Asia/Bangkok",
    "iso:country":"TH",
    "name:tha_x_preferred":[
        "Ban Nong Kapat"
    ],
    "name:tha_x_variant":[
        "\u0e1a\u0e49\u0e32\u0e19\u0e2b\u0e19\u0e2d\u0e07\u0e01\u0e30\u0e1b\u0e32\u0e14"
    ],
    "wof:name":"Ban Nong Kapat",
    "wof:placetype":"locality"
},
  "geometry": {"coordinates":[104.36958,16.52131],"type":"Point"}
}