{
  "type": "Feature",
  "properties": {
    "iso:country":"TH",
    "name:bpy_x_preferred":[
        "\u0986\u09ae\u09cd\u09ab\u09cb\u09af\u09bc\u09c7 \u09b8\u09be\u09ae \u09ab\u09b0\u09be\u09a8"
    ],
    "name:ceb_x_preferred":[
        "Amphoe Sam Phran"
    ],
    "name:deu_x_preferred":[
        "Amphoe Sam Phran"
    ],
    "name:eng_x_preferred":[
        "Sam Phran"
    ],
    "name:fra_x_preferred":[
        "Sam Phran"
    ],
    "name:ita_x_preferred":[
        "Sam Phran"
    ],
    "name:nan_x_preferred":[
        "Sam Phran K\u016bn"
    ],
    "name:nob_x_preferred":[
        "Sam Phran"
    ],
    "name:ron_x_preferred":[
        "Districtul Sam Phran"
    ],
    "name:rus_x_preferred":[
        "\u0421\u0430\u043c\u0444\u0440\u0430\u043d"
    ],
    "name:spa_x_preferred":[
        "Sam Phran"
    ],
    "name:tha_x_preferred":[
        "\u0e2d\u0e33\u0e40\u0e20\u0e2d\u0e2a\u0e32\u0e21\u0e1e\u0e23\u0e32\u0e19"
    ],
    "name:urd_x_preferred":[
        "\u0633\u0627\u0645 \u067e\u06be\u0631\u0627\u0646 \u0636\u0644\u0639"
    ],
    "name:vie_x_preferred":[
        "Sam Phran"
    ],
    "qs:name":"Rai Khing",
    "qs:name_adm0":"Thailand",
    "qs:name_adm1":"Nathon Pathon",
    "qs:photos":166,
    "qs:photos_1k":34,
    "qs:photos_9k":1,
    "qs:photos_9r":4,
    "qs:photos_all":166,
    "qs:photos_sr":4,
    "qs:placetype":"Town",
    "qs:pop_sr":"0",
    "wd:wordcount":711,
    "wof:name":"Rai Khing",
    "wof:placetype":"locality"
},
  "geometry": {"coordinates":[100.25616599999999,13.7375],"type":"Point"}
}