{
  "type": "Feature",
  "properties": {
    "iso:country":"TH",
    "qs:name":"Rai Khing",
    "qs:name_adm0":"Thailand",
    "qs:name_adm1":"Nathon Pathon",
    "qs:photos":166,
    "qs:photos_1k":34,
    "qs:photos_9k":1,
    "qs:photos_9r":4,
    "qs:photos_all":166,
    "qs:photos_sr":4,
    "qs:placetype":"Town",
    "qs:pop_sr":"0",
    "wd:wordcount":711,
    "wof:name":"Rai Khing",
    "wof:placetype":"locality"
},
  "geometry": {"coordinates":[100.25616599999999,13.7375],"type":"Point"}
}