{
  "type": "Feature",
  "properties": {
    "gn:admin1_code":"53.0",
    "gn:asciiname":"Ban Huai Yang Kruat",
    "gn:country_code":"TH",
    "gn:dem":9,
    "gn:feature_class":"P",
    "gn:feature_code":"PPL",
    "gn:name":"Ban Huai Yang Kruat",
    "gn:population":0,
    "gn:timezone":"Asia/Bangkok",
    "iso:country":"TH",
    "name:tha_x_preferred":[
        "\u0e1a\u0e49\u0e32\u0e19\u0e2b\u0e49\u0e27\u0e22\u0e22\u0e32\u0e07\u0e01\u0e23\u0e27\u0e14"
    ],
    "wof:name":"Ban Huai Yang Kruat",
    "wof:placetype":"locality"
},
  "geometry": {"coordinates":[100.02733000000001,13.89181],"type":"Point"}
}