{
  "type": "Feature",
  "properties": {
    "gn:admin1_code":"8.0",
    "gn:asciiname":"Ban Sam Ngao",
    "gn:country_code":"TH",
    "gn:dem":136,
    "gn:feature_class":"P",
    "gn:feature_code":"PPL",
    "gn:name":"Ban Sam Ngao",
    "gn:population":0,
    "gn:timezone":"Asia/Bangkok",
    "iso:country":"TH",
    "name:tha_x_preferred":[
        "Ban Sam Ngao"
    ],
    "name:tha_x_variant":[
        "\u0e1a\u0e49\u0e32\u0e19\u0e2a\u0e32\u0e21\u0e40\u0e07\u0e32"
    ],
    "name:und_x_variant":[
        "Ban Sam Ngao Luang"
    ],
    "wof:name":"Ban Sam Ngao",
    "wof:placetype":"locality"
},
  "geometry": {"coordinates":[99.06531,17.19428],"type":"Point"}
}