{
  "type": "Feature",
  "properties": {
    "gn:admin1_code":"40.0",
    "gn:admin2_code":"1021.0",
    "gn:asciiname":"Muban Wiset Suk Nakhon",
    "gn:country_code":"TH",
    "gn:dem":4,
    "gn:feature_class":"P",
    "gn:feature_code":"PPL",
    "gn:name":"Muban Wiset Suk Nakhon",
    "gn:population":0,
    "gn:timezone":"Asia/Bangkok",
    "iso:country":"TH",
    "name:tha_x_preferred":[
        "\u0e2b\u0e21\u0e39\u0e48\u0e1a\u0e49\u0e32\u0e19\u0e27\u0e34\u0e40\u0e28\u0e29\u0e2a\u0e38\u0e02\u0e19\u0e04\u0e23"
    ],
    "wof:name":"Muban Wiset Suk Nakhon",
    "wof:placetype":"locality"
},
  "geometry": {"coordinates":[100.38844,13.6125],"type":"Point"}
}