{
  "type": "Feature",
  "properties": {
    "gn:admin1_code":"46.0",
    "gn:asciiname":"Ban Lum Yang",
    "gn:country_code":"TH",
    "gn:dem":115,
    "gn:feature_class":"P",
    "gn:feature_code":"PPL",
    "gn:name":"Ban Lum Yang",
    "gn:population":0,
    "gn:timezone":"Asia/Bangkok",
    "iso:country":"TH",
    "name:tha_x_preferred":[
        "\u0e1a\u0e49\u0e32\u0e19\u0e2b\u0e25\u0e38\u0e21\u0e22\u0e32\u0e07"
    ],
    "wof:name":"Ban Lum Yang",
    "wof:placetype":"locality"
},
  "geometry": {"coordinates":[101.14807999999999,13.20136],"type":"Point"}
}