{
  "type": "Feature",
  "properties": {
    "gn:admin1_code":"24",
    "gn:asciiname":"Ban Khu Rang",
    "gn:country_code":"TH",
    "gn:dem":139,
    "gn:feature_class":"P",
    "gn:feature_code":"PPL",
    "gn:name":"Ban Khu Rang",
    "gn:population":0,
    "gn:timezone":"Asia/Bangkok",
    "iso:country":"TH",
    "name:tha_x_preferred":[
        "\u0e1a\u0e49\u0e32\u0e19\u0e04\u0e39\u0e23\u0e31\u0e07"
    ],
    "wof:name":"Ban Khu Rang",
    "wof:placetype":"locality"
},
  "geometry": {"coordinates":[103.23744000000001,15.57133],"type":"Point"}
}