{
  "type": "Feature",
  "properties": {
    "gn:admin1_code":"27.0",
    "gn:asciiname":"Ban Tha Lat Khao",
    "gn:country_code":"TH",
    "gn:dem":197,
    "gn:feature_class":"P",
    "gn:feature_code":"PPL",
    "gn:name":"Ban Tha Lat Khao",
    "gn:population":0,
    "gn:timezone":"Asia/Bangkok",
    "iso:country":"TH",
    "name:tha_x_preferred":[
        "\u0e1a\u0e49\u0e32\u0e19\u0e17\u0e48\u0e32\u0e25\u0e32\u0e14\u0e02\u0e32\u0e27"
    ],
    "name:und_x_variant":[
        "Lat Khao",
        "Tha Lat Khao",
        "Ban Lat Khao",
        "Ban Tha Lat Khao"
    ],
    "wof:name":"Ban Tha Lat Khao",
    "wof:placetype":"locality"
},
  "geometry": {"coordinates":[102.14492,14.68564],"type":"Point"}
}