{
  "type": "Feature",
  "properties": {
    "gn:admin1_code":"70.0",
    "gn:asciiname":"Ban Ku Bae La Ti",
    "gn:country_code":"TH",
    "gn:dem":26,
    "gn:feature_class":"P",
    "gn:feature_code":"PPL",
    "gn:name":"Ban Ku Bae La Ti",
    "gn:population":0,
    "gn:timezone":"Asia/Bangkok",
    "iso:country":"TH",
    "name:tha_x_preferred":[
        "\u0e1a\u0e49\u0e32\u0e19\u0e01\u0e39\u0e41\u0e1a\u0e25\u0e32\u0e15\u0e35"
    ],
    "wof:name":"Ban Ku Bae La Ti",
    "wof:placetype":"locality"
},
  "geometry": {"coordinates":[101.21975,6.49614],"type":"Point"}
}