{
  "type": "Feature",
  "properties": {
    "gn:admin1_code":"40.0",
    "gn:admin2_code":"1048.0",
    "gn:asciiname":"Muban Sin Phatthana Thani",
    "gn:country_code":"TH",
    "gn:dem":6,
    "gn:feature_class":"P",
    "gn:feature_code":"PPL",
    "gn:name":"Muban Sin Phatthana Thani",
    "gn:population":0,
    "gn:timezone":"Asia/Bangkok",
    "iso:country":"TH",
    "name:tha_x_preferred":[
        "\u0e2b\u0e21\u0e39\u0e48\u0e1a\u0e49\u0e32\u0e19\u0e2a\u0e34\u0e19\u0e1e\u0e31\u0e12\u0e19\u0e32\u0e18\u0e32\u0e19\u0e35"
    ],
    "wof:lang_x_official":[
        "tha"
    ],
    "wof:lang_x_spoken":[
        "tha"
    ],
    "wof:name":"Muban Sin Phatthana Thani",
    "wof:placetype":"locality"
},
  "geometry": {"coordinates":[100.34202999999999,13.74022],"type":"Point"}
}