{
  "type": "Feature",
  "properties": {
    "gn:admin1_code":"2.0",
    "gn:asciiname":"Ban Wang Phra",
    "gn:country_code":"TH",
    "gn:dem":623,
    "gn:feature_class":"P",
    "gn:feature_code":"PPL",
    "gn:name":"Ban Wang Phra",
    "gn:population":0,
    "gn:timezone":"Asia/Bangkok",
    "iso:country":"TH",
    "name:tha_x_preferred":[
        "\u0e1a\u0e49\u0e32\u0e19\u0e27\u0e31\u0e07\u0e1e\u0e23\u0e30"
    ],
    "wof:name":"Ban Wang Phra",
    "wof:placetype":"locality"
},
  "geometry": {"coordinates":[98.72217000000001,19.36636],"type":"Point"}
}