{
  "type": "Feature",
  "properties": {
    "gn:admin1_code":"74",
    "gn:asciiname":"Ban Inthanin",
    "gn:country_code":"TH",
    "gn:dem":5,
    "gn:feature_class":"P",
    "gn:feature_code":"PPL",
    "gn:name":"Ban Inthanin",
    "gn:population":0,
    "gn:timezone":"Asia/Bangkok",
    "iso:country":"TH",
    "name:tha_x_preferred":[
        "\u0e1a\u0e49\u0e32\u0e19\u0e2d\u0e34\u0e19\u0e17\u0e19\u0e34\u0e25"
    ],
    "wof:name":"Ban Inthanin",
    "wof:placetype":"locality"
},
  "geometry": {"coordinates":[101.32931000000001,14.00358],"type":"Point"}
}