{
  "type": "Feature",
  "properties": {
    "gn:admin1_code":"26.0",
    "gn:asciiname":"Ban Nong Kasa",
    "gn:country_code":"TH",
    "gn:dem":739,
    "gn:feature_class":"P",
    "gn:feature_code":"PPL",
    "gn:name":"Ban Nong Kasa",
    "gn:population":0,
    "gn:timezone":"Asia/Bangkok",
    "iso:country":"TH",
    "wof:name":"Ban Nong Kasa",
    "wof:placetype":"locality"
},
  "geometry": {"coordinates":[101.38527999999999,15.62917],"type":"Point"}
}