{
  "type": "Feature",
  "properties": {
    "gn:admin1_code":"36.0",
    "gn:asciiname":"Ban Khlong Nueng",
    "gn:country_code":"TH",
    "gn:dem":6,
    "gn:feature_class":"P",
    "gn:feature_code":"PPL",
    "gn:name":"Ban Khlong Nueng",
    "gn:population":0,
    "gn:timezone":"Asia/Bangkok",
    "iso:country":"TH",
    "name:tha_x_preferred":[
        "Ban Khlong Nung (1)"
    ],
    "name:tha_x_variant":[
        "\u0e1a\u0e49\u0e32\u0e19\u0e04\u0e25\u0e2d\u0e07 \u0e2b\u0e19\u0e36\u0e48\u0e07"
    ],
    "name:und_x_variant":[
        "Ban Khlong 1"
    ],
    "wof:name":"Ban Khlong Nueng",
    "wof:placetype":"locality"
},
  "geometry": {"coordinates":[100.63714,14.1515],"type":"Point"}
}