{
  "type": "Feature",
  "properties": {
    "gn:admin1_code":"36",
    "gn:asciiname":"Ban Sam Khao",
    "gn:country_code":"TH",
    "gn:dem":6,
    "gn:feature_class":"P",
    "gn:feature_code":"PPL",
    "gn:name":"Ban Sam Khao",
    "gn:population":0,
    "gn:timezone":"Asia/Bangkok",
    "iso:country":"TH",
    "name:tha_x_preferred":[
        "\u0e1a\u0e49\u0e32\u0e19\u0e2a\u0e32\u0e21\u0e40\u0e02\u0e32"
    ],
    "wof:lang_x_official":[
        "tha"
    ],
    "wof:lang_x_spoken":[
        "tha"
    ],
    "wof:name":"Ban Sam Khao",
    "wof:placetype":"locality"
},
  "geometry": {"coordinates":[100.61736000000001,14.36675],"type":"Point"}
}