{
  "type": "Feature",
  "properties": {
    "gn:admin1_code":"48.0",
    "gn:asciiname":"Ban Ko Takhian",
    "gn:country_code":"TH",
    "gn:dem":6,
    "gn:feature_class":"P",
    "gn:feature_code":"PPL",
    "gn:name":"Ban Ko Takhian",
    "gn:population":0,
    "gn:timezone":"Asia/Bangkok",
    "iso:country":"TH",
    "name:tha_x_preferred":[
        "\u0e1a\u0e49\u0e32\u0e19\u0e40\u0e01\u0e32\u0e30\u0e15\u0e30\u0e40\u0e04\u0e35\u0e22\u0e19"
    ],
    "wof:name":"Ban Ko Takhian",
    "wof:placetype":"locality"
},
  "geometry": {"coordinates":[102.11511,12.56275],"type":"Point"}
}