{
  "type": "Feature",
  "properties": {
    "gn:admin1_code":"75.0",
    "gn:asciiname":"Ban Phu Thai Phatthana",
    "gn:country_code":"TH",
    "gn:dem":183,
    "gn:feature_class":"P",
    "gn:feature_code":"PPL",
    "gn:name":"Ban Phu Thai Phatthana",
    "gn:population":0,
    "gn:timezone":"Asia/Bangkok",
    "iso:country":"TH",
    "name:tha_x_preferred":[
        "\u0e1a\u0e49\u0e32\u0e19\u0e20\u0e39\u0e44\u0e17\u0e1e\u0e31\u0e12\u0e19\u0e32"
    ],
    "wof:name":"Ban Phu Thai Phatthana",
    "wof:placetype":"locality"
},
  "geometry": {"coordinates":[105.45757999999999,14.97219],"type":"Point"}
}