{
  "type": "Feature",
  "properties": {
    "gn:admin1_code":"40.0",
    "gn:admin2_code":"1050.0",
    "gn:asciiname":"Muban Si Thawi",
    "gn:country_code":"TH",
    "gn:dem":7,
    "gn:feature_class":"P",
    "gn:feature_code":"PPL",
    "gn:name":"Muban Si Thawi",
    "gn:population":0,
    "gn:timezone":"Asia/Bangkok",
    "iso:country":"TH",
    "name:tha_x_preferred":[
        "\u0e2b\u0e21\u0e39\u0e48\u0e1a\u0e49\u0e32\u0e19\u0e28\u0e23\u0e35\u0e17\u0e27\u0e35"
    ],
    "wof:name":"Muban Si Thawi",
    "wof:placetype":"locality"
},
  "geometry": {"coordinates":[100.35075000000001,13.64978],"type":"Point"}
}