{
  "type": "Feature",
  "properties": {
    "gn:admin1_code":"70.0",
    "gn:asciiname":"Ban Yue Nang",
    "gn:country_code":"TH",
    "gn:dem":59,
    "gn:feature_class":"P",
    "gn:feature_code":"PPL",
    "gn:name":"Ban Yue Nang",
    "gn:population":0,
    "gn:timezone":"Asia/Bangkok",
    "iso:country":"TH",
    "name:tha_x_preferred":[
        "\u0e1a\u0e49\u0e32\u0e19\u0e22\u0e37\u0e2d\u0e19\u0e31\u0e07"
    ],
    "name:und_x_variant":[
        "Kampong Jerenang",
        "Kampong Buranaeng",
        "Kampong Yoe Ranaeng",
        "Kampong Yuranaeng",
        "Ban Yue Nang"
    ],
    "wof:name":"Ban Yue Nang",
    "wof:placetype":"locality"
},
  "geometry": {"coordinates":[101.03658,6.42869],"type":"Point"}
}