{
  "type": "Feature",
  "properties": {
    "gn:admin1_code":"4.0",
    "gn:asciiname":"Ban Nam Khrok Mai",
    "gn:country_code":"TH",
    "gn:dem":198,
    "gn:feature_class":"P",
    "gn:feature_code":"PPL",
    "gn:name":"Ban Nam Khrok Mai",
    "gn:population":0,
    "gn:timezone":"Asia/Bangkok",
    "iso:country":"TH",
    "name:tha_x_preferred":[
        "\u0e1a\u0e49\u0e32\u0e19\u0e19\u0e49\u0e33\u0e04\u0e23\u0e01\u0e43\u0e2b\u0e21\u0e48"
    ],
    "name:und_x_variant":[
        "Ban Nam Khok Chaeng",
        "B\u0101n Nam Kok Cheang",
        "Ban Nam Khrok Mai"
    ],
    "wof:name":"Ban Nam Khrok Mai",
    "wof:placetype":"locality"
},
  "geometry": {"coordinates":[100.75028,18.67907],"type":"Point"}
}