{
  "type": "Feature",
  "properties": {
    "gn:admin1_code":"61.0",
    "gn:asciiname":"Ban Tha Sai",
    "gn:country_code":"TH",
    "gn:dem":24,
    "gn:feature_class":"P",
    "gn:feature_code":"PPL",
    "gn:name":"Ban Tha Sai",
    "gn:population":0,
    "gn:timezone":"Asia/Bangkok",
    "iso:country":"TH",
    "name:tha_x_preferred":[
        "\u0e1a\u0e49\u0e32\u0e19\u0e17\u0e48\u0e32\u0e44\u0e17\u0e23"
    ],
    "wof:name":"Ban Tha Sai",
    "wof:placetype":"locality"
},
  "geometry": {"coordinates":[98.43536,8.78564],"type":"Point"}
}