{
  "type": "Feature",
  "properties": {
    "gn:admin1_code":"50.0",
    "gn:asciiname":"Ban Thi Phu Ye",
    "gn:country_code":"TH",
    "gn:dem":513,
    "gn:feature_class":"P",
    "gn:feature_code":"PPL",
    "gn:name":"Ban Thi Phu Ye",
    "gn:population":0,
    "gn:timezone":"Asia/Bangkok",
    "iso:country":"TH",
    "name:tha_x_preferred":[
        "\u0e1a\u0e49\u0e32\u0e19\u0e17\u0e34\u0e1e\u0e38\u0e40\u0e22"
    ],
    "name:und_x_variant":[
        "Ban Thiphaye",
        "Ban Thi Phu Ye"
    ],
    "wof:name":"Ban Thi Phu Ye",
    "wof:placetype":"locality"
},
  "geometry": {"coordinates":[98.69528,14.95386],"type":"Point"}
}