{
  "type": "Feature",
  "properties": {
    "gn:admin1_code":"34",
    "gn:asciiname":"Ban Noi Phatthana",
    "gn:country_code":"TH",
    "gn:dem":88,
    "gn:feature_class":"P",
    "gn:feature_code":"PPL",
    "gn:name":"Ban Noi Phatthana",
    "gn:population":0,
    "gn:timezone":"Asia/Bangkok",
    "iso:country":"TH",
    "name:tha_x_preferred":[
        "\u0e1a\u0e49\u0e32\u0e19\u0e19\u0e49\u0e2d\u0e22\u0e1e\u0e31\u0e12\u0e19\u0e32"
    ],
    "wof:lang_x_official":[
        "tha"
    ],
    "wof:lang_x_spoken":[
        "tha"
    ],
    "wof:name":"Ban Noi Phatthana",
    "wof:placetype":"locality"
},
  "geometry": {"coordinates":[101.32469,15.28153],"type":"Point"}
}