{
  "type": "Feature",
  "properties": {
    "gn:admin1_code":"76.0",
    "gn:asciiname":"Ban Kut Ling Ngo",
    "gn:country_code":"TH",
    "gn:dem":205,
    "gn:feature_class":"P",
    "gn:feature_code":"PPL",
    "gn:name":"Ban Kut Ling Ngo",
    "gn:population":0,
    "gn:timezone":"Asia/Bangkok",
    "iso:country":"TH",
    "name:tha_x_preferred":[
        "\u0e1a\u0e49\u0e32\u0e19\u0e01\u0e38\u0e14\u0e25\u0e34\u0e07\u0e07\u0e49\u0e2d"
    ],
    "wof:name":"Ban Kut Ling Ngo",
    "wof:placetype":"locality"
},
  "geometry": {"coordinates":[102.73050000000001,17.33214],"type":"Point"}
}