{
  "type": "Feature",
  "properties": {
    "gn:admin1_code":"74.0",
    "gn:asciiname":"Ban Pak Phraek",
    "gn:country_code":"TH",
    "gn:dem":16,
    "gn:feature_class":"P",
    "gn:feature_code":"PPL",
    "gn:name":"Ban Pak Phraek",
    "gn:population":0,
    "gn:timezone":"Asia/Bangkok",
    "iso:country":"TH",
    "name:tha_x_preferred":[
        "\u0e1a\u0e49\u0e32\u0e19\u0e1b\u0e32\u0e01\u0e41\u0e1e\u0e23\u0e01"
    ],
    "wof:name":"Ban Pak Phraek",
    "wof:placetype":"locality"
},
  "geometry": {"coordinates":[101.68805999999999,13.98397],"type":"Point"}
}