{
  "type": "Feature",
  "properties": {
    "gn:admin1_code":"44.0",
    "gn:asciiname":"Ban Khlong Mai",
    "gn:country_code":"TH",
    "gn:dem":3,
    "gn:feature_class":"P",
    "gn:feature_code":"PPL",
    "gn:name":"Ban Khlong Mai",
    "gn:population":0,
    "gn:timezone":"Asia/Bangkok",
    "iso:country":"TH",
    "name:tha_x_preferred":[
        "\u0e1a\u0e49\u0e32\u0e19\u0e04\u0e25\u0e2d\u0e07\u0e43\u0e2b\u0e21\u0e48"
    ],
    "name:und_x_variant":[
        "Ban Khlong Mai (3)",
        "Ban Khlong Mai"
    ],
    "wof:name":"Ban Khlong Mai",
    "wof:placetype":"locality"
},
  "geometry": {"coordinates":[100.93541999999999,13.48414],"type":"Point"}
}