{
  "type": "Feature",
  "properties": {
    "gn:admin1_code":"70.0",
    "gn:asciiname":"Ban Ai Yoe Baro",
    "gn:country_code":"TH",
    "gn:dem":288,
    "gn:feature_class":"P",
    "gn:feature_code":"PPL",
    "gn:name":"Ban Ai Yoe Baro",
    "gn:population":0,
    "gn:timezone":"Asia/Bangkok",
    "iso:country":"TH",
    "wof:name":"Ban Ai Yoe Baro",
    "wof:placetype":"locality"
},
  "geometry": {"coordinates":[101.16667,5.98333],"type":"Point"}
}