{
  "type": "Feature",
  "properties": {
    "gn:admin1_code":"63.0",
    "gn:asciiname":"Ban Phan Phon",
    "gn:country_code":"TH",
    "gn:dem":71,
    "gn:feature_class":"P",
    "gn:feature_code":"PPL",
    "gn:name":"Ban Phan Phon",
    "gn:population":0,
    "gn:timezone":"Asia/Bangkok",
    "iso:country":"TH",
    "wof:name":"Ban Phan Phon",
    "wof:placetype":"locality"
},
  "geometry": {"coordinates":[99.26667,8.05],"type":"Point"}
}