{
  "type": "Feature",
  "properties": {
    "gn:admin1_code":"27",
    "gn:asciiname":"Ban Non Sai Thong",
    "gn:country_code":"TH",
    "gn:dem":189,
    "gn:feature_class":"P",
    "gn:feature_code":"PPL",
    "gn:name":"Ban Non Sai Thong",
    "gn:population":0,
    "gn:timezone":"Asia/Bangkok",
    "iso:country":"TH",
    "name:tha_x_preferred":[
        "\u0e1a\u0e49\u0e32\u0e19\u0e42\u0e19\u0e19\u0e17\u0e23\u0e32\u0e22\u0e17\u0e2d\u0e07"
    ],
    "wof:name":"Ban Non Sai Thong",
    "wof:placetype":"locality"
},
  "geometry": {"coordinates":[102.39955999999999,14.88467],"type":"Point"}
}