{
  "type": "Feature",
  "properties": {
    "gn:admin1_code":"56.0",
    "gn:asciiname":"Ban Kham",
    "gn:country_code":"TH",
    "gn:dem":7,
    "gn:feature_class":"P",
    "gn:feature_code":"PPL",
    "gn:name":"Ban Kham",
    "gn:population":0,
    "gn:timezone":"Asia/Bangkok",
    "iso:country":"TH",
    "name:tha_x_preferred":[
        "\u0e1a\u0e49\u0e32\u0e19\u0e02\u0e32\u0e21"
    ],
    "name:und_x_variant":[
        "Ban Bang Ham",
        "Ban Bang Kham",
        "Ban Kham"
    ],
    "wof:name":"Ban Kham",
    "wof:placetype":"locality"
},
  "geometry": {"coordinates":[99.89308,13.13197],"type":"Point"}
}