{
  "type": "Feature",
  "properties": {
    "gn:admin1_code":"25.0",
    "gn:asciiname":"Ban Hong Hae",
    "gn:country_code":"TH",
    "gn:dem":144,
    "gn:feature_class":"P",
    "gn:feature_code":"PPL",
    "gn:name":"Ban Hong Hae",
    "gn:population":0,
    "gn:timezone":"Asia/Bangkok",
    "iso:country":"TH",
    "name:tha_x_preferred":[
        "\u0e1a\u0e49\u0e32\u0e19\u0e2e\u0e48\u0e2d\u0e07\u0e41\u0e2e\u0e48"
    ],
    "wof:name":"Ban Hong Hae",
    "wof:placetype":"locality"
},
  "geometry": {"coordinates":[103.43206000000001,15.60714],"type":"Point"}
}