{
  "type": "Feature",
  "properties": {
    "gn:admin1_code":"30.0",
    "gn:asciiname":"Ban Lum Phuk",
    "gn:country_code":"TH",
    "gn:dem":179,
    "gn:feature_class":"P",
    "gn:feature_code":"PPL",
    "gn:name":"Ban Lum Phuk",
    "gn:population":0,
    "gn:timezone":"Asia/Bangkok",
    "iso:country":"TH",
    "name:tha_x_preferred":[
        "\u0e1a\u0e49\u0e32\u0e19\u0e25\u0e38\u0e21\u0e1e\u0e38\u0e01"
    ],
    "name:und_x_variant":[
        "Lom Puwa",
        "Ban Lumphur",
        "Lom Puk",
        "Ban Lumphuk",
        "Ban Lum Phuk"
    ],
    "wof:name":"Ban Lum Phuk",
    "wof:placetype":"locality"
},
  "geometry": {"coordinates":[104.22675,14.56269],"type":"Point"}
}