{
  "type": "Feature",
  "properties": {
    "gn:admin1_code":"5.0",
    "gn:asciiname":"Ban Nong Kok",
    "gn:country_code":"TH",
    "gn:dem":565,
    "gn:feature_class":"P",
    "gn:feature_code":"PPL",
    "gn:name":"Ban Nong Kok",
    "gn:population":0,
    "gn:timezone":"Asia/Bangkok",
    "iso:country":"TH",
    "name:tha_x_preferred":[
        "\u0e1a\u0e49\u0e32\u0e19\u0e2b\u0e19\u0e2d\u0e07\u0e01\u0e2d\u0e01"
    ],
    "wof:name":"Ban Nong Kok",
    "wof:placetype":"locality"
},
  "geometry": {"coordinates":[99.05192,17.86003],"type":"Point"}
}