{
  "type": "Feature",
  "properties": {
    "gn:admin1_code":"6.0",
    "gn:asciiname":"Ban Rong Kok",
    "gn:country_code":"TH",
    "gn:dem":301,
    "gn:feature_class":"P",
    "gn:feature_code":"PPL",
    "gn:name":"Ban Rong Kok",
    "gn:population":0,
    "gn:timezone":"Asia/Bangkok",
    "iso:country":"TH",
    "name:tha_x_preferred":[
        "\u0e1a\u0e49\u0e32\u0e19\u0e23\u0e49\u0e2d\u0e07\u0e01\u0e2d\u0e01"
    ],
    "name:und_x_variant":[
        "B\u0101n Raung Gauk",
        "Ban Long Kok"
    ],
    "wof:name":"Ban Rong Kok",
    "wof:placetype":"locality"
},
  "geometry": {"coordinates":[99.43292,18.49856],"type":"Point"}
}