{
  "type": "Feature",
  "properties": {
    "gn:admin1_code":"66.0",
    "gn:asciiname":"Ban Tha Khanun",
    "gn:country_code":"TH",
    "gn:dem":12,
    "gn:feature_class":"P",
    "gn:feature_code":"PPL",
    "gn:name":"Ban Tha Khanun",
    "gn:population":0,
    "gn:timezone":"Asia/Bangkok",
    "iso:country":"TH",
    "name:tha_x_preferred":[
        "\u0e1a\u0e49\u0e32\u0e19\u0e17\u0e48\u0e32\u0e02\u0e19\u0e38\u0e19"
    ],
    "wof:name":"Ban Tha Khanun",
    "wof:placetype":"locality"
},
  "geometry": {"coordinates":[100.05997000000001,7.69478],"type":"Point"}
}