{
  "type": "Feature",
  "properties": {
    "gn:admin1_code":"11.0",
    "gn:asciiname":"Ban Lan Dokmai Tai",
    "gn:country_code":"TH",
    "gn:dem":90,
    "gn:feature_class":"P",
    "gn:feature_code":"PPL",
    "gn:name":"Ban Lan Dokmai Tai",
    "gn:population":0,
    "gn:timezone":"Asia/Bangkok",
    "iso:country":"TH",
    "name:tha_x_preferred":[
        "\u0e1a\u0e49\u0e32\u0e19\u0e25\u0e32\u0e19\u0e14\u0e2d\u0e01\u0e44\u0e21\u0e49\u0e43\u0e15\u0e49"
    ],
    "wof:name":"Ban Lan Dokmai Tai",
    "wof:placetype":"locality"
},
  "geometry": {"coordinates":[99.45558,16.57956],"type":"Point"}
}