{
  "type": "Feature",
  "properties": {
    "gn:admin1_code":"76.0",
    "gn:asciiname":"Ban Dong Wai",
    "gn:country_code":"TH",
    "gn:dem":188,
    "gn:feature_class":"P",
    "gn:feature_code":"PPL",
    "gn:name":"Ban Dong Wai",
    "gn:population":0,
    "gn:timezone":"Asia/Bangkok",
    "iso:country":"TH",
    "name:tha_x_preferred":[
        "\u0e1a\u0e49\u0e32\u0e19\u0e14\u0e07\u0e2b\u0e27\u0e32\u0e22"
    ],
    "wof:name":"Ban Dong Wai",
    "wof:placetype":"locality"
},
  "geometry": {"coordinates":[103.26291999999999,17.83835],"type":"Point"}
}