{
  "type": "Feature",
  "properties": {
    "iso:country":"TH",
    "qs:name":"Hai Ya",
    "qs:name_adm0":"Thailand",
    "qs:name_adm1":"Chiang Mai",
    "qs:photos":55,
    "qs:photos_1k":11,
    "qs:photos_9k":1,
    "qs:photos_9r":2,
    "qs:photos_all":55,
    "qs:photos_sr":2,
    "qs:placetype":"Town",
    "qs:pop_sr":"0",
    "wof:name":"Hai Ya",
    "wof:placetype":"locality"
},
  "geometry": {"coordinates":[98.98956200000001,18.7765],"type":"Point"}
}