{
  "type": "Feature",
  "properties": {
    "gn:admin1_code":"52.0",
    "gn:asciiname":"Ban Mai Sai Ngam",
    "gn:country_code":"TH",
    "gn:dem":123,
    "gn:feature_class":"P",
    "gn:feature_code":"PPL",
    "gn:name":"Ban Mai Sai Ngam",
    "gn:population":0,
    "gn:timezone":"Asia/Bangkok",
    "iso:country":"TH",
    "name:tha_x_preferred":[
        "\u0e1a\u0e49\u0e32\u0e19\u0e43\u0e2b\u0e21\u0e48\u0e44\u0e17\u0e23\u0e07\u0e32\u0e21"
    ],
    "wof:name":"Ban Mai Sai Ngam",
    "wof:placetype":"locality"
},
  "geometry": {"coordinates":[99.529,13.70058],"type":"Point"}
}