{
  "type": "Feature",
  "properties": {
    "gn:admin1_code":"46.0",
    "gn:asciiname":"Ban Noen Saen Suk",
    "gn:country_code":"TH",
    "gn:dem":91,
    "gn:feature_class":"P",
    "gn:feature_code":"PPL",
    "gn:name":"Ban Noen Saen Suk",
    "gn:population":0,
    "gn:timezone":"Asia/Bangkok",
    "iso:country":"TH",
    "name:tha_x_preferred":[
        "\u0e1a\u0e49\u0e32\u0e19\u0e40\u0e19\u0e34\u0e19\u0e41\u0e2a\u0e19\u0e2a\u0e38\u0e02"
    ],
    "wof:name":"Ban Noen Saen Suk",
    "wof:placetype":"locality"
},
  "geometry": {"coordinates":[101.0425,13.14981],"type":"Point"}
}