{
  "type": "Feature",
  "properties": {
    "gn:admin1_code":"29",
    "gn:asciiname":"Ban Phram",
    "gn:country_code":"TH",
    "gn:dem":138,
    "gn:feature_class":"P",
    "gn:feature_code":"PPL",
    "gn:name":"Ban Phram",
    "gn:population":0,
    "gn:timezone":"Asia/Bangkok",
    "iso:country":"TH",
    "name:tha_x_preferred":[
        "\u0e1a\u0e49\u0e32\u0e19\u0e1e\u0e23\u0e32\u0e2b\u0e21\u0e13\u0e4c"
    ],
    "wof:name":"Ban Phram",
    "wof:placetype":"locality"
},
  "geometry": {"coordinates":[103.93772,15.20431],"type":"Point"}
}