{
  "type": "Feature",
  "properties": {
    "gn:admin1_code":"81.0",
    "gn:asciiname":"Ban Ta Koeng",
    "gn:country_code":"TH",
    "gn:dem":153,
    "gn:feature_class":"P",
    "gn:feature_code":"PPL",
    "gn:name":"Ban Ta Koeng",
    "gn:population":0,
    "gn:timezone":"Asia/Bangkok",
    "iso:country":"TH",
    "name:und_x_variant":[
        "Ban Sam Pong",
        "Ban Ta Koeng"
    ],
    "wof:name":"Ban Ta Koeng",
    "wof:placetype":"locality"
},
  "geometry": {"coordinates":[103.58333,18.06667],"type":"Point"}
}