{
  "type": "Feature",
  "properties": {
    "gn:admin1_code":"79.0",
    "gn:asciiname":"Ban Non Ko",
    "gn:country_code":"TH",
    "gn:dem":222,
    "gn:feature_class":"P",
    "gn:feature_code":"PPL",
    "gn:name":"Ban Non Ko",
    "gn:population":0,
    "gn:timezone":"Asia/Bangkok",
    "iso:country":"TH",
    "name:tha_x_preferred":[
        "\u0e1a\u0e49\u0e32\u0e19\u0e42\u0e19\u0e19\u0e42\u0e01"
    ],
    "wof:name":"Ban Non Ko",
    "wof:placetype":"locality"
},
  "geometry": {"coordinates":[102.42932999999999,17.21681],"type":"Point"}
}