{
  "type": "Feature",
  "properties": {
    "gn:admin1_code":"52.0",
    "gn:asciiname":"Ban Khok Oi",
    "gn:country_code":"TH",
    "gn:dem":6,
    "gn:feature_class":"P",
    "gn:feature_code":"PPL",
    "gn:name":"Ban Khok Oi",
    "gn:population":0,
    "gn:timezone":"Asia/Bangkok",
    "iso:country":"TH",
    "name:tha_x_preferred":[
        "\u0e1a\u0e49\u0e32\u0e19\u0e42\u0e04\u0e01\u0e2d\u0e49\u0e2d\u0e22"
    ],
    "wof:name":"Ban Khok Oi",
    "wof:placetype":"locality"
},
  "geometry": {"coordinates":[99.88367,13.58136],"type":"Point"}
}