{
  "type": "Feature",
  "properties": {
    "gn:admin1_code":"10.0",
    "gn:asciiname":"Ban Thai Nam",
    "gn:country_code":"TH",
    "gn:dem":59,
    "gn:feature_class":"P",
    "gn:feature_code":"PPL",
    "gn:name":"Ban Thai Nam",
    "gn:population":0,
    "gn:timezone":"Asia/Bangkok",
    "iso:country":"TH",
    "name:tha_x_preferred":[
        "Ban Thai Nam"
    ],
    "name:tha_x_variant":[
        "\u0e1a\u0e49\u0e32\u0e19\u0e17\u0e49\u0e32\u0e22\u0e19\u0e49\u0e33"
    ],
    "wof:name":"Ban Thai Nam",
    "wof:placetype":"locality"
},
  "geometry": {"coordinates":[100.0677,17.25247],"type":"Point"}
}