{
  "type": "Feature",
  "properties": {
    "gn:admin1_code":"2.0",
    "gn:asciiname":"Ban Mae Bon",
    "gn:country_code":"TH",
    "gn:dem":471,
    "gn:feature_class":"P",
    "gn:feature_code":"PPL",
    "gn:name":"Ban Mae Bon",
    "gn:population":0,
    "gn:timezone":"Asia/Bangkok",
    "iso:country":"TH",
    "name:tha_x_preferred":[
        "\u0e1a\u0e49\u0e32\u0e19\u0e41\u0e21\u0e48\u0e1a\u0e2d\u0e19"
    ],
    "name:und_x_variant":[
        "Ban Mae Pon"
    ],
    "wof:name":"Ban Mae Bon",
    "wof:placetype":"locality"
},
  "geometry": {"coordinates":[99.20419,19.103],"type":"Point"}
}