{
  "type": "Feature",
  "properties": {
    "gn:admin1_code":"34.0",
    "gn:asciiname":"Ban Nong Pladuk",
    "gn:country_code":"TH",
    "gn:dem":11,
    "gn:feature_class":"P",
    "gn:feature_code":"PPL",
    "gn:name":"Ban Nong Pladuk",
    "gn:population":0,
    "gn:timezone":"Asia/Bangkok",
    "iso:country":"TH",
    "name:tha_x_preferred":[
        "\u0e1a\u0e49\u0e32\u0e19\u0e2b\u0e19\u0e2d\u0e07\u0e1b\u0e25\u0e32\u0e14\u0e38\u0e01"
    ],
    "name:und_x_variant":[
        "Ban Nong Pla Duk"
    ],
    "wof:name":"Ban Nong Pladuk",
    "wof:placetype":"locality"
},
  "geometry": {"coordinates":[100.53185999999999,14.90017],"type":"Point"}
}