{
  "type": "Feature",
  "properties": {
    "gn:admin1_code":"38.0",
    "gn:asciiname":"Ban Khlong Phai Khat",
    "gn:country_code":"TH",
    "gn:dem":2,
    "gn:feature_class":"P",
    "gn:feature_code":"PPL",
    "gn:name":"Ban Khlong Phai Khat",
    "gn:population":0,
    "gn:timezone":"Asia/Bangkok",
    "iso:country":"TH",
    "name:tha_x_preferred":[
        "\u0e1a\u0e49\u0e32\u0e19\u0e04\u0e25\u0e2d\u0e07\u0e44\u0e1c\u0e48\u0e02\u0e32\u0e14"
    ],
    "wof:name":"Ban Khlong Phai Khat",
    "wof:placetype":"locality"
},
  "geometry": {"coordinates":[100.31769,13.85289],"type":"Point"}
}