{
  "type": "Feature",
  "properties": {
    "gn:admin1_code":"66.0",
    "gn:asciiname":"Ban Rae",
    "gn:country_code":"TH",
    "gn:dem":17,
    "gn:feature_class":"P",
    "gn:feature_code":"PPL",
    "gn:name":"Ban Rae",
    "gn:population":0,
    "gn:timezone":"Asia/Bangkok",
    "iso:country":"TH",
    "name:tha_x_preferred":[
        "\u0e1a\u0e49\u0e32\u0e19\u0e41\u0e23\u0e48"
    ],
    "name:und_x_variant":[
        "Ban Khuan Rai",
        "Ban Khuan Rae",
        "Ban Rae"
    ],
    "wof:name":"Ban Rae",
    "wof:placetype":"locality"
},
  "geometry": {"coordinates":[100.11872,7.62408],"type":"Point"}
}