{
  "type": "Feature",
  "properties": {
    "gn:admin1_code":"72.0",
    "gn:asciiname":"Ban Non Nong Phue",
    "gn:country_code":"TH",
    "gn:dem":145,
    "gn:feature_class":"P",
    "gn:feature_code":"PPL",
    "gn:name":"Ban Non Nong Phue",
    "gn:population":0,
    "gn:timezone":"Asia/Bangkok",
    "iso:country":"TH",
    "name:tha_x_preferred":[
        "\u0e1a\u0e49\u0e32\u0e19\u0e42\u0e19\u0e19\u0e2b\u0e19\u0e2d\u0e07\u0e1c\u0e37\u0e2d"
    ],
    "wof:name":"Ban Non Nong Phue",
    "wof:placetype":"locality"
},
  "geometry": {"coordinates":[104.52786,16.05702999999999],"type":"Point"}
}