{
  "type": "Feature",
  "properties": {
    "gn:admin1_code":"60.0",
    "gn:asciiname":"Ban Suan Prang",
    "gn:country_code":"TH",
    "gn:dem":73,
    "gn:feature_class":"P",
    "gn:feature_code":"PPL",
    "gn:name":"Ban Suan Prang",
    "gn:population":0,
    "gn:timezone":"Asia/Bangkok",
    "iso:country":"TH",
    "name:tha_x_preferred":[
        "\u0e1a\u0e49\u0e32\u0e19\u0e2a\u0e27\u0e19\u0e1b\u0e23\u0e32\u0e07"
    ],
    "wof:name":"Ban Suan Prang",
    "wof:placetype":"locality"
},
  "geometry": {"coordinates":[99.64597000000001,9.01072],"type":"Point"}
}