{
  "type": "Feature",
  "properties": {
    "gn:admin1_code":"44.0",
    "gn:asciiname":"Ban Bang Ruean",
    "gn:country_code":"TH",
    "gn:dem":5,
    "gn:feature_class":"P",
    "gn:feature_code":"PPL",
    "gn:name":"Ban Bang Ruean",
    "gn:population":0,
    "gn:timezone":"Asia/Bangkok",
    "iso:country":"TH",
    "name:tha_x_preferred":[
        "\u0e1a\u0e49\u0e32\u0e19\u0e1a\u0e32\u0e07\u0e40\u0e23\u0e37\u0e2d\u0e19"
    ],
    "wof:name":"Ban Bang Ruean",
    "wof:placetype":"locality"
},
  "geometry": {"coordinates":[101.00539000000001,13.67789],"type":"Point"}
}