{
  "type": "Feature",
  "properties": {
    "gn:admin1_code":"18.0",
    "gn:asciiname":"Ban Tha Sa-at",
    "gn:country_code":"TH",
    "gn:dem":334,
    "gn:feature_class":"P",
    "gn:feature_code":"PPL",
    "gn:name":"Ban Tha Sa-at",
    "gn:population":0,
    "gn:timezone":"Asia/Bangkok",
    "iso:country":"TH",
    "name:tha_x_preferred":[
        "Ban Tha Sa-at"
    ],
    "name:tha_x_variant":[
        "\u0e1a\u0e49\u0e32\u0e19\u0e17\u0e48\u0e32\u0e2a\u0e30\u0e2d\u0e32\u0e14"
    ],
    "name:und_x_variant":[
        "Ban Suai Tha Sa-at"
    ],
    "wof:name":"Ban Tha Sa-at",
    "wof:placetype":"locality"
},
  "geometry": {"coordinates":[101.923,17.49422],"type":"Point"}
}