{
  "type": "Feature",
  "properties": {
    "gn:admin1_code":"20.0",
    "gn:asciiname":"Ban Men Noi",
    "gn:country_code":"TH",
    "gn:dem":180,
    "gn:feature_class":"P",
    "gn:feature_code":"PPL",
    "gn:name":"Ban Men Noi",
    "gn:population":0,
    "gn:timezone":"Asia/Bangkok",
    "iso:country":"TH",
    "name:tha_x_preferred":[
        "\u0e1a\u0e49\u0e32\u0e19\u0e40\u0e21\u0e48\u0e19\u0e19\u0e49\u0e2d\u0e22"
    ],
    "wof:name":"Ban Men Noi",
    "wof:placetype":"locality"
},
  "geometry": {"coordinates":[104.00247,17.49152999999999],"type":"Point"}
}