{
  "type": "Feature",
  "properties": {
    "gn:admin1_code":"58.0",
    "gn:asciiname":"Ban Satong Lang",
    "gn:country_code":"TH",
    "gn:dem":118,
    "gn:feature_class":"P",
    "gn:feature_code":"PPL",
    "gn:name":"Ban Satong Lang",
    "gn:population":0,
    "gn:timezone":"Asia/Bangkok",
    "iso:country":"TH",
    "name:tha_x_preferred":[
        "\u0e1a\u0e49\u0e32\u0e19\u0e2a\u0e30\u0e15\u0e07\u0e25\u0e48\u0e32\u0e07"
    ],
    "wof:name":"Ban Satong Lang",
    "wof:placetype":"locality"
},
  "geometry": {"coordinates":[99.00731,10.79095],"type":"Point"}
}