{
  "type": "Feature",
  "properties": {
    "gn:admin1_code":"11.0",
    "gn:asciiname":"Ban Chom Khwaen",
    "gn:country_code":"TH",
    "gn:dem":114,
    "gn:feature_class":"P",
    "gn:feature_code":"PPL",
    "gn:name":"Ban Chom Khwaen",
    "gn:population":0,
    "gn:timezone":"Asia/Bangkok",
    "iso:country":"TH",
    "name:tha_x_preferred":[
        "\u0e1a\u0e49\u0e32\u0e19\u0e08\u0e2d\u0e21\u0e41\u0e02\u0e27\u0e19"
    ],
    "wof:name":"Ban Chom Khwaen",
    "wof:placetype":"locality"
},
  "geometry": {"coordinates":[99.44247,16.17461],"type":"Point"}
}