{
  "type": "Feature",
  "properties": {
    "gn:admin1_code":"26.0",
    "gn:asciiname":"Ban Hua Pluak Laem",
    "gn:country_code":"TH",
    "gn:dem":269,
    "gn:feature_class":"P",
    "gn:feature_code":"PPL",
    "gn:name":"Ban Hua Pluak Laem",
    "gn:population":0,
    "gn:timezone":"Asia/Bangkok",
    "iso:country":"TH",
    "name:tha_x_preferred":[
        "\u0e1a\u0e49\u0e32\u0e19\u0e2b\u0e31\u0e27\u0e1b\u0e25\u0e27\u0e01\u0e41\u0e2b\u0e25\u0e21"
    ],
    "wof:name":"Ban Hua Pluak Laem",
    "wof:placetype":"locality"
},
  "geometry": {"coordinates":[101.81447,16.63917],"type":"Point"}
}