{
  "type": "Feature",
  "properties": {
    "gn:admin1_code":"22.0",
    "gn:asciiname":"Ban Pak Ngam",
    "gn:country_code":"TH",
    "gn:dem":235,
    "gn:feature_class":"P",
    "gn:feature_code":"PPL",
    "gn:name":"Ban Pak Ngam",
    "gn:population":0,
    "gn:timezone":"Asia/Bangkok",
    "iso:country":"TH",
    "name:tha_x_preferred":[
        "\u0e1a\u0e49\u0e32\u0e19\u0e1b\u0e32\u0e01\u0e07\u0e48\u0e32\u0e21"
    ],
    "name:und_x_variant":[
        "Ban Nong Bak Ngam"
    ],
    "wof:name":"Ban Pak Ngam",
    "wof:placetype":"locality"
},
  "geometry": {"coordinates":[102.12375,16.66856],"type":"Point"}
}