{
  "type": "Feature",
  "properties": {
    "gn:admin1_code":"1.0",
    "gn:asciiname":"Ban Mo Chi Pho",
    "gn:country_code":"TH",
    "gn:dem":714,
    "gn:feature_class":"P",
    "gn:feature_code":"PPL",
    "gn:name":"Ban Mo Chi Pho",
    "gn:population":0,
    "gn:timezone":"Asia/Bangkok",
    "iso:country":"TH",
    "name:tha_x_preferred":[
        "\u0e1a\u0e49\u0e32\u0e19\u0e2b\u0e21\u0e48\u0e2d\u0e08\u0e35\u0e42\u0e1e"
    ],
    "wof:name":"Ban Mo Chi Pho",
    "wof:placetype":"locality"
},
  "geometry": {"coordinates":[97.75886,18.53203],"type":"Point"}
}