{
  "type": "Feature",
  "properties": {
    "gn:admin1_code":"24.0",
    "gn:asciiname":"Ban Phakwaen",
    "gn:country_code":"TH",
    "gn:dem":181,
    "gn:feature_class":"P",
    "gn:feature_code":"PPL",
    "gn:name":"Ban Phakwaen",
    "gn:population":0,
    "gn:timezone":"Asia/Bangkok",
    "iso:country":"TH",
    "name:tha_x_preferred":[
        "\u0e1a\u0e49\u0e32\u0e19\u0e1c\u0e31\u0e01\u0e41\u0e27\u0e48\u0e19"
    ],
    "name:und_x_variant":[
        "Ban Nong Phak Waen"
    ],
    "wof:name":"Ban Phakwaen",
    "wof:placetype":"locality"
},
  "geometry": {"coordinates":[103.15152999999999,16.50228],"type":"Point"}
}