{
  "type": "Feature",
  "properties": {
    "gn:admin1_code":"79.0",
    "gn:asciiname":"Ban Wang Pong",
    "gn:country_code":"TH",
    "gn:dem":260,
    "gn:feature_class":"P",
    "gn:feature_code":"PPL",
    "gn:name":"Ban Wang Pong",
    "gn:population":0,
    "gn:timezone":"Asia/Bangkok",
    "iso:country":"TH",
    "name:tha_x_preferred":[
        "\u0e1a\u0e49\u0e32\u0e19\u0e27\u0e31\u0e07\u0e42\u0e1b\u0e48\u0e07"
    ],
    "name:und_x_variant":[
        "Ban Wang Prong"
    ],
    "wof:name":"Ban Wang Pong",
    "wof:placetype":"locality"
},
  "geometry": {"coordinates":[102.11644,17.30425],"type":"Point"}
}