{
  "type": "Feature",
  "properties": {
    "gn:admin1_code":"11.0",
    "gn:asciiname":"Ban Si Bun Song",
    "gn:country_code":"TH",
    "gn:dem":65,
    "gn:feature_class":"P",
    "gn:feature_code":"PPL",
    "gn:name":"Ban Si Bun Song",
    "gn:population":0,
    "gn:timezone":"Asia/Bangkok",
    "iso:country":"TH",
    "name:tha_x_preferred":[
        "\u0e1a\u0e49\u0e32\u0e19\u0e28\u0e23\u0e35\u0e1a\u0e38\u0e0d\u0e2a\u0e48\u0e07"
    ],
    "wof:name":"Ban Si Bun Song",
    "wof:placetype":"locality"
},
  "geometry": {"coordinates":[99.73725,16.45581],"type":"Point"}
}