{
  "type": "Feature",
  "properties": {
    "gn:admin1_code":"39.0",
    "gn:asciiname":"Ban Lat Thong Wang",
    "gn:country_code":"TH",
    "gn:dem":4,
    "gn:feature_class":"P",
    "gn:feature_code":"PPL",
    "gn:name":"Ban Lat Thong Wang",
    "gn:population":0,
    "gn:timezone":"Asia/Bangkok",
    "iso:country":"TH",
    "name:tha_x_preferred":[
        "Ban Lat Thong Wang"
    ],
    "name:tha_x_variant":[
        "\u0e1a\u0e49\u0e32\u0e19\u0e25\u0e32\u0e14\u0e17\u0e49\u0e2d\u0e07\u0e27\u0e31\u0e07"
    ],
    "wof:name":"Ban Lat Thong Wang",
    "wof:placetype":"locality"
},
  "geometry": {"coordinates":[100.48399999999999,14.10822],"type":"Point"}
}