{
  "type": "Feature",
  "properties": {
    "gn:admin1_code":"30.0",
    "gn:asciiname":"Ban Nong Bua Lon",
    "gn:country_code":"TH",
    "gn:dem":127,
    "gn:feature_class":"P",
    "gn:feature_code":"PPL",
    "gn:name":"Ban Nong Bua Lon",
    "gn:population":0,
    "gn:timezone":"Asia/Bangkok",
    "iso:country":"TH",
    "name:tha_x_preferred":[
        "\u0e1a\u0e49\u0e32\u0e19\u0e2b\u0e19\u0e2d\u0e07\u0e1a\u0e31\u0e27\u0e2b\u0e25\u0e48\u0e19"
    ],
    "wof:name":"Ban Nong Bua Lon",
    "wof:placetype":"locality"
},
  "geometry": {"coordinates":[104.13203,15.49531],"type":"Point"}
}