{
  "type": "Feature",
  "properties": {
    "gn:admin1_code":"75.0",
    "gn:asciiname":"Ban Kham Nang Ruai",
    "gn:country_code":"TH",
    "gn:dem":129,
    "gn:feature_class":"P",
    "gn:feature_code":"PPL",
    "gn:name":"Ban Kham Nang Ruai",
    "gn:population":0,
    "gn:timezone":"Asia/Bangkok",
    "iso:country":"TH",
    "name:tha_x_preferred":[
        "\u0e1a\u0e49\u0e32\u0e19\u0e04\u0e33\u0e19\u0e32\u0e07\u0e23\u0e27\u0e22"
    ],
    "wof:name":"Ban Kham Nang Ruai",
    "wof:placetype":"locality"
},
  "geometry": {"coordinates":[104.83242,15.18956],"type":"Point"}
}