{
  "type": "Feature",
  "properties": {
    "gn:admin1_code":"13.0",
    "gn:asciiname":"Ban Yang Nokkrathung",
    "gn:country_code":"TH",
    "gn:dem":47,
    "gn:feature_class":"P",
    "gn:feature_code":"PPL",
    "gn:name":"Ban Yang Nokkrathung",
    "gn:population":0,
    "gn:timezone":"Asia/Bangkok",
    "iso:country":"TH",
    "name:tha_x_preferred":[
        "\u0e1a\u0e49\u0e32\u0e19\u0e22\u0e32\u0e07\u0e19\u0e01\u0e01\u0e23\u0e30\u0e17\u0e38\u0e07"
    ],
    "wof:name":"Ban Yang Nokkrathung",
    "wof:placetype":"locality"
},
  "geometry": {"coordinates":[100.14906000000001,16.55656],"type":"Point"}
}