{
  "type": "Feature",
  "properties": {
    "gn:admin1_code":"14.0",
    "gn:asciiname":"Ban Huai Ya Khruea",
    "gn:country_code":"TH",
    "gn:dem":777,
    "gn:feature_class":"P",
    "gn:feature_code":"PPL",
    "gn:name":"Ban Huai Ya Khruea",
    "gn:population":0,
    "gn:timezone":"Asia/Bangkok",
    "iso:country":"TH",
    "name:tha_x_preferred":[
        "\u0e1a\u0e49\u0e32\u0e19\u0e2b\u0e49\u0e27\u0e22\u0e2b\u0e0d\u0e49\u0e32\u0e40\u0e04\u0e23\u0e37\u0e2d"
    ],
    "name:und_x_variant":[
        "Ban Huai Ya Khrua"
    ],
    "wof:name":"Ban Huai Ya Khruea",
    "wof:placetype":"locality"
},
  "geometry": {"coordinates":[101.62457999999999,16.83086],"type":"Point"}
}