{
  "type": "Feature",
  "properties": {
    "gn:admin1_code":"26.0",
    "gn:asciiname":"Ban Non Khun",
    "gn:country_code":"TH",
    "gn:dem":225,
    "gn:feature_class":"P",
    "gn:feature_code":"PPL",
    "gn:name":"Ban Non Khun",
    "gn:population":0,
    "gn:timezone":"Asia/Bangkok",
    "iso:country":"TH",
    "name:tha_x_preferred":[
        "\u0e1a\u0e49\u0e32\u0e19\u0e42\u0e19\u0e19\u0e04\u0e39\u0e13"
    ],
    "wof:name":"Ban Non Khun",
    "wof:placetype":"locality"
},
  "geometry": {"coordinates":[102.03444,16.50567],"type":"Point"}
}