{
  "type": "Feature",
  "properties": {
    "gn:admin1_code":"36.0",
    "gn:asciiname":"Ban Ai Waen",
    "gn:country_code":"TH",
    "gn:dem":4,
    "gn:feature_class":"P",
    "gn:feature_code":"PPL",
    "gn:name":"Ban Ai Waen",
    "gn:population":0,
    "gn:timezone":"Asia/Bangkok",
    "iso:country":"TH",
    "name:tha_x_preferred":[
        "Ban Ai Waen"
    ],
    "wof:name":"Ban Ai Waen",
    "wof:placetype":"locality"
},
  "geometry": {"coordinates":[100.46666999999999,14.18333],"type":"Point"}
}