{
  "type": "Feature",
  "properties": {
    "gn:admin1_code":"74",
    "gn:asciiname":"Ban Rabo Ket",
    "gn:country_code":"TH",
    "gn:dem":46,
    "gn:feature_class":"P",
    "gn:feature_code":"PPL",
    "gn:name":"Ban Rabo Ket",
    "gn:population":0,
    "gn:timezone":"Asia/Bangkok",
    "iso:country":"TH",
    "name:tha_x_preferred":[
        "\u0e1a\u0e49\u0e32\u0e19\u0e23\u0e30\u0e40\u0e1a\u0e32\u0e30\u0e40\u0e01\u0e15\u0e38"
    ],
    "wof:name":"Ban Rabo Ket",
    "wof:placetype":"locality"
},
  "geometry": {"coordinates":[101.83983000000001,14.14031],"type":"Point"}
}