{
  "type": "Feature",
  "properties": {
    "gn:admin1_code":"29",
    "gn:asciiname":"Ban Kaen Methi",
    "gn:country_code":"TH",
    "gn:dem":140,
    "gn:feature_class":"P",
    "gn:feature_code":"PPL",
    "gn:name":"Ban Kaen Methi",
    "gn:population":0,
    "gn:timezone":"Asia/Bangkok",
    "iso:country":"TH",
    "name:tha_x_preferred":[
        "\u0e1a\u0e49\u0e32\u0e19\u0e41\u0e01\u0e48\u0e19\u0e40\u0e21\u0e18\u0e35"
    ],
    "wof:name":"Ban Kaen Methi",
    "wof:placetype":"locality"
},
  "geometry": {"coordinates":[103.92061,14.905],"type":"Point"}
}