{
  "type": "Feature",
  "properties": {
    "gn:admin1_code":"14.0",
    "gn:asciiname":"Ban Nam Om",
    "gn:country_code":"TH",
    "gn:dem":161,
    "gn:feature_class":"P",
    "gn:feature_code":"PPL",
    "gn:name":"Ban Nam Om",
    "gn:population":0,
    "gn:timezone":"Asia/Bangkok",
    "iso:country":"TH",
    "name:tha_x_preferred":[
        "\u0e1a\u0e49\u0e32\u0e19\u0e19\u0e49\u0e33\u0e2d\u0e49\u0e2d\u0e21"
    ],
    "wof:name":"Ban Nam Om",
    "wof:placetype":"locality"
},
  "geometry": {"coordinates":[101.19777999999999,16.74464],"type":"Point"}
}