{
  "type": "Feature",
  "properties": {
    "gn:admin1_code":"2.0",
    "gn:asciiname":"Ban Mon Tai",
    "gn:country_code":"TH",
    "gn:dem":305,
    "gn:feature_class":"P",
    "gn:feature_code":"PPL",
    "gn:name":"Ban Mon Tai",
    "gn:population":0,
    "gn:timezone":"Asia/Bangkok",
    "iso:country":"TH",
    "name:tha_x_preferred":[
        "\u0e1a\u0e49\u0e32\u0e19\u0e21\u0e2d\u0e0d\u0e43\u0e15\u0e49"
    ],
    "wof:name":"Ban Mon Tai",
    "wof:placetype":"locality"
},
  "geometry": {"coordinates":[99.04933,18.78645],"type":"Point"}
}