{
  "type": "Feature",
  "properties": {
    "gn:admin1_code":"3.0",
    "gn:asciiname":"Ban Pha Chi Phaya Phrai",
    "gn:country_code":"TH",
    "gn:dem":1047,
    "gn:feature_class":"P",
    "gn:feature_code":"PPL",
    "gn:name":"Ban Pha Chi Phaya Phrai",
    "gn:population":0,
    "gn:timezone":"Asia/Bangkok",
    "iso:country":"TH",
    "name:tha_x_preferred":[
        "\u0e1a\u0e49\u0e32\u0e19\u0e1c\u0e32\u0e08\u0e35\u0e1e\u0e0d\u0e32\u0e44\u0e1e\u0e23"
    ],
    "wof:name":"Ban Pha Chi Phaya Phrai",
    "wof:placetype":"locality"
},
  "geometry": {"coordinates":[99.64942000000001,20.308],"type":"Point"}
}