{
  "type": "Feature",
  "properties": {
    "gn:admin1_code":"3.0",
    "gn:asciiname":"Ban Nang Lae Nai",
    "gn:country_code":"TH",
    "gn:dem":407,
    "gn:feature_class":"P",
    "gn:feature_code":"PPL",
    "gn:name":"Ban Nang Lae Nai",
    "gn:population":0,
    "gn:timezone":"Asia/Bangkok",
    "iso:country":"TH",
    "name:tha_x_preferred":[
        "\u0e1a\u0e49\u0e32\u0e19\u0e19\u0e32\u0e07\u0e41\u0e25\u0e43\u0e19"
    ],
    "wof:name":"Ban Nang Lae Nai",
    "wof:placetype":"locality"
},
  "geometry": {"coordinates":[99.85092,20.02342],"type":"Point"}
}