{
  "type": "Feature",
  "properties": {
    "gn:admin1_code":"50.0",
    "gn:asciiname":"Ban Bong Ti Lang",
    "gn:country_code":"TH",
    "gn:dem":232,
    "gn:feature_class":"P",
    "gn:feature_code":"PPL",
    "gn:name":"Ban Bong Ti Lang",
    "gn:population":0,
    "gn:timezone":"Asia/Bangkok",
    "iso:country":"TH",
    "name:tha_x_preferred":[
        "\u0e1a\u0e49\u0e32\u0e19\u0e1a\u0e49\u0e2d\u0e07\u0e15\u0e35\u0e49\u0e25\u0e48\u0e32\u0e07"
    ],
    "name:und_x_variant":[
        "Baung Ti Lang",
        "Ban Bong Ti Lang",
        "B\u014dhng Ti",
        "B\u0101n Bohng Ti",
        "Ban Bong Ti"
    ],
    "wof:name":"Ban Bong Ti Lang",
    "wof:placetype":"locality"
},
  "geometry": {"coordinates":[98.9997,14.10308],"type":"Point"}
}