{
  "type": "Feature",
  "properties": {
    "gn:admin1_code":"68.0",
    "gn:asciiname":"Ban Plai Han",
    "gn:country_code":"TH",
    "gn:dem":124,
    "gn:feature_class":"P",
    "gn:feature_code":"PPL",
    "gn:name":"Ban Plai Han",
    "gn:population":0,
    "gn:timezone":"Asia/Bangkok",
    "iso:country":"TH",
    "name:tha_x_preferred":[
        "\u0e1a\u0e49\u0e32\u0e19\u0e1b\u0e25\u0e32\u0e22\u0e2e\u0e31\u0e19"
    ],
    "wof:name":"Ban Plai Han",
    "wof:placetype":"locality"
},
  "geometry": {"coordinates":[100.76939,6.531],"type":"Point"}
}