{
  "type": "Feature",
  "properties": {
    "gn:admin1_code":"31.0",
    "gn:asciiname":"Ban To Ka Po",
    "gn:country_code":"TH",
    "gn:dem":57,
    "gn:feature_class":"P",
    "gn:feature_code":"PPL",
    "gn:name":"Ban To Ka Po",
    "gn:population":0,
    "gn:timezone":"Asia/Bangkok",
    "iso:country":"TH",
    "name:tha_x_preferred":[
        "\u0e1a\u0e49\u0e32\u0e19\u0e42\u0e15\u0e4a\u0e30\u0e01\u0e32\u0e40\u0e1b\u0e32\u0e30"
    ],
    "wof:lang_x_official":[
        "tha"
    ],
    "wof:lang_x_spoken":[
        "tha"
    ],
    "wof:name":"Ban To Ka Po",
    "wof:placetype":"locality"
},
  "geometry": {"coordinates":[101.57080999999999,6.37711],"type":"Point"}
}