{
  "type": "Feature",
  "properties": {
    "gn:admin1_code":"75.0",
    "gn:asciiname":"Ban Na Krasaeng",
    "gn:country_code":"TH",
    "gn:dem":165,
    "gn:feature_class":"P",
    "gn:feature_code":"PPL",
    "gn:name":"Ban Na Krasaeng",
    "gn:population":0,
    "gn:timezone":"Asia/Bangkok",
    "iso:country":"TH",
    "name:tha_x_preferred":[
        "\u0e1a\u0e49\u0e32\u0e19\u0e19\u0e32\u0e01\u0e23\u0e30\u0e41\u0e0b\u0e07"
    ],
    "name:und_x_variant":[
        "Ban Na Kasaeng"
    ],
    "wof:name":"Ban Na Krasaeng",
    "wof:placetype":"locality"
},
  "geometry": {"coordinates":[104.93492000000001,14.88403],"type":"Point"}
}