{
  "type": "Feature",
  "properties": {
    "gn:admin1_code":"69.0",
    "gn:asciiname":"Ban Yae Ra",
    "gn:country_code":"TH",
    "gn:dem":10,
    "gn:feature_class":"P",
    "gn:feature_code":"PPL",
    "gn:name":"Ban Yae Ra",
    "gn:population":0,
    "gn:timezone":"Asia/Bangkok",
    "iso:country":"TH",
    "name:tha_x_preferred":[
        "\u0e1a\u0e49\u0e32\u0e19\u0e41\u0e22\u0e23\u0e30"
    ],
    "wof:name":"Ban Yae Ra",
    "wof:placetype":"locality"
},
  "geometry": {"coordinates":[101.36557999999999,6.73058],"type":"Point"}
}