{
  "type": "Feature",
  "properties": {
    "gn:admin1_code":"4.0",
    "gn:asciiname":"Ban Takhian Thong",
    "gn:country_code":"TH",
    "gn:dem":476,
    "gn:feature_class":"P",
    "gn:feature_code":"PPL",
    "gn:name":"Ban Takhian Thong",
    "gn:population":0,
    "gn:timezone":"Asia/Bangkok",
    "iso:country":"TH",
    "name:tha_x_preferred":[
        "\u0e1a\u0e49\u0e32\u0e19\u0e15\u0e30\u0e40\u0e04\u0e35\u0e22\u0e19\u0e17\u0e2d\u0e07"
    ],
    "wof:name":"Ban Takhian Thong",
    "wof:placetype":"locality"
},
  "geometry": {"coordinates":[100.53972,18.76294],"type":"Point"}
}