{
  "type": "Feature",
  "properties": {
    "gn:admin1_code":"14.0",
    "gn:asciiname":"Ban Ko Takrut",
    "gn:country_code":"TH",
    "gn:dem":58,
    "gn:feature_class":"P",
    "gn:feature_code":"PPL",
    "gn:name":"Ban Ko Takrut",
    "gn:population":0,
    "gn:timezone":"Asia/Bangkok",
    "iso:country":"TH",
    "name:tha_x_preferred":[
        "\u0e1a\u0e49\u0e32\u0e19\u0e40\u0e01\u0e32\u0e30\u0e15\u0e30\u0e01\u0e23\u0e38\u0e14"
    ],
    "name:und_x_variant":[
        "Ban Na Takrut"
    ],
    "wof:name":"Ban Ko Takrut",
    "wof:placetype":"locality"
},
  "geometry": {"coordinates":[101.16189,15.42503],"type":"Point"}
}