{
  "type": "Feature",
  "properties": {
    "gn:admin1_code":"69.0",
    "gn:asciiname":"Ban Muang Wan",
    "gn:country_code":"TH",
    "gn:dem":19,
    "gn:feature_class":"P",
    "gn:feature_code":"PPL",
    "gn:name":"Ban Muang Wan",
    "gn:population":0,
    "gn:timezone":"Asia/Bangkok",
    "iso:country":"TH",
    "name:und_x_variant":[
        "Muang Wan",
        "Ban Muang Wan",
        "\u0e1a\u0e49\u0e32\u0e19\u0e21\u0e48\u0e27\u0e07\u0e2b\u0e27\u0e32\u0e19"
    ],
    "wof:name":"Ban Muang Wan",
    "wof:placetype":"locality"
},
  "geometry": {"coordinates":[101.23039,6.64106],"type":"Point"}
}