{
  "type": "Feature",
  "properties": {
    "gn:admin1_code":"74.0",
    "gn:asciiname":"Ban Pak Khlong Chang",
    "gn:country_code":"TH",
    "gn:dem":3,
    "gn:feature_class":"P",
    "gn:feature_code":"PPL",
    "gn:name":"Ban Pak Khlong Chang",
    "gn:population":0,
    "gn:timezone":"Asia/Bangkok",
    "iso:country":"TH",
    "name:und_x_variant":[
        "Pak Khlaung Chang",
        "Ban Pak Khlong Chang"
    ],
    "wof:name":"Ban Pak Khlong Chang",
    "wof:placetype":"locality"
},
  "geometry": {"coordinates":[101.34999999999999,13.96667],"type":"Point"}
}