{
  "type": "Feature",
  "properties": {
    "gn:admin1_code":"11.0",
    "gn:asciiname":"Ban Wang Phet Phatthana",
    "gn:country_code":"TH",
    "gn:dem":69,
    "gn:feature_class":"P",
    "gn:feature_code":"PPL",
    "gn:name":"Ban Wang Phet Phatthana",
    "gn:population":0,
    "gn:timezone":"Asia/Bangkok",
    "iso:country":"TH",
    "name:tha_x_preferred":[
        "\u0e1a\u0e49\u0e32\u0e19\u0e27\u0e31\u0e07\u0e40\u0e1e\u0e0a\u0e23\u0e1e\u0e31\u0e12\u0e19\u0e32"
    ],
    "wof:name":"Ban Wang Phet Phatthana",
    "wof:placetype":"locality"
},
  "geometry": {"coordinates":[99.72553000000001,16.45406],"type":"Point"}
}