{
  "type": "Feature",
  "properties": {
    "gn:admin1_code":"51.0",
    "gn:asciiname":"Ban Bang Ngam (2)",
    "gn:country_code":"TH",
    "gn:dem":10,
    "gn:feature_class":"P",
    "gn:feature_code":"PPL",
    "gn:name":"Ban Bang Ngam (2)",
    "gn:population":0,
    "gn:timezone":"Asia/Bangkok",
    "iso:country":"TH",
    "wof:name":"Ban Bang Ngam (2)",
    "wof:placetype":"locality"
},
  "geometry": {"coordinates":[100.08333,14.61667],"type":"Point"}
}