{
  "type": "Feature",
  "properties": {
    "gn:admin1_code":"25.0",
    "gn:asciiname":"Ban Lao Hua Phu",
    "gn:country_code":"TH",
    "gn:dem":148,
    "gn:feature_class":"P",
    "gn:feature_code":"PPL",
    "gn:name":"Ban Lao Hua Phu",
    "gn:population":0,
    "gn:timezone":"Asia/Bangkok",
    "iso:country":"TH",
    "name:tha_x_preferred":[
        "\u0e1a\u0e49\u0e32\u0e19\u0e40\u0e2b\u0e25\u0e48\u0e32\u0e2b\u0e31\u0e27\u0e20\u0e39"
    ],
    "wof:name":"Ban Lao Hua Phu",
    "wof:placetype":"locality"
},
  "geometry": {"coordinates":[103.75833,15.78369],"type":"Point"}
}