{
  "type": "Feature",
  "properties": {
    "gn:admin1_code":"49.0",
    "gn:asciiname":"Ban Soi Chaiwa",
    "gn:country_code":"TH",
    "gn:dem":14,
    "gn:feature_class":"P",
    "gn:feature_code":"PPL",
    "gn:name":"Ban Soi Chaiwa",
    "gn:population":0,
    "gn:timezone":"Asia/Bangkok",
    "iso:country":"TH",
    "name:tha_x_preferred":[
        "\u0e1a\u0e49\u0e32\u0e19\u0e0b\u0e2d\u0e22\u0e44\u0e0a\u0e22\u0e27\u0e32"
    ],
    "wof:name":"Ban Soi Chaiwa",
    "wof:placetype":"locality"
},
  "geometry": {"coordinates":[102.43347,12.41483],"type":"Point"}
}