{
  "type": "Feature",
  "properties": {
    "gn:admin1_code":"3.0",
    "gn:asciiname":"Ban Thung Tom",
    "gn:country_code":"TH",
    "gn:dem":387,
    "gn:feature_class":"P",
    "gn:feature_code":"PPL",
    "gn:name":"Ban Thung Tom",
    "gn:population":0,
    "gn:timezone":"Asia/Bangkok",
    "iso:country":"TH",
    "name:tha_x_preferred":[
        "\u0e1a\u0e49\u0e32\u0e19\u0e17\u0e38\u0e48\u0e07\u0e15\u0e49\u0e2d\u0e21"
    ],
    "wof:name":"Ban Thung Tom",
    "wof:placetype":"locality"
},
  "geometry": {"coordinates":[100.07256,19.61661],"type":"Point"}
}