{
  "type": "Feature",
  "properties": {
    "gn:admin1_code":"6.0",
    "gn:asciiname":"Ban Huai Pet",
    "gn:country_code":"TH",
    "gn:dem":300,
    "gn:feature_class":"P",
    "gn:feature_code":"PPL",
    "gn:name":"Ban Huai Pet",
    "gn:population":0,
    "gn:timezone":"Asia/Bangkok",
    "iso:country":"TH",
    "name:tha_x_preferred":[
        "\u0e1a\u0e49\u0e32\u0e19\u0e2b\u0e49\u0e27\u0e22\u0e40\u0e1b\u0e47\u0e14"
    ],
    "wof:name":"Ban Huai Pet",
    "wof:placetype":"locality"
},
  "geometry": {"coordinates":[99.71428,18.27447],"type":"Point"}
}