{
  "type": "Feature",
  "properties": {
    "gn:admin1_code":"29",
    "gn:asciiname":"Ban Sanuan",
    "gn:country_code":"TH",
    "gn:dem":139,
    "gn:feature_class":"P",
    "gn:feature_code":"PPL",
    "gn:name":"Ban Sanuan",
    "gn:population":0,
    "gn:timezone":"Asia/Bangkok",
    "iso:country":"TH",
    "name:tha_x_preferred":[
        "\u0e1a\u0e49\u0e32\u0e19\u0e2a\u0e19\u0e27\u0e19"
    ],
    "wof:name":"Ban Sanuan",
    "wof:placetype":"locality"
},
  "geometry": {"coordinates":[103.58253000000001,15.14539],"type":"Point"}
}