{
  "type": "Feature",
  "properties": {
    "gn:admin1_code":"29",
    "gn:asciiname":"Ban Rom Sai",
    "gn:country_code":"TH",
    "gn:dem":158,
    "gn:feature_class":"P",
    "gn:feature_code":"PPL",
    "gn:name":"Ban Rom Sai",
    "gn:population":0,
    "gn:timezone":"Asia/Bangkok",
    "iso:country":"TH",
    "name:tha_x_preferred":[
        "\u0e1a\u0e49\u0e32\u0e19\u0e23\u0e48\u0e21\u0e44\u0e17\u0e23"
    ],
    "wof:name":"Ban Rom Sai",
    "wof:placetype":"locality"
},
  "geometry": {"coordinates":[103.68579,15.22712],"type":"Point"}
}