{
  "type": "Feature",
  "properties": {
    "gn:admin1_code":"59.0",
    "gn:asciiname":"Ban Khao Phrik Thai",
    "gn:country_code":"TH",
    "gn:dem":23,
    "gn:feature_class":"P",
    "gn:feature_code":"PPL",
    "gn:name":"Ban Khao Phrik Thai",
    "gn:population":0,
    "gn:timezone":"Asia/Bangkok",
    "iso:country":"TH",
    "name:tha_x_preferred":[
        "\u0e1a\u0e49\u0e32\u0e19\u0e40\u0e02\u0e32\u0e1e\u0e23\u0e34\u0e01\u0e44\u0e17\u0e22"
    ],
    "wof:name":"Ban Khao Phrik Thai",
    "wof:placetype":"locality"
},
  "geometry": {"coordinates":[98.63686,9.98703],"type":"Point"}
}