{
  "type": "Feature",
  "properties": {
    "gn:admin1_code":"78.0",
    "gn:asciiname":"Ban Anurak Bamrung",
    "gn:country_code":"TH",
    "gn:dem":158,
    "gn:feature_class":"P",
    "gn:feature_code":"PPL",
    "gn:name":"Ban Anurak Bamrung",
    "gn:population":0,
    "gn:timezone":"Asia/Bangkok",
    "iso:country":"TH",
    "name:tha_x_preferred":[
        "Ban Anurak Bamrung"
    ],
    "name:tha_x_variant":[
        "\u0e1a\u0e49\u0e32\u0e19\u0e2d\u0e19\u0e38\u0e23\u0e31\u0e01\u0e29\u0e4c\u0e1a\u0e33\u0e23\u0e38\u0e07"
    ],
    "wof:lang_x_official":[
        "tha"
    ],
    "wof:lang_x_spoken":[
        "tha"
    ],
    "wof:name":"Ban Anurak Bamrung",
    "wof:placetype":"locality"
},
  "geometry": {"coordinates":[104.71672,16.52061],"type":"Point"}
}