{
  "type": "Feature",
  "properties": {
    "gn:admin1_code":"55.0",
    "gn:asciiname":"Ban Rang Saphan",
    "gn:country_code":"TH",
    "gn:dem":6,
    "gn:feature_class":"P",
    "gn:feature_code":"PPL",
    "gn:name":"Ban Rang Saphan",
    "gn:population":0,
    "gn:timezone":"Asia/Bangkok",
    "iso:country":"TH",
    "name:tha_x_preferred":[
        "\u0e1a\u0e49\u0e32\u0e19\u0e23\u0e32\u0e07\u0e2a\u0e30\u0e1e\u0e32\u0e19"
    ],
    "wof:name":"Ban Rang Saphan",
    "wof:placetype":"locality"
},
  "geometry": {"coordinates":[100.04707999999999,13.54367],"type":"Point"}
}