{
  "type": "Feature",
  "properties": {
    "gn:admin1_code":"16.0",
    "gn:asciiname":"Ban Nong Khao Khwai",
    "gn:country_code":"TH",
    "gn:dem":31,
    "gn:feature_class":"P",
    "gn:feature_code":"PPL",
    "gn:name":"Ban Nong Khao Khwai",
    "gn:population":0,
    "gn:timezone":"Asia/Bangkok",
    "iso:country":"TH",
    "name:tha_x_preferred":[
        "\u0e1a\u0e49\u0e32\u0e19\u0e2b\u0e19\u0e2d\u0e07\u0e40\u0e02\u0e32\u0e04\u0e27\u0e32\u0e22"
    ],
    "wof:name":"Ban Nong Khao Khwai",
    "wof:placetype":"locality"
},
  "geometry": {"coordinates":[100.43313999999999,15.79878],"type":"Point"}
}