{
  "type": "Feature",
  "properties": {
    "gn:admin1_code":"24",
    "gn:asciiname":"Ban Khan Chong",
    "gn:country_code":"TH",
    "gn:dem":153,
    "gn:feature_class":"P",
    "gn:feature_code":"PPL",
    "gn:name":"Ban Khan Chong",
    "gn:population":0,
    "gn:timezone":"Asia/Bangkok",
    "iso:country":"TH",
    "name:tha_x_preferred":[
        "\u0e1a\u0e49\u0e32\u0e19\u0e04\u0e31\u0e19\u0e08\u0e49\u0e2d\u0e07"
    ],
    "wof:name":"Ban Khan Chong",
    "wof:placetype":"locality"
},
  "geometry": {"coordinates":[103.11960999999999,16.28789],"type":"Point"}
}