{
  "type": "Feature",
  "properties": {
    "gn:admin1_code":"29",
    "gn:asciiname":"Ban Khok La O",
    "gn:country_code":"TH",
    "gn:dem":174,
    "gn:feature_class":"P",
    "gn:feature_code":"PPL",
    "gn:name":"Ban Khok La O",
    "gn:population":0,
    "gn:timezone":"Asia/Bangkok",
    "iso:country":"TH",
    "name:tha_x_preferred":[
        "\u0e1a\u0e49\u0e32\u0e19\u0e42\u0e04\u0e01\u0e25\u0e30\u0e42\u0e2d\u0e4a\u0e30"
    ],
    "wof:name":"Ban Khok La O",
    "wof:placetype":"locality"
},
  "geometry": {"coordinates":[103.72358,14.66644],"type":"Point"}
}