{
  "type": "Feature",
  "properties": {
    "gn:admin1_code":"53.0",
    "gn:asciiname":"Ban Phai Lam Chi",
    "gn:country_code":"TH",
    "gn:dem":6,
    "gn:feature_class":"P",
    "gn:feature_code":"PPL",
    "gn:name":"Ban Phai Lam Chi",
    "gn:population":0,
    "gn:timezone":"Asia/Bangkok",
    "iso:country":"TH",
    "name:tha_x_preferred":[
        "\u0e1a\u0e49\u0e32\u0e19\u0e44\u0e1c\u0e48\u0e25\u0e33\u0e0a\u0e35"
    ],
    "name:und_x_variant":[
        "\u0e1a\u0e49\u0e32\u0e19\u0e44\u0e1c\u0e48\u0e25\u0e33\u0e0a\u0e35",
        "Ban Phai Banchi (2)"
    ],
    "wof:name":"Ban Phai Lam Chi",
    "wof:placetype":"locality"
},
  "geometry": {"coordinates":[100.12929,13.76419],"type":"Point"}
}