{
  "type": "Feature",
  "properties": {
    "gn:admin1_code":"5.0",
    "gn:asciiname":"Ban Tha Kat",
    "gn:country_code":"TH",
    "gn:dem":338,
    "gn:feature_class":"P",
    "gn:feature_code":"PPL",
    "gn:name":"Ban Tha Kat",
    "gn:population":0,
    "gn:timezone":"Asia/Bangkok",
    "iso:country":"TH",
    "name:tha_x_preferred":[
        "\u0e1a\u0e49\u0e32\u0e19\u0e17\u0e32\u0e01\u0e32\u0e28"
    ],
    "wof:name":"Ban Tha Kat",
    "wof:placetype":"locality"
},
  "geometry": {"coordinates":[98.99147000000001,18.41408],"type":"Point"}
}