{
  "type": "Feature",
  "properties": {
    "gn:admin1_code":"9.0",
    "gn:asciiname":"Ban Khlong Pong",
    "gn:country_code":"TH",
    "gn:dem":61,
    "gn:feature_class":"P",
    "gn:feature_code":"PPL",
    "gn:name":"Ban Khlong Pong",
    "gn:population":0,
    "gn:timezone":"Asia/Bangkok",
    "iso:country":"TH",
    "name:tha_x_preferred":[
        "\u0e1a\u0e49\u0e32\u0e19\u0e04\u0e25\u0e2d\u0e07\u0e42\u0e1b\u0e48\u0e07"
    ],
    "wof:name":"Ban Khlong Pong",
    "wof:placetype":"locality"
},
  "geometry": {"coordinates":[99.86514,17.18206],"type":"Point"}
}