{
  "type": "Feature",
  "properties": {
    "gn:admin1_code":"14.0",
    "gn:asciiname":"Ban Dong Khui Nuea",
    "gn:country_code":"TH",
    "gn:dem":74,
    "gn:feature_class":"P",
    "gn:feature_code":"PPL",
    "gn:name":"Ban Dong Khui Nuea",
    "gn:population":0,
    "gn:timezone":"Asia/Bangkok",
    "iso:country":"TH",
    "name:tha_x_preferred":[
        "\u0e1a\u0e49\u0e32\u0e19\u0e14\u0e07\u0e02\u0e38\u0e22\u0e40\u0e2b\u0e19\u0e37\u0e2d"
    ],
    "name:und_x_variant":[
        "Ban Dong Kui Nua",
        "Ban Dong Khui Nua",
        "Ban Dong Khui Nuea"
    ],
    "wof:name":"Ban Dong Khui Nuea",
    "wof:placetype":"locality"
},
  "geometry": {"coordinates":[100.73736,16.11556],"type":"Point"}
}