{
  "type": "Feature",
  "properties": {
    "gn:admin1_code":"35.0",
    "gn:asciiname":"Ban Pho Muang Phan",
    "gn:country_code":"TH",
    "gn:dem":10,
    "gn:feature_class":"P",
    "gn:feature_code":"PPL",
    "gn:name":"Ban Pho Muang Phan",
    "gn:population":0,
    "gn:timezone":"Asia/Bangkok",
    "iso:country":"TH",
    "name:tha_x_preferred":[
        "\u0e1a\u0e49\u0e32\u0e19\u0e42\u0e1e\u0e18\u0e34\u0e4c\u0e21\u0e48\u0e27\u0e07\u0e1e\u0e31\u0e19\u0e18\u0e4c"
    ],
    "wof:name":"Ban Pho Muang Phan",
    "wof:placetype":"locality"
},
  "geometry": {"coordinates":[100.25503,14.56964],"type":"Point"}
}