{
  "type": "Feature",
  "properties": {
    "gn:admin1_code":"27",
    "gn:asciiname":"Ban Non Khro",
    "gn:country_code":"TH",
    "gn:dem":150,
    "gn:feature_class":"P",
    "gn:feature_code":"PPL",
    "gn:name":"Ban Non Khro",
    "gn:population":0,
    "gn:timezone":"Asia/Bangkok",
    "iso:country":"TH",
    "name:tha_x_preferred":[
        "\u0e1a\u0e49\u0e32\u0e19\u0e42\u0e19\u0e19\u0e04\u0e23\u0e49\u0e2d"
    ],
    "wof:name":"Ban Non Khro",
    "wof:placetype":"locality"
},
  "geometry": {"coordinates":[102.78361,15.47147],"type":"Point"}
}