{
  "type": "Feature",
  "properties": {
    "gn:admin1_code":"61.0",
    "gn:asciiname":"Ban Bang Ma",
    "gn:country_code":"TH",
    "gn:dem":155,
    "gn:feature_class":"P",
    "gn:feature_code":"PPL",
    "gn:name":"Ban Bang Ma",
    "gn:population":0,
    "gn:timezone":"Asia/Bangkok",
    "iso:country":"TH",
    "name:und_x_variant":[
        "Ban Plai Bang Phama",
        "Ban Bang Ma"
    ],
    "wof:name":"Ban Bang Ma",
    "wof:placetype":"locality"
},
  "geometry": {"coordinates":[98.43333,8.51667],"type":"Point"}
}