{
  "type": "Feature",
  "properties": {
    "gn:admin1_code":"22",
    "gn:asciiname":"Ban Thung Chomphu",
    "gn:country_code":"TH",
    "gn:dem":197,
    "gn:feature_class":"P",
    "gn:feature_code":"PPL",
    "gn:name":"Ban Thung Chomphu",
    "gn:population":0,
    "gn:timezone":"Asia/Bangkok",
    "iso:country":"TH",
    "name:tha_x_preferred":[
        "\u0e1a\u0e49\u0e32\u0e19\u0e17\u0e38\u0e48\u0e07\u0e0a\u0e21\u0e1e\u0e39"
    ],
    "wof:lang_x_official":[
        "tha"
    ],
    "wof:lang_x_spoken":[
        "tha"
    ],
    "wof:name":"Ban Thung Chomphu",
    "wof:placetype":"locality"
},
  "geometry": {"coordinates":[102.49308000000001,16.72575],"type":"Point"}
}