{
  "type": "Feature",
  "properties": {
    "gn:admin1_code":"48.0",
    "gn:asciiname":"Ban Sanam Chai",
    "gn:country_code":"TH",
    "gn:dem":8,
    "gn:feature_class":"P",
    "gn:feature_code":"PPL",
    "gn:name":"Ban Sanam Chai",
    "gn:population":0,
    "gn:timezone":"Asia/Bangkok",
    "iso:country":"TH",
    "name:tha_x_preferred":[
        "\u0e1a\u0e49\u0e32\u0e19\u0e2a\u0e19\u0e32\u0e21\u0e44\u0e0a\u0e22"
    ],
    "wof:name":"Ban Sanam Chai",
    "wof:placetype":"locality"
},
  "geometry": {"coordinates":[101.87483,12.65047],"type":"Point"}
}