{
  "type": "Feature",
  "properties": {
    "gn:admin1_code":"3.0",
    "gn:asciiname":"Ban San Pa Ko",
    "gn:country_code":"TH",
    "gn:dem":414,
    "gn:feature_class":"P",
    "gn:feature_code":"PPL",
    "gn:name":"Ban San Pa Ko",
    "gn:population":0,
    "gn:timezone":"Asia/Bangkok",
    "iso:country":"TH",
    "name:tha_x_preferred":[
        "\u0e1a\u0e49\u0e32\u0e19\u0e2a\u0e31\u0e19\u0e1b\u0e48\u0e32\u0e01\u0e48\u0e2d"
    ],
    "wof:lang_x_official":[
        "tha"
    ],
    "wof:lang_x_spoken":[
        "tha"
    ],
    "wof:name":"Ban San Pa Ko",
    "wof:placetype":"locality"
},
  "geometry": {"coordinates":[99.92883,19.69086],"type":"Point"}
}