{
  "type": "Feature",
  "properties": {
    "gn:admin1_code":"53.0",
    "gn:asciiname":"Ban Huai Mon Thong",
    "gn:country_code":"TH",
    "gn:dem":12,
    "gn:feature_class":"P",
    "gn:feature_code":"PPL",
    "gn:name":"Ban Huai Mon Thong",
    "gn:population":0,
    "gn:timezone":"Asia/Bangkok",
    "iso:country":"TH",
    "name:tha_x_preferred":[
        "Ban Huai Mon Thong"
    ],
    "name:tha_x_variant":[
        "\u0e1a\u0e49\u0e32\u0e19\u0e2b\u0e49\u0e27\u0e22\u0e2b\u0e21\u0e2d\u0e19\u0e17\u0e2d\u0e07"
    ],
    "wof:name":"Ban Huai Mon Thong",
    "wof:placetype":"locality"
},
  "geometry": {"coordinates":[99.9222,13.98264],"type":"Point"}
}