{
  "type": "Feature",
  "properties": {
    "gn:admin1_code":"41.0",
    "gn:asciiname":"Ban San Pa Thon",
    "gn:country_code":"TH",
    "gn:dem":400,
    "gn:feature_class":"P",
    "gn:feature_code":"PPL",
    "gn:name":"Ban San Pa Thon",
    "gn:population":0,
    "gn:timezone":"Asia/Bangkok",
    "iso:country":"TH",
    "name:tha_x_preferred":[
        "\u0e1a\u0e49\u0e32\u0e19\u0e2a\u0e31\u0e19\u0e1b\u0e48\u0e32\u0e16\u0e48\u0e2d\u0e19"
    ],
    "name:und_x_variant":[
        "Ban Pa Thon",
        "Ban San Pa Thon"
    ],
    "wof:name":"Ban San Pa Thon",
    "wof:placetype":"locality"
},
  "geometry": {"coordinates":[99.85556,19.14075],"type":"Point"}
}