{
  "type": "Feature",
  "properties": {
    "gn:admin1_code":"14.0",
    "gn:asciiname":"Ban Non Makluea",
    "gn:country_code":"TH",
    "gn:dem":204,
    "gn:feature_class":"P",
    "gn:feature_code":"PPL",
    "gn:name":"Ban Non Makluea",
    "gn:population":0,
    "gn:timezone":"Asia/Bangkok",
    "iso:country":"TH",
    "name:tha_x_preferred":[
        "\u0e1a\u0e49\u0e32\u0e19\u0e42\u0e19\u0e19\u0e21\u0e30\u0e40\u0e01\u0e25\u0e37\u0e2d"
    ],
    "wof:name":"Ban Non Makluea",
    "wof:placetype":"locality"
},
  "geometry": {"coordinates":[101.32386,16.47044],"type":"Point"}
}