{
  "type": "Feature",
  "properties": {
    "gn:admin1_code":"53.0",
    "gn:asciiname":"Ban Khlong Chinda",
    "gn:country_code":"TH",
    "gn:dem":5,
    "gn:feature_class":"P",
    "gn:feature_code":"PPL",
    "gn:name":"Ban Khlong Chinda",
    "gn:population":0,
    "gn:timezone":"Asia/Bangkok",
    "iso:country":"TH",
    "name:tha_x_preferred":[
        "\u0e1a\u0e49\u0e32\u0e19\u0e04\u0e25\u0e2d\u0e07\u0e08\u0e34\u0e19\u0e14\u0e32"
    ],
    "name:und_x_variant":[
        "Ban Tung Chinda",
        "Ban Thung Chinda",
        "Ban Khlong Chinda"
    ],
    "wof:lang_x_official":[
        "tha"
    ],
    "wof:lang_x_spoken":[
        "tha"
    ],
    "wof:name":"Ban Khlong Chinda",
    "wof:placetype":"locality"
},
  "geometry": {"coordinates":[100.15621,13.68379],"type":"Point"}
}