{
  "type": "Feature",
  "properties": {
    "gn:admin1_code":"70.0",
    "gn:asciiname":"Ban Ba Ngo Hi Le",
    "gn:country_code":"TH",
    "gn:dem":39,
    "gn:feature_class":"P",
    "gn:feature_code":"PPL",
    "gn:name":"Ban Ba Ngo Hi Le",
    "gn:population":0,
    "gn:timezone":"Asia/Bangkok",
    "iso:country":"TH",
    "name:tha_x_preferred":[
        "\u0e1a\u0e49\u0e32\u0e19\u0e1a\u0e32\u0e42\u0e07\u0e2e\u0e35\u0e40\u0e25"
    ],
    "wof:name":"Ban Ba Ngo Hi Le",
    "wof:placetype":"locality"
},
  "geometry": {"coordinates":[101.35158,6.45317],"type":"Point"}
}