{
  "type": "Feature",
  "properties": {
    "gn:admin1_code":"30.0",
    "gn:asciiname":"Ban Phraiwan Phatthana",
    "gn:country_code":"TH",
    "gn:dem":164,
    "gn:feature_class":"P",
    "gn:feature_code":"PPL",
    "gn:name":"Ban Phraiwan Phatthana",
    "gn:population":0,
    "gn:timezone":"Asia/Bangkok",
    "iso:country":"TH",
    "name:tha_x_preferred":[
        "\u0e1a\u0e49\u0e32\u0e19\u0e44\u0e1e\u0e23\u0e27\u0e23\u0e23\u0e13\u0e1e\u0e31\u0e12\u0e19\u0e32"
    ],
    "wof:name":"Ban Phraiwan Phatthana",
    "wof:placetype":"locality"
},
  "geometry": {"coordinates":[104.07505999999999,14.65617],"type":"Point"}
}