{
  "type": "Feature",
  "properties": {
    "gn:admin1_code":"53.0",
    "gn:asciiname":"Ban Thung Si Long",
    "gn:country_code":"TH",
    "gn:dem":7,
    "gn:feature_class":"P",
    "gn:feature_code":"PPL",
    "gn:name":"Ban Thung Si Long",
    "gn:population":0,
    "gn:timezone":"Asia/Bangkok",
    "iso:country":"TH",
    "name:tha_x_preferred":[
        "\u0e1a\u0e49\u0e32\u0e19\u0e17\u0e38\u0e48\u0e07\u0e2a\u0e35\u0e2b\u0e25\u0e07"
    ],
    "name:und_x_variant":[
        "Ban Tung Pilong",
        "Ban Thung Phi Long",
        "Ban Thung Si Long",
        "\u0e1a\u0e49\u0e32\u0e19\u0e17\u0e38\u0e48\u0e07\u0e2a\u0e35\u0e2b\u0e25\u0e07"
    ],
    "wof:name":"Ban Thung Si Long",
    "wof:placetype":"locality"
},
  "geometry": {"coordinates":[100.06005,13.95584],"type":"Point"}
}