{
  "type": "Feature",
  "properties": {
    "gn:admin1_code":"40.0",
    "gn:admin2_code":"1021.0",
    "gn:asciiname":"Ban Khlong Rang Baen",
    "gn:country_code":"TH",
    "gn:dem":5,
    "gn:feature_class":"P",
    "gn:feature_code":"PPL",
    "gn:name":"Ban Khlong Rang Baen",
    "gn:population":0,
    "gn:timezone":"Asia/Bangkok",
    "iso:country":"TH",
    "name:tha_x_preferred":[
        "\u0e1a\u0e49\u0e32\u0e19\u0e04\u0e25\u0e2d\u0e07\u0e23\u0e32\u0e07\u0e41\u0e1a\u0e19"
    ],
    "wof:name":"Ban Khlong Rang Baen",
    "wof:placetype":"locality"
},
  "geometry": {"coordinates":[100.47178,13.63914],"type":"Point"}
}