{
  "type": "Feature",
  "properties": {
    "gn:admin1_code":"22",
    "gn:asciiname":"Ban Lin Fa",
    "gn:country_code":"TH",
    "gn:dem":179,
    "gn:feature_class":"P",
    "gn:feature_code":"PPL",
    "gn:name":"Ban Lin Fa",
    "gn:population":0,
    "gn:timezone":"Asia/Bangkok",
    "iso:country":"TH",
    "name:tha_x_preferred":[
        "\u0e1a\u0e49\u0e32\u0e19\u0e25\u0e34\u0e49\u0e19\u0e1f\u0e49\u0e32"
    ],
    "wof:name":"Ban Lin Fa",
    "wof:placetype":"locality"
},
  "geometry": {"coordinates":[102.76364,16.02056],"type":"Point"}
}