{
  "type": "Feature",
  "properties": {
    "gn:admin1_code":"29.0",
    "gn:asciiname":"Ban Tuek Chum",
    "gn:country_code":"TH",
    "gn:dem":133,
    "gn:feature_class":"P",
    "gn:feature_code":"PPL",
    "gn:name":"Ban Tuek Chum",
    "gn:population":0,
    "gn:timezone":"Asia/Bangkok",
    "iso:country":"TH",
    "name:tha_x_preferred":[
        "\u0e1a\u0e49\u0e32\u0e19\u0e15\u0e36\u0e01\u0e0a\u0e38\u0e21"
    ],
    "name:und_x_variant":[
        "Ban Tuk Chum"
    ],
    "wof:name":"Ban Tuek Chum",
    "wof:placetype":"locality"
},
  "geometry": {"coordinates":[103.42641999999999,15.36489],"type":"Point"}
}