{
  "type": "Feature",
  "properties": {
    "gn:admin1_code":"31.0",
    "gn:asciiname":"Ban Kampong Ba Ru",
    "gn:country_code":"TH",
    "gn:dem":12,
    "gn:feature_class":"P",
    "gn:feature_code":"PPL",
    "gn:name":"Ban Kampong Ba Ru",
    "gn:population":0,
    "gn:timezone":"Asia/Bangkok",
    "iso:country":"TH",
    "name:tha_x_preferred":[
        "\u0e1a\u0e49\u0e32\u0e19\u0e01\u0e33\u0e1b\u0e07\u0e1a\u0e32\u0e23\u0e39"
    ],
    "wof:name":"Ban Kampong Ba Ru",
    "wof:placetype":"locality"
},
  "geometry": {"coordinates":[101.72257999999999,6.55433],"type":"Point"}
}