{
  "type": "Feature",
  "properties": {
    "gn:admin1_code":"55.0",
    "gn:asciiname":"Ban Lak Sam",
    "gn:country_code":"TH",
    "gn:dem":6,
    "gn:feature_class":"P",
    "gn:feature_code":"PPL",
    "gn:name":"Ban Lak Sam",
    "gn:population":0,
    "gn:timezone":"Asia/Bangkok",
    "iso:country":"TH",
    "name:tha_x_preferred":[
        "\u0e1a\u0e49\u0e32\u0e19\u0e2b\u0e25\u0e31\u0e01\u0e2a\u0e32\u0e21"
    ],
    "wof:name":"Ban Lak Sam",
    "wof:placetype":"locality"
},
  "geometry": {"coordinates":[100.10917000000001,13.58225],"type":"Point"}
}