{
  "type": "Feature",
  "properties": {
    "gn:admin1_code":"31.0",
    "gn:asciiname":"Ban Ai Tui",
    "gn:country_code":"TH",
    "gn:dem":54,
    "gn:feature_class":"P",
    "gn:feature_code":"PPL",
    "gn:name":"Ban Ai Tui",
    "gn:population":0,
    "gn:timezone":"Asia/Bangkok",
    "iso:country":"TH",
    "name:tha_x_preferred":[
        "\u0e1a\u0e49\u0e32\u0e19\u0e44\u0e2d\u0e23\u0e4c\u0e15\u0e38\u0e22"
    ],
    "wof:name":"Ban Ai Tui",
    "wof:placetype":"locality"
},
  "geometry": {"coordinates":[101.54367000000001,6.18294],"type":"Point"}
}