{
  "type": "Feature",
  "properties": {
    "gn:admin1_code":"64.0",
    "gn:asciiname":"Ban Khuan Khlang",
    "gn:country_code":"TH",
    "gn:dem":38,
    "gn:feature_class":"P",
    "gn:feature_code":"PPL",
    "gn:name":"Ban Khuan Khlang",
    "gn:population":0,
    "gn:timezone":"Asia/Bangkok",
    "iso:country":"TH",
    "name:tha_x_preferred":[
        "\u0e1a\u0e49\u0e32\u0e19\u0e04\u0e27\u0e19\u0e04\u0e25\u0e31\u0e07"
    ],
    "wof:name":"Ban Khuan Khlang",
    "wof:placetype":"locality"
},
  "geometry": {"coordinates":[99.4705,8.3715],"type":"Point"}
}