{
  "type": "Feature",
  "properties": {
    "gn:admin1_code":"73.0",
    "gn:asciiname":"Ban Si Chomphu",
    "gn:country_code":"TH",
    "gn:dem":155,
    "gn:feature_class":"P",
    "gn:feature_code":"PPL",
    "gn:name":"Ban Si Chomphu",
    "gn:population":0,
    "gn:timezone":"Asia/Bangkok",
    "iso:country":"TH",
    "name:tha_x_preferred":[
        "Ban Si Chomphu"
    ],
    "name:tha_x_variant":[
        "\u0e1a\u0e49\u0e32\u0e19\u0e2a\u0e35\u0e0a\u0e21\u0e1e\u0e39"
    ],
    "wof:name":"Ban Si Chomphu",
    "wof:placetype":"locality"
},
  "geometry": {"coordinates":[104.57272,16.92583],"type":"Point"}
}