{
  "type": "Feature",
  "properties": {
    "gn:admin1_code":"48.0",
    "gn:asciiname":"Ban Nong Hang",
    "gn:country_code":"TH",
    "gn:dem":13,
    "gn:feature_class":"P",
    "gn:feature_code":"PPL",
    "gn:name":"Ban Nong Hang",
    "gn:population":0,
    "gn:timezone":"Asia/Bangkok",
    "iso:country":"TH",
    "name:tha_x_preferred":[
        "\u0e1a\u0e49\u0e32\u0e19\u0e2b\u0e19\u0e2d\u0e07\u0e2b\u0e49\u0e32\u0e07"
    ],
    "wof:lang_x_official":[
        "tha"
    ],
    "wof:lang_x_spoken":[
        "tha"
    ],
    "wof:name":"Ban Nong Hang",
    "wof:placetype":"locality"
},
  "geometry": {"coordinates":[102.30131,12.48244],"type":"Point"}
}