{
  "type": "Feature",
  "properties": {
    "gn:admin1_code":"27",
    "gn:asciiname":"Ban Khok Wua Non",
    "gn:country_code":"TH",
    "gn:dem":260,
    "gn:feature_class":"P",
    "gn:feature_code":"PPL",
    "gn:name":"Ban Khok Wua Non",
    "gn:population":0,
    "gn:timezone":"Asia/Bangkok",
    "iso:country":"TH",
    "name:tha_x_preferred":[
        "\u0e1a\u0e49\u0e32\u0e19\u0e42\u0e04\u0e01\u0e27\u0e31\u0e27\u0e19\u0e2d\u0e19"
    ],
    "wof:name":"Ban Khok Wua Non",
    "wof:placetype":"locality"
},
  "geometry": {"coordinates":[102.45968999999999,14.38169],"type":"Point"}
}