{
  "type": "Feature",
  "properties": {
    "gn:admin1_code":"27",
    "gn:asciiname":"Ban Non Makhuea",
    "gn:country_code":"TH",
    "gn:dem":168,
    "gn:feature_class":"P",
    "gn:feature_code":"PPL",
    "gn:name":"Ban Non Makhuea",
    "gn:population":0,
    "gn:timezone":"Asia/Bangkok",
    "iso:country":"TH",
    "name:tha_x_preferred":[
        "\u0e1a\u0e49\u0e32\u0e19\u0e42\u0e19\u0e19\u0e21\u0e30\u0e40\u0e02\u0e37\u0e2d"
    ],
    "wof:name":"Ban Non Makhuea",
    "wof:placetype":"locality"
},
  "geometry": {"coordinates":[102.28178,15.16419],"type":"Point"}
}