{
  "type": "Feature",
  "properties": {
    "gn:admin1_code":"0.0",
    "gn:asciiname":"Ban Tidi Kariang",
    "gn:country_code":"TH",
    "gn:dem":428,
    "gn:feature_class":"P",
    "gn:feature_code":"PPL",
    "gn:name":"Ban Tidi Kariang",
    "gn:population":0,
    "gn:timezone":"Asia/Bangkok",
    "iso:country":"TH",
    "wof:name":"Ban Tidi Kariang",
    "wof:placetype":"locality"
},
  "geometry": {"coordinates":[98.51654000000001,17.10149],"type":"Point"}
}