{
  "type": "Feature",
  "properties": {
    "gn:admin1_code":"68.0",
    "gn:asciiname":"Ban Tin Na",
    "gn:country_code":"TH",
    "gn:dem":29,
    "gn:feature_class":"P",
    "gn:feature_code":"PPL",
    "gn:name":"Ban Tin Na",
    "gn:population":0,
    "gn:timezone":"Asia/Bangkok",
    "iso:country":"TH",
    "name:tha_x_preferred":[
        "\u0e1a\u0e49\u0e32\u0e19\u0e15\u0e35\u0e19\u0e19\u0e32"
    ],
    "wof:name":"Ban Tin Na",
    "wof:placetype":"locality"
},
  "geometry": {"coordinates":[100.62606,7.06006],"type":"Point"}
}