{
  "type": "Feature",
  "properties": {
    "gn:admin1_code":"16.0",
    "gn:asciiname":"Ban Khok Makok",
    "gn:country_code":"TH",
    "gn:dem":33,
    "gn:feature_class":"P",
    "gn:feature_code":"PPL",
    "gn:name":"Ban Khok Makok",
    "gn:population":0,
    "gn:timezone":"Asia/Bangkok",
    "iso:country":"TH",
    "name:tha_x_preferred":[
        "\u0e1a\u0e49\u0e32\u0e19\u0e42\u0e04\u0e01\u0e21\u0e30\u0e01\u0e2d\u0e01"
    ],
    "wof:name":"Ban Khok Makok",
    "wof:placetype":"locality"
},
  "geometry": {"coordinates":[100.49803,15.86431],"type":"Point"}
}