{
  "type": "Feature",
  "properties": {
    "gn:admin1_code":"43",
    "gn:asciiname":"Ban Phon Thawi",
    "gn:country_code":"TH",
    "gn:dem":12,
    "gn:feature_class":"P",
    "gn:feature_code":"PPL",
    "gn:name":"Ban Phon Thawi",
    "gn:population":0,
    "gn:timezone":"Asia/Bangkok",
    "iso:country":"TH",
    "name:tha_x_preferred":[
        "\u0e1a\u0e49\u0e32\u0e19\u0e1c\u0e25\u0e17\u0e27\u0e35"
    ],
    "wof:name":"Ban Phon Thawi",
    "wof:placetype":"locality"
},
  "geometry": {"coordinates":[101.16211,14.23319],"type":"Point"}
}