{
  "type": "Feature",
  "properties": {
    "gn:admin1_code":"29",
    "gn:asciiname":"Ban At Daek",
    "gn:country_code":"TH",
    "gn:dem":182,
    "gn:feature_class":"P",
    "gn:feature_code":"PPL",
    "gn:name":"Ban At Daek",
    "gn:population":0,
    "gn:timezone":"Asia/Bangkok",
    "iso:country":"TH",
    "name:tha_x_preferred":[
        "\u0e1a\u0e49\u0e32\u0e19\u0e2d\u0e31\u0e14\u0e41\u0e14\u0e01"
    ],
    "wof:name":"Ban At Daek",
    "wof:placetype":"locality"
},
  "geometry": {"coordinates":[103.44569,14.66575],"type":"Point"}
}