{
  "type": "Feature",
  "properties": {
    "gn:admin1_code":"40.0",
    "gn:admin2_code":"1032",
    "gn:asciiname":"Muban Retsiden",
    "gn:country_code":"TH",
    "gn:dem":5,
    "gn:feature_class":"P",
    "gn:feature_code":"PPL",
    "gn:name":"Muban Retsiden",
    "gn:population":0,
    "gn:timezone":"Asia/Bangkok",
    "iso:country":"TH",
    "name:tha_x_preferred":[
        "\u0e2b\u0e21\u0e39\u0e48\u0e1a\u0e49\u0e32\u0e19\u0e40\u0e23\u0e2a\u0e0b\u0e34\u0e40\u0e14\u0e19\u0e17\u0e4c"
    ],
    "wof:lang_x_official":[
        "tha"
    ],
    "wof:lang_x_spoken":[
        "tha"
    ],
    "wof:name":"Muban Retsiden",
    "wof:placetype":"locality"
},
  "geometry": {"coordinates":[100.67807999999999,13.66494],"type":"Point"}
}