{
  "type": "Feature",
  "properties": {
    "gn:admin1_code":"2.0",
    "gn:asciiname":"Ban Cha To",
    "gn:country_code":"TH",
    "gn:dem":616,
    "gn:feature_class":"P",
    "gn:feature_code":"PPL",
    "gn:name":"Ban Cha To",
    "gn:population":0,
    "gn:timezone":"Asia/Bangkok",
    "iso:country":"TH",
    "name:tha_x_preferred":[
        "\u0e1a\u0e49\u0e32\u0e19\u0e08\u0e30\u0e42\u0e15\u0e4a\u0e30"
    ],
    "wof:name":"Ban Cha To",
    "wof:placetype":"locality"
},
  "geometry": {"coordinates":[99.34311,19.83478],"type":"Point"}
}