{
  "type": "Feature",
  "properties": {
    "gn:admin1_code":"77.0",
    "gn:asciiname":"Ban Kham Ngulueam",
    "gn:country_code":"TH",
    "gn:dem":173,
    "gn:feature_class":"P",
    "gn:feature_code":"PPL",
    "gn:name":"Ban Kham Ngulueam",
    "gn:population":0,
    "gn:timezone":"Asia/Bangkok",
    "iso:country":"TH",
    "name:tha_x_preferred":[
        "Ban Kham Ngulueam"
    ],
    "name:tha_x_variant":[
        "\u0e1a\u0e49\u0e32\u0e19\u0e04\u0e33\u0e07\u0e39\u0e40\u0e2b\u0e25\u0e37\u0e2d\u0e21"
    ],
    "wof:name":"Ban Kham Ngulueam",
    "wof:placetype":"locality"
},
  "geometry": {"coordinates":[104.57589,15.89981],"type":"Point"}
}