{
  "type": "Feature",
  "properties": {
    "gn:admin1_code":"27",
    "gn:asciiname":"Ban Bu Yakha",
    "gn:country_code":"TH",
    "gn:dem":166,
    "gn:feature_class":"P",
    "gn:feature_code":"PPL",
    "gn:name":"Ban Bu Yakha",
    "gn:population":0,
    "gn:timezone":"Asia/Bangkok",
    "iso:country":"TH",
    "name:tha_x_preferred":[
        "\u0e1a\u0e49\u0e32\u0e19\u0e1a\u0e38\u0e2b\u0e0d\u0e49\u0e32\u0e04\u0e32"
    ],
    "wof:name":"Ban Bu Yakha",
    "wof:placetype":"locality"
},
  "geometry": {"coordinates":[102.35791999999999,15.32317],"type":"Point"}
}