{
  "type": "Feature",
  "properties": {
    "gn:admin1_code":"16.0",
    "gn:asciiname":"Ban Nong Chik Sai Mun",
    "gn:country_code":"TH",
    "gn:dem":84,
    "gn:feature_class":"P",
    "gn:feature_code":"PPL",
    "gn:name":"Ban Nong Chik Sai Mun",
    "gn:population":0,
    "gn:timezone":"Asia/Bangkok",
    "iso:country":"TH",
    "name:tha_x_preferred":[
        "\u0e1a\u0e49\u0e32\u0e19\u0e2b\u0e19\u0e2d\u0e07\u0e08\u0e34\u0e01\u0e17\u0e23\u0e32\u0e22\u0e21\u0e39\u0e25"
    ],
    "wof:lang_x_official":[
        "tha"
    ],
    "wof:lang_x_spoken":[
        "tha"
    ],
    "wof:name":"Ban Nong Chik Sai Mun",
    "wof:placetype":"locality"
},
  "geometry": {"coordinates":[99.64944,15.66875],"type":"Point"}
}