{
  "type": "Feature",
  "properties": {
    "gn:admin1_code":"17.0",
    "gn:asciiname":"Ban Non Phatthana",
    "gn:country_code":"TH",
    "gn:dem":363,
    "gn:feature_class":"P",
    "gn:feature_code":"PPL",
    "gn:name":"Ban Non Phatthana",
    "gn:population":0,
    "gn:timezone":"Asia/Bangkok",
    "iso:country":"TH",
    "name:tha_x_preferred":[
        "\u0e1a\u0e49\u0e32\u0e19\u0e42\u0e19\u0e19\u0e1e\u0e31\u0e12\u0e19\u0e32"
    ],
    "wof:name":"Ban Non Phatthana",
    "wof:placetype":"locality"
},
  "geometry": {"coordinates":[102.33492,18.01486],"type":"Point"}
}