{
  "type": "Feature",
  "properties": {
    "gn:admin1_code":"56.0",
    "gn:asciiname":"Ban Tako Ngam",
    "gn:country_code":"TH",
    "gn:dem":6,
    "gn:feature_class":"P",
    "gn:feature_code":"PPL",
    "gn:name":"Ban Tako Ngam",
    "gn:population":0,
    "gn:timezone":"Asia/Bangkok",
    "iso:country":"TH",
    "name:tha_x_preferred":[
        "\u0e1a\u0e49\u0e32\u0e19\u0e15\u0e30\u0e42\u0e01\u0e07\u0e32\u0e21"
    ],
    "wof:name":"Ban Tako Ngam",
    "wof:placetype":"locality"
},
  "geometry": {"coordinates":[99.96289,13.05125],"type":"Point"}
}