{
  "type": "Feature",
  "properties": {
    "gn:admin1_code":"20.0",
    "gn:asciiname":"Ban Tha Rae Samakkhi",
    "gn:country_code":"TH",
    "gn:dem":161,
    "gn:feature_class":"P",
    "gn:feature_code":"PPL",
    "gn:name":"Ban Tha Rae Samakkhi",
    "gn:population":0,
    "gn:timezone":"Asia/Bangkok",
    "iso:country":"TH",
    "name:tha_x_preferred":[
        "\u0e1a\u0e49\u0e32\u0e19\u0e17\u0e48\u0e32\u0e41\u0e23\u0e48\u0e2a\u0e32\u0e21\u0e31\u0e04\u0e04\u0e35"
    ],
    "wof:lang_x_official":[
        "tha"
    ],
    "wof:lang_x_spoken":[
        "tha"
    ],
    "wof:name":"Ban Tha Rae Samakkhi",
    "wof:placetype":"locality"
},
  "geometry": {"coordinates":[104.17008,17.25625],"type":"Point"}
}