{
  "type": "Feature",
  "properties": {
    "gn:admin1_code":"2.0",
    "gn:asciiname":"Ban Trai Saphawakham",
    "gn:country_code":"TH",
    "gn:dem":407,
    "gn:feature_class":"P",
    "gn:feature_code":"PPL",
    "gn:name":"Ban Trai Saphawakham",
    "gn:population":0,
    "gn:timezone":"Asia/Bangkok",
    "iso:country":"TH",
    "name:tha_x_preferred":[
        "\u0e1a\u0e49\u0e32\u0e19\u0e44\u0e15\u0e23\u0e2a\u0e20\u0e32\u0e27\u0e04\u0e32\u0e21"
    ],
    "wof:name":"Ban Trai Saphawakham",
    "wof:placetype":"locality"
},
  "geometry": {"coordinates":[98.98994,19.42033],"type":"Point"}
}