{
  "type": "Feature",
  "properties": {
    "gn:admin1_code":"31.0",
    "gn:asciiname":"Ban Ba Re Nai",
    "gn:country_code":"TH",
    "gn:dem":24,
    "gn:feature_class":"P",
    "gn:feature_code":"PPL",
    "gn:name":"Ban Ba Re Nai",
    "gn:population":0,
    "gn:timezone":"Asia/Bangkok",
    "iso:country":"TH",
    "name:tha_x_preferred":[
        "\u0e1a\u0e49\u0e32\u0e19\u0e1a\u0e32\u0e40\u0e23\u0e4a\u0e30\u0e44\u0e19\u0e49"
    ],
    "wof:name":"Ban Ba Re Nai",
    "wof:placetype":"locality"
},
  "geometry": {"coordinates":[101.69642,6.39003],"type":"Point"}
}