{
  "type": "Feature",
  "properties": {
    "gn:admin1_code":"23.0",
    "gn:asciiname":"Ban Lao Kho",
    "gn:country_code":"TH",
    "gn:dem":154,
    "gn:feature_class":"P",
    "gn:feature_code":"PPL",
    "gn:name":"Ban Lao Kho",
    "gn:population":0,
    "gn:timezone":"Asia/Bangkok",
    "iso:country":"TH",
    "name:tha_x_preferred":[
        "\u0e1a\u0e49\u0e32\u0e19\u0e40\u0e2b\u0e25\u0e48\u0e32\u0e04\u0e49\u0e2d"
    ],
    "wof:name":"Ban Lao Kho",
    "wof:placetype":"locality"
},
  "geometry": {"coordinates":[103.61669000000001,16.42092],"type":"Point"}
}