{
  "type": "Feature",
  "properties": {
    "gn:admin1_code":"3.0",
    "gn:asciiname":"Ban Phaya Cha Wa",
    "gn:country_code":"TH",
    "gn:dem":988,
    "gn:feature_class":"P",
    "gn:feature_code":"PPL",
    "gn:name":"Ban Phaya Cha Wa",
    "gn:population":0,
    "gn:timezone":"Asia/Bangkok",
    "iso:country":"TH",
    "name:tha_x_preferred":[
        "\u0e1a\u0e49\u0e32\u0e19\u0e1e\u0e0d\u0e32\u0e08\u0e30\u0e27\u0e30"
    ],
    "wof:name":"Ban Phaya Cha Wa",
    "wof:placetype":"locality"
},
  "geometry": {"coordinates":[99.39543999999999,19.53314],"type":"Point"}
}