{
  "type": "Feature",
  "properties": {
    "gn:admin1_code":"67.0",
    "gn:asciiname":"Ban Pak Thang",
    "gn:country_code":"TH",
    "gn:dem":26,
    "gn:feature_class":"P",
    "gn:feature_code":"PPL",
    "gn:name":"Ban Pak Thang",
    "gn:population":0,
    "gn:timezone":"Asia/Bangkok",
    "iso:country":"TH",
    "name:tha_x_preferred":[
        "Ban Pak Thang"
    ],
    "name:tha_x_variant":[
        "\u0e1a\u0e49\u0e32\u0e19\u0e1b\u0e32\u0e01\u0e17\u0e32\u0e07"
    ],
    "wof:name":"Ban Pak Thang",
    "wof:placetype":"locality"
},
  "geometry": {"coordinates":[99.88475,6.85811],"type":"Point"}
}