{
  "type": "Feature",
  "properties": {
    "gn:admin1_code":"28",
    "gn:asciiname":"Ban Si Takhrong",
    "gn:country_code":"TH",
    "gn:dem":190,
    "gn:feature_class":"P",
    "gn:feature_code":"PPL",
    "gn:name":"Ban Si Takhrong",
    "gn:population":0,
    "gn:timezone":"Asia/Bangkok",
    "iso:country":"TH",
    "name:tha_x_preferred":[
        "\u0e1a\u0e49\u0e32\u0e19\u0e28\u0e23\u0e35\u0e15\u0e30\u0e04\u0e23\u0e2d\u0e07"
    ],
    "wof:name":"Ban Si Takhrong",
    "wof:placetype":"locality"
},
  "geometry": {"coordinates":[103.10039,14.54128],"type":"Point"}
}