{
  "type": "Feature",
  "properties": {
    "gn:admin1_code":"14.0",
    "gn:asciiname":"Ban Sak Long",
    "gn:country_code":"TH",
    "gn:dem":155,
    "gn:feature_class":"P",
    "gn:feature_code":"PPL",
    "gn:name":"Ban Sak Long",
    "gn:population":0,
    "gn:timezone":"Asia/Bangkok",
    "iso:country":"TH",
    "name:tha_x_preferred":[
        "\u0e1a\u0e49\u0e32\u0e19\u0e2a\u0e31\u0e01\u0e2b\u0e25\u0e07"
    ],
    "wof:name":"Ban Sak Long",
    "wof:placetype":"locality"
},
  "geometry": {"coordinates":[101.26333,16.81707999999999],"type":"Point"}
}