{
  "type": "Feature",
  "properties": {
    "gn:admin1_code":"29.0",
    "gn:asciiname":"Ban Non Tat",
    "gn:country_code":"TH",
    "gn:dem":133,
    "gn:feature_class":"P",
    "gn:feature_code":"PPL",
    "gn:name":"Ban Non Tat",
    "gn:population":0,
    "gn:timezone":"Asia/Bangkok",
    "iso:country":"TH",
    "name:tha_x_preferred":[
        "\u0e1a\u0e49\u0e32\u0e19\u0e42\u0e19\u0e19\u0e15\u0e32\u0e14"
    ],
    "name:und_x_variant":[
        "Ban Non Trat"
    ],
    "wof:name":"Ban Non Tat",
    "wof:placetype":"locality"
},
  "geometry": {"coordinates":[103.48486,15.39694],"type":"Point"}
}