{
  "type": "Feature",
  "properties": {
    "gn:admin1_code":"64.0",
    "gn:asciiname":"Ban Rai Noen",
    "gn:country_code":"TH",
    "gn:dem":14,
    "gn:feature_class":"P",
    "gn:feature_code":"PPL",
    "gn:name":"Ban Rai Noen",
    "gn:population":0,
    "gn:timezone":"Asia/Bangkok",
    "iso:country":"TH",
    "name:tha_x_preferred":[
        "\u0e1a\u0e49\u0e32\u0e19\u0e44\u0e23\u0e48\u0e40\u0e19\u0e34\u0e19"
    ],
    "wof:name":"Ban Rai Noen",
    "wof:placetype":"locality"
},
  "geometry": {"coordinates":[100.02616999999999,7.95714],"type":"Point"}
}