{
  "type": "Feature",
  "properties": {
    "gn:admin1_code":"63.0",
    "gn:asciiname":"Ban Khao Nong Hong",
    "gn:country_code":"TH",
    "gn:dem":54,
    "gn:feature_class":"P",
    "gn:feature_code":"PPL",
    "gn:name":"Ban Khao Nong Hong",
    "gn:population":0,
    "gn:timezone":"Asia/Bangkok",
    "iso:country":"TH",
    "name:tha_x_preferred":[
        "\u0e1a\u0e49\u0e32\u0e19\u0e40\u0e02\u0e32\u0e2b\u0e19\u0e2d\u0e07\u0e2b\u0e07\u0e29\u0e4c"
    ],
    "wof:name":"Ban Khao Nong Hong",
    "wof:placetype":"locality"
},
  "geometry": {"coordinates":[98.75928,8.407],"type":"Point"}
}