{
  "type": "Feature",
  "properties": {
    "gn:admin1_code":"25.0",
    "gn:asciiname":"Ban Den Rat",
    "gn:country_code":"TH",
    "gn:dem":135,
    "gn:feature_class":"P",
    "gn:feature_code":"PPL",
    "gn:name":"Ban Den Rat",
    "gn:population":0,
    "gn:timezone":"Asia/Bangkok",
    "iso:country":"TH",
    "name:tha_x_preferred":[
        "\u0e1a\u0e49\u0e32\u0e19\u0e40\u0e14\u0e48\u0e19\u0e23\u0e32\u0e29\u0e0e\u0e23\u0e4c"
    ],
    "wof:name":"Ban Den Rat",
    "wof:placetype":"locality"
},
  "geometry": {"coordinates":[103.96572,15.56692],"type":"Point"}
}