{
  "type": "Feature",
  "properties": {
    "gn:admin1_code":"10.0",
    "gn:asciiname":"Ban Pa Kabak",
    "gn:country_code":"TH",
    "gn:dem":507,
    "gn:feature_class":"P",
    "gn:feature_code":"PPL",
    "gn:name":"Ban Pa Kabak",
    "gn:population":0,
    "gn:timezone":"Asia/Bangkok",
    "iso:country":"TH",
    "name:tha_x_preferred":[
        "\u0e1a\u0e49\u0e32\u0e19\u0e1b\u0e48\u0e32\u0e01\u0e30\u0e1a\u0e32\u0e01"
    ],
    "name:und_x_variant":[
        "Ban Noi Nam Phrae",
        "Ban Pa Kabak"
    ],
    "wof:lang_x_official":[
        "tha"
    ],
    "wof:lang_x_spoken":[
        "tha"
    ],
    "wof:name":"Ban Pa Kabak",
    "wof:placetype":"locality"
},
  "geometry": {"coordinates":[101.11592,18.0598],"type":"Point"}
}