{
  "type": "Feature",
  "properties": {
    "gn:admin1_code":"51.0",
    "gn:asciiname":"Ban Map Phayom",
    "gn:country_code":"TH",
    "gn:dem":28,
    "gn:feature_class":"P",
    "gn:feature_code":"PPL",
    "gn:name":"Ban Map Phayom",
    "gn:population":0,
    "gn:timezone":"Asia/Bangkok",
    "iso:country":"TH",
    "name:tha_x_preferred":[
        "\u0e1a\u0e49\u0e32\u0e19\u0e21\u0e32\u0e1a\u0e1e\u0e22\u0e2d\u0e21"
    ],
    "wof:name":"Ban Map Phayom",
    "wof:placetype":"locality"
},
  "geometry": {"coordinates":[99.92158000000001,14.74117],"type":"Point"}
}