{
  "type": "Feature",
  "properties": {
    "gn:admin1_code":"48.0",
    "gn:asciiname":"Ban Dong Saluep",
    "gn:country_code":"TH",
    "gn:dem":45,
    "gn:feature_class":"P",
    "gn:feature_code":"PPL",
    "gn:name":"Ban Dong Saluep",
    "gn:population":0,
    "gn:timezone":"Asia/Bangkok",
    "iso:country":"TH",
    "name:tha_x_preferred":[
        "\u0e1a\u0e49\u0e32\u0e19\u0e14\u0e07\u0e2a\u0e25\u0e36\u0e1a"
    ],
    "wof:name":"Ban Dong Saluep",
    "wof:placetype":"locality"
},
  "geometry": {"coordinates":[102.19797,12.80572],"type":"Point"}
}