{
  "type": "Feature",
  "properties": {
    "gn:admin1_code":"56.0",
    "gn:asciiname":"Ban Khlu Nuea",
    "gn:country_code":"TH",
    "gn:dem":4,
    "gn:feature_class":"P",
    "gn:feature_code":"PPL",
    "gn:name":"Ban Khlu Nuea",
    "gn:population":0,
    "gn:timezone":"Asia/Bangkok",
    "iso:country":"TH",
    "name:tha_x_preferred":[
        "\u0e1a\u0e49\u0e32\u0e19\u0e02\u0e25\u0e39\u0e48\u0e40\u0e2b\u0e19\u0e37\u0e2d"
    ],
    "name:und_x_variant":[
        "Ban Khlu",
        "Ban Khru",
        "Ban Khlu Nuea"
    ],
    "wof:name":"Ban Khlu Nuea",
    "wof:placetype":"locality"
},
  "geometry": {"coordinates":[99.91625000000001,13.16081],"type":"Point"}
}