{
  "type": "Feature",
  "properties": {
    "gn:admin1_code":"15.0",
    "gn:asciiname":"Ban Nong Ruea Klon",
    "gn:country_code":"TH",
    "gn:dem":50,
    "gn:feature_class":"P",
    "gn:feature_code":"PPL",
    "gn:name":"Ban Nong Ruea Klon",
    "gn:population":0,
    "gn:timezone":"Asia/Bangkok",
    "iso:country":"TH",
    "name:tha_x_preferred":[
        "\u0e1a\u0e49\u0e32\u0e19\u0e2b\u0e19\u0e2d\u0e07\u0e40\u0e23\u0e37\u0e2d\u0e42\u0e01\u0e25\u0e19"
    ],
    "name:und_x_variant":[
        "B\u0101n Naung Rua Glaun",
        "Ban Nong Rua Klon",
        "Ban Nong Ruea Klon"
    ],
    "wof:lang_x_official":[
        "tha"
    ],
    "wof:lang_x_spoken":[
        "tha"
    ],
    "wof:name":"Ban Nong Ruea Klon",
    "wof:placetype":"locality"
},
  "geometry": {"coordinates":[99.86319,15.46506],"type":"Point"}
}