{
  "type": "Feature",
  "properties": {
    "gn:admin1_code":"1.0",
    "gn:asciiname":"Ban Thi Kho Khi",
    "gn:country_code":"TH",
    "gn:dem":941,
    "gn:feature_class":"P",
    "gn:feature_code":"PPL",
    "gn:name":"Ban Thi Kho Khi",
    "gn:population":0,
    "gn:timezone":"Asia/Bangkok",
    "iso:country":"TH",
    "name:tha_x_preferred":[
        "\u0e1a\u0e49\u0e32\u0e19\u0e17\u0e35\u0e42\u0e04\u0e04\u0e35"
    ],
    "name:und_x_variant":[
        "Ban Thi Khlo Khli"
    ],
    "wof:name":"Ban Thi Kho Khi",
    "wof:placetype":"locality"
},
  "geometry": {"coordinates":[98.06486,18.46325],"type":"Point"}
}