{
  "type": "Feature",
  "properties": {
    "gn:admin1_code":"57.0",
    "gn:asciiname":"Ban Khlong Nam Chuet",
    "gn:country_code":"TH",
    "gn:dem":14,
    "gn:feature_class":"P",
    "gn:feature_code":"PPL",
    "gn:name":"Ban Khlong Nam Chuet",
    "gn:population":0,
    "gn:timezone":"Asia/Bangkok",
    "iso:country":"TH",
    "name:tha_x_preferred":[
        "\u0e1a\u0e49\u0e32\u0e19\u0e04\u0e25\u0e2d\u0e07\u0e19\u0e49\u0e33\u0e08\u0e37\u0e14"
    ],
    "wof:lang_x_official":[
        "tha"
    ],
    "wof:lang_x_spoken":[
        "tha"
    ],
    "wof:name":"Ban Khlong Nam Chuet",
    "wof:placetype":"locality"
},
  "geometry": {"coordinates":[99.59956,11.44092],"type":"Point"}
}