{
  "type": "Feature",
  "properties": {
    "gn:admin1_code":"68.0",
    "gn:asciiname":"Ban Muang Ngam",
    "gn:country_code":"TH",
    "gn:dem":9,
    "gn:feature_class":"P",
    "gn:feature_code":"PPL",
    "gn:name":"Ban Muang Ngam",
    "gn:population":0,
    "gn:timezone":"Asia/Bangkok",
    "iso:country":"TH",
    "name:tha_x_preferred":[
        "\u0e1a\u0e49\u0e32\u0e19\u0e21\u0e48\u0e27\u0e07\u0e07\u0e32\u0e21"
    ],
    "name:und_x_variant":[
        "Ma Maung Ngam",
        "Ban Mamuang Ngam (1)",
        "Ban Muang Ngam"
    ],
    "wof:name":"Ban Muang Ngam",
    "wof:placetype":"locality"
},
  "geometry": {"coordinates":[100.48853,7.35078],"type":"Point"}
}