{
  "type": "Feature",
  "properties": {
    "gn:admin1_code":"6.0",
    "gn:asciiname":"Ban Nong Hiang",
    "gn:country_code":"TH",
    "gn:dem":295,
    "gn:feature_class":"P",
    "gn:feature_code":"PPL",
    "gn:name":"Ban Nong Hiang",
    "gn:population":0,
    "gn:timezone":"Asia/Bangkok",
    "iso:country":"TH",
    "name:tha_x_preferred":[
        "\u0e1a\u0e49\u0e32\u0e19\u0e2b\u0e19\u0e2d\u0e07\u0e40\u0e2b\u0e35\u0e22\u0e07"
    ],
    "name:und_x_variant":[
        "B\u0101n Naung Tiang",
        "Ban Nong Thiang",
        "Ban Nong Hiang"
    ],
    "wof:name":"Ban Nong Hiang",
    "wof:placetype":"locality"
},
  "geometry": {"coordinates":[99.96969,18.77672],"type":"Point"}
}