{
  "type": "Feature",
  "properties": {
    "gn:admin1_code":"36.0",
    "gn:asciiname":"Ban Lat Chit (1)",
    "gn:cc2":"TH",
    "gn:country_code":"TH",
    "gn:dem":6,
    "gn:feature_class":"P",
    "gn:feature_code":"PPL",
    "gn:name":"Ban Lat Chit (1)",
    "gn:population":0,
    "gn:timezone":"Asia/Bangkok",
    "iso:country":"TH",
    "name:und_x_variant":[
        "Ban Ladchit",
        "Ban Lat Chit (1)"
    ],
    "wof:lang_x_official":[
        "tha"
    ],
    "wof:lang_x_spoken":[
        "tha"
    ],
    "wof:name":"Ban Lat Chit (1)",
    "wof:placetype":"locality"
},
  "geometry": {"coordinates":[100.34999999999999,14.43333],"type":"Point"}
}