{
  "type": "Feature",
  "properties": {
    "gn:admin1_code":"51.0",
    "gn:asciiname":"Ban Bo Rahaeng",
    "gn:country_code":"TH",
    "gn:dem":16,
    "gn:feature_class":"P",
    "gn:feature_code":"PPL",
    "gn:name":"Ban Bo Rahaeng",
    "gn:population":0,
    "gn:timezone":"Asia/Bangkok",
    "iso:country":"TH",
    "name:tha_x_preferred":[
        "\u0e1a\u0e49\u0e32\u0e19\u0e1a\u0e48\u0e2d\u0e23\u0e30\u0e41\u0e2b\u0e07"
    ],
    "wof:name":"Ban Bo Rahaeng",
    "wof:placetype":"locality"
},
  "geometry": {"coordinates":[99.74679999999999,14.10049],"type":"Point"}
}