{
  "type": "Feature",
  "properties": {
    "gn:admin1_code":"28.0",
    "gn:asciiname":"Ban Thonglang",
    "gn:country_code":"TH",
    "gn:dem":161,
    "gn:feature_class":"P",
    "gn:feature_code":"PPL",
    "gn:name":"Ban Thonglang",
    "gn:population":0,
    "gn:timezone":"Asia/Bangkok",
    "iso:country":"TH",
    "name:tha_x_preferred":[
        "\u0e1a\u0e49\u0e32\u0e19\u0e17\u0e2d\u0e07\u0e2b\u0e25\u0e32\u0e07"
    ],
    "name:und_x_variant":[
        "Ban Thong Lang",
        "Ban Thong",
        "Ban Thonglang"
    ],
    "wof:name":"Ban Thonglang",
    "wof:placetype":"locality"
},
  "geometry": {"coordinates":[102.81664000000001,15.60911],"type":"Point"}
}