{
  "type": "Feature",
  "properties": {
    "gn:admin1_code":"51.0",
    "gn:asciiname":"Ban Bo Pan",
    "gn:country_code":"TH",
    "gn:dem":11,
    "gn:feature_class":"P",
    "gn:feature_code":"PPL",
    "gn:name":"Ban Bo Pan",
    "gn:population":0,
    "gn:timezone":"Asia/Bangkok",
    "iso:country":"TH",
    "name:tha_x_preferred":[
        "\u0e1a\u0e49\u0e32\u0e19\u0e1a\u0e48\u0e2d\u0e1b\u0e31\u0e49\u0e19"
    ],
    "wof:name":"Ban Bo Pan",
    "wof:placetype":"locality"
},
  "geometry": {"coordinates":[99.82774999999999,14.23342],"type":"Point"}
}