{
  "type": "Feature",
  "properties": {
    "gn:admin1_code":"4.0",
    "gn:asciiname":"Ban Sop Bua",
    "gn:country_code":"TH",
    "gn:dem":274,
    "gn:feature_class":"P",
    "gn:feature_code":"PPL",
    "gn:name":"Ban Sop Bua",
    "gn:population":0,
    "gn:timezone":"Asia/Bangkok",
    "iso:country":"TH",
    "name:tha_x_preferred":[
        "\u0e1a\u0e49\u0e32\u0e19\u0e2a\u0e1a\u0e1a\u0e31\u0e27"
    ],
    "name:und_x_variant":[
        "B\u0101n Bau",
        "Ban Bo",
        "Ban Sop Bua"
    ],
    "wof:lang_x_official":[
        "tha"
    ],
    "wof:lang_x_spoken":[
        "tha"
    ],
    "wof:name":"Ban Sop Bua",
    "wof:placetype":"locality"
},
  "geometry": {"coordinates":[100.90089,19.08767000000001],"type":"Point"}
}