{
  "type": "Feature",
  "properties": {
    "gn:admin1_code":"18.0",
    "gn:asciiname":"Ban Khok Nong Kae",
    "gn:country_code":"TH",
    "gn:dem":310,
    "gn:feature_class":"P",
    "gn:feature_code":"PPL",
    "gn:name":"Ban Khok Nong Kae",
    "gn:population":0,
    "gn:timezone":"Asia/Bangkok",
    "iso:country":"TH",
    "name:tha_x_preferred":[
        "Ban Khok Nong Kae"
    ],
    "name:tha_x_variant":[
        "\u0e1a\u0e49\u0e32\u0e19\u0e42\u0e04\u0e01\u0e2b\u0e19\u0e2d\u0e07\u0e41\u0e01"
    ],
    "name:und_x_variant":[
        "Ban Nong Kae"
    ],
    "wof:name":"Ban Khok Nong Kae",
    "wof:placetype":"locality"
},
  "geometry": {"coordinates":[101.81461,17.20333],"type":"Point"}
}