{
  "type": "Feature",
  "properties": {
    "gn:admin1_code":"6.0",
    "gn:asciiname":"Ban Na Pong Han",
    "gn:country_code":"TH",
    "gn:dem":269,
    "gn:feature_class":"P",
    "gn:feature_code":"PPL",
    "gn:name":"Ban Na Pong Han",
    "gn:population":0,
    "gn:timezone":"Asia/Bangkok",
    "iso:country":"TH",
    "name:tha_x_preferred":[
        "\u0e1a\u0e49\u0e32\u0e19\u0e19\u0e32\u0e42\u0e1b\u0e48\u0e07\u0e2b\u0e32\u0e0d"
    ],
    "wof:name":"Ban Na Pong Han",
    "wof:placetype":"locality"
},
  "geometry": {"coordinates":[99.30842,18.26292],"type":"Point"}
}