{
  "type": "Feature",
  "properties": {
    "gn:admin1_code":"2.0",
    "gn:asciiname":"Ban Saluang Nai",
    "gn:country_code":"TH",
    "gn:dem":354,
    "gn:feature_class":"P",
    "gn:feature_code":"PPL",
    "gn:name":"Ban Saluang Nai",
    "gn:population":0,
    "gn:timezone":"Asia/Bangkok",
    "iso:country":"TH",
    "name:tha_x_preferred":[
        "\u0e1a\u0e49\u0e32\u0e19\u0e2a\u0e30\u0e25\u0e27\u0e07\u0e43\u0e19"
    ],
    "name:und_x_variant":[
        "Sal\u016bang",
        "Ban Saluang",
        "Ban Saluang Nai"
    ],
    "wof:name":"Ban Saluang Nai",
    "wof:placetype":"locality"
},
  "geometry": {"coordinates":[98.87586,19.01039],"type":"Point"}
}