{
  "type": "Feature",
  "properties": {
    "gn:admin1_code":"16.0",
    "gn:asciiname":"Ban Sai Lom",
    "gn:country_code":"TH",
    "gn:dem":90,
    "gn:feature_class":"P",
    "gn:feature_code":"PPL",
    "gn:name":"Ban Sai Lom",
    "gn:population":0,
    "gn:timezone":"Asia/Bangkok",
    "iso:country":"TH",
    "name:tha_x_preferred":[
        "\u0e1a\u0e49\u0e32\u0e19\u0e2a\u0e32\u0e22\u0e25\u0e21"
    ],
    "wof:name":"Ban Sai Lom",
    "wof:placetype":"locality"
},
  "geometry": {"coordinates":[100.74903,15.95281],"type":"Point"}
}