{
  "type": "Feature",
  "properties": {
    "gn:admin1_code":"24.0",
    "gn:asciiname":"Ban Khok Ko",
    "gn:country_code":"TH",
    "gn:dem":169,
    "gn:feature_class":"P",
    "gn:feature_code":"PPL",
    "gn:name":"Ban Khok Ko",
    "gn:population":0,
    "gn:timezone":"Asia/Bangkok",
    "iso:country":"TH",
    "name:tha_x_preferred":[
        "\u0e1a\u0e49\u0e32\u0e19\u0e42\u0e04\u0e01\u0e01\u0e48\u0e2d"
    ],
    "wof:name":"Ban Khok Ko",
    "wof:placetype":"locality"
},
  "geometry": {"coordinates":[103.26027999999999,16.05122],"type":"Point"}
}