{
  "type": "Feature",
  "properties": {
    "gn:admin1_code":"28.0",
    "gn:asciiname":"Ban Krok Kaeo",
    "gn:country_code":"TH",
    "gn:dem":205,
    "gn:feature_class":"P",
    "gn:feature_code":"PPL",
    "gn:name":"Ban Krok Kaeo",
    "gn:population":0,
    "gn:timezone":"Asia/Bangkok",
    "iso:country":"TH",
    "name:tha_x_preferred":[
        "\u0e1a\u0e49\u0e32\u0e19\u0e42\u0e01\u0e23\u0e01\u0e41\u0e01\u0e49\u0e27"
    ],
    "wof:name":"Ban Krok Kaeo",
    "wof:placetype":"locality"
},
  "geometry": {"coordinates":[102.60505999999999,14.61044],"type":"Point"}
}