{
  "type": "Feature",
  "properties": {
    "gn:admin1_code":"76.0",
    "gn:asciiname":"Ban Pong",
    "gn:country_code":"TH",
    "gn:dem":184,
    "gn:feature_class":"P",
    "gn:feature_code":"PPL",
    "gn:name":"Ban Pong",
    "gn:population":0,
    "gn:timezone":"Asia/Bangkok",
    "iso:country":"TH",
    "name:tha_x_preferred":[
        "\u0e1a\u0e49\u0e32\u0e19\u0e1b\u0e48\u0e2d\u0e07"
    ],
    "wof:name":"Ban Pong",
    "wof:placetype":"locality"
},
  "geometry": {"coordinates":[102.62606,17.43928],"type":"Point"}
}