{
  "type": "Feature",
  "properties": {
    "gn:admin1_code":"76.0",
    "gn:asciiname":"Ban Liam Philuek",
    "gn:country_code":"TH",
    "gn:dem":198,
    "gn:feature_class":"P",
    "gn:feature_code":"PPL",
    "gn:name":"Ban Liam Philuek",
    "gn:population":0,
    "gn:timezone":"Asia/Bangkok",
    "iso:country":"TH",
    "name:tha_x_preferred":[
        "\u0e1a\u0e49\u0e32\u0e19\u0e40\u0e25\u0e35\u0e48\u0e22\u0e21\u0e1e\u0e34\u0e25\u0e36\u0e01"
    ],
    "wof:name":"Ban Liam Philuek",
    "wof:placetype":"locality"
},
  "geometry": {"coordinates":[102.78408,17.33072],"type":"Point"}
}