{
  "type": "Feature",
  "properties": {
    "gn:admin1_code":"20.0",
    "gn:asciiname":"Ban Khok Sai Khao",
    "gn:country_code":"TH",
    "gn:dem":151,
    "gn:feature_class":"P",
    "gn:feature_code":"PPL",
    "gn:name":"Ban Khok Sai Khao",
    "gn:population":0,
    "gn:timezone":"Asia/Bangkok",
    "iso:country":"TH",
    "name:tha_x_preferred":[
        "\u0e1a\u0e49\u0e32\u0e19\u0e42\u0e04\u0e01\u0e17\u0e23\u0e32\u0e22\u0e02\u0e32\u0e27"
    ],
    "wof:name":"Ban Khok Sai Khao",
    "wof:placetype":"locality"
},
  "geometry": {"coordinates":[103.84997,17.84092],"type":"Point"}
}