{
  "type": "Feature",
  "properties": {
    "gn:admin1_code":"2.0",
    "gn:asciiname":"Ban Nam Bo Luang",
    "gn:country_code":"TH",
    "gn:dem":321,
    "gn:feature_class":"P",
    "gn:feature_code":"PPL",
    "gn:name":"Ban Nam Bo Luang",
    "gn:population":0,
    "gn:timezone":"Asia/Bangkok",
    "iso:country":"TH",
    "name:tha_x_preferred":[
        "\u0e1a\u0e49\u0e32\u0e19\u0e19\u0e49\u0e33\u0e1a\u0e48\u0e2d\u0e2b\u0e25\u0e27\u0e07"
    ],
    "wof:name":"Ban Nam Bo Luang",
    "wof:placetype":"locality"
},
  "geometry": {"coordinates":[98.84831,18.6445],"type":"Point"}
}