{
  "type": "Feature",
  "properties": {
    "gn:admin1_code":"67.0",
    "gn:asciiname":"Ban Lu Po Karanyi",
    "gn:country_code":"TH",
    "gn:dem":14,
    "gn:feature_class":"P",
    "gn:feature_code":"PPL",
    "gn:name":"Ban Lu Po Karanyi",
    "gn:population":0,
    "gn:timezone":"Asia/Bangkok",
    "iso:country":"TH",
    "name:tha_x_preferred":[
        "\u0e1a\u0e49\u0e32\u0e19\u0e25\u0e39\u0e42\u0e1b\u0e4a\u0e30\u0e01\u0e32\u0e23\u0e31\u0e19\u0e22\u0e35"
    ],
    "wof:name":"Ban Lu Po Karanyi",
    "wof:placetype":"locality"
},
  "geometry": {"coordinates":[100.05203,6.70906],"type":"Point"}
}