{
  "type": "Feature",
  "properties": {
    "gn:admin1_code":"66.0",
    "gn:asciiname":"Ban Chong Fuen",
    "gn:country_code":"TH",
    "gn:dem":12,
    "gn:feature_class":"P",
    "gn:feature_code":"PPL",
    "gn:name":"Ban Chong Fuen",
    "gn:population":0,
    "gn:timezone":"Asia/Bangkok",
    "iso:country":"TH",
    "name:tha_x_preferred":[
        "\u0e1a\u0e49\u0e32\u0e19\u0e0a\u0e48\u0e2d\u0e07\u0e1f\u0e36\u0e19"
    ],
    "name:tha_x_variant":[
        "\u0e1a\u0e49\u0e32\u0e19\u0e0a\u0e48\u0e2d\u0e07\u0e1f\u0e37\u0e19"
    ],
    "name:und_x_variant":[
        "Ban Chong Phun",
        "Ban Chong Fun",
        "Ban Chong Fuen",
        "Ban Chong Phuen"
    ],
    "wof:name":"Ban Chong Fuen",
    "wof:placetype":"locality"
},
  "geometry": {"coordinates":[100.32558,7.38656],"type":"Point"}
}