{
  "type": "Feature",
  "properties": {
    "gn:admin1_code":"3.0",
    "gn:asciiname":"Ban Phana Seri",
    "gn:country_code":"TH",
    "gn:dem":1086,
    "gn:feature_class":"P",
    "gn:feature_code":"PPL",
    "gn:name":"Ban Phana Seri",
    "gn:population":0,
    "gn:timezone":"Asia/Bangkok",
    "iso:country":"TH",
    "name:tha_x_preferred":[
        "\u0e1a\u0e49\u0e32\u0e19\u0e1e\u0e19\u0e32\u0e40\u0e2a\u0e23\u0e35"
    ],
    "wof:name":"Ban Phana Seri",
    "wof:placetype":"locality"
},
  "geometry": {"coordinates":[99.32347,19.49836],"type":"Point"}
}