{
  "type": "Feature",
  "properties": {
    "gn:admin1_code":"27.0",
    "gn:asciiname":"Ban Krok Don Muang",
    "gn:country_code":"TH",
    "gn:dem":175,
    "gn:feature_class":"P",
    "gn:feature_code":"PPL",
    "gn:name":"Ban Krok Don Muang",
    "gn:population":0,
    "gn:timezone":"Asia/Bangkok",
    "iso:country":"TH",
    "name:tha_x_preferred":[
        "\u0e1a\u0e49\u0e32\u0e19\u0e42\u0e01\u0e23\u0e01\u0e14\u0e2d\u0e19\u0e21\u0e48\u0e27\u0e07"
    ],
    "name:und_x_variant":[
        "Ban Nong Muang"
    ],
    "wof:lang_x_official":[
        "tha"
    ],
    "wof:lang_x_spoken":[
        "tha"
    ],
    "wof:name":"Ban Krok Don Muang",
    "wof:placetype":"locality"
},
  "geometry": {"coordinates":[102.29908,15.30169],"type":"Point"}
}