{
  "type": "Feature",
  "properties": {
    "gn:admin1_code":"3.0",
    "gn:asciiname":"Ban Pho Chai",
    "gn:country_code":"TH",
    "gn:dem":393,
    "gn:feature_class":"P",
    "gn:feature_code":"PPL",
    "gn:name":"Ban Pho Chai",
    "gn:population":0,
    "gn:timezone":"Asia/Bangkok",
    "iso:country":"TH",
    "name:tha_x_preferred":[
        "\u0e1a\u0e49\u0e32\u0e19\u0e42\u0e1e\u0e18\u0e34\u0e4c\u0e0a\u0e31\u0e22"
    ],
    "wof:name":"Ban Pho Chai",
    "wof:placetype":"locality"
},
  "geometry": {"coordinates":[99.90536,19.9017],"type":"Point"}
}