{
  "type": "Feature",
  "properties": {
    "gn:admin1_code":"6.0",
    "gn:asciiname":"Ban Tha Pun",
    "gn:cc2":"TH",
    "gn:country_code":"TH",
    "gn:dem":248,
    "gn:feature_class":"P",
    "gn:feature_code":"PPL",
    "gn:name":"Ban Tha Pun",
    "gn:population":0,
    "gn:timezone":"Asia/Bangkok",
    "iso:country":"TH",
    "name:und_x_variant":[
        "Ban Pha Pun",
        "Ban Tha Pun"
    ],
    "wof:name":"Ban Tha Pun",
    "wof:placetype":"locality"
},
  "geometry": {"coordinates":[99.34999999999999,18.06667],"type":"Point"}
}