{
  "type": "Feature",
  "properties": {
    "gn:admin1_code":"8.0",
    "gn:asciiname":"Ban Pak Rong",
    "gn:country_code":"TH",
    "gn:dem":115,
    "gn:feature_class":"P",
    "gn:feature_code":"PPL",
    "gn:name":"Ban Pak Rong",
    "gn:population":0,
    "gn:timezone":"Asia/Bangkok",
    "iso:country":"TH",
    "name:tha_x_preferred":[
        "Ban Pak Rong"
    ],
    "name:tha_x_variant":[
        "\u0e1a\u0e49\u0e32\u0e19\u0e1b\u0e32\u0e01\u0e23\u0e49\u0e2d\u0e07"
    ],
    "wof:name":"Ban Pak Rong",
    "wof:placetype":"locality"
},
  "geometry": {"coordinates":[99.11736000000001,16.87019],"type":"Point"}
}