{
  "type": "Feature",
  "properties": {
    "gn:admin1_code":"8.0",
    "gn:asciiname":"Ban Ya Pho",
    "gn:country_code":"TH",
    "gn:dem":326,
    "gn:feature_class":"P",
    "gn:feature_code":"PPL",
    "gn:name":"Ban Ya Pho",
    "gn:population":0,
    "gn:timezone":"Asia/Bangkok",
    "iso:country":"TH",
    "name:tha_x_preferred":[
        "\u0e1a\u0e49\u0e32\u0e19\u0e22\u0e30\u0e1e\u0e2d"
    ],
    "wof:name":"Ban Ya Pho",
    "wof:placetype":"locality"
},
  "geometry": {"coordinates":[98.73669,16.33964],"type":"Point"}
}