{
  "type": "Feature",
  "properties": {
    "gn:admin1_code":"27",
    "gn:asciiname":"Ban Khok Pha-ngat",
    "gn:country_code":"TH",
    "gn:dem":176,
    "gn:feature_class":"P",
    "gn:feature_code":"PPL",
    "gn:name":"Ban Khok Pha-ngat",
    "gn:population":0,
    "gn:timezone":"Asia/Bangkok",
    "iso:country":"TH",
    "name:tha_x_preferred":[
        "\u0e1a\u0e49\u0e32\u0e19\u0e42\u0e04\u0e01\u0e1e\u0e30\u0e07\u0e32\u0e14"
    ],
    "wof:name":"Ban Khok Pha-ngat",
    "wof:placetype":"locality"
},
  "geometry": {"coordinates":[102.38153,15.36953],"type":"Point"}
}