{
  "type": "Feature",
  "properties": {
    "gn:admin1_code":"27.0",
    "gn:asciiname":"Ban Don Tanin Noi",
    "gn:country_code":"TH",
    "gn:dem":205,
    "gn:feature_class":"P",
    "gn:feature_code":"PPL",
    "gn:name":"Ban Don Tanin Noi",
    "gn:population":0,
    "gn:timezone":"Asia/Bangkok",
    "iso:country":"TH",
    "name:tha_x_preferred":[
        "\u0e1a\u0e49\u0e32\u0e19\u0e14\u0e2d\u0e19\u0e15\u0e32\u0e2b\u0e19\u0e34\u0e19\u0e19\u0e49\u0e2d\u0e22"
    ],
    "name:und_x_variant":[
        "Ban Daun Da Nin",
        "Ban Don Ta Nin",
        "Ban Don Ta Nin Noi",
        "Ban Don Tanin Noi"
    ],
    "wof:name":"Ban Don Tanin Noi",
    "wof:placetype":"locality"
},
  "geometry": {"coordinates":[101.81328000000001,15.18019],"type":"Point"}
}