{
  "type": "Feature",
  "properties": {
    "gn:admin1_code":"58.0",
    "gn:asciiname":"Ban Cho Po Ro",
    "gn:country_code":"TH",
    "gn:dem":86,
    "gn:feature_class":"P",
    "gn:feature_code":"PPL",
    "gn:name":"Ban Cho Po Ro",
    "gn:population":0,
    "gn:timezone":"Asia/Bangkok",
    "iso:country":"TH",
    "name:tha_x_preferred":[
        "\u0e1a\u0e49\u0e32\u0e19 \u0e08\u0e1b\u0e23."
    ],
    "wof:name":"Ban Cho Po Ro",
    "wof:placetype":"locality"
},
  "geometry": {"coordinates":[98.9072,10.47364],"type":"Point"}
}