{
  "type": "Feature",
  "properties": {
    "gn:admin1_code":"10.0",
    "gn:asciiname":"Ban Pong Pun",
    "gn:country_code":"TH",
    "gn:dem":338,
    "gn:feature_class":"P",
    "gn:feature_code":"PPL",
    "gn:name":"Ban Pong Pun",
    "gn:population":0,
    "gn:timezone":"Asia/Bangkok",
    "iso:country":"TH",
    "name:tha_x_preferred":[
        "Ban Pong Pun"
    ],
    "name:tha_x_variant":[
        "\u0e1a\u0e49\u0e32\u0e19\u0e42\u0e1b\u0e48\u0e07\u0e1b\u0e38\u0e49\u0e19"
    ],
    "wof:name":"Ban Pong Pun",
    "wof:placetype":"locality"
},
  "geometry": {"coordinates":[100.96196999999999,17.85558],"type":"Point"}
}