{
  "type": "Feature",
  "properties": {
    "gn:admin1_code":"65.0",
    "gn:asciiname":"Ban Chai Wat",
    "gn:country_code":"TH",
    "gn:dem":13,
    "gn:feature_class":"P",
    "gn:feature_code":"PPL",
    "gn:name":"Ban Chai Wat",
    "gn:population":0,
    "gn:timezone":"Asia/Bangkok",
    "iso:country":"TH",
    "name:tha_x_preferred":[
        "\u0e1a\u0e49\u0e32\u0e19\u0e0a\u0e32\u0e22\u0e27\u0e31\u0e14"
    ],
    "wof:name":"Ban Chai Wat",
    "wof:placetype":"locality"
},
  "geometry": {"coordinates":[99.52831,7.40542],"type":"Point"}
}