{
  "type": "Feature",
  "properties": {
    "gn:admin1_code":"51.0",
    "gn:asciiname":"Ban Sakae Yang Mu",
    "gn:country_code":"TH",
    "gn:dem":6,
    "gn:feature_class":"P",
    "gn:feature_code":"PPL",
    "gn:name":"Ban Sakae Yang Mu",
    "gn:population":0,
    "gn:timezone":"Asia/Bangkok",
    "iso:country":"TH",
    "name:tha_x_preferred":[
        "\u0e1a\u0e49\u0e32\u0e19\u0e2a\u0e30\u0e41\u0e01\u0e22\u0e48\u0e32\u0e07\u0e2b\u0e21\u0e39"
    ],
    "name:und_x_variant":[
        "Sake Yang Mu",
        "Ban Sakae Yang Mu"
    ],
    "wof:lang_x_official":[
        "tha"
    ],
    "wof:lang_x_spoken":[
        "tha"
    ],
    "wof:name":"Ban Sakae Yang Mu",
    "wof:placetype":"locality"
},
  "geometry": {"coordinates":[100.07042,14.39608],"type":"Point"}
}