{
  "type": "Feature",
  "properties": {
    "gn:admin1_code":"80",
    "gn:asciiname":"Ban Saphan Song",
    "gn:country_code":"TH",
    "gn:dem":158,
    "gn:feature_class":"P",
    "gn:feature_code":"PPL",
    "gn:name":"Ban Saphan Song",
    "gn:population":0,
    "gn:timezone":"Asia/Bangkok",
    "iso:country":"TH",
    "name:tha_x_preferred":[
        "\u0e1a\u0e49\u0e32\u0e19\u0e2a\u0e30\u0e1e\u0e32\u0e19\u0e2a\u0e2d\u0e07"
    ],
    "wof:name":"Ban Saphan Song",
    "wof:placetype":"locality"
},
  "geometry": {"coordinates":[102.29892,13.42539],"type":"Point"}
}