{
  "type": "Feature",
  "properties": {
    "gn:admin1_code":"46.0",
    "gn:asciiname":"Ban Chak Makham",
    "gn:country_code":"TH",
    "gn:dem":35,
    "gn:feature_class":"P",
    "gn:feature_code":"PPL",
    "gn:name":"Ban Chak Makham",
    "gn:population":0,
    "gn:timezone":"Asia/Bangkok",
    "iso:country":"TH",
    "wof:name":"Ban Chak Makham",
    "wof:placetype":"locality"
},
  "geometry": {"coordinates":[100.96666999999999,13.18333],"type":"Point"}
}