{
  "type": "Feature",
  "properties": {
    "gn:admin1_code":"42.0",
    "gn:asciiname":"Ban Khlong Palat Priang",
    "gn:country_code":"TH",
    "gn:dem":5,
    "gn:feature_class":"P",
    "gn:feature_code":"PPL",
    "gn:name":"Ban Khlong Palat Priang",
    "gn:population":0,
    "gn:timezone":"Asia/Bangkok",
    "iso:country":"TH",
    "name:tha_x_preferred":[
        "\u0e1a\u0e49\u0e32\u0e19\u0e04\u0e25\u0e2d\u0e07\u0e1b\u0e25\u0e31\u0e14\u0e40\u0e1b\u0e23\u0e35\u0e22\u0e07"
    ],
    "name:und_x_variant":[
        "Ban Klong Plad Kriang",
        "Ban Khlong Palat Priang"
    ],
    "wof:name":"Ban Khlong Palat Priang",
    "wof:placetype":"locality"
},
  "geometry": {"coordinates":[100.65106,13.63258],"type":"Point"}
}