{
  "type": "Feature",
  "properties": {
    "gn:admin1_code":"2.0",
    "gn:asciiname":"Ban Chedi Phatthana",
    "gn:country_code":"TH",
    "gn:dem":334,
    "gn:feature_class":"P",
    "gn:feature_code":"PPL",
    "gn:name":"Ban Chedi Phatthana",
    "gn:population":0,
    "gn:timezone":"Asia/Bangkok",
    "iso:country":"TH",
    "name:tha_x_preferred":[
        "\u0e1a\u0e49\u0e32\u0e19\u0e40\u0e08\u0e14\u0e35\u0e22\u0e4c\u0e1e\u0e31\u0e12\u0e19\u0e32"
    ],
    "wof:name":"Ban Chedi Phatthana",
    "wof:placetype":"locality"
},
  "geometry": {"coordinates":[98.98575,18.988],"type":"Point"}
}