{
  "type": "Feature",
  "properties": {
    "gn:admin1_code":"43.0",
    "gn:asciiname":"Ban Bang Nang Lek",
    "gn:country_code":"TH",
    "gn:dem":5,
    "gn:feature_class":"P",
    "gn:feature_code":"PPL",
    "gn:name":"Ban Bang Nang Lek",
    "gn:population":0,
    "gn:timezone":"Asia/Bangkok",
    "iso:country":"TH",
    "name:tha_x_preferred":[
        "\u0e1a\u0e49\u0e32\u0e19\u0e1a\u0e32\u0e07\u0e19\u0e32\u0e07\u0e40\u0e25\u0e47\u0e01"
    ],
    "name:und_x_variant":[
        "Ban Khlong Bang I Lek"
    ],
    "wof:name":"Ban Bang Nang Lek",
    "wof:placetype":"locality"
},
  "geometry": {"coordinates":[101.0515,14.08689],"type":"Point"}
}