{
  "type": "Feature",
  "properties": {
    "gn:admin1_code":"28.0",
    "gn:asciiname":"Ban Lak Khet",
    "gn:country_code":"TH",
    "gn:dem":170,
    "gn:feature_class":"P",
    "gn:feature_code":"PPL",
    "gn:name":"Ban Lak Khet",
    "gn:population":0,
    "gn:timezone":"Asia/Bangkok",
    "iso:country":"TH",
    "name:tha_x_preferred":[
        "\u0e1a\u0e49\u0e32\u0e19\u0e2b\u0e25\u0e31\u0e01\u0e40\u0e02\u0e15"
    ],
    "name:und_x_variant":[
        "Ban Lak"
    ],
    "wof:lang_x_official":[
        "tha"
    ],
    "wof:lang_x_spoken":[
        "tha"
    ],
    "wof:name":"Ban Lak Khet",
    "wof:placetype":"locality"
},
  "geometry": {"coordinates":[103.16031,14.81242],"type":"Point"}
}