{
  "type": "Feature",
  "properties": {
    "gn:admin1_code":"7.0",
    "gn:asciiname":"Ban Bo Kaeo",
    "gn:country_code":"TH",
    "gn:dem":305,
    "gn:feature_class":"P",
    "gn:feature_code":"PPL",
    "gn:name":"Ban Bo Kaeo",
    "gn:population":0,
    "gn:timezone":"Asia/Bangkok",
    "iso:country":"TH",
    "name:tha_x_preferred":[
        "\u0e1a\u0e49\u0e32\u0e19\u0e1a\u0e48\u0e2d\u0e41\u0e01\u0e49\u0e27"
    ],
    "wof:name":"Ban Bo Kaeo",
    "wof:placetype":"locality"
},
  "geometry": {"coordinates":[99.89694,17.91492000000001],"type":"Point"}
}