{
  "type": "Feature",
  "properties": {
    "gn:admin1_code":"37",
    "gn:asciiname":"Ban Rang Waeng",
    "gn:country_code":"TH",
    "gn:dem":36,
    "gn:feature_class":"P",
    "gn:feature_code":"PPL",
    "gn:name":"Ban Rang Waeng",
    "gn:population":0,
    "gn:timezone":"Asia/Bangkok",
    "iso:country":"TH",
    "name:tha_x_preferred":[
        "\u0e1a\u0e49\u0e32\u0e19\u0e23\u0e31\u0e49\u0e07\u0e41\u0e27\u0e49\u0e07"
    ],
    "wof:name":"Ban Rang Waeng",
    "wof:placetype":"locality"
},
  "geometry": {"coordinates":[101.02925,14.49825],"type":"Point"}
}