{
  "type": "Feature",
  "properties": {
    "gn:admin1_code":"20.0",
    "gn:asciiname":"Ban Trai Thong",
    "gn:country_code":"TH",
    "gn:dem":161,
    "gn:feature_class":"P",
    "gn:feature_code":"PPL",
    "gn:name":"Ban Trai Thong",
    "gn:population":0,
    "gn:timezone":"Asia/Bangkok",
    "iso:country":"TH",
    "name:tha_x_preferred":[
        "\u0e1a\u0e49\u0e32\u0e19\u0e44\u0e15\u0e23\u0e17\u0e2d\u0e07"
    ],
    "wof:name":"Ban Trai Thong",
    "wof:placetype":"locality"
},
  "geometry": {"coordinates":[104.16792,17.15578],"type":"Point"}
}