{
  "type": "Feature",
  "properties": {
    "gn:admin1_code":"28",
    "gn:asciiname":"Ban Sok Nak",
    "gn:country_code":"TH",
    "gn:dem":166,
    "gn:feature_class":"P",
    "gn:feature_code":"PPL",
    "gn:name":"Ban Sok Nak",
    "gn:population":0,
    "gn:timezone":"Asia/Bangkok",
    "iso:country":"TH",
    "name:tha_x_preferred":[
        "\u0e1a\u0e49\u0e32\u0e19\u0e42\u0e28\u0e01\u0e19\u0e32\u0e04"
    ],
    "wof:name":"Ban Sok Nak",
    "wof:placetype":"locality"
},
  "geometry": {"coordinates":[103.06858,15.18044],"type":"Point"}
}