{
  "type": "Feature",
  "properties": {
    "gn:admin1_code":"50.0",
    "gn:asciiname":"Ban Tham Lawa",
    "gn:country_code":"TH",
    "gn:dem":81,
    "gn:feature_class":"P",
    "gn:feature_code":"PPL",
    "gn:name":"Ban Tham Lawa",
    "gn:population":0,
    "gn:timezone":"Asia/Bangkok",
    "iso:country":"TH",
    "name:tha_x_preferred":[
        "\u0e1a\u0e49\u0e32\u0e19\u0e16\u0e49\u0e33\u0e25\u0e30\u0e27\u0e49\u0e32"
    ],
    "wof:name":"Ban Tham Lawa",
    "wof:placetype":"locality"
},
  "geometry": {"coordinates":[98.97902999999999,14.28967],"type":"Point"}
}