{
  "type": "Feature",
  "properties": {
    "gn:admin1_code":"58.0",
    "gn:asciiname":"Ban Khao Ma Ngaen",
    "gn:country_code":"TH",
    "gn:dem":25,
    "gn:feature_class":"P",
    "gn:feature_code":"PPL",
    "gn:name":"Ban Khao Ma Ngaen",
    "gn:population":0,
    "gn:timezone":"Asia/Bangkok",
    "iso:country":"TH",
    "name:tha_x_preferred":[
        "\u0e1a\u0e49\u0e32\u0e19\u0e40\u0e02\u0e32\u0e2b\u0e21\u0e32\u0e41\u0e2b\u0e07\u0e19"
    ],
    "wof:name":"Ban Khao Ma Ngaen",
    "wof:placetype":"locality"
},
  "geometry": {"coordinates":[99.06297000000001,10.10886],"type":"Point"}
}