{
  "type": "Feature",
  "properties": {
    "gn:admin1_code":"64.0",
    "gn:asciiname":"Ban Nok Na",
    "gn:country_code":"TH",
    "gn:dem":5,
    "gn:feature_class":"P",
    "gn:feature_code":"PPL",
    "gn:name":"Ban Nok Na",
    "gn:population":0,
    "gn:timezone":"Asia/Bangkok",
    "iso:country":"TH",
    "name:tha_x_preferred":[
        "\u0e1a\u0e49\u0e32\u0e19\u0e19\u0e2d\u0e01\u0e19\u0e32"
    ],
    "wof:name":"Ban Nok Na",
    "wof:placetype":"locality"
},
  "geometry": {"coordinates":[100.18911,8.15114],"type":"Point"}
}