{
  "type": "Feature",
  "properties": {
    "gn:country":"TH",
    "gn:fcode":"PPL",
    "gn:pop":765,
    "iso:country":"TH",
    "name:rus_x_preferred":[
        "\u0422\u0430-\u041b\u043e-\u0412\u043e\u0443"
    ],
    "qs:name":"Ta Lo Wow",
    "qs:photos_9r":0,
    "qs:photos_sr":0,
    "qs:pop_sr":"2",
    "wof:name":"Ta Lo Wow",
    "wof:placetype":"locality",
    "wof:population":765
},
  "geometry": {"coordinates":[99.66539,6.70237],"type":"Point"}
}