{
  "type": "Feature",
  "properties": {
    "gn:admin1_code":"24",
    "gn:asciiname":"Ban Non Mueang Noi",
    "gn:country_code":"TH",
    "gn:dem":161,
    "gn:feature_class":"P",
    "gn:feature_code":"PPL",
    "gn:name":"Ban Non Mueang Noi",
    "gn:population":0,
    "gn:timezone":"Asia/Bangkok",
    "iso:country":"TH",
    "name:tha_x_preferred":[
        "\u0e1a\u0e49\u0e32\u0e19\u0e42\u0e19\u0e19\u0e40\u0e21\u0e37\u0e2d\u0e07\u0e19\u0e49\u0e2d\u0e22"
    ],
    "wof:name":"Ban Non Mueang Noi",
    "wof:placetype":"locality"
},
  "geometry": {"coordinates":[102.96047,16.41194],"type":"Point"}
}