{
  "type": "Feature",
  "properties": {
    "gn:admin1_code":"57.0",
    "gn:asciiname":"Ban Sa Noi",
    "gn:country_code":"TH",
    "gn:dem":20,
    "gn:feature_class":"P",
    "gn:feature_code":"PPL",
    "gn:name":"Ban Sa Noi",
    "gn:population":0,
    "gn:timezone":"Asia/Bangkok",
    "iso:country":"TH",
    "name:tha_x_preferred":[
        "\u0e1a\u0e49\u0e32\u0e19\u0e2a\u0e23\u0e30\u0e19\u0e49\u0e2d\u0e22"
    ],
    "wof:name":"Ban Sa Noi",
    "wof:placetype":"locality"
},
  "geometry": {"coordinates":[99.96914,12.44425],"type":"Point"}
}