{
  "type": "Feature",
  "properties": {
    "gn:admin1_code":"18.0",
    "gn:asciiname":"Ban Huai Sai Kham",
    "gn:country_code":"TH",
    "gn:dem":262,
    "gn:feature_class":"P",
    "gn:feature_code":"PPL",
    "gn:name":"Ban Huai Sai Kham",
    "gn:population":0,
    "gn:timezone":"Asia/Bangkok",
    "iso:country":"TH",
    "name:tha_x_preferred":[
        "Ban Huai Sai Kham"
    ],
    "name:tha_x_variant":[
        "\u0e1a\u0e49\u0e32\u0e19\u0e2b\u0e49\u0e27\u0e22\u0e17\u0e23\u0e32\u0e22\u0e04\u0e33"
    ],
    "name:und_x_variant":[
        "Sayagam",
        "Huai Chai Dam",
        "Ban Huai Chai Dam"
    ],
    "wof:name":"Ban Huai Sai Kham",
    "wof:placetype":"locality"
},
  "geometry": {"coordinates":[101.76397,17.26408],"type":"Point"}
}