{
  "type": "Feature",
  "properties": {
    "gn:admin1_code":"27.0",
    "gn:asciiname":"Ban Song Phi Nong",
    "gn:country_code":"TH",
    "gn:dem":283,
    "gn:feature_class":"P",
    "gn:feature_code":"PPL",
    "gn:name":"Ban Song Phi Nong",
    "gn:population":0,
    "gn:timezone":"Asia/Bangkok",
    "iso:country":"TH",
    "wof:name":"Ban Song Phi Nong",
    "wof:placetype":"locality"
},
  "geometry": {"coordinates":[101.63611,14.96639],"type":"Point"}
}