{
  "type": "Feature",
  "properties": {
    "gn:admin1_code":"61.0",
    "gn:asciiname":"Ban Laeng Hin",
    "gn:country_code":"TH",
    "gn:dem":21,
    "gn:feature_class":"P",
    "gn:feature_code":"PPL",
    "gn:name":"Ban Laeng Hin",
    "gn:population":0,
    "gn:timezone":"Asia/Bangkok",
    "iso:country":"TH",
    "name:tha_x_preferred":[
        "\u0e1a\u0e49\u0e32\u0e19\u0e41\u0e25\u0e48\u0e07\u0e2b\u0e34\u0e19"
    ],
    "wof:name":"Ban Laeng Hin",
    "wof:placetype":"locality"
},
  "geometry": {"coordinates":[98.41997000000001,8.73678],"type":"Point"}
}