{
  "type": "Feature",
  "properties": {
    "gn:admin1_code":"76.0",
    "gn:asciiname":"Ban Khok Phakchi",
    "gn:country_code":"TH",
    "gn:dem":203,
    "gn:feature_class":"P",
    "gn:feature_code":"PPL",
    "gn:name":"Ban Khok Phakchi",
    "gn:population":0,
    "gn:timezone":"Asia/Bangkok",
    "iso:country":"TH",
    "name:tha_x_preferred":[
        "\u0e1a\u0e49\u0e32\u0e19\u0e42\u0e04\u0e01\u0e1c\u0e31\u0e01\u0e0a\u0e35"
    ],
    "wof:name":"Ban Khok Phakchi",
    "wof:placetype":"locality"
},
  "geometry": {"coordinates":[102.83175,16.95272000000001],"type":"Point"}
}