{
  "type": "Feature",
  "properties": {
    "gn:admin1_code":"64.0",
    "gn:asciiname":"Ban Huai Yuan",
    "gn:country_code":"TH",
    "gn:dem":91,
    "gn:feature_class":"P",
    "gn:feature_code":"PPL",
    "gn:name":"Ban Huai Yuan",
    "gn:population":0,
    "gn:timezone":"Asia/Bangkok",
    "iso:country":"TH",
    "name:tha_x_preferred":[
        "\u0e1a\u0e49\u0e32\u0e19\u0e2b\u0e49\u0e27\u0e22\u0e0d\u0e27\u0e19"
    ],
    "wof:name":"Ban Huai Yuan",
    "wof:placetype":"locality"
},
  "geometry": {"coordinates":[99.52292,8.17697],"type":"Point"}
}