{
  "type": "Feature",
  "properties": {
    "gn:admin1_code":"46.0",
    "gn:asciiname":"Ban Noen Maprang",
    "gn:country_code":"TH",
    "gn:dem":50,
    "gn:feature_class":"P",
    "gn:feature_code":"PPL",
    "gn:name":"Ban Noen Maprang",
    "gn:population":0,
    "gn:timezone":"Asia/Bangkok",
    "iso:country":"TH",
    "name:tha_x_preferred":[
        "\u0e1a\u0e49\u0e32\u0e19\u0e40\u0e19\u0e34\u0e19\u0e21\u0e30\u0e1b\u0e23\u0e32\u0e07"
    ],
    "wof:name":"Ban Noen Maprang",
    "wof:placetype":"locality"
},
  "geometry": {"coordinates":[101.23275,13.28195],"type":"Point"}
}