{
  "type": "Feature",
  "properties": {
    "gn:admin1_code":"32.0",
    "gn:asciiname":"Ban Phrai Nokyung",
    "gn:country_code":"TH",
    "gn:dem":68,
    "gn:feature_class":"P",
    "gn:feature_code":"PPL",
    "gn:name":"Ban Phrai Nokyung",
    "gn:population":0,
    "gn:timezone":"Asia/Bangkok",
    "iso:country":"TH",
    "name:tha_x_preferred":[
        "\u0e1a\u0e49\u0e32\u0e19\u0e44\u0e1e\u0e23\u0e19\u0e01\u0e22\u0e39\u0e07"
    ],
    "wof:name":"Ban Phrai Nokyung",
    "wof:placetype":"locality"
},
  "geometry": {"coordinates":[99.85978,15.08311],"type":"Point"}
}