{
  "type": "Feature",
  "properties": {
    "gn:admin1_code":"68.0",
    "gn:asciiname":"Ban Thung Khet",
    "gn:country_code":"TH",
    "gn:dem":16,
    "gn:feature_class":"P",
    "gn:feature_code":"PPL",
    "gn:name":"Ban Thung Khet",
    "gn:population":0,
    "gn:timezone":"Asia/Bangkok",
    "iso:country":"TH",
    "name:tha_x_preferred":[
        "\u0e1a\u0e49\u0e32\u0e19\u0e17\u0e38\u0e48\u0e07\u0e40\u0e04\u0e47\u0e14"
    ],
    "wof:name":"Ban Thung Khet",
    "wof:placetype":"locality"
},
  "geometry": {"coordinates":[100.46769999999999,6.96683],"type":"Point"}
}