{
  "type": "Feature",
  "properties": {
    "gn:admin1_code":"27",
    "gn:asciiname":"Ban Khlong Chaeng",
    "gn:country_code":"TH",
    "gn:dem":362,
    "gn:feature_class":"P",
    "gn:feature_code":"PPL",
    "gn:name":"Ban Khlong Chaeng",
    "gn:population":0,
    "gn:timezone":"Asia/Bangkok",
    "iso:country":"TH",
    "name:tha_x_preferred":[
        "\u0e1a\u0e49\u0e32\u0e19\u0e04\u0e25\u0e2d\u0e07\u0e41\u0e08\u0e49\u0e07"
    ],
    "wof:name":"Ban Khlong Chaeng",
    "wof:placetype":"locality"
},
  "geometry": {"coordinates":[101.48469,14.91575],"type":"Point"}
}