{
  "type": "Feature",
  "properties": {
    "gn:admin1_code":"13.0",
    "gn:asciiname":"Ban Khok Phatthana",
    "gn:country_code":"TH",
    "gn:dem":56,
    "gn:feature_class":"P",
    "gn:feature_code":"PPL",
    "gn:name":"Ban Khok Phatthana",
    "gn:population":0,
    "gn:timezone":"Asia/Bangkok",
    "iso:country":"TH",
    "name:tha_x_preferred":[
        "\u0e1a\u0e49\u0e32\u0e19\u0e42\u0e04\u0e01\u0e1e\u0e31\u0e12\u0e19\u0e32"
    ],
    "wof:name":"Ban Khok Phatthana",
    "wof:placetype":"locality"
},
  "geometry": {"coordinates":[100.64772000000001,16.01506],"type":"Point"}
}