{
  "type": "Feature",
  "properties": {
    "gn:admin1_code":"2.0",
    "gn:asciiname":"Ban Mae Khong",
    "gn:country_code":"TH",
    "gn:dem":961,
    "gn:feature_class":"P",
    "gn:feature_code":"PPL",
    "gn:name":"Ban Mae Khong",
    "gn:population":0,
    "gn:timezone":"Asia/Bangkok",
    "iso:country":"TH",
    "name:tha_x_preferred":[
        "\u0e1a\u0e49\u0e32\u0e19\u0e41\u0e21\u0e48\u0e42\u0e02\u0e07"
    ],
    "wof:name":"Ban Mae Khong",
    "wof:placetype":"locality"
},
  "geometry": {"coordinates":[98.18143999999999,17.76436],"type":"Point"}
}