{
  "type": "Feature",
  "properties": {
    "gn:admin1_code":"74.0",
    "gn:asciiname":"Ban Khok Tabaek",
    "gn:country_code":"TH",
    "gn:dem":31,
    "gn:feature_class":"P",
    "gn:feature_code":"PPL",
    "gn:name":"Ban Khok Tabaek",
    "gn:population":0,
    "gn:timezone":"Asia/Bangkok",
    "iso:country":"TH",
    "name:und_x_variant":[
        "Ban Kok Ta Bek",
        "Ban Khok Tabaek"
    ],
    "wof:name":"Ban Khok Tabaek",
    "wof:placetype":"locality"
},
  "geometry": {"coordinates":[101.95528,14.08917],"type":"Point"}
}