{
  "type": "Feature",
  "properties": {
    "gn:admin1_code":"66.0",
    "gn:asciiname":"Ban U Khe",
    "gn:country_code":"TH",
    "gn:dem":4,
    "gn:feature_class":"P",
    "gn:feature_code":"PPL",
    "gn:name":"Ban U Khe",
    "gn:population":0,
    "gn:timezone":"Asia/Bangkok",
    "iso:country":"TH",
    "name:tha_x_preferred":[
        "\u0e1a\u0e49\u0e32\u0e19\u0e2d\u0e39\u0e48\u0e40\u0e02\u0e49"
    ],
    "wof:name":"Ban U Khe",
    "wof:placetype":"locality"
},
  "geometry": {"coordinates":[100.39706,7.36283],"type":"Point"}
}