{
  "type": "Feature",
  "properties": {
    "gn:admin1_code":"48.0",
    "gn:asciiname":"Ban Khlong Krasue",
    "gn:country_code":"TH",
    "gn:dem":75,
    "gn:feature_class":"P",
    "gn:feature_code":"PPL",
    "gn:name":"Ban Khlong Krasue",
    "gn:population":0,
    "gn:timezone":"Asia/Bangkok",
    "iso:country":"TH",
    "name:tha_x_preferred":[
        "\u0e1a\u0e49\u0e32\u0e19\u0e04\u0e25\u0e2d\u0e07\u0e01\u0e23\u0e30\u0e2a\u0e37\u0e2d"
    ],
    "wof:name":"Ban Khlong Krasue",
    "wof:placetype":"locality"
},
  "geometry": {"coordinates":[102.10783000000001,12.88061],"type":"Point"}
}