{
  "type": "Feature",
  "properties": {
    "gn:admin1_code":"66.0",
    "gn:asciiname":"Ban Makok Nuea",
    "gn:country_code":"TH",
    "gn:dem":9,
    "gn:feature_class":"P",
    "gn:feature_code":"PPL",
    "gn:name":"Ban Makok Nuea",
    "gn:population":0,
    "gn:timezone":"Asia/Bangkok",
    "iso:country":"TH",
    "name:tha_x_preferred":[
        "\u0e1a\u0e49\u0e32\u0e19\u0e21\u0e30\u0e01\u0e2d\u0e01\u0e40\u0e2b\u0e19\u0e37\u0e2d"
    ],
    "name:und_x_variant":[
        "Makok Nua",
        "Ban Makok Nua",
        "Ban Makok Nuea"
    ],
    "wof:name":"Ban Makok Nuea",
    "wof:placetype":"locality"
},
  "geometry": {"coordinates":[100.08906,7.71731],"type":"Point"}
}