{
  "type": "Feature",
  "properties": {
    "gn:admin1_code":"6.0",
    "gn:asciiname":"Ban Santi Tham",
    "gn:country_code":"TH",
    "gn:dem":254,
    "gn:feature_class":"P",
    "gn:feature_code":"PPL",
    "gn:name":"Ban Santi Tham",
    "gn:population":0,
    "gn:timezone":"Asia/Bangkok",
    "iso:country":"TH",
    "name:tha_x_preferred":[
        "\u0e1a\u0e49\u0e32\u0e19\u0e2a\u0e31\u0e19\u0e15\u0e34\u0e18\u0e23\u0e23\u0e21"
    ],
    "wof:name":"Ban Santi Tham",
    "wof:placetype":"locality"
},
  "geometry": {"coordinates":[99.33775,18.26828],"type":"Point"}
}