{
  "type": "Feature",
  "properties": {
    "gn:admin1_code":"72.0",
    "gn:asciiname":"Ban Mak Mai",
    "gn:country_code":"TH",
    "gn:dem":129,
    "gn:feature_class":"P",
    "gn:feature_code":"PPL",
    "gn:name":"Ban Mak Mai",
    "gn:population":0,
    "gn:timezone":"Asia/Bangkok",
    "iso:country":"TH",
    "name:tha_x_preferred":[
        "\u0e1a\u0e49\u0e32\u0e19\u0e2b\u0e21\u0e32\u0e01\u0e21\u0e32\u0e22"
    ],
    "wof:name":"Ban Mak Mai",
    "wof:placetype":"locality"
},
  "geometry": {"coordinates":[104.35436,15.34872],"type":"Point"}
}