{
  "type": "Feature",
  "properties": {
    "gn:admin1_code":"76.0",
    "gn:asciiname":"Ban Om Ko",
    "gn:country_code":"TH",
    "gn:dem":169,
    "gn:feature_class":"P",
    "gn:feature_code":"PPL",
    "gn:name":"Ban Om Ko",
    "gn:population":0,
    "gn:timezone":"Asia/Bangkok",
    "iso:country":"TH",
    "name:tha_x_preferred":[
        "\u0e1a\u0e49\u0e32\u0e19\u0e2d\u0e49\u0e2d\u0e21\u0e01\u0e2d"
    ],
    "wof:name":"Ban Om Ko",
    "wof:placetype":"locality"
},
  "geometry": {"coordinates":[103.32124,17.59498],"type":"Point"}
}