{
  "type": "Feature",
  "properties": {
    "gn:admin1_code":"16.0",
    "gn:asciiname":"Ban Chong Kwang",
    "gn:country_code":"TH",
    "gn:dem":30,
    "gn:feature_class":"P",
    "gn:feature_code":"PPL",
    "gn:name":"Ban Chong Kwang",
    "gn:population":0,
    "gn:timezone":"Asia/Bangkok",
    "iso:country":"TH",
    "name:tha_x_preferred":[
        "\u0e1a\u0e49\u0e32\u0e19\u0e0a\u0e48\u0e2d\u0e07\u0e01\u0e27\u0e49\u0e32\u0e07"
    ],
    "wof:name":"Ban Chong Kwang",
    "wof:placetype":"locality"
},
  "geometry": {"coordinates":[100.04897,15.61386],"type":"Point"}
}