{
  "type": "Feature",
  "properties": {
    "gn:admin1_code":"58.0",
    "gn:asciiname":"Ban Doi Phatthana",
    "gn:country_code":"TH",
    "gn:dem":121,
    "gn:feature_class":"P",
    "gn:feature_code":"PPL",
    "gn:name":"Ban Doi Phatthana",
    "gn:population":0,
    "gn:timezone":"Asia/Bangkok",
    "iso:country":"TH",
    "name:tha_x_preferred":[
        "\u0e1a\u0e49\u0e32\u0e19\u0e14\u0e2d\u0e22\u0e1e\u0e31\u0e12\u0e19\u0e32"
    ],
    "wof:name":"Ban Doi Phatthana",
    "wof:placetype":"locality"
},
  "geometry": {"coordinates":[98.88956,10.09211],"type":"Point"}
}