{
  "type": "Feature",
  "properties": {
    "gn:admin1_code":"13.0",
    "gn:asciiname":"Ban Khok Sanan",
    "gn:country_code":"TH",
    "gn:dem":69,
    "gn:feature_class":"P",
    "gn:feature_code":"PPL",
    "gn:name":"Ban Khok Sanan",
    "gn:population":0,
    "gn:timezone":"Asia/Bangkok",
    "iso:country":"TH",
    "name:tha_x_preferred":[
        "\u0e1a\u0e49\u0e32\u0e19\u0e42\u0e04\u0e01\u0e2a\u0e19\u0e31\u0e48\u0e19"
    ],
    "wof:name":"Ban Khok Sanan",
    "wof:placetype":"locality"
},
  "geometry": {"coordinates":[100.71599999999999,16.02175],"type":"Point"}
}