{
  "type": "Feature",
  "properties": {
    "gn:admin1_code":"2.0",
    "gn:asciiname":"Ban Mae Yoi San Si",
    "gn:country_code":"TH",
    "gn:dem":306,
    "gn:feature_class":"P",
    "gn:feature_code":"PPL",
    "gn:name":"Ban Mae Yoi San Si",
    "gn:population":0,
    "gn:timezone":"Asia/Bangkok",
    "iso:country":"TH",
    "name:tha_x_preferred":[
        "\u0e1a\u0e49\u0e32\u0e19\u0e41\u0e21\u0e48\u0e22\u0e48\u0e2d\u0e22\u0e2a\u0e31\u0e19\u0e28\u0e23\u0e35"
    ],
    "wof:name":"Ban Mae Yoi San Si",
    "wof:placetype":"locality"
},
  "geometry": {"coordinates":[99.09583000000001,18.76022],"type":"Point"}
}