{
  "type": "Feature",
  "properties": {
    "gn:admin1_code":"25.0",
    "gn:asciiname":"Ban Khok Na Kham",
    "gn:country_code":"TH",
    "gn:dem":176,
    "gn:feature_class":"P",
    "gn:feature_code":"PPL",
    "gn:name":"Ban Khok Na Kham",
    "gn:population":0,
    "gn:timezone":"Asia/Bangkok",
    "iso:country":"TH",
    "name:tha_x_preferred":[
        "\u0e1a\u0e49\u0e32\u0e19\u0e42\u0e04\u0e01\u0e19\u0e32\u0e04\u0e33"
    ],
    "wof:name":"Ban Khok Na Kham",
    "wof:placetype":"locality"
},
  "geometry": {"coordinates":[104.14731,16.29628],"type":"Point"}
}