{
  "type": "Feature",
  "properties": {
    "gn:admin1_code":"11.0",
    "gn:asciiname":"Ban Tha Khun Ram",
    "gn:country_code":"TH",
    "gn:dem":87,
    "gn:feature_class":"P",
    "gn:feature_code":"PPL",
    "gn:name":"Ban Tha Khun Ram",
    "gn:population":0,
    "gn:timezone":"Asia/Bangkok",
    "iso:country":"TH",
    "name:tha_x_preferred":[
        "\u0e1a\u0e49\u0e32\u0e19\u0e17\u0e48\u0e32\u0e02\u0e38\u0e19\u0e23\u0e32\u0e21"
    ],
    "wof:name":"Ban Tha Khun Ram",
    "wof:placetype":"locality"
},
  "geometry": {"coordinates":[99.46558,16.4575],"type":"Point"}
}