{
  "type": "Feature",
  "properties": {
    "gn:admin1_code":"60.0",
    "gn:asciiname":"Ban U Traphao",
    "gn:country_code":"TH",
    "gn:dem":20,
    "gn:feature_class":"P",
    "gn:feature_code":"PPL",
    "gn:name":"Ban U Traphao",
    "gn:population":0,
    "gn:timezone":"Asia/Bangkok",
    "iso:country":"TH",
    "name:tha_x_preferred":[
        "\u0e1a\u0e49\u0e32\u0e19\u0e2d\u0e39\u0e48\u0e15\u0e23\u0e30\u0e40\u0e20\u0e32"
    ],
    "wof:name":"Ban U Traphao",
    "wof:placetype":"locality"
},
  "geometry": {"coordinates":[99.13211,9.51778],"type":"Point"}
}