{
  "type": "Feature",
  "properties": {
    "gn:admin1_code":"66.0",
    "gn:asciiname":"Ban Hua Sai",
    "gn:country_code":"TH",
    "gn:dem":3,
    "gn:feature_class":"P",
    "gn:feature_code":"PPL",
    "gn:name":"Ban Hua Sai",
    "gn:population":0,
    "gn:timezone":"Asia/Bangkok",
    "iso:country":"TH",
    "name:tha_x_preferred":[
        "\u0e1a\u0e49\u0e32\u0e19\u0e2b\u0e31\u0e27\u0e44\u0e17\u0e23"
    ],
    "wof:name":"Ban Hua Sai",
    "wof:placetype":"locality"
},
  "geometry": {"coordinates":[100.14239000000001,7.66561],"type":"Point"}
}