{
  "type": "Feature",
  "properties": {
    "gn:admin1_code":"40.0",
    "gn:admin2_code":"1034",
    "gn:asciiname":"Muban Uea-Watthanasuk",
    "gn:country_code":"TH",
    "gn:dem":6,
    "gn:feature_class":"P",
    "gn:feature_code":"PPL",
    "gn:name":"Muban Uea-Watthanasuk",
    "gn:population":0,
    "gn:timezone":"Asia/Bangkok",
    "iso:country":"TH",
    "name:tha_x_preferred":[
        "\u0e2b\u0e21\u0e39\u0e48\u0e1a\u0e49\u0e32\u0e19\u0e40\u0e2d\u0e37\u0e49\u0e2d\u0e27\u0e31\u0e12\u0e19\u0e32\u0e2a\u0e38\u0e02"
    ],
    "wof:lang_x_official":[
        "tha"
    ],
    "wof:lang_x_spoken":[
        "tha"
    ],
    "wof:name":"Muban Uea-Watthanasuk",
    "wof:placetype":"locality"
},
  "geometry": {"coordinates":[100.64894,13.72753],"type":"Point"}
}