{
  "type": "Feature",
  "properties": {
    "gn:admin1_code":"2.0",
    "gn:asciiname":"Ban Rai Sawang Arom",
    "gn:country_code":"TH",
    "gn:dem":310,
    "gn:feature_class":"P",
    "gn:feature_code":"PPL",
    "gn:name":"Ban Rai Sawang Arom",
    "gn:population":0,
    "gn:timezone":"Asia/Bangkok",
    "iso:country":"TH",
    "name:tha_x_preferred":[
        "\u0e1a\u0e49\u0e32\u0e19\u0e44\u0e23\u0e48\u0e2a\u0e27\u0e48\u0e32\u0e07\u0e2d\u0e32\u0e23\u0e21\u0e13\u0e4c"
    ],
    "wof:name":"Ban Rai Sawang Arom",
    "wof:placetype":"locality"
},
  "geometry": {"coordinates":[98.78022,18.49622],"type":"Point"}
}