{
  "type": "Feature",
  "properties": {
    "gn:admin1_code":"23.0",
    "gn:asciiname":"Ban Khok Si",
    "gn:country_code":"TH",
    "gn:dem":150,
    "gn:feature_class":"P",
    "gn:feature_code":"PPL",
    "gn:name":"Ban Khok Si",
    "gn:population":0,
    "gn:timezone":"Asia/Bangkok",
    "iso:country":"TH",
    "name:tha_x_preferred":[
        "\u0e1a\u0e49\u0e32\u0e19\u0e42\u0e04\u0e01\u0e2a\u0e35"
    ],
    "wof:name":"Ban Khok Si",
    "wof:placetype":"locality"
},
  "geometry": {"coordinates":[103.65107999999999,16.32444],"type":"Point"}
}