{
  "type": "Feature",
  "properties": {
    "gn:admin1_code":"27",
    "gn:asciiname":"Ban Mai Charoen Tham",
    "gn:country_code":"TH",
    "gn:dem":280,
    "gn:feature_class":"P",
    "gn:feature_code":"PPL",
    "gn:name":"Ban Mai Charoen Tham",
    "gn:population":0,
    "gn:timezone":"Asia/Bangkok",
    "iso:country":"TH",
    "name:tha_x_preferred":[
        "\u0e1a\u0e49\u0e32\u0e19\u0e43\u0e2b\u0e21\u0e48\u0e40\u0e08\u0e23\u0e34\u0e0d\u0e18\u0e23\u0e23\u0e21"
    ],
    "wof:name":"Ban Mai Charoen Tham",
    "wof:placetype":"locality"
},
  "geometry": {"coordinates":[101.51918999999999,15.24147],"type":"Point"}
}