{
  "type": "Feature",
  "properties": {
    "gn:admin1_code":"31.0",
    "gn:asciiname":"Ban Po I Long",
    "gn:country_code":"TH",
    "gn:dem":59,
    "gn:feature_class":"P",
    "gn:feature_code":"PPL",
    "gn:name":"Ban Po I Long",
    "gn:population":0,
    "gn:timezone":"Asia/Bangkok",
    "iso:country":"TH",
    "name:tha_x_preferred":[
        "\u0e1a\u0e49\u0e32\u0e19\u0e40\u0e1b\u0e32\u0e30\u0e2d\u0e35\u0e25\u0e07"
    ],
    "wof:name":"Ban Po I Long",
    "wof:placetype":"locality"
},
  "geometry": {"coordinates":[101.69311,6.09636],"type":"Point"}
}