{
  "type": "Feature",
  "properties": {
    "gn:admin1_code":"29",
    "gn:asciiname":"Ban Phon Suk",
    "gn:country_code":"TH",
    "gn:dem":192,
    "gn:feature_class":"P",
    "gn:feature_code":"PPL",
    "gn:name":"Ban Phon Suk",
    "gn:population":0,
    "gn:timezone":"Asia/Bangkok",
    "iso:country":"TH",
    "name:tha_x_preferred":[
        "\u0e1a\u0e49\u0e32\u0e19\u0e1e\u0e23\u0e2a\u0e38\u0e02"
    ],
    "wof:name":"Ban Phon Suk",
    "wof:placetype":"locality"
},
  "geometry": {"coordinates":[103.91864,14.54972],"type":"Point"}
}