{
  "type": "Feature",
  "properties": {
    "gn:admin1_code":"69.0",
    "gn:asciiname":"Ban Ku Bae Sa Mae",
    "gn:country_code":"TH",
    "gn:dem":9,
    "gn:feature_class":"P",
    "gn:feature_code":"PPL",
    "gn:name":"Ban Ku Bae Sa Mae",
    "gn:population":0,
    "gn:timezone":"Asia/Bangkok",
    "iso:country":"TH",
    "name:tha_x_preferred":[
        "\u0e1a\u0e49\u0e32\u0e19\u0e01\u0e39\u0e41\u0e1a\u0e0b\u0e32\u0e41\u0e21"
    ],
    "wof:name":"Ban Ku Bae Sa Mae",
    "wof:placetype":"locality"
},
  "geometry": {"coordinates":[101.42178,6.76194],"type":"Point"}
}