{
  "type": "Feature",
  "properties": {
    "gn:admin1_code":"2.0",
    "gn:asciiname":"Ban Sop Pha Luang",
    "gn:country_code":"TH",
    "gn:dem":978,
    "gn:feature_class":"P",
    "gn:feature_code":"PPL",
    "gn:name":"Ban Sop Pha Luang",
    "gn:population":0,
    "gn:timezone":"Asia/Bangkok",
    "iso:country":"TH",
    "name:tha_x_preferred":[
        "\u0e1a\u0e49\u0e32\u0e19\u0e2a\u0e1a\u0e1c\u0e32\u0e2b\u0e25\u0e27\u0e07"
    ],
    "name:und_x_variant":[
        "Ban Pha Luang"
    ],
    "wof:name":"Ban Sop Pha Luang",
    "wof:placetype":"locality"
},
  "geometry": {"coordinates":[98.45695000000001,18.87831],"type":"Point"}
}