{
  "type": "Feature",
  "properties": {
    "gn:admin1_code":"58.0",
    "gn:asciiname":"Ban Na Tham",
    "gn:country_code":"TH",
    "gn:dem":27,
    "gn:feature_class":"P",
    "gn:feature_code":"PPL",
    "gn:name":"Ban Na Tham",
    "gn:population":0,
    "gn:timezone":"Asia/Bangkok",
    "iso:country":"TH",
    "name:tha_x_preferred":[
        "\u0e1a\u0e49\u0e32\u0e19\u0e2b\u0e19\u0e49\u0e32\u0e16\u0e49\u0e33"
    ],
    "name:und_x_variant":[
        "N\u0101mtham",
        "Ban Na Tham"
    ],
    "wof:name":"Ban Na Tham",
    "wof:placetype":"locality"
},
  "geometry": {"coordinates":[99.16803,10.26214],"type":"Point"}
}