{
  "type": "Feature",
  "properties": {
    "gn:admin1_code":"12.0",
    "gn:asciiname":"Ban Tha Pho",
    "gn:country_code":"TH",
    "gn:dem":44,
    "gn:feature_class":"P",
    "gn:feature_code":"PPL",
    "gn:name":"Ban Tha Pho",
    "gn:population":0,
    "gn:timezone":"Asia/Bangkok",
    "iso:country":"TH",
    "name:tha_x_preferred":[
        "\u0e1a\u0e49\u0e32\u0e19\u0e17\u0e48\u0e32\u0e42\u0e1e\u0e18\u0e34\u0e4c"
    ],
    "name:und_x_variant":[
        "Ban Phraya La",
        "Ban Tha Pho (1)",
        "Ban Tha Pho"
    ],
    "wof:name":"Ban Tha Pho",
    "wof:placetype":"locality"
},
  "geometry": {"coordinates":[100.20186,16.75825],"type":"Point"}
}