{
  "type": "Feature",
  "properties": {
    "gn:admin1_code":"63.0",
    "gn:asciiname":"Ban Li Ki",
    "gn:country_code":"TH",
    "gn:dem":20,
    "gn:feature_class":"P",
    "gn:feature_code":"PPL",
    "gn:name":"Ban Li Ki",
    "gn:population":0,
    "gn:timezone":"Asia/Bangkok",
    "iso:country":"TH",
    "name:tha_x_preferred":[
        "\u0e1a\u0e49\u0e32\u0e19\u0e25\u0e34\u0e01\u0e35"
    ],
    "wof:name":"Ban Li Ki",
    "wof:placetype":"locality"
},
  "geometry": {"coordinates":[99.06983,7.7395],"type":"Point"}
}