{
  "type": "Feature",
  "properties": {
    "gn:admin1_code":"38.0",
    "gn:asciiname":"Ban Son Loi",
    "gn:cc2":"TH",
    "gn:country_code":"TH",
    "gn:dem":6,
    "gn:feature_class":"P",
    "gn:feature_code":"PPL",
    "gn:name":"Ban Son Loi",
    "gn:population":0,
    "gn:timezone":"Asia/Bangkok",
    "iso:country":"TH",
    "name:tha_x_preferred":[
        "\u0e1a\u0e49\u0e32\u0e19\u0e42\u0e2a\u0e19\u0e25\u0e2d\u0e22"
    ],
    "name:und_x_variant":[
        "Sano Loi",
        "Ban Son Loi"
    ],
    "wof:name":"Ban Son Loi",
    "wof:placetype":"locality"
},
  "geometry": {"coordinates":[100.3695,13.93036],"type":"Point"}
}