{
  "type": "Feature",
  "properties": {
    "gn:admin1_code":"3.0",
    "gn:asciiname":"Ban Ko Chatsan",
    "gn:country_code":"TH",
    "gn:dem":466,
    "gn:feature_class":"P",
    "gn:feature_code":"PPL",
    "gn:name":"Ban Ko Chatsan",
    "gn:population":0,
    "gn:timezone":"Asia/Bangkok",
    "iso:country":"TH",
    "name:tha_x_preferred":[
        "\u0e1a\u0e49\u0e32\u0e19\u0e01\u0e49\u0e2d\u0e08\u0e31\u0e14\u0e2a\u0e23\u0e23"
    ],
    "wof:name":"Ban Ko Chatsan",
    "wof:placetype":"locality"
},
  "geometry": {"coordinates":[99.63433000000001,19.71497],"type":"Point"}
}