{
  "type": "Feature",
  "properties": {
    "gn:admin1_code":"75.0",
    "gn:asciiname":"Ban Non Bok",
    "gn:country_code":"TH",
    "gn:dem":190,
    "gn:feature_class":"P",
    "gn:feature_code":"PPL",
    "gn:name":"Ban Non Bok",
    "gn:population":0,
    "gn:timezone":"Asia/Bangkok",
    "iso:country":"TH",
    "name:tha_x_preferred":[
        "\u0e1a\u0e49\u0e32\u0e19\u0e42\u0e19\u0e19\u0e1a\u0e01"
    ],
    "wof:name":"Ban Non Bok",
    "wof:placetype":"locality"
},
  "geometry": {"coordinates":[104.97681,14.52689],"type":"Point"}
}