{
  "type": "Feature",
  "properties": {
    "gn:admin1_code":"22",
    "gn:asciiname":"Ban Non Tun",
    "gn:country_code":"TH",
    "gn:dem":196,
    "gn:feature_class":"P",
    "gn:feature_code":"PPL",
    "gn:name":"Ban Non Tun",
    "gn:population":0,
    "gn:timezone":"Asia/Bangkok",
    "iso:country":"TH",
    "name:tha_x_preferred":[
        "\u0e1a\u0e49\u0e32\u0e19\u0e42\u0e19\u0e19\u0e15\u0e38\u0e48\u0e19"
    ],
    "wof:name":"Ban Non Tun",
    "wof:placetype":"locality"
},
  "geometry": {"coordinates":[102.59256000000001,16.37961],"type":"Point"}
}