{
  "type": "Feature",
  "properties": {
    "gn:admin1_code":"25.0",
    "gn:asciiname":"Ban Na Di",
    "gn:country_code":"TH",
    "gn:dem":146,
    "gn:feature_class":"P",
    "gn:feature_code":"PPL",
    "gn:name":"Ban Na Di",
    "gn:population":0,
    "gn:timezone":"Asia/Bangkok",
    "iso:country":"TH",
    "name:tha_x_preferred":[
        "\u0e1a\u0e49\u0e32\u0e19\u0e19\u0e32\u0e14\u0e35"
    ],
    "wof:name":"Ban Na Di",
    "wof:placetype":"locality"
},
  "geometry": {"coordinates":[103.56892000000001,16.16572],"type":"Point"}
}