{
  "type": "Feature",
  "properties": {
    "gn:admin1_code":"70.0",
    "gn:asciiname":"Ban Ba Ngo Sa To",
    "gn:country_code":"TH",
    "gn:dem":261,
    "gn:feature_class":"P",
    "gn:feature_code":"PPL",
    "gn:name":"Ban Ba Ngo Sa To",
    "gn:population":0,
    "gn:timezone":"Asia/Bangkok",
    "iso:country":"TH",
    "name:tha_x_preferred":[
        "\u0e1a\u0e49\u0e32\u0e19\u0e1a\u0e32\u0e42\u0e07\u0e2a\u0e42\u0e15"
    ],
    "wof:name":"Ban Ba Ngo Sa To",
    "wof:placetype":"locality"
},
  "geometry": {"coordinates":[101.08636,5.77811],"type":"Point"}
}