{
  "type": "Feature",
  "properties": {
    "gn:admin1_code":"75.0",
    "gn:asciiname":"Ban Nong Khai Nok",
    "gn:country_code":"TH",
    "gn:dem":127,
    "gn:feature_class":"P",
    "gn:feature_code":"PPL",
    "gn:name":"Ban Nong Khai Nok",
    "gn:population":0,
    "gn:timezone":"Asia/Bangkok",
    "iso:country":"TH",
    "name:tha_x_preferred":[
        "\u0e1a\u0e49\u0e32\u0e19\u0e2b\u0e19\u0e2d\u0e07\u0e44\u0e02\u0e48\u0e19\u0e01"
    ],
    "name:und_x_variant":[
        "Ban Non Khok",
        "Ban Nong Khai Nok"
    ],
    "wof:name":"Ban Nong Khai Nok",
    "wof:placetype":"locality"
},
  "geometry": {"coordinates":[104.94602999999999,15.12272],"type":"Point"}
}