{
  "type": "Feature",
  "properties": {
    "gn:admin1_code":"52.0",
    "gn:asciiname":"Ban Nong Klin",
    "gn:country_code":"TH",
    "gn:dem":55,
    "gn:feature_class":"P",
    "gn:feature_code":"PPL",
    "gn:name":"Ban Nong Klin",
    "gn:population":0,
    "gn:timezone":"Asia/Bangkok",
    "iso:country":"TH",
    "name:tha_x_preferred":[
        "\u0e1a\u0e49\u0e32\u0e19\u0e2b\u0e19\u0e2d\u0e07\u0e01\u0e25\u0e34\u0e48\u0e19"
    ],
    "wof:name":"Ban Nong Klin",
    "wof:placetype":"locality"
},
  "geometry": {"coordinates":[99.61844000000001,13.79797],"type":"Point"}
}