{
  "type": "Feature",
  "properties": {
    "gn:admin1_code":"30.0",
    "gn:asciiname":"Ban Nong Phanaeng",
    "gn:country_code":"TH",
    "gn:dem":138,
    "gn:feature_class":"P",
    "gn:feature_code":"PPL",
    "gn:name":"Ban Nong Phanaeng",
    "gn:population":0,
    "gn:timezone":"Asia/Bangkok",
    "iso:country":"TH",
    "name:und_x_variant":[
        "\u0e1a\u0e49\u0e32\u0e19\u0e2b\u0e19\u0e2d\u0e07\u0e1e\u0e30\u0e41\u0e19\u0e07",
        "Ban Phanaeng"
    ],
    "wof:name":"Ban Nong Phanaeng",
    "wof:placetype":"locality"
},
  "geometry": {"coordinates":[104.45458000000001,14.87711],"type":"Point"}
}