{
  "type": "Feature",
  "properties": {
    "gn:admin1_code":"65.0",
    "gn:asciiname":"Ban Yang Kha Khim",
    "gn:country_code":"TH",
    "gn:dem":23,
    "gn:feature_class":"P",
    "gn:feature_code":"PPL",
    "gn:name":"Ban Yang Kha Khim",
    "gn:population":0,
    "gn:timezone":"Asia/Bangkok",
    "iso:country":"TH",
    "name:tha_x_preferred":[
        "\u0e1a\u0e49\u0e32\u0e19\u0e22\u0e32\u0e07\u0e02\u0e32\u0e04\u0e35\u0e21"
    ],
    "wof:name":"Ban Yang Kha Khim",
    "wof:placetype":"locality"
},
  "geometry": {"coordinates":[99.57125000000001,7.67672],"type":"Point"}
}