{
  "type": "Feature",
  "properties": {
    "gn:admin1_code":"16.0",
    "gn:asciiname":"Ban Huai Ruam Klang",
    "gn:country_code":"TH",
    "gn:dem":39,
    "gn:feature_class":"P",
    "gn:feature_code":"PPL",
    "gn:name":"Ban Huai Ruam Klang",
    "gn:population":0,
    "gn:timezone":"Asia/Bangkok",
    "iso:country":"TH",
    "name:tha_x_preferred":[
        "\u0e1a\u0e49\u0e32\u0e19\u0e2b\u0e49\u0e27\u0e22\u0e23\u0e48\u0e27\u0e21\u0e01\u0e25\u0e32\u0e07"
    ],
    "name:und_x_variant":[
        "Ban Huai Ruam"
    ],
    "wof:lang_x_official":[
        "tha"
    ],
    "wof:lang_x_spoken":[
        "tha"
    ],
    "wof:name":"Ban Huai Ruam Klang",
    "wof:placetype":"locality"
},
  "geometry": {"coordinates":[100.52003000000001,15.93286],"type":"Point"}
}