{
  "type": "Feature",
  "properties": {
    "gn:admin1_code":"13.0",
    "gn:asciiname":"Ban Paet Lang",
    "gn:country_code":"TH",
    "gn:dem":56,
    "gn:feature_class":"P",
    "gn:feature_code":"PPL",
    "gn:name":"Ban Paet Lang",
    "gn:population":0,
    "gn:timezone":"Asia/Bangkok",
    "iso:country":"TH",
    "name:tha_x_preferred":[
        "\u0e1a\u0e49\u0e32\u0e19\u0e41\u0e1b\u0e14\u0e2b\u0e25\u0e31\u0e07"
    ],
    "wof:name":"Ban Paet Lang",
    "wof:placetype":"locality"
},
  "geometry": {"coordinates":[100.57181,16.33917000000001],"type":"Point"}
}