{
  "type": "Feature",
  "properties": {
    "gn:admin1_code":"16.0",
    "gn:asciiname":"Ban Khao Ka",
    "gn:country_code":"TH",
    "gn:dem":70,
    "gn:feature_class":"P",
    "gn:feature_code":"PPL",
    "gn:name":"Ban Khao Ka",
    "gn:population":0,
    "gn:timezone":"Asia/Bangkok",
    "iso:country":"TH",
    "name:tha_x_preferred":[
        "\u0e1a\u0e49\u0e32\u0e19\u0e40\u0e02\u0e32\u0e01\u0e32"
    ],
    "wof:name":"Ban Khao Ka",
    "wof:placetype":"locality"
},
  "geometry": {"coordinates":[100.50336,15.31567],"type":"Point"}
}