{
  "type": "Feature",
  "properties": {
    "gn:admin1_code":"31.0",
    "gn:asciiname":"Ban Yue Li Tao",
    "gn:country_code":"TH",
    "gn:dem":22,
    "gn:feature_class":"P",
    "gn:feature_code":"PPL",
    "gn:name":"Ban Yue Li Tao",
    "gn:population":0,
    "gn:timezone":"Asia/Bangkok",
    "iso:country":"TH",
    "name:tha_x_preferred":[
        "\u0e1a\u0e49\u0e32\u0e19\u0e22\u0e37\u0e2d\u0e25\u0e35\u0e40\u0e15\u0e49\u0e32"
    ],
    "wof:name":"Ban Yue Li Tao",
    "wof:placetype":"locality"
},
  "geometry": {"coordinates":[101.92700000000001,5.94786],"type":"Point"}
}