{
  "type": "Feature",
  "properties": {
    "gn:admin1_code":"2.0",
    "gn:asciiname":"Ban Wang Phai",
    "gn:country_code":"TH",
    "gn:dem":464,
    "gn:feature_class":"P",
    "gn:feature_code":"PPL",
    "gn:name":"Ban Wang Phai",
    "gn:population":0,
    "gn:timezone":"Asia/Bangkok",
    "iso:country":"TH",
    "name:tha_x_preferred":[
        "\u0e1a\u0e49\u0e32\u0e19\u0e27\u0e31\u0e07\u0e44\u0e1c\u0e48"
    ],
    "wof:name":"Ban Wang Phai",
    "wof:placetype":"locality"
},
  "geometry": {"coordinates":[99.48386000000001,20.04108],"type":"Point"}
}