{
  "type": "Feature",
  "properties": {
    "gn:admin1_code":"47.0",
    "gn:asciiname":"Ban Ko Mo Sip Song",
    "gn:country_code":"TH",
    "gn:dem":90,
    "gn:feature_class":"P",
    "gn:feature_code":"PPL",
    "gn:name":"Ban Ko Mo Sip Song",
    "gn:population":0,
    "gn:timezone":"Asia/Bangkok",
    "iso:country":"TH",
    "name:tha_x_preferred":[
        "\u0e1a\u0e49\u0e32\u0e19 \u0e01\u0e21. \u0e2a\u0e34\u0e1a\u0e2a\u0e2d\u0e07"
    ],
    "wof:lang_x_official":[
        "tha"
    ],
    "wof:lang_x_spoken":[
        "tha"
    ],
    "wof:name":"Ban Ko Mo Sip Song",
    "wof:placetype":"locality"
},
  "geometry": {"coordinates":[101.2075,12.83639],"type":"Point"}
}