{
  "type": "Feature",
  "properties": {
    "gn:admin1_code":"69.0",
    "gn:asciiname":"Ban Cha Ro",
    "gn:country_code":"TH",
    "gn:dem":32,
    "gn:feature_class":"P",
    "gn:feature_code":"PPL",
    "gn:name":"Ban Cha Ro",
    "gn:population":0,
    "gn:timezone":"Asia/Bangkok",
    "iso:country":"TH",
    "name:tha_x_preferred":[
        "\u0e1a\u0e49\u0e32\u0e19\u0e08\u0e32\u0e40\u0e23\u0e32\u0e30"
    ],
    "wof:name":"Ban Cha Ro",
    "wof:placetype":"locality"
},
  "geometry": {"coordinates":[101.18483000000001,6.62139],"type":"Point"}
}