{
  "type": "Feature",
  "properties": {
    "gn:admin1_code":"31.0",
    "gn:asciiname":"Ban Bae Rae",
    "gn:country_code":"TH",
    "gn:dem":31,
    "gn:feature_class":"P",
    "gn:feature_code":"PPL",
    "gn:name":"Ban Bae Rae",
    "gn:population":0,
    "gn:timezone":"Asia/Bangkok",
    "iso:country":"TH",
    "name:tha_x_preferred":[
        "\u0e1a\u0e49\u0e32\u0e19\u0e41\u0e1a\u0e41\u0e23"
    ],
    "name:und_x_variant":[
        "Kampong Bele",
        "Kampong Baelae",
        "Ban Bae Rae"
    ],
    "wof:name":"Ban Bae Rae",
    "wof:placetype":"locality"
},
  "geometry": {"coordinates":[101.75785999999999,6.22253],"type":"Point"}
}