{
  "type": "Feature",
  "properties": {
    "gn:admin1_code":"28",
    "gn:asciiname":"Ban Khi Lek",
    "gn:country_code":"TH",
    "gn:dem":132,
    "gn:feature_class":"P",
    "gn:feature_code":"PPL",
    "gn:name":"Ban Khi Lek",
    "gn:population":0,
    "gn:timezone":"Asia/Bangkok",
    "iso:country":"TH",
    "name:tha_x_preferred":[
        "\u0e1a\u0e49\u0e32\u0e19\u0e02\u0e35\u0e49\u0e40\u0e2b\u0e25\u0e47\u0e01"
    ],
    "wof:lang_x_official":[
        "tha"
    ],
    "wof:lang_x_spoken":[
        "tha"
    ],
    "wof:name":"Ban Khi Lek",
    "wof:placetype":"locality"
},
  "geometry": {"coordinates":[103.44293999999999,15.27283],"type":"Point"}
}