{
  "type": "Feature",
  "properties": {
    "gn:admin1_code":"73.0",
    "gn:asciiname":"Ban Bung Hi",
    "gn:country_code":"TH",
    "gn:dem":148,
    "gn:feature_class":"P",
    "gn:feature_code":"PPL",
    "gn:name":"Ban Bung Hi",
    "gn:population":0,
    "gn:timezone":"Asia/Bangkok",
    "iso:country":"TH",
    "name:tha_x_preferred":[
        "Ban Bung Hi"
    ],
    "name:tha_x_variant":[
        "\u0e1a\u0e49\u0e32\u0e19\u0e1a\u0e38\u0e48\u0e07\u0e2e\u0e35"
    ],
    "name:und_x_variant":[
        "Ban Bung"
    ],
    "wof:name":"Ban Bung Hi",
    "wof:placetype":"locality"
},
  "geometry": {"coordinates":[104.72345,16.99193],"type":"Point"}
}