{
  "type": "Feature",
  "properties": {
    "gn:admin1_code":"16.0",
    "gn:asciiname":"Ban Kut Ta Man",
    "gn:country_code":"TH",
    "gn:dem":78,
    "gn:feature_class":"P",
    "gn:feature_code":"PPL",
    "gn:name":"Ban Kut Ta Man",
    "gn:population":0,
    "gn:timezone":"Asia/Bangkok",
    "iso:country":"TH",
    "name:tha_x_preferred":[
        "\u0e1a\u0e49\u0e32\u0e19\u0e01\u0e38\u0e0e\u0e15\u0e32\u0e21\u0e31\u0e48\u0e19"
    ],
    "wof:name":"Ban Kut Ta Man",
    "wof:placetype":"locality"
},
  "geometry": {"coordinates":[100.74102999999999,15.78389],"type":"Point"}
}