{
  "type": "Feature",
  "properties": {
    "gn:admin1_code":"12.0",
    "gn:asciiname":"Ban Khui Yang",
    "gn:country_code":"TH",
    "gn:dem":50,
    "gn:feature_class":"P",
    "gn:feature_code":"PPL",
    "gn:name":"Ban Khui Yang",
    "gn:population":0,
    "gn:timezone":"Asia/Bangkok",
    "iso:country":"TH",
    "name:tha_x_preferred":[
        "\u0e1a\u0e49\u0e32\u0e19\u0e04\u0e38\u0e22\u0e22\u0e32\u0e07"
    ],
    "wof:name":"Ban Khui Yang",
    "wof:placetype":"locality"
},
  "geometry": {"coordinates":[100.06100000000001,16.73552999999999],"type":"Point"}
}