{
  "type": "Feature",
  "properties": {
    "gn:admin1_code":"4.0",
    "gn:asciiname":"Ban Huai Kham",
    "gn:country_code":"TH",
    "gn:dem":221,
    "gn:feature_class":"P",
    "gn:feature_code":"PPL",
    "gn:name":"Ban Huai Kham",
    "gn:population":0,
    "gn:timezone":"Asia/Bangkok",
    "iso:country":"TH",
    "name:tha_x_preferred":[
        "\u0e1a\u0e49\u0e32\u0e19\u0e2b\u0e49\u0e27\u0e22\u0e02\u0e32\u0e21"
    ],
    "wof:name":"Ban Huai Kham",
    "wof:placetype":"locality"
},
  "geometry": {"coordinates":[100.90156,18.29164],"type":"Point"}
}