{
  "type": "Feature",
  "properties": {
    "gn:admin1_code":"1.0",
    "gn:asciiname":"Ban Mae Hat",
    "gn:country_code":"TH",
    "gn:dem":821,
    "gn:feature_class":"P",
    "gn:feature_code":"PPL",
    "gn:name":"Ban Mae Hat",
    "gn:population":0,
    "gn:timezone":"Asia/Bangkok",
    "iso:country":"TH",
    "name:tha_x_preferred":[
        "\u0e1a\u0e49\u0e32\u0e19\u0e41\u0e21\u0e48\u0e2b\u0e32\u0e14"
    ],
    "wof:name":"Ban Mae Hat",
    "wof:placetype":"locality"
},
  "geometry": {"coordinates":[98.03306000000001,18.79208],"type":"Point"}
}