{
  "type": "Feature",
  "properties": {
    "gn:admin1_code":"25",
    "gn:asciiname":"Ban Chang Phueak",
    "gn:country_code":"TH",
    "gn:dem":140,
    "gn:feature_class":"P",
    "gn:feature_code":"PPL",
    "gn:name":"Ban Chang Phueak",
    "gn:population":0,
    "gn:timezone":"Asia/Bangkok",
    "iso:country":"TH",
    "name:tha_x_preferred":[
        "\u0e1a\u0e49\u0e32\u0e19\u0e0a\u0e49\u0e32\u0e07\u0e40\u0e1c\u0e37\u0e2d\u0e01"
    ],
    "wof:name":"Ban Chang Phueak",
    "wof:placetype":"locality"
},
  "geometry": {"coordinates":[103.95493999999999,15.66631],"type":"Point"}
}