{
  "type": "Feature",
  "properties": {
    "gn:admin1_code":"5.0",
    "gn:asciiname":"Ban Mae Khanat",
    "gn:country_code":"TH",
    "gn:dem":357,
    "gn:feature_class":"P",
    "gn:feature_code":"PPL",
    "gn:name":"Ban Mae Khanat",
    "gn:population":0,
    "gn:timezone":"Asia/Bangkok",
    "iso:country":"TH",
    "name:tha_x_preferred":[
        "\u0e1a\u0e49\u0e32\u0e19\u0e41\u0e21\u0e48\u0e02\u0e30\u0e19\u0e32\u0e14"
    ],
    "wof:name":"Ban Mae Khanat",
    "wof:placetype":"locality"
},
  "geometry": {"coordinates":[98.99621999999999,18.39419],"type":"Point"}
}