{
  "type": "Feature",
  "properties": {
    "gn:admin1_code":"5.0",
    "gn:asciiname":"Ban San Pa Sak",
    "gn:country_code":"TH",
    "gn:dem":304,
    "gn:feature_class":"P",
    "gn:feature_code":"PPL",
    "gn:name":"Ban San Pa Sak",
    "gn:population":0,
    "gn:timezone":"Asia/Bangkok",
    "iso:country":"TH",
    "name:tha_x_preferred":[
        "\u0e1a\u0e49\u0e32\u0e19\u0e2a\u0e31\u0e19\u0e1b\u0e48\u0e32\u0e2a\u0e31\u0e01"
    ],
    "wof:name":"Ban San Pa Sak",
    "wof:placetype":"locality"
},
  "geometry": {"coordinates":[99.036,18.53792],"type":"Point"}
}