{
  "type": "Feature",
  "properties": {
    "gn:admin1_code":"25",
    "gn:asciiname":"Ban Ta Suea",
    "gn:country_code":"TH",
    "gn:dem":132,
    "gn:feature_class":"P",
    "gn:feature_code":"PPL",
    "gn:name":"Ban Ta Suea",
    "gn:population":0,
    "gn:timezone":"Asia/Bangkok",
    "iso:country":"TH",
    "name:tha_x_preferred":[
        "\u0e1a\u0e49\u0e32\u0e19\u0e15\u0e32\u0e40\u0e2a\u0e37\u0e2d"
    ],
    "wof:name":"Ban Ta Suea",
    "wof:placetype":"locality"
},
  "geometry": {"coordinates":[103.70538999999999,15.44172],"type":"Point"}
}