{
  "type": "Feature",
  "properties": {
    "gn:admin1_code":"74.0",
    "gn:asciiname":"Ban Tha Sala",
    "gn:country_code":"TH",
    "gn:dem":21,
    "gn:feature_class":"P",
    "gn:feature_code":"PPL",
    "gn:name":"Ban Tha Sala",
    "gn:population":0,
    "gn:timezone":"Asia/Bangkok",
    "iso:country":"TH",
    "name:tha_x_preferred":[
        "\u0e1a\u0e49\u0e32\u0e19\u0e17\u0e48\u0e32\u0e28\u0e32\u0e25\u0e32"
    ],
    "wof:name":"Ban Tha Sala",
    "wof:placetype":"locality"
},
  "geometry": {"coordinates":[101.34508,14.19081],"type":"Point"}
}