{
  "type": "Feature",
  "properties": {
    "gn:admin1_code":"12.0",
    "gn:asciiname":"Ban Plak Ta Mi",
    "gn:country_code":"TH",
    "gn:dem":56,
    "gn:feature_class":"P",
    "gn:feature_code":"PPL",
    "gn:name":"Ban Plak Ta Mi",
    "gn:population":0,
    "gn:timezone":"Asia/Bangkok",
    "iso:country":"TH",
    "name:tha_x_preferred":[
        "\u0e1a\u0e49\u0e32\u0e19\u0e1b\u0e25\u0e31\u0e01\u0e15\u0e32\u0e21\u0e35"
    ],
    "wof:name":"Ban Plak Ta Mi",
    "wof:placetype":"locality"
},
  "geometry": {"coordinates":[100.36866999999999,16.99672],"type":"Point"}
}