{
  "type": "Feature",
  "properties": {
    "gn:admin1_code":"50.0",
    "gn:asciiname":"Ban Tham Krasae",
    "gn:country_code":"TH",
    "gn:dem":57,
    "gn:feature_class":"P",
    "gn:feature_code":"PPL",
    "gn:name":"Ban Tham Krasae",
    "gn:population":0,
    "gn:timezone":"Asia/Bangkok",
    "iso:country":"TH",
    "name:tha_x_preferred":[
        "\u0e1a\u0e49\u0e32\u0e19\u0e16\u0e49\u0e33\u0e01\u0e23\u0e30\u0e41\u0e0b\u0e30"
    ],
    "wof:name":"Ban Tham Krasae",
    "wof:placetype":"locality"
},
  "geometry": {"coordinates":[99.15658000000001,14.10731],"type":"Point"}
}