{
  "type": "Feature",
  "properties": {
    "gn:admin1_code":"77.0",
    "gn:asciiname":"Ban Nong Masaeo",
    "gn:country_code":"TH",
    "gn:dem":153,
    "gn:feature_class":"P",
    "gn:feature_code":"PPL",
    "gn:name":"Ban Nong Masaeo",
    "gn:population":0,
    "gn:timezone":"Asia/Bangkok",
    "iso:country":"TH",
    "name:tha_x_preferred":[
        "Ban Nong Masaeo"
    ],
    "name:tha_x_variant":[
        "\u0e1a\u0e49\u0e32\u0e19\u0e2b\u0e19\u0e2d\u0e07\u0e21\u0e30\u0e41\u0e0b\u0e27"
    ],
    "wof:name":"Ban Nong Masaeo",
    "wof:placetype":"locality"
},
  "geometry": {"coordinates":[104.71622000000001,15.80783],"type":"Point"}
}