{
  "type": "Feature",
  "properties": {
    "gn:admin1_code":"70.0",
    "gn:asciiname":"Ban Ban Nang Lu Wa",
    "gn:country_code":"TH",
    "gn:dem":27,
    "gn:feature_class":"P",
    "gn:feature_code":"PPL",
    "gn:name":"Ban Ban Nang Lu Wa",
    "gn:population":0,
    "gn:timezone":"Asia/Bangkok",
    "iso:country":"TH",
    "name:tha_x_preferred":[
        "\u0e1a\u0e49\u0e32\u0e19\u0e1a\u0e31\u0e19\u0e19\u0e31\u0e07\u0e25\u0e39\u0e27\u0e32"
    ],
    "wof:name":"Ban Ban Nang Lu Wa",
    "wof:placetype":"locality"
},
  "geometry": {"coordinates":[101.22483,6.52311],"type":"Point"}
}