{
  "type": "Feature",
  "properties": {
    "gn:admin1_code":"8.0",
    "gn:asciiname":"Ban Mai Ngam",
    "gn:country_code":"TH",
    "gn:dem":118,
    "gn:feature_class":"P",
    "gn:feature_code":"PPL",
    "gn:name":"Ban Mai Ngam",
    "gn:population":0,
    "gn:timezone":"Asia/Bangkok",
    "iso:country":"TH",
    "name:tha_x_preferred":[
        "Ban Mai Ngam"
    ],
    "name:tha_x_variant":[
        "\u0e1a\u0e49\u0e32\u0e19\u0e44\u0e21\u0e49\u0e07\u0e32\u0e21"
    ],
    "wof:name":"Ban Mai Ngam",
    "wof:placetype":"locality"
},
  "geometry": {"coordinates":[99.08453,16.92083],"type":"Point"}
}