{
  "type": "Feature",
  "properties": {
    "gn:admin1_code":"7.0",
    "gn:asciiname":"Ban Ko Pao",
    "gn:country_code":"TH",
    "gn:dem":168,
    "gn:feature_class":"P",
    "gn:feature_code":"PPL",
    "gn:name":"Ban Ko Pao",
    "gn:population":0,
    "gn:timezone":"Asia/Bangkok",
    "iso:country":"TH",
    "name:tha_x_preferred":[
        "\u0e1a\u0e49\u0e32\u0e19\u0e01\u0e2d\u0e40\u0e1b\u0e32"
    ],
    "wof:name":"Ban Ko Pao",
    "wof:placetype":"locality"
},
  "geometry": {"coordinates":[100.18097,18.17908],"type":"Point"}
}