{
  "type": "Feature",
  "properties": {
    "gn:admin1_code":"15.0",
    "gn:asciiname":"Ban Sa Thale",
    "gn:country_code":"TH",
    "gn:dem":100,
    "gn:feature_class":"P",
    "gn:feature_code":"PPL",
    "gn:name":"Ban Sa Thale",
    "gn:population":0,
    "gn:timezone":"Asia/Bangkok",
    "iso:country":"TH",
    "name:tha_x_preferred":[
        "\u0e1a\u0e49\u0e32\u0e19\u0e2a\u0e23\u0e30\u0e17\u0e30\u0e40\u0e25"
    ],
    "wof:name":"Ban Sa Thale",
    "wof:placetype":"locality"
},
  "geometry": {"coordinates":[99.68358000000001,15.55111],"type":"Point"}
}