{
  "type": "Feature",
  "properties": {
    "gn:admin1_code":"42.0",
    "gn:asciiname":"Ban Khlong Ton Sai",
    "gn:country_code":"TH",
    "gn:dem":4,
    "gn:feature_class":"P",
    "gn:feature_code":"PPL",
    "gn:name":"Ban Khlong Ton Sai",
    "gn:population":0,
    "gn:timezone":"Asia/Bangkok",
    "iso:country":"TH",
    "name:tha_x_preferred":[
        "\u0e1a\u0e49\u0e32\u0e19\u0e04\u0e25\u0e2d\u0e07\u0e15\u0e49\u0e19\u0e44\u0e17\u0e23"
    ],
    "wof:name":"Ban Khlong Ton Sai",
    "wof:placetype":"locality"
},
  "geometry": {"coordinates":[100.80553,13.66217],"type":"Point"}
}