{
  "type": "Feature",
  "properties": {
    "gn:admin1_code":"67.0",
    "gn:asciiname":"Ban Phang 51",
    "gn:country_code":"TH",
    "gn:dem":33,
    "gn:feature_class":"P",
    "gn:feature_code":"PPL",
    "gn:name":"Ban Phang 51",
    "gn:population":0,
    "gn:timezone":"Asia/Bangkok",
    "iso:country":"TH",
    "name:tha_x_preferred":[
        "Ban Phang 51"
    ],
    "name:tha_x_variant":[
        "\u0e1a\u0e49\u0e32\u0e19\u0e1c\u0e31\u0e07 \u0e2b\u0e49\u0e32\u0e2a\u0e34\u0e1a\u0e40\u0e2d\u0e47\u0e14",
        "Ban Phang Ha Sip Et"
    ],
    "wof:lang_x_official":[
        "tha"
    ],
    "wof:lang_x_spoken":[
        "tha"
    ],
    "wof:name":"Ban Phang 51",
    "wof:placetype":"locality"
},
  "geometry": {"coordinates":[99.88500000000001,6.9445],"type":"Point"}
}