{
  "type": "Feature",
  "properties": {
    "gn:admin1_code":"49.0",
    "gn:asciiname":"Ban Samoe Rat",
    "gn:country_code":"TH",
    "gn:dem":2,
    "gn:feature_class":"P",
    "gn:feature_code":"PPL",
    "gn:name":"Ban Samoe Rat",
    "gn:population":0,
    "gn:timezone":"Asia/Bangkok",
    "iso:country":"TH",
    "name:tha_x_preferred":[
        "\u0e1a\u0e49\u0e32\u0e19\u0e40\u0e2a\u0e21\u0e2d\u0e23\u0e32\u0e29\u0e0e\u0e23\u0e4c"
    ],
    "wof:name":"Ban Samoe Rat",
    "wof:placetype":"locality"
},
  "geometry": {"coordinates":[102.35983,12.46703],"type":"Point"}
}