{
  "type": "Feature",
  "properties": {
    "gn:admin1_code":"0.0",
    "gn:asciiname":"Ban Kok Ko",
    "gn:country_code":"TH",
    "gn:dem":397,
    "gn:feature_class":"P",
    "gn:feature_code":"PPL",
    "gn:name":"Ban Kok Ko",
    "gn:population":0,
    "gn:timezone":"Asia/Bangkok",
    "iso:country":"TH",
    "wof:name":"Ban Kok Ko",
    "wof:placetype":"locality"
},
  "geometry": {"coordinates":[101.25,17.16667],"type":"Point"}
}