{
  "type": "Feature",
  "properties": {
    "gn:admin1_code":"51.0",
    "gn:asciiname":"Ban Don Thong",
    "gn:country_code":"TH",
    "gn:dem":7,
    "gn:feature_class":"P",
    "gn:feature_code":"PPL",
    "gn:name":"Ban Don Thong",
    "gn:population":0,
    "gn:timezone":"Asia/Bangkok",
    "iso:country":"TH",
    "name:tha_x_preferred":[
        "\u0e1a\u0e49\u0e32\u0e19\u0e14\u0e2d\u0e19\u0e17\u0e2d\u0e07"
    ],
    "name:und_x_variant":[
        "Ban Don Tong",
        "Ban Don Thong"
    ],
    "wof:name":"Ban Don Thong",
    "wof:placetype":"locality"
},
  "geometry": {"coordinates":[99.98363999999999,14.2735],"type":"Point"}
}