{
  "type": "Feature",
  "properties": {
    "gn:admin1_code":"37",
    "gn:asciiname":"Ban Patirup",
    "gn:country_code":"TH",
    "gn:dem":228,
    "gn:feature_class":"P",
    "gn:feature_code":"PPL",
    "gn:name":"Ban Patirup",
    "gn:population":0,
    "gn:timezone":"Asia/Bangkok",
    "iso:country":"TH",
    "name:tha_x_preferred":[
        "\u0e1a\u0e49\u0e32\u0e19\u0e1b\u0e0f\u0e34\u0e23\u0e39\u0e1b"
    ],
    "wof:name":"Ban Patirup",
    "wof:placetype":"locality"
},
  "geometry": {"coordinates":[101.23811000000001,14.88033],"type":"Point"}
}