{
  "type": "Feature",
  "properties": {
    "gn:admin1_code":"10.0",
    "gn:asciiname":"Ban Pa Thon",
    "gn:country_code":"TH",
    "gn:dem":62,
    "gn:feature_class":"P",
    "gn:feature_code":"PPL",
    "gn:name":"Ban Pa Thon",
    "gn:population":0,
    "gn:timezone":"Asia/Bangkok",
    "iso:country":"TH",
    "name:tha_x_preferred":[
        "Ban Pa Thon"
    ],
    "name:tha_x_variant":[
        "\u0e1a\u0e49\u0e32\u0e19\u0e1b\u0e48\u0e32\u0e16\u0e48\u0e2d\u0e19"
    ],
    "wof:name":"Ban Pa Thon",
    "wof:placetype":"locality"
},
  "geometry": {"coordinates":[100.07708,17.57236],"type":"Point"}
}