{
  "type": "Feature",
  "properties": {
    "gn:admin1_code":"80",
    "gn:asciiname":"Ban Khok Samphan",
    "gn:country_code":"TH",
    "gn:dem":68,
    "gn:feature_class":"P",
    "gn:feature_code":"PPL",
    "gn:name":"Ban Khok Samphan",
    "gn:population":0,
    "gn:timezone":"Asia/Bangkok",
    "iso:country":"TH",
    "name:tha_x_preferred":[
        "\u0e1a\u0e49\u0e32\u0e19\u0e42\u0e04\u0e01\u0e2a\u0e31\u0e21\u0e1e\u0e31\u0e19\u0e18\u0e4c"
    ],
    "wof:name":"Ban Khok Samphan",
    "wof:placetype":"locality"
},
  "geometry": {"coordinates":[102.17422000000001,13.74667],"type":"Point"}
}