{
  "type": "Feature",
  "properties": {
    "gn:admin1_code":"56.0",
    "gn:asciiname":"Ban Phriang Tai",
    "gn:country_code":"TH",
    "gn:dem":8,
    "gn:feature_class":"P",
    "gn:feature_code":"PPL",
    "gn:name":"Ban Phriang Tai",
    "gn:population":0,
    "gn:timezone":"Asia/Bangkok",
    "iso:country":"TH",
    "name:tha_x_preferred":[
        "\u0e1a\u0e49\u0e32\u0e19\u0e40\u0e1e\u0e23\u0e35\u0e22\u0e07\u0e43\u0e15\u0e49"
    ],
    "wof:name":"Ban Phriang Tai",
    "wof:placetype":"locality"
},
  "geometry": {"coordinates":[99.97311000000001,13.06747],"type":"Point"}
}