{
  "type": "Feature",
  "properties": {
    "gn:admin1_code":"38.0",
    "gn:asciiname":"Ban Wat Pracha Rangsan",
    "gn:country_code":"TH",
    "gn:dem":7,
    "gn:feature_class":"P",
    "gn:feature_code":"PPL",
    "gn:name":"Ban Wat Pracha Rangsan",
    "gn:population":0,
    "gn:timezone":"Asia/Bangkok",
    "iso:country":"TH",
    "name:tha_x_preferred":[
        "\u0e1a\u0e49\u0e32\u0e19\u0e27\u0e31\u0e14\u0e1b\u0e23\u0e30\u0e0a\u0e32\u0e23\u0e31\u0e07\u0e2a\u0e23\u0e23\u0e04\u0e4c"
    ],
    "wof:name":"Ban Wat Pracha Rangsan",
    "wof:placetype":"locality"
},
  "geometry": {"coordinates":[100.44503,13.84943],"type":"Point"}
}