{
  "type": "Feature",
  "properties": {
    "gn:admin1_code":"58.0",
    "gn:asciiname":"Ban Na Riang",
    "gn:country_code":"TH",
    "gn:dem":33,
    "gn:feature_class":"P",
    "gn:feature_code":"PPL",
    "gn:name":"Ban Na Riang",
    "gn:population":0,
    "gn:timezone":"Asia/Bangkok",
    "iso:country":"TH",
    "name:tha_x_preferred":[
        "\u0e1a\u0e49\u0e32\u0e19\u0e19\u0e32\u0e40\u0e2b\u0e23\u0e35\u0e48\u0e22\u0e07"
    ],
    "name:und_x_variant":[
        "Na Ka Hlieng",
        "Ban Na Kaliang",
        "Ban Na Krariang",
        "Ban Na Riang"
    ],
    "wof:name":"Ban Na Riang",
    "wof:placetype":"locality"
},
  "geometry": {"coordinates":[99.04567,10.30558],"type":"Point"}
}