{
  "type": "Feature",
  "properties": {
    "gn:admin1_code":"32.0",
    "gn:asciiname":"Ban U Taphao",
    "gn:country_code":"TH",
    "gn:dem":24,
    "gn:feature_class":"P",
    "gn:feature_code":"PPL",
    "gn:name":"Ban U Taphao",
    "gn:population":0,
    "gn:timezone":"Asia/Bangkok",
    "iso:country":"TH",
    "name:tha_x_preferred":[
        "\u0e1a\u0e49\u0e32\u0e19\u0e2d\u0e39\u0e48\u0e15\u0e30\u0e40\u0e20\u0e32"
    ],
    "name:und_x_variant":[
        "Ban U Samphao",
        "Ban U Taphao"
    ],
    "wof:name":"Ban U Taphao",
    "wof:placetype":"locality"
},
  "geometry": {"coordinates":[100.19022,15.27597],"type":"Point"}
}