{
  "type": "Feature",
  "properties": {
    "gn:admin1_code":"70.0",
    "gn:asciiname":"Ban Hua Saphan",
    "gn:country_code":"TH",
    "gn:dem":178,
    "gn:feature_class":"P",
    "gn:feature_code":"PPL",
    "gn:name":"Ban Hua Saphan",
    "gn:population":0,
    "gn:timezone":"Asia/Bangkok",
    "iso:country":"TH",
    "name:tha_x_preferred":[
        "\u0e1a\u0e49\u0e32\u0e19\u0e2b\u0e31\u0e27\u0e2a\u0e30\u0e1e\u0e32\u0e19"
    ],
    "wof:name":"Ban Hua Saphan",
    "wof:placetype":"locality"
},
  "geometry": {"coordinates":[101.18483000000001,6.11294],"type":"Point"}
}