{
  "type": "Feature",
  "properties": {
    "gn:admin1_code":"42.0",
    "gn:asciiname":"Ban Mueang Thai",
    "gn:country_code":"TH",
    "gn:dem":4,
    "gn:feature_class":"P",
    "gn:feature_code":"PPL",
    "gn:name":"Ban Mueang Thai",
    "gn:population":0,
    "gn:timezone":"Asia/Bangkok",
    "iso:country":"TH",
    "name:tha_x_preferred":[
        "\u0e1a\u0e49\u0e32\u0e19\u0e40\u0e21\u0e37\u0e2d\u0e07\u0e44\u0e17\u0e22"
    ],
    "wof:name":"Ban Mueang Thai",
    "wof:placetype":"locality"
},
  "geometry": {"coordinates":[100.83089,13.58478],"type":"Point"}
}