{
  "type": "Feature",
  "properties": {
    "gn:admin1_code":"80",
    "gn:asciiname":"Ban Khao Saraphi",
    "gn:country_code":"TH",
    "gn:dem":151,
    "gn:feature_class":"P",
    "gn:feature_code":"PPL",
    "gn:name":"Ban Khao Saraphi",
    "gn:population":0,
    "gn:timezone":"Asia/Bangkok",
    "iso:country":"TH",
    "name:tha_x_preferred":[
        "\u0e1a\u0e49\u0e32\u0e19\u0e40\u0e02\u0e32\u0e2a\u0e32\u0e23\u0e20\u0e35"
    ],
    "wof:name":"Ban Khao Saraphi",
    "wof:placetype":"locality"
},
  "geometry": {"coordinates":[102.32314,13.48725],"type":"Point"}
}