{
  "type": "Feature",
  "properties": {
    "gn:admin1_code":"24",
    "gn:asciiname":"Ban Hae Tai",
    "gn:country_code":"TH",
    "gn:dem":152,
    "gn:feature_class":"P",
    "gn:feature_code":"PPL",
    "gn:name":"Ban Hae Tai",
    "gn:population":0,
    "gn:timezone":"Asia/Bangkok",
    "iso:country":"TH",
    "name:tha_x_preferred":[
        "\u0e1a\u0e49\u0e32\u0e19\u0e41\u0e2b\u0e48\u0e43\u0e15\u0e49"
    ],
    "wof:name":"Ban Hae Tai",
    "wof:placetype":"locality"
},
  "geometry": {"coordinates":[103.1215,16.29603],"type":"Point"}
}