{
  "type": "Feature",
  "properties": {
    "gn:admin1_code":"24",
    "gn:asciiname":"Ban Kaen Kham",
    "gn:country_code":"TH",
    "gn:dem":148,
    "gn:feature_class":"P",
    "gn:feature_code":"PPL",
    "gn:name":"Ban Kaen Kham",
    "gn:population":0,
    "gn:timezone":"Asia/Bangkok",
    "iso:country":"TH",
    "name:tha_x_preferred":[
        "\u0e1a\u0e49\u0e32\u0e19\u0e41\u0e01\u0e48\u0e19\u0e04\u0e33"
    ],
    "wof:name":"Ban Kaen Kham",
    "wof:placetype":"locality"
},
  "geometry": {"coordinates":[103.24353000000001,15.62381],"type":"Point"}
}