{
  "type": "Feature",
  "properties": {
    "gn:admin1_code":"25.0",
    "gn:asciiname":"Ban Nam Thiang",
    "gn:country_code":"TH",
    "gn:dem":136,
    "gn:feature_class":"P",
    "gn:feature_code":"PPL",
    "gn:name":"Ban Nam Thiang",
    "gn:population":0,
    "gn:timezone":"Asia/Bangkok",
    "iso:country":"TH",
    "name:tha_x_preferred":[
        "\u0e1a\u0e49\u0e32\u0e19\u0e19\u0e49\u0e33\u0e40\u0e17\u0e35\u0e48\u0e22\u0e07"
    ],
    "wof:name":"Ban Nam Thiang",
    "wof:placetype":"locality"
},
  "geometry": {"coordinates":[103.92574999999999,15.89667],"type":"Point"}
}