{
  "type": "Feature",
  "properties": {
    "gn:admin1_code":"2.0",
    "gn:asciiname":"Ban San Nokkaeo",
    "gn:country_code":"TH",
    "gn:dem":312,
    "gn:feature_class":"P",
    "gn:feature_code":"PPL",
    "gn:name":"Ban San Nokkaeo",
    "gn:population":0,
    "gn:timezone":"Asia/Bangkok",
    "iso:country":"TH",
    "name:tha_x_preferred":[
        "\u0e1a\u0e49\u0e32\u0e19\u0e2a\u0e31\u0e19\u0e19\u0e01\u0e41\u0e01\u0e49\u0e27"
    ],
    "wof:name":"Ban San Nokkaeo",
    "wof:placetype":"locality"
},
  "geometry": {"coordinates":[98.82472,18.53331],"type":"Point"}
}