{
  "type": "Feature",
  "properties": {
    "gn:admin1_code":"20.0",
    "gn:asciiname":"Ban Hin Phaeng",
    "gn:country_code":"TH",
    "gn:dem":207,
    "gn:feature_class":"P",
    "gn:feature_code":"PPL",
    "gn:name":"Ban Hin Phaeng",
    "gn:population":0,
    "gn:timezone":"Asia/Bangkok",
    "iso:country":"TH",
    "name:tha_x_preferred":[
        "\u0e1a\u0e49\u0e32\u0e19\u0e2b\u0e34\u0e19\u0e41\u0e1c\u0e07"
    ],
    "wof:name":"Ban Hin Phaeng",
    "wof:placetype":"locality"
},
  "geometry": {"coordinates":[103.34305999999999,17.30814],"type":"Point"}
}