{
  "type": "Feature",
  "properties": {
    "gn:admin1_code":"3.0",
    "gn:asciiname":"Ban Musoe",
    "gn:country_code":"TH",
    "gn:dem":433,
    "gn:feature_class":"P",
    "gn:feature_code":"PPL",
    "gn:name":"Ban Musoe",
    "gn:population":0,
    "gn:timezone":"Asia/Bangkok",
    "iso:country":"TH",
    "wof:name":"Ban Musoe",
    "wof:placetype":"locality"
},
  "geometry": {"coordinates":[100.26667,20.33333],"type":"Point"}
}