{
  "type": "Feature",
  "properties": {
    "gn:admin1_code":"2.0",
    "gn:asciiname":"Ban San",
    "gn:country_code":"TH",
    "gn:dem":315,
    "gn:feature_class":"P",
    "gn:feature_code":"PPL",
    "gn:name":"Ban San",
    "gn:population":0,
    "gn:timezone":"Asia/Bangkok",
    "iso:country":"TH",
    "name:tha_x_preferred":[
        "\u0e1a\u0e49\u0e32\u0e19\u0e2a\u0e31\u0e19"
    ],
    "wof:name":"Ban San",
    "wof:placetype":"locality"
},
  "geometry": {"coordinates":[98.83692000000001,18.6445],"type":"Point"}
}