{
  "type": "Feature",
  "properties": {
    "gn:admin1_code":"3.0",
    "gn:asciiname":"Ban Mae Aep",
    "gn:country_code":"TH",
    "gn:dem":454,
    "gn:feature_class":"P",
    "gn:feature_code":"PPL",
    "gn:name":"Ban Mae Aep",
    "gn:population":0,
    "gn:timezone":"Asia/Bangkok",
    "iso:country":"TH",
    "wof:name":"Ban Mae Aep",
    "wof:placetype":"locality"
},
  "geometry": {"coordinates":[100.22583,20.18972],"type":"Point"}
}