{
  "type": "Feature",
  "properties": {
    "gn:admin1_code":"25",
    "gn:asciiname":"Ban Mayang",
    "gn:country_code":"TH",
    "gn:dem":142,
    "gn:feature_class":"P",
    "gn:feature_code":"PPL",
    "gn:name":"Ban Mayang",
    "gn:population":0,
    "gn:timezone":"Asia/Bangkok",
    "iso:country":"TH",
    "name:tha_x_preferred":[
        "\u0e1a\u0e49\u0e32\u0e19\u0e21\u0e30\u0e22\u0e32\u0e07"
    ],
    "wof:name":"Ban Mayang",
    "wof:placetype":"locality"
},
  "geometry": {"coordinates":[103.79833000000001,15.96289],"type":"Point"}
}