{
  "type": "Feature",
  "properties": {
    "gn:admin1_code":"54.0",
    "gn:asciiname":"Ban Thong Khung",
    "gn:country_code":"TH",
    "gn:dem":7,
    "gn:feature_class":"P",
    "gn:feature_code":"PPL",
    "gn:name":"Ban Thong Khung",
    "gn:population":0,
    "gn:timezone":"Asia/Bangkok",
    "iso:country":"TH",
    "name:tha_x_preferred":[
        "\u0e1a\u0e49\u0e32\u0e19\u0e17\u0e49\u0e2d\u0e07\u0e04\u0e38\u0e49\u0e07"
    ],
    "wof:name":"Ban Thong Khung",
    "wof:placetype":"locality"
},
  "geometry": {"coordinates":[99.94217,13.42111],"type":"Point"}
}