{
  "type": "Feature",
  "properties": {
    "gn:admin1_code":"4.0",
    "gn:asciiname":"Ban Ton Nun",
    "gn:country_code":"TH",
    "gn:dem":197,
    "gn:feature_class":"P",
    "gn:feature_code":"PPL",
    "gn:name":"Ban Ton Nun",
    "gn:population":0,
    "gn:timezone":"Asia/Bangkok",
    "iso:country":"TH",
    "name:tha_x_preferred":[
        "\u0e1a\u0e49\u0e32\u0e19\u0e15\u0e49\u0e19\u0e2b\u0e19\u0e38\u0e19"
    ],
    "wof:name":"Ban Ton Nun",
    "wof:placetype":"locality"
},
  "geometry": {"coordinates":[100.73699999999999,18.576],"type":"Point"}
}