{
  "type": "Feature",
  "properties": {
    "gn:admin1_code":"65.0",
    "gn:asciiname":"Ban Li Phang",
    "gn:country_code":"TH",
    "gn:dem":12,
    "gn:feature_class":"P",
    "gn:feature_code":"PPL",
    "gn:name":"Ban Li Phang",
    "gn:population":0,
    "gn:timezone":"Asia/Bangkok",
    "iso:country":"TH",
    "name:tha_x_preferred":[
        "\u0e1a\u0e49\u0e32\u0e19\u0e25\u0e34\u0e1e\u0e31\u0e07"
    ],
    "name:und_x_variant":[
        "Ban Siphang",
        "Ban Libhang",
        "Liphang",
        "Ban Li Phang (2)",
        "Ban Li Phang"
    ],
    "wof:lang_x_official":[
        "tha"
    ],
    "wof:lang_x_spoken":[
        "tha"
    ],
    "wof:name":"Ban Li Phang",
    "wof:placetype":"locality"
},
  "geometry": {"coordinates":[99.78539000000001,7.17047],"type":"Point"}
}