{
  "type": "Feature",
  "properties": {
    "gn:admin1_code":"11.0",
    "gn:asciiname":"Ban Khon Thong Kham",
    "gn:country_code":"TH",
    "gn:dem":69,
    "gn:feature_class":"P",
    "gn:feature_code":"PPL",
    "gn:name":"Ban Khon Thong Kham",
    "gn:population":0,
    "gn:timezone":"Asia/Bangkok",
    "iso:country":"TH",
    "name:tha_x_preferred":[
        "\u0e1a\u0e49\u0e32\u0e19\u0e02\u0e2d\u0e19\u0e17\u0e2d\u0e07\u0e04\u0e33"
    ],
    "wof:name":"Ban Khon Thong Kham",
    "wof:placetype":"locality"
},
  "geometry": {"coordinates":[99.59078,16.64883],"type":"Point"}
}