{
  "type": "Feature",
  "properties": {
    "gn:admin1_code":"31.0",
    "gn:asciiname":"Ban Ya Ka Bo Ngo",
    "gn:country_code":"TH",
    "gn:dem":74,
    "gn:feature_class":"P",
    "gn:feature_code":"PPL",
    "gn:name":"Ban Ya Ka Bo Ngo",
    "gn:population":0,
    "gn:timezone":"Asia/Bangkok",
    "iso:country":"TH",
    "name:tha_x_preferred":[
        "\u0e1a\u0e49\u0e32\u0e19\u0e22\u0e32\u0e01\u0e32\u0e1a\u0e2d\u0e07\u0e2d"
    ],
    "wof:name":"Ban Ya Ka Bo Ngo",
    "wof:placetype":"locality"
},
  "geometry": {"coordinates":[101.59394,6.12847],"type":"Point"}
}