{
  "type": "Feature",
  "properties": {
    "gn:admin1_code":"69.0",
    "gn:asciiname":"Ban Cha Bae Pa",
    "gn:country_code":"TH",
    "gn:dem":10,
    "gn:feature_class":"P",
    "gn:feature_code":"PPL",
    "gn:name":"Ban Cha Bae Pa",
    "gn:population":0,
    "gn:timezone":"Asia/Bangkok",
    "iso:country":"TH",
    "name:tha_x_preferred":[
        "\u0e1a\u0e49\u0e32\u0e19\u0e08\u0e32\u0e41\u0e1a\u0e1b\u0e30"
    ],
    "wof:name":"Ban Cha Bae Pa",
    "wof:placetype":"locality"
},
  "geometry": {"coordinates":[101.32047,6.7525],"type":"Point"}
}