{
  "type": "Feature",
  "properties": {
    "gn:admin1_code":"28.0",
    "gn:asciiname":"Ban Sawai So",
    "gn:country_code":"TH",
    "gn:dem":194,
    "gn:feature_class":"P",
    "gn:feature_code":"PPL",
    "gn:name":"Ban Sawai So",
    "gn:population":0,
    "gn:timezone":"Asia/Bangkok",
    "iso:country":"TH",
    "name:tha_x_preferred":[
        "\u0e1a\u0e49\u0e32\u0e19\u0e2a\u0e27\u0e32\u0e22\u0e2a\u0e2d"
    ],
    "name:und_x_variant":[
        "Ban Sawai Se"
    ],
    "wof:name":"Ban Sawai So",
    "wof:placetype":"locality"
},
  "geometry": {"coordinates":[102.83996999999999,14.59375],"type":"Point"}
}