{
  "type": "Feature",
  "properties": {
    "gn:admin1_code":"77.0",
    "gn:asciiname":"Ban Wiang Luang",
    "gn:country_code":"TH",
    "gn:dem":134,
    "gn:feature_class":"P",
    "gn:feature_code":"PPL",
    "gn:name":"Ban Wiang Luang",
    "gn:population":0,
    "gn:timezone":"Asia/Bangkok",
    "iso:country":"TH",
    "name:tha_x_preferred":[
        "Ban Wiang Luang"
    ],
    "name:tha_x_variant":[
        "\u0e1a\u0e49\u0e32\u0e19\u0e40\u0e27\u0e35\u0e22\u0e07\u0e2b\u0e25\u0e27\u0e07"
    ],
    "wof:name":"Ban Wiang Luang",
    "wof:placetype":"locality"
},
  "geometry": {"coordinates":[104.62532,15.65219],"type":"Point"}
}