{
  "type": "Feature",
  "properties": {
    "gn:admin1_code":"28.0",
    "gn:asciiname":"Ban Lalom",
    "gn:country_code":"TH",
    "gn:dem":214,
    "gn:feature_class":"P",
    "gn:feature_code":"PPL",
    "gn:name":"Ban Lalom",
    "gn:population":0,
    "gn:timezone":"Asia/Bangkok",
    "iso:country":"TH",
    "name:tha_x_preferred":[
        "\u0e1a\u0e49\u0e32\u0e19\u0e25\u0e30\u0e25\u0e21"
    ],
    "name:und_x_variant":[
        "Ban Ra Lom",
        "Ban Lalom"
    ],
    "wof:name":"Ban Lalom",
    "wof:placetype":"locality"
},
  "geometry": {"coordinates":[102.93247,14.42653],"type":"Point"}
}