{
  "type": "Feature",
  "properties": {
    "gn:admin1_code":"63.0",
    "gn:asciiname":"Ban Huai Riang",
    "gn:country_code":"TH",
    "gn:dem":38,
    "gn:feature_class":"P",
    "gn:feature_code":"PPL",
    "gn:name":"Ban Huai Riang",
    "gn:population":0,
    "gn:timezone":"Asia/Bangkok",
    "iso:country":"TH",
    "name:tha_x_preferred":[
        "\u0e1a\u0e49\u0e32\u0e19\u0e2b\u0e49\u0e27\u0e22\u0e40\u0e2b\u0e23\u0e35\u0e22\u0e07"
    ],
    "wof:name":"Ban Huai Riang",
    "wof:placetype":"locality"
},
  "geometry": {"coordinates":[98.96278,8.20172],"type":"Point"}
}