{
  "type": "Feature",
  "properties": {
    "gn:admin1_code":"2.0",
    "gn:asciiname":"Ban Palong No Lae",
    "gn:country_code":"TH",
    "gn:dem":1429,
    "gn:feature_class":"P",
    "gn:feature_code":"PPL",
    "gn:name":"Ban Palong No Lae",
    "gn:population":0,
    "gn:timezone":"Asia/Bangkok",
    "iso:country":"TH",
    "name:tha_x_preferred":[
        "\u0e1a\u0e49\u0e32\u0e19\u0e1b\u0e30\u0e2b\u0e25\u0e48\u0e2d\u0e07\u0e19\u0e2d\u0e41\u0e25"
    ],
    "wof:lang_x_official":[
        "tha"
    ],
    "wof:lang_x_spoken":[
        "tha"
    ],
    "wof:name":"Ban Palong No Lae",
    "wof:placetype":"locality"
},
  "geometry": {"coordinates":[99.04300000000001,19.93825],"type":"Point"}
}