{
  "type": "Feature",
  "properties": {
    "gn:admin1_code":"18.0",
    "gn:asciiname":"Ban Hua Na Yung",
    "gn:country_code":"TH",
    "gn:dem":357,
    "gn:feature_class":"P",
    "gn:feature_code":"PPL",
    "gn:name":"Ban Hua Na Yung",
    "gn:population":0,
    "gn:timezone":"Asia/Bangkok",
    "iso:country":"TH",
    "name:tha_x_preferred":[
        "Ban Hua Na Yung"
    ],
    "name:tha_x_variant":[
        "\u0e1a\u0e49\u0e32\u0e19\u0e2b\u0e31\u0e27\u0e19\u0e32\u0e22\u0e39\u0e07"
    ],
    "wof:name":"Ban Hua Na Yung",
    "wof:placetype":"locality"
},
  "geometry": {"coordinates":[101.14275000000001,17.27653],"type":"Point"}
}