{
  "type": "Feature",
  "properties": {
    "gn:admin1_code":"26.0",
    "gn:asciiname":"Ban Hua Khwai",
    "gn:cc2":"TH",
    "gn:country_code":"TH",
    "gn:dem":228,
    "gn:feature_class":"P",
    "gn:feature_code":"PPL",
    "gn:name":"Ban Hua Khwai",
    "gn:population":0,
    "gn:timezone":"Asia/Bangkok",
    "iso:country":"TH",
    "name:und_x_variant":[
        "Na Kian",
        "Ban Kian",
        "Ban Na Kian",
        "N\u014dhki\u0113n",
        "B\u0101n Na Gian",
        "Ban Hua Khwai"
    ],
    "wof:name":"Ban Hua Khwai",
    "wof:placetype":"locality"
},
  "geometry": {"coordinates":[101.98333,16.33333],"type":"Point"}
}