{
  "type": "Feature",
  "properties": {
    "gn:admin1_code":"60.0",
    "gn:asciiname":"Ban Lum Chum Saeng",
    "gn:country_code":"TH",
    "gn:dem":16,
    "gn:feature_class":"P",
    "gn:feature_code":"PPL",
    "gn:name":"Ban Lum Chum Saeng",
    "gn:population":0,
    "gn:timezone":"Asia/Bangkok",
    "iso:country":"TH",
    "name:tha_x_preferred":[
        "\u0e1a\u0e49\u0e32\u0e19\u0e25\u0e38\u0e48\u0e21\u0e0a\u0e38\u0e21\u0e41\u0e2a\u0e07"
    ],
    "wof:name":"Ban Lum Chum Saeng",
    "wof:placetype":"locality"
},
  "geometry": {"coordinates":[99.18128,9.44178],"type":"Point"}
}