{
  "type": "Feature",
  "properties": {
    "gn:admin1_code":"44.0",
    "gn:asciiname":"Ban Khao Kluai Mai",
    "gn:country_code":"TH",
    "gn:dem":96,
    "gn:feature_class":"P",
    "gn:feature_code":"PPL",
    "gn:name":"Ban Khao Kluai Mai",
    "gn:population":0,
    "gn:timezone":"Asia/Bangkok",
    "iso:country":"TH",
    "name:tha_x_preferred":[
        "\u0e1a\u0e49\u0e32\u0e19\u0e40\u0e02\u0e32\u0e01\u0e25\u0e31\u0e27\u0e22\u0e44\u0e21\u0e49"
    ],
    "wof:name":"Ban Khao Kluai Mai",
    "wof:placetype":"locality"
},
  "geometry": {"coordinates":[101.67717,13.32417],"type":"Point"}
}