{
  "type": "Feature",
  "properties": {
    "gn:admin1_code":"13.0",
    "gn:asciiname":"Ban Thung Praphat",
    "gn:country_code":"TH",
    "gn:dem":46,
    "gn:feature_class":"P",
    "gn:feature_code":"PPL",
    "gn:name":"Ban Thung Praphat",
    "gn:population":0,
    "gn:timezone":"Asia/Bangkok",
    "iso:country":"TH",
    "name:tha_x_preferred":[
        "\u0e1a\u0e49\u0e32\u0e19\u0e17\u0e38\u0e48\u0e07\u0e1b\u0e23\u0e30\u0e20\u0e32\u0e2a"
    ],
    "name:und_x_variant":[
        "Ban Thung Prapat"
    ],
    "wof:name":"Ban Thung Praphat",
    "wof:placetype":"locality"
},
  "geometry": {"coordinates":[100.10078,16.30236],"type":"Point"}
}