{
  "type": "Feature",
  "properties": {
    "gn:admin1_code":"12.0",
    "gn:asciiname":"Ban Si Yaek Khlong Du",
    "gn:country_code":"TH",
    "gn:dem":70,
    "gn:feature_class":"P",
    "gn:feature_code":"PPL",
    "gn:name":"Ban Si Yaek Khlong Du",
    "gn:population":0,
    "gn:timezone":"Asia/Bangkok",
    "iso:country":"TH",
    "name:tha_x_preferred":[
        "\u0e1a\u0e49\u0e32\u0e19\u0e2a\u0e35\u0e48\u0e41\u0e22\u0e01\u0e04\u0e25\u0e2d\u0e07\u0e14\u0e39\u0e48"
    ],
    "wof:name":"Ban Si Yaek Khlong Du",
    "wof:placetype":"locality"
},
  "geometry": {"coordinates":[100.5825,16.61833],"type":"Point"}
}