{
  "type": "Feature",
  "properties": {
    "gn:admin1_code":"2.0",
    "gn:asciiname":"Ban Phrachao Thong Thip",
    "gn:country_code":"TH",
    "gn:dem":290,
    "gn:feature_class":"P",
    "gn:feature_code":"PPL",
    "gn:name":"Ban Phrachao Thong Thip",
    "gn:population":0,
    "gn:timezone":"Asia/Bangkok",
    "iso:country":"TH",
    "name:tha_x_preferred":[
        "\u0e1a\u0e49\u0e32\u0e19\u0e1e\u0e23\u0e30\u0e40\u0e08\u0e49\u0e32\u0e17\u0e2d\u0e07\u0e17\u0e34\u0e1e\u0e22\u0e4c"
    ],
    "wof:name":"Ban Phrachao Thong Thip",
    "wof:placetype":"locality"
},
  "geometry": {"coordinates":[98.88817,18.55867000000001],"type":"Point"}
}