{
  "type": "Feature",
  "properties": {
    "gn:admin1_code":"31.0",
    "gn:asciiname":"Ban Chue Nga",
    "gn:country_code":"TH",
    "gn:dem":14,
    "gn:feature_class":"P",
    "gn:feature_code":"PPL",
    "gn:name":"Ban Chue Nga",
    "gn:population":0,
    "gn:timezone":"Asia/Bangkok",
    "iso:country":"TH",
    "name:tha_x_preferred":[
        "\u0e1a\u0e49\u0e32\u0e19\u0e08\u0e37\u0e2d\u0e07\u0e32"
    ],
    "wof:name":"Ban Chue Nga",
    "wof:placetype":"locality"
},
  "geometry": {"coordinates":[101.79186,6.3335],"type":"Point"}
}