{
  "type": "Feature",
  "properties": {
    "gn:admin1_code":"2.0",
    "gn:asciiname":"Ban San Hang",
    "gn:country_code":"TH",
    "gn:dem":511,
    "gn:feature_class":"P",
    "gn:feature_code":"PPL",
    "gn:name":"Ban San Hang",
    "gn:population":0,
    "gn:timezone":"Asia/Bangkok",
    "iso:country":"TH",
    "name:tha_x_preferred":[
        "\u0e1a\u0e49\u0e32\u0e19\u0e2a\u0e31\u0e19\u0e2b\u0e49\u0e32\u0e07"
    ],
    "wof:name":"Ban San Hang",
    "wof:placetype":"locality"
},
  "geometry": {"coordinates":[99.32093999999999,19.91525],"type":"Point"}
}