{
  "type": "Feature",
  "properties": {
    "gn:admin1_code":"11.0",
    "gn:asciiname":"Ban Thale Phatthana",
    "gn:country_code":"TH",
    "gn:dem":104,
    "gn:feature_class":"P",
    "gn:feature_code":"PPL",
    "gn:name":"Ban Thale Phatthana",
    "gn:population":0,
    "gn:timezone":"Asia/Bangkok",
    "iso:country":"TH",
    "name:tha_x_preferred":[
        "\u0e1a\u0e49\u0e32\u0e19\u0e17\u0e30\u0e40\u0e25\u0e1e\u0e31\u0e12\u0e19\u0e32"
    ],
    "wof:name":"Ban Thale Phatthana",
    "wof:placetype":"locality"
},
  "geometry": {"coordinates":[99.45447,16.10678],"type":"Point"}
}