{
  "type": "Feature",
  "properties": {
    "gn:admin1_code":"30.0",
    "gn:asciiname":"Ban Kan Throk",
    "gn:country_code":"TH",
    "gn:dem":161,
    "gn:feature_class":"P",
    "gn:feature_code":"PPL",
    "gn:name":"Ban Kan Throk",
    "gn:population":0,
    "gn:timezone":"Asia/Bangkok",
    "iso:country":"TH",
    "name:tha_x_preferred":[
        "\u0e1a\u0e49\u0e32\u0e19\u0e01\u0e31\u0e19\u0e42\u0e17\u0e23\u0e01"
    ],
    "wof:name":"Ban Kan Throk",
    "wof:placetype":"locality"
},
  "geometry": {"coordinates":[104.00789,14.72639],"type":"Point"}
}