{
  "type": "Feature",
  "properties": {
    "gn:admin1_code":"72.0",
    "gn:asciiname":"Ban Khui Tap Tao",
    "gn:country_code":"TH",
    "gn:dem":128,
    "gn:feature_class":"P",
    "gn:feature_code":"PPL",
    "gn:name":"Ban Khui Tap Tao",
    "gn:population":0,
    "gn:timezone":"Asia/Bangkok",
    "iso:country":"TH",
    "name:tha_x_preferred":[
        "\u0e1a\u0e49\u0e32\u0e19\u0e04\u0e38\u0e22\u0e15\u0e31\u0e1a\u0e40\u0e15\u0e48\u0e32"
    ],
    "wof:name":"Ban Khui Tap Tao",
    "wof:placetype":"locality"
},
  "geometry": {"coordinates":[104.16947,15.68619],"type":"Point"}
}