{
  "type": "Feature",
  "properties": {
    "gn:admin1_code":"64.0",
    "gn:asciiname":"Ban Bang Phai",
    "gn:country_code":"TH",
    "gn:dem":6,
    "gn:feature_class":"P",
    "gn:feature_code":"PPL",
    "gn:name":"Ban Bang Phai",
    "gn:population":0,
    "gn:timezone":"Asia/Bangkok",
    "iso:country":"TH",
    "name:tha_x_preferred":[
        "\u0e1a\u0e49\u0e32\u0e19\u0e1a\u0e32\u0e07\u0e44\u0e1c\u0e48"
    ],
    "name:und_x_variant":[
        "Ban Bang Pai",
        "Ban Bang Phai"
    ],
    "wof:name":"Ban Bang Phai",
    "wof:placetype":"locality"
},
  "geometry": {"coordinates":[100.16314,8.27058],"type":"Point"}
}