{
  "type": "Feature",
  "properties": {
    "gn:admin1_code":"72.0",
    "gn:asciiname":"Ban Du Thung",
    "gn:country_code":"TH",
    "gn:dem":140,
    "gn:feature_class":"P",
    "gn:feature_code":"PPL",
    "gn:name":"Ban Du Thung",
    "gn:population":0,
    "gn:timezone":"Asia/Bangkok",
    "iso:country":"TH",
    "name:tha_x_preferred":[
        "\u0e1a\u0e49\u0e32\u0e19\u0e14\u0e39\u0e48\u0e17\u0e38\u0e48\u0e07"
    ],
    "wof:name":"Ban Du Thung",
    "wof:placetype":"locality"
},
  "geometry": {"coordinates":[104.07899999999999,15.88472],"type":"Point"}
}