{
  "type": "Feature",
  "properties": {
    "gn:admin1_code":"27",
    "gn:asciiname":"Ban Chaeng Sawang",
    "gn:country_code":"TH",
    "gn:dem":168,
    "gn:feature_class":"P",
    "gn:feature_code":"PPL",
    "gn:name":"Ban Chaeng Sawang",
    "gn:population":0,
    "gn:timezone":"Asia/Bangkok",
    "iso:country":"TH",
    "name:tha_x_preferred":[
        "\u0e1a\u0e49\u0e32\u0e19\u0e41\u0e08\u0e49\u0e07\u0e2a\u0e27\u0e48\u0e32\u0e07"
    ],
    "wof:name":"Ban Chaeng Sawang",
    "wof:placetype":"locality"
},
  "geometry": {"coordinates":[102.43208,15.49836],"type":"Point"}
}