{
  "type": "Feature",
  "properties": {
    "gn:admin1_code":"70.0",
    "gn:asciiname":"Ban Si Paen",
    "gn:country_code":"TH",
    "gn:dem":203,
    "gn:feature_class":"P",
    "gn:feature_code":"PPL",
    "gn:name":"Ban Si Paen",
    "gn:population":0,
    "gn:timezone":"Asia/Bangkok",
    "iso:country":"TH",
    "name:tha_x_preferred":[
        "\u0e1a\u0e49\u0e32\u0e19\u0e28\u0e23\u0e35\u0e41\u0e1b\u0e49\u0e19"
    ],
    "wof:name":"Ban Si Paen",
    "wof:placetype":"locality"
},
  "geometry": {"coordinates":[101.20131000000001,6.16864],"type":"Point"}
}