{
  "type": "Feature",
  "properties": {
    "gn:admin1_code":"11.0",
    "gn:asciiname":"Ban Ang Hin Phloeng",
    "gn:country_code":"TH",
    "gn:dem":102,
    "gn:feature_class":"P",
    "gn:feature_code":"PPL",
    "gn:name":"Ban Ang Hin Phloeng",
    "gn:population":0,
    "gn:timezone":"Asia/Bangkok",
    "iso:country":"TH",
    "name:tha_x_preferred":[
        "\u0e1a\u0e49\u0e32\u0e19\u0e2d\u0e48\u0e32\u0e07\u0e2b\u0e34\u0e19\u0e40\u0e1e\u0e25\u0e34\u0e07"
    ],
    "wof:name":"Ban Ang Hin Phloeng",
    "wof:placetype":"locality"
},
  "geometry": {"coordinates":[99.49636,16.02803],"type":"Point"}
}