{
  "type": "Feature",
  "properties": {
    "gn:admin1_code":"8.0",
    "gn:asciiname":"Ban Phop Phra Sai Ngam",
    "gn:country_code":"TH",
    "gn:dem":335,
    "gn:feature_class":"P",
    "gn:feature_code":"PPL",
    "gn:name":"Ban Phop Phra Sai Ngam",
    "gn:population":0,
    "gn:timezone":"Asia/Bangkok",
    "iso:country":"TH",
    "name:tha_x_preferred":[
        "Ban Phop Phra Sai Ngam"
    ],
    "name:tha_x_variant":[
        "\u0e1a\u0e49\u0e32\u0e19\u0e1e\u0e1a\u0e1e\u0e23\u0e30\u0e17\u0e23\u0e32\u0e22\u0e07\u0e32\u0e21"
    ],
    "wof:name":"Ban Phop Phra Sai Ngam",
    "wof:placetype":"locality"
},
  "geometry": {"coordinates":[98.69128000000001,16.37653],"type":"Point"}
}