{
  "type": "Feature",
  "properties": {
    "gn:admin1_code":"58.0",
    "gn:asciiname":"Ban Khao Yai",
    "gn:country_code":"TH",
    "gn:dem":51,
    "gn:feature_class":"P",
    "gn:feature_code":"PPL",
    "gn:name":"Ban Khao Yai",
    "gn:population":0,
    "gn:timezone":"Asia/Bangkok",
    "iso:country":"TH",
    "name:tha_x_preferred":[
        "\u0e1a\u0e49\u0e32\u0e19\u0e40\u0e02\u0e32\u0e43\u0e2b\u0e0d\u0e48"
    ],
    "wof:name":"Ban Khao Yai",
    "wof:placetype":"locality"
},
  "geometry": {"coordinates":[99.30183,10.75494],"type":"Point"}
}