{
  "type": "Feature",
  "properties": {
    "gn:admin1_code":"12.0",
    "gn:asciiname":"Ban Nam Kum",
    "gn:country_code":"TH",
    "gn:dem":425,
    "gn:feature_class":"P",
    "gn:feature_code":"PPL",
    "gn:name":"Ban Nam Kum",
    "gn:population":0,
    "gn:timezone":"Asia/Bangkok",
    "iso:country":"TH",
    "name:tha_x_preferred":[
        "\u0e1a\u0e49\u0e32\u0e19\u0e19\u0e49\u0e33\u0e01\u0e38\u0e48\u0e21"
    ],
    "name:und_x_variant":[
        "Ban Nam Khum",
        "B\u0101n Na Kum",
        "Ban Nam Kum"
    ],
    "wof:name":"Ban Nam Kum",
    "wof:placetype":"locality"
},
  "geometry": {"coordinates":[100.85583,17.34794],"type":"Point"}
}