{
  "type": "Feature",
  "properties": {
    "gn:admin1_code":"3.0",
    "gn:asciiname":"Ban Ruammit",
    "gn:country_code":"TH",
    "gn:dem":413,
    "gn:feature_class":"P",
    "gn:feature_code":"PPL",
    "gn:name":"Ban Ruammit",
    "gn:population":0,
    "gn:timezone":"Asia/Bangkok",
    "iso:country":"TH",
    "name:tha_x_preferred":[
        "\u0e1a\u0e49\u0e32\u0e19\u0e23\u0e27\u0e21\u0e21\u0e34\u0e15\u0e23"
    ],
    "wof:name":"Ban Ruammit",
    "wof:placetype":"locality"
},
  "geometry": {"coordinates":[99.71131,19.96083],"type":"Point"}
}