{
  "type": "Feature",
  "properties": {
    "gn:admin1_code":"37.0",
    "gn:asciiname":"Ban Kong Thong",
    "gn:country_code":"TH",
    "gn:dem":9,
    "gn:feature_class":"P",
    "gn:feature_code":"PPL",
    "gn:name":"Ban Kong Thong",
    "gn:population":0,
    "gn:timezone":"Asia/Bangkok",
    "iso:country":"TH",
    "name:tha_x_preferred":[
        "\u0e1a\u0e49\u0e32\u0e19\u0e01\u0e2d\u0e07\u0e17\u0e2d\u0e07"
    ],
    "wof:name":"Ban Kong Thong",
    "wof:placetype":"locality"
},
  "geometry": {"coordinates":[100.67247,14.66825],"type":"Point"}
}