{
  "type": "Feature",
  "properties": {
    "gn:admin1_code":"1.0",
    "gn:asciiname":"Ban Mae Top Tai",
    "gn:country_code":"TH",
    "gn:dem":286,
    "gn:feature_class":"P",
    "gn:feature_code":"PPL",
    "gn:name":"Ban Mae Top Tai",
    "gn:population":0,
    "gn:timezone":"Asia/Bangkok",
    "iso:country":"TH",
    "name:tha_x_preferred":[
        "\u0e1a\u0e49\u0e32\u0e19\u0e41\u0e21\u0e48\u0e15\u0e49\u0e2d\u0e1a\u0e43\u0e15\u0e49"
    ],
    "name:tha_x_variant":[
        "M\u00e8 Taup"
    ],
    "name:und_x_variant":[
        "M\u00e8 Taup",
        "Ban Mae Top Tai",
        "Ban Mae Top"
    ],
    "wof:name":"Ban Mae Top Tai",
    "wof:placetype":"locality"
},
  "geometry": {"coordinates":[97.9025,18.2525],"type":"Point"}
}