{
  "type": "Feature",
  "properties": {
    "gn:admin1_code":"16.0",
    "gn:asciiname":"Ban Bo Krabak",
    "gn:country_code":"TH",
    "gn:dem":39,
    "gn:feature_class":"P",
    "gn:feature_code":"PPL",
    "gn:name":"Ban Bo Krabak",
    "gn:population":0,
    "gn:timezone":"Asia/Bangkok",
    "iso:country":"TH",
    "name:tha_x_preferred":[
        "\u0e1a\u0e49\u0e32\u0e19\u0e1a\u0e48\u0e2d\u0e01\u0e23\u0e30\u0e1a\u0e32\u0e01"
    ],
    "wof:name":"Ban Bo Krabak",
    "wof:placetype":"locality"
},
  "geometry": {"coordinates":[99.89858,15.883],"type":"Point"}
}