{
  "type": "Feature",
  "properties": {
    "gn:admin1_code":"4.0",
    "gn:asciiname":"Ban Khwaeng",
    "gn:country_code":"TH",
    "gn:dem":309,
    "gn:feature_class":"P",
    "gn:feature_code":"PPL",
    "gn:name":"Ban Khwaeng",
    "gn:population":0,
    "gn:timezone":"Asia/Bangkok",
    "iso:country":"TH",
    "name:tha_x_preferred":[
        "\u0e1a\u0e49\u0e32\u0e19\u0e41\u0e04\u0e27\u0e49\u0e07"
    ],
    "name:und_x_variant":[
        "Ban Kweang",
        "Ban Khwaeng"
    ],
    "wof:lang_x_official":[
        "tha"
    ],
    "wof:lang_x_spoken":[
        "tha"
    ],
    "wof:name":"Ban Khwaeng",
    "wof:placetype":"locality"
},
  "geometry": {"coordinates":[101.01275,18.74308],"type":"Point"}
}