{
  "type": "Feature",
  "properties": {
    "gn:admin1_code":"29",
    "gn:asciiname":"Ban Don Leng",
    "gn:country_code":"TH",
    "gn:dem":161,
    "gn:feature_class":"P",
    "gn:feature_code":"PPL",
    "gn:name":"Ban Don Leng",
    "gn:population":0,
    "gn:timezone":"Asia/Bangkok",
    "iso:country":"TH",
    "name:tha_x_preferred":[
        "\u0e1a\u0e49\u0e32\u0e19\u0e42\u0e14\u0e19\u0e40\u0e25\u0e07"
    ],
    "wof:name":"Ban Don Leng",
    "wof:placetype":"locality"
},
  "geometry": {"coordinates":[103.48456,14.71475],"type":"Point"}
}