{
  "type": "Feature",
  "properties": {
    "gn:admin1_code":"28.0",
    "gn:asciiname":"Ban Kan Lueang",
    "gn:country_code":"TH",
    "gn:dem":142,
    "gn:feature_class":"P",
    "gn:feature_code":"PPL",
    "gn:name":"Ban Kan Lueang",
    "gn:population":0,
    "gn:timezone":"Asia/Bangkok",
    "iso:country":"TH",
    "name:tha_x_preferred":[
        "\u0e1a\u0e49\u0e32\u0e19\u0e01\u0e49\u0e32\u0e19\u0e40\u0e2b\u0e25\u0e37\u0e2d\u0e07"
    ],
    "name:und_x_variant":[
        "Ban Kan Luang"
    ],
    "wof:lang_x_official":[
        "tha"
    ],
    "wof:lang_x_spoken":[
        "tha"
    ],
    "wof:name":"Ban Kan Lueang",
    "wof:placetype":"locality"
},
  "geometry": {"coordinates":[103.40136,14.9815],"type":"Point"}
}