{
  "type": "Feature",
  "properties": {
    "gn:admin1_code":"80",
    "gn:asciiname":"Ban Nong Ya Moei",
    "gn:country_code":"TH",
    "gn:dem":80,
    "gn:feature_class":"P",
    "gn:feature_code":"PPL",
    "gn:name":"Ban Nong Ya Moei",
    "gn:population":0,
    "gn:timezone":"Asia/Bangkok",
    "iso:country":"TH",
    "name:tha_x_preferred":[
        "\u0e1a\u0e49\u0e32\u0e19\u0e2b\u0e19\u0e2d\u0e07\u0e2b\u0e0d\u0e49\u0e32\u0e40\u0e21\u0e22"
    ],
    "wof:name":"Ban Nong Ya Moei",
    "wof:placetype":"locality"
},
  "geometry": {"coordinates":[102.56903,13.72692],"type":"Point"}
}