{
  "type": "Feature",
  "properties": {
    "gn:admin1_code":"29",
    "gn:asciiname":"Ban Sai Thap",
    "gn:country_code":"TH",
    "gn:dem":157,
    "gn:feature_class":"P",
    "gn:feature_code":"PPL",
    "gn:name":"Ban Sai Thap",
    "gn:population":0,
    "gn:timezone":"Asia/Bangkok",
    "iso:country":"TH",
    "name:tha_x_preferred":[
        "\u0e1a\u0e49\u0e32\u0e19\u0e44\u0e17\u0e23\u0e17\u0e32\u0e1a"
    ],
    "wof:name":"Ban Sai Thap",
    "wof:placetype":"locality"
},
  "geometry": {"coordinates":[103.41942,14.79906],"type":"Point"}
}