{
  "type": "Feature",
  "properties": {
    "gn:admin1_code":"9.0",
    "gn:asciiname":"Ban Khon Sung",
    "gn:country_code":"TH",
    "gn:dem":66,
    "gn:feature_class":"P",
    "gn:feature_code":"PPL",
    "gn:name":"Ban Khon Sung",
    "gn:population":0,
    "gn:timezone":"Asia/Bangkok",
    "iso:country":"TH",
    "name:tha_x_preferred":[
        "\u0e1a\u0e49\u0e32\u0e19\u0e02\u0e2d\u0e19\u0e0b\u0e38\u0e07"
    ],
    "name:und_x_variant":[
        "Khohnmaizung",
        "B\u0101n Kaun Mai Sung",
        "Khaun Mai Sung",
        "Ban Khon Mai Sung",
        "Ban Khon Sung"
    ],
    "wof:lang_x_official":[
        "tha"
    ],
    "wof:lang_x_spoken":[
        "tha"
    ],
    "wof:name":"Ban Khon Sung",
    "wof:placetype":"locality"
},
  "geometry": {"coordinates":[99.70636,17.22425],"type":"Point"}
}