{
  "type": "Feature",
  "properties": {
    "gn:admin1_code":"31.0",
    "gn:asciiname":"Ban Khao Ngu Lueam",
    "gn:country_code":"TH",
    "gn:dem":19,
    "gn:feature_class":"P",
    "gn:feature_code":"PPL",
    "gn:name":"Ban Khao Ngu Lueam",
    "gn:population":0,
    "gn:timezone":"Asia/Bangkok",
    "iso:country":"TH",
    "name:tha_x_preferred":[
        "\u0e1a\u0e49\u0e32\u0e19\u0e40\u0e02\u0e32\u0e07\u0e39\u0e40\u0e2b\u0e25\u0e37\u0e2d\u0e21"
    ],
    "wof:name":"Ban Khao Ngu Lueam",
    "wof:placetype":"locality"
},
  "geometry": {"coordinates":[101.76975,6.42125],"type":"Point"}
}