{
  "type": "Feature",
  "properties": {
    "gn:admin1_code":"64.0",
    "gn:asciiname":"Ban Thon Phakkut",
    "gn:country_code":"TH",
    "gn:dem":39,
    "gn:feature_class":"P",
    "gn:feature_code":"PPL",
    "gn:name":"Ban Thon Phakkut",
    "gn:population":0,
    "gn:timezone":"Asia/Bangkok",
    "iso:country":"TH",
    "name:tha_x_preferred":[
        "\u0e1a\u0e49\u0e32\u0e19\u0e17\u0e2d\u0e19\u0e1c\u0e31\u0e01\u0e01\u0e39\u0e14"
    ],
    "wof:name":"Ban Thon Phakkut",
    "wof:placetype":"locality"
},
  "geometry": {"coordinates":[99.78816999999999,8.71922],"type":"Point"}
}