{
  "type": "Feature",
  "properties": {
    "gn:admin1_code":"76.0",
    "gn:asciiname":"Ban Khaosan Noi",
    "gn:country_code":"TH",
    "gn:dem":189,
    "gn:feature_class":"P",
    "gn:feature_code":"PPL",
    "gn:name":"Ban Khaosan Noi",
    "gn:population":0,
    "gn:timezone":"Asia/Bangkok",
    "iso:country":"TH",
    "name:tha_x_preferred":[
        "\u0e1a\u0e49\u0e32\u0e19\u0e02\u0e49\u0e32\u0e27\u0e2a\u0e32\u0e23\u0e19\u0e49\u0e2d\u0e22"
    ],
    "wof:name":"Ban Khaosan Noi",
    "wof:placetype":"locality"
},
  "geometry": {"coordinates":[102.85006,17.32061],"type":"Point"}
}