{
  "type": "Feature",
  "properties": {
    "gn:admin1_code":"24",
    "gn:asciiname":"Ban Khok Rai Phatthana",
    "gn:country_code":"TH",
    "gn:dem":179,
    "gn:feature_class":"P",
    "gn:feature_code":"PPL",
    "gn:name":"Ban Khok Rai Phatthana",
    "gn:population":0,
    "gn:timezone":"Asia/Bangkok",
    "iso:country":"TH",
    "name:tha_x_preferred":[
        "\u0e1a\u0e49\u0e32\u0e19\u0e42\u0e04\u0e01\u0e44\u0e23\u0e48\u0e1e\u0e31\u0e12\u0e19\u0e32"
    ],
    "wof:name":"Ban Khok Rai Phatthana",
    "wof:placetype":"locality"
},
  "geometry": {"coordinates":[103.32011,15.94975],"type":"Point"}
}