{
  "type": "Feature",
  "properties": {
    "gn:admin1_code":"67.0",
    "gn:asciiname":"Ban Tola Nua",
    "gn:cc2":"TH",
    "gn:country_code":"TH",
    "gn:dem":11,
    "gn:feature_class":"P",
    "gn:feature_code":"PPL",
    "gn:name":"Ban Tola Nua",
    "gn:population":0,
    "gn:timezone":"Asia/Bangkok",
    "iso:country":"TH",
    "name:und_x_variant":[
        "To La Nua",
        "Ban Tola Nua"
    ],
    "wof:name":"Ban Tola Nua",
    "wof:placetype":"locality"
},
  "geometry": {"coordinates":[99.83333,6.95],"type":"Point"}
}