{
  "type": "Feature",
  "properties": {
    "gn:admin1_code":"27.0",
    "gn:asciiname":"Ban Bu Hua Chang",
    "gn:country_code":"TH",
    "gn:dem":249,
    "gn:feature_class":"P",
    "gn:feature_code":"PPL",
    "gn:name":"Ban Bu Hua Chang",
    "gn:population":0,
    "gn:timezone":"Asia/Bangkok",
    "iso:country":"TH",
    "name:tha_x_preferred":[
        "\u0e1a\u0e49\u0e32\u0e19\u0e1a\u0e38\u0e2b\u0e31\u0e27\u0e0a\u0e49\u0e32\u0e07"
    ],
    "name:und_x_variant":[
        "Ban Bu Hua Chaang",
        "Ban Bu Hua Chang"
    ],
    "wof:name":"Ban Bu Hua Chang",
    "wof:placetype":"locality"
},
  "geometry": {"coordinates":[101.83831000000001,14.60547],"type":"Point"}
}