{
  "type": "Feature",
  "properties": {
    "gn:admin1_code":"50.0",
    "gn:asciiname":"Ban Nong Salaep",
    "gn:country_code":"TH",
    "gn:dem":94,
    "gn:feature_class":"P",
    "gn:feature_code":"PPL",
    "gn:name":"Ban Nong Salaep",
    "gn:population":0,
    "gn:timezone":"Asia/Bangkok",
    "iso:country":"TH",
    "name:tha_x_preferred":[
        "\u0e1a\u0e49\u0e32\u0e19\u0e2b\u0e19\u0e2d\u0e07\u0e41\u0e2a\u0e25\u0e1a"
    ],
    "wof:name":"Ban Nong Salaep",
    "wof:placetype":"locality"
},
  "geometry": {"coordinates":[99.8185,14.49472],"type":"Point"}
}