{
  "type": "Feature",
  "properties": {
    "gn:admin1_code":"3.0",
    "gn:asciiname":"Ban San Nong Bua",
    "gn:country_code":"TH",
    "gn:dem":416,
    "gn:feature_class":"P",
    "gn:feature_code":"PPL",
    "gn:name":"Ban San Nong Bua",
    "gn:population":0,
    "gn:timezone":"Asia/Bangkok",
    "iso:country":"TH",
    "name:tha_x_preferred":[
        "\u0e1a\u0e49\u0e32\u0e19\u0e2a\u0e31\u0e19\u0e2b\u0e19\u0e2d\u0e07\u0e1a\u0e31\u0e27"
    ],
    "wof:name":"Ban San Nong Bua",
    "wof:placetype":"locality"
},
  "geometry": {"coordinates":[99.88467,20.07567],"type":"Point"}
}