{
  "type": "Feature",
  "properties": {
    "gn:admin1_code":"81.0",
    "gn:asciiname":"Ban Na Dong Noi",
    "gn:country_code":"TH",
    "gn:dem":173,
    "gn:feature_class":"P",
    "gn:feature_code":"PPL",
    "gn:name":"Ban Na Dong Noi",
    "gn:population":0,
    "gn:timezone":"Asia/Bangkok",
    "iso:country":"TH",
    "name:tha_x_preferred":[
        "\u0e1a\u0e49\u0e32\u0e19\u0e19\u0e32\u0e14\u0e07\u0e19\u0e49\u0e2d\u0e22"
    ],
    "wof:name":"Ban Na Dong Noi",
    "wof:placetype":"locality"
},
  "geometry": {"coordinates":[103.30417,18.25825],"type":"Point"}
}