{
  "type": "Feature",
  "properties": {
    "gn:admin1_code":"29",
    "gn:asciiname":"Ban Kan Nang",
    "gn:country_code":"TH",
    "gn:dem":140,
    "gn:feature_class":"P",
    "gn:feature_code":"PPL",
    "gn:name":"Ban Kan Nang",
    "gn:population":0,
    "gn:timezone":"Asia/Bangkok",
    "iso:country":"TH",
    "name:tha_x_preferred":[
        "\u0e1a\u0e49\u0e32\u0e19\u0e01\u0e31\u0e19\u0e19\u0e31\u0e07"
    ],
    "wof:name":"Ban Kan Nang",
    "wof:placetype":"locality"
},
  "geometry": {"coordinates":[103.4435,15.19781],"type":"Point"}
}