{
  "type": "Feature",
  "properties": {
    "gn:admin1_code":"81.0",
    "gn:asciiname":"Ban Lao Thong Phatthana",
    "gn:country_code":"TH",
    "gn:dem":166,
    "gn:feature_class":"P",
    "gn:feature_code":"PPL",
    "gn:name":"Ban Lao Thong Phatthana",
    "gn:population":0,
    "gn:timezone":"Asia/Bangkok",
    "iso:country":"TH",
    "name:tha_x_preferred":[
        "\u0e1a\u0e49\u0e32\u0e19\u0e40\u0e2b\u0e25\u0e48\u0e32\u0e17\u0e2d\u0e07\u0e1e\u0e31\u0e12\u0e19\u0e32"
    ],
    "wof:name":"Ban Lao Thong Phatthana",
    "wof:placetype":"locality"
},
  "geometry": {"coordinates":[103.42008,18.12156],"type":"Point"}
}