{
  "type": "Feature",
  "properties": {
    "gn:admin1_code":"16.0",
    "gn:asciiname":"Ban San Tawa",
    "gn:country_code":"TH",
    "gn:dem":33,
    "gn:feature_class":"P",
    "gn:feature_code":"PPL",
    "gn:name":"Ban San Tawa",
    "gn:population":0,
    "gn:timezone":"Asia/Bangkok",
    "iso:country":"TH",
    "name:tha_x_preferred":[
        "\u0e1a\u0e49\u0e32\u0e19\u0e2a\u0e31\u0e19\u0e15\u0e30\u0e27\u0e32"
    ],
    "wof:name":"Ban San Tawa",
    "wof:placetype":"locality"
},
  "geometry": {"coordinates":[100.15147,15.67842],"type":"Point"}
}