{
  "type": "Feature",
  "properties": {
    "gn:admin1_code":"75.0",
    "gn:asciiname":"Ban Kaeng Kok Hai",
    "gn:country_code":"TH",
    "gn:dem":153,
    "gn:feature_class":"P",
    "gn:feature_code":"PPL",
    "gn:name":"Ban Kaeng Kok Hai",
    "gn:population":0,
    "gn:timezone":"Asia/Bangkok",
    "iso:country":"TH",
    "name:tha_x_preferred":[
        "\u0e1a\u0e49\u0e32\u0e19\u0e41\u0e01\u0e49\u0e07\u0e01\u0e01\u0e44\u0e2e"
    ],
    "wof:lang_x_official":[
        "tha"
    ],
    "wof:lang_x_spoken":[
        "tha"
    ],
    "wof:name":"Ban Kaeng Kok Hai",
    "wof:placetype":"locality"
},
  "geometry": {"coordinates":[105.16525,14.62942],"type":"Point"}
}