{
  "type": "Feature",
  "properties": {
    "gn:admin1_code":"2.0",
    "gn:asciiname":"Ban Hong Nai",
    "gn:country_code":"TH",
    "gn:dem":337,
    "gn:feature_class":"P",
    "gn:feature_code":"PPL",
    "gn:name":"Ban Hong Nai",
    "gn:population":0,
    "gn:timezone":"Asia/Bangkok",
    "iso:country":"TH",
    "name:tha_x_preferred":[
        "\u0e1a\u0e49\u0e32\u0e19\u0e42\u0e2e\u0e48\u0e07\u0e43\u0e19"
    ],
    "name:und_x_variant":[
        "Ban Ho",
        "Ban Hong Nai"
    ],
    "wof:name":"Ban Hong Nai",
    "wof:placetype":"locality"
},
  "geometry": {"coordinates":[98.91167,18.92833],"type":"Point"}
}