{
  "type": "Feature",
  "properties": {
    "gn:admin1_code":"2.0",
    "gn:asciiname":"Ban Luang Mueang Khong",
    "gn:country_code":"TH",
    "gn:dem":612,
    "gn:feature_class":"P",
    "gn:feature_code":"PPL",
    "gn:name":"Ban Luang Mueang Khong",
    "gn:population":0,
    "gn:timezone":"Asia/Bangkok",
    "iso:country":"TH",
    "name:tha_x_preferred":[
        "\u0e1a\u0e49\u0e32\u0e19\u0e2b\u0e25\u0e27\u0e07\u0e40\u0e21\u0e37\u0e2d\u0e07\u0e04\u0e2d\u0e07"
    ],
    "wof:name":"Ban Luang Mueang Khong",
    "wof:placetype":"locality"
},
  "geometry": {"coordinates":[98.71567,19.38561],"type":"Point"}
}