{
  "type": "Feature",
  "properties": {
    "gn:admin1_code":"20.0",
    "gn:asciiname":"Ban Tha Wat",
    "gn:country_code":"TH",
    "gn:dem":183,
    "gn:feature_class":"P",
    "gn:feature_code":"PPL",
    "gn:name":"Ban Tha Wat",
    "gn:population":0,
    "gn:timezone":"Asia/Bangkok",
    "iso:country":"TH",
    "name:tha_x_preferred":[
        "\u0e1a\u0e49\u0e32\u0e19\u0e17\u0e48\u0e32\u0e27\u0e31\u0e14"
    ],
    "wof:name":"Ban Tha Wat",
    "wof:placetype":"locality"
},
  "geometry": {"coordinates":[103.32933,17.36856],"type":"Point"}
}