{
  "type": "Feature",
  "properties": {
    "gn:admin1_code":"39.0",
    "gn:asciiname":"Ban Noppharat Phatthana",
    "gn:country_code":"TH",
    "gn:dem":6,
    "gn:feature_class":"P",
    "gn:feature_code":"PPL",
    "gn:name":"Ban Noppharat Phatthana",
    "gn:population":0,
    "gn:timezone":"Asia/Bangkok",
    "iso:country":"TH",
    "name:tha_x_preferred":[
        "Ban Noppharat Phatthana"
    ],
    "name:tha_x_variant":[
        "\u0e1a\u0e49\u0e32\u0e19\u0e19\u0e1e\u0e23\u0e31\u0e15\u0e19\u0e4c\u0e1e\u0e31\u0e12\u0e19\u0e32"
    ],
    "wof:name":"Ban Noppharat Phatthana",
    "wof:placetype":"locality"
},
  "geometry": {"coordinates":[100.87008,14.20764],"type":"Point"}
}