{
  "type": "Feature",
  "properties": {
    "gn:admin1_code":"65.0",
    "gn:asciiname":"Ban Phu Chiang",
    "gn:country_code":"TH",
    "gn:dem":27,
    "gn:feature_class":"P",
    "gn:feature_code":"PPL",
    "gn:name":"Ban Phu Chiang",
    "gn:population":0,
    "gn:timezone":"Asia/Bangkok",
    "iso:country":"TH",
    "name:tha_x_preferred":[
        "\u0e1a\u0e49\u0e32\u0e19\u0e20\u0e39\u0e40\u0e0a\u0e35\u0e22\u0e07"
    ],
    "wof:name":"Ban Phu Chiang",
    "wof:placetype":"locality"
},
  "geometry": {"coordinates":[99.74592,7.49372],"type":"Point"}
}