{
  "type": "Feature",
  "properties": {
    "gn:admin1_code":"26.0",
    "gn:asciiname":"Ban Non Pho",
    "gn:country_code":"TH",
    "gn:dem":176,
    "gn:feature_class":"P",
    "gn:feature_code":"PPL",
    "gn:name":"Ban Non Pho",
    "gn:population":0,
    "gn:timezone":"Asia/Bangkok",
    "iso:country":"TH",
    "name:tha_x_preferred":[
        "\u0e1a\u0e49\u0e32\u0e19\u0e42\u0e19\u0e19\u0e42\u0e1e\u0e18\u0e34\u0e4c"
    ],
    "wof:name":"Ban Non Pho",
    "wof:placetype":"locality"
},
  "geometry": {"coordinates":[102.31778,15.90528],"type":"Point"}
}