{
  "type": "Feature",
  "properties": {
    "gn:admin1_code":"0.0",
    "gn:asciiname":"Ban Wang Nam So",
    "gn:country_code":"TH",
    "gn:dem":555,
    "gn:feature_class":"P",
    "gn:feature_code":"PPL",
    "gn:name":"Ban Wang Nam So",
    "gn:population":0,
    "gn:timezone":"Asia/Bangkok",
    "iso:country":"TH",
    "wof:name":"Ban Wang Nam So",
    "wof:placetype":"locality"
},
  "geometry": {"coordinates":[101.43333,16.98333],"type":"Point"}
}