{
  "type": "Feature",
  "properties": {
    "gn:admin1_code":"63.0",
    "gn:asciiname":"Ban Pak Bang San",
    "gn:country_code":"TH",
    "gn:dem":51,
    "gn:feature_class":"P",
    "gn:feature_code":"PPL",
    "gn:name":"Ban Pak Bang San",
    "gn:population":0,
    "gn:timezone":"Asia/Bangkok",
    "iso:country":"TH",
    "name:tha_x_preferred":[
        "\u0e1a\u0e49\u0e32\u0e19\u0e1b\u0e32\u0e01\u0e1a\u0e32\u0e07\u0e2a\u0e23\u0e49\u0e32\u0e19"
    ],
    "wof:name":"Ban Pak Bang San",
    "wof:placetype":"locality"
},
  "geometry": {"coordinates":[99.04268999999999,8.34283],"type":"Point"}
}