{
  "type": "Feature",
  "properties": {
    "gn:admin1_code":"66.0",
    "gn:asciiname":"Ban Khao To Bun",
    "gn:country_code":"TH",
    "gn:dem":14,
    "gn:feature_class":"P",
    "gn:feature_code":"PPL",
    "gn:name":"Ban Khao To Bun",
    "gn:population":0,
    "gn:timezone":"Asia/Bangkok",
    "iso:country":"TH",
    "name:tha_x_preferred":[
        "\u0e1a\u0e49\u0e32\u0e19\u0e40\u0e02\u0e32\u0e42\u0e15\u0e4a\u0e30\u0e1a\u0e38\u0e0d"
    ],
    "wof:name":"Ban Khao To Bun",
    "wof:placetype":"locality"
},
  "geometry": {"coordinates":[100.01094000000001,7.66594],"type":"Point"}
}