{
  "type": "Feature",
  "properties": {
    "gn:admin1_code":"31.0",
    "gn:asciiname":"Ban Tue La Kho Fa La",
    "gn:country_code":"TH",
    "gn:dem":10,
    "gn:feature_class":"P",
    "gn:feature_code":"PPL",
    "gn:name":"Ban Tue La Kho Fa La",
    "gn:population":0,
    "gn:timezone":"Asia/Bangkok",
    "iso:country":"TH",
    "name:tha_x_preferred":[
        "\u0e1a\u0e49\u0e32\u0e19\u0e15\u0e37\u0e2d\u0e25\u0e32\u0e06\u0e2d\u0e1f\u0e32\u0e25\u0e30\u0e2b\u0e4c"
    ],
    "wof:name":"Ban Tue La Kho Fa La",
    "wof:placetype":"locality"
},
  "geometry": {"coordinates":[101.89422,6.39167],"type":"Point"}
}