{
  "type": "Feature",
  "properties": {
    "gn:admin1_code":"80.0",
    "gn:asciiname":"Ban Phansuek Nueng",
    "gn:country_code":"TH",
    "gn:dem":86,
    "gn:feature_class":"P",
    "gn:feature_code":"PPL",
    "gn:name":"Ban Phansuek Nueng",
    "gn:population":0,
    "gn:timezone":"Asia/Bangkok",
    "iso:country":"TH",
    "name:tha_x_preferred":[
        "\u0e1a\u0e49\u0e32\u0e19\u0e1c\u0e48\u0e32\u0e19\u0e28\u0e36\u0e01 \u0e2b\u0e19\u0e36\u0e48\u0e07"
    ],
    "name:und_x_variant":[
        "Ban Nikhom Phan Suk",
        "Ban Phansuek",
        "Ban Phansuek Nueng"
    ],
    "wof:name":"Ban Phansuek Nueng",
    "wof:placetype":"locality"
},
  "geometry": {"coordinates":[102.41358,13.57403],"type":"Point"}
}