{
  "type": "Feature",
  "properties": {
    "gn:admin1_code":"59.0",
    "gn:asciiname":"Ban Chang Haek",
    "gn:country_code":"TH",
    "gn:dem":21,
    "gn:feature_class":"P",
    "gn:feature_code":"PPL",
    "gn:name":"Ban Chang Haek",
    "gn:population":0,
    "gn:timezone":"Asia/Bangkok",
    "iso:country":"TH",
    "name:tha_x_preferred":[
        "\u0e1a\u0e49\u0e32\u0e19\u0e0a\u0e49\u0e32\u0e07\u0e41\u0e2b\u0e01"
    ],
    "wof:name":"Ban Chang Haek",
    "wof:placetype":"locality"
},
  "geometry": {"coordinates":[98.56975,9.67492],"type":"Point"}
}