{
  "type": "Feature",
  "properties": {
    "gn:admin1_code":"30.0",
    "gn:asciiname":"Ban Sala PaTai",
    "gn:country_code":"TH",
    "gn:dem":134,
    "gn:feature_class":"P",
    "gn:feature_code":"PPL",
    "gn:name":"Ban Sala PaTai",
    "gn:population":0,
    "gn:timezone":"Asia/Bangkok",
    "iso:country":"TH",
    "name:tha_x_preferred":[
        "\u0e1a\u0e49\u0e32\u0e19\u0e28\u0e32\u0e25\u0e32\u0e1b\u0e48\u0e32\u0e43\u0e15\u0e49"
    ],
    "wof:lang_x_official":[
        "tha"
    ],
    "wof:lang_x_spoken":[
        "tha"
    ],
    "wof:name":"Ban Sala PaTai",
    "wof:placetype":"locality"
},
  "geometry": {"coordinates":[104.16489,14.96208],"type":"Point"}
}