{
  "type": "Feature",
  "properties": {
    "gn:admin1_code":"74",
    "gn:asciiname":"Ban Noen Hin Tang",
    "gn:country_code":"TH",
    "gn:dem":17,
    "gn:feature_class":"P",
    "gn:feature_code":"PPL",
    "gn:name":"Ban Noen Hin Tang",
    "gn:population":0,
    "gn:timezone":"Asia/Bangkok",
    "iso:country":"TH",
    "name:tha_x_preferred":[
        "\u0e1a\u0e49\u0e32\u0e19\u0e40\u0e19\u0e34\u0e19\u0e2b\u0e34\u0e19\u0e15\u0e31\u0e49\u0e07"
    ],
    "wof:name":"Ban Noen Hin Tang",
    "wof:placetype":"locality"
},
  "geometry": {"coordinates":[101.54986,14.15981],"type":"Point"}
}