{
  "type": "Feature",
  "properties": {
    "gn:admin1_code":"61.0",
    "gn:asciiname":"Ban Ao Bo Le",
    "gn:country_code":"TH",
    "gn:dem":18,
    "gn:feature_class":"P",
    "gn:feature_code":"PPL",
    "gn:name":"Ban Ao Bo Le",
    "gn:population":0,
    "gn:timezone":"Asia/Bangkok",
    "iso:country":"TH",
    "name:tha_x_preferred":[
        "\u0e1a\u0e49\u0e32\u0e19\u0e2d\u0e48\u0e32\u0e27\u0e1a\u0e48\u0e2d\u0e40\u0e25"
    ],
    "wof:name":"Ban Ao Bo Le",
    "wof:placetype":"locality"
},
  "geometry": {"coordinates":[98.57940000000001,7.9253],"type":"Point"}
}