{
  "type": "Feature",
  "properties": {
    "gn:admin1_code":"50.0",
    "gn:asciiname":"Ban Saphan Lao",
    "gn:country_code":"TH",
    "gn:dem":344,
    "gn:feature_class":"P",
    "gn:feature_code":"PPL",
    "gn:name":"Ban Saphan Lao",
    "gn:population":0,
    "gn:timezone":"Asia/Bangkok",
    "iso:country":"TH",
    "name:tha_x_preferred":[
        "\u0e1a\u0e49\u0e32\u0e19\u0e2a\u0e30\u0e1e\u0e32\u0e19\u0e25\u0e32\u0e27"
    ],
    "wof:name":"Ban Saphan Lao",
    "wof:placetype":"locality"
},
  "geometry": {"coordinates":[98.78633000000001,14.72842],"type":"Point"}
}