{
  "type": "Feature",
  "properties": {
    "gn:admin1_code":"0.0",
    "gn:asciiname":"Ban Thung Madan",
    "gn:country_code":"TH",
    "gn:dem":450,
    "gn:feature_class":"P",
    "gn:feature_code":"PPL",
    "gn:name":"Ban Thung Madan",
    "gn:population":0,
    "gn:timezone":"Asia/Bangkok",
    "iso:country":"TH",
    "wof:name":"Ban Thung Madan",
    "wof:placetype":"locality"
},
  "geometry": {"coordinates":[98.71666999999999,17.26667],"type":"Point"}
}