{
  "type": "Feature",
  "properties": {
    "gn:admin1_code":"18.0",
    "gn:asciiname":"Ban Huai Lek",
    "gn:country_code":"TH",
    "gn:dem":296,
    "gn:feature_class":"P",
    "gn:feature_code":"PPL",
    "gn:name":"Ban Huai Lek",
    "gn:population":0,
    "gn:timezone":"Asia/Bangkok",
    "iso:country":"TH",
    "name:tha_x_preferred":[
        "\u0e1a\u0e49\u0e32\u0e19\u0e2b\u0e49\u0e27\u0e22\u0e40\u0e2b\u0e25\u0e47\u0e01"
    ],
    "wof:name":"Ban Huai Lek",
    "wof:placetype":"locality"
},
  "geometry": {"coordinates":[101.61667,17.59661000000001],"type":"Point"}
}