{
  "type": "Feature",
  "properties": {
    "gn:admin1_code":"27.0",
    "gn:asciiname":"Ban Nong Phutsa",
    "gn:country_code":"TH",
    "gn:dem":218,
    "gn:feature_class":"P",
    "gn:feature_code":"PPL",
    "gn:name":"Ban Nong Phutsa",
    "gn:population":0,
    "gn:timezone":"Asia/Bangkok",
    "iso:country":"TH",
    "name:tha_x_preferred":[
        "\u0e1a\u0e49\u0e32\u0e19\u0e2b\u0e19\u0e2d\u0e07\u0e1e\u0e38\u0e14\u0e0b\u0e32"
    ],
    "wof:name":"Ban Nong Phutsa",
    "wof:placetype":"locality"
},
  "geometry": {"coordinates":[102.09538999999999,14.91983],"type":"Point"}
}