{
  "type": "Feature",
  "properties": {
    "gn:admin1_code":"4.0",
    "gn:asciiname":"Ban Nam Khrai",
    "gn:country_code":"TH",
    "gn:dem":346,
    "gn:feature_class":"P",
    "gn:feature_code":"PPL",
    "gn:name":"Ban Nam Khrai",
    "gn:population":0,
    "gn:timezone":"Asia/Bangkok",
    "iso:country":"TH",
    "name:tha_x_preferred":[
        "\u0e1a\u0e49\u0e32\u0e19\u0e19\u0e49\u0e33\u0e44\u0e04\u0e23\u0e49"
    ],
    "name:und_x_variant":[
        "Ban Huai Khai",
        "Ban Huai Dai",
        "Ban Nam Khai",
        "Ban Nam Khrai"
    ],
    "wof:name":"Ban Nam Khrai",
    "wof:placetype":"locality"
},
  "geometry": {"coordinates":[100.92697,19.06067],"type":"Point"}
}