{
  "type": "Feature",
  "properties": {
    "gn:admin1_code":"75.0",
    "gn:asciiname":"Ban Si Khai Tok",
    "gn:country_code":"TH",
    "gn:dem":123,
    "gn:feature_class":"P",
    "gn:feature_code":"PPL",
    "gn:name":"Ban Si Khai Tok",
    "gn:population":0,
    "gn:timezone":"Asia/Bangkok",
    "iso:country":"TH",
    "name:tha_x_preferred":[
        "\u0e1a\u0e49\u0e32\u0e19\u0e28\u0e23\u0e35\u0e44\u0e04\u0e15\u0e01"
    ],
    "name:und_x_variant":[
        "Ban Si Khai"
    ],
    "wof:name":"Ban Si Khai Tok",
    "wof:placetype":"locality"
},
  "geometry": {"coordinates":[104.89856,15.10914],"type":"Point"}
}