{
  "type": "Feature",
  "properties": {
    "gn:admin1_code":"11.0",
    "gn:asciiname":"Ban Khong Wilai",
    "gn:country_code":"TH",
    "gn:dem":65,
    "gn:feature_class":"P",
    "gn:feature_code":"PPL",
    "gn:name":"Ban Khong Wilai",
    "gn:population":0,
    "gn:timezone":"Asia/Bangkok",
    "iso:country":"TH",
    "name:tha_x_preferred":[
        "\u0e1a\u0e49\u0e32\u0e19\u0e42\u0e04\u0e49\u0e07\u0e27\u0e34\u0e44\u0e25"
    ],
    "wof:name":"Ban Khong Wilai",
    "wof:placetype":"locality"
},
  "geometry": {"coordinates":[99.72022,16.15394],"type":"Point"}
}