{
  "type": "Feature",
  "properties": {
    "gn:admin1_code":"31.0",
    "gn:asciiname":"Ban Chum Bok",
    "gn:country_code":"TH",
    "gn:dem":4,
    "gn:feature_class":"P",
    "gn:feature_code":"PPL",
    "gn:name":"Ban Chum Bok",
    "gn:population":0,
    "gn:timezone":"Asia/Bangkok",
    "iso:country":"TH",
    "name:tha_x_preferred":[
        "\u0e1a\u0e49\u0e32\u0e19\u0e0a\u0e38\u0e21\u0e1a\u0e01"
    ],
    "wof:name":"Ban Chum Bok",
    "wof:placetype":"locality"
},
  "geometry": {"coordinates":[102.05533,6.20886],"type":"Point"}
}