{
  "type": "Feature",
  "properties": {
    "gn:admin1_code":"70.0",
    "gn:asciiname":"Ban Chalong Chai",
    "gn:country_code":"TH",
    "gn:dem":368,
    "gn:feature_class":"P",
    "gn:feature_code":"PPL",
    "gn:name":"Ban Chalong Chai",
    "gn:population":0,
    "gn:timezone":"Asia/Bangkok",
    "iso:country":"TH",
    "name:tha_x_preferred":[
        "\u0e1a\u0e49\u0e32\u0e19\u0e09\u0e25\u0e2d\u0e07\u0e0a\u0e31\u0e22"
    ],
    "wof:name":"Ban Chalong Chai",
    "wof:placetype":"locality"
},
  "geometry": {"coordinates":[101.31950000000001,6.14239],"type":"Point"}
}