{
  "type": "Feature",
  "properties": {
    "gn:admin1_code":"30.0",
    "gn:asciiname":"Ban Bueng Mok Noi",
    "gn:country_code":"TH",
    "gn:dem":128,
    "gn:feature_class":"P",
    "gn:feature_code":"PPL",
    "gn:name":"Ban Bueng Mok Noi",
    "gn:population":0,
    "gn:timezone":"Asia/Bangkok",
    "iso:country":"TH",
    "name:tha_x_preferred":[
        "\u0e1a\u0e49\u0e32\u0e19\u0e1a\u0e36\u0e07\u0e2b\u0e21\u0e2d\u0e01\u0e19\u0e49\u0e2d\u0e22"
    ],
    "wof:name":"Ban Bueng Mok Noi",
    "wof:placetype":"locality"
},
  "geometry": {"coordinates":[104.22131,15.30308],"type":"Point"}
}