{
  "type": "Feature",
  "properties": {
    "gn:admin1_code":"31.0",
    "gn:asciiname":"Ban Ya Ho",
    "gn:country_code":"TH",
    "gn:dem":40,
    "gn:feature_class":"P",
    "gn:feature_code":"PPL",
    "gn:name":"Ban Ya Ho",
    "gn:population":0,
    "gn:timezone":"Asia/Bangkok",
    "iso:country":"TH",
    "name:tha_x_preferred":[
        "\u0e1a\u0e49\u0e32\u0e19\u0e22\u0e30\u0e2b\u0e2d"
    ],
    "name:und_x_variant":[
        "Kampong Jaho",
        "Kampong Ya Hau",
        "Kampong Yaho",
        "Ban Ya Ho"
    ],
    "wof:name":"Ban Ya Ho",
    "wof:placetype":"locality"
},
  "geometry": {"coordinates":[101.75322,6.1995],"type":"Point"}
}