{
  "type": "Feature",
  "properties": {
    "gn:admin1_code":"63.0",
    "gn:asciiname":"Ban Huai Yung",
    "gn:country_code":"TH",
    "gn:dem":28,
    "gn:feature_class":"P",
    "gn:feature_code":"PPL",
    "gn:name":"Ban Huai Yung",
    "gn:population":0,
    "gn:timezone":"Asia/Bangkok",
    "iso:country":"TH",
    "name:tha_x_preferred":[
        "\u0e1a\u0e49\u0e32\u0e19\u0e2b\u0e49\u0e27\u0e22\u0e22\u0e39\u0e07"
    ],
    "name:und_x_variant":[
        "Huai Yung",
        "Ban Huai Yung"
    ],
    "wof:name":"Ban Huai Yung",
    "wof:placetype":"locality"
},
  "geometry": {"coordinates":[99.01817,8.10586],"type":"Point"}
}