{
  "type": "Feature",
  "properties": {
    "gn:admin1_code":"30.0",
    "gn:asciiname":"Ban Kong Luang",
    "gn:country_code":"TH",
    "gn:dem":145,
    "gn:feature_class":"P",
    "gn:feature_code":"PPL",
    "gn:name":"Ban Kong Luang",
    "gn:population":0,
    "gn:timezone":"Asia/Bangkok",
    "iso:country":"TH",
    "name:tha_x_preferred":[
        "\u0e1a\u0e49\u0e32\u0e19\u0e01\u0e2d\u0e07\u0e2b\u0e25\u0e27\u0e07"
    ],
    "wof:name":"Ban Kong Luang",
    "wof:placetype":"locality"
},
  "geometry": {"coordinates":[104.27028,14.83756],"type":"Point"}
}