{
  "type": "Feature",
  "properties": {
    "gn:admin1_code":"24",
    "gn:asciiname":"Ban Ba Luang",
    "gn:country_code":"TH",
    "gn:dem":170,
    "gn:feature_class":"P",
    "gn:feature_code":"PPL",
    "gn:name":"Ban Ba Luang",
    "gn:population":0,
    "gn:timezone":"Asia/Bangkok",
    "iso:country":"TH",
    "name:tha_x_preferred":[
        "\u0e1a\u0e49\u0e32\u0e19\u0e1a\u0e30\u0e2b\u0e25\u0e27\u0e07"
    ],
    "wof:name":"Ban Ba Luang",
    "wof:placetype":"locality"
},
  "geometry": {"coordinates":[102.93131,16.24814],"type":"Point"}
}