{
  "type": "Feature",
  "properties": {
    "gn:admin1_code":"66.0",
    "gn:asciiname":"Ban Nai Lo",
    "gn:country_code":"TH",
    "gn:dem":16,
    "gn:feature_class":"P",
    "gn:feature_code":"PPL",
    "gn:name":"Ban Nai Lo",
    "gn:population":0,
    "gn:timezone":"Asia/Bangkok",
    "iso:country":"TH",
    "name:tha_x_preferred":[
        "\u0e1a\u0e49\u0e32\u0e19\u0e43\u0e19\u0e42\u0e2b\u0e25\u0e4a\u0e30"
    ],
    "wof:name":"Ban Nai Lo",
    "wof:placetype":"locality"
},
  "geometry": {"coordinates":[100.03214,7.80156],"type":"Point"}
}