{
  "type": "Feature",
  "properties": {
    "gn:admin1_code":"44.0",
    "gn:asciiname":"Ban Ton Krachap",
    "gn:country_code":"TH",
    "gn:dem":10,
    "gn:feature_class":"P",
    "gn:feature_code":"PPL",
    "gn:name":"Ban Ton Krachap",
    "gn:population":0,
    "gn:timezone":"Asia/Bangkok",
    "iso:country":"TH",
    "name:tha_x_preferred":[
        "\u0e1a\u0e49\u0e32\u0e19\u0e15\u0e49\u0e19\u0e01\u0e23\u0e30\u0e08\u0e31\u0e1a"
    ],
    "wof:name":"Ban Ton Krachap",
    "wof:placetype":"locality"
},
  "geometry": {"coordinates":[101.34019000000001,13.70567],"type":"Point"}
}