{
  "type": "Feature",
  "properties": {
    "gn:admin1_code":"31.0",
    "gn:asciiname":"Ban Mai Fat",
    "gn:country_code":"TH",
    "gn:dem":22,
    "gn:feature_class":"P",
    "gn:feature_code":"PPL",
    "gn:name":"Ban Mai Fat",
    "gn:population":0,
    "gn:timezone":"Asia/Bangkok",
    "iso:country":"TH",
    "name:tha_x_preferred":[
        "\u0e1a\u0e49\u0e32\u0e19\u0e44\u0e21\u0e49\u0e1d\u0e32\u0e14"
    ],
    "wof:name":"Ban Mai Fat",
    "wof:placetype":"locality"
},
  "geometry": {"coordinates":[101.91992,5.97231],"type":"Point"}
}