{
  "type": "Feature",
  "properties": {
    "gn:admin1_code":"32.0",
    "gn:asciiname":"Ban Nong Yai Kok",
    "gn:country_code":"TH",
    "gn:dem":44,
    "gn:feature_class":"P",
    "gn:feature_code":"PPL",
    "gn:name":"Ban Nong Yai Kok",
    "gn:population":0,
    "gn:timezone":"Asia/Bangkok",
    "iso:country":"TH",
    "name:tha_x_preferred":[
        "\u0e1a\u0e49\u0e32\u0e19\u0e2b\u0e19\u0e2d\u0e07\u0e22\u0e32\u0e22\u0e01\u0e01"
    ],
    "wof:name":"Ban Nong Yai Kok",
    "wof:placetype":"locality"
},
  "geometry": {"coordinates":[99.86686,15.21869],"type":"Point"}
}