{
  "type": "Feature",
  "properties": {
    "gn:admin1_code":"27.0",
    "gn:asciiname":"Ban Khok Nong Phai",
    "gn:cc2":"TH",
    "gn:country_code":"TH",
    "gn:dem":193,
    "gn:feature_class":"P",
    "gn:feature_code":"PPL",
    "gn:name":"Ban Khok Nong Phai",
    "gn:population":0,
    "gn:timezone":"Asia/Bangkok",
    "iso:country":"TH",
    "name:und_x_variant":[
        "Ban Nong Phai",
        "Ban Khok Nong Phai"
    ],
    "wof:name":"Ban Khok Nong Phai",
    "wof:placetype":"locality"
},
  "geometry": {"coordinates":[101.98083,15.21611],"type":"Point"}
}