{
  "type": "Feature",
  "properties": {
    "gn:admin1_code":"31.0",
    "gn:asciiname":"Ban Ka Teng",
    "gn:country_code":"TH",
    "gn:dem":41,
    "gn:feature_class":"P",
    "gn:feature_code":"PPL",
    "gn:name":"Ban Ka Teng",
    "gn:population":0,
    "gn:timezone":"Asia/Bangkok",
    "iso:country":"TH",
    "name:tha_x_preferred":[
        "\u0e1a\u0e49\u0e32\u0e19\u0e01\u0e30\u0e40\u0e15\u0e47\u0e07"
    ],
    "name:tha_x_variant":[
        "\u0e1a\u0e49\u0e32\u0e19\u0e0b\u0e32\u0e42\u0e01\u0e4a\u0e30"
    ],
    "name:und_x_variant":[
        "Ban Sa Ko"
    ],
    "wof:name":"Ban Ka Teng",
    "wof:placetype":"locality"
},
  "geometry": {"coordinates":[101.50086,6.30153],"type":"Point"}
}