{
  "type": "Feature",
  "properties": {
    "gn:admin1_code":"23.0",
    "gn:asciiname":"Ban Dong Klang",
    "gn:country_code":"TH",
    "gn:dem":186,
    "gn:feature_class":"P",
    "gn:feature_code":"PPL",
    "gn:name":"Ban Dong Klang",
    "gn:population":0,
    "gn:timezone":"Asia/Bangkok",
    "iso:country":"TH",
    "name:tha_x_preferred":[
        "\u0e1a\u0e49\u0e32\u0e19\u0e14\u0e07\u0e01\u0e25\u0e32\u0e07"
    ],
    "wof:name":"Ban Dong Klang",
    "wof:placetype":"locality"
},
  "geometry": {"coordinates":[103.37824999999999,16.8865],"type":"Point"}
}