{
  "type": "Feature",
  "properties": {
    "gn:admin1_code":"55.0",
    "gn:asciiname":"Muban Siwarat",
    "gn:country_code":"TH",
    "gn:dem":6,
    "gn:feature_class":"P",
    "gn:feature_code":"PPL",
    "gn:name":"Muban Siwarat",
    "gn:population":0,
    "gn:timezone":"Asia/Bangkok",
    "iso:country":"TH",
    "name:tha_x_preferred":[
        "\u0e2b\u0e21\u0e39\u0e48\u0e1a\u0e49\u0e32\u0e19\u0e28\u0e34\u0e27\u0e30\u0e23\u0e31\u0e15\u0e19\u0e4c"
    ],
    "wof:name":"Muban Siwarat",
    "wof:placetype":"locality"
},
  "geometry": {"coordinates":[100.29492,13.57683],"type":"Point"}
}