{
  "type": "Feature",
  "properties": {
    "gn:admin1_code":"75.0",
    "gn:asciiname":"Ban Talat",
    "gn:country_code":"TH",
    "gn:dem":145,
    "gn:feature_class":"P",
    "gn:feature_code":"PPL",
    "gn:name":"Ban Talat",
    "gn:population":0,
    "gn:timezone":"Asia/Bangkok",
    "iso:country":"TH",
    "name:tha_x_preferred":[
        "\u0e1a\u0e49\u0e32\u0e19\u0e15\u0e25\u0e32\u0e14"
    ],
    "name:und_x_variant":[
        "Ban Tha Lat",
        "Ban Talat"
    ],
    "wof:name":"Ban Talat",
    "wof:placetype":"locality"
},
  "geometry": {"coordinates":[104.76008,14.95353],"type":"Point"}
}