{
  "type": "Feature",
  "properties": {
    "gn:admin1_code":"14.0",
    "gn:asciiname":"Ban Lam Pa Sak Mun",
    "gn:country_code":"TH",
    "gn:dem":125,
    "gn:feature_class":"P",
    "gn:feature_code":"PPL",
    "gn:name":"Ban Lam Pa Sak Mun",
    "gn:population":0,
    "gn:timezone":"Asia/Bangkok",
    "iso:country":"TH",
    "name:tha_x_preferred":[
        "\u0e1a\u0e49\u0e32\u0e19\u0e25\u0e33\u0e1b\u0e48\u0e32\u0e2a\u0e31\u0e01\u0e21\u0e39\u0e25"
    ],
    "name:und_x_variant":[
        "Ban Lam Pa Sak"
    ],
    "wof:name":"Ban Lam Pa Sak Mun",
    "wof:placetype":"locality"
},
  "geometry": {"coordinates":[101.21303,16.50074],"type":"Point"}
}