{
  "type": "Feature",
  "properties": {
    "gn:admin1_code":"9.0",
    "gn:asciiname":"Ban Phai Wong Khong",
    "gn:country_code":"TH",
    "gn:dem":50,
    "gn:feature_class":"P",
    "gn:feature_code":"PPL",
    "gn:name":"Ban Phai Wong Khong",
    "gn:population":0,
    "gn:timezone":"Asia/Bangkok",
    "iso:country":"TH",
    "name:tha_x_preferred":[
        "\u0e1a\u0e49\u0e32\u0e19\u0e44\u0e1c\u0e48\u0e27\u0e07\u0e06\u0e49\u0e2d\u0e07"
    ],
    "wof:name":"Ban Phai Wong Khong",
    "wof:placetype":"locality"
},
  "geometry": {"coordinates":[99.93047,16.99014],"type":"Point"}
}