{
  "type": "Feature",
  "properties": {
    "gn:admin1_code":"28.0",
    "gn:asciiname":"Ban Thawon",
    "gn:country_code":"TH",
    "gn:dem":217,
    "gn:feature_class":"P",
    "gn:feature_code":"PPL",
    "gn:name":"Ban Thawon",
    "gn:population":0,
    "gn:timezone":"Asia/Bangkok",
    "iso:country":"TH",
    "name:tha_x_preferred":[
        "\u0e1a\u0e49\u0e32\u0e19\u0e16\u0e32\u0e27\u0e23"
    ],
    "wof:name":"Ban Thawon",
    "wof:placetype":"locality"
},
  "geometry": {"coordinates":[102.85192000000001,14.51164],"type":"Point"}
}