{
  "type": "Feature",
  "properties": {
    "gn:admin1_code":"27",
    "gn:asciiname":"Ban Wara Wiang",
    "gn:country_code":"TH",
    "gn:dem":205,
    "gn:feature_class":"P",
    "gn:feature_code":"PPL",
    "gn:name":"Ban Wara Wiang",
    "gn:population":0,
    "gn:timezone":"Asia/Bangkok",
    "iso:country":"TH",
    "name:tha_x_preferred":[
        "\u0e1a\u0e49\u0e32\u0e19\u0e27\u0e30\u0e23\u0e30\u0e40\u0e27\u0e35\u0e22\u0e07"
    ],
    "wof:name":"Ban Wara Wiang",
    "wof:placetype":"locality"
},
  "geometry": {"coordinates":[101.42281,15.07253],"type":"Point"}
}