{
  "type": "Feature",
  "properties": {
    "gn:admin1_code":"5.0",
    "gn:asciiname":"Ban Ko Faen",
    "gn:country_code":"TH",
    "gn:dem":356,
    "gn:feature_class":"P",
    "gn:feature_code":"PPL",
    "gn:name":"Ban Ko Faen",
    "gn:population":0,
    "gn:timezone":"Asia/Bangkok",
    "iso:country":"TH",
    "name:tha_x_preferred":[
        "\u0e1a\u0e49\u0e32\u0e19\u0e01\u0e2d\u0e41\u0e1f\u0e19"
    ],
    "wof:name":"Ban Ko Faen",
    "wof:placetype":"locality"
},
  "geometry": {"coordinates":[99.03883,18.42222000000001],"type":"Point"}
}