{
  "type": "Feature",
  "properties": {
    "gn:admin1_code":"36",
    "gn:asciiname":"Ban Bang Khian",
    "gn:country_code":"TH",
    "gn:dem":4,
    "gn:feature_class":"P",
    "gn:feature_code":"PPL",
    "gn:name":"Ban Bang Khian",
    "gn:population":0,
    "gn:timezone":"Asia/Bangkok",
    "iso:country":"TH",
    "name:tha_x_preferred":[
        "\u0e1a\u0e49\u0e32\u0e19\u0e1a\u0e32\u0e07\u0e40\u0e04\u0e35\u0e22\u0e19"
    ],
    "wof:name":"Ban Bang Khian",
    "wof:placetype":"locality"
},
  "geometry": {"coordinates":[100.55031,14.18914],"type":"Point"}
}