{
  "type": "Feature",
  "properties": {
    "gn:admin1_code":"75.0",
    "gn:asciiname":"Ban Non Nat",
    "gn:country_code":"TH",
    "gn:dem":145,
    "gn:feature_class":"P",
    "gn:feature_code":"PPL",
    "gn:name":"Ban Non Nat",
    "gn:population":0,
    "gn:timezone":"Asia/Bangkok",
    "iso:country":"TH",
    "name:tha_x_preferred":[
        "\u0e1a\u0e49\u0e32\u0e19\u0e42\u0e19\u0e19\u0e2b\u0e19\u0e32\u0e14"
    ],
    "wof:name":"Ban Non Nat",
    "wof:placetype":"locality"
},
  "geometry": {"coordinates":[104.91258000000001,14.95456],"type":"Point"}
}