{
  "type": "Feature",
  "properties": {
    "gn:admin1_code":"64.0",
    "gn:asciiname":"Ban Samet Ngam",
    "gn:country_code":"TH",
    "gn:dem":0,
    "gn:feature_class":"P",
    "gn:feature_code":"PPL",
    "gn:name":"Ban Samet Ngam",
    "gn:population":0,
    "gn:timezone":"Asia/Bangkok",
    "iso:country":"TH",
    "name:tha_x_preferred":[
        "\u0e1a\u0e49\u0e32\u0e19\u0e40\u0e2a\u0e21\u0e47\u0e14\u0e07\u0e32\u0e21"
    ],
    "wof:name":"Ban Samet Ngam",
    "wof:placetype":"locality"
},
  "geometry": {"coordinates":[100.13958,7.96769],"type":"Point"}
}