{
  "type": "Feature",
  "properties": {
    "gn:admin1_code":"22",
    "gn:asciiname":"Ban Non Ku",
    "gn:country_code":"TH",
    "gn:dem":194,
    "gn:feature_class":"P",
    "gn:feature_code":"PPL",
    "gn:name":"Ban Non Ku",
    "gn:population":0,
    "gn:timezone":"Asia/Bangkok",
    "iso:country":"TH",
    "name:tha_x_preferred":[
        "\u0e1a\u0e49\u0e32\u0e19\u0e42\u0e19\u0e19\u0e01\u0e39\u0e48"
    ],
    "wof:name":"Ban Non Ku",
    "wof:placetype":"locality"
},
  "geometry": {"coordinates":[102.66442000000001,16.51094],"type":"Point"}
}