{
  "type": "Feature",
  "properties": {
    "iso:country":"TH",
    "qs:name":"Pak Nam Lang Suan",
    "qs:name_adm0":"Thailand",
    "qs:name_adm1":"Chumphon",
    "qs:photos":5,
    "qs:photos_1k":1,
    "qs:photos_9k":1,
    "qs:photos_9r":1,
    "qs:photos_all":5,
    "qs:photos_sr":1,
    "qs:placetype":"Town",
    "qs:pop_sr":"0",
    "wof:name":"Pak Nam Lang Suan",
    "wof:placetype":"locality"
},
  "geometry": {"coordinates":[99.160708,9.938752],"type":"Point"}
}