{
  "type": "Feature",
  "properties": {
    "gn:admin1_code":"11.0",
    "gn:asciiname":"Ban Nong Puen Taek",
    "gn:country_code":"TH",
    "gn:dem":57,
    "gn:feature_class":"P",
    "gn:feature_code":"PPL",
    "gn:name":"Ban Nong Puen Taek",
    "gn:population":0,
    "gn:timezone":"Asia/Bangkok",
    "iso:country":"TH",
    "name:tha_x_preferred":[
        "\u0e1a\u0e49\u0e32\u0e19\u0e2b\u0e19\u0e2d\u0e07\u0e1b\u0e37\u0e19\u0e41\u0e15\u0e01"
    ],
    "wof:name":"Ban Nong Puen Taek",
    "wof:placetype":"locality"
},
  "geometry": {"coordinates":[99.91319,16.42169],"type":"Point"}
}