{
  "type": "Feature",
  "properties": {
    "gn:admin1_code":"7.0",
    "gn:asciiname":"Ban Na Khu Ha",
    "gn:country_code":"TH",
    "gn:dem":612,
    "gn:feature_class":"P",
    "gn:feature_code":"PPL",
    "gn:name":"Ban Na Khu Ha",
    "gn:population":0,
    "gn:timezone":"Asia/Bangkok",
    "iso:country":"TH",
    "name:tha_x_preferred":[
        "\u0e1a\u0e49\u0e32\u0e19\u0e19\u0e32\u0e04\u0e39\u0e2b\u0e32"
    ],
    "wof:name":"Ban Na Khu Ha",
    "wof:placetype":"locality"
},
  "geometry": {"coordinates":[100.31292000000001,18.12492],"type":"Point"}
}