{
  "type": "Feature",
  "properties": {
    "gn:admin1_code":"31.0",
    "gn:asciiname":"Ban Kho Lo Thu Wo",
    "gn:country_code":"TH",
    "gn:dem":23,
    "gn:feature_class":"P",
    "gn:feature_code":"PPL",
    "gn:name":"Ban Kho Lo Thu Wo",
    "gn:population":0,
    "gn:timezone":"Asia/Bangkok",
    "iso:country":"TH",
    "name:tha_x_preferred":[
        "\u0e1a\u0e49\u0e32\u0e19\u0e06\u0e2d\u0e40\u0e25\u0e32\u0e30\u0e17\u0e39\u0e27\u0e2d"
    ],
    "wof:lang_x_official":[
        "tha"
    ],
    "wof:lang_x_spoken":[
        "tha"
    ],
    "wof:name":"Ban Kho Lo Thu Wo",
    "wof:placetype":"locality"
},
  "geometry": {"coordinates":[101.89933000000001,5.93658],"type":"Point"}
}