{
  "type": "Feature",
  "properties": {
    "gn:country":"TH",
    "gn:fcode":"PPLA2",
    "gn:population":0,
    "iso:country":"TH",
    "name:bpy_x_preferred":[
        "\u0986\u09ae\u09cd\u09ab\u09cb\u09af\u09bc\u09c7 \u09a8\u09be \u09ae\u09c1\u09af\u09bc\u09c7\u09a8"
    ],
    "name:ceb_x_preferred":[
        "Amphoe Na Muen"
    ],
    "name:deu_x_preferred":[
        "Amphoe Na Muen"
    ],
    "name:eng_x_preferred":[
        "Na Muen"
    ],
    "name:fra_x_preferred":[
        "Na Muen"
    ],
    "name:jpn_x_preferred":[
        "\u30ca\u30fc\u30e0\u30fc\u30f3\u90e1"
    ],
    "name:nan_x_preferred":[
        "Na Muen K\u016bn"
    ],
    "name:ron_x_preferred":[
        "Districtul Na Muen"
    ],
    "name:tha_x_preferred":[
        "\u0e19\u0e32\u0e2b\u0e21\u0e37\u0e48\u0e19"
    ],
    "name:tha_x_variant":[
        "\u0e2d\u0e33\u0e40\u0e20\u0e2d\u0e19\u0e32\u0e2b\u0e21\u0e37\u0e48\u0e19"
    ],
    "name:und_x_variant":[
        "Ban Na Lak Mun"
    ],
    "name:urd_x_preferred":[
        "\u0646\u0627 \u0645\u0648\u0626\u0646 \u0636\u0644\u0639"
    ],
    "name:vie_x_preferred":[
        "Na Muen"
    ],
    "qs:name":"Na Muen",
    "qs:photos_9r":0,
    "qs:photos_sr":0,
    "qs:pop_sr":"0",
    "wd:wordcount":181,
    "wof:name":"Na Muen",
    "wof:placetype":"locality",
    "wof:population":0
},
  "geometry": {"coordinates":[100.66047,18.18931],"type":"Point"}
}