{
  "type": "Feature",
  "properties": {
    "gn:country":"TH",
    "gn:fcode":"PPLA2",
    "gn:pop":0,
    "iso:country":"TH",
    "name:tha_x_preferred":[
        "\u0e19\u0e32\u0e2b\u0e21\u0e37\u0e48\u0e19"
    ],
    "name:unk_x_variant":[
        "Ban Na Lak Mun"
    ],
    "qs:name":"Na Muen",
    "qs:photos_9r":0,
    "qs:photos_sr":0,
    "qs:pop_sr":"0",
    "wd:wordcount":181,
    "wof:name":"Na Muen",
    "wof:placetype":"locality",
    "wof:population":0
},
  "geometry": {"coordinates":[100.66047,18.18931],"type":"Point"}
}