{
  "type": "Feature",
  "properties": {
    "gn:admin1_code":"68.0",
    "gn:asciiname":"Ban Nikhom Sang Toneng Thepha",
    "gn:country_code":"TH",
    "gn:dem":12,
    "gn:feature_class":"P",
    "gn:feature_code":"PPL",
    "gn:name":"Ban Nikhom Sang Toneng Thepha",
    "gn:population":0,
    "gn:timezone":"Asia/Bangkok",
    "iso:country":"TH",
    "name:tha_x_preferred":[
        "\u0e1a\u0e49\u0e32\u0e19\u0e19\u0e34\u0e04\u0e21\u0e2a\u0e23\u0e49\u0e32\u0e07\u0e15\u0e19\u0e40\u0e2d\u0e07\u0e40\u0e17\u0e1e\u0e32"
    ],
    "wof:name":"Ban Nikhom Sang Toneng Thepha",
    "wof:placetype":"locality"
},
  "geometry": {"coordinates":[100.98217,6.75925],"type":"Point"}
}