{
  "type": "Feature",
  "properties": {
    "gn:admin1_code":"65.0",
    "gn:asciiname":"Ban Khao Phlu",
    "gn:country_code":"TH",
    "gn:dem":22,
    "gn:feature_class":"P",
    "gn:feature_code":"PPL",
    "gn:name":"Ban Khao Phlu",
    "gn:population":0,
    "gn:timezone":"Asia/Bangkok",
    "iso:country":"TH",
    "name:tha_x_preferred":[
        "\u0e1a\u0e49\u0e32\u0e19\u0e40\u0e02\u0e32\u0e1e\u0e25\u0e39"
    ],
    "wof:name":"Ban Khao Phlu",
    "wof:placetype":"locality"
},
  "geometry": {"coordinates":[99.39742,7.4165],"type":"Point"}
}