{
  "type": "Feature",
  "properties": {
    "gn:admin1_code":"14.0",
    "gn:asciiname":"Ban Dan Charoen Chai",
    "gn:country_code":"TH",
    "gn:dem":87,
    "gn:feature_class":"P",
    "gn:feature_code":"PPL",
    "gn:name":"Ban Dan Charoen Chai",
    "gn:population":0,
    "gn:timezone":"Asia/Bangkok",
    "iso:country":"TH",
    "name:tha_x_preferred":[
        "\u0e1a\u0e49\u0e32\u0e19\u0e14\u0e48\u0e32\u0e19\u0e40\u0e08\u0e23\u0e34\u0e0d\u0e0a\u0e31\u0e22"
    ],
    "wof:name":"Ban Dan Charoen Chai",
    "wof:placetype":"locality"
},
  "geometry": {"coordinates":[101.26964,15.39775],"type":"Point"}
}