{
  "type": "Feature",
  "properties": {
    "gn:admin1_code":"44.0",
    "gn:asciiname":"Ban Huai Nam Sai",
    "gn:country_code":"TH",
    "gn:dem":43,
    "gn:feature_class":"P",
    "gn:feature_code":"PPL",
    "gn:name":"Ban Huai Nam Sai",
    "gn:population":0,
    "gn:timezone":"Asia/Bangkok",
    "iso:country":"TH",
    "name:tha_x_preferred":[
        "\u0e1a\u0e49\u0e32\u0e19\u0e2b\u0e49\u0e27\u0e22\u0e19\u0e49\u0e33\u0e43\u0e2a"
    ],
    "wof:name":"Ban Huai Nam Sai",
    "wof:placetype":"locality"
},
  "geometry": {"coordinates":[101.47108,13.58603],"type":"Point"}
}