{
  "type": "Feature",
  "properties": {
    "gn:admin1_code":"63.0",
    "gn:asciiname":"Ban Thap Prik",
    "gn:country_code":"TH",
    "gn:dem":48,
    "gn:feature_class":"P",
    "gn:feature_code":"PPL",
    "gn:name":"Ban Thap Prik",
    "gn:population":0,
    "gn:timezone":"Asia/Bangkok",
    "iso:country":"TH",
    "name:tha_x_preferred":[
        "\u0e1a\u0e49\u0e32\u0e19\u0e17\u0e31\u0e1a\u0e1b\u0e23\u0e34\u0e01"
    ],
    "wof:name":"Ban Thap Prik",
    "wof:placetype":"locality"
},
  "geometry": {"coordinates":[98.87653,8.20172],"type":"Point"}
}