{
  "type": "Feature",
  "properties": {
    "gn:admin1_code":"49.0",
    "gn:asciiname":"Ban Huai Ta Lam",
    "gn:country_code":"TH",
    "gn:dem":20,
    "gn:feature_class":"P",
    "gn:feature_code":"PPL",
    "gn:name":"Ban Huai Ta Lam",
    "gn:population":0,
    "gn:timezone":"Asia/Bangkok",
    "iso:country":"TH",
    "name:tha_x_preferred":[
        "\u0e1a\u0e49\u0e32\u0e19\u0e2b\u0e49\u0e27\u0e22\u0e15\u0e32\u0e2b\u0e25\u0e33"
    ],
    "wof:name":"Ban Huai Ta Lam",
    "wof:placetype":"locality"
},
  "geometry": {"coordinates":[102.45858,12.33189],"type":"Point"}
}