{
  "type": "Feature",
  "properties": {
    "gn:admin1_code":"7.0",
    "gn:asciiname":"Ban Khok Chang",
    "gn:country_code":"TH",
    "gn:dem":129,
    "gn:feature_class":"P",
    "gn:feature_code":"PPL",
    "gn:name":"Ban Khok Chang",
    "gn:population":0,
    "gn:timezone":"Asia/Bangkok",
    "iso:country":"TH",
    "name:tha_x_preferred":[
        "\u0e1a\u0e49\u0e32\u0e19\u0e04\u0e2d\u0e01\u0e0a\u0e49\u0e32\u0e07"
    ],
    "wof:name":"Ban Khok Chang",
    "wof:placetype":"locality"
},
  "geometry": {"coordinates":[99.83722,18.067],"type":"Point"}
}