{
  "type": "Feature",
  "properties": {
    "gn:admin1_code":"56.0",
    "gn:asciiname":"Ban Khao Bandai",
    "gn:country_code":"TH",
    "gn:dem":140,
    "gn:feature_class":"P",
    "gn:feature_code":"PPL",
    "gn:name":"Ban Khao Bandai",
    "gn:population":0,
    "gn:timezone":"Asia/Bangkok",
    "iso:country":"TH",
    "name:tha_x_preferred":[
        "\u0e1a\u0e49\u0e32\u0e19\u0e40\u0e02\u0e32\u0e1a\u0e31\u0e19\u0e44\u0e14"
    ],
    "wof:name":"Ban Khao Bandai",
    "wof:placetype":"locality"
},
  "geometry": {"coordinates":[99.70081,13.24097],"type":"Point"}
}