{
  "type": "Feature",
  "properties": {
    "gn:admin1_code":"56.0",
    "gn:asciiname":"Ban Khao Laem",
    "gn:country_code":"TH",
    "gn:dem":237,
    "gn:feature_class":"P",
    "gn:feature_code":"PPL",
    "gn:name":"Ban Khao Laem",
    "gn:population":0,
    "gn:timezone":"Asia/Bangkok",
    "iso:country":"TH",
    "name:tha_x_preferred":[
        "\u0e1a\u0e49\u0e32\u0e19\u0e40\u0e02\u0e32\u0e41\u0e2b\u0e25\u0e21"
    ],
    "wof:name":"Ban Khao Laem",
    "wof:placetype":"locality"
},
  "geometry": {"coordinates":[99.57241999999999,12.6575],"type":"Point"}
}