{
  "type": "Feature",
  "properties": {
    "gn:admin1_code":"28",
    "gn:asciiname":"Ban Maitri Chit",
    "gn:country_code":"TH",
    "gn:dem":141,
    "gn:feature_class":"P",
    "gn:feature_code":"PPL",
    "gn:name":"Ban Maitri Chit",
    "gn:population":0,
    "gn:timezone":"Asia/Bangkok",
    "iso:country":"TH",
    "name:tha_x_preferred":[
        "\u0e1a\u0e49\u0e32\u0e19\u0e44\u0e21\u0e15\u0e23\u0e35\u0e08\u0e34\u0e15\u0e23"
    ],
    "wof:name":"Ban Maitri Chit",
    "wof:placetype":"locality"
},
  "geometry": {"coordinates":[103.13339000000001,15.32378],"type":"Point"}
}