{
  "type": "Feature",
  "properties": {
    "gn:admin1_code":"40.0",
    "gn:admin2_code":"1003",
    "gn:asciiname":"Ban Sam Ngam",
    "gn:country_code":"TH",
    "gn:dem":8,
    "gn:feature_class":"P",
    "gn:feature_code":"PPL",
    "gn:name":"Ban Sam Ngam",
    "gn:population":0,
    "gn:timezone":"Asia/Bangkok",
    "iso:country":"TH",
    "name:tha_x_preferred":[
        "\u0e1a\u0e49\u0e32\u0e19\u0e2a\u0e32\u0e21\u0e07\u0e48\u0e32\u0e21"
    ],
    "wof:name":"Ban Sam Ngam",
    "wof:placetype":"locality"
},
  "geometry": {"coordinates":[100.80922,13.88997],"type":"Point"}
}