{
  "type": "Feature",
  "properties": {
    "gn:admin1_code":"10.0",
    "gn:asciiname":"Ban Hat Kai Toi",
    "gn:country_code":"TH",
    "gn:dem":107,
    "gn:feature_class":"P",
    "gn:feature_code":"PPL",
    "gn:name":"Ban Hat Kai Toi",
    "gn:population":0,
    "gn:timezone":"Asia/Bangkok",
    "iso:country":"TH",
    "name:tha_x_preferred":[
        "\u0e1a\u0e49\u0e32\u0e19\u0e2b\u0e32\u0e14\u0e44\u0e01\u0e48\u0e15\u0e49\u0e2d\u0e22"
    ],
    "name:und_x_variant":[
        "B\u0101n H\u0101t G\u0101i Toi",
        "Ban Hat Kai Toi"
    ],
    "wof:name":"Ban Hat Kai Toi",
    "wof:placetype":"locality"
},
  "geometry": {"coordinates":[100.34343,17.7571],"type":"Point"}
}