{
  "type": "Feature",
  "properties": {
    "gn:admin1_code":"33.0",
    "gn:asciiname":"Ban Ok Roi",
    "gn:country_code":"TH",
    "gn:dem":12,
    "gn:feature_class":"P",
    "gn:feature_code":"PPL",
    "gn:name":"Ban Ok Roi",
    "gn:population":0,
    "gn:timezone":"Asia/Bangkok",
    "iso:country":"TH",
    "name:tha_x_preferred":[
        "\u0e1a\u0e49\u0e32\u0e19\u0e2d\u0e01\u0e42\u0e23\u0e22"
    ],
    "name:und_x_variant":[
        "Ban Ok Roi Tok",
        "Ban Ok Roi"
    ],
    "wof:name":"Ban Ok Roi",
    "wof:placetype":"locality"
},
  "geometry": {"coordinates":[100.42147,14.76303],"type":"Point"}
}