{
  "type": "Feature",
  "properties": {
    "gn:admin1_code":"30.0",
    "gn:asciiname":"Ban Ta Hing",
    "gn:country_code":"TH",
    "gn:dem":166,
    "gn:feature_class":"P",
    "gn:feature_code":"PPL",
    "gn:name":"Ban Ta Hing",
    "gn:population":0,
    "gn:timezone":"Asia/Bangkok",
    "iso:country":"TH",
    "name:tha_x_preferred":[
        "\u0e1a\u0e49\u0e32\u0e19\u0e15\u0e32\u0e2e\u0e34\u0e07"
    ],
    "wof:name":"Ban Ta Hing",
    "wof:placetype":"locality"
},
  "geometry": {"coordinates":[104.27845000000001,14.63633],"type":"Point"}
}