{
  "type": "Feature",
  "properties": {
    "gn:admin1_code":"3.0",
    "gn:asciiname":"Ban Chom Kitti",
    "gn:country_code":"TH",
    "gn:dem":377,
    "gn:feature_class":"P",
    "gn:feature_code":"PPL",
    "gn:name":"Ban Chom Kitti",
    "gn:population":0,
    "gn:timezone":"Asia/Bangkok",
    "iso:country":"TH",
    "name:tha_x_preferred":[
        "\u0e1a\u0e49\u0e32\u0e19\u0e08\u0e2d\u0e21\u0e01\u0e34\u0e15\u0e15\u0e34"
    ],
    "wof:name":"Ban Chom Kitti",
    "wof:placetype":"locality"
},
  "geometry": {"coordinates":[100.07353000000001,20.28153],"type":"Point"}
}