{
  "type": "Feature",
  "properties": {
    "gn:admin1_code":"24",
    "gn:asciiname":"Ban Don Khamin",
    "gn:country_code":"TH",
    "gn:dem":154,
    "gn:feature_class":"P",
    "gn:feature_code":"PPL",
    "gn:name":"Ban Don Khamin",
    "gn:population":0,
    "gn:timezone":"Asia/Bangkok",
    "iso:country":"TH",
    "name:tha_x_preferred":[
        "\u0e1a\u0e49\u0e32\u0e19\u0e14\u0e2d\u0e19\u0e02\u0e21\u0e34\u0e49\u0e19"
    ],
    "wof:name":"Ban Don Khamin",
    "wof:placetype":"locality"
},
  "geometry": {"coordinates":[103.29694000000001,16.35431],"type":"Point"}
}