{
  "type": "Feature",
  "properties": {
    "gn:admin1_code":"12.0",
    "gn:asciiname":"Ban Noen Makha",
    "gn:country_code":"TH",
    "gn:dem":73,
    "gn:feature_class":"P",
    "gn:feature_code":"PPL",
    "gn:name":"Ban Noen Makha",
    "gn:population":0,
    "gn:timezone":"Asia/Bangkok",
    "iso:country":"TH",
    "name:tha_x_preferred":[
        "\u0e1a\u0e49\u0e32\u0e19\u0e40\u0e19\u0e34\u0e19\u0e21\u0e30\u0e04\u0e48\u0e32"
    ],
    "wof:name":"Ban Noen Makha",
    "wof:placetype":"locality"
},
  "geometry": {"coordinates":[100.65131,16.44339],"type":"Point"}
}