{
  "type": "Feature",
  "properties": {
    "gn:admin1_code":"44.0",
    "gn:asciiname":"Ban Tha Sung Bon",
    "gn:country_code":"TH",
    "gn:dem":38,
    "gn:feature_class":"P",
    "gn:feature_code":"PPL",
    "gn:name":"Ban Tha Sung Bon",
    "gn:population":0,
    "gn:timezone":"Asia/Bangkok",
    "iso:country":"TH",
    "name:tha_x_preferred":[
        "\u0e1a\u0e49\u0e32\u0e19\u0e17\u0e48\u0e32\u0e0b\u0e38\u0e07\u0e1a\u0e2d\u0e19"
    ],
    "wof:name":"Ban Tha Sung Bon",
    "wof:placetype":"locality"
},
  "geometry": {"coordinates":[101.51421999999999,13.56031],"type":"Point"}
}