{
  "type": "Feature",
  "properties": {
    "gn:admin1_code":"5.0",
    "gn:asciiname":"Ban Nong Yuang",
    "gn:country_code":"TH",
    "gn:dem":290,
    "gn:feature_class":"P",
    "gn:feature_code":"PPL",
    "gn:name":"Ban Nong Yuang",
    "gn:population":0,
    "gn:timezone":"Asia/Bangkok",
    "iso:country":"TH",
    "name:tha_x_preferred":[
        "\u0e1a\u0e49\u0e32\u0e19\u0e2b\u0e19\u0e2d\u0e07\u0e22\u0e27\u0e07"
    ],
    "wof:name":"Ban Nong Yuang",
    "wof:placetype":"locality"
},
  "geometry": {"coordinates":[98.79358000000001,18.42572],"type":"Point"}
}