{
  "type": "Feature",
  "properties": {
    "gn:admin1_code":"39.0",
    "gn:asciiname":"Muban Than Samai",
    "gn:country_code":"TH",
    "gn:dem":9,
    "gn:feature_class":"P",
    "gn:feature_code":"PPL",
    "gn:name":"Muban Than Samai",
    "gn:population":0,
    "gn:timezone":"Asia/Bangkok",
    "iso:country":"TH",
    "name:tha_x_preferred":[
        "\u0e2b\u0e21\u0e39\u0e48\u0e1a\u0e49\u0e32\u0e19\u0e17\u0e31\u0e19\u0e2a\u0e21\u0e31\u0e22"
    ],
    "wof:name":"Muban Than Samai",
    "wof:placetype":"locality"
},
  "geometry": {"coordinates":[100.48169,13.96225],"type":"Point"}
}