{
  "type": "Feature",
  "properties": {
    "gn:admin1_code":"75.0",
    "gn:asciiname":"Ban Thap Thai",
    "gn:country_code":"TH",
    "gn:dem":117,
    "gn:feature_class":"P",
    "gn:feature_code":"PPL",
    "gn:name":"Ban Thap Thai",
    "gn:population":0,
    "gn:timezone":"Asia/Bangkok",
    "iso:country":"TH",
    "name:tha_x_preferred":[
        "\u0e1a\u0e49\u0e32\u0e19\u0e17\u0e31\u0e1e\u0e44\u0e17\u0e22"
    ],
    "wof:name":"Ban Thap Thai",
    "wof:placetype":"locality"
},
  "geometry": {"coordinates":[104.81658,15.22119],"type":"Point"}
}