{
  "type": "Feature",
  "properties": {
    "gn:admin1_code":"14.0",
    "gn:asciiname":"Ban Noen Ta Paen",
    "gn:country_code":"TH",
    "gn:dem":87,
    "gn:feature_class":"P",
    "gn:feature_code":"PPL",
    "gn:name":"Ban Noen Ta Paen",
    "gn:population":0,
    "gn:timezone":"Asia/Bangkok",
    "iso:country":"TH",
    "name:tha_x_preferred":[
        "\u0e1a\u0e49\u0e32\u0e19\u0e40\u0e19\u0e34\u0e19\u0e15\u0e32\u0e41\u0e1b\u0e49\u0e19"
    ],
    "wof:name":"Ban Noen Ta Paen",
    "wof:placetype":"locality"
},
  "geometry": {"coordinates":[100.77956,16.07817],"type":"Point"}
}