{
  "type": "Feature",
  "properties": {
    "gn:admin1_code":"3.0",
    "gn:asciiname":"Ban Pa Rai",
    "gn:country_code":"TH",
    "gn:dem":372,
    "gn:feature_class":"P",
    "gn:feature_code":"PPL",
    "gn:name":"Ban Pa Rai",
    "gn:population":0,
    "gn:timezone":"Asia/Bangkok",
    "iso:country":"TH",
    "name:tha_x_preferred":[
        "\u0e1a\u0e49\u0e32\u0e19\u0e1b\u0e48\u0e32\u0e44\u0e23\u0e48"
    ],
    "wof:name":"Ban Pa Rai",
    "wof:placetype":"locality"
},
  "geometry": {"coordinates":[99.98564,20.1637],"type":"Point"}
}