{
  "type": "Feature",
  "properties": {
    "gn:admin1_code":"14.0",
    "gn:asciiname":"Ban Bung Khla",
    "gn:country_code":"TH",
    "gn:dem":60,
    "gn:feature_class":"P",
    "gn:feature_code":"PPL",
    "gn:name":"Ban Bung Khla",
    "gn:population":0,
    "gn:timezone":"Asia/Bangkok",
    "iso:country":"TH",
    "name:tha_x_preferred":[
        "\u0e1a\u0e49\u0e32\u0e19\u0e1a\u0e38\u0e48\u0e07\u0e04\u0e25\u0e49\u0e32"
    ],
    "wof:name":"Ban Bung Khla",
    "wof:placetype":"locality"
},
  "geometry": {"coordinates":[100.65561,16.06469],"type":"Point"}
}