{
  "type": "Feature",
  "properties": {
    "gn:admin1_code":"38.0",
    "gn:asciiname":"Ban Bang Kho",
    "gn:cc2":"TH",
    "gn:country_code":"TH",
    "gn:dem":5,
    "gn:feature_class":"P",
    "gn:feature_code":"PPL",
    "gn:name":"Ban Bang Kho",
    "gn:population":0,
    "gn:timezone":"Asia/Bangkok",
    "iso:country":"TH",
    "name:tha_x_preferred":[
        "\u0e1a\u0e49\u0e32\u0e19\u0e1a\u0e32\u0e07\u0e04\u0e49\u0e2d"
    ],
    "wof:name":"Ban Bang Kho",
    "wof:placetype":"locality"
},
  "geometry": {"coordinates":[100.41396,13.82978],"type":"Point"}
}