{
  "type": "Feature",
  "properties": {
    "gn:admin1_code":"15.0",
    "gn:asciiname":"Ban Pa Phrik",
    "gn:country_code":"TH",
    "gn:dem":68,
    "gn:feature_class":"P",
    "gn:feature_code":"PPL",
    "gn:name":"Ban Pa Phrik",
    "gn:population":0,
    "gn:timezone":"Asia/Bangkok",
    "iso:country":"TH",
    "name:tha_x_preferred":[
        "\u0e1a\u0e49\u0e32\u0e19\u0e1b\u0e48\u0e32\u0e1e\u0e23\u0e34\u0e01"
    ],
    "wof:name":"Ban Pa Phrik",
    "wof:placetype":"locality"
},
  "geometry": {"coordinates":[99.76653,15.41342],"type":"Point"}
}