{
  "type": "Feature",
  "properties": {
    "gn:admin1_code":"14.0",
    "gn:asciiname":"Ban Khok Prue",
    "gn:country_code":"TH",
    "gn:dem":81,
    "gn:feature_class":"P",
    "gn:feature_code":"PPL",
    "gn:name":"Ban Khok Prue",
    "gn:population":0,
    "gn:timezone":"Asia/Bangkok",
    "iso:country":"TH",
    "name:tha_x_preferred":[
        "\u0e1a\u0e49\u0e32\u0e19\u0e42\u0e04\u0e01\u0e1b\u0e23\u0e37\u0e2d"
    ],
    "name:und_x_variant":[
        "Ban Khok Pu"
    ],
    "wof:name":"Ban Khok Prue",
    "wof:placetype":"locality"
},
  "geometry": {"coordinates":[101.09739,15.72561],"type":"Point"}
}