{
  "type": "Feature",
  "properties": {
    "gn:admin1_code":"57.0",
    "gn:asciiname":"Ban Bo Fai",
    "gn:country_code":"TH",
    "gn:dem":9,
    "gn:feature_class":"P",
    "gn:feature_code":"PPL",
    "gn:name":"Ban Bo Fai",
    "gn:population":0,
    "gn:timezone":"Asia/Bangkok",
    "iso:country":"TH",
    "name:tha_x_preferred":[
        "\u0e1a\u0e49\u0e32\u0e19\u0e1a\u0e48\u0e2d\u0e1d\u0e49\u0e32\u0e22"
    ],
    "name:und_x_variant":[
        "B\u0101n Boh Fhai",
        "Ban Bo Fai (1)",
        "Ban Bo Fai"
    ],
    "wof:lang_x_official":[
        "tha"
    ],
    "wof:lang_x_spoken":[
        "tha"
    ],
    "wof:name":"Ban Bo Fai",
    "wof:placetype":"locality"
},
  "geometry": {"coordinates":[99.95111,12.61456],"type":"Point"}
}