{
  "type": "Feature",
  "properties": {
    "gn:admin1_code":"68.0",
    "gn:asciiname":"Ban Bang Dan",
    "gn:country_code":"TH",
    "gn:dem":10,
    "gn:feature_class":"P",
    "gn:feature_code":"PPL",
    "gn:name":"Ban Bang Dan",
    "gn:population":0,
    "gn:timezone":"Asia/Bangkok",
    "iso:country":"TH",
    "name:tha_x_preferred":[
        "\u0e1a\u0e49\u0e32\u0e19\u0e1a\u0e32\u0e07\u0e14\u0e32\u0e19"
    ],
    "name:und_x_variant":[
        "Ban Bang Tan",
        "Ban Bang Dan"
    ],
    "wof:name":"Ban Bang Dan",
    "wof:placetype":"locality"
},
  "geometry": {"coordinates":[100.59103,7.14244],"type":"Point"}
}