{
  "type": "Feature",
  "properties": {
    "gn:admin1_code":"1.0",
    "gn:asciiname":"Ban Ko Cha Khi",
    "gn:country_code":"TH",
    "gn:dem":398,
    "gn:feature_class":"P",
    "gn:feature_code":"PPL",
    "gn:name":"Ban Ko Cha Khi",
    "gn:population":0,
    "gn:timezone":"Asia/Bangkok",
    "iso:country":"TH",
    "name:tha_x_preferred":[
        "\u0e1a\u0e49\u0e32\u0e19\u0e01\u0e2d\u0e08\u0e32\u0e04\u0e35"
    ],
    "wof:name":"Ban Ko Cha Khi",
    "wof:placetype":"locality"
},
  "geometry": {"coordinates":[98.06406,17.70422],"type":"Point"}
}