{
  "type": "Feature",
  "properties": {
    "gn:admin1_code":"30.0",
    "gn:asciiname":"Ban Tabaek",
    "gn:country_code":"TH",
    "gn:dem":159,
    "gn:feature_class":"P",
    "gn:feature_code":"PPL",
    "gn:name":"Ban Tabaek",
    "gn:population":0,
    "gn:timezone":"Asia/Bangkok",
    "iso:country":"TH",
    "name:tha_x_preferred":[
        "\u0e1a\u0e49\u0e32\u0e19\u0e15\u0e30\u0e41\u0e1a\u0e01"
    ],
    "name:und_x_variant":[
        "Traboek",
        "Ban Tabaek"
    ],
    "wof:name":"Ban Tabaek",
    "wof:placetype":"locality"
},
  "geometry": {"coordinates":[104.21505999999999,14.71545],"type":"Point"}
}