{
  "type": "Feature",
  "properties": {
    "gn:admin1_code":"36.0",
    "gn:asciiname":"Ban Pho Sam Ton",
    "gn:country_code":"TH",
    "gn:dem":11,
    "gn:feature_class":"P",
    "gn:feature_code":"PPL",
    "gn:name":"Ban Pho Sam Ton",
    "gn:population":0,
    "gn:timezone":"Asia/Bangkok",
    "iso:country":"TH",
    "name:tha_x_preferred":[
        "\u0e1a\u0e49\u0e32\u0e19\u0e42\u0e1e\u0e18\u0e34\u0e4c\u0e2a\u0e32\u0e21\u0e15\u0e49\u0e19"
    ],
    "wof:name":"Ban Pho Sam Ton",
    "wof:placetype":"locality"
},
  "geometry": {"coordinates":[100.54731,14.42417],"type":"Point"}
}