{
  "type": "Feature",
  "properties": {
    "gn:admin1_code":"12.0",
    "gn:asciiname":"Ban Tat Ya",
    "gn:country_code":"TH",
    "gn:dem":219,
    "gn:feature_class":"P",
    "gn:feature_code":"PPL",
    "gn:name":"Ban Tat Ya",
    "gn:population":0,
    "gn:timezone":"Asia/Bangkok",
    "iso:country":"TH",
    "name:tha_x_preferred":[
        "\u0e1a\u0e49\u0e32\u0e19\u0e15\u0e32\u0e14\u0e2b\u0e0d\u0e49\u0e32"
    ],
    "wof:name":"Ban Tat Ya",
    "wof:placetype":"locality"
},
  "geometry": {"coordinates":[100.52144,16.89803],"type":"Point"}
}