{
  "type": "Feature",
  "properties": {
    "gn:admin1_code":"27",
    "gn:asciiname":"Ban Taluk Phluang",
    "gn:country_code":"TH",
    "gn:dem":240,
    "gn:feature_class":"P",
    "gn:feature_code":"PPL",
    "gn:name":"Ban Taluk Phluang",
    "gn:population":0,
    "gn:timezone":"Asia/Bangkok",
    "iso:country":"TH",
    "name:tha_x_preferred":[
        "\u0e1a\u0e49\u0e32\u0e19\u0e15\u0e25\u0e38\u0e01\u0e1e\u0e25\u0e27\u0e07"
    ],
    "wof:name":"Ban Taluk Phluang",
    "wof:placetype":"locality"
},
  "geometry": {"coordinates":[102.20569,15.56969],"type":"Point"}
}