{
  "type": "Feature",
  "properties": {
    "gn:admin1_code":"25.0",
    "gn:asciiname":"Ban Nong O",
    "gn:country_code":"TH",
    "gn:dem":134,
    "gn:feature_class":"P",
    "gn:feature_code":"PPL",
    "gn:name":"Ban Nong O",
    "gn:population":0,
    "gn:timezone":"Asia/Bangkok",
    "iso:country":"TH",
    "name:tha_x_preferred":[
        "\u0e1a\u0e49\u0e32\u0e19\u0e2b\u0e19\u0e2d\u0e07\u0e2d\u0e49\u0e2d"
    ],
    "wof:name":"Ban Nong O",
    "wof:placetype":"locality"
},
  "geometry": {"coordinates":[103.59336,15.61186],"type":"Point"}
}