{
  "type": "Feature",
  "properties": {
    "gn:admin1_code":"4.0",
    "gn:asciiname":"Ban Phu Wiang",
    "gn:country_code":"TH",
    "gn:dem":242,
    "gn:feature_class":"P",
    "gn:feature_code":"PPL",
    "gn:name":"Ban Phu Wiang",
    "gn:population":0,
    "gn:timezone":"Asia/Bangkok",
    "iso:country":"TH",
    "name:tha_x_preferred":[
        "\u0e1a\u0e49\u0e32\u0e19\u0e20\u0e39\u0e40\u0e27\u0e35\u0e22\u0e07"
    ],
    "wof:name":"Ban Phu Wiang",
    "wof:placetype":"locality"
},
  "geometry": {"coordinates":[100.74083,18.95],"type":"Point"}
}