{
  "type": "Feature",
  "properties": {
    "gn:admin1_code":"41.0",
    "gn:asciiname":"Ban Rong",
    "gn:country_code":"TH",
    "gn:dem":406,
    "gn:feature_class":"P",
    "gn:feature_code":"PPL",
    "gn:name":"Ban Rong",
    "gn:population":0,
    "gn:timezone":"Asia/Bangkok",
    "iso:country":"TH",
    "name:tha_x_preferred":[
        "\u0e1a\u0e49\u0e32\u0e19\u0e23\u0e49\u0e2d\u0e07"
    ],
    "name:tha_x_variant":[
        "\u0e15\u0e33\u0e1a\u0e25\u0e1a\u0e49\u0e32\u0e19\u0e23\u0e49\u0e2d\u0e07"
    ],
    "name:und_x_variant":[
        "Ban Rong Kao",
        "B\u0101n Raung",
        "Ban Rong"
    ],
    "wof:name":"Ban Rong",
    "wof:placetype":"locality"
},
  "geometry": {"coordinates":[100.35138999999999,19.51617],"type":"Point"}
}