{
  "type": "Feature",
  "properties": {
    "gn:admin1_code":"7.0",
    "gn:asciiname":"Ban Thin",
    "gn:country_code":"TH",
    "gn:dem":186,
    "gn:feature_class":"P",
    "gn:feature_code":"PPL",
    "gn:name":"Ban Thin",
    "gn:population":0,
    "gn:timezone":"Asia/Bangkok",
    "iso:country":"TH",
    "name:tha_x_preferred":[
        "\u0e1a\u0e49\u0e32\u0e19\u0e16\u0e34\u0e48\u0e19"
    ],
    "wof:name":"Ban Thin",
    "wof:placetype":"locality"
},
  "geometry": {"coordinates":[100.20531,18.14369],"type":"Point"}
}