{
  "type": "Feature",
  "properties": {
    "gn:admin1_code":"60.0",
    "gn:asciiname":"Ban Chalok Ban Kao",
    "gn:country_code":"TH",
    "gn:dem":14,
    "gn:feature_class":"P",
    "gn:feature_code":"PPL",
    "gn:name":"Ban Chalok Ban Kao",
    "gn:population":0,
    "gn:timezone":"Asia/Bangkok",
    "iso:country":"TH",
    "name:tha_x_preferred":[
        "\u0e1a\u0e49\u0e32\u0e19\u0e42\u0e09\u0e25\u0e01\u0e1a\u0e49\u0e32\u0e19\u0e40\u0e01\u0e48\u0e32"
    ],
    "wof:name":"Ban Chalok Ban Kao",
    "wof:placetype":"locality"
},
  "geometry": {"coordinates":[99.82867,10.07119],"type":"Point"}
}