{
  "type": "Feature",
  "properties": {
    "gn:admin1_code":"23.0",
    "gn:asciiname":"Ban Yang Um",
    "gn:country_code":"TH",
    "gn:dem":180,
    "gn:feature_class":"P",
    "gn:feature_code":"PPL",
    "gn:name":"Ban Yang Um",
    "gn:population":0,
    "gn:timezone":"Asia/Bangkok",
    "iso:country":"TH",
    "name:tha_x_preferred":[
        "\u0e1a\u0e49\u0e32\u0e19\u0e22\u0e32\u0e07\u0e2d\u0e39\u0e49\u0e21"
    ],
    "wof:name":"Ban Yang Um",
    "wof:placetype":"locality"
},
  "geometry": {"coordinates":[103.29049999999999,16.91622000000001],"type":"Point"}
}