{
  "type": "Feature",
  "properties": {
    "gn:admin1_code":"29",
    "gn:asciiname":"Ban Sakrom",
    "gn:country_code":"TH",
    "gn:dem":174,
    "gn:feature_class":"P",
    "gn:feature_code":"PPL",
    "gn:name":"Ban Sakrom",
    "gn:population":0,
    "gn:timezone":"Asia/Bangkok",
    "iso:country":"TH",
    "name:tha_x_preferred":[
        "\u0e1a\u0e49\u0e32\u0e19\u0e2a\u0e01\u0e23\u0e47\u0e2d\u0e21"
    ],
    "wof:name":"Ban Sakrom",
    "wof:placetype":"locality"
},
  "geometry": {"coordinates":[103.44822000000001,14.80017],"type":"Point"}
}