{
  "type": "Feature",
  "properties": {
    "gn:admin1_code":"0.0",
    "gn:asciiname":"Ban Kao",
    "gn:country_code":"TH",
    "gn:dem":766,
    "gn:feature_class":"P",
    "gn:feature_code":"PPL",
    "gn:name":"Ban Kao",
    "gn:population":0,
    "gn:timezone":"Asia/Bangkok",
    "iso:country":"TH",
    "name:deu_x_preferred":[
        "Ban Kao"
    ],
    "wof:lang_x_official":[
        "tha"
    ],
    "wof:lang_x_spoken":[
        "tha"
    ],
    "wof:name":"Ban Kao",
    "wof:placetype":"locality"
},
  "geometry": {"coordinates":[98.61667,19.61667000000001],"type":"Point"}
}