{
  "type": "Feature",
  "properties": {
    "gn:admin1_code":"14.0",
    "gn:asciiname":"Ban Sap Phutsa Tai",
    "gn:country_code":"TH",
    "gn:dem":146,
    "gn:feature_class":"P",
    "gn:feature_code":"PPL",
    "gn:name":"Ban Sap Phutsa Tai",
    "gn:population":0,
    "gn:timezone":"Asia/Bangkok",
    "iso:country":"TH",
    "name:tha_x_preferred":[
        "\u0e1a\u0e49\u0e32\u0e19\u0e0b\u0e31\u0e1a\u0e1e\u0e38\u0e17\u0e23\u0e32\u0e43\u0e15\u0e49"
    ],
    "name:und_x_variant":[
        "Ban Sap Phutsa"
    ],
    "wof:name":"Ban Sap Phutsa Tai",
    "wof:placetype":"locality"
},
  "geometry": {"coordinates":[100.93925,16.01714],"type":"Point"}
}