{
  "type": "Feature",
  "properties": {
    "gn:admin1_code":"51.0",
    "gn:asciiname":"Ban Lat Makham",
    "gn:country_code":"TH",
    "gn:dem":5,
    "gn:feature_class":"P",
    "gn:feature_code":"PPL",
    "gn:name":"Ban Lat Makham",
    "gn:population":0,
    "gn:timezone":"Asia/Bangkok",
    "iso:country":"TH",
    "name:tha_x_preferred":[
        "\u0e1a\u0e49\u0e32\u0e19\u0e25\u0e32\u0e14\u0e21\u0e30\u0e02\u0e32\u0e21"
    ],
    "name:und_x_variant":[
        "Ban Don Lat Makham"
    ],
    "wof:name":"Ban Lat Makham",
    "wof:placetype":"locality"
},
  "geometry": {"coordinates":[100.07397,14.16553],"type":"Point"}
}