{
  "type": "Feature",
  "properties": {
    "gn:admin1_code":"58.0",
    "gn:asciiname":"Ban Salui",
    "gn:country_code":"TH",
    "gn:dem":36,
    "gn:feature_class":"P",
    "gn:feature_code":"PPL",
    "gn:name":"Ban Salui",
    "gn:population":0,
    "gn:timezone":"Asia/Bangkok",
    "iso:country":"TH",
    "name:tha_x_preferred":[
        "\u0e1a\u0e49\u0e32\u0e19\u0e2a\u0e25\u0e38\u0e22"
    ],
    "name:und_x_variant":[
        "Sa Hlui",
        "Salui",
        "Ban Salui"
    ],
    "wof:name":"Ban Salui",
    "wof:placetype":"locality"
},
  "geometry": {"coordinates":[99.19083999999999,10.78652],"type":"Point"}
}