{
  "type": "Feature",
  "properties": {
    "gn:admin1_code":"46.0",
    "gn:asciiname":"Ban Ko Lan",
    "gn:country_code":"TH",
    "gn:dem":10,
    "gn:feature_class":"P",
    "gn:feature_code":"PPL",
    "gn:name":"Ban Ko Lan",
    "gn:population":2000,
    "gn:timezone":"Asia/Bangkok",
    "iso:country":"TH",
    "name:aze_x_preferred":[
        "Lan adas\u0131"
    ],
    "name:ceb_x_preferred":[
        "Ko Lan"
    ],
    "name:deu_x_preferred":[
        "Ko Lan"
    ],
    "name:fra_x_preferred":[
        "Ko Lan"
    ],
    "name:ita_x_preferred":[
        "Ko Lan"
    ],
    "name:rus_x_preferred":[
        "\u041a\u043e \u041b\u0430\u043d"
    ],
    "name:rus_x_variant":[
        "\u041b\u0430\u043d"
    ],
    "name:spa_x_preferred":[
        "Ko Lan"
    ],
    "name:tha_x_preferred":[
        "\u0e1a\u0e49\u0e32\u0e19\u0e40\u0e01\u0e32\u0e30\u0e25\u0e49\u0e32\u0e19"
    ],
    "name:tha_x_variant":[
        "\u0e40\u0e01\u0e32\u0e30\u0e25\u0e49\u0e32\u0e19"
    ],
    "name:und_x_variant":[
        "Ban Ko San",
        "Ban Kok San",
        "Ban Ko Lan"
    ],
    "name:vie_x_preferred":[
        "Ko Lan"
    ],
    "name:wuu_x_preferred":[
        "\u5c0f\u73ca\u745a\u5c9b"
    ],
    "name:zho_x_preferred":[
        "\u5c0f\u73ca\u745a\u5cf6"
    ],
    "wof:name":"Ban Ko Lan",
    "wof:placetype":"locality",
    "wof:population":2000
},
  "geometry": {"coordinates":[100.78794000000001,12.92419],"type":"Point"}
}