{
  "type": "Feature",
  "properties": {
    "gn:admin1_code":"11.0",
    "gn:asciiname":"Ban Dong Dam",
    "gn:country_code":"TH",
    "gn:dem":112,
    "gn:feature_class":"P",
    "gn:feature_code":"PPL",
    "gn:name":"Ban Dong Dam",
    "gn:population":0,
    "gn:timezone":"Asia/Bangkok",
    "iso:country":"TH",
    "name:tha_x_preferred":[
        "\u0e1a\u0e49\u0e32\u0e19\u0e14\u0e07\u0e14\u0e33"
    ],
    "wof:name":"Ban Dong Dam",
    "wof:placetype":"locality"
},
  "geometry": {"coordinates":[99.43619,16.29122000000001],"type":"Point"}
}