{
  "type": "Feature",
  "properties": {
    "gn:admin1_code":"6.0",
    "gn:asciiname":"Ban San Makluea",
    "gn:country_code":"TH",
    "gn:dem":315,
    "gn:feature_class":"P",
    "gn:feature_code":"PPL",
    "gn:name":"Ban San Makluea",
    "gn:population":0,
    "gn:timezone":"Asia/Bangkok",
    "iso:country":"TH",
    "name:tha_x_preferred":[
        "\u0e1a\u0e49\u0e32\u0e19\u0e2a\u0e31\u0e19\u0e21\u0e30\u0e40\u0e01\u0e25\u0e37\u0e2d"
    ],
    "name:und_x_variant":[
        "Ban San Maklua"
    ],
    "wof:name":"Ban San Makluea",
    "wof:placetype":"locality"
},
  "geometry": {"coordinates":[99.57489,18.74644],"type":"Point"}
}