{
  "type": "Feature",
  "properties": {
    "gn:admin1_code":"36.0",
    "gn:asciiname":"Ban Khlong Khut",
    "gn:country_code":"TH",
    "gn:dem":7,
    "gn:feature_class":"P",
    "gn:feature_code":"PPL",
    "gn:name":"Ban Khlong Khut",
    "gn:population":0,
    "gn:timezone":"Asia/Bangkok",
    "iso:country":"TH",
    "name:tha_x_preferred":[
        "\u0e1a\u0e49\u0e32\u0e19\u0e04\u0e25\u0e2d\u0e07\u0e02\u0e38\u0e14"
    ],
    "name:und_x_variant":[
        "Ban Klong Kud",
        "Ban Khlong Khut"
    ],
    "wof:name":"Ban Khlong Khut",
    "wof:placetype":"locality"
},
  "geometry": {"coordinates":[100.35158,14.26719],"type":"Point"}
}