{
  "type": "Feature",
  "properties": {
    "gn:admin1_code":"76.0",
    "gn:asciiname":"Ban Thung Pa Phaeng",
    "gn:country_code":"TH",
    "gn:dem":244,
    "gn:feature_class":"P",
    "gn:feature_code":"PPL",
    "gn:name":"Ban Thung Pa Phaeng",
    "gn:population":0,
    "gn:timezone":"Asia/Bangkok",
    "iso:country":"TH",
    "name:tha_x_preferred":[
        "\u0e1a\u0e49\u0e32\u0e19\u0e17\u0e38\u0e48\u0e07\u0e1b\u0e48\u0e32\u0e41\u0e1e\u0e07"
    ],
    "wof:name":"Ban Thung Pa Phaeng",
    "wof:placetype":"locality"
},
  "geometry": {"coordinates":[102.41314,17.42231],"type":"Point"}
}