{
  "type": "Feature",
  "properties": {
    "gn:admin1_code":"38.0",
    "gn:asciiname":"Muban Saeng Bua Thong",
    "gn:country_code":"TH",
    "gn:dem":8,
    "gn:feature_class":"P",
    "gn:feature_code":"PPL",
    "gn:name":"Muban Saeng Bua Thong",
    "gn:population":0,
    "gn:timezone":"Asia/Bangkok",
    "iso:country":"TH",
    "name:tha_x_preferred":[
        "\u0e2b\u0e21\u0e39\u0e48\u0e1a\u0e49\u0e32\u0e19\u0e41\u0e2a\u0e07\u0e1a\u0e31\u0e27\u0e17\u0e2d\u0e07"
    ],
    "wof:name":"Muban Saeng Bua Thong",
    "wof:placetype":"locality"
},
  "geometry": {"coordinates":[100.39239000000001,13.96503],"type":"Point"}
}