{
  "type": "Feature",
  "properties": {
    "gn:admin1_code":"38.0",
    "gn:asciiname":"Ban Bang Krabue",
    "gn:cc2":"TH",
    "gn:country_code":"TH",
    "gn:dem":9,
    "gn:feature_class":"P",
    "gn:feature_code":"PPL",
    "gn:name":"Ban Bang Krabue",
    "gn:population":0,
    "gn:timezone":"Asia/Bangkok",
    "iso:country":"TH",
    "name:tha_x_preferred":[
        "\u0e1a\u0e49\u0e32\u0e19\u0e1a\u0e32\u0e07\u0e01\u0e23\u0e30\u0e1a\u0e37\u0e2d"
    ],
    "name:und_x_variant":[
        "Ban Bang Krabu",
        "Ban Bang Krabue"
    ],
    "wof:name":"Ban Bang Krabue",
    "wof:placetype":"locality"
},
  "geometry": {"coordinates":[100.41442000000001,13.85733],"type":"Point"}
}