{
  "type": "Feature",
  "properties": {
    "gn:admin1_code":"28",
    "gn:asciiname":"Ban Dong Yai Phatthana",
    "gn:country_code":"TH",
    "gn:dem":251,
    "gn:feature_class":"P",
    "gn:feature_code":"PPL",
    "gn:name":"Ban Dong Yai Phatthana",
    "gn:population":0,
    "gn:timezone":"Asia/Bangkok",
    "iso:country":"TH",
    "name:tha_x_preferred":[
        "\u0e1a\u0e49\u0e32\u0e19\u0e14\u0e07\u0e43\u0e2b\u0e0d\u0e48\u0e1e\u0e31\u0e12\u0e19\u0e32"
    ],
    "wof:name":"Ban Dong Yai Phatthana",
    "wof:placetype":"locality"
},
  "geometry": {"coordinates":[102.62983,14.37578],"type":"Point"}
}