{
  "type": "Feature",
  "properties": {
    "gn:admin1_code":"50.0",
    "gn:asciiname":"Ban Salaep Bang Khen",
    "gn:country_code":"TH",
    "gn:dem":61,
    "gn:feature_class":"P",
    "gn:feature_code":"PPL",
    "gn:name":"Ban Salaep Bang Khen",
    "gn:population":0,
    "gn:timezone":"Asia/Bangkok",
    "iso:country":"TH",
    "name:tha_x_preferred":[
        "\u0e1a\u0e49\u0e32\u0e19\u0e41\u0e2a\u0e25\u0e1a\u0e1a\u0e32\u0e07\u0e40\u0e02\u0e19"
    ],
    "wof:name":"Ban Salaep Bang Khen",
    "wof:placetype":"locality"
},
  "geometry": {"coordinates":[99.62278000000001,14.18792],"type":"Point"}
}