{
  "type": "Feature",
  "properties": {
    "gn:admin1_code":"28",
    "gn:asciiname":"Ban Ta Sadam Noi",
    "gn:country_code":"TH",
    "gn:dem":158,
    "gn:feature_class":"P",
    "gn:feature_code":"PPL",
    "gn:name":"Ban Ta Sadam Noi",
    "gn:population":0,
    "gn:timezone":"Asia/Bangkok",
    "iso:country":"TH",
    "name:tha_x_preferred":[
        "\u0e1a\u0e49\u0e32\u0e19\u0e15\u0e32\u0e2a\u0e30\u0e14\u0e33\u0e19\u0e49\u0e2d\u0e22"
    ],
    "wof:name":"Ban Ta Sadam Noi",
    "wof:placetype":"locality"
},
  "geometry": {"coordinates":[103.30553,14.87056],"type":"Point"}
}