{
  "type": "Feature",
  "properties": {
    "gn:admin1_code":"14.0",
    "gn:asciiname":"Ban Phra Thi Nang",
    "gn:country_code":"TH",
    "gn:dem":125,
    "gn:feature_class":"P",
    "gn:feature_code":"PPL",
    "gn:name":"Ban Phra Thi Nang",
    "gn:population":0,
    "gn:timezone":"Asia/Bangkok",
    "iso:country":"TH",
    "name:tha_x_preferred":[
        "\u0e1a\u0e49\u0e32\u0e19\u0e1e\u0e23\u0e30\u0e17\u0e35\u0e48\u0e19\u0e31\u0e48\u0e07"
    ],
    "wof:name":"Ban Phra Thi Nang",
    "wof:placetype":"locality"
},
  "geometry": {"coordinates":[100.88675000000001,15.59469],"type":"Point"}
}