{
  "type": "Feature",
  "properties": {
    "gn:admin1_code":"43",
    "gn:asciiname":"Ban Wat Rat Pradit",
    "gn:country_code":"TH",
    "gn:dem":9,
    "gn:feature_class":"P",
    "gn:feature_code":"PPL",
    "gn:name":"Ban Wat Rat Pradit",
    "gn:population":0,
    "gn:timezone":"Asia/Bangkok",
    "iso:country":"TH",
    "name:tha_x_preferred":[
        "\u0e1a\u0e49\u0e32\u0e19\u0e27\u0e31\u0e14\u0e23\u0e32\u0e29\u0e0e\u0e23\u0e4c\u0e1b\u0e23\u0e30\u0e14\u0e34\u0e29\u0e10\u0e4c"
    ],
    "wof:name":"Ban Wat Rat Pradit",
    "wof:placetype":"locality"
},
  "geometry": {"coordinates":[101.05078,14.006],"type":"Point"}
}