{
  "type": "Feature",
  "properties": {
    "gn:admin1_code":"58.0",
    "gn:asciiname":"Ban Ho Rakhang",
    "gn:country_code":"TH",
    "gn:dem":19,
    "gn:feature_class":"P",
    "gn:feature_code":"PPL",
    "gn:name":"Ban Ho Rakhang",
    "gn:population":0,
    "gn:timezone":"Asia/Bangkok",
    "iso:country":"TH",
    "name:tha_x_preferred":[
        "\u0e1a\u0e49\u0e32\u0e19\u0e2b\u0e2d\u0e23\u0e30\u0e06\u0e31\u0e07"
    ],
    "wof:name":"Ban Ho Rakhang",
    "wof:placetype":"locality"
},
  "geometry": {"coordinates":[99.16,10.61306],"type":"Point"}
}