{
  "type": "Feature",
  "properties": {
    "gn:admin1_code":"56.0",
    "gn:asciiname":"Ban Pong Salot",
    "gn:country_code":"TH",
    "gn:dem":18,
    "gn:feature_class":"P",
    "gn:feature_code":"PPL",
    "gn:name":"Ban Pong Salot",
    "gn:population":0,
    "gn:timezone":"Asia/Bangkok",
    "iso:country":"TH",
    "name:tha_x_preferred":[
        "\u0e1a\u0e49\u0e32\u0e19\u0e42\u0e1b\u0e48\u0e07\u0e2a\u0e25\u0e2d\u0e14"
    ],
    "wof:name":"Ban Pong Salot",
    "wof:placetype":"locality"
},
  "geometry": {"coordinates":[99.83197,13.06256],"type":"Point"}
}