{
  "type": "Feature",
  "properties": {
    "gn:admin1_code":"26.0",
    "gn:asciiname":"Ban Hin Pun",
    "gn:country_code":"TH",
    "gn:dem":336,
    "gn:feature_class":"P",
    "gn:feature_code":"PPL",
    "gn:name":"Ban Hin Pun",
    "gn:population":0,
    "gn:timezone":"Asia/Bangkok",
    "iso:country":"TH",
    "name:tha_x_preferred":[
        "\u0e1a\u0e49\u0e32\u0e19\u0e2b\u0e34\u0e19\u0e1b\u0e39\u0e19"
    ],
    "wof:name":"Ban Hin Pun",
    "wof:placetype":"locality"
},
  "geometry": {"coordinates":[101.61924999999999,15.65358],"type":"Point"}
}