{
  "type": "Feature",
  "properties": {
    "gn:admin1_code":"27",
    "gn:asciiname":"Ban Rok Fa",
    "gn:country_code":"TH",
    "gn:dem":198,
    "gn:feature_class":"P",
    "gn:feature_code":"PPL",
    "gn:name":"Ban Rok Fa",
    "gn:population":0,
    "gn:timezone":"Asia/Bangkok",
    "iso:country":"TH",
    "name:tha_x_preferred":[
        "\u0e1a\u0e49\u0e32\u0e19\u0e23\u0e01\u0e1f\u0e49\u0e32"
    ],
    "wof:name":"Ban Rok Fa",
    "wof:placetype":"locality"
},
  "geometry": {"coordinates":[102.41697000000001,15.6635],"type":"Point"}
}