{
  "type": "Feature",
  "properties": {
    "gn:admin1_code":"31.0",
    "gn:asciiname":"Kampong Bangae",
    "gn:cc2":"TH",
    "gn:country_code":"TH",
    "gn:dem":24,
    "gn:feature_class":"P",
    "gn:feature_code":"PPL",
    "gn:name":"Kampong Bangae",
    "gn:population":0,
    "gn:timezone":"Asia/Bangkok",
    "iso:country":"TH",
    "name:und_x_variant":[
        "Kampong Bangek"
    ],
    "wof:name":"Kampong Bangae",
    "wof:placetype":"locality"
},
  "geometry": {"coordinates":[101.88333,6.11667],"type":"Point"}
}