{
  "type": "Feature",
  "properties": {
    "gn:admin1_code":"48.0",
    "gn:asciiname":"Ban Salaeng It",
    "gn:country_code":"TH",
    "gn:dem":12,
    "gn:feature_class":"P",
    "gn:feature_code":"PPL",
    "gn:name":"Ban Salaeng It",
    "gn:population":0,
    "gn:timezone":"Asia/Bangkok",
    "iso:country":"TH",
    "name:tha_x_preferred":[
        "\u0e1a\u0e49\u0e32\u0e19\u0e41\u0e2a\u0e25\u0e07\u0e2d\u0e34\u0e10"
    ],
    "wof:name":"Ban Salaeng It",
    "wof:placetype":"locality"
},
  "geometry": {"coordinates":[102.30922,12.55664],"type":"Point"}
}