{
  "type": "Feature",
  "properties": {
    "gn:admin1_code":"27.0",
    "gn:asciiname":"Ban Saraphi",
    "gn:country_code":"TH",
    "gn:dem":194,
    "gn:feature_class":"P",
    "gn:feature_code":"PPL",
    "gn:name":"Ban Saraphi",
    "gn:population":0,
    "gn:timezone":"Asia/Bangkok",
    "iso:country":"TH",
    "name:tha_x_preferred":[
        "\u0e1a\u0e49\u0e32\u0e19\u0e2a\u0e32\u0e23\u0e20\u0e35"
    ],
    "name:und_x_variant":[
        "Saraphi",
        "Ban Saraphi"
    ],
    "wof:name":"Ban Saraphi",
    "wof:placetype":"locality"
},
  "geometry": {"coordinates":[102.39933000000001,14.82683],"type":"Point"}
}