{
  "type": "Feature",
  "properties": {
    "gn:admin1_code":"26.0",
    "gn:asciiname":"Ban Lat Tai",
    "gn:country_code":"TH",
    "gn:dem":247,
    "gn:feature_class":"P",
    "gn:feature_code":"PPL",
    "gn:name":"Ban Lat Tai",
    "gn:population":0,
    "gn:timezone":"Asia/Bangkok",
    "iso:country":"TH",
    "name:tha_x_preferred":[
        "\u0e1a\u0e49\u0e32\u0e19\u0e25\u0e32\u0e14\u0e43\u0e15\u0e49"
    ],
    "wof:name":"Ban Lat Tai",
    "wof:placetype":"locality"
},
  "geometry": {"coordinates":[101.80211,16.06903],"type":"Point"}
}