{
  "type": "Feature",
  "properties": {
    "gn:admin1_code":"79.0",
    "gn:asciiname":"Ban Sok Chang",
    "gn:country_code":"TH",
    "gn:dem":210,
    "gn:feature_class":"P",
    "gn:feature_code":"PPL",
    "gn:name":"Ban Sok Chang",
    "gn:population":0,
    "gn:timezone":"Asia/Bangkok",
    "iso:country":"TH",
    "name:tha_x_preferred":[
        "\u0e1a\u0e49\u0e32\u0e19\u0e42\u0e2a\u0e01\u0e0a\u0e49\u0e32\u0e07"
    ],
    "wof:name":"Ban Sok Chang",
    "wof:placetype":"locality"
},
  "geometry": {"coordinates":[102.56147,16.94878],"type":"Point"}
}