{
  "type": "Feature",
  "properties": {
    "gn:admin1_code":"36",
    "gn:asciiname":"Ban Nai Khlong",
    "gn:country_code":"TH",
    "gn:dem":10,
    "gn:feature_class":"P",
    "gn:feature_code":"PPL",
    "gn:name":"Ban Nai Khlong",
    "gn:population":0,
    "gn:timezone":"Asia/Bangkok",
    "iso:country":"TH",
    "name:tha_x_preferred":[
        "\u0e1a\u0e49\u0e32\u0e19\u0e43\u0e19\u0e04\u0e25\u0e2d\u0e07"
    ],
    "wof:name":"Ban Nai Khlong",
    "wof:placetype":"locality"
},
  "geometry": {"coordinates":[100.52406000000001,14.41619],"type":"Point"}
}