{
  "type": "Feature",
  "properties": {
    "gn:admin1_code":"10.0",
    "gn:asciiname":"Ban Khai",
    "gn:country_code":"TH",
    "gn:dem":112,
    "gn:feature_class":"P",
    "gn:feature_code":"PPL",
    "gn:name":"Ban Khai",
    "gn:population":0,
    "gn:timezone":"Asia/Bangkok",
    "iso:country":"TH",
    "name:tha_x_preferred":[
        "Ban Khai"
    ],
    "name:tha_x_variant":[
        "\u0e1a\u0e49\u0e32\u0e19\u0e04\u0e48\u0e32\u0e22"
    ],
    "name:und_x_variant":[
        "Ban Khoi"
    ],
    "wof:name":"Ban Khai",
    "wof:placetype":"locality"
},
  "geometry": {"coordinates":[100.29258,17.79972],"type":"Point"}
}