{
  "type": "Feature",
  "properties": {
    "gn:admin1_code":"68.0",
    "gn:asciiname":"Ban Tha Mai Phai",
    "gn:country_code":"TH",
    "gn:dem":80,
    "gn:feature_class":"P",
    "gn:feature_code":"PPL",
    "gn:name":"Ban Tha Mai Phai",
    "gn:population":0,
    "gn:timezone":"Asia/Bangkok",
    "iso:country":"TH",
    "name:tha_x_preferred":[
        "\u0e1a\u0e49\u0e32\u0e19\u0e17\u0e48\u0e32\u0e44\u0e21\u0e49\u0e44\u0e1c\u0e48"
    ],
    "wof:name":"Ban Tha Mai Phai",
    "wof:placetype":"locality"
},
  "geometry": {"coordinates":[100.80222000000001,6.52458],"type":"Point"}
}