{
  "type": "Feature",
  "properties": {
    "gn:admin1_code":"80",
    "gn:asciiname":"Ban Thanon Mai",
    "gn:country_code":"TH",
    "gn:dem":36,
    "gn:feature_class":"P",
    "gn:feature_code":"PPL",
    "gn:name":"Ban Thanon Mai",
    "gn:population":0,
    "gn:timezone":"Asia/Bangkok",
    "iso:country":"TH",
    "name:tha_x_preferred":[
        "\u0e1a\u0e49\u0e32\u0e19\u0e16\u0e19\u0e19\u0e43\u0e2b\u0e21\u0e48"
    ],
    "wof:name":"Ban Thanon Mai",
    "wof:placetype":"locality"
},
  "geometry": {"coordinates":[102.01022,14.01186],"type":"Point"}
}