{
  "type": "Feature",
  "properties": {
    "gn:admin1_code":"20.0",
    "gn:asciiname":"Ban Tha Charoen",
    "gn:country_code":"TH",
    "gn:dem":292,
    "gn:feature_class":"P",
    "gn:feature_code":"PPL",
    "gn:name":"Ban Tha Charoen",
    "gn:population":0,
    "gn:timezone":"Asia/Bangkok",
    "iso:country":"TH",
    "name:tha_x_preferred":[
        "\u0e1a\u0e49\u0e32\u0e19\u0e17\u0e48\u0e32\u0e40\u0e08\u0e23\u0e34\u0e0d"
    ],
    "wof:name":"Ban Tha Charoen",
    "wof:placetype":"locality"
},
  "geometry": {"coordinates":[103.93678,16.96327999999999],"type":"Point"}
}