{
  "type": "Feature",
  "properties": {
    "gn:admin1_code":"63.0",
    "gn:asciiname":"Ban Na Thao",
    "gn:country_code":"TH",
    "gn:dem":97,
    "gn:feature_class":"P",
    "gn:feature_code":"PPL",
    "gn:name":"Ban Na Thao",
    "gn:population":0,
    "gn:timezone":"Asia/Bangkok",
    "iso:country":"TH",
    "name:tha_x_preferred":[
        "\u0e1a\u0e49\u0e32\u0e19\u0e19\u0e32\u0e40\u0e17\u0e32"
    ],
    "wof:name":"Ban Na Thao",
    "wof:placetype":"locality"
},
  "geometry": {"coordinates":[98.78828,8.53092],"type":"Point"}
}