{
  "type": "Feature",
  "properties": {
    "gn:admin1_code":"50.0",
    "gn:asciiname":"Ban Nong Yang Chang",
    "gn:country_code":"TH",
    "gn:dem":78,
    "gn:feature_class":"P",
    "gn:feature_code":"PPL",
    "gn:name":"Ban Nong Yang Chang",
    "gn:population":0,
    "gn:timezone":"Asia/Bangkok",
    "iso:country":"TH",
    "name:tha_x_preferred":[
        "\u0e1a\u0e49\u0e32\u0e19\u0e2b\u0e19\u0e2d\u0e07\u0e22\u0e48\u0e32\u0e07\u0e0a\u0e49\u0e32\u0e07"
    ],
    "name:und_x_variant":[
        "Ban Hnong Yang Chaang",
        "Ban Nong Yang Chang"
    ],
    "wof:name":"Ban Nong Yang Chang",
    "wof:placetype":"locality"
},
  "geometry": {"coordinates":[99.50533,14.2985],"type":"Point"}
}