{
  "type": "Feature",
  "properties": {
    "gn:admin1_code":"20.0",
    "gn:asciiname":"Ban Lao Sombun",
    "gn:country_code":"TH",
    "gn:dem":168,
    "gn:feature_class":"P",
    "gn:feature_code":"PPL",
    "gn:name":"Ban Lao Sombun",
    "gn:population":0,
    "gn:timezone":"Asia/Bangkok",
    "iso:country":"TH",
    "name:tha_x_preferred":[
        "\u0e1a\u0e49\u0e32\u0e19\u0e40\u0e2b\u0e25\u0e48\u0e32\u0e2a\u0e21\u0e1a\u0e39\u0e23\u0e13\u0e4c"
    ],
    "wof:name":"Ban Lao Sombun",
    "wof:placetype":"locality"
},
  "geometry": {"coordinates":[103.46861,17.98944],"type":"Point"}
}