{
  "type": "Feature",
  "properties": {
    "gn:admin1_code":"38.0",
    "gn:asciiname":"Ban Plai Khlong Bang Khu Rat",
    "gn:country_code":"TH",
    "gn:dem":4,
    "gn:feature_class":"P",
    "gn:feature_code":"PPL",
    "gn:name":"Ban Plai Khlong Bang Khu Rat",
    "gn:population":0,
    "gn:timezone":"Asia/Bangkok",
    "iso:country":"TH",
    "name:tha_x_preferred":[
        "\u0e1a\u0e49\u0e32\u0e19\u0e1b\u0e25\u0e32\u0e22\u0e04\u0e25\u0e2d\u0e07\u0e1a\u0e32\u0e07\u0e04\u0e39\u0e23\u0e31\u0e14"
    ],
    "wof:lang_x_official":[
        "tha"
    ],
    "wof:lang_x_spoken":[
        "tha"
    ],
    "wof:name":"Ban Plai Khlong Bang Khu Rat",
    "wof:placetype":"locality"
},
  "geometry": {"coordinates":[100.35256,13.883],"type":"Point"}
}