{
  "type": "Feature",
  "properties": {
    "gn:admin1_code":"76.0",
    "gn:asciiname":"Ban Kut Nam Sai",
    "gn:country_code":"TH",
    "gn:dem":251,
    "gn:feature_class":"P",
    "gn:feature_code":"PPL",
    "gn:name":"Ban Kut Nam Sai",
    "gn:population":0,
    "gn:timezone":"Asia/Bangkok",
    "iso:country":"TH",
    "name:tha_x_preferred":[
        "\u0e1a\u0e49\u0e32\u0e19\u0e01\u0e38\u0e14\u0e19\u0e49\u0e33\u0e43\u0e2a"
    ],
    "wof:name":"Ban Kut Nam Sai",
    "wof:placetype":"locality"
},
  "geometry": {"coordinates":[102.62425,17.04503],"type":"Point"}
}