{
  "type": "Feature",
  "properties": {
    "gn:admin1_code":"25.0",
    "gn:asciiname":"Ban Rat Rangsi",
    "gn:country_code":"TH",
    "gn:dem":133,
    "gn:feature_class":"P",
    "gn:feature_code":"PPL",
    "gn:name":"Ban Rat Rangsi",
    "gn:population":0,
    "gn:timezone":"Asia/Bangkok",
    "iso:country":"TH",
    "name:tha_x_preferred":[
        "\u0e1a\u0e49\u0e32\u0e19\u0e23\u0e32\u0e29\u0e0e\u0e23\u0e4c\u0e23\u0e31\u0e07\u0e29\u0e35"
    ],
    "wof:name":"Ban Rat Rangsi",
    "wof:placetype":"locality"
},
  "geometry": {"coordinates":[103.99378,15.54897],"type":"Point"}
}