{
  "type": "Feature",
  "properties": {
    "gn:admin1_code":"18.0",
    "gn:asciiname":"Ban U-mung",
    "gn:country_code":"TH",
    "gn:dem":251,
    "gn:feature_class":"P",
    "gn:feature_code":"PPL",
    "gn:name":"Ban U-mung",
    "gn:population":0,
    "gn:timezone":"Asia/Bangkok",
    "iso:country":"TH",
    "name:tha_x_preferred":[
        "\u0e1a\u0e49\u0e32\u0e19\u0e2d\u0e38\u0e21\u0e38\u0e07"
    ],
    "name:tha_x_variant":[
        "Ban U-mung"
    ],
    "name:und_x_variant":[
        "Ban Umung"
    ],
    "wof:lang_x_official":[
        "tha"
    ],
    "wof:lang_x_spoken":[
        "tha"
    ],
    "wof:name":"Ban U-mung",
    "wof:placetype":"locality"
},
  "geometry": {"coordinates":[101.76106,17.89014],"type":"Point"}
}