{
  "type": "Feature",
  "properties": {
    "gn:admin1_code":"80",
    "gn:asciiname":"Ban Khlong Tanot",
    "gn:country_code":"TH",
    "gn:dem":131,
    "gn:feature_class":"P",
    "gn:feature_code":"PPL",
    "gn:name":"Ban Khlong Tanot",
    "gn:population":0,
    "gn:timezone":"Asia/Bangkok",
    "iso:country":"TH",
    "name:tha_x_preferred":[
        "\u0e1a\u0e49\u0e32\u0e19\u0e04\u0e25\u0e2d\u0e07\u0e42\u0e15\u0e19\u0e14"
    ],
    "wof:name":"Ban Khlong Tanot",
    "wof:placetype":"locality"
},
  "geometry": {"coordinates":[102.15349999999999,13.31467],"type":"Point"}
}