{
  "type": "Feature",
  "properties": {
    "gn:admin1_code":"1.0",
    "gn:asciiname":"Ban Kok Luang",
    "gn:country_code":"TH",
    "gn:dem":1050,
    "gn:feature_class":"P",
    "gn:feature_code":"PPL",
    "gn:name":"Ban Kok Luang",
    "gn:population":0,
    "gn:timezone":"Asia/Bangkok",
    "iso:country":"TH",
    "name:tha_x_preferred":[
        "\u0e1a\u0e49\u0e32\u0e19\u0e01\u0e2d\u0e01\u0e2b\u0e25\u0e27\u0e07"
    ],
    "wof:name":"Ban Kok Luang",
    "wof:placetype":"locality"
},
  "geometry": {"coordinates":[98.13964,18.52944],"type":"Point"}
}