{
  "type": "Feature",
  "properties": {
    "gn:admin1_code":"12.0",
    "gn:asciiname":"Ban Wat Chan",
    "gn:country_code":"TH",
    "gn:dem":48,
    "gn:feature_class":"P",
    "gn:feature_code":"PPL",
    "gn:name":"Ban Wat Chan",
    "gn:population":0,
    "gn:timezone":"Asia/Bangkok",
    "iso:country":"TH",
    "name:tha_x_preferred":[
        "\u0e1a\u0e49\u0e32\u0e19\u0e27\u0e31\u0e14\u0e08\u0e31\u0e19\u0e17\u0e23\u0e4c"
    ],
    "name:und_x_variant":[
        "B\u0101n Wat Jan",
        "Ban Wat Chan"
    ],
    "wof:lang_x_official":[
        "tha"
    ],
    "wof:lang_x_spoken":[
        "tha"
    ],
    "wof:name":"Ban Wat Chan",
    "wof:placetype":"locality"
},
  "geometry": {"coordinates":[100.26217,16.79947],"type":"Point"}
}