{
  "type": "Feature",
  "properties": {
    "gn:admin1_code":"31.0",
    "gn:asciiname":"Ban Ma Rue Bo Ok",
    "gn:country_code":"TH",
    "gn:dem":14,
    "gn:feature_class":"P",
    "gn:feature_code":"PPL",
    "gn:name":"Ban Ma Rue Bo Ok",
    "gn:population":0,
    "gn:timezone":"Asia/Bangkok",
    "iso:country":"TH",
    "name:tha_x_preferred":[
        "\u0e1a\u0e49\u0e32\u0e19\u0e21\u0e30\u0e23\u0e37\u0e2d\u0e42\u0e1a\u0e2d\u0e2d\u0e01"
    ],
    "name:und_x_variant":[
        "Ban Maru Bo Ok"
    ],
    "wof:lang_x_official":[
        "tha"
    ],
    "wof:lang_x_spoken":[
        "tha"
    ],
    "wof:name":"Ban Ma Rue Bo Ok",
    "wof:placetype":"locality"
},
  "geometry": {"coordinates":[101.84560999999999,6.2555],"type":"Point"}
}