{
  "type": "Feature",
  "properties": {
    "gn:admin1_code":"69.0",
    "gn:asciiname":"Ban Ka Lae Sin",
    "gn:country_code":"TH",
    "gn:dem":27,
    "gn:feature_class":"P",
    "gn:feature_code":"PPL",
    "gn:name":"Ban Ka Lae Sin",
    "gn:population":0,
    "gn:timezone":"Asia/Bangkok",
    "iso:country":"TH",
    "name:tha_x_preferred":[
        "\u0e1a\u0e49\u0e32\u0e19\u0e01\u0e32\u0e41\u0e25\u0e0b\u0e35\u0e19"
    ],
    "wof:name":"Ban Ka Lae Sin",
    "wof:placetype":"locality"
},
  "geometry": {"coordinates":[101.3035,6.60344],"type":"Point"}
}