{
  "type": "Feature",
  "properties": {
    "gn:admin1_code":"81.0",
    "gn:asciiname":"Ban Thong Sai",
    "gn:country_code":"TH",
    "gn:dem":163,
    "gn:feature_class":"P",
    "gn:feature_code":"PPL",
    "gn:name":"Ban Thong Sai",
    "gn:population":0,
    "gn:timezone":"Asia/Bangkok",
    "iso:country":"TH",
    "name:tha_x_preferred":[
        "\u0e1a\u0e49\u0e32\u0e19\u0e17\u0e2d\u0e07\u0e2a\u0e32\u0e22"
    ],
    "name:und_x_variant":[
        "\u0e1a\u0e49\u0e32\u0e19\u0e17\u0e2d\u0e07\u0e2a\u0e32\u0e22"
    ],
    "wof:name":"Ban Thong Sai",
    "wof:placetype":"locality"
},
  "geometry": {"coordinates":[103.70303,18.25667],"type":"Point"}
}