{
  "type": "Feature",
  "properties": {
    "gn:admin1_code":"9.0",
    "gn:asciiname":"Ban Tha Chanuan",
    "gn:country_code":"TH",
    "gn:dem":49,
    "gn:feature_class":"P",
    "gn:feature_code":"PPL",
    "gn:name":"Ban Tha Chanuan",
    "gn:population":0,
    "gn:timezone":"Asia/Bangkok",
    "iso:country":"TH",
    "name:tha_x_preferred":[
        "\u0e1a\u0e49\u0e32\u0e19\u0e17\u0e48\u0e32\u0e09\u0e19\u0e27\u0e19"
    ],
    "name:und_x_variant":[
        "Ban Wang Won"
    ],
    "wof:name":"Ban Tha Chanuan",
    "wof:placetype":"locality"
},
  "geometry": {"coordinates":[99.88263999999999,16.90719],"type":"Point"}
}