{
  "type": "Feature",
  "properties": {
    "gn:admin1_code":"74.0",
    "gn:asciiname":"Ban Ko Taphao",
    "gn:country_code":"TH",
    "gn:dem":14,
    "gn:feature_class":"P",
    "gn:feature_code":"PPL",
    "gn:name":"Ban Ko Taphao",
    "gn:population":0,
    "gn:timezone":"Asia/Bangkok",
    "iso:country":"TH",
    "name:tha_x_preferred":[
        "\u0e1a\u0e49\u0e32\u0e19\u0e40\u0e01\u0e32\u0e30\u0e15\u0e30\u0e40\u0e20\u0e32"
    ],
    "name:und_x_variant":[
        "Ban Ko Yai Phao"
    ],
    "wof:name":"Ban Ko Taphao",
    "wof:placetype":"locality"
},
  "geometry": {"coordinates":[101.58819,13.98775],"type":"Point"}
}