{
  "type": "Feature",
  "properties": {
    "gn:admin1_code":"60.0",
    "gn:asciiname":"Ban Tham Phueng",
    "gn:country_code":"TH",
    "gn:dem":40,
    "gn:feature_class":"P",
    "gn:feature_code":"PPL",
    "gn:name":"Ban Tham Phueng",
    "gn:population":0,
    "gn:timezone":"Asia/Bangkok",
    "iso:country":"TH",
    "name:tha_x_preferred":[
        "\u0e1a\u0e49\u0e32\u0e19\u0e16\u0e49\u0e33\u0e1c\u0e36\u0e49\u0e07"
    ],
    "wof:name":"Ban Tham Phueng",
    "wof:placetype":"locality"
},
  "geometry": {"coordinates":[98.899,9.01489],"type":"Point"}
}