{
  "type": "Feature",
  "properties": {
    "gn:admin1_code":"29.0",
    "gn:asciiname":"Ban Sawai",
    "gn:country_code":"TH",
    "gn:dem":152,
    "gn:feature_class":"P",
    "gn:feature_code":"PPL",
    "gn:name":"Ban Sawai",
    "gn:population":0,
    "gn:timezone":"Asia/Bangkok",
    "iso:country":"TH",
    "name:tha_x_preferred":[
        "\u0e1a\u0e49\u0e32\u0e19\u0e2a\u0e27\u0e32\u0e22"
    ],
    "wof:name":"Ban Sawai",
    "wof:placetype":"locality"
},
  "geometry": {"coordinates":[103.36739,14.80322],"type":"Point"}
}