{
  "type": "Feature",
  "properties": {
    "gn:admin1_code":"56.0",
    "gn:asciiname":"Ban Pho Phra",
    "gn:country_code":"TH",
    "gn:dem":6,
    "gn:feature_class":"P",
    "gn:feature_code":"PPL",
    "gn:name":"Ban Pho Phra",
    "gn:population":0,
    "gn:timezone":"Asia/Bangkok",
    "iso:country":"TH",
    "name:tha_x_preferred":[
        "\u0e1a\u0e49\u0e32\u0e19\u0e42\u0e1e\u0e1e\u0e23\u0e30"
    ],
    "name:und_x_variant":[
        "Ban Popra",
        "Ban Pho Phra",
        "\u0e1a\u0e49\u0e32\u0e19\u0e42\u0e1e\u0e1e\u0e23\u0e30"
    ],
    "wof:name":"Ban Pho Phra",
    "wof:placetype":"locality"
},
  "geometry": {"coordinates":[100.011,13.08903],"type":"Point"}
}