{
  "type": "Feature",
  "properties": {
    "gn:admin1_code":"60.0",
    "gn:asciiname":"Ban Tha Phak",
    "gn:country_code":"TH",
    "gn:dem":23,
    "gn:feature_class":"P",
    "gn:feature_code":"PPL",
    "gn:name":"Ban Tha Phak",
    "gn:population":0,
    "gn:timezone":"Asia/Bangkok",
    "iso:country":"TH",
    "name:tha_x_preferred":[
        "\u0e1a\u0e49\u0e32\u0e19\u0e17\u0e48\u0e32\u0e1c\u0e32\u0e01"
    ],
    "wof:name":"Ban Tha Phak",
    "wof:placetype":"locality"
},
  "geometry": {"coordinates":[99.09372,9.06644],"type":"Point"}
}