{
  "type": "Feature",
  "properties": {
    "gn:admin1_code":"80.0",
    "gn:asciiname":"Ban Phatthana Nikhom",
    "gn:country_code":"TH",
    "gn:dem":73,
    "gn:feature_class":"P",
    "gn:feature_code":"PPL",
    "gn:name":"Ban Phatthana Nikhom",
    "gn:population":0,
    "gn:timezone":"Asia/Bangkok",
    "iso:country":"TH",
    "name:tha_x_preferred":[
        "\u0e1a\u0e49\u0e32\u0e19\u0e1e\u0e31\u0e12\u0e19\u0e32\u0e19\u0e34\u0e04\u0e21"
    ],
    "wof:name":"Ban Phatthana Nikhom",
    "wof:placetype":"locality"
},
  "geometry": {"coordinates":[102.45303,13.60064],"type":"Point"}
}