{
  "type": "Feature",
  "properties": {
    "gn:admin1_code":"58.0",
    "gn:asciiname":"Ban Thung Khok Chang",
    "gn:country_code":"TH",
    "gn:dem":76,
    "gn:feature_class":"P",
    "gn:feature_code":"PPL",
    "gn:name":"Ban Thung Khok Chang",
    "gn:population":0,
    "gn:timezone":"Asia/Bangkok",
    "iso:country":"TH",
    "name:tha_x_preferred":[
        "\u0e1a\u0e49\u0e32\u0e19\u0e17\u0e38\u0e48\u0e07\u0e04\u0e2d\u0e01\u0e0a\u0e49\u0e32\u0e07"
    ],
    "wof:name":"Ban Thung Khok Chang",
    "wof:placetype":"locality"
},
  "geometry": {"coordinates":[98.96147000000001,10.28706],"type":"Point"}
}