{
  "type": "Feature",
  "properties": {
    "gn:admin1_code":"2.0",
    "gn:asciiname":"Ban Huai Thang",
    "gn:country_code":"TH",
    "gn:dem":285,
    "gn:feature_class":"P",
    "gn:feature_code":"PPL",
    "gn:name":"Ban Huai Thang",
    "gn:population":0,
    "gn:timezone":"Asia/Bangkok",
    "iso:country":"TH",
    "name:tha_x_preferred":[
        "\u0e1a\u0e49\u0e32\u0e19\u0e2b\u0e49\u0e27\u0e22\u0e17\u0e31\u0e07"
    ],
    "name:und_x_variant":[
        "Ban Ton Pin",
        "Ban Huai Tang",
        "Ban Huai Thang"
    ],
    "wof:name":"Ban Huai Thang",
    "wof:placetype":"locality"
},
  "geometry": {"coordinates":[98.81719,18.47908],"type":"Point"}
}