{
  "type": "Feature",
  "properties": {
    "gn:admin1_code":"75.0",
    "gn:asciiname":"Ban Phu Khao Kaeo",
    "gn:country_code":"TH",
    "gn:dem":143,
    "gn:feature_class":"P",
    "gn:feature_code":"PPL",
    "gn:name":"Ban Phu Khao Kaeo",
    "gn:population":0,
    "gn:timezone":"Asia/Bangkok",
    "iso:country":"TH",
    "name:tha_x_preferred":[
        "\u0e1a\u0e49\u0e32\u0e19\u0e20\u0e39\u0e40\u0e02\u0e32\u0e41\u0e01\u0e49\u0e27"
    ],
    "wof:name":"Ban Phu Khao Kaeo",
    "wof:placetype":"locality"
},
  "geometry": {"coordinates":[105.22163999999999,15.24106],"type":"Point"}
}