{
  "type": "Feature",
  "properties": {
    "gn:admin1_code":"30.0",
    "gn:asciiname":"Ban Tamung",
    "gn:country_code":"TH",
    "gn:dem":137,
    "gn:feature_class":"P",
    "gn:feature_code":"PPL",
    "gn:name":"Ban Tamung",
    "gn:population":0,
    "gn:timezone":"Asia/Bangkok",
    "iso:country":"TH",
    "name:tha_x_preferred":[
        "\u0e1a\u0e49\u0e32\u0e19\u0e15\u0e30\u0e21\u0e38\u0e07"
    ],
    "wof:name":"Ban Tamung",
    "wof:placetype":"locality"
},
  "geometry": {"coordinates":[104.05535999999999,14.91825],"type":"Point"}
}