{
  "type": "Feature",
  "properties": {
    "gn:admin1_code":"6.0",
    "gn:asciiname":"Ban Phae Luang",
    "gn:country_code":"TH",
    "gn:dem":175,
    "gn:feature_class":"P",
    "gn:feature_code":"PPL",
    "gn:name":"Ban Phae Luang",
    "gn:population":0,
    "gn:timezone":"Asia/Bangkok",
    "iso:country":"TH",
    "name:tha_x_preferred":[
        "\u0e1a\u0e49\u0e32\u0e19\u0e41\u0e1e\u0e30\u0e2b\u0e25\u0e27\u0e07"
    ],
    "wof:name":"Ban Phae Luang",
    "wof:placetype":"locality"
},
  "geometry": {"coordinates":[99.18831,17.60381],"type":"Point"}
}