{
  "type": "Feature",
  "properties": {
    "gn:admin1_code":"61.0",
    "gn:asciiname":"Ban Pak Khla",
    "gn:country_code":"TH",
    "gn:dem":31,
    "gn:feature_class":"P",
    "gn:feature_code":"PPL",
    "gn:name":"Ban Pak Khla",
    "gn:population":0,
    "gn:timezone":"Asia/Bangkok",
    "iso:country":"TH",
    "name:tha_x_preferred":[
        "\u0e1a\u0e49\u0e32\u0e19\u0e1b\u0e31\u0e01\u0e04\u0e25\u0e49\u0e32"
    ],
    "wof:name":"Ban Pak Khla",
    "wof:placetype":"locality"
},
  "geometry": {"coordinates":[98.27688999999999,8.43806],"type":"Point"}
}