{
  "type": "Feature",
  "properties": {
    "gn:admin1_code":"28",
    "gn:asciiname":"Ban Sin Phatthana",
    "gn:country_code":"TH",
    "gn:dem":199,
    "gn:feature_class":"P",
    "gn:feature_code":"PPL",
    "gn:name":"Ban Sin Phatthana",
    "gn:population":0,
    "gn:timezone":"Asia/Bangkok",
    "iso:country":"TH",
    "name:tha_x_preferred":[
        "\u0e1a\u0e49\u0e32\u0e19\u0e2a\u0e34\u0e19\u0e1e\u0e31\u0e12\u0e19\u0e32"
    ],
    "wof:name":"Ban Sin Phatthana",
    "wof:placetype":"locality"
},
  "geometry": {"coordinates":[102.68619,14.48206],"type":"Point"}
}