{
  "type": "Feature",
  "properties": {
    "gn:admin1_code":"10.0",
    "gn:asciiname":"Ban Fang Laeng",
    "gn:country_code":"TH",
    "gn:dem":108,
    "gn:feature_class":"P",
    "gn:feature_code":"PPL",
    "gn:name":"Ban Fang Laeng",
    "gn:population":0,
    "gn:timezone":"Asia/Bangkok",
    "iso:country":"TH",
    "name:tha_x_preferred":[
        "Ban Fang Laeng"
    ],
    "name:tha_x_variant":[
        "\u0e1a\u0e49\u0e32\u0e19\u0e1d\u0e32\u0e07\u0e41\u0e25\u0e49\u0e07"
    ],
    "wof:name":"Ban Fang Laeng",
    "wof:placetype":"locality"
},
  "geometry": {"coordinates":[100.21572,17.73425],"type":"Point"}
}