{
  "type": "Feature",
  "properties": {
    "gn:admin1_code":"68.0",
    "gn:asciiname":"Ban Ing Kamon",
    "gn:country_code":"TH",
    "gn:dem":21,
    "gn:feature_class":"P",
    "gn:feature_code":"PPL",
    "gn:name":"Ban Ing Kamon",
    "gn:population":0,
    "gn:timezone":"Asia/Bangkok",
    "iso:country":"TH",
    "name:tha_x_preferred":[
        "\u0e1a\u0e49\u0e32\u0e19\u0e2d\u0e34\u0e07\u0e01\u0e21\u0e25"
    ],
    "wof:name":"Ban Ing Kamon",
    "wof:placetype":"locality"
},
  "geometry": {"coordinates":[100.46814000000001,6.93136],"type":"Point"}
}