{
  "type": "Feature",
  "properties": {
    "gn:admin1_code":"22",
    "gn:asciiname":"Ban Kham Ya Daeng",
    "gn:country_code":"TH",
    "gn:dem":225,
    "gn:feature_class":"P",
    "gn:feature_code":"PPL",
    "gn:name":"Ban Kham Ya Daeng",
    "gn:population":0,
    "gn:timezone":"Asia/Bangkok",
    "iso:country":"TH",
    "name:tha_x_preferred":[
        "\u0e1a\u0e49\u0e32\u0e19\u0e04\u0e33\u0e2b\u0e0d\u0e49\u0e32\u0e41\u0e14\u0e07"
    ],
    "wof:name":"Ban Kham Ya Daeng",
    "wof:placetype":"locality"
},
  "geometry": {"coordinates":[102.60921999999999,16.58439],"type":"Point"}
}