{
  "type": "Feature",
  "properties": {
    "gn:admin1_code":"70.0",
    "gn:asciiname":"Ban Ban Nang Bu Bo",
    "gn:country_code":"TH",
    "gn:dem":133,
    "gn:feature_class":"P",
    "gn:feature_code":"PPL",
    "gn:name":"Ban Ban Nang Bu Bo",
    "gn:population":0,
    "gn:timezone":"Asia/Bangkok",
    "iso:country":"TH",
    "name:tha_x_preferred":[
        "\u0e1a\u0e49\u0e32\u0e19\u0e1a\u0e31\u0e19\u0e19\u0e31\u0e07\u0e1a\u0e39\u0e42\u0e1a"
    ],
    "name:und_x_variant":[
        "Na Pupo",
        "Ban Nang Pupo",
        "Ban Ban Nang Bu No",
        "Ban Ban Nang Bu Bo"
    ],
    "wof:name":"Ban Ban Nang Bu Bo",
    "wof:placetype":"locality"
},
  "geometry": {"coordinates":[101.16667,6.24306],"type":"Point"}
}