{
  "type": "Feature",
  "properties": {
    "gn:admin1_code":"31.0",
    "gn:asciiname":"Ban Sapom",
    "gn:country_code":"TH",
    "gn:dem":15,
    "gn:feature_class":"P",
    "gn:feature_code":"PPL",
    "gn:name":"Ban Sapom",
    "gn:population":0,
    "gn:timezone":"Asia/Bangkok",
    "iso:country":"TH",
    "name:tha_x_preferred":[
        "\u0e1a\u0e49\u0e32\u0e19\u0e2a\u0e30\u0e1b\u0e2d\u0e21"
    ],
    "name:und_x_variant":[
        "Sa Paum",
        "Ban Sapom"
    ],
    "wof:name":"Ban Sapom",
    "wof:placetype":"locality"
},
  "geometry": {"coordinates":[101.91036,6.36989],"type":"Point"}
}