{
  "type": "Feature",
  "properties": {
    "gn:admin1_code":"31.0",
    "gn:asciiname":"Ban Thung To Dang",
    "gn:country_code":"TH",
    "gn:dem":15,
    "gn:feature_class":"P",
    "gn:feature_code":"PPL",
    "gn:name":"Ban Thung To Dang",
    "gn:population":0,
    "gn:timezone":"Asia/Bangkok",
    "iso:country":"TH",
    "name:tha_x_preferred":[
        "\u0e1a\u0e49\u0e32\u0e19\u0e17\u0e38\u0e48\u0e07\u0e42\u0e15\u0e4a\u0e30\u0e14\u0e31\u0e07"
    ],
    "wof:name":"Ban Thung To Dang",
    "wof:placetype":"locality"
},
  "geometry": {"coordinates":[101.77922,6.33447],"type":"Point"}
}