{
  "type": "Feature",
  "properties": {
    "gn:admin1_code":"14.0",
    "gn:asciiname":"Ban Khao Din",
    "gn:country_code":"TH",
    "gn:dem":98,
    "gn:feature_class":"P",
    "gn:feature_code":"PPL",
    "gn:name":"Ban Khao Din",
    "gn:population":0,
    "gn:timezone":"Asia/Bangkok",
    "iso:country":"TH",
    "name:tha_x_preferred":[
        "\u0e1a\u0e49\u0e32\u0e19\u0e40\u0e02\u0e32\u0e14\u0e34\u0e19"
    ],
    "wof:name":"Ban Khao Din",
    "wof:placetype":"locality"
},
  "geometry": {"coordinates":[100.74861,16.22481],"type":"Point"}
}