{
  "type": "Feature",
  "properties": {
    "gn:admin1_code":"52.0",
    "gn:asciiname":"Ban Khao Changum",
    "gn:country_code":"TH",
    "gn:dem":22,
    "gn:feature_class":"P",
    "gn:feature_code":"PPL",
    "gn:name":"Ban Khao Changum",
    "gn:population":0,
    "gn:timezone":"Asia/Bangkok",
    "iso:country":"TH",
    "name:tha_x_preferred":[
        "\u0e1a\u0e49\u0e32\u0e19\u0e40\u0e02\u0e32\u0e0a\u0e30\u0e07\u0e38\u0e49\u0e21"
    ],
    "wof:name":"Ban Khao Changum",
    "wof:placetype":"locality"
},
  "geometry": {"coordinates":[99.72967,13.73503],"type":"Point"}
}