{
  "type": "Feature",
  "properties": {
    "gn:admin1_code":"0.0",
    "gn:asciiname":"Ban Tha Ko",
    "gn:country_code":"TH",
    "gn:dem":562,
    "gn:feature_class":"P",
    "gn:feature_code":"PPL",
    "gn:name":"Ban Tha Ko",
    "gn:population":0,
    "gn:timezone":"Asia/Bangkok",
    "iso:country":"TH",
    "wof:name":"Ban Tha Ko",
    "wof:placetype":"locality"
},
  "geometry": {"coordinates":[99.46666999999999,19.43333],"type":"Point"}
}