{
  "type": "Feature",
  "properties": {
    "gn:admin1_code":"69.0",
    "gn:asciiname":"Ban Tha Ya Mu",
    "gn:country_code":"TH",
    "gn:dem":1,
    "gn:feature_class":"P",
    "gn:feature_code":"PPL",
    "gn:name":"Ban Tha Ya Mu",
    "gn:population":0,
    "gn:timezone":"Asia/Bangkok",
    "iso:country":"TH",
    "wof:name":"Ban Tha Ya Mu",
    "wof:placetype":"locality"
},
  "geometry": {"coordinates":[101.07361,6.83722],"type":"Point"}
}