{
  "type": "Feature",
  "properties": {
    "gn:admin1_code":"22.0",
    "gn:asciiname":"Ban Don Daeng",
    "gn:country_code":"TH",
    "gn:dem":157,
    "gn:feature_class":"P",
    "gn:feature_code":"PPL",
    "gn:name":"Ban Don Daeng",
    "gn:population":0,
    "gn:timezone":"Asia/Bangkok",
    "iso:country":"TH",
    "name:tha_x_preferred":[
        "\u0e1a\u0e49\u0e32\u0e19\u0e14\u0e2d\u0e19\u0e41\u0e14\u0e07"
    ],
    "name:und_x_variant":[
        "Don Daeng",
        "Ban Don Daeng"
    ],
    "wof:name":"Ban Don Daeng",
    "wof:placetype":"locality"
},
  "geometry": {"coordinates":[102.85825,16.34317],"type":"Point"}
}