{
  "type": "Feature",
  "properties": {
    "gn:admin1_code":"56.0",
    "gn:asciiname":"Ban Bo Talung",
    "gn:country_code":"TH",
    "gn:dem":7,
    "gn:feature_class":"P",
    "gn:feature_code":"PPL",
    "gn:name":"Ban Bo Talung",
    "gn:population":0,
    "gn:timezone":"Asia/Bangkok",
    "iso:country":"TH",
    "name:tha_x_preferred":[
        "\u0e1a\u0e49\u0e32\u0e19\u0e1a\u0e48\u0e2d\u0e15\u0e30\u0e25\u0e38\u0e07"
    ],
    "wof:name":"Ban Bo Talung",
    "wof:placetype":"locality"
},
  "geometry": {"coordinates":[99.96725000000001,12.74742],"type":"Point"}
}