{
  "type": "Feature",
  "properties": {
    "gn:admin1_code":"12.0",
    "gn:asciiname":"Ban Aranyik",
    "gn:country_code":"TH",
    "gn:dem":47,
    "gn:feature_class":"P",
    "gn:feature_code":"PPL",
    "gn:name":"Ban Aranyik",
    "gn:population":0,
    "gn:timezone":"Asia/Bangkok",
    "iso:country":"TH",
    "name:tha_x_preferred":[
        "\u0e1a\u0e49\u0e32\u0e19\u0e2d\u0e23\u0e31\u0e0d\u0e0d\u0e34\u0e01"
    ],
    "wof:name":"Ban Aranyik",
    "wof:placetype":"locality"
},
  "geometry": {"coordinates":[100.28485999999999,16.82553],"type":"Point"}
}