{
  "type": "Feature",
  "properties": {
    "gn:admin1_code":"66.0",
    "gn:asciiname":"Ban Na Thom",
    "gn:country_code":"TH",
    "gn:dem":28,
    "gn:feature_class":"P",
    "gn:feature_code":"PPL",
    "gn:name":"Ban Na Thom",
    "gn:population":0,
    "gn:timezone":"Asia/Bangkok",
    "iso:country":"TH",
    "name:tha_x_preferred":[
        "\u0e1a\u0e49\u0e32\u0e19\u0e19\u0e32\u0e17\u0e48\u0e2d\u0e21"
    ],
    "wof:name":"Ban Na Thom",
    "wof:placetype":"locality"
},
  "geometry": {"coordinates":[99.95842,7.69139],"type":"Point"}
}