{
  "type": "Feature",
  "properties": {
    "gn:admin1_code":"80",
    "gn:asciiname":"Ban Wang Champi",
    "gn:country_code":"TH",
    "gn:dem":102,
    "gn:feature_class":"P",
    "gn:feature_code":"PPL",
    "gn:name":"Ban Wang Champi",
    "gn:population":0,
    "gn:timezone":"Asia/Bangkok",
    "iso:country":"TH",
    "name:tha_x_preferred":[
        "\u0e1a\u0e49\u0e32\u0e19\u0e27\u0e31\u0e07\u0e08\u0e33\u0e1b\u0e35"
    ],
    "wof:name":"Ban Wang Champi",
    "wof:placetype":"locality"
},
  "geometry": {"coordinates":[102.19741999999999,13.50306],"type":"Point"}
}