{
  "type": "Feature",
  "properties": {
    "gn:admin1_code":"56.0",
    "gn:asciiname":"Ban Tanot Luang",
    "gn:country_code":"TH",
    "gn:dem":7,
    "gn:feature_class":"P",
    "gn:feature_code":"PPL",
    "gn:name":"Ban Tanot Luang",
    "gn:population":0,
    "gn:timezone":"Asia/Bangkok",
    "iso:country":"TH",
    "name:tha_x_preferred":[
        "\u0e1a\u0e49\u0e32\u0e19\u0e42\u0e15\u0e19\u0e14\u0e2b\u0e25\u0e27\u0e07"
    ],
    "wof:name":"Ban Tanot Luang",
    "wof:placetype":"locality"
},
  "geometry": {"coordinates":[100.00055,12.87975],"type":"Point"}
}