{
  "type": "Feature",
  "properties": {
    "gn:admin1_code":"2.0",
    "gn:asciiname":"Ban Mae Ka Talat",
    "gn:country_code":"TH",
    "gn:dem":317,
    "gn:feature_class":"P",
    "gn:feature_code":"PPL",
    "gn:name":"Ban Mae Ka Talat",
    "gn:population":0,
    "gn:timezone":"Asia/Bangkok",
    "iso:country":"TH",
    "name:tha_x_preferred":[
        "\u0e1a\u0e49\u0e32\u0e19\u0e41\u0e21\u0e48\u0e01\u0e4a\u0e30\u0e15\u0e25\u0e32\u0e14"
    ],
    "name:und_x_variant":[
        "B\u0101n Mea Keu",
        "Ban Mae Khu",
        "Ban Mae Ka Talat Luang",
        "Ban Mae Ka Talat"
    ],
    "wof:name":"Ban Mae Ka Talat",
    "wof:placetype":"locality"
},
  "geometry": {"coordinates":[99.12244,18.81533],"type":"Point"}
}