{
  "type": "Feature",
  "properties": {
    "gn:admin1_code":"64.0",
    "gn:asciiname":"Ban Noen Nong Hong",
    "gn:country_code":"TH",
    "gn:dem":8,
    "gn:feature_class":"P",
    "gn:feature_code":"PPL",
    "gn:name":"Ban Noen Nong Hong",
    "gn:population":0,
    "gn:timezone":"Asia/Bangkok",
    "iso:country":"TH",
    "name:tha_x_preferred":[
        "\u0e1a\u0e49\u0e32\u0e19\u0e40\u0e19\u0e34\u0e19\u0e2b\u0e19\u0e2d\u0e07\u0e2b\u0e07\u0e2a\u0e4c"
    ],
    "name:und_x_variant":[
        "Ban Noen"
    ],
    "wof:name":"Ban Noen Nong Hong",
    "wof:placetype":"locality"
},
  "geometry": {"coordinates":[100.27988999999999,8.15358],"type":"Point"}
}