{
  "type": "Feature",
  "properties": {
    "gn:admin1_code":"14.0",
    "gn:asciiname":"Ban Huai Ron Thong",
    "gn:country_code":"TH",
    "gn:dem":244,
    "gn:feature_class":"P",
    "gn:feature_code":"PPL",
    "gn:name":"Ban Huai Ron Thong",
    "gn:population":0,
    "gn:timezone":"Asia/Bangkok",
    "iso:country":"TH",
    "name:tha_x_preferred":[
        "\u0e1a\u0e49\u0e32\u0e19\u0e2b\u0e49\u0e27\u0e22\u0e23\u0e48\u0e2d\u0e19\u0e17\u0e2d\u0e07"
    ],
    "wof:name":"Ban Huai Ron Thong",
    "wof:placetype":"locality"
},
  "geometry": {"coordinates":[101.31959000000001,16.52851],"type":"Point"}
}