{
  "type": "Feature",
  "properties": {
    "gn:admin1_code":"74.0",
    "gn:asciiname":"Ban Laem",
    "gn:country_code":"TH",
    "gn:dem":8,
    "gn:feature_class":"P",
    "gn:feature_code":"PPL",
    "gn:name":"Ban Laem",
    "gn:population":0,
    "gn:timezone":"Asia/Bangkok",
    "iso:country":"TH",
    "name:tha_x_preferred":[
        "\u0e1a\u0e49\u0e32\u0e19\u0e41\u0e2b\u0e25\u0e21"
    ],
    "wof:name":"Ban Laem",
    "wof:placetype":"locality"
},
  "geometry": {"coordinates":[101.21138999999999,13.96439],"type":"Point"}
}