{
  "type": "Feature",
  "properties": {
    "gn:admin1_code":"18.0",
    "gn:asciiname":"Ban Na Phakkam",
    "gn:country_code":"TH",
    "gn:dem":760,
    "gn:feature_class":"P",
    "gn:feature_code":"PPL",
    "gn:name":"Ban Na Phakkam",
    "gn:population":0,
    "gn:timezone":"Asia/Bangkok",
    "iso:country":"TH",
    "name:tha_x_preferred":[
        "Ban Na Phakkam"
    ],
    "name:tha_x_variant":[
        "\u0e1a\u0e49\u0e32\u0e19\u0e19\u0e32\u0e1c\u0e31\u0e01\u0e01\u0e49\u0e32\u0e21"
    ],
    "wof:name":"Ban Na Phakkam",
    "wof:placetype":"locality"
},
  "geometry": {"coordinates":[100.8826,17.52006],"type":"Point"}
}