{
  "type": "Feature",
  "properties": {
    "gn:admin1_code":"7.0",
    "gn:asciiname":"Ban Mae Lan Phatthana",
    "gn:country_code":"TH",
    "gn:dem":143,
    "gn:feature_class":"P",
    "gn:feature_code":"PPL",
    "gn:name":"Ban Mae Lan Phatthana",
    "gn:population":0,
    "gn:timezone":"Asia/Bangkok",
    "iso:country":"TH",
    "name:tha_x_preferred":[
        "\u0e1a\u0e49\u0e32\u0e19\u0e41\u0e21\u0e48\u0e25\u0e32\u0e19\u0e1e\u0e31\u0e12\u0e19\u0e32"
    ],
    "wof:name":"Ban Mae Lan Phatthana",
    "wof:placetype":"locality"
},
  "geometry": {"coordinates":[99.84769,18.08053],"type":"Point"}
}