{
  "type": "Feature",
  "properties": {
    "gn:admin1_code":"60.0",
    "gn:asciiname":"Ban Bang Yai Fang Sai",
    "gn:country_code":"TH",
    "gn:dem":9,
    "gn:feature_class":"P",
    "gn:feature_code":"PPL",
    "gn:name":"Ban Bang Yai Fang Sai",
    "gn:population":0,
    "gn:timezone":"Asia/Bangkok",
    "iso:country":"TH",
    "name:tha_x_preferred":[
        "\u0e1a\u0e49\u0e32\u0e19\u0e1a\u0e32\u0e07\u0e43\u0e2b\u0e0d\u0e48\u0e1d\u0e31\u0e48\u0e07\u0e0b\u0e49\u0e32\u0e22"
    ],
    "wof:name":"Ban Bang Yai Fang Sai",
    "wof:placetype":"locality"
},
  "geometry": {"coordinates":[99.23939,9.17672],"type":"Point"}
}