{
  "type": "Feature",
  "properties": {
    "gn:admin1_code":"16.0",
    "gn:asciiname":"Ban Noen Pho",
    "gn:country_code":"TH",
    "gn:dem":34,
    "gn:feature_class":"P",
    "gn:feature_code":"PPL",
    "gn:name":"Ban Noen Pho",
    "gn:population":0,
    "gn:timezone":"Asia/Bangkok",
    "iso:country":"TH",
    "name:tha_x_preferred":[
        "\u0e1a\u0e49\u0e32\u0e19\u0e40\u0e19\u0e34\u0e19\u0e42\u0e1e\u0e18\u0e34\u0e4c"
    ],
    "name:und_x_variant":[
        "Ban Non Pho",
        "Ban Noen Pho"
    ],
    "wof:name":"Ban Noen Pho",
    "wof:placetype":"locality"
},
  "geometry": {"coordinates":[100.15097,15.91886],"type":"Point"}
}