{
  "type": "Feature",
  "properties": {
    "gn:admin1_code":"50.0",
    "gn:asciiname":"Ban Thung Na Nang Rok",
    "gn:country_code":"TH",
    "gn:dem":51,
    "gn:feature_class":"P",
    "gn:feature_code":"PPL",
    "gn:name":"Ban Thung Na Nang Rok",
    "gn:population":0,
    "gn:timezone":"Asia/Bangkok",
    "iso:country":"TH",
    "name:tha_x_preferred":[
        "\u0e1a\u0e49\u0e32\u0e19\u0e17\u0e38\u0e48\u0e07\u0e19\u0e32\u0e19\u0e32\u0e07\u0e2b\u0e23\u0e2d\u0e01"
    ],
    "wof:name":"Ban Thung Na Nang Rok",
    "wof:placetype":"locality"
},
  "geometry": {"coordinates":[99.43647,14.17025],"type":"Point"}
}