{
  "type": "Feature",
  "properties": {
    "gn:admin1_code":"11.0",
    "gn:asciiname":"Ban Rungrot",
    "gn:country_code":"TH",
    "gn:dem":62,
    "gn:feature_class":"P",
    "gn:feature_code":"PPL",
    "gn:name":"Ban Rungrot",
    "gn:population":0,
    "gn:timezone":"Asia/Bangkok",
    "iso:country":"TH",
    "name:tha_x_preferred":[
        "\u0e1a\u0e49\u0e32\u0e19\u0e23\u0e38\u0e48\u0e07\u0e42\u0e23\u0e08\u0e19\u0e4c"
    ],
    "wof:name":"Ban Rungrot",
    "wof:placetype":"locality"
},
  "geometry": {"coordinates":[99.79594,16.60475],"type":"Point"}
}