{
  "type": "Feature",
  "properties": {
    "gn:admin1_code":"25.0",
    "gn:asciiname":"Ban Phon Tum",
    "gn:country_code":"TH",
    "gn:dem":137,
    "gn:feature_class":"P",
    "gn:feature_code":"PPL",
    "gn:name":"Ban Phon Tum",
    "gn:population":0,
    "gn:timezone":"Asia/Bangkok",
    "iso:country":"TH",
    "name:tha_x_preferred":[
        "\u0e1a\u0e49\u0e32\u0e19\u0e42\u0e1e\u0e19\u0e15\u0e39\u0e21"
    ],
    "name:und_x_variant":[
        "Ban Non Tum"
    ],
    "wof:lang_x_official":[
        "tha"
    ],
    "wof:lang_x_spoken":[
        "tha"
    ],
    "wof:name":"Ban Phon Tum",
    "wof:placetype":"locality"
},
  "geometry": {"coordinates":[103.47597,15.46736],"type":"Point"}
}