{
  "type": "Feature",
  "properties": {
    "gn:admin1_code":"14.0",
    "gn:asciiname":"Ban Nong Mae Raeng",
    "gn:country_code":"TH",
    "gn:dem":100,
    "gn:feature_class":"P",
    "gn:feature_code":"PPL",
    "gn:name":"Ban Nong Mae Raeng",
    "gn:population":0,
    "gn:timezone":"Asia/Bangkok",
    "iso:country":"TH",
    "name:tha_x_preferred":[
        "\u0e1a\u0e49\u0e32\u0e19\u0e2b\u0e19\u0e2d\u0e07\u0e41\u0e21\u0e48\u0e41\u0e23\u0e07"
    ],
    "wof:name":"Ban Nong Mae Raeng",
    "wof:placetype":"locality"
},
  "geometry": {"coordinates":[101.12067,15.85639],"type":"Point"}
}