{
  "type": "Feature",
  "properties": {
    "gn:admin1_code":"70.0",
    "gn:asciiname":"Ban Ba La Sa Me Lae",
    "gn:country_code":"TH",
    "gn:dem":32,
    "gn:feature_class":"P",
    "gn:feature_code":"PPL",
    "gn:name":"Ban Ba La Sa Me Lae",
    "gn:population":0,
    "gn:timezone":"Asia/Bangkok",
    "iso:country":"TH",
    "name:tha_x_preferred":[
        "\u0e1a\u0e49\u0e32\u0e19\u0e1a\u0e32\u0e25\u0e32\u0e2a\u0e30\u0e21\u0e35\u0e41\u0e25"
    ],
    "wof:name":"Ban Ba La Sa Me Lae",
    "wof:placetype":"locality"
},
  "geometry": {"coordinates":[101.41347,6.49581],"type":"Point"}
}