{
  "type": "Feature",
  "properties": {
    "gn:admin1_code":"28",
    "gn:asciiname":"Ban Nong Samet",
    "gn:country_code":"TH",
    "gn:dem":184,
    "gn:feature_class":"P",
    "gn:feature_code":"PPL",
    "gn:name":"Ban Nong Samet",
    "gn:population":0,
    "gn:timezone":"Asia/Bangkok",
    "iso:country":"TH",
    "name:tha_x_preferred":[
        "\u0e1a\u0e49\u0e32\u0e19\u0e2b\u0e19\u0e2d\u0e07\u0e40\u0e2a\u0e21\u0e47\u0e14"
    ],
    "wof:name":"Ban Nong Samet",
    "wof:placetype":"locality"
},
  "geometry": {"coordinates":[102.76927999999999,14.88494],"type":"Point"}
}