{
  "type": "Feature",
  "properties": {
    "gn:admin1_code":"37",
    "gn:asciiname":"Ban Khon Hom",
    "gn:country_code":"TH",
    "gn:dem":27,
    "gn:feature_class":"P",
    "gn:feature_code":"PPL",
    "gn:name":"Ban Khon Hom",
    "gn:population":0,
    "gn:timezone":"Asia/Bangkok",
    "iso:country":"TH",
    "name:tha_x_preferred":[
        "\u0e1a\u0e49\u0e32\u0e19\u0e02\u0e2d\u0e19\u0e2b\u0e2d\u0e21"
    ],
    "wof:name":"Ban Khon Hom",
    "wof:placetype":"locality"
},
  "geometry": {"coordinates":[100.98219,14.57725],"type":"Point"}
}