{
  "type": "Feature",
  "properties": {
    "gn:admin1_code":"27",
    "gn:asciiname":"Ban Khao Chan",
    "gn:country_code":"TH",
    "gn:dem":472,
    "gn:feature_class":"P",
    "gn:feature_code":"PPL",
    "gn:name":"Ban Khao Chan",
    "gn:population":0,
    "gn:timezone":"Asia/Bangkok",
    "iso:country":"TH",
    "name:tha_x_preferred":[
        "\u0e1a\u0e49\u0e32\u0e19\u0e40\u0e02\u0e32\u0e08\u0e31\u0e19\u0e17\u0e23\u0e4c"
    ],
    "wof:name":"Ban Khao Chan",
    "wof:placetype":"locality"
},
  "geometry": {"coordinates":[101.31939,14.57236],"type":"Point"}
}