{
  "type": "Feature",
  "properties": {
    "gn:admin1_code":"27.0",
    "gn:asciiname":"Ban Chong Maeo",
    "gn:country_code":"TH",
    "gn:dem":150,
    "gn:feature_class":"P",
    "gn:feature_code":"PPL",
    "gn:name":"Ban Chong Maeo",
    "gn:population":0,
    "gn:timezone":"Asia/Bangkok",
    "iso:country":"TH",
    "name:tha_x_preferred":[
        "\u0e1a\u0e49\u0e32\u0e19\u0e0a\u0e48\u0e2d\u0e07\u0e41\u0e21\u0e27"
    ],
    "name:und_x_variant":[
        "Chaung Meo",
        "Ban Chang Maeo",
        "Ban Chong Maeo"
    ],
    "wof:name":"Ban Chong Maeo",
    "wof:placetype":"locality"
},
  "geometry": {"coordinates":[102.77614,15.47228],"type":"Point"}
}