{
  "type": "Feature",
  "properties": {
    "gn:admin1_code":"25.0",
    "gn:asciiname":"Ban Khung Sa-at",
    "gn:country_code":"TH",
    "gn:dem":133,
    "gn:feature_class":"P",
    "gn:feature_code":"PPL",
    "gn:name":"Ban Khung Sa-at",
    "gn:population":0,
    "gn:timezone":"Asia/Bangkok",
    "iso:country":"TH",
    "name:tha_x_preferred":[
        "\u0e1a\u0e49\u0e32\u0e19\u0e04\u0e38\u0e49\u0e07\u0e2a\u0e30\u0e2d\u0e32\u0e14"
    ],
    "wof:name":"Ban Khung Sa-at",
    "wof:placetype":"locality"
},
  "geometry": {"coordinates":[103.90397,15.95169],"type":"Point"}
}