{
  "type": "Feature",
  "properties": {
    "gn:admin1_code":"50.0",
    "gn:asciiname":"Ban Don Ta Phet",
    "gn:country_code":"TH",
    "gn:dem":17,
    "gn:feature_class":"P",
    "gn:feature_code":"PPL",
    "gn:name":"Ban Don Ta Phet",
    "gn:population":0,
    "gn:timezone":"Asia/Bangkok",
    "iso:country":"TH",
    "name:tha_x_preferred":[
        "\u0e1a\u0e49\u0e32\u0e19\u0e14\u0e2d\u0e19\u0e15\u0e32\u0e40\u0e1e\u0e0a\u0e23"
    ],
    "wof:name":"Ban Don Ta Phet",
    "wof:placetype":"locality"
},
  "geometry": {"coordinates":[99.72933,14.18672],"type":"Point"}
}