{
  "type": "Feature",
  "properties": {
    "gn:admin1_code":"61.0",
    "gn:asciiname":"Ban Pak Phu",
    "gn:country_code":"TH",
    "gn:dem":24,
    "gn:feature_class":"P",
    "gn:feature_code":"PPL",
    "gn:name":"Ban Pak Phu",
    "gn:population":0,
    "gn:timezone":"Asia/Bangkok",
    "iso:country":"TH",
    "name:tha_x_preferred":[
        "\u0e1a\u0e49\u0e32\u0e19\u0e1b\u0e32\u0e01\u0e1e\u0e39\u0e48"
    ],
    "name:und_x_variant":[
        "Ban Phu"
    ],
    "wof:name":"Ban Pak Phu",
    "wof:placetype":"locality"
},
  "geometry": {"coordinates":[98.42456,8.71778],"type":"Point"}
}