{
  "type": "Feature",
  "properties": {
    "gn:admin1_code":"58.0",
    "gn:asciiname":"Ban Tha Kradan",
    "gn:country_code":"TH",
    "gn:dem":10,
    "gn:feature_class":"P",
    "gn:feature_code":"PPL",
    "gn:name":"Ban Tha Kradan",
    "gn:population":0,
    "gn:timezone":"Asia/Bangkok",
    "iso:country":"TH",
    "name:tha_x_preferred":[
        "\u0e1a\u0e49\u0e32\u0e19\u0e17\u0e48\u0e32\u0e01\u0e23\u0e30\u0e14\u0e32\u0e19"
    ],
    "name:und_x_variant":[
        "Ban Tha Kadan",
        "Ban Tha Kradan"
    ],
    "wof:name":"Ban Tha Kradan",
    "wof:placetype":"locality"
},
  "geometry": {"coordinates":[99.17,10.51989],"type":"Point"}
}