{
  "type": "Feature",
  "properties": {
    "gn:admin1_code":"3.0",
    "gn:asciiname":"Ban Tap Tao",
    "gn:country_code":"TH",
    "gn:dem":399,
    "gn:feature_class":"P",
    "gn:feature_code":"PPL",
    "gn:name":"Ban Tap Tao",
    "gn:population":0,
    "gn:timezone":"Asia/Bangkok",
    "iso:country":"TH",
    "name:tha_x_preferred":[
        "\u0e1a\u0e49\u0e32\u0e19\u0e15\u0e31\u0e1a\u0e40\u0e15\u0e48\u0e32"
    ],
    "name:und_x_variant":[
        "B\u0101n Tab T\u0101o",
        "Ban Tap Tao"
    ],
    "wof:lang_x_official":[
        "tha"
    ],
    "wof:lang_x_spoken":[
        "tha"
    ],
    "wof:name":"Ban Tap Tao",
    "wof:placetype":"locality"
},
  "geometry": {"coordinates":[100.29058000000001,19.71539],"type":"Point"}
}