{
  "type": "Feature",
  "properties": {
    "gn:admin1_code":"7.0",
    "gn:asciiname":"Ban Na Tong",
    "gn:country_code":"TH",
    "gn:dem":604,
    "gn:feature_class":"P",
    "gn:feature_code":"PPL",
    "gn:name":"Ban Na Tong",
    "gn:population":0,
    "gn:timezone":"Asia/Bangkok",
    "iso:country":"TH",
    "name:tha_x_preferred":[
        "\u0e1a\u0e49\u0e32\u0e19\u0e19\u0e32\u0e15\u0e2d\u0e07"
    ],
    "wof:name":"Ban Na Tong",
    "wof:placetype":"locality"
},
  "geometry": {"coordinates":[100.25153,17.99788999999999],"type":"Point"}
}