{
  "type": "Feature",
  "properties": {
    "gn:admin1_code":"3.0",
    "gn:asciiname":"Ban Ya Fu",
    "gn:country_code":"TH",
    "gn:dem":730,
    "gn:feature_class":"P",
    "gn:feature_code":"PPL",
    "gn:name":"Ban Ya Fu",
    "gn:population":0,
    "gn:timezone":"Asia/Bangkok",
    "iso:country":"TH",
    "name:tha_x_preferred":[
        "\u0e1a\u0e49\u0e32\u0e19\u0e22\u0e30\u0e1f\u0e39"
    ],
    "wof:name":"Ban Ya Fu",
    "wof:placetype":"locality"
},
  "geometry": {"coordinates":[99.70347,19.99539],"type":"Point"}
}