{
  "type": "Feature",
  "properties": {
    "gn:admin1_code":"1.0",
    "gn:asciiname":"Ban Mae Ok Klang",
    "gn:country_code":"TH",
    "gn:dem":742,
    "gn:feature_class":"P",
    "gn:feature_code":"PPL",
    "gn:name":"Ban Mae Ok Klang",
    "gn:population":0,
    "gn:timezone":"Asia/Bangkok",
    "iso:country":"TH",
    "name:tha_x_preferred":[
        "\u0e1a\u0e49\u0e32\u0e19\u0e41\u0e21\u0e48\u0e2d\u0e2d\u0e01\u0e01\u0e25\u0e32\u0e07"
    ],
    "name:und_x_variant":[
        "Ban Mae Ok"
    ],
    "wof:name":"Ban Mae Ok Klang",
    "wof:placetype":"locality"
},
  "geometry": {"coordinates":[98.02061,17.99192],"type":"Point"}
}