{
  "type": "Feature",
  "properties": {
    "gn:admin1_code":"20.0",
    "gn:asciiname":"Ban Thang Khong Phatthana",
    "gn:country_code":"TH",
    "gn:dem":166,
    "gn:feature_class":"P",
    "gn:feature_code":"PPL",
    "gn:name":"Ban Thang Khong Phatthana",
    "gn:population":0,
    "gn:timezone":"Asia/Bangkok",
    "iso:country":"TH",
    "name:tha_x_preferred":[
        "\u0e1a\u0e49\u0e32\u0e19\u0e17\u0e32\u0e07\u0e42\u0e04\u0e49\u0e07\u0e1e\u0e31\u0e12\u0e19\u0e32"
    ],
    "wof:name":"Ban Thang Khong Phatthana",
    "wof:placetype":"locality"
},
  "geometry": {"coordinates":[103.65364,17.94547],"type":"Point"}
}