{
  "type": "Feature",
  "properties": {
    "gn:admin1_code":"25",
    "gn:asciiname":"Ban Thung Yang Pia Phatthana",
    "gn:country_code":"TH",
    "gn:dem":141,
    "gn:feature_class":"P",
    "gn:feature_code":"PPL",
    "gn:name":"Ban Thung Yang Pia Phatthana",
    "gn:population":0,
    "gn:timezone":"Asia/Bangkok",
    "iso:country":"TH",
    "name:tha_x_preferred":[
        "\u0e1a\u0e49\u0e32\u0e19\u0e17\u0e38\u0e48\u0e07\u0e22\u0e32\u0e07\u0e40\u0e1b\u0e35\u0e49\u0e22\u0e1e\u0e31\u0e12\u0e19\u0e32"
    ],
    "wof:name":"Ban Thung Yang Pia Phatthana",
    "wof:placetype":"locality"
},
  "geometry": {"coordinates":[103.81514,16.12206],"type":"Point"}
}