{
  "type": "Feature",
  "properties": {
    "gn:admin1_code":"11.0",
    "gn:asciiname":"Ban Noen Kruat",
    "gn:country_code":"TH",
    "gn:dem":104,
    "gn:feature_class":"P",
    "gn:feature_code":"PPL",
    "gn:name":"Ban Noen Kruat",
    "gn:population":0,
    "gn:timezone":"Asia/Bangkok",
    "iso:country":"TH",
    "name:tha_x_preferred":[
        "\u0e1a\u0e49\u0e32\u0e19\u0e40\u0e19\u0e34\u0e19\u0e01\u0e23\u0e27\u0e14"
    ],
    "wof:name":"Ban Noen Kruat",
    "wof:placetype":"locality"
},
  "geometry": {"coordinates":[99.44522000000001,16.56603],"type":"Point"}
}