{
  "type": "Feature",
  "properties": {
    "gn:admin1_code":"37",
    "gn:asciiname":"Ban Phae Khaek Daeng",
    "gn:country_code":"TH",
    "gn:dem":15,
    "gn:feature_class":"P",
    "gn:feature_code":"PPL",
    "gn:name":"Ban Phae Khaek Daeng",
    "gn:population":0,
    "gn:timezone":"Asia/Bangkok",
    "iso:country":"TH",
    "name:tha_x_preferred":[
        "\u0e1a\u0e49\u0e32\u0e19\u0e41\u0e1e\u0e30\u0e41\u0e02\u0e01\u0e41\u0e14\u0e07"
    ],
    "wof:name":"Ban Phae Khaek Daeng",
    "wof:placetype":"locality"
},
  "geometry": {"coordinates":[100.858,14.54122],"type":"Point"}
}