{
  "type": "Feature",
  "properties": {
    "gn:admin1_code":"18.0",
    "gn:asciiname":"Ban Kok Kluea",
    "gn:country_code":"TH",
    "gn:dem":253,
    "gn:feature_class":"P",
    "gn:feature_code":"PPL",
    "gn:name":"Ban Kok Kluea",
    "gn:population":0,
    "gn:timezone":"Asia/Bangkok",
    "iso:country":"TH",
    "name:tha_x_preferred":[
        "Ban Kok Kluea"
    ],
    "name:tha_x_variant":[
        "\u0e1a\u0e49\u0e32\u0e19\u0e01\u0e01\u0e40\u0e01\u0e25\u0e37\u0e2d"
    ],
    "name:und_x_variant":[
        "Ban Nong Kok Kua"
    ],
    "wof:name":"Ban Kok Kluea",
    "wof:placetype":"locality"
},
  "geometry": {"coordinates":[101.75878,17.33006],"type":"Point"}
}