{
  "type": "Feature",
  "properties": {
    "gn:admin1_code":"70.0",
    "gn:asciiname":"Ban Kampong Ba-ngo",
    "gn:country_code":"TH",
    "gn:dem":24,
    "gn:feature_class":"P",
    "gn:feature_code":"PPL",
    "gn:name":"Ban Kampong Ba-ngo",
    "gn:population":0,
    "gn:timezone":"Asia/Bangkok",
    "iso:country":"TH",
    "name:tha_x_preferred":[
        "\u0e1a\u0e49\u0e32\u0e19\u0e01\u0e33\u0e1b\u0e07\u0e1a\u0e32\u0e42\u0e07"
    ],
    "wof:name":"Ban Kampong Ba-ngo",
    "wof:placetype":"locality"
},
  "geometry": {"coordinates":[101.45272,6.49122],"type":"Point"}
}