{
  "type": "Feature",
  "properties": {
    "gn:admin1_code":"60.0",
    "gn:asciiname":"Ban Chong Yung Thong",
    "gn:country_code":"TH",
    "gn:dem":73,
    "gn:feature_class":"P",
    "gn:feature_code":"PPL",
    "gn:name":"Ban Chong Yung Thong",
    "gn:population":0,
    "gn:timezone":"Asia/Bangkok",
    "iso:country":"TH",
    "name:tha_x_preferred":[
        "\u0e1a\u0e49\u0e32\u0e19\u0e0a\u0e48\u0e2d\u0e07\u0e22\u0e38\u0e07\u0e17\u0e2d\u0e07"
    ],
    "wof:name":"Ban Chong Yung Thong",
    "wof:placetype":"locality"
},
  "geometry": {"coordinates":[99.00275000000001,9.65528],"type":"Point"}
}