{
  "type": "Feature",
  "properties": {
    "gn:admin1_code":"53.0",
    "gn:asciiname":"Ban Rong Nam Khao",
    "gn:country_code":"TH",
    "gn:dem":7,
    "gn:feature_class":"P",
    "gn:feature_code":"PPL",
    "gn:name":"Ban Rong Nam Khao",
    "gn:population":0,
    "gn:timezone":"Asia/Bangkok",
    "iso:country":"TH",
    "name:tha_x_preferred":[
        "\u0e1a\u0e49\u0e32\u0e19\u0e42\u0e23\u0e07\u0e19\u0e49\u0e33\u0e02\u0e32\u0e27"
    ],
    "wof:name":"Ban Rong Nam Khao",
    "wof:placetype":"locality"
},
  "geometry": {"coordinates":[99.94867000000001,13.78006],"type":"Point"}
}