{
  "type": "Feature",
  "properties": {
    "gn:admin1_code":"46.0",
    "gn:asciiname":"Ban Si Yaek Nong Prue",
    "gn:country_code":"TH",
    "gn:dem":60,
    "gn:feature_class":"P",
    "gn:feature_code":"PPL",
    "gn:name":"Ban Si Yaek Nong Prue",
    "gn:population":0,
    "gn:timezone":"Asia/Bangkok",
    "iso:country":"TH",
    "name:tha_x_preferred":[
        "\u0e1a\u0e49\u0e32\u0e19\u0e2a\u0e35\u0e48\u0e41\u0e22\u0e01\u0e2b\u0e19\u0e2d\u0e07\u0e1b\u0e23\u0e37\u0e2d"
    ],
    "wof:name":"Ban Si Yaek Nong Prue",
    "wof:placetype":"locality"
},
  "geometry": {"coordinates":[101.23042,13.22956],"type":"Point"}
}