{
  "type": "Feature",
  "properties": {
    "gn:admin1_code":"4.0",
    "gn:asciiname":"Ban Yap Na Loem",
    "gn:country_code":"TH",
    "gn:dem":361,
    "gn:feature_class":"P",
    "gn:feature_code":"PPL",
    "gn:name":"Ban Yap Na Loem",
    "gn:population":0,
    "gn:timezone":"Asia/Bangkok",
    "iso:country":"TH",
    "name:tha_x_preferred":[
        "\u0e1a\u0e49\u0e32\u0e19\u0e22\u0e32\u0e1a\u0e19\u0e32\u0e40\u0e25\u0e34\u0e21"
    ],
    "name:und_x_variant":[
        "Ban Loem"
    ],
    "wof:lang_x_official":[
        "tha"
    ],
    "wof:lang_x_spoken":[
        "tha"
    ],
    "wof:name":"Ban Yap Na Loem",
    "wof:placetype":"locality"
},
  "geometry": {"coordinates":[100.55222000000001,18.67519],"type":"Point"}
}