{
  "type": "Feature",
  "properties": {
    "gn:admin1_code":"8.0",
    "gn:asciiname":"Ban Nong Chalap Nueng",
    "gn:country_code":"TH",
    "gn:dem":139,
    "gn:feature_class":"P",
    "gn:feature_code":"PPL",
    "gn:name":"Ban Nong Chalap Nueng",
    "gn:population":0,
    "gn:timezone":"Asia/Bangkok",
    "iso:country":"TH",
    "name:tha_x_preferred":[
        "Ban Nong Chalap Nueng"
    ],
    "name:tha_x_variant":[
        "\u0e1a\u0e49\u0e32\u0e19\u0e2b\u0e19\u0e2d\u0e07\u0e0a\u0e30\u0e25\u0e32\u0e1a \u0e2b\u0e19\u0e36\u0e48\u0e07"
    ],
    "wof:name":"Ban Nong Chalap Nueng",
    "wof:placetype":"locality"
},
  "geometry": {"coordinates":[99.13433000000001,16.97775],"type":"Point"}
}