{
  "type": "Feature",
  "properties": {
    "gn:admin1_code":"60.0",
    "gn:asciiname":"Ban Yung Ngam",
    "gn:country_code":"TH",
    "gn:dem":27,
    "gn:feature_class":"P",
    "gn:feature_code":"PPL",
    "gn:name":"Ban Yung Ngam",
    "gn:population":0,
    "gn:timezone":"Asia/Bangkok",
    "iso:country":"TH",
    "name:tha_x_preferred":[
        "\u0e1a\u0e49\u0e32\u0e19\u0e22\u0e39\u0e07\u0e07\u0e32\u0e21"
    ],
    "wof:name":"Ban Yung Ngam",
    "wof:placetype":"locality"
},
  "geometry": {"coordinates":[99.34258,8.55525],"type":"Point"}
}