{
  "type": "Feature",
  "properties": {
    "gn:admin1_code":"40.0",
    "gn:admin2_code":"1024.0",
    "gn:asciiname":"Ban Khlong Bang Pa Kok",
    "gn:country_code":"TH",
    "gn:dem":7,
    "gn:feature_class":"P",
    "gn:feature_code":"PPL",
    "gn:name":"Ban Khlong Bang Pa Kok",
    "gn:population":0,
    "gn:timezone":"Asia/Bangkok",
    "iso:country":"TH",
    "name:tha_x_preferred":[
        "\u0e1a\u0e49\u0e32\u0e19\u0e04\u0e25\u0e2d\u0e07\u0e1a\u0e32\u0e07\u0e1b\u0e30\u0e01\u0e2d\u0e01"
    ],
    "wof:lang_x_official":[
        "tha"
    ],
    "wof:lang_x_spoken":[
        "tha"
    ],
    "wof:name":"Ban Khlong Bang Pa Kok",
    "wof:placetype":"locality"
},
  "geometry": {"coordinates":[100.49414,13.66522],"type":"Point"}
}