{
  "type": "Feature",
  "properties": {
    "gn:admin1_code":"68.0",
    "gn:asciiname":"Ban Hu Ton",
    "gn:country_code":"TH",
    "gn:dem":57,
    "gn:feature_class":"P",
    "gn:feature_code":"PPL",
    "gn:name":"Ban Hu Ton",
    "gn:population":0,
    "gn:timezone":"Asia/Bangkok",
    "iso:country":"TH",
    "name:tha_x_preferred":[
        "\u0e1a\u0e49\u0e32\u0e19\u0e2b\u0e39\u0e42\u0e15\u0e19"
    ],
    "wof:name":"Ban Hu Ton",
    "wof:placetype":"locality"
},
  "geometry": {"coordinates":[100.55928,6.82808],"type":"Point"}
}