{
  "type": "Feature",
  "properties": {
    "gn:admin1_code":"27",
    "gn:asciiname":"Ban Don Tat Ruea",
    "gn:country_code":"TH",
    "gn:dem":151,
    "gn:feature_class":"P",
    "gn:feature_code":"PPL",
    "gn:name":"Ban Don Tat Ruea",
    "gn:population":0,
    "gn:timezone":"Asia/Bangkok",
    "iso:country":"TH",
    "name:tha_x_preferred":[
        "\u0e1a\u0e49\u0e32\u0e19\u0e14\u0e2d\u0e19\u0e15\u0e31\u0e14\u0e40\u0e23\u0e37\u0e2d"
    ],
    "wof:name":"Ban Don Tat Ruea",
    "wof:placetype":"locality"
},
  "geometry": {"coordinates":[102.53161,15.43267],"type":"Point"}
}