{
  "type": "Feature",
  "properties": {
    "gn:admin1_code":"39.0",
    "gn:asciiname":"Ban Thai Dong",
    "gn:country_code":"TH",
    "gn:dem":5,
    "gn:feature_class":"P",
    "gn:feature_code":"PPL",
    "gn:name":"Ban Thai Dong",
    "gn:population":0,
    "gn:timezone":"Asia/Bangkok",
    "iso:country":"TH",
    "name:tha_x_preferred":[
        "Ban Thai Dong"
    ],
    "name:tha_x_variant":[
        "\u0e1a\u0e49\u0e32\u0e19\u0e17\u0e49\u0e32\u0e22\u0e14\u0e07"
    ],
    "wof:name":"Ban Thai Dong",
    "wof:placetype":"locality"
},
  "geometry": {"coordinates":[100.51639,14.10169],"type":"Point"}
}