{
  "type": "Feature",
  "properties": {
    "gn:admin1_code":"18.0",
    "gn:asciiname":"Ban Chom Charoen",
    "gn:country_code":"TH",
    "gn:dem":346,
    "gn:feature_class":"P",
    "gn:feature_code":"PPL",
    "gn:name":"Ban Chom Charoen",
    "gn:population":0,
    "gn:timezone":"Asia/Bangkok",
    "iso:country":"TH",
    "name:tha_x_preferred":[
        "\u0e1a\u0e49\u0e32\u0e19\u0e0a\u0e21\u0e40\u0e08\u0e23\u0e34\u0e0d"
    ],
    "wof:name":"Ban Chom Charoen",
    "wof:placetype":"locality"
},
  "geometry": {"coordinates":[101.90743999999999,17.71878],"type":"Point"}
}