{
  "type": "Feature",
  "properties": {
    "gn:admin1_code":"26.0",
    "gn:asciiname":"Ban Mueang Noi Nuea",
    "gn:country_code":"TH",
    "gn:dem":188,
    "gn:feature_class":"P",
    "gn:feature_code":"PPL",
    "gn:name":"Ban Mueang Noi Nuea",
    "gn:population":0,
    "gn:timezone":"Asia/Bangkok",
    "iso:country":"TH",
    "name:tha_x_preferred":[
        "\u0e1a\u0e49\u0e32\u0e19\u0e40\u0e21\u0e37\u0e2d\u0e07\u0e19\u0e49\u0e2d\u0e22\u0e40\u0e2b\u0e19\u0e37\u0e2d"
    ],
    "wof:name":"Ban Mueang Noi Nuea",
    "wof:placetype":"locality"
},
  "geometry": {"coordinates":[102.02394,15.83278],"type":"Point"}
}