{
  "type": "Feature",
  "properties": {
    "iso:country":"TH",
    "name:ast_x_preferred":[
        "Bo Yang"
    ],
    "name:azb_x_preferred":[
        "\u0628\u0648 \u06cc\u0627\u0646\u0642"
    ],
    "name:cat_x_preferred":[
        "Bo Yang"
    ],
    "name:cym_x_preferred":[
        "Bo Yang"
    ],
    "name:deu_x_preferred":[
        "Bo Yang"
    ],
    "name:eng_x_preferred":[
        "Bo Yang"
    ],
    "name:fra_x_preferred":[
        "Bo Yang"
    ],
    "name:ita_x_preferred":[
        "Bo Yang"
    ],
    "name:jpn_x_preferred":[
        "\u67cf\u694a"
    ],
    "name:kor_x_preferred":[
        "\ubcf4\uc591"
    ],
    "name:nld_x_preferred":[
        "Bo Yang"
    ],
    "name:pol_x_preferred":[
        "Bo Yang"
    ],
    "name:por_x_preferred":[
        "Bo Yang"
    ],
    "name:rus_x_preferred":[
        "\u0411\u043e \u042f\u043d"
    ],
    "name:spa_x_preferred":[
        "Bo Yang"
    ],
    "name:vie_x_preferred":[
        "B\u00e1 D\u01b0\u01a1ng"
    ],
    "name:yue_x_preferred":[
        "\u67cf\u694a"
    ],
    "name:zho_x_preferred":[
        "\u67cf\u6768"
    ],
    "qs:name":"Bo Yang",
    "qs:name_adm0":"Thailand",
    "qs:name_adm1":"Songkhla",
    "qs:photos":194,
    "qs:photos_1k":39,
    "qs:photos_9k":1,
    "qs:photos_9r":4,
    "qs:photos_all":194,
    "qs:photos_sr":4,
    "qs:placetype":"Town",
    "qs:pop_sr":"0",
    "wd:wordcount":3069,
    "wof:name":"Bo Yang",
    "wof:placetype":"locality"
},
  "geometry": {"coordinates":[100.596144,7.20428],"type":"Point"}
}