{
  "type": "Feature",
  "properties": {
    "iso:country":"TH",
    "qs:name":"Bo Yang",
    "qs:name_adm0":"Thailand",
    "qs:name_adm1":"Songkhla",
    "qs:photos":194,
    "qs:photos_1k":39,
    "qs:photos_9k":1,
    "qs:photos_9r":4,
    "qs:photos_all":194,
    "qs:photos_sr":4,
    "qs:placetype":"Town",
    "qs:pop_sr":"0",
    "wd:wordcount":3069,
    "wof:name":"Bo Yang",
    "wof:placetype":"locality"
},
  "geometry": {"coordinates":[100.596144,7.20428],"type":"Point"}
}