{
  "type": "Feature",
  "properties": {
    "gn:admin1_code":"1.0",
    "gn:asciiname":"Ban Mae Na Toeng Nai",
    "gn:country_code":"TH",
    "gn:dem":558,
    "gn:feature_class":"P",
    "gn:feature_code":"PPL",
    "gn:name":"Ban Mae Na Toeng Nai",
    "gn:population":0,
    "gn:timezone":"Asia/Bangkok",
    "iso:country":"TH",
    "name:tha_x_preferred":[
        "\u0e1a\u0e49\u0e32\u0e19\u0e41\u0e21\u0e48\u0e19\u0e32\u0e40\u0e15\u0e34\u0e07\u0e43\u0e19"
    ],
    "name:und_x_variant":[
        "Ban Na Toeng Nai"
    ],
    "wof:name":"Ban Mae Na Toeng Nai",
    "wof:placetype":"locality"
},
  "geometry": {"coordinates":[98.42206,19.39589],"type":"Point"}
}