{
  "type": "Feature",
  "properties": {
    "gn:admin1_code":"69.0",
    "gn:asciiname":"Ban Rusamilae",
    "gn:country_code":"TH",
    "gn:dem":4,
    "gn:feature_class":"P",
    "gn:feature_code":"PPL",
    "gn:name":"Ban Rusamilae",
    "gn:population":0,
    "gn:timezone":"Asia/Bangkok",
    "iso:country":"TH",
    "name:tha_x_preferred":[
        "\u0e1a\u0e49\u0e32\u0e19\u0e23\u0e39\u0e2a\u0e30\u0e21\u0e34\u0e41\u0e25"
    ],
    "name:und_x_variant":[
        "Kampong Ru La Mi Lae",
        "Ban Rusamila",
        "Kampong Rusamileh",
        "Kampong Rusamilae",
        "Ban Rusamilae"
    ],
    "wof:name":"Ban Rusamilae",
    "wof:placetype":"locality"
},
  "geometry": {"coordinates":[101.22608,6.87045],"type":"Point"}
}