{
  "type": "Feature",
  "properties": {
    "gn:admin1_code":"56.0",
    "gn:asciiname":"Ban Bang In",
    "gn:country_code":"TH",
    "gn:dem":2,
    "gn:feature_class":"P",
    "gn:feature_code":"PPL",
    "gn:name":"Ban Bang In",
    "gn:population":0,
    "gn:timezone":"Asia/Bangkok",
    "iso:country":"TH",
    "name:tha_x_preferred":[
        "\u0e1a\u0e49\u0e32\u0e19\u0e1a\u0e32\u0e07\u0e2d\u0e34\u0e19\u0e17\u0e23\u0e4c"
    ],
    "wof:name":"Ban Bang In",
    "wof:placetype":"locality"
},
  "geometry": {"coordinates":[100.04268999999999,13.16667],"type":"Point"}
}