{
  "type": "Feature",
  "properties": {
    "gn:admin1_code":"65.0",
    "gn:asciiname":"Ban Tok Khao",
    "gn:country_code":"TH",
    "gn:dem":40,
    "gn:feature_class":"P",
    "gn:feature_code":"PPL",
    "gn:name":"Ban Tok Khao",
    "gn:population":0,
    "gn:timezone":"Asia/Bangkok",
    "iso:country":"TH",
    "name:tha_x_preferred":[
        "\u0e1a\u0e49\u0e32\u0e19\u0e15\u0e01\u0e40\u0e02\u0e32"
    ],
    "wof:name":"Ban Tok Khao",
    "wof:placetype":"locality"
},
  "geometry": {"coordinates":[99.66847,7.50789],"type":"Point"}
}