{
  "type": "Feature",
  "properties": {
    "gn:admin1_code":"3.0",
    "gn:asciiname":"Ban Si Don Chai",
    "gn:country_code":"TH",
    "gn:dem":356,
    "gn:feature_class":"P",
    "gn:feature_code":"PPL",
    "gn:name":"Ban Si Don Chai",
    "gn:population":0,
    "gn:timezone":"Asia/Bangkok",
    "iso:country":"TH",
    "name:tha_x_preferred":[
        "\u0e1a\u0e49\u0e32\u0e19\u0e28\u0e23\u0e35\u0e14\u0e2d\u0e19\u0e0a\u0e31\u0e22"
    ],
    "wof:name":"Ban Si Don Chai",
    "wof:placetype":"locality"
},
  "geometry": {"coordinates":[100.41603000000001,20.14358],"type":"Point"}
}