{
  "type": "Feature",
  "properties": {
    "gn:admin1_code":"53.0",
    "gn:asciiname":"Ban Thung Luk Nok",
    "gn:country_code":"TH",
    "gn:dem":12,
    "gn:feature_class":"P",
    "gn:feature_code":"PPL",
    "gn:name":"Ban Thung Luk Nok",
    "gn:population":0,
    "gn:timezone":"Asia/Bangkok",
    "iso:country":"TH",
    "name:tha_x_preferred":[
        "Ban Thung Luk Nok"
    ],
    "name:tha_x_variant":[
        "\u0e1a\u0e49\u0e32\u0e19\u0e17\u0e38\u0e48\u0e07\u0e25\u0e39\u0e01\u0e19\u0e01"
    ],
    "wof:name":"Ban Thung Luk Nok",
    "wof:placetype":"locality"
},
  "geometry": {"coordinates":[99.88539,14.03792],"type":"Point"}
}