{
  "type": "Feature",
  "properties": {
    "gn:admin1_code":"64.0",
    "gn:asciiname":"Ban Na Khi Pet",
    "gn:country_code":"TH",
    "gn:dem":52,
    "gn:feature_class":"P",
    "gn:feature_code":"PPL",
    "gn:name":"Ban Na Khi Pet",
    "gn:population":0,
    "gn:timezone":"Asia/Bangkok",
    "iso:country":"TH",
    "name:tha_x_preferred":[
        "\u0e1a\u0e49\u0e32\u0e19\u0e19\u0e32\u0e02\u0e35\u0e49\u0e40\u0e1b\u0e47\u0e14"
    ],
    "wof:name":"Ban Na Khi Pet",
    "wof:placetype":"locality"
},
  "geometry": {"coordinates":[99.64906000000001,8.15056],"type":"Point"}
}