{
  "type": "Feature",
  "properties": {
    "gn:admin1_code":"70.0",
    "gn:asciiname":"Kampong Kro",
    "gn:cc2":"TH",
    "gn:country_code":"TH",
    "gn:dem":56,
    "gn:feature_class":"P",
    "gn:feature_code":"PPL",
    "gn:name":"Kampong Kro",
    "gn:population":0,
    "gn:timezone":"Asia/Bangkok",
    "iso:country":"TH",
    "name:und_x_variant":[
        "Kampong Krau",
        "Kampong Krut",
        "Kampong Kro"
    ],
    "wof:name":"Kampong Kro",
    "wof:placetype":"locality"
},
  "geometry": {"coordinates":[101.09999999999999,6.48333],"type":"Point"}
}