{
  "type": "Feature",
  "properties": {
    "gn:admin1_code":"7.0",
    "gn:asciiname":"Ban Pang Mai Phatthana",
    "gn:country_code":"TH",
    "gn:dem":158,
    "gn:feature_class":"P",
    "gn:feature_code":"PPL",
    "gn:name":"Ban Pang Mai Phatthana",
    "gn:population":0,
    "gn:timezone":"Asia/Bangkok",
    "iso:country":"TH",
    "name:tha_x_preferred":[
        "\u0e1a\u0e49\u0e32\u0e19\u0e1b\u0e32\u0e07\u0e44\u0e21\u0e49\u0e1e\u0e31\u0e12\u0e19\u0e32"
    ],
    "wof:name":"Ban Pang Mai Phatthana",
    "wof:placetype":"locality"
},
  "geometry": {"coordinates":[99.48972000000001,17.80428],"type":"Point"}
}