{
  "type": "Feature",
  "properties": {
    "gn:admin1_code":"10.0",
    "gn:asciiname":"Ban Nam Khom",
    "gn:country_code":"TH",
    "gn:dem":119,
    "gn:feature_class":"P",
    "gn:feature_code":"PPL",
    "gn:name":"Ban Nam Khom",
    "gn:population":0,
    "gn:timezone":"Asia/Bangkok",
    "iso:country":"TH",
    "name:tha_x_preferred":[
        "Ban Nam Khom"
    ],
    "name:tha_x_variant":[
        "\u0e1a\u0e49\u0e32\u0e19\u0e19\u0e49\u0e33\u0e04\u0e2d\u0e21"
    ],
    "wof:name":"Ban Nam Khom",
    "wof:placetype":"locality"
},
  "geometry": {"coordinates":[100.37278000000001,17.79917],"type":"Point"}
}