{
  "type": "Feature",
  "properties": {
    "gn:admin1_code":"34",
    "gn:asciiname":"Ban Dong Champa",
    "gn:country_code":"TH",
    "gn:dem":29,
    "gn:feature_class":"P",
    "gn:feature_code":"PPL",
    "gn:name":"Ban Dong Champa",
    "gn:population":0,
    "gn:timezone":"Asia/Bangkok",
    "iso:country":"TH",
    "name:tha_x_preferred":[
        "\u0e1a\u0e49\u0e32\u0e19\u0e14\u0e07\u0e08\u0e33\u0e1b\u0e32"
    ],
    "wof:name":"Ban Dong Champa",
    "wof:placetype":"locality"
},
  "geometry": {"coordinates":[100.70855,14.75733],"type":"Point"}
}