{
  "type": "Feature",
  "properties": {
    "gn:admin1_code":"22",
    "gn:asciiname":"Ban Daeng Yai",
    "gn:country_code":"TH",
    "gn:dem":167,
    "gn:feature_class":"P",
    "gn:feature_code":"PPL",
    "gn:name":"Ban Daeng Yai",
    "gn:population":0,
    "gn:timezone":"Asia/Bangkok",
    "iso:country":"TH",
    "name:tha_x_preferred":[
        "\u0e1a\u0e49\u0e32\u0e19\u0e41\u0e14\u0e07\u0e43\u0e2b\u0e0d\u0e48"
    ],
    "wof:name":"Ban Daeng Yai",
    "wof:placetype":"locality"
},
  "geometry": {"coordinates":[102.72853000000001,16.47553],"type":"Point"}
}