{
  "type": "Feature",
  "properties": {
    "gn:admin1_code":"20.0",
    "gn:asciiname":"Ban Noi Charoen Si",
    "gn:country_code":"TH",
    "gn:dem":172,
    "gn:feature_class":"P",
    "gn:feature_code":"PPL",
    "gn:name":"Ban Noi Charoen Si",
    "gn:population":0,
    "gn:timezone":"Asia/Bangkok",
    "iso:country":"TH",
    "name:tha_x_preferred":[
        "\u0e1a\u0e49\u0e32\u0e19\u0e19\u0e49\u0e2d\u0e22\u0e40\u0e08\u0e23\u0e34\u0e0d\u0e28\u0e23\u0e35"
    ],
    "wof:name":"Ban Noi Charoen Si",
    "wof:placetype":"locality"
},
  "geometry": {"coordinates":[103.55586,17.83406],"type":"Point"}
}