{
  "type": "Feature",
  "properties": {
    "gn:admin1_code":"48.0",
    "gn:asciiname":"Ban Takhian Khu",
    "gn:country_code":"TH",
    "gn:dem":25,
    "gn:feature_class":"P",
    "gn:feature_code":"PPL",
    "gn:name":"Ban Takhian Khu",
    "gn:population":0,
    "gn:timezone":"Asia/Bangkok",
    "iso:country":"TH",
    "name:tha_x_preferred":[
        "\u0e1a\u0e49\u0e32\u0e19\u0e15\u0e30\u0e40\u0e04\u0e35\u0e22\u0e19\u0e04\u0e39\u0e48"
    ],
    "wof:name":"Ban Takhian Khu",
    "wof:placetype":"locality"
},
  "geometry": {"coordinates":[102.0765,12.64361],"type":"Point"}
}