{
  "type": "Feature",
  "properties": {
    "gn:admin1_code":"69.0",
    "gn:asciiname":"Ban Pa Se Ti Ngi",
    "gn:country_code":"TH",
    "gn:dem":16,
    "gn:feature_class":"P",
    "gn:feature_code":"PPL",
    "gn:name":"Ban Pa Se Ti Ngi",
    "gn:population":0,
    "gn:timezone":"Asia/Bangkok",
    "iso:country":"TH",
    "name:tha_x_preferred":[
        "\u0e1a\u0e49\u0e32\u0e19\u0e1b\u0e32\u0e40\u0e0b\u0e15\u0e35\u0e07\u0e35"
    ],
    "wof:name":"Ban Pa Se Ti Ngi",
    "wof:placetype":"locality"
},
  "geometry": {"coordinates":[101.56842,6.61931],"type":"Point"}
}