{
  "type": "Feature",
  "properties": {
    "gn:admin1_code":"50.0",
    "gn:asciiname":"Ban Dan Mae Chalaep",
    "gn:cc2":"TH",
    "gn:country_code":"TH",
    "gn:dem":172,
    "gn:feature_class":"P",
    "gn:feature_code":"PPL",
    "gn:name":"Ban Dan Mae Chalaep",
    "gn:population":0,
    "gn:timezone":"Asia/Bangkok",
    "iso:country":"TH",
    "name:und_x_variant":[
        "Ban Mae Chalaep",
        "Ban Meh Chaled",
        "Ban Meh Chaleb",
        "Ban Dan Mae Chalaep"
    ],
    "wof:name":"Ban Dan Mae Chalaep",
    "wof:placetype":"locality"
},
  "geometry": {"coordinates":[99.03333000000001,14.68333],"type":"Point"}
}