{
  "type": "Feature",
  "properties": {
    "gn:admin1_code":"58.0",
    "gn:asciiname":"Ban Khlong Wang Chang",
    "gn:country_code":"TH",
    "gn:dem":15,
    "gn:feature_class":"P",
    "gn:feature_code":"PPL",
    "gn:name":"Ban Khlong Wang Chang",
    "gn:population":0,
    "gn:timezone":"Asia/Bangkok",
    "iso:country":"TH",
    "name:tha_x_preferred":[
        "\u0e1a\u0e49\u0e32\u0e19\u0e04\u0e25\u0e2d\u0e07\u0e27\u0e31\u0e07\u0e0a\u0e49\u0e32\u0e07"
    ],
    "name:und_x_variant":[
        "Ban Wang Chang",
        "Ban Khlong Wang Chang"
    ],
    "wof:name":"Ban Khlong Wang Chang",
    "wof:placetype":"locality"
},
  "geometry": {"coordinates":[99.33506,10.74939],"type":"Point"}
}