{
  "type": "Feature",
  "properties": {
    "gn:admin1_code":"9.0",
    "gn:asciiname":"Ban Mae Rak Klang",
    "gn:country_code":"TH",
    "gn:dem":92,
    "gn:feature_class":"P",
    "gn:feature_code":"PPL",
    "gn:name":"Ban Mae Rak Klang",
    "gn:population":0,
    "gn:timezone":"Asia/Bangkok",
    "iso:country":"TH",
    "name:tha_x_preferred":[
        "\u0e1a\u0e49\u0e32\u0e19\u0e41\u0e21\u0e48\u0e23\u0e32\u0e01\u0e01\u0e25\u0e32\u0e07"
    ],
    "wof:lang_x_official":[
        "tha"
    ],
    "wof:lang_x_spoken":[
        "tha"
    ],
    "wof:name":"Ban Mae Rak Klang",
    "wof:placetype":"locality"
},
  "geometry": {"coordinates":[99.81519,17.58539],"type":"Point"}
}