{
  "type": "Feature",
  "properties": {
    "gn:admin1_code":"56.0",
    "gn:asciiname":"Ban Bang Khun Sai",
    "gn:country_code":"TH",
    "gn:dem":7,
    "gn:feature_class":"P",
    "gn:feature_code":"PPL",
    "gn:name":"Ban Bang Khun Sai",
    "gn:population":0,
    "gn:timezone":"Asia/Bangkok",
    "iso:country":"TH",
    "name:tha_x_preferred":[
        "\u0e1a\u0e49\u0e32\u0e19\u0e1a\u0e32\u0e07\u0e02\u0e38\u0e19\u0e44\u0e17\u0e23"
    ],
    "name:und_x_variant":[
        "Ban Bang Khun Zai",
        "Bang Ban Khun Sai",
        "Ban Bang Khun Sai"
    ],
    "wof:name":"Ban Bang Khun Sai",
    "wof:placetype":"locality"
},
  "geometry": {"coordinates":[100.01783,13.18211],"type":"Point"}
}