{
  "type": "Feature",
  "properties": {
    "gn:admin1_code":"52.0",
    "gn:asciiname":"Ban Prong Keng",
    "gn:country_code":"TH",
    "gn:dem":72,
    "gn:feature_class":"P",
    "gn:feature_code":"PPL",
    "gn:name":"Ban Prong Keng",
    "gn:population":0,
    "gn:timezone":"Asia/Bangkok",
    "iso:country":"TH",
    "name:tha_x_preferred":[
        "\u0e1a\u0e49\u0e32\u0e19\u0e42\u0e1b\u0e23\u0e48\u0e07\u0e40\u0e01\u0e49\u0e07"
    ],
    "wof:name":"Ban Prong Keng",
    "wof:placetype":"locality"
},
  "geometry": {"coordinates":[99.64136000000001,13.44431],"type":"Point"}
}