{
  "type": "Feature",
  "properties": {
    "gn:admin1_code":"75.0",
    "gn:asciiname":"Ban Sao Thong Yai",
    "gn:country_code":"TH",
    "gn:dem":124,
    "gn:feature_class":"P",
    "gn:feature_code":"PPL",
    "gn:name":"Ban Sao Thong Yai",
    "gn:population":0,
    "gn:timezone":"Asia/Bangkok",
    "iso:country":"TH",
    "name:tha_x_preferred":[
        "\u0e1a\u0e49\u0e32\u0e19\u0e40\u0e2a\u0e32\u0e18\u0e07\u0e43\u0e2b\u0e0d\u0e48"
    ],
    "wof:name":"Ban Sao Thong Yai",
    "wof:placetype":"locality"
},
  "geometry": {"coordinates":[105.01868,15.53989],"type":"Point"}
}