{
  "type": "Feature",
  "properties": {
    "gn:admin1_code":"44.0",
    "gn:asciiname":"Ban Wang Pla Nak",
    "gn:country_code":"TH",
    "gn:dem":4,
    "gn:feature_class":"P",
    "gn:feature_code":"PPL",
    "gn:name":"Ban Wang Pla Nak",
    "gn:population":0,
    "gn:timezone":"Asia/Bangkok",
    "iso:country":"TH",
    "name:tha_x_preferred":[
        "\u0e1a\u0e49\u0e32\u0e19\u0e27\u0e31\u0e07\u0e1b\u0e25\u0e32\u0e19\u0e31\u0e01"
    ],
    "name:und_x_variant":[
        "Ban Lam Pla Nak",
        "Ban Wang Pla Nak"
    ],
    "wof:name":"Ban Wang Pla Nak",
    "wof:placetype":"locality"
},
  "geometry": {"coordinates":[100.98228,13.73183],"type":"Point"}
}