{
  "type": "Feature",
  "properties": {
    "gn:admin1_code":"14.0",
    "gn:asciiname":"Ban Wang Chorakhe",
    "gn:country_code":"TH",
    "gn:dem":112,
    "gn:feature_class":"P",
    "gn:feature_code":"PPL",
    "gn:name":"Ban Wang Chorakhe",
    "gn:population":0,
    "gn:timezone":"Asia/Bangkok",
    "iso:country":"TH",
    "name:tha_x_preferred":[
        "\u0e1a\u0e49\u0e32\u0e19\u0e27\u0e31\u0e07\u0e08\u0e23\u0e30\u0e40\u0e02\u0e49"
    ],
    "wof:name":"Ban Wang Chorakhe",
    "wof:placetype":"locality"
},
  "geometry": {"coordinates":[100.82547,15.83244],"type":"Point"}
}