{
  "type": "Feature",
  "properties": {
    "gn:admin1_code":"31.0",
    "gn:asciiname":"Ban Ba Le Hi Le",
    "gn:country_code":"TH",
    "gn:dem":49,
    "gn:feature_class":"P",
    "gn:feature_code":"PPL",
    "gn:name":"Ban Ba Le Hi Le",
    "gn:population":0,
    "gn:timezone":"Asia/Bangkok",
    "iso:country":"TH",
    "name:tha_x_preferred":[
        "\u0e1a\u0e49\u0e32\u0e19\u0e1a\u0e32\u0e40\u0e25\u0e30\u0e2e\u0e35\u0e40\u0e25"
    ],
    "wof:lang_x_official":[
        "tha"
    ],
    "wof:lang_x_spoken":[
        "tha"
    ],
    "wof:name":"Ban Ba Le Hi Le",
    "wof:placetype":"locality"
},
  "geometry": {"coordinates":[101.56022,6.43139],"type":"Point"}
}