{
  "type": "Feature",
  "properties": {
    "gn:admin1_code":"2.0",
    "gn:asciiname":"Ban Han Kaeo",
    "gn:country_code":"TH",
    "gn:dem":300,
    "gn:feature_class":"P",
    "gn:feature_code":"PPL",
    "gn:name":"Ban Han Kaeo",
    "gn:population":0,
    "gn:timezone":"Asia/Bangkok",
    "iso:country":"TH",
    "name:tha_x_preferred":[
        "\u0e1a\u0e49\u0e32\u0e19\u0e2b\u0e32\u0e23\u0e41\u0e01\u0e49\u0e27"
    ],
    "name:und_x_variant":[
        "Ban Kaeo",
        "B\u0101n Geo",
        "Ban Han Kaeo"
    ],
    "wof:name":"Ban Han Kaeo",
    "wof:placetype":"locality"
},
  "geometry": {"coordinates":[98.92558,18.64906],"type":"Point"}
}