{
  "type": "Feature",
  "properties": {
    "gn:admin1_code":"66.0",
    "gn:asciiname":"Ban Nong Nok Kin Nam",
    "gn:country_code":"TH",
    "gn:dem":23,
    "gn:feature_class":"P",
    "gn:feature_code":"PPL",
    "gn:name":"Ban Nong Nok Kin Nam",
    "gn:population":0,
    "gn:timezone":"Asia/Bangkok",
    "iso:country":"TH",
    "name:tha_x_preferred":[
        "\u0e1a\u0e49\u0e32\u0e19\u0e2b\u0e19\u0e2d\u0e07\u0e19\u0e01\u0e01\u0e34\u0e19\u0e19\u0e49\u0e33"
    ],
    "wof:name":"Ban Nong Nok Kin Nam",
    "wof:placetype":"locality"
},
  "geometry": {"coordinates":[100.10825,7.42333],"type":"Point"}
}