{
  "type": "Feature",
  "properties": {
    "gn:admin1_code":"2.0",
    "gn:asciiname":"Ban Na Ma Uen",
    "gn:country_code":"TH",
    "gn:dem":1119,
    "gn:feature_class":"P",
    "gn:feature_code":"PPL",
    "gn:name":"Ban Na Ma Uen",
    "gn:population":0,
    "gn:timezone":"Asia/Bangkok",
    "iso:country":"TH",
    "name:tha_x_preferred":[
        "\u0e1a\u0e49\u0e32\u0e19\u0e19\u0e32\u0e21\u0e30\u0e2d\u0e37\u0e49\u0e19"
    ],
    "wof:name":"Ban Na Ma Uen",
    "wof:placetype":"locality"
},
  "geometry": {"coordinates":[99.22286,20.08678],"type":"Point"}
}