{
  "type": "Feature",
  "properties": {
    "gn:admin1_code":"61.0",
    "gn:asciiname":"Ban Ao Krapho",
    "gn:country_code":"TH",
    "gn:dem":15,
    "gn:feature_class":"P",
    "gn:feature_code":"PPL",
    "gn:name":"Ban Ao Krapho",
    "gn:population":0,
    "gn:timezone":"Asia/Bangkok",
    "iso:country":"TH",
    "name:tha_x_preferred":[
        "\u0e1a\u0e49\u0e32\u0e19\u0e2d\u0e48\u0e32\u0e27\u0e01\u0e23\u0e30\u0e1e\u0e49\u0e2d"
    ],
    "wof:name":"Ban Ao Krapho",
    "wof:placetype":"locality"
},
  "geometry": {"coordinates":[98.57993999999999,7.91433],"type":"Point"}
}