{
  "type": "Feature",
  "properties": {
    "gn:admin1_code":"30.0",
    "gn:asciiname":"Ban Chia",
    "gn:country_code":"TH",
    "gn:dem":128,
    "gn:feature_class":"P",
    "gn:feature_code":"PPL",
    "gn:name":"Ban Chia",
    "gn:population":0,
    "gn:timezone":"Asia/Bangkok",
    "iso:country":"TH",
    "name:tha_x_preferred":[
        "\u0e1a\u0e49\u0e32\u0e19\u0e40\u0e08\u0e35\u0e48\u0e22"
    ],
    "wof:name":"Ban Chia",
    "wof:placetype":"locality"
},
  "geometry": {"coordinates":[104.62281,15.22061],"type":"Point"}
}