{
  "type": "Feature",
  "properties": {
    "gn:admin1_code":"37",
    "gn:asciiname":"Ban Sap Heo",
    "gn:country_code":"TH",
    "gn:dem":349,
    "gn:feature_class":"P",
    "gn:feature_code":"PPL",
    "gn:name":"Ban Sap Heo",
    "gn:population":0,
    "gn:timezone":"Asia/Bangkok",
    "iso:country":"TH",
    "name:tha_x_preferred":[
        "\u0e1a\u0e49\u0e32\u0e19\u0e0b\u0e31\u0e1a\u0e40\u0e2b\u0e27"
    ],
    "wof:name":"Ban Sap Heo",
    "wof:placetype":"locality"
},
  "geometry": {"coordinates":[101.27306,14.84567],"type":"Point"}
}