{
  "type": "Feature",
  "properties": {
    "gn:admin1_code":"34.0",
    "gn:asciiname":"Ban Pong La Sat",
    "gn:country_code":"TH",
    "gn:dem":241,
    "gn:feature_class":"P",
    "gn:feature_code":"PPL",
    "gn:name":"Ban Pong La Sat",
    "gn:population":0,
    "gn:timezone":"Asia/Bangkok",
    "iso:country":"TH",
    "wof:name":"Ban Pong La Sat",
    "wof:placetype":"locality"
},
  "geometry": {"coordinates":[101.30777999999999,15.10361],"type":"Point"}
}