{
  "type": "Feature",
  "properties": {
    "gn:admin1_code":"11.0",
    "gn:asciiname":"Ban Kaeo Chai Mongkhon",
    "gn:country_code":"TH",
    "gn:dem":58,
    "gn:feature_class":"P",
    "gn:feature_code":"PPL",
    "gn:name":"Ban Kaeo Chai Mongkhon",
    "gn:population":0,
    "gn:timezone":"Asia/Bangkok",
    "iso:country":"TH",
    "name:tha_x_preferred":[
        "\u0e1a\u0e49\u0e32\u0e19\u0e41\u0e01\u0e49\u0e27\u0e0a\u0e31\u0e22\u0e21\u0e07\u0e04\u0e25"
    ],
    "wof:lang_x_official":[
        "tha"
    ],
    "wof:lang_x_spoken":[
        "tha"
    ],
    "wof:name":"Ban Kaeo Chai Mongkhon",
    "wof:placetype":"locality"
},
  "geometry": {"coordinates":[99.92092,16.46956],"type":"Point"}
}