{
  "type": "Feature",
  "properties": {
    "gn:admin1_code":"26.0",
    "gn:asciiname":"Ban Nang Daet Khok",
    "gn:country_code":"TH",
    "gn:dem":255,
    "gn:feature_class":"P",
    "gn:feature_code":"PPL",
    "gn:name":"Ban Nang Daet Khok",
    "gn:population":0,
    "gn:timezone":"Asia/Bangkok",
    "iso:country":"TH",
    "name:tha_x_preferred":[
        "\u0e1a\u0e49\u0e32\u0e19\u0e19\u0e32\u0e07\u0e41\u0e14\u0e14\u0e42\u0e04\u0e01"
    ],
    "wof:name":"Ban Nang Daet Khok",
    "wof:placetype":"locality"
},
  "geometry": {"coordinates":[101.57986,16.14589],"type":"Point"}
}