{
  "type": "Feature",
  "properties": {
    "gn:admin1_code":"31.0",
    "gn:asciiname":"Ban Kampong Bu Ke",
    "gn:country_code":"TH",
    "gn:dem":50,
    "gn:feature_class":"P",
    "gn:feature_code":"PPL",
    "gn:name":"Ban Kampong Bu Ke",
    "gn:population":0,
    "gn:timezone":"Asia/Bangkok",
    "iso:country":"TH",
    "name:tha_x_preferred":[
        "\u0e1a\u0e49\u0e32\u0e19\u0e01\u0e33\u0e1b\u0e07\u0e1a\u0e39\u0e40\u0e01\u0e4a\u0e30"
    ],
    "wof:name":"Ban Kampong Bu Ke",
    "wof:placetype":"locality"
},
  "geometry": {"coordinates":[101.50964,6.24817],"type":"Point"}
}