{
  "type": "Feature",
  "properties": {
    "gn:admin1_code":"74",
    "gn:asciiname":"Ban Khlong Ho Thong",
    "gn:country_code":"TH",
    "gn:dem":6,
    "gn:feature_class":"P",
    "gn:feature_code":"PPL",
    "gn:name":"Ban Khlong Ho Thong",
    "gn:population":0,
    "gn:timezone":"Asia/Bangkok",
    "iso:country":"TH",
    "name:tha_x_preferred":[
        "\u0e1a\u0e49\u0e32\u0e19\u0e04\u0e25\u0e2d\u0e07\u0e2b\u0e2d\u0e17\u0e2d\u0e07"
    ],
    "wof:name":"Ban Khlong Ho Thong",
    "wof:placetype":"locality"
},
  "geometry": {"coordinates":[101.23905999999999,13.95419],"type":"Point"}
}