{
  "type": "Feature",
  "properties": {
    "gn:admin1_code":"7.0",
    "gn:asciiname":"Ban Mueang Mo",
    "gn:country_code":"TH",
    "gn:dem":177,
    "gn:feature_class":"P",
    "gn:feature_code":"PPL",
    "gn:name":"Ban Mueang Mo",
    "gn:population":0,
    "gn:timezone":"Asia/Bangkok",
    "iso:country":"TH",
    "name:tha_x_preferred":[
        "\u0e1a\u0e49\u0e32\u0e19\u0e40\u0e2b\u0e21\u0e37\u0e2d\u0e07\u0e2b\u0e21\u0e49\u0e2d"
    ],
    "name:und_x_variant":[
        "Ban Muang Mau",
        "Ban Muang Mo",
        "Ban Mueang Mo"
    ],
    "wof:name":"Ban Mueang Mo",
    "wof:placetype":"locality"
},
  "geometry": {"coordinates":[100.18356,18.14292],"type":"Point"}
}