{
  "type": "Feature",
  "properties": {
    "gn:admin1_code":"30.0",
    "gn:asciiname":"Ban Makham",
    "gn:country_code":"TH",
    "gn:dem":149,
    "gn:feature_class":"P",
    "gn:feature_code":"PPL",
    "gn:name":"Ban Makham",
    "gn:population":0,
    "gn:timezone":"Asia/Bangkok",
    "iso:country":"TH",
    "name:tha_x_preferred":[
        "\u0e1a\u0e49\u0e32\u0e19\u0e21\u0e30\u0e02\u0e32\u0e21"
    ],
    "wof:name":"Ban Makham",
    "wof:placetype":"locality"
},
  "geometry": {"coordinates":[104.38964,14.71397],"type":"Point"}
}