{
  "type": "Feature",
  "properties": {
    "gn:admin1_code":"18.0",
    "gn:asciiname":"Ban Non Kut Chap",
    "gn:country_code":"TH",
    "gn:dem":254,
    "gn:feature_class":"P",
    "gn:feature_code":"PPL",
    "gn:name":"Ban Non Kut Chap",
    "gn:population":0,
    "gn:timezone":"Asia/Bangkok",
    "iso:country":"TH",
    "name:tha_x_preferred":[
        "Ban Non Kut Chap"
    ],
    "name:tha_x_variant":[
        "\u0e1a\u0e49\u0e32\u0e19\u0e42\u0e19\u0e19\u0e01\u0e38\u0e14\u0e08\u0e31\u0e1a"
    ],
    "wof:name":"Ban Non Kut Chap",
    "wof:placetype":"locality"
},
  "geometry": {"coordinates":[101.72499999999999,17.43011],"type":"Point"}
}