{
  "type": "Feature",
  "properties": {
    "gn:admin1_code":"79.0",
    "gn:asciiname":"Ban Soen Noi",
    "gn:country_code":"TH",
    "gn:dem":236,
    "gn:feature_class":"P",
    "gn:feature_code":"PPL",
    "gn:name":"Ban Soen Noi",
    "gn:population":0,
    "gn:timezone":"Asia/Bangkok",
    "iso:country":"TH",
    "name:und_x_variant":[
        "\u0e1a\u0e49\u0e32\u0e19\u0e40\u0e0b\u0e34\u0e19\u0e19\u0e49\u0e2d\u0e22",
        "Ban Soen"
    ],
    "wof:lang_x_official":[
        "tha"
    ],
    "wof:lang_x_spoken":[
        "tha"
    ],
    "wof:name":"Ban Soen Noi",
    "wof:placetype":"locality"
},
  "geometry": {"coordinates":[102.23703,17.50092],"type":"Point"}
}