{
  "type": "Feature",
  "properties": {
    "gn:admin1_code":"28.0",
    "gn:asciiname":"Ban Samrong",
    "gn:country_code":"TH",
    "gn:dem":171,
    "gn:feature_class":"P",
    "gn:feature_code":"PPL",
    "gn:name":"Ban Samrong",
    "gn:population":0,
    "gn:timezone":"Asia/Bangkok",
    "iso:country":"TH",
    "name:tha_x_preferred":[
        "\u0e1a\u0e49\u0e32\u0e19\u0e2a\u0e33\u0e42\u0e23\u0e07"
    ],
    "name:und_x_variant":[
        "Ban Samrong (1)"
    ],
    "wof:name":"Ban Samrong",
    "wof:placetype":"locality"
},
  "geometry": {"coordinates":[103.03433,15.16117],"type":"Point"}
}