{
  "type": "Feature",
  "properties": {
    "gn:admin1_code":"33.0",
    "gn:asciiname":"Ban Cha",
    "gn:country_code":"TH",
    "gn:dem":15,
    "gn:feature_class":"P",
    "gn:feature_code":"PPL",
    "gn:name":"Ban Cha",
    "gn:population":0,
    "gn:timezone":"Asia/Bangkok",
    "iso:country":"TH",
    "name:tha_x_preferred":[
        "\u0e1a\u0e49\u0e32\u0e19\u0e08\u0e48\u0e32"
    ],
    "name:und_x_variant":[
        "Ban Cha (1)"
    ],
    "wof:name":"Ban Cha",
    "wof:placetype":"locality"
},
  "geometry": {"coordinates":[100.28742,14.87139],"type":"Point"}
}