{
  "type": "Feature",
  "properties": {
    "gn:admin1_code":"25.0",
    "gn:asciiname":"Ban Roeng Kae",
    "gn:country_code":"TH",
    "gn:dem":136,
    "gn:feature_class":"P",
    "gn:feature_code":"PPL",
    "gn:name":"Ban Roeng Kae",
    "gn:population":0,
    "gn:timezone":"Asia/Bangkok",
    "iso:country":"TH",
    "name:tha_x_preferred":[
        "\u0e1a\u0e49\u0e32\u0e19\u0e40\u0e23\u0e34\u0e07\u0e41\u0e01"
    ],
    "wof:name":"Ban Roeng Kae",
    "wof:placetype":"locality"
},
  "geometry": {"coordinates":[103.426,15.54475],"type":"Point"}
}