{
  "type": "Feature",
  "properties": {
    "gn:admin1_code":"0.0",
    "gn:asciiname":"Ban Huai Phlu",
    "gn:country_code":"TH",
    "gn:dem":411,
    "gn:feature_class":"P",
    "gn:feature_code":"PPL",
    "gn:name":"Ban Huai Phlu",
    "gn:population":0,
    "gn:timezone":"Asia/Bangkok",
    "iso:country":"TH",
    "wof:name":"Ban Huai Phlu",
    "wof:placetype":"locality"
},
  "geometry": {"coordinates":[99.84999999999999,19.98333],"type":"Point"}
}