{
  "type": "Feature",
  "properties": {
    "gn:admin1_code":"34.0",
    "gn:asciiname":"Ban Bang Yi Nang",
    "gn:country_code":"TH",
    "gn:dem":12,
    "gn:feature_class":"P",
    "gn:feature_code":"PPL",
    "gn:name":"Ban Bang Yi Nang",
    "gn:population":0,
    "gn:timezone":"Asia/Bangkok",
    "iso:country":"TH",
    "name:tha_x_preferred":[
        "\u0e1a\u0e49\u0e32\u0e19\u0e1a\u0e32\u0e07\u0e22\u0e35\u0e48\u0e19\u0e32\u0e07"
    ],
    "name:und_x_variant":[
        "Ban Bang I Nang"
    ],
    "wof:name":"Ban Bang Yi Nang",
    "wof:placetype":"locality"
},
  "geometry": {"coordinates":[100.47808000000001,14.89192],"type":"Point"}
}