{
  "type": "Feature",
  "properties": {
    "gn:admin1_code":"5.0",
    "gn:asciiname":"Moo Ban Palm Springs",
    "gn:country_code":"TH",
    "gn:dem":305,
    "gn:feature_class":"P",
    "gn:feature_code":"PPL",
    "gn:name":"Moo Ban Palm Springs",
    "gn:population":0,
    "gn:timezone":"Asia/Bangkok",
    "iso:country":"TH",
    "wof:name":"Moo Ban Palm Springs",
    "wof:placetype":"locality"
},
  "geometry": {"coordinates":[99.02200999999999,18.76055],"type":"Point"}
}