{
  "type": "Feature",
  "properties": {
    "gn:admin1_code":"29.0",
    "gn:asciiname":"Ban Pha Chuen",
    "gn:country_code":"TH",
    "gn:dem":206,
    "gn:feature_class":"P",
    "gn:feature_code":"PPL",
    "gn:name":"Ban Pha Chuen",
    "gn:population":0,
    "gn:timezone":"Asia/Bangkok",
    "iso:country":"TH",
    "name:tha_x_preferred":[
        "\u0e1a\u0e49\u0e32\u0e19\u0e1e\u0e32\u0e0a\u0e37\u0e48\u0e19"
    ],
    "wof:name":"Ban Pha Chuen",
    "wof:placetype":"locality"
},
  "geometry": {"coordinates":[103.58172,14.48006],"type":"Point"}
}