{
  "type": "Feature",
  "properties": {
    "gn:admin1_code":"55.0",
    "gn:asciiname":"Ban Ruam Charoen",
    "gn:country_code":"TH",
    "gn:dem":4,
    "gn:feature_class":"P",
    "gn:feature_code":"PPL",
    "gn:name":"Ban Ruam Charoen",
    "gn:population":0,
    "gn:timezone":"Asia/Bangkok",
    "iso:country":"TH",
    "name:tha_x_preferred":[
        "\u0e1a\u0e49\u0e32\u0e19\u0e23\u0e27\u0e21\u0e40\u0e08\u0e23\u0e34\u0e0d"
    ],
    "wof:name":"Ban Ruam Charoen",
    "wof:placetype":"locality"
},
  "geometry": {"coordinates":[100.16919,13.57114],"type":"Point"}
}