{
  "type": "Feature",
  "properties": {
    "gn:admin1_code":"28.0",
    "gn:asciiname":"Ban Chan Dum",
    "gn:country_code":"TH",
    "gn:dem":158,
    "gn:feature_class":"P",
    "gn:feature_code":"PPL",
    "gn:name":"Ban Chan Dum",
    "gn:population":0,
    "gn:timezone":"Asia/Bangkok",
    "iso:country":"TH",
    "name:tha_x_preferred":[
        "\u0e1a\u0e49\u0e32\u0e19\u0e08\u0e31\u0e19\u0e14\u0e38\u0e21"
    ],
    "name:und_x_variant":[
        "Ban Chan Dom",
        "Ban Chan Dum"
    ],
    "wof:name":"Ban Chan Dum",
    "wof:placetype":"locality"
},
  "geometry": {"coordinates":[103.12983,14.67556],"type":"Point"}
}