{
  "type": "Feature",
  "properties": {
    "gn:admin1_code":"2.0",
    "gn:asciiname":"Ban Chok Pok",
    "gn:country_code":"TH",
    "gn:dem":973,
    "gn:feature_class":"P",
    "gn:feature_code":"PPL",
    "gn:name":"Ban Chok Pok",
    "gn:population":0,
    "gn:timezone":"Asia/Bangkok",
    "iso:country":"TH",
    "name:tha_x_preferred":[
        "\u0e1a\u0e49\u0e32\u0e19\u0e08\u0e01\u0e1b\u0e01"
    ],
    "wof:name":"Ban Chok Pok",
    "wof:placetype":"locality"
},
  "geometry": {"coordinates":[98.35492000000001,17.55922],"type":"Point"}
}