{
  "type": "Feature",
  "properties": {
    "gn:admin1_code":"51.0",
    "gn:asciiname":"Ban Pong Ta Hian",
    "gn:country_code":"TH",
    "gn:dem":12,
    "gn:feature_class":"P",
    "gn:feature_code":"PPL",
    "gn:name":"Ban Pong Ta Hian",
    "gn:population":0,
    "gn:timezone":"Asia/Bangkok",
    "iso:country":"TH",
    "name:tha_x_preferred":[
        "\u0e1a\u0e49\u0e32\u0e19\u0e42\u0e1b\u0e23\u0e07\u0e15\u0e32\u0e40\u0e2b\u0e35\u0e22\u0e19"
    ],
    "wof:lang_x_official":[
        "tha"
    ],
    "wof:lang_x_spoken":[
        "tha"
    ],
    "wof:name":"Ban Pong Ta Hian",
    "wof:placetype":"locality"
},
  "geometry": {"coordinates":[99.87461,14.13019],"type":"Point"}
}