{
  "type": "Feature",
  "properties": {
    "gn:admin1_code":"50.0",
    "gn:asciiname":"Ban Nong Khi",
    "gn:country_code":"TH",
    "gn:dem":28,
    "gn:feature_class":"P",
    "gn:feature_code":"PPL",
    "gn:name":"Ban Nong Khi",
    "gn:population":0,
    "gn:timezone":"Asia/Bangkok",
    "iso:country":"TH",
    "name:tha_x_preferred":[
        "\u0e1a\u0e49\u0e32\u0e19\u0e2b\u0e19\u0e2d\u0e07\u0e04\u0e35"
    ],
    "name:und_x_variant":[
        "Ban Nong Khli",
        "Ban Nong Khi"
    ],
    "wof:name":"Ban Nong Khi",
    "wof:placetype":"locality"
},
  "geometry": {"coordinates":[99.63943999999999,13.90144],"type":"Point"}
}