{
  "type": "Feature",
  "properties": {
    "gn:admin1_code":"70.0",
    "gn:asciiname":"Ban Phong Ku Wae",
    "gn:country_code":"TH",
    "gn:dem":60,
    "gn:feature_class":"P",
    "gn:feature_code":"PPL",
    "gn:name":"Ban Phong Ku Wae",
    "gn:population":0,
    "gn:timezone":"Asia/Bangkok",
    "iso:country":"TH",
    "name:tha_x_preferred":[
        "\u0e1a\u0e49\u0e32\u0e19\u0e1e\u0e07\u0e01\u0e39\u0e41\u0e27"
    ],
    "wof:name":"Ban Phong Ku Wae",
    "wof:placetype":"locality"
},
  "geometry": {"coordinates":[101.10256,6.50917],"type":"Point"}
}