{
  "type": "Feature",
  "properties": {
    "gn:admin1_code":"44.0",
    "gn:asciiname":"Ban Khwai Khao Hak",
    "gn:country_code":"TH",
    "gn:dem":5,
    "gn:feature_class":"P",
    "gn:feature_code":"PPL",
    "gn:name":"Ban Khwai Khao Hak",
    "gn:population":0,
    "gn:timezone":"Asia/Bangkok",
    "iso:country":"TH",
    "name:tha_x_preferred":[
        "\u0e1a\u0e49\u0e32\u0e19\u0e04\u0e27\u0e32\u0e22\u0e40\u0e02\u0e32\u0e2b\u0e31\u0e01"
    ],
    "name:und_x_variant":[
        "Ban Khao Khwai Hak"
    ],
    "wof:name":"Ban Khwai Khao Hak",
    "wof:placetype":"locality"
},
  "geometry": {"coordinates":[101.15664,13.7462],"type":"Point"}
}