{
  "type": "Feature",
  "properties": {
    "gn:admin1_code":"58.0",
    "gn:asciiname":"Ban Hua Krut",
    "gn:country_code":"TH",
    "gn:dem":16,
    "gn:feature_class":"P",
    "gn:feature_code":"PPL",
    "gn:name":"Ban Hua Krut",
    "gn:population":0,
    "gn:timezone":"Asia/Bangkok",
    "iso:country":"TH",
    "name:tha_x_preferred":[
        "\u0e1a\u0e49\u0e32\u0e19\u0e2b\u0e31\u0e27\u0e01\u0e23\u0e39\u0e14"
    ],
    "name:und_x_variant":[
        "Hua Kr\u016bd",
        "Ban Hua Krut"
    ],
    "wof:name":"Ban Hua Krut",
    "wof:placetype":"locality"
},
  "geometry": {"coordinates":[99.24028,10.38872],"type":"Point"}
}