{
  "type": "Feature",
  "properties": {
    "gn:admin1_code":"70.0",
    "gn:asciiname":"Ban Sakuwa",
    "gn:country_code":"TH",
    "gn:dem":39,
    "gn:feature_class":"P",
    "gn:feature_code":"PPL",
    "gn:name":"Ban Sakuwa",
    "gn:population":0,
    "gn:timezone":"Asia/Bangkok",
    "iso:country":"TH",
    "name:tha_x_preferred":[
        "\u0e1a\u0e49\u0e32\u0e19\u0e2a\u0e30\u0e01\u0e39\u0e27\u0e30"
    ],
    "wof:name":"Ban Sakuwa",
    "wof:placetype":"locality"
},
  "geometry": {"coordinates":[101.11058,6.47972],"type":"Point"}
}