{
  "type": "Feature",
  "properties": {
    "gn:admin1_code":"73.0",
    "gn:asciiname":"Ban Na Mak-ngaeo",
    "gn:country_code":"TH",
    "gn:dem":161,
    "gn:feature_class":"P",
    "gn:feature_code":"PPL",
    "gn:name":"Ban Na Mak-ngaeo",
    "gn:population":0,
    "gn:timezone":"Asia/Bangkok",
    "iso:country":"TH",
    "name:tha_x_preferred":[
        "Ban Na Mak-ngaeo"
    ],
    "name:tha_x_variant":[
        "\u0e1a\u0e49\u0e32\u0e19\u0e19\u0e32\u0e2b\u0e21\u0e32\u0e01\u0e41\u0e07\u0e27"
    ],
    "wof:name":"Ban Na Mak-ngaeo",
    "wof:placetype":"locality"
},
  "geometry": {"coordinates":[104.55753,17.48895],"type":"Point"}
}