{
  "type": "Feature",
  "properties": {
    "gn:admin1_code":"69.0",
    "gn:asciiname":"Ban Pa O",
    "gn:country_code":"TH",
    "gn:dem":13,
    "gn:feature_class":"P",
    "gn:feature_code":"PPL",
    "gn:name":"Ban Pa O",
    "gn:population":0,
    "gn:timezone":"Asia/Bangkok",
    "iso:country":"TH",
    "name:tha_x_preferred":[
        "\u0e1a\u0e49\u0e32\u0e19\u0e1b\u0e32\u0e42\u0e2d\u0e4a\u0e30"
    ],
    "wof:name":"Ban Pa O",
    "wof:placetype":"locality"
},
  "geometry": {"coordinates":[101.59202999999999,6.64358],"type":"Point"}
}