{
  "type": "Feature",
  "properties": {
    "gn:admin1_code":"26.0",
    "gn:asciiname":"Ban Kong Si",
    "gn:country_code":"TH",
    "gn:dem":233,
    "gn:feature_class":"P",
    "gn:feature_code":"PPL",
    "gn:name":"Ban Kong Si",
    "gn:population":0,
    "gn:timezone":"Asia/Bangkok",
    "iso:country":"TH",
    "name:tha_x_preferred":[
        "\u0e1a\u0e49\u0e32\u0e19\u0e01\u0e2d\u0e07\u0e28\u0e23\u0e35"
    ],
    "wof:name":"Ban Kong Si",
    "wof:placetype":"locality"
},
  "geometry": {"coordinates":[102.37085999999999,16.26902999999999],"type":"Point"}
}