{
  "type": "Feature",
  "properties": {
    "gn:admin1_code":"57.0",
    "gn:asciiname":"Ban Lum Pho",
    "gn:country_code":"TH",
    "gn:dem":6,
    "gn:feature_class":"P",
    "gn:feature_code":"PPL",
    "gn:name":"Ban Lum Pho",
    "gn:population":0,
    "gn:timezone":"Asia/Bangkok",
    "iso:country":"TH",
    "name:tha_x_preferred":[
        "\u0e1a\u0e49\u0e32\u0e19\u0e25\u0e38\u0e48\u0e21\u0e42\u0e1e\u0e18\u0e34\u0e4c"
    ],
    "name:und_x_variant":[
        "Ban Rom Pho"
    ],
    "wof:name":"Ban Lum Pho",
    "wof:placetype":"locality"
},
  "geometry": {"coordinates":[99.929,12.35333],"type":"Point"}
}