{
  "type": "Feature",
  "properties": {
    "gn:admin1_code":"70.0",
    "gn:asciiname":"Ban Suan Maphrao",
    "gn:country_code":"TH",
    "gn:dem":64,
    "gn:feature_class":"P",
    "gn:feature_code":"PPL",
    "gn:name":"Ban Suan Maphrao",
    "gn:population":0,
    "gn:timezone":"Asia/Bangkok",
    "iso:country":"TH",
    "name:tha_x_preferred":[
        "\u0e1a\u0e49\u0e32\u0e19\u0e2a\u0e27\u0e19\u0e21\u0e30\u0e1e\u0e23\u0e49\u0e32\u0e27"
    ],
    "wof:lang_x_official":[
        "tha"
    ],
    "wof:lang_x_spoken":[
        "tha"
    ],
    "wof:name":"Ban Suan Maphrao",
    "wof:placetype":"locality"
},
  "geometry": {"coordinates":[101.02175,6.37578],"type":"Point"}
}