{
  "type": "Feature",
  "properties": {
    "gn:admin1_code":"44.0",
    "gn:asciiname":"Ban Ko Mo Si",
    "gn:country_code":"TH",
    "gn:dem":84,
    "gn:feature_class":"P",
    "gn:feature_code":"PPL",
    "gn:name":"Ban Ko Mo Si",
    "gn:population":0,
    "gn:timezone":"Asia/Bangkok",
    "iso:country":"TH",
    "name:tha_x_preferred":[
        "\u0e1a\u0e49\u0e32\u0e19 \u0e01\u0e21.\u0e2a\u0e35\u0e48"
    ],
    "wof:name":"Ban Ko Mo Si",
    "wof:placetype":"locality"
},
  "geometry": {"coordinates":[101.47347000000001,13.54806],"type":"Point"}
}