{
  "type": "Feature",
  "properties": {
    "gn:admin1_code":"59.0",
    "gn:asciiname":"Ban Sam Laem",
    "gn:country_code":"TH",
    "gn:dem":72,
    "gn:feature_class":"P",
    "gn:feature_code":"PPL",
    "gn:name":"Ban Sam Laem",
    "gn:population":0,
    "gn:timezone":"Asia/Bangkok",
    "iso:country":"TH",
    "name:tha_x_preferred":[
        "\u0e1a\u0e49\u0e32\u0e19\u0e2a\u0e32\u0e21\u0e41\u0e2b\u0e25\u0e21"
    ],
    "wof:name":"Ban Sam Laem",
    "wof:placetype":"locality"
},
  "geometry": {"coordinates":[98.61857999999999,10.006],"type":"Point"}
}