{
  "type": "Feature",
  "properties": {
    "gn:admin1_code":"28",
    "gn:asciiname":"Ban Ta Long",
    "gn:country_code":"TH",
    "gn:dem":135,
    "gn:feature_class":"P",
    "gn:feature_code":"PPL",
    "gn:name":"Ban Ta Long",
    "gn:population":0,
    "gn:timezone":"Asia/Bangkok",
    "iso:country":"TH",
    "name:tha_x_preferred":[
        "\u0e1a\u0e49\u0e32\u0e19\u0e15\u0e32\u0e25\u0e2d\u0e07"
    ],
    "wof:name":"Ban Ta Long",
    "wof:placetype":"locality"
},
  "geometry": {"coordinates":[103.38697000000001,15.28508],"type":"Point"}
}