{
  "type": "Feature",
  "properties": {
    "gn:admin1_code":"3.0",
    "gn:asciiname":"Ban Ko Lung",
    "gn:country_code":"TH",
    "gn:dem":550,
    "gn:feature_class":"P",
    "gn:feature_code":"PPL",
    "gn:name":"Ban Ko Lung",
    "gn:population":0,
    "gn:timezone":"Asia/Bangkok",
    "iso:country":"TH",
    "name:tha_x_preferred":[
        "\u0e1a\u0e49\u0e32\u0e19\u0e01\u0e2d\u0e25\u0e38\u0e07"
    ],
    "wof:name":"Ban Ko Lung",
    "wof:placetype":"locality"
},
  "geometry": {"coordinates":[99.51066,19.31091],"type":"Point"}
}