{
  "type": "Feature",
  "properties": {
    "gn:admin1_code":"77.0",
    "gn:asciiname":"Ban Khok Chakkachan",
    "gn:country_code":"TH",
    "gn:dem":160,
    "gn:feature_class":"P",
    "gn:feature_code":"PPL",
    "gn:name":"Ban Khok Chakkachan",
    "gn:population":0,
    "gn:timezone":"Asia/Bangkok",
    "iso:country":"TH",
    "name:tha_x_preferred":[
        "Ban Khok Chakkachan"
    ],
    "name:tha_x_variant":[
        "\u0e1a\u0e49\u0e32\u0e19\u0e42\u0e04\u0e01\u0e08\u0e31\u0e01\u0e08\u0e31\u0e48\u0e19"
    ],
    "name:und_x_variant":[
        "Ban Khok Chakohan"
    ],
    "wof:name":"Ban Khok Chakkachan",
    "wof:placetype":"locality"
},
  "geometry": {"coordinates":[104.62947,15.84274],"type":"Point"}
}