{
  "type": "Feature",
  "properties": {
    "gn:admin1_code":"50.0",
    "gn:asciiname":"Ban Krap Noi",
    "gn:country_code":"TH",
    "gn:dem":70,
    "gn:feature_class":"P",
    "gn:feature_code":"PPL",
    "gn:name":"Ban Krap Noi",
    "gn:population":0,
    "gn:timezone":"Asia/Bangkok",
    "iso:country":"TH",
    "name:tha_x_preferred":[
        "\u0e1a\u0e49\u0e32\u0e19\u0e01\u0e23\u0e31\u0e1a\u0e19\u0e49\u0e2d\u0e22"
    ],
    "wof:name":"Ban Krap Noi",
    "wof:placetype":"locality"
},
  "geometry": {"coordinates":[99.68814,14.65247],"type":"Point"}
}