{
  "type": "Feature",
  "properties": {
    "gn:admin1_code":"73.0",
    "gn:asciiname":"Ban Phiman",
    "gn:country_code":"TH",
    "gn:dem":146,
    "gn:feature_class":"P",
    "gn:feature_code":"PPL",
    "gn:name":"Ban Phiman",
    "gn:population":0,
    "gn:timezone":"Asia/Bangkok",
    "iso:country":"TH",
    "name:tha_x_preferred":[
        "Ban Phiman"
    ],
    "name:tha_x_variant":[
        "\u0e1a\u0e49\u0e32\u0e19\u0e1e\u0e34\u0e21\u0e32\u0e19"
    ],
    "wof:name":"Ban Phiman",
    "wof:placetype":"locality"
},
  "geometry": {"coordinates":[104.56233,16.94389],"type":"Point"}
}