{
  "type": "Feature",
  "properties": {
    "gn:admin1_code":"68.0",
    "gn:asciiname":"Ban Mai Phok",
    "gn:country_code":"TH",
    "gn:dem":21,
    "gn:feature_class":"P",
    "gn:feature_code":"PPL",
    "gn:name":"Ban Mai Phok",
    "gn:population":0,
    "gn:timezone":"Asia/Bangkok",
    "iso:country":"TH",
    "name:tha_x_preferred":[
        "\u0e1a\u0e49\u0e32\u0e19\u0e44\u0e21\u0e49\u0e1e\u0e2d\u0e01"
    ],
    "wof:name":"Ban Mai Phok",
    "wof:placetype":"locality"
},
  "geometry": {"coordinates":[100.69181,6.84536],"type":"Point"}
}