{
  "type": "Feature",
  "properties": {
    "gn:admin1_code":"9.0",
    "gn:asciiname":"Ban Kaeng Luang",
    "gn:country_code":"TH",
    "gn:dem":75,
    "gn:feature_class":"P",
    "gn:feature_code":"PPL",
    "gn:name":"Ban Kaeng Luang",
    "gn:population":0,
    "gn:timezone":"Asia/Bangkok",
    "iso:country":"TH",
    "name:tha_x_preferred":[
        "\u0e1a\u0e49\u0e32\u0e19\u0e41\u0e01\u0e48\u0e07\u0e2b\u0e25\u0e27\u0e07"
    ],
    "wof:name":"Ban Kaeng Luang",
    "wof:placetype":"locality"
},
  "geometry": {"coordinates":[99.78910999999999,17.43636],"type":"Point"}
}