{
  "type": "Feature",
  "properties": {
    "gn:country":"TH",
    "gn:fcode":"PPL",
    "gn:pop":0,
    "iso:country":"TH",
    "name:tha_x_preferred":[
        "\u0e1a\u0e49\u0e32\u0e19\u0e2b\u0e19\u0e2d\u0e07\u0e41\u0e2b\u0e19"
    ],
    "name:unk_x_variant":[
        "Ban Nong Haen"
    ],
    "qs:name":"Ban Nong Nae",
    "qs:name_adm0":"Thailand",
    "qs:name_adm1":"Chachoengsao",
    "qs:photos_9k":1,
    "qs:photos_9r":1,
    "qs:photos_all":1,
    "qs:photos_sr":0,
    "qs:placetype":"Town",
    "qs:pop_sr":"0",
    "wof:name":"Ban Nong Nae",
    "wof:placetype":"locality",
    "wof:population":0
},
  "geometry": {"coordinates":[101.33156,13.67411],"type":"Point"}
}