{
  "type": "Feature",
  "properties": {
    "gn:admin1_code":"23.0",
    "gn:asciiname":"Ban Nong Yang Kham Tai",
    "gn:country_code":"TH",
    "gn:dem":173,
    "gn:feature_class":"P",
    "gn:feature_code":"PPL",
    "gn:name":"Ban Nong Yang Kham Tai",
    "gn:population":0,
    "gn:timezone":"Asia/Bangkok",
    "iso:country":"TH",
    "name:tha_x_preferred":[
        "\u0e1a\u0e49\u0e32\u0e19\u0e2b\u0e19\u0e2d\u0e07\u0e22\u0e32\u0e07\u0e04\u0e33\u0e43\u0e15\u0e49"
    ],
    "name:und_x_variant":[
        "Ban Nong Yang Tai"
    ],
    "wof:name":"Ban Nong Yang Kham Tai",
    "wof:placetype":"locality"
},
  "geometry": {"coordinates":[103.63856,16.77444],"type":"Point"}
}