{
  "type": "Feature",
  "properties": {
    "gn:admin1_code":"67.0",
    "gn:asciiname":"Ban Soi 2",
    "gn:country_code":"TH",
    "gn:dem":36,
    "gn:feature_class":"P",
    "gn:feature_code":"PPL",
    "gn:name":"Ban Soi 2",
    "gn:population":0,
    "gn:timezone":"Asia/Bangkok",
    "iso:country":"TH",
    "name:tha_x_preferred":[
        "\u0e1a\u0e49\u0e32\u0e19\u0e0b\u0e2d\u0e22 \u0e2a\u0e2d\u0e07"
    ],
    "name:tha_x_variant":[
        "Ban Soi 2"
    ],
    "name:und_x_variant":[
        "Ban Soi Song"
    ],
    "wof:name":"Ban Soi 2",
    "wof:placetype":"locality"
},
  "geometry": {"coordinates":[100.01456,6.84381],"type":"Point"}
}