{
  "type": "Feature",
  "properties": {
    "gn:admin1_code":"2.0",
    "gn:asciiname":"Ban Wang Chom",
    "gn:country_code":"TH",
    "gn:dem":392,
    "gn:feature_class":"P",
    "gn:feature_code":"PPL",
    "gn:name":"Ban Wang Chom",
    "gn:population":0,
    "gn:timezone":"Asia/Bangkok",
    "iso:country":"TH",
    "name:tha_x_preferred":[
        "\u0e1a\u0e49\u0e32\u0e19\u0e27\u0e31\u0e07\u0e08\u0e4a\u0e2d\u0e21"
    ],
    "wof:name":"Ban Wang Chom",
    "wof:placetype":"locality"
},
  "geometry": {"coordinates":[98.96241999999999,19.38433],"type":"Point"}
}