{
  "type": "Feature",
  "properties": {
    "gn:admin1_code":"4.0",
    "gn:asciiname":"Ban Nat",
    "gn:country_code":"TH",
    "gn:dem":262,
    "gn:feature_class":"P",
    "gn:feature_code":"PPL",
    "gn:name":"Ban Nat",
    "gn:population":0,
    "gn:timezone":"Asia/Bangkok",
    "iso:country":"TH",
    "name:tha_x_preferred":[
        "\u0e1a\u0e49\u0e32\u0e19\u0e2b\u0e19\u0e32\u0e14"
    ],
    "wof:name":"Ban Nat",
    "wof:placetype":"locality"
},
  "geometry": {"coordinates":[100.90061,19.20236],"type":"Point"}
}