{
  "type": "Feature",
  "properties": {
    "gn:admin1_code":"73.0",
    "gn:asciiname":"Ban Kut Takla",
    "gn:country_code":"TH",
    "gn:dem":161,
    "gn:feature_class":"P",
    "gn:feature_code":"PPL",
    "gn:name":"Ban Kut Takla",
    "gn:population":0,
    "gn:timezone":"Asia/Bangkok",
    "iso:country":"TH",
    "name:tha_x_preferred":[
        "Ban Kut Takla"
    ],
    "name:tha_x_variant":[
        "\u0e1a\u0e49\u0e32\u0e19\u0e01\u0e38\u0e14\u0e15\u0e30\u0e01\u0e25\u0e49\u0e32"
    ],
    "wof:name":"Ban Kut Takla",
    "wof:placetype":"locality"
},
  "geometry": {"coordinates":[104.39378000000001,17.44431],"type":"Point"}
}