{
  "type": "Feature",
  "properties": {
    "gn:admin1_code":"16.0",
    "gn:asciiname":"Ban Bang Mafo",
    "gn:country_code":"TH",
    "gn:dem":29,
    "gn:feature_class":"P",
    "gn:feature_code":"PPL",
    "gn:name":"Ban Bang Mafo",
    "gn:population":0,
    "gn:timezone":"Asia/Bangkok",
    "iso:country":"TH",
    "name:tha_x_preferred":[
        "\u0e1a\u0e49\u0e32\u0e19\u0e1a\u0e32\u0e07\u0e21\u0e30\u0e1d\u0e2d"
    ],
    "name:und_x_variant":[
        "Ban Bang Mato",
        "Ban Bang Mafo",
        "B\u0101n Bang Mafau",
        "Ban Dong Mato",
        "Ban Bang Mafo Nai"
    ],
    "wof:name":"Ban Bang Mafo",
    "wof:placetype":"locality"
},
  "geometry": {"coordinates":[100.08767,15.60733],"type":"Point"}
}