{
  "type": "Feature",
  "properties": {
    "gn:admin1_code":"28.0",
    "gn:asciiname":"Ban Palat Puk",
    "gn:country_code":"TH",
    "gn:dem":148,
    "gn:feature_class":"P",
    "gn:feature_code":"PPL",
    "gn:name":"Ban Palat Puk",
    "gn:population":0,
    "gn:timezone":"Asia/Bangkok",
    "iso:country":"TH",
    "name:tha_x_preferred":[
        "\u0e1a\u0e49\u0e32\u0e19\u0e1b\u0e25\u0e31\u0e14\u0e1b\u0e38\u0e4a\u0e01"
    ],
    "name:und_x_variant":[
        "Ban Palat Pluk"
    ],
    "wof:name":"Ban Palat Puk",
    "wof:placetype":"locality"
},
  "geometry": {"coordinates":[103.19914,15.14808],"type":"Point"}
}