{
  "type": "Feature",
  "properties": {
    "gn:admin1_code":"24",
    "gn:asciiname":"Ban Lao Wilai",
    "gn:country_code":"TH",
    "gn:dem":156,
    "gn:feature_class":"P",
    "gn:feature_code":"PPL",
    "gn:name":"Ban Lao Wilai",
    "gn:population":0,
    "gn:timezone":"Asia/Bangkok",
    "iso:country":"TH",
    "name:tha_x_preferred":[
        "\u0e1a\u0e49\u0e32\u0e19\u0e40\u0e2b\u0e25\u0e48\u0e32\u0e27\u0e34\u0e44\u0e25"
    ],
    "wof:name":"Ban Lao Wilai",
    "wof:placetype":"locality"
},
  "geometry": {"coordinates":[103.40881,16.12867],"type":"Point"}
}