{
  "type": "Feature",
  "properties": {
    "gn:admin1_code":"58.0",
    "gn:asciiname":"Ban Ko Tiap",
    "gn:country_code":"TH",
    "gn:dem":7,
    "gn:feature_class":"P",
    "gn:feature_code":"PPL",
    "gn:name":"Ban Ko Tiap",
    "gn:population":0,
    "gn:timezone":"Asia/Bangkok",
    "iso:country":"TH",
    "name:tha_x_preferred":[
        "\u0e1a\u0e49\u0e32\u0e19\u0e40\u0e01\u0e32\u0e30\u0e40\u0e15\u0e35\u0e22\u0e1a"
    ],
    "wof:name":"Ban Ko Tiap",
    "wof:placetype":"locality"
},
  "geometry": {"coordinates":[99.49957999999999,10.86908],"type":"Point"}
}