{
  "type": "Feature",
  "properties": {
    "gn:admin1_code":"23.0",
    "gn:asciiname":"Ban Non Nam Thaeng",
    "gn:country_code":"TH",
    "gn:dem":178,
    "gn:feature_class":"P",
    "gn:feature_code":"PPL",
    "gn:name":"Ban Non Nam Thaeng",
    "gn:population":0,
    "gn:timezone":"Asia/Bangkok",
    "iso:country":"TH",
    "name:tha_x_preferred":[
        "\u0e1a\u0e49\u0e32\u0e19\u0e42\u0e19\u0e19\u0e2b\u0e19\u0e32\u0e21\u0e41\u0e17\u0e07"
    ],
    "wof:name":"Ban Non Nam Thaeng",
    "wof:placetype":"locality"
},
  "geometry": {"coordinates":[103.71369,16.47939],"type":"Point"}
}