{
  "type": "Feature",
  "properties": {
    "gn:admin1_code":"18.0",
    "gn:asciiname":"Ban Phon Thong",
    "gn:country_code":"TH",
    "gn:dem":259,
    "gn:feature_class":"P",
    "gn:feature_code":"PPL",
    "gn:name":"Ban Phon Thong",
    "gn:population":0,
    "gn:timezone":"Asia/Bangkok",
    "iso:country":"TH",
    "name:tha_x_preferred":[
        "Ban Phon Thong"
    ],
    "name:tha_x_variant":[
        "\u0e1a\u0e49\u0e32\u0e19\u0e1e\u0e25\u0e17\u0e2d\u0e07"
    ],
    "wof:name":"Ban Phon Thong",
    "wof:placetype":"locality"
},
  "geometry": {"coordinates":[101.91871999999999,16.87295],"type":"Point"}
}