{
  "type": "Feature",
  "properties": {
    "gn:admin1_code":"68.0",
    "gn:asciiname":"Ban Ao Thale Nok",
    "gn:country_code":"TH",
    "gn:dem":6,
    "gn:feature_class":"P",
    "gn:feature_code":"PPL",
    "gn:name":"Ban Ao Thale Nok",
    "gn:population":0,
    "gn:timezone":"Asia/Bangkok",
    "iso:country":"TH",
    "name:tha_x_preferred":[
        "\u0e1a\u0e49\u0e32\u0e19\u0e2d\u0e48\u0e32\u0e27\u0e17\u0e30\u0e40\u0e25\u0e19\u0e2d\u0e01"
    ],
    "wof:name":"Ban Ao Thale Nok",
    "wof:placetype":"locality"
},
  "geometry": {"coordinates":[100.56236,7.23117],"type":"Point"}
}