{
  "type": "Feature",
  "properties": {
    "gn:admin1_code":"27",
    "gn:asciiname":"Ban Hua Krok",
    "gn:country_code":"TH",
    "gn:dem":236,
    "gn:feature_class":"P",
    "gn:feature_code":"PPL",
    "gn:name":"Ban Hua Krok",
    "gn:population":0,
    "gn:timezone":"Asia/Bangkok",
    "iso:country":"TH",
    "name:tha_x_preferred":[
        "\u0e1a\u0e49\u0e32\u0e19\u0e2b\u0e31\u0e27\u0e42\u0e01\u0e23\u0e01"
    ],
    "wof:name":"Ban Hua Krok",
    "wof:placetype":"locality"
},
  "geometry": {"coordinates":[101.22028,14.67994],"type":"Point"}
}