{
  "type": "Feature",
  "properties": {
    "gn:admin1_code":"61.0",
    "gn:asciiname":"Ban Bang Ma",
    "gn:country_code":"TH",
    "gn:dem":73,
    "gn:feature_class":"P",
    "gn:feature_code":"PPL",
    "gn:name":"Ban Bang Ma",
    "gn:population":0,
    "gn:timezone":"Asia/Bangkok",
    "iso:country":"TH",
    "name:tha_x_preferred":[
        "\u0e1a\u0e49\u0e32\u0e19\u0e1a\u0e32\u0e07\u0e21\u0e48\u0e32"
    ],
    "name:und_x_variant":[
        "Ban Bang Phama",
        "Ban Bang Pamah",
        "Ban Bang Ma"
    ],
    "wof:name":"Ban Bang Ma",
    "wof:placetype":"locality"
},
  "geometry": {"coordinates":[98.42119,8.53597],"type":"Point"}
}