{
  "type": "Feature",
  "properties": {
    "gn:admin1_code":"1.0",
    "gn:asciiname":"Ban Ka Lo Kho",
    "gn:country_code":"TH",
    "gn:dem":580,
    "gn:feature_class":"P",
    "gn:feature_code":"PPL",
    "gn:name":"Ban Ka Lo Kho",
    "gn:population":0,
    "gn:timezone":"Asia/Bangkok",
    "iso:country":"TH",
    "name:tha_x_preferred":[
        "\u0e1a\u0e49\u0e32\u0e19\u0e01\u0e30\u0e25\u0e2d\u0e42\u0e04\u0e49\u0e30"
    ],
    "name:und_x_variant":[
        "Ban Klo Kho"
    ],
    "wof:lang_x_official":[
        "tha"
    ],
    "wof:lang_x_spoken":[
        "tha"
    ],
    "wof:name":"Ban Ka Lo Kho",
    "wof:placetype":"locality"
},
  "geometry": {"coordinates":[97.84472,17.80433],"type":"Point"}
}