{
  "type": "Feature",
  "properties": {
    "gn:admin1_code":"70.0",
    "gn:asciiname":"Ban Si Se Nai",
    "gn:country_code":"TH",
    "gn:dem":44,
    "gn:feature_class":"P",
    "gn:feature_code":"PPL",
    "gn:name":"Ban Si Se Nai",
    "gn:population":0,
    "gn:timezone":"Asia/Bangkok",
    "iso:country":"TH",
    "name:tha_x_preferred":[
        "\u0e1a\u0e49\u0e32\u0e19\u0e0b\u0e35\u0e40\u0e0b\u0e4a\u0e30\u0e43\u0e19"
    ],
    "wof:name":"Ban Si Se Nai",
    "wof:placetype":"locality"
},
  "geometry": {"coordinates":[101.14324999999999,6.45442],"type":"Point"}
}