{
  "type": "Feature",
  "properties": {
    "gn:admin1_code":"6.0",
    "gn:asciiname":"Ban Hong Li",
    "gn:country_code":"TH",
    "gn:dem":244,
    "gn:feature_class":"P",
    "gn:feature_code":"PPL",
    "gn:name":"Ban Hong Li",
    "gn:population":0,
    "gn:timezone":"Asia/Bangkok",
    "iso:country":"TH",
    "name:tha_x_preferred":[
        "\u0e1a\u0e49\u0e32\u0e19\u0e2e\u0e48\u0e2d\u0e07\u0e25\u0e35"
    ],
    "wof:name":"Ban Hong Li",
    "wof:placetype":"locality"
},
  "geometry": {"coordinates":[99.51039,18.10519],"type":"Point"}
}