{
  "type": "Feature",
  "properties": {
    "gn:admin1_code":"31.0",
    "gn:asciiname":"Ban U Tae Chi Ching",
    "gn:country_code":"TH",
    "gn:dem":19,
    "gn:feature_class":"P",
    "gn:feature_code":"PPL",
    "gn:name":"Ban U Tae Chi Ching",
    "gn:population":0,
    "gn:timezone":"Asia/Bangkok",
    "iso:country":"TH",
    "name:tha_x_preferred":[
        "\u0e1a\u0e49\u0e32\u0e19\u0e2d\u0e39\u0e41\u0e15\u0e08\u0e35\u0e08\u0e34\u0e07"
    ],
    "wof:name":"Ban U Tae Chi Ching",
    "wof:placetype":"locality"
},
  "geometry": {"coordinates":[101.68947,6.44067],"type":"Point"}
}