{
  "type": "Feature",
  "properties": {
    "gn:admin1_code":"3.0",
    "gn:asciiname":"Ban San Champa",
    "gn:country_code":"TH",
    "gn:dem":484,
    "gn:feature_class":"P",
    "gn:feature_code":"PPL",
    "gn:name":"Ban San Champa",
    "gn:population":0,
    "gn:timezone":"Asia/Bangkok",
    "iso:country":"TH",
    "name:tha_x_preferred":[
        "\u0e1a\u0e49\u0e32\u0e19\u0e2a\u0e31\u0e19\u0e08\u0e33\u0e1b\u0e32"
    ],
    "name:und_x_variant":[
        "B\u0101n San Jam Pa",
        "Ban San Champa",
        "Ban San Champa (1)"
    ],
    "wof:name":"Ban San Champa",
    "wof:placetype":"locality"
},
  "geometry": {"coordinates":[99.51555999999999,19.62442],"type":"Point"}
}