{
  "type": "Feature",
  "properties": {
    "gn:admin1_code":"20.0",
    "gn:asciiname":"Ban Champa Dong",
    "gn:country_code":"TH",
    "gn:dem":163,
    "gn:feature_class":"P",
    "gn:feature_code":"PPL",
    "gn:name":"Ban Champa Dong",
    "gn:population":0,
    "gn:timezone":"Asia/Bangkok",
    "iso:country":"TH",
    "name:tha_x_preferred":[
        "\u0e1a\u0e49\u0e32\u0e19\u0e08\u0e33\u0e1b\u0e32\u0e14\u0e07"
    ],
    "wof:name":"Ban Champa Dong",
    "wof:placetype":"locality"
},
  "geometry": {"coordinates":[103.62846999999999,17.76527999999999],"type":"Point"}
}