{
  "type": "Feature",
  "properties": {
    "gn:admin1_code":"11.0",
    "gn:asciiname":"Ban Na Wang Mai Daeng",
    "gn:country_code":"TH",
    "gn:dem":105,
    "gn:feature_class":"P",
    "gn:feature_code":"PPL",
    "gn:name":"Ban Na Wang Mai Daeng",
    "gn:population":0,
    "gn:timezone":"Asia/Bangkok",
    "iso:country":"TH",
    "name:tha_x_preferred":[
        "\u0e1a\u0e49\u0e32\u0e19\u0e19\u0e32\u0e27\u0e31\u0e07\u0e44\u0e21\u0e49\u0e41\u0e14\u0e07"
    ],
    "name:und_x_variant":[
        "Ban Wang Mai Daeng"
    ],
    "wof:name":"Ban Na Wang Mai Daeng",
    "wof:placetype":"locality"
},
  "geometry": {"coordinates":[99.45594,16.73503],"type":"Point"}
}