{
  "type": "Feature",
  "properties": {
    "gn:admin1_code":"14.0",
    "gn:asciiname":"Ban Tha Rong",
    "gn:country_code":"TH",
    "gn:dem":78,
    "gn:feature_class":"P",
    "gn:feature_code":"PPL",
    "gn:name":"Ban Tha Rong",
    "gn:population":0,
    "gn:timezone":"Asia/Bangkok",
    "iso:country":"TH",
    "name:tha_x_preferred":[
        "\u0e1a\u0e49\u0e32\u0e19\u0e17\u0e48\u0e32\u0e42\u0e23\u0e07"
    ],
    "name:und_x_variant":[
        "B\u0101n Tha Sam Raung",
        "Ban Tha Samrong",
        "Ban Tha Rong"
    ],
    "wof:name":"Ban Tha Rong",
    "wof:placetype":"locality"
},
  "geometry": {"coordinates":[101.11485999999999,15.65586],"type":"Point"}
}