{
  "type": "Feature",
  "properties": {
    "gn:admin1_code":"32.0",
    "gn:asciiname":"Ban Nong Ta Kaeo",
    "gn:country_code":"TH",
    "gn:dem":13,
    "gn:feature_class":"P",
    "gn:feature_code":"PPL",
    "gn:name":"Ban Nong Ta Kaeo",
    "gn:population":0,
    "gn:timezone":"Asia/Bangkok",
    "iso:country":"TH",
    "name:tha_x_preferred":[
        "\u0e1a\u0e49\u0e32\u0e19\u0e2b\u0e19\u0e2d\u0e07\u0e15\u0e32\u0e41\u0e01\u0e49\u0e27"
    ],
    "name:und_x_variant":[
        "Ban Nong Ta Khaeo"
    ],
    "wof:name":"Ban Nong Ta Kaeo",
    "wof:placetype":"locality"
},
  "geometry": {"coordinates":[100.17725,14.95242],"type":"Point"}
}