{
  "type": "Feature",
  "properties": {
    "gn:admin1_code":"68.0",
    "gn:asciiname":"Ban Khuan Din Daeng",
    "gn:country_code":"TH",
    "gn:dem":15,
    "gn:feature_class":"P",
    "gn:feature_code":"PPL",
    "gn:name":"Ban Khuan Din Daeng",
    "gn:population":0,
    "gn:timezone":"Asia/Bangkok",
    "iso:country":"TH",
    "name:tha_x_preferred":[
        "\u0e1a\u0e49\u0e32\u0e19\u0e04\u0e27\u0e19\u0e14\u0e34\u0e19\u0e41\u0e14\u0e07"
    ],
    "wof:name":"Ban Khuan Din Daeng",
    "wof:placetype":"locality"
},
  "geometry": {"coordinates":[100.85108,6.89375],"type":"Point"}
}