{
  "type": "Feature",
  "properties": {
    "gn:admin1_code":"29",
    "gn:asciiname":"Ban Kae Yai",
    "gn:country_code":"TH",
    "gn:dem":151,
    "gn:feature_class":"P",
    "gn:feature_code":"PPL",
    "gn:name":"Ban Kae Yai",
    "gn:population":0,
    "gn:timezone":"Asia/Bangkok",
    "iso:country":"TH",
    "name:tha_x_preferred":[
        "\u0e1a\u0e49\u0e32\u0e19\u0e41\u0e01\u0e43\u0e2b\u0e0d\u0e48"
    ],
    "wof:name":"Ban Kae Yai",
    "wof:placetype":"locality"
},
  "geometry": {"coordinates":[103.50103,14.92215],"type":"Point"}
}