{
  "type": "Feature",
  "properties": {
    "gn:admin1_code":"14.0",
    "gn:asciiname":"Ban Kaen Sieo",
    "gn:country_code":"TH",
    "gn:dem":153,
    "gn:feature_class":"P",
    "gn:feature_code":"PPL",
    "gn:name":"Ban Kaen Sieo",
    "gn:population":0,
    "gn:timezone":"Asia/Bangkok",
    "iso:country":"TH",
    "name:tha_x_preferred":[
        "\u0e1a\u0e49\u0e32\u0e19\u0e41\u0e01\u0e48\u0e19\u0e40\u0e2a\u0e35\u0e49\u0e22\u0e27"
    ],
    "wof:name":"Ban Kaen Sieo",
    "wof:placetype":"locality"
},
  "geometry": {"coordinates":[101.04761000000001,16.24247],"type":"Point"}
}