{
  "type": "Feature",
  "properties": {
    "gn:admin1_code":"74",
    "gn:asciiname":"Ban Ko I Sao",
    "gn:country_code":"TH",
    "gn:dem":9,
    "gn:feature_class":"P",
    "gn:feature_code":"PPL",
    "gn:name":"Ban Ko I Sao",
    "gn:population":0,
    "gn:timezone":"Asia/Bangkok",
    "iso:country":"TH",
    "name:tha_x_preferred":[
        "\u0e1a\u0e49\u0e32\u0e19\u0e40\u0e01\u0e32\u0e30\u0e2d\u0e35\u0e2a\u0e32\u0e27"
    ],
    "wof:name":"Ban Ko I Sao",
    "wof:placetype":"locality"
},
  "geometry": {"coordinates":[101.37478,14.10558],"type":"Point"}
}