{
  "type": "Feature",
  "properties": {
    "gn:admin1_code":"70.0",
    "gn:asciiname":"Ban Cha Long",
    "gn:country_code":"TH",
    "gn:dem":52,
    "gn:feature_class":"P",
    "gn:feature_code":"PPL",
    "gn:name":"Ban Cha Long",
    "gn:population":0,
    "gn:timezone":"Asia/Bangkok",
    "iso:country":"TH",
    "name:tha_x_preferred":[
        "\u0e1a\u0e49\u0e32\u0e19\u0e08\u0e32\u0e2b\u0e25\u0e07"
    ],
    "name:und_x_variant":[
        "Kampong Ka Long",
        "Ban Cha Long"
    ],
    "wof:name":"Ban Cha Long",
    "wof:placetype":"locality"
},
  "geometry": {"coordinates":[101.09858,6.44219],"type":"Point"}
}