{
  "type": "Feature",
  "properties": {
    "gn:admin1_code":"1.0",
    "gn:asciiname":"Ban Pha A Bo Khi",
    "gn:country_code":"TH",
    "gn:dem":1112,
    "gn:feature_class":"P",
    "gn:feature_code":"PPL",
    "gn:name":"Ban Pha A Bo Khi",
    "gn:population":0,
    "gn:timezone":"Asia/Bangkok",
    "iso:country":"TH",
    "name:tha_x_preferred":[
        "\u0e1a\u0e49\u0e32\u0e19\u0e1e\u0e30\u0e2d\u0e30\u0e1a\u0e2d\u0e04\u0e35"
    ],
    "wof:lang_x_official":[
        "tha"
    ],
    "wof:lang_x_spoken":[
        "tha"
    ],
    "wof:name":"Ban Pha A Bo Khi",
    "wof:placetype":"locality"
},
  "geometry": {"coordinates":[98.05856,18.42581],"type":"Point"}
}