{
  "type": "Feature",
  "properties": {
    "gn:admin1_code":"16.0",
    "gn:asciiname":"Ban Nikhom Sai Nueng",
    "gn:country_code":"TH",
    "gn:dem":46,
    "gn:feature_class":"P",
    "gn:feature_code":"PPL",
    "gn:name":"Ban Nikhom Sai Nueng",
    "gn:population":0,
    "gn:timezone":"Asia/Bangkok",
    "iso:country":"TH",
    "name:tha_x_preferred":[
        "\u0e1a\u0e49\u0e32\u0e19\u0e19\u0e34\u0e04\u0e21\u0e2a\u0e32\u0e22 \u0e2b\u0e19\u0e36\u0e48\u0e07"
    ],
    "wof:name":"Ban Nikhom Sai Nueng",
    "wof:placetype":"locality"
},
  "geometry": {"coordinates":[100.22203,15.46111],"type":"Point"}
}