{
  "type": "Feature",
  "properties": {
    "gn:admin1_code":"22.0",
    "gn:asciiname":"Ban Phon Phek",
    "gn:country_code":"TH",
    "gn:dem":181,
    "gn:feature_class":"P",
    "gn:feature_code":"PPL",
    "gn:name":"Ban Phon Phek",
    "gn:population":0,
    "gn:timezone":"Asia/Bangkok",
    "iso:country":"TH",
    "name:tha_x_preferred":[
        "\u0e1a\u0e49\u0e32\u0e19\u0e42\u0e1e\u0e19\u0e40\u0e1e\u0e47\u0e01"
    ],
    "wof:name":"Ban Phon Phek",
    "wof:placetype":"locality"
},
  "geometry": {"coordinates":[102.54107999999999,16.19158],"type":"Point"}
}