{
  "type": "Feature",
  "properties": {
    "gn:admin1_code":"40.0",
    "gn:admin2_code":"1032",
    "gn:asciiname":"Muban Thep Thani",
    "gn:country_code":"TH",
    "gn:dem":4,
    "gn:feature_class":"P",
    "gn:feature_code":"PPL",
    "gn:name":"Muban Thep Thani",
    "gn:population":0,
    "gn:timezone":"Asia/Bangkok",
    "iso:country":"TH",
    "name:tha_x_preferred":[
        "\u0e2b\u0e21\u0e39\u0e48\u0e1a\u0e49\u0e32\u0e19\u0e40\u0e17\u0e1e\u0e18\u0e32\u0e19\u0e35"
    ],
    "wof:name":"Muban Thep Thani",
    "wof:placetype":"locality"
},
  "geometry": {"coordinates":[100.69405999999999,13.69919],"type":"Point"}
}