{
  "type": "Feature",
  "properties": {
    "gn:country":"TH",
    "gn:fcode":"PPL",
    "gn:pop":0,
    "iso:country":"TH",
    "name:tha_x_preferred":[
        "\u0e1a\u0e49\u0e32\u0e19\u0e40\u0e25\u0e32\u0e02\u0e27\u0e31\u0e0d"
    ],
    "name:unk_x_variant":[
        "Ban Lau Kwan"
    ],
    "qs:name":"Lao Khwan",
    "qs:name_adm0":"Thailand",
    "qs:name_adm1":"Kanchanaburi",
    "qs:photos_9r":0,
    "qs:photos_sr":0,
    "qs:placetype":"Town",
    "qs:pop_sr":"0",
    "wd:wordcount":217,
    "wof:name":"Lao Khwan",
    "wof:placetype":"locality",
    "wof:population":0
},
  "geometry": {"coordinates":[99.77242,14.58531],"type":"Point"}
}