{
  "type": "Feature",
  "properties": {
    "gn:country":"TH",
    "gn:fcode":"PPL",
    "gn:population":0,
    "iso:country":"TH",
    "name:bpy_x_preferred":[
        "\u0986\u09ae\u09cd\u09ab\u09cb\u09af\u09bc\u09c7 \u09b2\u09be\u0993\u0996\u09f1\u09be\u09a8"
    ],
    "name:ceb_x_preferred":[
        "Amphoe Lao Khwan"
    ],
    "name:deu_x_preferred":[
        "Amphoe Lao Khwan"
    ],
    "name:eng_x_preferred":[
        "Lao Khwan"
    ],
    "name:fas_x_preferred":[
        "\u0634\u0647\u0631\u0633\u062a\u0627\u0646 \u0644\u0622\u0648 \u06a9\u0648\u0622\u0646"
    ],
    "name:fra_x_preferred":[
        "Lao Khwan"
    ],
    "name:jpn_x_preferred":[
        "\u30e9\u30aa\u30af\u30ef\u30f3\u90e1"
    ],
    "name:kor_x_preferred":[
        "\ub77c\uc624\ucf74\uad70"
    ],
    "name:nan_x_preferred":[
        "Lao Khwan K\u016bn"
    ],
    "name:ron_x_preferred":[
        "Districtul Lao Khwan"
    ],
    "name:tha_x_preferred":[
        "\u0e1a\u0e49\u0e32\u0e19\u0e40\u0e25\u0e32\u0e02\u0e27\u0e31\u0e0d"
    ],
    "name:tha_x_variant":[
        "\u0e2d\u0e33\u0e40\u0e20\u0e2d\u0e40\u0e25\u0e32\u0e02\u0e27\u0e31\u0e0d"
    ],
    "name:und_x_variant":[
        "Ban Lau Kwan"
    ],
    "name:urd_x_preferred":[
        "\u0644\u0627\u0648 \u06a9\u06be\u0648\u0627\u0646 \u0636\u0644\u0639"
    ],
    "name:vie_x_preferred":[
        "Lao Khwan"
    ],
    "name:zho_x_preferred":[
        "\u52b3\u5bbd\u53bf"
    ],
    "qs:name":"Lao Khwan",
    "qs:name_adm0":"Thailand",
    "qs:name_adm1":"Kanchanaburi",
    "qs:photos_9r":0,
    "qs:photos_sr":0,
    "qs:placetype":"Town",
    "qs:pop_sr":"0",
    "wd:wordcount":217,
    "wof:name":"Lao Khwan",
    "wof:placetype":"locality",
    "wof:population":0
},
  "geometry": {"coordinates":[99.77242,14.58531],"type":"Point"}
}