{
  "type": "Feature",
  "properties": {
    "gn:admin1_code":"14.0",
    "gn:asciiname":"Ban Sap Ngoen",
    "gn:country_code":"TH",
    "gn:dem":130,
    "gn:feature_class":"P",
    "gn:feature_code":"PPL",
    "gn:name":"Ban Sap Ngoen",
    "gn:population":0,
    "gn:timezone":"Asia/Bangkok",
    "iso:country":"TH",
    "name:tha_x_preferred":[
        "\u0e1a\u0e49\u0e32\u0e19\u0e0b\u0e31\u0e1a\u0e40\u0e07\u0e34\u0e19"
    ],
    "wof:name":"Ban Sap Ngoen",
    "wof:placetype":"locality"
},
  "geometry": {"coordinates":[100.94886,15.80153],"type":"Point"}
}