{
  "type": "Feature",
  "properties": {
    "gn:admin1_code":"66.0",
    "gn:asciiname":"Ban Khok Nak But",
    "gn:country_code":"TH",
    "gn:dem":23,
    "gn:feature_class":"P",
    "gn:feature_code":"PPL",
    "gn:name":"Ban Khok Nak But",
    "gn:population":0,
    "gn:timezone":"Asia/Bangkok",
    "iso:country":"TH",
    "name:tha_x_preferred":[
        "\u0e1a\u0e49\u0e32\u0e19\u0e42\u0e04\u0e01\u0e19\u0e32\u0e04\u0e1a\u0e38\u0e15\u0e23"
    ],
    "wof:name":"Ban Khok Nak But",
    "wof:placetype":"locality"
},
  "geometry": {"coordinates":[100.18147,7.36708],"type":"Point"}
}