{
  "type": "Feature",
  "properties": {
    "gn:admin1_code":"9.0",
    "gn:asciiname":"Ban Pa Muang Nueng",
    "gn:country_code":"TH",
    "gn:dem":67,
    "gn:feature_class":"P",
    "gn:feature_code":"PPL",
    "gn:name":"Ban Pa Muang Nueng",
    "gn:population":0,
    "gn:timezone":"Asia/Bangkok",
    "iso:country":"TH",
    "name:tha_x_preferred":[
        "\u0e1a\u0e49\u0e32\u0e19\u0e1b\u0e48\u0e32\u0e21\u0e48\u0e27\u0e07 \u0e2b\u0e19\u0e36\u0e48\u0e07"
    ],
    "name:und_x_variant":[
        "Ban Na Wat Pa Mamuang",
        "Ban Pa Muang 1",
        "Ban Pa Muang Nueng"
    ],
    "wof:name":"Ban Pa Muang Nueng",
    "wof:placetype":"locality"
},
  "geometry": {"coordinates":[99.83761,17.33672],"type":"Point"}
}