{
  "type": "Feature",
  "properties": {
    "gn:admin1_code":"56.0",
    "gn:asciiname":"Ban Tha Krathiam",
    "gn:country_code":"TH",
    "gn:dem":17,
    "gn:feature_class":"P",
    "gn:feature_code":"PPL",
    "gn:name":"Ban Tha Krathiam",
    "gn:population":0,
    "gn:timezone":"Asia/Bangkok",
    "iso:country":"TH",
    "name:tha_x_preferred":[
        "\u0e1a\u0e49\u0e32\u0e19\u0e17\u0e48\u0e32\u0e01\u0e23\u0e30\u0e40\u0e17\u0e35\u0e22\u0e21"
    ],
    "wof:name":"Ban Tha Krathiam",
    "wof:placetype":"locality"
},
  "geometry": {"coordinates":[99.90089,12.99089],"type":"Point"}
}