{
  "type": "Feature",
  "properties": {
    "gn:admin1_code":"27.0",
    "gn:asciiname":"Ban Takut",
    "gn:country_code":"TH",
    "gn:dem":204,
    "gn:feature_class":"P",
    "gn:feature_code":"PPL",
    "gn:name":"Ban Takut",
    "gn:population":0,
    "gn:timezone":"Asia/Bangkok",
    "iso:country":"TH",
    "name:tha_x_preferred":[
        "\u0e1a\u0e49\u0e32\u0e19\u0e15\u0e30\u0e01\u0e38\u0e14"
    ],
    "name:und_x_variant":[
        "Ban Takrut"
    ],
    "wof:name":"Ban Takut",
    "wof:placetype":"locality"
},
  "geometry": {"coordinates":[102.07517,14.69742],"type":"Point"}
}