{
  "type": "Feature",
  "properties": {
    "gn:admin1_code":"6.0",
    "gn:asciiname":"Ban Nikhom Sang Toneng Ha",
    "gn:country_code":"TH",
    "gn:dem":272,
    "gn:feature_class":"P",
    "gn:feature_code":"PPL",
    "gn:name":"Ban Nikhom Sang Toneng Ha",
    "gn:population":0,
    "gn:timezone":"Asia/Bangkok",
    "iso:country":"TH",
    "name:tha_x_preferred":[
        "\u0e1a\u0e49\u0e32\u0e19\u0e19\u0e34\u0e04\u0e21\u0e2a\u0e23\u0e49\u0e32\u0e07\u0e15\u0e19\u0e40\u0e2d\u0e07 \u0e2b\u0e49\u0e32"
    ],
    "wof:lang_x_official":[
        "tha"
    ],
    "wof:lang_x_spoken":[
        "tha"
    ],
    "wof:name":"Ban Nikhom Sang Toneng Ha",
    "wof:placetype":"locality"
},
  "geometry": {"coordinates":[99.55575,18.39881],"type":"Point"}
}