{
  "type": "Feature",
  "properties": {
    "gn:admin1_code":"31.0",
    "gn:asciiname":"Ban La Lae Lu Rat",
    "gn:country_code":"TH",
    "gn:dem":48,
    "gn:feature_class":"P",
    "gn:feature_code":"PPL",
    "gn:name":"Ban La Lae Lu Rat",
    "gn:population":0,
    "gn:timezone":"Asia/Bangkok",
    "iso:country":"TH",
    "name:tha_x_preferred":[
        "\u0e1a\u0e49\u0e32\u0e19\u0e25\u0e32\u0e41\u0e25\u0e25\u0e39\u0e23\u0e31\u0e2a"
    ],
    "wof:name":"Ban La Lae Lu Rat",
    "wof:placetype":"locality"
},
  "geometry": {"coordinates":[101.84636,6.05672],"type":"Point"}
}