{
  "type": "Feature",
  "properties": {
    "gn:admin1_code":"56.0",
    "gn:asciiname":"Ban Thap Khang Bon",
    "gn:country_code":"TH",
    "gn:dem":8,
    "gn:feature_class":"P",
    "gn:feature_code":"PPL",
    "gn:name":"Ban Thap Khang Bon",
    "gn:population":0,
    "gn:timezone":"Asia/Bangkok",
    "iso:country":"TH",
    "name:tha_x_preferred":[
        "\u0e1a\u0e49\u0e32\u0e19\u0e17\u0e31\u0e1a\u0e04\u0e32\u0e07\u0e1a\u0e19"
    ],
    "wof:name":"Ban Thap Khang Bon",
    "wof:placetype":"locality"
},
  "geometry": {"coordinates":[99.82877999999999,13.20631],"type":"Point"}
}