{
  "type": "Feature",
  "properties": {
    "gn:admin1_code":"65.0",
    "gn:asciiname":"Ban Ton Chi",
    "gn:country_code":"TH",
    "gn:dem":83,
    "gn:feature_class":"P",
    "gn:feature_code":"PPL",
    "gn:name":"Ban Ton Chi",
    "gn:population":0,
    "gn:timezone":"Asia/Bangkok",
    "iso:country":"TH",
    "name:tha_x_preferred":[
        "\u0e1a\u0e49\u0e32\u0e19\u0e42\u0e15\u0e19\u0e0a\u0e35"
    ],
    "wof:name":"Ban Ton Chi",
    "wof:placetype":"locality"
},
  "geometry": {"coordinates":[99.34922,7.83525],"type":"Point"}
}