{
  "type": "Feature",
  "properties": {
    "gn:admin1_code":"76.0",
    "gn:asciiname":"Ban Yuak",
    "gn:country_code":"TH",
    "gn:dem":239,
    "gn:feature_class":"P",
    "gn:feature_code":"PPL",
    "gn:name":"Ban Yuak",
    "gn:population":0,
    "gn:timezone":"Asia/Bangkok",
    "iso:country":"TH",
    "name:und_x_variant":[
        "Yuak",
        "Ban Yuaki",
        "Ban Yuak",
        "\u0e1a\u0e49\u0e32\u0e19\u0e2b\u0e22\u0e27\u0e01"
    ],
    "wof:name":"Ban Yuak",
    "wof:placetype":"locality"
},
  "geometry": {"coordinates":[102.16453,17.68502999999999],"type":"Point"}
}