{
  "type": "Feature",
  "properties": {
    "gn:admin1_code":"64.0",
    "gn:asciiname":"Ban Chong Khao Ngam",
    "gn:country_code":"TH",
    "gn:dem":106,
    "gn:feature_class":"P",
    "gn:feature_code":"PPL",
    "gn:name":"Ban Chong Khao Ngam",
    "gn:population":0,
    "gn:timezone":"Asia/Bangkok",
    "iso:country":"TH",
    "name:tha_x_preferred":[
        "\u0e1a\u0e49\u0e32\u0e19\u0e0a\u0e48\u0e2d\u0e07\u0e40\u0e02\u0e32\u0e07\u0e32\u0e21"
    ],
    "wof:lang_x_official":[
        "tha"
    ],
    "wof:lang_x_spoken":[
        "tha"
    ],
    "wof:name":"Ban Chong Khao Ngam",
    "wof:placetype":"locality"
},
  "geometry": {"coordinates":[99.40569000000001,8.05861],"type":"Point"}
}