{
  "type": "Feature",
  "properties": {
    "gn:admin1_code":"52.0",
    "gn:asciiname":"Ban Nong Tao Dam",
    "gn:country_code":"TH",
    "gn:dem":13,
    "gn:feature_class":"P",
    "gn:feature_code":"PPL",
    "gn:name":"Ban Nong Tao Dam",
    "gn:population":0,
    "gn:timezone":"Asia/Bangkok",
    "iso:country":"TH",
    "name:tha_x_preferred":[
        "\u0e1a\u0e49\u0e32\u0e19\u0e2b\u0e19\u0e2d\u0e07\u0e40\u0e15\u0e48\u0e32\u0e14\u0e33"
    ],
    "wof:name":"Ban Nong Tao Dam",
    "wof:placetype":"locality"
},
  "geometry": {"coordinates":[99.88043999999999,13.71517],"type":"Point"}
}