{
  "type": "Feature",
  "properties": {
    "gn:admin1_code":"27.0",
    "gn:asciiname":"Ban Map Ueang",
    "gn:country_code":"TH",
    "gn:dem":239,
    "gn:feature_class":"P",
    "gn:feature_code":"PPL",
    "gn:name":"Ban Map Ueang",
    "gn:population":0,
    "gn:timezone":"Asia/Bangkok",
    "iso:country":"TH",
    "name:tha_x_preferred":[
        "\u0e1a\u0e49\u0e32\u0e19\u0e21\u0e32\u0e1a\u0e40\u0e2d\u0e37\u0e49\u0e2d\u0e07"
    ],
    "name:und_x_variant":[
        "Ban Map Uang"
    ],
    "wof:lang_x_official":[
        "tha"
    ],
    "wof:lang_x_spoken":[
        "tha"
    ],
    "wof:name":"Ban Map Ueang",
    "wof:placetype":"locality"
},
  "geometry": {"coordinates":[102.03055999999999,14.90725],"type":"Point"}
}