{
  "type": "Feature",
  "properties": {
    "gn:admin1_code":"75.0",
    "gn:asciiname":"Ban Na Thom Tai",
    "gn:country_code":"TH",
    "gn:dem":140,
    "gn:feature_class":"P",
    "gn:feature_code":"PPL",
    "gn:name":"Ban Na Thom Tai",
    "gn:population":0,
    "gn:timezone":"Asia/Bangkok",
    "iso:country":"TH",
    "name:tha_x_preferred":[
        "\u0e1a\u0e49\u0e32\u0e19\u0e19\u0e32\u0e17\u0e38\u0e48\u0e21\u0e43\u0e15\u0e49"
    ],
    "name:und_x_variant":[
        "Ban Na Thom Yai"
    ],
    "wof:lang_x_official":[
        "tha"
    ],
    "wof:lang_x_spoken":[
        "tha"
    ],
    "wof:name":"Ban Na Thom Tai",
    "wof:placetype":"locality"
},
  "geometry": {"coordinates":[105.18567,15.38944],"type":"Point"}
}