{
  "type": "Feature",
  "properties": {
    "gn:admin1_code":"25.0",
    "gn:asciiname":"Ban Rai Oi Phatthana",
    "gn:country_code":"TH",
    "gn:dem":135,
    "gn:feature_class":"P",
    "gn:feature_code":"PPL",
    "gn:name":"Ban Rai Oi Phatthana",
    "gn:population":0,
    "gn:timezone":"Asia/Bangkok",
    "iso:country":"TH",
    "name:tha_x_preferred":[
        "\u0e1a\u0e49\u0e32\u0e19\u0e44\u0e23\u0e48\u0e2d\u0e49\u0e2d\u0e22\u0e1e\u0e31\u0e12\u0e19\u0e32"
    ],
    "wof:name":"Ban Rai Oi Phatthana",
    "wof:placetype":"locality"
},
  "geometry": {"coordinates":[103.52889,15.49483],"type":"Point"}
}