{
  "type": "Feature",
  "properties": {
    "gn:admin1_code":"14.0",
    "gn:asciiname":"Ban Tha Ko",
    "gn:country_code":"TH",
    "gn:dem":145,
    "gn:feature_class":"P",
    "gn:feature_code":"PPL",
    "gn:name":"Ban Tha Ko",
    "gn:population":0,
    "gn:timezone":"Asia/Bangkok",
    "iso:country":"TH",
    "name:tha_x_preferred":[
        "\u0e1a\u0e49\u0e32\u0e19\u0e17\u0e48\u0e32\u0e42\u0e01"
    ],
    "wof:name":"Ban Tha Ko",
    "wof:placetype":"locality"
},
  "geometry": {"coordinates":[101.25338000000001,16.75122],"type":"Point"}
}