{
  "type": "Feature",
  "properties": {
    "gn:admin1_code":"75.0",
    "gn:asciiname":"Ban Saen Kham",
    "gn:country_code":"TH",
    "gn:dem":147,
    "gn:feature_class":"P",
    "gn:feature_code":"PPL",
    "gn:name":"Ban Saen Kham",
    "gn:population":0,
    "gn:timezone":"Asia/Bangkok",
    "iso:country":"TH",
    "name:tha_x_preferred":[
        "\u0e1a\u0e49\u0e32\u0e19\u0e41\u0e2a\u0e19\u0e04\u0e33"
    ],
    "wof:name":"Ban Saen Kham",
    "wof:placetype":"locality"
},
  "geometry": {"coordinates":[104.91443999999998,14.96358],"type":"Point"}
}