{
  "type": "Feature",
  "properties": {
    "gn:admin1_code":"72.0",
    "gn:asciiname":"Ban Dong Sawan",
    "gn:country_code":"TH",
    "gn:dem":181,
    "gn:feature_class":"P",
    "gn:feature_code":"PPL",
    "gn:name":"Ban Dong Sawan",
    "gn:population":0,
    "gn:timezone":"Asia/Bangkok",
    "iso:country":"TH",
    "name:tha_x_preferred":[
        "\u0e1a\u0e49\u0e32\u0e19\u0e14\u0e07\u0e2a\u0e27\u0e23\u0e23\u0e04\u0e4c"
    ],
    "wof:name":"Ban Dong Sawan",
    "wof:placetype":"locality"
},
  "geometry": {"coordinates":[104.33608,16.13747],"type":"Point"}
}