{
  "type": "Feature",
  "properties": {
    "gn:admin1_code":"60.0",
    "gn:asciiname":"Ban Bang Phlu Thuean",
    "gn:country_code":"TH",
    "gn:dem":57,
    "gn:feature_class":"P",
    "gn:feature_code":"PPL",
    "gn:name":"Ban Bang Phlu Thuean",
    "gn:population":0,
    "gn:timezone":"Asia/Bangkok",
    "iso:country":"TH",
    "name:tha_x_preferred":[
        "\u0e1a\u0e49\u0e32\u0e19\u0e1a\u0e32\u0e07\u0e1e\u0e25\u0e39\u0e40\u0e16\u0e37\u0e48\u0e2d\u0e19"
    ],
    "name:und_x_variant":[
        "Ban Phlu Thuan",
        "Ban Bang Bhlu Thoean",
        "Bang Phlu Thuan",
        "Bang Bhlu Thoean",
        "Ban Bang Phlu Thuan",
        "Ban Bang Phlu Thuean"
    ],
    "wof:name":"Ban Bang Phlu Thuean",
    "wof:placetype":"locality"
},
  "geometry": {"coordinates":[98.75543999999999,8.73986],"type":"Point"}
}