{
  "type": "Feature",
  "properties": {
    "gn:admin1_code":"20.0",
    "gn:asciiname":"Ban Na Mueang Noi",
    "gn:country_code":"TH",
    "gn:dem":174,
    "gn:feature_class":"P",
    "gn:feature_code":"PPL",
    "gn:name":"Ban Na Mueang Noi",
    "gn:population":0,
    "gn:timezone":"Asia/Bangkok",
    "iso:country":"TH",
    "name:tha_x_preferred":[
        "\u0e1a\u0e49\u0e32\u0e19\u0e19\u0e32\u0e40\u0e2b\u0e21\u0e37\u0e2d\u0e07\u0e19\u0e49\u0e2d\u0e22"
    ],
    "wof:name":"Ban Na Mueang Noi",
    "wof:placetype":"locality"
},
  "geometry": {"coordinates":[103.72253000000001,17.37281],"type":"Point"}
}