{
  "type": "Feature",
  "properties": {
    "gn:admin1_code":"68.0",
    "gn:asciiname":"Ban Khao Ram",
    "gn:country_code":"TH",
    "gn:dem":23,
    "gn:feature_class":"P",
    "gn:feature_code":"PPL",
    "gn:name":"Ban Khao Ram",
    "gn:population":0,
    "gn:timezone":"Asia/Bangkok",
    "iso:country":"TH",
    "name:tha_x_preferred":[
        "\u0e1a\u0e49\u0e32\u0e19\u0e40\u0e02\u0e32\u0e23\u0e32\u0e21"
    ],
    "wof:name":"Ban Khao Ram",
    "wof:placetype":"locality"
},
  "geometry": {"coordinates":[100.63424999999999,7.06997],"type":"Point"}
}