{
  "type": "Feature",
  "properties": {
    "gn:admin1_code":"35.0",
    "gn:asciiname":"Ban Bang Ka Phan",
    "gn:country_code":"TH",
    "gn:dem":12,
    "gn:feature_class":"P",
    "gn:feature_code":"PPL",
    "gn:name":"Ban Bang Ka Phan",
    "gn:population":0,
    "gn:timezone":"Asia/Bangkok",
    "iso:country":"TH",
    "name:tha_x_preferred":[
        "\u0e1a\u0e49\u0e32\u0e19\u0e1a\u0e32\u0e07\u0e01\u0e30\u0e1e\u0e31\u0e19"
    ],
    "wof:name":"Ban Bang Ka Phan",
    "wof:placetype":"locality"
},
  "geometry": {"coordinates":[100.35178000000001,14.60617],"type":"Point"}
}