{
  "type": "Feature",
  "properties": {
    "gn:admin1_code":"23.0",
    "gn:asciiname":"Ban Phithak",
    "gn:country_code":"TH",
    "gn:dem":181,
    "gn:feature_class":"P",
    "gn:feature_code":"PPL",
    "gn:name":"Ban Phithak",
    "gn:population":0,
    "gn:timezone":"Asia/Bangkok",
    "iso:country":"TH",
    "name:tha_x_preferred":[
        "\u0e1a\u0e49\u0e32\u0e19\u0e1e\u0e34\u0e17\u0e31\u0e01\u0e29\u0e4c"
    ],
    "wof:name":"Ban Phithak",
    "wof:placetype":"locality"
},
  "geometry": {"coordinates":[103.22931,16.59783],"type":"Point"}
}