{
  "type": "Feature",
  "properties": {
    "gn:admin1_code":"66.0",
    "gn:asciiname":"Ban Khuan NokWa",
    "gn:country_code":"TH",
    "gn:dem":32,
    "gn:feature_class":"P",
    "gn:feature_code":"PPL",
    "gn:name":"Ban Khuan NokWa",
    "gn:population":0,
    "gn:timezone":"Asia/Bangkok",
    "iso:country":"TH",
    "name:tha_x_preferred":[
        "\u0e1a\u0e49\u0e32\u0e19\u0e04\u0e27\u0e19\u0e19\u0e01\u0e2b\u0e27\u0e49\u0e32"
    ],
    "wof:name":"Ban Khuan NokWa",
    "wof:placetype":"locality"
},
  "geometry": {"coordinates":[100.21472,7.2675],"type":"Point"}
}