{
  "type": "Feature",
  "properties": {
    "gn:admin1_code":"2.0",
    "gn:asciiname":"Ban Maeo MaeThoei",
    "gn:country_code":"TH",
    "gn:dem":1154,
    "gn:feature_class":"P",
    "gn:feature_code":"PPL",
    "gn:name":"Ban Maeo MaeThoei",
    "gn:population":0,
    "gn:timezone":"Asia/Bangkok",
    "iso:country":"TH",
    "name:tha_x_preferred":[
        "\u0e1a\u0e49\u0e32\u0e19\u0e41\u0e21\u0e49\u0e27\u0e41\u0e21\u0e48\u0e40\u0e17\u0e22"
    ],
    "wof:name":"Ban Maeo MaeThoei",
    "wof:placetype":"locality"
},
  "geometry": {"coordinates":[98.31645,17.39292],"type":"Point"}
}