{
  "type": "Feature",
  "properties": {
    "gn:admin1_code":"16.0",
    "gn:asciiname":"Ban Kok Kham",
    "gn:country_code":"TH",
    "gn:dem":58,
    "gn:feature_class":"P",
    "gn:feature_code":"PPL",
    "gn:name":"Ban Kok Kham",
    "gn:population":0,
    "gn:timezone":"Asia/Bangkok",
    "iso:country":"TH",
    "name:tha_x_preferred":[
        "\u0e1a\u0e49\u0e32\u0e19\u0e01\u0e01\u0e02\u0e32\u0e21"
    ],
    "wof:name":"Ban Kok Kham",
    "wof:placetype":"locality"
},
  "geometry": {"coordinates":[99.798,15.71978],"type":"Point"}
}