{
  "type": "Feature",
  "properties": {
    "gn:admin1_code":"38.0",
    "gn:asciiname":"Ban Bang Rak Yai",
    "gn:country_code":"TH",
    "gn:dem":6,
    "gn:feature_class":"P",
    "gn:feature_code":"PPL",
    "gn:name":"Ban Bang Rak Yai",
    "gn:population":0,
    "gn:timezone":"Asia/Bangkok",
    "iso:country":"TH",
    "name:tha_x_preferred":[
        "\u0e1a\u0e49\u0e32\u0e19\u0e1a\u0e32\u0e07\u0e23\u0e31\u0e01\u0e43\u0e2b\u0e0d\u0e48"
    ],
    "wof:name":"Ban Bang Rak Yai",
    "wof:placetype":"locality"
},
  "geometry": {"coordinates":[100.44602999999999,13.88336],"type":"Point"}
}