{
  "type": "Feature",
  "properties": {
    "gn:admin1_code":"63.0",
    "gn:asciiname":"Ban Wang Khlong Thai",
    "gn:country_code":"TH",
    "gn:dem":30,
    "gn:feature_class":"P",
    "gn:feature_code":"PPL",
    "gn:name":"Ban Wang Khlong Thai",
    "gn:population":0,
    "gn:timezone":"Asia/Bangkok",
    "iso:country":"TH",
    "name:tha_x_preferred":[
        "\u0e1a\u0e49\u0e32\u0e19\u0e2b\u0e27\u0e48\u0e32\u0e07\u0e04\u0e25\u0e2d\u0e07\u0e44\u0e17\u0e22"
    ],
    "wof:name":"Ban Wang Khlong Thai",
    "wof:placetype":"locality"
},
  "geometry": {"coordinates":[98.97367,8.17642],"type":"Point"}
}