{
  "type": "Feature",
  "properties": {
    "gn:admin1_code":"76.0",
    "gn:asciiname":"Ban Mueang Phan",
    "gn:country_code":"TH",
    "gn:dem":197,
    "gn:feature_class":"P",
    "gn:feature_code":"PPL",
    "gn:name":"Ban Mueang Phan",
    "gn:population":0,
    "gn:timezone":"Asia/Bangkok",
    "iso:country":"TH",
    "name:tha_x_preferred":[
        "\u0e1a\u0e49\u0e32\u0e19\u0e40\u0e21\u0e37\u0e2d\u0e07\u0e1e\u0e32\u0e19"
    ],
    "name:und_x_variant":[
        "Muang Pan",
        "Ban Muang Phan",
        "Ban Mueang Phan"
    ],
    "wof:name":"Ban Mueang Phan",
    "wof:placetype":"locality"
},
  "geometry": {"coordinates":[102.36897,17.68425],"type":"Point"}
}