{
  "type": "Feature",
  "properties": {
    "gn:admin1_code":"64.0",
    "gn:asciiname":"Ban Yuan Lae",
    "gn:country_code":"TH",
    "gn:dem":20,
    "gn:feature_class":"P",
    "gn:feature_code":"PPL",
    "gn:name":"Ban Yuan Lae",
    "gn:population":0,
    "gn:timezone":"Asia/Bangkok",
    "iso:country":"TH",
    "name:tha_x_preferred":[
        "\u0e1a\u0e49\u0e32\u0e19\u0e22\u0e27\u0e19\u0e41\u0e2b\u0e25"
    ],
    "wof:name":"Ban Yuan Lae",
    "wof:placetype":"locality"
},
  "geometry": {"coordinates":[99.90385999999999,8.43225],"type":"Point"}
}