{
  "type": "Feature",
  "properties": {
    "gn:admin1_code":"70.0",
    "gn:asciiname":"Ban Maphrao",
    "gn:country_code":"TH",
    "gn:dem":166,
    "gn:feature_class":"P",
    "gn:feature_code":"PPL",
    "gn:name":"Ban Maphrao",
    "gn:population":0,
    "gn:timezone":"Asia/Bangkok",
    "iso:country":"TH",
    "name:tha_x_preferred":[
        "\u0e1a\u0e49\u0e32\u0e19\u0e21\u0e30\u0e1e\u0e23\u0e49\u0e32\u0e27"
    ],
    "wof:name":"Ban Maphrao",
    "wof:placetype":"locality"
},
  "geometry": {"coordinates":[101.22566999999999,5.97522],"type":"Point"}
}