{
  "type": "Feature",
  "properties": {
    "gn:admin1_code":"27",
    "gn:asciiname":"Ban Nong Manao",
    "gn:country_code":"TH",
    "gn:dem":192,
    "gn:feature_class":"P",
    "gn:feature_code":"PPL",
    "gn:name":"Ban Nong Manao",
    "gn:population":0,
    "gn:timezone":"Asia/Bangkok",
    "iso:country":"TH",
    "name:tha_x_preferred":[
        "\u0e1a\u0e49\u0e32\u0e19\u0e2b\u0e19\u0e2d\u0e07\u0e21\u0e30\u0e19\u0e32\u0e27"
    ],
    "wof:name":"Ban Nong Manao",
    "wof:placetype":"locality"
},
  "geometry": {"coordinates":[102.29680999999999,15.47869],"type":"Point"}
}