{
  "type": "Feature",
  "properties": {
    "gn:admin1_code":"47.0",
    "gn:asciiname":"Ban Khao Samrong",
    "gn:country_code":"TH",
    "gn:dem":30,
    "gn:feature_class":"P",
    "gn:feature_code":"PPL",
    "gn:name":"Ban Khao Samrong",
    "gn:population":0,
    "gn:timezone":"Asia/Bangkok",
    "iso:country":"TH",
    "name:tha_x_preferred":[
        "\u0e1a\u0e49\u0e32\u0e19\u0e40\u0e02\u0e32\u0e2a\u0e33\u0e23\u0e2d\u0e07"
    ],
    "wof:name":"Ban Khao Samrong",
    "wof:placetype":"locality"
},
  "geometry": {"coordinates":[101.81332999999999,12.82917],"type":"Point"}
}