{
  "type": "Feature",
  "properties": {
    "gn:admin1_code":"73.0",
    "gn:asciiname":"Ban Khok Phathai",
    "gn:country_code":"TH",
    "gn:dem":161,
    "gn:feature_class":"P",
    "gn:feature_code":"PPL",
    "gn:name":"Ban Khok Phathai",
    "gn:population":0,
    "gn:timezone":"Asia/Bangkok",
    "iso:country":"TH",
    "name:tha_x_preferred":[
        "\u0e1a\u0e49\u0e32\u0e19\u0e42\u0e04\u0e01\u0e1e\u0e30\u0e18\u0e32\u0e22"
    ],
    "wof:name":"Ban Khok Phathai",
    "wof:placetype":"locality"
},
  "geometry": {"coordinates":[104.21456999999999,17.88278],"type":"Point"}
}