{
  "type": "Feature",
  "properties": {
    "gn:country":"TH",
    "gn:fcode":"ADM3",
    "gn:pop":7015,
    "iso:country":"TH",
    "name:eng_x_preferred":[
        "Sop Moei subdistrict"
    ],
    "name:rus_x_preferred":[
        "\u0421\u043e\u043f-\u041c\u043e\u0438"
    ],
    "name:tha_x_preferred":[
        "\u0e2a\u0e1a\u0e40\u0e21\u0e22"
    ],
    "name:tha_x_variant":[
        "\u0e15\u0e33\u0e1a\u0e25\u0e2a\u0e1a\u0e40\u0e21\u0e22"
    ],
    "name:unk_x_variant":[
        "Sop Moei"
    ],
    "qs:name":"Ban Sop Moei",
    "qs:photos_9r":0,
    "qs:photos_sr":0,
    "qs:pop_sr":"5",
    "wd:wordcount":298,
    "wof:name":"Ban Sop Moei",
    "wof:placetype":"localadmin",
    "wof:population":7015
},
  "geometry": {"coordinates":[97.9311,17.96126],"type":"Point"}
}