{
  "type": "Feature",
  "properties": {
    "gn:admin1_code":"63.0",
    "gn:asciiname":"Tup Kaek Beach",
    "gn:country_code":"TH",
    "gn:dem":14,
    "gn:feature_class":"P",
    "gn:feature_code":"PPL",
    "gn:name":"Tup Kaek Beach",
    "gn:population":0,
    "gn:timezone":"Asia/Bangkok",
    "iso:country":"TH",
    "wof:name":"Tup Kaek Beach",
    "wof:placetype":"locality"
},
  "geometry": {"coordinates":[98.75507,8.12449],"type":"Point"}
}