{
  "type": "Feature",
  "properties": {
    "gn:admin1_code":"80.0",
    "gn:asciiname":"Ban Santisuk",
    "gn:country_code":"TH",
    "gn:dem":92,
    "gn:feature_class":"P",
    "gn:feature_code":"PPL",
    "gn:name":"Ban Santisuk",
    "gn:population":0,
    "gn:timezone":"Asia/Bangkok",
    "iso:country":"TH",
    "name:tha_x_preferred":[
        "\u0e1a\u0e49\u0e32\u0e19\u0e2a\u0e31\u0e19\u0e15\u0e34\u0e2a\u0e38\u0e02"
    ],
    "wof:name":"Ban Santisuk",
    "wof:placetype":"locality"
},
  "geometry": {"coordinates":[102.34397,13.60761],"type":"Point"}
}