{
  "type": "Feature",
  "properties": {
    "gn:admin1_code":"75.0",
    "gn:asciiname":"Ban Na Wa",
    "gn:country_code":"TH",
    "gn:dem":121,
    "gn:feature_class":"P",
    "gn:feature_code":"PPL",
    "gn:name":"Ban Na Wa",
    "gn:population":0,
    "gn:timezone":"Asia/Bangkok",
    "iso:country":"TH",
    "name:tha_x_preferred":[
        "\u0e1a\u0e49\u0e32\u0e19\u0e19\u0e32\u0e2b\u0e27\u0e49\u0e32"
    ],
    "name:und_x_variant":[
        "Nao",
        "Ban Na Wa"
    ],
    "wof:name":"Ban Na Wa",
    "wof:placetype":"locality"
},
  "geometry": {"coordinates":[105.23847000000001,15.29981],"type":"Point"}
}