{
  "type": "Feature",
  "properties": {
    "gn:admin1_code":"10.0",
    "gn:asciiname":"Ban Nong Chik",
    "gn:country_code":"TH",
    "gn:dem":74,
    "gn:feature_class":"P",
    "gn:feature_code":"PPL",
    "gn:name":"Ban Nong Chik",
    "gn:population":0,
    "gn:timezone":"Asia/Bangkok",
    "iso:country":"TH",
    "name:tha_x_preferred":[
        "Ban Nong Chik"
    ],
    "name:tha_x_variant":[
        "\u0e1a\u0e49\u0e32\u0e19\u0e2b\u0e19\u0e2d\u0e07\u0e08\u0e34\u0e01"
    ],
    "wof:name":"Ban Nong Chik",
    "wof:placetype":"locality"
},
  "geometry": {"coordinates":[100.22275,17.65558],"type":"Point"}
}