{
  "type": "Feature",
  "properties": {
    "gn:admin1_code":"8.0",
    "gn:asciiname":"Ban Loe Toe",
    "gn:country_code":"TH",
    "gn:dem":828,
    "gn:feature_class":"P",
    "gn:feature_code":"PPL",
    "gn:name":"Ban Loe Toe",
    "gn:population":0,
    "gn:timezone":"Asia/Bangkok",
    "iso:country":"TH",
    "name:tha_x_preferred":[
        "\u0e1a\u0e49\u0e32\u0e19\u0e40\u0e25\u0e2d\u0e40\u0e15\u0e2d"
    ],
    "wof:name":"Ban Loe Toe",
    "wof:placetype":"locality"
},
  "geometry": {"coordinates":[98.48417999999999,17.19755],"type":"Point"}
}