{
  "type": "Feature",
  "properties": {
    "gn:admin1_code":"30.0",
    "gn:asciiname":"Ban Ta Set",
    "gn:country_code":"TH",
    "gn:dem":181,
    "gn:feature_class":"P",
    "gn:feature_code":"PPL",
    "gn:name":"Ban Ta Set",
    "gn:population":0,
    "gn:timezone":"Asia/Bangkok",
    "iso:country":"TH",
    "name:tha_x_preferred":[
        "\u0e1a\u0e49\u0e32\u0e19\u0e15\u0e32\u0e40\u0e2a\u0e47\u0e14"
    ],
    "name:und_x_variant":[
        "Tra Set",
        "Ban Prasaet",
        "Ban Ta Set"
    ],
    "wof:name":"Ban Ta Set",
    "wof:placetype":"locality"
},
  "geometry": {"coordinates":[104.45631,14.55158],"type":"Point"}
}