{
  "type": "Feature",
  "properties": {
    "gn:admin1_code":"47.0",
    "gn:asciiname":"Ban Chak Mak",
    "gn:country_code":"TH",
    "gn:dem":66,
    "gn:feature_class":"P",
    "gn:feature_code":"PPL",
    "gn:name":"Ban Chak Mak",
    "gn:population":0,
    "gn:timezone":"Asia/Bangkok",
    "iso:country":"TH",
    "name:tha_x_preferred":[
        "\u0e1a\u0e49\u0e32\u0e19\u0e0a\u0e32\u0e01\u0e2b\u0e21\u0e32\u0e01"
    ],
    "wof:name":"Ban Chak Mak",
    "wof:placetype":"locality"
},
  "geometry": {"coordinates":[101.03361,12.79667],"type":"Point"}
}