{
  "type": "Feature",
  "properties": {
    "gn:admin1_code":"50.0",
    "gn:asciiname":"Ban Thung Yot Kaeo",
    "gn:country_code":"TH",
    "gn:dem":73,
    "gn:feature_class":"P",
    "gn:feature_code":"PPL",
    "gn:name":"Ban Thung Yot Kaeo",
    "gn:population":0,
    "gn:timezone":"Asia/Bangkok",
    "iso:country":"TH",
    "wof:name":"Ban Thung Yot Kaeo",
    "wof:placetype":"locality"
},
  "geometry": {"coordinates":[99.52556,14.24389],"type":"Point"}
}