{
  "type": "Feature",
  "properties": {
    "gn:admin1_code":"34",
    "gn:asciiname":"Ban Chon Ruam",
    "gn:country_code":"TH",
    "gn:dem":37,
    "gn:feature_class":"P",
    "gn:feature_code":"PPL",
    "gn:name":"Ban Chon Ruam",
    "gn:population":0,
    "gn:timezone":"Asia/Bangkok",
    "iso:country":"TH",
    "name:tha_x_preferred":[
        "\u0e1a\u0e49\u0e32\u0e19\u0e0a\u0e2d\u0e19\u0e23\u0e48\u0e27\u0e21"
    ],
    "wof:name":"Ban Chon Ruam",
    "wof:placetype":"locality"
},
  "geometry": {"coordinates":[100.76828,15.14564],"type":"Point"}
}