{
  "type": "Feature",
  "properties": {
    "gn:admin1_code":"74.0",
    "gn:asciiname":"Ban Ko Yai Nak",
    "gn:country_code":"TH",
    "gn:dem":13,
    "gn:feature_class":"P",
    "gn:feature_code":"PPL",
    "gn:name":"Ban Ko Yai Nak",
    "gn:population":0,
    "gn:timezone":"Asia/Bangkok",
    "iso:country":"TH",
    "name:tha_x_preferred":[
        "\u0e1a\u0e49\u0e32\u0e19\u0e40\u0e01\u0e32\u0e30\u0e22\u0e32\u0e22\u0e2b\u0e19\u0e31\u0e01"
    ],
    "wof:name":"Ban Ko Yai Nak",
    "wof:placetype":"locality"
},
  "geometry": {"coordinates":[101.52933,14.10447],"type":"Point"}
}