{
  "type": "Feature",
  "properties": {
    "gn:admin1_code":"13.0",
    "gn:asciiname":"Ban Wang Hu Thip",
    "gn:country_code":"TH",
    "gn:dem":42,
    "gn:feature_class":"P",
    "gn:feature_code":"PPL",
    "gn:name":"Ban Wang Hu Thip",
    "gn:population":0,
    "gn:timezone":"Asia/Bangkok",
    "iso:country":"TH",
    "name:tha_x_preferred":[
        "\u0e1a\u0e49\u0e32\u0e19\u0e27\u0e31\u0e07\u0e2b\u0e39\u0e17\u0e34\u0e1e\u0e22\u0e4c"
    ],
    "name:und_x_variant":[
        "Ban Wang Khun Thip"
    ],
    "wof:name":"Ban Wang Hu Thip",
    "wof:placetype":"locality"
},
  "geometry": {"coordinates":[100.38133000000001,16.27453],"type":"Point"}
}