{
  "type": "Feature",
  "properties": {
    "gn:admin1_code":"81.0",
    "gn:asciiname":"Ban Don Yom",
    "gn:country_code":"TH",
    "gn:dem":164,
    "gn:feature_class":"P",
    "gn:feature_code":"PPL",
    "gn:name":"Ban Don Yom",
    "gn:population":0,
    "gn:timezone":"Asia/Bangkok",
    "iso:country":"TH",
    "name:tha_x_preferred":[
        "\u0e1a\u0e49\u0e32\u0e19\u0e14\u0e2d\u0e19\u0e22\u0e21"
    ],
    "name:und_x_variant":[
        "Ban Don"
    ],
    "wof:name":"Ban Don Yom",
    "wof:placetype":"locality"
},
  "geometry": {"coordinates":[103.55822000000001,18.40294],"type":"Point"}
}