{
  "type": "Feature",
  "properties": {
    "gn:admin1_code":"25.0",
    "gn:asciiname":"Ban Mueang Noi",
    "gn:country_code":"TH",
    "gn:dem":145,
    "gn:feature_class":"P",
    "gn:feature_code":"PPL",
    "gn:name":"Ban Mueang Noi",
    "gn:population":0,
    "gn:timezone":"Asia/Bangkok",
    "iso:country":"TH",
    "name:tha_x_preferred":[
        "\u0e1a\u0e49\u0e32\u0e19\u0e40\u0e21\u0e37\u0e2d\u0e07\u0e19\u0e49\u0e2d\u0e22"
    ],
    "name:und_x_variant":[
        "Ban Muang Noi"
    ],
    "wof:name":"Ban Mueang Noi",
    "wof:placetype":"locality"
},
  "geometry": {"coordinates":[103.77211,15.97539],"type":"Point"}
}