{
  "type": "Feature",
  "properties": {
    "gn:admin1_code":"37",
    "gn:asciiname":"Ban Nong Mai Liam",
    "gn:country_code":"TH",
    "gn:dem":23,
    "gn:feature_class":"P",
    "gn:feature_code":"PPL",
    "gn:name":"Ban Nong Mai Liam",
    "gn:population":0,
    "gn:timezone":"Asia/Bangkok",
    "iso:country":"TH",
    "name:tha_x_preferred":[
        "\u0e1a\u0e49\u0e32\u0e19\u0e2b\u0e19\u0e2d\u0e07\u0e44\u0e21\u0e49\u0e40\u0e2b\u0e25\u0e35\u0e49\u0e22\u0e21"
    ],
    "wof:name":"Ban Nong Mai Liam",
    "wof:placetype":"locality"
},
  "geometry": {"coordinates":[100.85719,14.61128],"type":"Point"}
}