{
  "type": "Feature",
  "properties": {
    "gn:admin1_code":"76.0",
    "gn:asciiname":"Ban Nam Song",
    "gn:country_code":"TH",
    "gn:dem":229,
    "gn:feature_class":"P",
    "gn:feature_code":"PPL",
    "gn:name":"Ban Nam Song",
    "gn:population":0,
    "gn:timezone":"Asia/Bangkok",
    "iso:country":"TH",
    "name:und_x_variant":[
        "\u0e1a\u0e49\u0e32\u0e19\u0e19\u0e49\u0e33\u0e17\u0e23\u0e07"
    ],
    "wof:name":"Ban Nam Song",
    "wof:placetype":"locality"
},
  "geometry": {"coordinates":[102.14507999999999,17.76306],"type":"Point"}
}