{
  "type": "Feature",
  "properties": {
    "gn:admin1_code":"65.0",
    "gn:asciiname":"Ban Khuan Rakam",
    "gn:country_code":"TH",
    "gn:dem":58,
    "gn:feature_class":"P",
    "gn:feature_code":"PPL",
    "gn:name":"Ban Khuan Rakam",
    "gn:population":0,
    "gn:timezone":"Asia/Bangkok",
    "iso:country":"TH",
    "name:tha_x_preferred":[
        "\u0e1a\u0e49\u0e32\u0e19\u0e04\u0e27\u0e19\u0e23\u0e30\u0e01\u0e33"
    ],
    "wof:name":"Ban Khuan Rakam",
    "wof:placetype":"locality"
},
  "geometry": {"coordinates":[99.67283,7.98139],"type":"Point"}
}