{
  "type": "Feature",
  "properties": {
    "gn:admin1_code":"25.0",
    "gn:asciiname":"Ban Khilek",
    "gn:country_code":"TH",
    "gn:dem":136,
    "gn:feature_class":"P",
    "gn:feature_code":"PPL",
    "gn:name":"Ban Khilek",
    "gn:population":0,
    "gn:timezone":"Asia/Bangkok",
    "iso:country":"TH",
    "name:tha_x_preferred":[
        "\u0e1a\u0e49\u0e32\u0e19\u0e02\u0e35\u0e49\u0e40\u0e2b\u0e25\u0e47\u0e01"
    ],
    "name:und_x_variant":[
        "Ban Khi",
        "Ban Khi Lek",
        "Ban Khilek"
    ],
    "wof:name":"Ban Khilek",
    "wof:placetype":"locality"
},
  "geometry": {"coordinates":[103.99525,16.00907999999999],"type":"Point"}
}