{
  "type": "Feature",
  "properties": {
    "gn:admin1_code":"44.0",
    "gn:asciiname":"Ban Ton Krabok",
    "gn:country_code":"TH",
    "gn:dem":7,
    "gn:feature_class":"P",
    "gn:feature_code":"PPL",
    "gn:name":"Ban Ton Krabok",
    "gn:population":0,
    "gn:timezone":"Asia/Bangkok",
    "iso:country":"TH",
    "name:tha_x_preferred":[
        "\u0e1a\u0e49\u0e32\u0e19\u0e15\u0e49\u0e19\u0e01\u0e23\u0e30\u0e1a\u0e01"
    ],
    "wof:name":"Ban Ton Krabok",
    "wof:placetype":"locality"
},
  "geometry": {"coordinates":[101.34603,13.73361],"type":"Point"}
}