{
  "type": "Feature",
  "properties": {
    "gn:admin1_code":"18.0",
    "gn:asciiname":"Ban Na Noi",
    "gn:country_code":"TH",
    "gn:dem":722,
    "gn:feature_class":"P",
    "gn:feature_code":"PPL",
    "gn:name":"Ban Na Noi",
    "gn:population":0,
    "gn:timezone":"Asia/Bangkok",
    "iso:country":"TH",
    "name:tha_x_preferred":[
        "Ban Na Noi"
    ],
    "name:tha_x_variant":[
        "\u0e1a\u0e49\u0e32\u0e19\u0e19\u0e32\u0e19\u0e49\u0e2d\u0e22"
    ],
    "wof:name":"Ban Na Noi",
    "wof:placetype":"locality"
},
  "geometry": {"coordinates":[101.49091,17.38025],"type":"Point"}
}