{
  "type": "Feature",
  "properties": {
    "gn:admin1_code":"70.0",
    "gn:asciiname":"Ban U Yong Su Ngae",
    "gn:country_code":"TH",
    "gn:dem":95,
    "gn:feature_class":"P",
    "gn:feature_code":"PPL",
    "gn:name":"Ban U Yong Su Ngae",
    "gn:population":0,
    "gn:timezone":"Asia/Bangkok",
    "iso:country":"TH",
    "name:tha_x_preferred":[
        "\u0e1a\u0e49\u0e32\u0e19\u0e2d\u0e38\u0e22\u0e07\u0e0b\u0e39\u0e41\u0e07"
    ],
    "wof:name":"Ban U Yong Su Ngae",
    "wof:placetype":"locality"
},
  "geometry": {"coordinates":[101.09041999999999,6.39911],"type":"Point"}
}