{
  "type": "Feature",
  "properties": {
    "gn:admin1_code":"17.0",
    "gn:asciiname":"Ban Dong Lao",
    "gn:country_code":"TH",
    "gn:dem":166,
    "gn:feature_class":"P",
    "gn:feature_code":"PPL",
    "gn:name":"Ban Dong Lao",
    "gn:population":0,
    "gn:timezone":"Asia/Bangkok",
    "iso:country":"TH",
    "name:tha_x_preferred":[
        "\u0e1a\u0e49\u0e32\u0e19\u0e14\u0e07\u0e40\u0e25\u0e49\u0e32"
    ],
    "wof:name":"Ban Dong Lao",
    "wof:placetype":"locality"
},
  "geometry": {"coordinates":[103.23642,18.26353],"type":"Point"}
}