{
  "type": "Feature",
  "properties": {
    "gn:admin1_code":"18.0",
    "gn:asciiname":"Ban Saeng Arun",
    "gn:country_code":"TH",
    "gn:dem":314,
    "gn:feature_class":"P",
    "gn:feature_code":"PPL",
    "gn:name":"Ban Saeng Arun",
    "gn:population":0,
    "gn:timezone":"Asia/Bangkok",
    "iso:country":"TH",
    "name:tha_x_preferred":[
        "Ban Saeng Arun"
    ],
    "name:tha_x_variant":[
        "\u0e1a\u0e49\u0e32\u0e19\u0e41\u0e2a\u0e07\u0e2d\u0e23\u0e38\u0e13"
    ],
    "wof:name":"Ban Saeng Arun",
    "wof:placetype":"locality"
},
  "geometry": {"coordinates":[101.99274,17.48612],"type":"Point"}
}