{
  "type": "Feature",
  "properties": {
    "gn:admin1_code":"73.0",
    "gn:asciiname":"Ban Tha Phan Hong",
    "gn:country_code":"TH",
    "gn:dem":163,
    "gn:feature_class":"P",
    "gn:feature_code":"PPL",
    "gn:name":"Ban Tha Phan Hong",
    "gn:population":0,
    "gn:timezone":"Asia/Bangkok",
    "iso:country":"TH",
    "name:tha_x_preferred":[
        "\u0e1a\u0e49\u0e32\u0e19\u0e17\u0e48\u0e32\u0e1e\u0e31\u0e19\u0e42\u0e2e\u0e07"
    ],
    "wof:lang_x_official":[
        "tha"
    ],
    "wof:lang_x_spoken":[
        "tha"
    ],
    "wof:name":"Ban Tha Phan Hong",
    "wof:placetype":"locality"
},
  "geometry": {"coordinates":[104.0248,17.81103],"type":"Point"}
}