{
  "type": "Feature",
  "properties": {
    "gn:admin1_code":"29.0",
    "gn:asciiname":"Ban Nikhom Song",
    "gn:country_code":"TH",
    "gn:dem":195,
    "gn:feature_class":"P",
    "gn:feature_code":"PPL",
    "gn:name":"Ban Nikhom Song",
    "gn:population":0,
    "gn:timezone":"Asia/Bangkok",
    "iso:country":"TH",
    "name:tha_x_preferred":[
        "\u0e1a\u0e49\u0e32\u0e19\u0e19\u0e34\u0e04\u0e21 \u0e2a\u0e2d\u0e07"
    ],
    "wof:name":"Ban Nikhom Song",
    "wof:placetype":"locality"
},
  "geometry": {"coordinates":[103.39022,14.47167],"type":"Point"}
}