{
  "type": "Feature",
  "properties": {
    "gn:admin1_code":"68.0",
    "gn:asciiname":"Ban Sa Muen Saen",
    "gn:country_code":"TH",
    "gn:dem":3,
    "gn:feature_class":"P",
    "gn:feature_code":"PPL",
    "gn:name":"Ban Sa Muen Saen",
    "gn:population":0,
    "gn:timezone":"Asia/Bangkok",
    "iso:country":"TH",
    "name:tha_x_preferred":[
        "\u0e1a\u0e49\u0e32\u0e19\u0e2a\u0e23\u0e30\u0e2b\u0e21\u0e37\u0e48\u0e19\u0e41\u0e2a\u0e19"
    ],
    "name:und_x_variant":[
        "Ban Sa Mun Saen"
    ],
    "wof:lang_x_official":[
        "tha"
    ],
    "wof:lang_x_spoken":[
        "tha"
    ],
    "wof:name":"Ban Sa Muen Saen",
    "wof:placetype":"locality"
},
  "geometry": {"coordinates":[100.29246999999999,7.82797],"type":"Point"}
}