{
  "type": "Feature",
  "properties": {
    "gn:admin1_code":"60.0",
    "gn:asciiname":"Ban Laem So",
    "gn:country_code":"TH",
    "gn:dem":9,
    "gn:feature_class":"P",
    "gn:feature_code":"PPL",
    "gn:name":"Ban Laem So",
    "gn:population":0,
    "gn:timezone":"Asia/Bangkok",
    "iso:country":"TH",
    "name:tha_x_preferred":[
        "\u0e1a\u0e49\u0e32\u0e19\u0e41\u0e2b\u0e25\u0e21\u0e2a\u0e2d"
    ],
    "name:und_x_variant":[
        "Ban Hua Laem Ma So"
    ],
    "wof:name":"Ban Laem So",
    "wof:placetype":"locality"
},
  "geometry": {"coordinates":[99.96639,9.417],"type":"Point"}
}