{
  "type": "Feature",
  "properties": {
    "gn:admin1_code":"1.0",
    "gn:asciiname":"Ban Nam Rin",
    "gn:country_code":"TH",
    "gn:dem":871,
    "gn:feature_class":"P",
    "gn:feature_code":"PPL",
    "gn:name":"Ban Nam Rin",
    "gn:population":0,
    "gn:timezone":"Asia/Bangkok",
    "iso:country":"TH",
    "name:tha_x_preferred":[
        "\u0e1a\u0e49\u0e32\u0e19\u0e19\u0e49\u0e33\u0e23\u0e34\u0e19"
    ],
    "wof:name":"Ban Nam Rin",
    "wof:placetype":"locality"
},
  "geometry": {"coordinates":[98.29567,19.46244],"type":"Point"}
}