{
  "type": "Feature",
  "properties": {
    "gn:admin1_code":"25.0",
    "gn:asciiname":"Ban Samran",
    "gn:country_code":"TH",
    "gn:dem":134,
    "gn:feature_class":"P",
    "gn:feature_code":"PPL",
    "gn:name":"Ban Samran",
    "gn:population":0,
    "gn:timezone":"Asia/Bangkok",
    "iso:country":"TH",
    "name:tha_x_preferred":[
        "\u0e1a\u0e49\u0e32\u0e19\u0e2a\u0e33\u0e23\u0e32\u0e0d"
    ],
    "wof:name":"Ban Samran",
    "wof:placetype":"locality"
},
  "geometry": {"coordinates":[103.54956,15.60794],"type":"Point"}
}