{
  "type": "Feature",
  "properties": {
    "gn:admin1_code":"39.0",
    "gn:asciiname":"Muban Song Fang Khlong",
    "gn:country_code":"TH",
    "gn:dem":3,
    "gn:feature_class":"P",
    "gn:feature_code":"PPL",
    "gn:name":"Muban Song Fang Khlong",
    "gn:population":0,
    "gn:timezone":"Asia/Bangkok",
    "iso:country":"TH",
    "name:tha_x_preferred":[
        "\u0e2b\u0e21\u0e39\u0e48\u0e1a\u0e49\u0e32\u0e19\u0e2a\u0e2d\u0e07\u0e1d\u0e31\u0e48\u0e07\u0e04\u0e25\u0e2d\u0e07"
    ],
    "wof:name":"Muban Song Fang Khlong",
    "wof:placetype":"locality"
},
  "geometry": {"coordinates":[100.38283,13.99175],"type":"Point"}
}