{
  "type": "Feature",
  "properties": {
    "gn:admin1_code":"48.0",
    "gn:asciiname":"Ban Pong Nam Ron",
    "gn:country_code":"TH",
    "gn:dem":170,
    "gn:feature_class":"P",
    "gn:feature_code":"PPL",
    "gn:name":"Ban Pong Nam Ron",
    "gn:population":0,
    "gn:timezone":"Asia/Bangkok",
    "iso:country":"TH",
    "name:tha_x_preferred":[
        "\u0e1a\u0e49\u0e32\u0e19\u0e42\u0e1b\u0e48\u0e07\u0e19\u0e49\u0e33\u0e23\u0e49\u0e2d\u0e19"
    ],
    "wof:name":"Ban Pong Nam Ron",
    "wof:placetype":"locality"
},
  "geometry": {"coordinates":[102.37353,12.92044],"type":"Point"}
}