{
  "type": "Feature",
  "properties": {
    "gn:admin1_code":"50.0",
    "gn:asciiname":"Ban Don Makluea",
    "gn:country_code":"TH",
    "gn:dem":16,
    "gn:feature_class":"P",
    "gn:feature_code":"PPL",
    "gn:name":"Ban Don Makluea",
    "gn:population":0,
    "gn:timezone":"Asia/Bangkok",
    "iso:country":"TH",
    "name:tha_x_preferred":[
        "\u0e1a\u0e49\u0e32\u0e19\u0e14\u0e2d\u0e19\u0e21\u0e30\u0e40\u0e01\u0e25\u0e37\u0e2d"
    ],
    "wof:name":"Ban Don Makluea",
    "wof:placetype":"locality"
},
  "geometry": {"coordinates":[99.80783,13.84561],"type":"Point"}
}