{
  "type": "Feature",
  "properties": {
    "gn:admin1_code":"25.0",
    "gn:asciiname":"Ban Noi Hua Fai",
    "gn:country_code":"TH",
    "gn:dem":153,
    "gn:feature_class":"P",
    "gn:feature_code":"PPL",
    "gn:name":"Ban Noi Hua Fai",
    "gn:population":0,
    "gn:timezone":"Asia/Bangkok",
    "iso:country":"TH",
    "name:tha_x_preferred":[
        "\u0e1a\u0e49\u0e32\u0e19\u0e19\u0e49\u0e2d\u0e22\u0e2b\u0e31\u0e27\u0e1d\u0e32\u0e22"
    ],
    "wof:name":"Ban Noi Hua Fai",
    "wof:placetype":"locality"
},
  "geometry": {"coordinates":[103.64281,16.02611],"type":"Point"}
}