{
  "type": "Feature",
  "properties": {
    "gn:admin1_code":"4.0",
    "gn:asciiname":"Ban Huai Pa",
    "gn:country_code":"TH",
    "gn:dem":273,
    "gn:feature_class":"P",
    "gn:feature_code":"PPL",
    "gn:name":"Ban Huai Pa",
    "gn:population":0,
    "gn:timezone":"Asia/Bangkok",
    "iso:country":"TH",
    "name:tha_x_preferred":[
        "\u0e1a\u0e49\u0e32\u0e19\u0e2b\u0e49\u0e27\u0e22\u0e1b\u0e32"
    ],
    "name:und_x_variant":[
        "Ban P\u0101k Bau",
        "Ban Pak Bo",
        "Ban Huai Pa (1)",
        "Ban Huai Pa"
    ],
    "wof:lang_x_official":[
        "tha"
    ],
    "wof:lang_x_spoken":[
        "tha"
    ],
    "wof:name":"Ban Huai Pa",
    "wof:placetype":"locality"
},
  "geometry": {"coordinates":[100.93133,18.92103],"type":"Point"}
}