{
  "type": "Feature",
  "properties": {
    "gn:admin1_code":"20.0",
    "gn:asciiname":"Ban Non Khok Wua",
    "gn:country_code":"TH",
    "gn:dem":295,
    "gn:feature_class":"P",
    "gn:feature_code":"PPL",
    "gn:name":"Ban Non Khok Wua",
    "gn:population":0,
    "gn:timezone":"Asia/Bangkok",
    "iso:country":"TH",
    "name:tha_x_preferred":[
        "\u0e1a\u0e49\u0e32\u0e19\u0e42\u0e19\u0e19\u0e04\u0e2d\u0e01\u0e27\u0e31\u0e27"
    ],
    "wof:name":"Ban Non Khok Wua",
    "wof:placetype":"locality"
},
  "geometry": {"coordinates":[103.95178,16.96697],"type":"Point"}
}