{
  "type": "Feature",
  "properties": {
    "gn:admin1_code":"22.0",
    "gn:asciiname":"Ban Nong Ru Khae",
    "gn:country_code":"TH",
    "gn:dem":185,
    "gn:feature_class":"P",
    "gn:feature_code":"PPL",
    "gn:name":"Ban Nong Ru Khae",
    "gn:population":0,
    "gn:timezone":"Asia/Bangkok",
    "iso:country":"TH",
    "name:tha_x_preferred":[
        "\u0e1a\u0e49\u0e32\u0e19\u0e2b\u0e19\u0e2d\u0e07\u0e23\u0e39\u0e41\u0e02\u0e49"
    ],
    "name:und_x_variant":[
        "Hu Khae",
        "Ban Hu Khae",
        "Ban Nong Ru Khae"
    ],
    "wof:name":"Ban Nong Ru Khae",
    "wof:placetype":"locality"
},
  "geometry": {"coordinates":[102.80347,16.13572000000001],"type":"Point"}
}