{
  "type": "Feature",
  "properties": {
    "gn:admin1_code":"70.0",
    "gn:asciiname":"Ban Than Mali",
    "gn:country_code":"TH",
    "gn:dem":235,
    "gn:feature_class":"P",
    "gn:feature_code":"PPL",
    "gn:name":"Ban Than Mali",
    "gn:population":0,
    "gn:timezone":"Asia/Bangkok",
    "iso:country":"TH",
    "name:tha_x_preferred":[
        "\u0e1a\u0e49\u0e32\u0e19\u0e18\u0e32\u0e23\u0e21\u0e30\u0e25\u0e34"
    ],
    "wof:name":"Ban Than Mali",
    "wof:placetype":"locality"
},
  "geometry": {"coordinates":[101.17628000000001,6.00647],"type":"Point"}
}