{
  "type": "Feature",
  "properties": {
    "gn:admin1_code":"58.0",
    "gn:asciiname":"Ban Pak Nam Chumphon",
    "gn:country_code":"TH",
    "gn:dem":6,
    "gn:feature_class":"P",
    "gn:feature_code":"PPL",
    "gn:name":"Ban Pak Nam Chumphon",
    "gn:population":0,
    "gn:timezone":"Asia/Bangkok",
    "iso:country":"TH",
    "name:und_x_variant":[
        "P\u0101k Nam",
        "Ban Pak Nam",
        "Pak Nam Tako",
        "Ban Pak Nam Chumphon"
    ],
    "wof:name":"Ban Pak Nam Chumphon",
    "wof:placetype":"locality"
},
  "geometry": {"coordinates":[99.24627,10.43561],"type":"Point"}
}