{
  "type": "Feature",
  "properties": {
    "gn:admin1_code":"56.0",
    "gn:asciiname":"Ban Huai Sat Yai",
    "gn:country_code":"TH",
    "gn:dem":169,
    "gn:feature_class":"P",
    "gn:feature_code":"PPL",
    "gn:name":"Ban Huai Sat Yai",
    "gn:population":0,
    "gn:timezone":"Asia/Bangkok",
    "iso:country":"TH",
    "name:tha_x_preferred":[
        "\u0e1a\u0e49\u0e32\u0e19\u0e2b\u0e49\u0e27\u0e22\u0e2a\u0e31\u0e15\u0e27\u0e4c\u0e43\u0e2b\u0e0d\u0e48"
    ],
    "wof:lang_x_official":[
        "tha"
    ],
    "wof:lang_x_spoken":[
        "tha"
    ],
    "wof:name":"Ban Huai Sat Yai",
    "wof:placetype":"locality"
},
  "geometry": {"coordinates":[99.52975000000001,12.64222],"type":"Point"}
}