{
  "type": "Feature",
  "properties": {
    "gn:admin1_code":"70.0",
    "gn:asciiname":"Ban Pu Ta",
    "gn:country_code":"TH",
    "gn:dem":42,
    "gn:feature_class":"P",
    "gn:feature_code":"PPL",
    "gn:name":"Ban Pu Ta",
    "gn:population":0,
    "gn:timezone":"Asia/Bangkok",
    "iso:country":"TH",
    "name:tha_x_preferred":[
        "\u0e1a\u0e49\u0e32\u0e19\u0e1b\u0e39\u0e15\u0e4a\u0e30"
    ],
    "wof:name":"Ban Pu Ta",
    "wof:placetype":"locality"
},
  "geometry": {"coordinates":[101.37058,6.43803],"type":"Point"}
}