{
  "type": "Feature",
  "properties": {
    "gn:admin1_code":"37",
    "gn:asciiname":"Ban Ang Hin",
    "gn:country_code":"TH",
    "gn:dem":234,
    "gn:feature_class":"P",
    "gn:feature_code":"PPL",
    "gn:name":"Ban Ang Hin",
    "gn:population":0,
    "gn:timezone":"Asia/Bangkok",
    "iso:country":"TH",
    "name:tha_x_preferred":[
        "\u0e1a\u0e49\u0e32\u0e19\u0e2d\u0e48\u0e32\u0e07\u0e2b\u0e34\u0e19"
    ],
    "wof:name":"Ban Ang Hin",
    "wof:placetype":"locality"
},
  "geometry": {"coordinates":[101.18208,14.66494],"type":"Point"}
}