{
  "type": "Feature",
  "properties": {
    "gn:admin1_code":"38.0",
    "gn:asciiname":"Muban Nio Woen",
    "gn:country_code":"TH",
    "gn:dem":4,
    "gn:feature_class":"P",
    "gn:feature_code":"PPL",
    "gn:name":"Muban Nio Woen",
    "gn:population":0,
    "gn:timezone":"Asia/Bangkok",
    "iso:country":"TH",
    "name:tha_x_preferred":[
        "\u0e2b\u0e21\u0e39\u0e48\u0e1a\u0e49\u0e32\u0e19\u0e19\u0e34\u0e27\u0e40\u0e27\u0e34\u0e25\u0e14\u0e4c"
    ],
    "wof:name":"Muban Nio Woen",
    "wof:placetype":"locality"
},
  "geometry": {"coordinates":[100.41175,13.95497],"type":"Point"}
}