{
  "type": "Feature",
  "properties": {
    "gn:admin1_code":"24",
    "gn:asciiname":"Ban Nong Siri Rat",
    "gn:country_code":"TH",
    "gn:dem":178,
    "gn:feature_class":"P",
    "gn:feature_code":"PPL",
    "gn:name":"Ban Nong Siri Rat",
    "gn:population":0,
    "gn:timezone":"Asia/Bangkok",
    "iso:country":"TH",
    "name:tha_x_preferred":[
        "\u0e1a\u0e49\u0e32\u0e19\u0e2b\u0e19\u0e2d\u0e07\u0e28\u0e34\u0e23\u0e34\u0e23\u0e32\u0e29\u0e0e\u0e23\u0e4c"
    ],
    "wof:name":"Ban Nong Siri Rat",
    "wof:placetype":"locality"
},
  "geometry": {"coordinates":[103.10272000000001,16.43117],"type":"Point"}
}