{
  "type": "Feature",
  "properties": {
    "gn:admin1_code":"76.0",
    "gn:asciiname":"Ban Khok Klang Tai",
    "gn:country_code":"TH",
    "gn:dem":209,
    "gn:feature_class":"P",
    "gn:feature_code":"PPL",
    "gn:name":"Ban Khok Klang Tai",
    "gn:population":0,
    "gn:timezone":"Asia/Bangkok",
    "iso:country":"TH",
    "name:tha_x_preferred":[
        "\u0e1a\u0e49\u0e32\u0e19\u0e42\u0e04\u0e01\u0e01\u0e25\u0e32\u0e07\u0e43\u0e15\u0e49"
    ],
    "wof:name":"Ban Khok Klang Tai",
    "wof:placetype":"locality"
},
  "geometry": {"coordinates":[103.25029000000001,17.53231],"type":"Point"}
}