{
  "type": "Feature",
  "properties": {
    "gn:admin1_code":"26.0",
    "gn:asciiname":"Ban Nong Ko Thong",
    "gn:country_code":"TH",
    "gn:dem":285,
    "gn:feature_class":"P",
    "gn:feature_code":"PPL",
    "gn:name":"Ban Nong Ko Thong",
    "gn:population":0,
    "gn:timezone":"Asia/Bangkok",
    "iso:country":"TH",
    "name:tha_x_preferred":[
        "\u0e1a\u0e49\u0e32\u0e19\u0e2b\u0e19\u0e2d\u0e07\u0e42\u0e01\u0e17\u0e2d\u0e07"
    ],
    "wof:name":"Ban Nong Ko Thong",
    "wof:placetype":"locality"
},
  "geometry": {"coordinates":[101.42061,15.88306],"type":"Point"}
}