{
  "type": "Feature",
  "properties": {
    "gn:admin1_code":"42.0",
    "gn:asciiname":"Ban Thap Yao",
    "gn:country_code":"TH",
    "gn:dem":2,
    "gn:feature_class":"P",
    "gn:feature_code":"PPL",
    "gn:name":"Ban Thap Yao",
    "gn:population":0,
    "gn:timezone":"Asia/Bangkok",
    "iso:country":"TH",
    "name:tha_x_preferred":[
        "\u0e1a\u0e49\u0e32\u0e19\u0e17\u0e31\u0e1a\u0e22\u0e32\u0e27"
    ],
    "wof:name":"Ban Thap Yao",
    "wof:placetype":"locality"
},
  "geometry": {"coordinates":[100.78843999999999,13.71297],"type":"Point"}
}