{
  "type": "Feature",
  "properties": {
    "gn:admin1_code":"50.0",
    "gn:asciiname":"Ban Lai Wo",
    "gn:country_code":"TH",
    "gn:dem":488,
    "gn:feature_class":"P",
    "gn:feature_code":"PPL",
    "gn:name":"Ban Lai Wo",
    "gn:population":0,
    "gn:timezone":"Asia/Bangkok",
    "iso:country":"TH",
    "name:tha_x_preferred":[
        "\u0e1a\u0e49\u0e32\u0e19\u0e44\u0e25\u0e48\u0e42\u0e27\u0e48"
    ],
    "wof:name":"Ban Lai Wo",
    "wof:placetype":"locality"
},
  "geometry": {"coordinates":[98.51003,15.30753],"type":"Point"}
}