{
  "type": "Feature",
  "properties": {
    "gn:admin1_code":"50.0",
    "gn:asciiname":"Ban Song Phi Nong",
    "gn:country_code":"TH",
    "gn:dem":239,
    "gn:feature_class":"P",
    "gn:feature_code":"PPL",
    "gn:name":"Ban Song Phi Nong",
    "gn:population":0,
    "gn:timezone":"Asia/Bangkok",
    "iso:country":"TH",
    "name:tha_x_preferred":[
        "\u0e1a\u0e49\u0e32\u0e19\u0e2a\u0e2d\u0e07\u0e1e\u0e35\u0e48\u0e19\u0e49\u0e2d\u0e07"
    ],
    "wof:name":"Ban Song Phi Nong",
    "wof:placetype":"locality"
},
  "geometry": {"coordinates":[99.14939,14.45],"type":"Point"}
}