{
  "type": "Feature",
  "properties": {
    "gn:admin1_code":"0.0",
    "gn:asciiname":"Ban Pae Pho",
    "gn:country_code":"TH",
    "gn:dem":1005,
    "gn:feature_class":"P",
    "gn:feature_code":"PPL",
    "gn:name":"Ban Pae Pho",
    "gn:population":0,
    "gn:timezone":"Asia/Bangkok",
    "iso:country":"TH",
    "wof:name":"Ban Pae Pho",
    "wof:placetype":"locality"
},
  "geometry": {"coordinates":[98.14556,18.17833],"type":"Point"}
}