{
  "type": "Feature",
  "properties": {
    "gn:admin1_code":"16.0",
    "gn:asciiname":"Ban Dan Chang",
    "gn:country_code":"TH",
    "gn:dem":38,
    "gn:feature_class":"P",
    "gn:feature_code":"PPL",
    "gn:name":"Ban Dan Chang",
    "gn:population":0,
    "gn:timezone":"Asia/Bangkok",
    "iso:country":"TH",
    "name:tha_x_preferred":[
        "\u0e1a\u0e49\u0e32\u0e19\u0e14\u0e48\u0e32\u0e19\u0e0a\u0e49\u0e32\u0e07"
    ],
    "wof:name":"Ban Dan Chang",
    "wof:placetype":"locality"
},
  "geometry": {"coordinates":[100.01613999999999,16.04428],"type":"Point"}
}