{
  "type": "Feature",
  "properties": {
    "gn:admin1_code":"65.0",
    "gn:asciiname":"Ban Bon Khuan",
    "gn:country_code":"TH",
    "gn:dem":25,
    "gn:feature_class":"P",
    "gn:feature_code":"PPL",
    "gn:name":"Ban Bon Khuan",
    "gn:population":0,
    "gn:timezone":"Asia/Bangkok",
    "iso:country":"TH",
    "name:tha_x_preferred":[
        "\u0e1a\u0e49\u0e32\u0e19\u0e1a\u0e19\u0e04\u0e27\u0e19"
    ],
    "wof:name":"Ban Bon Khuan",
    "wof:placetype":"locality"
},
  "geometry": {"coordinates":[99.57942,7.68664],"type":"Point"}
}