{
  "type": "Feature",
  "properties": {
    "gn:admin1_code":"3.0",
    "gn:asciiname":"Ban Thung Phatthana",
    "gn:country_code":"TH",
    "gn:dem":418,
    "gn:feature_class":"P",
    "gn:feature_code":"PPL",
    "gn:name":"Ban Thung Phatthana",
    "gn:population":0,
    "gn:timezone":"Asia/Bangkok",
    "iso:country":"TH",
    "name:tha_x_preferred":[
        "\u0e1a\u0e49\u0e32\u0e19\u0e17\u0e38\u0e48\u0e07\u0e1e\u0e31\u0e12\u0e19\u0e32"
    ],
    "wof:name":"Ban Thung Phatthana",
    "wof:placetype":"locality"
},
  "geometry": {"coordinates":[99.75869,19.44778],"type":"Point"}
}