{
  "type": "Feature",
  "properties": {
    "gn:admin1_code":"51.0",
    "gn:asciiname":"Ban Rang Khamoi",
    "gn:country_code":"TH",
    "gn:dem":7,
    "gn:feature_class":"P",
    "gn:feature_code":"PPL",
    "gn:name":"Ban Rang Khamoi",
    "gn:population":0,
    "gn:timezone":"Asia/Bangkok",
    "iso:country":"TH",
    "name:tha_x_preferred":[
        "\u0e1a\u0e49\u0e32\u0e19\u0e23\u0e32\u0e07\u0e02\u0e42\u0e21\u0e22"
    ],
    "wof:name":"Ban Rang Khamoi",
    "wof:placetype":"locality"
},
  "geometry": {"coordinates":[100.26414,14.37525],"type":"Point"}
}