{
  "type": "Feature",
  "properties": {
    "gn:admin1_code":"22.0",
    "gn:asciiname":"Ban Non Phayom",
    "gn:country_code":"TH",
    "gn:dem":168,
    "gn:feature_class":"P",
    "gn:feature_code":"PPL",
    "gn:name":"Ban Non Phayom",
    "gn:population":0,
    "gn:timezone":"Asia/Bangkok",
    "iso:country":"TH",
    "name:tha_x_preferred":[
        "\u0e1a\u0e49\u0e32\u0e19\u0e42\u0e19\u0e19\u0e1e\u0e22\u0e2d\u0e21"
    ],
    "wof:name":"Ban Non Phayom",
    "wof:placetype":"locality"
},
  "geometry": {"coordinates":[102.82122,16.64275],"type":"Point"}
}