{
  "type": "Feature",
  "properties": {
    "gn:admin1_code":"73.0",
    "gn:asciiname":"Ban That Si Bunrueang",
    "gn:country_code":"TH",
    "gn:dem":148,
    "gn:feature_class":"P",
    "gn:feature_code":"PPL",
    "gn:name":"Ban That Si Bunrueang",
    "gn:population":0,
    "gn:timezone":"Asia/Bangkok",
    "iso:country":"TH",
    "name:tha_x_preferred":[
        "Ban That Si Bunrueang"
    ],
    "name:tha_x_variant":[
        "\u0e1a\u0e49\u0e32\u0e19\u0e18\u0e32\u0e15\u0e38\u0e28\u0e23\u0e35\u0e1a\u0e38\u0e0d\u0e40\u0e23\u0e37\u0e2d\u0e07"
    ],
    "wof:name":"Ban That Si Bunrueang",
    "wof:placetype":"locality"
},
  "geometry": {"coordinates":[104.72893999999999,17.01922],"type":"Point"}
}