{
  "type": "Feature",
  "properties": {
    "gn:admin1_code":"11.0",
    "gn:asciiname":"Ban Krok Nam Suem",
    "gn:country_code":"TH",
    "gn:dem":63,
    "gn:feature_class":"P",
    "gn:feature_code":"PPL",
    "gn:name":"Ban Krok Nam Suem",
    "gn:population":0,
    "gn:timezone":"Asia/Bangkok",
    "iso:country":"TH",
    "name:tha_x_preferred":[
        "\u0e1a\u0e49\u0e32\u0e19\u0e42\u0e01\u0e23\u0e01\u0e19\u0e49\u0e33\u0e0b\u0e36\u0e21"
    ],
    "wof:name":"Ban Krok Nam Suem",
    "wof:placetype":"locality"
},
  "geometry": {"coordinates":[99.72742,16.32658],"type":"Point"}
}