{
  "type": "Feature",
  "properties": {
    "gn:admin1_code":"55.0",
    "gn:asciiname":"Muban Sinthon",
    "gn:country_code":"TH",
    "gn:dem":4,
    "gn:feature_class":"P",
    "gn:feature_code":"PPL",
    "gn:name":"Muban Sinthon",
    "gn:population":0,
    "gn:timezone":"Asia/Bangkok",
    "iso:country":"TH",
    "name:tha_x_preferred":[
        "\u0e2b\u0e21\u0e39\u0e48\u0e1a\u0e49\u0e32\u0e19\u0e2a\u0e34\u0e19\u0e18\u0e23"
    ],
    "wof:name":"Muban Sinthon",
    "wof:placetype":"locality"
},
  "geometry": {"coordinates":[100.25389,13.51106],"type":"Point"}
}