{
  "type": "Feature",
  "properties": {
    "gn:admin1_code":"51.0",
    "gn:asciiname":"Ban Nong Mai Chaikhlui",
    "gn:country_code":"TH",
    "gn:dem":19,
    "gn:feature_class":"P",
    "gn:feature_code":"PPL",
    "gn:name":"Ban Nong Mai Chaikhlui",
    "gn:population":0,
    "gn:timezone":"Asia/Bangkok",
    "iso:country":"TH",
    "name:tha_x_preferred":[
        "\u0e1a\u0e49\u0e32\u0e19\u0e2b\u0e19\u0e2d\u0e07\u0e44\u0e21\u0e49\u0e0a\u0e32\u0e22\u0e02\u0e25\u0e38\u0e48\u0e22"
    ],
    "wof:name":"Ban Nong Mai Chaikhlui",
    "wof:placetype":"locality"
},
  "geometry": {"coordinates":[99.96983,14.72469],"type":"Point"}
}