{
  "type": "Feature",
  "properties": {
    "gn:admin1_code":"75.0",
    "gn:asciiname":"Ban Thung Kham Phai",
    "gn:country_code":"TH",
    "gn:dem":132,
    "gn:feature_class":"P",
    "gn:feature_code":"PPL",
    "gn:name":"Ban Thung Kham Phai",
    "gn:population":0,
    "gn:timezone":"Asia/Bangkok",
    "iso:country":"TH",
    "name:tha_x_preferred":[
        "\u0e1a\u0e49\u0e32\u0e19\u0e17\u0e38\u0e48\u0e07\u0e04\u0e33\u0e44\u0e1c\u0e48"
    ],
    "wof:name":"Ban Thung Kham Phai",
    "wof:placetype":"locality"
},
  "geometry": {"coordinates":[104.83042,15.36678],"type":"Point"}
}