{
  "type": "Feature",
  "properties": {
    "gn:admin1_code":"42.0",
    "gn:asciiname":"Ban Khlong Sai Yok",
    "gn:country_code":"TH",
    "gn:dem":5,
    "gn:feature_class":"P",
    "gn:feature_code":"PPL",
    "gn:name":"Ban Khlong Sai Yok",
    "gn:population":0,
    "gn:timezone":"Asia/Bangkok",
    "iso:country":"TH",
    "name:tha_x_preferred":[
        "\u0e1a\u0e49\u0e32\u0e19\u0e04\u0e25\u0e2d\u0e07\u0e44\u0e17\u0e23\u0e42\u0e22\u0e04"
    ],
    "name:und_x_variant":[
        "Ban Sai Yok",
        "Ban Khlong Sai Yok"
    ],
    "wof:name":"Ban Khlong Sai Yok",
    "wof:placetype":"locality"
},
  "geometry": {"coordinates":[100.89994,13.64725],"type":"Point"}
}