{
  "type": "Feature",
  "properties": {
    "gn:admin1_code":"36.0",
    "gn:asciiname":"Ban Bo Ta Lo",
    "gn:country_code":"TH",
    "gn:dem":4,
    "gn:feature_class":"P",
    "gn:feature_code":"PPL",
    "gn:name":"Ban Bo Ta Lo",
    "gn:population":0,
    "gn:timezone":"Asia/Bangkok",
    "iso:country":"TH",
    "name:tha_x_preferred":[
        "\u0e1a\u0e49\u0e32\u0e19\u0e1a\u0e48\u0e2d\u0e15\u0e32\u0e42\u0e25\u0e48"
    ],
    "wof:name":"Ban Bo Ta Lo",
    "wof:placetype":"locality"
},
  "geometry": {"coordinates":[100.70831,14.25586],"type":"Point"}
}