{
  "type": "Feature",
  "properties": {
    "gn:admin1_code":"48.0",
    "gn:asciiname":"Ban Phaya Bon",
    "gn:country_code":"TH",
    "gn:dem":13,
    "gn:feature_class":"P",
    "gn:feature_code":"PPL",
    "gn:name":"Ban Phaya Bon",
    "gn:population":0,
    "gn:timezone":"Asia/Bangkok",
    "iso:country":"TH",
    "name:tha_x_preferred":[
        "\u0e1a\u0e49\u0e32\u0e19\u0e1e\u0e0d\u0e32\u0e1a\u0e19"
    ],
    "name:und_x_variant":[
        "Phayathi Bon",
        "Ban Phayat Bon",
        "Ban Phaya Bon"
    ],
    "wof:name":"Ban Phaya Bon",
    "wof:placetype":"locality"
},
  "geometry": {"coordinates":[102.18680999999999,12.73514],"type":"Point"}
}