{
  "type": "Feature",
  "properties": {
    "gn:admin1_code":"49.0",
    "gn:asciiname":"Ban Hat San Chao",
    "gn:country_code":"TH",
    "gn:dem":16,
    "gn:feature_class":"P",
    "gn:feature_code":"PPL",
    "gn:name":"Ban Hat San Chao",
    "gn:population":0,
    "gn:timezone":"Asia/Bangkok",
    "iso:country":"TH",
    "name:tha_x_preferred":[
        "\u0e1a\u0e49\u0e32\u0e19\u0e2b\u0e32\u0e14\u0e28\u0e32\u0e25\u0e40\u0e08\u0e49\u0e32"
    ],
    "wof:name":"Ban Hat San Chao",
    "wof:placetype":"locality"
},
  "geometry": {"coordinates":[102.9036,11.68051],"type":"Point"}
}