{
  "type": "Feature",
  "properties": {
    "gn:admin1_code":"31.0",
    "gn:asciiname":"Ban Kue Bong Ka Mae",
    "gn:country_code":"TH",
    "gn:dem":29,
    "gn:feature_class":"P",
    "gn:feature_code":"PPL",
    "gn:name":"Ban Kue Bong Ka Mae",
    "gn:population":0,
    "gn:timezone":"Asia/Bangkok",
    "iso:country":"TH",
    "name:tha_x_preferred":[
        "\u0e1a\u0e49\u0e32\u0e19\u0e01\u0e37\u0e2d\u0e1a\u0e07\u0e01\u0e32\u0e41\u0e21"
    ],
    "wof:name":"Ban Kue Bong Ka Mae",
    "wof:placetype":"locality"
},
  "geometry": {"coordinates":[101.92197,6.02017],"type":"Point"}
}