{
  "type": "Feature",
  "properties": {
    "gn:admin1_code":"2.0",
    "gn:asciiname":"Ban Pang Saen Phap",
    "gn:country_code":"TH",
    "gn:dem":1004,
    "gn:feature_class":"P",
    "gn:feature_code":"PPL",
    "gn:name":"Ban Pang Saen Phap",
    "gn:population":0,
    "gn:timezone":"Asia/Bangkok",
    "iso:country":"TH",
    "name:tha_x_preferred":[
        "\u0e1a\u0e49\u0e32\u0e19\u0e1b\u0e32\u0e07\u0e41\u0e2a\u0e19\u0e20\u0e32\u0e1e"
    ],
    "wof:name":"Ban Pang Saen Phap",
    "wof:placetype":"locality"
},
  "geometry": {"coordinates":[99.357,18.87831],"type":"Point"}
}