{
  "type": "Feature",
  "properties": {
    "gn:admin1_code":"0.0",
    "gn:asciiname":"Ban Ru Sa Mi Lae",
    "gn:country_code":"TH",
    "gn:dem":4,
    "gn:feature_class":"P",
    "gn:feature_code":"PPL",
    "gn:name":"Ban Ru Sa Mi Lae",
    "gn:population":0,
    "gn:timezone":"Asia/Bangkok",
    "iso:country":"TH",
    "wof:name":"Ban Ru Sa Mi Lae",
    "wof:placetype":"locality"
},
  "geometry": {"coordinates":[101.22417,6.87111],"type":"Point"}
}