{
  "type": "Feature",
  "properties": {
    "gn:admin1_code":"68.0",
    "gn:asciiname":"Ban Pa Mai Phai",
    "gn:country_code":"TH",
    "gn:dem":10,
    "gn:feature_class":"P",
    "gn:feature_code":"PPL",
    "gn:name":"Ban Pa Mai Phai",
    "gn:population":0,
    "gn:timezone":"Asia/Bangkok",
    "iso:country":"TH",
    "name:tha_x_preferred":[
        "\u0e1a\u0e49\u0e32\u0e19\u0e1b\u0e48\u0e32\u0e44\u0e21\u0e49\u0e44\u0e1c\u0e48"
    ],
    "wof:name":"Ban Pa Mai Phai",
    "wof:placetype":"locality"
},
  "geometry": {"coordinates":[100.94775,6.80558],"type":"Point"}
}