{
  "type": "Feature",
  "properties": {
    "gn:admin1_code":"57.0",
    "gn:asciiname":"Ban Khlong Kettia",
    "gn:country_code":"TH",
    "gn:dem":-9999,
    "gn:feature_class":"P",
    "gn:feature_code":"PPL",
    "gn:name":"Ban Khlong Kettia",
    "gn:population":0,
    "gn:timezone":"Asia/Bangkok",
    "iso:country":"TH",
    "wof:lang_x_official":[
        "tha"
    ],
    "wof:lang_x_spoken":[
        "tha"
    ],
    "wof:name":"Ban Khlong Kettia",
    "wof:placetype":"locality"
},
  "geometry": {"coordinates":[99.65000000000001,11.53333],"type":"Point"}
}