{
  "type": "Feature",
  "properties": {
    "gn:admin1_code":"28.0",
    "gn:asciiname":"Ban Nong So Sae",
    "gn:country_code":"TH",
    "gn:dem":179,
    "gn:feature_class":"P",
    "gn:feature_code":"PPL",
    "gn:name":"Ban Nong So Sae",
    "gn:population":0,
    "gn:timezone":"Asia/Bangkok",
    "iso:country":"TH",
    "name:tha_x_preferred":[
        "\u0e1a\u0e49\u0e32\u0e19\u0e2b\u0e19\u0e2d\u0e07\u0e0b\u0e2d\u0e41\u0e0b"
    ],
    "name:und_x_variant":[
        "Ban Nong Sachaeng"
    ],
    "wof:name":"Ban Nong So Sae",
    "wof:placetype":"locality"
},
  "geometry": {"coordinates":[102.75584000000001,14.97178],"type":"Point"}
}