{
  "type": "Feature",
  "properties": {
    "gn:admin1_code":"31.0",
    "gn:asciiname":"Ban Ku Bae Pi Nga",
    "gn:country_code":"TH",
    "gn:dem":14,
    "gn:feature_class":"P",
    "gn:feature_code":"PPL",
    "gn:name":"Ban Ku Bae Pi Nga",
    "gn:population":0,
    "gn:timezone":"Asia/Bangkok",
    "iso:country":"TH",
    "name:tha_x_preferred":[
        "\u0e1a\u0e49\u0e32\u0e19\u0e01\u0e39\u0e41\u0e1a\u0e1b\u0e35\u0e07\u0e4a\u0e30"
    ],
    "wof:name":"Ban Ku Bae Pi Nga",
    "wof:placetype":"locality"
},
  "geometry": {"coordinates":[101.64243999999999,6.60717],"type":"Point"}
}