{
  "type": "Feature",
  "properties": {
    "gn:admin1_code":"29.0",
    "gn:asciiname":"Ban Non Mayang",
    "gn:country_code":"TH",
    "gn:dem":202,
    "gn:feature_class":"P",
    "gn:feature_code":"PPL",
    "gn:name":"Ban Non Mayang",
    "gn:population":0,
    "gn:timezone":"Asia/Bangkok",
    "iso:country":"TH",
    "name:tha_x_preferred":[
        "\u0e1a\u0e49\u0e32\u0e19\u0e42\u0e19\u0e19\u0e21\u0e30\u0e22\u0e32\u0e07"
    ],
    "wof:name":"Ban Non Mayang",
    "wof:placetype":"locality"
},
  "geometry": {"coordinates":[103.23508,14.3847],"type":"Point"}
}