{
  "type": "Feature",
  "properties": {
    "gn:admin1_code":"16.0",
    "gn:asciiname":"Ban Om Ratchaphongsa",
    "gn:country_code":"TH",
    "gn:dem":33,
    "gn:feature_class":"P",
    "gn:feature_code":"PPL",
    "gn:name":"Ban Om Ratchaphongsa",
    "gn:population":0,
    "gn:timezone":"Asia/Bangkok",
    "iso:country":"TH",
    "name:tha_x_preferred":[
        "\u0e1a\u0e49\u0e32\u0e19\u0e2d\u0e49\u0e2d\u0e21\u0e23\u0e32\u0e0a\u0e1e\u0e07\u0e29\u0e32"
    ],
    "wof:lang_x_official":[
        "tha"
    ],
    "wof:lang_x_spoken":[
        "tha"
    ],
    "wof:name":"Ban Om Ratchaphongsa",
    "wof:placetype":"locality"
},
  "geometry": {"coordinates":[100.21467,15.79378],"type":"Point"}
}