{
  "type": "Feature",
  "properties": {
    "gn:admin1_code":"18.0",
    "gn:asciiname":"Ban Kut To Ruea",
    "gn:country_code":"TH",
    "gn:dem":264,
    "gn:feature_class":"P",
    "gn:feature_code":"PPL",
    "gn:name":"Ban Kut To Ruea",
    "gn:population":0,
    "gn:timezone":"Asia/Bangkok",
    "iso:country":"TH",
    "name:tha_x_preferred":[
        "Ban Kut To Ruea"
    ],
    "name:tha_x_variant":[
        "\u0e1a\u0e49\u0e32\u0e19\u0e01\u0e38\u0e14\u0e15\u0e2d\u0e40\u0e23\u0e37\u0e2d"
    ],
    "wof:name":"Ban Kut To Ruea",
    "wof:placetype":"locality"
},
  "geometry": {"coordinates":[101.67989,17.21381],"type":"Point"}
}