{
  "type": "Feature",
  "properties": {
    "gn:admin1_code":"56.0",
    "gn:asciiname":"Ban Khao Samo Rabang",
    "gn:country_code":"TH",
    "gn:dem":7,
    "gn:feature_class":"P",
    "gn:feature_code":"PPL",
    "gn:name":"Ban Khao Samo Rabang",
    "gn:population":0,
    "gn:timezone":"Asia/Bangkok",
    "iso:country":"TH",
    "name:tha_x_preferred":[
        "\u0e1a\u0e49\u0e32\u0e19\u0e40\u0e02\u0e32\u0e2a\u0e21\u0e2d\u0e23\u0e30\u0e1a\u0e31\u0e07"
    ],
    "name:und_x_variant":[
        "Ban Khao Samo Bang"
    ],
    "wof:name":"Ban Khao Samo Rabang",
    "wof:placetype":"locality"
},
  "geometry": {"coordinates":[99.87769,13.20886],"type":"Point"}
}