{
  "type": "Feature",
  "properties": {
    "gn:admin1_code":"63.0",
    "gn:asciiname":"Ban Khao Na Wua",
    "gn:country_code":"TH",
    "gn:dem":105,
    "gn:feature_class":"P",
    "gn:feature_code":"PPL",
    "gn:name":"Ban Khao Na Wua",
    "gn:population":0,
    "gn:timezone":"Asia/Bangkok",
    "iso:country":"TH",
    "name:tha_x_preferred":[
        "\u0e1a\u0e49\u0e32\u0e19\u0e40\u0e02\u0e32\u0e2b\u0e19\u0e49\u0e32\u0e27\u0e31\u0e27"
    ],
    "wof:name":"Ban Khao Na Wua",
    "wof:placetype":"locality"
},
  "geometry": {"coordinates":[98.83658,8.20983],"type":"Point"}
}