{
  "type": "Feature",
  "properties": {
    "gn:admin1_code":"46.0",
    "gn:asciiname":"Ban Map Phai",
    "gn:country_code":"TH",
    "gn:dem":36,
    "gn:feature_class":"P",
    "gn:feature_code":"PPL",
    "gn:name":"Ban Map Phai",
    "gn:population":0,
    "gn:timezone":"Asia/Bangkok",
    "iso:country":"TH",
    "name:tha_x_preferred":[
        "\u0e1a\u0e49\u0e32\u0e19\u0e21\u0e32\u0e1a\u0e44\u0e1c\u0e48"
    ],
    "name:und_x_variant":[
        "Map Pai",
        "Ban Map Phai (1)",
        "Ban Map Phai"
    ],
    "wof:name":"Ban Map Phai",
    "wof:placetype":"locality"
},
  "geometry": {"coordinates":[101.08678,13.36633],"type":"Point"}
}