{
  "type": "Feature",
  "properties": {
    "gn:admin1_code":"31.0",
    "gn:asciiname":"Ban Lamthan Thong",
    "gn:country_code":"TH",
    "gn:dem":171,
    "gn:feature_class":"P",
    "gn:feature_code":"PPL",
    "gn:name":"Ban Lamthan Thong",
    "gn:population":0,
    "gn:timezone":"Asia/Bangkok",
    "iso:country":"TH",
    "name:tha_x_preferred":[
        "\u0e1a\u0e49\u0e32\u0e19\u0e25\u0e33\u0e18\u0e32\u0e23\u0e17\u0e2d\u0e07"
    ],
    "wof:name":"Ban Lamthan Thong",
    "wof:placetype":"locality"
},
  "geometry": {"coordinates":[101.71414,5.80489],"type":"Point"}
}