{
  "type": "Feature",
  "properties": {
    "gn:admin1_code":"20.0",
    "gn:asciiname":"Ban Ba Thong",
    "gn:country_code":"TH",
    "gn:dem":168,
    "gn:feature_class":"P",
    "gn:feature_code":"PPL",
    "gn:name":"Ban Ba Thong",
    "gn:population":0,
    "gn:timezone":"Asia/Bangkok",
    "iso:country":"TH",
    "name:tha_x_preferred":[
        "\u0e1a\u0e49\u0e32\u0e19\u0e1a\u0e30\u0e17\u0e2d\u0e07"
    ],
    "wof:name":"Ban Ba Thong",
    "wof:placetype":"locality"
},
  "geometry": {"coordinates":[103.76336000000001,17.74708],"type":"Point"}
}