{
  "type": "Feature",
  "properties": {
    "gn:admin1_code":"72.0",
    "gn:asciiname":"Ban Laeng Nu",
    "gn:country_code":"TH",
    "gn:dem":131,
    "gn:feature_class":"P",
    "gn:feature_code":"PPL",
    "gn:name":"Ban Laeng Nu",
    "gn:population":0,
    "gn:timezone":"Asia/Bangkok",
    "iso:country":"TH",
    "name:tha_x_preferred":[
        "\u0e1a\u0e49\u0e32\u0e19\u0e41\u0e2b\u0e25\u0e48\u0e07\u0e2b\u0e19\u0e39"
    ],
    "wof:name":"Ban Laeng Nu",
    "wof:placetype":"locality"
},
  "geometry": {"coordinates":[104.30944,15.6885],"type":"Point"}
}