{
  "type": "Feature",
  "properties": {
    "gn:admin1_code":"28.0",
    "gn:asciiname":"Ban Na Klang",
    "gn:country_code":"TH",
    "gn:dem":178,
    "gn:feature_class":"P",
    "gn:feature_code":"PPL",
    "gn:name":"Ban Na Klang",
    "gn:population":0,
    "gn:timezone":"Asia/Bangkok",
    "iso:country":"TH",
    "name:tha_x_preferred":[
        "\u0e1a\u0e49\u0e32\u0e19\u0e19\u0e32\u0e01\u0e25\u0e32\u0e07"
    ],
    "wof:name":"Ban Na Klang",
    "wof:placetype":"locality"
},
  "geometry": {"coordinates":[103.01119,15.048],"type":"Point"}
}