{
  "type": "Feature",
  "properties": {
    "gn:admin1_code":"35.0",
    "gn:asciiname":"Ban Huai Ratchakhram",
    "gn:country_code":"TH",
    "gn:dem":10,
    "gn:feature_class":"P",
    "gn:feature_code":"PPL",
    "gn:name":"Ban Huai Ratchakhram",
    "gn:population":0,
    "gn:timezone":"Asia/Bangkok",
    "iso:country":"TH",
    "name:tha_x_preferred":[
        "\u0e1a\u0e49\u0e32\u0e19\u0e2b\u0e49\u0e27\u0e22\u0e23\u0e32\u0e0a\u0e04\u0e23\u0e32\u0e21"
    ],
    "name:und_x_variant":[
        "Ban Huai Chakhram"
    ],
    "wof:name":"Ban Huai Ratchakhram",
    "wof:placetype":"locality"
},
  "geometry": {"coordinates":[100.29353,14.64536],"type":"Point"}
}