{
  "type": "Feature",
  "properties": {
    "gn:admin1_code":"41.0",
    "gn:asciiname":"Ban Pueai Piang",
    "gn:country_code":"TH",
    "gn:dem":396,
    "gn:feature_class":"P",
    "gn:feature_code":"PPL",
    "gn:name":"Ban Pueai Piang",
    "gn:population":0,
    "gn:timezone":"Asia/Bangkok",
    "iso:country":"TH",
    "name:tha_x_preferred":[
        "\u0e1a\u0e49\u0e32\u0e19\u0e40\u0e1b\u0e37\u0e4b\u0e2d\u0e22\u0e40\u0e1b\u0e35\u0e22\u0e07"
    ],
    "name:und_x_variant":[
        "Ban Puai Piang",
        "Ban Pueai Piang"
    ],
    "wof:name":"Ban Pueai Piang",
    "wof:placetype":"locality"
},
  "geometry": {"coordinates":[100.31168,19.54361],"type":"Point"}
}