{
  "type": "Feature",
  "properties": {
    "gn:admin1_code":"9.0",
    "gn:asciiname":"Ban Nam Lat",
    "gn:country_code":"TH",
    "gn:dem":81,
    "gn:feature_class":"P",
    "gn:feature_code":"PPL",
    "gn:name":"Ban Nam Lat",
    "gn:population":0,
    "gn:timezone":"Asia/Bangkok",
    "iso:country":"TH",
    "name:tha_x_preferred":[
        "\u0e1a\u0e49\u0e32\u0e19\u0e19\u0e49\u0e33\u0e25\u0e32\u0e14"
    ],
    "wof:name":"Ban Nam Lat",
    "wof:placetype":"locality"
},
  "geometry": {"coordinates":[99.57808,17.10172],"type":"Point"}
}