{
  "type": "Feature",
  "properties": {
    "gn:admin1_code":"15.0",
    "gn:asciiname":"Ban Wong Duean",
    "gn:country_code":"TH",
    "gn:dem":48,
    "gn:feature_class":"P",
    "gn:feature_code":"PPL",
    "gn:name":"Ban Wong Duean",
    "gn:population":0,
    "gn:timezone":"Asia/Bangkok",
    "iso:country":"TH",
    "name:tha_x_preferred":[
        "\u0e1a\u0e49\u0e32\u0e19\u0e27\u0e07\u0e40\u0e14\u0e37\u0e2d\u0e19"
    ],
    "name:und_x_variant":[
        "Wong Duan",
        "B\u0101n Wang Duan",
        "Ban Wong Duan",
        "Ban Wong Duean"
    ],
    "wof:name":"Ban Wong Duean",
    "wof:placetype":"locality"
},
  "geometry": {"coordinates":[99.87036000000001,15.61283],"type":"Point"}
}