{
  "type": "Feature",
  "properties": {
    "gn:admin1_code":"23.0",
    "gn:asciiname":"Ban Nong Phon Samakkhi",
    "gn:country_code":"TH",
    "gn:dem":193,
    "gn:feature_class":"P",
    "gn:feature_code":"PPL",
    "gn:name":"Ban Nong Phon Samakkhi",
    "gn:population":0,
    "gn:timezone":"Asia/Bangkok",
    "iso:country":"TH",
    "name:tha_x_preferred":[
        "\u0e1a\u0e49\u0e32\u0e19\u0e2b\u0e19\u0e2d\u0e07\u0e42\u0e1e\u0e19\u0e2a\u0e32\u0e21\u0e31\u0e04\u0e04\u0e35"
    ],
    "wof:name":"Ban Nong Phon Samakkhi",
    "wof:placetype":"locality"
},
  "geometry": {"coordinates":[103.73224999999999,16.65122],"type":"Point"}
}