{
  "type": "Feature",
  "properties": {
    "gn:admin1_code":"26.0",
    "gn:asciiname":"Ban Lam Chi",
    "gn:cc2":"TH",
    "gn:country_code":"TH",
    "gn:dem":223,
    "gn:feature_class":"P",
    "gn:feature_code":"PPL",
    "gn:name":"Ban Lam Chi",
    "gn:population":0,
    "gn:timezone":"Asia/Bangkok",
    "iso:country":"TH",
    "name:und_x_variant":[
        "Ban Nong Haeng",
        "Naung Haeng",
        "B\u0101n Naung Heang",
        "Ban Lam Chi"
    ],
    "wof:name":"Ban Lam Chi",
    "wof:placetype":"locality"
},
  "geometry": {"coordinates":[101.68722,15.985],"type":"Point"}
}