{
  "type": "Feature",
  "properties": {
    "gn:admin1_code":"0.0",
    "gn:asciiname":"Ban Toei Luang",
    "gn:country_code":"TH",
    "gn:dem":750,
    "gn:feature_class":"P",
    "gn:feature_code":"PPL",
    "gn:name":"Ban Toei Luang",
    "gn:population":0,
    "gn:timezone":"Asia/Bangkok",
    "iso:country":"TH",
    "wof:name":"Ban Toei Luang",
    "wof:placetype":"locality"
},
  "geometry": {"coordinates":[100.98333,19.15],"type":"Point"}
}