{
  "type": "Feature",
  "properties": {
    "gn:admin1_code":"78.0",
    "gn:asciiname":"Ban Na Khok Kung",
    "gn:country_code":"TH",
    "gn:dem":342,
    "gn:feature_class":"P",
    "gn:feature_code":"PPL",
    "gn:name":"Ban Na Khok Kung",
    "gn:population":0,
    "gn:timezone":"Asia/Bangkok",
    "iso:country":"TH",
    "name:tha_x_preferred":[
        "Ban Na Khok Kung"
    ],
    "name:tha_x_variant":[
        "\u0e1a\u0e49\u0e32\u0e19\u0e19\u0e32\u0e42\u0e04\u0e01\u0e01\u0e38\u0e07"
    ],
    "wof:name":"Ban Na Khok Kung",
    "wof:placetype":"locality"
},
  "geometry": {"coordinates":[104.14794999999999,16.78531],"type":"Point"}
}