{
  "type": "Feature",
  "properties": {
    "gn:admin1_code":"7.0",
    "gn:asciiname":"Ban Hat On",
    "gn:country_code":"TH",
    "gn:dem":113,
    "gn:feature_class":"P",
    "gn:feature_code":"PPL",
    "gn:name":"Ban Hat On",
    "gn:population":0,
    "gn:timezone":"Asia/Bangkok",
    "iso:country":"TH",
    "name:tha_x_preferred":[
        "\u0e1a\u0e49\u0e32\u0e19\u0e2b\u0e32\u0e14\u0e2d\u0e49\u0e2d\u0e19"
    ],
    "wof:name":"Ban Hat On",
    "wof:placetype":"locality"
},
  "geometry": {"coordinates":[99.64216999999999,17.95025],"type":"Point"}
}