{
  "type": "Feature",
  "properties": {
    "gn:admin1_code":"3.0",
    "gn:asciiname":"Ban Musoe Mae Tang",
    "gn:country_code":"TH",
    "gn:dem":492,
    "gn:feature_class":"P",
    "gn:feature_code":"PPL",
    "gn:name":"Ban Musoe Mae Tang",
    "gn:population":0,
    "gn:timezone":"Asia/Bangkok",
    "iso:country":"TH",
    "name:tha_x_preferred":[
        "\u0e1a\u0e49\u0e32\u0e19\u0e21\u0e39\u0e40\u0e0b\u0e2d\u0e41\u0e21\u0e48\u0e15\u0e48\u0e32\u0e07"
    ],
    "wof:lang_x_official":[
        "tha"
    ],
    "wof:lang_x_spoken":[
        "tha"
    ],
    "wof:name":"Ban Musoe Mae Tang",
    "wof:placetype":"locality"
},
  "geometry": {"coordinates":[99.72458,19.92178],"type":"Point"}
}