{
  "type": "Feature",
  "properties": {
    "gn:admin1_code":"6.0",
    "gn:asciiname":"Ban Pha Cho Tai",
    "gn:country_code":"TH",
    "gn:dem":367,
    "gn:feature_class":"P",
    "gn:feature_code":"PPL",
    "gn:name":"Ban Pha Cho Tai",
    "gn:population":0,
    "gn:timezone":"Asia/Bangkok",
    "iso:country":"TH",
    "name:tha_x_preferred":[
        "\u0e1a\u0e49\u0e32\u0e19\u0e1c\u0e32\u0e0a\u0e48\u0e2d\u0e43\u0e15\u0e49"
    ],
    "wof:name":"Ban Pha Cho Tai",
    "wof:placetype":"locality"
},
  "geometry": {"coordinates":[99.60581000000001,18.89664],"type":"Point"}
}