{
  "type": "Feature",
  "properties": {
    "gn:admin1_code":"0.0",
    "gn:asciiname":"Ban Sup",
    "gn:country_code":"TH",
    "gn:dem":329,
    "gn:feature_class":"P",
    "gn:feature_code":"PPL",
    "gn:name":"Ban Sup",
    "gn:population":0,
    "gn:timezone":"Asia/Bangkok",
    "iso:country":"TH",
    "wof:name":"Ban Sup",
    "wof:placetype":"locality"
},
  "geometry": {"coordinates":[101.81667,17.61667000000001],"type":"Point"}
}