{
  "type": "Feature",
  "properties": {
    "gn:admin1_code":"29",
    "gn:asciiname":"Ban Na Nuan Noi",
    "gn:country_code":"TH",
    "gn:dem":162,
    "gn:feature_class":"P",
    "gn:feature_code":"PPL",
    "gn:name":"Ban Na Nuan Noi",
    "gn:population":0,
    "gn:timezone":"Asia/Bangkok",
    "iso:country":"TH",
    "name:tha_x_preferred":[
        "\u0e1a\u0e49\u0e32\u0e19\u0e19\u0e32\u0e19\u0e27\u0e19\u0e19\u0e49\u0e2d\u0e22"
    ],
    "wof:name":"Ban Na Nuan Noi",
    "wof:placetype":"locality"
},
  "geometry": {"coordinates":[103.78039,15.12667],"type":"Point"}
}