{
  "type": "Feature",
  "properties": {
    "gn:admin1_code":"3.0",
    "gn:asciiname":"Ban Pa Ruak",
    "gn:country_code":"TH",
    "gn:dem":374,
    "gn:feature_class":"P",
    "gn:feature_code":"PPL",
    "gn:name":"Ban Pa Ruak",
    "gn:population":0,
    "gn:timezone":"Asia/Bangkok",
    "iso:country":"TH",
    "name:tha_x_preferred":[
        "\u0e1a\u0e49\u0e32\u0e19\u0e1b\u0e48\u0e32\u0e23\u0e27\u0e01"
    ],
    "name:und_x_variant":[
        "Ban San Pa Huak",
        "B\u0101n San Pao Huak",
        "Ban Pa Ruak"
    ],
    "wof:name":"Ban Pa Ruak",
    "wof:placetype":"locality"
},
  "geometry": {"coordinates":[100.09578,19.62089],"type":"Point"}
}