{
  "type": "Feature",
  "properties": {
    "gn:admin1_code":"33",
    "gn:asciiname":"Ban Wat Wihan Daeng",
    "gn:country_code":"TH",
    "gn:dem":13,
    "gn:feature_class":"P",
    "gn:feature_code":"PPL",
    "gn:name":"Ban Wat Wihan Daeng",
    "gn:population":0,
    "gn:timezone":"Asia/Bangkok",
    "iso:country":"TH",
    "name:tha_x_preferred":[
        "\u0e1a\u0e49\u0e32\u0e19\u0e27\u0e31\u0e14\u0e27\u0e34\u0e2b\u0e32\u0e23\u0e41\u0e14\u0e07"
    ],
    "wof:name":"Ban Wat Wihan Daeng",
    "wof:placetype":"locality"
},
  "geometry": {"coordinates":[100.27583,14.79733],"type":"Point"}
}