{
  "type": "Feature",
  "properties": {
    "gn:admin1_code":"75.0",
    "gn:asciiname":"Ban Lat Khwai",
    "gn:country_code":"TH",
    "gn:dem":150,
    "gn:feature_class":"P",
    "gn:feature_code":"PPL",
    "gn:name":"Ban Lat Khwai",
    "gn:population":0,
    "gn:timezone":"Asia/Bangkok",
    "iso:country":"TH",
    "name:tha_x_preferred":[
        "\u0e1a\u0e49\u0e32\u0e19\u0e25\u0e32\u0e14\u0e04\u0e27\u0e32\u0e22"
    ],
    "wof:name":"Ban Lat Khwai",
    "wof:placetype":"locality"
},
  "geometry": {"coordinates":[105.26267,15.54247],"type":"Point"}
}