{
  "type": "Feature",
  "properties": {
    "gn:admin1_code":"41.0",
    "gn:asciiname":"Ban Don Kaeo",
    "gn:country_code":"TH",
    "gn:dem":322,
    "gn:feature_class":"P",
    "gn:feature_code":"PPL",
    "gn:name":"Ban Don Kaeo",
    "gn:population":0,
    "gn:timezone":"Asia/Bangkok",
    "iso:country":"TH",
    "name:tha_x_preferred":[
        "\u0e1a\u0e49\u0e32\u0e19\u0e14\u0e2d\u0e19\u0e41\u0e01\u0e49\u0e27"
    ],
    "name:und_x_variant":[
        "Ban Daun Geo",
        "Muang Oi",
        "Daun Keo",
        "Muang Loi",
        "\u014ci",
        "Oil",
        "Ban Don Kaeo"
    ],
    "wof:name":"Ban Don Kaeo",
    "wof:placetype":"locality"
},
  "geometry": {"coordinates":[100.32169,19.22325],"type":"Point"}
}