{
  "type": "Feature",
  "properties": {
    "gn:admin1_code":"15.0",
    "gn:asciiname":"Ban Watthana Thung Na",
    "gn:country_code":"TH",
    "gn:dem":69,
    "gn:feature_class":"P",
    "gn:feature_code":"PPL",
    "gn:name":"Ban Watthana Thung Na",
    "gn:population":0,
    "gn:timezone":"Asia/Bangkok",
    "iso:country":"TH",
    "name:tha_x_preferred":[
        "\u0e1a\u0e49\u0e32\u0e19\u0e27\u0e31\u0e12\u0e19\u0e32\u0e17\u0e38\u0e48\u0e07\u0e19\u0e32"
    ],
    "wof:name":"Ban Watthana Thung Na",
    "wof:placetype":"locality"
},
  "geometry": {"coordinates":[99.71633,15.31506],"type":"Point"}
}