{
  "type": "Feature",
  "properties": {
    "gn:admin1_code":"23.0",
    "gn:asciiname":"Ban Mai Chai Mongkhon",
    "gn:country_code":"TH",
    "gn:dem":185,
    "gn:feature_class":"P",
    "gn:feature_code":"PPL",
    "gn:name":"Ban Mai Chai Mongkhon",
    "gn:population":0,
    "gn:timezone":"Asia/Bangkok",
    "iso:country":"TH",
    "name:tha_x_preferred":[
        "\u0e1a\u0e49\u0e32\u0e19\u0e43\u0e2b\u0e21\u0e48\u0e0a\u0e31\u0e22\u0e21\u0e07\u0e04\u0e25"
    ],
    "wof:name":"Ban Mai Chai Mongkhon",
    "wof:placetype":"locality"
},
  "geometry": {"coordinates":[103.63244,16.84308],"type":"Point"}
}