{
  "type": "Feature",
  "properties": {
    "gn:admin1_code":"24",
    "gn:asciiname":"Ban Nong Bua Kaeo",
    "gn:country_code":"TH",
    "gn:dem":141,
    "gn:feature_class":"P",
    "gn:feature_code":"PPL",
    "gn:name":"Ban Nong Bua Kaeo",
    "gn:population":0,
    "gn:timezone":"Asia/Bangkok",
    "iso:country":"TH",
    "name:tha_x_preferred":[
        "\u0e1a\u0e49\u0e32\u0e19\u0e2b\u0e19\u0e2d\u0e07\u0e1a\u0e31\u0e27\u0e41\u0e01\u0e49\u0e27"
    ],
    "wof:name":"Ban Nong Bua Kaeo",
    "wof:placetype":"locality"
},
  "geometry": {"coordinates":[103.30758,15.54839],"type":"Point"}
}