{
  "type": "Feature",
  "properties": {
    "gn:admin1_code":"40.0",
    "gn:admin2_code":"1021.0",
    "gn:asciiname":"Ban Choeng Ta Phe",
    "gn:country_code":"TH",
    "gn:dem":2,
    "gn:feature_class":"P",
    "gn:feature_code":"PPL",
    "gn:name":"Ban Choeng Ta Phe",
    "gn:population":0,
    "gn:timezone":"Asia/Bangkok",
    "iso:country":"TH",
    "name:tha_x_preferred":[
        "\u0e1a\u0e49\u0e32\u0e19\u0e40\u0e0a\u0e34\u0e07\u0e15\u0e32\u0e40\u0e1e"
    ],
    "name:und_x_variant":[
        "Ban Choeng Ta Phae"
    ],
    "wof:name":"Ban Choeng Ta Phe",
    "wof:placetype":"locality"
},
  "geometry": {"coordinates":[100.42046999999999,13.55989],"type":"Point"}
}