{
  "type": "Feature",
  "properties": {
    "gn:admin1_code":"50.0",
    "gn:asciiname":"Ban Krai Kriang Lang",
    "gn:country_code":"TH",
    "gn:dem":189,
    "gn:feature_class":"P",
    "gn:feature_code":"PPL",
    "gn:name":"Ban Krai Kriang Lang",
    "gn:population":0,
    "gn:timezone":"Asia/Bangkok",
    "iso:country":"TH",
    "name:tha_x_preferred":[
        "\u0e1a\u0e49\u0e32\u0e19\u0e44\u0e01\u0e23\u0e40\u0e01\u0e23\u0e35\u0e22\u0e07\u0e25\u0e48\u0e32\u0e07"
    ],
    "wof:lang_x_official":[
        "tha"
    ],
    "wof:lang_x_spoken":[
        "tha"
    ],
    "wof:name":"Ban Krai Kriang Lang",
    "wof:placetype":"locality"
},
  "geometry": {"coordinates":[99.18397,14.97781],"type":"Point"}
}