{
  "type": "Feature",
  "properties": {
    "gn:admin1_code":"81.0",
    "gn:asciiname":"Ban Buan Khla Thung",
    "gn:country_code":"TH",
    "gn:dem":160,
    "gn:feature_class":"P",
    "gn:feature_code":"PPL",
    "gn:name":"Ban Buan Khla Thung",
    "gn:population":0,
    "gn:timezone":"Asia/Bangkok",
    "iso:country":"TH",
    "name:tha_x_preferred":[
        "\u0e1a\u0e49\u0e32\u0e19\u0e1a\u0e38\u0e48\u0e07\u0e04\u0e25\u0e49\u0e32\u0e17\u0e38\u0e48\u0e07"
    ],
    "wof:name":"Ban Buan Khla Thung",
    "wof:placetype":"locality"
},
  "geometry": {"coordinates":[103.98303,18.291],"type":"Point"}
}