{
  "type": "Feature",
  "properties": {
    "gn:admin1_code":"75.0",
    "gn:asciiname":"Ban Udom Phatthana",
    "gn:country_code":"TH",
    "gn:dem":157,
    "gn:feature_class":"P",
    "gn:feature_code":"PPL",
    "gn:name":"Ban Udom Phatthana",
    "gn:population":0,
    "gn:timezone":"Asia/Bangkok",
    "iso:country":"TH",
    "name:tha_x_preferred":[
        "\u0e1a\u0e49\u0e32\u0e19\u0e2d\u0e38\u0e14\u0e21\u0e1e\u0e31\u0e12\u0e19\u0e32"
    ],
    "wof:name":"Ban Udom Phatthana",
    "wof:placetype":"locality"
},
  "geometry": {"coordinates":[104.87636000000001,14.88672],"type":"Point"}
}