{
  "type": "Feature",
  "properties": {
    "gn:admin1_code":"70.0",
    "gn:asciiname":"Ban Ri Nge",
    "gn:country_code":"TH",
    "gn:dem":96,
    "gn:feature_class":"P",
    "gn:feature_code":"PPL",
    "gn:name":"Ban Ri Nge",
    "gn:population":0,
    "gn:timezone":"Asia/Bangkok",
    "iso:country":"TH",
    "name:tha_x_preferred":[
        "\u0e1a\u0e49\u0e32\u0e19\u0e23\u0e34\u0e40\u0e07\u0e4a\u0e30"
    ],
    "wof:name":"Ban Ri Nge",
    "wof:placetype":"locality"
},
  "geometry": {"coordinates":[101.34147,6.27942],"type":"Point"}
}