{
  "type": "Feature",
  "properties": {
    "gn:admin1_code":"14.0",
    "gn:asciiname":"Ban Noen Makha Ngam",
    "gn:country_code":"TH",
    "gn:dem":169,
    "gn:feature_class":"P",
    "gn:feature_code":"PPL",
    "gn:name":"Ban Noen Makha Ngam",
    "gn:population":0,
    "gn:timezone":"Asia/Bangkok",
    "iso:country":"TH",
    "name:tha_x_preferred":[
        "\u0e1a\u0e49\u0e32\u0e19\u0e40\u0e19\u0e34\u0e19\u0e21\u0e30\u0e04\u0e48\u0e32\u0e07\u0e32\u0e21"
    ],
    "wof:lang_x_official":[
        "tha"
    ],
    "wof:lang_x_spoken":[
        "tha"
    ],
    "wof:name":"Ban Noen Makha Ngam",
    "wof:placetype":"locality"
},
  "geometry": {"coordinates":[100.84533,16.26556],"type":"Point"}
}