{
  "type": "Feature",
  "properties": {
    "gn:admin1_code":"74",
    "gn:asciiname":"Ban Mai Chu Thong",
    "gn:country_code":"TH",
    "gn:dem":27,
    "gn:feature_class":"P",
    "gn:feature_code":"PPL",
    "gn:name":"Ban Mai Chu Thong",
    "gn:population":0,
    "gn:timezone":"Asia/Bangkok",
    "iso:country":"TH",
    "name:tha_x_preferred":[
        "\u0e1a\u0e49\u0e32\u0e19\u0e43\u0e2b\u0e21\u0e48\u0e0a\u0e39\u0e17\u0e2d\u0e07"
    ],
    "wof:name":"Ban Mai Chu Thong",
    "wof:placetype":"locality"
},
  "geometry": {"coordinates":[101.65561,13.89669],"type":"Point"}
}