{
  "type": "Feature",
  "properties": {
    "gn:admin1_code":"27",
    "gn:asciiname":"Ban Sa Wan Phraya",
    "gn:country_code":"TH",
    "gn:dem":256,
    "gn:feature_class":"P",
    "gn:feature_code":"PPL",
    "gn:name":"Ban Sa Wan Phraya",
    "gn:population":0,
    "gn:timezone":"Asia/Bangkok",
    "iso:country":"TH",
    "name:tha_x_preferred":[
        "\u0e1a\u0e49\u0e32\u0e19\u0e2a\u0e23\u0e30\u0e27\u0e48\u0e32\u0e19\u0e1e\u0e23\u0e30\u0e22\u0e32"
    ],
    "wof:name":"Ban Sa Wan Phraya",
    "wof:placetype":"locality"
},
  "geometry": {"coordinates":[102.40803,14.55667],"type":"Point"}
}