{
  "type": "Feature",
  "properties": {
    "gn:admin1_code":"47.0",
    "gn:asciiname":"Ban Prong Sathon",
    "gn:country_code":"TH",
    "gn:dem":27,
    "gn:feature_class":"P",
    "gn:feature_code":"PPL",
    "gn:name":"Ban Prong Sathon",
    "gn:population":0,
    "gn:timezone":"Asia/Bangkok",
    "iso:country":"TH",
    "name:tha_x_preferred":[
        "\u0e1a\u0e49\u0e32\u0e19\u0e42\u0e1b\u0e23\u0e48\u0e07\u0e2a\u0e30\u0e17\u0e49\u0e2d\u0e19"
    ],
    "wof:name":"Ban Prong Sathon",
    "wof:placetype":"locality"
},
  "geometry": {"coordinates":[101.62917,12.90861],"type":"Point"}
}