{
  "type": "Feature",
  "properties": {
    "gn:admin1_code":"25.0",
    "gn:asciiname":"Ban Don Ya Nang",
    "gn:country_code":"TH",
    "gn:dem":164,
    "gn:feature_class":"P",
    "gn:feature_code":"PPL",
    "gn:name":"Ban Don Ya Nang",
    "gn:population":0,
    "gn:timezone":"Asia/Bangkok",
    "iso:country":"TH",
    "name:tha_x_preferred":[
        "\u0e1a\u0e49\u0e32\u0e19\u0e14\u0e2d\u0e19\u0e22\u0e48\u0e32\u0e19\u0e32\u0e07"
    ],
    "wof:name":"Ban Don Ya Nang",
    "wof:placetype":"locality"
},
  "geometry": {"coordinates":[103.92258,16.31244],"type":"Point"}
}