{
  "type": "Feature",
  "properties": {
    "gn:admin1_code":"36",
    "gn:asciiname":"Ban Khlong Ta Sio",
    "gn:country_code":"TH",
    "gn:dem":7,
    "gn:feature_class":"P",
    "gn:feature_code":"PPL",
    "gn:name":"Ban Khlong Ta Sio",
    "gn:population":0,
    "gn:timezone":"Asia/Bangkok",
    "iso:country":"TH",
    "name:tha_x_preferred":[
        "\u0e1a\u0e49\u0e32\u0e19\u0e04\u0e25\u0e2d\u0e07\u0e15\u0e32\u0e2a\u0e34\u0e49\u0e27"
    ],
    "wof:name":"Ban Khlong Ta Sio",
    "wof:placetype":"locality"
},
  "geometry": {"coordinates":[100.71102999999999,14.24589],"type":"Point"}
}