{
  "type": "Feature",
  "properties": {
    "gn:admin1_code":"18.0",
    "gn:asciiname":"Ban Tit To",
    "gn:country_code":"TH",
    "gn:dem":247,
    "gn:feature_class":"P",
    "gn:feature_code":"PPL",
    "gn:name":"Ban Tit To",
    "gn:population":0,
    "gn:timezone":"Asia/Bangkok",
    "iso:country":"TH",
    "name:tha_x_preferred":[
        "\u0e1a\u0e49\u0e32\u0e19\u0e15\u0e34\u0e14\u0e15\u0e48\u0e2d"
    ],
    "name:und_x_variant":[
        "Ban Thit Yo",
        "B\u0101n Thit Yau",
        "Ban Tit To"
    ],
    "wof:name":"Ban Tit To",
    "wof:placetype":"locality"
},
  "geometry": {"coordinates":[101.73645,17.4675],"type":"Point"}
}