{
  "type": "Feature",
  "properties": {
    "gn:admin1_code":"2.0",
    "gn:asciiname":"Ban Nong Pa Kha",
    "gn:cc2":"TH",
    "gn:country_code":"TH",
    "gn:dem":325,
    "gn:feature_class":"P",
    "gn:feature_code":"PPL",
    "gn:name":"Ban Nong Pa Kha",
    "gn:population":0,
    "gn:timezone":"Asia/Bangkok",
    "iso:country":"TH",
    "name:tha_x_preferred":[
        "\u0e1a\u0e49\u0e32\u0e19\u0e2b\u0e19\u0e2d\u0e07\u0e1b\u0e48\u0e32\u0e04\u0e32"
    ],
    "name:und_x_variant":[
        "Ban Pa Kha",
        "Ban Pa Ka",
        "Ban Nong Pa Kha"
    ],
    "wof:name":"Ban Nong Pa Kha",
    "wof:placetype":"locality"
},
  "geometry": {"coordinates":[98.96666999999999,18.96667],"type":"Point"}
}