{
  "type": "Feature",
  "properties": {
    "gn:admin1_code":"69.0",
    "gn:asciiname":"Ban Kala Pho Tok",
    "gn:country_code":"TH",
    "gn:dem":34,
    "gn:feature_class":"P",
    "gn:feature_code":"PPL",
    "gn:name":"Ban Kala Pho Tok",
    "gn:population":0,
    "gn:timezone":"Asia/Bangkok",
    "iso:country":"TH",
    "name:tha_x_preferred":[
        "\u0e1a\u0e49\u0e32\u0e19\u0e01\u0e30\u0e25\u0e32\u0e1e\u0e2d\u0e15\u0e01"
    ],
    "wof:name":"Ban Kala Pho Tok",
    "wof:placetype":"locality"
},
  "geometry": {"coordinates":[101.52728,6.70628],"type":"Point"}
}