{
  "type": "Feature",
  "properties": {
    "gn:admin1_code":"50.0",
    "gn:asciiname":"Ban I Pu",
    "gn:country_code":"TH",
    "gn:dem":817,
    "gn:feature_class":"P",
    "gn:feature_code":"PPL",
    "gn:name":"Ban I Pu",
    "gn:population":0,
    "gn:timezone":"Asia/Bangkok",
    "iso:country":"TH",
    "name:tha_x_preferred":[
        "\u0e1a\u0e49\u0e32\u0e19\u0e2d\u0e35\u0e1b\u0e39\u0e48"
    ],
    "wof:name":"Ban I Pu",
    "wof:placetype":"locality"
},
  "geometry": {"coordinates":[98.38025,14.67475],"type":"Point"}
}