{
  "type": "Feature",
  "properties": {
    "gn:admin1_code":"1.0",
    "gn:asciiname":"Ban Mae Na Chang Tai",
    "gn:country_code":"TH",
    "gn:dem":669,
    "gn:feature_class":"P",
    "gn:feature_code":"PPL",
    "gn:name":"Ban Mae Na Chang Tai",
    "gn:population":0,
    "gn:timezone":"Asia/Bangkok",
    "iso:country":"TH",
    "name:tha_x_preferred":[
        "\u0e1a\u0e49\u0e32\u0e19\u0e41\u0e21\u0e48\u0e19\u0e32\u0e08\u0e32\u0e07\u0e43\u0e15\u0e49"
    ],
    "wof:name":"Ban Mae Na Chang Tai",
    "wof:placetype":"locality"
},
  "geometry": {"coordinates":[98.08853000000001,18.56231],"type":"Point"}
}