{
  "type": "Feature",
  "properties": {
    "gn:admin1_code":"53.0",
    "gn:asciiname":"Ban Thung Phao Tao",
    "gn:country_code":"TH",
    "gn:dem":8,
    "gn:feature_class":"P",
    "gn:feature_code":"PPL",
    "gn:name":"Ban Thung Phao Tao",
    "gn:population":0,
    "gn:timezone":"Asia/Bangkok",
    "iso:country":"TH",
    "name:tha_x_preferred":[
        "\u0e1a\u0e49\u0e32\u0e19\u0e17\u0e38\u0e48\u0e07\u0e40\u0e1c\u0e32\u0e40\u0e15\u0e48\u0e32"
    ],
    "name:und_x_variant":[
        "\u0e1a\u0e49\u0e32\u0e19\u0e17\u0e38\u0e48\u0e07\u0e40\u0e1c\u0e32\u0e40\u0e15\u0e48\u0e32"
    ],
    "wof:name":"Ban Thung Phao Tao",
    "wof:placetype":"locality"
},
  "geometry": {"coordinates":[100.0356,13.8647],"type":"Point"}
}