{
  "type": "Feature",
  "properties": {
    "gn:admin1_code":"3.0",
    "gn:asciiname":"Ban Langka",
    "gn:country_code":"TH",
    "gn:dem":547,
    "gn:feature_class":"P",
    "gn:feature_code":"PPL",
    "gn:name":"Ban Langka",
    "gn:population":0,
    "gn:timezone":"Asia/Bangkok",
    "iso:country":"TH",
    "name:tha_x_preferred":[
        "\u0e1a\u0e49\u0e32\u0e19\u0e25\u0e31\u0e07\u0e01\u0e32"
    ],
    "wof:lang_x_official":[
        "tha"
    ],
    "wof:lang_x_spoken":[
        "tha"
    ],
    "wof:name":"Ban Langka",
    "wof:placetype":"locality"
},
  "geometry": {"coordinates":[99.49703,19.33392000000001],"type":"Point"}
}