{
  "type": "Feature",
  "properties": {
    "gn:admin1_code":"28",
    "gn:asciiname":"Ban Dong Krathing",
    "gn:country_code":"TH",
    "gn:dem":149,
    "gn:feature_class":"P",
    "gn:feature_code":"PPL",
    "gn:name":"Ban Dong Krathing",
    "gn:population":0,
    "gn:timezone":"Asia/Bangkok",
    "iso:country":"TH",
    "name:tha_x_preferred":[
        "\u0e1a\u0e49\u0e32\u0e19\u0e14\u0e07\u0e01\u0e23\u0e30\u0e17\u0e34\u0e07"
    ],
    "wof:name":"Ban Dong Krathing",
    "wof:placetype":"locality"
},
  "geometry": {"coordinates":[103.16558000000001,15.15414],"type":"Point"}
}