{
  "type": "Feature",
  "properties": {
    "gn:admin1_code":"75.0",
    "gn:asciiname":"Ban Khok Thiam",
    "gn:country_code":"TH",
    "gn:dem":149,
    "gn:feature_class":"P",
    "gn:feature_code":"PPL",
    "gn:name":"Ban Khok Thiam",
    "gn:population":0,
    "gn:timezone":"Asia/Bangkok",
    "iso:country":"TH",
    "name:tha_x_preferred":[
        "\u0e1a\u0e49\u0e32\u0e19\u0e42\u0e04\u0e01\u0e40\u0e17\u0e35\u0e22\u0e21"
    ],
    "wof:name":"Ban Khok Thiam",
    "wof:placetype":"locality"
},
  "geometry": {"coordinates":[105.17756,14.71725],"type":"Point"}
}