{
  "type": "Feature",
  "properties": {
    "gn:admin1_code":"60.0",
    "gn:asciiname":"Ban Tha Rong Chang",
    "gn:country_code":"TH",
    "gn:dem":10,
    "gn:feature_class":"P",
    "gn:feature_code":"PPL",
    "gn:name":"Ban Tha Rong Chang",
    "gn:population":0,
    "gn:timezone":"Asia/Bangkok",
    "iso:country":"TH",
    "name:und_x_variant":[
        "Amphoe Dha Rong Jang",
        "Tha Rong Chang",
        "Amphoe Tha Rong Chang",
        "Ban Tah Rong Chaang",
        "Dha Rong Jang",
        "Ban Tha Rong Chang"
    ],
    "wof:name":"Ban Tha Rong Chang",
    "wof:placetype":"locality"
},
  "geometry": {"coordinates":[99.16425,9.08044],"type":"Point"}
}