{
  "type": "Feature",
  "properties": {
    "gn:admin1_code":"12.0",
    "gn:asciiname":"Ban Nam Sap",
    "gn:country_code":"TH",
    "gn:dem":74,
    "gn:feature_class":"P",
    "gn:feature_code":"PPL",
    "gn:name":"Ban Nam Sap",
    "gn:population":0,
    "gn:timezone":"Asia/Bangkok",
    "iso:country":"TH",
    "name:tha_x_preferred":[
        "\u0e1a\u0e49\u0e32\u0e19\u0e19\u0e49\u0e33\u0e17\u0e23\u0e31\u0e1e\u0e22\u0e4c"
    ],
    "wof:name":"Ban Nam Sap",
    "wof:placetype":"locality"
},
  "geometry": {"coordinates":[100.64717,16.39642000000001],"type":"Point"}
}