{
  "type": "Feature",
  "properties": {
    "gn:admin1_code":"1.0",
    "gn:asciiname":"Ban Mae Salap",
    "gn:country_code":"TH",
    "gn:dem":263,
    "gn:feature_class":"P",
    "gn:feature_code":"PPL",
    "gn:name":"Ban Mae Salap",
    "gn:population":0,
    "gn:timezone":"Asia/Bangkok",
    "iso:country":"TH",
    "name:tha_x_preferred":[
        "\u0e1a\u0e49\u0e32\u0e19\u0e41\u0e21\u0e48\u0e2a\u0e30\u0e25\u0e32\u0e1a"
    ],
    "wof:name":"Ban Mae Salap",
    "wof:placetype":"locality"
},
  "geometry": {"coordinates":[97.89572,18.16281],"type":"Point"}
}