{
  "type": "Feature",
  "properties": {
    "gn:admin1_code":"68.0",
    "gn:asciiname":"Ban Talat Na Thawi",
    "gn:country_code":"TH",
    "gn:dem":28,
    "gn:feature_class":"P",
    "gn:feature_code":"PPL",
    "gn:name":"Ban Talat Na Thawi",
    "gn:population":0,
    "gn:timezone":"Asia/Bangkok",
    "iso:country":"TH",
    "name:tha_x_preferred":[
        "\u0e1a\u0e49\u0e32\u0e19\u0e15\u0e25\u0e32\u0e14\u0e19\u0e32\u0e17\u0e27\u0e35"
    ],
    "wof:name":"Ban Talat Na Thawi",
    "wof:placetype":"locality"
},
  "geometry": {"coordinates":[100.68219000000001,6.74336],"type":"Point"}
}