{
  "type": "Feature",
  "properties": {
    "gn:admin1_code":"31.0",
    "gn:asciiname":"Ban Sai Ek",
    "gn:country_code":"TH",
    "gn:dem":112,
    "gn:feature_class":"P",
    "gn:feature_code":"PPL",
    "gn:name":"Ban Sai Ek",
    "gn:population":0,
    "gn:timezone":"Asia/Bangkok",
    "iso:country":"TH",
    "name:tha_x_preferred":[
        "\u0e1a\u0e49\u0e32\u0e19\u0e2a\u0e32\u0e22\u0e40\u0e2d\u0e01"
    ],
    "wof:name":"Ban Sai Ek",
    "wof:placetype":"locality"
},
  "geometry": {"coordinates":[101.78749999999999,5.93233],"type":"Point"}
}