{
  "type": "Feature",
  "properties": {
    "gn:admin1_code":"75.0",
    "gn:asciiname":"Ban Nong Mak Khaeng",
    "gn:country_code":"TH",
    "gn:dem":137,
    "gn:feature_class":"P",
    "gn:feature_code":"PPL",
    "gn:name":"Ban Nong Mak Khaeng",
    "gn:population":0,
    "gn:timezone":"Asia/Bangkok",
    "iso:country":"TH",
    "name:tha_x_preferred":[
        "\u0e1a\u0e49\u0e32\u0e19\u0e2b\u0e19\u0e2d\u0e07\u0e2b\u0e21\u0e32\u0e01\u0e41\u0e02\u0e49\u0e07"
    ],
    "wof:name":"Ban Nong Mak Khaeng",
    "wof:placetype":"locality"
},
  "geometry": {"coordinates":[104.89203000000001,15.17153],"type":"Point"}
}