{
  "type": "Feature",
  "properties": {
    "gn:admin1_code":"1.0",
    "gn:asciiname":"Ban Kho Kae",
    "gn:country_code":"TH",
    "gn:dem":703,
    "gn:feature_class":"P",
    "gn:feature_code":"PPL",
    "gn:name":"Ban Kho Kae",
    "gn:population":0,
    "gn:timezone":"Asia/Bangkok",
    "iso:country":"TH",
    "name:tha_x_preferred":[
        "\u0e1a\u0e49\u0e32\u0e19\u0e04\u0e2d\u0e41\u0e01"
    ],
    "name:und_x_variant":[
        "Ban Cho Kae",
        "Ban Kho Kae"
    ],
    "wof:name":"Ban Kho Kae",
    "wof:placetype":"locality"
},
  "geometry": {"coordinates":[97.76669,18.53481],"type":"Point"}
}