{
  "type": "Feature",
  "properties": {
    "gn:admin1_code":"43.0",
    "gn:asciiname":"Ban Som Phung Haeng (1)",
    "gn:country_code":"TH",
    "gn:dem":47,
    "gn:feature_class":"P",
    "gn:feature_code":"PPL",
    "gn:name":"Ban Som Phung Haeng (1)",
    "gn:population":0,
    "gn:timezone":"Asia/Bangkok",
    "iso:country":"TH",
    "wof:name":"Ban Som Phung Haeng (1)",
    "wof:placetype":"locality"
},
  "geometry": {"coordinates":[101.28333000000001,14.31667],"type":"Point"}
}