{
  "type": "Feature",
  "properties": {
    "gn:admin1_code":"6.0",
    "gn:asciiname":"Ban Rai Oi",
    "gn:country_code":"TH",
    "gn:dem":224,
    "gn:feature_class":"P",
    "gn:feature_code":"PPL",
    "gn:name":"Ban Rai Oi",
    "gn:population":0,
    "gn:timezone":"Asia/Bangkok",
    "iso:country":"TH",
    "name:tha_x_preferred":[
        "\u0e1a\u0e49\u0e32\u0e19\u0e44\u0e23\u0e48\u0e2d\u0e49\u0e2d\u0e22"
    ],
    "name:und_x_variant":[
        "Nong Muang",
        "Ban Rai Oi"
    ],
    "wof:name":"Ban Rai Oi",
    "wof:placetype":"locality"
},
  "geometry": {"coordinates":[99.40000000000001,18.18319],"type":"Point"}
}