{
  "type": "Feature",
  "properties": {
    "gn:admin1_code":"58.0",
    "gn:asciiname":"Ban Pak Lek",
    "gn:country_code":"TH",
    "gn:dem":79,
    "gn:feature_class":"P",
    "gn:feature_code":"PPL",
    "gn:name":"Ban Pak Lek",
    "gn:population":0,
    "gn:timezone":"Asia/Bangkok",
    "iso:country":"TH",
    "name:tha_x_preferred":[
        "\u0e1a\u0e49\u0e32\u0e19\u0e1b\u0e32\u0e01\u0e40\u0e25\u0e02"
    ],
    "wof:name":"Ban Pak Lek",
    "wof:placetype":"locality"
},
  "geometry": {"coordinates":[98.75288999999999,9.78183],"type":"Point"}
}