{
  "type": "Feature",
  "properties": {
    "gn:admin1_code":"76.0",
    "gn:asciiname":"Ban Tha Li",
    "gn:country_code":"TH",
    "gn:dem":176,
    "gn:feature_class":"P",
    "gn:feature_code":"PPL",
    "gn:name":"Ban Tha Li",
    "gn:population":0,
    "gn:timezone":"Asia/Bangkok",
    "iso:country":"TH",
    "name:tha_x_preferred":[
        "\u0e1a\u0e49\u0e32\u0e19\u0e17\u0e48\u0e32\u0e25\u0e35\u0e48"
    ],
    "name:und_x_variant":[
        "Ban Phali",
        "Ban Ta Li",
        "Ban Tha Li"
    ],
    "wof:lang_x_official":[
        "tha"
    ],
    "wof:lang_x_spoken":[
        "tha"
    ],
    "wof:name":"Ban Tha Li",
    "wof:placetype":"locality"
},
  "geometry": {"coordinates":[103.07478,16.9615],"type":"Point"}
}