{
  "type": "Feature",
  "properties": {
    "gn:admin1_code":"27.0",
    "gn:asciiname":"Ban Hua Thale",
    "gn:country_code":"TH",
    "gn:dem":183,
    "gn:feature_class":"P",
    "gn:feature_code":"PPL",
    "gn:name":"Ban Hua Thale",
    "gn:population":0,
    "gn:timezone":"Asia/Bangkok",
    "iso:country":"TH",
    "name:tha_x_preferred":[
        "\u0e1a\u0e49\u0e32\u0e19\u0e2b\u0e31\u0e27\u0e17\u0e30\u0e40\u0e25"
    ],
    "wof:name":"Ban Hua Thale",
    "wof:placetype":"locality"
},
  "geometry": {"coordinates":[102.11908,14.95536],"type":"Point"}
}