{
  "type": "Feature",
  "properties": {
    "gn:admin1_code":"20.0",
    "gn:asciiname":"Ban Lao Nokyung",
    "gn:country_code":"TH",
    "gn:dem":210,
    "gn:feature_class":"P",
    "gn:feature_code":"PPL",
    "gn:name":"Ban Lao Nokyung",
    "gn:population":0,
    "gn:timezone":"Asia/Bangkok",
    "iso:country":"TH",
    "name:tha_x_preferred":[
        "\u0e1a\u0e49\u0e32\u0e19\u0e40\u0e2b\u0e25\u0e48\u0e32\u0e19\u0e01\u0e22\u0e39\u0e07"
    ],
    "wof:name":"Ban Lao Nokyung",
    "wof:placetype":"locality"
},
  "geometry": {"coordinates":[104.10639,17.0262],"type":"Point"}
}