{
  "type": "Feature",
  "properties": {
    "gn:admin1_code":"27",
    "gn:asciiname":"Ban Mai Chai Narong",
    "gn:country_code":"TH",
    "gn:dem":268,
    "gn:feature_class":"P",
    "gn:feature_code":"PPL",
    "gn:name":"Ban Mai Chai Narong",
    "gn:population":0,
    "gn:timezone":"Asia/Bangkok",
    "iso:country":"TH",
    "name:tha_x_preferred":[
        "\u0e1a\u0e49\u0e32\u0e19\u0e43\u0e2b\u0e21\u0e48\u0e44\u0e0a\u0e22\u0e13\u0e23\u0e07\u0e04\u0e4c"
    ],
    "wof:name":"Ban Mai Chai Narong",
    "wof:placetype":"locality"
},
  "geometry": {"coordinates":[101.74476,15.11434],"type":"Point"}
}