{
  "type": "Feature",
  "properties": {
    "gn:admin1_code":"41.0",
    "gn:asciiname":"Ban Si Mueang Chum",
    "gn:country_code":"TH",
    "gn:dem":384,
    "gn:feature_class":"P",
    "gn:feature_code":"PPL",
    "gn:name":"Ban Si Mueang Chum",
    "gn:population":0,
    "gn:timezone":"Asia/Bangkok",
    "iso:country":"TH",
    "name:tha_x_preferred":[
        "\u0e1a\u0e49\u0e32\u0e19\u0e28\u0e23\u0e35\u0e40\u0e21\u0e37\u0e2d\u0e07\u0e0a\u0e38\u0e21"
    ],
    "wof:name":"Ban Si Mueang Chum",
    "wof:placetype":"locality"
},
  "geometry": {"coordinates":[100.07258,19.42947],"type":"Point"}
}