{
  "type": "Feature",
  "properties": {
    "gn:admin1_code":"27.0",
    "gn:asciiname":"Ban Mai Na Yao",
    "gn:country_code":"TH",
    "gn:dem":200,
    "gn:feature_class":"P",
    "gn:feature_code":"PPL",
    "gn:name":"Ban Mai Na Yao",
    "gn:population":0,
    "gn:timezone":"Asia/Bangkok",
    "iso:country":"TH",
    "wof:name":"Ban Mai Na Yao",
    "wof:placetype":"locality"
},
  "geometry": {"coordinates":[101.83111,15.22333],"type":"Point"}
}