{
  "type": "Feature",
  "properties": {
    "gn:admin1_code":"50.0",
    "gn:asciiname":"Ban Sawai Ba (1)",
    "gn:cc2":"TH",
    "gn:country_code":"TH",
    "gn:dem":416,
    "gn:feature_class":"P",
    "gn:feature_code":"PPL",
    "gn:name":"Ban Sawai Ba (1)",
    "gn:population":0,
    "gn:timezone":"Asia/Bangkok",
    "iso:country":"TH",
    "name:und_x_variant":[
        "Mae Phlu Bon",
        "Ban Sawai Ba (1)"
    ],
    "wof:name":"Ban Sawai Ba (1)",
    "wof:placetype":"locality"
},
  "geometry": {"coordinates":[99.21861,14.77278],"type":"Point"}
}