{
  "type": "Feature",
  "properties": {
    "gn:admin1_code":"28",
    "gn:asciiname":"Ban Khok Udom",
    "gn:country_code":"TH",
    "gn:dem":218,
    "gn:feature_class":"P",
    "gn:feature_code":"PPL",
    "gn:name":"Ban Khok Udom",
    "gn:population":0,
    "gn:timezone":"Asia/Bangkok",
    "iso:country":"TH",
    "name:tha_x_preferred":[
        "\u0e1a\u0e49\u0e32\u0e19\u0e42\u0e04\u0e01\u0e2d\u0e38\u0e14\u0e21"
    ],
    "wof:name":"Ban Khok Udom",
    "wof:placetype":"locality"
},
  "geometry": {"coordinates":[102.56758000000001,14.64347],"type":"Point"}
}