{
  "type": "Feature",
  "properties": {
    "gn:admin1_code":"55.0",
    "gn:asciiname":"Ban Bang Tho Lat",
    "gn:country_code":"TH",
    "gn:dem":7,
    "gn:feature_class":"P",
    "gn:feature_code":"PPL",
    "gn:name":"Ban Bang Tho Lat",
    "gn:population":0,
    "gn:timezone":"Asia/Bangkok",
    "iso:country":"TH",
    "name:tha_x_preferred":[
        "\u0e1a\u0e49\u0e32\u0e19\u0e1a\u0e32\u0e07\u0e42\u0e17\u0e25\u0e31\u0e14"
    ],
    "name:und_x_variant":[
        "Ban Bang Tho Rat",
        "Ban Bang Torad",
        "Ban Bang Tho Lak",
        "Ban Bang Tho Lat"
    ],
    "wof:lang_x_official":[
        "tha"
    ],
    "wof:lang_x_spoken":[
        "tha"
    ],
    "wof:name":"Ban Bang Tho Lat",
    "wof:placetype":"locality"
},
  "geometry": {"coordinates":[100.15868,13.49792],"type":"Point"}
}