{
  "type": "Feature",
  "properties": {
    "gn:admin1_code":"51.0",
    "gn:asciiname":"Ban Pong Talai",
    "gn:country_code":"TH",
    "gn:dem":10,
    "gn:feature_class":"P",
    "gn:feature_code":"PPL",
    "gn:name":"Ban Pong Talai",
    "gn:population":0,
    "gn:timezone":"Asia/Bangkok",
    "iso:country":"TH",
    "name:tha_x_preferred":[
        "\u0e1a\u0e49\u0e32\u0e19\u0e42\u0e1b\u0e48\u0e07\u0e15\u0e30\u0e44\u0e25"
    ],
    "wof:name":"Ban Pong Talai",
    "wof:placetype":"locality"
},
  "geometry": {"coordinates":[99.91564,14.19694],"type":"Point"}
}