{
  "type": "Feature",
  "properties": {
    "gn:admin1_code":"38.0",
    "gn:asciiname":"Ban Khung Nam Won",
    "gn:country_code":"TH",
    "gn:dem":5,
    "gn:feature_class":"P",
    "gn:feature_code":"PPL",
    "gn:name":"Ban Khung Nam Won",
    "gn:population":0,
    "gn:timezone":"Asia/Bangkok",
    "iso:country":"TH",
    "name:tha_x_preferred":[
        "\u0e1a\u0e49\u0e32\u0e19\u0e04\u0e38\u0e49\u0e07\u0e19\u0e49\u0e33\u0e27\u0e19"
    ],
    "wof:name":"Ban Khung Nam Won",
    "wof:placetype":"locality"
},
  "geometry": {"coordinates":[100.45135999999999,13.92131],"type":"Point"}
}