{
  "type": "Feature",
  "properties": {
    "gn:admin1_code":"12.0",
    "gn:asciiname":"Ban Nikhom Bang Rakam",
    "gn:country_code":"TH",
    "gn:dem":54,
    "gn:feature_class":"P",
    "gn:feature_code":"PPL",
    "gn:name":"Ban Nikhom Bang Rakam",
    "gn:population":0,
    "gn:timezone":"Asia/Bangkok",
    "iso:country":"TH",
    "name:tha_x_preferred":[
        "\u0e1a\u0e49\u0e32\u0e19\u0e19\u0e34\u0e04\u0e21\u0e1a\u0e32\u0e07\u0e23\u0e30\u0e01\u0e33"
    ],
    "wof:name":"Ban Nikhom Bang Rakam",
    "wof:placetype":"locality"
},
  "geometry": {"coordinates":[99.93492000000001,16.65478],"type":"Point"}
}