{
  "type": "Feature",
  "properties": {
    "gn:admin1_code":"79.0",
    "gn:asciiname":"Ban Nong Lao Khao",
    "gn:country_code":"TH",
    "gn:dem":232,
    "gn:feature_class":"P",
    "gn:feature_code":"PPL",
    "gn:name":"Ban Nong Lao Khao",
    "gn:population":0,
    "gn:timezone":"Asia/Bangkok",
    "iso:country":"TH",
    "name:tha_x_preferred":[
        "\u0e1a\u0e49\u0e32\u0e19\u0e2b\u0e19\u0e2d\u0e07\u0e40\u0e25\u0e49\u0e32\u0e02\u0e32\u0e27"
    ],
    "wof:name":"Ban Nong Lao Khao",
    "wof:placetype":"locality"
},
  "geometry": {"coordinates":[102.52064,16.98622],"type":"Point"}
}