{
  "type": "Feature",
  "properties": {
    "gn:admin1_code":"64.0",
    "gn:asciiname":"Ban Don Kloi",
    "gn:country_code":"TH",
    "gn:dem":7,
    "gn:feature_class":"P",
    "gn:feature_code":"PPL",
    "gn:name":"Ban Don Kloi",
    "gn:population":0,
    "gn:timezone":"Asia/Bangkok",
    "iso:country":"TH",
    "name:tha_x_preferred":[
        "\u0e1a\u0e49\u0e32\u0e19\u0e14\u0e2d\u0e19\u0e01\u0e25\u0e2d\u0e22"
    ],
    "wof:name":"Ban Don Kloi",
    "wof:placetype":"locality"
},
  "geometry": {"coordinates":[100.2135,7.95572],"type":"Point"}
}