{
  "type": "Feature",
  "properties": {
    "gn:admin1_code":"75.0",
    "gn:asciiname":"Ban Ari Phatthana",
    "gn:country_code":"TH",
    "gn:dem":158,
    "gn:feature_class":"P",
    "gn:feature_code":"PPL",
    "gn:name":"Ban Ari Phatthana",
    "gn:population":0,
    "gn:timezone":"Asia/Bangkok",
    "iso:country":"TH",
    "name:tha_x_preferred":[
        "\u0e1a\u0e49\u0e32\u0e19\u0e2d\u0e32\u0e23\u0e35\u0e22\u0e4c\u0e1e\u0e31\u0e12\u0e19\u0e32"
    ],
    "wof:name":"Ban Ari Phatthana",
    "wof:placetype":"locality"
},
  "geometry": {"coordinates":[105.1865,15.53672],"type":"Point"}
}