{
  "type": "Feature",
  "properties": {
    "gn:admin1_code":"68.0",
    "gn:asciiname":"Ban Chum Pho",
    "gn:country_code":"TH",
    "gn:dem":19,
    "gn:feature_class":"P",
    "gn:feature_code":"PPL",
    "gn:name":"Ban Chum Pho",
    "gn:population":0,
    "gn:timezone":"Asia/Bangkok",
    "iso:country":"TH",
    "name:tha_x_preferred":[
        "\u0e1a\u0e49\u0e32\u0e19\u0e0a\u0e38\u0e21\u0e1e\u0e2d"
    ],
    "wof:name":"Ban Chum Pho",
    "wof:placetype":"locality"
},
  "geometry": {"coordinates":[100.63081,7.11972],"type":"Point"}
}