{
  "type": "Feature",
  "properties": {
    "gn:admin1_code":"52.0",
    "gn:asciiname":"Ban Wat Prok Charoen",
    "gn:country_code":"TH",
    "gn:dem":10,
    "gn:feature_class":"P",
    "gn:feature_code":"PPL",
    "gn:name":"Ban Wat Prok Charoen",
    "gn:population":0,
    "gn:timezone":"Asia/Bangkok",
    "iso:country":"TH",
    "name:tha_x_preferred":[
        "\u0e1a\u0e49\u0e32\u0e19\u0e27\u0e31\u0e14\u0e1b\u0e23\u0e01\u0e40\u0e08\u0e23\u0e34\u0e0d"
    ],
    "wof:name":"Ban Wat Prok Charoen",
    "wof:placetype":"locality"
},
  "geometry": {"coordinates":[99.96093999999999,13.49608],"type":"Point"}
}