{
  "type": "Feature",
  "properties": {
    "gn:admin1_code":"63.0",
    "gn:asciiname":"Ban Ao Luek Noi",
    "gn:country_code":"TH",
    "gn:dem":31,
    "gn:feature_class":"P",
    "gn:feature_code":"PPL",
    "gn:name":"Ban Ao Luek Noi",
    "gn:population":0,
    "gn:timezone":"Asia/Bangkok",
    "iso:country":"TH",
    "name:tha_x_preferred":[
        "\u0e1a\u0e49\u0e32\u0e19\u0e2d\u0e48\u0e32\u0e27\u0e25\u0e36\u0e01\u0e19\u0e49\u0e2d\u0e22"
    ],
    "wof:name":"Ban Ao Luek Noi",
    "wof:placetype":"locality"
},
  "geometry": {"coordinates":[98.75021,8.29802],"type":"Point"}
}