{
  "type": "Feature",
  "properties": {
    "gn:admin1_code":"27",
    "gn:asciiname":"Ban Nong Hua Wua",
    "gn:country_code":"TH",
    "gn:dem":282,
    "gn:feature_class":"P",
    "gn:feature_code":"PPL",
    "gn:name":"Ban Nong Hua Wua",
    "gn:population":0,
    "gn:timezone":"Asia/Bangkok",
    "iso:country":"TH",
    "name:tha_x_preferred":[
        "\u0e1a\u0e49\u0e32\u0e19\u0e2b\u0e19\u0e2d\u0e07\u0e2b\u0e31\u0e27\u0e27\u0e31\u0e27"
    ],
    "wof:name":"Ban Nong Hua Wua",
    "wof:placetype":"locality"
},
  "geometry": {"coordinates":[101.63581000000001,14.96736],"type":"Point"}
}