{
  "type": "Feature",
  "properties": {
    "gn:admin1_code":"31.0",
    "gn:asciiname":"Ban Pu Yo",
    "gn:country_code":"TH",
    "gn:dem":10,
    "gn:feature_class":"P",
    "gn:feature_code":"PPL",
    "gn:name":"Ban Pu Yo",
    "gn:population":0,
    "gn:timezone":"Asia/Bangkok",
    "iso:country":"TH",
    "name:tha_x_preferred":[
        "\u0e1a\u0e49\u0e32\u0e19\u0e1b\u0e39\u0e42\u0e22\u0e30"
    ],
    "name:und_x_variant":[
        "Kampong Poyuk",
        "Kampong Poi",
        "Kampong Bo Yu",
        "Kampong Po Yu",
        "Ban Pu Yo"
    ],
    "wof:name":"Ban Pu Yo",
    "wof:placetype":"locality"
},
  "geometry": {"coordinates":[102.00097,6.08481],"type":"Point"}
}