{
  "type": "Feature",
  "properties": {
    "gn:admin1_code":"18.0",
    "gn:asciiname":"Ban Khua Mai Daeng",
    "gn:country_code":"TH",
    "gn:dem":300,
    "gn:feature_class":"P",
    "gn:feature_code":"PPL",
    "gn:name":"Ban Khua Mai Daeng",
    "gn:population":0,
    "gn:timezone":"Asia/Bangkok",
    "iso:country":"TH",
    "name:tha_x_preferred":[
        "Ban Khua Mai Daeng"
    ],
    "name:tha_x_variant":[
        "\u0e1a\u0e49\u0e32\u0e19\u0e02\u0e31\u0e27\u0e44\u0e21\u0e49\u0e41\u0e14\u0e07"
    ],
    "wof:name":"Ban Khua Mai Daeng",
    "wof:placetype":"locality"
},
  "geometry": {"coordinates":[101.95833,17.35822000000001],"type":"Point"}
}