{
  "type": "Feature",
  "properties": {
    "gn:admin1_code":"75.0",
    "gn:asciiname":"Ban Lat Yakha",
    "gn:country_code":"TH",
    "gn:dem":195,
    "gn:feature_class":"P",
    "gn:feature_code":"PPL",
    "gn:name":"Ban Lat Yakha",
    "gn:population":0,
    "gn:timezone":"Asia/Bangkok",
    "iso:country":"TH",
    "name:tha_x_preferred":[
        "\u0e1a\u0e49\u0e32\u0e19\u0e25\u0e32\u0e14\u0e2b\u0e0d\u0e49\u0e32\u0e04\u0e32"
    ],
    "wof:name":"Ban Lat Yakha",
    "wof:placetype":"locality"
},
  "geometry": {"coordinates":[104.99628,15.90022],"type":"Point"}
}