{
  "type": "Feature",
  "properties": {
    "gn:admin1_code":"79.0",
    "gn:asciiname":"Ban Na Wang",
    "gn:country_code":"TH",
    "gn:dem":270,
    "gn:feature_class":"P",
    "gn:feature_code":"PPL",
    "gn:name":"Ban Na Wang",
    "gn:population":0,
    "gn:timezone":"Asia/Bangkok",
    "iso:country":"TH",
    "name:tha_x_preferred":[
        "\u0e1a\u0e49\u0e32\u0e19\u0e19\u0e32\u0e27\u0e31\u0e07"
    ],
    "wof:name":"Ban Na Wang",
    "wof:placetype":"locality"
},
  "geometry": {"coordinates":[102.07666999999999,17.31794],"type":"Point"}
}