{
  "type": "Feature",
  "properties": {
    "gn:admin1_code":"75.0",
    "gn:asciiname":"Ban Phak Chonlaprathan",
    "gn:country_code":"TH",
    "gn:dem":152,
    "gn:feature_class":"P",
    "gn:feature_code":"PPL",
    "gn:name":"Ban Phak Chonlaprathan",
    "gn:population":0,
    "gn:timezone":"Asia/Bangkok",
    "iso:country":"TH",
    "name:tha_x_preferred":[
        "\u0e1a\u0e49\u0e32\u0e19\u0e1e\u0e31\u0e01\u0e0a\u0e25\u0e1b\u0e23\u0e30\u0e17\u0e32\u0e19"
    ],
    "wof:name":"Ban Phak Chonlaprathan",
    "wof:placetype":"locality"
},
  "geometry": {"coordinates":[105.34153000000001,15.05597],"type":"Point"}
}