{
  "type": "Feature",
  "properties": {
    "gn:admin1_code":"8.0",
    "gn:asciiname":"Ban Umphang Khi",
    "gn:country_code":"TH",
    "gn:dem":527,
    "gn:feature_class":"P",
    "gn:feature_code":"PPL",
    "gn:name":"Ban Umphang Khi",
    "gn:population":0,
    "gn:timezone":"Asia/Bangkok",
    "iso:country":"TH",
    "name:tha_x_preferred":[
        "\u0e1a\u0e49\u0e32\u0e19\u0e2d\u0e38\u0e49\u0e21\u0e1c\u0e32\u0e07\u0e04\u0e35"
    ],
    "wof:name":"Ban Umphang Khi",
    "wof:placetype":"locality"
},
  "geometry": {"coordinates":[98.93378,15.99695],"type":"Point"}
}