{
  "type": "Feature",
  "properties": {
    "gn:admin1_code":"3.0",
    "gn:asciiname":"Ban Cho Ko",
    "gn:country_code":"TH",
    "gn:dem":421,
    "gn:feature_class":"P",
    "gn:feature_code":"PPL",
    "gn:name":"Ban Cho Ko",
    "gn:population":0,
    "gn:timezone":"Asia/Bangkok",
    "iso:country":"TH",
    "name:tha_x_preferred":[
        "\u0e1a\u0e49\u0e32\u0e19\u0e42\u0e08\u0e49\u0e42\u0e01\u0e49"
    ],
    "name:und_x_variant":[
        "B\u0101n Daun Fuang",
        "Ban Don Fuang",
        "Ban Don Fueang"
    ],
    "wof:lang_x_official":[
        "tha"
    ],
    "wof:lang_x_spoken":[
        "tha"
    ],
    "wof:name":"Ban Cho Ko",
    "wof:placetype":"locality"
},
  "geometry": {"coordinates":[100.3081,19.75271],"type":"Point"}
}