{
  "type": "Feature",
  "properties": {
    "gn:admin1_code":"20.0",
    "gn:asciiname":"Ban Nong Hai Noi",
    "gn:country_code":"TH",
    "gn:dem":183,
    "gn:feature_class":"P",
    "gn:feature_code":"PPL",
    "gn:name":"Ban Nong Hai Noi",
    "gn:population":0,
    "gn:timezone":"Asia/Bangkok",
    "iso:country":"TH",
    "name:tha_x_preferred":[
        "\u0e1a\u0e49\u0e32\u0e19\u0e2b\u0e19\u0e2d\u0e07\u0e44\u0e2e\u0e19\u0e49\u0e2d\u0e22"
    ],
    "wof:name":"Ban Nong Hai Noi",
    "wof:placetype":"locality"
},
  "geometry": {"coordinates":[103.76443999999999,17.30714],"type":"Point"}
}