{
  "type": "Feature",
  "properties": {
    "gn:admin1_code":"3.0",
    "gn:asciiname":"Ban Pa Bong",
    "gn:country_code":"TH",
    "gn:dem":394,
    "gn:feature_class":"P",
    "gn:feature_code":"PPL",
    "gn:name":"Ban Pa Bong",
    "gn:population":0,
    "gn:timezone":"Asia/Bangkok",
    "iso:country":"TH",
    "name:tha_x_preferred":[
        "\u0e1a\u0e49\u0e32\u0e19\u0e1b\u0e48\u0e32\u0e1a\u0e07"
    ],
    "wof:name":"Ban Pa Bong",
    "wof:placetype":"locality"
},
  "geometry": {"coordinates":[99.89033999999999,19.9176],"type":"Point"}
}