{
  "type": "Feature",
  "properties": {
    "gn:admin1_code":"75.0",
    "gn:asciiname":"Ban Don Tap Tao",
    "gn:country_code":"TH",
    "gn:dem":146,
    "gn:feature_class":"P",
    "gn:feature_code":"PPL",
    "gn:name":"Ban Don Tap Tao",
    "gn:population":0,
    "gn:timezone":"Asia/Bangkok",
    "iso:country":"TH",
    "name:tha_x_preferred":[
        "\u0e1a\u0e49\u0e32\u0e19\u0e14\u0e2d\u0e19\u0e15\u0e31\u0e1a\u0e40\u0e15\u0e48\u0e32"
    ],
    "wof:name":"Ban Don Tap Tao",
    "wof:placetype":"locality"
},
  "geometry": {"coordinates":[105.27042,15.90978],"type":"Point"}
}