{
  "type": "Feature",
  "properties": {
    "gn:admin1_code":"26.0",
    "gn:asciiname":"Ban Na Wong Duean",
    "gn:country_code":"TH",
    "gn:dem":264,
    "gn:feature_class":"P",
    "gn:feature_code":"PPL",
    "gn:name":"Ban Na Wong Duean",
    "gn:population":0,
    "gn:timezone":"Asia/Bangkok",
    "iso:country":"TH",
    "name:tha_x_preferred":[
        "\u0e1a\u0e49\u0e32\u0e19\u0e19\u0e32\u0e27\u0e07\u0e40\u0e14\u0e37\u0e2d\u0e19"
    ],
    "name:und_x_variant":[
        "Ban Na Wong Duan"
    ],
    "wof:lang_x_official":[
        "tha"
    ],
    "wof:lang_x_spoken":[
        "tha"
    ],
    "wof:name":"Ban Na Wong Duean",
    "wof:placetype":"locality"
},
  "geometry": {"coordinates":[101.91439,16.58767000000001],"type":"Point"}
}