{
  "type": "Feature",
  "properties": {
    "gn:admin1_code":"4.0",
    "gn:asciiname":"Ban Khun Nam Sanan",
    "gn:country_code":"TH",
    "gn:dem":584,
    "gn:feature_class":"P",
    "gn:feature_code":"PPL",
    "gn:name":"Ban Khun Nam Sanan",
    "gn:population":0,
    "gn:timezone":"Asia/Bangkok",
    "iso:country":"TH",
    "name:tha_x_preferred":[
        "\u0e1a\u0e49\u0e32\u0e19\u0e02\u0e38\u0e19\u0e19\u0e49\u0e33\u0e2a\u0e19\u0e32\u0e19"
    ],
    "wof:name":"Ban Khun Nam Sanan",
    "wof:placetype":"locality"
},
  "geometry": {"coordinates":[101.06780999999999,18.90147],"type":"Point"}
}