{
  "type": "Feature",
  "properties": {
    "gn:admin1_code":"2.0",
    "gn:asciiname":"Ban Si Dong Yen",
    "gn:country_code":"TH",
    "gn:dem":503,
    "gn:feature_class":"P",
    "gn:feature_code":"PPL",
    "gn:name":"Ban Si Dong Yen",
    "gn:population":0,
    "gn:timezone":"Asia/Bangkok",
    "iso:country":"TH",
    "name:tha_x_preferred":[
        "\u0e1a\u0e49\u0e32\u0e19\u0e28\u0e23\u0e35\u0e14\u0e07\u0e40\u0e22\u0e47\u0e19"
    ],
    "wof:name":"Ban Si Dong Yen",
    "wof:placetype":"locality"
},
  "geometry": {"coordinates":[99.14592,19.70372],"type":"Point"}
}