{
  "type": "Feature",
  "properties": {
    "gn:admin1_code":"12.0",
    "gn:asciiname":"Ban I Len",
    "gn:cc2":"TH",
    "gn:country_code":"TH",
    "gn:dem":45,
    "gn:feature_class":"P",
    "gn:feature_code":"PPL",
    "gn:name":"Ban I Len",
    "gn:population":0,
    "gn:timezone":"Asia/Bangkok",
    "iso:country":"TH",
    "name:und_x_variant":[
        "Ban Naung-i-Len Yai",
        "Ban Nong I Len Yai",
        "Ban I Len"
    ],
    "wof:lang_x_official":[
        "tha"
    ],
    "wof:lang_x_spoken":[
        "tha"
    ],
    "wof:name":"Ban I Len",
    "wof:placetype":"locality"
},
  "geometry": {"coordinates":[100.33333,16.95],"type":"Point"}
}