{
  "type": "Feature",
  "properties": {
    "gn:admin1_code":"27.0",
    "gn:asciiname":"Ban Khlong Khwang",
    "gn:country_code":"TH",
    "gn:dem":216,
    "gn:feature_class":"P",
    "gn:feature_code":"PPL",
    "gn:name":"Ban Khlong Khwang",
    "gn:population":0,
    "gn:timezone":"Asia/Bangkok",
    "iso:country":"TH",
    "name:tha_x_preferred":[
        "\u0e1a\u0e49\u0e32\u0e19\u0e04\u0e25\u0e2d\u0e07\u0e02\u0e27\u0e32\u0e07"
    ],
    "name:und_x_variant":[
        "Ban Klong Kwang",
        "Ban Khlong Khwang"
    ],
    "wof:name":"Ban Khlong Khwang",
    "wof:placetype":"locality"
},
  "geometry": {"coordinates":[101.79217,14.91581],"type":"Point"}
}