{
  "type": "Feature",
  "properties": {
    "gn:admin1_code":"46.0",
    "gn:asciiname":"Ban Na Phrathat",
    "gn:country_code":"TH",
    "gn:dem":9,
    "gn:feature_class":"P",
    "gn:feature_code":"PPL",
    "gn:name":"Ban Na Phrathat",
    "gn:population":0,
    "gn:timezone":"Asia/Bangkok",
    "iso:country":"TH",
    "name:tha_x_preferred":[
        "\u0e1a\u0e49\u0e32\u0e19\u0e2b\u0e19\u0e49\u0e32\u0e1e\u0e23\u0e30\u0e18\u0e32\u0e15\u0e38"
    ],
    "name:und_x_variant":[
        "Na Prathat",
        "Ban Na Phrathat"
    ],
    "wof:name":"Ban Na Phrathat",
    "wof:placetype":"locality"
},
  "geometry": {"coordinates":[101.16428000000001,13.46689],"type":"Point"}
}