{
  "type": "Feature",
  "properties": {
    "gn:admin1_code":"63.0",
    "gn:asciiname":"Ban Thung",
    "gn:country_code":"TH",
    "gn:dem":79,
    "gn:feature_class":"P",
    "gn:feature_code":"PPL",
    "gn:name":"Ban Thung",
    "gn:population":0,
    "gn:timezone":"Asia/Bangkok",
    "iso:country":"TH",
    "name:tha_x_preferred":[
        "\u0e1a\u0e49\u0e32\u0e19\u0e17\u0e38\u0e48\u0e07"
    ],
    "name:und_x_variant":[
        "Ban Thung Khwai"
    ],
    "wof:name":"Ban Thung",
    "wof:placetype":"locality"
},
  "geometry": {"coordinates":[98.80108,8.40431],"type":"Point"}
}