{
  "type": "Feature",
  "properties": {
    "gn:admin1_code":"12.0",
    "gn:asciiname":"Ban Kraphuang",
    "gn:country_code":"TH",
    "gn:dem":46,
    "gn:feature_class":"P",
    "gn:feature_code":"PPL",
    "gn:name":"Ban Kraphuang",
    "gn:population":0,
    "gn:timezone":"Asia/Bangkok",
    "iso:country":"TH",
    "name:tha_x_preferred":[
        "\u0e1a\u0e49\u0e32\u0e19\u0e01\u0e23\u0e30\u0e1e\u0e27\u0e07"
    ],
    "name:und_x_variant":[
        "B\u0101n Gaphuang",
        "Ban Kaphuang",
        "Ban Kraphuang"
    ],
    "wof:name":"Ban Kraphuang",
    "wof:placetype":"locality"
},
  "geometry": {"coordinates":[100.19423999999999,16.69609],"type":"Point"}
}