{
  "type": "Feature",
  "properties": {
    "gn:admin1_code":"2.0",
    "gn:asciiname":"Ban Pang Tat",
    "gn:country_code":"TH",
    "gn:dem":881,
    "gn:feature_class":"P",
    "gn:feature_code":"PPL",
    "gn:name":"Ban Pang Tat",
    "gn:population":0,
    "gn:timezone":"Asia/Bangkok",
    "iso:country":"TH",
    "name:tha_x_preferred":[
        "\u0e1a\u0e49\u0e32\u0e19\u0e1b\u0e32\u0e07\u0e15\u0e32\u0e14"
    ],
    "wof:name":"Ban Pang Tat",
    "wof:placetype":"locality"
},
  "geometry": {"coordinates":[98.87231,19.31464],"type":"Point"}
}