{
  "type": "Feature",
  "properties": {
    "gn:admin1_code":"50.0",
    "gn:asciiname":"Ban Nong Khai Kai",
    "gn:cc2":"TH",
    "gn:country_code":"TH",
    "gn:dem":124,
    "gn:feature_class":"P",
    "gn:feature_code":"PPL",
    "gn:name":"Ban Nong Khai Kai",
    "gn:population":0,
    "gn:timezone":"Asia/Bangkok",
    "iso:country":"TH",
    "name:und_x_variant":[
        "Ban Hnong Khie Kie",
        "Ban Nong Khai Kai"
    ],
    "wof:name":"Ban Nong Khai Kai",
    "wof:placetype":"locality"
},
  "geometry": {"coordinates":[99.46666999999999,14.55],"type":"Point"}
}