{
  "type": "Feature",
  "properties": {
    "gn:admin1_code":"68.0",
    "gn:asciiname":"Ban Nikhom Phatthana",
    "gn:country_code":"TH",
    "gn:dem":40,
    "gn:feature_class":"P",
    "gn:feature_code":"PPL",
    "gn:name":"Ban Nikhom Phatthana",
    "gn:population":0,
    "gn:timezone":"Asia/Bangkok",
    "iso:country":"TH",
    "name:tha_x_preferred":[
        "\u0e1a\u0e49\u0e32\u0e19\u0e19\u0e34\u0e04\u0e21\u0e1e\u0e31\u0e12\u0e19\u0e32"
    ],
    "wof:name":"Ban Nikhom Phatthana",
    "wof:placetype":"locality"
},
  "geometry": {"coordinates":[100.25492,7.06208],"type":"Point"}
}