{
  "type": "Feature",
  "properties": {
    "gn:admin1_code":"69.0",
    "gn:asciiname":"Ban Ka Lae Ta Ma",
    "gn:country_code":"TH",
    "gn:dem":4,
    "gn:feature_class":"P",
    "gn:feature_code":"PPL",
    "gn:name":"Ban Ka Lae Ta Ma",
    "gn:population":0,
    "gn:timezone":"Asia/Bangkok",
    "iso:country":"TH",
    "name:tha_x_preferred":[
        "\u0e1a\u0e49\u0e32\u0e19\u0e01\u0e32\u0e41\u0e25\u0e30\u0e15\u0e32\u0e21\u0e30"
    ],
    "wof:lang_x_official":[
        "tha"
    ],
    "wof:lang_x_spoken":[
        "tha"
    ],
    "wof:name":"Ban Ka Lae Ta Ma",
    "wof:placetype":"locality"
},
  "geometry": {"coordinates":[101.41733000000001,6.77372],"type":"Point"}
}