{
  "type": "Feature",
  "properties": {
    "gn:admin1_code":"60.0",
    "gn:asciiname":"Ban Khuan Charoen",
    "gn:country_code":"TH",
    "gn:dem":31,
    "gn:feature_class":"P",
    "gn:feature_code":"PPL",
    "gn:name":"Ban Khuan Charoen",
    "gn:population":0,
    "gn:timezone":"Asia/Bangkok",
    "iso:country":"TH",
    "name:tha_x_preferred":[
        "\u0e1a\u0e49\u0e32\u0e19\u0e04\u0e27\u0e19\u0e40\u0e08\u0e23\u0e34\u0e0d"
    ],
    "wof:name":"Ban Khuan Charoen",
    "wof:placetype":"locality"
},
  "geometry": {"coordinates":[99.34444000000001,8.60047],"type":"Point"}
}