{
  "type": "Feature",
  "properties": {
    "gn:admin1_code":"11.0",
    "gn:asciiname":"Ban Khui Mamuang Hom",
    "gn:country_code":"TH",
    "gn:dem":71,
    "gn:feature_class":"P",
    "gn:feature_code":"PPL",
    "gn:name":"Ban Khui Mamuang Hom",
    "gn:population":0,
    "gn:timezone":"Asia/Bangkok",
    "iso:country":"TH",
    "name:tha_x_preferred":[
        "\u0e1a\u0e49\u0e32\u0e19\u0e04\u0e38\u0e22\u0e21\u0e30\u0e21\u0e48\u0e27\u0e07\u0e2b\u0e2d\u0e21"
    ],
    "wof:name":"Ban Khui Mamuang Hom",
    "wof:placetype":"locality"
},
  "geometry": {"coordinates":[99.58432999999999,16.68772],"type":"Point"}
}