{
  "type": "Feature",
  "properties": {
    "gn:admin1_code":"43.0",
    "gn:asciiname":"Ban Kamphaeng Sian",
    "gn:country_code":"TH",
    "gn:dem":5,
    "gn:feature_class":"P",
    "gn:feature_code":"PPL",
    "gn:name":"Ban Kamphaeng Sian",
    "gn:population":0,
    "gn:timezone":"Asia/Bangkok",
    "iso:country":"TH",
    "name:tha_x_preferred":[
        "\u0e1a\u0e49\u0e32\u0e19\u0e01\u0e33\u0e41\u0e1e\u0e07\u0e40\u0e28\u0e35\u0e22\u0e23"
    ],
    "name:und_x_variant":[
        "Kam Peng Sien",
        "Ban Kamphaeng Sian"
    ],
    "wof:lang_x_official":[
        "tha"
    ],
    "wof:lang_x_spoken":[
        "tha"
    ],
    "wof:name":"Ban Kamphaeng Sian",
    "wof:placetype":"locality"
},
  "geometry": {"coordinates":[101.18825,14.06036],"type":"Point"}
}