{
  "type": "Feature",
  "properties": {
    "gn:admin1_code":"8.0",
    "gn:asciiname":"Ban Wa Bop Khi",
    "gn:country_code":"TH",
    "gn:dem":883,
    "gn:feature_class":"P",
    "gn:feature_code":"PPL",
    "gn:name":"Ban Wa Bop Khi",
    "gn:population":0,
    "gn:timezone":"Asia/Bangkok",
    "iso:country":"TH",
    "name:tha_x_preferred":[
        "\u0e1a\u0e49\u0e32\u0e19\u0e27\u0e30\u0e42\u0e1a\u0e1a\u0e04\u0e35"
    ],
    "wof:name":"Ban Wa Bop Khi",
    "wof:placetype":"locality"
},
  "geometry": {"coordinates":[98.27197,17.39936],"type":"Point"}
}