{
  "type": "Feature",
  "properties": {
    "gn:admin1_code":"64.0",
    "gn:asciiname":"Ban Chan Di",
    "gn:country_code":"TH",
    "gn:dem":6,
    "gn:feature_class":"P",
    "gn:feature_code":"PPL",
    "gn:name":"Ban Chan Di",
    "gn:population":0,
    "gn:timezone":"Asia/Bangkok",
    "iso:country":"TH",
    "name:tha_x_preferred":[
        "\u0e1a\u0e49\u0e32\u0e19\u0e08\u0e31\u0e19\u0e14\u0e35"
    ],
    "wof:name":"Ban Chan Di",
    "wof:placetype":"locality"
},
  "geometry": {"coordinates":[100.22996999999999,8.15464],"type":"Point"}
}