{
  "type": "Feature",
  "properties": {
    "gn:admin1_code":"80.0",
    "gn:asciiname":"Ban Sap Phlu Nuea",
    "gn:country_code":"TH",
    "gn:dem":130,
    "gn:feature_class":"P",
    "gn:feature_code":"PPL",
    "gn:name":"Ban Sap Phlu Nuea",
    "gn:population":0,
    "gn:timezone":"Asia/Bangkok",
    "iso:country":"TH",
    "name:tha_x_preferred":[
        "\u0e1a\u0e49\u0e32\u0e19\u0e0b\u0e31\u0e1a\u0e1e\u0e25\u0e39\u0e40\u0e2b\u0e19\u0e37\u0e2d"
    ],
    "name:und_x_variant":[
        "Ban Sap Phlu",
        "Ban Sup Phlu Nuea",
        "Ban Sap Phlu Nuea"
    ],
    "wof:name":"Ban Sap Phlu Nuea",
    "wof:placetype":"locality"
},
  "geometry": {"coordinates":[102.29877999999999,13.5195],"type":"Point"}
}