{
  "type": "Feature",
  "properties": {
    "gn:admin1_code":"49.0",
    "gn:asciiname":"Ban Noen Tabok",
    "gn:country_code":"TH",
    "gn:dem":36,
    "gn:feature_class":"P",
    "gn:feature_code":"PPL",
    "gn:name":"Ban Noen Tabok",
    "gn:population":0,
    "gn:timezone":"Asia/Bangkok",
    "iso:country":"TH",
    "name:tha_x_preferred":[
        "\u0e1a\u0e49\u0e32\u0e19\u0e40\u0e19\u0e34\u0e19\u0e15\u0e30\u0e1a\u0e01"
    ],
    "wof:name":"Ban Noen Tabok",
    "wof:placetype":"locality"
},
  "geometry": {"coordinates":[102.40971999999999,12.40636],"type":"Point"}
}