{
  "type": "Feature",
  "properties": {
    "gn:admin1_code":"72.0",
    "gn:asciiname":"Ban Nong Khaen Noi",
    "gn:country_code":"TH",
    "gn:dem":208,
    "gn:feature_class":"P",
    "gn:feature_code":"PPL",
    "gn:name":"Ban Nong Khaen Noi",
    "gn:population":0,
    "gn:timezone":"Asia/Bangkok",
    "iso:country":"TH",
    "name:tha_x_preferred":[
        "\u0e1a\u0e49\u0e32\u0e19\u0e2b\u0e19\u0e2d\u0e07\u0e41\u0e04\u0e19\u0e19\u0e49\u0e2d\u0e22"
    ],
    "wof:name":"Ban Nong Khaen Noi",
    "wof:placetype":"locality"
},
  "geometry": {"coordinates":[104.72589000000001,16.13914],"type":"Point"}
}