{
  "type": "Feature",
  "properties": {
    "gn:admin1_code":"60.0",
    "gn:asciiname":"Ban Bang Tha Kham",
    "gn:country_code":"TH",
    "gn:dem":6,
    "gn:feature_class":"P",
    "gn:feature_code":"PPL",
    "gn:name":"Ban Bang Tha Kham",
    "gn:population":0,
    "gn:timezone":"Asia/Bangkok",
    "iso:country":"TH",
    "name:tha_x_preferred":[
        "\u0e1a\u0e49\u0e32\u0e19\u0e1a\u0e32\u0e07\u0e2d\u0e32\u0e02\u0e49\u0e32\u0e21"
    ],
    "name:und_x_variant":[
        "Ban Huai Kam"
    ],
    "wof:name":"Ban Bang Tha Kham",
    "wof:placetype":"locality"
},
  "geometry": {"coordinates":[99.23296999999999,9.09714],"type":"Point"}
}