{
  "type": "Feature",
  "properties": {
    "gn:admin1_code":"2.0",
    "gn:asciiname":"Ban Mae Ngon Klang",
    "gn:country_code":"TH",
    "gn:dem":486,
    "gn:feature_class":"P",
    "gn:feature_code":"PPL",
    "gn:name":"Ban Mae Ngon Klang",
    "gn:population":0,
    "gn:timezone":"Asia/Bangkok",
    "iso:country":"TH",
    "name:tha_x_preferred":[
        "\u0e1a\u0e49\u0e32\u0e19\u0e41\u0e21\u0e48\u0e07\u0e2d\u0e19\u0e01\u0e25\u0e32\u0e07"
    ],
    "name:und_x_variant":[
        "Mae Ngon Klang",
        "B\u0101n Mea Ngaun Gl\u0101ng",
        "Ban Mae Ngon Klang"
    ],
    "wof:name":"Ban Mae Ngon Klang",
    "wof:placetype":"locality"
},
  "geometry": {"coordinates":[99.16755999999999,19.80128],"type":"Point"}
}