{
  "type": "Feature",
  "properties": {
    "gn:admin1_code":"5.0",
    "gn:asciiname":"Ban Muang Pom",
    "gn:cc2":"TH",
    "gn:country_code":"TH",
    "gn:dem":283,
    "gn:feature_class":"P",
    "gn:feature_code":"PPL",
    "gn:name":"Ban Muang Pom",
    "gn:population":0,
    "gn:timezone":"Asia/Bangkok",
    "iso:country":"TH",
    "name:und_x_variant":[
        "B\u0101n Muang Paum",
        "Ban Muang Pom"
    ],
    "wof:name":"Ban Muang Pom",
    "wof:placetype":"locality"
},
  "geometry": {"coordinates":[98.73333,18.41667],"type":"Point"}
}