{
  "type": "Feature",
  "properties": {
    "gn:admin1_code":"28.0",
    "gn:asciiname":"Ban Ngang",
    "gn:country_code":"TH",
    "gn:dem":152,
    "gn:feature_class":"P",
    "gn:feature_code":"PPL",
    "gn:name":"Ban Ngang",
    "gn:population":0,
    "gn:timezone":"Asia/Bangkok",
    "iso:country":"TH",
    "name:tha_x_preferred":[
        "\u0e1a\u0e49\u0e32\u0e19\u0e07\u0e49\u0e32\u0e07"
    ],
    "wof:name":"Ban Ngang",
    "wof:placetype":"locality"
},
  "geometry": {"coordinates":[103.19083000000001,15.03053],"type":"Point"}
}