{
  "type": "Feature",
  "properties": {
    "gn:admin1_code":"43.0",
    "gn:asciiname":"Ban Tha Daeng",
    "gn:country_code":"TH",
    "gn:dem":8,
    "gn:feature_class":"P",
    "gn:feature_code":"PPL",
    "gn:name":"Ban Tha Daeng",
    "gn:population":0,
    "gn:timezone":"Asia/Bangkok",
    "iso:country":"TH",
    "name:tha_x_preferred":[
        "\u0e1a\u0e49\u0e32\u0e19\u0e17\u0e48\u0e32\u0e41\u0e14\u0e07"
    ],
    "name:und_x_variant":[
        "Ban Ta Daeng",
        "Ban Tha Daeng"
    ],
    "wof:name":"Ban Tha Daeng",
    "wof:placetype":"locality"
},
  "geometry": {"coordinates":[101.2745,14.16058],"type":"Point"}
}