{
  "type": "Feature",
  "properties": {
    "gn:admin1_code":"50.0",
    "gn:asciiname":"Ban Si Mongkhon",
    "gn:country_code":"TH",
    "gn:dem":68,
    "gn:feature_class":"P",
    "gn:feature_code":"PPL",
    "gn:name":"Ban Si Mongkhon",
    "gn:population":0,
    "gn:timezone":"Asia/Bangkok",
    "iso:country":"TH",
    "name:tha_x_preferred":[
        "\u0e1a\u0e49\u0e32\u0e19\u0e28\u0e23\u0e35\u0e21\u0e07\u0e04\u0e25"
    ],
    "name:und_x_variant":[
        "Naung Si Mong Khon",
        "Ban Hnong Sri Mongol",
        "B\u0101n Hnohng Sri Mong-gol",
        "Ban Nong Si Mongkhon",
        "Ban Si Mongkhon"
    ],
    "wof:name":"Ban Si Mongkhon",
    "wof:placetype":"locality"
},
  "geometry": {"coordinates":[99.15558,14.0205],"type":"Point"}
}