{
  "type": "Feature",
  "properties": {
    "gn:admin1_code":"2.0",
    "gn:asciiname":"Ban Fon",
    "gn:country_code":"TH",
    "gn:dem":334,
    "gn:feature_class":"P",
    "gn:feature_code":"PPL",
    "gn:name":"Ban Fon",
    "gn:population":0,
    "gn:timezone":"Asia/Bangkok",
    "iso:country":"TH",
    "name:tha_x_preferred":[
        "\u0e1a\u0e49\u0e32\u0e19\u0e1f\u0e48\u0e2d\u0e19"
    ],
    "name:und_x_variant":[
        "B\u0101n Faun",
        "Ban Fon"
    ],
    "wof:name":"Ban Fon",
    "wof:placetype":"locality"
},
  "geometry": {"coordinates":[98.90514,18.73492],"type":"Point"}
}