{
  "type": "Feature",
  "properties": {
    "gn:admin1_code":"11.0",
    "gn:asciiname":"Ban Khui Ban Ong",
    "gn:country_code":"TH",
    "gn:dem":62,
    "gn:feature_class":"P",
    "gn:feature_code":"PPL",
    "gn:name":"Ban Khui Ban Ong",
    "gn:population":0,
    "gn:timezone":"Asia/Bangkok",
    "iso:country":"TH",
    "name:tha_x_preferred":[
        "\u0e1a\u0e49\u0e32\u0e19\u0e04\u0e38\u0e22\u0e1a\u0e49\u0e32\u0e19\u0e42\u0e2d\u0e48\u0e07"
    ],
    "wof:name":"Ban Khui Ban Ong",
    "wof:placetype":"locality"
},
  "geometry": {"coordinates":[99.66022,16.66761],"type":"Point"}
}