{
  "type": "Feature",
  "properties": {
    "gn:admin1_code":"55.0",
    "gn:asciiname":"Muban Kanda",
    "gn:country_code":"TH",
    "gn:dem":3,
    "gn:feature_class":"P",
    "gn:feature_code":"PPL",
    "gn:name":"Muban Kanda",
    "gn:population":0,
    "gn:timezone":"Asia/Bangkok",
    "iso:country":"TH",
    "name:tha_x_preferred":[
        "\u0e2b\u0e21\u0e39\u0e48\u0e1a\u0e49\u0e32\u0e19\u0e01\u0e32\u0e19\u0e14\u0e32"
    ],
    "wof:name":"Muban Kanda",
    "wof:placetype":"locality"
},
  "geometry": {"coordinates":[100.36888999999999,13.58731],"type":"Point"}
}