{
  "type": "Feature",
  "properties": {
    "gn:admin1_code":"1.0",
    "gn:asciiname":"Ban Maeo Khun Mae U-Kho",
    "gn:country_code":"TH",
    "gn:dem":1281,
    "gn:feature_class":"P",
    "gn:feature_code":"PPL",
    "gn:name":"Ban Maeo Khun Mae U-Kho",
    "gn:population":0,
    "gn:timezone":"Asia/Bangkok",
    "iso:country":"TH",
    "wof:name":"Ban Maeo Khun Mae U-Kho",
    "wof:placetype":"locality"
},
  "geometry": {"coordinates":[98.10722,18.97083],"type":"Point"}
}