{
  "type": "Feature",
  "properties": {
    "gn:admin1_code":"50.0",
    "gn:asciiname":"Ban Pak Mueang",
    "gn:country_code":"TH",
    "gn:dem":262,
    "gn:feature_class":"P",
    "gn:feature_code":"PPL",
    "gn:name":"Ban Pak Mueang",
    "gn:population":0,
    "gn:timezone":"Asia/Bangkok",
    "iso:country":"TH",
    "name:tha_x_preferred":[
        "\u0e1a\u0e49\u0e32\u0e19\u0e1b\u0e32\u0e01\u0e40\u0e2b\u0e21\u0e37\u0e2d\u0e07"
    ],
    "wof:name":"Ban Pak Mueang",
    "wof:placetype":"locality"
},
  "geometry": {"coordinates":[98.98886,14.64897],"type":"Point"}
}