{
  "type": "Feature",
  "properties": {
    "gn:admin1_code":"53.0",
    "gn:asciiname":"Ban Bo Takua",
    "gn:country_code":"TH",
    "gn:dem":4,
    "gn:feature_class":"P",
    "gn:feature_code":"PPL",
    "gn:name":"Ban Bo Takua",
    "gn:population":0,
    "gn:timezone":"Asia/Bangkok",
    "iso:country":"TH",
    "name:tha_x_preferred":[
        "\u0e1a\u0e49\u0e32\u0e19\u0e1a\u0e48\u0e2d\u0e15\u0e30\u0e01\u0e31\u0e48\u0e27"
    ],
    "wof:name":"Ban Bo Takua",
    "wof:placetype":"locality"
},
  "geometry": {"coordinates":[100.12211000000001,13.77839],"type":"Point"}
}