{
  "type": "Feature",
  "properties": {
    "gn:admin1_code":"51.0",
    "gn:asciiname":"Ban Pho Naruemit",
    "gn:country_code":"TH",
    "gn:dem":11,
    "gn:feature_class":"P",
    "gn:feature_code":"PPL",
    "gn:name":"Ban Pho Naruemit",
    "gn:population":0,
    "gn:timezone":"Asia/Bangkok",
    "iso:country":"TH",
    "name:tha_x_preferred":[
        "\u0e1a\u0e49\u0e32\u0e19\u0e42\u0e1e\u0e18\u0e34\u0e4c\u0e19\u0e24\u0e21\u0e34\u0e15\u0e23"
    ],
    "wof:name":"Ban Pho Naruemit",
    "wof:placetype":"locality"
},
  "geometry": {"coordinates":[100.14814,14.71664],"type":"Point"}
}