{
  "type": "Feature",
  "properties": {
    "gn:admin1_code":"76.0",
    "gn:asciiname":"Ban Sao Lao",
    "gn:country_code":"TH",
    "gn:dem":235,
    "gn:feature_class":"P",
    "gn:feature_code":"PPL",
    "gn:name":"Ban Sao Lao",
    "gn:population":0,
    "gn:timezone":"Asia/Bangkok",
    "iso:country":"TH",
    "name:tha_x_preferred":[
        "\u0e1a\u0e49\u0e32\u0e19\u0e40\u0e2a\u0e32\u0e40\u0e25\u0e49\u0e32"
    ],
    "wof:name":"Ban Sao Lao",
    "wof:placetype":"locality"
},
  "geometry": {"coordinates":[102.57966999999999,17.12731],"type":"Point"}
}