{
  "type": "Feature",
  "properties": {
    "gn:admin1_code":"54.0",
    "gn:asciiname":"Ban Khlong Khut Lek",
    "gn:country_code":"TH",
    "gn:dem":7,
    "gn:feature_class":"P",
    "gn:feature_code":"PPL",
    "gn:name":"Ban Khlong Khut Lek",
    "gn:population":0,
    "gn:timezone":"Asia/Bangkok",
    "iso:country":"TH",
    "name:tha_x_preferred":[
        "\u0e1a\u0e49\u0e32\u0e19\u0e04\u0e25\u0e2d\u0e07\u0e02\u0e38\u0e14\u0e40\u0e25\u0e47\u0e01"
    ],
    "name:und_x_variant":[
        "Ban Khlong Khut Noi"
    ],
    "wof:name":"Ban Khlong Khut Lek",
    "wof:placetype":"locality"
},
  "geometry": {"coordinates":[99.93644,13.37142],"type":"Point"}
}