{
  "type": "Feature",
  "properties": {
    "gn:admin1_code":"46.0",
    "gn:asciiname":"Ban Khlong Ta Phet Lang",
    "gn:country_code":"TH",
    "gn:dem":74,
    "gn:feature_class":"P",
    "gn:feature_code":"PPL",
    "gn:name":"Ban Khlong Ta Phet Lang",
    "gn:population":0,
    "gn:timezone":"Asia/Bangkok",
    "iso:country":"TH",
    "name:tha_x_preferred":[
        "\u0e1a\u0e49\u0e32\u0e19\u0e04\u0e25\u0e2d\u0e07\u0e15\u0e32\u0e40\u0e1e\u0e0a\u0e23\u0e25\u0e48\u0e32\u0e07"
    ],
    "wof:name":"Ban Khlong Ta Phet Lang",
    "wof:placetype":"locality"
},
  "geometry": {"coordinates":[101.53858,13.24114],"type":"Point"}
}