{
  "type": "Feature",
  "properties": {
    "gn:admin1_code":"14.0",
    "gn:asciiname":"Ban Thung Tanot",
    "gn:country_code":"TH",
    "gn:dem":65,
    "gn:feature_class":"P",
    "gn:feature_code":"PPL",
    "gn:name":"Ban Thung Tanot",
    "gn:population":0,
    "gn:timezone":"Asia/Bangkok",
    "iso:country":"TH",
    "name:tha_x_preferred":[
        "\u0e1a\u0e49\u0e32\u0e19\u0e17\u0e38\u0e48\u0e07\u0e42\u0e15\u0e19\u0e14"
    ],
    "wof:name":"Ban Thung Tanot",
    "wof:placetype":"locality"
},
  "geometry": {"coordinates":[100.68575,16.09067000000001],"type":"Point"}
}