{
  "type": "Feature",
  "properties": {
    "gn:admin1_code":"46.0",
    "gn:asciiname":"Ban Plaeng Suea Khrut",
    "gn:country_code":"TH",
    "gn:dem":59,
    "gn:feature_class":"P",
    "gn:feature_code":"PPL",
    "gn:name":"Ban Plaeng Suea Khrut",
    "gn:population":0,
    "gn:timezone":"Asia/Bangkok",
    "iso:country":"TH",
    "name:tha_x_preferred":[
        "\u0e1a\u0e49\u0e32\u0e19\u0e41\u0e1b\u0e25\u0e07\u0e40\u0e2a\u0e37\u0e2d\u0e04\u0e23\u0e39\u0e14"
    ],
    "wof:name":"Ban Plaeng Suea Khrut",
    "wof:placetype":"locality"
},
  "geometry": {"coordinates":[101.28156,13.47039],"type":"Point"}
}