{
  "type": "Feature",
  "properties": {
    "gn:admin1_code":"20.0",
    "gn:asciiname":"Ban Kham Bo Tai",
    "gn:country_code":"TH",
    "gn:dem":200,
    "gn:feature_class":"P",
    "gn:feature_code":"PPL",
    "gn:name":"Ban Kham Bo Tai",
    "gn:population":0,
    "gn:timezone":"Asia/Bangkok",
    "iso:country":"TH",
    "name:tha_x_preferred":[
        "\u0e1a\u0e49\u0e32\u0e19\u0e04\u0e33\u0e1a\u0e48\u0e2d\u0e43\u0e15\u0e49"
    ],
    "wof:name":"Ban Kham Bo Tai",
    "wof:placetype":"locality"
},
  "geometry": {"coordinates":[103.559,17.24292],"type":"Point"}
}