{
  "type": "Feature",
  "properties": {
    "gn:admin1_code":"48.0",
    "gn:asciiname":"Ban Bueng Chanang Klang",
    "gn:country_code":"TH",
    "gn:dem":94,
    "gn:feature_class":"P",
    "gn:feature_code":"PPL",
    "gn:name":"Ban Bueng Chanang Klang",
    "gn:population":0,
    "gn:timezone":"Asia/Bangkok",
    "iso:country":"TH",
    "name:tha_x_preferred":[
        "\u0e1a\u0e49\u0e32\u0e19\u0e1a\u0e36\u0e07\u0e0a\u0e19\u0e31\u0e07\u0e01\u0e25\u0e32\u0e07"
    ],
    "name:und_x_variant":[
        "Ban Pung Chang",
        "Ban Bung Chanang",
        "Ban Bueng Chanang Klang"
    ],
    "wof:name":"Ban Bueng Chanang Klang",
    "wof:placetype":"locality"
},
  "geometry": {"coordinates":[102.45617,13.03511],"type":"Point"}
}