{
  "type": "Feature",
  "properties": {
    "gn:admin1_code":"68.0",
    "gn:asciiname":"Ban Plak Pling",
    "gn:country_code":"TH",
    "gn:dem":12,
    "gn:feature_class":"P",
    "gn:feature_code":"PPL",
    "gn:name":"Ban Plak Pling",
    "gn:population":0,
    "gn:timezone":"Asia/Bangkok",
    "iso:country":"TH",
    "name:tha_x_preferred":[
        "\u0e1a\u0e49\u0e32\u0e19\u0e1b\u0e25\u0e31\u0e01\u0e1b\u0e25\u0e34\u0e07"
    ],
    "wof:name":"Ban Plak Pling",
    "wof:placetype":"locality"
},
  "geometry": {"coordinates":[100.66764000000001,7.04181],"type":"Point"}
}