{
  "type": "Feature",
  "properties": {
    "gn:admin1_code":"31.0",
    "gn:asciiname":"Ban Ai Ka We",
    "gn:country_code":"TH",
    "gn:dem":54,
    "gn:feature_class":"P",
    "gn:feature_code":"PPL",
    "gn:name":"Ban Ai Ka We",
    "gn:population":0,
    "gn:timezone":"Asia/Bangkok",
    "iso:country":"TH",
    "name:tha_x_preferred":[
        "\u0e1a\u0e49\u0e32\u0e19\u0e44\u0e2d\u0e23\u0e4c\u0e01\u0e32\u0e40\u0e27"
    ],
    "wof:name":"Ban Ai Ka We",
    "wof:placetype":"locality"
},
  "geometry": {"coordinates":[101.47425,6.20856],"type":"Point"}
}