{
  "type": "Feature",
  "properties": {
    "gn:admin1_code":"51.0",
    "gn:asciiname":"Ban Nong Sang Thong",
    "gn:country_code":"TH",
    "gn:dem":18,
    "gn:feature_class":"P",
    "gn:feature_code":"PPL",
    "gn:name":"Ban Nong Sang Thong",
    "gn:population":0,
    "gn:timezone":"Asia/Bangkok",
    "iso:country":"TH",
    "name:tha_x_preferred":[
        "\u0e1a\u0e49\u0e32\u0e19\u0e2b\u0e19\u0e2d\u0e07\u0e2a\u0e31\u0e07\u0e02\u0e4c\u0e17\u0e2d\u0e07"
    ],
    "wof:name":"Ban Nong Sang Thong",
    "wof:placetype":"locality"
},
  "geometry": {"coordinates":[100.02622,14.73027],"type":"Point"}
}