{
  "type": "Feature",
  "properties": {
    "gn:admin1_code":"23.0",
    "gn:asciiname":"Ban Thai Charoen",
    "gn:country_code":"TH",
    "gn:dem":156,
    "gn:feature_class":"P",
    "gn:feature_code":"PPL",
    "gn:name":"Ban Thai Charoen",
    "gn:population":0,
    "gn:timezone":"Asia/Bangkok",
    "iso:country":"TH",
    "name:tha_x_preferred":[
        "\u0e1a\u0e49\u0e32\u0e19\u0e44\u0e17\u0e22\u0e40\u0e08\u0e23\u0e34\u0e0d"
    ],
    "wof:name":"Ban Thai Charoen",
    "wof:placetype":"locality"
},
  "geometry": {"coordinates":[103.29911,16.39575],"type":"Point"}
}