{
  "type": "Feature",
  "properties": {
    "gn:admin1_code":"32.0",
    "gn:asciiname":"Ban Nong Krabian",
    "gn:country_code":"TH",
    "gn:dem":29,
    "gn:feature_class":"P",
    "gn:feature_code":"PPL",
    "gn:name":"Ban Nong Krabian",
    "gn:population":0,
    "gn:timezone":"Asia/Bangkok",
    "iso:country":"TH",
    "name:tha_x_preferred":[
        "\u0e1a\u0e49\u0e32\u0e19\u0e2b\u0e19\u0e2d\u0e07\u0e01\u0e23\u0e30\u0e40\u0e1a\u0e35\u0e22\u0e19"
    ],
    "wof:name":"Ban Nong Krabian",
    "wof:placetype":"locality"
},
  "geometry": {"coordinates":[99.96357999999999,15.20114],"type":"Point"}
}