{
  "type": "Feature",
  "properties": {
    "gn:admin1_code":"69.0",
    "gn:asciiname":"Ban Plak Prue",
    "gn:country_code":"TH",
    "gn:dem":14,
    "gn:feature_class":"P",
    "gn:feature_code":"PPL",
    "gn:name":"Ban Plak Prue",
    "gn:population":0,
    "gn:timezone":"Asia/Bangkok",
    "iso:country":"TH",
    "name:tha_x_preferred":[
        "\u0e1a\u0e49\u0e32\u0e19\u0e1b\u0e25\u0e31\u0e01\u0e1b\u0e23\u0e37\u0e2d"
    ],
    "wof:name":"Ban Plak Prue",
    "wof:placetype":"locality"
},
  "geometry": {"coordinates":[101.26488999999999,6.66056],"type":"Point"}
}