{
  "type": "Feature",
  "properties": {
    "gn:admin1_code":"55.0",
    "gn:asciiname":"Ban Tha Mai",
    "gn:country_code":"TH",
    "gn:dem":6,
    "gn:feature_class":"P",
    "gn:feature_code":"PPL",
    "gn:name":"Ban Tha Mai",
    "gn:population":0,
    "gn:timezone":"Asia/Bangkok",
    "iso:country":"TH",
    "name:tha_x_preferred":[
        "\u0e1a\u0e49\u0e32\u0e19\u0e17\u0e48\u0e32\u0e44\u0e21\u0e49"
    ],
    "name:und_x_variant":[
        "Ban Tah Mai",
        "Ban Tha Mai",
        "Ban Bang Tha Mai"
    ],
    "wof:name":"Ban Tha Mai",
    "wof:placetype":"locality"
},
  "geometry": {"coordinates":[100.26764,13.66197],"type":"Point"}
}