{
  "type": "Feature",
  "properties": {
    "gn:admin1_code":"65.0",
    "gn:asciiname":"Ban Khuan Sai Tok",
    "gn:country_code":"TH",
    "gn:dem":65,
    "gn:feature_class":"P",
    "gn:feature_code":"PPL",
    "gn:name":"Ban Khuan Sai Tok",
    "gn:population":0,
    "gn:timezone":"Asia/Bangkok",
    "iso:country":"TH",
    "name:tha_x_preferred":[
        "\u0e1a\u0e49\u0e32\u0e19\u0e04\u0e27\u0e19\u0e44\u0e17\u0e23\u0e15\u0e2d\u0e01"
    ],
    "wof:name":"Ban Khuan Sai Tok",
    "wof:placetype":"locality"
},
  "geometry": {"coordinates":[99.67883,7.94231],"type":"Point"}
}