{
  "type": "Feature",
  "properties": {
    "gn:admin1_code":"4.0",
    "gn:asciiname":"Ban Ton Muang",
    "gn:country_code":"TH",
    "gn:dem":278,
    "gn:feature_class":"P",
    "gn:feature_code":"PPL",
    "gn:name":"Ban Ton Muang",
    "gn:population":0,
    "gn:timezone":"Asia/Bangkok",
    "iso:country":"TH",
    "name:tha_x_preferred":[
        "\u0e1a\u0e49\u0e32\u0e19\u0e15\u0e49\u0e19\u0e21\u0e48\u0e27\u0e07"
    ],
    "wof:name":"Ban Ton Muang",
    "wof:placetype":"locality"
},
  "geometry": {"coordinates":[100.74686,18.33378],"type":"Point"}
}