{
  "type": "Feature",
  "properties": {
    "gn:admin1_code":"18.0",
    "gn:asciiname":"Ban Kok Kliang",
    "gn:country_code":"TH",
    "gn:dem":255,
    "gn:feature_class":"P",
    "gn:feature_code":"PPL",
    "gn:name":"Ban Kok Kliang",
    "gn:population":0,
    "gn:timezone":"Asia/Bangkok",
    "iso:country":"TH",
    "wof:name":"Ban Kok Kliang",
    "wof:placetype":"locality"
},
  "geometry": {"coordinates":[101.75,17.25],"type":"Point"}
}