{
  "type": "Feature",
  "properties": {
    "gn:admin1_code":"30.0",
    "gn:asciiname":"Ban Kradue",
    "gn:country_code":"TH",
    "gn:dem":144,
    "gn:feature_class":"P",
    "gn:feature_code":"PPL",
    "gn:name":"Ban Kradue",
    "gn:population":0,
    "gn:timezone":"Asia/Bangkok",
    "iso:country":"TH",
    "name:und_x_variant":[
        "Ban Katu",
        "Ban Kadu",
        "Ban Kradue",
        "\u0e1a\u0e49\u0e32\u0e19\u0e01\u0e23\u0e30\u0e14\u0e36"
    ],
    "wof:lang_x_official":[
        "tha"
    ],
    "wof:lang_x_spoken":[
        "tha"
    ],
    "wof:name":"Ban Kradue",
    "wof:placetype":"locality"
},
  "geometry": {"coordinates":[103.90603,14.84481],"type":"Point"}
}