{
  "type": "Feature",
  "properties": {
    "gn:admin1_code":"27",
    "gn:asciiname":"Ban Non Phai Noi",
    "gn:country_code":"TH",
    "gn:dem":143,
    "gn:feature_class":"P",
    "gn:feature_code":"PPL",
    "gn:name":"Ban Non Phai Noi",
    "gn:population":0,
    "gn:timezone":"Asia/Bangkok",
    "iso:country":"TH",
    "name:tha_x_preferred":[
        "\u0e1a\u0e49\u0e32\u0e19\u0e42\u0e19\u0e19\u0e44\u0e1c\u0e48\u0e19\u0e49\u0e2d\u0e22"
    ],
    "wof:name":"Ban Non Phai Noi",
    "wof:placetype":"locality"
},
  "geometry": {"coordinates":[102.73706,15.38244],"type":"Point"}
}