{
  "type": "Feature",
  "properties": {
    "gn:admin1_code":"63.0",
    "gn:asciiname":"Ban Tham Rop",
    "gn:country_code":"TH",
    "gn:dem":127,
    "gn:feature_class":"P",
    "gn:feature_code":"PPL",
    "gn:name":"Ban Tham Rop",
    "gn:population":0,
    "gn:timezone":"Asia/Bangkok",
    "iso:country":"TH",
    "name:tha_x_preferred":[
        "\u0e1a\u0e49\u0e32\u0e19\u0e16\u0e49\u0e33\u0e23\u0e2d\u0e1a"
    ],
    "wof:name":"Ban Tham Rop",
    "wof:placetype":"locality"
},
  "geometry": {"coordinates":[98.82277999999999,8.60964],"type":"Point"}
}