{
  "type": "Feature",
  "properties": {
    "gn:admin1_code":"28.0",
    "gn:asciiname":"Ban Sai Yong",
    "gn:country_code":"TH",
    "gn:dem":163,
    "gn:feature_class":"P",
    "gn:feature_code":"PPL",
    "gn:name":"Ban Sai Yong",
    "gn:population":0,
    "gn:timezone":"Asia/Bangkok",
    "iso:country":"TH",
    "name:tha_x_preferred":[
        "\u0e1a\u0e49\u0e32\u0e19\u0e44\u0e17\u0e23\u0e42\u0e22\u0e07"
    ],
    "name:und_x_variant":[
        "Ban Sai Rayong"
    ],
    "wof:name":"Ban Sai Yong",
    "wof:placetype":"locality"
},
  "geometry": {"coordinates":[103.01667,14.96667],"type":"Point"}
}