{
  "type": "Feature",
  "properties": {
    "gn:admin1_code":"40.0",
    "gn:admin2_code":"1021.0",
    "gn:asciiname":"Muban Sirinda",
    "gn:country_code":"TH",
    "gn:dem":4,
    "gn:feature_class":"P",
    "gn:feature_code":"PPL",
    "gn:name":"Muban Sirinda",
    "gn:population":0,
    "gn:timezone":"Asia/Bangkok",
    "iso:country":"TH",
    "name:tha_x_preferred":[
        "\u0e2b\u0e21\u0e39\u0e48\u0e1a\u0e49\u0e32\u0e19\u0e2a\u0e34\u0e23\u0e34\u0e19\u0e14\u0e32"
    ],
    "wof:name":"Muban Sirinda",
    "wof:placetype":"locality"
},
  "geometry": {"coordinates":[100.39113999999999,13.59711],"type":"Point"}
}