{
  "type": "Feature",
  "properties": {
    "gn:admin1_code":"28",
    "gn:asciiname":"Ban Cho Phaka",
    "gn:country_code":"TH",
    "gn:dem":174,
    "gn:feature_class":"P",
    "gn:feature_code":"PPL",
    "gn:name":"Ban Cho Phaka",
    "gn:population":0,
    "gn:timezone":"Asia/Bangkok",
    "iso:country":"TH",
    "name:tha_x_preferred":[
        "\u0e1a\u0e49\u0e32\u0e19\u0e0a\u0e48\u0e2d\u0e1c\u0e01\u0e32"
    ],
    "wof:name":"Ban Cho Phaka",
    "wof:placetype":"locality"
},
  "geometry": {"coordinates":[102.83392000000001,14.83314],"type":"Point"}
}