{
  "type": "Feature",
  "properties": {
    "gn:admin1_code":"46.0",
    "gn:asciiname":"Ban Nong Sak",
    "gn:country_code":"TH",
    "gn:dem":46,
    "gn:feature_class":"P",
    "gn:feature_code":"PPL",
    "gn:name":"Ban Nong Sak",
    "gn:population":0,
    "gn:timezone":"Asia/Bangkok",
    "iso:country":"TH",
    "name:tha_x_preferred":[
        "\u0e1a\u0e49\u0e32\u0e19\u0e2b\u0e19\u0e2d\u0e07\u0e0b\u0e32\u0e01"
    ],
    "name:und_x_variant":[
        "Ban Nong Chak"
    ],
    "wof:name":"Ban Nong Sak",
    "wof:placetype":"locality"
},
  "geometry": {"coordinates":[101.17928000000001,13.28875],"type":"Point"}
}