{
  "type": "Feature",
  "properties": {
    "gn:admin1_code":"15.0",
    "gn:asciiname":"Ban Pa Daeng",
    "gn:country_code":"TH",
    "gn:dem":120,
    "gn:feature_class":"P",
    "gn:feature_code":"PPL",
    "gn:name":"Ban Pa Daeng",
    "gn:population":0,
    "gn:timezone":"Asia/Bangkok",
    "iso:country":"TH",
    "name:tha_x_preferred":[
        "\u0e1a\u0e49\u0e32\u0e19\u0e1b\u0e48\u0e32\u0e41\u0e14\u0e07"
    ],
    "wof:name":"Ban Pa Daeng",
    "wof:placetype":"locality"
},
  "geometry": {"coordinates":[99.59256000000001,15.02069],"type":"Point"}
}