{
  "type": "Feature",
  "properties": {
    "gn:admin1_code":"75.0",
    "gn:asciiname":"Ban Lat",
    "gn:country_code":"TH",
    "gn:dem":143,
    "gn:feature_class":"P",
    "gn:feature_code":"PPL",
    "gn:name":"Ban Lat",
    "gn:population":0,
    "gn:timezone":"Asia/Bangkok",
    "iso:country":"TH",
    "name:tha_x_preferred":[
        "\u0e1a\u0e49\u0e32\u0e19\u0e25\u0e32\u0e14"
    ],
    "wof:name":"Ban Lat",
    "wof:placetype":"locality"
},
  "geometry": {"coordinates":[105.05131000000002,15.62811],"type":"Point"}
}