{
  "type": "Feature",
  "properties": {
    "gn:admin1_code":"2.0",
    "gn:asciiname":"Ban Pang Nam Thu",
    "gn:country_code":"TH",
    "gn:dem":908,
    "gn:feature_class":"P",
    "gn:feature_code":"PPL",
    "gn:name":"Ban Pang Nam Thu",
    "gn:population":0,
    "gn:timezone":"Asia/Bangkok",
    "iso:country":"TH",
    "name:tha_x_preferred":[
        "\u0e1a\u0e49\u0e32\u0e19\u0e1b\u0e32\u0e07\u0e19\u0e49\u0e33\u0e16\u0e38"
    ],
    "name:und_x_variant":[
        "Ban Pang Nam Thu (1)"
    ],
    "wof:name":"Ban Pang Nam Thu",
    "wof:placetype":"locality"
},
  "geometry": {"coordinates":[99.35991,19.05441],"type":"Point"}
}