{
  "type": "Feature",
  "properties": {
    "gn:admin1_code":"60.0",
    "gn:asciiname":"Ban Khao Hua Khwai",
    "gn:country_code":"TH",
    "gn:dem":15,
    "gn:feature_class":"P",
    "gn:feature_code":"PPL",
    "gn:name":"Ban Khao Hua Khwai",
    "gn:population":0,
    "gn:timezone":"Asia/Bangkok",
    "iso:country":"TH",
    "name:tha_x_preferred":[
        "\u0e1a\u0e49\u0e32\u0e19\u0e40\u0e02\u0e32\u0e2b\u0e31\u0e27\u0e04\u0e27\u0e32\u0e22"
    ],
    "wof:name":"Ban Khao Hua Khwai",
    "wof:placetype":"locality"
},
  "geometry": {"coordinates":[99.25569,9.05822],"type":"Point"}
}