{
  "type": "Feature",
  "properties": {
    "gn:admin1_code":"26.0",
    "gn:asciiname":"Ban Thung Kamang",
    "gn:country_code":"TH",
    "gn:dem":860,
    "gn:feature_class":"P",
    "gn:feature_code":"PPL",
    "gn:name":"Ban Thung Kamang",
    "gn:population":0,
    "gn:timezone":"Asia/Bangkok",
    "iso:country":"TH",
    "wof:name":"Ban Thung Kamang",
    "wof:placetype":"locality"
},
  "geometry": {"coordinates":[101.56667,16.38332999999999],"type":"Point"}
}