{
  "type": "Feature",
  "properties": {
    "gn:admin1_code":"59.0",
    "gn:asciiname":"Ban Chiao Liang",
    "gn:country_code":"TH",
    "gn:dem":41,
    "gn:feature_class":"P",
    "gn:feature_code":"PPL",
    "gn:name":"Ban Chiao Liang",
    "gn:population":0,
    "gn:timezone":"Asia/Bangkok",
    "iso:country":"TH",
    "name:tha_x_preferred":[
        "\u0e1a\u0e49\u0e32\u0e19\u0e40\u0e0a\u0e35\u0e22\u0e27\u0e40\u0e2b\u0e25\u0e35\u0e22\u0e07"
    ],
    "wof:name":"Ban Chiao Liang",
    "wof:placetype":"locality"
},
  "geometry": {"coordinates":[98.67194000000001,9.56919],"type":"Point"}
}