{
  "type": "Feature",
  "properties": {
    "gn:admin1_code":"0.0",
    "gn:asciiname":"Ban Yang Huai Samae",
    "gn:country_code":"TH",
    "gn:dem":887,
    "gn:feature_class":"P",
    "gn:feature_code":"PPL",
    "gn:name":"Ban Yang Huai Samae",
    "gn:population":0,
    "gn:timezone":"Asia/Bangkok",
    "iso:country":"TH",
    "wof:name":"Ban Yang Huai Samae",
    "wof:placetype":"locality"
},
  "geometry": {"coordinates":[98.61667,17.08333],"type":"Point"}
}