{
  "type": "Feature",
  "properties": {
    "gn:admin1_code":"44.0",
    "gn:asciiname":"Ban Khlong Bang Kradan",
    "gn:country_code":"TH",
    "gn:dem":5,
    "gn:feature_class":"P",
    "gn:feature_code":"PPL",
    "gn:name":"Ban Khlong Bang Kradan",
    "gn:population":0,
    "gn:timezone":"Asia/Bangkok",
    "iso:country":"TH",
    "name:tha_x_preferred":[
        "\u0e1a\u0e49\u0e32\u0e19\u0e04\u0e25\u0e2d\u0e07\u0e1a\u0e32\u0e07\u0e01\u0e23\u0e30\u0e14\u0e32\u0e19"
    ],
    "name:tha_x_variant":[
        "Ban Khlong Bang Kradan"
    ],
    "name:und_x_variant":[
        "Khlaung Bang Kadan",
        "Ban Khlong Bang Kadan"
    ],
    "wof:name":"Ban Khlong Bang Kradan",
    "wof:placetype":"locality"
},
  "geometry": {"coordinates":[101.16142000000001,13.86181],"type":"Point"}
}