{
  "type": "Feature",
  "properties": {
    "gn:admin1_code":"66.0",
    "gn:asciiname":"Ban Khlong Yai",
    "gn:country_code":"TH",
    "gn:dem":47,
    "gn:feature_class":"P",
    "gn:feature_code":"PPL",
    "gn:name":"Ban Khlong Yai",
    "gn:population":0,
    "gn:timezone":"Asia/Bangkok",
    "iso:country":"TH",
    "name:tha_x_preferred":[
        "\u0e1a\u0e49\u0e32\u0e19\u0e04\u0e25\u0e2d\u0e07\u0e43\u0e2b\u0e0d\u0e48"
    ],
    "name:und_x_variant":[
        "Ban Klong Yai",
        "Ban Khlong Yai"
    ],
    "wof:name":"Ban Khlong Yai",
    "wof:placetype":"locality"
},
  "geometry": {"coordinates":[100.07892,7.28956],"type":"Point"}
}