{
  "type": "Feature",
  "properties": {
    "gn:admin1_code":"29",
    "gn:asciiname":"Ban Takhiat",
    "gn:country_code":"TH",
    "gn:dem":180,
    "gn:feature_class":"P",
    "gn:feature_code":"PPL",
    "gn:name":"Ban Takhiat",
    "gn:population":0,
    "gn:timezone":"Asia/Bangkok",
    "iso:country":"TH",
    "name:tha_x_preferred":[
        "\u0e1a\u0e49\u0e32\u0e19\u0e15\u0e30\u0e40\u0e02\u0e35\u0e22\u0e14"
    ],
    "wof:name":"Ban Takhiat",
    "wof:placetype":"locality"
},
  "geometry": {"coordinates":[103.43594,14.71458],"type":"Point"}
}