{
  "type": "Feature",
  "properties": {
    "gn:admin1_code":"2.0",
    "gn:asciiname":"Ban Mae Phae",
    "gn:country_code":"TH",
    "gn:dem":853,
    "gn:feature_class":"P",
    "gn:feature_code":"PPL",
    "gn:name":"Ban Mae Phae",
    "gn:population":0,
    "gn:timezone":"Asia/Bangkok",
    "iso:country":"TH",
    "name:tha_x_preferred":[
        "\u0e1a\u0e49\u0e32\u0e19\u0e41\u0e21\u0e48\u0e41\u0e1e\u0e30"
    ],
    "name:und_x_variant":[
        "Bhe\u0101",
        "Ban Phae",
        "Ban Mae Phae"
    ],
    "wof:lang_x_official":[
        "tha"
    ],
    "wof:lang_x_spoken":[
        "tha"
    ],
    "wof:name":"Ban Mae Phae",
    "wof:placetype":"locality"
},
  "geometry": {"coordinates":[98.70742,19.00542],"type":"Point"}
}