{
  "type": "Feature",
  "properties": {
    "gn:admin1_code":"41.0",
    "gn:asciiname":"Ban Rong Bua Loi",
    "gn:country_code":"TH",
    "gn:dem":394,
    "gn:feature_class":"P",
    "gn:feature_code":"PPL",
    "gn:name":"Ban Rong Bua Loi",
    "gn:population":0,
    "gn:timezone":"Asia/Bangkok",
    "iso:country":"TH",
    "name:tha_x_preferred":[
        "\u0e1a\u0e49\u0e32\u0e19\u0e23\u0e48\u0e2d\u0e07\u0e1a\u0e31\u0e27\u0e25\u0e2d\u0e22"
    ],
    "wof:name":"Ban Rong Bua Loi",
    "wof:placetype":"locality"
},
  "geometry": {"coordinates":[99.99227999999999,19.16786],"type":"Point"}
}