{
  "type": "Feature",
  "properties": {
    "gn:admin1_code":"7.0",
    "gn:asciiname":"Ban Mae Phrao",
    "gn:country_code":"TH",
    "gn:dem":358,
    "gn:feature_class":"P",
    "gn:feature_code":"PPL",
    "gn:name":"Ban Mae Phrao",
    "gn:population":0,
    "gn:timezone":"Asia/Bangkok",
    "iso:country":"TH",
    "name:tha_x_preferred":[
        "\u0e1a\u0e49\u0e32\u0e19\u0e41\u0e21\u0e48\u0e1e\u0e23\u0e49\u0e32\u0e27"
    ],
    "wof:name":"Ban Mae Phrao",
    "wof:placetype":"locality"
},
  "geometry": {"coordinates":[100.17274999999999,18.77917],"type":"Point"}
}