{
  "type": "Feature",
  "properties": {
    "gn:admin1_code":"70.0",
    "gn:asciiname":"Ban Khotchasila",
    "gn:country_code":"TH",
    "gn:dem":93,
    "gn:feature_class":"P",
    "gn:feature_code":"PPL",
    "gn:name":"Ban Khotchasila",
    "gn:population":0,
    "gn:timezone":"Asia/Bangkok",
    "iso:country":"TH",
    "name:tha_x_preferred":[
        "\u0e1a\u0e49\u0e32\u0e19\u0e04\u0e0a\u0e28\u0e34\u0e25\u0e32"
    ],
    "wof:name":"Ban Khotchasila",
    "wof:placetype":"locality"
},
  "geometry": {"coordinates":[101.05597,6.37639],"type":"Point"}
}