{
  "type": "Feature",
  "properties": {
    "gn:admin1_code":"51.0",
    "gn:asciiname":"Ban Tao It",
    "gn:cc2":"TH",
    "gn:country_code":"TH",
    "gn:dem":10,
    "gn:feature_class":"P",
    "gn:feature_code":"PPL",
    "gn:name":"Ban Tao It",
    "gn:population":0,
    "gn:timezone":"Asia/Bangkok",
    "iso:country":"TH",
    "name:und_x_variant":[
        "Ban Don Katai",
        "Ban Tao It"
    ],
    "wof:name":"Ban Tao It",
    "wof:placetype":"locality"
},
  "geometry": {"coordinates":[100.08333,14.61667],"type":"Point"}
}