{
  "type": "Feature",
  "properties": {
    "gn:admin1_code":"25",
    "gn:asciiname":"Ban Phon Ngio",
    "gn:country_code":"TH",
    "gn:dem":128,
    "gn:feature_class":"P",
    "gn:feature_code":"PPL",
    "gn:name":"Ban Phon Ngio",
    "gn:population":0,
    "gn:timezone":"Asia/Bangkok",
    "iso:country":"TH",
    "name:tha_x_preferred":[
        "\u0e1a\u0e49\u0e32\u0e19\u0e42\u0e1e\u0e19\u0e07\u0e34\u0e49\u0e27"
    ],
    "wof:name":"Ban Phon Ngio",
    "wof:placetype":"locality"
},
  "geometry": {"coordinates":[103.74311,15.52236],"type":"Point"}
}