{
  "type": "Feature",
  "properties": {
    "gn:admin1_code":"58.0",
    "gn:asciiname":"Ban Bok Fai",
    "gn:country_code":"TH",
    "gn:dem":124,
    "gn:feature_class":"P",
    "gn:feature_code":"PPL",
    "gn:name":"Ban Bok Fai",
    "gn:population":0,
    "gn:timezone":"Asia/Bangkok",
    "iso:country":"TH",
    "name:tha_x_preferred":[
        "\u0e1a\u0e49\u0e32\u0e19\u0e1a\u0e01\u0e44\u0e1f"
    ],
    "name:und_x_variant":[
        "Ban Buk Fai",
        "Ban Bok Fai"
    ],
    "wof:name":"Ban Bok Fai",
    "wof:placetype":"locality"
},
  "geometry": {"coordinates":[98.67178,9.74739],"type":"Point"}
}