{
  "type": "Feature",
  "properties": {
    "gn:admin1_code":"10.0",
    "gn:asciiname":"Ban Pha Mup",
    "gn:country_code":"TH",
    "gn:dem":137,
    "gn:feature_class":"P",
    "gn:feature_code":"PPL",
    "gn:name":"Ban Pha Mup",
    "gn:population":0,
    "gn:timezone":"Asia/Bangkok",
    "iso:country":"TH",
    "name:tha_x_preferred":[
        "Ban Pha Mup"
    ],
    "name:tha_x_variant":[
        "\u0e1a\u0e49\u0e32\u0e19\u0e1c\u0e32\u0e21\u0e39\u0e1a"
    ],
    "wof:name":"Ban Pha Mup",
    "wof:placetype":"locality"
},
  "geometry": {"coordinates":[100.00922,17.73631],"type":"Point"}
}