{
  "type": "Feature",
  "properties": {
    "gn:admin1_code":"4.0",
    "gn:asciiname":"Ban Chae Haeng",
    "gn:country_code":"TH",
    "gn:dem":209,
    "gn:feature_class":"P",
    "gn:feature_code":"PPL",
    "gn:name":"Ban Chae Haeng",
    "gn:population":0,
    "gn:timezone":"Asia/Bangkok",
    "iso:country":"TH",
    "name:tha_x_preferred":[
        "\u0e1a\u0e49\u0e32\u0e19\u0e41\u0e0b\u0e48\u0e41\u0e2b\u0e49\u0e07"
    ],
    "name:und_x_variant":[
        "Ban Nong (2)"
    ],
    "wof:name":"Ban Chae Haeng",
    "wof:placetype":"locality"
},
  "geometry": {"coordinates":[100.79289,18.75528],"type":"Point"}
}