{
  "type": "Feature",
  "properties": {
    "gn:admin1_code":"9.0",
    "gn:asciiname":"Ban Nong Klap",
    "gn:country_code":"TH",
    "gn:dem":62,
    "gn:feature_class":"P",
    "gn:feature_code":"PPL",
    "gn:name":"Ban Nong Klap",
    "gn:population":0,
    "gn:timezone":"Asia/Bangkok",
    "iso:country":"TH",
    "name:tha_x_preferred":[
        "\u0e1a\u0e49\u0e32\u0e19\u0e2b\u0e19\u0e2d\u0e07\u0e01\u0e25\u0e31\u0e1a"
    ],
    "name:und_x_variant":[
        "B\u0101n Naung Glab",
        "Ban Nong Klap"
    ],
    "wof:name":"Ban Nong Klap",
    "wof:placetype":"locality"
},
  "geometry": {"coordinates":[99.77133000000001,17.24208],"type":"Point"}
}