{
  "type": "Feature",
  "properties": {
    "gn:admin1_code":"75.0",
    "gn:asciiname":"Ban Phon Ngam",
    "gn:country_code":"TH",
    "gn:dem":128,
    "gn:feature_class":"P",
    "gn:feature_code":"PPL",
    "gn:name":"Ban Phon Ngam",
    "gn:population":0,
    "gn:timezone":"Asia/Bangkok",
    "iso:country":"TH",
    "name:tha_x_preferred":[
        "\u0e1a\u0e49\u0e32\u0e19\u0e42\u0e1e\u0e19\u0e07\u0e32\u0e21"
    ],
    "name:und_x_variant":[
        "Ban Pon Ngan",
        "Ban Phon Ngam"
    ],
    "wof:name":"Ban Phon Ngam",
    "wof:placetype":"locality"
},
  "geometry": {"coordinates":[104.72156,15.26089],"type":"Point"}
}