{
  "type": "Feature",
  "properties": {
    "gn:admin1_code":"57.0",
    "gn:asciiname":"Ban Yan Sue",
    "gn:country_code":"TH",
    "gn:dem":101,
    "gn:feature_class":"P",
    "gn:feature_code":"PPL",
    "gn:name":"Ban Yan Sue",
    "gn:population":0,
    "gn:timezone":"Asia/Bangkok",
    "iso:country":"TH",
    "name:tha_x_preferred":[
        "\u0e1a\u0e49\u0e32\u0e19\u0e22\u0e48\u0e32\u0e19\u0e0b\u0e37\u0e48\u0e2d"
    ],
    "wof:name":"Ban Yan Sue",
    "wof:placetype":"locality"
},
  "geometry": {"coordinates":[99.63878,12.06331],"type":"Point"}
}