{
  "type": "Feature",
  "properties": {
    "gn:admin1_code":"37.0",
    "gn:asciiname":"Ban Huai San Chao",
    "gn:country_code":"TH",
    "gn:dem":21,
    "gn:feature_class":"P",
    "gn:feature_code":"PPL",
    "gn:name":"Ban Huai San Chao",
    "gn:population":0,
    "gn:timezone":"Asia/Bangkok",
    "iso:country":"TH",
    "name:tha_x_preferred":[
        "\u0e1a\u0e49\u0e32\u0e19\u0e2b\u0e49\u0e27\u0e22\u0e28\u0e32\u0e25\u0e40\u0e08\u0e49\u0e32"
    ],
    "wof:name":"Ban Huai San Chao",
    "wof:placetype":"locality"
},
  "geometry": {"coordinates":[100.836,14.62889],"type":"Point"}
}