{
  "type": "Feature",
  "properties": {
    "gn:admin1_code":"74.0",
    "gn:asciiname":"Ban Khok Ta Rak",
    "gn:country_code":"TH",
    "gn:dem":17,
    "gn:feature_class":"P",
    "gn:feature_code":"PPL",
    "gn:name":"Ban Khok Ta Rak",
    "gn:population":0,
    "gn:timezone":"Asia/Bangkok",
    "iso:country":"TH",
    "name:tha_x_preferred":[
        "\u0e1a\u0e49\u0e32\u0e19\u0e42\u0e04\u0e01\u0e15\u0e32\u0e23\u0e31\u0e01\u0e29\u0e4c"
    ],
    "wof:name":"Ban Khok Ta Rak",
    "wof:placetype":"locality"
},
  "geometry": {"coordinates":[101.64091999999999,13.98808],"type":"Point"}
}