{
  "type": "Feature",
  "properties": {
    "gn:admin1_code":"26.0",
    "gn:asciiname":"Ban Prong Sang",
    "gn:country_code":"TH",
    "gn:dem":216,
    "gn:feature_class":"P",
    "gn:feature_code":"PPL",
    "gn:name":"Ban Prong Sang",
    "gn:population":0,
    "gn:timezone":"Asia/Bangkok",
    "iso:country":"TH",
    "name:tha_x_preferred":[
        "\u0e1a\u0e49\u0e32\u0e19\u0e42\u0e1b\u0e23\u0e48\u0e07\u0e2a\u0e31\u0e07\u0e02\u0e4c"
    ],
    "wof:name":"Ban Prong Sang",
    "wof:placetype":"locality"
},
  "geometry": {"coordinates":[102.18147,16.10853],"type":"Point"}
}