{
  "type": "Feature",
  "properties": {
    "gn:admin1_code":"74",
    "gn:asciiname":"Ban Wang Mit",
    "gn:country_code":"TH",
    "gn:dem":102,
    "gn:feature_class":"P",
    "gn:feature_code":"PPL",
    "gn:name":"Ban Wang Mit",
    "gn:population":0,
    "gn:timezone":"Asia/Bangkok",
    "iso:country":"TH",
    "name:tha_x_preferred":[
        "\u0e1a\u0e49\u0e32\u0e19\u0e27\u0e31\u0e07\u0e21\u0e35\u0e14"
    ],
    "wof:name":"Ban Wang Mit",
    "wof:placetype":"locality"
},
  "geometry": {"coordinates":[101.89072,14.28511],"type":"Point"}
}