{
  "type": "Feature",
  "properties": {
    "gn:admin1_code":"57.0",
    "gn:asciiname":"Ban Don Hiang",
    "gn:country_code":"TH",
    "gn:dem":10,
    "gn:feature_class":"P",
    "gn:feature_code":"PPL",
    "gn:name":"Ban Don Hiang",
    "gn:population":0,
    "gn:timezone":"Asia/Bangkok",
    "iso:country":"TH",
    "name:tha_x_preferred":[
        "\u0e1a\u0e49\u0e32\u0e19\u0e14\u0e2d\u0e19\u0e40\u0e2b\u0e35\u0e22\u0e07"
    ],
    "name:und_x_variant":[
        "Dohn Hieng",
        "Ban Don Hiang"
    ],
    "wof:name":"Ban Don Hiang",
    "wof:placetype":"locality"
},
  "geometry": {"coordinates":[99.78628,11.82978],"type":"Point"}
}