{
  "type": "Feature",
  "properties": {
    "gn:admin1_code":"51.0",
    "gn:asciiname":"Ban Aen Yi Sip Sam",
    "gn:country_code":"TH",
    "gn:dem":17,
    "gn:feature_class":"P",
    "gn:feature_code":"PPL",
    "gn:name":"Ban Aen Yi Sip Sam",
    "gn:population":0,
    "gn:timezone":"Asia/Bangkok",
    "iso:country":"TH",
    "name:tha_x_preferred":[
        "\u0e1a\u0e49\u0e32\u0e19\u0e41\u0e2d\u0e25 \u0e22\u0e35\u0e48\u0e2a\u0e34\u0e1a\u0e2a\u0e32\u0e21"
    ],
    "wof:lang_x_official":[
        "tha"
    ],
    "wof:lang_x_spoken":[
        "tha"
    ],
    "wof:name":"Ban Aen Yi Sip Sam",
    "wof:placetype":"locality"
},
  "geometry": {"coordinates":[99.89821999999999,14.47364],"type":"Point"}
}