{
  "type": "Feature",
  "properties": {
    "gn:admin1_code":"74.0",
    "gn:asciiname":"Ban Tha Makok",
    "gn:country_code":"TH",
    "gn:dem":17,
    "gn:feature_class":"P",
    "gn:feature_code":"PPL",
    "gn:name":"Ban Tha Makok",
    "gn:population":0,
    "gn:timezone":"Asia/Bangkok",
    "iso:country":"TH",
    "name:tha_x_preferred":[
        "\u0e1a\u0e49\u0e32\u0e19\u0e17\u0e48\u0e32\u0e21\u0e30\u0e01\u0e2d\u0e01"
    ],
    "name:und_x_variant":[
        "Ban Chaeng",
        "Ban Cheng",
        "Ban Tha Makok (1)",
        "Ban Tha Makok"
    ],
    "wof:name":"Ban Tha Makok",
    "wof:placetype":"locality"
},
  "geometry": {"coordinates":[101.75869,14.07081],"type":"Point"}
}