{
  "type": "Feature",
  "properties": {
    "gn:admin1_code":"10.0",
    "gn:asciiname":"Ban Khlong Samphan",
    "gn:country_code":"TH",
    "gn:dem":86,
    "gn:feature_class":"P",
    "gn:feature_code":"PPL",
    "gn:name":"Ban Khlong Samphan",
    "gn:population":0,
    "gn:timezone":"Asia/Bangkok",
    "iso:country":"TH",
    "name:tha_x_preferred":[
        "Ban Khlong Samphan"
    ],
    "name:tha_x_variant":[
        "\u0e1a\u0e49\u0e32\u0e19\u0e04\u0e25\u0e2d\u0e07\u0e2a\u0e31\u0e21\u0e1e\u0e31\u0e19\u0e18\u0e4c"
    ],
    "wof:name":"Ban Khlong Samphan",
    "wof:placetype":"locality"
},
  "geometry": {"coordinates":[100.25806,17.71861],"type":"Point"}
}