{
  "type": "Feature",
  "properties": {
    "gn:admin1_code":"46.0",
    "gn:asciiname":"Ban Nong Kham Pom",
    "gn:country_code":"TH",
    "gn:dem":67,
    "gn:feature_class":"P",
    "gn:feature_code":"PPL",
    "gn:name":"Ban Nong Kham Pom",
    "gn:population":0,
    "gn:timezone":"Asia/Bangkok",
    "iso:country":"TH",
    "name:tha_x_preferred":[
        "\u0e1a\u0e49\u0e32\u0e19\u0e2b\u0e19\u0e2d\u0e07\u0e02\u0e32\u0e21\u0e1b\u0e49\u0e2d\u0e21"
    ],
    "wof:name":"Ban Nong Kham Pom",
    "wof:placetype":"locality"
},
  "geometry": {"coordinates":[101.21381,13.22792],"type":"Point"}
}