{
  "type": "Feature",
  "properties": {
    "gn:admin1_code":"4.0",
    "gn:asciiname":"Ban Don Thaen",
    "gn:country_code":"TH",
    "gn:dem":196,
    "gn:feature_class":"P",
    "gn:feature_code":"PPL",
    "gn:name":"Ban Don Thaen",
    "gn:population":0,
    "gn:timezone":"Asia/Bangkok",
    "iso:country":"TH",
    "name:tha_x_preferred":[
        "\u0e1a\u0e49\u0e32\u0e19\u0e14\u0e2d\u0e19\u0e41\u0e17\u0e48\u0e19"
    ],
    "name:und_x_variant":[
        "B\u0101n Daun Geo",
        "Ban Don Kaeo",
        "Ban Don Thaen"
    ],
    "wof:name":"Ban Don Thaen",
    "wof:placetype":"locality"
},
  "geometry": {"coordinates":[100.75033000000001,18.58131],"type":"Point"}
}