{
  "type": "Feature",
  "properties": {
    "gn:admin1_code":"67.0",
    "gn:asciiname":"Ban To Yu Da",
    "gn:country_code":"TH",
    "gn:dem":21,
    "gn:feature_class":"P",
    "gn:feature_code":"PPL",
    "gn:name":"Ban To Yu Da",
    "gn:population":0,
    "gn:timezone":"Asia/Bangkok",
    "iso:country":"TH",
    "name:tha_x_preferred":[
        "\u0e1a\u0e49\u0e32\u0e19\u0e42\u0e15\u0e4a\u0e30\u0e22\u0e39\u0e14\u0e4a\u0e30"
    ],
    "wof:name":"Ban To Yu Da",
    "wof:placetype":"locality"
},
  "geometry": {"coordinates":[100.07119,6.73217],"type":"Point"}
}