{
  "type": "Feature",
  "properties": {
    "gn:admin1_code":"27.0",
    "gn:asciiname":"Ban Pong Chanuan",
    "gn:country_code":"TH",
    "gn:dem":458,
    "gn:feature_class":"P",
    "gn:feature_code":"PPL",
    "gn:name":"Ban Pong Chanuan",
    "gn:population":0,
    "gn:timezone":"Asia/Bangkok",
    "iso:country":"TH",
    "name:tha_x_preferred":[
        "\u0e1a\u0e49\u0e32\u0e19\u0e42\u0e1b\u0e48\u0e07\u0e09\u0e19\u0e27\u0e19"
    ],
    "wof:name":"Ban Pong Chanuan",
    "wof:placetype":"locality"
},
  "geometry": {"coordinates":[101.60299999999999,14.47269],"type":"Point"}
}