{
  "type": "Feature",
  "properties": {
    "gn:admin1_code":"49.0",
    "gn:asciiname":"Ban Noen Ta Maeo",
    "gn:country_code":"TH",
    "gn:dem":4,
    "gn:feature_class":"P",
    "gn:feature_code":"PPL",
    "gn:name":"Ban Noen Ta Maeo",
    "gn:population":0,
    "gn:timezone":"Asia/Bangkok",
    "iso:country":"TH",
    "name:tha_x_preferred":[
        "\u0e1a\u0e49\u0e32\u0e19\u0e40\u0e19\u0e34\u0e19\u0e15\u0e32\u0e41\u0e21\u0e27"
    ],
    "wof:name":"Ban Noen Ta Maeo",
    "wof:placetype":"locality"
},
  "geometry": {"coordinates":[102.52607999999999,12.23344],"type":"Point"}
}