{
  "type": "Feature",
  "properties": {
    "gn:admin1_code":"57.0",
    "gn:asciiname":"Ban Fak Na",
    "gn:country_code":"TH",
    "gn:dem":10,
    "gn:feature_class":"P",
    "gn:feature_code":"PPL",
    "gn:name":"Ban Fak Na",
    "gn:population":0,
    "gn:timezone":"Asia/Bangkok",
    "iso:country":"TH",
    "name:tha_x_preferred":[
        "\u0e1a\u0e49\u0e32\u0e19\u0e1f\u0e32\u0e01\u0e19\u0e32"
    ],
    "wof:name":"Ban Fak Na",
    "wof:placetype":"locality"
},
  "geometry": {"coordinates":[99.84341999999999,12.13028],"type":"Point"}
}