{
  "type": "Feature",
  "properties": {
    "gn:admin1_code":"68.0",
    "gn:asciiname":"Ban Hin Kliang",
    "gn:country_code":"TH",
    "gn:dem":34,
    "gn:feature_class":"P",
    "gn:feature_code":"PPL",
    "gn:name":"Ban Hin Kliang",
    "gn:population":0,
    "gn:timezone":"Asia/Bangkok",
    "iso:country":"TH",
    "name:tha_x_preferred":[
        "\u0e1a\u0e49\u0e32\u0e19\u0e2b\u0e34\u0e19\u0e40\u0e01\u0e25\u0e35\u0e49\u0e22\u0e07"
    ],
    "name:und_x_variant":[
        "Ban Hin Kiang",
        "Ban Hin Kliang"
    ],
    "wof:name":"Ban Hin Kliang",
    "wof:placetype":"locality"
},
  "geometry": {"coordinates":[100.58344,7.03758],"type":"Point"}
}