{
  "type": "Feature",
  "properties": {
    "gn:admin1_code":"68.0",
    "gn:asciiname":"Ban Kho Ngam",
    "gn:cc2":"TH",
    "gn:country_code":"TH",
    "gn:dem":94,
    "gn:feature_class":"P",
    "gn:feature_code":"PPL",
    "gn:name":"Ban Kho Ngam",
    "gn:population":0,
    "gn:timezone":"Asia/Bangkok",
    "iso:country":"TH",
    "name:und_x_variant":[
        "Kho Nga",
        "Ban Kho Ngam"
    ],
    "wof:name":"Ban Kho Ngam",
    "wof:placetype":"locality"
},
  "geometry": {"coordinates":[100.76667,6.68333],"type":"Point"}
}