{
  "type": "Feature",
  "properties": {
    "gn:admin1_code":"28.0",
    "gn:asciiname":"Ban Don Khwang",
    "gn:country_code":"TH",
    "gn:dem":195,
    "gn:feature_class":"P",
    "gn:feature_code":"PPL",
    "gn:name":"Ban Don Khwang",
    "gn:population":0,
    "gn:timezone":"Asia/Bangkok",
    "iso:country":"TH",
    "name:tha_x_preferred":[
        "\u0e1a\u0e49\u0e32\u0e19\u0e14\u0e2d\u0e19\u0e02\u0e27\u0e32\u0e07"
    ],
    "name:und_x_variant":[
        "Ban Don Khuang"
    ],
    "wof:name":"Ban Don Khwang",
    "wof:placetype":"locality"
},
  "geometry": {"coordinates":[102.90619,14.55731],"type":"Point"}
}