{
  "type": "Feature",
  "properties": {
    "gn:admin1_code":"68.0",
    "gn:asciiname":"Muban Khaeo Samit",
    "gn:country_code":"TH",
    "gn:dem":10,
    "gn:feature_class":"P",
    "gn:feature_code":"PPL",
    "gn:name":"Muban Khaeo Samit",
    "gn:population":0,
    "gn:timezone":"Asia/Bangkok",
    "iso:country":"TH",
    "name:tha_x_preferred":[
        "\u0e2b\u0e21\u0e39\u0e48\u0e1a\u0e49\u0e32\u0e19\u0e41\u0e01\u0e49\u0e27\u0e2a\u0e21\u0e34\u0e18"
    ],
    "wof:name":"Muban Khaeo Samit",
    "wof:placetype":"locality"
},
  "geometry": {"coordinates":[100.46786,6.99214],"type":"Point"}
}