{
  "type": "Feature",
  "properties": {
    "gn:admin1_code":"68.0",
    "gn:asciiname":"Ban Tha Sa-an",
    "gn:country_code":"TH",
    "gn:dem":6,
    "gn:feature_class":"P",
    "gn:feature_code":"PPL",
    "gn:name":"Ban Tha Sa-an",
    "gn:population":0,
    "gn:timezone":"Asia/Bangkok",
    "iso:country":"TH",
    "name:tha_x_preferred":[
        "\u0e1a\u0e49\u0e32\u0e19\u0e17\u0e48\u0e32\u0e2a\u0e30\u0e2d\u0e49\u0e32\u0e19"
    ],
    "wof:name":"Ban Tha Sa-an",
    "wof:placetype":"locality"
},
  "geometry": {"coordinates":[100.59478,7.17228],"type":"Point"}
}