{
  "type": "Feature",
  "properties": {
    "gn:admin1_code":"70.0",
    "gn:asciiname":"Ban Tan Yuk Mian",
    "gn:country_code":"TH",
    "gn:dem":451,
    "gn:feature_class":"P",
    "gn:feature_code":"PPL",
    "gn:name":"Ban Tan Yuk Mian",
    "gn:population":0,
    "gn:timezone":"Asia/Bangkok",
    "iso:country":"TH",
    "name:tha_x_preferred":[
        "\u0e1a\u0e49\u0e32\u0e19\u0e15\u0e31\u0e19\u0e2b\u0e22\u0e38\u0e01\u0e40\u0e2b\u0e21\u0e35\u0e22\u0e19"
    ],
    "wof:name":"Ban Tan Yuk Mian",
    "wof:placetype":"locality"
},
  "geometry": {"coordinates":[101.09394,5.85128],"type":"Point"}
}