{
  "type": "Feature",
  "properties": {
    "gn:admin1_code":"64.0",
    "gn:asciiname":"Ban San Khun",
    "gn:country_code":"TH",
    "gn:dem":87,
    "gn:feature_class":"P",
    "gn:feature_code":"PPL",
    "gn:name":"Ban San Khun",
    "gn:population":0,
    "gn:timezone":"Asia/Bangkok",
    "iso:country":"TH",
    "name:tha_x_preferred":[
        "\u0e1a\u0e49\u0e32\u0e19\u0e28\u0e32\u0e25\u0e02\u0e38\u0e19"
    ],
    "wof:name":"Ban San Khun",
    "wof:placetype":"locality"
},
  "geometry": {"coordinates":[99.72535999999999,8.35331],"type":"Point"}
}