{
  "type": "Feature",
  "properties": {
    "gn:admin1_code":"31.0",
    "gn:asciiname":"Ban Ba Sa Hu Pi",
    "gn:country_code":"TH",
    "gn:dem":64,
    "gn:feature_class":"P",
    "gn:feature_code":"PPL",
    "gn:name":"Ban Ba Sa Hu Pi",
    "gn:population":0,
    "gn:timezone":"Asia/Bangkok",
    "iso:country":"TH",
    "name:tha_x_preferred":[
        "\u0e1a\u0e49\u0e32\u0e19\u0e1a\u0e32\u0e0b\u0e32\u0e2e\u0e39\u0e1b\u0e34"
    ],
    "wof:name":"Ban Ba Sa Hu Pi",
    "wof:placetype":"locality"
},
  "geometry": {"coordinates":[101.46267,6.29011],"type":"Point"}
}