{
  "type": "Feature",
  "properties": {
    "gn:admin1_code":"28",
    "gn:asciiname":"Ban Non Klang",
    "gn:country_code":"TH",
    "gn:dem":151,
    "gn:feature_class":"P",
    "gn:feature_code":"PPL",
    "gn:name":"Ban Non Klang",
    "gn:population":0,
    "gn:timezone":"Asia/Bangkok",
    "iso:country":"TH",
    "name:tha_x_preferred":[
        "\u0e1a\u0e49\u0e32\u0e19\u0e42\u0e19\u0e19\u0e01\u0e25\u0e32\u0e07"
    ],
    "wof:name":"Ban Non Klang",
    "wof:placetype":"locality"
},
  "geometry": {"coordinates":[103.18577999999999,15.18594],"type":"Point"}
}