{
  "type": "Feature",
  "properties": {
    "gn:admin1_code":"53.0",
    "gn:asciiname":"Ban O Krathing",
    "gn:country_code":"TH",
    "gn:dem":8,
    "gn:feature_class":"P",
    "gn:feature_code":"PPL",
    "gn:name":"Ban O Krathing",
    "gn:population":0,
    "gn:timezone":"Asia/Bangkok",
    "iso:country":"TH",
    "name:tha_x_preferred":[
        "\u0e1a\u0e49\u0e32\u0e19\u0e2d\u0e49\u0e2d\u0e01\u0e23\u0e30\u0e17\u0e34\u0e07"
    ],
    "name:und_x_variant":[
        "Ban Kathin Daeng",
        "Ban O Kathing",
        "Ban O Krathing",
        "\u0e1a\u0e49\u0e32\u0e19\u0e2d\u0e49\u0e2d\u0e01\u0e23\u0e30\u0e17\u0e34\u0e07"
    ],
    "wof:name":"Ban O Krathing",
    "wof:placetype":"locality"
},
  "geometry": {"coordinates":[100.0022,13.92182],"type":"Point"}
}