{
  "type": "Feature",
  "properties": {
    "gn:admin1_code":"75.0",
    "gn:asciiname":"Ban Muang Diat",
    "gn:country_code":"TH",
    "gn:dem":148,
    "gn:feature_class":"P",
    "gn:feature_code":"PPL",
    "gn:name":"Ban Muang Diat",
    "gn:population":0,
    "gn:timezone":"Asia/Bangkok",
    "iso:country":"TH",
    "name:tha_x_preferred":[
        "\u0e1a\u0e49\u0e32\u0e19\u0e21\u0e48\u0e27\u0e07\u0e40\u0e14\u0e35\u0e22\u0e14"
    ],
    "wof:name":"Ban Muang Diat",
    "wof:placetype":"locality"
},
  "geometry": {"coordinates":[105.03358,15.62992],"type":"Point"}
}