{
  "type": "Feature",
  "properties": {
    "gn:admin1_code":"25",
    "gn:asciiname":"Ban Nong Fai Nam",
    "gn:country_code":"TH",
    "gn:dem":147,
    "gn:feature_class":"P",
    "gn:feature_code":"PPL",
    "gn:name":"Ban Nong Fai Nam",
    "gn:population":0,
    "gn:timezone":"Asia/Bangkok",
    "iso:country":"TH",
    "name:tha_x_preferred":[
        "\u0e1a\u0e49\u0e32\u0e19\u0e2b\u0e19\u0e2d\u0e07\u0e1d\u0e32\u0e22\u0e19\u0e49\u0e33"
    ],
    "wof:name":"Ban Nong Fai Nam",
    "wof:placetype":"locality"
},
  "geometry": {"coordinates":[104.01608,16.15678],"type":"Point"}
}