{
  "type": "Feature",
  "properties": {
    "gn:admin1_code":"3.0",
    "gn:asciiname":"Ban Mae Poen Pa Miang",
    "gn:country_code":"TH",
    "gn:dem":483,
    "gn:feature_class":"P",
    "gn:feature_code":"PPL",
    "gn:name":"Ban Mae Poen Pa Miang",
    "gn:population":0,
    "gn:timezone":"Asia/Bangkok",
    "iso:country":"TH",
    "name:tha_x_preferred":[
        "\u0e1a\u0e49\u0e32\u0e19\u0e41\u0e21\u0e48\u0e40\u0e1b\u0e34\u0e19\u0e1b\u0e48\u0e32\u0e40\u0e21\u0e35\u0e48\u0e22\u0e07"
    ],
    "wof:lang_x_official":[
        "tha"
    ],
    "wof:lang_x_spoken":[
        "tha"
    ],
    "wof:name":"Ban Mae Poen Pa Miang",
    "wof:placetype":"locality"
},
  "geometry": {"coordinates":[99.77988999999999,20.15747],"type":"Point"}
}