{
  "type": "Feature",
  "properties": {
    "gn:admin1_code":"16.0",
    "gn:asciiname":"Ban Rong Rakam",
    "gn:country_code":"TH",
    "gn:dem":54,
    "gn:feature_class":"P",
    "gn:feature_code":"PPL",
    "gn:name":"Ban Rong Rakam",
    "gn:population":0,
    "gn:timezone":"Asia/Bangkok",
    "iso:country":"TH",
    "name:tha_x_preferred":[
        "\u0e1a\u0e49\u0e32\u0e19\u0e23\u0e48\u0e2d\u0e07\u0e23\u0e30\u0e01\u0e33"
    ],
    "wof:name":"Ban Rong Rakam",
    "wof:placetype":"locality"
},
  "geometry": {"coordinates":[100.66088999999999,15.50903],"type":"Point"}
}