{
  "type": "Feature",
  "properties": {
    "gn:admin1_code":"15.0",
    "gn:asciiname":"Ban Krachon",
    "gn:country_code":"TH",
    "gn:dem":77,
    "gn:feature_class":"P",
    "gn:feature_code":"PPL",
    "gn:name":"Ban Krachon",
    "gn:population":0,
    "gn:timezone":"Asia/Bangkok",
    "iso:country":"TH",
    "name:tha_x_preferred":[
        "\u0e1a\u0e49\u0e32\u0e19\u0e01\u0e23\u0e30\u0e0a\u0e2d\u0e19"
    ],
    "wof:name":"Ban Krachon",
    "wof:placetype":"locality"
},
  "geometry": {"coordinates":[99.6885,15.34769],"type":"Point"}
}