{
  "type": "Feature",
  "properties": {
    "gn:admin1_code":"64.0",
    "gn:asciiname":"Ban Dan Pap",
    "gn:country_code":"TH",
    "gn:dem":73,
    "gn:feature_class":"P",
    "gn:feature_code":"PPL",
    "gn:name":"Ban Dan Pap",
    "gn:population":0,
    "gn:timezone":"Asia/Bangkok",
    "iso:country":"TH",
    "name:tha_x_preferred":[
        "\u0e1a\u0e49\u0e32\u0e19\u0e14\u0e48\u0e32\u0e19\u0e1b\u0e32\u0e1a"
    ],
    "wof:name":"Ban Dan Pap",
    "wof:placetype":"locality"
},
  "geometry": {"coordinates":[99.69631,8.18214],"type":"Point"}
}