{
  "type": "Feature",
  "properties": {
    "gn:admin1_code":"28",
    "gn:asciiname":"Ban Khok Makham",
    "gn:country_code":"TH",
    "gn:dem":155,
    "gn:feature_class":"P",
    "gn:feature_code":"PPL",
    "gn:name":"Ban Khok Makham",
    "gn:population":0,
    "gn:timezone":"Asia/Bangkok",
    "iso:country":"TH",
    "name:tha_x_preferred":[
        "\u0e1a\u0e49\u0e32\u0e19\u0e42\u0e04\u0e01\u0e21\u0e30\u0e02\u0e32\u0e21"
    ],
    "wof:name":"Ban Khok Makham",
    "wof:placetype":"locality"
},
  "geometry": {"coordinates":[103.15756,15.00858],"type":"Point"}
}