{
  "type": "Feature",
  "properties": {
    "gn:admin1_code":"64.0",
    "gn:asciiname":"Ban Wang Nai",
    "gn:country_code":"TH",
    "gn:dem":209,
    "gn:feature_class":"P",
    "gn:feature_code":"PPL",
    "gn:name":"Ban Wang Nai",
    "gn:population":0,
    "gn:timezone":"Asia/Bangkok",
    "iso:country":"TH",
    "name:tha_x_preferred":[
        "\u0e1a\u0e49\u0e32\u0e19\u0e27\u0e31\u0e07\u0e43\u0e19"
    ],
    "wof:name":"Ban Wang Nai",
    "wof:placetype":"locality"
},
  "geometry": {"coordinates":[99.76244,8.11781],"type":"Point"}
}