{
  "type": "Feature",
  "properties": {
    "gn:admin1_code":"33",
    "gn:asciiname":"Ban Tha San Chao",
    "gn:country_code":"TH",
    "gn:dem":17,
    "gn:feature_class":"P",
    "gn:feature_code":"PPL",
    "gn:name":"Ban Tha San Chao",
    "gn:population":0,
    "gn:timezone":"Asia/Bangkok",
    "iso:country":"TH",
    "name:tha_x_preferred":[
        "\u0e1a\u0e49\u0e32\u0e19\u0e17\u0e48\u0e32\u0e28\u0e32\u0e25\u0e40\u0e08\u0e49\u0e32"
    ],
    "wof:name":"Ban Tha San Chao",
    "wof:placetype":"locality"
},
  "geometry": {"coordinates":[100.27939000000001,14.92747],"type":"Point"}
}