{
  "type": "Feature",
  "properties": {
    "gn:admin1_code":"30.0",
    "gn:asciiname":"Ban Phia Nam",
    "gn:country_code":"TH",
    "gn:dem":131,
    "gn:feature_class":"P",
    "gn:feature_code":"PPL",
    "gn:name":"Ban Phia Nam",
    "gn:population":0,
    "gn:timezone":"Asia/Bangkok",
    "iso:country":"TH",
    "name:tha_x_preferred":[
        "\u0e1a\u0e49\u0e32\u0e19\u0e40\u0e1e\u0e35\u0e22\u0e19\u0e32\u0e21"
    ],
    "name:und_x_variant":[
        "Ban Phon Nam",
        "Ban Phia Nam"
    ],
    "wof:lang_x_official":[
        "tha"
    ],
    "wof:lang_x_spoken":[
        "tha"
    ],
    "wof:name":"Ban Phia Nam",
    "wof:placetype":"locality"
},
  "geometry": {"coordinates":[104.27683,15.12881],"type":"Point"}
}