{
  "type": "Feature",
  "properties": {
    "gn:admin1_code":"50.0",
    "gn:asciiname":"Ban Tha Krabue",
    "gn:country_code":"TH",
    "gn:dem":39,
    "gn:feature_class":"P",
    "gn:feature_code":"PPL",
    "gn:name":"Ban Tha Krabue",
    "gn:population":0,
    "gn:timezone":"Asia/Bangkok",
    "iso:country":"TH",
    "name:tha_x_preferred":[
        "\u0e1a\u0e49\u0e32\u0e19\u0e17\u0e48\u0e32\u0e01\u0e23\u0e30\u0e1a\u0e37\u0e2d"
    ],
    "wof:name":"Ban Tha Krabue",
    "wof:placetype":"locality"
},
  "geometry": {"coordinates":[99.50031,13.92633],"type":"Point"}
}