{
  "type": "Feature",
  "properties": {
    "gn:admin1_code":"58.0",
    "gn:asciiname":"Ban Khlong A-rak",
    "gn:country_code":"TH",
    "gn:dem":116,
    "gn:feature_class":"P",
    "gn:feature_code":"PPL",
    "gn:name":"Ban Khlong A-rak",
    "gn:population":0,
    "gn:timezone":"Asia/Bangkok",
    "iso:country":"TH",
    "name:tha_x_preferred":[
        "\u0e1a\u0e49\u0e32\u0e19\u0e04\u0e25\u0e2d\u0e07\u0e2d\u0e32\u0e23\u0e31\u0e01\u0e29\u0e4c"
    ],
    "wof:name":"Ban Khlong A-rak",
    "wof:placetype":"locality"
},
  "geometry": {"coordinates":[98.86225,9.94017],"type":"Point"}
}