{
  "type": "Feature",
  "properties": {
    "gn:admin1_code":"55.0",
    "gn:asciiname":"Ban Rang Nam Sai",
    "gn:country_code":"TH",
    "gn:dem":7,
    "gn:feature_class":"P",
    "gn:feature_code":"PPL",
    "gn:name":"Ban Rang Nam Sai",
    "gn:population":0,
    "gn:timezone":"Asia/Bangkok",
    "iso:country":"TH",
    "name:tha_x_preferred":[
        "\u0e1a\u0e49\u0e32\u0e19\u0e23\u0e32\u0e07\u0e19\u0e49\u0e33\u0e43\u0e2a"
    ],
    "wof:name":"Ban Rang Nam Sai",
    "wof:placetype":"locality"
},
  "geometry": {"coordinates":[100.30744,13.67261],"type":"Point"}
}