{
  "type": "Feature",
  "properties": {
    "gn:admin1_code":"74",
    "gn:asciiname":"Ban Sa Thaen",
    "gn:country_code":"TH",
    "gn:dem":39,
    "gn:feature_class":"P",
    "gn:feature_code":"PPL",
    "gn:name":"Ban Sa Thaen",
    "gn:population":0,
    "gn:timezone":"Asia/Bangkok",
    "iso:country":"TH",
    "name:tha_x_preferred":[
        "\u0e1a\u0e49\u0e32\u0e19\u0e2a\u0e23\u0e30\u0e41\u0e17\u0e48\u0e19"
    ],
    "wof:name":"Ban Sa Thaen",
    "wof:placetype":"locality"
},
  "geometry": {"coordinates":[101.84786,14.11492],"type":"Point"}
}