{
  "type": "Feature",
  "properties": {
    "gn:admin1_code":"37",
    "gn:asciiname":"Ban Khlong Krathing",
    "gn:country_code":"TH",
    "gn:dem":59,
    "gn:feature_class":"P",
    "gn:feature_code":"PPL",
    "gn:name":"Ban Khlong Krathing",
    "gn:population":0,
    "gn:timezone":"Asia/Bangkok",
    "iso:country":"TH",
    "name:tha_x_preferred":[
        "\u0e1a\u0e49\u0e32\u0e19\u0e04\u0e25\u0e2d\u0e07\u0e01\u0e23\u0e30\u0e17\u0e34\u0e07"
    ],
    "wof:name":"Ban Khlong Krathing",
    "wof:placetype":"locality"
},
  "geometry": {"coordinates":[101.11922,14.88239],"type":"Point"}
}