{
  "type": "Feature",
  "properties": {
    "gn:admin1_code":"3.0",
    "gn:asciiname":"Ban San Klang",
    "gn:country_code":"TH",
    "gn:dem":470,
    "gn:feature_class":"P",
    "gn:feature_code":"PPL",
    "gn:name":"Ban San Klang",
    "gn:population":0,
    "gn:timezone":"Asia/Bangkok",
    "iso:country":"TH",
    "name:tha_x_preferred":[
        "\u0e1a\u0e49\u0e32\u0e19\u0e2a\u0e31\u0e19\u0e01\u0e25\u0e32\u0e07"
    ],
    "wof:name":"Ban San Klang",
    "wof:placetype":"locality"
},
  "geometry": {"coordinates":[99.53625,19.67028],"type":"Point"}
}