{
  "type": "Feature",
  "properties": {
    "gn:admin1_code":"80",
    "gn:asciiname":"Ban Nong Pa Mak",
    "gn:country_code":"TH",
    "gn:dem":66,
    "gn:feature_class":"P",
    "gn:feature_code":"PPL",
    "gn:name":"Ban Nong Pa Mak",
    "gn:population":0,
    "gn:timezone":"Asia/Bangkok",
    "iso:country":"TH",
    "name:tha_x_preferred":[
        "\u0e1a\u0e49\u0e32\u0e19\u0e2b\u0e19\u0e2d\u0e07\u0e1b\u0e48\u0e32\u0e2b\u0e21\u0e32\u0e01"
    ],
    "wof:name":"Ban Nong Pa Mak",
    "wof:placetype":"locality"
},
  "geometry": {"coordinates":[102.21611,13.79953],"type":"Point"}
}