{
  "type": "Feature",
  "properties": {
    "gn:admin1_code":"55.0",
    "gn:asciiname":"Ban Klang Don",
    "gn:country_code":"TH",
    "gn:dem":3,
    "gn:feature_class":"P",
    "gn:feature_code":"PPL",
    "gn:name":"Ban Klang Don",
    "gn:population":0,
    "gn:timezone":"Asia/Bangkok",
    "iso:country":"TH",
    "name:tha_x_preferred":[
        "\u0e1a\u0e49\u0e32\u0e19\u0e01\u0e25\u0e32\u0e07\u0e14\u0e2d\u0e19"
    ],
    "wof:name":"Ban Klang Don",
    "wof:placetype":"locality"
},
  "geometry": {"coordinates":[100.31453,13.61742],"type":"Point"}
}