{
  "type": "Feature",
  "properties": {
    "gn:admin1_code":"56.0",
    "gn:asciiname":"Ban Yang Yong",
    "gn:country_code":"TH",
    "gn:dem":16,
    "gn:feature_class":"P",
    "gn:feature_code":"PPL",
    "gn:name":"Ban Yang Yong",
    "gn:population":0,
    "gn:timezone":"Asia/Bangkok",
    "iso:country":"TH",
    "name:tha_x_preferred":[
        "\u0e1a\u0e49\u0e32\u0e19\u0e22\u0e32\u0e07\u0e2b\u0e22\u0e48\u0e2d\u0e07"
    ],
    "name:und_x_variant":[
        "Amphu Yang Ryong",
        "Yang Yaung",
        "Yang Yohng",
        "Yang Yong",
        "Ban Yang Yong"
    ],
    "wof:lang_x_official":[
        "tha"
    ],
    "wof:lang_x_spoken":[
        "tha"
    ],
    "wof:name":"Ban Yang Yong",
    "wof:placetype":"locality"
},
  "geometry": {"coordinates":[99.88794,12.98278],"type":"Point"}
}