{
  "type": "Feature",
  "properties": {
    "gn:admin1_code":"30.0",
    "gn:asciiname":"Ban Bing",
    "gn:country_code":"TH",
    "gn:dem":149,
    "gn:feature_class":"P",
    "gn:feature_code":"PPL",
    "gn:name":"Ban Bing",
    "gn:population":0,
    "gn:timezone":"Asia/Bangkok",
    "iso:country":"TH",
    "name:tha_x_preferred":[
        "\u0e1a\u0e49\u0e32\u0e19\u0e1a\u0e34\u0e07"
    ],
    "name:und_x_variant":[
        "Ban Baeng",
        "Ban Bing"
    ],
    "wof:name":"Ban Bing",
    "wof:placetype":"locality"
},
  "geometry": {"coordinates":[104.19441999999999,14.77233],"type":"Point"}
}