{
  "type": "Feature",
  "properties": {
    "gn:admin1_code":"80",
    "gn:asciiname":"Ban Mai Sa Buri",
    "gn:country_code":"TH",
    "gn:dem":85,
    "gn:feature_class":"P",
    "gn:feature_code":"PPL",
    "gn:name":"Ban Mai Sa Buri",
    "gn:population":0,
    "gn:timezone":"Asia/Bangkok",
    "iso:country":"TH",
    "name:tha_x_preferred":[
        "\u0e1a\u0e49\u0e32\u0e19\u0e43\u0e2b\u0e21\u0e48\u0e2a\u0e23\u0e30\u0e1a\u0e38\u0e23\u0e35"
    ],
    "wof:name":"Ban Mai Sa Buri",
    "wof:placetype":"locality"
},
  "geometry": {"coordinates":[102.12094,13.49225],"type":"Point"}
}