{
  "type": "Feature",
  "properties": {
    "gn:admin1_code":"52.0",
    "gn:asciiname":"Ban Dong Chani",
    "gn:country_code":"TH",
    "gn:dem":128,
    "gn:feature_class":"P",
    "gn:feature_code":"PPL",
    "gn:name":"Ban Dong Chani",
    "gn:population":0,
    "gn:timezone":"Asia/Bangkok",
    "iso:country":"TH",
    "name:tha_x_preferred":[
        "\u0e1a\u0e49\u0e32\u0e19\u0e14\u0e07\u0e0a\u0e30\u0e19\u0e35"
    ],
    "wof:name":"Ban Dong Chani",
    "wof:placetype":"locality"
},
  "geometry": {"coordinates":[99.367,13.60072],"type":"Point"}
}