{
  "type": "Feature",
  "properties": {
    "gn:admin1_code":"70.0",
    "gn:asciiname":"Ban Ko Mo Sam Sip Paet",
    "gn:country_code":"TH",
    "gn:dem":122,
    "gn:feature_class":"P",
    "gn:feature_code":"PPL",
    "gn:name":"Ban Ko Mo Sam Sip Paet",
    "gn:population":0,
    "gn:timezone":"Asia/Bangkok",
    "iso:country":"TH",
    "name:tha_x_preferred":[
        "\u0e1a\u0e49\u0e32\u0e19 \u0e01\u0e21. \u0e2a\u0e32\u0e21\u0e2a\u0e34\u0e1a\u0e41\u0e1b\u0e14"
    ],
    "name:und_x_variant":[
        "Ban Ko Mo 38",
        "Ban Ko Mo Sam Sip Paet"
    ],
    "wof:lang_x_official":[
        "tha"
    ],
    "wof:lang_x_spoken":[
        "tha"
    ],
    "wof:name":"Ban Ko Mo Sam Sip Paet",
    "wof:placetype":"locality"
},
  "geometry": {"coordinates":[101.20068999999999,5.97239],"type":"Point"}
}