{
  "type": "Feature",
  "properties": {
    "gn:admin1_code":"53.0",
    "gn:asciiname":"Ban Rang Phikun",
    "gn:country_code":"TH",
    "gn:dem":12,
    "gn:feature_class":"P",
    "gn:feature_code":"PPL",
    "gn:name":"Ban Rang Phikun",
    "gn:population":0,
    "gn:timezone":"Asia/Bangkok",
    "iso:country":"TH",
    "name:tha_x_preferred":[
        "Ban Rang Phikun"
    ],
    "name:tha_x_variant":[
        "\u0e1a\u0e49\u0e32\u0e19\u0e23\u0e32\u0e07\u0e1e\u0e34\u0e01\u0e38\u0e25"
    ],
    "wof:name":"Ban Rang Phikun",
    "wof:placetype":"locality"
},
  "geometry": {"coordinates":[99.97689,13.99689],"type":"Point"}
}