{
  "type": "Feature",
  "properties": {
    "gn:admin1_code":"27",
    "gn:asciiname":"Ban Pradu Ngam",
    "gn:country_code":"TH",
    "gn:dem":251,
    "gn:feature_class":"P",
    "gn:feature_code":"PPL",
    "gn:name":"Ban Pradu Ngam",
    "gn:population":0,
    "gn:timezone":"Asia/Bangkok",
    "iso:country":"TH",
    "name:tha_x_preferred":[
        "\u0e1a\u0e49\u0e32\u0e19\u0e1b\u0e23\u0e30\u0e14\u0e39\u0e48\u0e07\u0e32\u0e21"
    ],
    "wof:name":"Ban Pradu Ngam",
    "wof:placetype":"locality"
},
  "geometry": {"coordinates":[102.36908,14.553],"type":"Point"}
}