{
  "type": "Feature",
  "properties": {
    "gn:admin1_code":"52.0",
    "gn:asciiname":"Ban Nai Ko",
    "gn:country_code":"TH",
    "gn:dem":10,
    "gn:feature_class":"P",
    "gn:feature_code":"PPL",
    "gn:name":"Ban Nai Ko",
    "gn:population":0,
    "gn:timezone":"Asia/Bangkok",
    "iso:country":"TH",
    "name:tha_x_preferred":[
        "\u0e1a\u0e49\u0e32\u0e19\u0e43\u0e19\u0e40\u0e01\u0e32\u0e30"
    ],
    "wof:name":"Ban Nai Ko",
    "wof:placetype":"locality"
},
  "geometry": {"coordinates":[99.852,13.51728],"type":"Point"}
}