{
  "type": "Feature",
  "properties": {
    "gn:admin1_code":"4.0",
    "gn:asciiname":"Ban Na Kin",
    "gn:country_code":"TH",
    "gn:dem":944,
    "gn:feature_class":"P",
    "gn:feature_code":"PPL",
    "gn:name":"Ban Na Kin",
    "gn:population":0,
    "gn:timezone":"Asia/Bangkok",
    "iso:country":"TH",
    "name:tha_x_preferred":[
        "\u0e1a\u0e49\u0e32\u0e19\u0e19\u0e32\u0e01\u0e34\u0e4b\u0e19"
    ],
    "wof:name":"Ban Na Kin",
    "wof:placetype":"locality"
},
  "geometry": {"coordinates":[101.17381,19.31575],"type":"Point"}
}