{
  "type": "Feature",
  "properties": {
    "gn:admin1_code":"51.0",
    "gn:asciiname":"Ban Talat Wang Wa",
    "gn:country_code":"TH",
    "gn:dem":15,
    "gn:feature_class":"P",
    "gn:feature_code":"PPL",
    "gn:name":"Ban Talat Wang Wa",
    "gn:population":0,
    "gn:timezone":"Asia/Bangkok",
    "iso:country":"TH",
    "name:tha_x_preferred":[
        "\u0e1a\u0e49\u0e32\u0e19\u0e15\u0e25\u0e32\u0e14\u0e27\u0e31\u0e07\u0e2b\u0e27\u0e49\u0e32"
    ],
    "name:und_x_variant":[
        "Ban Wang Wa"
    ],
    "wof:lang_x_official":[
        "tha"
    ],
    "wof:lang_x_spoken":[
        "tha"
    ],
    "wof:name":"Ban Talat Wang Wa",
    "wof:placetype":"locality"
},
  "geometry": {"coordinates":[100.10708,14.68158],"type":"Point"}
}