{
  "type": "Feature",
  "properties": {
    "gn:admin1_code":"26.0",
    "gn:asciiname":"Ban Kut Chanuan",
    "gn:country_code":"TH",
    "gn:dem":188,
    "gn:feature_class":"P",
    "gn:feature_code":"PPL",
    "gn:name":"Ban Kut Chanuan",
    "gn:population":0,
    "gn:timezone":"Asia/Bangkok",
    "iso:country":"TH",
    "name:tha_x_preferred":[
        "\u0e1a\u0e49\u0e32\u0e19\u0e01\u0e38\u0e14\u0e09\u0e19\u0e27\u0e19"
    ],
    "name:und_x_variant":[
        "B\u0101n Gut Ta Phuang",
        "Ban Kut Ta Phuang",
        "Ban Kut Chanuan"
    ],
    "wof:name":"Ban Kut Chanuan",
    "wof:placetype":"locality"
},
  "geometry": {"coordinates":[101.92506,15.72331],"type":"Point"}
}