{
  "type": "Feature",
  "properties": {
    "gn:admin1_code":"69.0",
    "gn:asciiname":"Ban Phun Sawat Phatthana",
    "gn:country_code":"TH",
    "gn:dem":5,
    "gn:feature_class":"P",
    "gn:feature_code":"PPL",
    "gn:name":"Ban Phun Sawat Phatthana",
    "gn:population":0,
    "gn:timezone":"Asia/Bangkok",
    "iso:country":"TH",
    "name:tha_x_preferred":[
        "\u0e1a\u0e49\u0e32\u0e19\u0e1e\u0e39\u0e19\u0e2a\u0e27\u0e31\u0e2a\u0e14\u0e34\u0e4c\u0e1e\u0e31\u0e12\u0e19\u0e32"
    ],
    "wof:name":"Ban Phun Sawat Phatthana",
    "wof:placetype":"locality"
},
  "geometry": {"coordinates":[101.26053,6.88475],"type":"Point"}
}