{
  "type": "Feature",
  "properties": {
    "gn:admin1_code":"26.0",
    "gn:asciiname":"Ban Wang Katha",
    "gn:country_code":"TH",
    "gn:dem":261,
    "gn:feature_class":"P",
    "gn:feature_code":"PPL",
    "gn:name":"Ban Wang Katha",
    "gn:population":0,
    "gn:timezone":"Asia/Bangkok",
    "iso:country":"TH",
    "name:tha_x_preferred":[
        "\u0e1a\u0e49\u0e32\u0e19\u0e27\u0e31\u0e07\u0e01\u0e30\u0e17\u0e30"
    ],
    "wof:name":"Ban Wang Katha",
    "wof:placetype":"locality"
},
  "geometry": {"coordinates":[101.57971999999999,15.80806],"type":"Point"}
}