{
  "type": "Feature",
  "properties": {
    "gn:admin1_code":"12.0",
    "gn:asciiname":"Ban Pha Luang Sap Rang",
    "gn:country_code":"TH",
    "gn:dem":80,
    "gn:feature_class":"P",
    "gn:feature_code":"PPL",
    "gn:name":"Ban Pha Luang Sap Rang",
    "gn:population":0,
    "gn:timezone":"Asia/Bangkok",
    "iso:country":"TH",
    "name:tha_x_preferred":[
        "\u0e1a\u0e49\u0e32\u0e19\u0e1c\u0e32\u0e2b\u0e25\u0e27\u0e07\u0e0b\u0e31\u0e1a\u0e23\u0e31\u0e07"
    ],
    "wof:name":"Ban Pha Luang Sap Rang",
    "wof:placetype":"locality"
},
  "geometry": {"coordinates":[100.67780999999999,16.47661],"type":"Point"}
}