{
  "type": "Feature",
  "properties": {
    "gn:admin1_code":"72.0",
    "gn:asciiname":"Ban Si Than",
    "gn:country_code":"TH",
    "gn:dem":139,
    "gn:feature_class":"P",
    "gn:feature_code":"PPL",
    "gn:name":"Ban Si Than",
    "gn:population":0,
    "gn:timezone":"Asia/Bangkok",
    "iso:country":"TH",
    "name:tha_x_preferred":[
        "\u0e1a\u0e49\u0e32\u0e19\u0e28\u0e23\u0e35\u0e10\u0e32\u0e19"
    ],
    "name:und_x_variant":[
        "Ban Si Chan",
        "Ban Si Than"
    ],
    "wof:name":"Ban Si Than",
    "wof:placetype":"locality"
},
  "geometry": {"coordinates":[104.33247,15.77806],"type":"Point"}
}