{
  "type": "Feature",
  "properties": {
    "gn:admin1_code":"3.0",
    "gn:asciiname":"Ban Pa Hang Ngam",
    "gn:country_code":"TH",
    "gn:dem":407,
    "gn:feature_class":"P",
    "gn:feature_code":"PPL",
    "gn:name":"Ban Pa Hang Ngam",
    "gn:population":0,
    "gn:timezone":"Asia/Bangkok",
    "iso:country":"TH",
    "name:tha_x_preferred":[
        "\u0e1a\u0e49\u0e32\u0e19\u0e1b\u0e48\u0e32\u0e2e\u0e32\u0e07\u0e07\u0e32\u0e21"
    ],
    "wof:name":"Ban Pa Hang Ngam",
    "wof:placetype":"locality"
},
  "geometry": {"coordinates":[99.76658,19.47569],"type":"Point"}
}