{
  "type": "Feature",
  "properties": {
    "gn:admin1_code":"29",
    "gn:asciiname":"Ban Phum Mai",
    "gn:country_code":"TH",
    "gn:dem":165,
    "gn:feature_class":"P",
    "gn:feature_code":"PPL",
    "gn:name":"Ban Phum Mai",
    "gn:population":0,
    "gn:timezone":"Asia/Bangkok",
    "iso:country":"TH",
    "name:tha_x_preferred":[
        "\u0e1a\u0e49\u0e32\u0e19\u0e20\u0e39\u0e21\u0e34\u0e43\u0e2b\u0e21\u0e48"
    ],
    "wof:name":"Ban Phum Mai",
    "wof:placetype":"locality"
},
  "geometry": {"coordinates":[103.38352999999999,14.71403],"type":"Point"}
}