{
  "type": "Feature",
  "properties": {
    "gn:admin1_code":"2.0",
    "gn:asciiname":"Ban Huai Khang Fai",
    "gn:country_code":"TH",
    "gn:dem":318,
    "gn:feature_class":"P",
    "gn:feature_code":"PPL",
    "gn:name":"Ban Huai Khang Fai",
    "gn:population":0,
    "gn:timezone":"Asia/Bangkok",
    "iso:country":"TH",
    "wof:name":"Ban Huai Khang Fai",
    "wof:placetype":"locality"
},
  "geometry": {"coordinates":[98.66167,18.48806],"type":"Point"}
}