{
  "type": "Feature",
  "properties": {
    "gn:admin1_code":"42.0",
    "gn:asciiname":"Ban Bang Ping",
    "gn:cc2":"TH",
    "gn:country_code":"TH",
    "gn:dem":4,
    "gn:feature_class":"P",
    "gn:feature_code":"PPL",
    "gn:name":"Ban Bang Ping",
    "gn:population":0,
    "gn:timezone":"Asia/Bangkok",
    "iso:country":"TH",
    "name:tha_x_preferred":[
        "\u0e1a\u0e49\u0e32\u0e19\u0e1a\u0e32\u0e07\u0e1b\u0e34\u0e49\u0e07"
    ],
    "name:und_x_variant":[
        "Ban Khlong Bang Ping",
        "Ban Bang Ping"
    ],
    "wof:name":"Ban Bang Ping",
    "wof:placetype":"locality"
},
  "geometry": {"coordinates":[100.63336,13.61372],"type":"Point"}
}