{
  "type": "Feature",
  "properties": {
    "gn:admin1_code":"14.0",
    "gn:asciiname":"Ban Nam Ko Prong",
    "gn:country_code":"TH",
    "gn:dem":173,
    "gn:feature_class":"P",
    "gn:feature_code":"PPL",
    "gn:name":"Ban Nam Ko Prong",
    "gn:population":0,
    "gn:timezone":"Asia/Bangkok",
    "iso:country":"TH",
    "name:tha_x_preferred":[
        "\u0e1a\u0e49\u0e32\u0e19\u0e19\u0e49\u0e33\u0e01\u0e49\u0e2d\u0e42\u0e1b\u0e23\u0e48\u0e07"
    ],
    "wof:name":"Ban Nam Ko Prong",
    "wof:placetype":"locality"
},
  "geometry": {"coordinates":[101.18142,16.79089],"type":"Point"}
}