{
  "type": "Feature",
  "properties": {
    "gn:admin1_code":"10.0",
    "gn:asciiname":"Ban Cham Thong",
    "gn:country_code":"TH",
    "gn:dem":63,
    "gn:feature_class":"P",
    "gn:feature_code":"PPL",
    "gn:name":"Ban Cham Thong",
    "gn:population":0,
    "gn:timezone":"Asia/Bangkok",
    "iso:country":"TH",
    "name:tha_x_preferred":[
        "Ban Cham Thong"
    ],
    "name:tha_x_variant":[
        "\u0e1a\u0e49\u0e32\u0e19\u0e0a\u0e33\u0e17\u0e2d\u0e07"
    ],
    "wof:name":"Ban Cham Thong",
    "wof:placetype":"locality"
},
  "geometry": {"coordinates":[100.09989,17.44753],"type":"Point"}
}