{
  "type": "Feature",
  "properties": {
    "gn:admin1_code":"3.0",
    "gn:asciiname":"Ban Chaiyaphum",
    "gn:country_code":"TH",
    "gn:dem":394,
    "gn:feature_class":"P",
    "gn:feature_code":"PPL",
    "gn:name":"Ban Chaiyaphum",
    "gn:population":0,
    "gn:timezone":"Asia/Bangkok",
    "iso:country":"TH",
    "name:tha_x_preferred":[
        "\u0e1a\u0e49\u0e32\u0e19\u0e0a\u0e31\u0e22\u0e20\u0e39\u0e21\u0e34"
    ],
    "wof:name":"Ban Chaiyaphum",
    "wof:placetype":"locality"
},
  "geometry": {"coordinates":[99.93581,19.87675],"type":"Point"}
}