{
  "type": "Feature",
  "properties": {
    "gn:admin1_code":"76.0",
    "gn:asciiname":"Ban Kham O",
    "gn:country_code":"TH",
    "gn:dem":177,
    "gn:feature_class":"P",
    "gn:feature_code":"PPL",
    "gn:name":"Ban Kham O",
    "gn:population":0,
    "gn:timezone":"Asia/Bangkok",
    "iso:country":"TH",
    "name:tha_x_preferred":[
        "\u0e1a\u0e49\u0e32\u0e19\u0e04\u0e33\u0e2d\u0e49\u0e2d"
    ],
    "wof:name":"Ban Kham O",
    "wof:placetype":"locality"
},
  "geometry": {"coordinates":[103.22908,17.35764],"type":"Point"}
}