{
  "type": "Feature",
  "properties": {
    "gn:admin1_code":"27",
    "gn:asciiname":"Ban Wa Phu Kaeo",
    "gn:country_code":"TH",
    "gn:dem":288,
    "gn:feature_class":"P",
    "gn:feature_code":"PPL",
    "gn:name":"Ban Wa Phu Kaeo",
    "gn:population":0,
    "gn:timezone":"Asia/Bangkok",
    "iso:country":"TH",
    "name:tha_x_preferred":[
        "\u0e1a\u0e49\u0e32\u0e19\u0e27\u0e30\u0e20\u0e39\u0e41\u0e01\u0e49\u0e27"
    ],
    "wof:name":"Ban Wa Phu Kaeo",
    "wof:placetype":"locality"
},
  "geometry": {"coordinates":[101.717,14.77219],"type":"Point"}
}