{
  "type": "Feature",
  "properties": {
    "gn:admin1_code":"12.0",
    "gn:asciiname":"Ban Huai Hom",
    "gn:country_code":"TH",
    "gn:dem":485,
    "gn:feature_class":"P",
    "gn:feature_code":"PPL",
    "gn:name":"Ban Huai Hom",
    "gn:population":0,
    "gn:timezone":"Asia/Bangkok",
    "iso:country":"TH",
    "name:tha_x_preferred":[
        "\u0e1a\u0e49\u0e32\u0e19\u0e2b\u0e49\u0e27\u0e22\u0e2b\u0e49\u0e2d\u0e21"
    ],
    "wof:name":"Ban Huai Hom",
    "wof:placetype":"locality"
},
  "geometry": {"coordinates":[100.67731000000001,17.06217],"type":"Point"}
}