{
  "type": "Feature",
  "properties": {
    "gn:admin1_code":"68.0",
    "gn:asciiname":"Ban Lo Bon",
    "gn:country_code":"TH",
    "gn:dem":44,
    "gn:feature_class":"P",
    "gn:feature_code":"PPL",
    "gn:name":"Ban Lo Bon",
    "gn:population":0,
    "gn:timezone":"Asia/Bangkok",
    "iso:country":"TH",
    "name:tha_x_preferred":[
        "\u0e1a\u0e49\u0e32\u0e19\u0e42\u0e2b\u0e25\u0e4a\u0e30\u0e1a\u0e2d\u0e19"
    ],
    "name:und_x_variant":[
        "Lum Baun",
        "Ban Lum Bonc",
        "Ban Lum Bon",
        "Ban Lo Bon"
    ],
    "wof:name":"Ban Lo Bon",
    "wof:placetype":"locality"
},
  "geometry": {"coordinates":[100.86472000000001,6.75611],"type":"Point"}
}