{
  "type": "Feature",
  "properties": {
    "gn:admin1_code":"25",
    "gn:asciiname":"Ban Nong Si Thong",
    "gn:country_code":"TH",
    "gn:dem":137,
    "gn:feature_class":"P",
    "gn:feature_code":"PPL",
    "gn:name":"Ban Nong Si Thong",
    "gn:population":0,
    "gn:timezone":"Asia/Bangkok",
    "iso:country":"TH",
    "name:tha_x_preferred":[
        "\u0e1a\u0e49\u0e32\u0e19\u0e2b\u0e19\u0e2d\u0e07\u0e28\u0e23\u0e35\u0e17\u0e2d\u0e07"
    ],
    "wof:name":"Ban Nong Si Thong",
    "wof:placetype":"locality"
},
  "geometry": {"coordinates":[104.10925,15.58833],"type":"Point"}
}