{
  "type": "Feature",
  "properties": {
    "gn:admin1_code":"27.0",
    "gn:asciiname":"Ban Khon In",
    "gn:country_code":"TH",
    "gn:dem":180,
    "gn:feature_class":"P",
    "gn:feature_code":"PPL",
    "gn:name":"Ban Khon In",
    "gn:population":0,
    "gn:timezone":"Asia/Bangkok",
    "iso:country":"TH",
    "name:tha_x_preferred":[
        "\u0e1a\u0e49\u0e32\u0e19\u0e04\u0e2d\u0e19\u0e2d\u0e34\u0e19\u0e17\u0e23\u0e4c"
    ],
    "name:und_x_variant":[
        "Ban Nong Khon"
    ],
    "wof:lang_x_official":[
        "tha"
    ],
    "wof:lang_x_spoken":[
        "tha"
    ],
    "wof:name":"Ban Khon In",
    "wof:placetype":"locality"
},
  "geometry": {"coordinates":[102.17816999999999,14.98228],"type":"Point"}
}