{
  "type": "Feature",
  "properties": {
    "gn:admin1_code":"2.0",
    "gn:asciiname":"Ban San Pu Loei",
    "gn:country_code":"TH",
    "gn:dem":423,
    "gn:feature_class":"P",
    "gn:feature_code":"PPL",
    "gn:name":"Ban San Pu Loei",
    "gn:population":0,
    "gn:timezone":"Asia/Bangkok",
    "iso:country":"TH",
    "name:tha_x_preferred":[
        "\u0e1a\u0e49\u0e32\u0e19\u0e2a\u0e31\u0e19\u0e1b\u0e39\u0e40\u0e25\u0e22"
    ],
    "wof:name":"Ban San Pu Loei",
    "wof:placetype":"locality"
},
  "geometry": {"coordinates":[99.17278,19.12053],"type":"Point"}
}