{
  "type": "Feature",
  "properties": {
    "gn:admin1_code":"56.0",
    "gn:asciiname":"Ban Bang Song",
    "gn:country_code":"TH",
    "gn:dem":5,
    "gn:feature_class":"P",
    "gn:feature_code":"PPL",
    "gn:name":"Ban Bang Song",
    "gn:population":0,
    "gn:timezone":"Asia/Bangkok",
    "iso:country":"TH",
    "name:tha_x_preferred":[
        "\u0e1a\u0e49\u0e32\u0e19\u0e1a\u0e32\u0e07\u0e0b\u0e2d\u0e07"
    ],
    "name:und_x_variant":[
        "Ban Bang Chong"
    ],
    "wof:name":"Ban Bang Song",
    "wof:placetype":"locality"
},
  "geometry": {"coordinates":[100.02611,12.92494],"type":"Point"}
}