{
  "type": "Feature",
  "properties": {
    "gn:admin1_code":"22.0",
    "gn:asciiname":"Ban Sai Kai",
    "gn:country_code":"TH",
    "gn:dem":206,
    "gn:feature_class":"P",
    "gn:feature_code":"PPL",
    "gn:name":"Ban Sai Kai",
    "gn:population":0,
    "gn:timezone":"Asia/Bangkok",
    "iso:country":"TH",
    "name:tha_x_preferred":[
        "\u0e1a\u0e49\u0e32\u0e19\u0e44\u0e2a\u0e49\u0e44\u0e01\u0e48"
    ],
    "name:und_x_variant":[
        "Ban Huai Sai Kai"
    ],
    "wof:name":"Ban Sai Kai",
    "wof:placetype":"locality"
},
  "geometry": {"coordinates":[102.58214,16.27425],"type":"Point"}
}