{
  "type": "Feature",
  "properties": {
    "gn:admin1_code":"31.0",
    "gn:asciiname":"Ban Ai Ka Lu Pae",
    "gn:country_code":"TH",
    "gn:dem":45,
    "gn:feature_class":"P",
    "gn:feature_code":"PPL",
    "gn:name":"Ban Ai Ka Lu Pae",
    "gn:population":0,
    "gn:timezone":"Asia/Bangkok",
    "iso:country":"TH",
    "name:tha_x_preferred":[
        "\u0e1a\u0e49\u0e32\u0e19\u0e44\u0e2d\u0e23\u0e4c\u0e01\u0e30\u0e25\u0e39\u0e41\u0e1b"
    ],
    "name:und_x_variant":[
        "Ban I Ka Lu Pae",
        "Ban Ai Ka Lu Pae"
    ],
    "wof:lang_x_official":[
        "tha"
    ],
    "wof:lang_x_spoken":[
        "tha"
    ],
    "wof:name":"Ban Ai Ka Lu Pae",
    "wof:placetype":"locality"
},
  "geometry": {"coordinates":[101.47742,6.28953],"type":"Point"}
}