{
  "type": "Feature",
  "properties": {
    "gn:admin1_code":"24",
    "gn:asciiname":"Ban Don Tum Samakkhi",
    "gn:country_code":"TH",
    "gn:dem":152,
    "gn:feature_class":"P",
    "gn:feature_code":"PPL",
    "gn:name":"Ban Don Tum Samakkhi",
    "gn:population":0,
    "gn:timezone":"Asia/Bangkok",
    "iso:country":"TH",
    "name:tha_x_preferred":[
        "\u0e1a\u0e49\u0e32\u0e19\u0e14\u0e2d\u0e19\u0e15\u0e39\u0e21\u0e2a\u0e32\u0e21\u0e31\u0e04\u0e04\u0e35"
    ],
    "wof:name":"Ban Don Tum Samakkhi",
    "wof:placetype":"locality"
},
  "geometry": {"coordinates":[103.25530999999999,16.18736],"type":"Point"}
}