{
  "type": "Feature",
  "properties": {
    "gn:admin1_code":"18.0",
    "gn:asciiname":"Ban Wang Khaen",
    "gn:country_code":"TH",
    "gn:dem":307,
    "gn:feature_class":"P",
    "gn:feature_code":"PPL",
    "gn:name":"Ban Wang Khaen",
    "gn:population":0,
    "gn:timezone":"Asia/Bangkok",
    "iso:country":"TH",
    "name:tha_x_preferred":[
        "\u0e1a\u0e49\u0e32\u0e19\u0e27\u0e31\u0e07\u0e41\u0e04\u0e19"
    ],
    "name:und_x_variant":[
        "B\u0101n Wang Kean",
        "Ban Wang Khaen"
    ],
    "wof:name":"Ban Wang Khaen",
    "wof:placetype":"locality"
},
  "geometry": {"coordinates":[101.82285,17.57418],"type":"Point"}
}