{
  "type": "Feature",
  "properties": {
    "gn:admin1_code":"55.0",
    "gn:asciiname":"Ban Rim Thang Rot Fai",
    "gn:country_code":"TH",
    "gn:dem":3,
    "gn:feature_class":"P",
    "gn:feature_code":"PPL",
    "gn:name":"Ban Rim Thang Rot Fai",
    "gn:population":0,
    "gn:timezone":"Asia/Bangkok",
    "iso:country":"TH",
    "name:tha_x_preferred":[
        "\u0e1a\u0e49\u0e32\u0e19\u0e23\u0e34\u0e21\u0e17\u0e32\u0e07\u0e23\u0e16\u0e44\u0e1f"
    ],
    "wof:lang_x_official":[
        "tha"
    ],
    "wof:lang_x_spoken":[
        "tha"
    ],
    "wof:name":"Ban Rim Thang Rot Fai",
    "wof:placetype":"locality"
},
  "geometry": {"coordinates":[100.34596999999999,13.61997],"type":"Point"}
}