{
  "type": "Feature",
  "properties": {
    "gn:admin1_code":"66.0",
    "gn:asciiname":"Ban Phru Pom",
    "gn:country_code":"TH",
    "gn:dem":18,
    "gn:feature_class":"P",
    "gn:feature_code":"PPL",
    "gn:name":"Ban Phru Pom",
    "gn:population":0,
    "gn:timezone":"Asia/Bangkok",
    "iso:country":"TH",
    "name:tha_x_preferred":[
        "\u0e1a\u0e49\u0e32\u0e19\u0e1e\u0e23\u0e38\u0e1b\u0e2d\u0e21"
    ],
    "wof:name":"Ban Phru Pom",
    "wof:placetype":"locality"
},
  "geometry": {"coordinates":[100.26364,7.26647],"type":"Point"}
}