{
  "type": "Feature",
  "properties": {
    "gn:admin1_code":"22",
    "gn:asciiname":"Ban Dong Rueang",
    "gn:country_code":"TH",
    "gn:dem":183,
    "gn:feature_class":"P",
    "gn:feature_code":"PPL",
    "gn:name":"Ban Dong Rueang",
    "gn:population":0,
    "gn:timezone":"Asia/Bangkok",
    "iso:country":"TH",
    "name:tha_x_preferred":[
        "\u0e1a\u0e49\u0e32\u0e19\u0e14\u0e07\u0e40\u0e23\u0e37\u0e2d\u0e07"
    ],
    "wof:name":"Ban Dong Rueang",
    "wof:placetype":"locality"
},
  "geometry": {"coordinates":[102.82331000000001,16.82886],"type":"Point"}
}