{
  "type": "Feature",
  "properties": {
    "gn:admin1_code":"31.0",
    "gn:asciiname":"Ban Takhian Ton Diao",
    "gn:country_code":"TH",
    "gn:dem":272,
    "gn:feature_class":"P",
    "gn:feature_code":"PPL",
    "gn:name":"Ban Takhian Ton Diao",
    "gn:population":0,
    "gn:timezone":"Asia/Bangkok",
    "iso:country":"TH",
    "name:tha_x_preferred":[
        "\u0e1a\u0e49\u0e32\u0e19\u0e15\u0e30\u0e40\u0e04\u0e35\u0e22\u0e19\u0e15\u0e49\u0e19\u0e40\u0e14\u0e35\u0e48\u0e22\u0e27"
    ],
    "wof:name":"Ban Takhian Ton Diao",
    "wof:placetype":"locality"
},
  "geometry": {"coordinates":[101.58522000000001,6.18817],"type":"Point"}
}