{
  "type": "Feature",
  "properties": {
    "gn:admin1_code":"77.0",
    "gn:asciiname":"Ban Nikhom Chanuman Plaeng Thi",
    "gn:country_code":"TH",
    "gn:dem":167,
    "gn:feature_class":"P",
    "gn:feature_code":"PPL",
    "gn:name":"Ban Nikhom Chanuman Plaeng Thi",
    "gn:population":0,
    "gn:timezone":"Asia/Bangkok",
    "iso:country":"TH",
    "name:tha_x_preferred":[
        "Ban Nikhom Chanuman Plaeng Thi"
    ],
    "name:tha_x_variant":[
        "\u0e1a\u0e49\u0e32\u0e19\u0e19\u0e34\u0e04\u0e21\u0e0a\u0e32\u0e19\u0e38\u0e21\u0e32\u0e19\u0e41\u0e1b\u0e25\u0e07\u0e17\u0e35\u0e48"
    ],
    "wof:lang_x_official":[
        "tha"
    ],
    "wof:lang_x_spoken":[
        "tha"
    ],
    "wof:name":"Ban Nikhom Chanuman Plaeng Thi",
    "wof:placetype":"locality"
},
  "geometry": {"coordinates":[104.98783,16.22389],"type":"Point"}
}