{
  "type": "Feature",
  "properties": {
    "gn:admin1_code":"27",
    "gn:asciiname":"Ban Talat Yakha",
    "gn:country_code":"TH",
    "gn:dem":154,
    "gn:feature_class":"P",
    "gn:feature_code":"PPL",
    "gn:name":"Ban Talat Yakha",
    "gn:population":0,
    "gn:timezone":"Asia/Bangkok",
    "iso:country":"TH",
    "name:tha_x_preferred":[
        "\u0e1a\u0e49\u0e32\u0e19\u0e15\u0e25\u0e32\u0e14\u0e2b\u0e0d\u0e49\u0e32\u0e04\u0e32"
    ],
    "wof:name":"Ban Talat Yakha",
    "wof:placetype":"locality"
},
  "geometry": {"coordinates":[102.63544,15.47625],"type":"Point"}
}