{
  "type": "Feature",
  "properties": {
    "gn:admin1_code":"51.0",
    "gn:asciiname":"Ban Chara Kao",
    "gn:country_code":"TH",
    "gn:dem":19,
    "gn:feature_class":"P",
    "gn:feature_code":"PPL",
    "gn:name":"Ban Chara Kao",
    "gn:population":0,
    "gn:timezone":"Asia/Bangkok",
    "iso:country":"TH",
    "name:tha_x_preferred":[
        "\u0e1a\u0e49\u0e32\u0e19\u0e08\u0e30\u0e23\u0e49\u0e32\u0e40\u0e01\u0e48\u0e32"
    ],
    "name:und_x_variant":[
        "Ban Cha Ra Kau",
        "Ban Chara Kao"
    ],
    "wof:lang_x_official":[
        "tha"
    ],
    "wof:lang_x_spoken":[
        "tha"
    ],
    "wof:name":"Ban Chara Kao",
    "wof:placetype":"locality"
},
  "geometry": {"coordinates":[99.90042,14.55953],"type":"Point"}
}