{
  "type": "Feature",
  "properties": {
    "gn:admin1_code":"73.0",
    "gn:asciiname":"Ban Wang Sim",
    "gn:country_code":"TH",
    "gn:dem":162,
    "gn:feature_class":"P",
    "gn:feature_code":"PPL",
    "gn:name":"Ban Wang Sim",
    "gn:population":0,
    "gn:timezone":"Asia/Bangkok",
    "iso:country":"TH",
    "name:tha_x_preferred":[
        "Ban Wang Sim"
    ],
    "name:tha_x_variant":[
        "\u0e1a\u0e49\u0e32\u0e19\u0e27\u0e31\u0e07\u0e2a\u0e34\u0e21"
    ],
    "wof:name":"Ban Wang Sim",
    "wof:placetype":"locality"
},
  "geometry": {"coordinates":[104.46875,17.17456],"type":"Point"}
}