{
  "type": "Feature",
  "properties": {
    "gn:admin1_code":"23.0",
    "gn:asciiname":"Ban Muang Kun",
    "gn:country_code":"TH",
    "gn:dem":191,
    "gn:feature_class":"P",
    "gn:feature_code":"PPL",
    "gn:name":"Ban Muang Kun",
    "gn:population":0,
    "gn:timezone":"Asia/Bangkok",
    "iso:country":"TH",
    "name:tha_x_preferred":[
        "\u0e1a\u0e49\u0e32\u0e19\u0e21\u0e48\u0e27\u0e07\u0e01\u0e38\u0e25"
    ],
    "name:und_x_variant":[
        "Wang Khaun",
        "Ban Wang Khon",
        "Ban Wang Ku",
        "Ban Muang Kun"
    ],
    "wof:name":"Ban Muang Kun",
    "wof:placetype":"locality"
},
  "geometry": {"coordinates":[103.982,16.76286],"type":"Point"}
}