{
  "type": "Feature",
  "properties": {
    "gn:admin1_code":"22",
    "gn:asciiname":"Ban Wai Luem",
    "gn:country_code":"TH",
    "gn:dem":203,
    "gn:feature_class":"P",
    "gn:feature_code":"PPL",
    "gn:name":"Ban Wai Luem",
    "gn:population":0,
    "gn:timezone":"Asia/Bangkok",
    "iso:country":"TH",
    "name:tha_x_preferred":[
        "\u0e1a\u0e49\u0e32\u0e19\u0e2b\u0e27\u0e32\u0e22\u0e2b\u0e25\u0e37\u0e21"
    ],
    "wof:name":"Ban Wai Luem",
    "wof:placetype":"locality"
},
  "geometry": {"coordinates":[102.47111,16.18081],"type":"Point"}
}