{
  "type": "Feature",
  "properties": {
    "gn:admin1_code":"34",
    "gn:asciiname":"Ban Fa Long Man",
    "gn:country_code":"TH",
    "gn:dem":10,
    "gn:feature_class":"P",
    "gn:feature_code":"PPL",
    "gn:name":"Ban Fa Long Man",
    "gn:population":0,
    "gn:timezone":"Asia/Bangkok",
    "iso:country":"TH",
    "name:tha_x_preferred":[
        "\u0e1a\u0e49\u0e32\u0e19\u0e1f\u0e49\u0e32\u0e25\u0e07\u0e21\u0e31\u0e19"
    ],
    "wof:name":"Ban Fa Long Man",
    "wof:placetype":"locality"
},
  "geometry": {"coordinates":[100.59744000000001,14.79261],"type":"Point"}
}