{
  "type": "Feature",
  "properties": {
    "gn:admin1_code":"7.0",
    "gn:asciiname":"Ban Ut Thon",
    "gn:country_code":"TH",
    "gn:dem":167,
    "gn:feature_class":"P",
    "gn:feature_code":"PPL",
    "gn:name":"Ban Ut Thon",
    "gn:population":0,
    "gn:timezone":"Asia/Bangkok",
    "iso:country":"TH",
    "name:tha_x_preferred":[
        "\u0e1a\u0e49\u0e32\u0e19\u0e2d\u0e38\u0e17\u0e18\u0e23\u0e13\u0e4c"
    ],
    "wof:name":"Ban Ut Thon",
    "wof:placetype":"locality"
},
  "geometry": {"coordinates":[100.175,18.27761],"type":"Point"}
}