{
  "type": "Feature",
  "properties": {
    "gn:admin1_code":"2.0",
    "gn:asciiname":"Ban Khae Liso",
    "gn:country_code":"TH",
    "gn:dem":950,
    "gn:feature_class":"P",
    "gn:feature_code":"PPL",
    "gn:name":"Ban Khae Liso",
    "gn:population":0,
    "gn:timezone":"Asia/Bangkok",
    "iso:country":"TH",
    "name:tha_x_preferred":[
        "\u0e1a\u0e49\u0e32\u0e19\u0e41\u0e02\u0e25\u0e35\u0e0b\u0e2d"
    ],
    "wof:name":"Ban Khae Liso",
    "wof:placetype":"locality"
},
  "geometry": {"coordinates":[99.06036,19.71378],"type":"Point"}
}