{
  "type": "Feature",
  "properties": {
    "gn:admin1_code":"20.0",
    "gn:asciiname":"Ban Song Pueai",
    "gn:country_code":"TH",
    "gn:dem":177,
    "gn:feature_class":"P",
    "gn:feature_code":"PPL",
    "gn:name":"Ban Song Pueai",
    "gn:population":0,
    "gn:timezone":"Asia/Bangkok",
    "iso:country":"TH",
    "name:tha_x_preferred":[
        "\u0e1a\u0e49\u0e32\u0e19\u0e2a\u0e07\u0e40\u0e1b\u0e37\u0e2d\u0e22"
    ],
    "wof:name":"Ban Song Pueai",
    "wof:placetype":"locality"
},
  "geometry": {"coordinates":[103.90555000000001,17.72057999999999],"type":"Point"}
}