{
  "type": "Feature",
  "properties": {
    "gn:admin1_code":"32.0",
    "gn:asciiname":"Ban Thiang Thae",
    "gn:country_code":"TH",
    "gn:dem":27,
    "gn:feature_class":"P",
    "gn:feature_code":"PPL",
    "gn:name":"Ban Thiang Thae",
    "gn:population":0,
    "gn:timezone":"Asia/Bangkok",
    "iso:country":"TH",
    "name:tha_x_preferred":[
        "\u0e1a\u0e49\u0e32\u0e19\u0e40\u0e17\u0e35\u0e48\u0e22\u0e07\u0e41\u0e17\u0e49"
    ],
    "name:und_x_variant":[
        "B\u0101n Thiang Thea",
        "Ban Thiang Thae"
    ],
    "wof:name":"Ban Thiang Thae",
    "wof:placetype":"locality"
},
  "geometry": {"coordinates":[100.14139,15.09733],"type":"Point"}
}