{
  "type": "Feature",
  "properties": {
    "gn:admin1_code":"75.0",
    "gn:asciiname":"Ban Non Khun Noi",
    "gn:country_code":"TH",
    "gn:dem":150,
    "gn:feature_class":"P",
    "gn:feature_code":"PPL",
    "gn:name":"Ban Non Khun Noi",
    "gn:population":0,
    "gn:timezone":"Asia/Bangkok",
    "iso:country":"TH",
    "name:tha_x_preferred":[
        "\u0e1a\u0e49\u0e32\u0e19\u0e42\u0e19\u0e19\u0e04\u0e39\u0e13\u0e19\u0e49\u0e2d\u0e22"
    ],
    "wof:name":"Ban Non Khun Noi",
    "wof:placetype":"locality"
},
  "geometry": {"coordinates":[105.34717000000001,14.94356],"type":"Point"}
}