{
  "type": "Feature",
  "properties": {
    "gn:admin1_code":"14.0",
    "gn:asciiname":"Ban Noen Hin On",
    "gn:country_code":"TH",
    "gn:dem":77,
    "gn:feature_class":"P",
    "gn:feature_code":"PPL",
    "gn:name":"Ban Noen Hin On",
    "gn:population":0,
    "gn:timezone":"Asia/Bangkok",
    "iso:country":"TH",
    "name:tha_x_preferred":[
        "\u0e1a\u0e49\u0e32\u0e19\u0e40\u0e19\u0e34\u0e19\u0e2b\u0e34\u0e19\u0e2d\u0e48\u0e2d\u0e19"
    ],
    "wof:name":"Ban Noen Hin On",
    "wof:placetype":"locality"
},
  "geometry": {"coordinates":[101.01061,15.38758],"type":"Point"}
}