{
  "type": "Feature",
  "properties": {
    "gn:admin1_code":"38.0",
    "gn:asciiname":"Ban Bang Khu Wiang",
    "gn:cc2":"TH",
    "gn:country_code":"TH",
    "gn:dem":6,
    "gn:feature_class":"P",
    "gn:feature_code":"PPL",
    "gn:name":"Ban Bang Khu Wiang",
    "gn:population":0,
    "gn:timezone":"Asia/Bangkok",
    "iso:country":"TH",
    "name:tha_x_preferred":[
        "\u0e1a\u0e49\u0e32\u0e19\u0e1a\u0e32\u0e07\u0e04\u0e39\u0e40\u0e27\u0e35\u0e22\u0e07"
    ],
    "name:und_x_variant":[
        "Bang Kuwiang",
        "Ban Bang Khu Wiang"
    ],
    "wof:name":"Ban Bang Khu Wiang",
    "wof:placetype":"locality"
},
  "geometry": {"coordinates":[100.40895999999999,13.81537],"type":"Point"}
}