{
  "type": "Feature",
  "properties": {
    "gn:admin1_code":"5.0",
    "gn:asciiname":"Ban Thung Khao Hang",
    "gn:country_code":"TH",
    "gn:dem":663,
    "gn:feature_class":"P",
    "gn:feature_code":"PPL",
    "gn:name":"Ban Thung Khao Hang",
    "gn:population":0,
    "gn:timezone":"Asia/Bangkok",
    "iso:country":"TH",
    "name:tha_x_preferred":[
        "\u0e1a\u0e49\u0e32\u0e19\u0e17\u0e38\u0e48\u0e07\u0e02\u0e49\u0e32\u0e27\u0e2b\u0e32\u0e07"
    ],
    "name:und_x_variant":[
        "Thung Khao Hang",
        "B\u0101n Thung K\u0101o Hang",
        "Dhungkhaoh\u0101ng",
        "Ban Thung Khao Hang"
    ],
    "wof:lang_x_official":[
        "tha"
    ],
    "wof:lang_x_spoken":[
        "tha"
    ],
    "wof:name":"Ban Thung Khao Hang",
    "wof:placetype":"locality"
},
  "geometry": {"coordinates":[99.01419,18.13753],"type":"Point"}
}