{
  "type": "Feature",
  "properties": {
    "gn:admin1_code":"0.0",
    "gn:asciiname":"Ban Hin So",
    "gn:country_code":"TH",
    "gn:dem":960,
    "gn:feature_class":"P",
    "gn:feature_code":"PPL",
    "gn:name":"Ban Hin So",
    "gn:population":0,
    "gn:timezone":"Asia/Bangkok",
    "iso:country":"TH",
    "wof:name":"Ban Hin So",
    "wof:placetype":"locality"
},
  "geometry": {"coordinates":[101.34999999999999,17.25],"type":"Point"}
}