{
  "type": "Feature",
  "properties": {
    "gn:admin1_code":"29",
    "gn:asciiname":"Ban Ta Treao",
    "gn:country_code":"TH",
    "gn:dem":195,
    "gn:feature_class":"P",
    "gn:feature_code":"PPL",
    "gn:name":"Ban Ta Treao",
    "gn:population":0,
    "gn:timezone":"Asia/Bangkok",
    "iso:country":"TH",
    "name:tha_x_preferred":[
        "\u0e1a\u0e49\u0e32\u0e19\u0e15\u0e32\u0e41\u0e15\u0e23\u0e27"
    ],
    "wof:name":"Ban Ta Treao",
    "wof:placetype":"locality"
},
  "geometry": {"coordinates":[103.83889000000001,14.5385],"type":"Point"}
}