{
  "type": "Feature",
  "properties": {
    "gn:admin1_code":"15.0",
    "gn:asciiname":"Ban Hinlon",
    "gn:country_code":"TH",
    "gn:dem":115,
    "gn:feature_class":"P",
    "gn:feature_code":"PPL",
    "gn:name":"Ban Hinlon",
    "gn:population":0,
    "gn:timezone":"Asia/Bangkok",
    "iso:country":"TH",
    "name:tha_x_preferred":[
        "\u0e1a\u0e49\u0e32\u0e19\u0e2b\u0e34\u0e19\u0e42\u0e2b\u0e25\u0e48\u0e19"
    ],
    "wof:name":"Ban Hinlon",
    "wof:placetype":"locality"
},
  "geometry": {"coordinates":[99.60992,15.22947],"type":"Point"}
}