{
  "type": "Feature",
  "properties": {
    "gn:admin1_code":"18.0",
    "gn:asciiname":"Ban Nam Kho Noi",
    "gn:country_code":"TH",
    "gn:dem":279,
    "gn:feature_class":"P",
    "gn:feature_code":"PPL",
    "gn:name":"Ban Nam Kho Noi",
    "gn:population":0,
    "gn:timezone":"Asia/Bangkok",
    "iso:country":"TH",
    "name:tha_x_preferred":[
        "Ban Nam Kho Noi"
    ],
    "name:tha_x_variant":[
        "\u0e1a\u0e49\u0e32\u0e19\u0e19\u0e49\u0e33\u0e04\u0e49\u0e2d\u0e19\u0e49\u0e2d\u0e22"
    ],
    "wof:name":"Ban Nam Kho Noi",
    "wof:placetype":"locality"
},
  "geometry": {"coordinates":[101.64586,17.17495],"type":"Point"}
}