{
  "type": "Feature",
  "properties": {
    "gn:admin1_code":"68.0",
    "gn:asciiname":"Ban Khlong Ammarin",
    "gn:country_code":"TH",
    "gn:dem":71,
    "gn:feature_class":"P",
    "gn:feature_code":"PPL",
    "gn:name":"Ban Khlong Ammarin",
    "gn:population":0,
    "gn:timezone":"Asia/Bangkok",
    "iso:country":"TH",
    "name:tha_x_preferred":[
        "\u0e1a\u0e49\u0e32\u0e19\u0e04\u0e25\u0e2d\u0e07\u0e2d\u0e31\u0e21\u0e23\u0e34\u0e19\u0e17\u0e23\u0e4c"
    ],
    "wof:name":"Ban Khlong Ammarin",
    "wof:placetype":"locality"
},
  "geometry": {"coordinates":[100.9135,6.39],"type":"Point"}
}