{
  "type": "Feature",
  "properties": {
    "gn:admin1_code":"4.0",
    "gn:asciiname":"Ban Nam Muap",
    "gn:country_code":"TH",
    "gn:dem":300,
    "gn:feature_class":"P",
    "gn:feature_code":"PPL",
    "gn:name":"Ban Nam Muap",
    "gn:population":0,
    "gn:timezone":"Asia/Bangkok",
    "iso:country":"TH",
    "name:tha_x_preferred":[
        "\u0e1a\u0e49\u0e32\u0e19\u0e19\u0e49\u0e33\u0e21\u0e27\u0e1a"
    ],
    "wof:name":"Ban Nam Muap",
    "wof:placetype":"locality"
},
  "geometry": {"coordinates":[100.94061000000001,18.48458],"type":"Point"}
}