{
  "type": "Feature",
  "properties": {
    "gn:admin1_code":"27.0",
    "gn:asciiname":"Ban Chan Thuk Mai",
    "gn:country_code":"TH",
    "gn:dem":339,
    "gn:feature_class":"P",
    "gn:feature_code":"PPL",
    "gn:name":"Ban Chan Thuk Mai",
    "gn:population":0,
    "gn:timezone":"Asia/Bangkok",
    "iso:country":"TH",
    "wof:name":"Ban Chan Thuk Mai",
    "wof:placetype":"locality"
},
  "geometry": {"coordinates":[101.53361,14.83361],"type":"Point"}
}