{
  "type": "Feature",
  "properties": {
    "gn:admin1_code":"0.0",
    "gn:asciiname":"Ban Yang Noi",
    "gn:country_code":"TH",
    "gn:dem":1112,
    "gn:feature_class":"P",
    "gn:feature_code":"PPL",
    "gn:name":"Ban Yang Noi",
    "gn:population":0,
    "gn:timezone":"Asia/Bangkok",
    "iso:country":"TH",
    "wof:name":"Ban Yang Noi",
    "wof:placetype":"locality"
},
  "geometry": {"coordinates":[98.54528000000001,18.36],"type":"Point"}
}