{
  "type": "Feature",
  "properties": {
    "gn:admin1_code":"42.0",
    "gn:asciiname":"Ban Khlong Chorakhe Noi",
    "gn:country_code":"TH",
    "gn:dem":3,
    "gn:feature_class":"P",
    "gn:feature_code":"PPL",
    "gn:name":"Ban Khlong Chorakhe Noi",
    "gn:population":0,
    "gn:timezone":"Asia/Bangkok",
    "iso:country":"TH",
    "name:tha_x_preferred":[
        "\u0e1a\u0e49\u0e32\u0e19\u0e04\u0e25\u0e2d\u0e07\u0e08\u0e23\u0e30\u0e40\u0e02\u0e49\u0e19\u0e49\u0e2d\u0e22"
    ],
    "wof:name":"Ban Khlong Chorakhe Noi",
    "wof:placetype":"locality"
},
  "geometry": {"coordinates":[100.95050000000001,13.65836],"type":"Point"}
}