{
  "type": "Feature",
  "properties": {
    "gn:admin1_code":"0.0",
    "gn:asciiname":"Ban Khok Nong Sano",
    "gn:country_code":"TH",
    "gn:dem":201,
    "gn:feature_class":"P",
    "gn:feature_code":"PPL",
    "gn:name":"Ban Khok Nong Sano",
    "gn:population":0,
    "gn:timezone":"Asia/Bangkok",
    "iso:country":"TH",
    "wof:name":"Ban Khok Nong Sano",
    "wof:placetype":"locality"
},
  "geometry": {"coordinates":[102.38333,14.81667],"type":"Point"}
}