{
  "type": "Feature",
  "properties": {
    "gn:admin1_code":"41.0",
    "gn:asciiname":"Ban Mae Na Ruea Pong",
    "gn:country_code":"TH",
    "gn:dem":412,
    "gn:feature_class":"P",
    "gn:feature_code":"PPL",
    "gn:name":"Ban Mae Na Ruea Pong",
    "gn:population":0,
    "gn:timezone":"Asia/Bangkok",
    "iso:country":"TH",
    "name:tha_x_preferred":[
        "\u0e1a\u0e49\u0e32\u0e19\u0e41\u0e21\u0e48\u0e19\u0e32\u0e40\u0e23\u0e37\u0e2d\u0e1b\u0e07"
    ],
    "name:und_x_variant":[
        "M\u0113n\u0101hoe",
        "Ban Mae Na Rua",
        "B\u0101n Mea Na Rua",
        "Ban Na Rua",
        "Ban Mae Na Ruea Pong"
    ],
    "wof:lang_x_official":[
        "tha"
    ],
    "wof:lang_x_spoken":[
        "tha"
    ],
    "wof:name":"Ban Mae Na Ruea Pong",
    "wof:placetype":"locality"
},
  "geometry": {"coordinates":[99.85035999999999,19.11742000000001],"type":"Point"}
}