{
  "type": "Feature",
  "properties": {
    "gn:admin1_code":"16.0",
    "gn:asciiname":"Ban Hua Lon",
    "gn:country_code":"TH",
    "gn:dem":133,
    "gn:feature_class":"P",
    "gn:feature_code":"PPL",
    "gn:name":"Ban Hua Lon",
    "gn:population":0,
    "gn:timezone":"Asia/Bangkok",
    "iso:country":"TH",
    "name:tha_x_preferred":[
        "\u0e1a\u0e49\u0e32\u0e19\u0e2b\u0e31\u0e27\u0e42\u0e25\u0e49\u0e19"
    ],
    "wof:lang_x_official":[
        "tha"
    ],
    "wof:lang_x_spoken":[
        "tha"
    ],
    "wof:name":"Ban Hua Lon",
    "wof:placetype":"locality"
},
  "geometry": {"coordinates":[99.53592,15.78386],"type":"Point"}
}