{
  "type": "Feature",
  "properties": {
    "gn:admin1_code":"75.0",
    "gn:asciiname":"Ban Sanam Ma",
    "gn:country_code":"TH",
    "gn:dem":157,
    "gn:feature_class":"P",
    "gn:feature_code":"PPL",
    "gn:name":"Ban Sanam Ma",
    "gn:population":0,
    "gn:timezone":"Asia/Bangkok",
    "iso:country":"TH",
    "name:tha_x_preferred":[
        "\u0e1a\u0e49\u0e32\u0e19\u0e2a\u0e19\u0e32\u0e21\u0e21\u0e49\u0e32"
    ],
    "wof:name":"Ban Sanam Ma",
    "wof:placetype":"locality"
},
  "geometry": {"coordinates":[104.83261,14.95631],"type":"Point"}
}