{
  "type": "Feature",
  "properties": {
    "gn:admin1_code":"13.0",
    "gn:asciiname":"Ban Yang Taphai",
    "gn:country_code":"TH",
    "gn:dem":51,
    "gn:feature_class":"P",
    "gn:feature_code":"PPL",
    "gn:name":"Ban Yang Taphai",
    "gn:population":0,
    "gn:timezone":"Asia/Bangkok",
    "iso:country":"TH",
    "name:tha_x_preferred":[
        "\u0e1a\u0e49\u0e32\u0e19\u0e22\u0e32\u0e07\u0e15\u0e30\u0e1e\u0e32\u0e22"
    ],
    "wof:name":"Ban Yang Taphai",
    "wof:placetype":"locality"
},
  "geometry": {"coordinates":[100.05989,16.53217],"type":"Point"}
}