{
  "type": "Feature",
  "properties": {
    "gn:admin1_code":"76.0",
    "gn:asciiname":"Ban Seri Phatthana",
    "gn:country_code":"TH",
    "gn:dem":172,
    "gn:feature_class":"P",
    "gn:feature_code":"PPL",
    "gn:name":"Ban Seri Phatthana",
    "gn:population":0,
    "gn:timezone":"Asia/Bangkok",
    "iso:country":"TH",
    "name:tha_x_preferred":[
        "\u0e1a\u0e49\u0e32\u0e19\u0e40\u0e2a\u0e23\u0e35\u0e1e\u0e31\u0e12\u0e19\u0e32"
    ],
    "wof:name":"Ban Seri Phatthana",
    "wof:placetype":"locality"
},
  "geometry": {"coordinates":[103.10814000000001,17.57244],"type":"Point"}
}