{
  "type": "Feature",
  "properties": {
    "gn:admin1_code":"66.0",
    "gn:asciiname":"Ban Tha Nang Phrom",
    "gn:country_code":"TH",
    "gn:dem":21,
    "gn:feature_class":"P",
    "gn:feature_code":"PPL",
    "gn:name":"Ban Tha Nang Phrom",
    "gn:population":0,
    "gn:timezone":"Asia/Bangkok",
    "iso:country":"TH",
    "name:tha_x_preferred":[
        "\u0e1a\u0e49\u0e32\u0e19\u0e17\u0e48\u0e32\u0e19\u0e32\u0e07\u0e1e\u0e23\u0e2b\u0e21"
    ],
    "wof:name":"Ban Tha Nang Phrom",
    "wof:placetype":"locality"
},
  "geometry": {"coordinates":[100.08117,7.46411],"type":"Point"}
}