{
  "type": "Feature",
  "properties": {
    "gn:admin1_code":"50.0",
    "gn:asciiname":"Ban Prong Makrut",
    "gn:country_code":"TH",
    "gn:dem":51,
    "gn:feature_class":"P",
    "gn:feature_code":"PPL",
    "gn:name":"Ban Prong Makrut",
    "gn:population":0,
    "gn:timezone":"Asia/Bangkok",
    "iso:country":"TH",
    "name:tha_x_preferred":[
        "\u0e1a\u0e49\u0e32\u0e19\u0e42\u0e1b\u0e48\u0e07\u0e21\u0e30\u0e01\u0e23\u0e39\u0e14"
    ],
    "wof:name":"Ban Prong Makrut",
    "wof:placetype":"locality"
},
  "geometry": {"coordinates":[99.41358,13.81361],"type":"Point"}
}