{
  "type": "Feature",
  "properties": {
    "gn:admin1_code":"52.0",
    "gn:asciiname":"Ban Wang Plachon",
    "gn:country_code":"TH",
    "gn:dem":101,
    "gn:feature_class":"P",
    "gn:feature_code":"PPL",
    "gn:name":"Ban Wang Plachon",
    "gn:population":0,
    "gn:timezone":"Asia/Bangkok",
    "iso:country":"TH",
    "name:tha_x_preferred":[
        "\u0e1a\u0e49\u0e32\u0e19\u0e27\u0e31\u0e07\u0e1b\u0e25\u0e32\u0e0a\u0e48\u0e2d\u0e19"
    ],
    "wof:name":"Ban Wang Plachon",
    "wof:placetype":"locality"
},
  "geometry": {"coordinates":[99.66547,13.23722],"type":"Point"}
}