{
  "type": "Feature",
  "properties": {
    "gn:admin1_code":"14.0",
    "gn:asciiname":"Ban Nam Ko Yai",
    "gn:country_code":"TH",
    "gn:dem":175,
    "gn:feature_class":"P",
    "gn:feature_code":"PPL",
    "gn:name":"Ban Nam Ko Yai",
    "gn:population":0,
    "gn:timezone":"Asia/Bangkok",
    "iso:country":"TH",
    "name:tha_x_preferred":[
        "\u0e1a\u0e49\u0e32\u0e19\u0e19\u0e49\u0e33\u0e01\u0e49\u0e2d\u0e43\u0e2b\u0e0d\u0e48"
    ],
    "name:und_x_variant":[
        "B\u0101n Nam Go Y\u0101i",
        "Ban Nam Ko Yai"
    ],
    "wof:lang_x_official":[
        "tha"
    ],
    "wof:lang_x_spoken":[
        "tha"
    ],
    "wof:name":"Ban Nam Ko Yai",
    "wof:placetype":"locality"
},
  "geometry": {"coordinates":[101.17303,16.79458],"type":"Point"}
}