{
  "type": "Feature",
  "properties": {
    "gn:admin1_code":"41.0",
    "gn:asciiname":"Ban Mae Chai Hang Ban",
    "gn:country_code":"TH",
    "gn:dem":406,
    "gn:feature_class":"P",
    "gn:feature_code":"PPL",
    "gn:name":"Ban Mae Chai Hang Ban",
    "gn:population":0,
    "gn:timezone":"Asia/Bangkok",
    "iso:country":"TH",
    "name:tha_x_preferred":[
        "\u0e1a\u0e49\u0e32\u0e19\u0e41\u0e21\u0e48\u0e43\u0e08\u0e2b\u0e32\u0e07\u0e1a\u0e49\u0e32\u0e19"
    ],
    "name:und_x_variant":[
        "Ban Mae Chai Tai"
    ],
    "wof:name":"Ban Mae Chai Hang Ban",
    "wof:placetype":"locality"
},
  "geometry": {"coordinates":[99.81083,19.34597],"type":"Point"}
}