{
  "type": "Feature",
  "properties": {
    "gn:admin1_code":"12.0",
    "gn:asciiname":"Ban Phatthana Dong Noi",
    "gn:country_code":"TH",
    "gn:dem":63,
    "gn:feature_class":"P",
    "gn:feature_code":"PPL",
    "gn:name":"Ban Phatthana Dong Noi",
    "gn:population":0,
    "gn:timezone":"Asia/Bangkok",
    "iso:country":"TH",
    "name:tha_x_preferred":[
        "\u0e1a\u0e49\u0e32\u0e19\u0e1e\u0e31\u0e12\u0e19\u0e32\u0e14\u0e07\u0e19\u0e49\u0e2d\u0e22"
    ],
    "wof:name":"Ban Phatthana Dong Noi",
    "wof:placetype":"locality"
},
  "geometry": {"coordinates":[100.61011000000001,16.55936],"type":"Point"}
}