{
  "type": "Feature",
  "properties": {
    "gn:admin1_code":"36.0",
    "gn:asciiname":"Ban Krathum",
    "gn:country_code":"TH",
    "gn:dem":8,
    "gn:feature_class":"P",
    "gn:feature_code":"PPL",
    "gn:name":"Ban Krathum",
    "gn:population":0,
    "gn:timezone":"Asia/Bangkok",
    "iso:country":"TH",
    "name:tha_x_preferred":[
        "\u0e1a\u0e49\u0e32\u0e19\u0e01\u0e23\u0e30\u0e17\u0e38\u0e48\u0e21"
    ],
    "wof:name":"Ban Krathum",
    "wof:placetype":"locality"
},
  "geometry": {"coordinates":[100.40152999999999,14.39797],"type":"Point"}
}