{
  "type": "Feature",
  "properties": {
    "gn:admin1_code":"3.0",
    "gn:asciiname":"Ban Pa Miang Mae Phrik",
    "gn:country_code":"TH",
    "gn:dem":678,
    "gn:feature_class":"P",
    "gn:feature_code":"PPL",
    "gn:name":"Ban Pa Miang Mae Phrik",
    "gn:population":0,
    "gn:timezone":"Asia/Bangkok",
    "iso:country":"TH",
    "wof:name":"Ban Pa Miang Mae Phrik",
    "wof:placetype":"locality"
},
  "geometry": {"coordinates":[99.61476999999999,19.59789],"type":"Point"}
}