{
  "type": "Feature",
  "properties": {
    "gn:admin1_code":"74.0",
    "gn:asciiname":"Ban Tha Tameng",
    "gn:country_code":"TH",
    "gn:dem":16,
    "gn:feature_class":"P",
    "gn:feature_code":"PPL",
    "gn:name":"Ban Tha Tameng",
    "gn:population":0,
    "gn:timezone":"Asia/Bangkok",
    "iso:country":"TH",
    "name:tha_x_preferred":[
        "\u0e1a\u0e49\u0e32\u0e19\u0e17\u0e48\u0e32\u0e15\u0e30\u0e40\u0e21\u0e47\u0e07"
    ],
    "name:und_x_variant":[
        "Ban Tha Ta Meng"
    ],
    "wof:name":"Ban Tha Tameng",
    "wof:placetype":"locality"
},
  "geometry": {"coordinates":[101.61808000000001,14.05428],"type":"Point"}
}