{
  "type": "Feature",
  "properties": {
    "gn:admin1_code":"34.0",
    "gn:asciiname":"Ban Makham",
    "gn:cc2":"TH",
    "gn:country_code":"TH",
    "gn:dem":14,
    "gn:feature_class":"P",
    "gn:feature_code":"PPL",
    "gn:name":"Ban Makham",
    "gn:population":0,
    "gn:timezone":"Asia/Bangkok",
    "iso:country":"TH",
    "name:und_x_variant":[
        "Ban Makham En",
        "Ban Makham"
    ],
    "wof:name":"Ban Makham",
    "wof:placetype":"locality"
},
  "geometry": {"coordinates":[100.58333,15.05],"type":"Point"}
}