{
  "type": "Feature",
  "properties": {
    "gn:admin1_code":"22.0",
    "gn:asciiname":"Ban Kut Phang Thui",
    "gn:country_code":"TH",
    "gn:dem":177,
    "gn:feature_class":"P",
    "gn:feature_code":"PPL",
    "gn:name":"Ban Kut Phang Thui",
    "gn:population":0,
    "gn:timezone":"Asia/Bangkok",
    "iso:country":"TH",
    "name:tha_x_preferred":[
        "\u0e1a\u0e49\u0e32\u0e19\u0e01\u0e38\u0e14\u0e1e\u0e31\u0e07\u0e17\u0e38\u0e22"
    ],
    "name:und_x_variant":[
        "Ban Fang",
        "Ban Kut Phang Thui",
        "Ban Si Than"
    ],
    "wof:lang_x_official":[
        "tha"
    ],
    "wof:lang_x_spoken":[
        "tha"
    ],
    "wof:name":"Ban Kut Phang Thui",
    "wof:placetype":"locality"
},
  "geometry": {"coordinates":[102.92308,16.75492],"type":"Point"}
}