{
  "type": "Feature",
  "properties": {
    "gn:admin1_code":"14.0",
    "gn:asciiname":"Ban Ko Mo Sam Sip",
    "gn:country_code":"TH",
    "gn:dem":99,
    "gn:feature_class":"P",
    "gn:feature_code":"PPL",
    "gn:name":"Ban Ko Mo Sam Sip",
    "gn:population":0,
    "gn:timezone":"Asia/Bangkok",
    "iso:country":"TH",
    "name:tha_x_preferred":[
        "\u0e1a\u0e49\u0e32\u0e19\u0e01\u0e21.\u0e2a\u0e32\u0e21\u0e2a\u0e34\u0e1a"
    ],
    "wof:name":"Ban Ko Mo Sam Sip",
    "wof:placetype":"locality"
},
  "geometry": {"coordinates":[101.07693999999999,16.05108],"type":"Point"}
}