{
  "type": "Feature",
  "properties": {
    "gn:admin1_code":"65.0",
    "gn:asciiname":"Ban Nong Phap Nam",
    "gn:country_code":"TH",
    "gn:dem":44,
    "gn:feature_class":"P",
    "gn:feature_code":"PPL",
    "gn:name":"Ban Nong Phap Nam",
    "gn:population":0,
    "gn:timezone":"Asia/Bangkok",
    "iso:country":"TH",
    "name:tha_x_preferred":[
        "\u0e1a\u0e49\u0e32\u0e19\u0e2b\u0e19\u0e2d\u0e07\u0e1e\u0e32\u0e1a\u0e19\u0e49\u0e33"
    ],
    "wof:name":"Ban Nong Phap Nam",
    "wof:placetype":"locality"
},
  "geometry": {"coordinates":[99.73142,7.49739],"type":"Point"}
}