{
  "type": "Feature",
  "properties": {
    "gn:admin1_code":"53.0",
    "gn:asciiname":"Muban Mit Thae Thani",
    "gn:country_code":"TH",
    "gn:dem":4,
    "gn:feature_class":"P",
    "gn:feature_code":"PPL",
    "gn:name":"Muban Mit Thae Thani",
    "gn:population":0,
    "gn:timezone":"Asia/Bangkok",
    "iso:country":"TH",
    "name:tha_x_preferred":[
        "\u0e2b\u0e21\u0e39\u0e48\u0e1a\u0e49\u0e32\u0e19\u0e21\u0e34\u0e15\u0e23\u0e41\u0e17\u0e49\u0e18\u0e32\u0e19\u0e35"
    ],
    "wof:name":"Muban Mit Thae Thani",
    "wof:placetype":"locality"
},
  "geometry": {"coordinates":[100.28147,13.82642],"type":"Point"}
}