{
  "type": "Feature",
  "properties": {
    "gn:admin1_code":"3.0",
    "gn:asciiname":"Ban A Choe",
    "gn:country_code":"TH",
    "gn:dem":526,
    "gn:feature_class":"P",
    "gn:feature_code":"PPL",
    "gn:name":"Ban A Choe",
    "gn:population":0,
    "gn:timezone":"Asia/Bangkok",
    "iso:country":"TH",
    "name:tha_x_preferred":[
        "\u0e1a\u0e49\u0e32\u0e19\u0e2d\u0e32\u0e40\u0e08\u0e2d\u0e30"
    ],
    "wof:name":"Ban A Choe",
    "wof:placetype":"locality"
},
  "geometry": {"coordinates":[99.73994999999999,20.00947],"type":"Point"}
}