{
  "type": "Feature",
  "properties": {
    "gn:admin1_code":"34.0",
    "gn:asciiname":"Ban Din Daeng",
    "gn:country_code":"TH",
    "gn:dem":75,
    "gn:feature_class":"P",
    "gn:feature_code":"PPL",
    "gn:name":"Ban Din Daeng",
    "gn:population":0,
    "gn:timezone":"Asia/Bangkok",
    "iso:country":"TH",
    "name:tha_x_preferred":[
        "\u0e1a\u0e49\u0e32\u0e19\u0e14\u0e34\u0e19\u0e41\u0e14\u0e07"
    ],
    "name:und_x_variant":[
        "Ban Rai Din Daeng"
    ],
    "wof:name":"Ban Din Daeng",
    "wof:placetype":"locality"
},
  "geometry": {"coordinates":[100.77597,15.38406],"type":"Point"}
}