{
  "type": "Feature",
  "properties": {
    "gn:admin1_code":"53.0",
    "gn:asciiname":"Ban Sa Phang Phae Loi",
    "gn:country_code":"TH",
    "gn:dem":5,
    "gn:feature_class":"P",
    "gn:feature_code":"PPL",
    "gn:name":"Ban Sa Phang Phae Loi",
    "gn:population":0,
    "gn:timezone":"Asia/Bangkok",
    "iso:country":"TH",
    "name:tha_x_preferred":[
        "Ban Sa Phang Phae Loi"
    ],
    "name:tha_x_variant":[
        "\u0e1a\u0e49\u0e32\u0e19\u0e2a\u0e23\u0e30\u0e1e\u0e31\u0e07\u0e41\u0e1e\u0e25\u0e2d\u0e22"
    ],
    "wof:name":"Ban Sa Phang Phae Loi",
    "wof:placetype":"locality"
},
  "geometry": {"coordinates":[100.26833000000001,14.13294],"type":"Point"}
}