{
  "type": "Feature",
  "properties": {
    "gn:admin1_code":"49.0",
    "gn:asciiname":"Ban Ao Kathueng",
    "gn:country_code":"TH",
    "gn:dem":2,
    "gn:feature_class":"P",
    "gn:feature_code":"PPL",
    "gn:name":"Ban Ao Kathueng",
    "gn:population":0,
    "gn:timezone":"Asia/Bangkok",
    "iso:country":"TH",
    "name:tha_x_preferred":[
        "\u0e1a\u0e49\u0e32\u0e19\u0e2d\u0e48\u0e32\u0e27\u0e01\u0e30\u0e17\u0e36\u0e07"
    ],
    "wof:name":"Ban Ao Kathueng",
    "wof:placetype":"locality"
},
  "geometry": {"coordinates":[102.59392,11.56928],"type":"Point"}
}