{
  "type": "Feature",
  "properties": {
    "gn:admin1_code":"20.0",
    "gn:asciiname":"Ban Dong Chiang Khruea",
    "gn:country_code":"TH",
    "gn:dem":190,
    "gn:feature_class":"P",
    "gn:feature_code":"PPL",
    "gn:name":"Ban Dong Chiang Khruea",
    "gn:population":0,
    "gn:timezone":"Asia/Bangkok",
    "iso:country":"TH",
    "name:tha_x_preferred":[
        "\u0e1a\u0e49\u0e32\u0e19\u0e14\u0e07\u0e40\u0e0a\u0e35\u0e22\u0e07\u0e40\u0e04\u0e23\u0e37\u0e2d"
    ],
    "wof:name":"Ban Dong Chiang Khruea",
    "wof:placetype":"locality"
},
  "geometry": {"coordinates":[103.66262,17.29865],"type":"Point"}
}