{
  "type": "Feature",
  "properties": {
    "gn:country":"TH",
    "gn:fcode":"PPL",
    "gn:pop":26113,
    "iso:country":"TH",
    "name:tha_x_preferred":[
        "\u0e1a\u0e49\u0e32\u0e19\u0e15\u0e25\u0e32\u0e14\u0e1a\u0e36\u0e07"
    ],
    "name:unk_x_variant":[
        "Boeng"
    ],
    "qs:name":"Ban Talat Bueng",
    "qs:photos_9r":0,
    "qs:photos_sr":0,
    "qs:pop_sr":"7",
    "wof:name":"Ban Talat Bueng",
    "wof:placetype":"locality",
    "wof:population":26113
},
  "geometry": {"coordinates":[101.00314,13.07147],"type":"Point"}
}