{
  "type": "Feature",
  "properties": {
    "gn:admin1_code":"30.0",
    "gn:asciiname":"Ban Noen Lue Chai",
    "gn:country_code":"TH",
    "gn:dem":140,
    "gn:feature_class":"P",
    "gn:feature_code":"PPL",
    "gn:name":"Ban Noen Lue Chai",
    "gn:population":0,
    "gn:timezone":"Asia/Bangkok",
    "iso:country":"TH",
    "name:tha_x_preferred":[
        "\u0e1a\u0e49\u0e32\u0e19\u0e40\u0e19\u0e34\u0e19\u0e25\u0e37\u0e2d\u0e0a\u0e31\u0e22"
    ],
    "wof:name":"Ban Noen Lue Chai",
    "wof:placetype":"locality"
},
  "geometry": {"coordinates":[104.60181,14.86069],"type":"Point"}
}