{
  "type": "Feature",
  "properties": {
    "gn:admin1_code":"53.0",
    "gn:asciiname":"Ban Khok",
    "gn:country_code":"TH",
    "gn:dem":7,
    "gn:feature_class":"P",
    "gn:feature_code":"PPL",
    "gn:name":"Ban Khok",
    "gn:population":0,
    "gn:timezone":"Asia/Bangkok",
    "iso:country":"TH",
    "name:tha_x_preferred":[
        "Ban Khok"
    ],
    "name:tha_x_variant":[
        "\u0e1a\u0e49\u0e32\u0e19\u0e42\u0e04\u0e01"
    ],
    "name:und_x_variant":[
        "Ban Khok (2)"
    ],
    "wof:name":"Ban Khok",
    "wof:placetype":"locality"
},
  "geometry": {"coordinates":[100.00497,14.06731],"type":"Point"}
}