{
  "type": "Feature",
  "properties": {
    "gn:admin1_code":"40.0",
    "gn:admin2_code":"1021",
    "gn:asciiname":"Ban Hua Krabue",
    "gn:country_code":"TH",
    "gn:dem":5,
    "gn:feature_class":"P",
    "gn:feature_code":"PPL",
    "gn:name":"Ban Hua Krabue",
    "gn:population":0,
    "gn:timezone":"Asia/Bangkok",
    "iso:country":"TH",
    "name:tha_x_preferred":[
        "\u0e1a\u0e49\u0e32\u0e19\u0e2b\u0e31\u0e27\u0e01\u0e23\u0e30\u0e1a\u0e37\u0e2d"
    ],
    "name:und_x_variant":[
        "Hua Kraboe",
        "Ban Hua Krabue",
        "Ban Hua Krabu"
    ],
    "wof:name":"Ban Hua Krabue",
    "wof:placetype":"locality"
},
  "geometry": {"coordinates":[100.44856,13.61939],"type":"Point"}
}