{
  "type": "Feature",
  "properties": {
    "gn:admin1_code":"68.0",
    "gn:asciiname":"Ban Chai Map",
    "gn:country_code":"TH",
    "gn:dem":7,
    "gn:feature_class":"P",
    "gn:feature_code":"PPL",
    "gn:name":"Ban Chai Map",
    "gn:population":0,
    "gn:timezone":"Asia/Bangkok",
    "iso:country":"TH",
    "name:tha_x_preferred":[
        "\u0e1a\u0e49\u0e32\u0e19\u0e0a\u0e32\u0e22\u0e21\u0e32\u0e1a"
    ],
    "wof:name":"Ban Chai Map",
    "wof:placetype":"locality"
},
  "geometry": {"coordinates":[100.438,7.12758],"type":"Point"}
}