{
  "type": "Feature",
  "properties": {
    "gn:admin1_code":"26.0",
    "gn:asciiname":"Ban Sap Pa Fa",
    "gn:country_code":"TH",
    "gn:dem":240,
    "gn:feature_class":"P",
    "gn:feature_code":"PPL",
    "gn:name":"Ban Sap Pa Fa",
    "gn:population":0,
    "gn:timezone":"Asia/Bangkok",
    "iso:country":"TH",
    "name:tha_x_preferred":[
        "\u0e1a\u0e49\u0e32\u0e19\u0e0b\u0e31\u0e1a\u0e1b\u0e32\u0e1d\u0e32"
    ],
    "wof:name":"Ban Sap Pa Fa",
    "wof:placetype":"locality"
},
  "geometry": {"coordinates":[101.66108,15.71494],"type":"Point"}
}