{
  "type": "Feature",
  "properties": {
    "gn:admin1_code":"60.0",
    "gn:asciiname":"Ban Khuan Wat",
    "gn:country_code":"TH",
    "gn:dem":16,
    "gn:feature_class":"P",
    "gn:feature_code":"PPL",
    "gn:name":"Ban Khuan Wat",
    "gn:population":0,
    "gn:timezone":"Asia/Bangkok",
    "iso:country":"TH",
    "name:tha_x_preferred":[
        "\u0e1a\u0e49\u0e32\u0e19\u0e04\u0e27\u0e19\u0e27\u0e31\u0e14"
    ],
    "wof:name":"Ban Khuan Wat",
    "wof:placetype":"locality"
},
  "geometry": {"coordinates":[99.31272,8.71358],"type":"Point"}
}