{
  "type": "Feature",
  "properties": {
    "gn:admin1_code":"0.0",
    "gn:asciiname":"Ban Om Sing Nua",
    "gn:country_code":"TH",
    "gn:dem":338,
    "gn:feature_class":"P",
    "gn:feature_code":"PPL",
    "gn:name":"Ban Om Sing Nua",
    "gn:population":0,
    "gn:timezone":"Asia/Bangkok",
    "iso:country":"TH",
    "wof:name":"Ban Om Sing Nua",
    "wof:placetype":"locality"
},
  "geometry": {"coordinates":[100.96666999999999,17.08333],"type":"Point"}
}