{
  "type": "Feature",
  "properties": {
    "gn:admin1_code":"72.0",
    "gn:asciiname":"Ban Dong Yang",
    "gn:country_code":"TH",
    "gn:dem":131,
    "gn:feature_class":"P",
    "gn:feature_code":"PPL",
    "gn:name":"Ban Dong Yang",
    "gn:population":0,
    "gn:timezone":"Asia/Bangkok",
    "iso:country":"TH",
    "name:tha_x_preferred":[
        "\u0e1a\u0e49\u0e32\u0e19\u0e14\u0e07\u0e22\u0e32\u0e07"
    ],
    "wof:name":"Ban Dong Yang",
    "wof:placetype":"locality"
},
  "geometry": {"coordinates":[104.29394000000001,15.57997],"type":"Point"}
}