{
  "type": "Feature",
  "properties": {
    "gn:admin1_code":"68.0",
    "gn:asciiname":"Ban Samnak Yo",
    "gn:country_code":"TH",
    "gn:dem":95,
    "gn:feature_class":"P",
    "gn:feature_code":"PPL",
    "gn:name":"Ban Samnak Yo",
    "gn:population":0,
    "gn:timezone":"Asia/Bangkok",
    "iso:country":"TH",
    "name:tha_x_preferred":[
        "\u0e1a\u0e49\u0e32\u0e19\u0e2a\u0e33\u0e19\u0e31\u0e01\u0e22\u0e2d"
    ],
    "wof:name":"Ban Samnak Yo",
    "wof:placetype":"locality"
},
  "geometry": {"coordinates":[100.59032999999999,6.83133],"type":"Point"}
}