{
  "type": "Feature",
  "properties": {
    "gn:admin1_code":"36",
    "gn:asciiname":"Ban Khlong Sa Bua",
    "gn:country_code":"TH",
    "gn:dem":7,
    "gn:feature_class":"P",
    "gn:feature_code":"PPL",
    "gn:name":"Ban Khlong Sa Bua",
    "gn:population":0,
    "gn:timezone":"Asia/Bangkok",
    "iso:country":"TH",
    "name:tha_x_preferred":[
        "\u0e1a\u0e49\u0e32\u0e19\u0e04\u0e25\u0e2d\u0e07\u0e2a\u0e23\u0e30\u0e1a\u0e31\u0e27"
    ],
    "wof:name":"Ban Khlong Sa Bua",
    "wof:placetype":"locality"
},
  "geometry": {"coordinates":[100.54794,14.38531],"type":"Point"}
}