{
  "type": "Feature",
  "properties": {
    "gn:admin1_code":"3.0",
    "gn:asciiname":"Ban Ton Yang",
    "gn:country_code":"TH",
    "gn:dem":415,
    "gn:feature_class":"P",
    "gn:feature_code":"PPL",
    "gn:name":"Ban Ton Yang",
    "gn:population":0,
    "gn:timezone":"Asia/Bangkok",
    "iso:country":"TH",
    "name:tha_x_preferred":[
        "\u0e1a\u0e49\u0e32\u0e19\u0e15\u0e49\u0e19\u0e22\u0e32\u0e07"
    ],
    "wof:name":"Ban Ton Yang",
    "wof:placetype":"locality"
},
  "geometry": {"coordinates":[99.75378000000001,19.79708],"type":"Point"}
}