{
  "type": "Feature",
  "properties": {
    "gn:admin1_code":"26.0",
    "gn:asciiname":"Ban Wang Ai Khong",
    "gn:country_code":"TH",
    "gn:dem":282,
    "gn:feature_class":"P",
    "gn:feature_code":"PPL",
    "gn:name":"Ban Wang Ai Khong",
    "gn:population":0,
    "gn:timezone":"Asia/Bangkok",
    "iso:country":"TH",
    "name:tha_x_preferred":[
        "\u0e1a\u0e49\u0e32\u0e19\u0e27\u0e31\u0e07\u0e2d\u0e49\u0e32\u0e22\u0e04\u0e07"
    ],
    "name:und_x_variant":[
        "Ban Ai Khong",
        "Ban Wang Ai Khong"
    ],
    "wof:name":"Ban Wang Ai Khong",
    "wof:placetype":"locality"
},
  "geometry": {"coordinates":[101.48739,15.54086],"type":"Point"}
}