{
  "type": "Feature",
  "properties": {
    "gn:admin1_code":"6.0",
    "gn:asciiname":"Ban Sathani",
    "gn:country_code":"TH",
    "gn:dem":278,
    "gn:feature_class":"P",
    "gn:feature_code":"PPL",
    "gn:name":"Ban Sathani",
    "gn:population":0,
    "gn:timezone":"Asia/Bangkok",
    "iso:country":"TH",
    "name:tha_x_preferred":[
        "\u0e1a\u0e49\u0e32\u0e19\u0e2a\u0e16\u0e32\u0e19\u0e35"
    ],
    "wof:name":"Ban Sathani",
    "wof:placetype":"locality"
},
  "geometry": {"coordinates":[99.37006,18.33331],"type":"Point"}
}