{
  "type": "Feature",
  "properties": {
    "gn:country":"TH",
    "gn:fcode":"PPL",
    "gn:pop":0,
    "iso:country":"TH",
    "name:eng_x_preferred":[
        "Saen Suk"
    ],
    "name:ger_x_preferred":[
        "Saen Suk"
    ],
    "name:tha_x_preferred":[
        "\u0e41\u0e2a\u0e19\u0e2a\u0e38\u0e02"
    ],
    "name:unk_x_variant":[
        "Ban Saen Suk"
    ],
    "qs:name":"Saen Suk",
    "qs:name_adm0":"Thailand",
    "qs:name_adm1":"Chon Buri",
    "qs:photos":1287,
    "qs:photos_1k":261,
    "qs:photos_9k":6,
    "qs:photos_9r":7,
    "qs:photos_all":1287,
    "qs:photos_sr":12,
    "qs:placetype":"Town",
    "qs:pop_sr":"0",
    "wd:wordcount":532,
    "wof:name":"Saen Suk",
    "wof:placetype":"locality",
    "wof:population":0
},
  "geometry": {"coordinates":[100.93333,13.28333],"type":"Point"}
}