{
  "type": "Feature",
  "properties": {
    "gn:admin1_code":"60.0",
    "gn:asciiname":"Ban Don Niang",
    "gn:country_code":"TH",
    "gn:dem":10,
    "gn:feature_class":"P",
    "gn:feature_code":"PPL",
    "gn:name":"Ban Don Niang",
    "gn:population":0,
    "gn:timezone":"Asia/Bangkok",
    "iso:country":"TH",
    "name:tha_x_preferred":[
        "\u0e1a\u0e49\u0e32\u0e19\u0e14\u0e2d\u0e19\u0e40\u0e19\u0e35\u0e22\u0e07"
    ],
    "wof:name":"Ban Don Niang",
    "wof:placetype":"locality"
},
  "geometry": {"coordinates":[99.19839,9.11253],"type":"Point"}
}