{
  "type": "Feature",
  "properties": {
    "gn:admin1_code":"28.0",
    "gn:asciiname":"Ban Phakkat Ya",
    "gn:country_code":"TH",
    "gn:dem":167,
    "gn:feature_class":"P",
    "gn:feature_code":"PPL",
    "gn:name":"Ban Phakkat Ya",
    "gn:population":0,
    "gn:timezone":"Asia/Bangkok",
    "iso:country":"TH",
    "name:tha_x_preferred":[
        "\u0e1a\u0e49\u0e32\u0e19\u0e1c\u0e31\u0e01\u0e01\u0e32\u0e14\u0e2b\u0e0d\u0e49\u0e32"
    ],
    "name:und_x_variant":[
        "Ban Phak Ya",
        "Ban Phak Kat Ya",
        "Ban Phakkat Ya",
        "Ban Phak Kat Ya (One)"
    ],
    "wof:name":"Ban Phakkat Ya",
    "wof:placetype":"locality"
},
  "geometry": {"coordinates":[102.82186,15.01464],"type":"Point"}
}