{
  "type": "Feature",
  "properties": {
    "gn:admin1_code":"27.0",
    "gn:asciiname":"Ban Prasuk",
    "gn:country_code":"TH",
    "gn:dem":154,
    "gn:feature_class":"P",
    "gn:feature_code":"PPL",
    "gn:name":"Ban Prasuk",
    "gn:population":0,
    "gn:timezone":"Asia/Bangkok",
    "iso:country":"TH",
    "name:tha_x_preferred":[
        "\u0e1a\u0e49\u0e32\u0e19\u0e1b\u0e23\u0e30\u0e2a\u0e38\u0e02"
    ],
    "name:und_x_variant":[
        "Prasuk",
        "Ban Pra Suk",
        "Ban Prasuk"
    ],
    "wof:name":"Ban Prasuk",
    "wof:placetype":"locality"
},
  "geometry": {"coordinates":[102.63639000000001,15.30914],"type":"Point"}
}