{
  "type": "Feature",
  "properties": {
    "gn:admin1_code":"5.0",
    "gn:asciiname":"Ban San Tap Tao",
    "gn:country_code":"TH",
    "gn:dem":316,
    "gn:feature_class":"P",
    "gn:feature_code":"PPL",
    "gn:name":"Ban San Tap Tao",
    "gn:population":0,
    "gn:timezone":"Asia/Bangkok",
    "iso:country":"TH",
    "name:tha_x_preferred":[
        "\u0e1a\u0e49\u0e32\u0e19\u0e2a\u0e31\u0e19\u0e15\u0e31\u0e1a\u0e40\u0e15\u0e48\u0e32"
    ],
    "name:und_x_variant":[
        "Ban Son Tap Tao"
    ],
    "wof:name":"Ban San Tap Tao",
    "wof:placetype":"locality"
},
  "geometry": {"coordinates":[98.81544,18.33717],"type":"Point"}
}