{
  "type": "Feature",
  "properties": {
    "gn:admin1_code":"2.0",
    "gn:asciiname":"Ban Nong I Pum",
    "gn:cc2":"TH",
    "gn:country_code":"TH",
    "gn:dem":249,
    "gn:feature_class":"P",
    "gn:feature_code":"PPL",
    "gn:name":"Ban Nong I Pum",
    "gn:population":0,
    "gn:timezone":"Asia/Bangkok",
    "iso:country":"TH",
    "name:und_x_variant":[
        "Naung-i-Pum",
        "B\u0101n Naung-i-Pum",
        "Hn\u014dhngipum",
        "Ban Nong I Pum"
    ],
    "wof:name":"Ban Nong I Pum",
    "wof:placetype":"locality"
},
  "geometry": {"coordinates":[98.5925,18.05861],"type":"Point"}
}