{
  "type": "Feature",
  "properties": {
    "gn:admin1_code":"38.0",
    "gn:asciiname":"Ban Nong Phrao Ngai",
    "gn:country_code":"TH",
    "gn:dem":3,
    "gn:feature_class":"P",
    "gn:feature_code":"PPL",
    "gn:name":"Ban Nong Phrao Ngai",
    "gn:population":0,
    "gn:timezone":"Asia/Bangkok",
    "iso:country":"TH",
    "name:tha_x_preferred":[
        "\u0e1a\u0e49\u0e32\u0e19\u0e2b\u0e19\u0e2d\u0e07\u0e40\u0e1e\u0e23\u0e32\u0e07\u0e32\u0e22"
    ],
    "wof:name":"Ban Nong Phrao Ngai",
    "wof:placetype":"locality"
},
  "geometry": {"coordinates":[100.33547,13.88761],"type":"Point"}
}