{
  "type": "Feature",
  "properties": {
    "gn:admin1_code":"15.0",
    "gn:asciiname":"Ban Khao Hin Thoen",
    "gn:country_code":"TH",
    "gn:dem":60,
    "gn:feature_class":"P",
    "gn:feature_code":"PPL",
    "gn:name":"Ban Khao Hin Thoen",
    "gn:population":0,
    "gn:timezone":"Asia/Bangkok",
    "iso:country":"TH",
    "name:tha_x_preferred":[
        "\u0e1a\u0e49\u0e32\u0e19\u0e40\u0e02\u0e32\u0e2b\u0e34\u0e19\u0e40\u0e17\u0e34\u0e19"
    ],
    "wof:name":"Ban Khao Hin Thoen",
    "wof:placetype":"locality"
},
  "geometry": {"coordinates":[99.75257999999999,15.54636],"type":"Point"}
}