{
  "type": "Feature",
  "properties": {
    "gn:admin1_code":"14.0",
    "gn:asciiname":"Ban Sap Ta Khian",
    "gn:country_code":"TH",
    "gn:dem":254,
    "gn:feature_class":"P",
    "gn:feature_code":"PPL",
    "gn:name":"Ban Sap Ta Khian",
    "gn:population":0,
    "gn:timezone":"Asia/Bangkok",
    "iso:country":"TH",
    "name:tha_x_preferred":[
        "\u0e1a\u0e49\u0e32\u0e19\u0e0b\u0e31\u0e1a\u0e15\u0e30\u0e40\u0e04\u0e35\u0e22\u0e19"
    ],
    "wof:name":"Ban Sap Ta Khian",
    "wof:placetype":"locality"
},
  "geometry": {"coordinates":[101.34764,15.94892],"type":"Point"}
}