{
  "type": "Feature",
  "properties": {
    "gn:admin1_code":"28",
    "gn:asciiname":"Ban Banlang",
    "gn:country_code":"TH",
    "gn:dem":150,
    "gn:feature_class":"P",
    "gn:feature_code":"PPL",
    "gn:name":"Ban Banlang",
    "gn:population":0,
    "gn:timezone":"Asia/Bangkok",
    "iso:country":"TH",
    "name:tha_x_preferred":[
        "\u0e1a\u0e49\u0e32\u0e19\u0e1a\u0e31\u0e25\u0e25\u0e31\u0e07"
    ],
    "wof:name":"Ban Banlang",
    "wof:placetype":"locality"
},
  "geometry": {"coordinates":[103.30533,15.01425],"type":"Point"}
}