{
  "type": "Feature",
  "properties": {
    "gn:admin1_code":"25",
    "gn:asciiname":"Ban Na Kham Kha",
    "gn:country_code":"TH",
    "gn:dem":203,
    "gn:feature_class":"P",
    "gn:feature_code":"PPL",
    "gn:name":"Ban Na Kham Kha",
    "gn:population":0,
    "gn:timezone":"Asia/Bangkok",
    "iso:country":"TH",
    "name:tha_x_preferred":[
        "\u0e1a\u0e49\u0e32\u0e19\u0e19\u0e32\u0e04\u0e33\u0e02\u0e48\u0e32"
    ],
    "wof:name":"Ban Na Kham Kha",
    "wof:placetype":"locality"
},
  "geometry": {"coordinates":[104.27539,16.38128],"type":"Point"}
}