{
  "type": "Feature",
  "properties": {
    "gn:admin1_code":"28.0",
    "gn:asciiname":"Ban Nong Sai",
    "gn:country_code":"TH",
    "gn:dem":192,
    "gn:feature_class":"P",
    "gn:feature_code":"PPL",
    "gn:name":"Ban Nong Sai",
    "gn:population":0,
    "gn:timezone":"Asia/Bangkok",
    "iso:country":"TH",
    "name:tha_x_preferred":[
        "\u0e1a\u0e49\u0e32\u0e19\u0e2b\u0e19\u0e2d\u0e07\u0e44\u0e17\u0e23"
    ],
    "name:und_x_variant":[
        "Ban Nong Sai (1)"
    ],
    "wof:name":"Ban Nong Sai",
    "wof:placetype":"locality"
},
  "geometry": {"coordinates":[102.76836,14.519],"type":"Point"}
}