{
  "type": "Feature",
  "properties": {
    "gn:admin1_code":"3.0",
    "gn:asciiname":"Ban Nong Raet",
    "gn:country_code":"TH",
    "gn:dem":372,
    "gn:feature_class":"P",
    "gn:feature_code":"PPL",
    "gn:name":"Ban Nong Raet",
    "gn:population":0,
    "gn:timezone":"Asia/Bangkok",
    "iso:country":"TH",
    "name:tha_x_preferred":[
        "\u0e1a\u0e49\u0e32\u0e19\u0e2b\u0e19\u0e2d\u0e07\u0e41\u0e23\u0e14"
    ],
    "name:und_x_variant":[
        "Ban Mae Loi",
        "B\u0101n Mea Loi",
        "Ban Nong Raet",
        "Ban Mae Loi Nong Haet"
    ],
    "wof:name":"Ban Nong Raet",
    "wof:placetype":"locality"
},
  "geometry": {"coordinates":[100.11658,19.62256],"type":"Point"}
}