{
  "type": "Feature",
  "properties": {
    "gn:admin1_code":"10.0",
    "gn:asciiname":"Ban Hua Bueng",
    "gn:country_code":"TH",
    "gn:dem":57,
    "gn:feature_class":"P",
    "gn:feature_code":"PPL",
    "gn:name":"Ban Hua Bueng",
    "gn:population":0,
    "gn:timezone":"Asia/Bangkok",
    "iso:country":"TH",
    "name:tha_x_preferred":[
        "Ban Hua Bueng"
    ],
    "name:tha_x_variant":[
        "\u0e1a\u0e49\u0e32\u0e19\u0e2b\u0e31\u0e27\u0e1a\u0e36\u0e07"
    ],
    "name:und_x_variant":[
        "Ban Bung"
    ],
    "wof:name":"Ban Hua Bueng",
    "wof:placetype":"locality"
},
  "geometry": {"coordinates":[100.04208,17.21647],"type":"Point"}
}