{
  "type": "Feature",
  "properties": {
    "gn:admin1_code":"75.0",
    "gn:asciiname":"Ban Kum",
    "gn:country_code":"TH",
    "gn:dem":114,
    "gn:feature_class":"P",
    "gn:feature_code":"PPL",
    "gn:name":"Ban Kum",
    "gn:population":0,
    "gn:timezone":"Asia/Bangkok",
    "iso:country":"TH",
    "name:tha_x_preferred":[
        "\u0e1a\u0e49\u0e32\u0e19\u0e01\u0e38\u0e48\u0e21"
    ],
    "name:und_x_variant":[
        "Ban Kaeng Kum",
        "Ban Kum"
    ],
    "wof:name":"Ban Kum",
    "wof:placetype":"locality"
},
  "geometry": {"coordinates":[105.49522,15.39042],"type":"Point"}
}