{
  "type": "Feature",
  "properties": {
    "gn:admin1_code":"15.0",
    "gn:asciiname":"Ban Khao Kwang Thong",
    "gn:country_code":"TH",
    "gn:dem":81,
    "gn:feature_class":"P",
    "gn:feature_code":"PPL",
    "gn:name":"Ban Khao Kwang Thong",
    "gn:population":0,
    "gn:timezone":"Asia/Bangkok",
    "iso:country":"TH",
    "name:tha_x_preferred":[
        "\u0e1a\u0e49\u0e32\u0e19\u0e40\u0e02\u0e32\u0e01\u0e27\u0e32\u0e07\u0e17\u0e2d\u0e07"
    ],
    "wof:name":"Ban Khao Kwang Thong",
    "wof:placetype":"locality"
},
  "geometry": {"coordinates":[99.67180999999999,15.36853],"type":"Point"}
}