{
  "type": "Feature",
  "properties": {
    "gn:admin1_code":"52.0",
    "gn:asciiname":"Ban Dong Khilek",
    "gn:country_code":"TH",
    "gn:dem":11,
    "gn:feature_class":"P",
    "gn:feature_code":"PPL",
    "gn:name":"Ban Dong Khilek",
    "gn:population":0,
    "gn:timezone":"Asia/Bangkok",
    "iso:country":"TH",
    "name:tha_x_preferred":[
        "\u0e1a\u0e49\u0e32\u0e19\u0e14\u0e07\u0e02\u0e35\u0e49\u0e40\u0e2b\u0e25\u0e47\u0e01"
    ],
    "wof:lang_x_official":[
        "tha"
    ],
    "wof:lang_x_spoken":[
        "tha"
    ],
    "wof:name":"Ban Dong Khilek",
    "wof:placetype":"locality"
},
  "geometry": {"coordinates":[99.90872,13.60839],"type":"Point"}
}