{
  "type": "Feature",
  "properties": {
    "gn:admin1_code":"80",
    "gn:asciiname":"Ban Kilo Si",
    "gn:country_code":"TH",
    "gn:dem":50,
    "gn:feature_class":"P",
    "gn:feature_code":"PPL",
    "gn:name":"Ban Kilo Si",
    "gn:population":0,
    "gn:timezone":"Asia/Bangkok",
    "iso:country":"TH",
    "name:tha_x_preferred":[
        "\u0e1a\u0e49\u0e32\u0e19\u0e01\u0e34\u0e42\u0e25\u0e2a\u0e35\u0e48"
    ],
    "wof:name":"Ban Kilo Si",
    "wof:placetype":"locality"
},
  "geometry": {"coordinates":[102.53216999999999,13.67281],"type":"Point"}
}