{
  "type": "Feature",
  "properties": {
    "gn:admin1_code":"49.0",
    "gn:asciiname":"Ban Chang Kluea",
    "gn:country_code":"TH",
    "gn:dem":17,
    "gn:feature_class":"P",
    "gn:feature_code":"PPL",
    "gn:name":"Ban Chang Kluea",
    "gn:population":0,
    "gn:timezone":"Asia/Bangkok",
    "iso:country":"TH",
    "name:tha_x_preferred":[
        "\u0e1a\u0e49\u0e32\u0e19\u0e09\u0e32\u0e07\u0e40\u0e01\u0e25\u0e37\u0e2d"
    ],
    "name:und_x_variant":[
        "Chang Klua",
        "Ban Chang Klua",
        "Ban Chang Kluea"
    ],
    "wof:lang_x_official":[
        "tha"
    ],
    "wof:lang_x_spoken":[
        "tha"
    ],
    "wof:name":"Ban Chang Kluea",
    "wof:placetype":"locality"
},
  "geometry": {"coordinates":[102.58283,12.40744],"type":"Point"}
}