{
  "type": "Feature",
  "properties": {
    "gn:admin1_code":"55.0",
    "gn:asciiname":"Ban Wat Yai Ban Bo",
    "gn:country_code":"TH",
    "gn:dem":7,
    "gn:feature_class":"P",
    "gn:feature_code":"PPL",
    "gn:name":"Ban Wat Yai Ban Bo",
    "gn:population":0,
    "gn:timezone":"Asia/Bangkok",
    "iso:country":"TH",
    "name:tha_x_preferred":[
        "\u0e1a\u0e49\u0e32\u0e19\u0e27\u0e31\u0e14\u0e43\u0e2b\u0e0d\u0e48\u0e1a\u0e49\u0e32\u0e19\u0e1a\u0e48\u0e2d"
    ],
    "wof:name":"Ban Wat Yai Ban Bo",
    "wof:placetype":"locality"
},
  "geometry": {"coordinates":[100.17353,13.51144],"type":"Point"}
}