{
  "type": "Feature",
  "properties": {
    "gn:admin1_code":"0.0",
    "gn:asciiname":"Ban Sop Khun",
    "gn:country_code":"TH",
    "gn:dem":937,
    "gn:feature_class":"P",
    "gn:feature_code":"PPL",
    "gn:name":"Ban Sop Khun",
    "gn:population":0,
    "gn:timezone":"Asia/Bangkok",
    "iso:country":"TH",
    "wof:name":"Ban Sop Khun",
    "wof:placetype":"locality"
},
  "geometry": {"coordinates":[100.51667,19.06667],"type":"Point"}
}