{
  "type": "Feature",
  "properties": {
    "gn:admin1_code":"20.0",
    "gn:asciiname":"Ban Na Duea",
    "gn:country_code":"TH",
    "gn:dem":167,
    "gn:feature_class":"P",
    "gn:feature_code":"PPL",
    "gn:name":"Ban Na Duea",
    "gn:population":0,
    "gn:timezone":"Asia/Bangkok",
    "iso:country":"TH",
    "name:tha_x_preferred":[
        "\u0e1a\u0e49\u0e32\u0e19\u0e19\u0e32\u0e40\u0e14\u0e37\u0e48\u0e2d"
    ],
    "name:und_x_variant":[
        "Ban Na Dua"
    ],
    "wof:name":"Ban Na Duea",
    "wof:placetype":"locality"
},
  "geometry": {"coordinates":[104.27333,17.24917],"type":"Point"}
}