{
  "type": "Feature",
  "properties": {
    "gn:admin1_code":"72.0",
    "gn:asciiname":"Ban Nong Siao",
    "gn:country_code":"TH",
    "gn:dem":137,
    "gn:feature_class":"P",
    "gn:feature_code":"PPL",
    "gn:name":"Ban Nong Siao",
    "gn:population":0,
    "gn:timezone":"Asia/Bangkok",
    "iso:country":"TH",
    "name:tha_x_preferred":[
        "\u0e1a\u0e49\u0e32\u0e19\u0e2b\u0e19\u0e2d\u0e07\u0e40\u0e2a\u0e35\u0e22\u0e27"
    ],
    "name:und_x_variant":[
        "Ban Nong Sieo"
    ],
    "wof:name":"Ban Nong Siao",
    "wof:placetype":"locality"
},
  "geometry": {"coordinates":[104.39806,15.70233],"type":"Point"}
}