{
  "type": "Feature",
  "properties": {
    "gn:admin1_code":"22",
    "gn:asciiname":"Ban Kham Pak Dao",
    "gn:country_code":"TH",
    "gn:dem":217,
    "gn:feature_class":"P",
    "gn:feature_code":"PPL",
    "gn:name":"Ban Kham Pak Dao",
    "gn:population":0,
    "gn:timezone":"Asia/Bangkok",
    "iso:country":"TH",
    "name:tha_x_preferred":[
        "\u0e1a\u0e49\u0e32\u0e19\u0e04\u0e33\u0e1b\u0e32\u0e01\u0e14\u0e32\u0e27"
    ],
    "wof:name":"Ban Kham Pak Dao",
    "wof:placetype":"locality"
},
  "geometry": {"coordinates":[102.48356,16.30381],"type":"Point"}
}