{
  "type": "Feature",
  "properties": {
    "gn:admin1_code":"48.0",
    "gn:asciiname":"Ban Ko Khwang",
    "gn:country_code":"TH",
    "gn:dem":10,
    "gn:feature_class":"P",
    "gn:feature_code":"PPL",
    "gn:name":"Ban Ko Khwang",
    "gn:population":0,
    "gn:timezone":"Asia/Bangkok",
    "iso:country":"TH",
    "name:tha_x_preferred":[
        "\u0e1a\u0e49\u0e32\u0e19\u0e40\u0e01\u0e32\u0e30\u0e02\u0e27\u0e32\u0e07"
    ],
    "name:und_x_variant":[
        "Kau Khwang",
        "Ban Ko Khwang"
    ],
    "wof:name":"Ban Ko Khwang",
    "wof:placetype":"locality"
},
  "geometry": {"coordinates":[102.11870999999999,12.57814],"type":"Point"}
}