{
  "type": "Feature",
  "properties": {
    "gn:admin1_code":"69.0",
    "gn:asciiname":"Ban Cho Ka Pho Nai",
    "gn:country_code":"TH",
    "gn:dem":29,
    "gn:feature_class":"P",
    "gn:feature_code":"PPL",
    "gn:name":"Ban Cho Ka Pho Nai",
    "gn:population":0,
    "gn:timezone":"Asia/Bangkok",
    "iso:country":"TH",
    "name:tha_x_preferred":[
        "\u0e1a\u0e49\u0e32\u0e19\u0e40\u0e08\u0e32\u0e30\u0e01\u0e30\u0e1e\u0e49\u0e2d\u0e43\u0e19"
    ],
    "name:und_x_variant":[
        "Kampong Chau Ka Phau",
        "Kampong Chokapo",
        "Kampong Chaokapho",
        "Ban Cho Ka Pho Nai"
    ],
    "wof:name":"Ban Cho Ka Pho Nai",
    "wof:placetype":"locality"
},
  "geometry": {"coordinates":[101.54194,6.56703],"type":"Point"}
}