{
  "type": "Feature",
  "properties": {
    "gn:admin1_code":"41.0",
    "gn:asciiname":"Ban Sak Noi",
    "gn:country_code":"TH",
    "gn:dem":370,
    "gn:feature_class":"P",
    "gn:feature_code":"PPL",
    "gn:name":"Ban Sak Noi",
    "gn:population":0,
    "gn:timezone":"Asia/Bangkok",
    "iso:country":"TH",
    "wof:name":"Ban Sak Noi",
    "wof:placetype":"locality"
},
  "geometry": {"coordinates":[100.11667,19.51667],"type":"Point"}
}