{
  "type": "Feature",
  "properties": {
    "gn:admin1_code":"16.0",
    "gn:asciiname":"Ban Khao Khok Phen",
    "gn:country_code":"TH",
    "gn:dem":66,
    "gn:feature_class":"P",
    "gn:feature_code":"PPL",
    "gn:name":"Ban Khao Khok Phen",
    "gn:population":0,
    "gn:timezone":"Asia/Bangkok",
    "iso:country":"TH",
    "name:tha_x_preferred":[
        "\u0e1a\u0e49\u0e32\u0e19\u0e40\u0e02\u0e32\u0e42\u0e04\u0e01\u0e40\u0e1c\u0e48\u0e19"
    ],
    "wof:name":"Ban Khao Khok Phen",
    "wof:placetype":"locality"
},
  "geometry": {"coordinates":[100.18814,15.56569],"type":"Point"}
}