{
  "type": "Feature",
  "properties": {
    "gn:admin1_code":"68.0",
    "gn:asciiname":"Ban Khlong Rang",
    "gn:country_code":"TH",
    "gn:dem":56,
    "gn:feature_class":"P",
    "gn:feature_code":"PPL",
    "gn:name":"Ban Khlong Rang",
    "gn:population":0,
    "gn:timezone":"Asia/Bangkok",
    "iso:country":"TH",
    "name:tha_x_preferred":[
        "\u0e1a\u0e49\u0e32\u0e19\u0e04\u0e25\u0e2d\u0e07\u0e2b\u0e23\u0e31\u0e07"
    ],
    "wof:name":"Ban Khlong Rang",
    "wof:placetype":"locality"
},
  "geometry": {"coordinates":[100.58195000000001,6.94881],"type":"Point"}
}