{
  "type": "Feature",
  "properties": {
    "gn:admin1_code":"44.0",
    "gn:asciiname":"Ban Don Sakae",
    "gn:country_code":"TH",
    "gn:dem":6,
    "gn:feature_class":"P",
    "gn:feature_code":"PPL",
    "gn:name":"Ban Don Sakae",
    "gn:population":0,
    "gn:timezone":"Asia/Bangkok",
    "iso:country":"TH",
    "name:tha_x_preferred":[
        "\u0e1a\u0e49\u0e32\u0e19\u0e14\u0e2d\u0e19\u0e2a\u0e30\u0e41\u0e01"
    ],
    "wof:name":"Ban Don Sakae",
    "wof:placetype":"locality"
},
  "geometry": {"coordinates":[101.10478000000001,13.63186],"type":"Point"}
}