{
  "type": "Feature",
  "properties": {
    "gn:admin1_code":"24",
    "gn:asciiname":"Ban Kut Takhe",
    "gn:country_code":"TH",
    "gn:dem":169,
    "gn:feature_class":"P",
    "gn:feature_code":"PPL",
    "gn:name":"Ban Kut Takhe",
    "gn:population":0,
    "gn:timezone":"Asia/Bangkok",
    "iso:country":"TH",
    "name:tha_x_preferred":[
        "\u0e1a\u0e49\u0e32\u0e19\u0e01\u0e38\u0e14\u0e15\u0e30\u0e40\u0e02\u0e49"
    ],
    "wof:name":"Ban Kut Takhe",
    "wof:placetype":"locality"
},
  "geometry": {"coordinates":[103.08141999999999,15.70828],"type":"Point"}
}