{
  "type": "Feature",
  "properties": {
    "gn:admin1_code":"27",
    "gn:asciiname":"Ban Suk Sombun",
    "gn:country_code":"TH",
    "gn:dem":437,
    "gn:feature_class":"P",
    "gn:feature_code":"PPL",
    "gn:name":"Ban Suk Sombun",
    "gn:population":0,
    "gn:timezone":"Asia/Bangkok",
    "iso:country":"TH",
    "name:tha_x_preferred":[
        "\u0e1a\u0e49\u0e32\u0e19\u0e2a\u0e38\u0e02\u0e2a\u0e21\u0e1a\u0e39\u0e23\u0e13\u0e4c"
    ],
    "wof:name":"Ban Suk Sombun",
    "wof:placetype":"locality"
},
  "geometry": {"coordinates":[101.94061000000001,14.34681],"type":"Point"}
}