{
  "type": "Feature",
  "properties": {
    "gn:admin1_code":"80.0",
    "gn:asciiname":"Ban Suk Kasem",
    "gn:country_code":"TH",
    "gn:dem":62,
    "gn:feature_class":"P",
    "gn:feature_code":"PPL",
    "gn:name":"Ban Suk Kasem",
    "gn:population":0,
    "gn:timezone":"Asia/Bangkok",
    "iso:country":"TH",
    "name:tha_x_preferred":[
        "\u0e1a\u0e49\u0e32\u0e19\u0e2a\u0e38\u0e02\u0e40\u0e01\u0e29\u0e21"
    ],
    "wof:name":"Ban Suk Kasem",
    "wof:placetype":"locality"
},
  "geometry": {"coordinates":[102.45725,13.63681],"type":"Point"}
}