{
  "type": "Feature",
  "properties": {
    "gn:admin1_code":"63.0",
    "gn:asciiname":"Ban Khao Khwang",
    "gn:country_code":"TH",
    "gn:dem":104,
    "gn:feature_class":"P",
    "gn:feature_code":"PPL",
    "gn:name":"Ban Khao Khwang",
    "gn:population":0,
    "gn:timezone":"Asia/Bangkok",
    "iso:country":"TH",
    "name:tha_x_preferred":[
        "\u0e1a\u0e49\u0e32\u0e19\u0e40\u0e02\u0e32\u0e02\u0e27\u0e32\u0e07"
    ],
    "wof:name":"Ban Khao Khwang",
    "wof:placetype":"locality"
},
  "geometry": {"coordinates":[99.10442,8.18364],"type":"Point"}
}