{
  "type": "Feature",
  "properties": {
    "gn:country":"TH",
    "gn:fcode":"PPL",
    "gn:pop":0,
    "iso:country":"TH",
    "name:tha_x_preferred":[
        "\u0e1a\u0e49\u0e32\u0e19\u0e1e\u0e38\u0e40\u0e15\u0e22"
    ],
    "name:unk_x_variant":[
        "Tha Phu"
    ],
    "qs:name":"Phu Toei",
    "qs:name_adm0":"Thailand",
    "qs:name_adm1":"Phetchabun",
    "qs:photos":25,
    "qs:photos_1k":5,
    "qs:photos_9k":1,
    "qs:photos_9r":1,
    "qs:photos_all":25,
    "qs:photos_sr":1,
    "qs:placetype":"Town",
    "qs:pop_sr":"0",
    "wof:name":"Phu Toei",
    "wof:placetype":"locality",
    "wof:population":0
},
  "geometry": {"coordinates":[101.06455,15.57521],"type":"Point"}
}