{
  "type": "Feature",
  "properties": {
    "gn:admin1_code":"61.0",
    "gn:asciiname":"Ban Racha",
    "gn:country_code":"TH",
    "gn:dem":21,
    "gn:feature_class":"P",
    "gn:feature_code":"PPL",
    "gn:name":"Ban Racha",
    "gn:population":0,
    "gn:timezone":"Asia/Bangkok",
    "iso:country":"TH",
    "name:tha_x_preferred":[
        "\u0e1a\u0e49\u0e32\u0e19\u0e23\u0e32\u0e0a\u0e32"
    ],
    "name:und_x_variant":[
        "Ban Raoh Cha",
        "Ban Rat Cha",
        "Ban Racha Tai",
        "Ban Racha"
    ],
    "wof:name":"Ban Racha",
    "wof:placetype":"locality"
},
  "geometry": {"coordinates":[98.32964,8.40378],"type":"Point"}
}