{
  "type": "Feature",
  "properties": {
    "gn:admin1_code":"28.0",
    "gn:asciiname":"Ban Talat Khwai",
    "gn:country_code":"TH",
    "gn:dem":172,
    "gn:feature_class":"P",
    "gn:feature_code":"PPL",
    "gn:name":"Ban Talat Khwai",
    "gn:population":0,
    "gn:timezone":"Asia/Bangkok",
    "iso:country":"TH",
    "name:tha_x_preferred":[
        "\u0e1a\u0e49\u0e32\u0e19\u0e15\u0e25\u0e32\u0e14\u0e04\u0e27\u0e32\u0e22"
    ],
    "wof:name":"Ban Talat Khwai",
    "wof:placetype":"locality"
},
  "geometry": {"coordinates":[103.09267,14.86794],"type":"Point"}
}