{
  "type": "Feature",
  "properties": {
    "gn:admin1_code":"16.0",
    "gn:asciiname":"Ban Ta Nio",
    "gn:country_code":"TH",
    "gn:dem":31,
    "gn:feature_class":"P",
    "gn:feature_code":"PPL",
    "gn:name":"Ban Ta Nio",
    "gn:population":0,
    "gn:timezone":"Asia/Bangkok",
    "iso:country":"TH",
    "name:tha_x_preferred":[
        "\u0e1a\u0e49\u0e32\u0e19\u0e15\u0e32\u0e19\u0e34\u0e27"
    ],
    "name:und_x_variant":[
        "Ban Ta Niu"
    ],
    "wof:name":"Ban Ta Nio",
    "wof:placetype":"locality"
},
  "geometry": {"coordinates":[100.09669,15.55125],"type":"Point"}
}