{
  "type": "Feature",
  "properties": {
    "gn:admin1_code":"70.0",
    "gn:asciiname":"Ban Khla",
    "gn:country_code":"TH",
    "gn:dem":21,
    "gn:feature_class":"P",
    "gn:feature_code":"PPL",
    "gn:name":"Ban Khla",
    "gn:population":0,
    "gn:timezone":"Asia/Bangkok",
    "iso:country":"TH",
    "name:tha_x_preferred":[
        "\u0e1a\u0e49\u0e32\u0e19\u0e04\u0e25\u0e49\u0e32"
    ],
    "wof:name":"Ban Khla",
    "wof:placetype":"locality"
},
  "geometry": {"coordinates":[101.28145000000001,6.63091],"type":"Point"}
}