{
  "type": "Feature",
  "properties": {
    "gn:admin1_code":"41.0",
    "gn:asciiname":"Ban Huai Sai Kaeo",
    "gn:country_code":"TH",
    "gn:dem":414,
    "gn:feature_class":"P",
    "gn:feature_code":"PPL",
    "gn:name":"Ban Huai Sai Kaeo",
    "gn:population":0,
    "gn:timezone":"Asia/Bangkok",
    "iso:country":"TH",
    "name:tha_x_preferred":[
        "\u0e1a\u0e49\u0e32\u0e19\u0e2b\u0e49\u0e27\u0e22\u0e17\u0e23\u0e32\u0e22\u0e41\u0e01\u0e49\u0e27"
    ],
    "wof:name":"Ban Huai Sai Kaeo",
    "wof:placetype":"locality"
},
  "geometry": {"coordinates":[100.06361,19.20222],"type":"Point"}
}