{
  "type": "Feature",
  "properties": {
    "gn:admin1_code":"42.0",
    "gn:asciiname":"Ban Khlong Bang Sao Thong",
    "gn:country_code":"TH",
    "gn:dem":5,
    "gn:feature_class":"P",
    "gn:feature_code":"PPL",
    "gn:name":"Ban Khlong Bang Sao Thong",
    "gn:population":0,
    "gn:timezone":"Asia/Bangkok",
    "iso:country":"TH",
    "name:tha_x_preferred":[
        "\u0e1a\u0e49\u0e32\u0e19\u0e04\u0e25\u0e2d\u0e07\u0e1a\u0e32\u0e07\u0e40\u0e2a\u0e32\u0e18\u0e07"
    ],
    "wof:name":"Ban Khlong Bang Sao Thong",
    "wof:placetype":"locality"
},
  "geometry": {"coordinates":[100.82292,13.60383],"type":"Point"}
}