{
  "type": "Feature",
  "properties": {
    "gn:admin1_code":"25.0",
    "gn:asciiname":"Ban Don Kham",
    "gn:country_code":"TH",
    "gn:dem":126,
    "gn:feature_class":"P",
    "gn:feature_code":"PPL",
    "gn:name":"Ban Don Kham",
    "gn:population":0,
    "gn:timezone":"Asia/Bangkok",
    "iso:country":"TH",
    "name:tha_x_preferred":[
        "\u0e1a\u0e49\u0e32\u0e19\u0e14\u0e2d\u0e19\u0e02\u0e32\u0e21"
    ],
    "wof:name":"Ban Don Kham",
    "wof:placetype":"locality"
},
  "geometry": {"coordinates":[103.89597000000001,15.53042],"type":"Point"}
}