{
  "type": "Feature",
  "properties": {
    "gn:admin1_code":"66.0",
    "gn:asciiname":"Ban Sala Tam Sao",
    "gn:country_code":"TH",
    "gn:dem":27,
    "gn:feature_class":"P",
    "gn:feature_code":"PPL",
    "gn:name":"Ban Sala Tam Sao",
    "gn:population":0,
    "gn:timezone":"Asia/Bangkok",
    "iso:country":"TH",
    "name:tha_x_preferred":[
        "\u0e1a\u0e49\u0e32\u0e19\u0e28\u0e32\u0e25\u0e32\u0e15\u0e33\u0e40\u0e2a\u0e32"
    ],
    "wof:name":"Ban Sala Tam Sao",
    "wof:placetype":"locality"
},
  "geometry": {"coordinates":[99.96368,7.785],"type":"Point"}
}