{
  "type": "Feature",
  "properties": {
    "gn:admin1_code":"25.0",
    "gn:asciiname":"Ban Um Chan",
    "gn:country_code":"TH",
    "gn:dem":153,
    "gn:feature_class":"P",
    "gn:feature_code":"PPL",
    "gn:name":"Ban Um Chan",
    "gn:population":0,
    "gn:timezone":"Asia/Bangkok",
    "iso:country":"TH",
    "name:tha_x_preferred":[
        "\u0e1a\u0e49\u0e32\u0e19\u0e2d\u0e38\u0e48\u0e21\u0e08\u0e32\u0e19"
    ],
    "wof:name":"Ban Um Chan",
    "wof:placetype":"locality"
},
  "geometry": {"coordinates":[103.50869,15.83906],"type":"Point"}
}