{
  "type": "Feature",
  "properties": {
    "gn:admin1_code":"66.0",
    "gn:asciiname":"Ban Khuan Kut",
    "gn:country_code":"TH",
    "gn:dem":9,
    "gn:feature_class":"P",
    "gn:feature_code":"PPL",
    "gn:name":"Ban Khuan Kut",
    "gn:population":0,
    "gn:timezone":"Asia/Bangkok",
    "iso:country":"TH",
    "name:tha_x_preferred":[
        "\u0e1a\u0e49\u0e32\u0e19\u0e04\u0e27\u0e19\u0e01\u0e38\u0e0e"
    ],
    "name:und_x_variant":[
        "Ban Khuan Kut (1)"
    ],
    "wof:name":"Ban Khuan Kut",
    "wof:placetype":"locality"
},
  "geometry": {"coordinates":[100.1195,7.57253],"type":"Point"}
}