{
  "type": "Feature",
  "properties": {
    "gn:admin1_code":"47.0",
    "gn:asciiname":"Ban Sap Sanae",
    "gn:country_code":"TH",
    "gn:dem":24,
    "gn:feature_class":"P",
    "gn:feature_code":"PPL",
    "gn:name":"Ban Sap Sanae",
    "gn:population":0,
    "gn:timezone":"Asia/Bangkok",
    "iso:country":"TH",
    "name:tha_x_preferred":[
        "\u0e1a\u0e49\u0e32\u0e19\u0e17\u0e23\u0e31\u0e1e\u0e22\u0e4c\u0e2a\u0e30\u0e41\u0e2b\u0e19"
    ],
    "wof:name":"Ban Sap Sanae",
    "wof:placetype":"locality"
},
  "geometry": {"coordinates":[101.57138999999999,12.94361],"type":"Point"}
}