{
  "type": "Feature",
  "properties": {
    "gn:admin1_code":"26.0",
    "gn:asciiname":"Ban Sa Khai Nam",
    "gn:country_code":"TH",
    "gn:dem":186,
    "gn:feature_class":"P",
    "gn:feature_code":"PPL",
    "gn:name":"Ban Sa Khai Nam",
    "gn:population":0,
    "gn:timezone":"Asia/Bangkok",
    "iso:country":"TH",
    "name:tha_x_preferred":[
        "\u0e1a\u0e49\u0e32\u0e19\u0e2a\u0e23\u0e30\u0e44\u0e02\u0e48\u0e19\u0e49\u0e33"
    ],
    "name:und_x_variant":[
        "B\u0101n Naung K\u0101i Nam",
        "Ban Nong Khai Nam",
        "Ban Sa Khai Nam"
    ],
    "wof:name":"Ban Sa Khai Nam",
    "wof:placetype":"locality"
},
  "geometry": {"coordinates":[102.10078,15.80764],"type":"Point"}
}