{
  "type": "Feature",
  "properties": {
    "gn:admin1_code":"1.0",
    "gn:asciiname":"Ban Huai Sai",
    "gn:country_code":"TH",
    "gn:dem":188,
    "gn:feature_class":"P",
    "gn:feature_code":"PPL",
    "gn:name":"Ban Huai Sai",
    "gn:population":0,
    "gn:timezone":"Asia/Bangkok",
    "iso:country":"TH",
    "name:tha_x_preferred":[
        "\u0e1a\u0e49\u0e32\u0e19\u0e2b\u0e49\u0e27\u0e22\u0e17\u0e23\u0e32\u0e22"
    ],
    "name:und_x_variant":[
        "Hw\u00e8 S\u0101i",
        "H\u016bis\u0101i",
        "Huai Sai",
        "Ban Huai Sai"
    ],
    "wof:lang_x_official":[
        "tha"
    ],
    "wof:lang_x_spoken":[
        "tha"
    ],
    "wof:name":"Ban Huai Sai",
    "wof:placetype":"locality"
},
  "geometry": {"coordinates":[97.92742,18.08122],"type":"Point"}
}