{
  "type": "Feature",
  "properties": {
    "gn:country":"TH",
    "gn:fcode":"PPLA2",
    "gn:population":0,
    "iso:country":"TH",
    "name:tha_x_preferred":[
        "\u0e1a\u0e32\u0e07\u0e19\u0e49\u0e33\u0e40\u0e1b\u0e23\u0e35\u0e49\u0e22\u0e27"
    ],
    "name:und_x_variant":[
        "Amphoe Bang Nam Prieo"
    ],
    "qs:name":"Bang Nam Prieo",
    "qs:name_adm0":"Thailand",
    "qs:name_adm1":"Chachoengsao",
    "qs:photos":33,
    "qs:photos_1k":7,
    "qs:photos_9k":1,
    "qs:photos_9r":2,
    "qs:photos_all":33,
    "qs:photos_sr":2,
    "qs:placetype":"Town",
    "qs:pop_sr":"0",
    "wof:name":"Bang Nam Prieo",
    "wof:placetype":"locality",
    "wof:population":0
},
  "geometry": {"coordinates":[101.05306,13.84739],"type":"Point"}
}