{
  "type": "Feature",
  "properties": {
    "gn:admin1_code":"66.0",
    "gn:asciiname":"Ban Khlong Chaloem",
    "gn:country_code":"TH",
    "gn:dem":51,
    "gn:feature_class":"P",
    "gn:feature_code":"PPL",
    "gn:name":"Ban Khlong Chaloem",
    "gn:population":0,
    "gn:timezone":"Asia/Bangkok",
    "iso:country":"TH",
    "name:tha_x_preferred":[
        "\u0e1a\u0e49\u0e32\u0e19\u0e04\u0e25\u0e2d\u0e07\u0e40\u0e09\u0e25\u0e34\u0e21"
    ],
    "wof:name":"Ban Khlong Chaloem",
    "wof:placetype":"locality"
},
  "geometry": {"coordinates":[99.98488999999999,7.36392],"type":"Point"}
}