{
  "type": "Feature",
  "properties": {
    "gn:admin1_code":"1.0",
    "gn:asciiname":"Ban Chom Chaeng",
    "gn:country_code":"TH",
    "gn:dem":245,
    "gn:feature_class":"P",
    "gn:feature_code":"PPL",
    "gn:name":"Ban Chom Chaeng",
    "gn:population":0,
    "gn:timezone":"Asia/Bangkok",
    "iso:country":"TH",
    "name:tha_x_preferred":[
        "\u0e1a\u0e49\u0e32\u0e19\u0e08\u0e2d\u0e21\u0e41\u0e08\u0e49\u0e07"
    ],
    "wof:name":"Ban Chom Chaeng",
    "wof:placetype":"locality"
},
  "geometry": {"coordinates":[97.94583,18.16264],"type":"Point"}
}