{
  "type": "Feature",
  "properties": {
    "gn:admin1_code":"2.0",
    "gn:asciiname":"Ban Sop Mae Satop",
    "gn:country_code":"TH",
    "gn:dem":673,
    "gn:feature_class":"P",
    "gn:feature_code":"PPL",
    "gn:name":"Ban Sop Mae Satop",
    "gn:population":0,
    "gn:timezone":"Asia/Bangkok",
    "iso:country":"TH",
    "name:tha_x_preferred":[
        "\u0e1a\u0e49\u0e32\u0e19\u0e2a\u0e1a\u0e41\u0e21\u0e48\u0e2a\u0e30\u0e15\u0e4a\u0e2d\u0e1a"
    ],
    "name:und_x_variant":[
        "Ban Yang Sop Satom",
        "Ban Sop Mae Satop"
    ],
    "wof:name":"Ban Sop Mae Satop",
    "wof:placetype":"locality"
},
  "geometry": {"coordinates":[98.24106,18.69994],"type":"Point"}
}