{
  "type": "Feature",
  "properties": {
    "gn:admin1_code":"76.0",
    "gn:asciiname":"Ban Non Tan",
    "gn:country_code":"TH",
    "gn:dem":181,
    "gn:feature_class":"P",
    "gn:feature_code":"PPL",
    "gn:name":"Ban Non Tan",
    "gn:population":0,
    "gn:timezone":"Asia/Bangkok",
    "iso:country":"TH",
    "name:tha_x_preferred":[
        "\u0e1a\u0e49\u0e32\u0e19\u0e42\u0e19\u0e19\u0e15\u0e32\u0e25"
    ],
    "wof:name":"Ban Non Tan",
    "wof:placetype":"locality"
},
  "geometry": {"coordinates":[102.72857999999999,17.40892],"type":"Point"}
}