{
  "type": "Feature",
  "properties": {
    "gn:admin1_code":"23.0",
    "gn:asciiname":"Ban Phai Kham Bon",
    "gn:country_code":"TH",
    "gn:dem":202,
    "gn:feature_class":"P",
    "gn:feature_code":"PPL",
    "gn:name":"Ban Phai Kham Bon",
    "gn:population":0,
    "gn:timezone":"Asia/Bangkok",
    "iso:country":"TH",
    "name:tha_x_preferred":[
        "\u0e1a\u0e49\u0e32\u0e19\u0e44\u0e1c\u0e48\u0e04\u0e33\u0e1a\u0e2d\u0e19"
    ],
    "wof:name":"Ban Phai Kham Bon",
    "wof:placetype":"locality"
},
  "geometry": {"coordinates":[103.57133,16.60408],"type":"Point"}
}