{
  "type": "Feature",
  "properties": {
    "gn:admin1_code":"68.0",
    "gn:asciiname":"Ban Ba Ra Pha",
    "gn:country_code":"TH",
    "gn:dem":12,
    "gn:feature_class":"P",
    "gn:feature_code":"PPL",
    "gn:name":"Ban Ba Ra Pha",
    "gn:population":0,
    "gn:timezone":"Asia/Bangkok",
    "iso:country":"TH",
    "name:tha_x_preferred":[
        "\u0e1a\u0e49\u0e32\u0e19\u0e1a\u0e32\u0e23\u0e32\u0e1e\u0e32"
    ],
    "name:und_x_variant":[
        "Ban Bang Ra Pha"
    ],
    "wof:name":"Ban Ba Ra Pha",
    "wof:placetype":"locality"
},
  "geometry": {"coordinates":[101.06465,6.85339],"type":"Point"}
}