{
  "type": "Feature",
  "properties": {
    "gn:admin1_code":"29.0",
    "gn:asciiname":"Ban Priang",
    "gn:country_code":"TH",
    "gn:dem":151,
    "gn:feature_class":"P",
    "gn:feature_code":"PPL",
    "gn:name":"Ban Priang",
    "gn:population":0,
    "gn:timezone":"Asia/Bangkok",
    "iso:country":"TH",
    "name:tha_x_preferred":[
        "\u0e1a\u0e49\u0e32\u0e19\u0e40\u0e1b\u0e23\u0e35\u0e22\u0e07"
    ],
    "name:und_x_variant":[
        "Sr\u012bkh\u014dhrabh\u016bm",
        "Ban Nang Rong",
        "Prung",
        "Ban Yang",
        "Sri Kra Pum",
        "Srikhonphum",
        "Srikhohrabbum",
        "Sikaunphum",
        "Si Kara Pum",
        "Ban Priang"
    ],
    "wof:name":"Ban Priang",
    "wof:placetype":"locality"
},
  "geometry": {"coordinates":[103.69583,14.87311],"type":"Point"}
}