{
  "type": "Feature",
  "properties": {
    "gn:admin1_code":"70.0",
    "gn:asciiname":"Ban Suan Nai",
    "gn:country_code":"TH",
    "gn:dem":433,
    "gn:feature_class":"P",
    "gn:feature_code":"PPL",
    "gn:name":"Ban Suan Nai",
    "gn:population":0,
    "gn:timezone":"Asia/Bangkok",
    "iso:country":"TH",
    "name:tha_x_preferred":[
        "\u0e1a\u0e49\u0e32\u0e19\u0e2a\u0e27\u0e19\u0e43\u0e19"
    ],
    "wof:name":"Ban Suan Nai",
    "wof:placetype":"locality"
},
  "geometry": {"coordinates":[101.13343999999999,5.95331],"type":"Point"}
}