{
  "type": "Feature",
  "properties": {
    "gn:admin1_code":"32.0",
    "gn:asciiname":"Ban Wat Kamphaeng",
    "gn:country_code":"TH",
    "gn:dem":20,
    "gn:feature_class":"P",
    "gn:feature_code":"PPL",
    "gn:name":"Ban Wat Kamphaeng",
    "gn:population":0,
    "gn:timezone":"Asia/Bangkok",
    "iso:country":"TH",
    "name:tha_x_preferred":[
        "\u0e1a\u0e49\u0e32\u0e19\u0e27\u0e31\u0e14\u0e01\u0e33\u0e41\u0e1e\u0e07"
    ],
    "name:und_x_variant":[
        "Ban Kamphaeng"
    ],
    "wof:name":"Ban Wat Kamphaeng",
    "wof:placetype":"locality"
},
  "geometry": {"coordinates":[100.10517,15.01642],"type":"Point"}
}