{
  "type": "Feature",
  "properties": {
    "gn:admin1_code":"64.0",
    "gn:asciiname":"Ban Ao Si Mueang",
    "gn:country_code":"TH",
    "gn:dem":101,
    "gn:feature_class":"P",
    "gn:feature_code":"PPL",
    "gn:name":"Ban Ao Si Mueang",
    "gn:population":0,
    "gn:timezone":"Asia/Bangkok",
    "iso:country":"TH",
    "name:tha_x_preferred":[
        "\u0e1a\u0e49\u0e32\u0e19\u0e2d\u0e48\u0e32\u0e27\u0e28\u0e23\u0e35\u0e40\u0e21\u0e37\u0e2d\u0e07"
    ],
    "wof:name":"Ban Ao Si Mueang",
    "wof:placetype":"locality"
},
  "geometry": {"coordinates":[99.80767,8.03494],"type":"Point"}
}