{
  "type": "Feature",
  "properties": {
    "gn:admin1_code":"25",
    "gn:asciiname":"Ban Kho Yai",
    "gn:country_code":"TH",
    "gn:dem":130,
    "gn:feature_class":"P",
    "gn:feature_code":"PPL",
    "gn:name":"Ban Kho Yai",
    "gn:population":0,
    "gn:timezone":"Asia/Bangkok",
    "iso:country":"TH",
    "name:tha_x_preferred":[
        "\u0e1a\u0e49\u0e32\u0e19\u0e04\u0e49\u0e2d\u0e43\u0e2b\u0e0d\u0e48"
    ],
    "wof:name":"Ban Kho Yai",
    "wof:placetype":"locality"
},
  "geometry": {"coordinates":[104.14369000000001,15.60294],"type":"Point"}
}