{
  "type": "Feature",
  "properties": {
    "gn:admin1_code":"25",
    "gn:asciiname":"Ban Ba Ta Ka",
    "gn:country_code":"TH",
    "gn:dem":159,
    "gn:feature_class":"P",
    "gn:feature_code":"PPL",
    "gn:name":"Ban Ba Ta Ka",
    "gn:population":0,
    "gn:timezone":"Asia/Bangkok",
    "iso:country":"TH",
    "name:tha_x_preferred":[
        "\u0e1a\u0e49\u0e32\u0e19\u0e1a\u0e30\u0e15\u0e32\u0e01\u0e32"
    ],
    "wof:name":"Ban Ba Ta Ka",
    "wof:placetype":"locality"
},
  "geometry": {"coordinates":[104.00278,16.37339],"type":"Point"}
}