{
  "type": "Feature",
  "properties": {
    "gn:admin1_code":"53.0",
    "gn:asciiname":"Ban Tako Sung",
    "gn:country_code":"TH",
    "gn:dem":8,
    "gn:feature_class":"P",
    "gn:feature_code":"PPL",
    "gn:name":"Ban Tako Sung",
    "gn:population":0,
    "gn:timezone":"Asia/Bangkok",
    "iso:country":"TH",
    "name:tha_x_preferred":[
        "\u0e1a\u0e49\u0e32\u0e19\u0e15\u0e30\u0e42\u0e01\u0e2a\u0e39\u0e07"
    ],
    "name:und_x_variant":[
        "\u0e1a\u0e49\u0e32\u0e19\u0e15\u0e30\u0e42\u0e01\u0e2a\u0e39\u0e07"
    ],
    "wof:name":"Ban Tako Sung",
    "wof:placetype":"locality"
},
  "geometry": {"coordinates":[100.06023999999999,13.99928],"type":"Point"}
}