{
  "type": "Feature",
  "properties": {
    "gn:admin1_code":"64.0",
    "gn:asciiname":"Ban Suea Hueng",
    "gn:country_code":"TH",
    "gn:dem":4,
    "gn:feature_class":"P",
    "gn:feature_code":"PPL",
    "gn:name":"Ban Suea Hueng",
    "gn:population":0,
    "gn:timezone":"Asia/Bangkok",
    "iso:country":"TH",
    "name:tha_x_preferred":[
        "\u0e1a\u0e49\u0e32\u0e19\u0e40\u0e2a\u0e37\u0e2d\u0e2b\u0e36\u0e07"
    ],
    "wof:name":"Ban Suea Hueng",
    "wof:placetype":"locality"
},
  "geometry": {"coordinates":[100.25272,8.17536],"type":"Point"}
}