{
  "type": "Feature",
  "properties": {
    "gn:admin1_code":"64.0",
    "gn:asciiname":"Ban Huai Hoi",
    "gn:country_code":"TH",
    "gn:dem":55,
    "gn:feature_class":"P",
    "gn:feature_code":"PPL",
    "gn:name":"Ban Huai Hoi",
    "gn:population":0,
    "gn:timezone":"Asia/Bangkok",
    "iso:country":"TH",
    "name:tha_x_preferred":[
        "\u0e1a\u0e49\u0e32\u0e19\u0e2b\u0e49\u0e27\u0e22\u0e2b\u0e2d\u0e22"
    ],
    "wof:name":"Ban Huai Hoi",
    "wof:placetype":"locality"
},
  "geometry": {"coordinates":[99.45466999999999,8.03053],"type":"Point"}
}