{
  "type": "Feature",
  "properties": {
    "gn:admin1_code":"31.0",
    "gn:asciiname":"Ban Kue Yaeng",
    "gn:country_code":"TH",
    "gn:dem":42,
    "gn:feature_class":"P",
    "gn:feature_code":"PPL",
    "gn:name":"Ban Kue Yaeng",
    "gn:population":0,
    "gn:timezone":"Asia/Bangkok",
    "iso:country":"TH",
    "name:tha_x_preferred":[
        "\u0e1a\u0e49\u0e32\u0e19\u0e01\u0e37\u0e2d\u0e41\u0e22\u0e07"
    ],
    "wof:name":"Ban Kue Yaeng",
    "wof:placetype":"locality"
},
  "geometry": {"coordinates":[101.48466999999999,6.26986],"type":"Point"}
}