{
  "type": "Feature",
  "properties": {
    "gn:admin1_code":"65.0",
    "gn:asciiname":"Ban Hin Ru Yang (2)",
    "gn:country_code":"TH",
    "gn:dem":-9999,
    "gn:feature_class":"P",
    "gn:feature_code":"PPL",
    "gn:name":"Ban Hin Ru Yang (2)",
    "gn:population":0,
    "gn:timezone":"Asia/Bangkok",
    "iso:country":"TH",
    "wof:name":"Ban Hin Ru Yang (2)",
    "wof:placetype":"locality"
},
  "geometry": {"coordinates":[99.33333,7.46667],"type":"Point"}
}