{
  "type": "Feature",
  "properties": {
    "gn:admin1_code":"64.0",
    "gn:asciiname":"Ban Talat Ron Phibun",
    "gn:country_code":"TH",
    "gn:dem":37,
    "gn:feature_class":"P",
    "gn:feature_code":"PPL",
    "gn:name":"Ban Talat Ron Phibun",
    "gn:population":0,
    "gn:timezone":"Asia/Bangkok",
    "iso:country":"TH",
    "name:tha_x_preferred":[
        "\u0e1a\u0e49\u0e32\u0e19\u0e15\u0e25\u0e32\u0e14\u0e23\u0e48\u0e2d\u0e19\u0e1e\u0e34\u0e1a\u0e39\u0e25\u0e22\u0e4c"
    ],
    "wof:name":"Ban Talat Ron Phibun",
    "wof:placetype":"locality"
},
  "geometry": {"coordinates":[99.84428,8.18367],"type":"Point"}
}