{
  "type": "Feature",
  "properties": {
    "gn:admin1_code":"27.0",
    "gn:asciiname":"Ban Kaphi",
    "gn:country_code":"TH",
    "gn:dem":191,
    "gn:feature_class":"P",
    "gn:feature_code":"PPL",
    "gn:name":"Ban Kaphi",
    "gn:population":0,
    "gn:timezone":"Asia/Bangkok",
    "iso:country":"TH",
    "name:tha_x_preferred":[
        "\u0e1a\u0e49\u0e32\u0e19\u0e01\u0e30\u0e1e\u0e35\u0e49"
    ],
    "name:und_x_variant":[
        "B\u0101n Gaphi",
        "Ban Kapi",
        "Ban Kaphi"
    ],
    "wof:name":"Ban Kaphi",
    "wof:placetype":"locality"
},
  "geometry": {"coordinates":[101.95267,15.10436],"type":"Point"}
}