{
  "type": "Feature",
  "properties": {
    "gn:admin1_code":"39.0",
    "gn:asciiname":"Ban Sam Sip Sam Phatthana",
    "gn:country_code":"TH",
    "gn:dem":7,
    "gn:feature_class":"P",
    "gn:feature_code":"PPL",
    "gn:name":"Ban Sam Sip Sam Phatthana",
    "gn:population":0,
    "gn:timezone":"Asia/Bangkok",
    "iso:country":"TH",
    "name:tha_x_preferred":[
        "Ban Sam Sip Sam Phatthana"
    ],
    "name:tha_x_variant":[
        "\u0e1a\u0e49\u0e32\u0e19\u0e2a\u0e32\u0e21\u0e2a\u0e34\u0e1a\u0e2a\u0e32\u0e21\u0e1e\u0e31\u0e12\u0e19\u0e32"
    ],
    "wof:name":"Ban Sam Sip Sam Phatthana",
    "wof:placetype":"locality"
},
  "geometry": {"coordinates":[100.90731,14.2277],"type":"Point"}
}