{
  "type": "Feature",
  "properties": {
    "gn:admin1_code":"49.0",
    "gn:asciiname":"Ban Khlong Nam Dam",
    "gn:country_code":"TH",
    "gn:dem":7,
    "gn:feature_class":"P",
    "gn:feature_code":"PPL",
    "gn:name":"Ban Khlong Nam Dam",
    "gn:population":0,
    "gn:timezone":"Asia/Bangkok",
    "iso:country":"TH",
    "name:tha_x_preferred":[
        "\u0e1a\u0e49\u0e32\u0e19\u0e04\u0e25\u0e2d\u0e07\u0e19\u0e49\u0e33\u0e14\u0e33"
    ],
    "wof:name":"Ban Khlong Nam Dam",
    "wof:placetype":"locality"
},
  "geometry": {"coordinates":[102.679,12.13267],"type":"Point"}
}