{
  "type": "Feature",
  "properties": {
    "gn:admin1_code":"28.0",
    "gn:asciiname":"Ban Ta Pek",
    "gn:country_code":"TH",
    "gn:dem":194,
    "gn:feature_class":"P",
    "gn:feature_code":"PPL",
    "gn:name":"Ban Ta Pek",
    "gn:population":0,
    "gn:timezone":"Asia/Bangkok",
    "iso:country":"TH",
    "name:tha_x_preferred":[
        "\u0e1a\u0e49\u0e32\u0e19\u0e15\u0e32\u0e40\u0e1b\u0e4a\u0e01"
    ],
    "wof:name":"Ban Ta Pek",
    "wof:placetype":"locality"
},
  "geometry": {"coordinates":[102.89778,14.56536],"type":"Point"}
}