{
  "type": "Feature",
  "properties": {
    "gn:admin1_code":"72.0",
    "gn:asciiname":"Ban Nong Suea Tai",
    "gn:country_code":"TH",
    "gn:dem":140,
    "gn:feature_class":"P",
    "gn:feature_code":"PPL",
    "gn:name":"Ban Nong Suea Tai",
    "gn:population":0,
    "gn:timezone":"Asia/Bangkok",
    "iso:country":"TH",
    "name:tha_x_preferred":[
        "\u0e1a\u0e49\u0e32\u0e19\u0e2b\u0e19\u0e2d\u0e07\u0e40\u0e2a\u0e37\u0e2d\u0e15\u0e32\u0e22"
    ],
    "wof:name":"Ban Nong Suea Tai",
    "wof:placetype":"locality"
},
  "geometry": {"coordinates":[104.18386,15.82367],"type":"Point"}
}