{
  "type": "Feature",
  "properties": {
    "gn:admin1_code":"66.0",
    "gn:asciiname":"Ban Nai Mueang",
    "gn:country_code":"TH",
    "gn:dem":11,
    "gn:feature_class":"P",
    "gn:feature_code":"PPL",
    "gn:name":"Ban Nai Mueang",
    "gn:population":0,
    "gn:timezone":"Asia/Bangkok",
    "iso:country":"TH",
    "name:tha_x_preferred":[
        "\u0e1a\u0e49\u0e32\u0e19\u0e43\u0e19\u0e40\u0e21\u0e37\u0e2d\u0e07"
    ],
    "wof:name":"Ban Nai Mueang",
    "wof:placetype":"locality"
},
  "geometry": {"coordinates":[100.05906,7.69117],"type":"Point"}
}