{
  "type": "Feature",
  "properties": {
    "gn:admin1_code":"7.0",
    "gn:asciiname":"Ban Huai Lak Puen",
    "gn:country_code":"TH",
    "gn:dem":238,
    "gn:feature_class":"P",
    "gn:feature_code":"PPL",
    "gn:name":"Ban Huai Lak Puen",
    "gn:population":0,
    "gn:timezone":"Asia/Bangkok",
    "iso:country":"TH",
    "name:tha_x_preferred":[
        "\u0e1a\u0e49\u0e32\u0e19\u0e2b\u0e49\u0e27\u0e22\u0e25\u0e32\u0e01\u0e1b\u0e37\u0e19"
    ],
    "wof:name":"Ban Huai Lak Puen",
    "wof:placetype":"locality"
},
  "geometry": {"coordinates":[100.07232999999999,17.88331],"type":"Point"}
}