{
  "type": "Feature",
  "properties": {
    "gn:admin1_code":"22",
    "gn:asciiname":"Ban Ba Kham",
    "gn:country_code":"TH",
    "gn:dem":158,
    "gn:feature_class":"P",
    "gn:feature_code":"PPL",
    "gn:name":"Ban Ba Kham",
    "gn:population":0,
    "gn:timezone":"Asia/Bangkok",
    "iso:country":"TH",
    "name:tha_x_preferred":[
        "\u0e1a\u0e49\u0e32\u0e19\u0e1a\u0e30\u0e02\u0e32\u0e21"
    ],
    "wof:name":"Ban Ba Kham",
    "wof:placetype":"locality"
},
  "geometry": {"coordinates":[102.86947000000001,16.42911],"type":"Point"}
}