{
  "type": "Feature",
  "properties": {
    "gn:admin1_code":"13.0",
    "gn:asciiname":"Ban Mai Dai Rang",
    "gn:country_code":"TH",
    "gn:dem":42,
    "gn:feature_class":"P",
    "gn:feature_code":"PPL",
    "gn:name":"Ban Mai Dai Rang",
    "gn:population":0,
    "gn:timezone":"Asia/Bangkok",
    "iso:country":"TH",
    "name:tha_x_preferred":[
        "\u0e1a\u0e49\u0e32\u0e19\u0e43\u0e2b\u0e21\u0e48\u0e44\u0e14\u0e23\u0e31\u0e07"
    ],
    "wof:name":"Ban Mai Dai Rang",
    "wof:placetype":"locality"
},
  "geometry": {"coordinates":[100.55286,15.95069],"type":"Point"}
}