{
  "type": "Feature",
  "properties": {
    "gn:admin1_code":"75.0",
    "gn:asciiname":"Ban Si Bunrueang",
    "gn:country_code":"TH",
    "gn:dem":183,
    "gn:feature_class":"P",
    "gn:feature_code":"PPL",
    "gn:name":"Ban Si Bunrueang",
    "gn:population":0,
    "gn:timezone":"Asia/Bangkok",
    "iso:country":"TH",
    "name:tha_x_preferred":[
        "\u0e1a\u0e49\u0e32\u0e19\u0e28\u0e23\u0e35\u0e1a\u0e38\u0e0d\u0e40\u0e23\u0e37\u0e2d\u0e07"
    ],
    "wof:name":"Ban Si Bunrueang",
    "wof:placetype":"locality"
},
  "geometry": {"coordinates":[104.99397,14.48217],"type":"Point"}
}