{
  "type": "Feature",
  "properties": {
    "gn:admin1_code":"43",
    "gn:asciiname":"Ban Wang Muang",
    "gn:country_code":"TH",
    "gn:dem":44,
    "gn:feature_class":"P",
    "gn:feature_code":"PPL",
    "gn:name":"Ban Wang Muang",
    "gn:population":0,
    "gn:timezone":"Asia/Bangkok",
    "iso:country":"TH",
    "name:tha_x_preferred":[
        "\u0e1a\u0e49\u0e32\u0e19\u0e27\u0e31\u0e07\u0e21\u0e48\u0e27\u0e07"
    ],
    "wof:name":"Ban Wang Muang",
    "wof:placetype":"locality"
},
  "geometry": {"coordinates":[101.34453000000001,14.22697],"type":"Point"}
}