{
  "type": "Feature",
  "properties": {
    "gn:admin1_code":"26.0",
    "gn:asciiname":"Ban Bu Sisiat",
    "gn:country_code":"TH",
    "gn:dem":233,
    "gn:feature_class":"P",
    "gn:feature_code":"PPL",
    "gn:name":"Ban Bu Sisiat",
    "gn:population":0,
    "gn:timezone":"Asia/Bangkok",
    "iso:country":"TH",
    "name:tha_x_preferred":[
        "\u0e1a\u0e49\u0e32\u0e19\u0e1a\u0e38\u0e2a\u0e35\u0e40\u0e2a\u0e35\u0e22\u0e14"
    ],
    "wof:name":"Ban Bu Sisiat",
    "wof:placetype":"locality"
},
  "geometry": {"coordinates":[101.56706,16.02319],"type":"Point"}
}