{
  "type": "Feature",
  "properties": {
    "gn:admin1_code":"30.0",
    "gn:asciiname":"Ban Prasat Yoe Tai",
    "gn:country_code":"TH",
    "gn:dem":142,
    "gn:feature_class":"P",
    "gn:feature_code":"PPL",
    "gn:name":"Ban Prasat Yoe Tai",
    "gn:population":0,
    "gn:timezone":"Asia/Bangkok",
    "iso:country":"TH",
    "name:tha_x_preferred":[
        "\u0e1a\u0e49\u0e32\u0e19\u0e1b\u0e23\u0e32\u0e2a\u0e32\u0e17\u0e40\u0e22\u0e2d\u0e43\u0e15\u0e49"
    ],
    "wof:name":"Ban Prasat Yoe Tai",
    "wof:placetype":"locality"
},
  "geometry": {"coordinates":[104.36620000000001,14.82725],"type":"Point"}
}