{
  "type": "Feature",
  "properties": {
    "gn:admin1_code":"46.0",
    "gn:asciiname":"Ban Noen Hin 1",
    "gn:country_code":"TH",
    "gn:dem":42,
    "gn:feature_class":"P",
    "gn:feature_code":"PPL",
    "gn:name":"Ban Noen Hin 1",
    "gn:population":0,
    "gn:timezone":"Asia/Bangkok",
    "iso:country":"TH",
    "name:tha_x_preferred":[
        "\u0e1a\u0e49\u0e32\u0e19\u0e40\u0e19\u0e34\u0e19\u0e2b\u0e34\u0e19 \u0e2b\u0e19\u0e36\u0e48\u0e07"
    ],
    "name:und_x_variant":[
        "Ban Noen Hin Nueng"
    ],
    "wof:lang_x_official":[
        "tha"
    ],
    "wof:lang_x_spoken":[
        "tha"
    ],
    "wof:name":"Ban Noen Hin 1",
    "wof:placetype":"locality"
},
  "geometry": {"coordinates":[101.29006,13.48928],"type":"Point"}
}