{
  "type": "Feature",
  "properties": {
    "gn:admin1_code":"70.0",
    "gn:asciiname":"Ban Ba Lu Ka",
    "gn:country_code":"TH",
    "gn:dem":35,
    "gn:feature_class":"P",
    "gn:feature_code":"PPL",
    "gn:name":"Ban Ba Lu Ka",
    "gn:population":0,
    "gn:timezone":"Asia/Bangkok",
    "iso:country":"TH",
    "name:tha_x_preferred":[
        "\u0e1a\u0e49\u0e32\u0e19\u0e1a\u0e32\u0e25\u0e39\u0e01\u0e32"
    ],
    "wof:name":"Ban Ba Lu Ka",
    "wof:placetype":"locality"
},
  "geometry": {"coordinates":[101.38078,6.46803],"type":"Point"}
}