{
  "type": "Feature",
  "properties": {
    "gn:admin1_code":"28.0",
    "gn:asciiname":"Ban Kut Khlon",
    "gn:country_code":"TH",
    "gn:dem":146,
    "gn:feature_class":"P",
    "gn:feature_code":"PPL",
    "gn:name":"Ban Kut Khlon",
    "gn:population":0,
    "gn:timezone":"Asia/Bangkok",
    "iso:country":"TH",
    "name:tha_x_preferred":[
        "\u0e1a\u0e49\u0e32\u0e19\u0e01\u0e38\u0e14\u0e42\u0e04\u0e25\u0e19"
    ],
    "wof:name":"Ban Kut Khlon",
    "wof:placetype":"locality"
},
  "geometry": {"coordinates":[103.36353,15.06619],"type":"Point"}
}