{
  "type": "Feature",
  "properties": {
    "gn:admin1_code":"17.0",
    "gn:asciiname":"Ban Tha Chiang Khrua",
    "gn:country_code":"TH",
    "gn:dem":156,
    "gn:feature_class":"P",
    "gn:feature_code":"PPL",
    "gn:name":"Ban Tha Chiang Khrua",
    "gn:population":0,
    "gn:timezone":"Asia/Bangkok",
    "iso:country":"TH",
    "wof:name":"Ban Tha Chiang Khrua",
    "wof:placetype":"locality"
},
  "geometry": {"coordinates":[103.78888999999999,18.04944],"type":"Point"}
}