{
  "type": "Feature",
  "properties": {
    "gn:admin1_code":"28.0",
    "gn:asciiname":"Ban Khok Pradiak",
    "gn:country_code":"TH",
    "gn:dem":167,
    "gn:feature_class":"P",
    "gn:feature_code":"PPL",
    "gn:name":"Ban Khok Pradiak",
    "gn:population":0,
    "gn:timezone":"Asia/Bangkok",
    "iso:country":"TH",
    "name:tha_x_preferred":[
        "\u0e1a\u0e49\u0e32\u0e19\u0e42\u0e04\u0e01\u0e1b\u0e23\u0e30\u0e40\u0e14\u0e35\u0e22\u0e01"
    ],
    "wof:name":"Ban Khok Pradiak",
    "wof:placetype":"locality"
},
  "geometry": {"coordinates":[103.18494,14.57442],"type":"Point"}
}