{
  "type": "Feature",
  "properties": {
    "gn:admin1_code":"44.0",
    "gn:asciiname":"Ban Plaeng Khao Maeo",
    "gn:country_code":"TH",
    "gn:dem":47,
    "gn:feature_class":"P",
    "gn:feature_code":"PPL",
    "gn:name":"Ban Plaeng Khao Maeo",
    "gn:population":0,
    "gn:timezone":"Asia/Bangkok",
    "iso:country":"TH",
    "name:tha_x_preferred":[
        "\u0e1a\u0e49\u0e32\u0e19\u0e41\u0e1b\u0e25\u0e07\u0e40\u0e04\u0e49\u0e32\u0e41\u0e21\u0e27"
    ],
    "wof:name":"Ban Plaeng Khao Maeo",
    "wof:placetype":"locality"
},
  "geometry": {"coordinates":[101.35172,13.56369],"type":"Point"}
}