{
  "type": "Feature",
  "properties": {
    "gn:admin1_code":"69.0",
    "gn:asciiname":"Ban Ka La Kho",
    "gn:country_code":"TH",
    "gn:dem":8,
    "gn:feature_class":"P",
    "gn:feature_code":"PPL",
    "gn:name":"Ban Ka La Kho",
    "gn:population":0,
    "gn:timezone":"Asia/Bangkok",
    "iso:country":"TH",
    "name:tha_x_preferred":[
        "\u0e1a\u0e49\u0e32\u0e19\u0e01\u0e30\u0e25\u0e32\u0e04\u0e2d"
    ],
    "wof:name":"Ban Ka La Kho",
    "wof:placetype":"locality"
},
  "geometry": {"coordinates":[101.33708,6.82383],"type":"Point"}
}