{
  "type": "Feature",
  "properties": {
    "gn:admin1_code":"33",
    "gn:asciiname":"Ban Pho Phan",
    "gn:country_code":"TH",
    "gn:dem":13,
    "gn:feature_class":"P",
    "gn:feature_code":"PPL",
    "gn:name":"Ban Pho Phan",
    "gn:population":0,
    "gn:timezone":"Asia/Bangkok",
    "iso:country":"TH",
    "name:tha_x_preferred":[
        "\u0e1a\u0e49\u0e32\u0e19\u0e42\u0e1e\u0e18\u0e34\u0e4c\u0e1e\u0e31\u0e19\u0e18\u0e38\u0e4c"
    ],
    "wof:name":"Ban Pho Phan",
    "wof:placetype":"locality"
},
  "geometry": {"coordinates":[100.3245,14.85489],"type":"Point"}
}