{
  "type": "Feature",
  "properties": {
    "gn:admin1_code":"13.0",
    "gn:asciiname":"Ban Wang Samrong",
    "gn:country_code":"TH",
    "gn:dem":34,
    "gn:feature_class":"P",
    "gn:feature_code":"PPL",
    "gn:name":"Ban Wang Samrong",
    "gn:population":0,
    "gn:timezone":"Asia/Bangkok",
    "iso:country":"TH",
    "name:tha_x_preferred":[
        "\u0e1a\u0e49\u0e32\u0e19\u0e27\u0e31\u0e07\u0e2a\u0e33\u0e42\u0e23\u0e07"
    ],
    "name:und_x_variant":[
        "B\u0101n Wang Sam Raung",
        "Ban Wang Samrong"
    ],
    "wof:lang_x_official":[
        "tha"
    ],
    "wof:lang_x_spoken":[
        "tha"
    ],
    "wof:name":"Ban Wang Samrong",
    "wof:placetype":"locality"
},
  "geometry": {"coordinates":[100.41586,15.99864],"type":"Point"}
}