{
  "type": "Feature",
  "properties": {
    "gn:admin1_code":"27",
    "gn:asciiname":"Ban Don Makha",
    "gn:country_code":"TH",
    "gn:dem":200,
    "gn:feature_class":"P",
    "gn:feature_code":"PPL",
    "gn:name":"Ban Don Makha",
    "gn:population":0,
    "gn:timezone":"Asia/Bangkok",
    "iso:country":"TH",
    "name:tha_x_preferred":[
        "\u0e1a\u0e49\u0e32\u0e19\u0e14\u0e2d\u0e19\u0e21\u0e30\u0e04\u0e48\u0e32"
    ],
    "wof:name":"Ban Don Makha",
    "wof:placetype":"locality"
},
  "geometry": {"coordinates":[102.06735999999999,15.53539],"type":"Point"}
}