{
  "type": "Feature",
  "properties": {
    "gn:admin1_code":"56.0",
    "gn:asciiname":"Ban Mot Tanoi",
    "gn:country_code":"TH",
    "gn:dem":4,
    "gn:feature_class":"P",
    "gn:feature_code":"PPL",
    "gn:name":"Ban Mot Tanoi",
    "gn:population":0,
    "gn:timezone":"Asia/Bangkok",
    "iso:country":"TH",
    "name:tha_x_preferred":[
        "\u0e1a\u0e49\u0e32\u0e19\u0e21\u0e14\u0e15\u0e30\u0e19\u0e2d\u0e22"
    ],
    "name:und_x_variant":[
        "Ban Don Mot Tanoi"
    ],
    "wof:lang_x_official":[
        "tha"
    ],
    "wof:lang_x_spoken":[
        "tha"
    ],
    "wof:name":"Ban Mot Tanoi",
    "wof:placetype":"locality"
},
  "geometry": {"coordinates":[100.03644,12.99642],"type":"Point"}
}