{
  "type": "Feature",
  "properties": {
    "gn:admin1_code":"31.0",
    "gn:asciiname":"Ban Ba Ngo Mue Lue Ba",
    "gn:country_code":"TH",
    "gn:dem":46,
    "gn:feature_class":"P",
    "gn:feature_code":"PPL",
    "gn:name":"Ban Ba Ngo Mue Lue Ba",
    "gn:population":0,
    "gn:timezone":"Asia/Bangkok",
    "iso:country":"TH",
    "name:tha_x_preferred":[
        "\u0e1a\u0e49\u0e32\u0e19\u0e1a\u0e32\u0e42\u0e07\u0e21\u0e37\u0e2d\u0e25\u0e37\u0e2d\u0e1a\u0e32"
    ],
    "wof:name":"Ban Ba Ngo Mue Lue Ba",
    "wof:placetype":"locality"
},
  "geometry": {"coordinates":[101.53761,6.42428],"type":"Point"}
}