{
  "type": "Feature",
  "properties": {
    "gn:admin1_code":"72.0",
    "gn:asciiname":"Ban Bon",
    "gn:country_code":"TH",
    "gn:dem":130,
    "gn:feature_class":"P",
    "gn:feature_code":"PPL",
    "gn:name":"Ban Bon",
    "gn:population":0,
    "gn:timezone":"Asia/Bangkok",
    "iso:country":"TH",
    "name:tha_x_preferred":[
        "\u0e1a\u0e49\u0e32\u0e19\u0e1a\u0e2d\u0e19"
    ],
    "wof:name":"Ban Bon",
    "wof:placetype":"locality"
},
  "geometry": {"coordinates":[104.34553,15.49064],"type":"Point"}
}