{
  "type": "Feature",
  "properties": {
    "gn:admin1_code":"9.0",
    "gn:asciiname":"Ban Ko Noi Nueng",
    "gn:country_code":"TH",
    "gn:dem":74,
    "gn:feature_class":"P",
    "gn:feature_code":"PPL",
    "gn:name":"Ban Ko Noi Nueng",
    "gn:population":0,
    "gn:timezone":"Asia/Bangkok",
    "iso:country":"TH",
    "name:tha_x_preferred":[
        "\u0e1a\u0e49\u0e32\u0e19\u0e40\u0e01\u0e32\u0e30\u0e19\u0e49\u0e2d\u0e22 \u0e2b\u0e19\u0e36\u0e48\u0e07"
    ],
    "wof:name":"Ban Ko Noi Nueng",
    "wof:placetype":"locality"
},
  "geometry": {"coordinates":[99.76197000000001,17.47894],"type":"Point"}
}