{
  "type": "Feature",
  "properties": {
    "gn:admin1_code":"42.0",
    "gn:asciiname":"Muban Den Chai",
    "gn:country_code":"TH",
    "gn:dem":4,
    "gn:feature_class":"P",
    "gn:feature_code":"PPL",
    "gn:name":"Muban Den Chai",
    "gn:population":0,
    "gn:timezone":"Asia/Bangkok",
    "iso:country":"TH",
    "name:tha_x_preferred":[
        "\u0e2b\u0e21\u0e39\u0e48\u0e1a\u0e49\u0e32\u0e19\u0e40\u0e14\u0e48\u0e19\u0e0a\u0e31\u0e22"
    ],
    "wof:name":"Muban Den Chai",
    "wof:placetype":"locality"
},
  "geometry": {"coordinates":[100.69314,13.57356],"type":"Point"}
}