{
  "type": "Feature",
  "properties": {
    "iso:country":"TH",
    "qs:name":"Yonok",
    "qs:name_adm0":"Thailand",
    "qs:name_adm1":"Chiang Rai",
    "qs:photos":31,
    "qs:photos_1k":6,
    "qs:photos_9k":1,
    "qs:photos_9r":2,
    "qs:photos_all":31,
    "qs:photos_sr":2,
    "qs:placetype":"Town",
    "qs:pop_sr":"0",
    "wof:name":"Yonok",
    "wof:placetype":"locality"
},
  "geometry": {"coordinates":[100.05146000000001,20.262197],"type":"Point"}
}