{
  "type": "Feature",
  "properties": {
    "gn:admin1_code":"16.0",
    "gn:asciiname":"Ban Dong Ta Waen",
    "gn:country_code":"TH",
    "gn:dem":54,
    "gn:feature_class":"P",
    "gn:feature_code":"PPL",
    "gn:name":"Ban Dong Ta Waen",
    "gn:population":0,
    "gn:timezone":"Asia/Bangkok",
    "iso:country":"TH",
    "name:tha_x_preferred":[
        "\u0e1a\u0e49\u0e32\u0e19\u0e14\u0e07\u0e15\u0e32\u0e41\u0e27\u0e19"
    ],
    "wof:name":"Ban Dong Ta Waen",
    "wof:placetype":"locality"
},
  "geometry": {"coordinates":[99.81475,15.70344],"type":"Point"}
}