{
  "type": "Feature",
  "properties": {
    "gn:admin1_code":"44.0",
    "gn:asciiname":"Ban Chak Daeng",
    "gn:country_code":"TH",
    "gn:dem":6,
    "gn:feature_class":"P",
    "gn:feature_code":"PPL",
    "gn:name":"Ban Chak Daeng",
    "gn:population":0,
    "gn:timezone":"Asia/Bangkok",
    "iso:country":"TH",
    "name:tha_x_preferred":[
        "\u0e1a\u0e49\u0e32\u0e19\u0e08\u0e32\u0e01\u0e41\u0e14\u0e07"
    ],
    "wof:name":"Ban Chak Daeng",
    "wof:placetype":"locality"
},
  "geometry": {"coordinates":[101.04411,13.55917],"type":"Point"}
}