{
  "type": "Feature",
  "properties": {
    "gn:admin1_code":"66.0",
    "gn:asciiname":"Ban Khao Phang It",
    "gn:country_code":"TH",
    "gn:dem":18,
    "gn:feature_class":"P",
    "gn:feature_code":"PPL",
    "gn:name":"Ban Khao Phang It",
    "gn:population":0,
    "gn:timezone":"Asia/Bangkok",
    "iso:country":"TH",
    "name:tha_x_preferred":[
        "\u0e1a\u0e49\u0e32\u0e19\u0e40\u0e02\u0e32\u0e1e\u0e31\u0e07\u0e2d\u0e34\u0e10"
    ],
    "wof:name":"Ban Khao Phang It",
    "wof:placetype":"locality"
},
  "geometry": {"coordinates":[99.98917,7.65425],"type":"Point"}
}