{
  "type": "Feature",
  "properties": {
    "gn:admin1_code":"6.0",
    "gn:asciiname":"Ban Pong Kop",
    "gn:country_code":"TH",
    "gn:dem":309,
    "gn:feature_class":"P",
    "gn:feature_code":"PPL",
    "gn:name":"Ban Pong Kop",
    "gn:population":0,
    "gn:timezone":"Asia/Bangkok",
    "iso:country":"TH",
    "name:tha_x_preferred":[
        "\u0e1a\u0e49\u0e32\u0e19\u0e1b\u0e07\u0e01\u0e2d\u0e1a"
    ],
    "name:und_x_variant":[
        "Ban Pong Khrop",
        "B\u0101n Pong Kraup",
        "Ban Pong Khom",
        "Ban Pong Kop"
    ],
    "wof:name":"Ban Pong Kop",
    "wof:placetype":"locality"
},
  "geometry": {"coordinates":[99.5645,18.75939],"type":"Point"}
}