{
  "type": "Feature",
  "properties": {
    "gn:admin1_code":"70.0",
    "gn:asciiname":"Ban Tham Thalu",
    "gn:country_code":"TH",
    "gn:dem":146,
    "gn:feature_class":"P",
    "gn:feature_code":"PPL",
    "gn:name":"Ban Tham Thalu",
    "gn:population":0,
    "gn:timezone":"Asia/Bangkok",
    "iso:country":"TH",
    "name:tha_x_preferred":[
        "\u0e1a\u0e49\u0e32\u0e19\u0e16\u0e49\u0e33\u0e17\u0e30\u0e25\u0e38"
    ],
    "wof:name":"Ban Tham Thalu",
    "wof:placetype":"locality"
},
  "geometry": {"coordinates":[101.16703,6.25831],"type":"Point"}
}