{
  "type": "Feature",
  "properties": {
    "gn:admin1_code":"26.0",
    "gn:asciiname":"Ban Thung Lui Lai",
    "gn:country_code":"TH",
    "gn:dem":572,
    "gn:feature_class":"P",
    "gn:feature_code":"PPL",
    "gn:name":"Ban Thung Lui Lai",
    "gn:population":0,
    "gn:timezone":"Asia/Bangkok",
    "iso:country":"TH",
    "name:tha_x_preferred":[
        "\u0e1a\u0e49\u0e32\u0e19\u0e17\u0e38\u0e48\u0e07\u0e25\u0e38\u0e22\u0e25\u0e32\u0e22"
    ],
    "wof:name":"Ban Thung Lui Lai",
    "wof:placetype":"locality"
},
  "geometry": {"coordinates":[101.74681,16.50062999999999],"type":"Point"}
}