{
  "type": "Feature",
  "properties": {
    "gn:admin1_code":"2.0",
    "gn:asciiname":"Ban Pa Tueng",
    "gn:country_code":"TH",
    "gn:dem":324,
    "gn:feature_class":"P",
    "gn:feature_code":"PPL",
    "gn:name":"Ban Pa Tueng",
    "gn:population":0,
    "gn:timezone":"Asia/Bangkok",
    "iso:country":"TH",
    "name:tha_x_preferred":[
        "\u0e1a\u0e49\u0e32\u0e19\u0e1b\u0e48\u0e32\u0e15\u0e36\u0e07"
    ],
    "name:und_x_variant":[
        "B\u0101n Pa Teung",
        "Ban Pa Tung",
        "Ban Pa Tueng"
    ],
    "wof:name":"Ban Pa Tueng",
    "wof:placetype":"locality"
},
  "geometry": {"coordinates":[99.16889,18.76017],"type":"Point"}
}