{
  "type": "Feature",
  "properties": {
    "gn:admin1_code":"14.0",
    "gn:asciiname":"Ban Sap Poep",
    "gn:country_code":"TH",
    "gn:dem":185,
    "gn:feature_class":"P",
    "gn:feature_code":"PPL",
    "gn:name":"Ban Sap Poep",
    "gn:population":0,
    "gn:timezone":"Asia/Bangkok",
    "iso:country":"TH",
    "name:tha_x_preferred":[
        "\u0e1a\u0e49\u0e32\u0e19\u0e0b\u0e31\u0e1a\u0e40\u0e1b\u0e34\u0e1a"
    ],
    "wof:name":"Ban Sap Poep",
    "wof:placetype":"locality"
},
  "geometry": {"coordinates":[100.93411,16.3515],"type":"Point"}
}