{
  "type": "Feature",
  "properties": {
    "gn:admin1_code":"66.0",
    "gn:asciiname":"Ban Sai Hoi",
    "gn:country_code":"TH",
    "gn:dem":20,
    "gn:feature_class":"P",
    "gn:feature_code":"PPL",
    "gn:name":"Ban Sai Hoi",
    "gn:population":0,
    "gn:timezone":"Asia/Bangkok",
    "iso:country":"TH",
    "name:tha_x_preferred":[
        "\u0e1a\u0e49\u0e32\u0e19\u0e44\u0e17\u0e23\u0e2b\u0e49\u0e2d\u0e22"
    ],
    "wof:name":"Ban Sai Hoi",
    "wof:placetype":"locality"
},
  "geometry": {"coordinates":[100.05880999999999,7.58897],"type":"Point"}
}