{
  "type": "Feature",
  "properties": {
    "gn:admin1_code":"76.0",
    "gn:asciiname":"Ban Nong Sala Din",
    "gn:country_code":"TH",
    "gn:dem":188,
    "gn:feature_class":"P",
    "gn:feature_code":"PPL",
    "gn:name":"Ban Nong Sala Din",
    "gn:population":0,
    "gn:timezone":"Asia/Bangkok",
    "iso:country":"TH",
    "name:tha_x_preferred":[
        "\u0e1a\u0e49\u0e32\u0e19\u0e2b\u0e19\u0e2d\u0e07\u0e28\u0e32\u0e25\u0e32\u0e14\u0e34\u0e19"
    ],
    "wof:name":"Ban Nong Sala Din",
    "wof:placetype":"locality"
},
  "geometry": {"coordinates":[103.13375000000001,17.47939],"type":"Point"}
}