{
  "type": "Feature",
  "properties": {
    "gn:admin1_code":"75.0",
    "gn:asciiname":"Ban Kaeng Ho Trai",
    "gn:country_code":"TH",
    "gn:dem":129,
    "gn:feature_class":"P",
    "gn:feature_code":"PPL",
    "gn:name":"Ban Kaeng Ho Trai",
    "gn:population":0,
    "gn:timezone":"Asia/Bangkok",
    "iso:country":"TH",
    "name:tha_x_preferred":[
        "\u0e1a\u0e49\u0e32\u0e19\u0e41\u0e01\u0e49\u0e07\u0e2b\u0e2d\u0e44\u0e15\u0e23"
    ],
    "wof:name":"Ban Kaeng Ho Trai",
    "wof:placetype":"locality"
},
  "geometry": {"coordinates":[105.06058,15.42919],"type":"Point"}
}