{
  "type": "Feature",
  "properties": {
    "gn:admin1_code":"2.0",
    "gn:asciiname":"Ban Sahakon Plaeng Ha",
    "gn:country_code":"TH",
    "gn:dem":470,
    "gn:feature_class":"P",
    "gn:feature_code":"PPL",
    "gn:name":"Ban Sahakon Plaeng Ha",
    "gn:population":0,
    "gn:timezone":"Asia/Bangkok",
    "iso:country":"TH",
    "name:tha_x_preferred":[
        "\u0e1a\u0e49\u0e32\u0e19\u0e2a\u0e2b\u0e01\u0e23\u0e13\u0e4c\u0e41\u0e1b\u0e25\u0e07 \u0e2b\u0e49\u0e32"
    ],
    "name:und_x_variant":[
        "Ban Sahakon Plaeng 5"
    ],
    "wof:name":"Ban Sahakon Plaeng Ha",
    "wof:placetype":"locality"
},
  "geometry": {"coordinates":[99.23867,19.37619],"type":"Point"}
}