{
  "type": "Feature",
  "properties": {
    "gn:admin1_code":"14.0",
    "gn:asciiname":"Ban Lam Phian",
    "gn:country_code":"TH",
    "gn:dem":94,
    "gn:feature_class":"P",
    "gn:feature_code":"PPL",
    "gn:name":"Ban Lam Phian",
    "gn:population":0,
    "gn:timezone":"Asia/Bangkok",
    "iso:country":"TH",
    "name:tha_x_preferred":[
        "\u0e1a\u0e49\u0e32\u0e19\u0e25\u0e33\u0e40\u0e1e\u0e35\u0e22\u0e23"
    ],
    "wof:name":"Ban Lam Phian",
    "wof:placetype":"locality"
},
  "geometry": {"coordinates":[101.16275,15.77558],"type":"Point"}
}