{
  "type": "Feature",
  "properties": {
    "gn:admin1_code":"2.0",
    "gn:asciiname":"Ban Thi Noe",
    "gn:country_code":"TH",
    "gn:dem":1240,
    "gn:feature_class":"P",
    "gn:feature_code":"PPL",
    "gn:name":"Ban Thi Noe",
    "gn:population":0,
    "gn:timezone":"Asia/Bangkok",
    "iso:country":"TH",
    "name:tha_x_preferred":[
        "\u0e1a\u0e49\u0e32\u0e19\u0e17\u0e35\u0e40\u0e19\u0e2d\u0e30"
    ],
    "wof:name":"Ban Thi Noe",
    "wof:placetype":"locality"
},
  "geometry": {"coordinates":[98.12983,17.82307999999999],"type":"Point"}
}