{
  "type": "Feature",
  "properties": {
    "gn:admin1_code":"58.0",
    "gn:asciiname":"Ban Saphan Sung",
    "gn:country_code":"TH",
    "gn:dem":51,
    "gn:feature_class":"P",
    "gn:feature_code":"PPL",
    "gn:name":"Ban Saphan Sung",
    "gn:population":0,
    "gn:timezone":"Asia/Bangkok",
    "iso:country":"TH",
    "name:tha_x_preferred":[
        "\u0e1a\u0e49\u0e32\u0e19\u0e2a\u0e30\u0e1e\u0e32\u0e19\u0e2a\u0e39\u0e07"
    ],
    "wof:name":"Ban Saphan Sung",
    "wof:placetype":"locality"
},
  "geometry": {"coordinates":[99.04743999999999,10.02069],"type":"Point"}
}