{
  "type": "Feature",
  "properties": {
    "gn:admin1_code":"5.0",
    "gn:asciiname":"Ban Puang Kham",
    "gn:country_code":"TH",
    "gn:dem":462,
    "gn:feature_class":"P",
    "gn:feature_code":"PPL",
    "gn:name":"Ban Puang Kham",
    "gn:population":0,
    "gn:timezone":"Asia/Bangkok",
    "iso:country":"TH",
    "name:tha_x_preferred":[
        "\u0e1a\u0e49\u0e32\u0e19\u0e1b\u0e27\u0e07\u0e04\u0e33"
    ],
    "name:und_x_variant":[
        "Ban Muang Kham",
        "Pong G\u0101m",
        "Ban Muang Dam",
        "Ban Phuang Kham",
        "Ban Puang Kham"
    ],
    "wof:name":"Ban Puang Kham",
    "wof:placetype":"locality"
},
  "geometry": {"coordinates":[98.97989,17.76900000000001],"type":"Point"}
}