{
  "type": "Feature",
  "properties": {
    "gn:admin1_code":"70.0",
    "gn:asciiname":"Ban Yue Nue Re",
    "gn:country_code":"TH",
    "gn:dem":31,
    "gn:feature_class":"P",
    "gn:feature_code":"PPL",
    "gn:name":"Ban Yue Nue Re",
    "gn:population":0,
    "gn:timezone":"Asia/Bangkok",
    "iso:country":"TH",
    "name:tha_x_preferred":[
        "\u0e1a\u0e49\u0e32\u0e19\u0e22\u0e37\u0e2d\u0e19\u0e37\u0e2d\u0e40\u0e23\u0e4a\u0e30"
    ],
    "wof:name":"Ban Yue Nue Re",
    "wof:placetype":"locality"
},
  "geometry": {"coordinates":[101.47825,6.44544],"type":"Point"}
}