{
  "type": "Feature",
  "properties": {
    "gn:admin1_code":"81.0",
    "gn:asciiname":"Ban Tha Chiang Khruea Tai",
    "gn:country_code":"TH",
    "gn:dem":162,
    "gn:feature_class":"P",
    "gn:feature_code":"PPL",
    "gn:name":"Ban Tha Chiang Khruea Tai",
    "gn:population":0,
    "gn:timezone":"Asia/Bangkok",
    "iso:country":"TH",
    "name:tha_x_preferred":[
        "\u0e1a\u0e49\u0e32\u0e19\u0e17\u0e48\u0e32\u0e40\u0e0a\u0e35\u0e22\u0e07\u0e40\u0e04\u0e23\u0e37\u0e2d\u0e43\u0e15\u0e49"
    ],
    "wof:name":"Ban Tha Chiang Khruea Tai",
    "wof:placetype":"locality"
},
  "geometry": {"coordinates":[103.78400000000001,18.05145],"type":"Point"}
}