{
  "type": "Feature",
  "properties": {
    "gn:admin1_code":"4.0",
    "gn:asciiname":"Ban Don Mun",
    "gn:country_code":"TH",
    "gn:dem":394,
    "gn:feature_class":"P",
    "gn:feature_code":"PPL",
    "gn:name":"Ban Don Mun",
    "gn:population":0,
    "gn:timezone":"Asia/Bangkok",
    "iso:country":"TH",
    "name:tha_x_preferred":[
        "\u0e1a\u0e49\u0e32\u0e19\u0e14\u0e2d\u0e19\u0e21\u0e39\u0e25"
    ],
    "wof:name":"Ban Don Mun",
    "wof:placetype":"locality"
},
  "geometry": {"coordinates":[100.63839,18.16669],"type":"Point"}
}