{
  "type": "Feature",
  "properties": {
    "gn:admin1_code":"2.0",
    "gn:asciiname":"Ban Pha Sui",
    "gn:country_code":"TH",
    "gn:dem":1217,
    "gn:feature_class":"P",
    "gn:feature_code":"PPL",
    "gn:name":"Ban Pha Sui",
    "gn:population":0,
    "gn:timezone":"Asia/Bangkok",
    "iso:country":"TH",
    "name:tha_x_preferred":[
        "\u0e1a\u0e49\u0e32\u0e19\u0e1e\u0e30\u0e0b\u0e38\u0e22"
    ],
    "wof:name":"Ban Pha Sui",
    "wof:placetype":"locality"
},
  "geometry": {"coordinates":[98.47127999999999,18.41517],"type":"Point"}
}