{
  "type": "Feature",
  "properties": {
    "gn:admin1_code":"25.0",
    "gn:asciiname":"Ban Du Yai",
    "gn:country_code":"TH",
    "gn:dem":144,
    "gn:feature_class":"P",
    "gn:feature_code":"PPL",
    "gn:name":"Ban Du Yai",
    "gn:population":0,
    "gn:timezone":"Asia/Bangkok",
    "iso:country":"TH",
    "name:tha_x_preferred":[
        "\u0e1a\u0e49\u0e32\u0e19\u0e14\u0e39\u0e48\u0e43\u0e2b\u0e0d\u0e48"
    ],
    "wof:name":"Ban Du Yai",
    "wof:placetype":"locality"
},
  "geometry": {"coordinates":[103.39875000000001,15.69094],"type":"Point"}
}