{
  "type": "Feature",
  "properties": {
    "gn:admin1_code":"60.0",
    "gn:asciiname":"Ban Bang Mo",
    "gn:country_code":"TH",
    "gn:dem":47,
    "gn:feature_class":"P",
    "gn:feature_code":"PPL",
    "gn:name":"Ban Bang Mo",
    "gn:population":0,
    "gn:timezone":"Asia/Bangkok",
    "iso:country":"TH",
    "name:tha_x_preferred":[
        "\u0e1a\u0e49\u0e32\u0e19\u0e1a\u0e32\u0e07\u0e40\u0e21\u0e32\u0e30"
    ],
    "wof:name":"Ban Bang Mo",
    "wof:placetype":"locality"
},
  "geometry": {"coordinates":[98.90769,9.26],"type":"Point"}
}