{
  "type": "Feature",
  "properties": {
    "gn:admin1_code":"41.0",
    "gn:asciiname":"Ban Sak San",
    "gn:country_code":"TH",
    "gn:dem":377,
    "gn:feature_class":"P",
    "gn:feature_code":"PPL",
    "gn:name":"Ban Sak San",
    "gn:population":0,
    "gn:timezone":"Asia/Bangkok",
    "iso:country":"TH",
    "name:tha_x_preferred":[
        "\u0e1a\u0e49\u0e32\u0e19\u0e2a\u0e31\u0e01\u0e2a\u0e31\u0e19"
    ],
    "wof:name":"Ban Sak San",
    "wof:placetype":"locality"
},
  "geometry": {"coordinates":[100.1105,19.51475],"type":"Point"}
}