{
  "type": "Feature",
  "properties": {
    "gn:admin1_code":"70.0",
    "gn:asciiname":"Ban Si Yo",
    "gn:country_code":"TH",
    "gn:dem":47,
    "gn:feature_class":"P",
    "gn:feature_code":"PPL",
    "gn:name":"Ban Si Yo",
    "gn:population":0,
    "gn:timezone":"Asia/Bangkok",
    "iso:country":"TH",
    "name:tha_x_preferred":[
        "\u0e1a\u0e49\u0e32\u0e19\u0e0b\u0e35\u0e40\u0e22\u0e32\u0e30"
    ],
    "wof:name":"Ban Si Yo",
    "wof:placetype":"locality"
},
  "geometry": {"coordinates":[101.15945000000001,6.53033],"type":"Point"}
}