{
  "type": "Feature",
  "properties": {
    "gn:admin1_code":"76.0",
    "gn:asciiname":"Ban Na Ngio",
    "gn:country_code":"TH",
    "gn:dem":177,
    "gn:feature_class":"P",
    "gn:feature_code":"PPL",
    "gn:name":"Ban Na Ngio",
    "gn:population":0,
    "gn:timezone":"Asia/Bangkok",
    "iso:country":"TH",
    "name:tha_x_preferred":[
        "\u0e1a\u0e49\u0e32\u0e19\u0e19\u0e32\u0e07\u0e34\u0e49\u0e27"
    ],
    "wof:name":"Ban Na Ngio",
    "wof:placetype":"locality"
},
  "geometry": {"coordinates":[102.40328,17.81799999999999],"type":"Point"}
}