{
  "type": "Feature",
  "properties": {
    "gn:admin1_code":"14.0",
    "gn:asciiname":"Ban Noen Khontha",
    "gn:country_code":"TH",
    "gn:dem":93,
    "gn:feature_class":"P",
    "gn:feature_code":"PPL",
    "gn:name":"Ban Noen Khontha",
    "gn:population":0,
    "gn:timezone":"Asia/Bangkok",
    "iso:country":"TH",
    "name:tha_x_preferred":[
        "\u0e1a\u0e49\u0e32\u0e19\u0e40\u0e19\u0e34\u0e19\u0e04\u0e19\u0e18\u0e32"
    ],
    "wof:name":"Ban Noen Khontha",
    "wof:placetype":"locality"
},
  "geometry": {"coordinates":[101.15239,15.94283],"type":"Point"}
}