{
  "type": "Feature",
  "properties": {
    "gn:admin1_code":"40.0",
    "gn:admin2_code":"1010",
    "gn:asciiname":"Ban Phai Lueng",
    "gn:country_code":"TH",
    "gn:dem":5,
    "gn:feature_class":"P",
    "gn:feature_code":"PPL",
    "gn:name":"Ban Phai Lueng",
    "gn:population":0,
    "gn:timezone":"Asia/Bangkok",
    "iso:country":"TH",
    "name:tha_x_preferred":[
        "\u0e1a\u0e49\u0e32\u0e19\u0e44\u0e1c\u0e48\u0e40\u0e2b\u0e25\u0e37\u0e2d\u0e07"
    ],
    "wof:name":"Ban Phai Lueng",
    "wof:placetype":"locality"
},
  "geometry": {"coordinates":[100.77442000000001,13.81431],"type":"Point"}
}