{
  "type": "Feature",
  "properties": {
    "gn:admin1_code":"11.0",
    "gn:asciiname":"Ban Mo Charoen",
    "gn:country_code":"TH",
    "gn:dem":102,
    "gn:feature_class":"P",
    "gn:feature_code":"PPL",
    "gn:name":"Ban Mo Charoen",
    "gn:population":0,
    "gn:timezone":"Asia/Bangkok",
    "iso:country":"TH",
    "name:tha_x_preferred":[
        "\u0e1a\u0e49\u0e32\u0e19\u0e21\u0e2d\u0e40\u0e08\u0e23\u0e34\u0e0d"
    ],
    "wof:name":"Ban Mo Charoen",
    "wof:placetype":"locality"
},
  "geometry": {"coordinates":[99.49781,16.23053],"type":"Point"}
}