{
  "type": "Feature",
  "properties": {
    "gn:admin1_code":"27",
    "gn:asciiname":"Ban Sangkhom Mai",
    "gn:country_code":"TH",
    "gn:dem":392,
    "gn:feature_class":"P",
    "gn:feature_code":"PPL",
    "gn:name":"Ban Sangkhom Mai",
    "gn:population":0,
    "gn:timezone":"Asia/Bangkok",
    "iso:country":"TH",
    "name:tha_x_preferred":[
        "\u0e1a\u0e49\u0e32\u0e19\u0e2a\u0e31\u0e07\u0e04\u0e21\u0e43\u0e2b\u0e21\u0e48"
    ],
    "wof:name":"Ban Sangkhom Mai",
    "wof:placetype":"locality"
},
  "geometry": {"coordinates":[101.32061,14.68889],"type":"Point"}
}