{
  "type": "Feature",
  "properties": {
    "gn:admin1_code":"49",
    "gn:asciiname":"Laem Kai Ka",
    "gn:country_code":"TH",
    "gn:dem":5,
    "gn:elevation":"0.0",
    "gn:feature_class":"P",
    "gn:feature_code":"PPL",
    "gn:name":"Laem Kai Ka",
    "gn:population":0,
    "gn:timezone":"Asia/Bangkok",
    "iso:country":"TH",
    "wof:name":"Laem Kai Ka",
    "wof:placetype":"locality"
},
  "geometry": {"coordinates":[102.39847,11.98576],"type":"Point"}
}