{
  "type": "Feature",
  "properties": {
    "gn:admin1_code":"24.0",
    "gn:asciiname":"Ban Kham Pia",
    "gn:country_code":"TH",
    "gn:dem":160,
    "gn:feature_class":"P",
    "gn:feature_code":"PPL",
    "gn:name":"Ban Kham Pia",
    "gn:population":0,
    "gn:timezone":"Asia/Bangkok",
    "iso:country":"TH",
    "name:tha_x_preferred":[
        "\u0e1a\u0e49\u0e32\u0e19\u0e02\u0e32\u0e21\u0e40\u0e1b\u0e35\u0e49\u0e22"
    ],
    "wof:name":"Ban Kham Pia",
    "wof:placetype":"locality"
},
  "geometry": {"coordinates":[103.00091,16.44339],"type":"Point"}
}