{
  "type": "Feature",
  "properties": {
    "gn:admin1_code":"65.0",
    "gn:asciiname":"Ban La Mo",
    "gn:country_code":"TH",
    "gn:dem":48,
    "gn:feature_class":"P",
    "gn:feature_code":"PPL",
    "gn:name":"Ban La Mo",
    "gn:population":0,
    "gn:timezone":"Asia/Bangkok",
    "iso:country":"TH",
    "name:tha_x_preferred":[
        "\u0e1a\u0e49\u0e32\u0e19\u0e25\u0e30\u0e21\u0e2d"
    ],
    "name:und_x_variant":[
        "Ban La-Mo (1)"
    ],
    "wof:lang_x_official":[
        "tha"
    ],
    "wof:lang_x_spoken":[
        "tha"
    ],
    "wof:name":"Ban La Mo",
    "wof:placetype":"locality"
},
  "geometry": {"coordinates":[99.73878000000001,7.56519],"type":"Point"}
}