{
  "type": "Feature",
  "properties": {
    "gn:admin1_code":"27",
    "gn:asciiname":"Ban Samakkhi Phatthana",
    "gn:country_code":"TH",
    "gn:dem":217,
    "gn:feature_class":"P",
    "gn:feature_code":"PPL",
    "gn:name":"Ban Samakkhi Phatthana",
    "gn:population":0,
    "gn:timezone":"Asia/Bangkok",
    "iso:country":"TH",
    "name:tha_x_preferred":[
        "\u0e1a\u0e49\u0e32\u0e19\u0e2a\u0e32\u0e21\u0e31\u0e04\u0e04\u0e35\u0e1e\u0e31\u0e12\u0e19\u0e32"
    ],
    "wof:lang_x_official":[
        "tha"
    ],
    "wof:lang_x_spoken":[
        "tha"
    ],
    "wof:name":"Ban Samakkhi Phatthana",
    "wof:placetype":"locality"
},
  "geometry": {"coordinates":[102.17444,15.53858],"type":"Point"}
}