{
  "type": "Feature",
  "properties": {
    "gn:admin1_code":"8.0",
    "gn:asciiname":"Ban Lan Sang",
    "gn:country_code":"TH",
    "gn:dem":182,
    "gn:feature_class":"P",
    "gn:feature_code":"PPL",
    "gn:name":"Ban Lan Sang",
    "gn:population":0,
    "gn:timezone":"Asia/Bangkok",
    "iso:country":"TH",
    "name:tha_x_preferred":[
        "\u0e1a\u0e49\u0e32\u0e19\u0e25\u0e32\u0e19\u0e2a\u0e32\u0e07"
    ],
    "wof:name":"Ban Lan Sang",
    "wof:placetype":"locality"
},
  "geometry": {"coordinates":[98.99017000000001,16.83275],"type":"Point"}
}