{
  "type": "Feature",
  "properties": {
    "gn:admin1_code":"25",
    "gn:asciiname":"Wat Buppharam",
    "gn:country_code":"TH",
    "gn:dem":167,
    "gn:feature_class":"P",
    "gn:feature_code":"PPL",
    "gn:name":"Wat Buppharam",
    "gn:population":0,
    "gn:timezone":"Asia/Bangkok",
    "iso:country":"TH",
    "name:nld_x_preferred":[
        "Wat Buppharam"
    ],
    "name:tha_x_preferred":[
        "\u0e27\u0e31\u0e14\u0e1a\u0e38\u0e1b\u0e1c\u0e32\u0e23\u0e32\u0e21"
    ],
    "wof:name":"Wat Buppharam",
    "wof:placetype":"locality"
},
  "geometry": {"coordinates":[104.13298,16.33852000000001],"type":"Point"}
}