{
  "type": "Feature",
  "properties": {
    "gn:admin1_code":"65.0",
    "gn:asciiname":"Ban Nong Wa",
    "gn:country_code":"TH",
    "gn:dem":24,
    "gn:feature_class":"P",
    "gn:feature_code":"PPL",
    "gn:name":"Ban Nong Wa",
    "gn:population":0,
    "gn:timezone":"Asia/Bangkok",
    "iso:country":"TH",
    "name:tha_x_preferred":[
        "\u0e1a\u0e49\u0e32\u0e19\u0e2b\u0e19\u0e2d\u0e07\u0e2b\u0e27\u0e49\u0e32"
    ],
    "name:und_x_variant":[
        "Ban Nong Wa (1)"
    ],
    "wof:name":"Ban Nong Wa",
    "wof:placetype":"locality"
},
  "geometry": {"coordinates":[99.76653,7.23606],"type":"Point"}
}