{
  "type": "Feature",
  "properties": {
    "gn:admin1_code":"64.0",
    "gn:asciiname":"Ban Noen Thammang",
    "gn:country_code":"TH",
    "gn:dem":5,
    "gn:feature_class":"P",
    "gn:feature_code":"PPL",
    "gn:name":"Ban Noen Thammang",
    "gn:population":0,
    "gn:timezone":"Asia/Bangkok",
    "iso:country":"TH",
    "name:tha_x_preferred":[
        "\u0e1a\u0e49\u0e32\u0e19\u0e40\u0e19\u0e34\u0e19\u0e18\u0e31\u0e21\u0e21\u0e31\u0e07"
    ],
    "wof:name":"Ban Noen Thammang",
    "wof:placetype":"locality"
},
  "geometry": {"coordinates":[100.05717,8.02128],"type":"Point"}
}