{
  "type": "Feature",
  "properties": {
    "gn:admin1_code":"44.0",
    "gn:asciiname":"Ban Nong Sakae",
    "gn:country_code":"TH",
    "gn:dem":54,
    "gn:feature_class":"P",
    "gn:feature_code":"PPL",
    "gn:name":"Ban Nong Sakae",
    "gn:population":0,
    "gn:timezone":"Asia/Bangkok",
    "iso:country":"TH",
    "name:tha_x_preferred":[
        "\u0e1a\u0e49\u0e32\u0e19\u0e2b\u0e19\u0e2d\u0e07\u0e2a\u0e30\u0e41\u0e01"
    ],
    "wof:name":"Ban Nong Sakae",
    "wof:placetype":"locality"
},
  "geometry": {"coordinates":[101.76775000000001,13.76267],"type":"Point"}
}