{
  "type": "Feature",
  "properties": {
    "gn:admin1_code":"76.0",
    "gn:asciiname":"Ban Hin Loeng",
    "gn:country_code":"TH",
    "gn:dem":221,
    "gn:feature_class":"P",
    "gn:feature_code":"PPL",
    "gn:name":"Ban Hin Loeng",
    "gn:population":0,
    "gn:timezone":"Asia/Bangkok",
    "iso:country":"TH",
    "name:tha_x_preferred":[
        "\u0e1a\u0e49\u0e32\u0e19\u0e2b\u0e34\u0e19\u0e40\u0e2b\u0e25\u0e34\u0e48\u0e07"
    ],
    "wof:name":"Ban Hin Loeng",
    "wof:placetype":"locality"
},
  "geometry": {"coordinates":[103.12564,17.08006],"type":"Point"}
}