{
  "type": "Feature",
  "properties": {
    "gn:admin1_code":"4.0",
    "gn:asciiname":"Ban Den Thara",
    "gn:country_code":"TH",
    "gn:dem":325,
    "gn:feature_class":"P",
    "gn:feature_code":"PPL",
    "gn:name":"Ban Den Thara",
    "gn:population":0,
    "gn:timezone":"Asia/Bangkok",
    "iso:country":"TH",
    "name:tha_x_preferred":[
        "\u0e1a\u0e49\u0e32\u0e19\u0e40\u0e14\u0e48\u0e19\u0e18\u0e32\u0e23\u0e32"
    ],
    "wof:name":"Ban Den Thara",
    "wof:placetype":"locality"
},
  "geometry": {"coordinates":[100.90194,19.32461],"type":"Point"}
}