{
  "type": "Feature",
  "properties": {
    "gn:admin1_code":"74.0",
    "gn:asciiname":"Ban Nam Cha",
    "gn:country_code":"TH",
    "gn:dem":13,
    "gn:feature_class":"P",
    "gn:feature_code":"PPL",
    "gn:name":"Ban Nam Cha",
    "gn:population":0,
    "gn:timezone":"Asia/Bangkok",
    "iso:country":"TH",
    "name:tha_x_preferred":[
        "\u0e1a\u0e49\u0e32\u0e19\u0e19\u0e49\u0e33\u0e09\u0e48\u0e32"
    ],
    "name:und_x_variant":[
        "Ban Nam Cha (1)"
    ],
    "wof:name":"Ban Nam Cha",
    "wof:placetype":"locality"
},
  "geometry": {"coordinates":[101.64539000000001,13.9745],"type":"Point"}
}