{
  "type": "Feature",
  "properties": {
    "gn:admin1_code":"6.0",
    "gn:asciiname":"Ban Sam Kha",
    "gn:country_code":"TH",
    "gn:dem":355,
    "gn:feature_class":"P",
    "gn:feature_code":"PPL",
    "gn:name":"Ban Sam Kha",
    "gn:population":0,
    "gn:timezone":"Asia/Bangkok",
    "iso:country":"TH",
    "name:tha_x_preferred":[
        "\u0e1a\u0e49\u0e32\u0e19\u0e2a\u0e32\u0e21\u0e02\u0e32"
    ],
    "name:und_x_variant":[
        "B\u0101n S\u0101m Ka",
        "Ban Sam Kha"
    ],
    "wof:lang_x_official":[
        "tha"
    ],
    "wof:lang_x_spoken":[
        "tha"
    ],
    "wof:name":"Ban Sam Kha",
    "wof:placetype":"locality"
},
  "geometry": {"coordinates":[99.70044,18.1245],"type":"Point"}
}