{
  "type": "Feature",
  "properties": {
    "gn:admin1_code":"4.0",
    "gn:asciiname":"Ban Fueai Lung",
    "gn:country_code":"TH",
    "gn:dem":322,
    "gn:feature_class":"P",
    "gn:feature_code":"PPL",
    "gn:name":"Ban Fueai Lung",
    "gn:population":0,
    "gn:timezone":"Asia/Bangkok",
    "iso:country":"TH",
    "name:tha_x_preferred":[
        "\u0e1a\u0e49\u0e32\u0e19\u0e40\u0e1f\u0e37\u0e2d\u0e22\u0e25\u0e38\u0e07"
    ],
    "wof:name":"Ban Fueai Lung",
    "wof:placetype":"locality"
},
  "geometry": {"coordinates":[100.88256,19.40944],"type":"Point"}
}