{
  "type": "Feature",
  "properties": {
    "gn:admin1_code":"4.0",
    "gn:asciiname":"Ban Nam Phang Noi",
    "gn:country_code":"TH",
    "gn:dem":1149,
    "gn:feature_class":"P",
    "gn:feature_code":"PPL",
    "gn:name":"Ban Nam Phang Noi",
    "gn:population":0,
    "gn:timezone":"Asia/Bangkok",
    "iso:country":"TH",
    "wof:name":"Ban Nam Phang Noi",
    "wof:placetype":"locality"
},
  "geometry": {"coordinates":[101.09999999999999,18.58333],"type":"Point"}
}