{
  "type": "Feature",
  "properties": {
    "gn:admin1_code":"53.0",
    "gn:asciiname":"Ban Khlong Chai Khan",
    "gn:country_code":"TH",
    "gn:dem":5,
    "gn:feature_class":"P",
    "gn:feature_code":"PPL",
    "gn:name":"Ban Khlong Chai Khan",
    "gn:population":0,
    "gn:timezone":"Asia/Bangkok",
    "iso:country":"TH",
    "name:tha_x_preferred":[
        "\u0e1a\u0e49\u0e32\u0e19\u0e04\u0e25\u0e2d\u0e07\u0e0a\u0e31\u0e22\u0e02\u0e31\u0e19\u0e18\u0e4c"
    ],
    "wof:name":"Ban Khlong Chai Khan",
    "wof:placetype":"locality"
},
  "geometry": {"coordinates":[100.26506000000001,13.869],"type":"Point"}
}