{
  "type": "Feature",
  "properties": {
    "gn:admin1_code":"28",
    "gn:asciiname":"Ban Sadao Wan",
    "gn:country_code":"TH",
    "gn:dem":211,
    "gn:feature_class":"P",
    "gn:feature_code":"PPL",
    "gn:name":"Ban Sadao Wan",
    "gn:population":0,
    "gn:timezone":"Asia/Bangkok",
    "iso:country":"TH",
    "name:tha_x_preferred":[
        "\u0e1a\u0e49\u0e32\u0e19\u0e2a\u0e30\u0e40\u0e14\u0e32\u0e2b\u0e27\u0e32\u0e19"
    ],
    "wof:name":"Ban Sadao Wan",
    "wof:placetype":"locality"
},
  "geometry": {"coordinates":[102.58975,14.82258],"type":"Point"}
}