{
  "type": "Feature",
  "properties": {
    "gn:admin1_code":"79.0",
    "gn:asciiname":"Ban Na Chum Saeng",
    "gn:country_code":"TH",
    "gn:dem":266,
    "gn:feature_class":"P",
    "gn:feature_code":"PPL",
    "gn:name":"Ban Na Chum Saeng",
    "gn:population":0,
    "gn:timezone":"Asia/Bangkok",
    "iso:country":"TH",
    "name:tha_x_preferred":[
        "\u0e1a\u0e49\u0e32\u0e19\u0e19\u0e32\u0e0a\u0e38\u0e21\u0e41\u0e2a\u0e07"
    ],
    "name:und_x_variant":[
        "Ban Na Sam Saeng"
    ],
    "wof:name":"Ban Na Chum Saeng",
    "wof:placetype":"locality"
},
  "geometry": {"coordinates":[102.09569,17.32069],"type":"Point"}
}