{
  "type": "Feature",
  "properties": {
    "gn:admin1_code":"13.0",
    "gn:asciiname":"Ban Pong Phai",
    "gn:country_code":"TH",
    "gn:dem":58,
    "gn:feature_class":"P",
    "gn:feature_code":"PPL",
    "gn:name":"Ban Pong Phai",
    "gn:population":0,
    "gn:timezone":"Asia/Bangkok",
    "iso:country":"TH",
    "name:tha_x_preferred":[
        "\u0e1a\u0e49\u0e32\u0e19\u0e42\u0e1b\u0e48\u0e07\u0e44\u0e1c\u0e48"
    ],
    "wof:name":"Ban Pong Phai",
    "wof:placetype":"locality"
},
  "geometry": {"coordinates":[100.59492,16.536],"type":"Point"}
}