{
  "type": "Feature",
  "properties": {
    "gn:country":"TH",
    "gn:fcode":"PPL",
    "gn:population":0,
    "iso:country":"TH",
    "name:tha_x_preferred":[
        "\u0e1a\u0e49\u0e32\u0e19\u0e1a\u0e32\u0e07\u0e25\u0e32\u0e22"
    ],
    "name:und_x_variant":[
        "Bang Lai"
    ],
    "qs:name":"Ban Bang Lai (1)",
    "qs:name_adm0":"Thailand",
    "qs:name_adm1":"Phichit",
    "qs:photos_9r":0,
    "qs:photos_sr":0,
    "qs:placetype":"Town",
    "qs:pop_sr":"0",
    "wof:name":"Ban Bang Lai (1)",
    "wof:placetype":"locality",
    "wof:population":0
},
  "geometry": {"coordinates":[100.23022,16.19772],"type":"Point"}
}