{
  "type": "Feature",
  "properties": {
    "gn:admin1_code":"17.0",
    "gn:asciiname":"Nong Khiaw",
    "gn:country_code":"TH",
    "gn:dem":171,
    "gn:feature_class":"P",
    "gn:feature_code":"PPL",
    "gn:name":"Nong Khiaw",
    "gn:population":0,
    "gn:timezone":"Asia/Bangkok",
    "iso:country":"TH",
    "name:jpn_x_preferred":[
        "\u30ce\u30fc\u30f3\u30ad\u30e3\u30a6"
    ],
    "wof:lang_x_official":[
        "tha"
    ],
    "wof:lang_x_spoken":[
        "tha"
    ],
    "wof:name":"Nong Khiaw",
    "wof:placetype":"locality"
},
  "geometry": {"coordinates":[102.7466,17.88411],"type":"Point"}
}