{
  "type": "Feature",
  "properties": {
    "gn:admin1_code":"12.0",
    "gn:asciiname":"Ban Na Man",
    "gn:country_code":"TH",
    "gn:dem":48,
    "gn:feature_class":"P",
    "gn:feature_code":"PPL",
    "gn:name":"Ban Na Man",
    "gn:population":0,
    "gn:timezone":"Asia/Bangkok",
    "iso:country":"TH",
    "name:tha_x_preferred":[
        "\u0e1a\u0e49\u0e32\u0e19\u0e19\u0e32\u0e2b\u0e21\u0e31\u0e19"
    ],
    "wof:name":"Ban Na Man",
    "wof:placetype":"locality"
},
  "geometry": {"coordinates":[100.07189,16.66722],"type":"Point"}
}