{
  "type": "Feature",
  "properties": {
    "gn:admin1_code":"27",
    "gn:asciiname":"Ban Talat Non Ta Then",
    "gn:country_code":"TH",
    "gn:dem":159,
    "gn:feature_class":"P",
    "gn:feature_code":"PPL",
    "gn:name":"Ban Talat Non Ta Then",
    "gn:population":0,
    "gn:timezone":"Asia/Bangkok",
    "iso:country":"TH",
    "name:tha_x_preferred":[
        "\u0e1a\u0e49\u0e32\u0e19\u0e15\u0e25\u0e32\u0e14\u0e42\u0e19\u0e19\u0e15\u0e32\u0e40\u0e16\u0e23"
    ],
    "wof:name":"Ban Talat Non Ta Then",
    "wof:placetype":"locality"
},
  "geometry": {"coordinates":[102.50144,15.46303],"type":"Point"}
}