{
  "type": "Feature",
  "properties": {
    "gn:admin1_code":"60.0",
    "gn:asciiname":"Ban Tha Mai",
    "gn:country_code":"TH",
    "gn:dem":278,
    "gn:feature_class":"P",
    "gn:feature_code":"PPL",
    "gn:name":"Ban Tha Mai",
    "gn:population":0,
    "gn:timezone":"Asia/Bangkok",
    "iso:country":"TH",
    "name:tha_x_preferred":[
        "\u0e1a\u0e49\u0e32\u0e19\u0e17\u0e48\u0e32\u0e43\u0e2b\u0e21\u0e48"
    ],
    "wof:name":"Ban Tha Mai",
    "wof:placetype":"locality"
},
  "geometry": {"coordinates":[98.86333,9.50964],"type":"Point"}
}