{
  "type": "Feature",
  "properties": {
    "gn:admin1_code":"3.0",
    "gn:asciiname":"Ban Pang Khon",
    "gn:country_code":"TH",
    "gn:dem":1248,
    "gn:feature_class":"P",
    "gn:feature_code":"PPL",
    "gn:name":"Ban Pang Khon",
    "gn:population":0,
    "gn:timezone":"Asia/Bangkok",
    "iso:country":"TH",
    "name:tha_x_preferred":[
        "\u0e1a\u0e49\u0e32\u0e19\u0e1b\u0e32\u0e07\u0e02\u0e2d\u0e19"
    ],
    "wof:name":"Ban Pang Khon",
    "wof:placetype":"locality"
},
  "geometry": {"coordinates":[99.61731,19.89917],"type":"Point"}
}