{
  "type": "Feature",
  "properties": {
    "gn:admin1_code":"48.0",
    "gn:asciiname":"Ban Chanthakhlem",
    "gn:country_code":"TH",
    "gn:dem":64,
    "gn:feature_class":"P",
    "gn:feature_code":"PPL",
    "gn:name":"Ban Chanthakhlem",
    "gn:population":0,
    "gn:timezone":"Asia/Bangkok",
    "iso:country":"TH",
    "name:tha_x_preferred":[
        "\u0e1a\u0e49\u0e32\u0e19\u0e08\u0e31\u0e19\u0e17\u0e40\u0e02\u0e25\u0e21"
    ],
    "name:und_x_variant":[
        "Ban Chan Khrem"
    ],
    "wof:name":"Ban Chanthakhlem",
    "wof:placetype":"locality"
},
  "geometry": {"coordinates":[102.05389,13.00736],"type":"Point"}
}