{
  "type": "Feature",
  "properties": {
    "gn:admin1_code":"48.0",
    "gn:asciiname":"Ban Khao Sompoi",
    "gn:country_code":"TH",
    "gn:dem":38,
    "gn:feature_class":"P",
    "gn:feature_code":"PPL",
    "gn:name":"Ban Khao Sompoi",
    "gn:population":0,
    "gn:timezone":"Asia/Bangkok",
    "iso:country":"TH",
    "name:tha_x_preferred":[
        "\u0e1a\u0e49\u0e32\u0e19\u0e40\u0e02\u0e32\u0e2a\u0e49\u0e21\u0e1b\u0e48\u0e2d\u0e22"
    ],
    "wof:name":"Ban Khao Sompoi",
    "wof:placetype":"locality"
},
  "geometry": {"coordinates":[101.92341999999999,13.03381],"type":"Point"}
}