{
  "type": "Feature",
  "properties": {
    "gn:admin1_code":"52.0",
    "gn:asciiname":"Ban Rang Bot",
    "gn:country_code":"TH",
    "gn:dem":6,
    "gn:feature_class":"P",
    "gn:feature_code":"PPL",
    "gn:name":"Ban Rang Bot",
    "gn:population":0,
    "gn:timezone":"Asia/Bangkok",
    "iso:country":"TH",
    "name:tha_x_preferred":[
        "\u0e1a\u0e49\u0e32\u0e19\u0e23\u0e32\u0e07\u0e42\u0e1a\u0e2a\u0e16\u0e4c"
    ],
    "wof:name":"Ban Rang Bot",
    "wof:placetype":"locality"
},
  "geometry": {"coordinates":[99.79703000000001,13.38003],"type":"Point"}
}