{
  "type": "Feature",
  "properties": {
    "gn:admin1_code":"16.0",
    "gn:asciiname":"Ban Nikhom Khao Bo Kaeo",
    "gn:country_code":"TH",
    "gn:dem":59,
    "gn:feature_class":"P",
    "gn:feature_code":"PPL",
    "gn:name":"Ban Nikhom Khao Bo Kaeo",
    "gn:population":0,
    "gn:timezone":"Asia/Bangkok",
    "iso:country":"TH",
    "name:tha_x_preferred":[
        "\u0e1a\u0e49\u0e32\u0e19\u0e19\u0e34\u0e04\u0e21\u0e40\u0e02\u0e32\u0e1a\u0e48\u0e2d\u0e41\u0e01\u0e49\u0e27"
    ],
    "name:und_x_variant":[
        "Ban Nikhom Sang Ton Eng Khao Bo Kaeo"
    ],
    "wof:name":"Ban Nikhom Khao Bo Kaeo",
    "wof:placetype":"locality"
},
  "geometry": {"coordinates":[100.22302999999999,15.47014],"type":"Point"}
}