{
  "type": "Feature",
  "properties": {
    "gn:admin1_code":"69.0",
    "gn:asciiname":"Ban Lu Bo Mala",
    "gn:country_code":"TH",
    "gn:dem":16,
    "gn:feature_class":"P",
    "gn:feature_code":"PPL",
    "gn:name":"Ban Lu Bo Mala",
    "gn:population":0,
    "gn:timezone":"Asia/Bangkok",
    "iso:country":"TH",
    "name:tha_x_preferred":[
        "\u0e1a\u0e49\u0e32\u0e19\u0e25\u0e39\u0e42\u0e1a\u0e30\u0e21\u0e32\u0e25\u0e32"
    ],
    "wof:name":"Ban Lu Bo Mala",
    "wof:placetype":"locality"
},
  "geometry": {"coordinates":[101.32889,6.6205],"type":"Point"}
}