{
  "type": "Feature",
  "properties": {
    "gn:admin1_code":"65.0",
    "gn:asciiname":"Ban Na To Khem",
    "gn:country_code":"TH",
    "gn:dem":24,
    "gn:feature_class":"P",
    "gn:feature_code":"PPL",
    "gn:name":"Ban Na To Khem",
    "gn:population":0,
    "gn:timezone":"Asia/Bangkok",
    "iso:country":"TH",
    "name:tha_x_preferred":[
        "\u0e1a\u0e49\u0e32\u0e19\u0e19\u0e32\u0e42\u0e15\u0e4a\u0e30\u0e40\u0e04\u0e47\u0e21"
    ],
    "wof:name":"Ban Na To Khem",
    "wof:placetype":"locality"
},
  "geometry": {"coordinates":[99.67872,7.40519],"type":"Point"}
}