{
  "type": "Feature",
  "properties": {
    "gn:admin1_code":"12.0",
    "gn:asciiname":"Ban Chung Nang",
    "gn:country_code":"TH",
    "gn:dem":50,
    "gn:feature_class":"P",
    "gn:feature_code":"PPL",
    "gn:name":"Ban Chung Nang",
    "gn:population":0,
    "gn:timezone":"Asia/Bangkok",
    "iso:country":"TH",
    "name:tha_x_preferred":[
        "\u0e1a\u0e49\u0e32\u0e19\u0e08\u0e39\u0e07\u0e19\u0e32\u0e07"
    ],
    "wof:name":"Ban Chung Nang",
    "wof:placetype":"locality"
},
  "geometry": {"coordinates":[100.20766999999999,16.78806],"type":"Point"}
}