{
  "type": "Feature",
  "properties": {
    "gn:admin1_code":"27.0",
    "gn:asciiname":"Ban Non Kham",
    "gn:country_code":"TH",
    "gn:dem":146,
    "gn:feature_class":"P",
    "gn:feature_code":"PPL",
    "gn:name":"Ban Non Kham",
    "gn:population":0,
    "gn:timezone":"Asia/Bangkok",
    "iso:country":"TH",
    "name:tha_x_preferred":[
        "\u0e1a\u0e49\u0e32\u0e19\u0e42\u0e19\u0e19\u0e02\u0e32\u0e21"
    ],
    "name:und_x_variant":[
        "Ban Kham",
        "Ban Non Kham"
    ],
    "wof:name":"Ban Non Kham",
    "wof:placetype":"locality"
},
  "geometry": {"coordinates":[102.83638999999999,15.41236],"type":"Point"}
}