{
  "type": "Feature",
  "properties": {
    "gn:admin1_code":"50.0",
    "gn:asciiname":"Ban Surasi",
    "gn:country_code":"TH",
    "gn:dem":54,
    "gn:feature_class":"P",
    "gn:feature_code":"PPL",
    "gn:name":"Ban Surasi",
    "gn:population":0,
    "gn:timezone":"Asia/Bangkok",
    "iso:country":"TH",
    "name:tha_x_preferred":[
        "\u0e1a\u0e49\u0e32\u0e19\u0e2a\u0e38\u0e23\u0e2a\u0e35\u0e2b\u0e4c"
    ],
    "wof:name":"Ban Surasi",
    "wof:placetype":"locality"
},
  "geometry": {"coordinates":[99.26318999999999,14.16961],"type":"Point"}
}