{
  "type": "Feature",
  "properties": {
    "gn:admin1_code":"4.0",
    "gn:asciiname":"Ban Salai Noi",
    "gn:country_code":"TH",
    "gn:dem":1071,
    "gn:feature_class":"P",
    "gn:feature_code":"PPL",
    "gn:name":"Ban Salai Noi",
    "gn:population":0,
    "gn:timezone":"Asia/Bangkok",
    "iso:country":"TH",
    "name:tha_x_preferred":[
        "\u0e1a\u0e49\u0e32\u0e19\u0e2a\u0e44\u0e25\u0e19\u0e49\u0e2d\u0e22"
    ],
    "wof:name":"Ban Salai Noi",
    "wof:placetype":"locality"
},
  "geometry": {"coordinates":[101.17778,19.32836],"type":"Point"}
}