{
  "type": "Feature",
  "properties": {
    "gn:admin1_code":"47.0",
    "gn:asciiname":"Ban Pho Than",
    "gn:country_code":"TH",
    "gn:dem":12,
    "gn:feature_class":"P",
    "gn:feature_code":"PPL",
    "gn:name":"Ban Pho Than",
    "gn:population":0,
    "gn:timezone":"Asia/Bangkok",
    "iso:country":"TH",
    "name:tha_x_preferred":[
        "\u0e1a\u0e49\u0e32\u0e19\u0e42\u0e1e\u0e18\u0e34\u0e4c\u0e10\u0e32\u0e19"
    ],
    "wof:name":"Ban Pho Than",
    "wof:placetype":"locality"
},
  "geometry": {"coordinates":[101.745,12.79917],"type":"Point"}
}