{
  "type": "Feature",
  "properties": {
    "gn:admin1_code":"75.0",
    "gn:asciiname":"Ban Don Nam Kliang",
    "gn:country_code":"TH",
    "gn:dem":188,
    "gn:feature_class":"P",
    "gn:feature_code":"PPL",
    "gn:name":"Ban Don Nam Kliang",
    "gn:population":0,
    "gn:timezone":"Asia/Bangkok",
    "iso:country":"TH",
    "name:tha_x_preferred":[
        "\u0e1a\u0e49\u0e32\u0e19\u0e14\u0e2d\u0e19\u0e19\u0e49\u0e33\u0e40\u0e01\u0e25\u0e35\u0e49\u0e22\u0e07"
    ],
    "wof:name":"Ban Don Nam Kliang",
    "wof:placetype":"locality"
},
  "geometry": {"coordinates":[105.21193999999998,15.79525],"type":"Point"}
}