{
  "type": "Feature",
  "properties": {
    "gn:admin1_code":"26.0",
    "gn:asciiname":"Ban Na Sida",
    "gn:country_code":"TH",
    "gn:dem":273,
    "gn:feature_class":"P",
    "gn:feature_code":"PPL",
    "gn:name":"Ban Na Sida",
    "gn:population":0,
    "gn:timezone":"Asia/Bangkok",
    "iso:country":"TH",
    "name:tha_x_preferred":[
        "\u0e1a\u0e49\u0e32\u0e19\u0e19\u0e32\u0e2a\u0e35\u0e14\u0e32"
    ],
    "wof:name":"Ban Na Sida",
    "wof:placetype":"locality"
},
  "geometry": {"coordinates":[101.8875,16.09769],"type":"Point"}
}