{
  "type": "Feature",
  "properties": {
    "gn:admin1_code":"48.0",
    "gn:asciiname":"Ban Yaek Khuean Siri Than",
    "gn:country_code":"TH",
    "gn:dem":24,
    "gn:feature_class":"P",
    "gn:feature_code":"PPL",
    "gn:name":"Ban Yaek Khuean Siri Than",
    "gn:population":0,
    "gn:timezone":"Asia/Bangkok",
    "iso:country":"TH",
    "name:tha_x_preferred":[
        "\u0e1a\u0e49\u0e32\u0e19\u0e41\u0e22\u0e01\u0e40\u0e02\u0e37\u0e48\u0e2d\u0e19\u0e28\u0e34\u0e23\u0e34\u0e18\u0e32\u0e23"
    ],
    "wof:name":"Ban Yaek Khuean Siri Than",
    "wof:placetype":"locality"
},
  "geometry": {"coordinates":[102.24353000000001,12.76464],"type":"Point"}
}