{
  "type": "Feature",
  "properties": {
    "gn:admin1_code":"6.0",
    "gn:asciiname":"Ban Mae Mok Klang",
    "gn:country_code":"TH",
    "gn:dem":306,
    "gn:feature_class":"P",
    "gn:feature_code":"PPL",
    "gn:name":"Ban Mae Mok Klang",
    "gn:population":0,
    "gn:timezone":"Asia/Bangkok",
    "iso:country":"TH",
    "name:tha_x_preferred":[
        "\u0e1a\u0e49\u0e32\u0e19\u0e41\u0e21\u0e48\u0e21\u0e2d\u0e01\u0e01\u0e25\u0e32\u0e07"
    ],
    "name:und_x_variant":[
        "B\u0101n Mea Mauk",
        "Ban Mae Mok",
        "Ban Mae Mok Hua Nam",
        "Ban Mae Mok Klang"
    ],
    "wof:name":"Ban Mae Mok Klang",
    "wof:placetype":"locality"
},
  "geometry": {"coordinates":[99.37403,17.62775],"type":"Point"}
}