{
  "type": "Feature",
  "properties": {
    "gn:admin1_code":"48.0",
    "gn:asciiname":"Ban Khao Ang",
    "gn:country_code":"TH",
    "gn:dem":30,
    "gn:feature_class":"P",
    "gn:feature_code":"PPL",
    "gn:name":"Ban Khao Ang",
    "gn:population":0,
    "gn:timezone":"Asia/Bangkok",
    "iso:country":"TH",
    "name:tha_x_preferred":[
        "\u0e1a\u0e49\u0e32\u0e19\u0e40\u0e02\u0e32\u0e2d\u0e48\u0e32\u0e07"
    ],
    "wof:name":"Ban Khao Ang",
    "wof:placetype":"locality"
},
  "geometry": {"coordinates":[102.24614,12.60658],"type":"Point"}
}