{
  "type": "Feature",
  "properties": {
    "gn:admin1_code":"80.0",
    "gn:asciiname":"Ban Wang Ti Ok",
    "gn:country_code":"TH",
    "gn:dem":37,
    "gn:feature_class":"P",
    "gn:feature_code":"PPL",
    "gn:name":"Ban Wang Ti Ok",
    "gn:population":0,
    "gn:timezone":"Asia/Bangkok",
    "iso:country":"TH",
    "name:tha_x_preferred":[
        "\u0e1a\u0e49\u0e32\u0e19\u0e27\u0e31\u0e07\u0e15\u0e35\u0e2d\u0e01"
    ],
    "wof:name":"Ban Wang Ti Ok",
    "wof:placetype":"locality"
},
  "geometry": {"coordinates":[102.01689,13.84053],"type":"Point"}
}