{
  "type": "Feature",
  "properties": {
    "gn:admin1_code":"2.0",
    "gn:asciiname":"Ban Sam Sop",
    "gn:country_code":"TH",
    "gn:dem":855,
    "gn:feature_class":"P",
    "gn:feature_code":"PPL",
    "gn:name":"Ban Sam Sop",
    "gn:population":0,
    "gn:timezone":"Asia/Bangkok",
    "iso:country":"TH",
    "name:tha_x_preferred":[
        "\u0e1a\u0e49\u0e32\u0e19\u0e2a\u0e32\u0e21\u0e2a\u0e1a"
    ],
    "wof:name":"Ban Sam Sop",
    "wof:placetype":"locality"
},
  "geometry": {"coordinates":[98.46619,18.50125],"type":"Point"}
}