{
  "type": "Feature",
  "properties": {
    "gn:admin1_code":"69.0",
    "gn:asciiname":"Ban Khuan Tha Ruea",
    "gn:country_code":"TH",
    "gn:dem":3,
    "gn:feature_class":"P",
    "gn:feature_code":"PPL",
    "gn:name":"Ban Khuan Tha Ruea",
    "gn:population":0,
    "gn:timezone":"Asia/Bangkok",
    "iso:country":"TH",
    "name:tha_x_preferred":[
        "\u0e1a\u0e49\u0e32\u0e19\u0e04\u0e27\u0e19\u0e17\u0e48\u0e32\u0e40\u0e23\u0e37\u0e2d"
    ],
    "name:und_x_variant":[
        "Ban Khuan Tha Rua"
    ],
    "wof:name":"Ban Khuan Tha Ruea",
    "wof:placetype":"locality"
},
  "geometry": {"coordinates":[101.0945,6.77431],"type":"Point"}
}