{
  "type": "Feature",
  "properties": {
    "gn:admin1_code":"14.0",
    "gn:asciiname":"Ban Mai Khon Yang Khwang",
    "gn:cc2":"TH",
    "gn:country_code":"TH",
    "gn:dem":92,
    "gn:feature_class":"P",
    "gn:feature_code":"PPL",
    "gn:name":"Ban Mai Khon Yang Khwang",
    "gn:population":0,
    "gn:timezone":"Asia/Bangkok",
    "iso:country":"TH",
    "name:und_x_variant":[
        "B\u0101n Kaun Y\u0101ng Kw\u0101ng",
        "Ban Khon Yang Khwang",
        "Ban Mai Khon Yang Khwang"
    ],
    "wof:name":"Ban Mai Khon Yang Khwang",
    "wof:placetype":"locality"
},
  "geometry": {"coordinates":[101.10444,15.88167],"type":"Point"}
}