{
  "type": "Feature",
  "properties": {
    "gn:admin1_code":"3.0",
    "gn:asciiname":"Ban Faen",
    "gn:country_code":"TH",
    "gn:dem":370,
    "gn:feature_class":"P",
    "gn:feature_code":"PPL",
    "gn:name":"Ban Faen",
    "gn:population":0,
    "gn:timezone":"Asia/Bangkok",
    "iso:country":"TH",
    "name:tha_x_preferred":[
        "\u0e1a\u0e49\u0e32\u0e19\u0e41\u0e1f\u0e19"
    ],
    "wof:name":"Ban Faen",
    "wof:placetype":"locality"
},
  "geometry": {"coordinates":[100.38227999999999,20.22064],"type":"Point"}
}