{
  "type": "Feature",
  "properties": {
    "gn:admin1_code":"24.0",
    "gn:asciiname":"Ban Wang Chot",
    "gn:country_code":"TH",
    "gn:dem":180,
    "gn:feature_class":"P",
    "gn:feature_code":"PPL",
    "gn:name":"Ban Wang Chot",
    "gn:population":0,
    "gn:timezone":"Asia/Bangkok",
    "iso:country":"TH",
    "name:tha_x_preferred":[
        "\u0e1a\u0e49\u0e32\u0e19\u0e27\u0e31\u0e07\u0e42\u0e08\u0e14"
    ],
    "wof:name":"Ban Wang Chot",
    "wof:placetype":"locality"
},
  "geometry": {"coordinates":[103.05089,16.101],"type":"Point"}
}