{
  "type": "Feature",
  "properties": {
    "gn:admin1_code":"2.0",
    "gn:asciiname":"Ban Huai Ngu Klang",
    "gn:country_code":"TH",
    "gn:dem":483,
    "gn:feature_class":"P",
    "gn:feature_code":"PPL",
    "gn:name":"Ban Huai Ngu Klang",
    "gn:population":0,
    "gn:timezone":"Asia/Bangkok",
    "iso:country":"TH",
    "name:tha_x_preferred":[
        "\u0e1a\u0e49\u0e32\u0e19\u0e2b\u0e49\u0e27\u0e22\u0e07\u0e39\u0e01\u0e25\u0e32\u0e07"
    ],
    "name:und_x_variant":[
        "Ban Huai Ngu"
    ],
    "wof:name":"Ban Huai Ngu Klang",
    "wof:placetype":"locality"
},
  "geometry": {"coordinates":[99.17006000000001,19.88803],"type":"Point"}
}