{
  "type": "Feature",
  "properties": {
    "gn:admin1_code":"5.0",
    "gn:asciiname":"Ban Muang Sam Pi",
    "gn:country_code":"TH",
    "gn:dem":462,
    "gn:feature_class":"P",
    "gn:feature_code":"PPL",
    "gn:name":"Ban Muang Sam Pi",
    "gn:population":0,
    "gn:timezone":"Asia/Bangkok",
    "iso:country":"TH",
    "name:tha_x_preferred":[
        "\u0e1a\u0e49\u0e32\u0e19\u0e21\u0e48\u0e27\u0e07\u0e2a\u0e32\u0e21\u0e1b\u0e35"
    ],
    "wof:lang_x_official":[
        "tha"
    ],
    "wof:lang_x_spoken":[
        "tha"
    ],
    "wof:name":"Ban Muang Sam Pi",
    "wof:placetype":"locality"
},
  "geometry": {"coordinates":[98.96922000000001,17.76428],"type":"Point"}
}