{
  "type": "Feature",
  "properties": {
    "gn:admin1_code":"11.0",
    "gn:asciiname":"Ban Tham Sadao",
    "gn:country_code":"TH",
    "gn:dem":54,
    "gn:feature_class":"P",
    "gn:feature_code":"PPL",
    "gn:name":"Ban Tham Sadao",
    "gn:population":0,
    "gn:timezone":"Asia/Bangkok",
    "iso:country":"TH",
    "name:tha_x_preferred":[
        "\u0e1a\u0e49\u0e32\u0e19\u0e16\u0e49\u0e33\u0e2a\u0e30\u0e40\u0e14\u0e32"
    ],
    "wof:lang_x_official":[
        "tha"
    ],
    "wof:lang_x_spoken":[
        "tha"
    ],
    "wof:name":"Ban Tham Sadao",
    "wof:placetype":"locality"
},
  "geometry": {"coordinates":[99.90622,16.53017],"type":"Point"}
}