{
  "type": "Feature",
  "properties": {
    "gn:admin1_code":"41.0",
    "gn:asciiname":"Ban Na Do",
    "gn:country_code":"TH",
    "gn:dem":353,
    "gn:feature_class":"P",
    "gn:feature_code":"PPL",
    "gn:name":"Ban Na Do",
    "gn:population":0,
    "gn:timezone":"Asia/Bangkok",
    "iso:country":"TH",
    "name:tha_x_preferred":[
        "\u0e1a\u0e49\u0e32\u0e19\u0e19\u0e32\u0e14\u0e2d"
    ],
    "wof:name":"Ban Na Do",
    "wof:placetype":"locality"
},
  "geometry": {"coordinates":[100.36929000000001,19.27629],"type":"Point"}
}