{
  "type": "Feature",
  "properties": {
    "gn:admin1_code":"44.0",
    "gn:asciiname":"Ban Pak Khlong Tha Thua",
    "gn:country_code":"TH",
    "gn:dem":4,
    "gn:feature_class":"P",
    "gn:feature_code":"PPL",
    "gn:name":"Ban Pak Khlong Tha Thua",
    "gn:population":0,
    "gn:timezone":"Asia/Bangkok",
    "iso:country":"TH",
    "name:tha_x_preferred":[
        "\u0e1a\u0e49\u0e32\u0e19\u0e1b\u0e32\u0e01\u0e04\u0e25\u0e2d\u0e07\u0e17\u0e48\u0e32\u0e16\u0e31\u0e48\u0e27"
    ],
    "wof:name":"Ban Pak Khlong Tha Thua",
    "wof:placetype":"locality"
},
  "geometry": {"coordinates":[101.06131000000001,13.62592],"type":"Point"}
}