{
  "type": "Feature",
  "properties": {
    "gn:admin1_code":"43.0",
    "gn:asciiname":"Ban Nong Prachin",
    "gn:country_code":"TH",
    "gn:dem":10,
    "gn:feature_class":"P",
    "gn:feature_code":"PPL",
    "gn:name":"Ban Nong Prachin",
    "gn:population":0,
    "gn:timezone":"Asia/Bangkok",
    "iso:country":"TH",
    "name:tha_x_preferred":[
        "\u0e1a\u0e49\u0e32\u0e19\u0e2b\u0e19\u0e2d\u0e07\u0e1b\u0e23\u0e32\u0e08\u0e35\u0e19"
    ],
    "name:und_x_variant":[
        "Ban Nong Pla Chin (1)"
    ],
    "wof:name":"Ban Nong Prachin",
    "wof:placetype":"locality"
},
  "geometry": {"coordinates":[101.23488999999999,14.19186],"type":"Point"}
}