{
  "type": "Feature",
  "properties": {
    "gn:admin1_code":"49.0",
    "gn:asciiname":"Ban Sa-aeng",
    "gn:country_code":"TH",
    "gn:dem":26,
    "gn:feature_class":"P",
    "gn:feature_code":"PPL",
    "gn:name":"Ban Sa-aeng",
    "gn:population":0,
    "gn:timezone":"Asia/Bangkok",
    "iso:country":"TH",
    "name:tha_x_preferred":[
        "\u0e1a\u0e49\u0e32\u0e19\u0e2a\u0e30\u0e41\u0e2d\u0e07"
    ],
    "wof:name":"Ban Sa-aeng",
    "wof:placetype":"locality"
},
  "geometry": {"coordinates":[102.47247,12.50944],"type":"Point"}
}