{
  "type": "Feature",
  "properties": {
    "gn:admin1_code":"40.0",
    "gn:admin2_code":"1021",
    "gn:asciiname":"Ban Luk Wua",
    "gn:country_code":"TH",
    "gn:dem":4,
    "gn:feature_class":"P",
    "gn:feature_code":"PPL",
    "gn:name":"Ban Luk Wua",
    "gn:population":0,
    "gn:timezone":"Asia/Bangkok",
    "iso:country":"TH",
    "name:tha_x_preferred":[
        "\u0e1a\u0e49\u0e32\u0e19\u0e25\u0e39\u0e01\u0e27\u0e31\u0e27"
    ],
    "name:und_x_variant":[
        "Ban Luk Ngua",
        "Ban Luk Wua"
    ],
    "wof:name":"Ban Luk Wua",
    "wof:placetype":"locality"
},
  "geometry": {"coordinates":[100.44494,13.56535],"type":"Point"}
}