{
  "type": "Feature",
  "properties": {
    "gn:admin1_code":"3.0",
    "gn:asciiname":"Ban San Kang Pla",
    "gn:country_code":"TH",
    "gn:dem":479,
    "gn:feature_class":"P",
    "gn:feature_code":"PPL",
    "gn:name":"Ban San Kang Pla",
    "gn:population":0,
    "gn:timezone":"Asia/Bangkok",
    "iso:country":"TH",
    "name:tha_x_preferred":[
        "\u0e1a\u0e49\u0e32\u0e19\u0e2a\u0e31\u0e19\u0e01\u0e49\u0e32\u0e07\u0e1b\u0e25\u0e32"
    ],
    "name:und_x_variant":[
        "B\u0101n San Glang",
        "Ban San Klang",
        "Ban San Kang Pla"
    ],
    "wof:name":"Ban San Kang Pla",
    "wof:placetype":"locality"
},
  "geometry": {"coordinates":[99.47653,19.59189],"type":"Point"}
}