{
  "type": "Feature",
  "properties": {
    "gn:admin1_code":"58.0",
    "gn:asciiname":"Ban Tha Sathon",
    "gn:country_code":"TH",
    "gn:dem":12,
    "gn:feature_class":"P",
    "gn:feature_code":"PPL",
    "gn:name":"Ban Tha Sathon",
    "gn:population":0,
    "gn:timezone":"Asia/Bangkok",
    "iso:country":"TH",
    "name:tha_x_preferred":[
        "\u0e1a\u0e49\u0e32\u0e19\u0e17\u0e48\u0e32\u0e2a\u0e30\u0e17\u0e49\u0e2d\u0e19"
    ],
    "wof:name":"Ban Tha Sathon",
    "wof:placetype":"locality"
},
  "geometry": {"coordinates":[99.02464000000001,9.93747],"type":"Point"}
}