{
  "type": "Feature",
  "properties": {
    "gn:admin1_code":"56.0",
    "gn:asciiname":"Ban Tha Mai Ruak",
    "gn:country_code":"TH",
    "gn:dem":33,
    "gn:feature_class":"P",
    "gn:feature_code":"PPL",
    "gn:name":"Ban Tha Mai Ruak",
    "gn:population":0,
    "gn:timezone":"Asia/Bangkok",
    "iso:country":"TH",
    "name:tha_x_preferred":[
        "\u0e1a\u0e49\u0e32\u0e19\u0e17\u0e48\u0e32\u0e44\u0e21\u0e49\u0e23\u0e27\u0e01"
    ],
    "name:und_x_variant":[
        "Dh\u0101mair\u016bak",
        "Ban Tha Mai Ruak"
    ],
    "wof:name":"Ban Tha Mai Ruak",
    "wof:placetype":"locality"
},
  "geometry": {"coordinates":[99.79536,12.86011],"type":"Point"}
}