{
  "type": "Feature",
  "properties": {
    "gn:admin1_code":"1.0",
    "gn:asciiname":"Ban Huai Pong Tak",
    "gn:country_code":"TH",
    "gn:dem":842,
    "gn:feature_class":"P",
    "gn:feature_code":"PPL",
    "gn:name":"Ban Huai Pong Tak",
    "gn:population":0,
    "gn:timezone":"Asia/Bangkok",
    "iso:country":"TH",
    "name:tha_x_preferred":[
        "\u0e1a\u0e49\u0e32\u0e19\u0e2b\u0e49\u0e27\u0e22\u0e42\u0e1b\u0e48\u0e07\u0e15\u0e4a\u0e32\u0e01"
    ],
    "wof:name":"Ban Huai Pong Tak",
    "wof:placetype":"locality"
},
  "geometry": {"coordinates":[98.47914,19.06408],"type":"Point"}
}