{
  "type": "Feature",
  "properties": {
    "gn:admin1_code":"18.0",
    "gn:asciiname":"Ban Na Hin",
    "gn:country_code":"TH",
    "gn:dem":631,
    "gn:feature_class":"P",
    "gn:feature_code":"PPL",
    "gn:name":"Ban Na Hin",
    "gn:population":0,
    "gn:timezone":"Asia/Bangkok",
    "iso:country":"TH",
    "name:tha_x_preferred":[
        "\u0e1a\u0e49\u0e32\u0e19\u0e19\u0e32\u0e2b\u0e34\u0e19"
    ],
    "name:und_x_variant":[
        "B\u0101n Muat Faung",
        "Ban Muat Fong",
        "Ban Na Hin"
    ],
    "wof:lang_x_official":[
        "tha"
    ],
    "wof:lang_x_spoken":[
        "tha"
    ],
    "wof:name":"Ban Na Hin",
    "wof:placetype":"locality"
},
  "geometry": {"coordinates":[101.25812000000001,17.28192],"type":"Point"}
}