{
  "type": "Feature",
  "properties": {
    "gn:admin1_code":"74.0",
    "gn:asciiname":"Ban Nong Chik",
    "gn:country_code":"TH",
    "gn:dem":6,
    "gn:feature_class":"P",
    "gn:feature_code":"PPL",
    "gn:name":"Ban Nong Chik",
    "gn:population":0,
    "gn:timezone":"Asia/Bangkok",
    "iso:country":"TH",
    "name:und_x_variant":[
        "Hnong Chik",
        "Ban Nong Chik"
    ],
    "wof:name":"Ban Nong Chik",
    "wof:placetype":"locality"
},
  "geometry": {"coordinates":[101.46666999999999,14.08333],"type":"Point"}
}