{
  "type": "Feature",
  "properties": {
    "gn:admin1_code":"43.0",
    "gn:asciiname":"Ban Dong Lakhon",
    "gn:country_code":"TH",
    "gn:dem":13,
    "gn:feature_class":"P",
    "gn:feature_code":"PPL",
    "gn:name":"Ban Dong Lakhon",
    "gn:population":0,
    "gn:timezone":"Asia/Bangkok",
    "iso:country":"TH",
    "name:tha_x_preferred":[
        "\u0e1a\u0e49\u0e32\u0e19\u0e14\u0e07\u0e25\u0e30\u0e04\u0e23"
    ],
    "name:und_x_variant":[
        "Ban Dong Lakon",
        "Ban Dong Lakhon"
    ],
    "wof:name":"Ban Dong Lakhon",
    "wof:placetype":"locality"
},
  "geometry": {"coordinates":[101.16422,14.16181],"type":"Point"}
}