{
  "type": "Feature",
  "properties": {
    "gn:admin1_code":"49.0",
    "gn:asciiname":"Ban Laem Thian",
    "gn:country_code":"TH",
    "gn:dem":-9999,
    "gn:feature_class":"P",
    "gn:feature_code":"PPL",
    "gn:name":"Ban Laem Thian",
    "gn:population":0,
    "gn:timezone":"Asia/Bangkok",
    "iso:country":"TH",
    "wof:name":"Ban Laem Thian",
    "wof:placetype":"locality"
},
  "geometry": {"coordinates":[102.59999999999999,11.56667],"type":"Point"}
}