{
  "type": "Feature",
  "properties": {
    "gn:admin1_code":"75.0",
    "gn:asciiname":"Ban Pa Tia",
    "gn:country_code":"TH",
    "gn:dem":179,
    "gn:feature_class":"P",
    "gn:feature_code":"PPL",
    "gn:name":"Ban Pa Tia",
    "gn:population":0,
    "gn:timezone":"Asia/Bangkok",
    "iso:country":"TH",
    "name:tha_x_preferred":[
        "\u0e1a\u0e49\u0e32\u0e19\u0e1b\u0e48\u0e32\u0e40\u0e15\u0e35\u0e49\u0e22"
    ],
    "wof:name":"Ban Pa Tia",
    "wof:placetype":"locality"
},
  "geometry": {"coordinates":[105.47247,14.80264],"type":"Point"}
}