{
  "type": "Feature",
  "properties": {
    "gn:admin1_code":"68.0",
    "gn:asciiname":"Ban Takhian Phao",
    "gn:country_code":"TH",
    "gn:dem":72,
    "gn:feature_class":"P",
    "gn:feature_code":"PPL",
    "gn:name":"Ban Takhian Phao",
    "gn:population":0,
    "gn:timezone":"Asia/Bangkok",
    "iso:country":"TH",
    "name:tha_x_preferred":[
        "\u0e1a\u0e49\u0e32\u0e19\u0e15\u0e30\u0e40\u0e04\u0e35\u0e22\u0e19\u0e40\u0e20\u0e32"
    ],
    "wof:name":"Ban Takhian Phao",
    "wof:placetype":"locality"
},
  "geometry": {"coordinates":[100.75167,6.65845],"type":"Point"}
}