{
  "type": "Feature",
  "properties": {
    "gn:admin1_code":"44.0",
    "gn:asciiname":"Ban Wat Khu Kasem Samoson",
    "gn:country_code":"TH",
    "gn:dem":7,
    "gn:feature_class":"P",
    "gn:feature_code":"PPL",
    "gn:name":"Ban Wat Khu Kasem Samoson",
    "gn:population":0,
    "gn:timezone":"Asia/Bangkok",
    "iso:country":"TH",
    "name:tha_x_preferred":[
        "\u0e1a\u0e49\u0e32\u0e19\u0e27\u0e31\u0e14\u0e04\u0e39\u0e49\u0e40\u0e01\u0e29\u0e21\u0e2a\u0e42\u0e21\u0e2a\u0e23"
    ],
    "wof:name":"Ban Wat Khu Kasem Samoson",
    "wof:placetype":"locality"
},
  "geometry": {"coordinates":[100.94319,13.75881],"type":"Point"}
}