{
  "type": "Feature",
  "properties": {
    "gn:admin1_code":"28",
    "gn:asciiname":"Ban Khok Phet",
    "gn:country_code":"TH",
    "gn:dem":159,
    "gn:feature_class":"P",
    "gn:feature_code":"PPL",
    "gn:name":"Ban Khok Phet",
    "gn:population":0,
    "gn:timezone":"Asia/Bangkok",
    "iso:country":"TH",
    "name:tha_x_preferred":[
        "\u0e1a\u0e49\u0e32\u0e19\u0e42\u0e04\u0e01\u0e40\u0e1e\u0e0a\u0e23"
    ],
    "wof:name":"Ban Khok Phet",
    "wof:placetype":"locality"
},
  "geometry": {"coordinates":[103.23953,14.81544],"type":"Point"}
}