{
  "type": "Feature",
  "properties": {
    "gn:admin1_code":"15.0",
    "gn:asciiname":"Ban Tha Rak Wai",
    "gn:country_code":"TH",
    "gn:dem":27,
    "gn:feature_class":"P",
    "gn:feature_code":"PPL",
    "gn:name":"Ban Tha Rak Wai",
    "gn:population":0,
    "gn:timezone":"Asia/Bangkok",
    "iso:country":"TH",
    "name:tha_x_preferred":[
        "\u0e1a\u0e49\u0e32\u0e19\u0e17\u0e48\u0e32\u0e23\u0e32\u0e01\u0e2b\u0e27\u0e32\u0e22"
    ],
    "name:und_x_variant":[
        "Ban Klak Wai",
        "Ban Tha Lak Wai",
        "Ban Tha Rak Wai"
    ],
    "wof:name":"Ban Tha Rak Wai",
    "wof:placetype":"locality"
},
  "geometry": {"coordinates":[100.08167,15.35244],"type":"Point"}
}