{
  "type": "Feature",
  "properties": {
    "gn:admin1_code":"51.0",
    "gn:asciiname":"Ban Nong Hin Pun",
    "gn:country_code":"TH",
    "gn:dem":35,
    "gn:feature_class":"P",
    "gn:feature_code":"PPL",
    "gn:name":"Ban Nong Hin Pun",
    "gn:population":0,
    "gn:timezone":"Asia/Bangkok",
    "iso:country":"TH",
    "name:tha_x_preferred":[
        "\u0e1a\u0e49\u0e32\u0e19\u0e2b\u0e19\u0e2d\u0e07\u0e2b\u0e34\u0e19\u0e1b\u0e39\u0e19"
    ],
    "wof:name":"Ban Nong Hin Pun",
    "wof:placetype":"locality"
},
  "geometry": {"coordinates":[99.87539,14.80011],"type":"Point"}
}