{
  "type": "Feature",
  "properties": {
    "gn:admin1_code":"18.0",
    "gn:asciiname":"Ban Si Chomchuen",
    "gn:country_code":"TH",
    "gn:dem":327,
    "gn:feature_class":"P",
    "gn:feature_code":"PPL",
    "gn:name":"Ban Si Chomchuen",
    "gn:population":0,
    "gn:timezone":"Asia/Bangkok",
    "iso:country":"TH",
    "name:tha_x_preferred":[
        "\u0e1a\u0e49\u0e32\u0e19\u0e28\u0e23\u0e35\u0e0a\u0e21\u0e0a\u0e37\u0e48\u0e19"
    ],
    "wof:name":"Ban Si Chomchuen",
    "wof:placetype":"locality"
},
  "geometry": {"coordinates":[101.83644,17.62298999999999],"type":"Point"}
}