{
  "type": "Feature",
  "properties": {
    "gn:admin1_code":"6.0",
    "gn:asciiname":"Ban Ling Kan",
    "gn:country_code":"TH",
    "gn:dem":263,
    "gn:feature_class":"P",
    "gn:feature_code":"PPL",
    "gn:name":"Ban Ling Kan",
    "gn:population":0,
    "gn:timezone":"Asia/Bangkok",
    "iso:country":"TH",
    "name:tha_x_preferred":[
        "\u0e1a\u0e49\u0e32\u0e19\u0e2b\u0e25\u0e34\u0e48\u0e07\u0e01\u0e49\u0e32\u0e19"
    ],
    "name:und_x_variant":[
        "Ban Ring Kan"
    ],
    "wof:name":"Ban Ling Kan",
    "wof:placetype":"locality"
},
  "geometry": {"coordinates":[99.39749999999999,18.34136],"type":"Point"}
}