{
  "type": "Feature",
  "properties": {
    "gn:admin1_code":"57.0",
    "gn:asciiname":"Ban Huai Khwang",
    "gn:country_code":"TH",
    "gn:dem":6,
    "gn:feature_class":"P",
    "gn:feature_code":"PPL",
    "gn:name":"Ban Huai Khwang",
    "gn:population":0,
    "gn:timezone":"Asia/Bangkok",
    "iso:country":"TH",
    "name:tha_x_preferred":[
        "\u0e1a\u0e49\u0e32\u0e19\u0e2b\u0e49\u0e27\u0e22\u0e02\u0e27\u0e32\u0e07"
    ],
    "wof:name":"Ban Huai Khwang",
    "wof:placetype":"locality"
},
  "geometry": {"coordinates":[99.90900000000001,12.32561],"type":"Point"}
}