{
  "type": "Feature",
  "properties": {
    "gn:admin1_code":"70.0",
    "gn:asciiname":"Ban Suan Mai Pono",
    "gn:country_code":"TH",
    "gn:dem":280,
    "gn:feature_class":"P",
    "gn:feature_code":"PPL",
    "gn:name":"Ban Suan Mai Pono",
    "gn:population":0,
    "gn:timezone":"Asia/Bangkok",
    "iso:country":"TH",
    "name:tha_x_preferred":[
        "\u0e1a\u0e49\u0e32\u0e19\u0e2a\u0e27\u0e19\u0e43\u0e2b\u0e21\u0e48\u0e1b\u0e2d\u0e40\u0e19\u0e32\u0e30"
    ],
    "wof:name":"Ban Suan Mai Pono",
    "wof:placetype":"locality"
},
  "geometry": {"coordinates":[101.10218999999999,5.76739],"type":"Point"}
}