{
  "type": "Feature",
  "properties": {
    "gn:admin1_code":"22",
    "gn:asciiname":"Ban Thai Niyom",
    "gn:country_code":"TH",
    "gn:dem":168,
    "gn:feature_class":"P",
    "gn:feature_code":"PPL",
    "gn:name":"Ban Thai Niyom",
    "gn:population":0,
    "gn:timezone":"Asia/Bangkok",
    "iso:country":"TH",
    "name:tha_x_preferred":[
        "\u0e1a\u0e49\u0e32\u0e19\u0e44\u0e17\u0e22\u0e19\u0e34\u0e22\u0e21"
    ],
    "wof:name":"Ban Thai Niyom",
    "wof:placetype":"locality"
},
  "geometry": {"coordinates":[102.80208,15.74811],"type":"Point"}
}