{
  "type": "Feature",
  "properties": {
    "gn:admin1_code":"63.0",
    "gn:asciiname":"Ban Ton Han",
    "gn:country_code":"TH",
    "gn:dem":91,
    "gn:feature_class":"P",
    "gn:feature_code":"PPL",
    "gn:name":"Ban Ton Han",
    "gn:population":0,
    "gn:timezone":"Asia/Bangkok",
    "iso:country":"TH",
    "name:tha_x_preferred":[
        "\u0e1a\u0e49\u0e32\u0e19\u0e15\u0e49\u0e19\u0e2b\u0e32\u0e23"
    ],
    "wof:name":"Ban Ton Han",
    "wof:placetype":"locality"
},
  "geometry": {"coordinates":[98.96914,8.31119],"type":"Point"}
}