{
  "type": "Feature",
  "properties": {
    "gn:admin1_code":"8.0",
    "gn:asciiname":"Ban Huai Phak La",
    "gn:country_code":"TH",
    "gn:dem":226,
    "gn:feature_class":"P",
    "gn:feature_code":"PPL",
    "gn:name":"Ban Huai Phak La",
    "gn:population":0,
    "gn:timezone":"Asia/Bangkok",
    "iso:country":"TH",
    "name:tha_x_preferred":[
        "\u0e1a\u0e49\u0e32\u0e19\u0e2b\u0e49\u0e27\u0e22\u0e1c\u0e31\u0e01\u0e2b\u0e25\u0e30"
    ],
    "wof:name":"Ban Huai Phak La",
    "wof:placetype":"locality"
},
  "geometry": {"coordinates":[98.61181000000001,16.61072],"type":"Point"}
}