{
  "type": "Feature",
  "properties": {
    "gn:admin1_code":"76.0",
    "gn:asciiname":"Ban Khok Yai Phatthana",
    "gn:country_code":"TH",
    "gn:dem":185,
    "gn:feature_class":"P",
    "gn:feature_code":"PPL",
    "gn:name":"Ban Khok Yai Phatthana",
    "gn:population":0,
    "gn:timezone":"Asia/Bangkok",
    "iso:country":"TH",
    "name:tha_x_preferred":[
        "\u0e1a\u0e49\u0e32\u0e19\u0e42\u0e04\u0e01\u0e43\u0e2b\u0e0d\u0e48\u0e1e\u0e31\u0e12\u0e19\u0e32"
    ],
    "wof:name":"Ban Khok Yai Phatthana",
    "wof:placetype":"locality"
},
  "geometry": {"coordinates":[103.43808,16.88744],"type":"Point"}
}