{
  "type": "Feature",
  "properties": {
    "gn:admin1_code":"27.0",
    "gn:asciiname":"Ban Noi Chai Di Krok Samong",
    "gn:country_code":"TH",
    "gn:dem":258,
    "gn:feature_class":"P",
    "gn:feature_code":"PPL",
    "gn:name":"Ban Noi Chai Di Krok Samong",
    "gn:population":0,
    "gn:timezone":"Asia/Bangkok",
    "iso:country":"TH",
    "name:tha_x_preferred":[
        "\u0e1a\u0e49\u0e32\u0e19\u0e19\u0e49\u0e2d\u0e22\u0e43\u0e08\u0e14\u0e35\u0e42\u0e01\u0e23\u0e01\u0e42\u0e2a\u0e21\u0e07"
    ],
    "name:und_x_variant":[
        "Ban Samrong"
    ],
    "wof:name":"Ban Noi Chai Di Krok Samong",
    "wof:placetype":"locality"
},
  "geometry": {"coordinates":[102.07971999999999,14.56292],"type":"Point"}
}