{
  "type": "Feature",
  "properties": {
    "gn:admin1_code":"26.0",
    "gn:asciiname":"Ban Nong Rai",
    "gn:country_code":"TH",
    "gn:dem":227,
    "gn:feature_class":"P",
    "gn:feature_code":"PPL",
    "gn:name":"Ban Nong Rai",
    "gn:population":0,
    "gn:timezone":"Asia/Bangkok",
    "iso:country":"TH",
    "name:tha_x_preferred":[
        "\u0e1a\u0e49\u0e32\u0e19\u0e2b\u0e19\u0e2d\u0e07\u0e44\u0e23\u0e48"
    ],
    "wof:name":"Ban Nong Rai",
    "wof:placetype":"locality"
},
  "geometry": {"coordinates":[102.34389,16.25875],"type":"Point"}
}