{
  "type": "Feature",
  "properties": {
    "gn:admin1_code":"47.0",
    "gn:asciiname":"Ban Nong Inthanin",
    "gn:country_code":"TH",
    "gn:dem":36,
    "gn:feature_class":"P",
    "gn:feature_code":"PPL",
    "gn:name":"Ban Nong Inthanin",
    "gn:population":0,
    "gn:timezone":"Asia/Bangkok",
    "iso:country":"TH",
    "name:tha_x_preferred":[
        "\u0e1a\u0e49\u0e32\u0e19\u0e2b\u0e19\u0e2d\u0e07\u0e2d\u0e34\u0e19\u0e17\u0e19\u0e34\u0e25"
    ],
    "wof:name":"Ban Nong Inthanin",
    "wof:placetype":"locality"
},
  "geometry": {"coordinates":[101.32805999999999,12.91528],"type":"Point"}
}