{
  "type": "Feature",
  "properties": {
    "gn:admin1_code":"30.0",
    "gn:asciiname":"Ban Nong Phai Noi",
    "gn:country_code":"TH",
    "gn:dem":135,
    "gn:feature_class":"P",
    "gn:feature_code":"PPL",
    "gn:name":"Ban Nong Phai Noi",
    "gn:population":0,
    "gn:timezone":"Asia/Bangkok",
    "iso:country":"TH",
    "name:tha_x_preferred":[
        "\u0e1a\u0e49\u0e32\u0e19\u0e2b\u0e19\u0e2d\u0e07\u0e44\u0e1c\u0e48\u0e19\u0e49\u0e2d\u0e22"
    ],
    "wof:name":"Ban Nong Phai Noi",
    "wof:placetype":"locality"
},
  "geometry": {"coordinates":[104.29194,14.99317],"type":"Point"}
}