{
  "type": "Feature",
  "properties": {
    "gn:admin1_code":"64.0",
    "gn:asciiname":"Ban Kuan Suan Pat",
    "gn:country_code":"TH",
    "gn:dem":35,
    "gn:feature_class":"P",
    "gn:feature_code":"PPL",
    "gn:name":"Ban Kuan Suan Pat",
    "gn:population":0,
    "gn:timezone":"Asia/Bangkok",
    "iso:country":"TH",
    "name:tha_x_preferred":[
        "\u0e1a\u0e49\u0e32\u0e19\u0e04\u0e27\u0e19\u0e2a\u0e27\u0e19\u0e1b\u0e31\u0e14"
    ],
    "wof:name":"Ban Kuan Suan Pat",
    "wof:placetype":"locality"
},
  "geometry": {"coordinates":[99.76817,8.70931],"type":"Point"}
}