{
  "type": "Feature",
  "properties": {
    "gn:admin1_code":"30.0",
    "gn:asciiname":"Ban Prasat",
    "gn:country_code":"TH",
    "gn:dem":156,
    "gn:feature_class":"P",
    "gn:feature_code":"PPL",
    "gn:name":"Ban Prasat",
    "gn:population":0,
    "gn:timezone":"Asia/Bangkok",
    "iso:country":"TH",
    "name:tha_x_preferred":[
        "\u0e1a\u0e49\u0e32\u0e19\u0e1b\u0e23\u0e32\u0e2a\u0e32\u0e17"
    ],
    "wof:name":"Ban Prasat",
    "wof:placetype":"locality"
},
  "geometry": {"coordinates":[104.01994999999999,14.72917],"type":"Point"}
}