{
  "type": "Feature",
  "properties": {
    "gn:admin1_code":"20.0",
    "gn:asciiname":"Ban Muang Lai",
    "gn:country_code":"TH",
    "gn:dem":166,
    "gn:feature_class":"P",
    "gn:feature_code":"PPL",
    "gn:name":"Ban Muang Lai",
    "gn:population":0,
    "gn:timezone":"Asia/Bangkok",
    "iso:country":"TH",
    "name:tha_x_preferred":[
        "\u0e1a\u0e49\u0e32\u0e19\u0e21\u0e48\u0e27\u0e07\u0e25\u0e32\u0e22"
    ],
    "name:und_x_variant":[
        "Ban Muang",
        "Ban Muang Lai"
    ],
    "wof:name":"Ban Muang Lai",
    "wof:placetype":"locality"
},
  "geometry": {"coordinates":[104.259,17.11895],"type":"Point"}
}