{
  "type": "Feature",
  "properties": {
    "gn:admin1_code":"30.0",
    "gn:asciiname":"Ban La-o",
    "gn:country_code":"TH",
    "gn:dem":143,
    "gn:feature_class":"P",
    "gn:feature_code":"PPL",
    "gn:name":"Ban La-o",
    "gn:population":0,
    "gn:timezone":"Asia/Bangkok",
    "iso:country":"TH",
    "name:und_x_variant":[
        "\u0e1a\u0e49\u0e32\u0e19\u0e25\u0e30\u0e40\u0e2d\u0e32\u0e30"
    ],
    "wof:name":"Ban La-o",
    "wof:placetype":"locality"
},
  "geometry": {"coordinates":[104.45431000000001,14.93989],"type":"Point"}
}