{
  "type": "Feature",
  "properties": {
    "gn:admin1_code":"1.0",
    "gn:asciiname":"Ban Nam Hu",
    "gn:country_code":"TH",
    "gn:dem":1039,
    "gn:feature_class":"P",
    "gn:feature_code":"PPL",
    "gn:name":"Ban Nam Hu",
    "gn:population":0,
    "gn:timezone":"Asia/Bangkok",
    "iso:country":"TH",
    "name:tha_x_preferred":[
        "\u0e1a\u0e49\u0e32\u0e19\u0e19\u0e49\u0e33\u0e2e\u0e39"
    ],
    "wof:name":"Ban Nam Hu",
    "wof:placetype":"locality"
},
  "geometry": {"coordinates":[98.13825,19.294],"type":"Point"}
}