{
  "type": "Feature",
  "properties": {
    "gn:admin1_code":"0.0",
    "gn:asciiname":"Ban Chang",
    "gn:country_code":"TH",
    "gn:dem":25,
    "gn:feature_class":"P",
    "gn:feature_code":"PPL",
    "gn:name":"Ban Chang",
    "gn:population":0,
    "gn:timezone":"Asia/Bangkok",
    "iso:country":"TH",
    "name:ceb_x_preferred":[
        "Ban Chang"
    ],
    "wof:name":"Ban Chang",
    "wof:placetype":"locality"
},
  "geometry": {"coordinates":[99.34999999999999,7.58333],"type":"Point"}
}