{
  "type": "Feature",
  "properties": {
    "gn:admin1_code":"75.0",
    "gn:asciiname":"Ban Kok",
    "gn:country_code":"TH",
    "gn:dem":130,
    "gn:feature_class":"P",
    "gn:feature_code":"PPL",
    "gn:name":"Ban Kok",
    "gn:population":0,
    "gn:timezone":"Asia/Bangkok",
    "iso:country":"TH",
    "name:tha_x_preferred":[
        "\u0e1a\u0e49\u0e32\u0e19\u0e01\u0e2d\u0e01"
    ],
    "name:und_x_variant":[
        "Ban Ok",
        "Ban Kok"
    ],
    "wof:name":"Ban Kok",
    "wof:placetype":"locality"
},
  "geometry": {"coordinates":[104.46856,15.50453],"type":"Point"}
}