{
  "type": "Feature",
  "properties": {
    "gn:admin1_code":"68.0",
    "gn:asciiname":"Ban Bang Khwai",
    "gn:country_code":"TH",
    "gn:dem":38,
    "gn:feature_class":"P",
    "gn:feature_code":"PPL",
    "gn:name":"Ban Bang Khwai",
    "gn:population":0,
    "gn:timezone":"Asia/Bangkok",
    "iso:country":"TH",
    "name:tha_x_preferred":[
        "\u0e1a\u0e49\u0e32\u0e19\u0e1a\u0e32\u0e07\u0e04\u0e27\u0e32\u0e22"
    ],
    "name:und_x_variant":[
        "Bang Nom Khwai",
        "Ban Bang Nom Kwai",
        "Ban Bang Nom Khwai",
        "Ban Bang Khwai"
    ],
    "wof:name":"Ban Bang Khwai",
    "wof:placetype":"locality"
},
  "geometry": {"coordinates":[100.36622,6.72672],"type":"Point"}
}