{
  "type": "Feature",
  "properties": {
    "gn:admin1_code":"16.0",
    "gn:asciiname":"Ban Tha Kabak",
    "gn:country_code":"TH",
    "gn:dem":38,
    "gn:feature_class":"P",
    "gn:feature_code":"PPL",
    "gn:name":"Ban Tha Kabak",
    "gn:population":0,
    "gn:timezone":"Asia/Bangkok",
    "iso:country":"TH",
    "name:tha_x_preferred":[
        "\u0e1a\u0e49\u0e32\u0e19\u0e17\u0e48\u0e32\u0e01\u0e30\u0e1a\u0e32\u0e01"
    ],
    "wof:name":"Ban Tha Kabak",
    "wof:placetype":"locality"
},
  "geometry": {"coordinates":[100.25942000000001,15.93453],"type":"Point"}
}