{
  "type": "Feature",
  "properties": {
    "gn:admin1_code":"60.0",
    "gn:asciiname":"Ban Nuea Khlong",
    "gn:country_code":"TH",
    "gn:dem":38,
    "gn:feature_class":"P",
    "gn:feature_code":"PPL",
    "gn:name":"Ban Nuea Khlong",
    "gn:population":0,
    "gn:timezone":"Asia/Bangkok",
    "iso:country":"TH",
    "name:tha_x_preferred":[
        "\u0e1a\u0e49\u0e32\u0e19\u0e40\u0e2b\u0e19\u0e37\u0e2d\u0e04\u0e25\u0e2d\u0e07"
    ],
    "wof:name":"Ban Nuea Khlong",
    "wof:placetype":"locality"
},
  "geometry": {"coordinates":[99.20711,8.41333],"type":"Point"}
}