{
  "type": "Feature",
  "properties": {
    "gn:admin1_code":"27.0",
    "gn:asciiname":"Ban La Ko",
    "gn:country_code":"TH",
    "gn:dem":183,
    "gn:feature_class":"P",
    "gn:feature_code":"PPL",
    "gn:name":"Ban La Ko",
    "gn:population":0,
    "gn:timezone":"Asia/Bangkok",
    "iso:country":"TH",
    "name:tha_x_preferred":[
        "\u0e1a\u0e49\u0e32\u0e19\u0e25\u0e30\u0e01\u0e2d"
    ],
    "name:und_x_variant":[
        "Ban Lako (1)"
    ],
    "wof:name":"Ban La Ko",
    "wof:placetype":"locality"
},
  "geometry": {"coordinates":[102.40336000000001,14.95517],"type":"Point"}
}