{
  "type": "Feature",
  "properties": {
    "gn:admin1_code":"11.0",
    "gn:asciiname":"Ban Mo Suea Du",
    "gn:country_code":"TH",
    "gn:dem":125,
    "gn:feature_class":"P",
    "gn:feature_code":"PPL",
    "gn:name":"Ban Mo Suea Du",
    "gn:population":0,
    "gn:timezone":"Asia/Bangkok",
    "iso:country":"TH",
    "name:tha_x_preferred":[
        "\u0e1a\u0e49\u0e32\u0e19\u0e21\u0e2d\u0e40\u0e2a\u0e37\u0e2d\u0e14\u0e38"
    ],
    "wof:lang_x_official":[
        "tha"
    ],
    "wof:lang_x_spoken":[
        "tha"
    ],
    "wof:name":"Ban Mo Suea Du",
    "wof:placetype":"locality"
},
  "geometry": {"coordinates":[99.36461,16.55806],"type":"Point"}
}