{
  "type": "Feature",
  "properties": {
    "gn:admin1_code":"10.0",
    "gn:asciiname":"Ban Tha Thong",
    "gn:country_code":"TH",
    "gn:dem":66,
    "gn:feature_class":"P",
    "gn:feature_code":"PPL",
    "gn:name":"Ban Tha Thong",
    "gn:population":0,
    "gn:timezone":"Asia/Bangkok",
    "iso:country":"TH",
    "name:tha_x_preferred":[
        "\u0e1a\u0e49\u0e32\u0e19\u0e17\u0e48\u0e32\u0e17\u0e2d\u0e07"
    ],
    "name:und_x_variant":[
        "B\u0101n Tha Thaung",
        "Ban Tha Thong"
    ],
    "wof:name":"Ban Tha Thong",
    "wof:placetype":"locality"
},
  "geometry": {"coordinates":[100.11756,17.56311],"type":"Point"}
}