{
  "type": "Feature",
  "properties": {
    "gn:admin1_code":"38.0",
    "gn:asciiname":"Ban Bang Maduea",
    "gn:cc2":"TH",
    "gn:country_code":"TH",
    "gn:dem":7,
    "gn:feature_class":"P",
    "gn:feature_code":"PPL",
    "gn:name":"Ban Bang Maduea",
    "gn:population":0,
    "gn:timezone":"Asia/Bangkok",
    "iso:country":"TH",
    "name:tha_x_preferred":[
        "\u0e1a\u0e49\u0e32\u0e19\u0e1a\u0e32\u0e07\u0e21\u0e30\u0e40\u0e14\u0e37\u0e48\u0e2d"
    ],
    "name:und_x_variant":[
        "Ban Bang Madua",
        "Ban Bang Maduea"
    ],
    "wof:name":"Ban Bang Maduea",
    "wof:placetype":"locality"
},
  "geometry": {"coordinates":[100.4207,13.86634],"type":"Point"}
}