{
  "type": "Feature",
  "properties": {
    "gn:admin1_code":"25.0",
    "gn:asciiname":"Ban Kut Sa Noi",
    "gn:country_code":"TH",
    "gn:dem":153,
    "gn:feature_class":"P",
    "gn:feature_code":"PPL",
    "gn:name":"Ban Kut Sa Noi",
    "gn:population":0,
    "gn:timezone":"Asia/Bangkok",
    "iso:country":"TH",
    "name:tha_x_preferred":[
        "\u0e1a\u0e49\u0e32\u0e19\u0e01\u0e38\u0e14\u0e2a\u0e23\u0e30\u0e19\u0e49\u0e2d\u0e22"
    ],
    "wof:name":"Ban Kut Sa Noi",
    "wof:placetype":"locality"
},
  "geometry": {"coordinates":[103.94247,16.26825],"type":"Point"}
}