{
  "type": "Feature",
  "properties": {
    "gn:admin1_code":"76.0",
    "gn:asciiname":"Ban Thon Na Lap",
    "gn:country_code":"TH",
    "gn:dem":169,
    "gn:feature_class":"P",
    "gn:feature_code":"PPL",
    "gn:name":"Ban Thon Na Lap",
    "gn:population":0,
    "gn:timezone":"Asia/Bangkok",
    "iso:country":"TH",
    "name:tha_x_preferred":[
        "\u0e1a\u0e49\u0e32\u0e19\u0e16\u0e48\u0e2d\u0e19\u0e19\u0e32\u0e25\u0e31\u0e1a"
    ],
    "wof:name":"Ban Thon Na Lap",
    "wof:placetype":"locality"
},
  "geometry": {"coordinates":[103.20828,17.84358],"type":"Point"}
}