{
  "type": "Feature",
  "properties": {
    "gn:admin1_code":"64.0",
    "gn:asciiname":"Ban Trok Khae",
    "gn:country_code":"TH",
    "gn:dem":44,
    "gn:feature_class":"P",
    "gn:feature_code":"PPL",
    "gn:name":"Ban Trok Khae",
    "gn:population":0,
    "gn:timezone":"Asia/Bangkok",
    "iso:country":"TH",
    "name:tha_x_preferred":[
        "\u0e1a\u0e49\u0e32\u0e19\u0e15\u0e23\u0e2d\u0e01\u0e41\u0e04"
    ],
    "wof:name":"Ban Trok Khae",
    "wof:placetype":"locality"
},
  "geometry": {"coordinates":[99.56186,8.42733],"type":"Point"}
}