{
  "type": "Feature",
  "properties": {
    "gn:admin1_code":"44.0",
    "gn:asciiname":"Ban Don Si Non",
    "gn:country_code":"TH",
    "gn:dem":6,
    "gn:feature_class":"P",
    "gn:feature_code":"PPL",
    "gn:name":"Ban Don Si Non",
    "gn:population":0,
    "gn:timezone":"Asia/Bangkok",
    "iso:country":"TH",
    "name:tha_x_preferred":[
        "\u0e1a\u0e49\u0e32\u0e19\u0e14\u0e2d\u0e19\u0e2a\u0e35\u0e19\u0e19\u0e17\u0e4c"
    ],
    "wof:name":"Ban Don Si Non",
    "wof:placetype":"locality"
},
  "geometry": {"coordinates":[101.09806,13.603],"type":"Point"}
}