{
  "type": "Feature",
  "properties": {
    "gn:admin1_code":"13.0",
    "gn:asciiname":"Ban Noen Ban",
    "gn:country_code":"TH",
    "gn:dem":45,
    "gn:feature_class":"P",
    "gn:feature_code":"PPL",
    "gn:name":"Ban Noen Ban",
    "gn:population":0,
    "gn:timezone":"Asia/Bangkok",
    "iso:country":"TH",
    "name:tha_x_preferred":[
        "\u0e1a\u0e49\u0e32\u0e19\u0e40\u0e19\u0e34\u0e19\u0e1a\u0e49\u0e32\u0e19"
    ],
    "wof:name":"Ban Noen Ban",
    "wof:placetype":"locality"
},
  "geometry": {"coordinates":[100.05638999999999,16.22847],"type":"Point"}
}