{
  "type": "Feature",
  "properties": {
    "gn:admin1_code":"30.0",
    "gn:asciiname":"Ban I Kaeo",
    "gn:country_code":"TH",
    "gn:dem":157,
    "gn:feature_class":"P",
    "gn:feature_code":"PPL",
    "gn:name":"Ban I Kaeo",
    "gn:population":0,
    "gn:timezone":"Asia/Bangkok",
    "iso:country":"TH",
    "name:tha_x_preferred":[
        "\u0e1a\u0e49\u0e32\u0e19\u0e2d\u0e35\u0e41\u0e01\u0e49\u0e27"
    ],
    "wof:name":"Ban I Kaeo",
    "wof:placetype":"locality"
},
  "geometry": {"coordinates":[104.10556,15.14083],"type":"Point"}
}