{
  "type": "Feature",
  "properties": {
    "gn:admin1_code":"1.0",
    "gn:asciiname":"Ban Kaeng Hom",
    "gn:country_code":"TH",
    "gn:dem":977,
    "gn:feature_class":"P",
    "gn:feature_code":"PPL",
    "gn:name":"Ban Kaeng Hom",
    "gn:population":0,
    "gn:timezone":"Asia/Bangkok",
    "iso:country":"TH",
    "name:tha_x_preferred":[
        "\u0e1a\u0e49\u0e32\u0e19\u0e41\u0e01\u0e07\u0e2b\u0e2d\u0e21"
    ],
    "wof:name":"Ban Kaeng Hom",
    "wof:placetype":"locality"
},
  "geometry": {"coordinates":[98.20031,19.18572],"type":"Point"}
}