{
  "type": "Feature",
  "properties": {
    "gn:admin1_code":"46.0",
    "gn:asciiname":"Ban Rong Ngan Namtan",
    "gn:country_code":"TH",
    "gn:dem":51,
    "gn:feature_class":"P",
    "gn:feature_code":"PPL",
    "gn:name":"Ban Rong Ngan Namtan",
    "gn:population":0,
    "gn:timezone":"Asia/Bangkok",
    "iso:country":"TH",
    "name:tha_x_preferred":[
        "\u0e1a\u0e49\u0e32\u0e19\u0e42\u0e23\u0e07\u0e07\u0e32\u0e19\u0e19\u0e49\u0e33\u0e15\u0e32\u0e25"
    ],
    "wof:name":"Ban Rong Ngan Namtan",
    "wof:placetype":"locality"
},
  "geometry": {"coordinates":[101.00749999999999,12.76867],"type":"Point"}
}