{
  "type": "Feature",
  "properties": {
    "gn:admin1_code":"47.0",
    "gn:asciiname":"Ban Khao Mai Nuan",
    "gn:country_code":"TH",
    "gn:dem":50,
    "gn:feature_class":"P",
    "gn:feature_code":"PPL",
    "gn:name":"Ban Khao Mai Nuan",
    "gn:population":0,
    "gn:timezone":"Asia/Bangkok",
    "iso:country":"TH",
    "name:tha_x_preferred":[
        "\u0e1a\u0e49\u0e32\u0e19\u0e40\u0e02\u0e32\u0e44\u0e21\u0e49\u0e19\u0e27\u0e25"
    ],
    "wof:name":"Ban Khao Mai Nuan",
    "wof:placetype":"locality"
},
  "geometry": {"coordinates":[101.51056,13.01639],"type":"Point"}
}