{
  "type": "Feature",
  "properties": {
    "gn:admin1_code":"12.0",
    "gn:asciiname":"Ban Mai Lam Kradon",
    "gn:country_code":"TH",
    "gn:dem":81,
    "gn:feature_class":"P",
    "gn:feature_code":"PPL",
    "gn:name":"Ban Mai Lam Kradon",
    "gn:population":0,
    "gn:timezone":"Asia/Bangkok",
    "iso:country":"TH",
    "name:tha_x_preferred":[
        "\u0e1a\u0e49\u0e32\u0e19\u0e43\u0e2b\u0e21\u0e48\u0e25\u0e33\u0e01\u0e23\u0e30\u0e42\u0e14\u0e19"
    ],
    "wof:name":"Ban Mai Lam Kradon",
    "wof:placetype":"locality"
},
  "geometry": {"coordinates":[100.60639,16.84317],"type":"Point"}
}