{
  "type": "Feature",
  "properties": {
    "gn:admin1_code":"23.0",
    "gn:asciiname":"Ban Kham Dok Son",
    "gn:country_code":"TH",
    "gn:dem":195,
    "gn:feature_class":"P",
    "gn:feature_code":"PPL",
    "gn:name":"Ban Kham Dok Son",
    "gn:population":0,
    "gn:timezone":"Asia/Bangkok",
    "iso:country":"TH",
    "name:tha_x_preferred":[
        "\u0e1a\u0e49\u0e32\u0e19\u0e04\u0e33\u0e14\u0e2d\u0e01\u0e0b\u0e49\u0e2d\u0e19"
    ],
    "wof:name":"Ban Kham Dok Son",
    "wof:placetype":"locality"
},
  "geometry": {"coordinates":[103.63261,16.68944],"type":"Point"}
}