{
  "type": "Feature",
  "properties": {
    "gn:admin1_code":"8.0",
    "gn:asciiname":"Ban San Phrabat",
    "gn:country_code":"TH",
    "gn:dem":168,
    "gn:feature_class":"P",
    "gn:feature_code":"PPL",
    "gn:name":"Ban San Phrabat",
    "gn:population":0,
    "gn:timezone":"Asia/Bangkok",
    "iso:country":"TH",
    "name:tha_x_preferred":[
        "Ban San Phrabat"
    ],
    "name:tha_x_variant":[
        "\u0e1a\u0e49\u0e32\u0e19\u0e2a\u0e31\u0e19\u0e1e\u0e23\u0e30\u0e1a\u0e32\u0e17"
    ],
    "wof:name":"Ban San Phrabat",
    "wof:placetype":"locality"
},
  "geometry": {"coordinates":[98.98694999999999,17.06658],"type":"Point"}
}