{
  "type": "Feature",
  "properties": {
    "gn:admin1_code":"63.0",
    "gn:asciiname":"Ban Hua Non Wat",
    "gn:country_code":"TH",
    "gn:dem":46,
    "gn:feature_class":"P",
    "gn:feature_code":"PPL",
    "gn:name":"Ban Hua Non Wat",
    "gn:population":0,
    "gn:timezone":"Asia/Bangkok",
    "iso:country":"TH",
    "name:tha_x_preferred":[
        "\u0e1a\u0e49\u0e32\u0e19\u0e2b\u0e31\u0e27\u0e19\u0e2d\u0e19\u0e27\u0e31\u0e14"
    ],
    "wof:name":"Ban Hua Non Wat",
    "wof:placetype":"locality"
},
  "geometry": {"coordinates":[99.03542,8.18725],"type":"Point"}
}