{
  "type": "Feature",
  "properties": {
    "gn:admin1_code":"48.0",
    "gn:asciiname":"Ban Tha Khlaeng",
    "gn:country_code":"TH",
    "gn:dem":11,
    "gn:feature_class":"P",
    "gn:feature_code":"PPL",
    "gn:name":"Ban Tha Khlaeng",
    "gn:population":0,
    "gn:timezone":"Asia/Bangkok",
    "iso:country":"TH",
    "name:tha_x_preferred":[
        "\u0e1a\u0e49\u0e32\u0e19\u0e17\u0e48\u0e32\u0e41\u0e04\u0e25\u0e07"
    ],
    "name:und_x_variant":[
        "Ban Tha Khraeng",
        "Ban Tha Khlaeng"
    ],
    "wof:name":"Ban Tha Khlaeng",
    "wof:placetype":"locality"
},
  "geometry": {"coordinates":[101.88731,12.61419],"type":"Point"}
}