{
  "type": "Feature",
  "properties": {
    "gn:admin1_code":"44.0",
    "gn:asciiname":"Ban Khao Sam Sip",
    "gn:country_code":"TH",
    "gn:dem":87,
    "gn:feature_class":"P",
    "gn:feature_code":"PPL",
    "gn:name":"Ban Khao Sam Sip",
    "gn:population":0,
    "gn:timezone":"Asia/Bangkok",
    "iso:country":"TH",
    "name:tha_x_preferred":[
        "\u0e1a\u0e49\u0e32\u0e19\u0e40\u0e02\u0e32\u0e2a\u0e32\u0e21\u0e2a\u0e34\u0e1a"
    ],
    "wof:name":"Ban Khao Sam Sip",
    "wof:placetype":"locality"
},
  "geometry": {"coordinates":[101.75181000000001,13.584],"type":"Point"}
}