{
  "type": "Feature",
  "properties": {
    "gn:admin1_code":"48.0",
    "gn:asciiname":"Ban Wang Wian",
    "gn:country_code":"TH",
    "gn:dem":10,
    "gn:feature_class":"P",
    "gn:feature_code":"PPL",
    "gn:name":"Ban Wang Wian",
    "gn:population":0,
    "gn:timezone":"Asia/Bangkok",
    "iso:country":"TH",
    "name:tha_x_preferred":[
        "\u0e1a\u0e49\u0e32\u0e19\u0e27\u0e31\u0e07\u0e40\u0e27\u0e35\u0e22\u0e19"
    ],
    "wof:name":"Ban Wang Wian",
    "wof:placetype":"locality"
},
  "geometry": {"coordinates":[101.9645,12.68833],"type":"Point"}
}