{
  "type": "Feature",
  "properties": {
    "gn:admin1_code":"3.0",
    "gn:asciiname":"Ban Mae Kon",
    "gn:country_code":"TH",
    "gn:dem":424,
    "gn:feature_class":"P",
    "gn:feature_code":"PPL",
    "gn:name":"Ban Mae Kon",
    "gn:population":0,
    "gn:timezone":"Asia/Bangkok",
    "iso:country":"TH",
    "name:tha_x_preferred":[
        "\u0e1a\u0e49\u0e32\u0e19\u0e41\u0e21\u0e48\u0e01\u0e23\u0e13\u0e4c"
    ],
    "name:und_x_variant":[
        "B\u0101n Mea Gaun",
        "Ban Mae Kon"
    ],
    "wof:name":"Ban Mae Kon",
    "wof:placetype":"locality"
},
  "geometry": {"coordinates":[99.74231,19.84808],"type":"Point"}
}