{
  "type": "Feature",
  "properties": {
    "gn:admin1_code":"52.0",
    "gn:asciiname":"Ban Bo Trakhro",
    "gn:country_code":"TH",
    "gn:dem":9,
    "gn:feature_class":"P",
    "gn:feature_code":"PPL",
    "gn:name":"Ban Bo Trakhro",
    "gn:population":0,
    "gn:timezone":"Asia/Bangkok",
    "iso:country":"TH",
    "name:tha_x_preferred":[
        "\u0e1a\u0e49\u0e32\u0e19\u0e1a\u0e48\u0e2d\u0e15\u0e23\u0e30\u0e04\u0e23\u0e49\u0e2d"
    ],
    "name:und_x_variant":[
        "Ban Bo Takhro"
    ],
    "wof:name":"Ban Bo Trakhro",
    "wof:placetype":"locality"
},
  "geometry": {"coordinates":[99.83277,13.43745],"type":"Point"}
}