{
  "type": "Feature",
  "properties": {
    "gn:admin1_code":"26.0",
    "gn:asciiname":"Ban Taluk Khun",
    "gn:country_code":"TH",
    "gn:dem":289,
    "gn:feature_class":"P",
    "gn:feature_code":"PPL",
    "gn:name":"Ban Taluk Khun",
    "gn:population":0,
    "gn:timezone":"Asia/Bangkok",
    "iso:country":"TH",
    "name:tha_x_preferred":[
        "\u0e1a\u0e49\u0e32\u0e19\u0e15\u0e25\u0e38\u0e01\u0e04\u0e39\u0e13"
    ],
    "wof:name":"Ban Taluk Khun",
    "wof:placetype":"locality"
},
  "geometry": {"coordinates":[101.59558,15.58839],"type":"Point"}
}