{
  "type": "Feature",
  "properties": {
    "gn:admin1_code":"66.0",
    "gn:asciiname":"Ban Nong Len",
    "gn:country_code":"TH",
    "gn:dem":55,
    "gn:feature_class":"P",
    "gn:feature_code":"PPL",
    "gn:name":"Ban Nong Len",
    "gn:population":0,
    "gn:timezone":"Asia/Bangkok",
    "iso:country":"TH",
    "name:tha_x_preferred":[
        "\u0e1a\u0e49\u0e32\u0e19\u0e2b\u0e19\u0e2d\u0e07\u0e40\u0e25\u0e19"
    ],
    "wof:name":"Ban Nong Len",
    "wof:placetype":"locality"
},
  "geometry": {"coordinates":[100.09845,7.25515],"type":"Point"}
}