{
  "type": "Feature",
  "properties": {
    "gn:admin1_code":"11.0",
    "gn:asciiname":"Ban Noen Sa-at",
    "gn:country_code":"TH",
    "gn:dem":44,
    "gn:feature_class":"P",
    "gn:feature_code":"PPL",
    "gn:name":"Ban Noen Sa-at",
    "gn:population":0,
    "gn:timezone":"Asia/Bangkok",
    "iso:country":"TH",
    "name:tha_x_preferred":[
        "\u0e1a\u0e49\u0e32\u0e19\u0e40\u0e19\u0e34\u0e19\u0e2a\u0e30\u0e2d\u0e32\u0e14"
    ],
    "wof:name":"Ban Noen Sa-at",
    "wof:placetype":"locality"
},
  "geometry": {"coordinates":[100.02828,16.21958],"type":"Point"}
}