{
  "type": "Feature",
  "properties": {
    "gn:admin1_code":"66.0",
    "gn:asciiname":"Ban Pak Pra",
    "gn:country_code":"TH",
    "gn:dem":4,
    "gn:feature_class":"P",
    "gn:feature_code":"PPL",
    "gn:name":"Ban Pak Pra",
    "gn:population":0,
    "gn:timezone":"Asia/Bangkok",
    "iso:country":"TH",
    "name:tha_x_preferred":[
        "\u0e1a\u0e49\u0e32\u0e19\u0e1b\u0e32\u0e01\u0e1b\u0e23\u0e30"
    ],
    "name:und_x_variant":[
        "Ban Pak Prak",
        "Ban Pak Pra (1)",
        "Ban Pak Pra"
    ],
    "wof:lang_x_official":[
        "tha"
    ],
    "wof:lang_x_spoken":[
        "tha"
    ],
    "wof:name":"Ban Pak Pra",
    "wof:placetype":"locality"
},
  "geometry": {"coordinates":[100.14521999999999,7.70181],"type":"Point"}
}