{
  "type": "Feature",
  "properties": {
    "gn:admin1_code":"74",
    "gn:asciiname":"Ban Sila Khao",
    "gn:country_code":"TH",
    "gn:dem":28,
    "gn:feature_class":"P",
    "gn:feature_code":"PPL",
    "gn:name":"Ban Sila Khao",
    "gn:population":0,
    "gn:timezone":"Asia/Bangkok",
    "iso:country":"TH",
    "name:tha_x_preferred":[
        "\u0e1a\u0e49\u0e32\u0e19\u0e28\u0e34\u0e25\u0e32\u0e02\u0e32\u0e27"
    ],
    "wof:name":"Ban Sila Khao",
    "wof:placetype":"locality"
},
  "geometry": {"coordinates":[101.74933,13.84597],"type":"Point"}
}