{
  "type": "Feature",
  "properties": {
    "gn:admin1_code":"34",
    "gn:asciiname":"Ban Noen Sawang",
    "gn:country_code":"TH",
    "gn:dem":63,
    "gn:feature_class":"P",
    "gn:feature_code":"PPL",
    "gn:name":"Ban Noen Sawang",
    "gn:population":0,
    "gn:timezone":"Asia/Bangkok",
    "iso:country":"TH",
    "name:tha_x_preferred":[
        "\u0e1a\u0e49\u0e32\u0e19\u0e40\u0e19\u0e34\u0e19\u0e2a\u0e27\u0e48\u0e32\u0e07"
    ],
    "wof:name":"Ban Noen Sawang",
    "wof:placetype":"locality"
},
  "geometry": {"coordinates":[100.96138999999999,15.0505],"type":"Point"}
}