{
  "type": "Feature",
  "properties": {
    "gn:admin1_code":"25.0",
    "gn:asciiname":"Ban That Prathap",
    "gn:country_code":"TH",
    "gn:dem":142,
    "gn:feature_class":"P",
    "gn:feature_code":"PPL",
    "gn:name":"Ban That Prathap",
    "gn:population":0,
    "gn:timezone":"Asia/Bangkok",
    "iso:country":"TH",
    "name:tha_x_preferred":[
        "\u0e1a\u0e49\u0e32\u0e19\u0e18\u0e32\u0e15\u0e38\u0e1b\u0e23\u0e30\u0e17\u0e31\u0e1a"
    ],
    "wof:name":"Ban That Prathap",
    "wof:placetype":"locality"
},
  "geometry": {"coordinates":[103.70506,16.08525],"type":"Point"}
}