{
  "type": "Feature",
  "properties": {
    "gn:admin1_code":"73.0",
    "gn:asciiname":"Ban I Ut",
    "gn:country_code":"TH",
    "gn:dem":166,
    "gn:feature_class":"P",
    "gn:feature_code":"PPL",
    "gn:name":"Ban I Ut",
    "gn:population":0,
    "gn:timezone":"Asia/Bangkok",
    "iso:country":"TH",
    "name:tha_x_preferred":[
        "\u0e1a\u0e49\u0e32\u0e19\u0e2d\u0e35\u0e2d\u0e39\u0e14"
    ],
    "wof:name":"Ban I Ut",
    "wof:placetype":"locality"
},
  "geometry": {"coordinates":[104.32459,17.53642],"type":"Point"}
}