{
  "type": "Feature",
  "properties": {
    "gn:admin1_code":"28.0",
    "gn:asciiname":"Ban Trat",
    "gn:country_code":"TH",
    "gn:dem":133,
    "gn:feature_class":"P",
    "gn:feature_code":"PPL",
    "gn:name":"Ban Trat",
    "gn:population":0,
    "gn:timezone":"Asia/Bangkok",
    "iso:country":"TH",
    "name:tha_x_preferred":[
        "\u0e1a\u0e49\u0e32\u0e19\u0e15\u0e23\u0e32\u0e14"
    ],
    "name:und_x_variant":[
        "Ban Tat"
    ],
    "wof:name":"Ban Trat",
    "wof:placetype":"locality"
},
  "geometry": {"coordinates":[103.45305999999999,15.29097],"type":"Point"}
}