{
  "type": "Feature",
  "properties": {
    "gn:admin1_code":"1.0",
    "gn:asciiname":"Ban Pha Tho",
    "gn:country_code":"TH",
    "gn:dem":682,
    "gn:feature_class":"P",
    "gn:feature_code":"PPL",
    "gn:name":"Ban Pha Tho",
    "gn:population":0,
    "gn:timezone":"Asia/Bangkok",
    "iso:country":"TH",
    "name:tha_x_preferred":[
        "\u0e1a\u0e49\u0e32\u0e19\u0e1e\u0e30\u0e42\u0e17"
    ],
    "wof:name":"Ban Pha Tho",
    "wof:placetype":"locality"
},
  "geometry": {"coordinates":[97.8005,18.67147000000001],"type":"Point"}
}