{
  "type": "Feature",
  "properties": {
    "gn:admin1_code":"23.0",
    "gn:asciiname":"Ban Hua Non Ko",
    "gn:country_code":"TH",
    "gn:dem":146,
    "gn:feature_class":"P",
    "gn:feature_code":"PPL",
    "gn:name":"Ban Hua Non Ko",
    "gn:population":0,
    "gn:timezone":"Asia/Bangkok",
    "iso:country":"TH",
    "name:tha_x_preferred":[
        "\u0e1a\u0e49\u0e32\u0e19\u0e2b\u0e31\u0e27\u0e42\u0e19\u0e19\u0e42\u0e01"
    ],
    "wof:name":"Ban Hua Non Ko",
    "wof:placetype":"locality"
},
  "geometry": {"coordinates":[103.52003000000001,16.45189],"type":"Point"}
}