{
  "type": "Feature",
  "properties": {
    "gn:admin1_code":"1.0",
    "gn:asciiname":"Ban Thung Kong Mu",
    "gn:country_code":"TH",
    "gn:dem":206,
    "gn:feature_class":"P",
    "gn:feature_code":"PPL",
    "gn:name":"Ban Thung Kong Mu",
    "gn:population":0,
    "gn:timezone":"Asia/Bangkok",
    "iso:country":"TH",
    "name:tha_x_preferred":[
        "\u0e1a\u0e49\u0e32\u0e19\u0e17\u0e38\u0e48\u0e07\u0e01\u0e2d\u0e07\u0e21\u0e39"
    ],
    "name:und_x_variant":[
        "Ban Gaung Mu",
        "Ban Kong Mu",
        "Ban Thung Kong Mu"
    ],
    "wof:name":"Ban Thung Kong Mu",
    "wof:placetype":"locality"
},
  "geometry": {"coordinates":[97.95186,19.33203],"type":"Point"}
}