{
  "type": "Feature",
  "properties": {
    "gn:admin1_code":"75.0",
    "gn:asciiname":"Ban Pa Mong Noi",
    "gn:country_code":"TH",
    "gn:dem":148,
    "gn:feature_class":"P",
    "gn:feature_code":"PPL",
    "gn:name":"Ban Pa Mong Noi",
    "gn:population":0,
    "gn:timezone":"Asia/Bangkok",
    "iso:country":"TH",
    "name:tha_x_preferred":[
        "\u0e1a\u0e49\u0e32\u0e19\u0e1b\u0e48\u0e32\u0e42\u0e21\u0e07\u0e19\u0e49\u0e2d\u0e22"
    ],
    "name:und_x_variant":[
        "Ban Pa Mong"
    ],
    "wof:name":"Ban Pa Mong Noi",
    "wof:placetype":"locality"
},
  "geometry": {"coordinates":[104.98978,14.96269],"type":"Point"}
}