{
  "type": "Feature",
  "properties": {
    "gn:admin1_code":"8.0",
    "gn:asciiname":"Ban Pha Te",
    "gn:country_code":"TH",
    "gn:dem":256,
    "gn:feature_class":"P",
    "gn:feature_code":"PPL",
    "gn:name":"Ban Pha Te",
    "gn:population":0,
    "gn:timezone":"Asia/Bangkok",
    "iso:country":"TH",
    "name:tha_x_preferred":[
        "\u0e1a\u0e49\u0e32\u0e19\u0e1c\u0e32\u0e40\u0e15\u0e4a\u0e30"
    ],
    "wof:name":"Ban Pha Te",
    "wof:placetype":"locality"
},
  "geometry": {"coordinates":[98.62882999999999,16.67722],"type":"Point"}
}