{
  "type": "Feature",
  "properties": {
    "gn:admin1_code":"2.0",
    "gn:asciiname":"Ban Nong Pla Man",
    "gn:country_code":"TH",
    "gn:dem":439,
    "gn:feature_class":"P",
    "gn:feature_code":"PPL",
    "gn:name":"Ban Nong Pla Man",
    "gn:population":0,
    "gn:timezone":"Asia/Bangkok",
    "iso:country":"TH",
    "name:tha_x_preferred":[
        "\u0e1a\u0e49\u0e32\u0e19\u0e2b\u0e19\u0e2d\u0e07\u0e1b\u0e25\u0e32\u0e21\u0e31\u0e19"
    ],
    "wof:name":"Ban Nong Pla Man",
    "wof:placetype":"locality"
},
  "geometry": {"coordinates":[99.17189,19.36511],"type":"Point"}
}