{
  "type": "Feature",
  "properties": {
    "gn:admin1_code":"41.0",
    "gn:asciiname":"Ban Sai",
    "gn:country_code":"TH",
    "gn:dem":408,
    "gn:feature_class":"P",
    "gn:feature_code":"PPL",
    "gn:name":"Ban Sai",
    "gn:population":0,
    "gn:timezone":"Asia/Bangkok",
    "iso:country":"TH",
    "name:tha_x_preferred":[
        "\u0e1a\u0e49\u0e32\u0e19\u0e17\u0e23\u0e32\u0e22"
    ],
    "wof:name":"Ban Sai",
    "wof:placetype":"locality"
},
  "geometry": {"coordinates":[100.32736,19.49014],"type":"Point"}
}