{
  "type": "Feature",
  "properties": {
    "gn:admin1_code":"6.0",
    "gn:asciiname":"Ban Pong Khok",
    "gn:country_code":"TH",
    "gn:dem":274,
    "gn:feature_class":"P",
    "gn:feature_code":"PPL",
    "gn:name":"Ban Pong Khok",
    "gn:population":0,
    "gn:timezone":"Asia/Bangkok",
    "iso:country":"TH",
    "name:tha_x_preferred":[
        "\u0e1a\u0e49\u0e32\u0e19\u0e1b\u0e07\u0e04\u0e01"
    ],
    "wof:name":"Ban Pong Khok",
    "wof:placetype":"locality"
},
  "geometry": {"coordinates":[99.98564,18.745],"type":"Point"}
}