{
  "type": "Feature",
  "properties": {
    "gn:admin1_code":"48.0",
    "gn:asciiname":"Ban Nong Makha 1",
    "gn:country_code":"TH",
    "gn:dem":73,
    "gn:feature_class":"P",
    "gn:feature_code":"PPL",
    "gn:name":"Ban Nong Makha 1",
    "gn:population":0,
    "gn:timezone":"Asia/Bangkok",
    "iso:country":"TH",
    "name:tha_x_preferred":[
        "\u0e1a\u0e49\u0e32\u0e19\u0e2b\u0e19\u0e2d\u0e07\u0e21\u0e30\u0e04\u0e48\u0e32 \u0e2b\u0e19\u0e36\u0e48\u0e07"
    ],
    "name:und_x_variant":[
        "Ban Nong Makha Nueng"
    ],
    "wof:name":"Ban Nong Makha 1",
    "wof:placetype":"locality"
},
  "geometry": {"coordinates":[101.79122,12.99372],"type":"Point"}
}