{
  "type": "Feature",
  "properties": {
    "gn:admin1_code":"2.0",
    "gn:asciiname":"Ban Mae Tho Luang",
    "gn:country_code":"TH",
    "gn:dem":1115,
    "gn:feature_class":"P",
    "gn:feature_code":"PPL",
    "gn:name":"Ban Mae Tho Luang",
    "gn:population":0,
    "gn:timezone":"Asia/Bangkok",
    "iso:country":"TH",
    "name:tha_x_preferred":[
        "\u0e1a\u0e49\u0e32\u0e19\u0e41\u0e21\u0e48\u0e42\u0e16\u0e2b\u0e25\u0e27\u0e07"
    ],
    "name:und_x_variant":[
        "Ban Mae Tho"
    ],
    "wof:name":"Ban Mae Tho Luang",
    "wof:placetype":"locality"
},
  "geometry": {"coordinates":[98.19386,18.23978],"type":"Point"}
}