{
  "type": "Feature",
  "properties": {
    "gn:admin1_code":"47.0",
    "gn:asciiname":"Ban Chak Nok",
    "gn:country_code":"TH",
    "gn:dem":101,
    "gn:feature_class":"P",
    "gn:feature_code":"PPL",
    "gn:name":"Ban Chak Nok",
    "gn:population":0,
    "gn:timezone":"Asia/Bangkok",
    "iso:country":"TH",
    "name:tha_x_preferred":[
        "\u0e1a\u0e49\u0e32\u0e19\u0e0a\u0e32\u0e01\u0e19\u0e2d\u0e01"
    ],
    "wof:name":"Ban Chak Nok",
    "wof:placetype":"locality"
},
  "geometry": {"coordinates":[101.09694,12.88389],"type":"Point"}
}