{
  "type": "Feature",
  "properties": {
    "gn:admin1_code":"41.0",
    "gn:asciiname":"Ban Nam Wao",
    "gn:country_code":"TH",
    "gn:dem":672,
    "gn:feature_class":"P",
    "gn:feature_code":"PPL",
    "gn:name":"Ban Nam Wao",
    "gn:population":0,
    "gn:timezone":"Asia/Bangkok",
    "iso:country":"TH",
    "wof:name":"Ban Nam Wao",
    "wof:placetype":"locality"
},
  "geometry": {"coordinates":[100.59999999999999,19.11667000000001],"type":"Point"}
}