{
  "type": "Feature",
  "properties": {
    "gn:admin1_code":"41.0",
    "gn:asciiname":"Ban Mai San Klang",
    "gn:country_code":"TH",
    "gn:dem":410,
    "gn:feature_class":"P",
    "gn:feature_code":"PPL",
    "gn:name":"Ban Mai San Klang",
    "gn:population":0,
    "gn:timezone":"Asia/Bangkok",
    "iso:country":"TH",
    "name:tha_x_preferred":[
        "\u0e1a\u0e49\u0e32\u0e19\u0e43\u0e2b\u0e21\u0e48\u0e2a\u0e31\u0e19\u0e01\u0e25\u0e32\u0e07"
    ],
    "wof:name":"Ban Mai San Klang",
    "wof:placetype":"locality"
},
  "geometry": {"coordinates":[100.06403,19.17678],"type":"Point"}
}