{
  "type": "Feature",
  "properties": {
    "gn:admin1_code":"50.0",
    "gn:asciiname":"Ban Mai Daeng Hu Chang",
    "gn:country_code":"TH",
    "gn:dem":24,
    "gn:feature_class":"P",
    "gn:feature_code":"PPL",
    "gn:name":"Ban Mai Daeng Hu Chang",
    "gn:population":0,
    "gn:timezone":"Asia/Bangkok",
    "iso:country":"TH",
    "name:tha_x_preferred":[
        "\u0e1a\u0e49\u0e32\u0e19\u0e44\u0e21\u0e49\u0e41\u0e14\u0e07\u0e2b\u0e39\u0e0a\u0e49\u0e32\u0e07"
    ],
    "wof:name":"Ban Mai Daeng Hu Chang",
    "wof:placetype":"locality"
},
  "geometry": {"coordinates":[99.69694,13.91906],"type":"Point"}
}