{
  "type": "Feature",
  "properties": {
    "gn:admin1_code":"48.0",
    "gn:asciiname":"Ban Huai Kabok Tia",
    "gn:cc2":"TH",
    "gn:country_code":"TH",
    "gn:dem":4,
    "gn:feature_class":"P",
    "gn:feature_code":"PPL",
    "gn:name":"Ban Huai Kabok Tia",
    "gn:population":0,
    "gn:timezone":"Asia/Bangkok",
    "iso:country":"TH",
    "name:und_x_variant":[
        "Ban Thai Kabok Tia",
        "Thai Kabok Tai",
        "Ban Huai Kabok Tia"
    ],
    "wof:name":"Ban Huai Kabok Tia",
    "wof:placetype":"locality"
},
  "geometry": {"coordinates":[102.09999999999999,12.58333],"type":"Point"}
}