{
  "type": "Feature",
  "properties": {
    "gn:admin1_code":"57.0",
    "gn:asciiname":"Ban Don Yai",
    "gn:country_code":"TH",
    "gn:dem":41,
    "gn:feature_class":"P",
    "gn:feature_code":"PPL",
    "gn:name":"Ban Don Yai",
    "gn:population":0,
    "gn:timezone":"Asia/Bangkok",
    "iso:country":"TH",
    "name:tha_x_preferred":[
        "\u0e1a\u0e49\u0e32\u0e19\u0e14\u0e2d\u0e19\u0e43\u0e2b\u0e0d\u0e48"
    ],
    "wof:name":"Ban Don Yai",
    "wof:placetype":"locality"
},
  "geometry": {"coordinates":[99.86257999999999,12.37536],"type":"Point"}
}