{
  "type": "Feature",
  "properties": {
    "gn:admin1_code":"1.0",
    "gn:asciiname":"Ban Makhuea Dan",
    "gn:country_code":"TH",
    "gn:dem":636,
    "gn:feature_class":"P",
    "gn:feature_code":"PPL",
    "gn:name":"Ban Makhuea Dan",
    "gn:population":0,
    "gn:timezone":"Asia/Bangkok",
    "iso:country":"TH",
    "name:tha_x_preferred":[
        "\u0e1a\u0e49\u0e32\u0e19\u0e21\u0e30\u0e40\u0e02\u0e37\u0e2d\u0e14\u0e31\u0e19"
    ],
    "name:und_x_variant":[
        "Ban Makhua Khan",
        "Ban Makhuea Dan"
    ],
    "wof:name":"Ban Makhuea Dan",
    "wof:placetype":"locality"
},
  "geometry": {"coordinates":[98.50727999999999,19.50789],"type":"Point"}
}