{
  "type": "Feature",
  "properties": {
    "gn:admin1_code":"4.0",
    "gn:asciiname":"Ban Na Pong",
    "gn:country_code":"TH",
    "gn:dem":748,
    "gn:feature_class":"P",
    "gn:feature_code":"PPL",
    "gn:name":"Ban Na Pong",
    "gn:population":0,
    "gn:timezone":"Asia/Bangkok",
    "iso:country":"TH",
    "name:tha_x_preferred":[
        "\u0e1a\u0e49\u0e32\u0e19\u0e19\u0e32\u0e42\u0e1b\u0e48\u0e07"
    ],
    "wof:name":"Ban Na Pong",
    "wof:placetype":"locality"
},
  "geometry": {"coordinates":[101.20576,19.20425],"type":"Point"}
}