{
  "type": "Feature",
  "properties": {
    "gn:admin1_code":"15.0",
    "gn:asciiname":"Ban Khun Kaeo",
    "gn:country_code":"TH",
    "gn:dem":38,
    "gn:feature_class":"P",
    "gn:feature_code":"PPL",
    "gn:name":"Ban Khun Kaeo",
    "gn:population":0,
    "gn:timezone":"Asia/Bangkok",
    "iso:country":"TH",
    "name:tha_x_preferred":[
        "\u0e1a\u0e49\u0e32\u0e19\u0e02\u0e38\u0e19\u0e41\u0e01\u0e49\u0e27"
    ],
    "wof:lang_x_official":[
        "tha"
    ],
    "wof:lang_x_spoken":[
        "tha"
    ],
    "wof:name":"Ban Khun Kaeo",
    "wof:placetype":"locality"
},
  "geometry": {"coordinates":[99.94781,15.31058],"type":"Point"}
}