{
  "type": "Feature",
  "properties": {
    "gn:admin1_code":"44.0",
    "gn:asciiname":"Ban Saphan Rot Fai",
    "gn:country_code":"TH",
    "gn:dem":4,
    "gn:feature_class":"P",
    "gn:feature_code":"PPL",
    "gn:name":"Ban Saphan Rot Fai",
    "gn:population":0,
    "gn:timezone":"Asia/Bangkok",
    "iso:country":"TH",
    "name:tha_x_preferred":[
        "\u0e1a\u0e49\u0e32\u0e19\u0e2a\u0e30\u0e1e\u0e32\u0e19\u0e23\u0e16\u0e44\u0e1f"
    ],
    "wof:name":"Ban Saphan Rot Fai",
    "wof:placetype":"locality"
},
  "geometry": {"coordinates":[101.08819,13.84619],"type":"Point"}
}