{
  "type": "Feature",
  "properties": {
    "gn:admin1_code":"22",
    "gn:asciiname":"Ban Non Tako",
    "gn:country_code":"TH",
    "gn:dem":195,
    "gn:feature_class":"P",
    "gn:feature_code":"PPL",
    "gn:name":"Ban Non Tako",
    "gn:population":0,
    "gn:timezone":"Asia/Bangkok",
    "iso:country":"TH",
    "name:tha_x_preferred":[
        "\u0e1a\u0e49\u0e32\u0e19\u0e42\u0e19\u0e19\u0e15\u0e30\u0e42\u0e01"
    ],
    "wof:name":"Ban Non Tako",
    "wof:placetype":"locality"
},
  "geometry": {"coordinates":[102.52864,15.75872],"type":"Point"}
}