{
  "type": "Feature",
  "properties": {
    "gn:admin1_code":"11.0",
    "gn:asciiname":"Ban Khlong Mot Daeng",
    "gn:country_code":"TH",
    "gn:dem":197,
    "gn:feature_class":"P",
    "gn:feature_code":"PPL",
    "gn:name":"Ban Khlong Mot Daeng",
    "gn:population":0,
    "gn:timezone":"Asia/Bangkok",
    "iso:country":"TH",
    "name:tha_x_preferred":[
        "\u0e1a\u0e49\u0e32\u0e19\u0e04\u0e25\u0e2d\u0e07\u0e21\u0e14\u0e41\u0e14\u0e07"
    ],
    "wof:name":"Ban Khlong Mot Daeng",
    "wof:placetype":"locality"
},
  "geometry": {"coordinates":[99.23788999999999,16.41358],"type":"Point"}
}