{
  "type": "Feature",
  "properties": {
    "gn:admin1_code":"48.0",
    "gn:asciiname":"Ban Thap Pati",
    "gn:cc2":"TH",
    "gn:country_code":"TH",
    "gn:dem":228,
    "gn:feature_class":"P",
    "gn:feature_code":"PPL",
    "gn:name":"Ban Thap Pati",
    "gn:population":0,
    "gn:timezone":"Asia/Bangkok",
    "iso:country":"TH",
    "name:und_x_variant":[
        "Thap Pati",
        "Tap Saloei",
        "Ban Thap Pati"
    ],
    "wof:name":"Ban Thap Pati",
    "wof:placetype":"locality"
},
  "geometry": {"coordinates":[102.43333,12.88333],"type":"Point"}
}