{
  "type": "Feature",
  "properties": {
    "gn:admin1_code":"2.0",
    "gn:asciiname":"Ban Mae Hom",
    "gn:country_code":"TH",
    "gn:dem":305,
    "gn:feature_class":"P",
    "gn:feature_code":"PPL",
    "gn:name":"Ban Mae Hom",
    "gn:population":0,
    "gn:timezone":"Asia/Bangkok",
    "iso:country":"TH",
    "name:tha_x_preferred":[
        "\u0e1a\u0e49\u0e32\u0e19\u0e41\u0e21\u0e48\u0e42\u0e2e\u0e21"
    ],
    "name:und_x_variant":[
        "B\u0101n Mea Hom",
        "Ban Mae Hom"
    ],
    "wof:name":"Ban Mae Hom",
    "wof:placetype":"locality"
},
  "geometry": {"coordinates":[99.09867,18.75569],"type":"Point"}
}