{
  "type": "Feature",
  "properties": {
    "gn:admin1_code":"27.0",
    "gn:asciiname":"Ban Phra Hua Bueng",
    "gn:country_code":"TH",
    "gn:dem":199,
    "gn:feature_class":"P",
    "gn:feature_code":"PPL",
    "gn:name":"Ban Phra Hua Bueng",
    "gn:population":0,
    "gn:timezone":"Asia/Bangkok",
    "iso:country":"TH",
    "name:tha_x_preferred":[
        "\u0e1a\u0e49\u0e32\u0e19\u0e1e\u0e23\u0e30\u0e2b\u0e31\u0e27\u0e1a\u0e36\u0e07"
    ],
    "name:und_x_variant":[
        "Ban Bung Pru",
        "B\u0101n Beung Preu",
        "Ban Phra Hua Bung",
        "Ban Phra Hua Bueng"
    ],
    "wof:name":"Ban Phra Hua Bueng",
    "wof:placetype":"locality"
},
  "geometry": {"coordinates":[101.84556000000001,15.159],"type":"Point"}
}