{
  "type": "Feature",
  "properties": {
    "gn:admin1_code":"64.0",
    "gn:asciiname":"Ban Chai Thung",
    "gn:country_code":"TH",
    "gn:dem":69,
    "gn:feature_class":"P",
    "gn:feature_code":"PPL",
    "gn:name":"Ban Chai Thung",
    "gn:population":0,
    "gn:timezone":"Asia/Bangkok",
    "iso:country":"TH",
    "name:tha_x_preferred":[
        "\u0e1a\u0e49\u0e32\u0e19\u0e0a\u0e32\u0e22\u0e17\u0e38\u0e48\u0e07"
    ],
    "wof:name":"Ban Chai Thung",
    "wof:placetype":"locality"
},
  "geometry": {"coordinates":[99.54067000000001,8.53514],"type":"Point"}
}