{
  "type": "Feature",
  "properties": {
    "gn:admin1_code":"48.0",
    "gn:asciiname":"Ban Talat Khom Bang",
    "gn:country_code":"TH",
    "gn:dem":19,
    "gn:feature_class":"P",
    "gn:feature_code":"PPL",
    "gn:name":"Ban Talat Khom Bang",
    "gn:population":0,
    "gn:timezone":"Asia/Bangkok",
    "iso:country":"TH",
    "name:tha_x_preferred":[
        "\u0e1a\u0e49\u0e32\u0e19\u0e15\u0e25\u0e32\u0e14\u0e04\u0e21\u0e1a\u0e32\u0e07"
    ],
    "wof:name":"Ban Talat Khom Bang",
    "wof:placetype":"locality"
},
  "geometry": {"coordinates":[102.15481,12.54872],"type":"Point"}
}