{
  "type": "Feature",
  "properties": {
    "gn:admin1_code":"26.0",
    "gn:asciiname":"Ban Mai Na Charoen",
    "gn:country_code":"TH",
    "gn:dem":248,
    "gn:feature_class":"P",
    "gn:feature_code":"PPL",
    "gn:name":"Ban Mai Na Charoen",
    "gn:population":0,
    "gn:timezone":"Asia/Bangkok",
    "iso:country":"TH",
    "name:tha_x_preferred":[
        "\u0e1a\u0e49\u0e32\u0e19\u0e43\u0e2b\u0e21\u0e48\u0e19\u0e32\u0e40\u0e08\u0e23\u0e34\u0e0d"
    ],
    "wof:name":"Ban Mai Na Charoen",
    "wof:placetype":"locality"
},
  "geometry": {"coordinates":[101.81572,16.36911],"type":"Point"}
}