{
  "type": "Feature",
  "properties": {
    "gn:admin1_code":"75.0",
    "gn:asciiname":"Ban Rai Klang",
    "gn:country_code":"TH",
    "gn:dem":121,
    "gn:feature_class":"P",
    "gn:feature_code":"PPL",
    "gn:name":"Ban Rai Klang",
    "gn:population":0,
    "gn:timezone":"Asia/Bangkok",
    "iso:country":"TH",
    "name:tha_x_preferred":[
        "\u0e1a\u0e49\u0e32\u0e19\u0e44\u0e23\u0e48\u0e01\u0e25\u0e32\u0e07"
    ],
    "wof:name":"Ban Rai Klang",
    "wof:placetype":"locality"
},
  "geometry": {"coordinates":[105.13500000000001,15.17422],"type":"Point"}
}