{
  "type": "Feature",
  "properties": {
    "gn:admin1_code":"27",
    "gn:asciiname":"Ban Pong Dinso",
    "gn:country_code":"TH",
    "gn:dem":220,
    "gn:feature_class":"P",
    "gn:feature_code":"PPL",
    "gn:name":"Ban Pong Dinso",
    "gn:population":0,
    "gn:timezone":"Asia/Bangkok",
    "iso:country":"TH",
    "name:tha_x_preferred":[
        "\u0e1a\u0e49\u0e32\u0e19\u0e42\u0e1b\u0e48\u0e07\u0e14\u0e34\u0e19\u0e2a\u0e2d"
    ],
    "wof:name":"Ban Pong Dinso",
    "wof:placetype":"locality"
},
  "geometry": {"coordinates":[101.99047,14.8835],"type":"Point"}
}