{
  "type": "Feature",
  "properties": {
    "gn:admin1_code":"20.0",
    "gn:asciiname":"Ban Chumchai",
    "gn:country_code":"TH",
    "gn:dem":186,
    "gn:feature_class":"P",
    "gn:feature_code":"PPL",
    "gn:name":"Ban Chumchai",
    "gn:population":0,
    "gn:timezone":"Asia/Bangkok",
    "iso:country":"TH",
    "name:tha_x_preferred":[
        "\u0e1a\u0e49\u0e32\u0e19\u0e0a\u0e38\u0e21\u0e0a\u0e31\u0e22"
    ],
    "wof:name":"Ban Chumchai",
    "wof:placetype":"locality"
},
  "geometry": {"coordinates":[103.37345999999999,17.40716],"type":"Point"}
}