{
  "type": "Feature",
  "properties": {
    "gn:admin1_code":"16.0",
    "gn:asciiname":"Ban Noen Sanuan",
    "gn:country_code":"TH",
    "gn:dem":38,
    "gn:feature_class":"P",
    "gn:feature_code":"PPL",
    "gn:name":"Ban Noen Sanuan",
    "gn:population":0,
    "gn:timezone":"Asia/Bangkok",
    "iso:country":"TH",
    "name:tha_x_preferred":[
        "\u0e1a\u0e49\u0e32\u0e19\u0e40\u0e19\u0e34\u0e19\u0e2a\u0e19\u0e27\u0e19"
    ],
    "name:und_x_variant":[
        "Ban Noen Sanon"
    ],
    "wof:name":"Ban Noen Sanuan",
    "wof:placetype":"locality"
},
  "geometry": {"coordinates":[100.15797000000001,15.50575],"type":"Point"}
}