{
  "type": "Feature",
  "properties": {
    "gn:admin1_code":"47.0",
    "gn:asciiname":"Ban Chet Luk Noen",
    "gn:country_code":"TH",
    "gn:dem":61,
    "gn:feature_class":"P",
    "gn:feature_code":"PPL",
    "gn:name":"Ban Chet Luk Noen",
    "gn:population":0,
    "gn:timezone":"Asia/Bangkok",
    "iso:country":"TH",
    "name:tha_x_preferred":[
        "\u0e1a\u0e49\u0e32\u0e19\u0e40\u0e08\u0e47\u0e14\u0e25\u0e39\u0e01\u0e40\u0e19\u0e34\u0e19"
    ],
    "wof:name":"Ban Chet Luk Noen",
    "wof:placetype":"locality"
},
  "geometry": {"coordinates":[101.39610999999999,12.77167],"type":"Point"}
}