{
  "type": "Feature",
  "properties": {
    "gn:admin1_code":"3.0",
    "gn:asciiname":"Ban Yang Hom",
    "gn:country_code":"TH",
    "gn:dem":375,
    "gn:feature_class":"P",
    "gn:feature_code":"PPL",
    "gn:name":"Ban Yang Hom",
    "gn:population":0,
    "gn:timezone":"Asia/Bangkok",
    "iso:country":"TH",
    "name:tha_x_preferred":[
        "\u0e1a\u0e49\u0e32\u0e19\u0e22\u0e32\u0e07\u0e2e\u0e2d\u0e21"
    ],
    "name:und_x_variant":[
        "Yang Huam",
        "Ban Yang Huam",
        "Ban Yang Hom",
        "Ban Yang Hom (1)"
    ],
    "wof:name":"Ban Yang Hom",
    "wof:placetype":"locality"
},
  "geometry": {"coordinates":[100.29258,19.90511],"type":"Point"}
}