{
  "type": "Feature",
  "properties": {
    "gn:admin1_code":"70.0",
    "gn:asciiname":"Ban To Mu Se",
    "gn:country_code":"TH",
    "gn:dem":275,
    "gn:feature_class":"P",
    "gn:feature_code":"PPL",
    "gn:name":"Ban To Mu Se",
    "gn:population":0,
    "gn:timezone":"Asia/Bangkok",
    "iso:country":"TH",
    "name:tha_x_preferred":[
        "\u0e1a\u0e49\u0e32\u0e19\u0e42\u0e15\u0e4a\u0e30\u0e21\u0e39\u0e40\u0e0b\u0e4a\u0e30"
    ],
    "name:und_x_variant":[
        "Ban To Mu Sae",
        "Ban To Mu Se"
    ],
    "wof:name":"Ban To Mu Se",
    "wof:placetype":"locality"
},
  "geometry": {"coordinates":[101.20733,6.09856],"type":"Point"}
}