{
  "type": "Feature",
  "properties": {
    "gn:admin1_code":"4.0",
    "gn:asciiname":"Ban Ton Laeng",
    "gn:country_code":"TH",
    "gn:dem":251,
    "gn:feature_class":"P",
    "gn:feature_code":"PPL",
    "gn:name":"Ban Ton Laeng",
    "gn:population":0,
    "gn:timezone":"Asia/Bangkok",
    "iso:country":"TH",
    "name:tha_x_preferred":[
        "\u0e1a\u0e49\u0e32\u0e19\u0e15\u0e49\u0e19\u0e41\u0e2b\u0e25\u0e07"
    ],
    "wof:name":"Ban Ton Laeng",
    "wof:placetype":"locality"
},
  "geometry": {"coordinates":[100.90581,19.18964],"type":"Point"}
}