{
  "type": "Feature",
  "properties": {
    "gn:admin1_code":"4.0",
    "gn:asciiname":"Ban Salung",
    "gn:country_code":"TH",
    "gn:dem":321,
    "gn:feature_class":"P",
    "gn:feature_code":"PPL",
    "gn:name":"Ban Salung",
    "gn:population":0,
    "gn:timezone":"Asia/Bangkok",
    "iso:country":"TH",
    "wof:name":"Ban Salung",
    "wof:placetype":"locality"
},
  "geometry": {"coordinates":[100.88333,19.41667],"type":"Point"}
}