{
  "type": "Feature",
  "properties": {
    "gn:admin1_code":"23.0",
    "gn:asciiname":"Ban Khamin",
    "gn:country_code":"TH",
    "gn:dem":145,
    "gn:feature_class":"P",
    "gn:feature_code":"PPL",
    "gn:name":"Ban Khamin",
    "gn:population":0,
    "gn:timezone":"Asia/Bangkok",
    "iso:country":"TH",
    "name:tha_x_preferred":[
        "\u0e1a\u0e49\u0e32\u0e19\u0e02\u0e21\u0e34\u0e49\u0e19"
    ],
    "name:tha_x_variant":[
        "\u0e41\u0e22\u0e01\u0e1a\u0e49\u0e32\u0e19\u0e02\u0e21\u0e34\u0e49\u0e19"
    ],
    "wof:name":"Ban Khamin",
    "wof:placetype":"locality"
},
  "geometry": {"coordinates":[103.49547,16.34933],"type":"Point"}
}