{
  "type": "Feature",
  "properties": {
    "gn:admin1_code":"37",
    "gn:asciiname":"Ban Sap Rang",
    "gn:country_code":"TH",
    "gn:dem":59,
    "gn:feature_class":"P",
    "gn:feature_code":"PPL",
    "gn:name":"Ban Sap Rang",
    "gn:population":0,
    "gn:timezone":"Asia/Bangkok",
    "iso:country":"TH",
    "name:tha_x_preferred":[
        "\u0e1a\u0e49\u0e32\u0e19\u0e0b\u0e31\u0e1a\u0e23\u0e32\u0e07"
    ],
    "wof:name":"Ban Sap Rang",
    "wof:placetype":"locality"
},
  "geometry": {"coordinates":[100.75144,14.79239],"type":"Point"}
}