{
  "type": "Feature",
  "properties": {
    "gn:admin1_code":"26.0",
    "gn:asciiname":"Ban Duea",
    "gn:country_code":"TH",
    "gn:dem":205,
    "gn:feature_class":"P",
    "gn:feature_code":"PPL",
    "gn:name":"Ban Duea",
    "gn:population":0,
    "gn:timezone":"Asia/Bangkok",
    "iso:country":"TH",
    "name:tha_x_preferred":[
        "\u0e1a\u0e49\u0e32\u0e19\u0e40\u0e14\u0e37\u0e48\u0e2d"
    ],
    "name:und_x_variant":[
        "Ban Dua"
    ],
    "wof:name":"Ban Duea",
    "wof:placetype":"locality"
},
  "geometry": {"coordinates":[101.83583,15.54025],"type":"Point"}
}