{
  "type": "Feature",
  "properties": {
    "gn:admin1_code":"64.0",
    "gn:asciiname":"Ban Don Bua Bok",
    "gn:country_code":"TH",
    "gn:dem":6,
    "gn:feature_class":"P",
    "gn:feature_code":"PPL",
    "gn:name":"Ban Don Bua Bok",
    "gn:population":0,
    "gn:timezone":"Asia/Bangkok",
    "iso:country":"TH",
    "name:tha_x_preferred":[
        "\u0e1a\u0e49\u0e32\u0e19\u0e14\u0e2d\u0e19\u0e1a\u0e31\u0e27\u0e1a\u0e01"
    ],
    "wof:name":"Ban Don Bua Bok",
    "wof:placetype":"locality"
},
  "geometry": {"coordinates":[100.17461,8.15661],"type":"Point"}
}