{
  "type": "Feature",
  "properties": {
    "gn:admin1_code":"50.0",
    "gn:asciiname":"Ban Don Kratai",
    "gn:country_code":"TH",
    "gn:dem":35,
    "gn:feature_class":"P",
    "gn:feature_code":"PPL",
    "gn:name":"Ban Don Kratai",
    "gn:population":0,
    "gn:timezone":"Asia/Bangkok",
    "iso:country":"TH",
    "name:tha_x_preferred":[
        "\u0e1a\u0e49\u0e32\u0e19\u0e14\u0e2d\u0e19\u0e01\u0e23\u0e30\u0e15\u0e48\u0e32\u0e22"
    ],
    "wof:name":"Ban Don Kratai",
    "wof:placetype":"locality"
},
  "geometry": {"coordinates":[99.51289,13.88419],"type":"Point"}
}