{
  "type": "Feature",
  "properties": {
    "gn:admin1_code":"1.0",
    "gn:asciiname":"Ban Buak",
    "gn:country_code":"TH",
    "gn:dem":998,
    "gn:feature_class":"P",
    "gn:feature_code":"PPL",
    "gn:name":"Ban Buak",
    "gn:population":0,
    "gn:timezone":"Asia/Bangkok",
    "iso:country":"TH",
    "name:tha_x_preferred":[
        "\u0e1a\u0e49\u0e32\u0e19\u0e1a\u0e27\u0e01"
    ],
    "wof:name":"Ban Buak",
    "wof:placetype":"locality"
},
  "geometry": {"coordinates":[98.10325,18.10242],"type":"Point"}
}