{
  "type": "Feature",
  "properties": {
    "gn:admin1_code":"3.0",
    "gn:asciiname":"Ban Pa Ko Dam Tai",
    "gn:country_code":"TH",
    "gn:dem":419,
    "gn:feature_class":"P",
    "gn:feature_code":"PPL",
    "gn:name":"Ban Pa Ko Dam Tai",
    "gn:population":0,
    "gn:timezone":"Asia/Bangkok",
    "iso:country":"TH",
    "name:tha_x_preferred":[
        "\u0e1a\u0e49\u0e32\u0e19\u0e1b\u0e48\u0e32\u0e01\u0e48\u0e2d\u0e14\u0e33\u0e43\u0e15\u0e49"
    ],
    "name:und_x_variant":[
        "Thung Kau",
        "Ban Thung Ko",
        "B\u0101n Thung Gau",
        "Ban Pa Ko Dam Tai",
        "Ban Pa Ko Dam (1)"
    ],
    "wof:name":"Ban Pa Ko Dam Tai",
    "wof:placetype":"locality"
},
  "geometry": {"coordinates":[99.74142000000001,19.77217000000001],"type":"Point"}
}