{
  "type": "Feature",
  "properties": {
    "gn:admin1_code":"77.0",
    "gn:asciiname":"Ban Sam Yaek Chomphu",
    "gn:country_code":"TH",
    "gn:dem":170,
    "gn:feature_class":"P",
    "gn:feature_code":"PPL",
    "gn:name":"Ban Sam Yaek Chomphu",
    "gn:population":0,
    "gn:timezone":"Asia/Bangkok",
    "iso:country":"TH",
    "name:tha_x_preferred":[
        "Ban Sam Yaek Chomphu"
    ],
    "name:tha_x_variant":[
        "\u0e1a\u0e49\u0e32\u0e19\u0e2a\u0e32\u0e21\u0e41\u0e22\u0e01\u0e0a\u0e21\u0e20\u0e39"
    ],
    "wof:name":"Ban Sam Yaek Chomphu",
    "wof:placetype":"locality"
},
  "geometry": {"coordinates":[104.87244,15.8774],"type":"Point"}
}