{
  "type": "Feature",
  "properties": {
    "gn:admin1_code":"36",
    "gn:asciiname":"Ban Nai Bueng",
    "gn:country_code":"TH",
    "gn:dem":4,
    "gn:feature_class":"P",
    "gn:feature_code":"PPL",
    "gn:name":"Ban Nai Bueng",
    "gn:population":0,
    "gn:timezone":"Asia/Bangkok",
    "iso:country":"TH",
    "name:tha_x_preferred":[
        "\u0e1a\u0e49\u0e32\u0e19\u0e43\u0e19\u0e1a\u0e36\u0e07"
    ],
    "wof:name":"Ban Nai Bueng",
    "wof:placetype":"locality"
},
  "geometry": {"coordinates":[100.71633,14.21378],"type":"Point"}
}