{
  "type": "Feature",
  "properties": {
    "gn:admin1_code":"76.0",
    "gn:asciiname":"Ban Kut Na Kho",
    "gn:country_code":"TH",
    "gn:dem":178,
    "gn:feature_class":"P",
    "gn:feature_code":"PPL",
    "gn:name":"Ban Kut Na Kho",
    "gn:population":0,
    "gn:timezone":"Asia/Bangkok",
    "iso:country":"TH",
    "name:tha_x_preferred":[
        "\u0e1a\u0e49\u0e32\u0e19\u0e01\u0e38\u0e14\u0e19\u0e32\u0e04\u0e49\u0e2d"
    ],
    "wof:name":"Ban Kut Na Kho",
    "wof:placetype":"locality"
},
  "geometry": {"coordinates":[103.06447,17.02789],"type":"Point"}
}