{
  "type": "Feature",
  "properties": {
    "gn:admin1_code":"7.0",
    "gn:asciiname":"Ban Mae Pak",
    "gn:country_code":"TH",
    "gn:dem":145,
    "gn:feature_class":"P",
    "gn:feature_code":"PPL",
    "gn:name":"Ban Mae Pak",
    "gn:population":0,
    "gn:timezone":"Asia/Bangkok",
    "iso:country":"TH",
    "name:tha_x_preferred":[
        "\u0e1a\u0e49\u0e32\u0e19\u0e41\u0e21\u0e48\u0e1b\u0e49\u0e32\u0e01"
    ],
    "name:und_x_variant":[
        "Mae Pak",
        "B\u0101n Mea P\u0101n",
        "M\u0113p\u0101k",
        "Ban Mae Pak"
    ],
    "wof:name":"Ban Mae Pak",
    "wof:placetype":"locality"
},
  "geometry": {"coordinates":[99.65267,17.98639],"type":"Point"}
}