{
  "type": "Feature",
  "properties": {
    "gn:admin1_code":"70.0",
    "gn:asciiname":"Ban Khlong Nam Sai",
    "gn:country_code":"TH",
    "gn:dem":93,
    "gn:feature_class":"P",
    "gn:feature_code":"PPL",
    "gn:name":"Ban Khlong Nam Sai",
    "gn:population":0,
    "gn:timezone":"Asia/Bangkok",
    "iso:country":"TH",
    "name:tha_x_preferred":[
        "\u0e1a\u0e49\u0e32\u0e19\u0e04\u0e25\u0e2d\u0e07\u0e19\u0e49\u0e33\u0e43\u0e2a"
    ],
    "wof:name":"Ban Khlong Nam Sai",
    "wof:placetype":"locality"
},
  "geometry": {"coordinates":[101.02106000000001,6.33192],"type":"Point"}
}