{
  "type": "Feature",
  "properties": {
    "gn:admin1_code":"39.0",
    "gn:asciiname":"Ban Khlong Ha",
    "gn:country_code":"TH",
    "gn:dem":5,
    "gn:feature_class":"P",
    "gn:feature_code":"PPL",
    "gn:name":"Ban Khlong Ha",
    "gn:population":0,
    "gn:timezone":"Asia/Bangkok",
    "iso:country":"TH",
    "name:tha_x_preferred":[
        "Ban Khlong Ha"
    ],
    "name:tha_x_variant":[
        "\u0e1a\u0e49\u0e32\u0e19\u0e04\u0e25\u0e2d\u0e07 \u0e2b\u0e49\u0e32",
        "Ban Khlong 5"
    ],
    "name:und_x_variant":[
        "Ban Khlong Ha (2)"
    ],
    "wof:name":"Ban Khlong Ha",
    "wof:placetype":"locality"
},
  "geometry": {"coordinates":[100.70928000000001,14.076],"type":"Point"}
}