{
  "type": "Feature",
  "properties": {
    "gn:admin1_code":"14.0",
    "gn:asciiname":"Ban Nam Khrang Noi",
    "gn:country_code":"TH",
    "gn:dem":172,
    "gn:feature_class":"P",
    "gn:feature_code":"PPL",
    "gn:name":"Ban Nam Khrang Noi",
    "gn:population":0,
    "gn:timezone":"Asia/Bangkok",
    "iso:country":"TH",
    "name:tha_x_preferred":[
        "\u0e1a\u0e49\u0e32\u0e19\u0e19\u0e49\u0e33\u0e04\u0e23\u0e31\u0e48\u0e07\u0e19\u0e49\u0e2d\u0e22"
    ],
    "wof:name":"Ban Nam Khrang Noi",
    "wof:placetype":"locality"
},
  "geometry": {"coordinates":[101.19508,16.91811],"type":"Point"}
}