{
  "type": "Feature",
  "properties": {
    "gn:admin1_code":"1.0",
    "gn:asciiname":"Ban Mae Surin",
    "gn:country_code":"TH",
    "gn:dem":400,
    "gn:feature_class":"P",
    "gn:feature_code":"PPL",
    "gn:name":"Ban Mae Surin",
    "gn:population":0,
    "gn:timezone":"Asia/Bangkok",
    "iso:country":"TH",
    "name:tha_x_preferred":[
        "\u0e1a\u0e49\u0e32\u0e19\u0e41\u0e21\u0e48\u0e2a\u0e38\u0e23\u0e34\u0e19"
    ],
    "name:und_x_variant":[
        "Hua Thung",
        "Ban Hua Thung",
        "H\u016ba Dhung",
        "Ban Mae Surin"
    ],
    "wof:lang_x_official":[
        "tha"
    ],
    "wof:lang_x_spoken":[
        "tha"
    ],
    "wof:name":"Ban Mae Surin",
    "wof:placetype":"locality"
},
  "geometry": {"coordinates":[97.93738999999999,18.919],"type":"Point"}
}