{
  "type": "Feature",
  "properties": {
    "gn:admin1_code":"55.0",
    "gn:asciiname":"Ban Tan Sot",
    "gn:country_code":"TH",
    "gn:dem":5,
    "gn:feature_class":"P",
    "gn:feature_code":"PPL",
    "gn:name":"Ban Tan Sot",
    "gn:population":0,
    "gn:timezone":"Asia/Bangkok",
    "iso:country":"TH",
    "name:tha_x_preferred":[
        "\u0e1a\u0e49\u0e32\u0e19\u0e15\u0e32\u0e25\u0e2a\u0e14"
    ],
    "wof:name":"Ban Tan Sot",
    "wof:placetype":"locality"
},
  "geometry": {"coordinates":[100.27307999999999,13.64475],"type":"Point"}
}