{
  "type": "Feature",
  "properties": {
    "gn:admin1_code":"73.0",
    "gn:asciiname":"Ban Huai Huat",
    "gn:country_code":"TH",
    "gn:dem":400,
    "gn:feature_class":"P",
    "gn:feature_code":"PPL",
    "gn:name":"Ban Huai Huat",
    "gn:population":0,
    "gn:timezone":"Asia/Bangkok",
    "iso:country":"TH",
    "wof:name":"Ban Huai Huat",
    "wof:placetype":"locality"
},
  "geometry": {"coordinates":[104.33333,16.91667],"type":"Point"}
}