{
  "type": "Feature",
  "properties": {
    "gn:admin1_code":"15.0",
    "gn:asciiname":"Ban Khao Ruesi",
    "gn:country_code":"TH",
    "gn:dem":105,
    "gn:feature_class":"P",
    "gn:feature_code":"PPL",
    "gn:name":"Ban Khao Ruesi",
    "gn:population":0,
    "gn:timezone":"Asia/Bangkok",
    "iso:country":"TH",
    "name:tha_x_preferred":[
        "\u0e1a\u0e49\u0e32\u0e19\u0e40\u0e02\u0e32\u0e24\u0e32\u0e29\u0e35"
    ],
    "wof:name":"Ban Khao Ruesi",
    "wof:placetype":"locality"
},
  "geometry": {"coordinates":[99.54935999999999,15.58042],"type":"Point"}
}