{
  "type": "Feature",
  "properties": {
    "gn:admin1_code":"39.0",
    "gn:asciiname":"Ban Thung Tan",
    "gn:country_code":"TH",
    "gn:dem":6,
    "gn:feature_class":"P",
    "gn:feature_code":"PPL",
    "gn:name":"Ban Thung Tan",
    "gn:population":0,
    "gn:timezone":"Asia/Bangkok",
    "iso:country":"TH",
    "name:tha_x_preferred":[
        "\u0e1a\u0e49\u0e32\u0e19\u0e17\u0e38\u0e48\u0e07\u0e15\u0e32\u0e25"
    ],
    "name:und_x_variant":[
        "Ban Thung Ton Tan",
        "Ban Thung",
        "Ban Thung Tan"
    ],
    "wof:name":"Ban Thung Tan",
    "wof:placetype":"locality"
},
  "geometry": {"coordinates":[100.56336,13.99564],"type":"Point"}
}