{
  "type": "Feature",
  "properties": {
    "gn:admin1_code":"10.0",
    "gn:asciiname":"Ban Hat Thung",
    "gn:country_code":"TH",
    "gn:dem":86,
    "gn:feature_class":"P",
    "gn:feature_code":"PPL",
    "gn:name":"Ban Hat Thung",
    "gn:population":0,
    "gn:timezone":"Asia/Bangkok",
    "iso:country":"TH",
    "name:tha_x_preferred":[
        "Ban Hat Thung"
    ],
    "name:tha_x_variant":[
        "\u0e1a\u0e49\u0e32\u0e19\u0e2b\u0e32\u0e14\u0e17\u0e38\u0e48\u0e07"
    ],
    "wof:name":"Ban Hat Thung",
    "wof:placetype":"locality"
},
  "geometry": {"coordinates":[100.39389,17.72583],"type":"Point"}
}