{
  "type": "Feature",
  "properties": {
    "gn:admin1_code":"7.0",
    "gn:asciiname":"Ban Pae",
    "gn:cc2":"TH",
    "gn:country_code":"TH",
    "gn:dem":175,
    "gn:feature_class":"P",
    "gn:feature_code":"PPL",
    "gn:name":"Ban Pae",
    "gn:population":0,
    "gn:timezone":"Asia/Bangkok",
    "iso:country":"TH",
    "name:und_x_variant":[
        "B\u0101n Pea",
        "Ban Pae"
    ],
    "wof:name":"Ban Pae",
    "wof:placetype":"locality"
},
  "geometry": {"coordinates":[100.25,18.28333],"type":"Point"}
}