{
  "type": "Feature",
  "properties": {
    "gn:admin1_code":"24.0",
    "gn:asciiname":"Ban Suea Thao",
    "gn:country_code":"TH",
    "gn:dem":175,
    "gn:feature_class":"P",
    "gn:feature_code":"PPL",
    "gn:name":"Ban Suea Thao",
    "gn:population":0,
    "gn:timezone":"Asia/Bangkok",
    "iso:country":"TH",
    "name:tha_x_preferred":[
        "\u0e1a\u0e49\u0e32\u0e19\u0e40\u0e2a\u0e37\u0e2d\u0e40\u0e12\u0e48\u0e32"
    ],
    "name:und_x_variant":[
        "Ban Nam Sua Thao",
        "Ban Nong Sua Thao",
        "Ban Suea Thao"
    ],
    "wof:name":"Ban Suea Thao",
    "wof:placetype":"locality"
},
  "geometry": {"coordinates":[103.03847,16.46758],"type":"Point"}
}