{
  "type": "Feature",
  "properties": {
    "gn:country":"TH",
    "gn:fcode":"PPL",
    "gn:population":0,
    "iso:country":"TH",
    "name:tha_x_preferred":[
        "\u0e1a\u0e49\u0e32\u0e19\u0e2b\u0e25\u0e27\u0e07"
    ],
    "name:und_x_variant":[
        "Ban Luang"
    ],
    "qs:name":"Ta Luang",
    "qs:name_adm0":"Thailand",
    "qs:name_adm1":"Ratchaburi",
    "qs:photos":16,
    "qs:photos_1k":3,
    "qs:photos_9k":1,
    "qs:photos_9r":1,
    "qs:photos_all":16,
    "qs:photos_sr":1,
    "qs:placetype":"Town",
    "qs:pop_sr":"0",
    "wof:name":"Ta Luang",
    "wof:placetype":"locality",
    "wof:population":0
},
  "geometry": {"coordinates":[99.91352999999999,13.66081],"type":"Point"}
}