{
  "type": "Feature",
  "properties": {
    "gn:admin1_code":"22",
    "gn:asciiname":"Ban Phrabat Non Khun",
    "gn:country_code":"TH",
    "gn:dem":216,
    "gn:feature_class":"P",
    "gn:feature_code":"PPL",
    "gn:name":"Ban Phrabat Non Khun",
    "gn:population":0,
    "gn:timezone":"Asia/Bangkok",
    "iso:country":"TH",
    "name:tha_x_preferred":[
        "\u0e1a\u0e49\u0e32\u0e19\u0e1e\u0e23\u0e30\u0e1a\u0e32\u0e17\u0e42\u0e19\u0e19\u0e04\u0e39\u0e13"
    ],
    "wof:lang_x_official":[
        "tha"
    ],
    "wof:lang_x_spoken":[
        "tha"
    ],
    "wof:name":"Ban Phrabat Non Khun",
    "wof:placetype":"locality"
},
  "geometry": {"coordinates":[102.46630999999999,16.69561],"type":"Point"}
}