{
  "type": "Feature",
  "properties": {
    "gn:admin1_code":"75.0",
    "gn:asciiname":"Ban Na Dun",
    "gn:country_code":"TH",
    "gn:dem":129,
    "gn:feature_class":"P",
    "gn:feature_code":"PPL",
    "gn:name":"Ban Na Dun",
    "gn:population":0,
    "gn:timezone":"Asia/Bangkok",
    "iso:country":"TH",
    "name:tha_x_preferred":[
        "\u0e1a\u0e49\u0e32\u0e19\u0e19\u0e32\u0e14\u0e39\u0e19"
    ],
    "wof:name":"Ban Na Dun",
    "wof:placetype":"locality"
},
  "geometry": {"coordinates":[104.82956,15.30078],"type":"Point"}
}