{
  "type": "Feature",
  "properties": {
    "gn:admin1_code":"18.0",
    "gn:asciiname":"Ban Nong Haeo",
    "gn:country_code":"TH",
    "gn:dem":383,
    "gn:feature_class":"P",
    "gn:feature_code":"PPL",
    "gn:name":"Ban Nong Haeo",
    "gn:population":0,
    "gn:timezone":"Asia/Bangkok",
    "iso:country":"TH",
    "name:tha_x_preferred":[
        "\u0e1a\u0e49\u0e32\u0e19\u0e2b\u0e19\u0e2d\u0e07\u0e41\u0e2b\u0e49\u0e27"
    ],
    "name:und_x_variant":[
        "Ban Chang Mun Si",
        "B\u0101n Jang Meun Si",
        "Ban Nong Haeo"
    ],
    "wof:name":"Ban Nong Haeo",
    "wof:placetype":"locality"
},
  "geometry": {"coordinates":[101.28314,17.21525],"type":"Point"}
}