{
  "type": "Feature",
  "properties": {
    "gn:admin1_code":"17.0",
    "gn:asciiname":"Ban Don Muat",
    "gn:country_code":"TH",
    "gn:dem":170,
    "gn:feature_class":"P",
    "gn:feature_code":"PPL",
    "gn:name":"Ban Don Muat",
    "gn:population":0,
    "gn:timezone":"Asia/Bangkok",
    "iso:country":"TH",
    "name:tha_x_preferred":[
        "\u0e1a\u0e49\u0e32\u0e19\u0e14\u0e2d\u0e19\u0e40\u0e2b\u0e21\u0e37\u0e2d\u0e14"
    ],
    "wof:name":"Ban Don Muat",
    "wof:placetype":"locality"
},
  "geometry": {"coordinates":[103.25214,18.24878],"type":"Point"}
}