{
  "type": "Feature",
  "properties": {
    "gn:admin1_code":"15.0",
    "gn:asciiname":"Ban Khlong Khot",
    "gn:country_code":"TH",
    "gn:dem":96,
    "gn:feature_class":"P",
    "gn:feature_code":"PPL",
    "gn:name":"Ban Khlong Khot",
    "gn:population":0,
    "gn:timezone":"Asia/Bangkok",
    "iso:country":"TH",
    "name:tha_x_preferred":[
        "\u0e1a\u0e49\u0e32\u0e19\u0e04\u0e25\u0e2d\u0e07\u0e04\u0e15"
    ],
    "wof:name":"Ban Khlong Khot",
    "wof:placetype":"locality"
},
  "geometry": {"coordinates":[99.70431000000001,15.05292],"type":"Point"}
}