{
  "type": "Feature",
  "properties": {
    "gn:admin1_code":"3.0",
    "gn:asciiname":"Ban Sak Tai",
    "gn:country_code":"TH",
    "gn:dem":384,
    "gn:feature_class":"P",
    "gn:feature_code":"PPL",
    "gn:name":"Ban Sak Tai",
    "gn:population":0,
    "gn:timezone":"Asia/Bangkok",
    "iso:country":"TH",
    "name:tha_x_preferred":[
        "\u0e1a\u0e49\u0e32\u0e19\u0e2a\u0e31\u0e01\u0e43\u0e15\u0e49"
    ],
    "wof:name":"Ban Sak Tai",
    "wof:placetype":"locality"
},
  "geometry": {"coordinates":[100.00346999999999,19.49856],"type":"Point"}
}