{
  "type": "Feature",
  "properties": {
    "gn:admin1_code":"22",
    "gn:asciiname":"Ban Chamroen",
    "gn:country_code":"TH",
    "gn:dem":161,
    "gn:feature_class":"P",
    "gn:feature_code":"PPL",
    "gn:name":"Ban Chamroen",
    "gn:population":0,
    "gn:timezone":"Asia/Bangkok",
    "iso:country":"TH",
    "name:tha_x_preferred":[
        "\u0e1a\u0e49\u0e32\u0e19\u0e08\u0e33\u0e40\u0e23\u0e34\u0e0d"
    ],
    "wof:name":"Ban Chamroen",
    "wof:placetype":"locality"
},
  "geometry": {"coordinates":[102.95228,16.56728],"type":"Point"}
}