{
  "type": "Feature",
  "properties": {
    "gn:admin1_code":"3.0",
    "gn:asciiname":"Ban Dong Luang",
    "gn:country_code":"TH",
    "gn:dem":592,
    "gn:feature_class":"P",
    "gn:feature_code":"PPL",
    "gn:name":"Ban Dong Luang",
    "gn:population":0,
    "gn:timezone":"Asia/Bangkok",
    "iso:country":"TH",
    "name:tha_x_preferred":[
        "\u0e1a\u0e49\u0e32\u0e19\u0e14\u0e07\u0e2b\u0e25\u0e27\u0e07"
    ],
    "wof:name":"Ban Dong Luang",
    "wof:placetype":"locality"
},
  "geometry": {"coordinates":[99.62772,19.39794],"type":"Point"}
}