{
  "type": "Feature",
  "properties": {
    "gn:admin1_code":"28",
    "gn:asciiname":"Ban Si Thawon",
    "gn:country_code":"TH",
    "gn:dem":164,
    "gn:feature_class":"P",
    "gn:feature_code":"PPL",
    "gn:name":"Ban Si Thawon",
    "gn:population":0,
    "gn:timezone":"Asia/Bangkok",
    "iso:country":"TH",
    "name:tha_x_preferred":[
        "\u0e1a\u0e49\u0e32\u0e19\u0e28\u0e23\u0e35\u0e16\u0e32\u0e27\u0e23"
    ],
    "wof:name":"Ban Si Thawon",
    "wof:placetype":"locality"
},
  "geometry": {"coordinates":[103.06117,14.65575],"type":"Point"}
}