{
  "type": "Feature",
  "properties": {
    "gn:admin1_code":"0.0",
    "gn:asciiname":"Ban Ta Nen",
    "gn:country_code":"TH",
    "gn:dem":2,
    "gn:feature_class":"P",
    "gn:feature_code":"PPL",
    "gn:name":"Ban Ta Nen",
    "gn:population":0,
    "gn:timezone":"Asia/Bangkok",
    "iso:country":"TH",
    "wof:name":"Ban Ta Nen",
    "wof:placetype":"locality"
},
  "geometry": {"coordinates":[100.95,13.46667],"type":"Point"}
}