{
  "type": "Feature",
  "properties": {
    "gn:admin1_code":"62.0",
    "gn:asciiname":"Ban Bo Sai",
    "gn:country_code":"TH",
    "gn:dem":13,
    "gn:feature_class":"P",
    "gn:feature_code":"PPL",
    "gn:name":"Ban Bo Sai",
    "gn:population":0,
    "gn:timezone":"Asia/Bangkok",
    "iso:country":"TH",
    "name:tha_x_preferred":[
        "\u0e1a\u0e49\u0e32\u0e19\u0e1a\u0e48\u0e2d\u0e44\u0e17\u0e23"
    ],
    "name:und_x_variant":[
        "Ban Bo Sai Klang",
        "Ban Bo Sai"
    ],
    "wof:name":"Ban Bo Sai",
    "wof:placetype":"locality"
},
  "geometry": {"coordinates":[98.31017,8.10978],"type":"Point"}
}