{
  "type": "Feature",
  "properties": {
    "gn:admin1_code":"3.0",
    "gn:asciiname":"Ban Pa Kum",
    "gn:country_code":"TH",
    "gn:dem":425,
    "gn:feature_class":"P",
    "gn:feature_code":"PPL",
    "gn:name":"Ban Pa Kum",
    "gn:population":0,
    "gn:timezone":"Asia/Bangkok",
    "iso:country":"TH",
    "name:tha_x_preferred":[
        "\u0e1a\u0e49\u0e32\u0e19\u0e1b\u0e48\u0e32\u0e01\u0e38\u0e48\u0e21"
    ],
    "wof:name":"Ban Pa Kum",
    "wof:placetype":"locality"
},
  "geometry": {"coordinates":[99.82758,20.13153],"type":"Point"}
}