{
  "type": "Feature",
  "properties": {
    "gn:admin1_code":"60.0",
    "gn:asciiname":"Ban Mat Pak",
    "gn:country_code":"TH",
    "gn:dem":25,
    "gn:feature_class":"P",
    "gn:feature_code":"PPL",
    "gn:name":"Ban Mat Pak",
    "gn:population":0,
    "gn:timezone":"Asia/Bangkok",
    "iso:country":"TH",
    "name:tha_x_preferred":[
        "\u0e1a\u0e49\u0e32\u0e19\u0e21\u0e32\u0e28\u0e1b\u0e31\u0e01"
    ],
    "wof:name":"Ban Mat Pak",
    "wof:placetype":"locality"
},
  "geometry": {"coordinates":[98.97544000000001,9.10806],"type":"Point"}
}