{
  "type": "Feature",
  "properties": {
    "gn:admin1_code":"18.0",
    "gn:asciiname":"Ban Nong Ta Kai",
    "gn:country_code":"TH",
    "gn:dem":279,
    "gn:feature_class":"P",
    "gn:feature_code":"PPL",
    "gn:name":"Ban Nong Ta Kai",
    "gn:population":0,
    "gn:timezone":"Asia/Bangkok",
    "iso:country":"TH",
    "name:tha_x_preferred":[
        "Ban Nong Ta Kai"
    ],
    "name:tha_x_variant":[
        "\u0e1a\u0e49\u0e32\u0e19\u0e2b\u0e19\u0e2d\u0e07\u0e15\u0e32\u0e44\u0e01\u0e49"
    ],
    "wof:name":"Ban Nong Ta Kai",
    "wof:placetype":"locality"
},
  "geometry": {"coordinates":[101.87350000000001,17.299],"type":"Point"}
}