{
  "type": "Feature",
  "properties": {
    "gn:admin1_code":"6.0",
    "gn:asciiname":"Ban Mae Mo Sathani",
    "gn:country_code":"TH",
    "gn:dem":302,
    "gn:feature_class":"P",
    "gn:feature_code":"PPL",
    "gn:name":"Ban Mae Mo Sathani",
    "gn:population":0,
    "gn:timezone":"Asia/Bangkok",
    "iso:country":"TH",
    "name:tha_x_preferred":[
        "\u0e1a\u0e49\u0e32\u0e19\u0e41\u0e21\u0e48\u0e40\u0e21\u0e32\u0e30\u0e2a\u0e16\u0e32\u0e19\u0e35"
    ],
    "wof:name":"Ban Mae Mo Sathani",
    "wof:placetype":"locality"
},
  "geometry": {"coordinates":[99.70383,18.25914],"type":"Point"}
}