{
  "type": "Feature",
  "properties": {
    "gn:admin1_code":"36",
    "gn:asciiname":"Ban Mai Tra",
    "gn:country_code":"TH",
    "gn:dem":7,
    "gn:feature_class":"P",
    "gn:feature_code":"PPL",
    "gn:name":"Ban Mai Tra",
    "gn:population":0,
    "gn:timezone":"Asia/Bangkok",
    "iso:country":"TH",
    "name:tha_x_preferred":[
        "\u0e1a\u0e49\u0e32\u0e19\u0e44\u0e21\u0e49\u0e15\u0e23\u0e32"
    ],
    "wof:name":"Ban Mai Tra",
    "wof:placetype":"locality"
},
  "geometry": {"coordinates":[100.47878,14.15886],"type":"Point"}
}