{
  "type": "Feature",
  "properties": {
    "gn:admin1_code":"63.0",
    "gn:asciiname":"Ban Hin Rao",
    "gn:country_code":"TH",
    "gn:dem":19,
    "gn:feature_class":"P",
    "gn:feature_code":"PPL",
    "gn:name":"Ban Hin Rao",
    "gn:population":0,
    "gn:timezone":"Asia/Bangkok",
    "iso:country":"TH",
    "name:tha_x_preferred":[
        "\u0e1a\u0e49\u0e32\u0e19\u0e2b\u0e34\u0e19\u0e23\u0e32\u0e27"
    ],
    "name:und_x_variant":[
        "Hia Lao",
        "Ban Hin Lao",
        "Ban Hin Rao"
    ],
    "wof:name":"Ban Hin Rao",
    "wof:placetype":"locality"
},
  "geometry": {"coordinates":[98.64033000000001,8.36439],"type":"Point"}
}