{
  "type": "Feature",
  "properties": {
    "gn:admin1_code":"76.0",
    "gn:asciiname":"Ku Kaeo",
    "gn:country_code":"TH",
    "gn:dem":202,
    "gn:feature_class":"P",
    "gn:feature_code":"PPLA2",
    "gn:name":"Ku Kaeo",
    "gn:population":0,
    "gn:timezone":"Asia/Bangkok",
    "iso:country":"TH",
    "name:tha_x_preferred":[
        "\u0e01\u0e39\u0e48\u0e41\u0e01\u0e49\u0e27"
    ],
    "name:und_x_variant":[
        "King Amphoe Ku Kaeo",
        "Amphoe Ku Kaeo"
    ],
    "wof:lang_x_official":[
        "tha"
    ],
    "wof:lang_x_spoken":[
        "tha"
    ],
    "wof:name":"Ku Kaeo",
    "wof:placetype":"locality"
},
  "geometry": {"coordinates":[103.15303,17.17214],"type":"Point"}
}