{
  "type": "Feature",
  "properties": {
    "gn:admin1_code":"30.0",
    "gn:asciiname":"Ban Ta Mok",
    "gn:country_code":"TH",
    "gn:dem":142,
    "gn:feature_class":"P",
    "gn:feature_code":"PPL",
    "gn:name":"Ban Ta Mok",
    "gn:population":0,
    "gn:timezone":"Asia/Bangkok",
    "iso:country":"TH",
    "name:tha_x_preferred":[
        "\u0e1a\u0e49\u0e32\u0e19\u0e15\u0e32\u0e42\u0e21\u0e01\u0e02\u0e4c"
    ],
    "wof:name":"Ban Ta Mok",
    "wof:placetype":"locality"
},
  "geometry": {"coordinates":[104.26269000000001,14.839],"type":"Point"}
}