{
  "type": "Feature",
  "properties": {
    "gn:admin1_code":"44.0",
    "gn:asciiname":"Ban Khao Talat",
    "gn:country_code":"TH",
    "gn:dem":97,
    "gn:feature_class":"P",
    "gn:feature_code":"PPL",
    "gn:name":"Ban Khao Talat",
    "gn:population":0,
    "gn:timezone":"Asia/Bangkok",
    "iso:country":"TH",
    "name:tha_x_preferred":[
        "\u0e1a\u0e49\u0e32\u0e19\u0e40\u0e02\u0e32\u0e15\u0e25\u0e32\u0e14"
    ],
    "wof:name":"Ban Khao Talat",
    "wof:placetype":"locality"
},
  "geometry": {"coordinates":[101.79608,13.42092],"type":"Point"}
}