{
  "type": "Feature",
  "properties": {
    "gn:admin1_code":"48.0",
    "gn:asciiname":"Ban I Mang Bon",
    "gn:country_code":"TH",
    "gn:dem":33,
    "gn:feature_class":"P",
    "gn:feature_code":"PPL",
    "gn:name":"Ban I Mang Bon",
    "gn:population":0,
    "gn:timezone":"Asia/Bangkok",
    "iso:country":"TH",
    "name:tha_x_preferred":[
        "\u0e1a\u0e49\u0e32\u0e19\u0e2d\u0e35\u0e21\u0e31\u0e49\u0e07\u0e1a\u0e19"
    ],
    "name:und_x_variant":[
        "I-mang",
        "Ban I Mang",
        "Ban I Mang Bon"
    ],
    "wof:lang_x_official":[
        "tha"
    ],
    "wof:lang_x_spoken":[
        "tha"
    ],
    "wof:name":"Ban I Mang Bon",
    "wof:placetype":"locality"
},
  "geometry": {"coordinates":[102.25552999999999,12.50369],"type":"Point"}
}