{
  "type": "Feature",
  "properties": {
    "gn:admin1_code":"6.0",
    "gn:asciiname":"Ban Huai Chang Hai",
    "gn:country_code":"TH",
    "gn:dem":226,
    "gn:feature_class":"P",
    "gn:feature_code":"PPL",
    "gn:name":"Ban Huai Chang Hai",
    "gn:population":0,
    "gn:timezone":"Asia/Bangkok",
    "iso:country":"TH",
    "wof:name":"Ban Huai Chang Hai",
    "wof:placetype":"locality"
},
  "geometry": {"coordinates":[99.13361,17.63806],"type":"Point"}
}