{
  "type": "Feature",
  "properties": {
    "gn:admin1_code":"69.0",
    "gn:asciiname":"Ban Thamnop",
    "gn:country_code":"TH",
    "gn:dem":36,
    "gn:feature_class":"P",
    "gn:feature_code":"PPL",
    "gn:name":"Ban Thamnop",
    "gn:population":0,
    "gn:timezone":"Asia/Bangkok",
    "iso:country":"TH",
    "name:und_x_variant":[
        "Tham Nop",
        "Ban Tam Nob",
        "Ban Thamnop",
        "\u0e1a\u0e49\u0e32\u0e19\u0e17\u0e33\u0e19\u0e1a"
    ],
    "wof:name":"Ban Thamnop",
    "wof:placetype":"locality"
},
  "geometry": {"coordinates":[101.4457,6.66242],"type":"Point"}
}