{
  "type": "Feature",
  "properties": {
    "gn:admin1_code":"11.0",
    "gn:asciiname":"Ban Bang Lat",
    "gn:country_code":"TH",
    "gn:dem":82,
    "gn:feature_class":"P",
    "gn:feature_code":"PPL",
    "gn:name":"Ban Bang Lat",
    "gn:population":0,
    "gn:timezone":"Asia/Bangkok",
    "iso:country":"TH",
    "name:tha_x_preferred":[
        "\u0e1a\u0e49\u0e32\u0e19\u0e1a\u0e32\u0e07\u0e25\u0e32\u0e14"
    ],
    "wof:name":"Ban Bang Lat",
    "wof:placetype":"locality"
},
  "geometry": {"coordinates":[99.57708,16.77181],"type":"Point"}
}