{
  "type": "Feature",
  "properties": {
    "gn:admin1_code":"39.0",
    "gn:asciiname":"Ban Khlong Sip Sam",
    "gn:country_code":"TH",
    "gn:dem":6,
    "gn:feature_class":"P",
    "gn:feature_code":"PPL",
    "gn:name":"Ban Khlong Sip Sam",
    "gn:population":0,
    "gn:timezone":"Asia/Bangkok",
    "iso:country":"TH",
    "name:tha_x_preferred":[
        "Ban Khlong Sip Sam"
    ],
    "name:tha_x_variant":[
        "\u0e1a\u0e49\u0e32\u0e19\u0e04\u0e25\u0e2d\u0e07\u0e2a\u0e34\u0e1a\u0e2a\u0e32\u0e21",
        "Ban Khlong 13"
    ],
    "name:und_x_variant":[
        "Ban Khlong Thi Sip Sam",
        "Ban Khlong Sip Sam Lang"
    ],
    "wof:name":"Ban Khlong Sip Sam",
    "wof:placetype":"locality"
},
  "geometry": {"coordinates":[100.89275000000001,14.03756],"type":"Point"}
}