{
  "type": "Feature",
  "properties": {
    "gn:admin1_code":"50.0",
    "gn:asciiname":"Ban Phu Ong Ka",
    "gn:country_code":"TH",
    "gn:dem":193,
    "gn:feature_class":"P",
    "gn:feature_code":"PPL",
    "gn:name":"Ban Phu Ong Ka",
    "gn:population":0,
    "gn:timezone":"Asia/Bangkok",
    "iso:country":"TH",
    "name:tha_x_preferred":[
        "\u0e1a\u0e49\u0e32\u0e19\u0e1e\u0e38\u0e2d\u0e07\u0e01\u0e30"
    ],
    "wof:name":"Ban Phu Ong Ka",
    "wof:placetype":"locality"
},
  "geometry": {"coordinates":[99.03986,14.25383],"type":"Point"}
}