{
  "type": "Feature",
  "properties": {
    "gn:admin1_code":"69.0",
    "gn:asciiname":"Ban Yu Yo",
    "gn:country_code":"TH",
    "gn:dem":2,
    "gn:feature_class":"P",
    "gn:feature_code":"PPL",
    "gn:name":"Ban Yu Yo",
    "gn:population":0,
    "gn:timezone":"Asia/Bangkok",
    "iso:country":"TH",
    "name:tha_x_preferred":[
        "\u0e1a\u0e49\u0e32\u0e19\u0e22\u0e39\u0e42\u0e22"
    ],
    "wof:name":"Ban Yu Yo",
    "wof:placetype":"locality"
},
  "geometry": {"coordinates":[101.26143999999999,6.88928],"type":"Point"}
}