{
  "type": "Feature",
  "properties": {
    "gn:admin1_code":"46.0",
    "gn:asciiname":"Ban Bo Thong",
    "gn:country_code":"TH",
    "gn:dem":114,
    "gn:feature_class":"P",
    "gn:feature_code":"PPL",
    "gn:name":"Ban Bo Thong",
    "gn:population":0,
    "gn:timezone":"Asia/Bangkok",
    "iso:country":"TH",
    "name:tha_x_preferred":[
        "\u0e1a\u0e49\u0e32\u0e19\u0e1a\u0e48\u0e2d\u0e17\u0e2d\u0e07"
    ],
    "name:und_x_variant":[
        "Bau Tmaung",
        "Ban Bo Thong"
    ],
    "wof:name":"Ban Bo Thong",
    "wof:placetype":"locality"
},
  "geometry": {"coordinates":[101.48820000000001,13.18292],"type":"Point"}
}