{
  "type": "Feature",
  "properties": {
    "gn:admin1_code":"80.0",
    "gn:asciiname":"Ban Nong Ian",
    "gn:country_code":"TH",
    "gn:dem":77,
    "gn:feature_class":"P",
    "gn:feature_code":"PPL",
    "gn:name":"Ban Nong Ian",
    "gn:population":0,
    "gn:timezone":"Asia/Bangkok",
    "iso:country":"TH",
    "name:tha_x_preferred":[
        "\u0e1a\u0e49\u0e32\u0e19\u0e2b\u0e19\u0e2d\u0e07\u0e40\u0e2d\u0e35\u0e48\u0e22\u0e19"
    ],
    "wof:name":"Ban Nong Ian",
    "wof:placetype":"locality"
},
  "geometry": {"coordinates":[102.57264000000001,13.73464],"type":"Point"}
}