{
  "type": "Feature",
  "properties": {
    "gn:admin1_code":"55.0",
    "gn:asciiname":"Muban Ko Samut",
    "gn:country_code":"TH",
    "gn:dem":5,
    "gn:feature_class":"P",
    "gn:feature_code":"PPL",
    "gn:name":"Muban Ko Samut",
    "gn:population":0,
    "gn:timezone":"Asia/Bangkok",
    "iso:country":"TH",
    "name:tha_x_preferred":[
        "\u0e2b\u0e21\u0e39\u0e48\u0e1a\u0e49\u0e32\u0e19\u0e40\u0e01\u0e32\u0e30\u0e2a\u0e21\u0e38\u0e17\u0e23"
    ],
    "wof:name":"Muban Ko Samut",
    "wof:placetype":"locality"
},
  "geometry": {"coordinates":[100.26246999999999,13.55983],"type":"Point"}
}