{
  "type": "Feature",
  "properties": {
    "gn:admin1_code":"6.0",
    "gn:asciiname":"Ban Thung Pao",
    "gn:country_code":"TH",
    "gn:dem":419,
    "gn:feature_class":"P",
    "gn:feature_code":"PPL",
    "gn:name":"Ban Thung Pao",
    "gn:population":0,
    "gn:timezone":"Asia/Bangkok",
    "iso:country":"TH",
    "name:tha_x_preferred":[
        "\u0e1a\u0e49\u0e32\u0e19\u0e17\u0e38\u0e48\u0e07\u0e40\u0e1b\u0e49\u0e32"
    ],
    "name:und_x_variant":[
        "B\u0101n Thung P\u0101u",
        "Ban Thung Pao"
    ],
    "wof:name":"Ban Thung Pao",
    "wof:placetype":"locality"
},
  "geometry": {"coordinates":[99.61839000000001,19.15031],"type":"Point"}
}