{
  "type": "Feature",
  "properties": {
    "gn:country":"TH",
    "gn:fcode":"PPL",
    "gn:population":0,
    "iso:country":"TH",
    "name:bpy_x_preferred":[
        "\u0986\u09ae\u09cd\u09ab\u09cb\u09af\u09bc\u09c7 \u09ac\u09cd\u09af\u09be\u0982 \u09b2\u09af\u09bc\u09c7\u09a8"
    ],
    "name:ceb_x_preferred":[
        "Amphoe Bang Len"
    ],
    "name:deu_x_preferred":[
        "Amphoe Bang Len"
    ],
    "name:eng_x_preferred":[
        "Bang Len"
    ],
    "name:fra_x_preferred":[
        "Bang Len"
    ],
    "name:nan_x_preferred":[
        "Bang Len K\u016bn"
    ],
    "name:ron_x_preferred":[
        "Districtul Bang Len"
    ],
    "name:tha_x_preferred":[
        "\u0e1a\u0e49\u0e32\u0e19\u0e1a\u0e32\u0e07\u0e44\u0e1c\u0e48"
    ],
    "name:tha_x_variant":[
        "\u0e2d\u0e33\u0e40\u0e20\u0e2d\u0e1a\u0e32\u0e07\u0e40\u0e25\u0e19"
    ],
    "name:und_x_variant":[
        "Bang Phai"
    ],
    "name:urd_x_preferred":[
        "\u0628\u0627\u0646\u06af \u0644\u0626\u0646 \u0636\u0644\u0639"
    ],
    "name:vie_x_preferred":[
        "Bang Len"
    ],
    "qs:name":"Ban Bang Phai",
    "qs:name_adm0":"Thailand",
    "qs:name_adm1":"Chachoengsao",
    "qs:photos_9k":1,
    "qs:photos_9r":1,
    "qs:photos_all":1,
    "qs:photos_sr":0,
    "qs:placetype":"Town",
    "qs:pop_sr":"0",
    "wd:wordcount":232,
    "wof:name":"Ban Bang Phai",
    "wof:placetype":"locality",
    "wof:population":0
},
  "geometry": {"coordinates":[101.13086,13.65333],"type":"Point"}
}