{
  "type": "Feature",
  "properties": {
    "gn:admin1_code":"48.0",
    "gn:asciiname":"Ban Samnak Lang",
    "gn:country_code":"TH",
    "gn:dem":3,
    "gn:feature_class":"P",
    "gn:feature_code":"PPL",
    "gn:name":"Ban Samnak Lang",
    "gn:population":0,
    "gn:timezone":"Asia/Bangkok",
    "iso:country":"TH",
    "name:tha_x_preferred":[
        "\u0e1a\u0e49\u0e32\u0e19\u0e2a\u0e33\u0e19\u0e31\u0e01\u0e25\u0e48\u0e32\u0e07"
    ],
    "wof:name":"Ban Samnak Lang",
    "wof:placetype":"locality"
},
  "geometry": {"coordinates":[102.28183,12.34792],"type":"Point"}
}