{
  "type": "Feature",
  "properties": {
    "gn:admin1_code":"18.0",
    "gn:asciiname":"Ban Nam Huai",
    "gn:country_code":"TH",
    "gn:dem":252,
    "gn:feature_class":"P",
    "gn:feature_code":"PPL",
    "gn:name":"Ban Nam Huai",
    "gn:population":0,
    "gn:timezone":"Asia/Bangkok",
    "iso:country":"TH",
    "wof:name":"Ban Nam Huai",
    "wof:placetype":"locality"
},
  "geometry": {"coordinates":[101.71666999999999,17.41667],"type":"Point"}
}