{
  "type": "Feature",
  "properties": {
    "gn:admin1_code":"30.0",
    "gn:asciiname":"Ban Krapho Sayam",
    "gn:country_code":"TH",
    "gn:dem":151,
    "gn:feature_class":"P",
    "gn:feature_code":"PPL",
    "gn:name":"Ban Krapho Sayam",
    "gn:population":0,
    "gn:timezone":"Asia/Bangkok",
    "iso:country":"TH",
    "name:tha_x_preferred":[
        "\u0e1a\u0e49\u0e32\u0e19\u0e01\u0e23\u0e30\u0e42\u0e1e\u0e18\u0e34\u0e4c\u0e2a\u0e22\u0e32\u0e21"
    ],
    "wof:name":"Ban Krapho Sayam",
    "wof:placetype":"locality"
},
  "geometry": {"coordinates":[104.20735999999999,14.78956],"type":"Point"}
}