{
  "type": "Feature",
  "properties": {
    "gn:admin1_code":"2.0",
    "gn:asciiname":"Ban Mae Phaeng",
    "gn:country_code":"TH",
    "gn:dem":432,
    "gn:feature_class":"P",
    "gn:feature_code":"PPL",
    "gn:name":"Ban Mae Phaeng",
    "gn:population":0,
    "gn:timezone":"Asia/Bangkok",
    "iso:country":"TH",
    "name:tha_x_preferred":[
        "\u0e1a\u0e49\u0e32\u0e19\u0e41\u0e21\u0e48\u0e41\u0e1e\u0e07"
    ],
    "name:und_x_variant":[
        "Ban Mea Pheang",
        "Ban Mae Phaeng (1)",
        "Ban Mae Phaeng"
    ],
    "wof:name":"Ban Mae Phaeng",
    "wof:placetype":"locality"
},
  "geometry": {"coordinates":[99.16589,19.22456],"type":"Point"}
}