{
  "type": "Feature",
  "properties": {
    "gn:admin1_code":"24",
    "gn:asciiname":"Ban Ho Klong",
    "gn:country_code":"TH",
    "gn:dem":181,
    "gn:feature_class":"P",
    "gn:feature_code":"PPL",
    "gn:name":"Ban Ho Klong",
    "gn:population":0,
    "gn:timezone":"Asia/Bangkok",
    "iso:country":"TH",
    "name:tha_x_preferred":[
        "\u0e1a\u0e49\u0e32\u0e19\u0e2b\u0e2d\u0e01\u0e25\u0e2d\u0e07"
    ],
    "wof:name":"Ban Ho Klong",
    "wof:placetype":"locality"
},
  "geometry": {"coordinates":[103.12597,16.0135],"type":"Point"}
}