{
  "type": "Feature",
  "properties": {
    "gn:admin1_code":"32.0",
    "gn:asciiname":"Ban Nong Pla Rai",
    "gn:country_code":"TH",
    "gn:dem":18,
    "gn:feature_class":"P",
    "gn:feature_code":"PPL",
    "gn:name":"Ban Nong Pla Rai",
    "gn:population":0,
    "gn:timezone":"Asia/Bangkok",
    "iso:country":"TH",
    "name:tha_x_preferred":[
        "\u0e1a\u0e49\u0e32\u0e19\u0e2b\u0e19\u0e2d\u0e07\u0e1b\u0e25\u0e32\u0e22\u0e44\u0e23\u0e48"
    ],
    "name:und_x_variant":[
        "Ban Nong Pla Lai"
    ],
    "wof:name":"Ban Nong Pla Rai",
    "wof:placetype":"locality"
},
  "geometry": {"coordinates":[100.16088999999999,15.02086],"type":"Point"}
}