{
  "type": "Feature",
  "properties": {
    "gn:admin1_code":"57.0",
    "gn:asciiname":"Ban Huai Kriap",
    "gn:country_code":"TH",
    "gn:dem":49,
    "gn:feature_class":"P",
    "gn:feature_code":"PPL",
    "gn:name":"Ban Huai Kriap",
    "gn:population":0,
    "gn:timezone":"Asia/Bangkok",
    "iso:country":"TH",
    "name:tha_x_preferred":[
        "\u0e1a\u0e49\u0e32\u0e19\u0e2b\u0e49\u0e27\u0e22\u0e40\u0e01\u0e23\u0e35\u0e22\u0e1a"
    ],
    "wof:name":"Ban Huai Kriap",
    "wof:placetype":"locality"
},
  "geometry": {"coordinates":[99.40058000000001,11.18519],"type":"Point"}
}