{
  "type": "Feature",
  "properties": {
    "gn:admin1_code":"3.0",
    "gn:asciiname":"Ban Hua Fai Phatthana",
    "gn:country_code":"TH",
    "gn:dem":573,
    "gn:feature_class":"P",
    "gn:feature_code":"PPL",
    "gn:name":"Ban Hua Fai Phatthana",
    "gn:population":0,
    "gn:timezone":"Asia/Bangkok",
    "iso:country":"TH",
    "name:tha_x_preferred":[
        "\u0e1a\u0e49\u0e32\u0e19\u0e2b\u0e31\u0e27\u0e1d\u0e32\u0e22\u0e1e\u0e31\u0e12\u0e19\u0e32"
    ],
    "name:und_x_variant":[
        "Ban Mae Kho Wai",
        "B\u0101n Mea Kau W\u0101i",
        "Ban Hua Fai",
        "Ban Hua Fai Phatthana"
    ],
    "wof:name":"Ban Hua Fai Phatthana",
    "wof:placetype":"locality"
},
  "geometry": {"coordinates":[99.53232,19.24721],"type":"Point"}
}