{
  "type": "Feature",
  "properties": {
    "gn:admin1_code":"18.0",
    "gn:asciiname":"Ban Na Hong",
    "gn:country_code":"TH",
    "gn:dem":238,
    "gn:feature_class":"P",
    "gn:feature_code":"PPL",
    "gn:name":"Ban Na Hong",
    "gn:population":0,
    "gn:timezone":"Asia/Bangkok",
    "iso:country":"TH",
    "name:tha_x_preferred":[
        "Ban Na Hong"
    ],
    "name:tha_x_variant":[
        "\u0e1a\u0e49\u0e32\u0e19\u0e19\u0e32\u0e2b\u0e07\u0e29\u0e4c"
    ],
    "name:und_x_variant":[
        "Ban Na"
    ],
    "wof:lang_x_official":[
        "tha"
    ],
    "wof:lang_x_spoken":[
        "tha"
    ],
    "wof:name":"Ban Na Hong",
    "wof:placetype":"locality"
},
  "geometry": {"coordinates":[101.88472,17.97222],"type":"Point"}
}