{
  "type": "Feature",
  "properties": {
    "gn:admin1_code":"3.0",
    "gn:asciiname":"Ban Pang Klang",
    "gn:country_code":"TH",
    "gn:dem":655,
    "gn:feature_class":"P",
    "gn:feature_code":"PPL",
    "gn:name":"Ban Pang Klang",
    "gn:population":0,
    "gn:timezone":"Asia/Bangkok",
    "iso:country":"TH",
    "name:tha_x_preferred":[
        "\u0e1a\u0e49\u0e32\u0e19\u0e1b\u0e32\u0e07\u0e01\u0e25\u0e32\u0e07"
    ],
    "wof:name":"Ban Pang Klang",
    "wof:placetype":"locality"
},
  "geometry": {"coordinates":[99.60225,19.60172],"type":"Point"}
}