{
  "type": "Feature",
  "properties": {
    "gn:admin1_code":"14.0",
    "gn:asciiname":"Ban Khao Khat",
    "gn:country_code":"TH",
    "gn:dem":997,
    "gn:feature_class":"P",
    "gn:feature_code":"PPL",
    "gn:name":"Ban Khao Khat",
    "gn:population":0,
    "gn:timezone":"Asia/Bangkok",
    "iso:country":"TH",
    "wof:name":"Ban Khao Khat",
    "wof:placetype":"locality"
},
  "geometry": {"coordinates":[101.03333000000001,16.83333],"type":"Point"}
}