{
  "type": "Feature",
  "properties": {
    "gn:admin1_code":"36.0",
    "gn:asciiname":"Ban Pak Khu Ta Chat",
    "gn:country_code":"TH",
    "gn:dem":4,
    "gn:feature_class":"P",
    "gn:feature_code":"PPL",
    "gn:name":"Ban Pak Khu Ta Chat",
    "gn:population":0,
    "gn:timezone":"Asia/Bangkok",
    "iso:country":"TH",
    "name:tha_x_preferred":[
        "Ban Ta Chat"
    ],
    "name:tha_x_variant":[
        "\u0e1a\u0e49\u0e32\u0e19\u0e1b\u0e32\u0e01\u0e04\u0e39\u0e15\u0e32\u0e09\u0e31\u0e15\u0e23"
    ],
    "wof:name":"Ban Pak Khu Ta Chat",
    "wof:placetype":"locality"
},
  "geometry": {"coordinates":[100.42041999999999,14.15831],"type":"Point"}
}