{
  "type": "Feature",
  "properties": {
    "gn:admin1_code":"77.0",
    "gn:asciiname":"Ban Kham Sang Bo",
    "gn:country_code":"TH",
    "gn:dem":149,
    "gn:feature_class":"P",
    "gn:feature_code":"PPL",
    "gn:name":"Ban Kham Sang Bo",
    "gn:population":0,
    "gn:timezone":"Asia/Bangkok",
    "iso:country":"TH",
    "name:tha_x_preferred":[
        "Ban Kham Sang Bo"
    ],
    "name:tha_x_variant":[
        "\u0e1a\u0e49\u0e32\u0e19\u0e04\u0e33\u0e2a\u0e23\u0e49\u0e32\u0e07\u0e1a\u0e48\u0e2d"
    ],
    "wof:name":"Ban Kham Sang Bo",
    "wof:placetype":"locality"
},
  "geometry": {"coordinates":[104.5261,15.80116],"type":"Point"}
}