{
  "type": "Feature",
  "properties": {
    "gn:admin1_code":"44.0",
    "gn:asciiname":"Ban Nong Ket",
    "gn:country_code":"TH",
    "gn:dem":21,
    "gn:feature_class":"P",
    "gn:feature_code":"PPL",
    "gn:name":"Ban Nong Ket",
    "gn:population":0,
    "gn:timezone":"Asia/Bangkok",
    "iso:country":"TH",
    "name:tha_x_preferred":[
        "\u0e1a\u0e49\u0e32\u0e19\u0e2b\u0e19\u0e2d\u0e07\u0e40\u0e01\u0e15\u0e38"
    ],
    "wof:name":"Ban Nong Ket",
    "wof:placetype":"locality"
},
  "geometry": {"coordinates":[101.30432999999999,13.631],"type":"Point"}
}