{
  "type": "Feature",
  "properties": {
    "gn:admin1_code":"14.0",
    "gn:asciiname":"Ban Sok Duea",
    "gn:country_code":"TH",
    "gn:dem":170,
    "gn:feature_class":"P",
    "gn:feature_code":"PPL",
    "gn:name":"Ban Sok Duea",
    "gn:population":0,
    "gn:timezone":"Asia/Bangkok",
    "iso:country":"TH",
    "name:tha_x_preferred":[
        "\u0e1a\u0e49\u0e32\u0e19\u0e42\u0e2a\u0e01\u0e40\u0e14\u0e37\u0e48\u0e2d"
    ],
    "name:und_x_variant":[
        "Ban Sok Dua"
    ],
    "wof:name":"Ban Sok Duea",
    "wof:placetype":"locality"
},
  "geometry": {"coordinates":[101.16208,16.7405],"type":"Point"}
}