{
  "type": "Feature",
  "properties": {
    "gn:admin1_code":"37.0",
    "gn:asciiname":"Ban Phlap",
    "gn:country_code":"TH",
    "gn:dem":27,
    "gn:feature_class":"P",
    "gn:feature_code":"PPL",
    "gn:name":"Ban Phlap",
    "gn:population":0,
    "gn:timezone":"Asia/Bangkok",
    "iso:country":"TH",
    "name:tha_x_preferred":[
        "\u0e1a\u0e49\u0e32\u0e19\u0e1e\u0e25\u0e31\u0e1a"
    ],
    "name:und_x_variant":[
        "Ban Dong Phlap",
        "Ban Phlap (2)",
        "Ban Phlap"
    ],
    "wof:lang_x_official":[
        "tha"
    ],
    "wof:lang_x_spoken":[
        "tha"
    ],
    "wof:name":"Ban Phlap",
    "wof:placetype":"locality"
},
  "geometry": {"coordinates":[100.931,14.47942],"type":"Point"}
}