{
  "type": "Feature",
  "properties": {
    "gn:admin1_code":"27",
    "gn:asciiname":"Ban Khok Khlong Khun Thian",
    "gn:country_code":"TH",
    "gn:dem":212,
    "gn:feature_class":"P",
    "gn:feature_code":"PPL",
    "gn:name":"Ban Khok Khlong Khun Thian",
    "gn:population":0,
    "gn:timezone":"Asia/Bangkok",
    "iso:country":"TH",
    "name:tha_x_preferred":[
        "\u0e1a\u0e49\u0e32\u0e19\u0e42\u0e04\u0e01\u0e04\u0e25\u0e2d\u0e07\u0e02\u0e38\u0e19\u0e40\u0e17\u0e35\u0e22\u0e19"
    ],
    "wof:name":"Ban Khok Khlong Khun Thian",
    "wof:placetype":"locality"
},
  "geometry": {"coordinates":[102.00427999999999,14.67741],"type":"Point"}
}