{
  "type": "Feature",
  "properties": {
    "gn:admin1_code":"44.0",
    "gn:asciiname":"Ban Tha Thong Dam",
    "gn:country_code":"TH",
    "gn:dem":48,
    "gn:feature_class":"P",
    "gn:feature_code":"PPL",
    "gn:name":"Ban Tha Thong Dam",
    "gn:population":0,
    "gn:timezone":"Asia/Bangkok",
    "iso:country":"TH",
    "name:tha_x_preferred":[
        "\u0e1a\u0e49\u0e32\u0e19\u0e17\u0e48\u0e32\u0e17\u0e2d\u0e07\u0e14\u0e33"
    ],
    "wof:name":"Ban Tha Thong Dam",
    "wof:placetype":"locality"
},
  "geometry": {"coordinates":[101.69681,13.70114],"type":"Point"}
}