{
  "type": "Feature",
  "properties": {
    "gn:admin1_code":"60.0",
    "gn:asciiname":"Ban Huai Sai Khao",
    "gn:country_code":"TH",
    "gn:dem":62,
    "gn:feature_class":"P",
    "gn:feature_code":"PPL",
    "gn:name":"Ban Huai Sai Khao",
    "gn:population":0,
    "gn:timezone":"Asia/Bangkok",
    "iso:country":"TH",
    "name:tha_x_preferred":[
        "\u0e1a\u0e49\u0e32\u0e19\u0e2b\u0e49\u0e27\u0e22\u0e17\u0e23\u0e32\u0e22\u0e02\u0e32\u0e27"
    ],
    "wof:name":"Ban Huai Sai Khao",
    "wof:placetype":"locality"
},
  "geometry": {"coordinates":[99.15633,8.60694],"type":"Point"}
}