{
  "type": "Feature",
  "properties": {
    "gn:admin1_code":"65.0",
    "gn:asciiname":"Ban Nong Mai Phai",
    "gn:country_code":"TH",
    "gn:dem":23,
    "gn:feature_class":"P",
    "gn:feature_code":"PPL",
    "gn:name":"Ban Nong Mai Phai",
    "gn:population":0,
    "gn:timezone":"Asia/Bangkok",
    "iso:country":"TH",
    "name:tha_x_preferred":[
        "\u0e1a\u0e49\u0e32\u0e19\u0e2b\u0e19\u0e2d\u0e07\u0e44\u0e21\u0e49\u0e44\u0e1c\u0e48"
    ],
    "name:und_x_variant":[
        "Ban Nong Mai Phai (1)"
    ],
    "wof:name":"Ban Nong Mai Phai",
    "wof:placetype":"locality"
},
  "geometry": {"coordinates":[99.48769,7.56103],"type":"Point"}
}