{
  "type": "Feature",
  "properties": {
    "gn:admin1_code":"27",
    "gn:asciiname":"Ban Nong Lak Phan",
    "gn:country_code":"TH",
    "gn:dem":259,
    "gn:feature_class":"P",
    "gn:feature_code":"PPL",
    "gn:name":"Ban Nong Lak Phan",
    "gn:population":0,
    "gn:timezone":"Asia/Bangkok",
    "iso:country":"TH",
    "name:tha_x_preferred":[
        "\u0e1a\u0e49\u0e32\u0e19\u0e2b\u0e19\u0e2d\u0e07\u0e2b\u0e25\u0e31\u0e01\u0e1e\u0e31\u0e19"
    ],
    "wof:name":"Ban Nong Lak Phan",
    "wof:placetype":"locality"
},
  "geometry": {"coordinates":[101.82731,14.76003],"type":"Point"}
}