{
  "type": "Feature",
  "properties": {
    "gn:admin1_code":"68.0",
    "gn:asciiname":"Ban Thung Sae Nieo",
    "gn:country_code":"TH",
    "gn:dem":33,
    "gn:feature_class":"P",
    "gn:feature_code":"PPL",
    "gn:name":"Ban Thung Sae Nieo",
    "gn:population":0,
    "gn:timezone":"Asia/Bangkok",
    "iso:country":"TH",
    "name:tha_x_preferred":[
        "\u0e1a\u0e49\u0e32\u0e19\u0e17\u0e38\u0e48\u0e07\u0e41\u0e0b\u0e30\u0e40\u0e2b\u0e19\u0e35\u0e22\u0e27"
    ],
    "wof:name":"Ban Thung Sae Nieo",
    "wof:placetype":"locality"
},
  "geometry": {"coordinates":[100.23083,7.17583],"type":"Point"}
}