{
  "type": "Feature",
  "properties": {
    "gn:admin1_code":"35.0",
    "gn:asciiname":"Ban Sao Rong Hai (1)",
    "gn:cc2":"TH",
    "gn:country_code":"TH",
    "gn:dem":7,
    "gn:feature_class":"P",
    "gn:feature_code":"PPL",
    "gn:name":"Ban Sao Rong Hai (1)",
    "gn:population":0,
    "gn:timezone":"Asia/Bangkok",
    "iso:country":"TH",
    "name:und_x_variant":[
        "Ban Sao Rong Hie",
        "Ban Sao Rong Hai (1)"
    ],
    "wof:name":"Ban Sao Rong Hai (1)",
    "wof:placetype":"locality"
},
  "geometry": {"coordinates":[100.19528,14.56444],"type":"Point"}
}