{
  "type": "Feature",
  "properties": {
    "gn:admin1_code":"75.0",
    "gn:asciiname":"Ban Rung Tawan",
    "gn:country_code":"TH",
    "gn:dem":173,
    "gn:feature_class":"P",
    "gn:feature_code":"PPL",
    "gn:name":"Ban Rung Tawan",
    "gn:population":0,
    "gn:timezone":"Asia/Bangkok",
    "iso:country":"TH",
    "name:tha_x_preferred":[
        "\u0e1a\u0e49\u0e32\u0e19\u0e23\u0e38\u0e48\u0e07\u0e15\u0e30\u0e27\u0e31\u0e19"
    ],
    "wof:name":"Ban Rung Tawan",
    "wof:placetype":"locality"
},
  "geometry": {"coordinates":[104.90716999999999,14.59108],"type":"Point"}
}