{
  "type": "Feature",
  "properties": {
    "gn:admin1_code":"36.0",
    "gn:asciiname":"Ban Bang Krasan",
    "gn:country_code":"TH",
    "gn:dem":6,
    "gn:feature_class":"P",
    "gn:feature_code":"PPL",
    "gn:name":"Ban Bang Krasan",
    "gn:population":0,
    "gn:timezone":"Asia/Bangkok",
    "iso:country":"TH",
    "name:tha_x_preferred":[
        "\u0e1a\u0e49\u0e32\u0e19\u0e1a\u0e32\u0e07\u0e01\u0e23\u0e30\u0e2a\u0e31\u0e49\u0e19"
    ],
    "name:und_x_variant":[
        "Ban Bang Kra Son",
        "Ban Bang Krasan"
    ],
    "wof:name":"Ban Bang Krasan",
    "wof:placetype":"locality"
},
  "geometry": {"coordinates":[100.56147,14.19539],"type":"Point"}
}