{
  "type": "Feature",
  "properties": {
    "gn:admin1_code":"3.0",
    "gn:asciiname":"Ban Dong Pa Miang",
    "gn:country_code":"TH",
    "gn:dem":398,
    "gn:feature_class":"P",
    "gn:feature_code":"PPL",
    "gn:name":"Ban Dong Pa Miang",
    "gn:population":0,
    "gn:timezone":"Asia/Bangkok",
    "iso:country":"TH",
    "name:tha_x_preferred":[
        "\u0e1a\u0e49\u0e32\u0e19\u0e14\u0e07\u0e1b\u0e48\u0e32\u0e40\u0e2b\u0e21\u0e35\u0e49\u0e22\u0e07"
    ],
    "wof:name":"Ban Dong Pa Miang",
    "wof:placetype":"locality"
},
  "geometry": {"coordinates":[99.95458000000001,19.76839],"type":"Point"}
}