{
  "type": "Feature",
  "properties": {
    "gn:admin1_code":"1.0",
    "gn:asciiname":"Ban Plai Hua Nam Kat",
    "gn:country_code":"TH",
    "gn:dem":612,
    "gn:feature_class":"P",
    "gn:feature_code":"PPL",
    "gn:name":"Ban Plai Hua Nam Kat",
    "gn:population":0,
    "gn:timezone":"Asia/Bangkok",
    "iso:country":"TH",
    "name:tha_x_preferred":[
        "\u0e1a\u0e49\u0e32\u0e19\u0e1b\u0e25\u0e32\u0e22\u0e2b\u0e31\u0e27\u0e19\u0e49\u0e33\u0e01\u0e31\u0e14"
    ],
    "wof:lang_x_official":[
        "tha"
    ],
    "wof:lang_x_spoken":[
        "tha"
    ],
    "wof:name":"Ban Plai Hua Nam Kat",
    "wof:placetype":"locality"
},
  "geometry": {"coordinates":[98.08396999999999,19.45947],"type":"Point"}
}