{
  "type": "Feature",
  "properties": {
    "gn:admin1_code":"70.0",
    "gn:asciiname":"Ban A No Po",
    "gn:country_code":"TH",
    "gn:dem":343,
    "gn:feature_class":"P",
    "gn:feature_code":"PPL",
    "gn:name":"Ban A No Po",
    "gn:population":0,
    "gn:timezone":"Asia/Bangkok",
    "iso:country":"TH",
    "name:tha_x_preferred":[
        "\u0e1a\u0e49\u0e32\u0e19\u0e2d\u0e32\u0e40\u0e19\u0e32\u0e30\u0e40\u0e1b\u0e32\u0e30"
    ],
    "wof:name":"Ban A No Po",
    "wof:placetype":"locality"
},
  "geometry": {"coordinates":[101.22742,5.94258],"type":"Point"}
}