{
  "type": "Feature",
  "properties": {
    "gn:admin1_code":"0.0",
    "gn:asciiname":"Ban Mae Kham Phong",
    "gn:country_code":"TH",
    "gn:dem":498,
    "gn:feature_class":"P",
    "gn:feature_code":"PPL",
    "gn:name":"Ban Mae Kham Phong",
    "gn:population":0,
    "gn:timezone":"Asia/Bangkok",
    "iso:country":"TH",
    "wof:name":"Ban Mae Kham Phong",
    "wof:placetype":"locality"
},
  "geometry": {"coordinates":[99.51861,19.00556],"type":"Point"}
}