{
  "type": "Feature",
  "properties": {
    "gn:admin1_code":"60.0",
    "gn:asciiname":"Ban Tha Thai",
    "gn:country_code":"TH",
    "gn:dem":96,
    "gn:feature_class":"P",
    "gn:feature_code":"PPL",
    "gn:name":"Ban Tha Thai",
    "gn:population":0,
    "gn:timezone":"Asia/Bangkok",
    "iso:country":"TH",
    "name:tha_x_preferred":[
        "\u0e1a\u0e49\u0e32\u0e19\u0e17\u0e48\u0e32\u0e44\u0e17"
    ],
    "wof:name":"Ban Tha Thai",
    "wof:placetype":"locality"
},
  "geometry": {"coordinates":[98.965,9.67472],"type":"Point"}
}