{
  "type": "Feature",
  "properties": {
    "gn:admin1_code":"25",
    "gn:asciiname":"Ban Khu Fa",
    "gn:country_code":"TH",
    "gn:dem":134,
    "gn:feature_class":"P",
    "gn:feature_code":"PPL",
    "gn:name":"Ban Khu Fa",
    "gn:population":0,
    "gn:timezone":"Asia/Bangkok",
    "iso:country":"TH",
    "name:tha_x_preferred":[
        "\u0e1a\u0e49\u0e32\u0e19\u0e04\u0e39\u0e1f\u0e49\u0e32"
    ],
    "wof:name":"Ban Khu Fa",
    "wof:placetype":"locality"
},
  "geometry": {"coordinates":[104.04671999999999,15.79689],"type":"Point"}
}