{
  "type": "Feature",
  "properties": {
    "gn:admin1_code":"67.0",
    "gn:asciiname":"Ban Wang Prachan Tai",
    "gn:country_code":"TH",
    "gn:dem":64,
    "gn:feature_class":"P",
    "gn:feature_code":"PPL",
    "gn:name":"Ban Wang Prachan Tai",
    "gn:population":0,
    "gn:timezone":"Asia/Bangkok",
    "iso:country":"TH",
    "name:tha_x_preferred":[
        "\u0e1a\u0e49\u0e32\u0e19\u0e27\u0e31\u0e07\u0e1b\u0e23\u0e30\u0e08\u0e31\u0e19\u0e43\u0e15\u0e49"
    ],
    "wof:name":"Ban Wang Prachan Tai",
    "wof:placetype":"locality"
},
  "geometry": {"coordinates":[100.15506000000001,6.74222],"type":"Point"}
}