{
  "type": "Feature",
  "properties": {
    "gn:admin1_code":"30.0",
    "gn:asciiname":"Ban Loeng Faek",
    "gn:country_code":"TH",
    "gn:dem":129,
    "gn:feature_class":"P",
    "gn:feature_code":"PPL",
    "gn:name":"Ban Loeng Faek",
    "gn:population":0,
    "gn:timezone":"Asia/Bangkok",
    "iso:country":"TH",
    "name:tha_x_preferred":[
        "\u0e1a\u0e49\u0e32\u0e19\u0e40\u0e25\u0e34\u0e07\u0e41\u0e1d\u0e01"
    ],
    "wof:name":"Ban Loeng Faek",
    "wof:placetype":"locality"
},
  "geometry": {"coordinates":[104.66970000000001,15.04378],"type":"Point"}
}