{
  "type": "Feature",
  "properties": {
    "gn:admin1_code":"38.0",
    "gn:asciiname":"Ban Wat Mai Phadung Khet",
    "gn:country_code":"TH",
    "gn:dem":3,
    "gn:feature_class":"P",
    "gn:feature_code":"PPL",
    "gn:name":"Ban Wat Mai Phadung Khet",
    "gn:population":0,
    "gn:timezone":"Asia/Bangkok",
    "iso:country":"TH",
    "name:tha_x_preferred":[
        "\u0e1a\u0e49\u0e32\u0e19\u0e27\u0e31\u0e14\u0e43\u0e2b\u0e21\u0e48\u0e1c\u0e14\u0e38\u0e07\u0e40\u0e02\u0e15"
    ],
    "wof:name":"Ban Wat Mai Phadung Khet",
    "wof:placetype":"locality"
},
  "geometry": {"coordinates":[100.372,13.80694],"type":"Point"}
}