{
  "type": "Feature",
  "properties": {
    "gn:admin1_code":"3.0",
    "gn:asciiname":"Ban Nong Bua Sot",
    "gn:country_code":"TH",
    "gn:dem":382,
    "gn:feature_class":"P",
    "gn:feature_code":"PPL",
    "gn:name":"Ban Nong Bua Sot",
    "gn:population":0,
    "gn:timezone":"Asia/Bangkok",
    "iso:country":"TH",
    "wof:name":"Ban Nong Bua Sot",
    "wof:placetype":"locality"
},
  "geometry": {"coordinates":[100.00221999999999,20.27528],"type":"Point"}
}