{
  "type": "Feature",
  "properties": {
    "gn:admin1_code":"2.0",
    "gn:asciiname":"Ban Sa-ngin",
    "gn:country_code":"TH",
    "gn:dem":998,
    "gn:feature_class":"P",
    "gn:feature_code":"PPL",
    "gn:name":"Ban Sa-ngin",
    "gn:population":0,
    "gn:timezone":"Asia/Bangkok",
    "iso:country":"TH",
    "name:tha_x_preferred":[
        "\u0e1a\u0e49\u0e32\u0e19\u0e2a\u0e07\u0e34\u0e19"
    ],
    "wof:name":"Ban Sa-ngin",
    "wof:placetype":"locality"
},
  "geometry": {"coordinates":[98.21142,17.91202999999999],"type":"Point"}
}