{
  "type": "Feature",
  "properties": {
    "gn:admin1_code":"62.0",
    "gn:asciiname":"Ban Phru Champa",
    "gn:country_code":"TH",
    "gn:dem":17,
    "gn:feature_class":"P",
    "gn:feature_code":"PPL",
    "gn:name":"Ban Phru Champa",
    "gn:population":0,
    "gn:timezone":"Asia/Bangkok",
    "iso:country":"TH",
    "name:tha_x_preferred":[
        "\u0e1a\u0e49\u0e32\u0e19\u0e1e\u0e23\u0e38\u0e08\u0e33\u0e1b\u0e32"
    ],
    "name:und_x_variant":[
        "Ban Phru Chan",
        "Ban Phru Champa"
    ],
    "wof:name":"Ban Phru Champa",
    "wof:placetype":"locality"
},
  "geometry": {"coordinates":[98.32028,8.03925],"type":"Point"}
}