{
  "type": "Feature",
  "properties": {
    "gn:admin1_code":"52.0",
    "gn:asciiname":"Ban Chai Rang",
    "gn:country_code":"TH",
    "gn:dem":5,
    "gn:feature_class":"P",
    "gn:feature_code":"PPL",
    "gn:name":"Ban Chai Rang",
    "gn:population":0,
    "gn:timezone":"Asia/Bangkok",
    "iso:country":"TH",
    "name:tha_x_preferred":[
        "\u0e1a\u0e49\u0e32\u0e19\u0e0a\u0e32\u0e22\u0e23\u0e32\u0e07"
    ],
    "wof:name":"Ban Chai Rang",
    "wof:placetype":"locality"
},
  "geometry": {"coordinates":[99.98161,13.581],"type":"Point"}
}