{
  "type": "Feature",
  "properties": {
    "gn:admin1_code":"23.0",
    "gn:asciiname":"Ban Kham Khuean Kaeo Nuea",
    "gn:country_code":"TH",
    "gn:dem":177,
    "gn:feature_class":"P",
    "gn:feature_code":"PPL",
    "gn:name":"Ban Kham Khuean Kaeo Nuea",
    "gn:population":0,
    "gn:timezone":"Asia/Bangkok",
    "iso:country":"TH",
    "name:tha_x_preferred":[
        "\u0e1a\u0e49\u0e32\u0e19\u0e04\u0e33\u0e40\u0e02\u0e37\u0e48\u0e2d\u0e19\u0e41\u0e01\u0e49\u0e27\u0e40\u0e2b\u0e19\u0e37\u0e2d"
    ],
    "wof:name":"Ban Kham Khuean Kaeo Nuea",
    "wof:placetype":"locality"
},
  "geometry": {"coordinates":[103.43881,16.81242],"type":"Point"}
}