{
  "type": "Feature",
  "properties": {
    "gn:admin1_code":"44.0",
    "gn:asciiname":"Ban Pak Ta Lak",
    "gn:country_code":"TH",
    "gn:dem":37,
    "gn:feature_class":"P",
    "gn:feature_code":"PPL",
    "gn:name":"Ban Pak Ta Lak",
    "gn:population":0,
    "gn:timezone":"Asia/Bangkok",
    "iso:country":"TH",
    "name:tha_x_preferred":[
        "\u0e1a\u0e49\u0e32\u0e19\u0e1b\u0e31\u0e01\u0e15\u0e30\u0e25\u0e31\u0e01\u0e29\u0e13\u0e4c"
    ],
    "wof:lang_x_official":[
        "tha"
    ],
    "wof:lang_x_spoken":[
        "tha"
    ],
    "wof:name":"Ban Pak Ta Lak",
    "wof:placetype":"locality"
},
  "geometry": {"coordinates":[101.35053000000001,13.53481],"type":"Point"}
}