{
  "type": "Feature",
  "properties": {
    "gn:admin1_code":"39.0",
    "gn:asciiname":"Ban Chao Khun",
    "gn:country_code":"TH",
    "gn:dem":5,
    "gn:feature_class":"P",
    "gn:feature_code":"PPL",
    "gn:name":"Ban Chao Khun",
    "gn:population":0,
    "gn:timezone":"Asia/Bangkok",
    "iso:country":"TH",
    "name:tha_x_preferred":[
        "Ban Chao Khun"
    ],
    "name:tha_x_variant":[
        "\u0e1a\u0e49\u0e32\u0e19\u0e40\u0e08\u0e49\u0e32\u0e04\u0e38\u0e13"
    ],
    "wof:name":"Ban Chao Khun",
    "wof:placetype":"locality"
},
  "geometry": {"coordinates":[100.46495,14.02336],"type":"Point"}
}