{
  "type": "Feature",
  "properties": {
    "gn:admin1_code":"3.0",
    "gn:asciiname":"Ban Pa Sang Wiwat",
    "gn:country_code":"TH",
    "gn:dem":405,
    "gn:feature_class":"P",
    "gn:feature_code":"PPL",
    "gn:name":"Ban Pa Sang Wiwat",
    "gn:population":0,
    "gn:timezone":"Asia/Bangkok",
    "iso:country":"TH",
    "name:tha_x_preferred":[
        "\u0e1a\u0e49\u0e32\u0e19\u0e1b\u0e48\u0e32\u0e0b\u0e32\u0e07\u0e27\u0e34\u0e27\u0e31\u0e12\u0e19\u0e4c"
    ],
    "wof:name":"Ban Pa Sang Wiwat",
    "wof:placetype":"locality"
},
  "geometry": {"coordinates":[99.87011,20.03417],"type":"Point"}
}