{
  "type": "Feature",
  "properties": {
    "gn:admin1_code":"7.0",
    "gn:asciiname":"Ban Chae Fa",
    "gn:country_code":"TH",
    "gn:dem":126,
    "gn:feature_class":"P",
    "gn:feature_code":"PPL",
    "gn:name":"Ban Chae Fa",
    "gn:population":0,
    "gn:timezone":"Asia/Bangkok",
    "iso:country":"TH",
    "name:tha_x_preferred":[
        "\u0e1a\u0e49\u0e32\u0e19\u0e41\u0e0a\u0e48\u0e1f\u0e49\u0e32"
    ],
    "name:und_x_variant":[
        "B\u0101n Jai Fa",
        "Ban Chai Fa",
        "Ban Chae Fa"
    ],
    "wof:name":"Ban Chae Fa",
    "wof:placetype":"locality"
},
  "geometry": {"coordinates":[99.64975,17.96469],"type":"Point"}
}