{
  "type": "Feature",
  "properties": {
    "gn:country":"TH",
    "gn:fcode":"PPL",
    "gn:pop":0,
    "iso:country":"TH",
    "name:tha_x_preferred":[
        "\u0e1a\u0e49\u0e32\u0e19\u0e04\u0e25\u0e2d\u0e07\u0e1a\u0e32\u0e07\u0e40\u0e0a\u0e37\u0e2d\u0e01\u0e2b\u0e19\u0e31\u0e07"
    ],
    "name:unk_x_variant":[
        "Ban Bang Chuak Nang"
    ],
    "qs:name":"Ban Khlong Bang Chuak Nang",
    "qs:name_adm0":"Thailand",
    "qs:name_adm1":"Bangkok",
    "qs:photos":27,
    "qs:photos_1k":5,
    "qs:photos_9k":1,
    "qs:photos_9r":2,
    "qs:photos_all":27,
    "qs:photos_sr":2,
    "qs:placetype":"Suburb",
    "qs:pop_sr":"0",
    "wof:name":"Ban Khlong Bang Chuak Nang",
    "wof:placetype":"neighbourhood",
    "wof:population":0
},
  "geometry": {"coordinates":[100.41794,13.75336],"type":"Point"}
}