{
  "type": "Feature",
  "properties": {
    "gn:admin1_code":"75.0",
    "gn:asciiname":"Ban Samrong",
    "gn:country_code":"TH",
    "gn:dem":132,
    "gn:feature_class":"P",
    "gn:feature_code":"PPL",
    "gn:name":"Ban Samrong",
    "gn:population":0,
    "gn:timezone":"Asia/Bangkok",
    "iso:country":"TH",
    "name:tha_x_preferred":[
        "\u0e1a\u0e49\u0e32\u0e19\u0e2a\u0e33\u0e42\u0e23\u0e07"
    ],
    "name:und_x_variant":[
        "Son Hong",
        "Ban Son Hong",
        "Ban Som Hong",
        "Ban Samrong"
    ],
    "wof:name":"Ban Samrong",
    "wof:placetype":"locality"
},
  "geometry": {"coordinates":[105.45614,15.74181],"type":"Point"}
}