{
  "type": "Feature",
  "properties": {
    "gn:admin1_code":"59.0",
    "gn:asciiname":"Ban Hin Chang",
    "gn:country_code":"TH",
    "gn:dem":9,
    "gn:feature_class":"P",
    "gn:feature_code":"PPL",
    "gn:name":"Ban Hin Chang",
    "gn:population":0,
    "gn:timezone":"Asia/Bangkok",
    "iso:country":"TH",
    "name:tha_x_preferred":[
        "\u0e1a\u0e49\u0e32\u0e19\u0e2b\u0e34\u0e19\u0e0a\u0e49\u0e32\u0e07"
    ],
    "name:und_x_variant":[
        "B\u0101n K\u0101o Hin Ch\u0101ng",
        "Ban Khao Hin Chang",
        "Ban Hin Chang"
    ],
    "wof:name":"Ban Hin Chang",
    "wof:placetype":"locality"
},
  "geometry": {"coordinates":[98.63861,10.05306],"type":"Point"}
}