{
  "type": "Feature",
  "properties": {
    "gn:country":"TH",
    "gn:fcode":"PPL",
    "gn:pop":0,
    "iso:country":"TH",
    "name:tha_x_preferred":[
        "\u0e1a\u0e49\u0e32\u0e19\u0e27\u0e31\u0e07\u0e01\u0e23\u0e30\u0e41\u0e08\u0e30"
    ],
    "name:unk_x_variant":[
        "Ban Wang Krachae"
    ],
    "qs:name":"Wang Kra Chae",
    "qs:name_adm0":"Thailand",
    "qs:name_adm1":"Kanchanaburi",
    "qs:photos":219,
    "qs:photos_1k":44,
    "qs:photos_9k":1,
    "qs:photos_9r":4,
    "qs:photos_all":219,
    "qs:photos_sr":4,
    "qs:placetype":"Town",
    "qs:pop_sr":"0",
    "wof:name":"Wang Kra Chae",
    "wof:placetype":"locality",
    "wof:population":0
},
  "geometry": {"coordinates":[99.02316999999999,14.23214],"type":"Point"}
}