{
  "type": "Feature",
  "properties": {
    "gn:admin1_code":"3.0",
    "gn:asciiname":"Ban Wang Khiao",
    "gn:country_code":"TH",
    "gn:dem":374,
    "gn:feature_class":"P",
    "gn:feature_code":"PPL",
    "gn:name":"Ban Wang Khiao",
    "gn:population":0,
    "gn:timezone":"Asia/Bangkok",
    "iso:country":"TH",
    "name:tha_x_preferred":[
        "\u0e1a\u0e49\u0e32\u0e19\u0e27\u0e31\u0e07\u0e40\u0e02\u0e35\u0e22\u0e27"
    ],
    "name:und_x_variant":[
        "Ban Wang Khieo",
        "Ban Wang Khiao"
    ],
    "wof:name":"Ban Wang Khiao",
    "wof:placetype":"locality"
},
  "geometry": {"coordinates":[100.08328,20.16764],"type":"Point"}
}