{
  "type": "Feature",
  "properties": {
    "gn:admin1_code":"51.0",
    "gn:asciiname":"Ban Naret Phatthana",
    "gn:country_code":"TH",
    "gn:dem":20,
    "gn:feature_class":"P",
    "gn:feature_code":"PPL",
    "gn:name":"Ban Naret Phatthana",
    "gn:population":0,
    "gn:timezone":"Asia/Bangkok",
    "iso:country":"TH",
    "name:tha_x_preferred":[
        "\u0e1a\u0e49\u0e32\u0e19\u0e19\u0e40\u0e23\u0e28\u0e1e\u0e31\u0e12\u0e19\u0e32"
    ],
    "wof:name":"Ban Naret Phatthana",
    "wof:placetype":"locality"
},
  "geometry": {"coordinates":[99.94994,14.63797],"type":"Point"}
}