{
  "type": "Feature",
  "properties": {
    "gn:admin1_code":"26.0",
    "gn:asciiname":"Ban Non Ma Wo",
    "gn:country_code":"TH",
    "gn:dem":190,
    "gn:feature_class":"P",
    "gn:feature_code":"PPL",
    "gn:name":"Ban Non Ma Wo",
    "gn:population":0,
    "gn:timezone":"Asia/Bangkok",
    "iso:country":"TH",
    "name:tha_x_preferred":[
        "\u0e1a\u0e49\u0e32\u0e19\u0e42\u0e19\u0e19\u0e2b\u0e21\u0e32\u0e27\u0e2d"
    ],
    "name:und_x_variant":[
        "Ban Non Mo"
    ],
    "wof:name":"Ban Non Ma Wo",
    "wof:placetype":"locality"
},
  "geometry": {"coordinates":[101.89528,15.72642],"type":"Point"}
}