{
  "type": "Feature",
  "properties": {
    "gn:admin1_code":"2.0",
    "gn:asciiname":"Ban Saen Tong",
    "gn:country_code":"TH",
    "gn:dem":501,
    "gn:feature_class":"P",
    "gn:feature_code":"PPL",
    "gn:name":"Ban Saen Tong",
    "gn:population":0,
    "gn:timezone":"Asia/Bangkok",
    "iso:country":"TH",
    "name:tha_x_preferred":[
        "\u0e1a\u0e49\u0e32\u0e19\u0e41\u0e2a\u0e19\u0e15\u0e2d\u0e07"
    ],
    "name:und_x_variant":[
        "B\u0101n San Taung",
        "Ban Saen Thong",
        "Ban San Tong",
        "Ban Saen Tong"
    ],
    "wof:name":"Ban Saen Tong",
    "wof:placetype":"locality"
},
  "geometry": {"coordinates":[98.73256000000001,18.84011],"type":"Point"}
}