{
  "type": "Feature",
  "properties": {
    "gn:admin1_code":"37",
    "gn:asciiname":"Ban Nong Kae Noi",
    "gn:country_code":"TH",
    "gn:dem":28,
    "gn:feature_class":"P",
    "gn:feature_code":"PPL",
    "gn:name":"Ban Nong Kae Noi",
    "gn:population":0,
    "gn:timezone":"Asia/Bangkok",
    "iso:country":"TH",
    "name:tha_x_preferred":[
        "\u0e1a\u0e49\u0e32\u0e19\u0e2b\u0e19\u0e2d\u0e07\u0e41\u0e01\u0e19\u0e49\u0e2d\u0e22"
    ],
    "wof:name":"Ban Nong Kae Noi",
    "wof:placetype":"locality"
},
  "geometry": {"coordinates":[100.75569,14.71781],"type":"Point"}
}