{
  "type": "Feature",
  "properties": {
    "gn:admin1_code":"41.0",
    "gn:asciiname":"Ban Lao Oi",
    "gn:country_code":"TH",
    "gn:dem":406,
    "gn:feature_class":"P",
    "gn:feature_code":"PPL",
    "gn:name":"Ban Lao Oi",
    "gn:population":0,
    "gn:timezone":"Asia/Bangkok",
    "iso:country":"TH",
    "name:tha_x_preferred":[
        "\u0e1a\u0e49\u0e32\u0e19\u0e40\u0e2b\u0e25\u0e48\u0e32\u0e2d\u0e49\u0e2d\u0e22"
    ],
    "wof:name":"Ban Lao Oi",
    "wof:placetype":"locality"
},
  "geometry": {"coordinates":[99.83477999999999,19.35208],"type":"Point"}
}