{
  "type": "Feature",
  "properties": {
    "gn:admin1_code":"66.0",
    "gn:asciiname":"Ban Ko Nam Rop",
    "gn:country_code":"TH",
    "gn:dem":15,
    "gn:feature_class":"P",
    "gn:feature_code":"PPL",
    "gn:name":"Ban Ko Nam Rop",
    "gn:population":0,
    "gn:timezone":"Asia/Bangkok",
    "iso:country":"TH",
    "name:tha_x_preferred":[
        "\u0e1a\u0e49\u0e32\u0e19\u0e40\u0e01\u0e32\u0e30\u0e19\u0e49\u0e33\u0e23\u0e2d\u0e1a"
    ],
    "wof:name":"Ban Ko Nam Rop",
    "wof:placetype":"locality"
},
  "geometry": {"coordinates":[100.24297,7.32531],"type":"Point"}
}