{
  "type": "Feature",
  "properties": {
    "gn:admin1_code":"3.0",
    "gn:asciiname":"Ban San Pa Daet",
    "gn:country_code":"TH",
    "gn:dem":385,
    "gn:feature_class":"P",
    "gn:feature_code":"PPL",
    "gn:name":"Ban San Pa Daet",
    "gn:population":0,
    "gn:timezone":"Asia/Bangkok",
    "iso:country":"TH",
    "name:tha_x_preferred":[
        "\u0e1a\u0e49\u0e32\u0e19\u0e2a\u0e31\u0e19\u0e1b\u0e48\u0e32\u0e41\u0e14\u0e14"
    ],
    "wof:name":"Ban San Pa Daet",
    "wof:placetype":"locality"
},
  "geometry": {"coordinates":[99.95406,20.00347],"type":"Point"}
}