{
  "type": "Feature",
  "properties": {
    "gn:admin1_code":"26.0",
    "gn:asciiname":"Ban Talat Raeng",
    "gn:country_code":"TH",
    "gn:dem":207,
    "gn:feature_class":"P",
    "gn:feature_code":"PPL",
    "gn:name":"Ban Talat Raeng",
    "gn:population":0,
    "gn:timezone":"Asia/Bangkok",
    "iso:country":"TH",
    "name:tha_x_preferred":[
        "\u0e1a\u0e49\u0e32\u0e19\u0e15\u0e25\u0e32\u0e14\u0e41\u0e23\u0e49\u0e07"
    ],
    "wof:name":"Ban Talat Raeng",
    "wof:placetype":"locality"
},
  "geometry": {"coordinates":[101.85039,15.81822],"type":"Point"}
}