{
  "type": "Feature",
  "properties": {
    "gn:admin1_code":"75.0",
    "gn:asciiname":"Ban Bak",
    "gn:country_code":"TH",
    "gn:dem":134,
    "gn:feature_class":"P",
    "gn:feature_code":"PPL",
    "gn:name":"Ban Bak",
    "gn:population":0,
    "gn:timezone":"Asia/Bangkok",
    "iso:country":"TH",
    "name:tha_x_preferred":[
        "\u0e1a\u0e49\u0e32\u0e19\u0e1a\u0e32\u0e01"
    ],
    "name:und_x_variant":[
        "Ban Bak Nam"
    ],
    "wof:name":"Ban Bak",
    "wof:placetype":"locality"
},
  "geometry": {"coordinates":[104.90031,15.34692],"type":"Point"}
}