{
  "type": "Feature",
  "properties": {
    "gn:admin1_code":"80",
    "gn:asciiname":"Ban Thap Sayam",
    "gn:country_code":"TH",
    "gn:dem":72,
    "gn:feature_class":"P",
    "gn:feature_code":"PPL",
    "gn:name":"Ban Thap Sayam",
    "gn:population":0,
    "gn:timezone":"Asia/Bangkok",
    "iso:country":"TH",
    "name:tha_x_preferred":[
        "\u0e1a\u0e49\u0e32\u0e19\u0e17\u0e31\u0e1e\u0e2a\u0e22\u0e32\u0e21"
    ],
    "wof:name":"Ban Thap Sayam",
    "wof:placetype":"locality"
},
  "geometry": {"coordinates":[102.74491999999999,13.88897],"type":"Point"}
}