{
  "type": "Feature",
  "properties": {
    "gn:admin1_code":"51.0",
    "gn:asciiname":"Ban Rang Bua Thong",
    "gn:country_code":"TH",
    "gn:dem":5,
    "gn:feature_class":"P",
    "gn:feature_code":"PPL",
    "gn:name":"Ban Rang Bua Thong",
    "gn:population":0,
    "gn:timezone":"Asia/Bangkok",
    "iso:country":"TH",
    "name:tha_x_preferred":[
        "\u0e1a\u0e49\u0e32\u0e19\u0e23\u0e32\u0e07\u0e1a\u0e31\u0e27\u0e17\u0e2d\u0e07"
    ],
    "name:und_x_variant":[
        "Ban Rang Thong (2)"
    ],
    "wof:lang_x_official":[
        "tha"
    ],
    "wof:lang_x_spoken":[
        "tha"
    ],
    "wof:name":"Ban Rang Bua Thong",
    "wof:placetype":"locality"
},
  "geometry": {"coordinates":[100.11060999999999,14.26933],"type":"Point"}
}