{
  "type": "Feature",
  "properties": {
    "gn:admin1_code":"11.0",
    "gn:asciiname":"Ban Samrit",
    "gn:country_code":"TH",
    "gn:dem":99,
    "gn:feature_class":"P",
    "gn:feature_code":"PPL",
    "gn:name":"Ban Samrit",
    "gn:population":0,
    "gn:timezone":"Asia/Bangkok",
    "iso:country":"TH",
    "name:tha_x_preferred":[
        "\u0e1a\u0e49\u0e32\u0e19\u0e2a\u0e31\u0e21\u0e24\u0e17\u0e18\u0e34\u0e4c"
    ],
    "wof:name":"Ban Samrit",
    "wof:placetype":"locality"
},
  "geometry": {"coordinates":[99.50344,16.23594],"type":"Point"}
}