{
  "type": "Feature",
  "properties": {
    "gn:admin1_code":"66.0",
    "gn:asciiname":"Ban Pa Sai Ok",
    "gn:country_code":"TH",
    "gn:dem":50,
    "gn:feature_class":"P",
    "gn:feature_code":"PPL",
    "gn:name":"Ban Pa Sai Ok",
    "gn:population":0,
    "gn:timezone":"Asia/Bangkok",
    "iso:country":"TH",
    "name:tha_x_preferred":[
        "\u0e1a\u0e49\u0e32\u0e19\u0e1b\u0e48\u0e32\u0e43\u0e2a\u0e2d\u0e2d\u0e01"
    ],
    "wof:name":"Ban Pa Sai Ok",
    "wof:placetype":"locality"
},
  "geometry": {"coordinates":[99.93392,7.47392],"type":"Point"}
}