{
  "type": "Feature",
  "properties": {
    "gn:admin1_code":"59.0",
    "gn:asciiname":"Ban Hat Sai Dam",
    "gn:country_code":"TH",
    "gn:dem":6,
    "gn:feature_class":"P",
    "gn:feature_code":"PPL",
    "gn:name":"Ban Hat Sai Dam",
    "gn:population":0,
    "gn:timezone":"Asia/Bangkok",
    "iso:country":"TH",
    "name:tha_x_preferred":[
        "\u0e1a\u0e49\u0e32\u0e19\u0e2b\u0e32\u0e14\u0e17\u0e23\u0e32\u0e22\u0e14\u0e33"
    ],
    "wof:name":"Ban Hat Sai Dam",
    "wof:placetype":"locality"
},
  "geometry": {"coordinates":[98.51944,9.78792],"type":"Point"}
}