{
  "type": "Feature",
  "properties": {
    "gn:admin1_code":"12.0",
    "gn:asciiname":"Ban Sap Samut",
    "gn:country_code":"TH",
    "gn:dem":184,
    "gn:feature_class":"P",
    "gn:feature_code":"PPL",
    "gn:name":"Ban Sap Samut",
    "gn:population":0,
    "gn:timezone":"Asia/Bangkok",
    "iso:country":"TH",
    "name:tha_x_preferred":[
        "\u0e1a\u0e49\u0e32\u0e19\u0e0b\u0e31\u0e1a\u0e2a\u0e21\u0e38\u0e17\u0e23"
    ],
    "wof:name":"Ban Sap Samut",
    "wof:placetype":"locality"
},
  "geometry": {"coordinates":[100.58672,17.12706],"type":"Point"}
}