{
  "type": "Feature",
  "properties": {
    "gn:admin1_code":"39.0",
    "gn:asciiname":"Ban Khok Chaphlu",
    "gn:country_code":"TH",
    "gn:dem":5,
    "gn:feature_class":"P",
    "gn:feature_code":"PPL",
    "gn:name":"Ban Khok Chaphlu",
    "gn:population":0,
    "gn:timezone":"Asia/Bangkok",
    "iso:country":"TH",
    "name:tha_x_preferred":[
        "\u0e1a\u0e49\u0e32\u0e19\u0e42\u0e04\u0e01\u0e0a\u0e30\u0e1e\u0e25\u0e39"
    ],
    "wof:name":"Ban Khok Chaphlu",
    "wof:placetype":"locality"
},
  "geometry": {"coordinates":[100.53506,13.98317],"type":"Point"}
}