{
  "type": "Feature",
  "properties": {
    "gn:admin1_code":"16.0",
    "gn:asciiname":"Ban Noen Phayom",
    "gn:country_code":"TH",
    "gn:dem":38,
    "gn:feature_class":"P",
    "gn:feature_code":"PPL",
    "gn:name":"Ban Noen Phayom",
    "gn:population":0,
    "gn:timezone":"Asia/Bangkok",
    "iso:country":"TH",
    "name:tha_x_preferred":[
        "\u0e1a\u0e49\u0e32\u0e19\u0e40\u0e19\u0e34\u0e19\u0e1e\u0e22\u0e2d\u0e21"
    ],
    "name:und_x_variant":[
        "Naung Phayaum",
        "Ban Non Phayom",
        "B\u0101n Naun Phayaum",
        "Ban Noen Phayom"
    ],
    "wof:lang_x_official":[
        "tha"
    ],
    "wof:lang_x_spoken":[
        "tha"
    ],
    "wof:name":"Ban Noen Phayom",
    "wof:placetype":"locality"
},
  "geometry": {"coordinates":[100.06874999999999,15.91839],"type":"Point"}
}