{
  "type": "Feature",
  "properties": {
    "gn:admin1_code":"53.0",
    "gn:asciiname":"Ban Bang Kaeo",
    "gn:country_code":"TH",
    "gn:dem":6,
    "gn:feature_class":"P",
    "gn:feature_code":"PPL",
    "gn:name":"Ban Bang Kaeo",
    "gn:population":0,
    "gn:timezone":"Asia/Bangkok",
    "iso:country":"TH",
    "name:tha_x_preferred":[
        "\u0e1a\u0e49\u0e32\u0e19\u0e1a\u0e32\u0e07\u0e41\u0e01\u0e49\u0e27"
    ],
    "name:und_x_variant":[
        "Ban Bang Kew",
        "Ban Bang Kaeo"
    ],
    "wof:name":"Ban Bang Kaeo",
    "wof:placetype":"locality"
},
  "geometry": {"coordinates":[100.1589,13.73843],"type":"Point"}
}