{
  "type": "Feature",
  "properties": {
    "gn:admin1_code":"37",
    "gn:asciiname":"Ban Raphi Phat",
    "gn:country_code":"TH",
    "gn:dem":5,
    "gn:feature_class":"P",
    "gn:feature_code":"PPL",
    "gn:name":"Ban Raphi Phat",
    "gn:population":0,
    "gn:timezone":"Asia/Bangkok",
    "iso:country":"TH",
    "name:tha_x_preferred":[
        "\u0e1a\u0e49\u0e32\u0e19\u0e23\u0e30\u0e1e\u0e35\u0e1e\u0e31\u0e12\u0e19\u0e4c"
    ],
    "wof:name":"Ban Raphi Phat",
    "wof:placetype":"locality"
},
  "geometry": {"coordinates":[100.83333,14.24769],"type":"Point"}
}