{
  "type": "Feature",
  "properties": {
    "gn:admin1_code":"7.0",
    "gn:asciiname":"Ban Na Khaem",
    "gn:country_code":"TH",
    "gn:dem":742,
    "gn:feature_class":"P",
    "gn:feature_code":"PPL",
    "gn:name":"Ban Na Khaem",
    "gn:population":0,
    "gn:timezone":"Asia/Bangkok",
    "iso:country":"TH",
    "name:tha_x_preferred":[
        "\u0e1a\u0e49\u0e32\u0e19\u0e19\u0e32\u0e41\u0e04\u0e21"
    ],
    "wof:name":"Ban Na Khaem",
    "wof:placetype":"locality"
},
  "geometry": {"coordinates":[100.33293999999999,18.15008],"type":"Point"}
}