{
  "type": "Feature",
  "properties": {
    "gn:admin1_code":"5.0",
    "gn:asciiname":"Ban Mae Moei",
    "gn:country_code":"TH",
    "gn:dem":337,
    "gn:feature_class":"P",
    "gn:feature_code":"PPL",
    "gn:name":"Ban Mae Moei",
    "gn:population":0,
    "gn:timezone":"Asia/Bangkok",
    "iso:country":"TH",
    "name:tha_x_preferred":[
        "\u0e1a\u0e49\u0e32\u0e19\u0e41\u0e21\u0e48\u0e40\u0e21\u0e22"
    ],
    "wof:name":"Ban Mae Moei",
    "wof:placetype":"locality"
},
  "geometry": {"coordinates":[98.96496999999999,18.40414],"type":"Point"}
}