{
  "type": "Feature",
  "properties": {
    "gn:admin1_code":"6.0",
    "gn:asciiname":"Ban Mae Tip Luang",
    "gn:country_code":"TH",
    "gn:dem":246,
    "gn:feature_class":"P",
    "gn:feature_code":"PPL",
    "gn:name":"Ban Mae Tip Luang",
    "gn:population":0,
    "gn:timezone":"Asia/Bangkok",
    "iso:country":"TH",
    "name:tha_x_preferred":[
        "\u0e1a\u0e49\u0e32\u0e19\u0e41\u0e21\u0e48\u0e15\u0e35\u0e1a\u0e2b\u0e25\u0e27\u0e07"
    ],
    "wof:name":"Ban Mae Tip Luang",
    "wof:placetype":"locality"
},
  "geometry": {"coordinates":[100.03697,18.60467],"type":"Point"}
}