{
  "type": "Feature",
  "properties": {
    "gn:admin1_code":"26.0",
    "gn:asciiname":"Ban Non Kha",
    "gn:country_code":"TH",
    "gn:dem":209,
    "gn:feature_class":"P",
    "gn:feature_code":"PPL",
    "gn:name":"Ban Non Kha",
    "gn:population":0,
    "gn:timezone":"Asia/Bangkok",
    "iso:country":"TH",
    "name:tha_x_preferred":[
        "\u0e1a\u0e49\u0e32\u0e19\u0e42\u0e19\u0e19\u0e02\u0e48\u0e32"
    ],
    "wof:name":"Ban Non Kha",
    "wof:placetype":"locality"
},
  "geometry": {"coordinates":[102.18781,16.38586],"type":"Point"}
}