{
  "type": "Feature",
  "properties": {
    "gn:admin1_code":"75.0",
    "gn:asciiname":"Ban Dong Mai Ngam",
    "gn:country_code":"TH",
    "gn:dem":137,
    "gn:feature_class":"P",
    "gn:feature_code":"PPL",
    "gn:name":"Ban Dong Mai Ngam",
    "gn:population":0,
    "gn:timezone":"Asia/Bangkok",
    "iso:country":"TH",
    "name:tha_x_preferred":[
        "\u0e1a\u0e49\u0e32\u0e19\u0e14\u0e07\u0e44\u0e21\u0e49\u0e07\u0e32\u0e21"
    ],
    "wof:name":"Ban Dong Mai Ngam",
    "wof:placetype":"locality"
},
  "geometry": {"coordinates":[104.93844,15.57294],"type":"Point"}
}