{
  "type": "Feature",
  "properties": {
    "gn:admin1_code":"3.0",
    "gn:asciiname":"Ban Rong Bong Tai",
    "gn:country_code":"TH",
    "gn:dem":389,
    "gn:feature_class":"P",
    "gn:feature_code":"PPL",
    "gn:name":"Ban Rong Bong Tai",
    "gn:population":0,
    "gn:timezone":"Asia/Bangkok",
    "iso:country":"TH",
    "name:tha_x_preferred":[
        "\u0e1a\u0e49\u0e32\u0e19\u0e23\u0e48\u0e2d\u0e07\u0e1a\u0e07\u0e43\u0e15\u0e49"
    ],
    "wof:name":"Ban Rong Bong Tai",
    "wof:placetype":"locality"
},
  "geometry": {"coordinates":[99.97533,19.43311],"type":"Point"}
}