{
  "type": "Feature",
  "properties": {
    "gn:admin1_code":"69.0",
    "gn:asciiname":"Ban Bae Ro Sa Ning",
    "gn:country_code":"TH",
    "gn:dem":10,
    "gn:feature_class":"P",
    "gn:feature_code":"PPL",
    "gn:name":"Ban Bae Ro Sa Ning",
    "gn:population":0,
    "gn:timezone":"Asia/Bangkok",
    "iso:country":"TH",
    "name:tha_x_preferred":[
        "\u0e1a\u0e49\u0e32\u0e19\u0e41\u0e1a\u0e23\u0e2d\u0e2a\u0e30\u0e19\u0e34\u0e07"
    ],
    "wof:name":"Ban Bae Ro Sa Ning",
    "wof:placetype":"locality"
},
  "geometry": {"coordinates":[101.26844,6.84314],"type":"Point"}
}