{
  "type": "Feature",
  "properties": {
    "gn:admin1_code":"74",
    "gn:asciiname":"Ban Huai Krabok",
    "gn:country_code":"TH",
    "gn:dem":59,
    "gn:feature_class":"P",
    "gn:feature_code":"PPL",
    "gn:name":"Ban Huai Krabok",
    "gn:population":0,
    "gn:timezone":"Asia/Bangkok",
    "iso:country":"TH",
    "name:tha_x_preferred":[
        "\u0e1a\u0e49\u0e32\u0e19\u0e2b\u0e49\u0e27\u0e22\u0e01\u0e23\u0e30\u0e1a\u0e2d\u0e01"
    ],
    "wof:name":"Ban Huai Krabok",
    "wof:placetype":"locality"
},
  "geometry": {"coordinates":[101.94361000000001,13.78592],"type":"Point"}
}