{
  "type": "Feature",
  "properties": {
    "gn:admin1_code":"41.0",
    "gn:asciiname":"Ban Tham Mongkhon",
    "gn:country_code":"TH",
    "gn:dem":443,
    "gn:feature_class":"P",
    "gn:feature_code":"PPL",
    "gn:name":"Ban Tham Mongkhon",
    "gn:population":0,
    "gn:timezone":"Asia/Bangkok",
    "iso:country":"TH",
    "name:tha_x_preferred":[
        "\u0e1a\u0e49\u0e32\u0e19\u0e16\u0e49\u0e33\u0e21\u0e07\u0e04\u0e25"
    ],
    "wof:name":"Ban Tham Mongkhon",
    "wof:placetype":"locality"
},
  "geometry": {"coordinates":[100.07144,19.08739],"type":"Point"}
}