{
  "type": "Feature",
  "properties": {
    "gn:admin1_code":"75.0",
    "gn:asciiname":"Ban Nong Krabue",
    "gn:country_code":"TH",
    "gn:dem":134,
    "gn:feature_class":"P",
    "gn:feature_code":"PPL",
    "gn:name":"Ban Nong Krabue",
    "gn:population":0,
    "gn:timezone":"Asia/Bangkok",
    "iso:country":"TH",
    "name:tha_x_preferred":[
        "\u0e1a\u0e49\u0e32\u0e19\u0e2b\u0e19\u0e2d\u0e07\u0e01\u0e23\u0e30\u0e1a\u0e37\u0e2d"
    ],
    "name:und_x_variant":[
        "Ban Nong Krabu"
    ],
    "wof:name":"Ban Nong Krabue",
    "wof:placetype":"locality"
},
  "geometry": {"coordinates":[105.08914,14.97753],"type":"Point"}
}