{
  "type": "Feature",
  "properties": {
    "gn:admin1_code":"59.0",
    "gn:asciiname":"Ban Bang Song Ra",
    "gn:country_code":"TH",
    "gn:dem":21,
    "gn:feature_class":"P",
    "gn:feature_code":"PPL",
    "gn:name":"Ban Bang Song Ra",
    "gn:population":0,
    "gn:timezone":"Asia/Bangkok",
    "iso:country":"TH",
    "name:tha_x_preferred":[
        "\u0e1a\u0e49\u0e32\u0e19\u0e1a\u0e32\u0e07\u0e2a\u0e2d\u0e07\u0e23\u0e32"
    ],
    "wof:name":"Ban Bang Song Ra",
    "wof:placetype":"locality"
},
  "geometry": {"coordinates":[98.77097000000001,10.29917],"type":"Point"}
}