{
  "type": "Feature",
  "properties": {
    "gn:admin1_code":"11.0",
    "gn:asciiname":"Ban Kosamphi",
    "gn:country_code":"TH",
    "gn:dem":104,
    "gn:feature_class":"P",
    "gn:feature_code":"PPL",
    "gn:name":"Ban Kosamphi",
    "gn:population":0,
    "gn:timezone":"Asia/Bangkok",
    "iso:country":"TH",
    "name:tha_x_preferred":[
        "\u0e1a\u0e49\u0e32\u0e19\u0e42\u0e01\u0e2a\u0e31\u0e21\u0e1e\u0e35"
    ],
    "wof:name":"Ban Kosamphi",
    "wof:placetype":"locality"
},
  "geometry": {"coordinates":[99.28697,16.67117],"type":"Point"}
}