{
  "type": "Feature",
  "properties": {
    "gn:admin1_code":"17.0",
    "gn:asciiname":"Ban Na Thap Hai",
    "gn:country_code":"TH",
    "gn:dem":171,
    "gn:feature_class":"P",
    "gn:feature_code":"PPL",
    "gn:name":"Ban Na Thap Hai",
    "gn:population":0,
    "gn:timezone":"Asia/Bangkok",
    "iso:country":"TH",
    "name:tha_x_preferred":[
        "\u0e1a\u0e49\u0e32\u0e19\u0e19\u0e32\u0e17\u0e31\u0e1a\u0e44\u0e2e"
    ],
    "wof:name":"Ban Na Thap Hai",
    "wof:placetype":"locality"
},
  "geometry": {"coordinates":[103.29125000000001,18.21033],"type":"Point"}
}