{
  "type": "Feature",
  "properties": {
    "gn:admin1_code":"72.0",
    "gn:asciiname":"Ban Sok Phakwan",
    "gn:country_code":"TH",
    "gn:dem":157,
    "gn:feature_class":"P",
    "gn:feature_code":"PPL",
    "gn:name":"Ban Sok Phakwan",
    "gn:population":0,
    "gn:timezone":"Asia/Bangkok",
    "iso:country":"TH",
    "name:tha_x_preferred":[
        "\u0e1a\u0e49\u0e32\u0e19\u0e42\u0e2a\u0e01\u0e1c\u0e31\u0e01\u0e2b\u0e27\u0e32\u0e19"
    ],
    "wof:name":"Ban Sok Phakwan",
    "wof:placetype":"locality"
},
  "geometry": {"coordinates":[104.21586000000001,15.99733],"type":"Point"}
}