{
  "type": "Feature",
  "properties": {
    "gn:admin1_code":"67.0",
    "gn:asciiname":"Ban Pae-ra Tai",
    "gn:country_code":"TH",
    "gn:dem":22,
    "gn:feature_class":"P",
    "gn:feature_code":"PPL",
    "gn:name":"Ban Pae-ra Tai",
    "gn:population":0,
    "gn:timezone":"Asia/Bangkok",
    "iso:country":"TH",
    "name:tha_x_preferred":[
        "Ban Pae-ra Tai"
    ],
    "name:tha_x_variant":[
        "\u0e1a\u0e49\u0e32\u0e19\u0e41\u0e1b-\u0e23\u0e30\u0e43\u0e15\u0e49"
    ],
    "wof:name":"Ban Pae-ra Tai",
    "wof:placetype":"locality"
},
  "geometry": {"coordinates":[99.92764,6.82408],"type":"Point"}
}