{
  "type": "Feature",
  "properties": {
    "gn:admin1_code":"14.0",
    "gn:asciiname":"Ban Dong Mueang",
    "gn:country_code":"TH",
    "gn:dem":142,
    "gn:feature_class":"P",
    "gn:feature_code":"PPL",
    "gn:name":"Ban Dong Mueang",
    "gn:population":0,
    "gn:timezone":"Asia/Bangkok",
    "iso:country":"TH",
    "name:tha_x_preferred":[
        "\u0e1a\u0e49\u0e32\u0e19\u0e14\u0e07\u0e40\u0e21\u0e37\u0e2d\u0e07"
    ],
    "wof:name":"Ban Dong Mueang",
    "wof:placetype":"locality"
},
  "geometry": {"coordinates":[101.23314000000001,16.72256],"type":"Point"}
}