{
  "type": "Feature",
  "properties": {
    "gn:admin1_code":"49.0",
    "gn:asciiname":"Ban Thammachat Lang",
    "gn:country_code":"TH",
    "gn:dem":25,
    "gn:feature_class":"P",
    "gn:feature_code":"PPL",
    "gn:name":"Ban Thammachat Lang",
    "gn:population":0,
    "gn:timezone":"Asia/Bangkok",
    "iso:country":"TH",
    "name:tha_x_preferred":[
        "\u0e1a\u0e49\u0e32\u0e19\u0e18\u0e23\u0e23\u0e21\u0e0a\u0e32\u0e15\u0e34\u0e25\u0e48\u0e32\u0e07"
    ],
    "name:und_x_variant":[
        "Thama Chat Lang",
        "Ban Thammachat Lang"
    ],
    "wof:name":"Ban Thammachat Lang",
    "wof:placetype":"locality"
},
  "geometry": {"coordinates":[102.31467000000001,12.20256],"type":"Point"}
}