{
  "type": "Feature",
  "properties": {
    "gn:admin1_code":"2.0",
    "gn:asciiname":"Ban Pa Khaem",
    "gn:country_code":"TH",
    "gn:dem":377,
    "gn:feature_class":"P",
    "gn:feature_code":"PPL",
    "gn:name":"Ban Pa Khaem",
    "gn:population":0,
    "gn:timezone":"Asia/Bangkok",
    "iso:country":"TH",
    "name:tha_x_preferred":[
        "\u0e1a\u0e49\u0e32\u0e19\u0e1b\u0e48\u0e32\u0e41\u0e02\u0e21"
    ],
    "name:und_x_variant":[
        "Van Pa Khaem",
        "Ban Thung Pa Khaem",
        "B\u0101n Thung Pa Keam",
        "Ban Pa Khaem"
    ],
    "wof:lang_x_official":[
        "tha"
    ],
    "wof:lang_x_spoken":[
        "tha"
    ],
    "wof:name":"Ban Pa Khaem",
    "wof:placetype":"locality"
},
  "geometry": {"coordinates":[99.05756,19.10456],"type":"Point"}
}