{
  "type": "Feature",
  "properties": {
    "gn:admin1_code":"3.0",
    "gn:asciiname":"Ban Pa Kha Mai",
    "gn:country_code":"TH",
    "gn:dem":696,
    "gn:feature_class":"P",
    "gn:feature_code":"PPL",
    "gn:name":"Ban Pa Kha Mai",
    "gn:population":0,
    "gn:timezone":"Asia/Bangkok",
    "iso:country":"TH",
    "name:tha_x_preferred":[
        "\u0e1a\u0e49\u0e32\u0e19\u0e1b\u0e48\u0e32\u0e04\u0e32\u0e43\u0e2b\u0e21\u0e48"
    ],
    "wof:name":"Ban Pa Kha Mai",
    "wof:placetype":"locality"
},
  "geometry": {"coordinates":[99.67867,20.20942],"type":"Point"}
}