{
  "type": "Feature",
  "properties": {
    "gn:admin1_code":"58.0",
    "gn:asciiname":"Ban Huai Thap Thong",
    "gn:country_code":"TH",
    "gn:dem":47,
    "gn:feature_class":"P",
    "gn:feature_code":"PPL",
    "gn:name":"Ban Huai Thap Thong",
    "gn:population":0,
    "gn:timezone":"Asia/Bangkok",
    "iso:country":"TH",
    "name:tha_x_preferred":[
        "\u0e1a\u0e49\u0e32\u0e19\u0e2b\u0e49\u0e27\u0e22\u0e17\u0e31\u0e1a\u0e17\u0e2d\u0e07"
    ],
    "wof:name":"Ban Huai Thap Thong",
    "wof:placetype":"locality"
},
  "geometry": {"coordinates":[98.95435999999999,10.21333],"type":"Point"}
}