{
  "type": "Feature",
  "properties": {
    "gn:admin1_code":"46.0",
    "gn:asciiname":"Ban Sa Na",
    "gn:country_code":"TH",
    "gn:dem":26,
    "gn:feature_class":"P",
    "gn:feature_code":"PPL",
    "gn:name":"Ban Sa Na",
    "gn:population":0,
    "gn:timezone":"Asia/Bangkok",
    "iso:country":"TH",
    "name:tha_x_preferred":[
        "\u0e1a\u0e49\u0e32\u0e19\u0e2a\u0e23\u0e30\u0e19\u0e32"
    ],
    "name:und_x_variant":[
        "Ban Sana"
    ],
    "wof:name":"Ban Sa Na",
    "wof:placetype":"locality"
},
  "geometry": {"coordinates":[101.25358,13.44081],"type":"Point"}
}