{
  "type": "Feature",
  "properties": {
    "gn:admin1_code":"2.0",
    "gn:asciiname":"Ban Mueang Kung",
    "gn:country_code":"TH",
    "gn:dem":315,
    "gn:feature_class":"P",
    "gn:feature_code":"PPL",
    "gn:name":"Ban Mueang Kung",
    "gn:population":0,
    "gn:timezone":"Asia/Bangkok",
    "iso:country":"TH",
    "name:tha_x_preferred":[
        "\u0e1a\u0e49\u0e32\u0e19\u0e40\u0e2b\u0e21\u0e37\u0e2d\u0e07\u0e01\u0e38\u0e07"
    ],
    "name:und_x_variant":[
        "B\u0101n Muang Gung",
        "Ban Muang Kung",
        "Ban Mueang Kung"
    ],
    "wof:name":"Ban Mueang Kung",
    "wof:placetype":"locality"
},
  "geometry": {"coordinates":[98.93832999999999,18.73042],"type":"Point"}
}