{
  "type": "Feature",
  "properties": {
    "gn:admin1_code":"80",
    "gn:asciiname":"Ban Phakdi Phaendin",
    "gn:country_code":"TH",
    "gn:dem":93,
    "gn:feature_class":"P",
    "gn:feature_code":"PPL",
    "gn:name":"Ban Phakdi Phaendin",
    "gn:population":0,
    "gn:timezone":"Asia/Bangkok",
    "iso:country":"TH",
    "name:tha_x_preferred":[
        "\u0e1a\u0e49\u0e32\u0e19\u0e20\u0e31\u0e01\u0e14\u0e35\u0e41\u0e1c\u0e48\u0e19\u0e14\u0e34\u0e19"
    ],
    "wof:name":"Ban Phakdi Phaendin",
    "wof:placetype":"locality"
},
  "geometry": {"coordinates":[102.35393999999999,13.95192],"type":"Point"}
}