{
  "type": "Feature",
  "properties": {
    "gn:admin1_code":"26.0",
    "gn:asciiname":"Ban Non Makhang",
    "gn:country_code":"TH",
    "gn:dem":224,
    "gn:feature_class":"P",
    "gn:feature_code":"PPL",
    "gn:name":"Ban Non Makhang",
    "gn:population":0,
    "gn:timezone":"Asia/Bangkok",
    "iso:country":"TH",
    "name:tha_x_preferred":[
        "\u0e1a\u0e49\u0e32\u0e19\u0e42\u0e19\u0e19\u0e21\u0e30\u0e04\u0e48\u0e32\u0e07"
    ],
    "wof:name":"Ban Non Makhang",
    "wof:placetype":"locality"
},
  "geometry": {"coordinates":[101.97011000000001,16.31147],"type":"Point"}
}