{
  "type": "Feature",
  "properties": {
    "gn:admin1_code":"6.0",
    "gn:asciiname":"Ban Pa Cham Pa Kha",
    "gn:country_code":"TH",
    "gn:dem":231,
    "gn:feature_class":"P",
    "gn:feature_code":"PPL",
    "gn:name":"Ban Pa Cham Pa Kha",
    "gn:population":0,
    "gn:timezone":"Asia/Bangkok",
    "iso:country":"TH",
    "name:tha_x_preferred":[
        "\u0e1a\u0e49\u0e32\u0e19\u0e1b\u0e48\u0e32\u0e08\u0e49\u0e33\u0e1b\u0e48\u0e32\u0e04\u0e32"
    ],
    "wof:name":"Ban Pa Cham Pa Kha",
    "wof:placetype":"locality"
},
  "geometry": {"coordinates":[99.43586000000001,18.156],"type":"Point"}
}