{
  "type": "Feature",
  "properties": {
    "gn:admin1_code":"14.0",
    "gn:asciiname":"Ban Pho Paeng",
    "gn:country_code":"TH",
    "gn:dem":99,
    "gn:feature_class":"P",
    "gn:feature_code":"PPL",
    "gn:name":"Ban Pho Paeng",
    "gn:population":0,
    "gn:timezone":"Asia/Bangkok",
    "iso:country":"TH",
    "name:tha_x_preferred":[
        "\u0e1a\u0e49\u0e32\u0e19\u0e1e\u0e48\u0e2d\u0e41\u0e1b\u0e49\u0e07"
    ],
    "wof:name":"Ban Pho Paeng",
    "wof:placetype":"locality"
},
  "geometry": {"coordinates":[100.81399999999999,15.80225],"type":"Point"}
}