{
  "type": "Feature",
  "properties": {
    "gn:admin1_code":"22",
    "gn:asciiname":"Ban Nong No",
    "gn:country_code":"TH",
    "gn:dem":216,
    "gn:feature_class":"P",
    "gn:feature_code":"PPL",
    "gn:name":"Ban Nong No",
    "gn:population":0,
    "gn:timezone":"Asia/Bangkok",
    "iso:country":"TH",
    "name:tha_x_preferred":[
        "\u0e1a\u0e49\u0e32\u0e19\u0e2b\u0e19\u0e2d\u0e07\u0e42\u0e19"
    ],
    "wof:name":"Ban Nong No",
    "wof:placetype":"locality"
},
  "geometry": {"coordinates":[102.44719000000001,16.44067],"type":"Point"}
}