{
  "type": "Feature",
  "properties": {
    "gn:admin1_code":"41.0",
    "gn:asciiname":"Ban Kha Lang",
    "gn:country_code":"TH",
    "gn:dem":388,
    "gn:feature_class":"P",
    "gn:feature_code":"PPL",
    "gn:name":"Ban Kha Lang",
    "gn:population":0,
    "gn:timezone":"Asia/Bangkok",
    "iso:country":"TH",
    "name:tha_x_preferred":[
        "\u0e1a\u0e49\u0e32\u0e19\u0e04\u0e48\u0e32\u0e25\u0e48\u0e32\u0e07"
    ],
    "wof:name":"Ban Kha Lang",
    "wof:placetype":"locality"
},
  "geometry": {"coordinates":[100.02592,19.27794],"type":"Point"}
}