{
  "type": "Feature",
  "properties": {
    "gn:admin1_code":"18.0",
    "gn:asciiname":"Ban Na Lak",
    "gn:country_code":"TH",
    "gn:dem":256,
    "gn:feature_class":"P",
    "gn:feature_code":"PPL",
    "gn:name":"Ban Na Lak",
    "gn:population":0,
    "gn:timezone":"Asia/Bangkok",
    "iso:country":"TH",
    "name:tha_x_preferred":[
        "\u0e1a\u0e49\u0e32\u0e19\u0e19\u0e32\u0e2b\u0e25\u0e31\u0e01"
    ],
    "name:und_x_variant":[
        "Ban Ha Lak",
        "Ban Na Lak"
    ],
    "wof:name":"Ban Na Lak",
    "wof:placetype":"locality"
},
  "geometry": {"coordinates":[101.76861,17.31425],"type":"Point"}
}