{
  "type": "Feature",
  "properties": {
    "gn:admin1_code":"28",
    "gn:asciiname":"Ban Pik Fai",
    "gn:country_code":"TH",
    "gn:dem":173,
    "gn:feature_class":"P",
    "gn:feature_code":"PPL",
    "gn:name":"Ban Pik Fai",
    "gn:population":0,
    "gn:timezone":"Asia/Bangkok",
    "iso:country":"TH",
    "name:tha_x_preferred":[
        "\u0e1a\u0e49\u0e32\u0e19\u0e1b\u0e35\u0e01\u0e1d\u0e32\u0e22"
    ],
    "wof:name":"Ban Pik Fai",
    "wof:placetype":"locality"
},
  "geometry": {"coordinates":[103.04383,15.03925],"type":"Point"}
}