{
  "type": "Feature",
  "properties": {
    "gn:admin1_code":"39.0",
    "gn:asciiname":"Ban Khlong Sip Song Sai Klang",
    "gn:country_code":"TH",
    "gn:dem":8,
    "gn:feature_class":"P",
    "gn:feature_code":"PPL",
    "gn:name":"Ban Khlong Sip Song Sai Klang",
    "gn:population":0,
    "gn:timezone":"Asia/Bangkok",
    "iso:country":"TH",
    "name:tha_x_preferred":[
        "Ban Khlong Sip Song Sai Klang"
    ],
    "name:tha_x_variant":[
        "\u0e1a\u0e49\u0e32\u0e19\u0e04\u0e25\u0e2d\u0e07\u0e2a\u0e34\u0e1a\u0e2a\u0e2d\u0e07\u0e2a\u0e32\u0e22\u0e01\u0e25\u0e32\u0e07",
        "Ban Khlong 12 Sai Klang"
    ],
    "name:und_x_variant":[
        "Ban Khlong Thi Sip Song",
        "Ban Khlong Sip Song Sai Lang (2)"
    ],
    "wof:lang_x_official":[
        "tha"
    ],
    "wof:lang_x_spoken":[
        "tha"
    ],
    "wof:name":"Ban Khlong Sip Song Sai Klang",
    "wof:placetype":"locality"
},
  "geometry": {"coordinates":[100.86756,14.01156],"type":"Point"}
}