{
  "type": "Feature",
  "properties": {
    "gn:admin1_code":"30.0",
    "gn:asciiname":"Ban Thamnop",
    "gn:country_code":"TH",
    "gn:dem":178,
    "gn:feature_class":"P",
    "gn:feature_code":"PPL",
    "gn:name":"Ban Thamnop",
    "gn:population":0,
    "gn:timezone":"Asia/Bangkok",
    "iso:country":"TH",
    "name:tha_x_preferred":[
        "\u0e1a\u0e49\u0e32\u0e19\u0e17\u0e33\u0e19\u0e1a"
    ],
    "wof:name":"Ban Thamnop",
    "wof:placetype":"locality"
},
  "geometry": {"coordinates":[104.06435999999999,14.54853],"type":"Point"}
}