{
  "type": "Feature",
  "properties": {
    "gn:admin1_code":"64.0",
    "gn:asciiname":"Ban Pho Temi",
    "gn:country_code":"TH",
    "gn:dem":27,
    "gn:feature_class":"P",
    "gn:feature_code":"PPL",
    "gn:name":"Ban Pho Temi",
    "gn:population":0,
    "gn:timezone":"Asia/Bangkok",
    "iso:country":"TH",
    "name:tha_x_preferred":[
        "\u0e1a\u0e49\u0e32\u0e19\u0e42\u0e1e\u0e18\u0e34\u0e4c\u0e40\u0e15\u0e21\u0e35\u0e22\u0e4c"
    ],
    "name:und_x_variant":[
        "Ban Pho Tai"
    ],
    "wof:name":"Ban Pho Temi",
    "wof:placetype":"locality"
},
  "geometry": {"coordinates":[99.84083,8.68292],"type":"Point"}
}