{
  "type": "Feature",
  "properties": {
    "gn:admin1_code":"42.0",
    "gn:asciiname":"Ban Khlong Wat King Kaeo",
    "gn:country_code":"TH",
    "gn:dem":4,
    "gn:feature_class":"P",
    "gn:feature_code":"PPL",
    "gn:name":"Ban Khlong Wat King Kaeo",
    "gn:population":0,
    "gn:timezone":"Asia/Bangkok",
    "iso:country":"TH",
    "name:tha_x_preferred":[
        "\u0e1a\u0e49\u0e32\u0e19\u0e04\u0e25\u0e2d\u0e07\u0e27\u0e31\u0e14\u0e01\u0e34\u0e48\u0e07\u0e41\u0e01\u0e49\u0e27"
    ],
    "wof:name":"Ban Khlong Wat King Kaeo",
    "wof:placetype":"locality"
},
  "geometry": {"coordinates":[100.71603,13.67283],"type":"Point"}
}