{
  "type": "Feature",
  "properties": {
    "gn:admin1_code":"8.0",
    "gn:asciiname":"Ban Mae La Yo Khi",
    "gn:country_code":"TH",
    "gn:dem":548,
    "gn:feature_class":"P",
    "gn:feature_code":"PPL",
    "gn:name":"Ban Mae La Yo Khi",
    "gn:population":0,
    "gn:timezone":"Asia/Bangkok",
    "iso:country":"TH",
    "name:tha_x_preferred":[
        "Ban Mae La Yo Khi"
    ],
    "name:tha_x_variant":[
        "\u0e1a\u0e49\u0e32\u0e19\u0e41\u0e21\u0e48\u0e2b\u0e25\u0e30\u0e22\u0e2d\u0e04\u0e35"
    ],
    "wof:name":"Ban Mae La Yo Khi",
    "wof:placetype":"locality"
},
  "geometry": {"coordinates":[98.01810999999999,17.66542],"type":"Point"}
}