{
  "type": "Feature",
  "properties": {
    "gn:admin1_code":"44.0",
    "gn:asciiname":"Ban Tha Rahat",
    "gn:country_code":"TH",
    "gn:dem":5,
    "gn:feature_class":"P",
    "gn:feature_code":"PPL",
    "gn:name":"Ban Tha Rahat",
    "gn:population":0,
    "gn:timezone":"Asia/Bangkok",
    "iso:country":"TH",
    "name:tha_x_preferred":[
        "\u0e1a\u0e49\u0e32\u0e19\u0e17\u0e48\u0e32\u0e23\u0e30\u0e2b\u0e31\u0e14"
    ],
    "name:und_x_variant":[
        "Ban Wang Rahat"
    ],
    "wof:name":"Ban Tha Rahat",
    "wof:placetype":"locality"
},
  "geometry": {"coordinates":[101.22358,13.68867],"type":"Point"}
}