{
  "type": "Feature",
  "properties": {
    "gn:admin1_code":"2.0",
    "gn:asciiname":"Ban Mae Wan Pang Klang",
    "gn:country_code":"TH",
    "gn:dem":844,
    "gn:feature_class":"P",
    "gn:feature_code":"PPL",
    "gn:name":"Ban Mae Wan Pang Klang",
    "gn:population":0,
    "gn:timezone":"Asia/Bangkok",
    "iso:country":"TH",
    "name:tha_x_preferred":[
        "\u0e1a\u0e49\u0e32\u0e19\u0e41\u0e21\u0e48\u0e2b\u0e27\u0e32\u0e19\u0e1b\u0e32\u0e07\u0e01\u0e25\u0e32\u0e07"
    ],
    "wof:name":"Ban Mae Wan Pang Klang",
    "wof:placetype":"locality"
},
  "geometry": {"coordinates":[99.31919000000001,18.97056],"type":"Point"}
}