{
  "type": "Feature",
  "properties": {
    "gn:admin1_code":"18.0",
    "gn:asciiname":"Ban Pak Huai",
    "gn:country_code":"TH",
    "gn:dem":243,
    "gn:feature_class":"P",
    "gn:feature_code":"PPL",
    "gn:name":"Ban Pak Huai",
    "gn:population":0,
    "gn:timezone":"Asia/Bangkok",
    "iso:country":"TH",
    "name:tha_x_preferred":[
        "\u0e1a\u0e49\u0e32\u0e19\u0e1b\u0e32\u0e01\u0e2b\u0e49\u0e27\u0e22"
    ],
    "wof:name":"Ban Pak Huai",
    "wof:placetype":"locality"
},
  "geometry": {"coordinates":[101.41367,17.706],"type":"Point"}
}