{
  "type": "Feature",
  "properties": {
    "gn:admin1_code":"6.0",
    "gn:asciiname":"Ban Bun Koet",
    "gn:country_code":"TH",
    "gn:dem":263,
    "gn:feature_class":"P",
    "gn:feature_code":"PPL",
    "gn:name":"Ban Bun Koet",
    "gn:population":0,
    "gn:timezone":"Asia/Bangkok",
    "iso:country":"TH",
    "name:tha_x_preferred":[
        "\u0e1a\u0e49\u0e32\u0e19\u0e1a\u0e38\u0e0d\u0e40\u0e01\u0e34\u0e14"
    ],
    "wof:name":"Ban Bun Koet",
    "wof:placetype":"locality"
},
  "geometry": {"coordinates":[99.51842000000001,18.26064],"type":"Point"}
}