{
  "type": "Feature",
  "properties": {
    "gn:admin1_code":"68.0",
    "gn:asciiname":"Ban Yang Khwai",
    "gn:country_code":"TH",
    "gn:dem":23,
    "gn:feature_class":"P",
    "gn:feature_code":"PPL",
    "gn:name":"Ban Yang Khwai",
    "gn:population":0,
    "gn:timezone":"Asia/Bangkok",
    "iso:country":"TH",
    "name:tha_x_preferred":[
        "\u0e1a\u0e49\u0e32\u0e19\u0e22\u0e48\u0e32\u0e07\u0e04\u0e27\u0e32\u0e22"
    ],
    "wof:name":"Ban Yang Khwai",
    "wof:placetype":"locality"
},
  "geometry": {"coordinates":[100.65836,6.78642],"type":"Point"}
}