{
  "type": "Feature",
  "properties": {
    "gn:admin1_code":"50.0",
    "gn:asciiname":"Ban Khao Phu Rang Nimit",
    "gn:country_code":"TH",
    "gn:dem":32,
    "gn:feature_class":"P",
    "gn:feature_code":"PPL",
    "gn:name":"Ban Khao Phu Rang Nimit",
    "gn:population":0,
    "gn:timezone":"Asia/Bangkok",
    "iso:country":"TH",
    "name:tha_x_preferred":[
        "\u0e1a\u0e49\u0e32\u0e19\u0e40\u0e02\u0e32\u0e1e\u0e38\u0e23\u0e32\u0e07\u0e19\u0e34\u0e21\u0e34\u0e15"
    ],
    "wof:name":"Ban Khao Phu Rang Nimit",
    "wof:placetype":"locality"
},
  "geometry": {"coordinates":[99.53158000000001,14.03172],"type":"Point"}
}