{
  "type": "Feature",
  "properties": {
    "gn:admin1_code":"49.0",
    "gn:asciiname":"Ban Sa Sisiat",
    "gn:country_code":"TH",
    "gn:dem":26,
    "gn:feature_class":"P",
    "gn:feature_code":"PPL",
    "gn:name":"Ban Sa Sisiat",
    "gn:population":0,
    "gn:timezone":"Asia/Bangkok",
    "iso:country":"TH",
    "name:tha_x_preferred":[
        "\u0e1a\u0e49\u0e32\u0e19\u0e2a\u0e23\u0e30\u0e2a\u0e35\u0e40\u0e2a\u0e35\u0e22\u0e14"
    ],
    "name:und_x_variant":[
        "Ban Kra Sisiat",
        "Ban Sa Sisiat"
    ],
    "wof:name":"Ban Sa Sisiat",
    "wof:placetype":"locality"
},
  "geometry": {"coordinates":[102.49361,12.25094],"type":"Point"}
}