{
  "type": "Feature",
  "properties": {
    "gn:admin1_code":"25.0",
    "gn:asciiname":"Ban Fai Yai",
    "gn:country_code":"TH",
    "gn:dem":144,
    "gn:feature_class":"P",
    "gn:feature_code":"PPL",
    "gn:name":"Ban Fai Yai",
    "gn:population":0,
    "gn:timezone":"Asia/Bangkok",
    "iso:country":"TH",
    "name:tha_x_preferred":[
        "\u0e1a\u0e49\u0e32\u0e19\u0e1d\u0e32\u0e22\u0e43\u0e2b\u0e0d\u0e48"
    ],
    "wof:name":"Ban Fai Yai",
    "wof:placetype":"locality"
},
  "geometry": {"coordinates":[103.39592,15.69544],"type":"Point"}
}