{
  "type": "Feature",
  "properties": {
    "gn:admin1_code":"18.0",
    "gn:asciiname":"Ban Bong",
    "gn:country_code":"TH",
    "gn:dem":703,
    "gn:feature_class":"P",
    "gn:feature_code":"PPL",
    "gn:name":"Ban Bong",
    "gn:population":0,
    "gn:timezone":"Asia/Bangkok",
    "iso:country":"TH",
    "name:tha_x_preferred":[
        "Ban Bong"
    ],
    "name:tha_x_variant":[
        "\u0e1a\u0e49\u0e32\u0e19\u0e1a\u0e07"
    ],
    "wof:name":"Ban Bong",
    "wof:placetype":"locality"
},
  "geometry": {"coordinates":[101.41634000000001,17.41352],"type":"Point"}
}