{
  "type": "Feature",
  "properties": {
    "gn:admin1_code":"61.0",
    "gn:asciiname":"Ban Khlong Sai",
    "gn:country_code":"TH",
    "gn:dem":21,
    "gn:feature_class":"P",
    "gn:feature_code":"PPL",
    "gn:name":"Ban Khlong Sai",
    "gn:population":0,
    "gn:timezone":"Asia/Bangkok",
    "iso:country":"TH",
    "name:tha_x_preferred":[
        "\u0e1a\u0e49\u0e32\u0e19\u0e04\u0e25\u0e2d\u0e07\u0e43\u0e2a"
    ],
    "name:und_x_variant":[
        "Ban Klong Sai",
        "Ban Khlong Sai"
    ],
    "wof:name":"Ban Khlong Sai",
    "wof:placetype":"locality"
},
  "geometry": {"coordinates":[98.42531,8.19681],"type":"Point"}
}