{
  "type": "Feature",
  "properties": {
    "gn:admin1_code":"64.0",
    "gn:asciiname":"Ban Huai Si Chai",
    "gn:country_code":"TH",
    "gn:dem":39,
    "gn:feature_class":"P",
    "gn:feature_code":"PPL",
    "gn:name":"Ban Huai Si Chai",
    "gn:population":0,
    "gn:timezone":"Asia/Bangkok",
    "iso:country":"TH",
    "name:tha_x_preferred":[
        "\u0e1a\u0e49\u0e32\u0e19\u0e2b\u0e49\u0e27\u0e22\u0e28\u0e23\u0e35\u0e0a\u0e31\u0e22"
    ],
    "wof:name":"Ban Huai Si Chai",
    "wof:placetype":"locality"
},
  "geometry": {"coordinates":[99.85625,9.06547],"type":"Point"}
}