{
  "type": "Feature",
  "properties": {
    "gn:admin1_code":"33",
    "gn:asciiname":"Ban Tha Lop",
    "gn:country_code":"TH",
    "gn:dem":12,
    "gn:feature_class":"P",
    "gn:feature_code":"PPL",
    "gn:name":"Ban Tha Lop",
    "gn:population":0,
    "gn:timezone":"Asia/Bangkok",
    "iso:country":"TH",
    "name:tha_x_preferred":[
        "\u0e1a\u0e49\u0e32\u0e19\u0e17\u0e48\u0e32\u0e25\u0e2d\u0e1a"
    ],
    "wof:name":"Ban Tha Lop",
    "wof:placetype":"locality"
},
  "geometry": {"coordinates":[100.25014,14.85261],"type":"Point"}
}