{
  "type": "Feature",
  "properties": {
    "gn:admin1_code":"27",
    "gn:asciiname":"Ban Non Khun Chamnan",
    "gn:country_code":"TH",
    "gn:dem":149,
    "gn:feature_class":"P",
    "gn:feature_code":"PPL",
    "gn:name":"Ban Non Khun Chamnan",
    "gn:population":0,
    "gn:timezone":"Asia/Bangkok",
    "iso:country":"TH",
    "name:tha_x_preferred":[
        "\u0e1a\u0e49\u0e32\u0e19\u0e42\u0e19\u0e19\u0e02\u0e38\u0e19\u0e0a\u0e33\u0e19\u0e32\u0e0d"
    ],
    "wof:name":"Ban Non Khun Chamnan",
    "wof:placetype":"locality"
},
  "geometry": {"coordinates":[102.6155,15.42636],"type":"Point"}
}