{
  "type": "Feature",
  "properties": {
    "gn:admin1_code":"29",
    "gn:asciiname":"Ban Kran Ae",
    "gn:country_code":"TH",
    "gn:dem":164,
    "gn:feature_class":"P",
    "gn:feature_code":"PPL",
    "gn:name":"Ban Kran Ae",
    "gn:population":0,
    "gn:timezone":"Asia/Bangkok",
    "iso:country":"TH",
    "name:tha_x_preferred":[
        "\u0e1a\u0e49\u0e32\u0e19\u0e01\u0e23\u0e31\u0e19\u0e41\u0e2d\u0e23\u0e4c"
    ],
    "wof:name":"Ban Kran Ae",
    "wof:placetype":"locality"
},
  "geometry": {"coordinates":[103.48797,14.67222],"type":"Point"}
}