{
  "type": "Feature",
  "properties": {
    "gn:admin1_code":"29.0",
    "gn:asciiname":"Ban Thung Mon",
    "gn:country_code":"TH",
    "gn:dem":137,
    "gn:feature_class":"P",
    "gn:feature_code":"PPL",
    "gn:name":"Ban Thung Mon",
    "gn:population":0,
    "gn:timezone":"Asia/Bangkok",
    "iso:country":"TH",
    "name:tha_x_preferred":[
        "\u0e1a\u0e49\u0e32\u0e19\u0e17\u0e38\u0e48\u0e07\u0e21\u0e19"
    ],
    "name:und_x_variant":[
        "Khok",
        "Tung Mon",
        "Thung Mon",
        "Ban Thung Mon"
    ],
    "wof:name":"Ban Thung Mon",
    "wof:placetype":"locality"
},
  "geometry": {"coordinates":[103.60075000000001,15.20244],"type":"Point"}
}