{
  "type": "Feature",
  "properties": {
    "gn:admin1_code":"64.0",
    "gn:asciiname":"Ban Khlong Noi",
    "gn:country_code":"TH",
    "gn:dem":6,
    "gn:feature_class":"P",
    "gn:feature_code":"PPL",
    "gn:name":"Ban Khlong Noi",
    "gn:population":0,
    "gn:timezone":"Asia/Bangkok",
    "iso:country":"TH",
    "name:tha_x_preferred":[
        "\u0e1a\u0e49\u0e32\u0e19\u0e04\u0e25\u0e2d\u0e07\u0e19\u0e49\u0e2d\u0e22"
    ],
    "name:und_x_variant":[
        "Klong Noi",
        "Ban Klong Noi",
        "Ban Khlong Noi"
    ],
    "wof:name":"Ban Khlong Noi",
    "wof:placetype":"locality"
},
  "geometry": {"coordinates":[100.12881,8.32406],"type":"Point"}
}