{
  "type": "Feature",
  "properties": {
    "gn:admin1_code":"53.0",
    "gn:asciiname":"Ban Pridaram",
    "gn:country_code":"TH",
    "gn:dem":6,
    "gn:feature_class":"P",
    "gn:feature_code":"PPL",
    "gn:name":"Ban Pridaram",
    "gn:population":0,
    "gn:timezone":"Asia/Bangkok",
    "iso:country":"TH",
    "name:tha_x_preferred":[
        "\u0e1a\u0e49\u0e32\u0e19\u0e1b\u0e23\u0e35\u0e14\u0e32\u0e23\u0e32\u0e21"
    ],
    "wof:name":"Ban Pridaram",
    "wof:placetype":"locality"
},
  "geometry": {"coordinates":[100.14203000000001,13.69061],"type":"Point"}
}