{
  "type": "Feature",
  "properties": {
    "gn:admin1_code":"75.0",
    "gn:asciiname":"Ban Yang Thoeng",
    "gn:country_code":"TH",
    "gn:dem":140,
    "gn:feature_class":"P",
    "gn:feature_code":"PPL",
    "gn:name":"Ban Yang Thoeng",
    "gn:population":0,
    "gn:timezone":"Asia/Bangkok",
    "iso:country":"TH",
    "name:tha_x_preferred":[
        "\u0e1a\u0e49\u0e32\u0e19\u0e22\u0e32\u0e07\u0e40\u0e17\u0e34\u0e07"
    ],
    "wof:name":"Ban Yang Thoeng",
    "wof:placetype":"locality"
},
  "geometry": {"coordinates":[104.90778,15.32522],"type":"Point"}
}