{
  "type": "Feature",
  "properties": {
    "gn:admin1_code":"8.0",
    "gn:asciiname":"Ban Mae U Su",
    "gn:country_code":"TH",
    "gn:dem":143,
    "gn:feature_class":"P",
    "gn:feature_code":"PPL",
    "gn:name":"Ban Mae U Su",
    "gn:population":0,
    "gn:timezone":"Asia/Bangkok",
    "iso:country":"TH",
    "name:tha_x_preferred":[
        "\u0e1a\u0e49\u0e32\u0e19\u0e41\u0e21\u0e48\u0e2d\u0e38\u0e2a\u0e38"
    ],
    "name:und_x_variant":[
        "Ban Mae Usu",
        "Mae Usu",
        "Ban Yang Mae Usu",
        "Ban Mae U Su"
    ],
    "wof:lang_x_official":[
        "tha"
    ],
    "wof:lang_x_spoken":[
        "tha"
    ],
    "wof:name":"Ban Mae U Su",
    "wof:placetype":"locality"
},
  "geometry": {"coordinates":[98.17922,17.30292],"type":"Point"}
}