{
  "type": "Feature",
  "properties": {
    "gn:admin1_code":"38.0",
    "gn:asciiname":"Ban Sahakon",
    "gn:country_code":"TH",
    "gn:dem":4,
    "gn:feature_class":"P",
    "gn:feature_code":"PPL",
    "gn:name":"Ban Sahakon",
    "gn:population":0,
    "gn:timezone":"Asia/Bangkok",
    "iso:country":"TH",
    "name:tha_x_preferred":[
        "\u0e1a\u0e49\u0e32\u0e19\u0e2a\u0e2b\u0e01\u0e23\u0e13\u0e4c"
    ],
    "wof:name":"Ban Sahakon",
    "wof:placetype":"locality"
},
  "geometry": {"coordinates":[100.30054,13.87057],"type":"Point"}
}