{
  "type": "Feature",
  "properties": {
    "gn:admin1_code":"14.0",
    "gn:asciiname":"Ban Hin Dat Noi",
    "gn:country_code":"TH",
    "gn:dem":106,
    "gn:feature_class":"P",
    "gn:feature_code":"PPL",
    "gn:name":"Ban Hin Dat Noi",
    "gn:population":0,
    "gn:timezone":"Asia/Bangkok",
    "iso:country":"TH",
    "name:tha_x_preferred":[
        "\u0e1a\u0e49\u0e32\u0e19\u0e2b\u0e34\u0e19\u0e14\u0e32\u0e14\u0e19\u0e49\u0e2d\u0e22"
    ],
    "wof:name":"Ban Hin Dat Noi",
    "wof:placetype":"locality"
},
  "geometry": {"coordinates":[100.97286,15.77558],"type":"Point"}
}