{
  "type": "Feature",
  "properties": {
    "gn:admin1_code":"46.0",
    "gn:asciiname":"Ban Map Bon",
    "gn:country_code":"TH",
    "gn:dem":40,
    "gn:feature_class":"P",
    "gn:feature_code":"PPL",
    "gn:name":"Ban Map Bon",
    "gn:population":0,
    "gn:timezone":"Asia/Bangkok",
    "iso:country":"TH",
    "name:tha_x_preferred":[
        "\u0e1a\u0e49\u0e32\u0e19\u0e21\u0e32\u0e1a\u0e1a\u0e2d\u0e19"
    ],
    "wof:name":"Ban Map Bon",
    "wof:placetype":"locality"
},
  "geometry": {"coordinates":[100.95961,12.97097],"type":"Point"}
}