{
  "type": "Feature",
  "properties": {
    "gn:admin1_code":"41.0",
    "gn:asciiname":"Ban Pa Daet",
    "gn:country_code":"TH",
    "gn:dem":401,
    "gn:feature_class":"P",
    "gn:feature_code":"PPL",
    "gn:name":"Ban Pa Daet",
    "gn:population":0,
    "gn:timezone":"Asia/Bangkok",
    "iso:country":"TH",
    "name:tha_x_preferred":[
        "\u0e1a\u0e49\u0e32\u0e19\u0e1b\u0e48\u0e32\u0e41\u0e14\u0e14"
    ],
    "name:und_x_variant":[
        "B\u0101n Pa Dead",
        "Ban Pa Daet"
    ],
    "wof:name":"Ban Pa Daet",
    "wof:placetype":"locality"
},
  "geometry": {"coordinates":[100.31325,19.51103],"type":"Point"}
}