{
  "type": "Feature",
  "properties": {
    "gn:admin1_code":"35.0",
    "gn:asciiname":"Ban Suan Mamuang",
    "gn:country_code":"TH",
    "gn:dem":13,
    "gn:feature_class":"P",
    "gn:feature_code":"PPL",
    "gn:name":"Ban Suan Mamuang",
    "gn:population":0,
    "gn:timezone":"Asia/Bangkok",
    "iso:country":"TH",
    "name:tha_x_preferred":[
        "\u0e1a\u0e49\u0e32\u0e19\u0e2a\u0e27\u0e19\u0e21\u0e30\u0e21\u0e48\u0e27\u0e07"
    ],
    "wof:name":"Ban Suan Mamuang",
    "wof:placetype":"locality"
},
  "geometry": {"coordinates":[100.42489,14.57139],"type":"Point"}
}