{
  "type": "Feature",
  "properties": {
    "gn:admin1_code":"10.0",
    "gn:asciiname":"Ban Phak Rak",
    "gn:country_code":"TH",
    "gn:dem":122,
    "gn:feature_class":"P",
    "gn:feature_code":"PPL",
    "gn:name":"Ban Phak Rak",
    "gn:population":0,
    "gn:timezone":"Asia/Bangkok",
    "iso:country":"TH",
    "name:tha_x_preferred":[
        "Ban Phak Rak"
    ],
    "name:tha_x_variant":[
        "\u0e1a\u0e49\u0e32\u0e19\u0e1c\u0e31\u0e01\u0e23\u0e32\u0e01"
    ],
    "wof:name":"Ban Phak Rak",
    "wof:placetype":"locality"
},
  "geometry": {"coordinates":[100.02133000000001,17.71006000000001],"type":"Point"}
}