{
  "type": "Feature",
  "properties": {
    "gn:admin1_code":"81.0",
    "gn:asciiname":"Ban Huai Chuam Tha",
    "gn:country_code":"TH",
    "gn:dem":164,
    "gn:feature_class":"P",
    "gn:feature_code":"PPL",
    "gn:name":"Ban Huai Chuam Tha",
    "gn:population":0,
    "gn:timezone":"Asia/Bangkok",
    "iso:country":"TH",
    "wof:name":"Ban Huai Chuam Tha",
    "wof:placetype":"locality"
},
  "geometry": {"coordinates":[103.84639,18.28444],"type":"Point"}
}