{
  "type": "Feature",
  "properties": {
    "gn:admin1_code":"53.0",
    "gn:asciiname":"Ban Sa-at Phatthana",
    "gn:country_code":"TH",
    "gn:dem":9,
    "gn:feature_class":"P",
    "gn:feature_code":"PPL",
    "gn:name":"Ban Sa-at Phatthana",
    "gn:population":0,
    "gn:timezone":"Asia/Bangkok",
    "iso:country":"TH",
    "name:tha_x_preferred":[
        "Ban Sa-at Phatthana"
    ],
    "name:tha_x_variant":[
        "\u0e1a\u0e49\u0e32\u0e19\u0e2a\u0e30\u0e2d\u0e32\u0e14\u0e1e\u0e31\u0e12\u0e19\u0e32"
    ],
    "wof:name":"Ban Sa-at Phatthana",
    "wof:placetype":"locality"
},
  "geometry": {"coordinates":[100.02047,14.01297],"type":"Point"}
}