{
  "type": "Feature",
  "properties": {
    "gn:admin1_code":"66.0",
    "gn:asciiname":"Ban Wang La Pho",
    "gn:country_code":"TH",
    "gn:dem":63,
    "gn:feature_class":"P",
    "gn:feature_code":"PPL",
    "gn:name":"Ban Wang La Pho",
    "gn:population":0,
    "gn:timezone":"Asia/Bangkok",
    "iso:country":"TH",
    "name:tha_x_preferred":[
        "\u0e1a\u0e49\u0e32\u0e19\u0e27\u0e31\u0e07\u0e25\u0e32\u0e42\u0e20"
    ],
    "wof:name":"Ban Wang La Pho",
    "wof:placetype":"locality"
},
  "geometry": {"coordinates":[99.85330999999999,7.71603],"type":"Point"}
}