{
  "type": "Feature",
  "properties": {
    "gn:admin1_code":"3.0",
    "gn:asciiname":"Ban Pang Hat",
    "gn:country_code":"TH",
    "gn:dem":435,
    "gn:feature_class":"P",
    "gn:feature_code":"PPL",
    "gn:name":"Ban Pang Hat",
    "gn:population":0,
    "gn:timezone":"Asia/Bangkok",
    "iso:country":"TH",
    "name:tha_x_preferred":[
        "\u0e1a\u0e49\u0e32\u0e19\u0e1b\u0e32\u0e07\u0e2b\u0e31\u0e14"
    ],
    "name:und_x_variant":[
        "Pang Hat",
        "B\u0101n P\u0101ng Had",
        "Ban Pang Hat"
    ],
    "wof:name":"Ban Pang Hat",
    "wof:placetype":"locality"
},
  "geometry": {"coordinates":[100.46622000000001,19.98597],"type":"Point"}
}