{
  "type": "Feature",
  "properties": {
    "gn:admin1_code":"3.0",
    "gn:asciiname":"Ban San Ton Pui",
    "gn:country_code":"TH",
    "gn:dem":397,
    "gn:feature_class":"P",
    "gn:feature_code":"PPL",
    "gn:name":"Ban San Ton Pui",
    "gn:population":0,
    "gn:timezone":"Asia/Bangkok",
    "iso:country":"TH",
    "name:tha_x_preferred":[
        "\u0e1a\u0e49\u0e32\u0e19\u0e2a\u0e31\u0e19\u0e15\u0e49\u0e19\u0e1b\u0e38\u0e22"
    ],
    "wof:name":"Ban San Ton Pui",
    "wof:placetype":"locality"
},
  "geometry": {"coordinates":[99.86678000000001,20.29803],"type":"Point"}
}