{
  "type": "Feature",
  "properties": {
    "gn:admin1_code":"41.0",
    "gn:asciiname":"Ban Rong Hat",
    "gn:country_code":"TH",
    "gn:dem":420,
    "gn:feature_class":"P",
    "gn:feature_code":"PPL",
    "gn:name":"Ban Rong Hat",
    "gn:population":0,
    "gn:timezone":"Asia/Bangkok",
    "iso:country":"TH",
    "name:tha_x_preferred":[
        "\u0e1a\u0e49\u0e32\u0e19\u0e23\u0e48\u0e2d\u0e07\u0e2b\u0e32\u0e14"
    ],
    "wof:name":"Ban Rong Hat",
    "wof:placetype":"locality"
},
  "geometry": {"coordinates":[100.09875,19.35614],"type":"Point"}
}