{
  "type": "Feature",
  "properties": {
    "gn:admin1_code":"74",
    "gn:asciiname":"Ban Prue Wai Yai",
    "gn:country_code":"TH",
    "gn:dem":44,
    "gn:feature_class":"P",
    "gn:feature_code":"PPL",
    "gn:name":"Ban Prue Wai Yai",
    "gn:population":0,
    "gn:timezone":"Asia/Bangkok",
    "iso:country":"TH",
    "name:tha_x_preferred":[
        "\u0e1a\u0e49\u0e32\u0e19\u0e1b\u0e23\u0e37\u0e2d\u0e27\u0e32\u0e22\u0e43\u0e2b\u0e0d\u0e48"
    ],
    "wof:name":"Ban Prue Wai Yai",
    "wof:placetype":"locality"
},
  "geometry": {"coordinates":[101.54636000000001,13.80119],"type":"Point"}
}