{
  "type": "Feature",
  "properties": {
    "gn:admin1_code":"66.0",
    "gn:asciiname":"Ban Rang Khaep",
    "gn:country_code":"TH",
    "gn:dem":38,
    "gn:feature_class":"P",
    "gn:feature_code":"PPL",
    "gn:name":"Ban Rang Khaep",
    "gn:population":0,
    "gn:timezone":"Asia/Bangkok",
    "iso:country":"TH",
    "name:tha_x_preferred":[
        "\u0e1a\u0e49\u0e32\u0e19\u0e2b\u0e23\u0e31\u0e07\u0e41\u0e04\u0e1a"
    ],
    "wof:name":"Ban Rang Khaep",
    "wof:placetype":"locality"
},
  "geometry": {"coordinates":[99.94131,7.73667],"type":"Point"}
}