{
  "type": "Feature",
  "properties": {
    "gn:admin1_code":"81.0",
    "gn:asciiname":"Ban Khai Si",
    "gn:country_code":"TH",
    "gn:dem":162,
    "gn:feature_class":"P",
    "gn:feature_code":"PPL",
    "gn:name":"Ban Khai Si",
    "gn:population":0,
    "gn:timezone":"Asia/Bangkok",
    "iso:country":"TH",
    "name:tha_x_preferred":[
        "\u0e1a\u0e49\u0e32\u0e19\u0e44\u0e04\u0e2a\u0e35"
    ],
    "name:und_x_variant":[
        "Ban Khrai Si"
    ],
    "wof:name":"Ban Khai Si",
    "wof:placetype":"locality"
},
  "geometry": {"coordinates":[103.49139,18.42029],"type":"Point"}
}