{
  "type": "Feature",
  "properties": {
    "gn:admin1_code":"68.0",
    "gn:asciiname":"Ban Phru Lek Khwae",
    "gn:country_code":"TH",
    "gn:dem":36,
    "gn:feature_class":"P",
    "gn:feature_code":"PPL",
    "gn:name":"Ban Phru Lek Khwae",
    "gn:population":0,
    "gn:timezone":"Asia/Bangkok",
    "iso:country":"TH",
    "name:tha_x_preferred":[
        "\u0e1a\u0e49\u0e32\u0e19\u0e1e\u0e23\u0e38\u0e40\u0e2b\u0e25\u0e47\u0e01\u0e41\u0e02\u0e27\u0e30"
    ],
    "wof:name":"Ban Phru Lek Khwae",
    "wof:placetype":"locality"
},
  "geometry": {"coordinates":[101.03203000000001,6.68239],"type":"Point"}
}