{
  "type": "Feature",
  "properties": {
    "gn:admin1_code":"3.0",
    "gn:asciiname":"Ban Mae Mong Yao",
    "gn:country_code":"TH",
    "gn:dem":899,
    "gn:feature_class":"P",
    "gn:feature_code":"PPL",
    "gn:name":"Ban Mae Mong Yao",
    "gn:population":0,
    "gn:timezone":"Asia/Bangkok",
    "iso:country":"TH",
    "name:tha_x_preferred":[
        "\u0e1a\u0e49\u0e32\u0e19\u0e41\u0e21\u0e48\u0e42\u0e21\u0e07\u0e40\u0e22\u0e49\u0e32"
    ],
    "wof:lang_x_official":[
        "tha"
    ],
    "wof:lang_x_spoken":[
        "tha"
    ],
    "wof:name":"Ban Mae Mong Yao",
    "wof:placetype":"locality"
},
  "geometry": {"coordinates":[99.45556000000001,19.95553],"type":"Point"}
}