{
  "type": "Feature",
  "properties": {
    "gn:admin1_code":"2.0",
    "gn:asciiname":"Ban Khum",
    "gn:country_code":"TH",
    "gn:dem":1420,
    "gn:feature_class":"P",
    "gn:feature_code":"PPL",
    "gn:name":"Ban Khum",
    "gn:population":0,
    "gn:timezone":"Asia/Bangkok",
    "iso:country":"TH",
    "name:tha_x_preferred":[
        "\u0e1a\u0e49\u0e32\u0e19\u0e04\u0e38\u0e49\u0e21"
    ],
    "name:und_x_variant":[
        "Ban Khom"
    ],
    "wof:name":"Ban Khum",
    "wof:placetype":"locality"
},
  "geometry": {"coordinates":[99.04107999999999,19.90256],"type":"Point"}
}