{
  "type": "Feature",
  "properties": {
    "gn:admin1_code":"59.0",
    "gn:asciiname":"Ban Bang Ben",
    "gn:country_code":"TH",
    "gn:dem":5,
    "gn:feature_class":"P",
    "gn:feature_code":"PPL",
    "gn:name":"Ban Bang Ben",
    "gn:population":0,
    "gn:timezone":"Asia/Bangkok",
    "iso:country":"TH",
    "name:tha_x_preferred":[
        "\u0e1a\u0e49\u0e32\u0e19\u0e1a\u0e32\u0e07\u0e40\u0e1a\u0e19"
    ],
    "name:und_x_variant":[
        "Ban Tha Bang Ben",
        "Ban Bang Ben"
    ],
    "wof:name":"Ban Bang Ben",
    "wof:placetype":"locality"
},
  "geometry": {"coordinates":[98.48417000000001,9.60333],"type":"Point"}
}