{
  "type": "Feature",
  "properties": {
    "gn:admin1_code":"69.0",
    "gn:asciiname":"Ban Ka Hong",
    "gn:country_code":"TH",
    "gn:dem":10,
    "gn:feature_class":"P",
    "gn:feature_code":"PPL",
    "gn:name":"Ban Ka Hong",
    "gn:population":0,
    "gn:timezone":"Asia/Bangkok",
    "iso:country":"TH",
    "name:tha_x_preferred":[
        "\u0e1a\u0e49\u0e32\u0e19\u0e01\u0e32\u0e2e\u0e07"
    ],
    "wof:name":"Ban Ka Hong",
    "wof:placetype":"locality"
},
  "geometry": {"coordinates":[101.27652999999999,6.82772],"type":"Point"}
}