{
  "type": "Feature",
  "properties": {
    "gn:admin1_code":"34",
    "gn:asciiname":"Ban Prang Noi Phatthana",
    "gn:country_code":"TH",
    "gn:dem":116,
    "gn:feature_class":"P",
    "gn:feature_code":"PPL",
    "gn:name":"Ban Prang Noi Phatthana",
    "gn:population":0,
    "gn:timezone":"Asia/Bangkok",
    "iso:country":"TH",
    "name:tha_x_preferred":[
        "\u0e1a\u0e49\u0e32\u0e19\u0e1b\u0e23\u0e32\u0e07\u0e04\u0e4c\u0e19\u0e49\u0e2d\u0e22\u0e1e\u0e31\u0e12\u0e19\u0e32"
    ],
    "wof:name":"Ban Prang Noi Phatthana",
    "wof:placetype":"locality"
},
  "geometry": {"coordinates":[101.38972,15.14008],"type":"Point"}
}