{
  "type": "Feature",
  "properties": {
    "gn:admin1_code":"80",
    "gn:asciiname":"Ban Sap Mek",
    "gn:country_code":"TH",
    "gn:dem":109,
    "gn:feature_class":"P",
    "gn:feature_code":"PPL",
    "gn:name":"Ban Sap Mek",
    "gn:population":0,
    "gn:timezone":"Asia/Bangkok",
    "iso:country":"TH",
    "name:tha_x_preferred":[
        "\u0e1a\u0e49\u0e32\u0e19\u0e0b\u0e31\u0e1a\u0e40\u0e21\u0e47\u0e01"
    ],
    "wof:name":"Ban Sap Mek",
    "wof:placetype":"locality"
},
  "geometry": {"coordinates":[102.663,13.94153],"type":"Point"}
}