{
  "type": "Feature",
  "properties": {
    "gn:admin1_code":"56.0",
    "gn:asciiname":"Ban Khao Yoi",
    "gn:country_code":"TH",
    "gn:dem":13,
    "gn:feature_class":"P",
    "gn:feature_code":"PPL",
    "gn:name":"Ban Khao Yoi",
    "gn:population":0,
    "gn:timezone":"Asia/Bangkok",
    "iso:country":"TH",
    "name:tha_x_preferred":[
        "\u0e1a\u0e49\u0e32\u0e19\u0e40\u0e02\u0e32\u0e22\u0e49\u0e2d\u0e22"
    ],
    "name:und_x_variant":[
        "Khao Yoi",
        "Amphu Khao Yoi",
        "Ban Khao Yoi"
    ],
    "wof:name":"Ban Khao Yoi",
    "wof:placetype":"locality"
},
  "geometry": {"coordinates":[99.82422,13.22714],"type":"Point"}
}