{
  "type": "Feature",
  "properties": {
    "gn:admin1_code":"51.0",
    "gn:asciiname":"Ban Ong Phra",
    "gn:country_code":"TH",
    "gn:dem":348,
    "gn:feature_class":"P",
    "gn:feature_code":"PPL",
    "gn:name":"Ban Ong Phra",
    "gn:population":0,
    "gn:timezone":"Asia/Bangkok",
    "iso:country":"TH",
    "name:tha_x_preferred":[
        "\u0e1a\u0e49\u0e32\u0e19\u0e2d\u0e07\u0e04\u0e4c\u0e1e\u0e23\u0e30"
    ],
    "wof:name":"Ban Ong Phra",
    "wof:placetype":"locality"
},
  "geometry": {"coordinates":[99.39064,14.99594],"type":"Point"}
}