{
  "type": "Feature",
  "properties": {
    "gn:admin1_code":"64.0",
    "gn:asciiname":"Ban Bang Khayaeng",
    "gn:country_code":"TH",
    "gn:dem":2,
    "gn:feature_class":"P",
    "gn:feature_code":"PPL",
    "gn:name":"Ban Bang Khayaeng",
    "gn:population":0,
    "gn:timezone":"Asia/Bangkok",
    "iso:country":"TH",
    "name:tha_x_preferred":[
        "\u0e1a\u0e49\u0e32\u0e19\u0e1a\u0e32\u0e07\u0e41\u0e02\u0e22\u0e07"
    ],
    "wof:name":"Ban Bang Khayaeng",
    "wof:placetype":"locality"
},
  "geometry": {"coordinates":[100.32964,7.93516],"type":"Point"}
}