{
  "type": "Feature",
  "properties": {
    "gn:admin1_code":"57.0",
    "gn:asciiname":"Ban Bueng",
    "gn:country_code":"TH",
    "gn:dem":14,
    "gn:feature_class":"P",
    "gn:feature_code":"PPL",
    "gn:name":"Ban Bueng",
    "gn:population":0,
    "gn:timezone":"Asia/Bangkok",
    "iso:country":"TH",
    "name:tha_x_preferred":[
        "\u0e1a\u0e49\u0e32\u0e19\u0e1a\u0e36\u0e07"
    ],
    "name:tha_x_variant":[
        "\u0e40\u0e17\u0e28\u0e1a\u0e32\u0e25\u0e40\u0e21\u0e37\u0e2d\u0e07\u0e1a\u0e49\u0e32\u0e19\u0e1a\u0e36\u0e07"
    ],
    "name:und_x_variant":[
        "Bung",
        "B\u0101n Boeng",
        "Ban Bung (1)",
        "Ban Bueng"
    ],
    "wof:name":"Ban Bueng",
    "wof:placetype":"locality"
},
  "geometry": {"coordinates":[99.78556,11.868],"type":"Point"}
}