{
  "type": "Feature",
  "properties": {
    "gn:admin1_code":"56.0",
    "gn:asciiname":"Ban Na Yang",
    "gn:country_code":"TH",
    "gn:dem":8,
    "gn:feature_class":"P",
    "gn:feature_code":"PPL",
    "gn:name":"Ban Na Yang",
    "gn:population":0,
    "gn:timezone":"Asia/Bangkok",
    "iso:country":"TH",
    "name:tha_x_preferred":[
        "\u0e1a\u0e49\u0e32\u0e19\u0e19\u0e32\u0e22\u0e32\u0e07"
    ],
    "name:und_x_variant":[
        "Nay\u0101ng",
        "Ban Na Yang"
    ],
    "wof:name":"Ban Na Yang",
    "wof:placetype":"locality"
},
  "geometry": {"coordinates":[99.94750000000001,12.88492],"type":"Point"}
}