{
  "type": "Feature",
  "properties": {
    "gn:admin1_code":"27.0",
    "gn:asciiname":"Ban Maroeng Noi",
    "gn:country_code":"TH",
    "gn:dem":176,
    "gn:feature_class":"P",
    "gn:feature_code":"PPL",
    "gn:name":"Ban Maroeng Noi",
    "gn:population":0,
    "gn:timezone":"Asia/Bangkok",
    "iso:country":"TH",
    "name:tha_x_preferred":[
        "\u0e1a\u0e49\u0e32\u0e19\u0e21\u0e30\u0e40\u0e23\u0e34\u0e07\u0e19\u0e49\u0e2d\u0e22"
    ],
    "wof:name":"Ban Maroeng Noi",
    "wof:placetype":"locality"
},
  "geometry": {"coordinates":[102.19197,14.99283],"type":"Point"}
}