{
  "type": "Feature",
  "properties": {
    "gn:admin1_code":"9.0",
    "gn:asciiname":"Ban Thung Kan",
    "gn:country_code":"TH",
    "gn:dem":56,
    "gn:feature_class":"P",
    "gn:feature_code":"PPL",
    "gn:name":"Ban Thung Kan",
    "gn:population":0,
    "gn:timezone":"Asia/Bangkok",
    "iso:country":"TH",
    "name:tha_x_preferred":[
        "\u0e1a\u0e49\u0e32\u0e19\u0e17\u0e38\u0e48\u0e07\u0e01\u0e31\u0e19"
    ],
    "wof:name":"Ban Thung Kan",
    "wof:placetype":"locality"
},
  "geometry": {"coordinates":[99.79855999999999,16.78461],"type":"Point"}
}