{
  "type": "Feature",
  "properties": {
    "gn:admin1_code":"0.0",
    "gn:asciiname":"Ban Choeng Sae",
    "gn:country_code":"TH",
    "gn:dem":0,
    "gn:feature_class":"P",
    "gn:feature_code":"PPL",
    "gn:name":"Ban Choeng Sae",
    "gn:population":0,
    "gn:timezone":"Asia/Bangkok",
    "iso:country":"TH",
    "wof:name":"Ban Choeng Sae",
    "wof:placetype":"locality"
},
  "geometry": {"coordinates":[100.26667,7.58333],"type":"Point"}
}