{
  "type": "Feature",
  "properties": {
    "gn:admin1_code":"69.0",
    "gn:asciiname":"Ban Cho Ba Taeng",
    "gn:country_code":"TH",
    "gn:dem":9,
    "gn:feature_class":"P",
    "gn:feature_code":"PPL",
    "gn:name":"Ban Cho Ba Taeng",
    "gn:population":0,
    "gn:timezone":"Asia/Bangkok",
    "iso:country":"TH",
    "name:tha_x_preferred":[
        "\u0e1a\u0e49\u0e32\u0e19\u0e40\u0e08\u0e4a\u0e32\u0e30\u0e1a\u0e32\u0e41\u0e15\u0e07"
    ],
    "wof:name":"Ban Cho Ba Taeng",
    "wof:placetype":"locality"
},
  "geometry": {"coordinates":[101.50867,6.60336],"type":"Point"}
}