{
  "type": "Feature",
  "properties": {
    "gn:admin1_code":"69.0",
    "gn:asciiname":"Ban Thitman",
    "gn:country_code":"TH",
    "gn:dem":7,
    "gn:feature_class":"P",
    "gn:feature_code":"PPL",
    "gn:name":"Ban Thitman",
    "gn:population":0,
    "gn:timezone":"Asia/Bangkok",
    "iso:country":"TH",
    "name:tha_x_preferred":[
        "\u0e1a\u0e49\u0e32\u0e19\u0e17\u0e34\u0e14\u0e2b\u0e21\u0e32\u0e19"
    ],
    "wof:name":"Ban Thitman",
    "wof:placetype":"locality"
},
  "geometry": {"coordinates":[101.68595000000001,6.62772],"type":"Point"}
}