{
  "type": "Feature",
  "properties": {
    "gn:admin1_code":"13.0",
    "gn:asciiname":"Ban Noen Setthi",
    "gn:country_code":"TH",
    "gn:dem":35,
    "gn:feature_class":"P",
    "gn:feature_code":"PPL",
    "gn:name":"Ban Noen Setthi",
    "gn:population":0,
    "gn:timezone":"Asia/Bangkok",
    "iso:country":"TH",
    "name:tha_x_preferred":[
        "\u0e1a\u0e49\u0e32\u0e19\u0e40\u0e19\u0e34\u0e19\u0e40\u0e28\u0e23\u0e29\u0e10\u0e35"
    ],
    "wof:name":"Ban Noen Setthi",
    "wof:placetype":"locality"
},
  "geometry": {"coordinates":[100.26372000000001,16.17311],"type":"Point"}
}