{
  "type": "Feature",
  "properties": {
    "gn:admin1_code":"29",
    "gn:asciiname":"Ban Lalom Rasai",
    "gn:country_code":"TH",
    "gn:dem":163,
    "gn:feature_class":"P",
    "gn:feature_code":"PPL",
    "gn:name":"Ban Lalom Rasai",
    "gn:population":0,
    "gn:timezone":"Asia/Bangkok",
    "iso:country":"TH",
    "name:tha_x_preferred":[
        "\u0e1a\u0e49\u0e32\u0e19\u0e25\u0e30\u0e25\u0e21\u0e23\u0e30\u0e44\u0e0b\u0e23\u0e4c"
    ],
    "wof:name":"Ban Lalom Rasai",
    "wof:placetype":"locality"
},
  "geometry": {"coordinates":[103.33289000000001,14.59483],"type":"Point"}
}