{
  "type": "Feature",
  "properties": {
    "gn:admin1_code":"43.0",
    "gn:asciiname":"Ban Khaem Khong",
    "gn:country_code":"TH",
    "gn:dem":6,
    "gn:feature_class":"P",
    "gn:feature_code":"PPL",
    "gn:name":"Ban Khaem Khong",
    "gn:population":0,
    "gn:timezone":"Asia/Bangkok",
    "iso:country":"TH",
    "name:tha_x_preferred":[
        "\u0e1a\u0e49\u0e32\u0e19\u0e41\u0e02\u0e21\u0e42\u0e04\u0e49\u0e07"
    ],
    "wof:name":"Ban Khaem Khong",
    "wof:placetype":"locality"
},
  "geometry": {"coordinates":[101.22356000000001,14.0745],"type":"Point"}
}