{
  "type": "Feature",
  "properties": {
    "gn:admin1_code":"30.0",
    "gn:asciiname":"Ban Don Mueat Ae",
    "gn:country_code":"TH",
    "gn:dem":126,
    "gn:feature_class":"P",
    "gn:feature_code":"PPL",
    "gn:name":"Ban Don Mueat Ae",
    "gn:population":0,
    "gn:timezone":"Asia/Bangkok",
    "iso:country":"TH",
    "name:tha_x_preferred":[
        "\u0e1a\u0e49\u0e32\u0e19\u0e14\u0e2d\u0e19\u0e40\u0e2b\u0e21\u0e37\u0e2d\u0e14\u0e41\u0e2d\u0e48"
    ],
    "wof:name":"Ban Don Mueat Ae",
    "wof:placetype":"locality"
},
  "geometry": {"coordinates":[104.32297,15.25281],"type":"Point"}
}