{
  "type": "Feature",
  "properties": {
    "gn:admin1_code":"14.0",
    "gn:asciiname":"Ban Dong Long",
    "gn:country_code":"TH",
    "gn:dem":644,
    "gn:feature_class":"P",
    "gn:feature_code":"PPL",
    "gn:name":"Ban Dong Long",
    "gn:population":0,
    "gn:timezone":"Asia/Bangkok",
    "iso:country":"TH",
    "name:tha_x_preferred":[
        "\u0e1a\u0e49\u0e32\u0e19\u0e14\u0e07\u0e2b\u0e25\u0e07"
    ],
    "wof:name":"Ban Dong Long",
    "wof:placetype":"locality"
},
  "geometry": {"coordinates":[101.07222,16.75497],"type":"Point"}
}