{
  "type": "Feature",
  "properties": {
    "gn:admin1_code":"3.0",
    "gn:asciiname":"Ban Khun Suai",
    "gn:country_code":"TH",
    "gn:dem":869,
    "gn:feature_class":"P",
    "gn:feature_code":"PPL",
    "gn:name":"Ban Khun Suai",
    "gn:population":0,
    "gn:timezone":"Asia/Bangkok",
    "iso:country":"TH",
    "name:tha_x_preferred":[
        "\u0e1a\u0e49\u0e32\u0e19\u0e02\u0e38\u0e19\u0e2a\u0e23\u0e27\u0e22"
    ],
    "name:und_x_variant":[
        "Ban Mae Suai Tai",
        "\u0e1a\u0e49\u0e32\u0e19\u0e1b\u0e32\u0e07\u0e43\u0e15\u0e49",
        "Ban Pang Tai"
    ],
    "wof:name":"Ban Khun Suai",
    "wof:placetype":"locality"
},
  "geometry": {"coordinates":[99.40372000000001,19.87772],"type":"Point"}
}