{
  "type": "Feature",
  "properties": {
    "gn:admin1_code":"2.0",
    "gn:asciiname":"Ban Sop Mao",
    "gn:country_code":"TH",
    "gn:dem":469,
    "gn:feature_class":"P",
    "gn:feature_code":"PPL",
    "gn:name":"Ban Sop Mao",
    "gn:population":0,
    "gn:timezone":"Asia/Bangkok",
    "iso:country":"TH",
    "name:tha_x_preferred":[
        "\u0e1a\u0e49\u0e32\u0e19\u0e2a\u0e1a\u0e21\u0e32\u0e27"
    ],
    "name:und_x_variant":[
        "Ban Sop Mae Mao",
        "B\u0101n Sop Mea M\u0101u",
        "Ban Sop Mao"
    ],
    "wof:name":"Ban Sop Mao",
    "wof:placetype":"locality"
},
  "geometry": {"coordinates":[99.20636,19.89883],"type":"Point"}
}