{
  "type": "Feature",
  "properties": {
    "gn:admin1_code":"27",
    "gn:asciiname":"Ban Nong Plong",
    "gn:country_code":"TH",
    "gn:dem":263,
    "gn:feature_class":"P",
    "gn:feature_code":"PPL",
    "gn:name":"Ban Nong Plong",
    "gn:population":0,
    "gn:timezone":"Asia/Bangkok",
    "iso:country":"TH",
    "name:tha_x_preferred":[
        "\u0e1a\u0e49\u0e32\u0e19\u0e2b\u0e19\u0e2d\u0e07\u0e1b\u0e25\u0e49\u0e2d\u0e07"
    ],
    "wof:name":"Ban Nong Plong",
    "wof:placetype":"locality"
},
  "geometry": {"coordinates":[101.79597,14.66964],"type":"Point"}
}