{
  "type": "Feature",
  "properties": {
    "gn:admin1_code":"70.0",
    "gn:asciiname":"Ban Bannang Ba Ru",
    "gn:country_code":"TH",
    "gn:dem":27,
    "gn:feature_class":"P",
    "gn:feature_code":"PPL",
    "gn:name":"Ban Bannang Ba Ru",
    "gn:population":0,
    "gn:timezone":"Asia/Bangkok",
    "iso:country":"TH",
    "name:tha_x_preferred":[
        "\u0e1a\u0e49\u0e32\u0e19\u0e1a\u0e31\u0e19\u0e19\u0e31\u0e07\u0e1a\u0e32\u0e23\u0e39"
    ],
    "wof:name":"Ban Bannang Ba Ru",
    "wof:placetype":"locality"
},
  "geometry": {"coordinates":[101.21092,6.50236],"type":"Point"}
}