{
  "type": "Feature",
  "properties": {
    "gn:admin1_code":"27",
    "gn:asciiname":"Ban Yup Phatthana",
    "gn:country_code":"TH",
    "gn:dem":495,
    "gn:feature_class":"P",
    "gn:feature_code":"PPL",
    "gn:name":"Ban Yup Phatthana",
    "gn:population":0,
    "gn:timezone":"Asia/Bangkok",
    "iso:country":"TH",
    "name:tha_x_preferred":[
        "\u0e1a\u0e49\u0e32\u0e19\u0e22\u0e38\u0e1a\u0e1e\u0e31\u0e12\u0e19\u0e32"
    ],
    "wof:name":"Ban Yup Phatthana",
    "wof:placetype":"locality"
},
  "geometry": {"coordinates":[101.72808000000001,14.43064],"type":"Point"}
}