{
  "type": "Feature",
  "properties": {
    "gn:admin1_code":"2.0",
    "gn:asciiname":"Ban Nong Wai",
    "gn:country_code":"TH",
    "gn:dem":304,
    "gn:feature_class":"P",
    "gn:feature_code":"PPL",
    "gn:name":"Ban Nong Wai",
    "gn:population":0,
    "gn:timezone":"Asia/Bangkok",
    "iso:country":"TH",
    "name:tha_x_preferred":[
        "\u0e1a\u0e49\u0e32\u0e19\u0e2b\u0e19\u0e2d\u0e07\u0e2b\u0e27\u0e32\u0e22"
    ],
    "name:und_x_variant":[
        "Ban Muang Hom",
        "Ban Nong Wai"
    ],
    "wof:name":"Ban Nong Wai",
    "wof:placetype":"locality"
},
  "geometry": {"coordinates":[98.872,18.64],"type":"Point"}
}