{
  "type": "Feature",
  "properties": {
    "gn:admin1_code":"0.0",
    "gn:asciiname":"Ban Phon Pa Daeng",
    "gn:country_code":"TH",
    "gn:dem":492,
    "gn:feature_class":"P",
    "gn:feature_code":"PPL",
    "gn:name":"Ban Phon Pa Daeng",
    "gn:population":0,
    "gn:timezone":"Asia/Bangkok",
    "iso:country":"TH",
    "wof:name":"Ban Phon Pa Daeng",
    "wof:placetype":"locality"
},
  "geometry": {"coordinates":[101.53333000000001,17.43333],"type":"Point"}
}