{
  "type": "Feature",
  "properties": {
    "gn:admin1_code":"6.0",
    "gn:asciiname":"Ban Thung Luang",
    "gn:country_code":"TH",
    "gn:dem":296,
    "gn:feature_class":"P",
    "gn:feature_code":"PPL",
    "gn:name":"Ban Thung Luang",
    "gn:population":0,
    "gn:timezone":"Asia/Bangkok",
    "iso:country":"TH",
    "name:tha_x_preferred":[
        "\u0e1a\u0e49\u0e32\u0e19\u0e17\u0e38\u0e48\u0e07\u0e2b\u0e25\u0e27\u0e07"
    ],
    "name:und_x_variant":[
        "B\u0101n Thung Raung",
        "Ban Thung Rong",
        "Ban Thung Luang"
    ],
    "wof:name":"Ban Thung Luang",
    "wof:placetype":"locality"
},
  "geometry": {"coordinates":[99.21664,18.254],"type":"Point"}
}