{
  "type": "Feature",
  "properties": {
    "gn:admin1_code":"27.0",
    "gn:asciiname":"Ban Cho Ho",
    "gn:country_code":"TH",
    "gn:dem":183,
    "gn:feature_class":"P",
    "gn:feature_code":"PPL",
    "gn:name":"Ban Cho Ho",
    "gn:population":0,
    "gn:timezone":"Asia/Bangkok",
    "iso:country":"TH",
    "name:tha_x_preferred":[
        "\u0e1a\u0e49\u0e32\u0e19\u0e08\u0e2d\u0e2b\u0e2d"
    ],
    "name:und_x_variant":[
        "Choho",
        "Ban Choho",
        "Ban Cho Ho"
    ],
    "wof:name":"Ban Cho Ho",
    "wof:placetype":"locality"
},
  "geometry": {"coordinates":[102.13947,15.02786],"type":"Point"}
}