{
  "type": "Feature",
  "properties": {
    "gn:admin1_code":"18.0",
    "gn:asciiname":"Ban Sa Na Ung",
    "gn:country_code":"TH",
    "gn:dem":1038,
    "gn:feature_class":"P",
    "gn:feature_code":"PPL",
    "gn:name":"Ban Sa Na Ung",
    "gn:population":0,
    "gn:timezone":"Asia/Bangkok",
    "iso:country":"TH",
    "name:tha_x_preferred":[
        "\u0e1a\u0e49\u0e32\u0e19\u0e2a\u0e30\u0e19\u0e32\u0e2d\u0e38\u0e49\u0e07"
    ],
    "name:und_x_variant":[
        "Ban Maeo Na Sa-ung"
    ],
    "wof:name":"Ban Sa Na Ung",
    "wof:placetype":"locality"
},
  "geometry": {"coordinates":[101.13476,16.99957],"type":"Point"}
}