{
  "type": "Feature",
  "properties": {
    "gn:admin1_code":"27",
    "gn:asciiname":"Ban Don Tanin",
    "gn:country_code":"TH",
    "gn:dem":154,
    "gn:feature_class":"P",
    "gn:feature_code":"PPL",
    "gn:name":"Ban Don Tanin",
    "gn:population":0,
    "gn:timezone":"Asia/Bangkok",
    "iso:country":"TH",
    "name:tha_x_preferred":[
        "\u0e1a\u0e49\u0e32\u0e19\u0e14\u0e2d\u0e19\u0e15\u0e30\u0e2b\u0e19\u0e34\u0e19"
    ],
    "wof:name":"Ban Don Tanin",
    "wof:placetype":"locality"
},
  "geometry": {"coordinates":[102.76810999999999,15.61406],"type":"Point"}
}