{
  "type": "Feature",
  "properties": {
    "gn:admin1_code":"2.0",
    "gn:asciiname":"Ban Don Mun 2",
    "gn:country_code":"TH",
    "gn:dem":324,
    "gn:feature_class":"P",
    "gn:feature_code":"PPL",
    "gn:name":"Ban Don Mun 2",
    "gn:population":0,
    "gn:timezone":"Asia/Bangkok",
    "iso:country":"TH",
    "name:tha_x_preferred":[
        "\u0e1a\u0e49\u0e32\u0e19\u0e14\u0e2d\u0e19\u0e21\u0e39\u0e25 2"
    ],
    "name:und_x_variant":[
        "Ban Don Mun",
        "\u0e1a\u0e49\u0e32\u0e19\u0e14\u0e2d\u0e19\u0e21\u0e39\u0e25"
    ],
    "wof:lang_x_official":[
        "tha"
    ],
    "wof:lang_x_spoken":[
        "tha"
    ],
    "wof:name":"Ban Don Mun 2",
    "wof:placetype":"locality"
},
  "geometry": {"coordinates":[99.14989,18.7385],"type":"Point"}
}