{
  "type": "Feature",
  "properties": {
    "gn:admin1_code":"52.0",
    "gn:asciiname":"Ban Don Phutsa",
    "gn:country_code":"TH",
    "gn:dem":37,
    "gn:feature_class":"P",
    "gn:feature_code":"PPL",
    "gn:name":"Ban Don Phutsa",
    "gn:population":0,
    "gn:timezone":"Asia/Bangkok",
    "iso:country":"TH",
    "name:tha_x_preferred":[
        "\u0e1a\u0e49\u0e32\u0e19\u0e14\u0e2d\u0e19\u0e1e\u0e38\u0e17\u0e23\u0e32"
    ],
    "wof:name":"Ban Don Phutsa",
    "wof:placetype":"locality"
},
  "geometry": {"coordinates":[99.71625,13.34753],"type":"Point"}
}