{
  "type": "Feature",
  "properties": {
    "gn:admin1_code":"44.0",
    "gn:asciiname":"Ban Ang Toei Nok",
    "gn:country_code":"TH",
    "gn:dem":50,
    "gn:feature_class":"P",
    "gn:feature_code":"PPL",
    "gn:name":"Ban Ang Toei Nok",
    "gn:population":0,
    "gn:timezone":"Asia/Bangkok",
    "iso:country":"TH",
    "name:tha_x_preferred":[
        "\u0e1a\u0e49\u0e32\u0e19\u0e2d\u0e48\u0e32\u0e07\u0e40\u0e15\u0e22\u0e19\u0e2d\u0e01"
    ],
    "wof:name":"Ban Ang Toei Nok",
    "wof:placetype":"locality"
},
  "geometry": {"coordinates":[101.64172000000001,13.56531],"type":"Point"}
}