{
  "type": "Feature",
  "properties": {
    "gn:admin1_code":"70.0",
    "gn:asciiname":"Ban Plak Khla",
    "gn:country_code":"TH",
    "gn:dem":19,
    "gn:feature_class":"P",
    "gn:feature_code":"PPL",
    "gn:name":"Ban Plak Khla",
    "gn:population":0,
    "gn:timezone":"Asia/Bangkok",
    "iso:country":"TH",
    "name:tha_x_preferred":[
        "\u0e1a\u0e49\u0e32\u0e19\u0e1b\u0e25\u0e31\u0e01\u0e04\u0e25\u0e49\u0e32"
    ],
    "wof:name":"Ban Plak Khla",
    "wof:placetype":"locality"
},
  "geometry": {"coordinates":[101.26728,6.58733],"type":"Point"}
}