{
  "type": "Feature",
  "properties": {
    "gn:admin1_code":"70.0",
    "gn:asciiname":"Ban Ta Se",
    "gn:country_code":"TH",
    "gn:dem":24,
    "gn:feature_class":"P",
    "gn:feature_code":"PPL",
    "gn:name":"Ban Ta Se",
    "gn:population":0,
    "gn:timezone":"Asia/Bangkok",
    "iso:country":"TH",
    "name:tha_x_preferred":[
        "\u0e1a\u0e49\u0e32\u0e19\u0e15\u0e32\u0e40\u0e0b\u0e30"
    ],
    "wof:name":"Ban Ta Se",
    "wof:placetype":"locality"
},
  "geometry": {"coordinates":[101.26472,6.62442],"type":"Point"}
}