{
  "type": "Feature",
  "properties": {
    "gn:admin1_code":"57.0",
    "gn:asciiname":"Ban Bo Phai",
    "gn:country_code":"TH",
    "gn:dem":38,
    "gn:feature_class":"P",
    "gn:feature_code":"PPL",
    "gn:name":"Ban Bo Phai",
    "gn:population":0,
    "gn:timezone":"Asia/Bangkok",
    "iso:country":"TH",
    "name:tha_x_preferred":[
        "\u0e1a\u0e49\u0e32\u0e19\u0e1a\u0e48\u0e2d\u0e44\u0e1e"
    ],
    "wof:name":"Ban Bo Phai",
    "wof:placetype":"locality"
},
  "geometry": {"coordinates":[99.42797,11.00447],"type":"Point"}
}