{
  "type": "Feature",
  "properties": {
    "gn:admin1_code":"6.0",
    "gn:asciiname":"Ban Thung Yang",
    "gn:country_code":"TH",
    "gn:dem":502,
    "gn:feature_class":"P",
    "gn:feature_code":"PPL",
    "gn:name":"Ban Thung Yang",
    "gn:population":0,
    "gn:timezone":"Asia/Bangkok",
    "iso:country":"TH",
    "name:tha_x_preferred":[
        "\u0e1a\u0e49\u0e32\u0e19\u0e17\u0e38\u0e48\u0e07\u0e22\u0e32\u0e07"
    ],
    "wof:name":"Ban Thung Yang",
    "wof:placetype":"locality"
},
  "geometry": {"coordinates":[99.51642,19.03131],"type":"Point"}
}