{
  "type": "Feature",
  "properties": {
    "gn:admin1_code":"27.0",
    "gn:asciiname":"Ban Tha Wua Tai",
    "gn:country_code":"TH",
    "gn:dem":441,
    "gn:feature_class":"P",
    "gn:feature_code":"PPL",
    "gn:name":"Ban Tha Wua Tai",
    "gn:population":0,
    "gn:timezone":"Asia/Bangkok",
    "iso:country":"TH",
    "wof:name":"Ban Tha Wua Tai",
    "wof:placetype":"locality"
},
  "geometry": {"coordinates":[101.59721999999999,14.46583],"type":"Point"}
}