{
  "type": "Feature",
  "properties": {
    "gn:admin1_code":"68.0",
    "gn:asciiname":"Ban Tha Mot",
    "gn:country_code":"TH",
    "gn:dem":8,
    "gn:feature_class":"P",
    "gn:feature_code":"PPL",
    "gn:name":"Ban Tha Mot",
    "gn:population":0,
    "gn:timezone":"Asia/Bangkok",
    "iso:country":"TH",
    "name:tha_x_preferred":[
        "\u0e1a\u0e49\u0e32\u0e19\u0e17\u0e48\u0e32\u0e42\u0e2b\u0e21\u0e14"
    ],
    "wof:name":"Ban Tha Mot",
    "wof:placetype":"locality"
},
  "geometry": {"coordinates":[100.68572,7.03722],"type":"Point"}
}