{
  "type": "Feature",
  "properties": {
    "gn:admin1_code":"11.0",
    "gn:asciiname":"Ban Rai Phai Wan",
    "gn:country_code":"TH",
    "gn:dem":60,
    "gn:feature_class":"P",
    "gn:feature_code":"PPL",
    "gn:name":"Ban Rai Phai Wan",
    "gn:population":0,
    "gn:timezone":"Asia/Bangkok",
    "iso:country":"TH",
    "name:tha_x_preferred":[
        "\u0e1a\u0e49\u0e32\u0e19\u0e44\u0e23\u0e48\u0e44\u0e1e\u0e23\u0e27\u0e31\u0e25\u0e22\u0e4c"
    ],
    "wof:name":"Ban Rai Phai Wan",
    "wof:placetype":"locality"
},
  "geometry": {"coordinates":[99.73819,15.95683],"type":"Point"}
}