{
  "type": "Feature",
  "properties": {
    "gn:admin1_code":"5.0",
    "gn:asciiname":"Ban Nong Lak",
    "gn:country_code":"TH",
    "gn:dem":619,
    "gn:feature_class":"P",
    "gn:feature_code":"PPL",
    "gn:name":"Ban Nong Lak",
    "gn:population":0,
    "gn:timezone":"Asia/Bangkok",
    "iso:country":"TH",
    "name:tha_x_preferred":[
        "\u0e1a\u0e49\u0e32\u0e19\u0e2b\u0e19\u0e2d\u0e07\u0e2b\u0e25\u0e31\u0e01"
    ],
    "wof:name":"Ban Nong Lak",
    "wof:placetype":"locality"
},
  "geometry": {"coordinates":[99.02647,18.10228],"type":"Point"}
}