{
  "type": "Feature",
  "properties": {
    "gn:admin1_code":"2.0",
    "gn:asciiname":"Ban Huai Som Poi",
    "gn:country_code":"TH",
    "gn:dem":1182,
    "gn:feature_class":"P",
    "gn:feature_code":"PPL",
    "gn:name":"Ban Huai Som Poi",
    "gn:population":0,
    "gn:timezone":"Asia/Bangkok",
    "iso:country":"TH",
    "name:tha_x_preferred":[
        "\u0e1a\u0e49\u0e32\u0e19\u0e2b\u0e49\u0e27\u0e22\u0e2a\u0e49\u0e21\u0e1b\u0e48\u0e2d\u0e22"
    ],
    "name:und_x_variant":[
        "Ban Som Poi"
    ],
    "wof:name":"Ban Huai Som Poi",
    "wof:placetype":"locality"
},
  "geometry": {"coordinates":[98.52858000000001,18.37195],"type":"Point"}
}