{
  "type": "Feature",
  "properties": {
    "gn:admin1_code":"2.0",
    "gn:asciiname":"Ban I Mun",
    "gn:country_code":"TH",
    "gn:dem":837,
    "gn:feature_class":"P",
    "gn:feature_code":"PPL",
    "gn:name":"Ban I Mun",
    "gn:population":0,
    "gn:timezone":"Asia/Bangkok",
    "iso:country":"TH",
    "name:tha_x_preferred":[
        "\u0e1a\u0e49\u0e32\u0e19\u0e2d\u0e35\u0e21\u0e39\u0e19"
    ],
    "wof:name":"Ban I Mun",
    "wof:placetype":"locality"
},
  "geometry": {"coordinates":[98.43919,18.13045],"type":"Point"}
}