{
  "type": "Feature",
  "properties": {
    "gn:admin1_code":"27",
    "gn:asciiname":"Ban Yai Kok Lan",
    "gn:country_code":"TH",
    "gn:dem":207,
    "gn:feature_class":"P",
    "gn:feature_code":"PPL",
    "gn:name":"Ban Yai Kok Lan",
    "gn:population":0,
    "gn:timezone":"Asia/Bangkok",
    "iso:country":"TH",
    "name:tha_x_preferred":[
        "\u0e1a\u0e49\u0e32\u0e19\u0e43\u0e2b\u0e0d\u0e48\u0e01\u0e01\u0e25\u0e32\u0e19"
    ],
    "wof:name":"Ban Yai Kok Lan",
    "wof:placetype":"locality"
},
  "geometry": {"coordinates":[101.87311,14.92656],"type":"Point"}
}