{
  "type": "Feature",
  "properties": {
    "gn:admin1_code":"59.0",
    "gn:asciiname":"Ban Nikhom Phang Nueng",
    "gn:country_code":"TH",
    "gn:dem":40,
    "gn:feature_class":"P",
    "gn:feature_code":"PPL",
    "gn:name":"Ban Nikhom Phang Nueng",
    "gn:population":0,
    "gn:timezone":"Asia/Bangkok",
    "iso:country":"TH",
    "name:tha_x_preferred":[
        "\u0e1a\u0e49\u0e32\u0e19\u0e19\u0e34\u0e04\u0e21\u0e1c\u0e31\u0e07 \u0e2b\u0e19\u0e36\u0e48\u0e07"
    ],
    "wof:name":"Ban Nikhom Phang Nueng",
    "wof:placetype":"locality"
},
  "geometry": {"coordinates":[98.90403000000001,10.53892],"type":"Point"}
}