{
  "type": "Feature",
  "properties": {
    "gn:admin1_code":"25.0",
    "gn:asciiname":"Ban Hong Thong",
    "gn:country_code":"TH",
    "gn:dem":138,
    "gn:feature_class":"P",
    "gn:feature_code":"PPL",
    "gn:name":"Ban Hong Thong",
    "gn:population":0,
    "gn:timezone":"Asia/Bangkok",
    "iso:country":"TH",
    "name:tha_x_preferred":[
        "\u0e1a\u0e49\u0e32\u0e19\u0e2b\u0e07\u0e29\u0e4c\u0e17\u0e2d\u0e07"
    ],
    "wof:name":"Ban Hong Thong",
    "wof:placetype":"locality"
},
  "geometry": {"coordinates":[103.78422,16.13544],"type":"Point"}
}