{
  "type": "Feature",
  "properties": {
    "gn:admin1_code":"47.0",
    "gn:asciiname":"Ban Map Chan",
    "gn:country_code":"TH",
    "gn:dem":53,
    "gn:feature_class":"P",
    "gn:feature_code":"PPL",
    "gn:name":"Ban Map Chan",
    "gn:population":0,
    "gn:timezone":"Asia/Bangkok",
    "iso:country":"TH",
    "name:tha_x_preferred":[
        "\u0e1a\u0e49\u0e32\u0e19\u0e21\u0e32\u0e1a\u0e08\u0e31\u0e19\u0e17\u0e23\u0e4c"
    ],
    "wof:name":"Ban Map Chan",
    "wof:placetype":"locality"
},
  "geometry": {"coordinates":[101.43167,12.68278],"type":"Point"}
}