{
  "type": "Feature",
  "properties": {
    "gn:admin1_code":"25",
    "gn:asciiname":"Ban Na Charoen",
    "gn:country_code":"TH",
    "gn:dem":161,
    "gn:feature_class":"P",
    "gn:feature_code":"PPL",
    "gn:name":"Ban Na Charoen",
    "gn:population":0,
    "gn:timezone":"Asia/Bangkok",
    "iso:country":"TH",
    "name:tha_x_preferred":[
        "\u0e1a\u0e49\u0e32\u0e19\u0e19\u0e32\u0e40\u0e08\u0e23\u0e34\u0e0d"
    ],
    "wof:name":"Ban Na Charoen",
    "wof:placetype":"locality"
},
  "geometry": {"coordinates":[104.06553,16.36736],"type":"Point"}
}