{
  "type": "Feature",
  "properties": {
    "gn:admin1_code":"70.0",
    "gn:asciiname":"Ban Bue Nae Ba Li",
    "gn:country_code":"TH",
    "gn:dem":21,
    "gn:feature_class":"P",
    "gn:feature_code":"PPL",
    "gn:name":"Ban Bue Nae Ba Li",
    "gn:population":0,
    "gn:timezone":"Asia/Bangkok",
    "iso:country":"TH",
    "name:tha_x_preferred":[
        "\u0e1a\u0e49\u0e32\u0e19\u0e1a\u0e37\u0e2d\u0e41\u0e19\u0e1a\u0e32\u0e25\u0e35"
    ],
    "wof:name":"Ban Bue Nae Ba Li",
    "wof:placetype":"locality"
},
  "geometry": {"coordinates":[101.52378,6.55358],"type":"Point"}
}