{
  "type": "Feature",
  "properties": {
    "gn:admin1_code":"3.0",
    "gn:asciiname":"Ban Pong Noi",
    "gn:country_code":"TH",
    "gn:dem":396,
    "gn:feature_class":"P",
    "gn:feature_code":"PPL",
    "gn:name":"Ban Pong Noi",
    "gn:population":0,
    "gn:timezone":"Asia/Bangkok",
    "iso:country":"TH",
    "name:tha_x_preferred":[
        "\u0e1a\u0e49\u0e32\u0e19\u0e1b\u0e07\u0e19\u0e49\u0e2d\u0e22"
    ],
    "wof:name":"Ban Pong Noi",
    "wof:placetype":"locality"
},
  "geometry": {"coordinates":[100.08297,20.12336],"type":"Point"}
}