{
  "type": "Feature",
  "properties": {
    "gn:admin1_code":"11.0",
    "gn:asciiname":"Ban Wang Nam Suem",
    "gn:country_code":"TH",
    "gn:dem":80,
    "gn:feature_class":"P",
    "gn:feature_code":"PPL",
    "gn:name":"Ban Wang Nam Suem",
    "gn:population":0,
    "gn:timezone":"Asia/Bangkok",
    "iso:country":"TH",
    "name:tha_x_preferred":[
        "\u0e1a\u0e49\u0e32\u0e19\u0e27\u0e31\u0e07\u0e19\u0e49\u0e33\u0e0b\u0e36\u0e21"
    ],
    "wof:name":"Ban Wang Nam Suem",
    "wof:placetype":"locality"
},
  "geometry": {"coordinates":[99.69261,16.01664],"type":"Point"}
}