{
  "type": "Feature",
  "properties": {
    "gn:admin1_code":"4.0",
    "gn:asciiname":"Ban Thon",
    "gn:country_code":"TH",
    "gn:dem":270,
    "gn:feature_class":"P",
    "gn:feature_code":"PPL",
    "gn:name":"Ban Thon",
    "gn:population":0,
    "gn:timezone":"Asia/Bangkok",
    "iso:country":"TH",
    "name:tha_x_preferred":[
        "\u0e1a\u0e49\u0e32\u0e19\u0e16\u0e48\u0e2d\u0e19"
    ],
    "name:und_x_variant":[
        "Ban Muang Yom",
        "Ban Thon (1)",
        "Ban Thon"
    ],
    "wof:name":"Ban Thon",
    "wof:placetype":"locality"
},
  "geometry": {"coordinates":[100.87922,19.08303],"type":"Point"}
}