{
  "type": "Feature",
  "properties": {
    "gn:admin1_code":"73.0",
    "gn:asciiname":"Ban Ba Wa",
    "gn:country_code":"TH",
    "gn:dem":152,
    "gn:feature_class":"P",
    "gn:feature_code":"PPL",
    "gn:name":"Ban Ba Wa",
    "gn:population":0,
    "gn:timezone":"Asia/Bangkok",
    "iso:country":"TH",
    "name:tha_x_preferred":[
        "\u0e1a\u0e49\u0e32\u0e19\u0e1a\u0e30\u0e2b\u0e27\u0e49\u0e32"
    ],
    "wof:name":"Ban Ba Wa",
    "wof:placetype":"locality"
},
  "geometry": {"coordinates":[104.07489,17.52253],"type":"Point"}
}