{
  "type": "Feature",
  "properties": {
    "gn:admin1_code":"65.0",
    "gn:asciiname":"Ban Khuan Nok Wa",
    "gn:country_code":"TH",
    "gn:dem":45,
    "gn:feature_class":"P",
    "gn:feature_code":"PPL",
    "gn:name":"Ban Khuan Nok Wa",
    "gn:population":0,
    "gn:timezone":"Asia/Bangkok",
    "iso:country":"TH",
    "name:tha_x_preferred":[
        "\u0e1a\u0e49\u0e32\u0e19\u0e04\u0e27\u0e19\u0e19\u0e01\u0e2b\u0e27\u0e49\u0e32"
    ],
    "wof:name":"Ban Khuan Nok Wa",
    "wof:placetype":"locality"
},
  "geometry": {"coordinates":[99.47432999999999,7.77272],"type":"Point"}
}