{
  "type": "Feature",
  "properties": {
    "gn:admin1_code":"26.0",
    "gn:asciiname":"Ban Sam Khwai Noi",
    "gn:country_code":"TH",
    "gn:dem":234,
    "gn:feature_class":"P",
    "gn:feature_code":"PPL",
    "gn:name":"Ban Sam Khwai Noi",
    "gn:population":0,
    "gn:timezone":"Asia/Bangkok",
    "iso:country":"TH",
    "wof:name":"Ban Sam Khwai Noi",
    "wof:placetype":"locality"
},
  "geometry": {"coordinates":[101.80167,15.93278],"type":"Point"}
}