{
  "type": "Feature",
  "properties": {
    "gn:admin1_code":"7.0",
    "gn:asciiname":"Ban Mong Kaeng Luang",
    "gn:country_code":"TH",
    "gn:dem":156,
    "gn:feature_class":"P",
    "gn:feature_code":"PPL",
    "gn:name":"Ban Mong Kaeng Luang",
    "gn:population":0,
    "gn:timezone":"Asia/Bangkok",
    "iso:country":"TH",
    "name:tha_x_preferred":[
        "\u0e1a\u0e49\u0e32\u0e19\u0e21\u0e49\u0e07\u0e41\u0e01\u0e48\u0e07\u0e2b\u0e25\u0e27\u0e07"
    ],
    "wof:name":"Ban Mong Kaeng Luang",
    "wof:placetype":"locality"
},
  "geometry": {"coordinates":[99.95703,18.03119],"type":"Point"}
}