{
  "type": "Feature",
  "properties": {
    "gn:admin1_code":"16.0",
    "gn:asciiname":"Ban Sap Sombun",
    "gn:country_code":"TH",
    "gn:dem":131,
    "gn:feature_class":"P",
    "gn:feature_code":"PPL",
    "gn:name":"Ban Sap Sombun",
    "gn:population":0,
    "gn:timezone":"Asia/Bangkok",
    "iso:country":"TH",
    "name:tha_x_preferred":[
        "\u0e1a\u0e49\u0e32\u0e19\u0e0b\u0e31\u0e1a\u0e2a\u0e21\u0e1a\u0e39\u0e23\u0e13\u0e4c"
    ],
    "wof:name":"Ban Sap Sombun",
    "wof:placetype":"locality"
},
  "geometry": {"coordinates":[100.78122,15.57569],"type":"Point"}
}