{
  "type": "Feature",
  "properties": {
    "gn:admin1_code":"31.0",
    "gn:asciiname":"Ban Mo I So",
    "gn:country_code":"TH",
    "gn:dem":65,
    "gn:feature_class":"P",
    "gn:feature_code":"PPL",
    "gn:name":"Ban Mo I So",
    "gn:population":0,
    "gn:timezone":"Asia/Bangkok",
    "iso:country":"TH",
    "name:tha_x_preferred":[
        "\u0e1a\u0e49\u0e32\u0e19\u0e40\u0e21\u0e32\u0e30\u0e2d\u0e35\u0e40\u0e2a\u0e32\u0e30"
    ],
    "wof:name":"Ban Mo I So",
    "wof:placetype":"locality"
},
  "geometry": {"coordinates":[101.66725,6.16156],"type":"Point"}
}