{
  "type": "Feature",
  "properties": {
    "gn:admin1_code":"36.0",
    "gn:asciiname":"Ban Thap Nam",
    "gn:country_code":"TH",
    "gn:dem":5,
    "gn:feature_class":"P",
    "gn:feature_code":"PPL",
    "gn:name":"Ban Thap Nam",
    "gn:population":0,
    "gn:timezone":"Asia/Bangkok",
    "iso:country":"TH",
    "name:tha_x_preferred":[
        "\u0e1a\u0e49\u0e32\u0e19\u0e17\u0e31\u0e1a\u0e19\u0e49\u0e33"
    ],
    "name:und_x_variant":[
        "Ban Tab Nam",
        "Ban Thap Nam"
    ],
    "wof:name":"Ban Thap Nam",
    "wof:placetype":"locality"
},
  "geometry": {"coordinates":[100.51143999999999,14.47142],"type":"Point"}
}