{
  "type": "Feature",
  "properties": {
    "gn:admin1_code":"22.0",
    "gn:asciiname":"Ban Sala Din",
    "gn:country_code":"TH",
    "gn:dem":211,
    "gn:feature_class":"P",
    "gn:feature_code":"PPL",
    "gn:name":"Ban Sala Din",
    "gn:population":0,
    "gn:timezone":"Asia/Bangkok",
    "iso:country":"TH",
    "name:tha_x_preferred":[
        "\u0e1a\u0e49\u0e32\u0e19\u0e28\u0e32\u0e25\u0e32\u0e14\u0e34\u0e19"
    ],
    "wof:name":"Ban Sala Din",
    "wof:placetype":"locality"
},
  "geometry": {"coordinates":[102.39528,16.75072],"type":"Point"}
}