{
  "type": "Feature",
  "properties": {
    "gn:admin1_code":"65.0",
    "gn:asciiname":"Ban Tha Ruea",
    "gn:country_code":"TH",
    "gn:dem":13,
    "gn:feature_class":"P",
    "gn:feature_code":"PPL",
    "gn:name":"Ban Tha Ruea",
    "gn:population":0,
    "gn:timezone":"Asia/Bangkok",
    "iso:country":"TH",
    "name:tha_x_preferred":[
        "\u0e1a\u0e49\u0e32\u0e19\u0e17\u0e48\u0e32\u0e40\u0e23\u0e37\u0e2d"
    ],
    "name:und_x_variant":[
        "Ban Tha Rua"
    ],
    "wof:name":"Ban Tha Ruea",
    "wof:placetype":"locality"
},
  "geometry": {"coordinates":[99.56538999999999,7.36375],"type":"Point"}
}