{
  "type": "Feature",
  "properties": {
    "gn:admin1_code":"64.0",
    "gn:asciiname":"Ban Theppharat",
    "gn:country_code":"TH",
    "gn:dem":18,
    "gn:feature_class":"P",
    "gn:feature_code":"PPL",
    "gn:name":"Ban Theppharat",
    "gn:population":0,
    "gn:timezone":"Asia/Bangkok",
    "iso:country":"TH",
    "name:tha_x_preferred":[
        "\u0e1a\u0e49\u0e32\u0e19\u0e40\u0e17\u0e1e\u0e23\u0e32\u0e0a"
    ],
    "name:und_x_variant":[
        "Ban Theprat",
        "Ban Theppharap",
        "Ban Theppharat"
    ],
    "wof:name":"Ban Theppharat",
    "wof:placetype":"locality"
},
  "geometry": {"coordinates":[99.86214,8.86106],"type":"Point"}
}