{
  "type": "Feature",
  "properties": {
    "gn:admin1_code":"11.0",
    "gn:asciiname":"Ban Bo Tham",
    "gn:country_code":"TH",
    "gn:dem":48,
    "gn:feature_class":"P",
    "gn:feature_code":"PPL",
    "gn:name":"Ban Bo Tham",
    "gn:population":0,
    "gn:timezone":"Asia/Bangkok",
    "iso:country":"TH",
    "name:tha_x_preferred":[
        "\u0e1a\u0e49\u0e32\u0e19\u0e1a\u0e48\u0e2d\u0e16\u0e49\u0e33"
    ],
    "name:und_x_variant":[
        "Bo Tham",
        "B\u0101n Bau Tham",
        "B\u0101n Boh Tham",
        "Ban Bo Tham"
    ],
    "wof:name":"Ban Bo Tham",
    "wof:placetype":"locality"
},
  "geometry": {"coordinates":[99.76531,15.95583],"type":"Point"}
}