{
  "type": "Feature",
  "properties": {
    "gn:admin1_code":"68.0",
    "gn:asciiname":"Ban Thung Lan Chang",
    "gn:country_code":"TH",
    "gn:dem":22,
    "gn:feature_class":"P",
    "gn:feature_code":"PPL",
    "gn:name":"Ban Thung Lan Chang",
    "gn:population":0,
    "gn:timezone":"Asia/Bangkok",
    "iso:country":"TH",
    "name:tha_x_preferred":[
        "\u0e1a\u0e49\u0e32\u0e19\u0e17\u0e38\u0e48\u0e07\u0e25\u0e32\u0e19\u0e0a\u0e49\u0e32\u0e07"
    ],
    "wof:name":"Ban Thung Lan Chang",
    "wof:placetype":"locality"
},
  "geometry": {"coordinates":[100.93056,6.77069],"type":"Point"}
}