{
  "type": "Feature",
  "properties": {
    "gn:admin1_code":"31.0",
    "gn:asciiname":"Ban Ai Ba Tu",
    "gn:country_code":"TH",
    "gn:dem":30,
    "gn:feature_class":"P",
    "gn:feature_code":"PPL",
    "gn:name":"Ban Ai Ba Tu",
    "gn:population":0,
    "gn:timezone":"Asia/Bangkok",
    "iso:country":"TH",
    "name:tha_x_preferred":[
        "\u0e1a\u0e49\u0e32\u0e19\u0e44\u0e2d\u0e1a\u0e32\u0e15\u0e39"
    ],
    "name:und_x_variant":[
        "Kampong Aiketu"
    ],
    "wof:name":"Ban Ai Ba Tu",
    "wof:placetype":"locality"
},
  "geometry": {"coordinates":[101.88182999999999,6.10531],"type":"Point"}
}