{
  "type": "Feature",
  "properties": {
    "gn:admin1_code":"43.0",
    "gn:asciiname":"Ban Bang Takhong",
    "gn:country_code":"TH",
    "gn:dem":4,
    "gn:feature_class":"P",
    "gn:feature_code":"PPL",
    "gn:name":"Ban Bang Takhong",
    "gn:population":0,
    "gn:timezone":"Asia/Bangkok",
    "iso:country":"TH",
    "name:tha_x_preferred":[
        "\u0e1a\u0e49\u0e32\u0e19\u0e1a\u0e32\u0e07\u0e15\u0e30\u0e04\u0e07"
    ],
    "name:und_x_variant":[
        "Ban Bang Ta Khang",
        "Ban Khlong Ta Khong (1)",
        "Ban Bang Takhong"
    ],
    "wof:lang_x_official":[
        "tha"
    ],
    "wof:lang_x_spoken":[
        "tha"
    ],
    "wof:name":"Ban Bang Takhong",
    "wof:placetype":"locality"
},
  "geometry": {"coordinates":[101.12903,14.16119],"type":"Point"}
}