{
  "type": "Feature",
  "properties": {
    "gn:admin1_code":"31.0",
    "gn:asciiname":"Ban Ro Tan Ba Tu",
    "gn:country_code":"TH",
    "gn:dem":13,
    "gn:feature_class":"P",
    "gn:feature_code":"PPL",
    "gn:name":"Ban Ro Tan Ba Tu",
    "gn:population":0,
    "gn:timezone":"Asia/Bangkok",
    "iso:country":"TH",
    "name:tha_x_preferred":[
        "\u0e1a\u0e49\u0e32\u0e19\u0e23\u0e2d\u0e15\u0e31\u0e19\u0e1a\u0e32\u0e15\u0e39"
    ],
    "wof:name":"Ban Ro Tan Ba Tu",
    "wof:placetype":"locality"
},
  "geometry": {"coordinates":[101.84797,6.35486],"type":"Point"}
}