{
  "type": "Feature",
  "properties": {
    "gn:admin1_code":"18.0",
    "gn:asciiname":"Ban Noi Mi Chai",
    "gn:country_code":"TH",
    "gn:dem":301,
    "gn:feature_class":"P",
    "gn:feature_code":"PPL",
    "gn:name":"Ban Noi Mi Chai",
    "gn:population":0,
    "gn:timezone":"Asia/Bangkok",
    "iso:country":"TH",
    "name:tha_x_preferred":[
        "Ban Noi Mi Chai"
    ],
    "name:tha_x_variant":[
        "\u0e1a\u0e49\u0e32\u0e19\u0e19\u0e49\u0e2d\u0e22\u0e21\u0e35\u0e0a\u0e31\u0e22"
    ],
    "wof:name":"Ban Noi Mi Chai",
    "wof:placetype":"locality"
},
  "geometry": {"coordinates":[101.92478,16.96044],"type":"Point"}
}