{
  "type": "Feature",
  "properties": {
    "gn:admin1_code":"25.0",
    "gn:asciiname":"Ban Mai Prasat Phon",
    "gn:country_code":"TH",
    "gn:dem":153,
    "gn:feature_class":"P",
    "gn:feature_code":"PPL",
    "gn:name":"Ban Mai Prasat Phon",
    "gn:population":0,
    "gn:timezone":"Asia/Bangkok",
    "iso:country":"TH",
    "name:tha_x_preferred":[
        "\u0e1a\u0e49\u0e32\u0e19\u0e43\u0e2b\u0e21\u0e48\u0e1b\u0e23\u0e30\u0e2a\u0e32\u0e17\u0e1e\u0e23"
    ],
    "wof:name":"Ban Mai Prasat Phon",
    "wof:placetype":"locality"
},
  "geometry": {"coordinates":[103.49164,15.87328],"type":"Point"}
}