{
  "type": "Feature",
  "properties": {
    "gn:admin1_code":"80.0",
    "gn:asciiname":"Ban Nong Mak Fai",
    "gn:country_code":"TH",
    "gn:dem":76,
    "gn:feature_class":"P",
    "gn:feature_code":"PPL",
    "gn:name":"Ban Nong Mak Fai",
    "gn:population":0,
    "gn:timezone":"Asia/Bangkok",
    "iso:country":"TH",
    "name:tha_x_preferred":[
        "\u0e1a\u0e49\u0e32\u0e19\u0e2b\u0e19\u0e2d\u0e07\u0e2b\u0e21\u0e32\u0e01\u0e1d\u0e49\u0e32\u0e22"
    ],
    "wof:name":"Ban Nong Mak Fai",
    "wof:placetype":"locality"
},
  "geometry": {"coordinates":[102.39067,13.89358],"type":"Point"}
}