{
  "type": "Feature",
  "properties": {
    "gn:admin1_code":"2.0",
    "gn:asciiname":"Ban U Meng",
    "gn:country_code":"TH",
    "gn:dem":301,
    "gn:feature_class":"P",
    "gn:feature_code":"PPL",
    "gn:name":"Ban U Meng",
    "gn:population":0,
    "gn:timezone":"Asia/Bangkok",
    "iso:country":"TH",
    "name:tha_x_preferred":[
        "\u0e1a\u0e49\u0e32\u0e19\u0e2d\u0e38\u0e40\u0e21\u0e47\u0e07"
    ],
    "name:und_x_variant":[
        "Ban Umong",
        "Ban Umeng",
        "Ban U Meng"
    ],
    "wof:name":"Ban U Meng",
    "wof:placetype":"locality"
},
  "geometry": {"coordinates":[98.87108000000001,18.62192000000001],"type":"Point"}
}