{
  "type": "Feature",
  "properties": {
    "gn:admin1_code":"60.0",
    "gn:asciiname":"Ban Huai Phun",
    "gn:country_code":"TH",
    "gn:dem":11,
    "gn:feature_class":"P",
    "gn:feature_code":"PPL",
    "gn:name":"Ban Huai Phun",
    "gn:population":0,
    "gn:timezone":"Asia/Bangkok",
    "iso:country":"TH",
    "name:tha_x_preferred":[
        "\u0e1a\u0e49\u0e32\u0e19\u0e2b\u0e49\u0e27\u0e22\u0e1e\u0e38\u0e19"
    ],
    "name:und_x_variant":[
        "Ban Huai Phon Lang"
    ],
    "wof:name":"Ban Huai Phun",
    "wof:placetype":"locality"
},
  "geometry": {"coordinates":[99.20681,9.45894],"type":"Point"}
}