{
  "type": "Feature",
  "properties": {
    "gn:admin1_code":"62.0",
    "gn:asciiname":"Ban Hin Luk Diao",
    "gn:country_code":"TH",
    "gn:dem":18,
    "gn:feature_class":"P",
    "gn:feature_code":"PPL",
    "gn:name":"Ban Hin Luk Diao",
    "gn:population":0,
    "gn:timezone":"Asia/Bangkok",
    "iso:country":"TH",
    "name:tha_x_preferred":[
        "\u0e1a\u0e49\u0e32\u0e19\u0e2b\u0e34\u0e19\u0e25\u0e39\u0e01\u0e40\u0e14\u0e35\u0e22\u0e27"
    ],
    "wof:name":"Ban Hin Luk Diao",
    "wof:placetype":"locality"
},
  "geometry": {"coordinates":[98.30189,8.17672],"type":"Point"}
}