{
  "type": "Feature",
  "properties": {
    "gn:country":"TH",
    "gn:fcode":"PPLA",
    "gn:population":34595,
    "iso:country":"TH",
    "name:ace_x_preferred":[
        "Propinsi Nakhon Phanom"
    ],
    "name:bod_x_preferred":[
        "\u0f53\u0f0b\u0f41\u0f71\u0f7c\u0f53\u0f0b\u0f55\u0f0b\u0f53\u0f7c\u0f58\u0f0d"
    ],
    "name:ceb_x_preferred":[
        "Nakhon Phanom"
    ],
    "name:deu_x_preferred":[
        "Nakhon Phanom"
    ],
    "name:eng_x_preferred":[
        "Nakhon Phanom"
    ],
    "name:fas_x_preferred":[
        "\u0646\u0627\u062e\u0648\u0646 \u067e\u0627\u0646\u0648\u0645"
    ],
    "name:fra_x_preferred":[
        "Nakhon Phanom"
    ],
    "name:heb_x_preferred":[
        "\u05e0\u05d0\u05e7\u05d5\u05df \u05e4\u05d0\u05e0\u05d5\u05dd"
    ],
    "name:ita_x_preferred":[
        "Nakhon Phanom"
    ],
    "name:jpn_x_preferred":[
        "\u30ca\u30b3\u30fc\u30f3\u30d1\u30ce\u30e0"
    ],
    "name:kor_x_preferred":[
        "\ub098\ucf58\ud30c\ub188"
    ],
    "name:nld_x_preferred":[
        "Nakhon Phanom"
    ],
    "name:nob_x_preferred":[
        "Nakhon Phanom"
    ],
    "name:nor_x_preferred":[
        "Nakhon Phanom"
    ],
    "name:pnb_x_preferred":[
        "\u0646\u06a9\u06be\u0648\u0646 \u067e\u06be\u0627\u0646\u0648\u0645"
    ],
    "name:por_x_preferred":[
        "Nakhon Phanom"
    ],
    "name:rus_x_preferred":[
        "\u041d\u0430\u043a\u0445\u043e\u043d\u043f\u0445\u0430\u043d\u043e\u043c"
    ],
    "name:spa_x_preferred":[
        "Nakhon Phanom"
    ],
    "name:tha_x_preferred":[
        "\u0e19\u0e04\u0e23\u0e1e\u0e19\u0e21"
    ],
    "name:tha_x_variant":[
        "\u0e40\u0e17\u0e28\u0e1a\u0e32\u0e25\u0e40\u0e21\u0e37\u0e2d\u0e07\u0e19\u0e04\u0e23\u0e1e\u0e19\u0e21"
    ],
    "name:und_x_variant":[
        "Ban Nakhon Phnom"
    ],
    "name:vie_x_preferred":[
        "Nakhon Phanom"
    ],
    "name:war_x_preferred":[
        "Nakhon Phanom"
    ],
    "name:zho_x_preferred":[
        "\u90a3\u7a7a\u62cd\u5102"
    ],
    "qs_pg:aaroncc":"TH",
    "qs_pg:gn_country":"TH",
    "qs_pg:gn_fcode":"PPLA",
    "qs_pg:gn_pop":34595,
    "qs_pg:name":"Nakhon Phanom",
    "qs_pg:name_adm0":"Thailand",
    "qs_pg:name_adm1":"Nakhon Phanom",
    "qs_pg:photos_9k":1,
    "qs_pg:photos_9r":1,
    "qs_pg:photos_all":1,
    "qs_pg:photos_sr":0,
    "qs_pg:pop_sr":8,
    "qs_pg:qs_pg_placetype":"locality",
    "qs_pg:qs_pg_placetype_gp":"Town",
    "qs_pg:woe_adm0":23424960,
    "woe:adm0_id":23424960,
    "woe:name_adm0":"Thailand",
    "woe:name_adm1":"Nakhon Phanom",
    "woe:placetype":"Town",
    "wof:lang_x_official":[
        "tha"
    ],
    "wof:lang_x_spoken":[
        "tha"
    ],
    "wof:name":"Nakhon Phanom",
    "wof:placetype":"locality",
    "wof:population":34595
},
  "geometry": {"coordinates":[104.77856,17.41081],"type":"Point"}
}