{
  "type": "Feature",
  "properties": {
    "gn:admin1_code":"1.0",
    "gn:asciiname":"Ban Huai Dok Kuang",
    "gn:country_code":"TH",
    "gn:dem":1002,
    "gn:feature_class":"P",
    "gn:feature_code":"PPL",
    "gn:name":"Ban Huai Dok Kuang",
    "gn:population":0,
    "gn:timezone":"Asia/Bangkok",
    "iso:country":"TH",
    "name:tha_x_preferred":[
        "\u0e1a\u0e49\u0e32\u0e19\u0e2b\u0e49\u0e27\u0e22\u0e14\u0e2d\u0e01\u0e01\u0e27\u0e07"
    ],
    "wof:name":"Ban Huai Dok Kuang",
    "wof:placetype":"locality"
},
  "geometry": {"coordinates":[98.02261,18.08908],"type":"Point"}
}