{
  "type": "Feature",
  "properties": {
    "gn:admin1_code":"48.0",
    "gn:asciiname":"Ban Khlong Khrok",
    "gn:country_code":"TH",
    "gn:dem":73,
    "gn:feature_class":"P",
    "gn:feature_code":"PPL",
    "gn:name":"Ban Khlong Khrok",
    "gn:population":0,
    "gn:timezone":"Asia/Bangkok",
    "iso:country":"TH",
    "name:tha_x_preferred":[
        "\u0e1a\u0e49\u0e32\u0e19\u0e04\u0e25\u0e2d\u0e07\u0e04\u0e23\u0e01"
    ],
    "wof:name":"Ban Khlong Khrok",
    "wof:placetype":"locality"
},
  "geometry": {"coordinates":[101.81647,13.10817],"type":"Point"}
}