{
  "type": "Feature",
  "properties": {
    "gn:admin1_code":"68.0",
    "gn:asciiname":"Ban Plak Chamao Nuea",
    "gn:country_code":"TH",
    "gn:dem":24,
    "gn:feature_class":"P",
    "gn:feature_code":"PPL",
    "gn:name":"Ban Plak Chamao Nuea",
    "gn:population":0,
    "gn:timezone":"Asia/Bangkok",
    "iso:country":"TH",
    "name:tha_x_preferred":[
        "\u0e1a\u0e49\u0e32\u0e19\u0e1b\u0e25\u0e31\u0e01\u0e0a\u0e30\u0e40\u0e21\u0e32\u0e40\u0e2b\u0e19\u0e37\u0e2d"
    ],
    "wof:name":"Ban Plak Chamao Nuea",
    "wof:placetype":"locality"
},
  "geometry": {"coordinates":[100.70144999999999,6.75783],"type":"Point"}
}