{
  "type": "Feature",
  "properties": {
    "gn:admin1_code":"6.0",
    "gn:asciiname":"Ban Pong Pradu",
    "gn:country_code":"TH",
    "gn:dem":273,
    "gn:feature_class":"P",
    "gn:feature_code":"PPL",
    "gn:name":"Ban Pong Pradu",
    "gn:population":0,
    "gn:timezone":"Asia/Bangkok",
    "iso:country":"TH",
    "name:tha_x_preferred":[
        "\u0e1a\u0e49\u0e32\u0e19\u0e42\u0e1b\u0e48\u0e07\u0e1b\u0e23\u0e30\u0e14\u0e39\u0e48"
    ],
    "wof:name":"Ban Pong Pradu",
    "wof:placetype":"locality"
},
  "geometry": {"coordinates":[99.19564,18.10217],"type":"Point"}
}