{
  "type": "Feature",
  "properties": {
    "gn:admin1_code":"49.0",
    "gn:asciiname":"Ban Tak Waeng",
    "gn:country_code":"TH",
    "gn:dem":45,
    "gn:feature_class":"P",
    "gn:feature_code":"PPL",
    "gn:name":"Ban Tak Waeng",
    "gn:population":0,
    "gn:timezone":"Asia/Bangkok",
    "iso:country":"TH",
    "name:tha_x_preferred":[
        "\u0e1a\u0e49\u0e32\u0e19\u0e15\u0e32\u0e01\u0e41\u0e27\u0e49\u0e07"
    ],
    "name:und_x_variant":[
        "Tak Waeng",
        "Ban Tak Waeng"
    ],
    "wof:name":"Ban Tak Waeng",
    "wof:placetype":"locality"
},
  "geometry": {"coordinates":[102.55722,12.49125],"type":"Point"}
}