{
  "type": "Feature",
  "properties": {
    "gn:admin1_code":"4.0",
    "gn:asciiname":"Ban Thin Phu Dinso",
    "gn:country_code":"TH",
    "gn:dem":848,
    "gn:feature_class":"P",
    "gn:feature_code":"PPL",
    "gn:name":"Ban Thin Phu Dinso",
    "gn:population":0,
    "gn:timezone":"Asia/Bangkok",
    "iso:country":"TH",
    "wof:lang_x_official":[
        "tha"
    ],
    "wof:lang_x_spoken":[
        "tha"
    ],
    "wof:name":"Ban Thin Phu Dinso",
    "wof:placetype":"locality"
},
  "geometry": {"coordinates":[100.96666999999999,19.46667],"type":"Point"}
}