{
  "type": "Feature",
  "properties": {
    "gn:admin1_code":"13.0",
    "gn:asciiname":"Ban Bueng Wat Pa",
    "gn:country_code":"TH",
    "gn:dem":32,
    "gn:feature_class":"P",
    "gn:feature_code":"PPL",
    "gn:name":"Ban Bueng Wat Pa",
    "gn:population":0,
    "gn:timezone":"Asia/Bangkok",
    "iso:country":"TH",
    "name:tha_x_preferred":[
        "\u0e1a\u0e49\u0e32\u0e19\u0e1a\u0e36\u0e07\u0e27\u0e31\u0e14\u0e1b\u0e48\u0e32"
    ],
    "wof:name":"Ban Bueng Wat Pa",
    "wof:placetype":"locality"
},
  "geometry": {"coordinates":[100.28203000000001,15.96242],"type":"Point"}
}