{
  "type": "Feature",
  "properties": {
    "gn:admin1_code":"15.0",
    "gn:asciiname":"Ban Khao Nam Chon",
    "gn:country_code":"TH",
    "gn:dem":102,
    "gn:feature_class":"P",
    "gn:feature_code":"PPL",
    "gn:name":"Ban Khao Nam Chon",
    "gn:population":0,
    "gn:timezone":"Asia/Bangkok",
    "iso:country":"TH",
    "name:tha_x_preferred":[
        "\u0e1a\u0e49\u0e32\u0e19\u0e40\u0e02\u0e32\u0e19\u0e49\u0e33\u0e42\u0e08\u0e19"
    ],
    "wof:name":"Ban Khao Nam Chon",
    "wof:placetype":"locality"
},
  "geometry": {"coordinates":[99.58711,15.40314],"type":"Point"}
}