{
  "type": "Feature",
  "properties": {
    "gn:admin1_code":"44.0",
    "gn:asciiname":"Ban Khlong Yi Sip Et",
    "gn:country_code":"TH",
    "gn:dem":5,
    "gn:feature_class":"P",
    "gn:feature_code":"PPL",
    "gn:name":"Ban Khlong Yi Sip Et",
    "gn:population":0,
    "gn:timezone":"Asia/Bangkok",
    "iso:country":"TH",
    "name:tha_x_preferred":[
        "\u0e1a\u0e49\u0e32\u0e19\u0e04\u0e25\u0e2d\u0e07\u0e22\u0e35\u0e48\u0e2a\u0e34\u0e1a\u0e40\u0e2d\u0e47\u0e14"
    ],
    "wof:name":"Ban Khlong Yi Sip Et",
    "wof:placetype":"locality"
},
  "geometry": {"coordinates":[100.99469000000001,13.94186],"type":"Point"}
}