{
  "type": "Feature",
  "properties": {
    "gn:admin1_code":"46.0",
    "gn:asciiname":"Ban Khlong Khleng",
    "gn:country_code":"TH",
    "gn:dem":51,
    "gn:feature_class":"P",
    "gn:feature_code":"PPL",
    "gn:name":"Ban Khlong Khleng",
    "gn:population":0,
    "gn:timezone":"Asia/Bangkok",
    "iso:country":"TH",
    "name:tha_x_preferred":[
        "\u0e1a\u0e49\u0e32\u0e19\u0e42\u0e04\u0e25\u0e07\u0e40\u0e04\u0e25\u0e07"
    ],
    "name:und_x_variant":[
        "Khlong Khleng",
        "Ban Khlong Khleng"
    ],
    "wof:name":"Ban Khlong Khleng",
    "wof:placetype":"locality"
},
  "geometry": {"coordinates":[101.23157999999999,13.25667],"type":"Point"}
}