{
  "type": "Feature",
  "properties": {
    "gn:admin1_code":"65.0",
    "gn:asciiname":"Ban Bin Yi",
    "gn:country_code":"TH",
    "gn:dem":9,
    "gn:feature_class":"P",
    "gn:feature_code":"PPL",
    "gn:name":"Ban Bin Yi",
    "gn:population":0,
    "gn:timezone":"Asia/Bangkok",
    "iso:country":"TH",
    "name:tha_x_preferred":[
        "\u0e1a\u0e49\u0e32\u0e19\u0e1a\u0e34\u0e19\u0e2b\u0e22\u0e35"
    ],
    "wof:name":"Ban Bin Yi",
    "wof:placetype":"locality"
},
  "geometry": {"coordinates":[99.54612,7.50177],"type":"Point"}
}