{
  "type": "Feature",
  "properties": {
    "gn:admin1_code":"13.0",
    "gn:asciiname":"Ban Dong Khan Thaeo",
    "gn:country_code":"TH",
    "gn:dem":61,
    "gn:feature_class":"P",
    "gn:feature_code":"PPL",
    "gn:name":"Ban Dong Khan Thaeo",
    "gn:population":0,
    "gn:timezone":"Asia/Bangkok",
    "iso:country":"TH",
    "name:tha_x_preferred":[
        "\u0e1a\u0e49\u0e32\u0e19\u0e14\u0e07\u0e04\u0e31\u0e19\u0e41\u0e17\u0e27"
    ],
    "wof:name":"Ban Dong Khan Thaeo",
    "wof:placetype":"locality"
},
  "geometry": {"coordinates":[100.61111,16.33978],"type":"Point"}
}