{
  "type": "Feature",
  "properties": {
    "gn:admin1_code":"40.0",
    "gn:admin2_code":"1003",
    "gn:asciiname":"Ban Lam Pha-Ong",
    "gn:country_code":"TH",
    "gn:dem":4,
    "gn:feature_class":"P",
    "gn:feature_code":"PPL",
    "gn:name":"Ban Lam Pha-Ong",
    "gn:population":0,
    "gn:timezone":"Asia/Bangkok",
    "iso:country":"TH",
    "name:tha_x_preferred":[
        "\u0e1a\u0e49\u0e32\u0e19\u0e25\u0e33\u0e1e\u0e30\u0e2d\u0e07"
    ],
    "name:und_x_variant":[
        "Ban Lamphong",
        "Ban Lam Pha-Ong"
    ],
    "wof:name":"Ban Lam Pha-Ong",
    "wof:placetype":"locality"
},
  "geometry": {"coordinates":[100.82966999999999,13.785],"type":"Point"}
}