{
  "type": "Feature",
  "properties": {
    "gn:admin1_code":"2.0",
    "gn:asciiname":"Ban Huai Rin",
    "gn:country_code":"TH",
    "gn:dem":499,
    "gn:feature_class":"P",
    "gn:feature_code":"PPL",
    "gn:name":"Ban Huai Rin",
    "gn:population":0,
    "gn:timezone":"Asia/Bangkok",
    "iso:country":"TH",
    "name:tha_x_preferred":[
        "\u0e1a\u0e49\u0e32\u0e19\u0e2b\u0e49\u0e27\u0e22\u0e23\u0e34\u0e19"
    ],
    "wof:name":"Ban Huai Rin",
    "wof:placetype":"locality"
},
  "geometry": {"coordinates":[98.38467,18.50194],"type":"Point"}
}