{
  "type": "Feature",
  "properties": {
    "gn:admin1_code":"28",
    "gn:asciiname":"Ban Sa Prakham",
    "gn:country_code":"TH",
    "gn:dem":167,
    "gn:feature_class":"P",
    "gn:feature_code":"PPL",
    "gn:name":"Ban Sa Prakham",
    "gn:population":0,
    "gn:timezone":"Asia/Bangkok",
    "iso:country":"TH",
    "name:tha_x_preferred":[
        "\u0e1a\u0e49\u0e32\u0e19\u0e2a\u0e23\u0e30\u0e1b\u0e23\u0e30\u0e04\u0e33"
    ],
    "wof:name":"Ban Sa Prakham",
    "wof:placetype":"locality"
},
  "geometry": {"coordinates":[103.0535,15.20381],"type":"Point"}
}