{
  "type": "Feature",
  "properties": {
    "gn:admin1_code":"41.0",
    "gn:asciiname":"Ban Rong Phai Tai",
    "gn:country_code":"TH",
    "gn:dem":399,
    "gn:feature_class":"P",
    "gn:feature_code":"PPL",
    "gn:name":"Ban Rong Phai Tai",
    "gn:population":0,
    "gn:timezone":"Asia/Bangkok",
    "iso:country":"TH",
    "name:tha_x_preferred":[
        "\u0e1a\u0e49\u0e32\u0e19\u0e23\u0e48\u0e2d\u0e07\u0e44\u0e1c\u0e48\u0e43\u0e15\u0e49"
    ],
    "wof:name":"Ban Rong Phai Tai",
    "wof:placetype":"locality"
},
  "geometry": {"coordinates":[99.84225000000001,19.20711],"type":"Point"}
}