{
  "type": "Feature",
  "properties": {
    "gn:admin1_code":"2.0",
    "gn:asciiname":"Ban Huai Din Mo",
    "gn:country_code":"TH",
    "gn:dem":446,
    "gn:feature_class":"P",
    "gn:feature_code":"PPL",
    "gn:name":"Ban Huai Din Mo",
    "gn:population":0,
    "gn:timezone":"Asia/Bangkok",
    "iso:country":"TH",
    "name:tha_x_preferred":[
        "\u0e1a\u0e49\u0e32\u0e19\u0e2b\u0e49\u0e27\u0e22\u0e14\u0e34\u0e19\u0e2b\u0e21\u0e49\u0e2d"
    ],
    "wof:name":"Ban Huai Din Mo",
    "wof:placetype":"locality"
},
  "geometry": {"coordinates":[98.45431000000001,17.38839],"type":"Point"}
}