{
  "type": "Feature",
  "properties": {
    "gn:admin1_code":"31.0",
    "gn:asciiname":"Ban Ai Kue Lo",
    "gn:country_code":"TH",
    "gn:dem":60,
    "gn:feature_class":"P",
    "gn:feature_code":"PPL",
    "gn:name":"Ban Ai Kue Lo",
    "gn:population":0,
    "gn:timezone":"Asia/Bangkok",
    "iso:country":"TH",
    "name:tha_x_preferred":[
        "\u0e1a\u0e49\u0e32\u0e19\u0e44\u0e2d\u0e23\u0e4c\u0e01\u0e37\u0e2d\u0e42\u0e25\u0e4a\u0e30"
    ],
    "wof:name":"Ban Ai Kue Lo",
    "wof:placetype":"locality"
},
  "geometry": {"coordinates":[101.46081,6.23575],"type":"Point"}
}