{
  "type": "Feature",
  "properties": {
    "gn:admin1_code":"14.0",
    "gn:asciiname":"Ban Nam Chao",
    "gn:cc2":"TH",
    "gn:country_code":"TH",
    "gn:dem":246,
    "gn:feature_class":"P",
    "gn:feature_code":"PPL",
    "gn:name":"Ban Nam Chao",
    "gn:population":0,
    "gn:timezone":"Asia/Bangkok",
    "iso:country":"TH",
    "name:und_x_variant":[
        "B\u0101n Nam J\u0101o",
        "Ban Nam Chao"
    ],
    "wof:name":"Ban Nam Chao",
    "wof:placetype":"locality"
},
  "geometry": {"coordinates":[101.28333000000001,17.05],"type":"Point"}
}