{
  "type": "Feature",
  "properties": {
    "gn:admin1_code":"2.0",
    "gn:asciiname":"Ban Thong Fai",
    "gn:country_code":"TH",
    "gn:dem":480,
    "gn:feature_class":"P",
    "gn:feature_code":"PPL",
    "gn:name":"Ban Thong Fai",
    "gn:population":0,
    "gn:timezone":"Asia/Bangkok",
    "iso:country":"TH",
    "name:tha_x_preferred":[
        "\u0e1a\u0e49\u0e32\u0e19\u0e17\u0e49\u0e2d\u0e07\u0e1d\u0e32\u0e22"
    ],
    "name:und_x_variant":[
        "B\u0101n Thaung F\u0101i",
        "Ban Thong Fai"
    ],
    "wof:name":"Ban Thong Fai",
    "wof:placetype":"locality"
},
  "geometry": {"coordinates":[98.36311000000001,18.49131],"type":"Point"}
}