{
  "type": "Feature",
  "properties": {
    "gn:admin1_code":"64.0",
    "gn:asciiname":"Ban Thung Kruat",
    "gn:country_code":"TH",
    "gn:dem":33,
    "gn:feature_class":"P",
    "gn:feature_code":"PPL",
    "gn:name":"Ban Thung Kruat",
    "gn:population":0,
    "gn:timezone":"Asia/Bangkok",
    "iso:country":"TH",
    "name:tha_x_preferred":[
        "\u0e1a\u0e49\u0e32\u0e19\u0e17\u0e38\u0e48\u0e07\u0e01\u0e23\u0e27\u0e14"
    ],
    "wof:name":"Ban Thung Kruat",
    "wof:placetype":"locality"
},
  "geometry": {"coordinates":[99.31332999999999,8.35358],"type":"Point"}
}