{
  "type": "Feature",
  "properties": {
    "gn:admin1_code":"59.0",
    "gn:asciiname":"Ban Lang Phuttha Raksa",
    "gn:country_code":"TH",
    "gn:dem":12,
    "gn:feature_class":"P",
    "gn:feature_code":"PPL",
    "gn:name":"Ban Lang Phuttha Raksa",
    "gn:population":0,
    "gn:timezone":"Asia/Bangkok",
    "iso:country":"TH",
    "name:tha_x_preferred":[
        "\u0e1a\u0e49\u0e32\u0e19\u0e25\u0e48\u0e32\u0e07\u0e1e\u0e38\u0e17\u0e18\u0e23\u0e31\u0e01\u0e29\u0e32"
    ],
    "wof:lang_x_official":[
        "tha"
    ],
    "wof:lang_x_spoken":[
        "tha"
    ],
    "wof:name":"Ban Lang Phuttha Raksa",
    "wof:placetype":"locality"
},
  "geometry": {"coordinates":[98.75903,10.11194],"type":"Point"}
}