{
  "type": "Feature",
  "properties": {
    "gn:admin1_code":"6.0",
    "gn:asciiname":"Ban Don Kaeo",
    "gn:country_code":"TH",
    "gn:dem":167,
    "gn:feature_class":"P",
    "gn:feature_code":"PPL",
    "gn:name":"Ban Don Kaeo",
    "gn:population":0,
    "gn:timezone":"Asia/Bangkok",
    "iso:country":"TH",
    "name:tha_x_preferred":[
        "\u0e1a\u0e49\u0e32\u0e19\u0e14\u0e2d\u0e19\u0e41\u0e01\u0e49\u0e27"
    ],
    "wof:name":"Ban Don Kaeo",
    "wof:placetype":"locality"
},
  "geometry": {"coordinates":[99.19289000000001,17.57772000000001],"type":"Point"}
}