{
  "type": "Feature",
  "properties": {
    "gn:admin1_code":"47.0",
    "gn:asciiname":"Ban Krasae Bon",
    "gn:country_code":"TH",
    "gn:dem":17,
    "gn:feature_class":"P",
    "gn:feature_code":"PPL",
    "gn:name":"Ban Krasae Bon",
    "gn:population":0,
    "gn:timezone":"Asia/Bangkok",
    "iso:country":"TH",
    "name:tha_x_preferred":[
        "\u0e1a\u0e49\u0e32\u0e19\u0e01\u0e23\u0e30\u0e41\u0e2a\u0e1a\u0e19"
    ],
    "name:und_x_variant":[
        "Ban Prasae",
        "Prasae",
        "Ban Krasae Bon"
    ],
    "wof:name":"Ban Krasae Bon",
    "wof:placetype":"locality"
},
  "geometry": {"coordinates":[101.6275,12.83194],"type":"Point"}
}