{
  "type": "Feature",
  "properties": {
    "gn:admin1_code":"23.0",
    "gn:asciiname":"Ban Kae Pe",
    "gn:country_code":"TH",
    "gn:dem":148,
    "gn:feature_class":"P",
    "gn:feature_code":"PPL",
    "gn:name":"Ban Kae Pe",
    "gn:population":0,
    "gn:timezone":"Asia/Bangkok",
    "iso:country":"TH",
    "name:tha_x_preferred":[
        "\u0e1a\u0e49\u0e32\u0e19\u0e41\u0e01\u0e40\u0e1b\u0e30"
    ],
    "wof:name":"Ban Kae Pe",
    "wof:placetype":"locality"
},
  "geometry": {"coordinates":[103.64400000000001,16.3985],"type":"Point"}
}