{
  "type": "Feature",
  "properties": {
    "gn:admin1_code":"27",
    "gn:asciiname":"Ban Non Sombun",
    "gn:country_code":"TH",
    "gn:dem":254,
    "gn:feature_class":"P",
    "gn:feature_code":"PPL",
    "gn:name":"Ban Non Sombun",
    "gn:population":0,
    "gn:timezone":"Asia/Bangkok",
    "iso:country":"TH",
    "name:tha_x_preferred":[
        "\u0e1a\u0e49\u0e32\u0e19\u0e42\u0e19\u0e19\u0e2a\u0e21\u0e1a\u0e39\u0e23\u0e13\u0e4c"
    ],
    "wof:name":"Ban Non Sombun",
    "wof:placetype":"locality"
},
  "geometry": {"coordinates":[101.81574999999999,14.65586],"type":"Point"}
}