{
  "type": "Feature",
  "properties": {
    "gn:admin1_code":"39.0",
    "gn:asciiname":"Ban Khlong Ban Krachae",
    "gn:country_code":"TH",
    "gn:dem":6,
    "gn:feature_class":"P",
    "gn:feature_code":"PPL",
    "gn:name":"Ban Khlong Ban Krachae",
    "gn:population":0,
    "gn:timezone":"Asia/Bangkok",
    "iso:country":"TH",
    "name:tha_x_preferred":[
        "Ban Khlong Ban Krachae"
    ],
    "name:tha_x_variant":[
        "\u0e1a\u0e49\u0e32\u0e19\u0e04\u0e25\u0e2d\u0e07\u0e1a\u0e49\u0e32\u0e19\u0e01\u0e23\u0e30\u0e41\u0e0a\u0e30"
    ],
    "wof:name":"Ban Khlong Ban Krachae",
    "wof:placetype":"locality"
},
  "geometry": {"coordinates":[100.55672,14.04178],"type":"Point"}
}