{
  "type": "Feature",
  "properties": {
    "gn:admin1_code":"68.0",
    "gn:asciiname":"Ban Pak Bang Sakom",
    "gn:country_code":"TH",
    "gn:dem":8,
    "gn:feature_class":"P",
    "gn:feature_code":"PPL",
    "gn:name":"Ban Pak Bang Sakom",
    "gn:population":0,
    "gn:timezone":"Asia/Bangkok",
    "iso:country":"TH",
    "name:tha_x_preferred":[
        "\u0e1a\u0e49\u0e32\u0e19\u0e1b\u0e32\u0e01\u0e1a\u0e32\u0e07\u0e2a\u0e30\u0e01\u0e2d\u0e21"
    ],
    "name:und_x_variant":[
        "Pak Nam Sakaum",
        "Pak Nam Skon",
        "Ban Pak Nam Sakom",
        "Ban Pak Bang Sakom"
    ],
    "wof:lang_x_official":[
        "tha"
    ],
    "wof:lang_x_spoken":[
        "tha"
    ],
    "wof:name":"Ban Pak Bang Sakom",
    "wof:placetype":"locality"
},
  "geometry": {"coordinates":[100.83153,6.94897],"type":"Point"}
}