{
  "type": "Feature",
  "properties": {
    "gn:admin1_code":"25.0",
    "gn:asciiname":"Ban Sam Yaek",
    "gn:country_code":"TH",
    "gn:dem":143,
    "gn:feature_class":"P",
    "gn:feature_code":"PPL",
    "gn:name":"Ban Sam Yaek",
    "gn:population":0,
    "gn:timezone":"Asia/Bangkok",
    "iso:country":"TH",
    "name:tha_x_preferred":[
        "\u0e1a\u0e49\u0e32\u0e19\u0e2a\u0e32\u0e21\u0e41\u0e22\u0e01"
    ],
    "wof:name":"Ban Sam Yaek",
    "wof:placetype":"locality"
},
  "geometry": {"coordinates":[103.68656,16.05533],"type":"Point"}
}