{
  "type": "Feature",
  "properties": {
    "gn:admin1_code":"32.0",
    "gn:asciiname":"Ban Khayai",
    "gn:country_code":"TH",
    "gn:dem":31,
    "gn:feature_class":"P",
    "gn:feature_code":"PPL",
    "gn:name":"Ban Khayai",
    "gn:population":0,
    "gn:timezone":"Asia/Bangkok",
    "iso:country":"TH",
    "name:tha_x_preferred":[
        "\u0e1a\u0e49\u0e32\u0e19\u0e02\u0e22\u0e32\u0e22"
    ],
    "name:und_x_variant":[
        "Ban Khao Khayai (1)"
    ],
    "wof:name":"Ban Khayai",
    "wof:placetype":"locality"
},
  "geometry": {"coordinates":[100.15078,15.21561],"type":"Point"}
}