{
  "type": "Feature",
  "properties": {
    "gn:admin1_code":"41.0",
    "gn:asciiname":"Ban Katthi Tai",
    "gn:country_code":"TH",
    "gn:dem":387,
    "gn:feature_class":"P",
    "gn:feature_code":"PPL",
    "gn:name":"Ban Katthi Tai",
    "gn:population":0,
    "gn:timezone":"Asia/Bangkok",
    "iso:country":"TH",
    "name:tha_x_preferred":[
        "\u0e1a\u0e49\u0e32\u0e19\u0e01\u0e32\u0e14\u0e16\u0e35\u0e43\u0e15\u0e49"
    ],
    "wof:name":"Ban Katthi Tai",
    "wof:placetype":"locality"
},
  "geometry": {"coordinates":[99.9855,19.39578],"type":"Point"}
}