{
  "type": "Feature",
  "properties": {
    "gn:admin1_code":"28",
    "gn:asciiname":"Ban Huai Samran",
    "gn:country_code":"TH",
    "gn:dem":174,
    "gn:feature_class":"P",
    "gn:feature_code":"PPL",
    "gn:name":"Ban Huai Samran",
    "gn:population":0,
    "gn:timezone":"Asia/Bangkok",
    "iso:country":"TH",
    "name:tha_x_preferred":[
        "\u0e1a\u0e49\u0e32\u0e19\u0e2b\u0e49\u0e27\u0e22\u0e2a\u0e33\u0e23\u0e32\u0e0d"
    ],
    "wof:name":"Ban Huai Samran",
    "wof:placetype":"locality"
},
  "geometry": {"coordinates":[103.01416999999999,14.56714],"type":"Point"}
}