{
  "type": "Feature",
  "properties": {
    "gn:admin1_code":"74",
    "gn:asciiname":"Ban Nong Takhian",
    "gn:country_code":"TH",
    "gn:dem":17,
    "gn:feature_class":"P",
    "gn:feature_code":"PPL",
    "gn:name":"Ban Nong Takhian",
    "gn:population":0,
    "gn:timezone":"Asia/Bangkok",
    "iso:country":"TH",
    "name:tha_x_preferred":[
        "\u0e1a\u0e49\u0e32\u0e19\u0e2b\u0e19\u0e2d\u0e07\u0e15\u0e30\u0e40\u0e04\u0e35\u0e22\u0e19"
    ],
    "wof:name":"Ban Nong Takhian",
    "wof:placetype":"locality"
},
  "geometry": {"coordinates":[101.51594,13.89367],"type":"Point"}
}