{
  "type": "Feature",
  "properties": {
    "gn:admin1_code":"47.0",
    "gn:asciiname":"Ban Wang Ta Phin",
    "gn:country_code":"TH",
    "gn:dem":73,
    "gn:feature_class":"P",
    "gn:feature_code":"PPL",
    "gn:name":"Ban Wang Ta Phin",
    "gn:population":0,
    "gn:timezone":"Asia/Bangkok",
    "iso:country":"TH",
    "name:tha_x_preferred":[
        "\u0e1a\u0e49\u0e32\u0e19\u0e27\u0e31\u0e07\u0e15\u0e32\u0e1c\u0e34\u0e19"
    ],
    "wof:name":"Ban Wang Ta Phin",
    "wof:placetype":"locality"
},
  "geometry": {"coordinates":[101.16861,12.97833],"type":"Point"}
}