{
  "type": "Feature",
  "properties": {
    "gn:admin1_code":"51.0",
    "gn:asciiname":"Ban Don Klong Ton",
    "gn:cc2":"TH",
    "gn:country_code":"TH",
    "gn:dem":9,
    "gn:feature_class":"P",
    "gn:feature_code":"PPL",
    "gn:name":"Ban Don Klong Ton",
    "gn:population":0,
    "gn:timezone":"Asia/Bangkok",
    "iso:country":"TH",
    "name:und_x_variant":[
        "Ban Don Ai Chek",
        "Ban Don Klong Ton"
    ],
    "wof:name":"Ban Don Klong Ton",
    "wof:placetype":"locality"
},
  "geometry": {"coordinates":[99.93333,14.18333],"type":"Point"}
}