{
  "type": "Feature",
  "properties": {
    "gn:admin1_code":"49.0",
    "gn:asciiname":"Ban Laem Hin",
    "gn:cc2":"TH",
    "gn:country_code":"TH",
    "gn:dem":1,
    "gn:feature_class":"P",
    "gn:feature_code":"PPL",
    "gn:name":"Ban Laem Hin",
    "gn:population":0,
    "gn:timezone":"Asia/Bangkok",
    "iso:country":"TH",
    "name:und_x_variant":[
        "Laem Hin",
        "Ban Laem Hin"
    ],
    "wof:name":"Ban Laem Hin",
    "wof:placetype":"locality"
},
  "geometry": {"coordinates":[102.55,12.16667],"type":"Point"}
}