{
  "type": "Feature",
  "properties": {
    "gn:admin1_code":"75.0",
    "gn:asciiname":"Ban Phaeng",
    "gn:country_code":"TH",
    "gn:dem":135,
    "gn:feature_class":"P",
    "gn:feature_code":"PPL",
    "gn:name":"Ban Phaeng",
    "gn:population":0,
    "gn:timezone":"Asia/Bangkok",
    "iso:country":"TH",
    "name:tha_x_preferred":[
        "\u0e1a\u0e49\u0e32\u0e19\u0e41\u0e1e\u0e07"
    ],
    "wof:name":"Ban Phaeng",
    "wof:placetype":"locality"
},
  "geometry": {"coordinates":[105.01681000000001,15.64347],"type":"Point"}
}