{
  "type": "Feature",
  "properties": {
    "gn:admin1_code":"25",
    "gn:asciiname":"Ban Prang Ku",
    "gn:country_code":"TH",
    "gn:dem":142,
    "gn:feature_class":"P",
    "gn:feature_code":"PPL",
    "gn:name":"Ban Prang Ku",
    "gn:population":0,
    "gn:timezone":"Asia/Bangkok",
    "iso:country":"TH",
    "name:tha_x_preferred":[
        "\u0e1a\u0e49\u0e32\u0e19\u0e1b\u0e23\u0e32\u0e07\u0e04\u0e4c\u0e01\u0e39\u0e48"
    ],
    "wof:name":"Ban Prang Ku",
    "wof:placetype":"locality"
},
  "geometry": {"coordinates":[103.73222,16.07367],"type":"Point"}
}