{
  "type": "Feature",
  "properties": {
    "gn:admin1_code":"60.0",
    "gn:asciiname":"Ban Wang Sila Direk San",
    "gn:country_code":"TH",
    "gn:dem":69,
    "gn:feature_class":"P",
    "gn:feature_code":"PPL",
    "gn:name":"Ban Wang Sila Direk San",
    "gn:population":0,
    "gn:timezone":"Asia/Bangkok",
    "iso:country":"TH",
    "name:tha_x_preferred":[
        "\u0e1a\u0e49\u0e32\u0e19\u0e27\u0e31\u0e07\u0e28\u0e34\u0e25\u0e32\u0e14\u0e34\u0e40\u0e23\u0e01\u0e2a\u0e32\u0e23"
    ],
    "wof:lang_x_official":[
        "tha"
    ],
    "wof:lang_x_spoken":[
        "tha"
    ],
    "wof:name":"Ban Wang Sila Direk San",
    "wof:placetype":"locality"
},
  "geometry": {"coordinates":[99.42644,8.78944],"type":"Point"}
}