{
  "type": "Feature",
  "properties": {
    "gn:admin1_code":"18.0",
    "gn:asciiname":"Ban Thin",
    "gn:country_code":"TH",
    "gn:dem":257,
    "gn:feature_class":"P",
    "gn:feature_code":"PPL",
    "gn:name":"Ban Thin",
    "gn:population":0,
    "gn:timezone":"Asia/Bangkok",
    "iso:country":"TH",
    "name:tha_x_preferred":[
        "Ban Thin"
    ],
    "name:tha_x_variant":[
        "\u0e1a\u0e49\u0e32\u0e19\u0e16\u0e34\u0e48\u0e19"
    ],
    "wof:name":"Ban Thin",
    "wof:placetype":"locality"
},
  "geometry": {"coordinates":[101.70458000000001,17.41764],"type":"Point"}
}