{
  "type": "Feature",
  "properties": {
    "gn:admin1_code":"7.0",
    "gn:asciiname":"Ban Khuang Chomphu",
    "gn:country_code":"TH",
    "gn:dem":255,
    "gn:feature_class":"P",
    "gn:feature_code":"PPL",
    "gn:name":"Ban Khuang Chomphu",
    "gn:population":0,
    "gn:timezone":"Asia/Bangkok",
    "iso:country":"TH",
    "name:tha_x_preferred":[
        "\u0e1a\u0e49\u0e32\u0e19\u0e02\u0e48\u0e27\u0e07\u0e0a\u0e21\u0e1e\u0e39"
    ],
    "name:und_x_variant":[
        "Ban Pang Champhu",
        "B\u0101n P\u0101ng Jam Phu",
        "Ban Khuang Chomphu"
    ],
    "wof:lang_x_official":[
        "tha"
    ],
    "wof:lang_x_spoken":[
        "tha"
    ],
    "wof:name":"Ban Khuang Chomphu",
    "wof:placetype":"locality"
},
  "geometry": {"coordinates":[100.20261000000001,18.57475],"type":"Point"}
}