{
  "type": "Feature",
  "properties": {
    "gn:admin1_code":"53.0",
    "gn:asciiname":"Ban Bang Ratho",
    "gn:country_code":"TH",
    "gn:dem":8,
    "gn:feature_class":"P",
    "gn:feature_code":"PPL",
    "gn:name":"Ban Bang Ratho",
    "gn:population":0,
    "gn:timezone":"Asia/Bangkok",
    "iso:country":"TH",
    "name:tha_x_preferred":[
        "\u0e1a\u0e49\u0e32\u0e19\u0e1a\u0e32\u0e07\u0e23\u0e32\u0e42\u0e17"
    ],
    "name:und_x_variant":[
        "Bang Lato",
        "Ban Bang Latho (3)",
        "Ban Bang Ratho",
        "\u0e1a\u0e49\u0e32\u0e19\u0e1a\u0e32\u0e07\u0e23\u0e32\u0e42\u0e17"
    ],
    "wof:name":"Ban Bang Ratho",
    "wof:placetype":"locality"
},
  "geometry": {"coordinates":[100.10533,13.7495],"type":"Point"}
}