{
  "type": "Feature",
  "properties": {
    "gn:admin1_code":"51.0",
    "gn:asciiname":"Ban Don Kao",
    "gn:country_code":"TH",
    "gn:dem":31,
    "gn:feature_class":"P",
    "gn:feature_code":"PPL",
    "gn:name":"Ban Don Kao",
    "gn:population":0,
    "gn:timezone":"Asia/Bangkok",
    "iso:country":"TH",
    "name:tha_x_preferred":[
        "\u0e1a\u0e49\u0e32\u0e19\u0e14\u0e2d\u0e19\u0e40\u0e01\u0e49\u0e32"
    ],
    "name:und_x_variant":[
        "Ban Don Klao"
    ],
    "wof:name":"Ban Don Kao",
    "wof:placetype":"locality"
},
  "geometry": {"coordinates":[99.91761,14.89667],"type":"Point"}
}