{
  "type": "Feature",
  "properties": {
    "gn:admin1_code":"28",
    "gn:asciiname":"Ban Noi Nong Kae",
    "gn:country_code":"TH",
    "gn:dem":191,
    "gn:feature_class":"P",
    "gn:feature_code":"PPL",
    "gn:name":"Ban Noi Nong Kae",
    "gn:population":0,
    "gn:timezone":"Asia/Bangkok",
    "iso:country":"TH",
    "name:tha_x_preferred":[
        "\u0e1a\u0e49\u0e32\u0e19\u0e19\u0e49\u0e2d\u0e22\u0e2b\u0e19\u0e2d\u0e07\u0e41\u0e01"
    ],
    "wof:name":"Ban Noi Nong Kae",
    "wof:placetype":"locality"
},
  "geometry": {"coordinates":[102.67941999999999,14.77517],"type":"Point"}
}