{
  "type": "Feature",
  "properties": {
    "gn:admin1_code":"18.0",
    "gn:asciiname":"Ban Tat Kha",
    "gn:country_code":"TH",
    "gn:dem":321,
    "gn:feature_class":"P",
    "gn:feature_code":"PPL",
    "gn:name":"Ban Tat Kha",
    "gn:population":0,
    "gn:timezone":"Asia/Bangkok",
    "iso:country":"TH",
    "wof:name":"Ban Tat Kha",
    "wof:placetype":"locality"
},
  "geometry": {"coordinates":[101.88333,17.01667],"type":"Point"}
}