{
  "type": "Feature",
  "properties": {
    "gn:admin1_code":"3.0",
    "gn:asciiname":"Ban So Nam Bung",
    "gn:country_code":"TH",
    "gn:dem":497,
    "gn:feature_class":"P",
    "gn:feature_code":"PPL",
    "gn:name":"Ban So Nam Bung",
    "gn:population":0,
    "gn:timezone":"Asia/Bangkok",
    "iso:country":"TH",
    "wof:lang_x_official":[
        "tha"
    ],
    "wof:lang_x_spoken":[
        "tha"
    ],
    "wof:name":"Ban So Nam Bung",
    "wof:placetype":"locality"
},
  "geometry": {"coordinates":[99.77361000000001,20.26222000000001],"type":"Point"}
}