{
  "type": "Feature",
  "properties": {
    "gn:admin1_code":"22",
    "gn:asciiname":"Ban Rak Chat",
    "gn:country_code":"TH",
    "gn:dem":185,
    "gn:feature_class":"P",
    "gn:feature_code":"PPL",
    "gn:name":"Ban Rak Chat",
    "gn:population":0,
    "gn:timezone":"Asia/Bangkok",
    "iso:country":"TH",
    "name:tha_x_preferred":[
        "\u0e1a\u0e49\u0e32\u0e19\u0e23\u0e31\u0e01\u0e0a\u0e32\u0e15\u0e34"
    ],
    "wof:name":"Ban Rak Chat",
    "wof:placetype":"locality"
},
  "geometry": {"coordinates":[102.93486,16.61769],"type":"Point"}
}