{
  "type": "Feature",
  "properties": {
    "gn:admin1_code":"80",
    "gn:asciiname":"Ban Tha Phrachan",
    "gn:country_code":"TH",
    "gn:dem":56,
    "gn:feature_class":"P",
    "gn:feature_code":"PPL",
    "gn:name":"Ban Tha Phrachan",
    "gn:population":0,
    "gn:timezone":"Asia/Bangkok",
    "iso:country":"TH",
    "name:tha_x_preferred":[
        "\u0e1a\u0e49\u0e32\u0e19\u0e17\u0e48\u0e32\u0e1e\u0e23\u0e30\u0e08\u0e31\u0e19\u0e17\u0e23\u0e4c"
    ],
    "wof:name":"Ban Tha Phrachan",
    "wof:placetype":"locality"
},
  "geometry": {"coordinates":[102.31228,13.87467],"type":"Point"}
}