{
  "type": "Feature",
  "properties": {
    "gn:admin1_code":"62.0",
    "gn:asciiname":"Ban Na Bon Tai",
    "gn:country_code":"TH",
    "gn:dem":7,
    "gn:feature_class":"P",
    "gn:feature_code":"PPL",
    "gn:name":"Ban Na Bon Tai",
    "gn:population":0,
    "gn:timezone":"Asia/Bangkok",
    "iso:country":"TH",
    "name:tha_x_preferred":[
        "\u0e1a\u0e49\u0e32\u0e19\u0e19\u0e32\u0e1a\u0e2d\u0e19\u0e43\u0e15\u0e49"
    ],
    "name:und_x_variant":[
        "Ban Na Bon",
        "Ban Na Bon Tai"
    ],
    "wof:name":"Ban Na Bon Tai",
    "wof:placetype":"locality"
},
  "geometry": {"coordinates":[98.38225,7.86297],"type":"Point"}
}