{
  "type": "Feature",
  "properties": {
    "gn:admin1_code":"30.0",
    "gn:asciiname":"Ban Phue Kao",
    "gn:country_code":"TH",
    "gn:dem":169,
    "gn:feature_class":"P",
    "gn:feature_code":"PPL",
    "gn:name":"Ban Phue Kao",
    "gn:population":0,
    "gn:timezone":"Asia/Bangkok",
    "iso:country":"TH",
    "name:tha_x_preferred":[
        "\u0e1a\u0e49\u0e32\u0e19\u0e1c\u0e37\u0e2d\u0e40\u0e01\u0e48\u0e32"
    ],
    "wof:name":"Ban Phue Kao",
    "wof:placetype":"locality"
},
  "geometry": {"coordinates":[104.63511,14.59895],"type":"Point"}
}