{
  "type": "Feature",
  "properties": {
    "gn:admin1_code":"24",
    "gn:asciiname":"Ban Si Phila",
    "gn:country_code":"TH",
    "gn:dem":183,
    "gn:feature_class":"P",
    "gn:feature_code":"PPL",
    "gn:name":"Ban Si Phila",
    "gn:population":0,
    "gn:timezone":"Asia/Bangkok",
    "iso:country":"TH",
    "name:tha_x_preferred":[
        "\u0e1a\u0e49\u0e32\u0e19\u0e28\u0e23\u0e35\u0e1e\u0e34\u0e25\u0e32"
    ],
    "wof:name":"Ban Si Phila",
    "wof:placetype":"locality"
},
  "geometry": {"coordinates":[103.10894,16.03453],"type":"Point"}
}