{
  "type": "Feature",
  "properties": {
    "gn:admin1_code":"34",
    "gn:asciiname":"Ban Lam Nam Khiao",
    "gn:country_code":"TH",
    "gn:dem":169,
    "gn:feature_class":"P",
    "gn:feature_code":"PPL",
    "gn:name":"Ban Lam Nam Khiao",
    "gn:population":0,
    "gn:timezone":"Asia/Bangkok",
    "iso:country":"TH",
    "name:tha_x_preferred":[
        "\u0e1a\u0e49\u0e32\u0e19\u0e25\u0e33\u0e19\u0e49\u0e33\u0e40\u0e02\u0e35\u0e22\u0e27"
    ],
    "wof:name":"Ban Lam Nam Khiao",
    "wof:placetype":"locality"
},
  "geometry": {"coordinates":[101.39624999999999,15.06647],"type":"Point"}
}