{
  "type": "Feature",
  "properties": {
    "gn:admin1_code":"16.0",
    "gn:asciiname":"Ban Pu Lamyai",
    "gn:country_code":"TH",
    "gn:dem":135,
    "gn:feature_class":"P",
    "gn:feature_code":"PPL",
    "gn:name":"Ban Pu Lamyai",
    "gn:population":0,
    "gn:timezone":"Asia/Bangkok",
    "iso:country":"TH",
    "name:tha_x_preferred":[
        "\u0e1a\u0e49\u0e32\u0e19\u0e1e\u0e38\u0e25\u0e33\u0e43\u0e22"
    ],
    "wof:name":"Ban Pu Lamyai",
    "wof:placetype":"locality"
},
  "geometry": {"coordinates":[100.58006,15.35672],"type":"Point"}
}