{
  "type": "Feature",
  "properties": {
    "gn:admin1_code":"41.0",
    "gn:asciiname":"Ban Khrai",
    "gn:country_code":"TH",
    "gn:dem":412,
    "gn:feature_class":"P",
    "gn:feature_code":"PPL",
    "gn:name":"Ban Khrai",
    "gn:population":0,
    "gn:timezone":"Asia/Bangkok",
    "iso:country":"TH",
    "name:tha_x_preferred":[
        "\u0e1a\u0e49\u0e32\u0e19\u0e44\u0e04\u0e23\u0e49"
    ],
    "name:und_x_variant":[
        "B\u0101n P\u0101ng T\u0101i",
        "Ban Pang Khai",
        "Ban Khai",
        "Ban Khrai"
    ],
    "wof:name":"Ban Khrai",
    "wof:placetype":"locality"
},
  "geometry": {"coordinates":[100.24164,19.49345],"type":"Point"}
}