{
  "type": "Feature",
  "properties": {
    "gn:admin1_code":"15.0",
    "gn:asciiname":"Ban Nong Prakhon Chai",
    "gn:country_code":"TH",
    "gn:dem":43,
    "gn:feature_class":"P",
    "gn:feature_code":"PPL",
    "gn:name":"Ban Nong Prakhon Chai",
    "gn:population":0,
    "gn:timezone":"Asia/Bangkok",
    "iso:country":"TH",
    "name:tha_x_preferred":[
        "\u0e1a\u0e49\u0e32\u0e19\u0e2b\u0e19\u0e2d\u0e07\u0e1b\u0e23\u0e30\u0e42\u0e04\u0e19\u0e0a\u0e31\u0e22"
    ],
    "wof:name":"Ban Nong Prakhon Chai",
    "wof:placetype":"locality"
},
  "geometry": {"coordinates":[99.91036,15.37989],"type":"Point"}
}