{
  "type": "Feature",
  "properties": {
    "gn:admin1_code":"70.0",
    "gn:asciiname":"Ban Ko Mo Yi Sip Kao",
    "gn:country_code":"TH",
    "gn:dem":160,
    "gn:feature_class":"P",
    "gn:feature_code":"PPL",
    "gn:name":"Ban Ko Mo Yi Sip Kao",
    "gn:population":0,
    "gn:timezone":"Asia/Bangkok",
    "iso:country":"TH",
    "name:tha_x_preferred":[
        "\u0e1a\u0e49\u0e32\u0e19 \u0e01\u0e21. \u0e22\u0e35\u0e48\u0e2a\u0e34\u0e1a\u0e40\u0e01\u0e49\u0e32"
    ],
    "name:und_x_variant":[
        "Ban Ko Mo 29",
        "Ban Ko Mo Yi Sip Kao"
    ],
    "wof:name":"Ban Ko Mo Yi Sip Kao",
    "wof:placetype":"locality"
},
  "geometry": {"coordinates":[101.18028,5.92053],"type":"Point"}
}