{
  "type": "Feature",
  "properties": {
    "gn:admin1_code":"14.0",
    "gn:asciiname":"Ban Sap Khai Ka",
    "gn:country_code":"TH",
    "gn:dem":147,
    "gn:feature_class":"P",
    "gn:feature_code":"PPL",
    "gn:name":"Ban Sap Khai Ka",
    "gn:population":0,
    "gn:timezone":"Asia/Bangkok",
    "iso:country":"TH",
    "name:tha_x_preferred":[
        "\u0e1a\u0e49\u0e32\u0e19\u0e0b\u0e31\u0e1a\u0e44\u0e02\u0e48\u0e01\u0e32"
    ],
    "wof:name":"Ban Sap Khai Ka",
    "wof:placetype":"locality"
},
  "geometry": {"coordinates":[100.90411,16.153],"type":"Point"}
}