{
  "type": "Feature",
  "properties": {
    "gn:admin1_code":"29",
    "gn:asciiname":"Ban Prasat Phum Pon",
    "gn:country_code":"TH",
    "gn:dem":189,
    "gn:feature_class":"P",
    "gn:feature_code":"PPL",
    "gn:name":"Ban Prasat Phum Pon",
    "gn:population":0,
    "gn:timezone":"Asia/Bangkok",
    "iso:country":"TH",
    "name:tha_x_preferred":[
        "\u0e1a\u0e49\u0e32\u0e19\u0e1b\u0e23\u0e32\u0e2a\u0e32\u0e17\u0e20\u0e39\u0e21\u0e34\u0e42\u0e1b\u0e19"
    ],
    "wof:name":"Ban Prasat Phum Pon",
    "wof:placetype":"locality"
},
  "geometry": {"coordinates":[103.87503,14.54861],"type":"Point"}
}