{
  "type": "Feature",
  "properties": {
    "gn:admin1_code":"18.0",
    "gn:asciiname":"Ban Non Sawang",
    "gn:country_code":"TH",
    "gn:dem":266,
    "gn:feature_class":"P",
    "gn:feature_code":"PPL",
    "gn:name":"Ban Non Sawang",
    "gn:population":0,
    "gn:timezone":"Asia/Bangkok",
    "iso:country":"TH",
    "name:tha_x_preferred":[
        "\u0e1a\u0e49\u0e32\u0e19\u0e42\u0e19\u0e19\u0e2a\u0e27\u0e48\u0e32\u0e07"
    ],
    "wof:name":"Ban Non Sawang",
    "wof:placetype":"locality"
},
  "geometry": {"coordinates":[101.77436,17.28825],"type":"Point"}
}