{
  "type": "Feature",
  "properties": {
    "gn:admin1_code":"11.0",
    "gn:asciiname":"Ban Nam Dip Maphrao",
    "gn:country_code":"TH",
    "gn:dem":123,
    "gn:feature_class":"P",
    "gn:feature_code":"PPL",
    "gn:name":"Ban Nam Dip Maphrao",
    "gn:population":0,
    "gn:timezone":"Asia/Bangkok",
    "iso:country":"TH",
    "name:tha_x_preferred":[
        "\u0e1a\u0e49\u0e32\u0e19\u0e19\u0e49\u0e33\u0e14\u0e34\u0e1a\u0e21\u0e30\u0e1e\u0e23\u0e49\u0e32\u0e27"
    ],
    "wof:name":"Ban Nam Dip Maphrao",
    "wof:placetype":"locality"
},
  "geometry": {"coordinates":[99.46925,16.80281],"type":"Point"}
}