{
  "type": "Feature",
  "properties": {
    "gn:admin1_code":"23.0",
    "gn:asciiname":"Ban Nong Lum Phuk",
    "gn:country_code":"TH",
    "gn:dem":155,
    "gn:feature_class":"P",
    "gn:feature_code":"PPL",
    "gn:name":"Ban Nong Lum Phuk",
    "gn:population":0,
    "gn:timezone":"Asia/Bangkok",
    "iso:country":"TH",
    "name:tha_x_preferred":[
        "\u0e1a\u0e49\u0e32\u0e19\u0e2b\u0e19\u0e2d\u0e07\u0e25\u0e38\u0e21\u0e1e\u0e38\u0e01"
    ],
    "wof:name":"Ban Nong Lum Phuk",
    "wof:placetype":"locality"
},
  "geometry": {"coordinates":[103.39667,16.35906],"type":"Point"}
}