{
  "type": "Feature",
  "properties": {
    "gn:admin1_code":"28.0",
    "gn:asciiname":"Ban Nong Kha Yang",
    "gn:country_code":"TH",
    "gn:dem":176,
    "gn:feature_class":"P",
    "gn:feature_code":"PPL",
    "gn:name":"Ban Nong Kha Yang",
    "gn:population":0,
    "gn:timezone":"Asia/Bangkok",
    "iso:country":"TH",
    "name:tha_x_preferred":[
        "\u0e1a\u0e49\u0e32\u0e19\u0e2b\u0e19\u0e2d\u0e07\u0e02\u0e32\u0e2b\u0e22\u0e48\u0e32\u0e07"
    ],
    "wof:name":"Ban Nong Kha Yang",
    "wof:placetype":"locality"
},
  "geometry": {"coordinates":[103.07275,14.84011],"type":"Point"}
}