{
  "type": "Feature",
  "properties": {
    "gn:admin1_code":"3.0",
    "gn:asciiname":"Ban Dong Nam Lom",
    "gn:country_code":"TH",
    "gn:dem":432,
    "gn:feature_class":"P",
    "gn:feature_code":"PPL",
    "gn:name":"Ban Dong Nam Lom",
    "gn:population":0,
    "gn:timezone":"Asia/Bangkok",
    "iso:country":"TH",
    "name:tha_x_preferred":[
        "\u0e1a\u0e49\u0e32\u0e19\u0e14\u0e07\u0e19\u0e49\u0e33\u0e25\u0e49\u0e2d\u0e21"
    ],
    "wof:name":"Ban Dong Nam Lom",
    "wof:placetype":"locality"
},
  "geometry": {"coordinates":[99.73063999999999,19.45328],"type":"Point"}
}