{
  "type": "Feature",
  "properties": {
    "gn:admin1_code":"70.0",
    "gn:asciiname":"Ban Bue Nang Chi Cha",
    "gn:country_code":"TH",
    "gn:dem":246,
    "gn:feature_class":"P",
    "gn:feature_code":"PPL",
    "gn:name":"Ban Bue Nang Chi Cha",
    "gn:population":0,
    "gn:timezone":"Asia/Bangkok",
    "iso:country":"TH",
    "name:tha_x_preferred":[
        "\u0e1a\u0e49\u0e32\u0e19\u0e1a\u0e37\u0e2d\u0e19\u0e31\u0e07\u0e08\u0e34\u0e08\u0e32"
    ],
    "wof:name":"Ban Bue Nang Chi Cha",
    "wof:placetype":"locality"
},
  "geometry": {"coordinates":[101.11228,5.75742],"type":"Point"}
}