{
  "type": "Feature",
  "properties": {
    "gn:admin1_code":"64.0",
    "gn:asciiname":"Ban Rong Kuam",
    "gn:country_code":"TH",
    "gn:dem":50,
    "gn:feature_class":"P",
    "gn:feature_code":"PPL",
    "gn:name":"Ban Rong Kuam",
    "gn:population":0,
    "gn:timezone":"Asia/Bangkok",
    "iso:country":"TH",
    "name:tha_x_preferred":[
        "\u0e1a\u0e49\u0e32\u0e19\u0e42\u0e23\u0e07\u0e01\u0e27\u0e21"
    ],
    "wof:name":"Ban Rong Kuam",
    "wof:placetype":"locality"
},
  "geometry": {"coordinates":[99.55052999999999,8.25744],"type":"Point"}
}