{
  "type": "Feature",
  "properties": {
    "gn:admin1_code":"3.0",
    "gn:asciiname":"Ban Ko Sai",
    "gn:country_code":"TH",
    "gn:dem":392,
    "gn:feature_class":"P",
    "gn:feature_code":"PPL",
    "gn:name":"Ban Ko Sai",
    "gn:population":0,
    "gn:timezone":"Asia/Bangkok",
    "iso:country":"TH",
    "name:tha_x_preferred":[
        "\u0e1a\u0e49\u0e32\u0e19\u0e40\u0e01\u0e32\u0e30\u0e17\u0e23\u0e32\u0e22"
    ],
    "wof:name":"Ban Ko Sai",
    "wof:placetype":"locality"
},
  "geometry": {"coordinates":[99.89058,20.44339],"type":"Point"}
}