{
  "type": "Feature",
  "properties": {
    "gn:admin1_code":"50.0",
    "gn:asciiname":"Ban Trai Rat",
    "gn:country_code":"TH",
    "gn:dem":148,
    "gn:feature_class":"P",
    "gn:feature_code":"PPL",
    "gn:name":"Ban Trai Rat",
    "gn:population":0,
    "gn:timezone":"Asia/Bangkok",
    "iso:country":"TH",
    "name:tha_x_preferred":[
        "\u0e1a\u0e49\u0e32\u0e19\u0e44\u0e15\u0e23\u0e23\u0e31\u0e15\u0e19\u0e4c"
    ],
    "wof:name":"Ban Trai Rat",
    "wof:placetype":"locality"
},
  "geometry": {"coordinates":[99.13808,14.16608],"type":"Point"}
}