{
  "type": "Feature",
  "properties": {
    "gn:admin1_code":"2.0",
    "gn:asciiname":"Ban Na Meng",
    "gn:country_code":"TH",
    "gn:dem":431,
    "gn:feature_class":"P",
    "gn:feature_code":"PPL",
    "gn:name":"Ban Na Meng",
    "gn:population":0,
    "gn:timezone":"Asia/Bangkok",
    "iso:country":"TH",
    "name:tha_x_preferred":[
        "\u0e1a\u0e49\u0e32\u0e19\u0e19\u0e32\u0e40\u0e21\u0e47\u0e07"
    ],
    "name:und_x_variant":[
        "Ban Na Meng (1)"
    ],
    "wof:name":"Ban Na Meng",
    "wof:placetype":"locality"
},
  "geometry": {"coordinates":[99.17894,19.1105],"type":"Point"}
}