{
  "type": "Feature",
  "properties": {
    "gn:admin1_code":"80",
    "gn:asciiname":"Ban Thung Hin Khon",
    "gn:country_code":"TH",
    "gn:dem":65,
    "gn:feature_class":"P",
    "gn:feature_code":"PPL",
    "gn:name":"Ban Thung Hin Khon",
    "gn:population":0,
    "gn:timezone":"Asia/Bangkok",
    "iso:country":"TH",
    "name:tha_x_preferred":[
        "\u0e1a\u0e49\u0e32\u0e19\u0e17\u0e38\u0e48\u0e07\u0e2b\u0e34\u0e19\u0e42\u0e04\u0e19"
    ],
    "wof:name":"Ban Thung Hin Khon",
    "wof:placetype":"locality"
},
  "geometry": {"coordinates":[101.99036,13.75644],"type":"Point"}
}