{
  "type": "Feature",
  "properties": {
    "gn:admin1_code":"68.0",
    "gn:asciiname":"Ban Khi Lek",
    "gn:country_code":"TH",
    "gn:dem":6,
    "gn:feature_class":"P",
    "gn:feature_code":"PPL",
    "gn:name":"Ban Khi Lek",
    "gn:population":0,
    "gn:timezone":"Asia/Bangkok",
    "iso:country":"TH",
    "wof:name":"Ban Khi Lek",
    "wof:placetype":"locality"
},
  "geometry": {"coordinates":[100.33333,7.78333],"type":"Point"}
}