{
  "type": "Feature",
  "properties": {
    "gn:admin1_code":"14.0",
    "gn:asciiname":"Ban Sap Dokmai Ngam",
    "gn:country_code":"TH",
    "gn:dem":113,
    "gn:feature_class":"P",
    "gn:feature_code":"PPL",
    "gn:name":"Ban Sap Dokmai Ngam",
    "gn:population":0,
    "gn:timezone":"Asia/Bangkok",
    "iso:country":"TH",
    "name:tha_x_preferred":[
        "\u0e1a\u0e49\u0e32\u0e19\u0e0b\u0e31\u0e1a\u0e14\u0e2d\u0e01\u0e44\u0e21\u0e49\u0e07\u0e32\u0e21"
    ],
    "wof:name":"Ban Sap Dokmai Ngam",
    "wof:placetype":"locality"
},
  "geometry": {"coordinates":[100.95556000000001,15.77031],"type":"Point"}
}