{
  "type": "Feature",
  "properties": {
    "gn:admin1_code":"17.0",
    "gn:asciiname":"Ban Muang Nam Phrai",
    "gn:country_code":"TH",
    "gn:dem":259,
    "gn:feature_class":"P",
    "gn:feature_code":"PPL",
    "gn:name":"Ban Muang Nam Phrai",
    "gn:population":0,
    "gn:timezone":"Asia/Bangkok",
    "iso:country":"TH",
    "name:tha_x_preferred":[
        "\u0e1a\u0e49\u0e32\u0e19\u0e21\u0e48\u0e27\u0e07\u0e19\u0e33\u0e44\u0e1e\u0e23"
    ],
    "wof:lang_x_official":[
        "tha"
    ],
    "wof:lang_x_spoken":[
        "tha"
    ],
    "wof:name":"Ban Muang Nam Phrai",
    "wof:placetype":"locality"
},
  "geometry": {"coordinates":[102.1897,18.06417],"type":"Point"}
}