{
  "type": "Feature",
  "properties": {
    "gn:admin1_code":"69.0",
    "gn:asciiname":"Ban Ku Wing",
    "gn:country_code":"TH",
    "gn:dem":10,
    "gn:feature_class":"P",
    "gn:feature_code":"PPL",
    "gn:name":"Ban Ku Wing",
    "gn:population":0,
    "gn:timezone":"Asia/Bangkok",
    "iso:country":"TH",
    "name:tha_x_preferred":[
        "\u0e1a\u0e49\u0e32\u0e19\u0e01\u0e39\u0e27\u0e34\u0e07"
    ],
    "wof:name":"Ban Ku Wing",
    "wof:placetype":"locality"
},
  "geometry": {"coordinates":[101.43899999999999,6.77],"type":"Point"}
}