{
  "type": "Feature",
  "properties": {
    "gn:admin1_code":"43.0",
    "gn:asciiname":"Ban Khok Kruat",
    "gn:cc2":"TH",
    "gn:country_code":"TH",
    "gn:dem":11,
    "gn:feature_class":"P",
    "gn:feature_code":"PPL",
    "gn:name":"Ban Khok Kruat",
    "gn:population":0,
    "gn:timezone":"Asia/Bangkok",
    "iso:country":"TH",
    "name:und_x_variant":[
        "Ban Kok Kruad",
        "Ban Khrok Kruat",
        "Ban Khok Kruat"
    ],
    "wof:name":"Ban Khok Kruat",
    "wof:placetype":"locality"
},
  "geometry": {"coordinates":[101.31667,14.18333],"type":"Point"}
}