{
  "type": "Feature",
  "properties": {
    "gn:admin1_code":"12.0",
    "gn:asciiname":"Ban Na Ka Bak",
    "gn:country_code":"TH",
    "gn:dem":401,
    "gn:feature_class":"P",
    "gn:feature_code":"PPL",
    "gn:name":"Ban Na Ka Bak",
    "gn:population":0,
    "gn:timezone":"Asia/Bangkok",
    "iso:country":"TH",
    "name:tha_x_preferred":[
        "\u0e1a\u0e49\u0e32\u0e19\u0e19\u0e32\u0e01\u0e30\u0e1a\u0e32\u0e01"
    ],
    "wof:name":"Ban Na Ka Bak",
    "wof:placetype":"locality"
},
  "geometry": {"coordinates":[100.80897,17.27158],"type":"Point"}
}