{
  "type": "Feature",
  "properties": {
    "gn:admin1_code":"14.0",
    "gn:asciiname":"Ban Rong Tabaek",
    "gn:country_code":"TH",
    "gn:dem":90,
    "gn:feature_class":"P",
    "gn:feature_code":"PPL",
    "gn:name":"Ban Rong Tabaek",
    "gn:population":0,
    "gn:timezone":"Asia/Bangkok",
    "iso:country":"TH",
    "name:tha_x_preferred":[
        "\u0e1a\u0e49\u0e32\u0e19\u0e23\u0e48\u0e2d\u0e07\u0e15\u0e30\u0e41\u0e1a\u0e01"
    ],
    "wof:name":"Ban Rong Tabaek",
    "wof:placetype":"locality"
},
  "geometry": {"coordinates":[100.71093999999999,16.30283],"type":"Point"}
}