{
  "type": "Feature",
  "properties": {
    "gn:admin1_code":"35.0",
    "gn:asciiname":"Ban Phra Ngam",
    "gn:country_code":"TH",
    "gn:dem":13,
    "gn:feature_class":"P",
    "gn:feature_code":"PPL",
    "gn:name":"Ban Phra Ngam",
    "gn:population":0,
    "gn:timezone":"Asia/Bangkok",
    "iso:country":"TH",
    "name:tha_x_preferred":[
        "\u0e1a\u0e49\u0e32\u0e19\u0e1e\u0e23\u0e30\u0e07\u0e32\u0e21"
    ],
    "name:und_x_variant":[
        "Ban Pra Ngam",
        "Ban Phra Ngam",
        "Ban Phra Ngam Tok"
    ],
    "wof:lang_x_official":[
        "tha"
    ],
    "wof:lang_x_spoken":[
        "tha"
    ],
    "wof:name":"Ban Phra Ngam",
    "wof:placetype":"locality"
},
  "geometry": {"coordinates":[100.41672,14.74589],"type":"Point"}
}