{
  "type": "Feature",
  "properties": {
    "gn:admin1_code":"68.0",
    "gn:asciiname":"Ban Lum Samet",
    "gn:country_code":"TH",
    "gn:dem":48,
    "gn:feature_class":"P",
    "gn:feature_code":"PPL",
    "gn:name":"Ban Lum Samet",
    "gn:population":0,
    "gn:timezone":"Asia/Bangkok",
    "iso:country":"TH",
    "name:tha_x_preferred":[
        "\u0e1a\u0e49\u0e32\u0e19\u0e25\u0e38\u0e48\u0e21\u0e40\u0e2a\u0e21\u0e47\u0e14"
    ],
    "wof:name":"Ban Lum Samet",
    "wof:placetype":"locality"
},
  "geometry": {"coordinates":[100.589,6.97583],"type":"Point"}
}