{
  "type": "Feature",
  "properties": {
    "gn:admin1_code":"61.0",
    "gn:asciiname":"Ban Ao We",
    "gn:country_code":"TH",
    "gn:dem":16,
    "gn:feature_class":"P",
    "gn:feature_code":"PPL",
    "gn:name":"Ban Ao We",
    "gn:population":0,
    "gn:timezone":"Asia/Bangkok",
    "iso:country":"TH",
    "name:tha_x_preferred":[
        "\u0e1a\u0e49\u0e32\u0e19\u0e2d\u0e48\u0e32\u0e27\u0e40\u0e27\u0e30"
    ],
    "name:und_x_variant":[
        "Ban Ao Ek",
        "Ban Au Ek",
        "Ban Ao We"
    ],
    "wof:name":"Ban Ao We",
    "wof:placetype":"locality"
},
  "geometry": {"coordinates":[98.34492,9.02428],"type":"Point"}
}