{
  "type": "Feature",
  "properties": {
    "gn:admin1_code":"6.0",
    "gn:asciiname":"Ban To",
    "gn:country_code":"TH",
    "gn:dem":229,
    "gn:feature_class":"P",
    "gn:feature_code":"PPL",
    "gn:name":"Ban To",
    "gn:population":0,
    "gn:timezone":"Asia/Bangkok",
    "iso:country":"TH",
    "name:tha_x_preferred":[
        "\u0e1a\u0e49\u0e32\u0e19\u0e15\u0e4b\u0e2d"
    ],
    "name:und_x_variant":[
        "B\u0101n Tau",
        "Ban To"
    ],
    "wof:name":"Ban To",
    "wof:placetype":"locality"
},
  "geometry": {"coordinates":[99.43297,18.13883],"type":"Point"}
}