{
  "type": "Feature",
  "properties": {
    "gn:admin1_code":"4.0",
    "gn:asciiname":"Ban Pha Khwang",
    "gn:country_code":"TH",
    "gn:dem":229,
    "gn:feature_class":"P",
    "gn:feature_code":"PPL",
    "gn:name":"Ban Pha Khwang",
    "gn:population":0,
    "gn:timezone":"Asia/Bangkok",
    "iso:country":"TH",
    "name:tha_x_preferred":[
        "\u0e1a\u0e49\u0e32\u0e19\u0e1c\u0e32\u0e02\u0e27\u0e32\u0e07"
    ],
    "wof:name":"Ban Pha Khwang",
    "wof:placetype":"locality"
},
  "geometry": {"coordinates":[100.785,19.00703],"type":"Point"}
}