{
  "type": "Feature",
  "properties": {
    "gn:admin1_code":"69.0",
    "gn:asciiname":"Ban Pa Lu Ka Lu Wa",
    "gn:country_code":"TH",
    "gn:dem":38,
    "gn:feature_class":"P",
    "gn:feature_code":"PPL",
    "gn:name":"Ban Pa Lu Ka Lu Wa",
    "gn:population":0,
    "gn:timezone":"Asia/Bangkok",
    "iso:country":"TH",
    "wof:name":"Ban Pa Lu Ka Lu Wa",
    "wof:placetype":"locality"
},
  "geometry": {"coordinates":[101.40000000000001,6.61667],"type":"Point"}
}