{
  "type": "Feature",
  "properties": {
    "gn:admin1_code":"60.0",
    "gn:asciiname":"Ban Chong Mai Ngam",
    "gn:country_code":"TH",
    "gn:dem":24,
    "gn:feature_class":"P",
    "gn:feature_code":"PPL",
    "gn:name":"Ban Chong Mai Ngam",
    "gn:population":0,
    "gn:timezone":"Asia/Bangkok",
    "iso:country":"TH",
    "name:tha_x_preferred":[
        "\u0e1a\u0e49\u0e32\u0e19\u0e0a\u0e48\u0e2d\u0e07\u0e44\u0e21\u0e49\u0e07\u0e32\u0e21"
    ],
    "wof:name":"Ban Chong Mai Ngam",
    "wof:placetype":"locality"
},
  "geometry": {"coordinates":[98.91542,8.92717],"type":"Point"}
}