{
  "type": "Feature",
  "properties": {
    "gn:admin1_code":"58.0",
    "gn:asciiname":"Ban Klo Phai",
    "gn:country_code":"TH",
    "gn:dem":74,
    "gn:feature_class":"P",
    "gn:feature_code":"PPL",
    "gn:name":"Ban Klo Phai",
    "gn:population":0,
    "gn:timezone":"Asia/Bangkok",
    "iso:country":"TH",
    "name:tha_x_preferred":[
        "\u0e1a\u0e49\u0e32\u0e19\u0e01\u0e25\u0e2d\u0e44\u0e1c\u0e48"
    ],
    "wof:name":"Ban Klo Phai",
    "wof:placetype":"locality"
},
  "geometry": {"coordinates":[99.37092,10.77567],"type":"Point"}
}