{
  "type": "Feature",
  "properties": {
    "gn:admin1_code":"37.0",
    "gn:asciiname":"Ban Bua Yai Phae",
    "gn:country_code":"TH",
    "gn:dem":6,
    "gn:feature_class":"P",
    "gn:feature_code":"PPL",
    "gn:name":"Ban Bua Yai Phae",
    "gn:population":0,
    "gn:timezone":"Asia/Bangkok",
    "iso:country":"TH",
    "name:tha_x_preferred":[
        "Ban Bua Yai Phae"
    ],
    "wof:name":"Ban Bua Yai Phae",
    "wof:placetype":"locality"
},
  "geometry": {"coordinates":[100.90000000000001,14.28333],"type":"Point"}
}