{
  "type": "Feature",
  "properties": {
    "gn:admin1_code":"17.0",
    "gn:asciiname":"Ban Charoen Suk",
    "gn:country_code":"TH",
    "gn:dem":171,
    "gn:feature_class":"P",
    "gn:feature_code":"PPL",
    "gn:name":"Ban Charoen Suk",
    "gn:population":0,
    "gn:timezone":"Asia/Bangkok",
    "iso:country":"TH",
    "name:tha_x_preferred":[
        "\u0e1a\u0e49\u0e32\u0e19\u0e40\u0e08\u0e23\u0e34\u0e0d\u0e2a\u0e38\u0e02"
    ],
    "wof:name":"Ban Charoen Suk",
    "wof:placetype":"locality"
},
  "geometry": {"coordinates":[102.84846,17.96238],"type":"Point"}
}