{
  "type": "Feature",
  "properties": {
    "gn:admin1_code":"56.0",
    "gn:asciiname":"Ban Nong Chang Yiap",
    "gn:country_code":"TH",
    "gn:dem":69,
    "gn:feature_class":"P",
    "gn:feature_code":"PPL",
    "gn:name":"Ban Nong Chang Yiap",
    "gn:population":0,
    "gn:timezone":"Asia/Bangkok",
    "iso:country":"TH",
    "name:tha_x_preferred":[
        "\u0e1a\u0e49\u0e32\u0e19\u0e2b\u0e19\u0e2d\u0e07\u0e0a\u0e49\u0e32\u0e07\u0e40\u0e2b\u0e22\u0e35\u0e22\u0e1a"
    ],
    "wof:name":"Ban Nong Chang Yiap",
    "wof:placetype":"locality"
},
  "geometry": {"coordinates":[99.80847,12.63311],"type":"Point"}
}