{
  "type": "Feature",
  "properties": {
    "gn:admin1_code":"53.0",
    "gn:asciiname":"Ban Rang Sangkasi",
    "gn:country_code":"TH",
    "gn:dem":5,
    "gn:feature_class":"P",
    "gn:feature_code":"PPL",
    "gn:name":"Ban Rang Sangkasi",
    "gn:population":0,
    "gn:timezone":"Asia/Bangkok",
    "iso:country":"TH",
    "name:tha_x_preferred":[
        "\u0e1a\u0e49\u0e32\u0e19\u0e23\u0e32\u0e07\u0e2a\u0e31\u0e07\u0e01\u0e30\u0e2a\u0e35"
    ],
    "wof:name":"Ban Rang Sangkasi",
    "wof:placetype":"locality"
},
  "geometry": {"coordinates":[100.15694000000001,13.71314],"type":"Point"}
}