{
  "type": "Feature",
  "properties": {
    "gn:admin1_code":"13.0",
    "gn:asciiname":"Ban Phai Rop",
    "gn:country_code":"TH",
    "gn:dem":39,
    "gn:feature_class":"P",
    "gn:feature_code":"PPL",
    "gn:name":"Ban Phai Rop",
    "gn:population":0,
    "gn:timezone":"Asia/Bangkok",
    "iso:country":"TH",
    "name:tha_x_preferred":[
        "\u0e1a\u0e49\u0e32\u0e19\u0e44\u0e1c\u0e48\u0e23\u0e2d\u0e1a"
    ],
    "name:und_x_variant":[
        "Ban Phai Lop",
        "B\u0101n Ph\u0101i Laup",
        "Ban Phai Rop"
    ],
    "wof:name":"Ban Phai Rop",
    "wof:placetype":"locality"
},
  "geometry": {"coordinates":[100.22094,16.36408],"type":"Point"}
}