{
  "type": "Feature",
  "properties": {
    "gn:admin1_code":"68.0",
    "gn:asciiname":"Ban Khlong Ba Khae",
    "gn:country_code":"TH",
    "gn:dem":140,
    "gn:feature_class":"P",
    "gn:feature_code":"PPL",
    "gn:name":"Ban Khlong Ba Khae",
    "gn:population":0,
    "gn:timezone":"Asia/Bangkok",
    "iso:country":"TH",
    "name:tha_x_preferred":[
        "\u0e1a\u0e49\u0e32\u0e19\u0e04\u0e25\u0e2d\u0e07\u0e1a\u0e32\u0e41\u0e06\u0e30"
    ],
    "wof:name":"Ban Khlong Ba Khae",
    "wof:placetype":"locality"
},
  "geometry": {"coordinates":[100.90667000000001,6.37547],"type":"Point"}
}