{
  "type": "Feature",
  "properties": {
    "gn:admin1_code":"22.0",
    "gn:asciiname":"Ban Din Dam",
    "gn:country_code":"TH",
    "gn:dem":191,
    "gn:feature_class":"P",
    "gn:feature_code":"PPL",
    "gn:name":"Ban Din Dam",
    "gn:population":0,
    "gn:timezone":"Asia/Bangkok",
    "iso:country":"TH",
    "name:tha_x_preferred":[
        "\u0e1a\u0e49\u0e32\u0e19\u0e14\u0e34\u0e19\u0e14\u0e33"
    ],
    "wof:name":"Ban Din Dam",
    "wof:placetype":"locality"
},
  "geometry": {"coordinates":[102.42756,16.71953],"type":"Point"}
}