{
  "type": "Feature",
  "properties": {
    "gn:admin1_code":"74.0",
    "gn:asciiname":"Ban Nong Khlon",
    "gn:country_code":"TH",
    "gn:dem":16,
    "gn:feature_class":"P",
    "gn:feature_code":"PPL",
    "gn:name":"Ban Nong Khlon",
    "gn:population":0,
    "gn:timezone":"Asia/Bangkok",
    "iso:country":"TH",
    "name:tha_x_preferred":[
        "\u0e1a\u0e49\u0e32\u0e19\u0e2b\u0e19\u0e2d\u0e07\u0e42\u0e04\u0e25\u0e19"
    ],
    "name:und_x_variant":[
        "Ban Hnong Klon",
        "Ban Nong Khlon (1)",
        "Ban Nong Khlon"
    ],
    "wof:name":"Ban Nong Khlon",
    "wof:placetype":"locality"
},
  "geometry": {"coordinates":[101.64022,14.00708],"type":"Point"}
}