{
  "type": "Feature",
  "properties": {
    "gn:admin1_code":"13.0",
    "gn:asciiname":"Ban Bang Lamphu",
    "gn:country_code":"TH",
    "gn:dem":36,
    "gn:feature_class":"P",
    "gn:feature_code":"PPL",
    "gn:name":"Ban Bang Lamphu",
    "gn:population":0,
    "gn:timezone":"Asia/Bangkok",
    "iso:country":"TH",
    "name:tha_x_preferred":[
        "\u0e1a\u0e49\u0e32\u0e19\u0e1a\u0e32\u0e07\u0e25\u0e33\u0e20\u0e39"
    ],
    "wof:name":"Ban Bang Lamphu",
    "wof:placetype":"locality"
},
  "geometry": {"coordinates":[100.43386,16.03194],"type":"Point"}
}