{
  "type": "Feature",
  "properties": {
    "gn:admin1_code":"78.0",
    "gn:asciiname":"Ban Khong Samran",
    "gn:country_code":"TH",
    "gn:dem":194,
    "gn:feature_class":"P",
    "gn:feature_code":"PPL",
    "gn:name":"Ban Khong Samran",
    "gn:population":0,
    "gn:timezone":"Asia/Bangkok",
    "iso:country":"TH",
    "name:tha_x_preferred":[
        "Ban Khong Samran"
    ],
    "name:tha_x_variant":[
        "\u0e1a\u0e49\u0e32\u0e19\u0e42\u0e04\u0e49\u0e07\u0e2a\u0e33\u0e23\u0e32\u0e0d"
    ],
    "wof:name":"Ban Khong Samran",
    "wof:placetype":"locality"
},
  "geometry": {"coordinates":[104.63,16.43961],"type":"Point"}
}