{
  "type": "Feature",
  "properties": {
    "gn:admin1_code":"50.0",
    "gn:asciiname":"Ban Wang Kalo",
    "gn:country_code":"TH",
    "gn:dem":32,
    "gn:feature_class":"P",
    "gn:feature_code":"PPL",
    "gn:name":"Ban Wang Kalo",
    "gn:population":0,
    "gn:timezone":"Asia/Bangkok",
    "iso:country":"TH",
    "name:tha_x_preferred":[
        "\u0e1a\u0e49\u0e32\u0e19\u0e27\u0e31\u0e07\u0e01\u0e30\u0e42\u0e25\u0e48"
    ],
    "wof:name":"Ban Wang Kalo",
    "wof:placetype":"locality"
},
  "geometry": {"coordinates":[99.75408,14.38194],"type":"Point"}
}