{
  "type": "Feature",
  "properties": {
    "gn:admin1_code":"8.0",
    "gn:asciiname":"Ban Tha Phai",
    "gn:country_code":"TH",
    "gn:dem":150,
    "gn:feature_class":"P",
    "gn:feature_code":"PPL",
    "gn:name":"Ban Tha Phai",
    "gn:population":0,
    "gn:timezone":"Asia/Bangkok",
    "iso:country":"TH",
    "name:tha_x_preferred":[
        "\u0e1a\u0e49\u0e32\u0e19\u0e17\u0e48\u0e32\u0e44\u0e1c\u0e48"
    ],
    "name:und_x_variant":[
        "Ban Tha Phai Noi"
    ],
    "wof:name":"Ban Tha Phai",
    "wof:placetype":"locality"
},
  "geometry": {"coordinates":[99.06399999999999,17.31497],"type":"Point"}
}