{
  "type": "Feature",
  "properties": {
    "gn:admin1_code":"27.0",
    "gn:asciiname":"Ban Muen Wai",
    "gn:country_code":"TH",
    "gn:dem":182,
    "gn:feature_class":"P",
    "gn:feature_code":"PPL",
    "gn:name":"Ban Muen Wai",
    "gn:population":0,
    "gn:timezone":"Asia/Bangkok",
    "iso:country":"TH",
    "name:tha_x_preferred":[
        "\u0e1a\u0e49\u0e32\u0e19\u0e2b\u0e21\u0e37\u0e48\u0e19\u0e44\u0e27\u0e22"
    ],
    "name:und_x_variant":[
        "Ban Mun Wai"
    ],
    "wof:name":"Ban Muen Wai",
    "wof:placetype":"locality"
},
  "geometry": {"coordinates":[102.09219,15.01914],"type":"Point"}
}