{
  "type": "Feature",
  "properties": {
    "gn:admin1_code":"52.0",
    "gn:asciiname":"Ban Huai Makrut",
    "gn:country_code":"TH",
    "gn:dem":261,
    "gn:feature_class":"P",
    "gn:feature_code":"PPL",
    "gn:name":"Ban Huai Makrut",
    "gn:population":0,
    "gn:timezone":"Asia/Bangkok",
    "iso:country":"TH",
    "name:tha_x_preferred":[
        "\u0e1a\u0e49\u0e32\u0e19\u0e2b\u0e49\u0e27\u0e22\u0e21\u0e30\u0e01\u0e23\u0e39\u0e14"
    ],
    "wof:name":"Ban Huai Makrut",
    "wof:placetype":"locality"
},
  "geometry": {"coordinates":[99.45742,13.31869],"type":"Point"}
}