{
  "type": "Feature",
  "properties": {
    "gn:admin1_code":"37.0",
    "gn:asciiname":"Ban Lat Hin Pun",
    "gn:country_code":"TH",
    "gn:dem":23,
    "gn:feature_class":"P",
    "gn:feature_code":"PPL",
    "gn:name":"Ban Lat Hin Pun",
    "gn:population":0,
    "gn:timezone":"Asia/Bangkok",
    "iso:country":"TH",
    "name:tha_x_preferred":[
        "\u0e1a\u0e49\u0e32\u0e19\u0e25\u0e32\u0e14\u0e2b\u0e34\u0e19\u0e1b\u0e39\u0e19"
    ],
    "name:und_x_variant":[
        "Ban Lat Khao Pun"
    ],
    "wof:name":"Ban Lat Hin Pun",
    "wof:placetype":"locality"
},
  "geometry": {"coordinates":[100.93831,14.59842],"type":"Point"}
}