{
  "type": "Feature",
  "properties": {
    "gn:admin1_code":"32.0",
    "gn:asciiname":"Ban Khung Samphao",
    "gn:country_code":"TH",
    "gn:dem":33,
    "gn:feature_class":"P",
    "gn:feature_code":"PPL",
    "gn:name":"Ban Khung Samphao",
    "gn:population":0,
    "gn:timezone":"Asia/Bangkok",
    "iso:country":"TH",
    "name:tha_x_preferred":[
        "\u0e1a\u0e49\u0e32\u0e19\u0e40\u0e01\u0e32\u0e30\u0e04\u0e38\u0e49\u0e07\u0e2a\u0e33\u0e40\u0e20\u0e32"
    ],
    "name:tha_x_variant":[
        "\u0e1a\u0e49\u0e32\u0e19\u0e04\u0e38\u0e49\u0e07\u0e2a\u0e33\u0e40\u0e20\u0e32"
    ],
    "name:und_x_variant":[
        "Ban Ko Khung Samphao",
        "Ban Khung Samphao"
    ],
    "wof:name":"Ban Khung Samphao",
    "wof:placetype":"locality"
},
  "geometry": {"coordinates":[100.06353,15.26394],"type":"Point"}
}