{
  "type": "Feature",
  "properties": {
    "gn:admin1_code":"2.0",
    "gn:asciiname":"Ban U Tum",
    "gn:country_code":"TH",
    "gn:dem":1389,
    "gn:feature_class":"P",
    "gn:feature_code":"PPL",
    "gn:name":"Ban U Tum",
    "gn:population":0,
    "gn:timezone":"Asia/Bangkok",
    "iso:country":"TH",
    "name:tha_x_preferred":[
        "\u0e1a\u0e49\u0e32\u0e19\u0e2d\u0e39\u0e15\u0e39\u0e21"
    ],
    "wof:name":"Ban U Tum",
    "wof:placetype":"locality"
},
  "geometry": {"coordinates":[98.20986000000001,17.86214],"type":"Point"}
}