{
  "type": "Feature",
  "properties": {
    "gn:admin1_code":"51.0",
    "gn:asciiname":"Ban Nong Ma Fan",
    "gn:country_code":"TH",
    "gn:dem":27,
    "gn:feature_class":"P",
    "gn:feature_code":"PPL",
    "gn:name":"Ban Nong Ma Fan",
    "gn:population":0,
    "gn:timezone":"Asia/Bangkok",
    "iso:country":"TH",
    "name:tha_x_preferred":[
        "\u0e1a\u0e49\u0e32\u0e19\u0e2b\u0e19\u0e2d\u0e07\u0e21\u0e30\u0e1d\u0e32\u0e19"
    ],
    "wof:name":"Ban Nong Ma Fan",
    "wof:placetype":"locality"
},
  "geometry": {"coordinates":[99.91146999999999,14.762],"type":"Point"}
}