{
  "type": "Feature",
  "properties": {
    "gn:admin1_code":"70.0",
    "gn:asciiname":"Ban Lato",
    "gn:country_code":"TH",
    "gn:dem":50,
    "gn:feature_class":"P",
    "gn:feature_code":"PPL",
    "gn:name":"Ban Lato",
    "gn:population":0,
    "gn:timezone":"Asia/Bangkok",
    "iso:country":"TH",
    "name:tha_x_preferred":[
        "\u0e1a\u0e49\u0e32\u0e19\u0e25\u0e32\u0e40\u0e15\u0e4a\u0e32\u0e30"
    ],
    "wof:name":"Ban Lato",
    "wof:placetype":"locality"
},
  "geometry": {"coordinates":[101.01011,6.42469],"type":"Point"}
}