{
  "type": "Feature",
  "properties": {
    "gn:admin1_code":"25",
    "gn:asciiname":"Ban Na Khok",
    "gn:country_code":"TH",
    "gn:dem":212,
    "gn:feature_class":"P",
    "gn:feature_code":"PPL",
    "gn:name":"Ban Na Khok",
    "gn:population":0,
    "gn:timezone":"Asia/Bangkok",
    "iso:country":"TH",
    "name:tha_x_preferred":[
        "\u0e1a\u0e49\u0e32\u0e19\u0e19\u0e32\u0e42\u0e04\u0e01"
    ],
    "wof:name":"Ban Na Khok",
    "wof:placetype":"locality"
},
  "geometry": {"coordinates":[104.28297000000001,16.25607999999999],"type":"Point"}
}