{
  "type": "Feature",
  "properties": {
    "gn:admin1_code":"80",
    "gn:asciiname":"Ban Khao Phaeng Ma",
    "gn:country_code":"TH",
    "gn:dem":107,
    "gn:feature_class":"P",
    "gn:feature_code":"PPL",
    "gn:name":"Ban Khao Phaeng Ma",
    "gn:population":0,
    "gn:timezone":"Asia/Bangkok",
    "iso:country":"TH",
    "name:tha_x_preferred":[
        "\u0e1a\u0e49\u0e32\u0e19\u0e40\u0e02\u0e32\u0e41\u0e1c\u0e07\u0e21\u0e49\u0e32"
    ],
    "wof:name":"Ban Khao Phaeng Ma",
    "wof:placetype":"locality"
},
  "geometry": {"coordinates":[102.10511,13.42703],"type":"Point"}
}