{
  "type": "Feature",
  "properties": {
    "gn:admin1_code":"28.0",
    "gn:asciiname":"Ban Nong Prue",
    "gn:country_code":"TH",
    "gn:dem":170,
    "gn:feature_class":"P",
    "gn:feature_code":"PPL",
    "gn:name":"Ban Nong Prue",
    "gn:population":0,
    "gn:timezone":"Asia/Bangkok",
    "iso:country":"TH",
    "name:tha_x_preferred":[
        "\u0e1a\u0e49\u0e32\u0e19\u0e2b\u0e19\u0e2d\u0e07\u0e1b\u0e23\u0e37\u0e2d"
    ],
    "name:und_x_variant":[
        "Ban Nong Pru"
    ],
    "wof:name":"Ban Nong Prue",
    "wof:placetype":"locality"
},
  "geometry": {"coordinates":[103.0715,15.06481],"type":"Point"}
}