{
  "type": "Feature",
  "properties": {
    "gn:admin1_code":"50.0",
    "gn:asciiname":"Muban Chang Phu Thong",
    "gn:country_code":"TH",
    "gn:dem":107,
    "gn:feature_class":"P",
    "gn:feature_code":"PPL",
    "gn:name":"Muban Chang Phu Thong",
    "gn:population":0,
    "gn:timezone":"Asia/Bangkok",
    "iso:country":"TH",
    "name:tha_x_preferred":[
        "\u0e2b\u0e21\u0e39\u0e48\u0e1a\u0e49\u0e32\u0e19\u0e0a\u0e49\u0e32\u0e07\u0e1e\u0e38\u0e16\u0e48\u0e2d\u0e07"
    ],
    "wof:lang_x_official":[
        "tha"
    ],
    "wof:lang_x_spoken":[
        "tha"
    ],
    "wof:name":"Muban Chang Phu Thong",
    "wof:placetype":"locality"
},
  "geometry": {"coordinates":[98.75861,14.59006],"type":"Point"}
}