{
  "type": "Feature",
  "properties": {
    "gn:admin1_code":"81.0",
    "gn:asciiname":"Ban Huai Dok Mai",
    "gn:country_code":"TH",
    "gn:dem":173,
    "gn:feature_class":"P",
    "gn:feature_code":"PPL",
    "gn:name":"Ban Huai Dok Mai",
    "gn:population":0,
    "gn:timezone":"Asia/Bangkok",
    "iso:country":"TH",
    "name:tha_x_preferred":[
        "\u0e1a\u0e49\u0e32\u0e19\u0e2b\u0e49\u0e27\u0e22\u0e14\u0e2d\u0e01\u0e44\u0e21\u0e49"
    ],
    "wof:name":"Ban Huai Dok Mai",
    "wof:placetype":"locality"
},
  "geometry": {"coordinates":[103.57922000000001,18.35083],"type":"Point"}
}