{
  "type": "Feature",
  "properties": {
    "gn:admin1_code":"75.0",
    "gn:asciiname":"Ban Si Samut",
    "gn:country_code":"TH",
    "gn:dem":160,
    "gn:feature_class":"P",
    "gn:feature_code":"PPL",
    "gn:name":"Ban Si Samut",
    "gn:population":0,
    "gn:timezone":"Asia/Bangkok",
    "iso:country":"TH",
    "name:tha_x_preferred":[
        "\u0e1a\u0e49\u0e32\u0e19\u0e28\u0e23\u0e35\u0e2a\u0e21\u0e38\u0e17\u0e23"
    ],
    "wof:name":"Ban Si Samut",
    "wof:placetype":"locality"
},
  "geometry": {"coordinates":[105.39294,14.71464],"type":"Point"}
}