{
  "type": "Feature",
  "properties": {
    "gn:admin1_code":"30.0",
    "gn:asciiname":"Ban Pueai",
    "gn:country_code":"TH",
    "gn:dem":140,
    "gn:feature_class":"P",
    "gn:feature_code":"PPL",
    "gn:name":"Ban Pueai",
    "gn:population":0,
    "gn:timezone":"Asia/Bangkok",
    "iso:country":"TH",
    "name:tha_x_preferred":[
        "\u0e1a\u0e49\u0e32\u0e19\u0e40\u0e1b\u0e37\u0e2d\u0e22"
    ],
    "wof:name":"Ban Pueai",
    "wof:placetype":"locality"
},
  "geometry": {"coordinates":[104.39069000000001,14.89022],"type":"Point"}
}