{
  "type": "Feature",
  "properties": {
    "gn:admin1_code":"42.0",
    "gn:asciiname":"Ban Chuat Bua",
    "gn:country_code":"TH",
    "gn:dem":5,
    "gn:feature_class":"P",
    "gn:feature_code":"PPL",
    "gn:name":"Ban Chuat Bua",
    "gn:population":0,
    "gn:timezone":"Asia/Bangkok",
    "iso:country":"TH",
    "name:tha_x_preferred":[
        "\u0e1a\u0e49\u0e32\u0e19\u0e0a\u0e27\u0e14\u0e1a\u0e31\u0e27"
    ],
    "wof:name":"Ban Chuat Bua",
    "wof:placetype":"locality"
},
  "geometry": {"coordinates":[100.83364,13.67489],"type":"Point"}
}