{
  "type": "Feature",
  "properties": {
    "gn:admin1_code":"18.0",
    "gn:asciiname":"Ban Wang Peng",
    "gn:country_code":"TH",
    "gn:dem":287,
    "gn:feature_class":"P",
    "gn:feature_code":"PPL",
    "gn:name":"Ban Wang Peng",
    "gn:population":0,
    "gn:timezone":"Asia/Bangkok",
    "iso:country":"TH",
    "name:tha_x_preferred":[
        "\u0e1a\u0e49\u0e32\u0e19\u0e27\u0e31\u0e07\u0e40\u0e1b\u0e07"
    ],
    "wof:name":"Ban Wang Peng",
    "wof:placetype":"locality"
},
  "geometry": {"coordinates":[101.30042,17.61794],"type":"Point"}
}