{
  "type": "Feature",
  "properties": {
    "gn:admin1_code":"8.0",
    "gn:asciiname":"Ban Pang Thong",
    "gn:country_code":"TH",
    "gn:dem":827,
    "gn:feature_class":"P",
    "gn:feature_code":"PPL",
    "gn:name":"Ban Pang Thong",
    "gn:population":0,
    "gn:timezone":"Asia/Bangkok",
    "iso:country":"TH",
    "name:tha_x_preferred":[
        "\u0e1a\u0e49\u0e32\u0e19\u0e1b\u0e32\u0e07\u0e17\u0e2d\u0e07"
    ],
    "wof:name":"Ban Pang Thong",
    "wof:placetype":"locality"
},
  "geometry": {"coordinates":[97.94113,17.74105],"type":"Point"}
}