{
  "type": "Feature",
  "properties": {
    "gn:admin1_code":"66.0",
    "gn:asciiname":"Ban Tha Wa",
    "gn:country_code":"TH",
    "gn:dem":10,
    "gn:feature_class":"P",
    "gn:feature_code":"PPL",
    "gn:name":"Ban Tha Wa",
    "gn:population":0,
    "gn:timezone":"Asia/Bangkok",
    "iso:country":"TH",
    "name:tha_x_preferred":[
        "\u0e1a\u0e49\u0e32\u0e19\u0e17\u0e48\u0e32\u0e27\u0e32"
    ],
    "name:und_x_variant":[
        "Ban Thawa",
        "Ban Tha Wa"
    ],
    "wof:name":"Ban Tha Wa",
    "wof:placetype":"locality"
},
  "geometry": {"coordinates":[100.32281,7.36667],"type":"Point"}
}