{
  "type": "Feature",
  "properties": {
    "gn:admin1_code":"2.0",
    "gn:asciiname":"Ban Kham Sum Pa",
    "gn:country_code":"TH",
    "gn:dem":444,
    "gn:feature_class":"P",
    "gn:feature_code":"PPL",
    "gn:name":"Ban Kham Sum Pa",
    "gn:population":0,
    "gn:timezone":"Asia/Bangkok",
    "iso:country":"TH",
    "name:tha_x_preferred":[
        "\u0e1a\u0e49\u0e32\u0e19\u0e02\u0e32\u0e21\u0e2a\u0e38\u0e48\u0e21\u0e1b\u0e48\u0e32"
    ],
    "name:und_x_variant":[
        "B\u0101n K\u0101m Jam",
        "Ban Kham Chum",
        "Ban Kham Sum Nok",
        "Ban Kham Sum Pa"
    ],
    "wof:name":"Ban Kham Sum Pa",
    "wof:placetype":"locality"
},
  "geometry": {"coordinates":[99.19564,19.41039],"type":"Point"}
}