{
  "type": "Feature",
  "properties": {
    "gn:admin1_code":"61.0",
    "gn:asciiname":"Ban Tham Thonglang Nai",
    "gn:country_code":"TH",
    "gn:dem":77,
    "gn:feature_class":"P",
    "gn:feature_code":"PPL",
    "gn:name":"Ban Tham Thonglang Nai",
    "gn:population":0,
    "gn:timezone":"Asia/Bangkok",
    "iso:country":"TH",
    "name:tha_x_preferred":[
        "\u0e1a\u0e49\u0e32\u0e19\u0e16\u0e49\u0e33\u0e17\u0e2d\u0e07\u0e2b\u0e25\u0e32\u0e07\u0e43\u0e19"
    ],
    "wof:name":"Ban Tham Thonglang Nai",
    "wof:placetype":"locality"
},
  "geometry": {"coordinates":[98.58199999999999,8.54161],"type":"Point"}
}