{
  "type": "Feature",
  "properties": {
    "gn:admin1_code":"27",
    "gn:asciiname":"Ban Thai Doem",
    "gn:country_code":"TH",
    "gn:dem":340,
    "gn:feature_class":"P",
    "gn:feature_code":"PPL",
    "gn:name":"Ban Thai Doem",
    "gn:population":0,
    "gn:timezone":"Asia/Bangkok",
    "iso:country":"TH",
    "name:tha_x_preferred":[
        "\u0e1a\u0e49\u0e32\u0e19\u0e44\u0e17\u0e22\u0e40\u0e14\u0e34\u0e21"
    ],
    "wof:name":"Ban Thai Doem",
    "wof:placetype":"locality"
},
  "geometry": {"coordinates":[101.38711000000001,14.65931],"type":"Point"}
}