{
  "type": "Feature",
  "properties": {
    "gn:admin1_code":"31.0",
    "gn:asciiname":"Ban Tanyong Lu Lo",
    "gn:country_code":"TH",
    "gn:dem":12,
    "gn:feature_class":"P",
    "gn:feature_code":"PPL",
    "gn:name":"Ban Tanyong Lu Lo",
    "gn:population":0,
    "gn:timezone":"Asia/Bangkok",
    "iso:country":"TH",
    "name:tha_x_preferred":[
        "\u0e1a\u0e49\u0e32\u0e19\u0e15\u0e31\u0e19\u0e2b\u0e22\u0e07\u0e25\u0e39\u0e42\u0e25\u0e4a\u0e30"
    ],
    "wof:lang_x_official":[
        "tha"
    ],
    "wof:lang_x_spoken":[
        "tha"
    ],
    "wof:name":"Ban Tanyong Lu Lo",
    "wof:placetype":"locality"
},
  "geometry": {"coordinates":[101.81822,6.36406],"type":"Point"}
}