{
  "type": "Feature",
  "properties": {
    "gn:admin1_code":"4.0",
    "gn:asciiname":"Ban Nam Wa",
    "gn:country_code":"TH",
    "gn:dem":284,
    "gn:feature_class":"P",
    "gn:feature_code":"PPL",
    "gn:name":"Ban Nam Wa",
    "gn:population":0,
    "gn:timezone":"Asia/Bangkok",
    "iso:country":"TH",
    "name:tha_x_preferred":[
        "\u0e1a\u0e49\u0e32\u0e19\u0e19\u0e49\u0e33\u0e27\u0e49\u0e32"
    ],
    "wof:name":"Ban Nam Wa",
    "wof:placetype":"locality"
},
  "geometry": {"coordinates":[101.00778,18.64289],"type":"Point"}
}