{
  "type": "Feature",
  "properties": {
    "gn:admin1_code":"25.0",
    "gn:asciiname":"Ban Tha Siao",
    "gn:country_code":"TH",
    "gn:dem":143,
    "gn:feature_class":"P",
    "gn:feature_code":"PPL",
    "gn:name":"Ban Tha Siao",
    "gn:population":0,
    "gn:timezone":"Asia/Bangkok",
    "iso:country":"TH",
    "name:tha_x_preferred":[
        "\u0e1a\u0e49\u0e32\u0e19\u0e17\u0e48\u0e32\u0e40\u0e2a\u0e35\u0e22\u0e27"
    ],
    "name:und_x_variant":[
        "Ban Tha Sien"
    ],
    "wof:name":"Ban Tha Siao",
    "wof:placetype":"locality"
},
  "geometry": {"coordinates":[103.77631,16.20408],"type":"Point"}
}