{
  "type": "Feature",
  "properties": {
    "gn:admin1_code":"47.0",
    "gn:asciiname":"Ban Na",
    "gn:country_code":"TH",
    "gn:dem":7,
    "gn:feature_class":"P",
    "gn:feature_code":"PPL",
    "gn:name":"Ban Na",
    "gn:population":0,
    "gn:timezone":"Asia/Bangkok",
    "iso:country":"TH",
    "name:tha_x_preferred":[
        "\u0e1a\u0e49\u0e32\u0e19\u0e19\u0e32"
    ],
    "wof:name":"Ban Na",
    "wof:placetype":"locality"
},
  "geometry": {"coordinates":[101.66772,12.8099],"type":"Point"}
}