{
  "type": "Feature",
  "properties": {
    "gn:admin1_code":"2.0",
    "gn:asciiname":"Ban Mae Sap Nuea",
    "gn:country_code":"TH",
    "gn:dem":570,
    "gn:feature_class":"P",
    "gn:feature_code":"PPL",
    "gn:name":"Ban Mae Sap Nuea",
    "gn:population":0,
    "gn:timezone":"Asia/Bangkok",
    "iso:country":"TH",
    "name:tha_x_preferred":[
        "\u0e1a\u0e49\u0e32\u0e19\u0e41\u0e21\u0e48\u0e2a\u0e32\u0e1a\u0e40\u0e2b\u0e19\u0e37\u0e2d"
    ],
    "name:und_x_variant":[
        "Ban Mae Sap Nua"
    ],
    "wof:lang_x_official":[
        "tha"
    ],
    "wof:lang_x_spoken":[
        "tha"
    ],
    "wof:name":"Ban Mae Sap Nuea",
    "wof:placetype":"locality"
},
  "geometry": {"coordinates":[98.70180999999999,18.85945],"type":"Point"}
}