{
  "type": "Feature",
  "properties": {
    "gn:admin1_code":"27",
    "gn:asciiname":"Ban Si Watthana",
    "gn:country_code":"TH",
    "gn:dem":156,
    "gn:feature_class":"P",
    "gn:feature_code":"PPL",
    "gn:name":"Ban Si Watthana",
    "gn:population":0,
    "gn:timezone":"Asia/Bangkok",
    "iso:country":"TH",
    "name:tha_x_preferred":[
        "\u0e1a\u0e49\u0e32\u0e19\u0e28\u0e23\u0e35\u0e27\u0e31\u0e12\u0e19\u0e32"
    ],
    "wof:name":"Ban Si Watthana",
    "wof:placetype":"locality"
},
  "geometry": {"coordinates":[102.51831,15.45508],"type":"Point"}
}