{
  "type": "Feature",
  "properties": {
    "gn:admin1_code":"14.0",
    "gn:asciiname":"Ban Rong Kathin",
    "gn:country_code":"TH",
    "gn:dem":137,
    "gn:feature_class":"P",
    "gn:feature_code":"PPL",
    "gn:name":"Ban Rong Kathin",
    "gn:population":0,
    "gn:timezone":"Asia/Bangkok",
    "iso:country":"TH",
    "name:tha_x_preferred":[
        "\u0e1a\u0e49\u0e32\u0e19\u0e23\u0e48\u0e2d\u0e07\u0e01\u0e30\u0e16\u0e34\u0e19"
    ],
    "wof:name":"Ban Rong Kathin",
    "wof:placetype":"locality"
},
  "geometry": {"coordinates":[101.23942,16.61861],"type":"Point"}
}