{
  "type": "Feature",
  "properties": {
    "gn:admin1_code":"75.0",
    "gn:asciiname":"Ban Non Sawan",
    "gn:country_code":"TH",
    "gn:dem":160,
    "gn:feature_class":"P",
    "gn:feature_code":"PPL",
    "gn:name":"Ban Non Sawan",
    "gn:population":0,
    "gn:timezone":"Asia/Bangkok",
    "iso:country":"TH",
    "name:tha_x_preferred":[
        "\u0e1a\u0e49\u0e32\u0e19\u0e42\u0e19\u0e19\u0e2a\u0e27\u0e23\u0e23\u0e04\u0e4c"
    ],
    "wof:name":"Ban Non Sawan",
    "wof:placetype":"locality"
},
  "geometry": {"coordinates":[105.18628,14.74592],"type":"Point"}
}