{
  "type": "Feature",
  "properties": {
    "gn:admin1_code":"60.0",
    "gn:asciiname":"Ban Mai Chattawa",
    "gn:country_code":"TH",
    "gn:dem":30,
    "gn:feature_class":"P",
    "gn:feature_code":"PPL",
    "gn:name":"Ban Mai Chattawa",
    "gn:population":0,
    "gn:timezone":"Asia/Bangkok",
    "iso:country":"TH",
    "name:tha_x_preferred":[
        "\u0e1a\u0e49\u0e32\u0e19\u0e43\u0e2b\u0e21\u0e48\u0e08\u0e31\u0e15\u0e27\u0e32"
    ],
    "wof:name":"Ban Mai Chattawa",
    "wof:placetype":"locality"
},
  "geometry": {"coordinates":[99.35025,8.98581],"type":"Point"}
}