{
  "type": "Feature",
  "properties": {
    "gn:admin1_code":"53.0",
    "gn:asciiname":"Ban Don Kae Rae",
    "gn:country_code":"TH",
    "gn:dem":9,
    "gn:feature_class":"P",
    "gn:feature_code":"PPL",
    "gn:name":"Ban Don Kae Rae",
    "gn:population":0,
    "gn:timezone":"Asia/Bangkok",
    "iso:country":"TH",
    "name:tha_x_preferred":[
        "\u0e1a\u0e49\u0e32\u0e19\u0e14\u0e2d\u0e19\u0e41\u0e01\u0e30\u0e41\u0e23\u0e30"
    ],
    "wof:name":"Ban Don Kae Rae",
    "wof:placetype":"locality"
},
  "geometry": {"coordinates":[100.10431,13.92583],"type":"Point"}
}