{
  "type": "Feature",
  "properties": {
    "gn:admin1_code":"3.0",
    "gn:asciiname":"Ban San Khue",
    "gn:country_code":"TH",
    "gn:dem":415,
    "gn:feature_class":"P",
    "gn:feature_code":"PPL",
    "gn:name":"Ban San Khue",
    "gn:population":0,
    "gn:timezone":"Asia/Bangkok",
    "iso:country":"TH",
    "name:tha_x_preferred":[
        "\u0e1a\u0e49\u0e32\u0e19\u0e2a\u0e31\u0e19\u0e04\u0e37\u0e2d"
    ],
    "name:und_x_variant":[
        "Ban San Khu",
        "Ban San Khue"
    ],
    "wof:name":"Ban San Khue",
    "wof:placetype":"locality"
},
  "geometry": {"coordinates":[99.85657999999999,20.18333],"type":"Point"}
}