{
  "type": "Feature",
  "properties": {
    "gn:admin1_code":"76.0",
    "gn:asciiname":"Ban Nong Hin Nuea",
    "gn:country_code":"TH",
    "gn:dem":172,
    "gn:feature_class":"P",
    "gn:feature_code":"PPL",
    "gn:name":"Ban Nong Hin Nuea",
    "gn:population":0,
    "gn:timezone":"Asia/Bangkok",
    "iso:country":"TH",
    "name:tha_x_preferred":[
        "\u0e1a\u0e49\u0e32\u0e19\u0e2b\u0e19\u0e2d\u0e07\u0e2b\u0e34\u0e19\u0e40\u0e2b\u0e19\u0e37\u0e2d"
    ],
    "wof:name":"Ban Nong Hin Nuea",
    "wof:placetype":"locality"
},
  "geometry": {"coordinates":[103.26667,17.6892],"type":"Point"}
}