{
  "type": "Feature",
  "properties": {
    "gn:admin1_code":"3.0",
    "gn:asciiname":"Ban Saen Chai Mai",
    "gn:country_code":"TH",
    "gn:dem":665,
    "gn:feature_class":"P",
    "gn:feature_code":"PPL",
    "gn:name":"Ban Saen Chai Mai",
    "gn:population":0,
    "gn:timezone":"Asia/Bangkok",
    "iso:country":"TH",
    "wof:name":"Ban Saen Chai Mai",
    "wof:placetype":"locality"
},
  "geometry": {"coordinates":[99.75333000000001,20.20472],"type":"Point"}
}