{
  "type": "Feature",
  "properties": {
    "gn:admin1_code":"9.0",
    "gn:asciiname":"Ban Khao Thong Pha Ngap",
    "gn:country_code":"TH",
    "gn:dem":73,
    "gn:feature_class":"P",
    "gn:feature_code":"PPL",
    "gn:name":"Ban Khao Thong Pha Ngap",
    "gn:population":0,
    "gn:timezone":"Asia/Bangkok",
    "iso:country":"TH",
    "name:tha_x_preferred":[
        "\u0e1a\u0e49\u0e32\u0e19\u0e40\u0e02\u0e32\u0e17\u0e2d\u0e07\u0e1c\u0e32\u0e07\u0e31\u0e1a"
    ],
    "wof:name":"Ban Khao Thong Pha Ngap",
    "wof:placetype":"locality"
},
  "geometry": {"coordinates":[99.64181000000001,16.76619],"type":"Point"}
}