{
  "type": "Feature",
  "properties": {
    "gn:admin1_code":"48.0",
    "gn:asciiname":"Ban Wang Ta Mueang",
    "gn:country_code":"TH",
    "gn:dem":35,
    "gn:feature_class":"P",
    "gn:feature_code":"PPL",
    "gn:name":"Ban Wang Ta Mueang",
    "gn:population":0,
    "gn:timezone":"Asia/Bangkok",
    "iso:country":"TH",
    "name:tha_x_preferred":[
        "\u0e1a\u0e49\u0e32\u0e19\u0e27\u0e31\u0e07\u0e15\u0e32\u0e40\u0e21\u0e37\u0e2d\u0e07"
    ],
    "wof:name":"Ban Wang Ta Mueang",
    "wof:placetype":"locality"
},
  "geometry": {"coordinates":[101.91119,13.01228],"type":"Point"}
}