{
  "type": "Feature",
  "properties": {
    "gn:admin1_code":"3.0",
    "gn:asciiname":"Ban Ian",
    "gn:country_code":"TH",
    "gn:dem":395,
    "gn:feature_class":"P",
    "gn:feature_code":"PPL",
    "gn:name":"Ban Ian",
    "gn:population":0,
    "gn:timezone":"Asia/Bangkok",
    "iso:country":"TH",
    "name:tha_x_preferred":[
        "\u0e1a\u0e49\u0e32\u0e19\u0e40\u0e2d\u0e35\u0e22\u0e19"
    ],
    "wof:name":"Ban Ian",
    "wof:placetype":"locality"
},
  "geometry": {"coordinates":[100.28445000000001,19.70274],"type":"Point"}
}