{
  "type": "Feature",
  "properties": {
    "iso:country":"TH",
    "name:ara_x_preferred":[
        "\u0645\u0646\u0637\u0642\u0629 \u0644\u064a\u062a \u0643\u0631\u0627\u0628\u0627\u0646\u062c"
    ],
    "name:bpy_x_preferred":[
        "\u0996\u09c7\u09a4 \u09b2\u09af\u09bc\u09be\u09a4 \u0995\u09cd\u09b0\u09be\u09ac\u09cd\u09af\u09be\u0982"
    ],
    "name:ceb_x_preferred":[
        "Khet Lat Krabang"
    ],
    "name:deu_x_preferred":[
        "Lat Krabang"
    ],
    "name:eng_x_preferred":[
        "Lat Krabang"
    ],
    "name:ita_x_preferred":[
        "Lat Krabang"
    ],
    "name:jpn_x_preferred":[
        "\u30e9\u30fc\u30c8\u30af\u30e9\u30d0\u30f3\u533a"
    ],
    "name:lao_x_preferred":[
        "\u0ec0\u0e82\u0e94\u0ea5\u0eb2\u0e94\u0e81\u0eb0\u0e9a\u0eb1\u0e87"
    ],
    "name:nld_x_preferred":[
        "Lat Krabang"
    ],
    "name:nob_x_preferred":[
        "Lat Krabang"
    ],
    "name:rus_x_preferred":[
        "\u041b\u0430\u0442\u043a\u0440\u0430\u0431\u0430\u043d\u0433"
    ],
    "name:sco_x_preferred":[
        "Lat Krabang Destrict"
    ],
    "name:sme_x_preferred":[
        "Lat Krabang"
    ],
    "name:spa_x_preferred":[
        "Lat Krabang"
    ],
    "name:tha_x_preferred":[
        "\u0e40\u0e02\u0e15\u0e25\u0e32\u0e14\u0e01\u0e23\u0e30\u0e1a\u0e31\u0e07"
    ],
    "name:urd_x_preferred":[
        "\u0644\u0627\u062a \u06a9\u0631\u0627\u0628\u0627\u0646\u06af \u0636\u0644\u0639"
    ],
    "name:vie_x_preferred":[
        "Lat Krabang"
    ],
    "name:zho_x_preferred":[
        "\u53fb\u7532\u633d\u7e23"
    ],
    "qs:name":"Khlong Sam Prawet",
    "qs:name_adm0":"Thailand",
    "qs:name_adm1":"Bangkok",
    "qs:photos":25,
    "qs:photos_1k":5,
    "qs:photos_9k":1,
    "qs:photos_9r":1,
    "qs:photos_all":25,
    "qs:photos_sr":1,
    "qs:placetype":"Town",
    "qs:pop_sr":"0",
    "wd:wordcount":248,
    "wof:name":"Khlong Sam Prawet",
    "wof:placetype":"locality"
},
  "geometry": {"coordinates":[100.733642,13.776388],"type":"Point"}
}