{
  "type": "Feature",
  "properties": {
    "iso:country":"TH",
    "qs:name":"Khlong Sam Prawet",
    "qs:name_adm0":"Thailand",
    "qs:name_adm1":"Bangkok",
    "qs:photos":25,
    "qs:photos_1k":5,
    "qs:photos_9k":1,
    "qs:photos_9r":1,
    "qs:photos_all":25,
    "qs:photos_sr":1,
    "qs:placetype":"Town",
    "qs:pop_sr":"0",
    "wd:wordcount":248,
    "wof:name":"Khlong Sam Prawet",
    "wof:placetype":"locality"
},
  "geometry": {"coordinates":[100.733642,13.776388],"type":"Point"}
}