{
  "type": "Feature",
  "properties": {
    "gn:admin1_code":"44.0",
    "gn:asciiname":"Ban Bang Krachet",
    "gn:country_code":"TH",
    "gn:dem":5,
    "gn:feature_class":"P",
    "gn:feature_code":"PPL",
    "gn:name":"Ban Bang Krachet",
    "gn:population":0,
    "gn:timezone":"Asia/Bangkok",
    "iso:country":"TH",
    "name:tha_x_preferred":[
        "\u0e1a\u0e49\u0e32\u0e19\u0e1a\u0e32\u0e07\u0e01\u0e23\u0e30\u0e40\u0e08\u0e47\u0e14"
    ],
    "name:und_x_variant":[
        "Krachet",
        "Ban Krachet",
        "Ban Bang Kachet",
        "Ban Bang Krachet"
    ],
    "wof:name":"Ban Bang Krachet",
    "wof:placetype":"locality"
},
  "geometry": {"coordinates":[101.18413,13.81735],"type":"Point"}
}