{
  "type": "Feature",
  "properties": {
    "gn:admin1_code":"25.0",
    "gn:asciiname":"Ban Sa-at Na Di",
    "gn:country_code":"TH",
    "gn:dem":159,
    "gn:feature_class":"P",
    "gn:feature_code":"PPL",
    "gn:name":"Ban Sa-at Na Di",
    "gn:population":0,
    "gn:timezone":"Asia/Bangkok",
    "iso:country":"TH",
    "name:tha_x_preferred":[
        "\u0e1a\u0e49\u0e32\u0e19\u0e2a\u0e30\u0e2d\u0e32\u0e14\u0e19\u0e32\u0e14\u0e35"
    ],
    "wof:name":"Ban Sa-at Na Di",
    "wof:placetype":"locality"
},
  "geometry": {"coordinates":[103.51606,16.10664],"type":"Point"}
}