{
  "type": "Feature",
  "properties": {
    "gn:admin1_code":"37",
    "gn:asciiname":"Ban Bu Mara",
    "gn:country_code":"TH",
    "gn:dem":75,
    "gn:feature_class":"P",
    "gn:feature_code":"PPL",
    "gn:name":"Ban Bu Mara",
    "gn:population":0,
    "gn:timezone":"Asia/Bangkok",
    "iso:country":"TH",
    "name:tha_x_preferred":[
        "\u0e1a\u0e49\u0e32\u0e19\u0e1a\u0e38\u0e21\u0e30\u0e23\u0e30"
    ],
    "wof:name":"Ban Bu Mara",
    "wof:placetype":"locality"
},
  "geometry": {"coordinates":[101.15469,14.42483],"type":"Point"}
}