{
  "type": "Feature",
  "properties": {
    "gn:admin1_code":"8.0",
    "gn:asciiname":"Ban Yokkrabat",
    "gn:country_code":"TH",
    "gn:dem":151,
    "gn:feature_class":"P",
    "gn:feature_code":"PPL",
    "gn:name":"Ban Yokkrabat",
    "gn:population":0,
    "gn:timezone":"Asia/Bangkok",
    "iso:country":"TH",
    "name:tha_x_preferred":[
        "Ban Yokkrabat"
    ],
    "name:tha_x_variant":[
        "\u0e1a\u0e49\u0e32\u0e19\u0e22\u0e01\u0e01\u0e23\u0e30\u0e1a\u0e31\u0e15\u0e23"
    ],
    "wof:name":"Ban Yokkrabat",
    "wof:placetype":"locality"
},
  "geometry": {"coordinates":[99.08094,17.31678],"type":"Point"}
}