{
  "type": "Feature",
  "properties": {
    "gn:admin1_code":"58.0",
    "gn:asciiname":"Ban Huai Kruat",
    "gn:country_code":"TH",
    "gn:dem":11,
    "gn:feature_class":"P",
    "gn:feature_code":"PPL",
    "gn:name":"Ban Huai Kruat",
    "gn:population":0,
    "gn:timezone":"Asia/Bangkok",
    "iso:country":"TH",
    "name:tha_x_preferred":[
        "\u0e1a\u0e49\u0e32\u0e19\u0e2b\u0e49\u0e27\u0e22\u0e01\u0e23\u0e27\u0e14"
    ],
    "name:und_x_variant":[
        "Huikr\u016bad",
        "Ban Huai Kruat"
    ],
    "wof:name":"Ban Huai Kruat",
    "wof:placetype":"locality"
},
  "geometry": {"coordinates":[99.12963999999999,10.18167],"type":"Point"}
}