{
  "type": "Feature",
  "properties": {
    "gn:admin1_code":"27.0",
    "gn:asciiname":"Ban Don",
    "gn:country_code":"TH",
    "gn:dem":217,
    "gn:feature_class":"P",
    "gn:feature_code":"PPL",
    "gn:name":"Ban Don",
    "gn:population":0,
    "gn:timezone":"Asia/Bangkok",
    "iso:country":"TH",
    "name:tha_x_preferred":[
        "\u0e1a\u0e49\u0e32\u0e19\u0e14\u0e2d\u0e19"
    ],
    "name:und_x_variant":[
        "B\u0101n Daun Ta Nin",
        "Ban Don Ta Nin",
        "B\u0101n Huai Lam",
        "Ban Huai Lam Choeng Krai",
        "Ban Don"
    ],
    "wof:name":"Ban Don",
    "wof:placetype":"locality"
},
  "geometry": {"coordinates":[101.75536,15.23058],"type":"Point"}
}