{
  "type": "Feature",
  "properties": {
    "gn:admin1_code":"6.0",
    "gn:asciiname":"Ban Mae Ta Luang",
    "gn:country_code":"TH",
    "gn:dem":310,
    "gn:feature_class":"P",
    "gn:feature_code":"PPL",
    "gn:name":"Ban Mae Ta Luang",
    "gn:population":0,
    "gn:timezone":"Asia/Bangkok",
    "iso:country":"TH",
    "name:tha_x_preferred":[
        "\u0e1a\u0e49\u0e32\u0e19\u0e41\u0e21\u0e48\u0e15\u0e32\u0e2b\u0e25\u0e27\u0e07"
    ],
    "name:und_x_variant":[
        "B\u0101n Mea Ta Luang",
        "Ban Mae Ta Luang"
    ],
    "wof:name":"Ban Mae Ta Luang",
    "wof:placetype":"locality"
},
  "geometry": {"coordinates":[99.61669000000001,18.75742],"type":"Point"}
}