{
  "type": "Feature",
  "properties": {
    "gn:admin1_code":"73.0",
    "gn:asciiname":"Ban Nong Khrong",
    "gn:country_code":"TH",
    "gn:dem":161,
    "gn:feature_class":"P",
    "gn:feature_code":"PPL",
    "gn:name":"Ban Nong Khrong",
    "gn:population":0,
    "gn:timezone":"Asia/Bangkok",
    "iso:country":"TH",
    "name:tha_x_preferred":[
        "\u0e1a\u0e49\u0e32\u0e19\u0e2b\u0e19\u0e2d\u0e07\u0e04\u0e23\u0e2d\u0e07"
    ],
    "wof:name":"Ban Nong Khrong",
    "wof:placetype":"locality"
},
  "geometry": {"coordinates":[104.51094999999999,17.03192],"type":"Point"}
}