{
  "type": "Feature",
  "properties": {
    "gn:admin1_code":"75.0",
    "gn:asciiname":"Ban Som Sa-at",
    "gn:country_code":"TH",
    "gn:dem":138,
    "gn:feature_class":"P",
    "gn:feature_code":"PPL",
    "gn:name":"Ban Som Sa-at",
    "gn:population":0,
    "gn:timezone":"Asia/Bangkok",
    "iso:country":"TH",
    "name:tha_x_preferred":[
        "\u0e1a\u0e49\u0e32\u0e19\u0e2a\u0e21\u0e2a\u0e30\u0e2d\u0e32\u0e14"
    ],
    "name:und_x_variant":[
        "Som Sahat",
        "Ban Som Sa-at"
    ],
    "wof:name":"Ban Som Sa-at",
    "wof:placetype":"locality"
},
  "geometry": {"coordinates":[105.10544,14.94442],"type":"Point"}
}