{
  "type": "Feature",
  "properties": {
    "gn:admin1_code":"20.0",
    "gn:asciiname":"Ban Tham Tio",
    "gn:country_code":"TH",
    "gn:dem":226,
    "gn:feature_class":"P",
    "gn:feature_code":"PPL",
    "gn:name":"Ban Tham Tio",
    "gn:population":0,
    "gn:timezone":"Asia/Bangkok",
    "iso:country":"TH",
    "name:tha_x_preferred":[
        "\u0e1a\u0e49\u0e32\u0e19\u0e16\u0e49\u0e33\u0e15\u0e34\u0e49\u0e27"
    ],
    "wof:name":"Ban Tham Tio",
    "wof:placetype":"locality"
},
  "geometry": {"coordinates":[103.44665000000001,17.29926],"type":"Point"}
}