{
  "type": "Feature",
  "properties": {
    "gn:admin1_code":"29.0",
    "gn:asciiname":"Ban Nong Ra-ang",
    "gn:country_code":"TH",
    "gn:dem":186,
    "gn:feature_class":"P",
    "gn:feature_code":"PPL",
    "gn:name":"Ban Nong Ra-ang",
    "gn:population":0,
    "gn:timezone":"Asia/Bangkok",
    "iso:country":"TH",
    "name:tha_x_preferred":[
        "\u0e1a\u0e49\u0e32\u0e19\u0e2b\u0e19\u0e2d\u0e07\u0e23\u0e30\u0e2d\u0e32\u0e07"
    ],
    "name:und_x_variant":[
        "Ban Nikhom Soi 14",
        "Ban Nong Ra-ang"
    ],
    "wof:name":"Ban Nong Ra-ang",
    "wof:placetype":"locality"
},
  "geometry": {"coordinates":[103.35489,14.48408],"type":"Point"}
}