{
  "type": "Feature",
  "properties": {
    "gn:admin1_code":"47.0",
    "gn:asciiname":"Ban Khlong Kha",
    "gn:country_code":"TH",
    "gn:dem":38,
    "gn:feature_class":"P",
    "gn:feature_code":"PPL",
    "gn:name":"Ban Khlong Kha",
    "gn:population":0,
    "gn:timezone":"Asia/Bangkok",
    "iso:country":"TH",
    "name:tha_x_preferred":[
        "\u0e1a\u0e49\u0e32\u0e19\u0e04\u0e25\u0e2d\u0e07\u0e04\u0e32"
    ],
    "name:und_x_variant":[
        "Ban Khlong Kha (1)"
    ],
    "wof:name":"Ban Khlong Kha",
    "wof:placetype":"locality"
},
  "geometry": {"coordinates":[101.59139,12.73278],"type":"Point"}
}