{
  "type": "Feature",
  "properties": {
    "gn:admin1_code":"70.0",
    "gn:asciiname":"Ban Bue Ka Sa Ma",
    "gn:country_code":"TH",
    "gn:dem":19,
    "gn:feature_class":"P",
    "gn:feature_code":"PPL",
    "gn:name":"Ban Bue Ka Sa Ma",
    "gn:population":0,
    "gn:timezone":"Asia/Bangkok",
    "iso:country":"TH",
    "name:tha_x_preferred":[
        "\u0e1a\u0e49\u0e32\u0e19\u0e1a\u0e37\u0e2d\u0e01\u0e30\u0e2a\u0e30\u0e21\u0e32"
    ],
    "wof:name":"Ban Bue Ka Sa Ma",
    "wof:placetype":"locality"
},
  "geometry": {"coordinates":[101.38444,6.5172],"type":"Point"}
}