{
  "type": "Feature",
  "properties": {
    "gn:admin1_code":"64.0",
    "gn:asciiname":"Ban Sai Na Sung",
    "gn:country_code":"TH",
    "gn:dem":60,
    "gn:feature_class":"P",
    "gn:feature_code":"PPL",
    "gn:name":"Ban Sai Na Sung",
    "gn:population":0,
    "gn:timezone":"Asia/Bangkok",
    "iso:country":"TH",
    "name:tha_x_preferred":[
        "\u0e1a\u0e49\u0e32\u0e19\u0e43\u0e2a\u0e2b\u0e19\u0e32\u0e2a\u0e39\u0e07"
    ],
    "wof:name":"Ban Sai Na Sung",
    "wof:placetype":"locality"
},
  "geometry": {"coordinates":[99.59186,8.13708],"type":"Point"}
}