{
  "type": "Feature",
  "properties": {
    "gn:admin1_code":"15.0",
    "gn:asciiname":"Ban Ka Lot Buang",
    "gn:country_code":"TH",
    "gn:dem":110,
    "gn:feature_class":"P",
    "gn:feature_code":"PPL",
    "gn:name":"Ban Ka Lot Buang",
    "gn:population":0,
    "gn:timezone":"Asia/Bangkok",
    "iso:country":"TH",
    "name:tha_x_preferred":[
        "\u0e1a\u0e49\u0e32\u0e19\u0e01\u0e32\u0e25\u0e2d\u0e14\u0e1a\u0e48\u0e27\u0e07"
    ],
    "wof:name":"Ban Ka Lot Buang",
    "wof:placetype":"locality"
},
  "geometry": {"coordinates":[99.56569,15.40861],"type":"Point"}
}