{
  "type": "Feature",
  "properties": {
    "gn:admin1_code":"60.0",
    "gn:asciiname":"Ban Thap Chan",
    "gn:country_code":"TH",
    "gn:dem":33,
    "gn:feature_class":"P",
    "gn:feature_code":"PPL",
    "gn:name":"Ban Thap Chan",
    "gn:population":0,
    "gn:timezone":"Asia/Bangkok",
    "iso:country":"TH",
    "name:tha_x_preferred":[
        "\u0e1a\u0e49\u0e32\u0e19\u0e17\u0e31\u0e1a\u0e0a\u0e31\u0e19"
    ],
    "wof:name":"Ban Thap Chan",
    "wof:placetype":"locality"
},
  "geometry": {"coordinates":[99.07474999999999,9.65075],"type":"Point"}
}