{
  "type": "Feature",
  "properties": {
    "gn:admin1_code":"46.0",
    "gn:asciiname":"Ban Nong Plalai",
    "gn:country_code":"TH",
    "gn:dem":27,
    "gn:feature_class":"P",
    "gn:feature_code":"PPL",
    "gn:name":"Ban Nong Plalai",
    "gn:population":0,
    "gn:timezone":"Asia/Bangkok",
    "iso:country":"TH",
    "name:tha_x_preferred":[
        "\u0e1a\u0e49\u0e32\u0e19\u0e2b\u0e19\u0e2d\u0e07\u0e1b\u0e25\u0e32\u0e44\u0e2b\u0e25"
    ],
    "name:und_x_variant":[
        "Ban Hnong Plahlai",
        "Naung Pla Lai",
        "Ban Hnohng Pl\u0101 Hiai",
        "Ban Nong Plalai"
    ],
    "wof:name":"Ban Nong Plalai",
    "wof:placetype":"locality"
},
  "geometry": {"coordinates":[100.94458,12.97022],"type":"Point"}
}