{
  "type": "Feature",
  "properties": {
    "gn:admin1_code":"50.0",
    "gn:asciiname":"Ban Mae Krathang",
    "gn:cc2":"TH",
    "gn:country_code":"TH",
    "gn:dem":172,
    "gn:feature_class":"P",
    "gn:feature_code":"PPL",
    "gn:name":"Ban Mae Krathang",
    "gn:population":0,
    "gn:timezone":"Asia/Bangkok",
    "iso:country":"TH",
    "name:und_x_variant":[
        "Ban Mae Kathang",
        "Ban Mae Krathang"
    ],
    "wof:name":"Ban Mae Krathang",
    "wof:placetype":"locality"
},
  "geometry": {"coordinates":[99.05472,14.56278],"type":"Point"}
}