{
  "type": "Feature",
  "properties": {
    "gn:admin1_code":"18.0",
    "gn:asciiname":"Ban Pak Mang",
    "gn:country_code":"TH",
    "gn:dem":199,
    "gn:feature_class":"P",
    "gn:feature_code":"PPL",
    "gn:name":"Ban Pak Mang",
    "gn:population":0,
    "gn:timezone":"Asia/Bangkok",
    "iso:country":"TH",
    "name:tha_x_preferred":[
        "\u0e1a\u0e49\u0e32\u0e19\u0e1b\u0e32\u0e01\u0e21\u0e31\u0e48\u0e07"
    ],
    "wof:name":"Ban Pak Mang",
    "wof:placetype":"locality"
},
  "geometry": {"coordinates":[102.00867,18.13008],"type":"Point"}
}