{
  "type": "Feature",
  "properties": {
    "gn:admin1_code":"75.0",
    "gn:asciiname":"Ban Sisa Krabue",
    "gn:country_code":"TH",
    "gn:dem":130,
    "gn:feature_class":"P",
    "gn:feature_code":"PPL",
    "gn:name":"Ban Sisa Krabue",
    "gn:population":0,
    "gn:timezone":"Asia/Bangkok",
    "iso:country":"TH",
    "name:tha_x_preferred":[
        "\u0e1a\u0e49\u0e32\u0e19\u0e28\u0e35\u0e23\u0e29\u0e30\u0e01\u0e23\u0e30\u0e1a\u0e37\u0e2d"
    ],
    "wof:name":"Ban Sisa Krabue",
    "wof:placetype":"locality"
},
  "geometry": {"coordinates":[104.8725,15.12089],"type":"Point"}
}