{
  "type": "Feature",
  "properties": {
    "gn:admin1_code":"12.0",
    "gn:asciiname":"Ban Bung Ta Rot",
    "gn:country_code":"TH",
    "gn:dem":215,
    "gn:feature_class":"P",
    "gn:feature_code":"PPL",
    "gn:name":"Ban Bung Ta Rot",
    "gn:population":0,
    "gn:timezone":"Asia/Bangkok",
    "iso:country":"TH",
    "name:tha_x_preferred":[
        "\u0e1a\u0e49\u0e32\u0e19\u0e1a\u0e38\u0e48\u0e07\u0e15\u0e32\u0e23\u0e2d\u0e14"
    ],
    "wof:name":"Ban Bung Ta Rot",
    "wof:placetype":"locality"
},
  "geometry": {"coordinates":[100.90278000000001,17.15506],"type":"Point"}
}