{
  "type": "Feature",
  "properties": {
    "gn:admin1_code":"27.0",
    "gn:asciiname":"Ban Non Tan Yai",
    "gn:country_code":"TH",
    "gn:dem":198,
    "gn:feature_class":"P",
    "gn:feature_code":"PPL",
    "gn:name":"Ban Non Tan Yai",
    "gn:population":0,
    "gn:timezone":"Asia/Bangkok",
    "iso:country":"TH",
    "name:tha_x_preferred":[
        "\u0e1a\u0e49\u0e32\u0e19\u0e42\u0e19\u0e19\u0e15\u0e32\u0e25\u0e43\u0e2b\u0e0d\u0e48"
    ],
    "wof:name":"Ban Non Tan Yai",
    "wof:placetype":"locality"
},
  "geometry": {"coordinates":[101.97581,15.03181],"type":"Point"}
}