{
  "type": "Feature",
  "properties": {
    "gn:admin1_code":"37",
    "gn:asciiname":"Ban Pong Keng",
    "gn:country_code":"TH",
    "gn:dem":176,
    "gn:feature_class":"P",
    "gn:feature_code":"PPL",
    "gn:name":"Ban Pong Keng",
    "gn:population":0,
    "gn:timezone":"Asia/Bangkok",
    "iso:country":"TH",
    "name:tha_x_preferred":[
        "\u0e1a\u0e49\u0e32\u0e19\u0e42\u0e1b\u0e48\u0e07\u0e40\u0e01\u0e49\u0e07"
    ],
    "wof:name":"Ban Pong Keng",
    "wof:placetype":"locality"
},
  "geometry": {"coordinates":[101.20699999999999,14.83547],"type":"Point"}
}