{
  "type": "Feature",
  "properties": {
    "gn:admin1_code":"50.0",
    "gn:asciiname":"Ban Hua Phong",
    "gn:country_code":"TH",
    "gn:dem":25,
    "gn:feature_class":"P",
    "gn:feature_code":"PPL",
    "gn:name":"Ban Hua Phong",
    "gn:population":0,
    "gn:timezone":"Asia/Bangkok",
    "iso:country":"TH",
    "name:tha_x_preferred":[
        "\u0e1a\u0e49\u0e32\u0e19\u0e2b\u0e31\u0e27\u0e1e\u0e07\u0e29\u0e4c"
    ],
    "wof:name":"Ban Hua Phong",
    "wof:placetype":"locality"
},
  "geometry": {"coordinates":[99.70961,13.95042],"type":"Point"}
}