{
  "type": "Feature",
  "properties": {
    "gn:admin1_code":"24",
    "gn:asciiname":"Ban Kham Kaen Khun",
    "gn:country_code":"TH",
    "gn:dem":163,
    "gn:feature_class":"P",
    "gn:feature_code":"PPL",
    "gn:name":"Ban Kham Kaen Khun",
    "gn:population":0,
    "gn:timezone":"Asia/Bangkok",
    "iso:country":"TH",
    "name:tha_x_preferred":[
        "\u0e1a\u0e49\u0e32\u0e19\u0e04\u0e33\u0e41\u0e01\u0e48\u0e19\u0e04\u0e39\u0e13"
    ],
    "wof:name":"Ban Kham Kaen Khun",
    "wof:placetype":"locality"
},
  "geometry": {"coordinates":[103.38124999999999,16.05544],"type":"Point"}
}