{
  "type": "Feature",
  "properties": {
    "gn:admin1_code":"70.0",
    "gn:asciiname":"Kampong Batungo",
    "gn:country_code":"TH",
    "gn:dem":50,
    "gn:feature_class":"P",
    "gn:feature_code":"PPL",
    "gn:name":"Kampong Batungo",
    "gn:population":0,
    "gn:timezone":"Asia/Bangkok",
    "iso:country":"TH",
    "wof:name":"Kampong Batungo",
    "wof:placetype":"locality"
},
  "geometry": {"coordinates":[101.26667,6.23333],"type":"Point"}
}