{
  "type": "Feature",
  "properties": {
    "gn:admin1_code":"68.0",
    "gn:asciiname":"Ban Plak Khui",
    "gn:country_code":"TH",
    "gn:dem":7,
    "gn:feature_class":"P",
    "gn:feature_code":"PPL",
    "gn:name":"Ban Plak Khui",
    "gn:population":0,
    "gn:timezone":"Asia/Bangkok",
    "iso:country":"TH",
    "name:tha_x_preferred":[
        "\u0e1a\u0e49\u0e32\u0e19\u0e1b\u0e25\u0e31\u0e01\u0e04\u0e38\u0e22"
    ],
    "wof:lang_x_official":[
        "tha"
    ],
    "wof:lang_x_spoken":[
        "tha"
    ],
    "wof:name":"Ban Plak Khui",
    "wof:placetype":"locality"
},
  "geometry": {"coordinates":[100.75852999999999,6.94322],"type":"Point"}
}