{
  "type": "Feature",
  "properties": {
    "gn:admin1_code":"3.0",
    "gn:asciiname":"Ban San Sai Na Pong",
    "gn:country_code":"TH",
    "gn:dem":391,
    "gn:feature_class":"P",
    "gn:feature_code":"PPL",
    "gn:name":"Ban San Sai Na Pong",
    "gn:population":0,
    "gn:timezone":"Asia/Bangkok",
    "iso:country":"TH",
    "name:tha_x_preferred":[
        "\u0e1a\u0e49\u0e32\u0e19\u0e2a\u0e31\u0e19\u0e17\u0e23\u0e32\u0e22\u0e19\u0e32\u0e1b\u0e07"
    ],
    "name:und_x_variant":[
        "Ban Na Pung",
        "Ban San Sai Na Pong"
    ],
    "wof:name":"Ban San Sai Na Pong",
    "wof:placetype":"locality"
},
  "geometry": {"coordinates":[99.8805,20.35219],"type":"Point"}
}