{
  "type": "Feature",
  "properties": {
    "gn:admin1_code":"30.0",
    "gn:asciiname":"Ban Kaban",
    "gn:cc2":"TH",
    "gn:country_code":"TH",
    "gn:dem":142,
    "gn:feature_class":"P",
    "gn:feature_code":"PPL",
    "gn:name":"Ban Kaban",
    "gn:population":0,
    "gn:timezone":"Asia/Bangkok",
    "iso:country":"TH",
    "name:und_x_variant":[
        "Kandan",
        "Ban Kaban"
    ],
    "wof:name":"Ban Kaban",
    "wof:placetype":"locality"
},
  "geometry": {"coordinates":[104.08333,15.08333],"type":"Point"}
}