{
  "type": "Feature",
  "properties": {
    "gn:admin1_code":"48.0",
    "gn:asciiname":"Ban Sam Phan",
    "gn:country_code":"TH",
    "gn:dem":15,
    "gn:feature_class":"P",
    "gn:feature_code":"PPL",
    "gn:name":"Ban Sam Phan",
    "gn:population":0,
    "gn:timezone":"Asia/Bangkok",
    "iso:country":"TH",
    "name:tha_x_preferred":[
        "\u0e1a\u0e49\u0e32\u0e19\u0e2a\u0e32\u0e21\u0e1c\u0e32\u0e19"
    ],
    "wof:name":"Ban Sam Phan",
    "wof:placetype":"locality"
},
  "geometry": {"coordinates":[101.98822,12.67361],"type":"Point"}
}