{
  "type": "Feature",
  "properties": {
    "gn:admin1_code":"14.0",
    "gn:asciiname":"Ban Khok Nong Chaeng",
    "gn:country_code":"TH",
    "gn:dem":74,
    "gn:feature_class":"P",
    "gn:feature_code":"PPL",
    "gn:name":"Ban Khok Nong Chaeng",
    "gn:population":0,
    "gn:timezone":"Asia/Bangkok",
    "iso:country":"TH",
    "name:tha_x_preferred":[
        "\u0e1a\u0e49\u0e32\u0e19\u0e42\u0e04\u0e01\u0e2b\u0e19\u0e2d\u0e07\u0e41\u0e08\u0e07"
    ],
    "wof:name":"Ban Khok Nong Chaeng",
    "wof:placetype":"locality"
},
  "geometry": {"coordinates":[101.06706,15.63014],"type":"Point"}
}