{
  "type": "Feature",
  "properties": {
    "gn:admin1_code":"2.0",
    "gn:asciiname":"Fang",
    "gn:country_code":"TH",
    "gn:dem":471,
    "gn:feature_class":"P",
    "gn:feature_code":"PPLA2",
    "gn:name":"Fang",
    "gn:population":7635,
    "gn:timezone":"Asia/Bangkok",
    "iso:country":"TH",
    "name:afr_x_preferred":[
        "Slagtand"
    ],
    "name:ara_x_preferred":[
        "\u0646\u0627\u0628 \u062f\u0627\u062e\u0644\u064a"
    ],
    "name:arc_x_preferred":[
        "\u0728\u0721\u0718\u072a\u072c\u0710"
    ],
    "name:deu_x_preferred":[
        "Fangzahn"
    ],
    "name:fra_x_preferred":[
        "Croc"
    ],
    "name:msa_x_preferred":[
        "Taring"
    ],
    "name:nor_x_preferred":[
        "Hoggtann"
    ],
    "name:ron_x_preferred":[
        "Col\u021b"
    ],
    "name:rus_x_preferred":[
        "\u0424\u0430\u043d\u0433"
    ],
    "name:tel_x_preferred":[
        "\u0c15\u0c4b\u0c30"
    ],
    "name:tha_x_preferred":[
        "\u0e1d\u0e32\u0e07"
    ],
    "name:und_x_variant":[
        "Moeang Fhang",
        "Ban Nai Wiang",
        "Fh\u0101ng",
        "Amphoe Moeangfhang",
        "Muang Fang",
        "Amphoe Fang",
        "Muang Pang",
        "Amphoe Moeang Bhang",
        "Amphoe Muang Fang",
        "Fang"
    ],
    "name:vie_x_preferred":[
        "Nanh"
    ],
    "wof:name":"Fang",
    "wof:placetype":"locality",
    "wof:population":7635
},
  "geometry": {"coordinates":[99.2145,19.91689],"type":"Point"}
}