{
  "type": "Feature",
  "properties": {
    "gn:admin1_code":"2.0",
    "gn:asciiname":"Fang",
    "gn:country_code":"TH",
    "gn:dem":471,
    "gn:feature_class":"P",
    "gn:feature_code":"PPLA2",
    "gn:name":"Fang",
    "gn:population":7635,
    "gn:timezone":"Asia/Bangkok",
    "iso:country":"TH",
    "name:rus_x_preferred":[
        "\u0424\u0430\u043d\u0433"
    ],
    "name:tha_x_preferred":[
        "\u0e1d\u0e32\u0e07"
    ],
    "name:und_x_variant":[
        "Moeang Fhang",
        "Ban Nai Wiang",
        "Fh\u0101ng",
        "Amphoe Moeangfhang",
        "Muang Fang",
        "Amphoe Fang",
        "Muang Pang",
        "Amphoe Moeang Bhang",
        "Amphoe Muang Fang",
        "Fang"
    ],
    "wof:name":"Fang",
    "wof:placetype":"locality",
    "wof:population":7635
},
  "geometry": {"coordinates":[99.2145,19.91689],"type":"Point"}
}