{
  "type": "Feature",
  "properties": {
    "gn:admin1_code":"28",
    "gn:asciiname":"Ban Khok Khwai",
    "gn:country_code":"TH",
    "gn:dem":186,
    "gn:feature_class":"P",
    "gn:feature_code":"PPL",
    "gn:name":"Ban Khok Khwai",
    "gn:population":0,
    "gn:timezone":"Asia/Bangkok",
    "iso:country":"TH",
    "name:tha_x_preferred":[
        "\u0e1a\u0e49\u0e32\u0e19\u0e04\u0e2d\u0e01\u0e04\u0e27\u0e32\u0e22"
    ],
    "wof:name":"Ban Khok Khwai",
    "wof:placetype":"locality"
},
  "geometry": {"coordinates":[102.79825,14.68464],"type":"Point"}
}