{
  "type": "Feature",
  "properties": {
    "gn:admin1_code":"58.0",
    "gn:asciiname":"Ban Saeng Daet",
    "gn:country_code":"TH",
    "gn:dem":11,
    "gn:feature_class":"P",
    "gn:feature_code":"PPL",
    "gn:name":"Ban Saeng Daet",
    "gn:population":0,
    "gn:timezone":"Asia/Bangkok",
    "iso:country":"TH",
    "name:tha_x_preferred":[
        "\u0e1a\u0e49\u0e32\u0e19\u0e41\u0e2a\u0e07\u0e41\u0e14\u0e14"
    ],
    "name:und_x_variant":[
        "Seng Ded",
        "Saeng Daet",
        "Ban Saeng Daet"
    ],
    "wof:name":"Ban Saeng Daet",
    "wof:placetype":"locality"
},
  "geometry": {"coordinates":[99.15716,10.4783],"type":"Point"}
}