{
  "type": "Feature",
  "properties": {
    "gn:admin1_code":"52.0",
    "gn:asciiname":"Ban Chuk Maphrao",
    "gn:country_code":"TH",
    "gn:dem":13,
    "gn:feature_class":"P",
    "gn:feature_code":"PPL",
    "gn:name":"Ban Chuk Maphrao",
    "gn:population":0,
    "gn:timezone":"Asia/Bangkok",
    "iso:country":"TH",
    "name:tha_x_preferred":[
        "\u0e1a\u0e49\u0e32\u0e19\u0e08\u0e38\u0e01\u0e21\u0e30\u0e1e\u0e23\u0e49\u0e32\u0e27"
    ],
    "wof:name":"Ban Chuk Maphrao",
    "wof:placetype":"locality"
},
  "geometry": {"coordinates":[99.85047,13.60678],"type":"Point"}
}