{
  "type": "Feature",
  "properties": {
    "gn:admin1_code":"64.0",
    "gn:asciiname":"Ban Bang Khem",
    "gn:country_code":"TH",
    "gn:dem":7,
    "gn:feature_class":"P",
    "gn:feature_code":"PPL",
    "gn:name":"Ban Bang Khem",
    "gn:population":0,
    "gn:timezone":"Asia/Bangkok",
    "iso:country":"TH",
    "name:tha_x_preferred":[
        "\u0e1a\u0e49\u0e32\u0e19\u0e1a\u0e32\u0e07\u0e40\u0e02\u0e47\u0e21"
    ],
    "name:und_x_variant":[
        "Bang Khem Tai",
        "Ban Bang Khem Nua",
        "Bang Khem",
        "Ban Bang Khaem",
        "Bang Khem Nua",
        "Ban Bang Khem Tai",
        "Ban Bang Khem"
    ],
    "wof:name":"Ban Bang Khem",
    "wof:placetype":"locality"
},
  "geometry": {"coordinates":[100.19664,8.24067],"type":"Point"}
}