{
  "type": "Feature",
  "properties": {
    "gn:admin1_code":"49.0",
    "gn:asciiname":"Ban Khlong Puk",
    "gn:country_code":"TH",
    "gn:dem":35,
    "gn:feature_class":"P",
    "gn:feature_code":"PPL",
    "gn:name":"Ban Khlong Puk",
    "gn:population":0,
    "gn:timezone":"Asia/Bangkok",
    "iso:country":"TH",
    "name:tha_x_preferred":[
        "\u0e1a\u0e49\u0e32\u0e19\u0e04\u0e25\u0e2d\u0e07\u0e1b\u0e38\u0e01"
    ],
    "name:und_x_variant":[
        "Aeng Pok",
        "Ban Aeng Puk",
        "Ban Khlong Puk"
    ],
    "wof:name":"Ban Khlong Puk",
    "wof:placetype":"locality"
},
  "geometry": {"coordinates":[102.44333,12.57242],"type":"Point"}
}