{
  "type": "Feature",
  "properties": {
    "gn:admin1_code":"56.0",
    "gn:asciiname":"Ban Phu Pladuk",
    "gn:country_code":"TH",
    "gn:dem":137,
    "gn:feature_class":"P",
    "gn:feature_code":"PPL",
    "gn:name":"Ban Phu Pladuk",
    "gn:population":0,
    "gn:timezone":"Asia/Bangkok",
    "iso:country":"TH",
    "name:tha_x_preferred":[
        "\u0e1a\u0e49\u0e32\u0e19\u0e1e\u0e38\u0e1b\u0e25\u0e32\u0e14\u0e38\u0e01"
    ],
    "wof:name":"Ban Phu Pladuk",
    "wof:placetype":"locality"
},
  "geometry": {"coordinates":[99.58060999999999,12.84983],"type":"Point"}
}