{
  "type": "Feature",
  "properties": {
    "gn:admin1_code":"15.0",
    "gn:asciiname":"Ban Pak Kuai",
    "gn:country_code":"TH",
    "gn:dem":151,
    "gn:feature_class":"P",
    "gn:feature_code":"PPL",
    "gn:name":"Ban Pak Kuai",
    "gn:population":0,
    "gn:timezone":"Asia/Bangkok",
    "iso:country":"TH",
    "name:tha_x_preferred":[
        "\u0e1a\u0e49\u0e32\u0e19\u0e1b\u0e32\u0e01\u0e01\u0e49\u0e27\u0e22"
    ],
    "wof:name":"Ban Pak Kuai",
    "wof:placetype":"locality"
},
  "geometry": {"coordinates":[99.53239000000001,15.13206],"type":"Point"}
}