{
  "type": "Feature",
  "properties": {
    "gn:admin1_code":"27.0",
    "gn:asciiname":"Ban Ba Dan",
    "gn:country_code":"TH",
    "gn:dem":236,
    "gn:feature_class":"P",
    "gn:feature_code":"PPL",
    "gn:name":"Ban Ba Dan",
    "gn:population":0,
    "gn:timezone":"Asia/Bangkok",
    "iso:country":"TH",
    "name:tha_x_preferred":[
        "\u0e1a\u0e49\u0e32\u0e19\u0e1a\u0e30\u0e14\u0e48\u0e32\u0e19"
    ],
    "name:und_x_variant":[
        "Ban Ban Dan"
    ],
    "wof:name":"Ban Ba Dan",
    "wof:placetype":"locality"
},
  "geometry": {"coordinates":[101.96693999999999,14.52972],"type":"Point"}
}