{
  "type": "Feature",
  "properties": {
    "gn:admin1_code":"1.0",
    "gn:asciiname":"Ban Huai Pu Loei",
    "gn:country_code":"TH",
    "gn:dem":1148,
    "gn:feature_class":"P",
    "gn:feature_code":"PPL",
    "gn:name":"Ban Huai Pu Loei",
    "gn:population":0,
    "gn:timezone":"Asia/Bangkok",
    "iso:country":"TH",
    "name:tha_x_preferred":[
        "\u0e1a\u0e49\u0e32\u0e19\u0e2b\u0e49\u0e27\u0e22\u0e1b\u0e39\u0e40\u0e25\u0e22"
    ],
    "wof:name":"Ban Huai Pu Loei",
    "wof:placetype":"locality"
},
  "geometry": {"coordinates":[98.20889,19.14544],"type":"Point"}
}