{
  "type": "Feature",
  "properties": {
    "gn:admin1_code":"53.0",
    "gn:asciiname":"Muban Kannasut Riwoe Wio",
    "gn:country_code":"TH",
    "gn:dem":5,
    "gn:feature_class":"P",
    "gn:feature_code":"PPL",
    "gn:name":"Muban Kannasut Riwoe Wio",
    "gn:population":0,
    "gn:timezone":"Asia/Bangkok",
    "iso:country":"TH",
    "name:tha_x_preferred":[
        "\u0e2b\u0e21\u0e39\u0e48\u0e1a\u0e49\u0e32\u0e19\u0e01\u0e23\u0e23\u0e13\u0e2a\u0e39\u0e15\u0e23\u0e34\u0e40\u0e27\u0e2d\u0e23\u0e4c\u0e27\u0e34\u0e25\u0e25\u0e4c"
    ],
    "wof:name":"Muban Kannasut Riwoe Wio",
    "wof:placetype":"locality"
},
  "geometry": {"coordinates":[100.20925,13.81414],"type":"Point"}
}