{
  "type": "Feature",
  "properties": {
    "gn:admin1_code":"23.0",
    "gn:asciiname":"Ban Muang Na Di",
    "gn:country_code":"TH",
    "gn:dem":187,
    "gn:feature_class":"P",
    "gn:feature_code":"PPL",
    "gn:name":"Ban Muang Na Di",
    "gn:population":0,
    "gn:timezone":"Asia/Bangkok",
    "iso:country":"TH",
    "name:tha_x_preferred":[
        "\u0e1a\u0e49\u0e32\u0e19\u0e21\u0e48\u0e27\u0e07\u0e19\u0e32\u0e14\u0e35"
    ],
    "wof:name":"Ban Muang Na Di",
    "wof:placetype":"locality"
},
  "geometry": {"coordinates":[103.98583000000001,16.74481],"type":"Point"}
}