{
  "type": "Feature",
  "properties": {
    "gn:admin1_code":"44.0",
    "gn:asciiname":"Ban Khlong Khun Phithak",
    "gn:country_code":"TH",
    "gn:dem":2,
    "gn:feature_class":"P",
    "gn:feature_code":"PPL",
    "gn:name":"Ban Khlong Khun Phithak",
    "gn:population":0,
    "gn:timezone":"Asia/Bangkok",
    "iso:country":"TH",
    "name:tha_x_preferred":[
        "\u0e1a\u0e49\u0e32\u0e19\u0e04\u0e25\u0e2d\u0e07\u0e02\u0e38\u0e19\u0e1e\u0e34\u0e17\u0e31\u0e01\u0e29\u0e4c"
    ],
    "wof:name":"Ban Khlong Khun Phithak",
    "wof:placetype":"locality"
},
  "geometry": {"coordinates":[100.976,13.60003],"type":"Point"}
}