{
  "type": "Feature",
  "properties": {
    "gn:admin1_code":"68.0",
    "gn:asciiname":"Ban Wat Boek",
    "gn:country_code":"TH",
    "gn:dem":4,
    "gn:feature_class":"P",
    "gn:feature_code":"PPL",
    "gn:name":"Ban Wat Boek",
    "gn:population":0,
    "gn:timezone":"Asia/Bangkok",
    "iso:country":"TH",
    "name:tha_x_preferred":[
        "\u0e1a\u0e49\u0e32\u0e19\u0e27\u0e31\u0e14\u0e40\u0e1a\u0e34\u0e01"
    ],
    "wof:name":"Ban Wat Boek",
    "wof:placetype":"locality"
},
  "geometry": {"coordinates":[100.37194,7.72372],"type":"Point"}
}