{
  "type": "Feature",
  "properties": {
    "gn:admin1_code":"27",
    "gn:asciiname":"Ban Nong Bua Sa-at",
    "gn:country_code":"TH",
    "gn:dem":184,
    "gn:feature_class":"P",
    "gn:feature_code":"PPL",
    "gn:name":"Ban Nong Bua Sa-at",
    "gn:population":0,
    "gn:timezone":"Asia/Bangkok",
    "iso:country":"TH",
    "name:tha_x_preferred":[
        "\u0e1a\u0e49\u0e32\u0e19\u0e2b\u0e19\u0e2d\u0e07\u0e1a\u0e31\u0e27\u0e2a\u0e30\u0e2d\u0e32\u0e14"
    ],
    "wof:name":"Ban Nong Bua Sa-at",
    "wof:placetype":"locality"
},
  "geometry": {"coordinates":[102.35092,15.58142],"type":"Point"}
}