{
  "type": "Feature",
  "properties": {
    "gn:admin1_code":"25.0",
    "gn:asciiname":"Ban Pho Roi Ton",
    "gn:country_code":"TH",
    "gn:dem":159,
    "gn:feature_class":"P",
    "gn:feature_code":"PPL",
    "gn:name":"Ban Pho Roi Ton",
    "gn:population":0,
    "gn:timezone":"Asia/Bangkok",
    "iso:country":"TH",
    "name:tha_x_preferred":[
        "\u0e1a\u0e49\u0e32\u0e19\u0e42\u0e1e\u0e18\u0e34\u0e4c\u0e23\u0e49\u0e2d\u0e22\u0e15\u0e49\u0e19"
    ],
    "wof:name":"Ban Pho Roi Ton",
    "wof:placetype":"locality"
},
  "geometry": {"coordinates":[103.93658000000001,16.32156],"type":"Point"}
}