{
  "type": "Feature",
  "properties": {
    "gn:admin1_code":"47.0",
    "gn:asciiname":"Ban Chak Kabok",
    "gn:cc2":"TH",
    "gn:country_code":"TH",
    "gn:dem":22,
    "gn:feature_class":"P",
    "gn:feature_code":"PPL",
    "gn:name":"Ban Chak Kabok",
    "gn:population":0,
    "gn:timezone":"Asia/Bangkok",
    "iso:country":"TH",
    "name:und_x_variant":[
        "Ban Chak Bok",
        "Ban Chak Kabok"
    ],
    "wof:name":"Ban Chak Kabok",
    "wof:placetype":"locality"
},
  "geometry": {"coordinates":[101.33333,12.76667],"type":"Point"}
}