{
  "type": "Feature",
  "properties": {
    "gn:admin1_code":"14.0",
    "gn:asciiname":"Ban Pak Khlong Phon",
    "gn:country_code":"TH",
    "gn:dem":109,
    "gn:feature_class":"P",
    "gn:feature_code":"PPL",
    "gn:name":"Ban Pak Khlong Phon",
    "gn:population":0,
    "gn:timezone":"Asia/Bangkok",
    "iso:country":"TH",
    "name:tha_x_preferred":[
        "\u0e1a\u0e49\u0e32\u0e19\u0e1b\u0e32\u0e01\u0e04\u0e25\u0e2d\u0e07\u0e1e\u0e25"
    ],
    "wof:name":"Ban Pak Khlong Phon",
    "wof:placetype":"locality"
},
  "geometry": {"coordinates":[101.11856,16.18711],"type":"Point"}
}