{
  "type": "Feature",
  "properties": {
    "gn:admin1_code":"22.0",
    "gn:asciiname":"Ban Wang Khon Phat",
    "gn:country_code":"TH",
    "gn:dem":206,
    "gn:feature_class":"P",
    "gn:feature_code":"PPL",
    "gn:name":"Ban Wang Khon Phat",
    "gn:population":0,
    "gn:timezone":"Asia/Bangkok",
    "iso:country":"TH",
    "name:tha_x_preferred":[
        "\u0e1a\u0e49\u0e32\u0e19\u0e27\u0e31\u0e07\u0e02\u0e2d\u0e19\u0e1e\u0e32\u0e14"
    ],
    "wof:name":"Ban Wang Khon Phat",
    "wof:placetype":"locality"
},
  "geometry": {"coordinates":[102.65908,15.85414],"type":"Point"}
}