{
  "type": "Feature",
  "properties": {
    "gn:admin1_code":"77.0",
    "gn:asciiname":"Ban Hong Toei",
    "gn:country_code":"TH",
    "gn:dem":147,
    "gn:feature_class":"P",
    "gn:feature_code":"PPL",
    "gn:name":"Ban Hong Toei",
    "gn:population":0,
    "gn:timezone":"Asia/Bangkok",
    "iso:country":"TH",
    "name:tha_x_preferred":[
        "Ban Hong Toei"
    ],
    "name:tha_x_variant":[
        "\u0e1a\u0e49\u0e32\u0e19\u0e2b\u0e2d\u0e07\u0e40\u0e15\u0e22"
    ],
    "wof:name":"Ban Hong Toei",
    "wof:placetype":"locality"
},
  "geometry": {"coordinates":[104.56068999999999,16.0155],"type":"Point"}
}