{
  "type": "Feature",
  "properties": {
    "gn:admin1_code":"16.0",
    "gn:asciiname":"Ban Khao Wiwat",
    "gn:country_code":"TH",
    "gn:dem":116,
    "gn:feature_class":"P",
    "gn:feature_code":"PPL",
    "gn:name":"Ban Khao Wiwat",
    "gn:population":0,
    "gn:timezone":"Asia/Bangkok",
    "iso:country":"TH",
    "wof:name":"Ban Khao Wiwat",
    "wof:placetype":"locality"
},
  "geometry": {"coordinates":[100.28333000000001,15.55],"type":"Point"}
}