{
  "type": "Feature",
  "properties": {
    "gn:admin1_code":"11.0",
    "gn:asciiname":"Ban Mo Daeng",
    "gn:country_code":"TH",
    "gn:dem":106,
    "gn:feature_class":"P",
    "gn:feature_code":"PPL",
    "gn:name":"Ban Mo Daeng",
    "gn:population":0,
    "gn:timezone":"Asia/Bangkok",
    "iso:country":"TH",
    "name:tha_x_preferred":[
        "\u0e1a\u0e49\u0e32\u0e19\u0e21\u0e2d\u0e41\u0e14\u0e07"
    ],
    "wof:name":"Ban Mo Daeng",
    "wof:placetype":"locality"
},
  "geometry": {"coordinates":[99.42697,16.36267],"type":"Point"}
}