{
  "type": "Feature",
  "properties": {
    "gn:admin1_code":"1.0",
    "gn:asciiname":"Ban Khun Mae Loe",
    "gn:country_code":"TH",
    "gn:dem":666,
    "gn:feature_class":"P",
    "gn:feature_code":"PPL",
    "gn:name":"Ban Khun Mae Loe",
    "gn:population":0,
    "gn:timezone":"Asia/Bangkok",
    "iso:country":"TH",
    "name:tha_x_preferred":[
        "\u0e1a\u0e49\u0e32\u0e19\u0e02\u0e38\u0e19\u0e41\u0e21\u0e48\u0e40\u0e2b\u0e25\u0e2d"
    ],
    "wof:name":"Ban Khun Mae Loe",
    "wof:placetype":"locality"
},
  "geometry": {"coordinates":[97.78946000000001,18.38167],"type":"Point"}
}