{
  "type": "Feature",
  "properties": {
    "gn:admin1_code":"64.0",
    "gn:asciiname":"Ban Sai Muang",
    "gn:country_code":"TH",
    "gn:dem":10,
    "gn:feature_class":"P",
    "gn:feature_code":"PPL",
    "gn:name":"Ban Sai Muang",
    "gn:population":0,
    "gn:timezone":"Asia/Bangkok",
    "iso:country":"TH",
    "name:tha_x_preferred":[
        "\u0e1a\u0e49\u0e32\u0e19\u0e43\u0e2a\u0e21\u0e48\u0e27\u0e07"
    ],
    "name:und_x_variant":[
        "Ban Sai Mamuang"
    ],
    "wof:name":"Ban Sai Muang",
    "wof:placetype":"locality"
},
  "geometry": {"coordinates":[99.95458000000001,8.37425],"type":"Point"}
}