{
  "type": "Feature",
  "properties": {
    "gn:admin1_code":"13.0",
    "gn:asciiname":"Ban Khok Khwang",
    "gn:country_code":"TH",
    "gn:dem":40,
    "gn:feature_class":"P",
    "gn:feature_code":"PPL",
    "gn:name":"Ban Khok Khwang",
    "gn:population":0,
    "gn:timezone":"Asia/Bangkok",
    "iso:country":"TH",
    "name:tha_x_preferred":[
        "\u0e1a\u0e49\u0e32\u0e19\u0e42\u0e04\u0e01\u0e02\u0e27\u0e32\u0e07"
    ],
    "wof:name":"Ban Khok Khwang",
    "wof:placetype":"locality"
},
  "geometry": {"coordinates":[100.47356000000001,16.34531],"type":"Point"}
}