{
  "type": "Feature",
  "properties": {
    "gn:admin1_code":"1.0",
    "gn:asciiname":"Ban Yang Thung Phrao",
    "gn:country_code":"TH",
    "gn:dem":230,
    "gn:feature_class":"P",
    "gn:feature_code":"PPL",
    "gn:name":"Ban Yang Thung Phrao",
    "gn:population":0,
    "gn:timezone":"Asia/Bangkok",
    "iso:country":"TH",
    "name:tha_x_preferred":[
        "\u0e1a\u0e49\u0e32\u0e19\u0e22\u0e32\u0e07\u0e17\u0e38\u0e48\u0e07\u0e1e\u0e23\u0e49\u0e32\u0e27"
    ],
    "name:und_x_variant":[
        "Ban Thung Phrao",
        "Ban Yang Thung Phrao"
    ],
    "wof:name":"Ban Yang Thung Phrao",
    "wof:placetype":"locality"
},
  "geometry": {"coordinates":[97.94219,18.13686],"type":"Point"}
}