{
  "type": "Feature",
  "properties": {
    "gn:admin1_code":"28.0",
    "gn:asciiname":"Ban Makhampom",
    "gn:country_code":"TH",
    "gn:dem":153,
    "gn:feature_class":"P",
    "gn:feature_code":"PPL",
    "gn:name":"Ban Makhampom",
    "gn:population":0,
    "gn:timezone":"Asia/Bangkok",
    "iso:country":"TH",
    "name:tha_x_preferred":[
        "\u0e1a\u0e49\u0e32\u0e19\u0e21\u0e30\u0e02\u0e32\u0e21\u0e1b\u0e49\u0e2d\u0e21"
    ],
    "name:und_x_variant":[
        "Ban Kham Pom",
        "Ban Nong Kham Pom",
        "Ban Makhampom"
    ],
    "wof:name":"Ban Makhampom",
    "wof:placetype":"locality"
},
  "geometry": {"coordinates":[103.19902999999999,15.05139],"type":"Point"}
}