{
  "type": "Feature",
  "properties": {
    "gn:admin1_code":"5.0",
    "gn:asciiname":"Ban Buak",
    "gn:country_code":"TH",
    "gn:dem":515,
    "gn:feature_class":"P",
    "gn:feature_code":"PPL",
    "gn:name":"Ban Buak",
    "gn:population":0,
    "gn:timezone":"Asia/Bangkok",
    "iso:country":"TH",
    "name:tha_x_preferred":[
        "\u0e1a\u0e49\u0e32\u0e19\u0e1a\u0e27\u0e01"
    ],
    "name:und_x_variant":[
        "Ban Bok Man",
        "B\u0101n Bauk Man",
        "Ban Buak"
    ],
    "wof:name":"Ban Buak",
    "wof:placetype":"locality"
},
  "geometry": {"coordinates":[99.03369000000001,17.73757999999999],"type":"Point"}
}