{
  "type": "Feature",
  "properties": {
    "gn:admin1_code":"29",
    "gn:asciiname":"Ban Phong Sawai",
    "gn:country_code":"TH",
    "gn:dem":131,
    "gn:feature_class":"P",
    "gn:feature_code":"PPL",
    "gn:name":"Ban Phong Sawai",
    "gn:population":0,
    "gn:timezone":"Asia/Bangkok",
    "iso:country":"TH",
    "name:tha_x_preferred":[
        "\u0e1a\u0e49\u0e32\u0e19\u0e1e\u0e07\u0e2a\u0e27\u0e32\u0e22"
    ],
    "wof:name":"Ban Phong Sawai",
    "wof:placetype":"locality"
},
  "geometry": {"coordinates":[103.68375,15.32861],"type":"Point"}
}