{
  "type": "Feature",
  "properties": {
    "gn:admin1_code":"24.0",
    "gn:asciiname":"Ban Kut Pladuk",
    "gn:country_code":"TH",
    "gn:dem":181,
    "gn:feature_class":"P",
    "gn:feature_code":"PPL",
    "gn:name":"Ban Kut Pladuk",
    "gn:population":0,
    "gn:timezone":"Asia/Bangkok",
    "iso:country":"TH",
    "name:tha_x_preferred":[
        "\u0e1a\u0e49\u0e32\u0e19\u0e01\u0e38\u0e14\u0e1b\u0e25\u0e32\u0e14\u0e38\u0e01"
    ],
    "name:und_x_variant":[
        "Ban Kut Pla Duk"
    ],
    "wof:lang_x_official":[
        "tha"
    ],
    "wof:lang_x_spoken":[
        "tha"
    ],
    "wof:name":"Ban Kut Pladuk",
    "wof:placetype":"locality"
},
  "geometry": {"coordinates":[103.14236,16.57811],"type":"Point"}
}