{
  "type": "Feature",
  "properties": {
    "gn:admin1_code":"76.0",
    "gn:asciiname":"Ban Ngoi",
    "gn:country_code":"TH",
    "gn:dem":177,
    "gn:feature_class":"P",
    "gn:feature_code":"PPL",
    "gn:name":"Ban Ngoi",
    "gn:population":0,
    "gn:timezone":"Asia/Bangkok",
    "iso:country":"TH",
    "wof:lang_x_official":[
        "tha"
    ],
    "wof:lang_x_spoken":[
        "tha"
    ],
    "wof:name":"Ban Ngoi",
    "wof:placetype":"locality"
},
  "geometry": {"coordinates":[102.73333,17.41611],"type":"Point"}
}