{
  "type": "Feature",
  "properties": {
    "gn:admin1_code":"15.0",
    "gn:asciiname":"Ban Huai Ruam",
    "gn:country_code":"TH",
    "gn:dem":220,
    "gn:feature_class":"P",
    "gn:feature_code":"PPL",
    "gn:name":"Ban Huai Ruam",
    "gn:population":0,
    "gn:timezone":"Asia/Bangkok",
    "iso:country":"TH",
    "name:tha_x_preferred":[
        "\u0e1a\u0e49\u0e32\u0e19\u0e2b\u0e49\u0e27\u0e22\u0e23\u0e48\u0e27\u0e21"
    ],
    "wof:name":"Ban Huai Ruam",
    "wof:placetype":"locality"
},
  "geometry": {"coordinates":[99.464,15.35731],"type":"Point"}
}