{
  "type": "Feature",
  "properties": {
    "gn:admin1_code":"13.0",
    "gn:asciiname":"Ban Bueng Pho",
    "gn:country_code":"TH",
    "gn:dem":37,
    "gn:feature_class":"P",
    "gn:feature_code":"PPL",
    "gn:name":"Ban Bueng Pho",
    "gn:population":0,
    "gn:timezone":"Asia/Bangkok",
    "iso:country":"TH",
    "name:tha_x_preferred":[
        "\u0e1a\u0e49\u0e32\u0e19\u0e1a\u0e36\u0e07\u0e42\u0e1e\u0e18\u0e34\u0e4c"
    ],
    "wof:name":"Ban Bueng Pho",
    "wof:placetype":"locality"
},
  "geometry": {"coordinates":[100.30389,16.30664],"type":"Point"}
}