{
  "type": "Feature",
  "properties": {
    "gn:admin1_code":"25.0",
    "gn:asciiname":"Ban Lao Tamyae",
    "gn:country_code":"TH",
    "gn:dem":149,
    "gn:feature_class":"P",
    "gn:feature_code":"PPL",
    "gn:name":"Ban Lao Tamyae",
    "gn:population":0,
    "gn:timezone":"Asia/Bangkok",
    "iso:country":"TH",
    "name:tha_x_preferred":[
        "\u0e1a\u0e49\u0e32\u0e19\u0e40\u0e2b\u0e25\u0e48\u0e32\u0e15\u0e33\u0e41\u0e22"
    ],
    "wof:name":"Ban Lao Tamyae",
    "wof:placetype":"locality"
},
  "geometry": {"coordinates":[103.53077999999999,16.14108],"type":"Point"}
}