{
  "type": "Feature",
  "properties": {
    "gn:admin1_code":"11.0",
    "gn:asciiname":"Ban San Chao Mae",
    "gn:country_code":"TH",
    "gn:dem":56,
    "gn:feature_class":"P",
    "gn:feature_code":"PPL",
    "gn:name":"Ban San Chao Mae",
    "gn:population":0,
    "gn:timezone":"Asia/Bangkok",
    "iso:country":"TH",
    "name:tha_x_preferred":[
        "\u0e1a\u0e49\u0e32\u0e19\u0e28\u0e32\u0e25\u0e40\u0e08\u0e49\u0e32\u0e41\u0e21\u0e48"
    ],
    "name:und_x_variant":[
        "Ban Talat San Chao Mae"
    ],
    "wof:name":"Ban San Chao Mae",
    "wof:placetype":"locality"
},
  "geometry": {"coordinates":[99.80867000000001,16.14857],"type":"Point"}
}