{
  "type": "Feature",
  "properties": {
    "gn:admin1_code":"11.0",
    "gn:asciiname":"Ban Sa Duai",
    "gn:country_code":"TH",
    "gn:dem":56,
    "gn:feature_class":"P",
    "gn:feature_code":"PPL",
    "gn:name":"Ban Sa Duai",
    "gn:population":0,
    "gn:timezone":"Asia/Bangkok",
    "iso:country":"TH",
    "name:tha_x_preferred":[
        "\u0e1a\u0e49\u0e32\u0e19\u0e2a\u0e30\u0e40\u0e14\u0e37\u0e2d\u0e22"
    ],
    "wof:name":"Ban Sa Duai",
    "wof:placetype":"locality"
},
  "geometry": {"coordinates":[99.82393999999999,16.57392],"type":"Point"}
}