{
  "type": "Feature",
  "properties": {
    "gn:admin1_code":"4.0",
    "gn:asciiname":"Ban Ko Kuang (1)",
    "gn:country_code":"TH",
    "gn:dem":1408,
    "gn:feature_class":"P",
    "gn:feature_code":"PPL",
    "gn:name":"Ban Ko Kuang (1)",
    "gn:population":0,
    "gn:timezone":"Asia/Bangkok",
    "iso:country":"TH",
    "name:tha_x_preferred":[
        "\u0e1a\u0e49\u0e32\u0e19\u0e01\u0e2d\u0e01\u0e27\u0e07 (\u0e2b\u0e19\u0e37\u0e48\u0e07)"
    ],
    "name:und_x_variant":[
        "Ban Ko Khuang",
        "Ban Ko Kuang"
    ],
    "wof:lang_x_official":[
        "tha"
    ],
    "wof:lang_x_spoken":[
        "tha"
    ],
    "wof:name":"Ban Ko Kuang (1)",
    "wof:placetype":"locality"
},
  "geometry": {"coordinates":[101.12014000000001,19.18153],"type":"Point"}
}