{
  "type": "Feature",
  "properties": {
    "gn:admin1_code":"75.0",
    "gn:asciiname":"Ban Khon Sai",
    "gn:country_code":"TH",
    "gn:dem":131,
    "gn:feature_class":"P",
    "gn:feature_code":"PPL",
    "gn:name":"Ban Khon Sai",
    "gn:population":0,
    "gn:timezone":"Asia/Bangkok",
    "iso:country":"TH",
    "name:tha_x_preferred":[
        "\u0e1a\u0e49\u0e32\u0e19\u0e04\u0e2d\u0e19\u0e2a\u0e32\u0e22"
    ],
    "wof:name":"Ban Khon Sai",
    "wof:placetype":"locality"
},
  "geometry": {"coordinates":[104.76425,15.39022],"type":"Point"}
}