{
  "type": "Feature",
  "properties": {
    "gn:admin1_code":"31.0",
    "gn:asciiname":"Ban Cha Ro Him",
    "gn:country_code":"TH",
    "gn:dem":8,
    "gn:feature_class":"P",
    "gn:feature_code":"PPL",
    "gn:name":"Ban Cha Ro Him",
    "gn:population":0,
    "gn:timezone":"Asia/Bangkok",
    "iso:country":"TH",
    "name:tha_x_preferred":[
        "\u0e1a\u0e49\u0e32\u0e19\u0e08\u0e32\u0e40\u0e23\u0e4a\u0e32\u0e30\u0e2b\u0e34\u0e21"
    ],
    "wof:name":"Ban Cha Ro Him",
    "wof:placetype":"locality"
},
  "geometry": {"coordinates":[101.82167,6.33422],"type":"Point"}
}