{
  "type": "Feature",
  "properties": {
    "gn:admin1_code":"34",
    "gn:asciiname":"Ban Tao Than",
    "gn:country_code":"TH",
    "gn:dem":43,
    "gn:feature_class":"P",
    "gn:feature_code":"PPL",
    "gn:name":"Ban Tao Than",
    "gn:population":0,
    "gn:timezone":"Asia/Bangkok",
    "iso:country":"TH",
    "name:tha_x_preferred":[
        "\u0e1a\u0e49\u0e32\u0e19\u0e40\u0e15\u0e32\u0e16\u0e48\u0e32\u0e19"
    ],
    "wof:name":"Ban Tao Than",
    "wof:placetype":"locality"
},
  "geometry": {"coordinates":[100.66397000000001,15.13378],"type":"Point"}
}