{
  "type": "Feature",
  "properties": {
    "gn:admin1_code":"7.0",
    "gn:asciiname":"Ban Hat Rua",
    "gn:country_code":"TH",
    "gn:dem":99,
    "gn:feature_class":"P",
    "gn:feature_code":"PPL",
    "gn:name":"Ban Hat Rua",
    "gn:population":0,
    "gn:timezone":"Asia/Bangkok",
    "iso:country":"TH",
    "name:tha_x_preferred":[
        "\u0e1a\u0e49\u0e32\u0e19\u0e2b\u0e32\u0e14\u0e23\u0e31\u0e48\u0e27"
    ],
    "wof:name":"Ban Hat Rua",
    "wof:placetype":"locality"
},
  "geometry": {"coordinates":[99.68119,17.78744],"type":"Point"}
}