{
  "type": "Feature",
  "properties": {
    "gn:admin1_code":"23.0",
    "gn:asciiname":"Ban Yot Kaeng",
    "gn:country_code":"TH",
    "gn:dem":176,
    "gn:feature_class":"P",
    "gn:feature_code":"PPL",
    "gn:name":"Ban Yot Kaeng",
    "gn:population":0,
    "gn:timezone":"Asia/Bangkok",
    "iso:country":"TH",
    "name:tha_x_preferred":[
        "\u0e1a\u0e49\u0e32\u0e19\u0e22\u0e2d\u0e14\u0e41\u0e01\u0e07"
    ],
    "wof:name":"Ban Yot Kaeng",
    "wof:placetype":"locality"
},
  "geometry": {"coordinates":[103.72875000000001,16.61142000000001],"type":"Point"}
}