{
  "type": "Feature",
  "properties": {
    "gn:admin1_code":"59.0",
    "gn:asciiname":"Ban Sai Daeng",
    "gn:country_code":"TH",
    "gn:dem":71,
    "gn:feature_class":"P",
    "gn:feature_code":"PPL",
    "gn:name":"Ban Sai Daeng",
    "gn:population":0,
    "gn:timezone":"Asia/Bangkok",
    "iso:country":"TH",
    "name:tha_x_preferred":[
        "\u0e1a\u0e49\u0e32\u0e19\u0e17\u0e23\u0e32\u0e22\u0e41\u0e14\u0e07"
    ],
    "name:und_x_variant":[
        "Ban S\u0101i Deang",
        "Ban Sai Daeng"
    ],
    "wof:lang_x_official":[
        "tha"
    ],
    "wof:lang_x_spoken":[
        "tha"
    ],
    "wof:name":"Ban Sai Daeng",
    "wof:placetype":"locality"
},
  "geometry": {"coordinates":[98.69147,10.13811],"type":"Point"}
}