{
  "type": "Feature",
  "properties": {
    "gn:admin1_code":"69.0",
    "gn:asciiname":"Ban Ku Bae Kue Rae",
    "gn:country_code":"TH",
    "gn:dem":12,
    "gn:feature_class":"P",
    "gn:feature_code":"PPL",
    "gn:name":"Ban Ku Bae Kue Rae",
    "gn:population":0,
    "gn:timezone":"Asia/Bangkok",
    "iso:country":"TH",
    "name:tha_x_preferred":[
        "\u0e1a\u0e49\u0e32\u0e19\u0e01\u0e39\u0e41\u0e1a\u0e01\u0e37\u0e2d\u0e41\u0e23"
    ],
    "wof:name":"Ban Ku Bae Kue Rae",
    "wof:placetype":"locality"
},
  "geometry": {"coordinates":[101.57247,6.70333],"type":"Point"}
}