{
  "type": "Feature",
  "properties": {
    "gn:admin1_code":"52.0",
    "gn:asciiname":"Ban Khao Kling",
    "gn:country_code":"TH",
    "gn:dem":177,
    "gn:feature_class":"P",
    "gn:feature_code":"PPL",
    "gn:name":"Ban Khao Kling",
    "gn:population":0,
    "gn:timezone":"Asia/Bangkok",
    "iso:country":"TH",
    "name:tha_x_preferred":[
        "\u0e1a\u0e49\u0e32\u0e19\u0e40\u0e02\u0e32\u0e01\u0e25\u0e34\u0e49\u0e07"
    ],
    "wof:name":"Ban Khao Kling",
    "wof:placetype":"locality"
},
  "geometry": {"coordinates":[99.41861,13.51928],"type":"Point"}
}