{
  "type": "Feature",
  "properties": {
    "gn:admin1_code":"67.0",
    "gn:asciiname":"Ban Sakhon",
    "gn:country_code":"TH",
    "gn:dem":8,
    "gn:feature_class":"P",
    "gn:feature_code":"PPL",
    "gn:name":"Ban Sakhon",
    "gn:population":0,
    "gn:timezone":"Asia/Bangkok",
    "iso:country":"TH",
    "name:tha_x_preferred":[
        "\u0e1a\u0e49\u0e32\u0e19\u0e2a\u0e32\u0e04\u0e23"
    ],
    "name:und_x_variant":[
        "Ban Sadong",
        "Ban Sa Khorn",
        "Ban Sakhon"
    ],
    "wof:name":"Ban Sakhon",
    "wof:placetype":"locality"
},
  "geometry": {"coordinates":[99.90161000000001,6.73811],"type":"Point"}
}