{
  "type": "Feature",
  "properties": {
    "gn:admin1_code":"20.0",
    "gn:asciiname":"Ban Saeng Charoen",
    "gn:country_code":"TH",
    "gn:dem":163,
    "gn:feature_class":"P",
    "gn:feature_code":"PPL",
    "gn:name":"Ban Saeng Charoen",
    "gn:population":0,
    "gn:timezone":"Asia/Bangkok",
    "iso:country":"TH",
    "name:tha_x_preferred":[
        "\u0e1a\u0e49\u0e32\u0e19\u0e41\u0e2a\u0e07\u0e40\u0e08\u0e23\u0e34\u0e0d"
    ],
    "wof:name":"Ban Saeng Charoen",
    "wof:placetype":"locality"
},
  "geometry": {"coordinates":[103.60214000000001,17.77106000000001],"type":"Point"}
}