{
  "type": "Feature",
  "properties": {
    "gn:admin1_code":"10.0",
    "gn:asciiname":"Ban Den Dan",
    "gn:country_code":"TH",
    "gn:dem":80,
    "gn:feature_class":"P",
    "gn:feature_code":"PPL",
    "gn:name":"Ban Den Dan",
    "gn:population":0,
    "gn:timezone":"Asia/Bangkok",
    "iso:country":"TH",
    "name:tha_x_preferred":[
        "\u0e1a\u0e49\u0e32\u0e19\u0e40\u0e14\u0e48\u0e19\u0e14\u0e48\u0e32\u0e19"
    ],
    "wof:name":"Ban Den Dan",
    "wof:placetype":"locality"
},
  "geometry": {"coordinates":[100.27203,17.69503],"type":"Point"}
}