{
  "type": "Feature",
  "properties": {
    "gn:admin1_code":"6.0",
    "gn:asciiname":"Ban Nam Long",
    "gn:country_code":"TH",
    "gn:dem":255,
    "gn:feature_class":"P",
    "gn:feature_code":"PPL",
    "gn:name":"Ban Nam Long",
    "gn:population":0,
    "gn:timezone":"Asia/Bangkok",
    "iso:country":"TH",
    "name:tha_x_preferred":[
        "\u0e1a\u0e49\u0e32\u0e19\u0e19\u0e49\u0e33\u0e2b\u0e25\u0e07"
    ],
    "name:und_x_variant":[
        "B\u0101n Nam Laung",
        "Ban Nam Long"
    ],
    "wof:name":"Ban Nam Long",
    "wof:placetype":"locality"
},
  "geometry": {"coordinates":[99.22108,18.02261],"type":"Point"}
}