{
  "type": "Feature",
  "properties": {
    "gn:admin1_code":"3.0",
    "gn:asciiname":"Ban Huai Rai",
    "gn:country_code":"TH",
    "gn:dem":392,
    "gn:feature_class":"P",
    "gn:feature_code":"PPL",
    "gn:name":"Ban Huai Rai",
    "gn:population":0,
    "gn:timezone":"Asia/Bangkok",
    "iso:country":"TH",
    "name:tha_x_preferred":[
        "\u0e1a\u0e49\u0e32\u0e19\u0e2b\u0e49\u0e27\u0e22\u0e44\u0e23\u0e48"
    ],
    "wof:name":"Ban Huai Rai",
    "wof:placetype":"locality"
},
  "geometry": {"coordinates":[100.07617,20.10803],"type":"Point"}
}