{
  "type": "Feature",
  "properties": {
    "gn:admin1_code":"60.0",
    "gn:asciiname":"Muban Chao Mo Kaen",
    "gn:country_code":"TH",
    "gn:dem":195,
    "gn:feature_class":"P",
    "gn:feature_code":"PPL",
    "gn:name":"Muban Chao Mo Kaen",
    "gn:population":0,
    "gn:timezone":"Asia/Bangkok",
    "iso:country":"TH",
    "name:tha_x_preferred":[
        "\u0e2b\u0e21\u0e39\u0e48\u0e1a\u0e49\u0e32\u0e19\u0e0a\u0e32\u0e27\u0e21\u0e2d\u0e23\u0e4c\u0e41\u0e01\u0e19"
    ],
    "wof:name":"Muban Chao Mo Kaen",
    "wof:placetype":"locality"
},
  "geometry": {"coordinates":[98.80278,9.44631],"type":"Point"}
}