{
  "type": "Feature",
  "properties": {
    "gn:admin1_code":"17.0",
    "gn:asciiname":"Ban Dong Mot Daeng",
    "gn:country_code":"TH",
    "gn:dem":166,
    "gn:feature_class":"P",
    "gn:feature_code":"PPL",
    "gn:name":"Ban Dong Mot Daeng",
    "gn:population":0,
    "gn:timezone":"Asia/Bangkok",
    "iso:country":"TH",
    "name:tha_x_preferred":[
        "\u0e1a\u0e49\u0e32\u0e19\u0e14\u0e07\u0e21\u0e14\u0e41\u0e14\u0e07"
    ],
    "wof:name":"Ban Dong Mot Daeng",
    "wof:placetype":"locality"
},
  "geometry": {"coordinates":[103.23331,18.23042],"type":"Point"}
}