{
  "type": "Feature",
  "properties": {
    "gn:admin1_code":"34.0",
    "gn:asciiname":"Ban Nong Song Ton",
    "gn:country_code":"TH",
    "gn:dem":67,
    "gn:feature_class":"P",
    "gn:feature_code":"PPL",
    "gn:name":"Ban Nong Song Ton",
    "gn:population":0,
    "gn:timezone":"Asia/Bangkok",
    "iso:country":"TH",
    "name:tha_x_preferred":[
        "\u0e1a\u0e49\u0e32\u0e19\u0e2b\u0e19\u0e2d\u0e07\u0e2a\u0e2d\u0e07\u0e15\u0e2d\u0e19"
    ],
    "name:und_x_variant":[
        "Ban Nong Samrong"
    ],
    "wof:name":"Ban Nong Song Ton",
    "wof:placetype":"locality"
},
  "geometry": {"coordinates":[101.0715,15.2325],"type":"Point"}
}