{
  "type": "Feature",
  "properties": {
    "gn:admin1_code":"73.0",
    "gn:asciiname":"Ban Na Som",
    "gn:country_code":"TH",
    "gn:dem":153,
    "gn:feature_class":"P",
    "gn:feature_code":"PPL",
    "gn:name":"Ban Na Som",
    "gn:population":0,
    "gn:timezone":"Asia/Bangkok",
    "iso:country":"TH",
    "name:tha_x_preferred":[
        "\u0e1a\u0e49\u0e32\u0e19\u0e19\u0e32\u0e0b\u0e48\u0e2d\u0e21"
    ],
    "wof:name":"Ban Na Som",
    "wof:placetype":"locality"
},
  "geometry": {"coordinates":[104.07344999999999,17.51093],"type":"Point"}
}