{
  "type": "Feature",
  "properties": {
    "gn:admin1_code":"52.0",
    "gn:asciiname":"Ban Nam Phung Do",
    "gn:country_code":"TH",
    "gn:dem":12,
    "gn:feature_class":"P",
    "gn:feature_code":"PPL",
    "gn:name":"Ban Nam Phung Do",
    "gn:population":0,
    "gn:timezone":"Asia/Bangkok",
    "iso:country":"TH",
    "name:tha_x_preferred":[
        "\u0e1a\u0e49\u0e32\u0e19\u0e2b\u0e19\u0e32\u0e21\u0e1e\u0e38\u0e07\u0e14\u0e2d"
    ],
    "wof:name":"Ban Nam Phung Do",
    "wof:placetype":"locality"
},
  "geometry": {"coordinates":[99.81853,13.45139],"type":"Point"}
}