{
  "type": "Feature",
  "properties": {
    "gn:admin1_code":"34",
    "gn:asciiname":"Ban Ang Nikhon",
    "gn:country_code":"TH",
    "gn:dem":72,
    "gn:feature_class":"P",
    "gn:feature_code":"PPL",
    "gn:name":"Ban Ang Nikhon",
    "gn:population":0,
    "gn:timezone":"Asia/Bangkok",
    "iso:country":"TH",
    "name:tha_x_preferred":[
        "\u0e1a\u0e49\u0e32\u0e19\u0e2d\u0e48\u0e32\u0e07\u0e19\u0e34\u0e04\u0e21"
    ],
    "wof:name":"Ban Ang Nikhon",
    "wof:placetype":"locality"
},
  "geometry": {"coordinates":[101.12636000000001,15.22747],"type":"Point"}
}