{
  "type": "Feature",
  "properties": {
    "gn:admin1_code":"8.0",
    "gn:asciiname":"Ban Mo Tha",
    "gn:country_code":"TH",
    "gn:dem":415,
    "gn:feature_class":"P",
    "gn:feature_code":"PPL",
    "gn:name":"Ban Mo Tha",
    "gn:population":0,
    "gn:timezone":"Asia/Bangkok",
    "iso:country":"TH",
    "name:tha_x_preferred":[
        "\u0e1a\u0e49\u0e32\u0e19\u0e21\u0e2d\u0e17\u0e30"
    ],
    "wof:name":"Ban Mo Tha",
    "wof:placetype":"locality"
},
  "geometry": {"coordinates":[98.68103000000001,15.70819],"type":"Point"}
}