{
  "type": "Feature",
  "properties": {
    "gn:admin1_code":"76.0",
    "gn:asciiname":"Ban Dong Phak Thiam",
    "gn:country_code":"TH",
    "gn:dem":169,
    "gn:feature_class":"P",
    "gn:feature_code":"PPL",
    "gn:name":"Ban Dong Phak Thiam",
    "gn:population":0,
    "gn:timezone":"Asia/Bangkok",
    "iso:country":"TH",
    "name:tha_x_preferred":[
        "\u0e1a\u0e49\u0e32\u0e19\u0e14\u0e07\u0e1c\u0e31\u0e01\u0e40\u0e17\u0e35\u0e22\u0e21"
    ],
    "wof:name":"Ban Dong Phak Thiam",
    "wof:placetype":"locality"
},
  "geometry": {"coordinates":[103.07256,17.83025],"type":"Point"}
}