{
  "type": "Feature",
  "properties": {
    "gn:admin1_code":"26.0",
    "gn:asciiname":"Ban Non Sung Pueai",
    "gn:country_code":"TH",
    "gn:dem":177,
    "gn:feature_class":"P",
    "gn:feature_code":"PPL",
    "gn:name":"Ban Non Sung Pueai",
    "gn:population":0,
    "gn:timezone":"Asia/Bangkok",
    "iso:country":"TH",
    "name:tha_x_preferred":[
        "\u0e1a\u0e49\u0e32\u0e19\u0e42\u0e19\u0e19\u0e2a\u0e39\u0e07\u0e40\u0e1b\u0e37\u0e2d\u0e22"
    ],
    "wof:name":"Ban Non Sung Pueai",
    "wof:placetype":"locality"
},
  "geometry": {"coordinates":[102.25453,15.81958],"type":"Point"}
}