{
  "type": "Feature",
  "properties": {
    "gn:admin1_code":"14.0",
    "gn:asciiname":"Ban Bu Khao Hom",
    "gn:country_code":"TH",
    "gn:dem":87,
    "gn:feature_class":"P",
    "gn:feature_code":"PPL",
    "gn:name":"Ban Bu Khao Hom",
    "gn:population":0,
    "gn:timezone":"Asia/Bangkok",
    "iso:country":"TH",
    "name:tha_x_preferred":[
        "\u0e1a\u0e49\u0e32\u0e19\u0e1a\u0e38\u0e40\u0e02\u0e32\u0e2b\u0e2d\u0e21"
    ],
    "wof:name":"Ban Bu Khao Hom",
    "wof:placetype":"locality"
},
  "geometry": {"coordinates":[100.73788999999999,16.28364],"type":"Point"}
}