{
  "type": "Feature",
  "properties": {
    "gn:admin1_code":"27",
    "gn:asciiname":"Ban Nong Ta Kaeo",
    "gn:country_code":"TH",
    "gn:dem":522,
    "gn:feature_class":"P",
    "gn:feature_code":"PPL",
    "gn:name":"Ban Nong Ta Kaeo",
    "gn:population":0,
    "gn:timezone":"Asia/Bangkok",
    "iso:country":"TH",
    "name:tha_x_preferred":[
        "\u0e1a\u0e49\u0e32\u0e19\u0e2b\u0e19\u0e2d\u0e07\u0e15\u0e32\u0e41\u0e01\u0e49\u0e27"
    ],
    "wof:name":"Ban Nong Ta Kaeo",
    "wof:placetype":"locality"
},
  "geometry": {"coordinates":[101.37894,14.76194],"type":"Point"}
}