{
  "type": "Feature",
  "properties": {
    "gn:admin1_code":"18.0",
    "gn:asciiname":"Ban Na Din Dam",
    "gn:country_code":"TH",
    "gn:dem":291,
    "gn:feature_class":"P",
    "gn:feature_code":"PPL",
    "gn:name":"Ban Na Din Dam",
    "gn:population":0,
    "gn:timezone":"Asia/Bangkok",
    "iso:country":"TH",
    "name:tha_x_preferred":[
        "Ban Na Din Dam"
    ],
    "name:tha_x_variant":[
        "\u0e1a\u0e49\u0e32\u0e19\u0e19\u0e32\u0e14\u0e34\u0e19\u0e14\u0e33"
    ],
    "wof:name":"Ban Na Din Dam",
    "wof:placetype":"locality"
},
  "geometry": {"coordinates":[101.8327,17.45281],"type":"Point"}
}