{
  "type": "Feature",
  "properties": {
    "gn:admin1_code":"74",
    "gn:asciiname":"Ban Khao Tham",
    "gn:country_code":"TH",
    "gn:dem":79,
    "gn:feature_class":"P",
    "gn:feature_code":"PPL",
    "gn:name":"Ban Khao Tham",
    "gn:population":0,
    "gn:timezone":"Asia/Bangkok",
    "iso:country":"TH",
    "name:tha_x_preferred":[
        "\u0e1a\u0e49\u0e32\u0e19\u0e40\u0e02\u0e32\u0e16\u0e49\u0e33"
    ],
    "wof:lang_x_official":[
        "tha"
    ],
    "wof:lang_x_spoken":[
        "tha"
    ],
    "wof:name":"Ban Khao Tham",
    "wof:placetype":"locality"
},
  "geometry": {"coordinates":[101.92811,13.65244],"type":"Point"}
}