{
  "type": "Feature",
  "properties": {
    "gn:admin1_code":"2.0",
    "gn:asciiname":"Ban Plaeng 5",
    "gn:country_code":"TH",
    "gn:dem":281,
    "gn:feature_class":"P",
    "gn:feature_code":"PPL",
    "gn:name":"Ban Plaeng 5",
    "gn:population":0,
    "gn:timezone":"Asia/Bangkok",
    "iso:country":"TH",
    "name:tha_x_preferred":[
        "\u0e1a\u0e49\u0e32\u0e19\u0e41\u0e1b\u0e25\u0e07 \u0e2b\u0e49\u0e32"
    ],
    "name:und_x_variant":[
        "Ban Plaeng Ha"
    ],
    "wof:name":"Ban Plaeng 5",
    "wof:placetype":"locality"
},
  "geometry": {"coordinates":[98.68822,17.95044],"type":"Point"}
}