{
  "type": "Feature",
  "properties": {
    "gn:admin1_code":"2.0",
    "gn:asciiname":"Ban Ton Hiao",
    "gn:country_code":"TH",
    "gn:dem":304,
    "gn:feature_class":"P",
    "gn:feature_code":"PPL",
    "gn:name":"Ban Ton Hiao",
    "gn:population":0,
    "gn:timezone":"Asia/Bangkok",
    "iso:country":"TH",
    "name:tha_x_preferred":[
        "\u0e1a\u0e49\u0e32\u0e19\u0e15\u0e49\u0e19\u0e40\u0e2b\u0e35\u0e22\u0e27"
    ],
    "wof:name":"Ban Ton Hiao",
    "wof:placetype":"locality"
},
  "geometry": {"coordinates":[99.04268999999999,18.69878],"type":"Point"}
}