{
  "type": "Feature",
  "properties": {
    "gn:admin1_code":"6.0",
    "gn:asciiname":"Ban Pha Daeng",
    "gn:country_code":"TH",
    "gn:dem":741,
    "gn:feature_class":"P",
    "gn:feature_code":"PPL",
    "gn:name":"Ban Pha Daeng",
    "gn:population":0,
    "gn:timezone":"Asia/Bangkok",
    "iso:country":"TH",
    "name:tha_x_preferred":[
        "\u0e1a\u0e49\u0e32\u0e19\u0e1c\u0e32\u0e41\u0e14\u0e07"
    ],
    "name:und_x_variant":[
        "B\u0101n Pha Deang",
        "Ban Pha Daeng"
    ],
    "wof:name":"Ban Pha Daeng",
    "wof:placetype":"locality"
},
  "geometry": {"coordinates":[99.79563,18.99175],"type":"Point"}
}