{
  "type": "Feature",
  "properties": {
    "gn:admin1_code":"51.0",
    "gn:asciiname":"Ban Wang Nam Chon",
    "gn:country_code":"TH",
    "gn:dem":50,
    "gn:feature_class":"P",
    "gn:feature_code":"PPL",
    "gn:name":"Ban Wang Nam Chon",
    "gn:population":0,
    "gn:timezone":"Asia/Bangkok",
    "iso:country":"TH",
    "name:tha_x_preferred":[
        "\u0e1a\u0e49\u0e32\u0e19\u0e27\u0e31\u0e07\u0e19\u0e49\u0e33\u0e42\u0e08\u0e19"
    ],
    "wof:name":"Ban Wang Nam Chon",
    "wof:placetype":"locality"
},
  "geometry": {"coordinates":[99.77607999999999,14.83208],"type":"Point"}
}