{
  "type": "Feature",
  "properties": {
    "gn:admin1_code":"26.0",
    "gn:asciiname":"Ban Tham Chan",
    "gn:country_code":"TH",
    "gn:dem":208,
    "gn:feature_class":"P",
    "gn:feature_code":"PPL",
    "gn:name":"Ban Tham Chan",
    "gn:population":0,
    "gn:timezone":"Asia/Bangkok",
    "iso:country":"TH",
    "name:tha_x_preferred":[
        "\u0e1a\u0e49\u0e32\u0e19\u0e17\u0e32\u0e21\u0e08\u0e32\u0e19"
    ],
    "wof:name":"Ban Tham Chan",
    "wof:placetype":"locality"
},
  "geometry": {"coordinates":[101.83336,15.49647],"type":"Point"}
}