{
  "type": "Feature",
  "properties": {
    "gn:country":"TH",
    "gn:fcode":"PPL",
    "gn:pop":52192,
    "iso:country":"TH",
    "name:eng_x_preferred":[
        "Talat Yai"
    ],
    "name:rus_x_preferred":[
        "\u0422\u0430\u043b\u0430\u0442-\u042f\u0438"
    ],
    "qs:name":"Ban Talat Yai",
    "qs:name_adm0":"Thailand",
    "qs:name_adm1":"Phuket",
    "qs:photos_9r":0,
    "qs:photos_sr":0,
    "qs:placetype":"Town",
    "qs:pop_sr":"8",
    "wof:name":"Ban Talat Yai",
    "wof:placetype":"locality",
    "wof:population":52192
},
  "geometry": {"coordinates":[98.40008,7.88481],"type":"Point"}
}