{
  "type": "Feature",
  "properties": {
    "gn:admin1_code":"70.0",
    "gn:asciiname":"Ban To Ku Sae",
    "gn:country_code":"TH",
    "gn:dem":33,
    "gn:feature_class":"P",
    "gn:feature_code":"PPL",
    "gn:name":"Ban To Ku Sae",
    "gn:population":0,
    "gn:timezone":"Asia/Bangkok",
    "iso:country":"TH",
    "name:tha_x_preferred":[
        "\u0e1a\u0e49\u0e32\u0e19\u0e42\u0e15\u0e4a\u0e30\u0e01\u0e39\u0e41\u0e0b"
    ],
    "wof:name":"Ban To Ku Sae",
    "wof:placetype":"locality"
},
  "geometry": {"coordinates":[101.38539,6.48608],"type":"Point"}
}