{
  "type": "Feature",
  "properties": {
    "gn:admin1_code":"27.0",
    "gn:asciiname":"Ban Khok Mai Ka Sang",
    "gn:country_code":"TH",
    "gn:dem":267,
    "gn:feature_class":"P",
    "gn:feature_code":"PPL",
    "gn:name":"Ban Khok Mai Ka Sang",
    "gn:population":0,
    "gn:timezone":"Asia/Bangkok",
    "iso:country":"TH",
    "wof:name":"Ban Khok Mai Ka Sang",
    "wof:placetype":"locality"
},
  "geometry": {"coordinates":[101.63472,15.30194],"type":"Point"}
}