{
  "type": "Feature",
  "properties": {
    "gn:admin1_code":"3.0",
    "gn:asciiname":"Ban Thung Duk",
    "gn:country_code":"TH",
    "gn:dem":365,
    "gn:feature_class":"P",
    "gn:feature_code":"PPL",
    "gn:name":"Ban Thung Duk",
    "gn:population":0,
    "gn:timezone":"Asia/Bangkok",
    "iso:country":"TH",
    "name:tha_x_preferred":[
        "\u0e1a\u0e49\u0e32\u0e19\u0e17\u0e38\u0e48\u0e07\u0e14\u0e38\u0e01"
    ],
    "wof:name":"Ban Thung Duk",
    "wof:placetype":"locality"
},
  "geometry": {"coordinates":[100.39785999999999,20.25306],"type":"Point"}
}