{
  "type": "Feature",
  "properties": {
    "gn:admin1_code":"66.0",
    "gn:asciiname":"Ban Khlong Chip",
    "gn:country_code":"TH",
    "gn:dem":11,
    "gn:feature_class":"P",
    "gn:feature_code":"PPL",
    "gn:name":"Ban Khlong Chip",
    "gn:population":0,
    "gn:timezone":"Asia/Bangkok",
    "iso:country":"TH",
    "name:tha_x_preferred":[
        "\u0e1a\u0e49\u0e32\u0e19\u0e04\u0e25\u0e2d\u0e07\u0e0a\u0e35\u0e1e"
    ],
    "wof:name":"Ban Khlong Chip",
    "wof:placetype":"locality"
},
  "geometry": {"coordinates":[100.20789000000001,7.41403],"type":"Point"}
}