{
  "type": "Feature",
  "properties": {
    "gn:admin1_code":"22",
    "gn:asciiname":"Ban Noi Tha Krasoem",
    "gn:country_code":"TH",
    "gn:dem":160,
    "gn:feature_class":"P",
    "gn:feature_code":"PPL",
    "gn:name":"Ban Noi Tha Krasoem",
    "gn:population":0,
    "gn:timezone":"Asia/Bangkok",
    "iso:country":"TH",
    "name:tha_x_preferred":[
        "\u0e1a\u0e49\u0e32\u0e19\u0e19\u0e49\u0e2d\u0e22\u0e17\u0e48\u0e32\u0e01\u0e23\u0e30\u0e40\u0e2a\u0e23\u0e34\u0e21"
    ],
    "wof:name":"Ban Noi Tha Krasoem",
    "wof:placetype":"locality"
},
  "geometry": {"coordinates":[102.86075,16.62689],"type":"Point"}
}