{
  "type": "Feature",
  "properties": {
    "gn:admin1_code":"37",
    "gn:asciiname":"Ban Nong Sai Nuea",
    "gn:country_code":"TH",
    "gn:dem":20,
    "gn:feature_class":"P",
    "gn:feature_code":"PPL",
    "gn:name":"Ban Nong Sai Nuea",
    "gn:population":0,
    "gn:timezone":"Asia/Bangkok",
    "iso:country":"TH",
    "name:tha_x_preferred":[
        "\u0e1a\u0e49\u0e32\u0e19\u0e2b\u0e19\u0e2d\u0e07\u0e44\u0e17\u0e23\u0e40\u0e2b\u0e19\u0e37\u0e2d"
    ],
    "wof:name":"Ban Nong Sai Nuea",
    "wof:placetype":"locality"
},
  "geometry": {"coordinates":[101.03642000000001,14.36894],"type":"Point"}
}