{
  "type": "Feature",
  "properties": {
    "gn:admin1_code":"70.0",
    "gn:asciiname":"Ban Thung Ya Mu",
    "gn:country_code":"TH",
    "gn:dem":30,
    "gn:feature_class":"P",
    "gn:feature_code":"PPL",
    "gn:name":"Ban Thung Ya Mu",
    "gn:population":0,
    "gn:timezone":"Asia/Bangkok",
    "iso:country":"TH",
    "name:tha_x_preferred":[
        "\u0e1a\u0e49\u0e32\u0e19\u0e17\u0e38\u0e48\u0e07\u0e22\u0e32\u0e21\u0e39"
    ],
    "wof:name":"Ban Thung Ya Mu",
    "wof:placetype":"locality"
},
  "geometry": {"coordinates":[101.23578000000001,6.58675],"type":"Point"}
}