{
  "type": "Feature",
  "properties": {
    "gn:admin1_code":"18.0",
    "gn:asciiname":"Ban Kok Ko",
    "gn:cc2":"TH",
    "gn:country_code":"TH",
    "gn:dem":654,
    "gn:feature_class":"P",
    "gn:feature_code":"PPL",
    "gn:name":"Ban Kok Ko",
    "gn:population":0,
    "gn:timezone":"Asia/Bangkok",
    "iso:country":"TH",
    "name:und_x_variant":[
        "Ban Khum Faek",
        "B\u0101n Kum Feak",
        "Ban Kok Ko"
    ],
    "wof:lang_x_official":[
        "tha"
    ],
    "wof:lang_x_spoken":[
        "tha"
    ],
    "wof:name":"Ban Kok Ko",
    "wof:placetype":"locality"
},
  "geometry": {"coordinates":[101.28333000000001,17.25],"type":"Point"}
}