{
  "type": "Feature",
  "properties": {
    "gn:admin1_code":"63.0",
    "gn:asciiname":"Ban Bo Muang",
    "gn:country_code":"TH",
    "gn:dem":28,
    "gn:feature_class":"P",
    "gn:feature_code":"PPL",
    "gn:name":"Ban Bo Muang",
    "gn:population":0,
    "gn:timezone":"Asia/Bangkok",
    "iso:country":"TH",
    "name:tha_x_preferred":[
        "\u0e1a\u0e49\u0e32\u0e19\u0e1a\u0e48\u0e2d\u0e21\u0e48\u0e27\u0e07"
    ],
    "wof:name":"Ban Bo Muang",
    "wof:placetype":"locality"
},
  "geometry": {"coordinates":[99.22396999999999,7.68789],"type":"Point"}
}