{
  "type": "Feature",
  "properties": {
    "gn:admin1_code":"27",
    "gn:asciiname":"Ban Khok Santisuk",
    "gn:country_code":"TH",
    "gn:dem":346,
    "gn:feature_class":"P",
    "gn:feature_code":"PPL",
    "gn:name":"Ban Khok Santisuk",
    "gn:population":0,
    "gn:timezone":"Asia/Bangkok",
    "iso:country":"TH",
    "name:tha_x_preferred":[
        "\u0e1a\u0e49\u0e32\u0e19\u0e42\u0e04\u0e01\u0e2a\u0e31\u0e19\u0e15\u0e34\u0e2a\u0e38\u0e02"
    ],
    "wof:lang_x_official":[
        "tha"
    ],
    "wof:lang_x_spoken":[
        "tha"
    ],
    "wof:name":"Ban Khok Santisuk",
    "wof:placetype":"locality"
},
  "geometry": {"coordinates":[101.78733,14.46067],"type":"Point"}
}