{
  "type": "Feature",
  "properties": {
    "gn:admin1_code":"61.0",
    "gn:asciiname":"Ban Phra Narai",
    "gn:country_code":"TH",
    "gn:dem":17,
    "gn:feature_class":"P",
    "gn:feature_code":"PPL",
    "gn:name":"Ban Phra Narai",
    "gn:population":0,
    "gn:timezone":"Asia/Bangkok",
    "iso:country":"TH",
    "name:tha_x_preferred":[
        "\u0e1a\u0e49\u0e32\u0e19\u0e1e\u0e23\u0e30\u0e19\u0e32\u0e23\u0e32\u0e22\u0e13\u0e4c"
    ],
    "wof:name":"Ban Phra Narai",
    "wof:placetype":"locality"
},
  "geometry": {"coordinates":[98.41719000000001,8.77747],"type":"Point"}
}