{
  "type": "Feature",
  "properties": {
    "gn:admin1_code":"16.0",
    "gn:asciiname":"Ban Wang Prathueang",
    "gn:country_code":"TH",
    "gn:dem":42,
    "gn:feature_class":"P",
    "gn:feature_code":"PPL",
    "gn:name":"Ban Wang Prathueang",
    "gn:population":0,
    "gn:timezone":"Asia/Bangkok",
    "iso:country":"TH",
    "name:tha_x_preferred":[
        "\u0e1a\u0e49\u0e32\u0e19\u0e27\u0e31\u0e07\u0e1b\u0e23\u0e30\u0e40\u0e17\u0e37\u0e2d\u0e07"
    ],
    "wof:name":"Ban Wang Prathueang",
    "wof:placetype":"locality"
},
  "geometry": {"coordinates":[99.98111,15.75608],"type":"Point"}
}