{
  "type": "Feature",
  "properties": {
    "gn:admin1_code":"34",
    "gn:asciiname":"Sun Wichai Lam Phaya Klang",
    "gn:country_code":"TH",
    "gn:dem":108,
    "gn:feature_class":"P",
    "gn:feature_code":"PPL",
    "gn:name":"Sun Wichai Lam Phaya Klang",
    "gn:population":0,
    "gn:timezone":"Asia/Bangkok",
    "iso:country":"TH",
    "name:tha_x_preferred":[
        "\u0e28\u0e39\u0e19\u0e22\u0e4c\u0e27\u0e34\u0e08\u0e31\u0e22\u0e25\u0e33\u0e1e\u0e0d\u0e32\u0e01\u0e25\u0e32\u0e07"
    ],
    "wof:lang_x_official":[
        "tha"
    ],
    "wof:lang_x_spoken":[
        "tha"
    ],
    "wof:name":"Sun Wichai Lam Phaya Klang",
    "wof:placetype":"locality"
},
  "geometry": {"coordinates":[101.38664,15.16344],"type":"Point"}
}