{
  "type": "Feature",
  "properties": {
    "gn:admin1_code":"25.0",
    "gn:asciiname":"Ban Nong Hu Ling",
    "gn:country_code":"TH",
    "gn:dem":159,
    "gn:feature_class":"P",
    "gn:feature_code":"PPL",
    "gn:name":"Ban Nong Hu Ling",
    "gn:population":0,
    "gn:timezone":"Asia/Bangkok",
    "iso:country":"TH",
    "name:tha_x_preferred":[
        "\u0e1a\u0e49\u0e32\u0e19\u0e2b\u0e19\u0e2d\u0e07\u0e2b\u0e39\u0e25\u0e34\u0e07"
    ],
    "wof:name":"Ban Nong Hu Ling",
    "wof:placetype":"locality"
},
  "geometry": {"coordinates":[103.80871999999999,16.25757999999999],"type":"Point"}
}