{
  "type": "Feature",
  "properties": {
    "gn:admin1_code":"28",
    "gn:asciiname":"Ban Borihan Chonnabot",
    "gn:country_code":"TH",
    "gn:dem":180,
    "gn:feature_class":"P",
    "gn:feature_code":"PPL",
    "gn:name":"Ban Borihan Chonnabot",
    "gn:population":0,
    "gn:timezone":"Asia/Bangkok",
    "iso:country":"TH",
    "name:tha_x_preferred":[
        "\u0e1a\u0e49\u0e32\u0e19\u0e1a\u0e23\u0e34\u0e2b\u0e32\u0e23\u0e0a\u0e19\u0e1a\u0e17"
    ],
    "wof:lang_x_official":[
        "tha"
    ],
    "wof:lang_x_spoken":[
        "tha"
    ],
    "wof:name":"Ban Borihan Chonnabot",
    "wof:placetype":"locality"
},
  "geometry": {"coordinates":[102.88211,15.03328],"type":"Point"}
}