{
  "type": "Feature",
  "properties": {
    "gn:admin1_code":"81.0",
    "gn:asciiname":"Ban Nong Na Saeng",
    "gn:country_code":"TH",
    "gn:dem":161,
    "gn:feature_class":"P",
    "gn:feature_code":"PPL",
    "gn:name":"Ban Nong Na Saeng",
    "gn:population":0,
    "gn:timezone":"Asia/Bangkok",
    "iso:country":"TH",
    "name:tha_x_preferred":[
        "\u0e1a\u0e49\u0e32\u0e19\u0e2b\u0e19\u0e2d\u0e07\u0e19\u0e32\u0e41\u0e0b\u0e07"
    ],
    "wof:name":"Ban Nong Na Saeng",
    "wof:placetype":"locality"
},
  "geometry": {"coordinates":[103.85850000000001,18.03694],"type":"Point"}
}