{
  "type": "Feature",
  "properties": {
    "gn:admin1_code":"50.0",
    "gn:asciiname":"Ban Hin Hak",
    "gn:cc2":"TH",
    "gn:country_code":"TH",
    "gn:dem":189,
    "gn:feature_class":"P",
    "gn:feature_code":"PPL",
    "gn:name":"Ban Hin Hak",
    "gn:population":0,
    "gn:timezone":"Asia/Bangkok",
    "iso:country":"TH",
    "name:und_x_variant":[
        "Ban Hin Huk",
        "Ban Hin Hak"
    ],
    "wof:name":"Ban Hin Hak",
    "wof:placetype":"locality"
},
  "geometry": {"coordinates":[99.15000000000001,14.46667],"type":"Point"}
}