{
  "type": "Feature",
  "properties": {
    "gn:admin1_code":"44.0",
    "gn:asciiname":"Ban Khlong Bang Chak",
    "gn:country_code":"TH",
    "gn:dem":2,
    "gn:feature_class":"P",
    "gn:feature_code":"PPL",
    "gn:name":"Ban Khlong Bang Chak",
    "gn:population":0,
    "gn:timezone":"Asia/Bangkok",
    "iso:country":"TH",
    "name:tha_x_preferred":[
        "\u0e1a\u0e49\u0e32\u0e19\u0e04\u0e25\u0e2d\u0e07\u0e1a\u0e32\u0e07\u0e08\u0e32\u0e01"
    ],
    "name:und_x_variant":[
        "Ban Bang Chak",
        "Ban Khlong Bang Chak"
    ],
    "wof:name":"Ban Khlong Bang Chak",
    "wof:placetype":"locality"
},
  "geometry": {"coordinates":[100.97781000000001,13.58575],"type":"Point"}
}