{
  "type": "Feature",
  "properties": {
    "gn:admin1_code":"23.0",
    "gn:asciiname":"Ban Thonburi",
    "gn:country_code":"TH",
    "gn:dem":147,
    "gn:feature_class":"P",
    "gn:feature_code":"PPL",
    "gn:name":"Ban Thonburi",
    "gn:population":0,
    "gn:timezone":"Asia/Bangkok",
    "iso:country":"TH",
    "name:tha_x_preferred":[
        "\u0e1a\u0e49\u0e32\u0e19\u0e18\u0e19\u0e1a\u0e38\u0e23\u0e35"
    ],
    "name:und_x_variant":[
        "Ban Thon Buri"
    ],
    "wof:name":"Ban Thonburi",
    "wof:placetype":"locality"
},
  "geometry": {"coordinates":[103.63794,16.32706],"type":"Point"}
}