{
  "type": "Feature",
  "properties": {
    "gn:admin1_code":"11.0",
    "gn:asciiname":"Ban Wang Mae Phai",
    "gn:country_code":"TH",
    "gn:dem":66,
    "gn:feature_class":"P",
    "gn:feature_code":"PPL",
    "gn:name":"Ban Wang Mae Phai",
    "gn:population":0,
    "gn:timezone":"Asia/Bangkok",
    "iso:country":"TH",
    "name:tha_x_preferred":[
        "\u0e1a\u0e49\u0e32\u0e19\u0e27\u0e31\u0e07\u0e41\u0e21\u0e48\u0e1e\u0e32\u0e22"
    ],
    "wof:name":"Ban Wang Mae Phai",
    "wof:placetype":"locality"
},
  "geometry": {"coordinates":[99.68714,16.58617000000001],"type":"Point"}
}