{
  "type": "Feature",
  "properties": {
    "gn:admin1_code":"65.0",
    "gn:asciiname":"Ban Chang Han",
    "gn:country_code":"TH",
    "gn:dem":33,
    "gn:feature_class":"P",
    "gn:feature_code":"PPL",
    "gn:name":"Ban Chang Han",
    "gn:population":0,
    "gn:timezone":"Asia/Bangkok",
    "iso:country":"TH",
    "name:tha_x_preferred":[
        "\u0e1a\u0e49\u0e32\u0e19\u0e0a\u0e49\u0e32\u0e07\u0e2b\u0e32\u0e23"
    ],
    "wof:lang_x_official":[
        "tha"
    ],
    "wof:lang_x_spoken":[
        "tha"
    ],
    "wof:name":"Ban Chang Han",
    "wof:placetype":"locality"
},
  "geometry": {"coordinates":[99.54431,7.87575],"type":"Point"}
}