{
  "type": "Feature",
  "properties": {
    "gn:admin1_code":"48.0",
    "gn:asciiname":"Ban Nong Ta Lin",
    "gn:country_code":"TH",
    "gn:dem":30,
    "gn:feature_class":"P",
    "gn:feature_code":"PPL",
    "gn:name":"Ban Nong Ta Lin",
    "gn:population":0,
    "gn:timezone":"Asia/Bangkok",
    "iso:country":"TH",
    "name:tha_x_preferred":[
        "\u0e1a\u0e49\u0e32\u0e19\u0e2b\u0e19\u0e2d\u0e07\u0e15\u0e32\u0e25\u0e34\u0e19"
    ],
    "wof:name":"Ban Nong Ta Lin",
    "wof:placetype":"locality"
},
  "geometry": {"coordinates":[101.99211,12.68983],"type":"Point"}
}