{
  "type": "Feature",
  "properties": {
    "gn:admin1_code":"6.0",
    "gn:asciiname":"Ban Pong Phan",
    "gn:country_code":"TH",
    "gn:dem":269,
    "gn:feature_class":"P",
    "gn:feature_code":"PPL",
    "gn:name":"Ban Pong Phan",
    "gn:population":0,
    "gn:timezone":"Asia/Bangkok",
    "iso:country":"TH",
    "name:tha_x_preferred":[
        "\u0e1a\u0e49\u0e32\u0e19\u0e42\u0e1b\u0e48\u0e07\u0e1e\u0e32\u0e19"
    ],
    "wof:name":"Ban Pong Phan",
    "wof:placetype":"locality"
},
  "geometry": {"coordinates":[99.20694,18.05878],"type":"Point"}
}