{
  "type": "Feature",
  "properties": {
    "gn:admin1_code":"49.0",
    "gn:asciiname":"Ban Choi Samrit Phon",
    "gn:country_code":"TH",
    "gn:dem":34,
    "gn:feature_class":"P",
    "gn:feature_code":"PPL",
    "gn:name":"Ban Choi Samrit Phon",
    "gn:population":0,
    "gn:timezone":"Asia/Bangkok",
    "iso:country":"TH",
    "name:tha_x_preferred":[
        "\u0e1a\u0e49\u0e32\u0e19\u0e0a\u0e2d\u0e22\u0e2a\u0e31\u0e21\u0e24\u0e17\u0e18\u0e34\u0e4c\u0e1c\u0e25"
    ],
    "wof:name":"Ban Choi Samrit Phon",
    "wof:placetype":"locality"
},
  "geometry": {"coordinates":[102.45377999999999,12.28506],"type":"Point"}
}