{
  "type": "Feature",
  "properties": {
    "gn:admin1_code":"15.0",
    "gn:asciiname":"Ban Hat Sai Ngam",
    "gn:country_code":"TH",
    "gn:dem":154,
    "gn:feature_class":"P",
    "gn:feature_code":"PPL",
    "gn:name":"Ban Hat Sai Ngam",
    "gn:population":0,
    "gn:timezone":"Asia/Bangkok",
    "iso:country":"TH",
    "name:tha_x_preferred":[
        "\u0e1a\u0e49\u0e32\u0e19\u0e2b\u0e32\u0e14\u0e17\u0e23\u0e32\u0e22\u0e07\u0e32\u0e21"
    ],
    "wof:name":"Ban Hat Sai Ngam",
    "wof:placetype":"locality"
},
  "geometry": {"coordinates":[99.47653,15.54261],"type":"Point"}
}