{
  "type": "Feature",
  "properties": {
    "gn:admin1_code":"18.0",
    "gn:asciiname":"Ban San Tom",
    "gn:country_code":"TH",
    "gn:dem":705,
    "gn:feature_class":"P",
    "gn:feature_code":"PPL",
    "gn:name":"Ban San Tom",
    "gn:population":0,
    "gn:timezone":"Asia/Bangkok",
    "iso:country":"TH",
    "name:tha_x_preferred":[
        "\u0e1a\u0e49\u0e32\u0e19\u0e2a\u0e32\u0e19\u0e15\u0e21"
    ],
    "name:und_x_variant":[
        "Ban Khon Phai",
        "B\u0101n Kaun Ph\u0101i",
        "Ban San Tom"
    ],
    "wof:name":"Ban San Tom",
    "wof:placetype":"locality"
},
  "geometry": {"coordinates":[101.47511,17.44242],"type":"Point"}
}