{
  "type": "Feature",
  "properties": {
    "gn:admin1_code":"31.0",
    "gn:asciiname":"Ban Sa Na Tong",
    "gn:country_code":"TH",
    "gn:dem":15,
    "gn:feature_class":"P",
    "gn:feature_code":"PPL",
    "gn:name":"Ban Sa Na Tong",
    "gn:population":0,
    "gn:timezone":"Asia/Bangkok",
    "iso:country":"TH",
    "name:tha_x_preferred":[
        "\u0e1a\u0e49\u0e32\u0e19\u0e2a\u0e30\u0e19\u0e32\u0e15\u0e07"
    ],
    "wof:name":"Ban Sa Na Tong",
    "wof:placetype":"locality"
},
  "geometry": {"coordinates":[101.74781,6.37258],"type":"Point"}
}