{
  "type": "Feature",
  "properties": {
    "gn:admin1_code":"68.0",
    "gn:asciiname":"Ban Khok Luk Mi",
    "gn:country_code":"TH",
    "gn:dem":71,
    "gn:feature_class":"P",
    "gn:feature_code":"PPL",
    "gn:name":"Ban Khok Luk Mi",
    "gn:population":0,
    "gn:timezone":"Asia/Bangkok",
    "iso:country":"TH",
    "name:tha_x_preferred":[
        "\u0e1a\u0e49\u0e32\u0e19\u0e42\u0e04\u0e01\u0e25\u0e39\u0e01\u0e2b\u0e21\u0e35"
    ],
    "wof:name":"Ban Khok Luk Mi",
    "wof:placetype":"locality"
},
  "geometry": {"coordinates":[100.60825,6.7542],"type":"Point"}
}