{
  "type": "Feature",
  "properties": {
    "gn:admin1_code":"44.0",
    "gn:asciiname":"Ban Nong Kaphong",
    "gn:cc2":"TH",
    "gn:country_code":"TH",
    "gn:dem":42,
    "gn:feature_class":"P",
    "gn:feature_code":"PPL",
    "gn:name":"Ban Nong Kaphong",
    "gn:population":0,
    "gn:timezone":"Asia/Bangkok",
    "iso:country":"TH",
    "name:und_x_variant":[
        "Ban Na Nong Kaphong",
        "Ban Nong Kaphong"
    ],
    "wof:name":"Ban Nong Kaphong",
    "wof:placetype":"locality"
},
  "geometry": {"coordinates":[101.65000000000001,13.65],"type":"Point"}
}