{
  "type": "Feature",
  "properties": {
    "gn:admin1_code":"44.0",
    "gn:asciiname":"Ban Bueng Krachap",
    "gn:country_code":"TH",
    "gn:dem":9,
    "gn:feature_class":"P",
    "gn:feature_code":"PPL",
    "gn:name":"Ban Bueng Krachap",
    "gn:population":0,
    "gn:timezone":"Asia/Bangkok",
    "iso:country":"TH",
    "name:tha_x_preferred":[
        "\u0e1a\u0e49\u0e32\u0e19\u0e1a\u0e36\u0e07\u0e01\u0e23\u0e30\u0e08\u0e31\u0e1a"
    ],
    "name:und_x_variant":[
        "Boeng Kachap",
        "Ban Bung Kachap",
        "Ban Bung Krachap (1)",
        "Ban Bueng Krachap"
    ],
    "wof:name":"Ban Bueng Krachap",
    "wof:placetype":"locality"
},
  "geometry": {"coordinates":[101.32911,13.70667],"type":"Point"}
}