{
  "type": "Feature",
  "properties": {
    "gn:admin1_code":"74",
    "gn:asciiname":"Ban Kaeng Phatthana",
    "gn:country_code":"TH",
    "gn:dem":25,
    "gn:feature_class":"P",
    "gn:feature_code":"PPL",
    "gn:name":"Ban Kaeng Phatthana",
    "gn:population":0,
    "gn:timezone":"Asia/Bangkok",
    "iso:country":"TH",
    "name:tha_x_preferred":[
        "\u0e1a\u0e49\u0e32\u0e19\u0e41\u0e01\u0e48\u0e07\u0e1e\u0e31\u0e12\u0e19\u0e32"
    ],
    "wof:name":"Ban Kaeng Phatthana",
    "wof:placetype":"locality"
},
  "geometry": {"coordinates":[101.87567,14.04503],"type":"Point"}
}