{
  "type": "Feature",
  "properties": {
    "gn:admin1_code":"76.0",
    "gn:asciiname":"Ban Muang Dong",
    "gn:country_code":"TH",
    "gn:dem":215,
    "gn:feature_class":"P",
    "gn:feature_code":"PPL",
    "gn:name":"Ban Muang Dong",
    "gn:population":0,
    "gn:timezone":"Asia/Bangkok",
    "iso:country":"TH",
    "name:tha_x_preferred":[
        "\u0e1a\u0e49\u0e32\u0e19\u0e21\u0e48\u0e27\u0e07\u0e14\u0e07"
    ],
    "wof:name":"Ban Muang Dong",
    "wof:placetype":"locality"
},
  "geometry": {"coordinates":[102.93886000000001,16.943],"type":"Point"}
}