{
  "type": "Feature",
  "properties": {
    "gn:admin1_code":"60.0",
    "gn:asciiname":"Ban Nikhom Phuthon Uthit",
    "gn:country_code":"TH",
    "gn:dem":13,
    "gn:feature_class":"P",
    "gn:feature_code":"PPL",
    "gn:name":"Ban Nikhom Phuthon Uthit",
    "gn:population":0,
    "gn:timezone":"Asia/Bangkok",
    "iso:country":"TH",
    "name:tha_x_preferred":[
        "\u0e1a\u0e49\u0e32\u0e19\u0e19\u0e34\u0e04\u0e21\u0e20\u0e39\u0e18\u0e23\u0e2d\u0e38\u0e17\u0e34\u0e28"
    ],
    "name:und_x_variant":[
        "Ban Nikhom Soi"
    ],
    "wof:name":"Ban Nikhom Phuthon Uthit",
    "wof:placetype":"locality"
},
  "geometry": {"coordinates":[99.37219,9.08528],"type":"Point"}
}