{
  "type": "Feature",
  "properties": {
    "gn:admin1_code":"6.0",
    "gn:asciiname":"Ban Thung Kham Tai",
    "gn:country_code":"TH",
    "gn:dem":246,
    "gn:feature_class":"P",
    "gn:feature_code":"PPL",
    "gn:name":"Ban Thung Kham Tai",
    "gn:population":0,
    "gn:timezone":"Asia/Bangkok",
    "iso:country":"TH",
    "name:tha_x_preferred":[
        "\u0e1a\u0e49\u0e32\u0e19\u0e17\u0e38\u0e48\u0e07\u0e02\u0e32\u0e21\u0e43\u0e15\u0e49"
    ],
    "wof:name":"Ban Thung Kham Tai",
    "wof:placetype":"locality"
},
  "geometry": {"coordinates":[99.31874999999999,18.23486],"type":"Point"}
}