{
  "type": "Feature",
  "properties": {
    "gn:admin1_code":"76.0",
    "gn:asciiname":"Ban Na Tham",
    "gn:country_code":"TH",
    "gn:dem":178,
    "gn:feature_class":"P",
    "gn:feature_code":"PPL",
    "gn:name":"Ban Na Tham",
    "gn:population":0,
    "gn:timezone":"Asia/Bangkok",
    "iso:country":"TH",
    "name:tha_x_preferred":[
        "\u0e1a\u0e49\u0e32\u0e19\u0e19\u0e32\u0e17\u0e32\u0e21"
    ],
    "wof:name":"Ban Na Tham",
    "wof:placetype":"locality"
},
  "geometry": {"coordinates":[102.73933,17.48869],"type":"Point"}
}