{
  "type": "Feature",
  "properties": {
    "gn:admin1_code":"47.0",
    "gn:asciiname":"Ban Samnak Mamuang",
    "gn:country_code":"TH",
    "gn:dem":14,
    "gn:feature_class":"P",
    "gn:feature_code":"PPL",
    "gn:name":"Ban Samnak Mamuang",
    "gn:population":0,
    "gn:timezone":"Asia/Bangkok",
    "iso:country":"TH",
    "name:tha_x_preferred":[
        "\u0e1a\u0e49\u0e32\u0e19\u0e2a\u0e33\u0e19\u0e31\u0e01\u0e21\u0e30\u0e21\u0e48\u0e27\u0e07"
    ],
    "name:und_x_variant":[
        "Ban Samnak Muang"
    ],
    "wof:name":"Ban Samnak Mamuang",
    "wof:placetype":"locality"
},
  "geometry": {"coordinates":[101.10138999999999,12.68667],"type":"Point"}
}