{
  "type": "Feature",
  "properties": {
    "gn:admin1_code":"3.0",
    "gn:asciiname":"Ban Musoe Phaya Kohok",
    "gn:country_code":"TH",
    "gn:dem":964,
    "gn:feature_class":"P",
    "gn:feature_code":"PPL",
    "gn:name":"Ban Musoe Phaya Kohok",
    "gn:population":0,
    "gn:timezone":"Asia/Bangkok",
    "iso:country":"TH",
    "name:tha_x_preferred":[
        "\u0e1a\u0e49\u0e32\u0e19\u0e21\u0e39\u0e40\u0e0b\u0e2d\u0e23\u0e4c\u0e1e\u0e0d\u0e32\u0e42\u0e01\u0e2b\u0e01"
    ],
    "wof:name":"Ban Musoe Phaya Kohok",
    "wof:placetype":"locality"
},
  "geometry": {"coordinates":[99.33772,19.69503],"type":"Point"}
}