{
  "type": "Feature",
  "properties": {
    "gn:admin1_code":"18.0",
    "gn:asciiname":"Ban Kaeng Dao",
    "gn:country_code":"TH",
    "gn:dem":648,
    "gn:feature_class":"P",
    "gn:feature_code":"PPL",
    "gn:name":"Ban Kaeng Dao",
    "gn:population":0,
    "gn:timezone":"Asia/Bangkok",
    "iso:country":"TH",
    "wof:name":"Ban Kaeng Dao",
    "wof:placetype":"locality"
},
  "geometry": {"coordinates":[101.06667,17.43333],"type":"Point"}
}