{
  "type": "Feature",
  "properties": {
    "gn:admin1_code":"26.0",
    "gn:asciiname":"Ban Noi Non Ma Wo",
    "gn:country_code":"TH",
    "gn:dem":193,
    "gn:feature_class":"P",
    "gn:feature_code":"PPL",
    "gn:name":"Ban Noi Non Ma Wo",
    "gn:population":0,
    "gn:timezone":"Asia/Bangkok",
    "iso:country":"TH",
    "name:tha_x_preferred":[
        "\u0e1a\u0e49\u0e32\u0e19\u0e19\u0e49\u0e2d\u0e22\u0e42\u0e19\u0e19\u0e2b\u0e21\u0e32\u0e27\u0e2d"
    ],
    "wof:name":"Ban Noi Non Ma Wo",
    "wof:placetype":"locality"
},
  "geometry": {"coordinates":[101.90442,15.71411],"type":"Point"}
}