{
  "type": "Feature",
  "properties": {
    "gn:admin1_code":"46.0",
    "gn:asciiname":"Ban Samnak Kato",
    "gn:country_code":"TH",
    "gn:dem":40,
    "gn:feature_class":"P",
    "gn:feature_code":"PPL",
    "gn:name":"Ban Samnak Kato",
    "gn:population":0,
    "gn:timezone":"Asia/Bangkok",
    "iso:country":"TH",
    "name:tha_x_preferred":[
        "\u0e1a\u0e49\u0e32\u0e19\u0e2a\u0e33\u0e19\u0e31\u0e01\u0e01\u0e30\u0e15\u0e2d"
    ],
    "wof:name":"Ban Samnak Kato",
    "wof:placetype":"locality"
},
  "geometry": {"coordinates":[101.18505999999999,13.314],"type":"Point"}
}