{
  "type": "Feature",
  "properties": {
    "gn:admin1_code":"52.0",
    "gn:asciiname":"Ban Nong Hu Chang",
    "gn:country_code":"TH",
    "gn:dem":11,
    "gn:feature_class":"P",
    "gn:feature_code":"PPL",
    "gn:name":"Ban Nong Hu Chang",
    "gn:population":0,
    "gn:timezone":"Asia/Bangkok",
    "iso:country":"TH",
    "name:tha_x_preferred":[
        "\u0e1a\u0e49\u0e32\u0e19\u0e2b\u0e19\u0e2d\u0e07\u0e2b\u0e39\u0e0a\u0e49\u0e32\u0e07"
    ],
    "name:und_x_variant":[
        "Ban Hua Chang"
    ],
    "wof:name":"Ban Nong Hu Chang",
    "wof:placetype":"locality"
},
  "geometry": {"coordinates":[99.89086,13.77753],"type":"Point"}
}