{
  "type": "Feature",
  "properties": {
    "gn:admin1_code":"31.0",
    "gn:asciiname":"Ban Nam Khun",
    "gn:country_code":"TH",
    "gn:dem":121,
    "gn:feature_class":"P",
    "gn:feature_code":"PPL",
    "gn:name":"Ban Nam Khun",
    "gn:population":0,
    "gn:timezone":"Asia/Bangkok",
    "iso:country":"TH",
    "name:tha_x_preferred":[
        "\u0e1a\u0e49\u0e32\u0e19\u0e19\u0e49\u0e33\u0e02\u0e38\u0e48\u0e19"
    ],
    "wof:name":"Ban Nam Khun",
    "wof:placetype":"locality"
},
  "geometry": {"coordinates":[101.71708,6.01492],"type":"Point"}
}