{
  "type": "Feature",
  "properties": {
    "gn:admin1_code":"64.0",
    "gn:asciiname":"Ban Pret",
    "gn:country_code":"TH",
    "gn:dem":17,
    "gn:feature_class":"P",
    "gn:feature_code":"PPL",
    "gn:name":"Ban Pret",
    "gn:population":0,
    "gn:timezone":"Asia/Bangkok",
    "iso:country":"TH",
    "name:tha_x_preferred":[
        "\u0e1a\u0e49\u0e32\u0e19\u0e40\u0e1b\u0e23\u0e47\u0e15"
    ],
    "wof:name":"Ban Pret",
    "wof:placetype":"locality"
},
  "geometry": {"coordinates":[99.86192,9.15047],"type":"Point"}
}