{
  "type": "Feature",
  "properties": {
    "gn:admin1_code":"36",
    "gn:asciiname":"Ban Kum Tae",
    "gn:country_code":"TH",
    "gn:dem":4,
    "gn:feature_class":"P",
    "gn:feature_code":"PPL",
    "gn:name":"Ban Kum Tae",
    "gn:population":0,
    "gn:timezone":"Asia/Bangkok",
    "iso:country":"TH",
    "name:tha_x_preferred":[
        "\u0e1a\u0e49\u0e32\u0e19\u0e01\u0e38\u0e21\u0e41\u0e15\u0e49"
    ],
    "wof:name":"Ban Kum Tae",
    "wof:placetype":"locality"
},
  "geometry": {"coordinates":[100.75089,14.36808],"type":"Point"}
}