{
  "type": "Feature",
  "properties": {
    "gn:admin1_code":"3.0",
    "gn:asciiname":"Ban Pa Yang Chum",
    "gn:country_code":"TH",
    "gn:dem":403,
    "gn:feature_class":"P",
    "gn:feature_code":"PPL",
    "gn:name":"Ban Pa Yang Chum",
    "gn:population":0,
    "gn:timezone":"Asia/Bangkok",
    "iso:country":"TH",
    "name:tha_x_preferred":[
        "\u0e1a\u0e49\u0e32\u0e19\u0e1b\u0e48\u0e32\u0e22\u0e32\u0e07\u0e0a\u0e38\u0e21"
    ],
    "wof:name":"Ban Pa Yang Chum",
    "wof:placetype":"locality"
},
  "geometry": {"coordinates":[99.88567,20.41992],"type":"Point"}
}