{
  "type": "Feature",
  "properties": {
    "gn:admin1_code":"29",
    "gn:asciiname":"Ban Pho Ngoen",
    "gn:country_code":"TH",
    "gn:dem":138,
    "gn:feature_class":"P",
    "gn:feature_code":"PPL",
    "gn:name":"Ban Pho Ngoen",
    "gn:population":0,
    "gn:timezone":"Asia/Bangkok",
    "iso:country":"TH",
    "name:tha_x_preferred":[
        "\u0e1a\u0e49\u0e32\u0e19\u0e42\u0e1e\u0e18\u0e34\u0e4c\u0e40\u0e07\u0e34\u0e19"
    ],
    "wof:name":"Ban Pho Ngoen",
    "wof:placetype":"locality"
},
  "geometry": {"coordinates":[103.17353,15.43023],"type":"Point"}
}