{
  "type": "Feature",
  "properties": {
    "gn:admin1_code":"18.0",
    "gn:asciiname":"Ban Huai Sisiat",
    "gn:country_code":"TH",
    "gn:dem":309,
    "gn:feature_class":"P",
    "gn:feature_code":"PPL",
    "gn:name":"Ban Huai Sisiat",
    "gn:population":0,
    "gn:timezone":"Asia/Bangkok",
    "iso:country":"TH",
    "name:tha_x_preferred":[
        "Ban Huai Sisiat"
    ],
    "name:tha_x_variant":[
        "\u0e1a\u0e49\u0e32\u0e19\u0e2b\u0e49\u0e27\u0e22\u0e2a\u0e35\u0e40\u0e2a\u0e35\u0e22\u0e14"
    ],
    "name:und_x_variant":[
        "Ban Huai Si Siat"
    ],
    "wof:lang_x_official":[
        "tha"
    ],
    "wof:lang_x_spoken":[
        "tha"
    ],
    "wof:name":"Ban Huai Sisiat",
    "wof:placetype":"locality"
},
  "geometry": {"coordinates":[101.73645,17.14203],"type":"Point"}
}