{
  "type": "Feature",
  "properties": {
    "gn:admin1_code":"23.0",
    "gn:asciiname":"Ban Suk Saeng Thong",
    "gn:country_code":"TH",
    "gn:dem":162,
    "gn:feature_class":"P",
    "gn:feature_code":"PPL",
    "gn:name":"Ban Suk Saeng Thong",
    "gn:population":0,
    "gn:timezone":"Asia/Bangkok",
    "iso:country":"TH",
    "name:tha_x_preferred":[
        "\u0e1a\u0e49\u0e32\u0e19\u0e2a\u0e38\u0e02\u0e41\u0e2a\u0e07\u0e17\u0e2d\u0e07"
    ],
    "wof:name":"Ban Suk Saeng Thong",
    "wof:placetype":"locality"
},
  "geometry": {"coordinates":[103.97214,16.49889],"type":"Point"}
}