{
  "type": "Feature",
  "properties": {
    "gn:admin1_code":"3.0",
    "gn:asciiname":"Ban Yai Tai",
    "gn:country_code":"TH",
    "gn:dem":372,
    "gn:feature_class":"P",
    "gn:feature_code":"PPL",
    "gn:name":"Ban Yai Tai",
    "gn:population":0,
    "gn:timezone":"Asia/Bangkok",
    "iso:country":"TH",
    "name:tha_x_preferred":[
        "\u0e1a\u0e49\u0e32\u0e19\u0e22\u0e32\u0e22\u0e43\u0e15\u0e49"
    ],
    "name:und_x_variant":[
        "Ban Yai",
        "Ban Yai Tai"
    ],
    "wof:lang_x_official":[
        "tha"
    ],
    "wof:lang_x_spoken":[
        "tha"
    ],
    "wof:name":"Ban Yai Tai",
    "wof:placetype":"locality"
},
  "geometry": {"coordinates":[100.52378,20.10925],"type":"Point"}
}