{
  "type": "Feature",
  "properties": {
    "gn:admin1_code":"22",
    "gn:asciiname":"Ban Si Ubon",
    "gn:country_code":"TH",
    "gn:dem":271,
    "gn:feature_class":"P",
    "gn:feature_code":"PPL",
    "gn:name":"Ban Si Ubon",
    "gn:population":0,
    "gn:timezone":"Asia/Bangkok",
    "iso:country":"TH",
    "name:tha_x_preferred":[
        "\u0e1a\u0e49\u0e32\u0e19\u0e28\u0e23\u0e35\u0e2d\u0e38\u0e1a\u0e25"
    ],
    "wof:name":"Ban Si Ubon",
    "wof:placetype":"locality"
},
  "geometry": {"coordinates":[102.09053,16.75883],"type":"Point"}
}