{
  "type": "Feature",
  "properties": {
    "gn:admin1_code":"54.0",
    "gn:asciiname":"Ban Khlong Bang Samrong",
    "gn:cc2":"TH",
    "gn:country_code":"TH",
    "gn:dem":8,
    "gn:feature_class":"P",
    "gn:feature_code":"PPL",
    "gn:name":"Ban Khlong Bang Samrong",
    "gn:population":0,
    "gn:timezone":"Asia/Bangkok",
    "iso:country":"TH",
    "name:und_x_variant":[
        "Ban Bang Samrong",
        "Ban Khlong Bang Samrong"
    ],
    "wof:name":"Ban Khlong Bang Samrong",
    "wof:placetype":"locality"
},
  "geometry": {"coordinates":[99.91667,13.45],"type":"Point"}
}