{
  "type": "Feature",
  "properties": {
    "gn:admin1_code":"4.0",
    "gn:asciiname":"Ban Na Pan",
    "gn:country_code":"TH",
    "gn:dem":259,
    "gn:feature_class":"P",
    "gn:feature_code":"PPL",
    "gn:name":"Ban Na Pan",
    "gn:population":0,
    "gn:timezone":"Asia/Bangkok",
    "iso:country":"TH",
    "name:tha_x_preferred":[
        "\u0e1a\u0e49\u0e32\u0e19\u0e19\u0e32\u0e1b\u0e48\u0e32\u0e19"
    ],
    "name:und_x_variant":[
        "Ban Ta Pan",
        "Ban Pan (1)",
        "Ban Na Pan"
    ],
    "wof:lang_x_official":[
        "tha"
    ],
    "wof:lang_x_spoken":[
        "tha"
    ],
    "wof:name":"Ban Na Pan",
    "wof:placetype":"locality"
},
  "geometry": {"coordinates":[100.92411,19.19739],"type":"Point"}
}