{
  "type": "Feature",
  "properties": {
    "gn:admin1_code":"16.0",
    "gn:asciiname":"Ban Wang Noi",
    "gn:country_code":"TH",
    "gn:dem":46,
    "gn:feature_class":"P",
    "gn:feature_code":"PPL",
    "gn:name":"Ban Wang Noi",
    "gn:population":0,
    "gn:timezone":"Asia/Bangkok",
    "iso:country":"TH",
    "wof:name":"Ban Wang Noi",
    "wof:placetype":"locality"
},
  "geometry": {"coordinates":[99.88472,15.70583],"type":"Point"}
}