{
  "type": "Feature",
  "properties": {
    "gn:admin1_code":"65.0",
    "gn:asciiname":"Ban Phrong Chorakhe",
    "gn:country_code":"TH",
    "gn:dem":38,
    "gn:feature_class":"P",
    "gn:feature_code":"PPL",
    "gn:name":"Ban Phrong Chorakhe",
    "gn:population":0,
    "gn:timezone":"Asia/Bangkok",
    "iso:country":"TH",
    "name:tha_x_preferred":[
        "\u0e1a\u0e49\u0e32\u0e19\u0e42\u0e1e\u0e23\u0e07\u0e08\u0e23\u0e30\u0e40\u0e02\u0e49"
    ],
    "wof:name":"Ban Phrong Chorakhe",
    "wof:placetype":"locality"
},
  "geometry": {"coordinates":[99.84344,7.31086],"type":"Point"}
}