{
  "type": "Feature",
  "properties": {
    "gn:admin1_code":"61.0",
    "gn:asciiname":"Ban Lum Salika",
    "gn:country_code":"TH",
    "gn:dem":34,
    "gn:feature_class":"P",
    "gn:feature_code":"PPL",
    "gn:name":"Ban Lum Salika",
    "gn:population":0,
    "gn:timezone":"Asia/Bangkok",
    "iso:country":"TH",
    "name:tha_x_preferred":[
        "\u0e1a\u0e49\u0e32\u0e19\u0e25\u0e38\u0e48\u0e21\u0e2a\u0e32\u0e25\u0e34\u0e01\u0e32"
    ],
    "wof:name":"Ban Lum Salika",
    "wof:placetype":"locality"
},
  "geometry": {"coordinates":[98.26514,8.41089],"type":"Point"}
}