{
  "type": "Feature",
  "properties": {
    "gn:admin1_code":"31.0",
    "gn:asciiname":"Ban Rue Po",
    "gn:country_code":"TH",
    "gn:dem":62,
    "gn:feature_class":"P",
    "gn:feature_code":"PPL",
    "gn:name":"Ban Rue Po",
    "gn:population":0,
    "gn:timezone":"Asia/Bangkok",
    "iso:country":"TH",
    "name:tha_x_preferred":[
        "\u0e1a\u0e49\u0e32\u0e19\u0e23\u0e37\u0e2d\u0e40\u0e1b\u0e32\u0e30"
    ],
    "name:und_x_variant":[
        "Ban Ru Po",
        "Ban Rue Po"
    ],
    "wof:name":"Ban Rue Po",
    "wof:placetype":"locality"
},
  "geometry": {"coordinates":[101.66994,6.15883],"type":"Point"}
}