{
  "type": "Feature",
  "properties": {
    "gn:admin1_code":"12.0",
    "gn:asciiname":"Ban Mung Tai",
    "gn:country_code":"TH",
    "gn:dem":72,
    "gn:feature_class":"P",
    "gn:feature_code":"PPL",
    "gn:name":"Ban Mung Tai",
    "gn:population":0,
    "gn:timezone":"Asia/Bangkok",
    "iso:country":"TH",
    "name:tha_x_preferred":[
        "\u0e1a\u0e49\u0e32\u0e19\u0e21\u0e38\u0e07\u0e43\u0e15\u0e49"
    ],
    "name:und_x_variant":[
        "Ban Mung"
    ],
    "wof:lang_x_official":[
        "tha"
    ],
    "wof:lang_x_spoken":[
        "tha"
    ],
    "wof:name":"Ban Mung Tai",
    "wof:placetype":"locality"
},
  "geometry": {"coordinates":[100.69347,16.55419],"type":"Point"}
}