{
  "type": "Feature",
  "properties": {
    "gn:country":"TH",
    "gn:fcode":"PPL",
    "gn:pop":856,
    "iso:country":"TH",
    "name:rus_x_preferred":[
        "\u041f\u0430\u043d\u0442\u0435-\u041c\u0430\u043b\u0430\u043a\u0430\u0440"
    ],
    "qs:name":"Pante Malakar",
    "qs:photos_9r":0,
    "qs:photos_sr":0,
    "qs:pop_sr":"2",
    "wof:name":"Pante Malakar",
    "wof:placetype":"locality",
    "wof:population":856
},
  "geometry": {"coordinates":[99.64359,6.68439],"type":"Point"}
}