{
  "type": "Feature",
  "properties": {
    "gn:admin1_code":"72.0",
    "gn:asciiname":"Ban Thiang Na Riang",
    "gn:country_code":"TH",
    "gn:dem":173,
    "gn:feature_class":"P",
    "gn:feature_code":"PPL",
    "gn:name":"Ban Thiang Na Riang",
    "gn:population":0,
    "gn:timezone":"Asia/Bangkok",
    "iso:country":"TH",
    "name:tha_x_preferred":[
        "\u0e1a\u0e49\u0e32\u0e19\u0e40\u0e17\u0e35\u0e48\u0e22\u0e07\u0e19\u0e32\u0e40\u0e23\u0e35\u0e22\u0e07"
    ],
    "wof:name":"Ban Thiang Na Riang",
    "wof:placetype":"locality"
},
  "geometry": {"coordinates":[104.28968999999999,16.08077999999999],"type":"Point"}
}