{
  "type": "Feature",
  "properties": {
    "gn:admin1_code":"48.0",
    "gn:asciiname":"Ban Thaeo Khlong",
    "gn:country_code":"TH",
    "gn:dem":21,
    "gn:feature_class":"P",
    "gn:feature_code":"PPL",
    "gn:name":"Ban Thaeo Khlong",
    "gn:population":0,
    "gn:timezone":"Asia/Bangkok",
    "iso:country":"TH",
    "name:tha_x_preferred":[
        "\u0e1a\u0e49\u0e32\u0e19\u0e41\u0e16\u0e27\u0e04\u0e25\u0e2d\u0e07"
    ],
    "wof:name":"Ban Thaeo Khlong",
    "wof:placetype":"locality"
},
  "geometry": {"coordinates":[102.17703,12.62031],"type":"Point"}
}