{
  "type": "Feature",
  "properties": {
    "gn:admin1_code":"44.0",
    "gn:asciiname":"Ban Ao Charoen",
    "gn:country_code":"TH",
    "gn:dem":48,
    "gn:feature_class":"P",
    "gn:feature_code":"PPL",
    "gn:name":"Ban Ao Charoen",
    "gn:population":0,
    "gn:timezone":"Asia/Bangkok",
    "iso:country":"TH",
    "name:tha_x_preferred":[
        "\u0e1a\u0e49\u0e32\u0e19\u0e2d\u0e48\u0e32\u0e27\u0e40\u0e08\u0e23\u0e34\u0e0d"
    ],
    "wof:name":"Ban Ao Charoen",
    "wof:placetype":"locality"
},
  "geometry": {"coordinates":[101.54975,13.60061],"type":"Point"}
}