{
  "type": "Feature",
  "properties": {
    "gn:admin1_code":"46.0",
    "gn:asciiname":"Ban Charoen Rat",
    "gn:country_code":"TH",
    "gn:dem":16,
    "gn:feature_class":"P",
    "gn:feature_code":"PPL",
    "gn:name":"Ban Charoen Rat",
    "gn:population":0,
    "gn:timezone":"Asia/Bangkok",
    "iso:country":"TH",
    "name:tha_x_preferred":[
        "\u0e1a\u0e49\u0e32\u0e19\u0e40\u0e08\u0e23\u0e34\u0e0d\u0e23\u0e31\u0e15\u0e19\u0e4c"
    ],
    "wof:name":"Ban Charoen Rat",
    "wof:placetype":"locality"
},
  "geometry": {"coordinates":[100.96817,13.31125],"type":"Point"}
}