{
  "type": "Feature",
  "properties": {
    "gn:admin1_code":"31.0",
    "gn:asciiname":"Ban Hu Mo Bu Lo",
    "gn:country_code":"TH",
    "gn:dem":57,
    "gn:feature_class":"P",
    "gn:feature_code":"PPL",
    "gn:name":"Ban Hu Mo Bu Lo",
    "gn:population":0,
    "gn:timezone":"Asia/Bangkok",
    "iso:country":"TH",
    "name:tha_x_preferred":[
        "\u0e1a\u0e49\u0e32\u0e19\u0e2e\u0e39\u0e21\u0e2d\u0e1a\u0e39\u0e42\u0e25\u0e4a\u0e30"
    ],
    "wof:name":"Ban Hu Mo Bu Lo",
    "wof:placetype":"locality"
},
  "geometry": {"coordinates":[101.84056,5.98083],"type":"Point"}
}