{
  "type": "Feature",
  "properties": {
    "gn:admin1_code":"74",
    "gn:asciiname":"Ban Wang Thalu",
    "gn:country_code":"TH",
    "gn:dem":15,
    "gn:feature_class":"P",
    "gn:feature_code":"PPL",
    "gn:name":"Ban Wang Thalu",
    "gn:population":0,
    "gn:timezone":"Asia/Bangkok",
    "iso:country":"TH",
    "name:tha_x_preferred":[
        "\u0e1a\u0e49\u0e32\u0e19\u0e27\u0e31\u0e07\u0e17\u0e30\u0e25\u0e38"
    ],
    "wof:name":"Ban Wang Thalu",
    "wof:placetype":"locality"
},
  "geometry": {"coordinates":[101.56953,14.13972],"type":"Point"}
}