{
  "type": "Feature",
  "properties": {
    "gn:admin1_code":"44.0",
    "gn:asciiname":"Ban Bang Ngua",
    "gn:cc2":"TH",
    "gn:country_code":"TH",
    "gn:dem":4,
    "gn:feature_class":"P",
    "gn:feature_code":"PPL",
    "gn:name":"Ban Bang Ngua",
    "gn:population":0,
    "gn:timezone":"Asia/Bangkok",
    "iso:country":"TH",
    "name:und_x_variant":[
        "Bang Ngua",
        "Ban Bang Wua",
        "Ban Bang Ngua"
    ],
    "wof:name":"Ban Bang Ngua",
    "wof:placetype":"locality"
},
  "geometry": {"coordinates":[100.96666999999999,13.55],"type":"Point"}
}