{
  "type": "Feature",
  "properties": {
    "gn:admin1_code":"63.0",
    "gn:asciiname":"Ban Khao Thong",
    "gn:country_code":"TH",
    "gn:dem":81,
    "gn:feature_class":"P",
    "gn:feature_code":"PPL",
    "gn:name":"Ban Khao Thong",
    "gn:population":0,
    "gn:timezone":"Asia/Bangkok",
    "iso:country":"TH",
    "name:tha_x_preferred":[
        "\u0e1a\u0e49\u0e32\u0e19\u0e40\u0e02\u0e32\u0e17\u0e2d\u0e07"
    ],
    "name:und_x_variant":[
        "Khao Thaung",
        "Ban Kau Tong",
        "Khao Thong",
        "Ban Khao Thong"
    ],
    "wof:name":"Ban Khao Thong",
    "wof:placetype":"locality"
},
  "geometry": {"coordinates":[98.76669,8.17181],"type":"Point"}
}