{
  "type": "Feature",
  "properties": {
    "gn:admin1_code":"7.0",
    "gn:asciiname":"Ban Na Rai Diao",
    "gn:country_code":"TH",
    "gn:dem":231,
    "gn:feature_class":"P",
    "gn:feature_code":"PPL",
    "gn:name":"Ban Na Rai Diao",
    "gn:population":0,
    "gn:timezone":"Asia/Bangkok",
    "iso:country":"TH",
    "name:tha_x_preferred":[
        "\u0e1a\u0e49\u0e32\u0e19\u0e19\u0e32\u0e44\u0e23\u0e48\u0e40\u0e14\u0e35\u0e22\u0e27"
    ],
    "name:und_x_variant":[
        "Ban Rai Na Dieo"
    ],
    "wof:name":"Ban Na Rai Diao",
    "wof:placetype":"locality"
},
  "geometry": {"coordinates":[100.19481,18.54136],"type":"Point"}
}