{
  "type": "Feature",
  "properties": {
    "gn:admin1_code":"13.0",
    "gn:asciiname":"Ban Nong Ko But",
    "gn:country_code":"TH",
    "gn:dem":31,
    "gn:feature_class":"P",
    "gn:feature_code":"PPL",
    "gn:name":"Ban Nong Ko But",
    "gn:population":0,
    "gn:timezone":"Asia/Bangkok",
    "iso:country":"TH",
    "name:tha_x_preferred":[
        "\u0e1a\u0e49\u0e32\u0e19\u0e2b\u0e19\u0e2d\u0e07\u0e42\u0e01\u0e1a\u0e38\u0e15\u0e23"
    ],
    "wof:name":"Ban Nong Ko But",
    "wof:placetype":"locality"
},
  "geometry": {"coordinates":[100.26111,16.05564],"type":"Point"}
}