{
  "type": "Feature",
  "properties": {
    "gn:admin1_code":"60.0",
    "gn:asciiname":"Ban Chong Inthanin",
    "gn:country_code":"TH",
    "gn:dem":60,
    "gn:feature_class":"P",
    "gn:feature_code":"PPL",
    "gn:name":"Ban Chong Inthanin",
    "gn:population":0,
    "gn:timezone":"Asia/Bangkok",
    "iso:country":"TH",
    "name:tha_x_preferred":[
        "\u0e1a\u0e49\u0e32\u0e19\u0e0a\u0e48\u0e2d\u0e07\u0e2d\u0e34\u0e19\u0e17\u0e19\u0e34\u0e25"
    ],
    "wof:name":"Ban Chong Inthanin",
    "wof:placetype":"locality"
},
  "geometry": {"coordinates":[98.95175,9.27903],"type":"Point"}
}