{
  "type": "Feature",
  "properties": {
    "gn:admin1_code":"64.0",
    "gn:asciiname":"Ban Wang Khong",
    "gn:country_code":"TH",
    "gn:dem":18,
    "gn:feature_class":"P",
    "gn:feature_code":"PPL",
    "gn:name":"Ban Wang Khong",
    "gn:population":0,
    "gn:timezone":"Asia/Bangkok",
    "iso:country":"TH",
    "name:tha_x_preferred":[
        "\u0e1a\u0e49\u0e32\u0e19\u0e27\u0e31\u0e07\u0e06\u0e49\u0e2d\u0e07"
    ],
    "wof:name":"Ban Wang Khong",
    "wof:placetype":"locality"
},
  "geometry": {"coordinates":[99.88124999999999,8.06828],"type":"Point"}
}