{
  "type": "Feature",
  "properties": {
    "gn:admin1_code":"61.0",
    "gn:asciiname":"Ban Khlong Chon",
    "gn:cc2":"TH",
    "gn:country_code":"TH",
    "gn:dem":30,
    "gn:feature_class":"P",
    "gn:feature_code":"PPL",
    "gn:name":"Ban Khlong Chon",
    "gn:population":0,
    "gn:timezone":"Asia/Bangkok",
    "iso:country":"TH",
    "name:und_x_variant":[
        "Ban Khlong Phon",
        "Ban Khlong Chon"
    ],
    "wof:name":"Ban Khlong Chon",
    "wof:placetype":"locality"
},
  "geometry": {"coordinates":[98.51667,8.53333],"type":"Point"}
}