{
  "type": "Feature",
  "properties": {
    "gn:admin1_code":"2.0",
    "gn:asciiname":"Ban Pa Miang Huai Hok",
    "gn:country_code":"TH",
    "gn:dem":804,
    "gn:feature_class":"P",
    "gn:feature_code":"PPL",
    "gn:name":"Ban Pa Miang Huai Hok",
    "gn:population":0,
    "gn:timezone":"Asia/Bangkok",
    "iso:country":"TH",
    "name:tha_x_preferred":[
        "\u0e1a\u0e49\u0e32\u0e19\u0e1b\u0e48\u0e32\u0e40\u0e21\u0e35\u0e48\u0e22\u0e07\u0e2b\u0e49\u0e27\u0e22\u0e2b\u0e01"
    ],
    "wof:name":"Ban Pa Miang Huai Hok",
    "wof:placetype":"locality"
},
  "geometry": {"coordinates":[99.27769000000001,19.07669],"type":"Point"}
}