{
  "type": "Feature",
  "properties": {
    "gn:admin1_code":"56.0",
    "gn:asciiname":"Ban Thin Pura",
    "gn:country_code":"TH",
    "gn:dem":11,
    "gn:feature_class":"P",
    "gn:feature_code":"PPL",
    "gn:name":"Ban Thin Pura",
    "gn:population":0,
    "gn:timezone":"Asia/Bangkok",
    "iso:country":"TH",
    "name:tha_x_preferred":[
        "\u0e1a\u0e49\u0e32\u0e19\u0e16\u0e34\u0e48\u0e19\u0e1b\u0e38\u0e23\u0e32"
    ],
    "name:und_x_variant":[
        "Ban Thin Pla Ra"
    ],
    "wof:name":"Ban Thin Pura",
    "wof:placetype":"locality"
},
  "geometry": {"coordinates":[99.97847,13.02314],"type":"Point"}
}