{
  "type": "Feature",
  "properties": {
    "gn:admin1_code":"3.0",
    "gn:asciiname":"Ban Pha Daeng",
    "gn:country_code":"TH",
    "gn:dem":538,
    "gn:feature_class":"P",
    "gn:feature_code":"PPL",
    "gn:name":"Ban Pha Daeng",
    "gn:population":0,
    "gn:timezone":"Asia/Bangkok",
    "iso:country":"TH",
    "name:tha_x_preferred":[
        "\u0e1a\u0e49\u0e32\u0e19\u0e1c\u0e32\u0e41\u0e14\u0e07"
    ],
    "name:tha_x_variant":[
        "\u0e1a\u0e49\u0e32\u0e19\u0e21\u0e39\u0e40\u0e0b\u0e2d"
    ],
    "name:und_x_variant":[
        "Ban Musoe",
        "\u0e1a\u0e49\u0e32\u0e19\u0e21\u0e39\u0e40\u0e0b\u0e2d"
    ],
    "wof:name":"Ban Pha Daeng",
    "wof:placetype":"locality"
},
  "geometry": {"coordinates":[99.50095,19.7427],"type":"Point"}
}