{
  "type": "Feature",
  "properties": {
    "gn:admin1_code":"43.0",
    "gn:asciiname":"Ban Tha Krathum",
    "gn:country_code":"TH",
    "gn:dem":4,
    "gn:feature_class":"P",
    "gn:feature_code":"PPL",
    "gn:name":"Ban Tha Krathum",
    "gn:population":0,
    "gn:timezone":"Asia/Bangkok",
    "iso:country":"TH",
    "name:tha_x_preferred":[
        "\u0e1a\u0e49\u0e32\u0e19\u0e17\u0e48\u0e32\u0e01\u0e23\u0e30\u0e17\u0e38\u0e48\u0e21"
    ],
    "name:und_x_variant":[
        "Ka Tum",
        "Ban Kathum",
        "Ban Tha Krathum (2)",
        "Ban Tha Krathum"
    ],
    "wof:name":"Ban Tha Krathum",
    "wof:placetype":"locality"
},
  "geometry": {"coordinates":[101.21035999999999,14.04933],"type":"Point"}
}