{
  "type": "Feature",
  "properties": {
    "gn:admin1_code":"51.0",
    "gn:asciiname":"Ban Nong Tat Sak",
    "gn:country_code":"TH",
    "gn:dem":15,
    "gn:feature_class":"P",
    "gn:feature_code":"PPL",
    "gn:name":"Ban Nong Tat Sak",
    "gn:population":0,
    "gn:timezone":"Asia/Bangkok",
    "iso:country":"TH",
    "name:tha_x_preferred":[
        "\u0e1a\u0e49\u0e32\u0e19\u0e2b\u0e19\u0e2d\u0e07\u0e15\u0e31\u0e14\u0e2a\u0e32\u0e01"
    ],
    "wof:name":"Ban Nong Tat Sak",
    "wof:placetype":"locality"
},
  "geometry": {"coordinates":[99.85957999999999,14.07147],"type":"Point"}
}