{
  "type": "Feature",
  "properties": {
    "gn:admin1_code":"74",
    "gn:asciiname":"Ban Wang Ruea Noi",
    "gn:country_code":"TH",
    "gn:dem":18,
    "gn:feature_class":"P",
    "gn:feature_code":"PPL",
    "gn:name":"Ban Wang Ruea Noi",
    "gn:population":0,
    "gn:timezone":"Asia/Bangkok",
    "iso:country":"TH",
    "name:tha_x_preferred":[
        "\u0e1a\u0e49\u0e32\u0e19\u0e27\u0e31\u0e07\u0e40\u0e23\u0e37\u0e2d\u0e19\u0e49\u0e2d\u0e22"
    ],
    "wof:name":"Ban Wang Ruea Noi",
    "wof:placetype":"locality"
},
  "geometry": {"coordinates":[101.57717,14.15953],"type":"Point"}
}