{
  "type": "Feature",
  "properties": {
    "gn:admin1_code":"10.0",
    "gn:asciiname":"Ban Nong Yim Paen",
    "gn:country_code":"TH",
    "gn:dem":157,
    "gn:feature_class":"P",
    "gn:feature_code":"PPL",
    "gn:name":"Ban Nong Yim Paen",
    "gn:population":0,
    "gn:timezone":"Asia/Bangkok",
    "iso:country":"TH",
    "name:tha_x_preferred":[
        "Ban Nong Yim Paen"
    ],
    "name:tha_x_variant":[
        "\u0e1a\u0e49\u0e32\u0e19\u0e2b\u0e19\u0e2d\u0e07\u0e22\u0e34\u0e49\u0e21\u0e41\u0e1b\u0e49\u0e19"
    ],
    "wof:name":"Ban Nong Yim Paen",
    "wof:placetype":"locality"
},
  "geometry": {"coordinates":[100.35914,17.61853],"type":"Point"}
}