{
  "type": "Feature",
  "properties": {
    "gn:admin1_code":"75.0",
    "gn:asciiname":"Ban Kalueng",
    "gn:country_code":"TH",
    "gn:dem":161,
    "gn:feature_class":"P",
    "gn:feature_code":"PPL",
    "gn:name":"Ban Kalueng",
    "gn:population":0,
    "gn:timezone":"Asia/Bangkok",
    "iso:country":"TH",
    "name:tha_x_preferred":[
        "\u0e1a\u0e49\u0e32\u0e19\u0e01\u0e30\u0e25\u0e36\u0e07"
    ],
    "name:und_x_variant":[
        "Ban Kalung"
    ],
    "wof:name":"Ban Kalueng",
    "wof:placetype":"locality"
},
  "geometry": {"coordinates":[105.28538,15.78119],"type":"Point"}
}