{
  "type": "Feature",
  "properties": {
    "gn:admin1_code":"60.0",
    "gn:asciiname":"Ban Ko Phaluai",
    "gn:country_code":"TH",
    "gn:dem":23,
    "gn:feature_class":"P",
    "gn:feature_code":"PPL",
    "gn:name":"Ban Ko Phaluai",
    "gn:population":0,
    "gn:timezone":"Asia/Bangkok",
    "iso:country":"TH",
    "name:tha_x_preferred":[
        "\u0e1a\u0e49\u0e32\u0e19\u0e40\u0e01\u0e32\u0e30\u0e1e\u0e30\u0e25\u0e27\u0e22"
    ],
    "wof:name":"Ban Ko Phaluai",
    "wof:placetype":"locality"
},
  "geometry": {"coordinates":[99.67975,9.53975],"type":"Point"}
}