{
  "type": "Feature",
  "properties": {
    "gn:admin1_code":"3.0",
    "gn:asciiname":"Ban Prang Phraratchathan (3)",
    "gn:country_code":"TH",
    "gn:dem":426,
    "gn:feature_class":"P",
    "gn:feature_code":"PPL",
    "gn:name":"Ban Prang Phraratchathan (3)",
    "gn:population":0,
    "gn:timezone":"Asia/Bangkok",
    "iso:country":"TH",
    "name:tha_x_preferred":[
        "\u0e1a\u0e49\u0e32\u0e19\u0e1b\u0e23\u0e32\u0e07\u0e1e\u0e23\u0e30\u0e23\u0e32\u0e0a\u0e17\u0e32\u0e19 \u0e2a\u0e32\u0e21"
    ],
    "name:und_x_variant":[
        "Ban Prang Phraratchathan",
        "Ban Prang Phraratchathan (3)",
        "Ban Prang Phraratchathan Sam"
    ],
    "wof:name":"Ban Prang Phraratchathan (3)",
    "wof:placetype":"locality"
},
  "geometry": {"coordinates":[99.80425,20.24231],"type":"Point"}
}