{
  "type": "Feature",
  "properties": {
    "gn:admin1_code":"25.0",
    "gn:asciiname":"Ban Nom",
    "gn:country_code":"TH",
    "gn:dem":138,
    "gn:feature_class":"P",
    "gn:feature_code":"PPL",
    "gn:name":"Ban Nom",
    "gn:population":0,
    "gn:timezone":"Asia/Bangkok",
    "iso:country":"TH",
    "name:tha_x_preferred":[
        "\u0e1a\u0e49\u0e32\u0e19\u0e2b\u0e19\u0e48\u0e2d\u0e21"
    ],
    "name:und_x_variant":[
        "Ban Mom"
    ],
    "wof:name":"Ban Nom",
    "wof:placetype":"locality"
},
  "geometry": {"coordinates":[103.94869,15.79372],"type":"Point"}
}