{
  "type": "Feature",
  "properties": {
    "gn:admin1_code":"48.0",
    "gn:asciiname":"Ban Khlong Chom",
    "gn:country_code":"TH",
    "gn:dem":85,
    "gn:feature_class":"P",
    "gn:feature_code":"PPL",
    "gn:name":"Ban Khlong Chom",
    "gn:population":0,
    "gn:timezone":"Asia/Bangkok",
    "iso:country":"TH",
    "name:tha_x_preferred":[
        "\u0e1a\u0e49\u0e32\u0e19\u0e04\u0e25\u0e2d\u0e07\u0e0a\u0e21"
    ],
    "wof:lang_x_official":[
        "tha"
    ],
    "wof:lang_x_spoken":[
        "tha"
    ],
    "wof:name":"Ban Khlong Chom",
    "wof:placetype":"locality"
},
  "geometry": {"coordinates":[102.03386,13.06494],"type":"Point"}
}