{
  "type": "Feature",
  "properties": {
    "gn:admin1_code":"10.0",
    "gn:asciiname":"Ban Mon Mai",
    "gn:country_code":"TH",
    "gn:dem":75,
    "gn:feature_class":"P",
    "gn:feature_code":"PPL",
    "gn:name":"Ban Mon Mai",
    "gn:population":0,
    "gn:timezone":"Asia/Bangkok",
    "iso:country":"TH",
    "name:tha_x_preferred":[
        "Ban Mon Mai"
    ],
    "name:tha_x_variant":[
        "\u0e1a\u0e49\u0e32\u0e19\u0e2b\u0e21\u0e2d\u0e19\u0e44\u0e21\u0e49"
    ],
    "wof:name":"Ban Mon Mai",
    "wof:placetype":"locality"
},
  "geometry": {"coordinates":[100.26139000000001,17.65442000000001],"type":"Point"}
}