{
  "type": "Feature",
  "properties": {
    "gn:admin1_code":"3.0",
    "gn:asciiname":"Ban Pham Wua",
    "gn:country_code":"TH",
    "gn:dem":403,
    "gn:feature_class":"P",
    "gn:feature_code":"PPL",
    "gn:name":"Ban Pham Wua",
    "gn:population":0,
    "gn:timezone":"Asia/Bangkok",
    "iso:country":"TH",
    "name:tha_x_preferred":[
        "\u0e1a\u0e49\u0e32\u0e19\u0e1c\u0e32\u0e21\u0e27\u0e31\u0e27"
    ],
    "wof:name":"Ban Pham Wua",
    "wof:placetype":"locality"
},
  "geometry": {"coordinates":[99.76600000000001,19.51311],"type":"Point"}
}