{
  "type": "Feature",
  "properties": {
    "gn:admin1_code":"20.0",
    "gn:asciiname":"Ban Noi Nong Hak",
    "gn:country_code":"TH",
    "gn:dem":181,
    "gn:feature_class":"P",
    "gn:feature_code":"PPL",
    "gn:name":"Ban Noi Nong Hak",
    "gn:population":0,
    "gn:timezone":"Asia/Bangkok",
    "iso:country":"TH",
    "name:tha_x_preferred":[
        "\u0e1a\u0e49\u0e32\u0e19\u0e19\u0e49\u0e2d\u0e22\u0e2b\u0e19\u0e2d\u0e07\u0e2e\u0e32\u0e01"
    ],
    "wof:name":"Ban Noi Nong Hak",
    "wof:placetype":"locality"
},
  "geometry": {"coordinates":[104.19211,17.04433],"type":"Point"}
}