{
  "type": "Feature",
  "properties": {
    "gn:admin1_code":"80",
    "gn:asciiname":"Ban Noen Sai Fon",
    "gn:country_code":"TH",
    "gn:dem":98,
    "gn:feature_class":"P",
    "gn:feature_code":"PPL",
    "gn:name":"Ban Noen Sai Fon",
    "gn:population":0,
    "gn:timezone":"Asia/Bangkok",
    "iso:country":"TH",
    "name:tha_x_preferred":[
        "\u0e1a\u0e49\u0e32\u0e19\u0e40\u0e19\u0e34\u0e19\u0e2a\u0e32\u0e22\u0e1d\u0e19"
    ],
    "wof:name":"Ban Noen Sai Fon",
    "wof:placetype":"locality"
},
  "geometry": {"coordinates":[101.90636000000001,13.53528],"type":"Point"}
}