{
  "type": "Feature",
  "properties": {
    "gn:admin1_code":"18.0",
    "gn:asciiname":"Ban Than Tawan",
    "gn:country_code":"TH",
    "gn:dem":257,
    "gn:feature_class":"P",
    "gn:feature_code":"PPL",
    "gn:name":"Ban Than Tawan",
    "gn:population":0,
    "gn:timezone":"Asia/Bangkok",
    "iso:country":"TH",
    "name:tha_x_preferred":[
        "Ban Than Tawan"
    ],
    "name:tha_x_variant":[
        "\u0e1a\u0e49\u0e32\u0e19\u0e17\u0e32\u0e19\u0e15\u0e30\u0e27\u0e31\u0e19"
    ],
    "wof:name":"Ban Than Tawan",
    "wof:placetype":"locality"
},
  "geometry": {"coordinates":[101.84111,16.82528],"type":"Point"}
}