{
  "type": "Feature",
  "properties": {
    "gn:admin1_code":"11.0",
    "gn:asciiname":"Ban Bueng Kradan",
    "gn:country_code":"TH",
    "gn:dem":54,
    "gn:feature_class":"P",
    "gn:feature_code":"PPL",
    "gn:name":"Ban Bueng Kradan",
    "gn:population":0,
    "gn:timezone":"Asia/Bangkok",
    "iso:country":"TH",
    "name:tha_x_preferred":[
        "\u0e1a\u0e49\u0e32\u0e19\u0e1a\u0e36\u0e07\u0e01\u0e23\u0e30\u0e14\u0e32\u0e19"
    ],
    "wof:name":"Ban Bueng Kradan",
    "wof:placetype":"locality"
},
  "geometry": {"coordinates":[99.89711,16.58717],"type":"Point"}
}