{
  "type": "Feature",
  "properties": {
    "gn:admin1_code":"23.0",
    "gn:asciiname":"Ban Noi Si Suk",
    "gn:country_code":"TH",
    "gn:dem":172,
    "gn:feature_class":"P",
    "gn:feature_code":"PPL",
    "gn:name":"Ban Noi Si Suk",
    "gn:population":0,
    "gn:timezone":"Asia/Bangkok",
    "iso:country":"TH",
    "name:tha_x_preferred":[
        "\u0e1a\u0e49\u0e32\u0e19\u0e19\u0e49\u0e2d\u0e22\u0e28\u0e23\u0e35\u0e2a\u0e38\u0e02"
    ],
    "wof:name":"Ban Noi Si Suk",
    "wof:placetype":"locality"
},
  "geometry": {"coordinates":[103.38197,16.68581],"type":"Point"}
}