{
  "type": "Feature",
  "properties": {
    "gn:admin1_code":"60.0",
    "gn:asciiname":"Ban Hat Kruat",
    "gn:country_code":"TH",
    "gn:dem":21,
    "gn:feature_class":"P",
    "gn:feature_code":"PPL",
    "gn:name":"Ban Hat Kruat",
    "gn:population":0,
    "gn:timezone":"Asia/Bangkok",
    "iso:country":"TH",
    "name:tha_x_preferred":[
        "\u0e1a\u0e49\u0e32\u0e19\u0e2b\u0e32\u0e14\u0e01\u0e23\u0e27\u0e14"
    ],
    "wof:name":"Ban Hat Kruat",
    "wof:placetype":"locality"
},
  "geometry": {"coordinates":[98.95542,9.00947],"type":"Point"}
}