{
  "type": "Feature",
  "properties": {
    "gn:admin1_code":"6.0",
    "gn:asciiname":"Ban Mae Kueai",
    "gn:country_code":"TH",
    "gn:dem":228,
    "gn:feature_class":"P",
    "gn:feature_code":"PPL",
    "gn:name":"Ban Mae Kueai",
    "gn:population":0,
    "gn:timezone":"Asia/Bangkok",
    "iso:country":"TH",
    "name:tha_x_preferred":[
        "\u0e1a\u0e49\u0e32\u0e19\u0e41\u0e21\u0e48\u0e01\u0e37\u0e22"
    ],
    "wof:name":"Ban Mae Kueai",
    "wof:placetype":"locality"
},
  "geometry": {"coordinates":[99.42283,18.24369],"type":"Point"}
}