{
  "type": "Feature",
  "properties": {
    "gn:admin1_code":"60.0",
    "gn:asciiname":"Ban Nong Nio Nang",
    "gn:country_code":"TH",
    "gn:dem":22,
    "gn:feature_class":"P",
    "gn:feature_code":"PPL",
    "gn:name":"Ban Nong Nio Nang",
    "gn:population":0,
    "gn:timezone":"Asia/Bangkok",
    "iso:country":"TH",
    "name:tha_x_preferred":[
        "\u0e1a\u0e49\u0e32\u0e19\u0e2b\u0e19\u0e2d\u0e07\u0e19\u0e34\u0e49\u0e27\u0e19\u0e32\u0e07"
    ],
    "name:und_x_variant":[
        "Ban Nong Niu Nang"
    ],
    "wof:lang_x_official":[
        "tha"
    ],
    "wof:lang_x_spoken":[
        "tha"
    ],
    "wof:name":"Ban Nong Nio Nang",
    "wof:placetype":"locality"
},
  "geometry": {"coordinates":[99.32261,8.57064],"type":"Point"}
}