{
  "type": "Feature",
  "properties": {
    "gn:admin1_code":"79.0",
    "gn:asciiname":"Ban Kok Kho",
    "gn:country_code":"TH",
    "gn:dem":246,
    "gn:feature_class":"P",
    "gn:feature_code":"PPL",
    "gn:name":"Ban Kok Kho",
    "gn:population":0,
    "gn:timezone":"Asia/Bangkok",
    "iso:country":"TH",
    "name:tha_x_preferred":[
        "\u0e1a\u0e49\u0e32\u0e19\u0e01\u0e01\u0e04\u0e49\u0e2d"
    ],
    "name:und_x_variant":[
        "Ban Khok Kho",
        "Ban Kok Kho"
    ],
    "wof:name":"Ban Kok Kho",
    "wof:placetype":"locality"
},
  "geometry": {"coordinates":[102.20544,17.29903],"type":"Point"}
}