{
  "type": "Feature",
  "properties": {
    "gn:admin1_code":"80.0",
    "gn:asciiname":"Ban Wang Thap Khwai",
    "gn:country_code":"TH",
    "gn:dem":56,
    "gn:feature_class":"P",
    "gn:feature_code":"PPL",
    "gn:name":"Ban Wang Thap Khwai",
    "gn:population":0,
    "gn:timezone":"Asia/Bangkok",
    "iso:country":"TH",
    "name:und_x_variant":[
        "Samnak Wang Thap Khwai",
        "Ban Wang Thap Khwai"
    ],
    "wof:name":"Ban Wang Thap Khwai",
    "wof:placetype":"locality"
},
  "geometry": {"coordinates":[102.61667,13.75],"type":"Point"}
}