{
  "type": "Feature",
  "properties": {
    "gn:admin1_code":"15.0",
    "gn:asciiname":"Ban Phet Namphueng",
    "gn:country_code":"TH",
    "gn:dem":138,
    "gn:feature_class":"P",
    "gn:feature_code":"PPL",
    "gn:name":"Ban Phet Namphueng",
    "gn:population":0,
    "gn:timezone":"Asia/Bangkok",
    "iso:country":"TH",
    "name:tha_x_preferred":[
        "\u0e1a\u0e49\u0e32\u0e19\u0e40\u0e1e\u0e0a\u0e23\u0e19\u0e49\u0e33\u0e1c\u0e36\u0e49\u0e07"
    ],
    "wof:lang_x_official":[
        "tha"
    ],
    "wof:lang_x_spoken":[
        "tha"
    ],
    "wof:name":"Ban Phet Namphueng",
    "wof:placetype":"locality"
},
  "geometry": {"coordinates":[99.53803000000001,15.52169],"type":"Point"}
}