{
  "type": "Feature",
  "properties": {
    "gn:admin1_code":"3.0",
    "gn:asciiname":"Ban Pa Koi (1)",
    "gn:cc2":"TH",
    "gn:country_code":"TH",
    "gn:dem":374,
    "gn:feature_class":"P",
    "gn:feature_code":"PPL",
    "gn:name":"Ban Pa Koi (1)",
    "gn:population":0,
    "gn:timezone":"Asia/Bangkok",
    "iso:country":"TH",
    "name:und_x_variant":[
        "Ban Pa Koi"
    ],
    "wof:name":"Ban Pa Koi (1)",
    "wof:placetype":"locality"
},
  "geometry": {"coordinates":[99.95833,20.3275],"type":"Point"}
}