{
  "type": "Feature",
  "properties": {
    "gn:admin1_code":"22",
    "gn:asciiname":"Ban Phu Lek Noi",
    "gn:country_code":"TH",
    "gn:dem":213,
    "gn:feature_class":"P",
    "gn:feature_code":"PPL",
    "gn:name":"Ban Phu Lek Noi",
    "gn:population":0,
    "gn:timezone":"Asia/Bangkok",
    "iso:country":"TH",
    "name:tha_x_preferred":[
        "\u0e1a\u0e49\u0e32\u0e19\u0e20\u0e39\u0e40\u0e2b\u0e25\u0e47\u0e01\u0e19\u0e49\u0e2d\u0e22"
    ],
    "wof:name":"Ban Phu Lek Noi",
    "wof:placetype":"locality"
},
  "geometry": {"coordinates":[102.83283,16.09897],"type":"Point"}
}