{
  "type": "Feature",
  "properties": {
    "gn:admin1_code":"68.0",
    "gn:asciiname":"Ban Tin No",
    "gn:country_code":"TH",
    "gn:dem":5,
    "gn:feature_class":"P",
    "gn:feature_code":"PPL",
    "gn:name":"Ban Tin No",
    "gn:population":0,
    "gn:timezone":"Asia/Bangkok",
    "iso:country":"TH",
    "name:tha_x_preferred":[
        "\u0e1a\u0e49\u0e32\u0e19\u0e15\u0e35\u0e19\u0e19\u0e2d"
    ],
    "name:und_x_variant":[
        "Ban Chin No",
        "Ban Tin No"
    ],
    "wof:name":"Ban Tin No",
    "wof:placetype":"locality"
},
  "geometry": {"coordinates":[100.31719,7.90206],"type":"Point"}
}