{
  "type": "Feature",
  "properties": {
    "gn:admin1_code":"37.0",
    "gn:asciiname":"Ban Non Khlo",
    "gn:country_code":"TH",
    "gn:dem":19,
    "gn:feature_class":"P",
    "gn:feature_code":"PPL",
    "gn:name":"Ban Non Khlo",
    "gn:population":0,
    "gn:timezone":"Asia/Bangkok",
    "iso:country":"TH",
    "name:tha_x_preferred":[
        "\u0e1a\u0e49\u0e32\u0e19\u0e42\u0e19\u0e19\u0e04\u0e25\u0e49\u0e2d"
    ],
    "name:und_x_variant":[
        "Ban Non Kho"
    ],
    "wof:name":"Ban Non Khlo",
    "wof:placetype":"locality"
},
  "geometry": {"coordinates":[100.96128,14.52231],"type":"Point"}
}