{
  "type": "Feature",
  "properties": {
    "gn:admin1_code":"28.0",
    "gn:asciiname":"Ban Sai Tho Kao Klang",
    "gn:country_code":"TH",
    "gn:dem":196,
    "gn:feature_class":"P",
    "gn:feature_code":"PPL",
    "gn:name":"Ban Sai Tho Kao Klang",
    "gn:population":0,
    "gn:timezone":"Asia/Bangkok",
    "iso:country":"TH",
    "name:tha_x_preferred":[
        "\u0e1a\u0e49\u0e32\u0e19\u0e2a\u0e32\u0e22\u0e42\u0e17 \u0e40\u0e01\u0e49\u0e32 \u0e01\u0e25\u0e32\u0e07"
    ],
    "wof:name":"Ban Sai Tho Kao Klang",
    "wof:placetype":"locality"
},
  "geometry": {"coordinates":[103.19036,14.41056],"type":"Point"}
}