{
  "type": "Feature",
  "properties": {
    "gn:admin1_code":"65.0",
    "gn:asciiname":"Ban Kantang Tai",
    "gn:country_code":"TH",
    "gn:dem":15,
    "gn:feature_class":"P",
    "gn:feature_code":"PPL",
    "gn:name":"Ban Kantang Tai",
    "gn:population":0,
    "gn:timezone":"Asia/Bangkok",
    "iso:country":"TH",
    "name:tha_x_preferred":[
        "\u0e1a\u0e49\u0e32\u0e19\u0e01\u0e31\u0e19\u0e15\u0e31\u0e07\u0e43\u0e15\u0e49"
    ],
    "name:und_x_variant":[
        "Ban Kantang Tai (1)"
    ],
    "wof:name":"Ban Kantang Tai",
    "wof:placetype":"locality"
},
  "geometry": {"coordinates":[99.51558,7.38733],"type":"Point"}
}