{
  "type": "Feature",
  "properties": {
    "gn:admin1_code":"75.0",
    "gn:asciiname":"Ban That Noi",
    "gn:country_code":"TH",
    "gn:dem":127,
    "gn:feature_class":"P",
    "gn:feature_code":"PPL",
    "gn:name":"Ban That Noi",
    "gn:population":0,
    "gn:timezone":"Asia/Bangkok",
    "iso:country":"TH",
    "name:tha_x_preferred":[
        "\u0e1a\u0e49\u0e32\u0e19\u0e18\u0e32\u0e15\u0e38\u0e19\u0e49\u0e2d\u0e22"
    ],
    "name:und_x_variant":[
        "That Noi",
        "Ban Thatu Noi",
        "Ban That Noi"
    ],
    "wof:name":"Ban That Noi",
    "wof:placetype":"locality"
},
  "geometry": {"coordinates":[104.42339,15.31003],"type":"Point"}
}