{
  "type": "Feature",
  "properties": {
    "gn:admin1_code":"60.0",
    "gn:asciiname":"Ban Khlong Ya",
    "gn:country_code":"TH",
    "gn:dem":27,
    "gn:feature_class":"P",
    "gn:feature_code":"PPL",
    "gn:name":"Ban Khlong Ya",
    "gn:population":0,
    "gn:timezone":"Asia/Bangkok",
    "iso:country":"TH",
    "name:tha_x_preferred":[
        "\u0e1a\u0e49\u0e32\u0e19\u0e04\u0e25\u0e2d\u0e07\u0e22\u0e32"
    ],
    "name:und_x_variant":[
        "Ban Ya"
    ],
    "wof:name":"Ban Khlong Ya",
    "wof:placetype":"locality"
},
  "geometry": {"coordinates":[99.30564,8.92161],"type":"Point"}
}