{
  "type": "Feature",
  "properties": {
    "gn:admin1_code":"6.0",
    "gn:asciiname":"Ban Nikhom Sang Toneng Nueng",
    "gn:country_code":"TH",
    "gn:dem":283,
    "gn:feature_class":"P",
    "gn:feature_code":"PPL",
    "gn:name":"Ban Nikhom Sang Toneng Nueng",
    "gn:population":0,
    "gn:timezone":"Asia/Bangkok",
    "iso:country":"TH",
    "name:tha_x_preferred":[
        "\u0e1a\u0e49\u0e32\u0e19\u0e19\u0e34\u0e04\u0e21\u0e2a\u0e23\u0e49\u0e32\u0e07\u0e15\u0e19\u0e40\u0e2d\u0e07 \u0e2b\u0e19\u0e36\u0e48\u0e07"
    ],
    "wof:name":"Ban Nikhom Sang Toneng Nueng",
    "wof:placetype":"locality"
},
  "geometry": {"coordinates":[99.55439,18.42097],"type":"Point"}
}