{
  "type": "Feature",
  "properties": {
    "gn:admin1_code":"50.0",
    "gn:asciiname":"Ban Tao Lao (2)",
    "gn:cc2":"TH",
    "gn:country_code":"TH",
    "gn:dem":172,
    "gn:feature_class":"P",
    "gn:feature_code":"PPL",
    "gn:name":"Ban Tao Lao (2)",
    "gn:population":0,
    "gn:timezone":"Asia/Bangkok",
    "iso:country":"TH",
    "name:und_x_variant":[
        "Ban Tao Lau",
        "Ban Tao Lao (2)"
    ],
    "wof:name":"Ban Tao Lao (2)",
    "wof:placetype":"locality"
},
  "geometry": {"coordinates":[99.08333,14.63333],"type":"Point"}
}