{
  "type": "Feature",
  "properties": {
    "gn:admin1_code":"29",
    "gn:asciiname":"Ban Khae Don",
    "gn:country_code":"TH",
    "gn:dem":131,
    "gn:feature_class":"P",
    "gn:feature_code":"PPL",
    "gn:name":"Ban Khae Don",
    "gn:population":0,
    "gn:timezone":"Asia/Bangkok",
    "iso:country":"TH",
    "name:tha_x_preferred":[
        "\u0e1a\u0e49\u0e32\u0e19\u0e41\u0e02\u0e49\u0e14\u0e48\u0e2d\u0e19"
    ],
    "wof:name":"Ban Khae Don",
    "wof:placetype":"locality"
},
  "geometry": {"coordinates":[103.64552999999999,15.33108],"type":"Point"}
}