{
  "type": "Feature",
  "properties": {
    "gn:admin1_code":"9.0",
    "gn:asciiname":"Ban Sang",
    "gn:country_code":"TH",
    "gn:dem":102,
    "gn:feature_class":"P",
    "gn:feature_code":"PPL",
    "gn:name":"Ban Sang",
    "gn:population":0,
    "gn:timezone":"Asia/Bangkok",
    "iso:country":"TH",
    "wof:name":"Ban Sang",
    "wof:placetype":"locality"
},
  "geometry": {"coordinates":[99.53333000000001,17.28333],"type":"Point"}
}