{
  "type": "Feature",
  "properties": {
    "gn:admin1_code":"75.0",
    "gn:asciiname":"Ban Si Phrom",
    "gn:country_code":"TH",
    "gn:dem":198,
    "gn:feature_class":"P",
    "gn:feature_code":"PPL",
    "gn:name":"Ban Si Phrom",
    "gn:population":0,
    "gn:timezone":"Asia/Bangkok",
    "iso:country":"TH",
    "name:tha_x_preferred":[
        "\u0e1a\u0e49\u0e32\u0e19\u0e28\u0e23\u0e35\u0e1e\u0e23\u0e2b\u0e21"
    ],
    "wof:name":"Ban Si Phrom",
    "wof:placetype":"locality"
},
  "geometry": {"coordinates":[105.24959,14.52656],"type":"Point"}
}