{
  "type": "Feature",
  "properties": {
    "gn:admin1_code":"18.0",
    "gn:asciiname":"Ban Non",
    "gn:country_code":"TH",
    "gn:dem":269,
    "gn:feature_class":"P",
    "gn:feature_code":"PPL",
    "gn:name":"Ban Non",
    "gn:population":0,
    "gn:timezone":"Asia/Bangkok",
    "iso:country":"TH",
    "name:tha_x_preferred":[
        "\u0e1a\u0e49\u0e32\u0e19\u0e42\u0e19\u0e19"
    ],
    "name:und_x_variant":[
        "B\u0101n Gok Naung",
        "Ban Kok Nong",
        "Ban Non"
    ],
    "wof:name":"Ban Non",
    "wof:placetype":"locality"
},
  "geometry": {"coordinates":[101.68622000000001,17.24392000000001],"type":"Point"}
}