{
  "type": "Feature",
  "properties": {
    "gn:admin1_code":"9.0",
    "gn:asciiname":"Ban Tha Chai",
    "gn:country_code":"TH",
    "gn:dem":69,
    "gn:feature_class":"P",
    "gn:feature_code":"PPL",
    "gn:name":"Ban Tha Chai",
    "gn:population":0,
    "gn:timezone":"Asia/Bangkok",
    "iso:country":"TH",
    "name:tha_x_preferred":[
        "\u0e1a\u0e49\u0e32\u0e19\u0e17\u0e48\u0e32\u0e0a\u0e31\u0e22"
    ],
    "name:und_x_variant":[
        "Tha Chai",
        "Ban Tha Chai"
    ],
    "wof:name":"Ban Tha Chai",
    "wof:placetype":"locality"
},
  "geometry": {"coordinates":[99.80019,17.39111],"type":"Point"}
}