{
  "type": "Feature",
  "properties": {
    "gn:admin1_code":"78.0",
    "gn:asciiname":"Ban Tan Rung",
    "gn:country_code":"TH",
    "gn:dem":157,
    "gn:feature_class":"P",
    "gn:feature_code":"PPL",
    "gn:name":"Ban Tan Rung",
    "gn:population":0,
    "gn:timezone":"Asia/Bangkok",
    "iso:country":"TH",
    "name:tha_x_preferred":[
        "Ban Tan Rung"
    ],
    "name:tha_x_variant":[
        "\u0e1a\u0e49\u0e32\u0e19\u0e15\u0e32\u0e25\u0e23\u0e38\u0e48\u0e07"
    ],
    "wof:name":"Ban Tan Rung",
    "wof:placetype":"locality"
},
  "geometry": {"coordinates":[104.91200000000001,16.32331],"type":"Point"}
}