{
  "type": "Feature",
  "properties": {
    "gn:admin1_code":"69.0",
    "gn:asciiname":"Ban Pho Cho",
    "gn:country_code":"TH",
    "gn:dem":10,
    "gn:feature_class":"P",
    "gn:feature_code":"PPL",
    "gn:name":"Ban Pho Cho",
    "gn:population":0,
    "gn:timezone":"Asia/Bangkok",
    "iso:country":"TH",
    "name:tha_x_preferred":[
        "\u0e1a\u0e49\u0e32\u0e19\u0e1e\u0e2d\u0e40\u0e0a\u0e32\u0e30"
    ],
    "wof:name":"Ban Pho Cho",
    "wof:placetype":"locality"
},
  "geometry": {"coordinates":[101.42814,6.76645],"type":"Point"}
}