{
  "type": "Feature",
  "properties": {
    "gn:admin1_code":"51.0",
    "gn:asciiname":"Ban Khlong Madan",
    "gn:country_code":"TH",
    "gn:dem":22,
    "gn:feature_class":"P",
    "gn:feature_code":"PPL",
    "gn:name":"Ban Khlong Madan",
    "gn:population":0,
    "gn:timezone":"Asia/Bangkok",
    "iso:country":"TH",
    "name:tha_x_preferred":[
        "\u0e1a\u0e49\u0e32\u0e19\u0e04\u0e25\u0e2d\u0e07\u0e21\u0e30\u0e14\u0e31\u0e19"
    ],
    "wof:name":"Ban Khlong Madan",
    "wof:placetype":"locality"
},
  "geometry": {"coordinates":[99.90231,14.56675],"type":"Point"}
}