{
  "type": "Feature",
  "properties": {
    "gn:admin1_code":"75.0",
    "gn:asciiname":"Ban Kaset Phatthana",
    "gn:country_code":"TH",
    "gn:dem":138,
    "gn:feature_class":"P",
    "gn:feature_code":"PPL",
    "gn:name":"Ban Kaset Phatthana",
    "gn:population":0,
    "gn:timezone":"Asia/Bangkok",
    "iso:country":"TH",
    "name:tha_x_preferred":[
        "\u0e1a\u0e49\u0e32\u0e19\u0e40\u0e01\u0e29\u0e15\u0e23\u0e1e\u0e31\u0e12\u0e19\u0e32"
    ],
    "wof:name":"Ban Kaset Phatthana",
    "wof:placetype":"locality"
},
  "geometry": {"coordinates":[104.89761,15.15978],"type":"Point"}
}