{
  "type": "Feature",
  "properties": {
    "gn:admin1_code":"27.0",
    "gn:asciiname":"Ban Talat Khae Tawan Ok",
    "gn:country_code":"TH",
    "gn:dem":160,
    "gn:feature_class":"P",
    "gn:feature_code":"PPL",
    "gn:name":"Ban Talat Khae Tawan Ok",
    "gn:population":0,
    "gn:timezone":"Asia/Bangkok",
    "iso:country":"TH",
    "name:tha_x_preferred":[
        "\u0e1a\u0e49\u0e32\u0e19\u0e15\u0e25\u0e32\u0e14\u0e41\u0e04\u0e15\u0e30\u0e27\u0e31\u0e19\u0e2d\u0e2d\u0e01"
    ],
    "name:und_x_variant":[
        "Ban Talat Khae Tai"
    ],
    "wof:name":"Ban Talat Khae Tawan Ok",
    "wof:placetype":"locality"
},
  "geometry": {"coordinates":[102.41916999999999,15.262],"type":"Point"}
}