{
  "type": "Feature",
  "properties": {
    "gn:admin1_code":"8.0",
    "gn:asciiname":"Ban San Kao Kom",
    "gn:country_code":"TH",
    "gn:dem":202,
    "gn:feature_class":"P",
    "gn:feature_code":"PPL",
    "gn:name":"Ban San Kao Kom",
    "gn:population":0,
    "gn:timezone":"Asia/Bangkok",
    "iso:country":"TH",
    "name:tha_x_preferred":[
        "\u0e1a\u0e49\u0e32\u0e19\u0e2a\u0e31\u0e19\u0e40\u0e01\u0e49\u0e32\u0e01\u0e2d\u0e21"
    ],
    "wof:name":"Ban San Kao Kom",
    "wof:placetype":"locality"
},
  "geometry": {"coordinates":[98.51244,16.98989],"type":"Point"}
}