{
  "type": "Feature",
  "properties": {
    "gn:admin1_code":"12.0",
    "gn:asciiname":"Ban Huai Tha Wua Tai",
    "gn:country_code":"TH",
    "gn:dem":69,
    "gn:feature_class":"P",
    "gn:feature_code":"PPL",
    "gn:name":"Ban Huai Tha Wua Tai",
    "gn:population":0,
    "gn:timezone":"Asia/Bangkok",
    "iso:country":"TH",
    "name:tha_x_preferred":[
        "\u0e1a\u0e49\u0e32\u0e19\u0e2b\u0e49\u0e27\u0e22\u0e17\u0e48\u0e32\u0e27\u0e31\u0e27\u0e43\u0e15\u0e49"
    ],
    "wof:name":"Ban Huai Tha Wua Tai",
    "wof:placetype":"locality"
},
  "geometry": {"coordinates":[100.68228000000001,16.56061],"type":"Point"}
}