{
  "type": "Feature",
  "properties": {
    "gn:admin1_code":"2.0",
    "gn:asciiname":"Ban Mae Sao",
    "gn:country_code":"TH",
    "gn:dem":462,
    "gn:feature_class":"P",
    "gn:feature_code":"PPL",
    "gn:name":"Ban Mae Sao",
    "gn:population":0,
    "gn:timezone":"Asia/Bangkok",
    "iso:country":"TH",
    "name:tha_x_preferred":[
        "\u0e1a\u0e49\u0e32\u0e19\u0e41\u0e21\u0e48\u0e2a\u0e32\u0e27"
    ],
    "name:und_x_variant":[
        "B\u0101n Mea S\u0101u",
        "Ban Mae Sao"
    ],
    "wof:lang_x_official":[
        "tha"
    ],
    "wof:lang_x_spoken":[
        "tha"
    ],
    "wof:name":"Ban Mae Sao",
    "wof:placetype":"locality"
},
  "geometry": {"coordinates":[99.27056,20.01172],"type":"Point"}
}