{
  "type": "Feature",
  "properties": {
    "gn:admin1_code":"15.0",
    "gn:asciiname":"Ban Nong Ma Kham Tia",
    "gn:country_code":"TH",
    "gn:dem":41,
    "gn:feature_class":"P",
    "gn:feature_code":"PPL",
    "gn:name":"Ban Nong Ma Kham Tia",
    "gn:population":0,
    "gn:timezone":"Asia/Bangkok",
    "iso:country":"TH",
    "name:tha_x_preferred":[
        "\u0e1a\u0e49\u0e32\u0e19\u0e2b\u0e19\u0e2d\u0e07\u0e21\u0e30\u0e02\u0e32\u0e21\u0e40\u0e15\u0e35\u0e49\u0e22"
    ],
    "wof:name":"Ban Nong Ma Kham Tia",
    "wof:placetype":"locality"
},
  "geometry": {"coordinates":[99.88419,15.31991],"type":"Point"}
}