{
  "type": "Feature",
  "properties": {
    "gn:admin1_code":"29",
    "gn:asciiname":"Ban Takhro",
    "gn:country_code":"TH",
    "gn:dem":156,
    "gn:feature_class":"P",
    "gn:feature_code":"PPL",
    "gn:name":"Ban Takhro",
    "gn:population":0,
    "gn:timezone":"Asia/Bangkok",
    "iso:country":"TH",
    "name:tha_x_preferred":[
        "\u0e1a\u0e49\u0e32\u0e19\u0e15\u0e30\u0e04\u0e23\u0e49\u0e2d"
    ],
    "wof:name":"Ban Takhro",
    "wof:placetype":"locality"
},
  "geometry": {"coordinates":[103.68906,14.92097],"type":"Point"}
}