{
  "type": "Feature",
  "properties": {
    "gn:admin1_code":"67.0",
    "gn:asciiname":"Ban Ke Tri",
    "gn:country_code":"TH",
    "gn:dem":16,
    "gn:feature_class":"P",
    "gn:feature_code":"PPL",
    "gn:name":"Ban Ke Tri",
    "gn:population":0,
    "gn:timezone":"Asia/Bangkok",
    "iso:country":"TH",
    "name:tha_x_preferred":[
        "\u0e1a\u0e49\u0e32\u0e19\u0e40\u0e01\u0e15\u0e23\u0e35"
    ],
    "wof:name":"Ban Ke Tri",
    "wof:placetype":"locality"
},
  "geometry": {"coordinates":[100.07989000000001,6.70878],"type":"Point"}
}