{
  "type": "Feature",
  "properties": {
    "gn:admin1_code":"1.0",
    "gn:asciiname":"Ban Khun Mae Tia",
    "gn:country_code":"TH",
    "gn:dem":816,
    "gn:feature_class":"P",
    "gn:feature_code":"PPL",
    "gn:name":"Ban Khun Mae Tia",
    "gn:population":0,
    "gn:timezone":"Asia/Bangkok",
    "iso:country":"TH",
    "name:tha_x_preferred":[
        "\u0e1a\u0e49\u0e32\u0e19\u0e02\u0e38\u0e19\u0e41\u0e21\u0e48\u0e40\u0e15\u0e35\u0e4b\u0e22"
    ],
    "wof:name":"Ban Khun Mae Tia",
    "wof:placetype":"locality"
},
  "geometry": {"coordinates":[98.00825,18.32564],"type":"Point"}
}