{
  "type": "Feature",
  "properties": {
    "gn:admin1_code":"0.0",
    "gn:asciiname":"Ban Klang",
    "gn:country_code":"TH",
    "gn:dem":-9999,
    "gn:feature_class":"P",
    "gn:feature_code":"PPL",
    "gn:name":"Ban Klang",
    "gn:population":0,
    "gn:timezone":"Asia/Bangkok",
    "iso:country":"TH",
    "wof:name":"Ban Klang",
    "wof:placetype":"locality"
},
  "geometry": {"coordinates":[98.90000000000001,7.76667],"type":"Point"}
}