{
  "type": "Feature",
  "properties": {
    "gn:admin1_code":"37",
    "gn:asciiname":"Ban Makha Ngam",
    "gn:country_code":"TH",
    "gn:dem":103,
    "gn:feature_class":"P",
    "gn:feature_code":"PPL",
    "gn:name":"Ban Makha Ngam",
    "gn:population":0,
    "gn:timezone":"Asia/Bangkok",
    "iso:country":"TH",
    "name:tha_x_preferred":[
        "\u0e1a\u0e49\u0e32\u0e19\u0e21\u0e30\u0e04\u0e48\u0e32\u0e07\u0e32\u0e21"
    ],
    "wof:name":"Ban Makha Ngam",
    "wof:placetype":"locality"
},
  "geometry": {"coordinates":[101.14175,14.81258],"type":"Point"}
}