{
  "type": "Feature",
  "properties": {
    "gn:admin1_code":"2.0",
    "gn:asciiname":"Ban Tha Mai Lung Tai",
    "gn:country_code":"TH",
    "gn:dem":340,
    "gn:feature_class":"P",
    "gn:feature_code":"PPL",
    "gn:name":"Ban Tha Mai Lung Tai",
    "gn:population":0,
    "gn:timezone":"Asia/Bangkok",
    "iso:country":"TH",
    "name:tha_x_preferred":[
        "\u0e1a\u0e49\u0e32\u0e19\u0e17\u0e48\u0e32\u0e44\u0e21\u0e49\u0e25\u0e38\u0e07\u0e43\u0e15\u0e49"
    ],
    "wof:name":"Ban Tha Mai Lung Tai",
    "wof:placetype":"locality"
},
  "geometry": {"coordinates":[98.87578000000001,18.68158],"type":"Point"}
}