{
  "type": "Feature",
  "properties": {
    "gn:admin1_code":"6.0",
    "gn:asciiname":"Ban Sadet",
    "gn:country_code":"TH",
    "gn:dem":253,
    "gn:feature_class":"P",
    "gn:feature_code":"PPL",
    "gn:name":"Ban Sadet",
    "gn:population":0,
    "gn:timezone":"Asia/Bangkok",
    "iso:country":"TH",
    "name:tha_x_preferred":[
        "\u0e1a\u0e49\u0e32\u0e19\u0e40\u0e2a\u0e14\u0e47\u0e08"
    ],
    "name:und_x_variant":[
        "Sad\u0113ch",
        "B\u0101n Set",
        "Sadet",
        "Ban Sadet"
    ],
    "wof:name":"Ban Sadet",
    "wof:placetype":"locality"
},
  "geometry": {"coordinates":[99.59264,18.39058],"type":"Point"}
}