{
  "type": "Feature",
  "properties": {
    "gn:admin1_code":"47.0",
    "gn:asciiname":"Ban Khao Saophao Thong",
    "gn:country_code":"TH",
    "gn:dem":17,
    "gn:feature_class":"P",
    "gn:feature_code":"PPL",
    "gn:name":"Ban Khao Saophao Thong",
    "gn:population":0,
    "gn:timezone":"Asia/Bangkok",
    "iso:country":"TH",
    "name:tha_x_preferred":[
        "\u0e1a\u0e49\u0e32\u0e19\u0e40\u0e02\u0e32\u0e2a\u0e33\u0e40\u0e20\u0e32\u0e17\u0e2d\u0e07"
    ],
    "wof:name":"Ban Khao Saophao Thong",
    "wof:placetype":"locality"
},
  "geometry": {"coordinates":[101.40833000000001,12.64056],"type":"Point"}
}