{
  "type": "Feature",
  "properties": {
    "gn:admin1_code":"54.0",
    "gn:asciiname":"Ban Khlong Ban Nok",
    "gn:country_code":"TH",
    "gn:dem":4,
    "gn:feature_class":"P",
    "gn:feature_code":"PPL",
    "gn:name":"Ban Khlong Ban Nok",
    "gn:population":0,
    "gn:timezone":"Asia/Bangkok",
    "iso:country":"TH",
    "name:tha_x_preferred":[
        "\u0e1a\u0e49\u0e32\u0e19\u0e04\u0e25\u0e2d\u0e07\u0e1a\u0e49\u0e32\u0e19\u0e19\u0e2d\u0e01"
    ],
    "wof:name":"Ban Khlong Ban Nok",
    "wof:placetype":"locality"
},
  "geometry": {"coordinates":[99.91726,13.28539],"type":"Point"}
}