{
  "type": "Feature",
  "properties": {
    "gn:admin1_code":"4.0",
    "gn:asciiname":"Ban Pu Na",
    "gn:country_code":"TH",
    "gn:dem":1208,
    "gn:feature_class":"P",
    "gn:feature_code":"PPL",
    "gn:name":"Ban Pu Na",
    "gn:population":0,
    "gn:timezone":"Asia/Bangkok",
    "iso:country":"TH",
    "name:tha_x_preferred":[
        "\u0e1a\u0e49\u0e32\u0e19\u0e1b\u0e39\u0e19\u0e32"
    ],
    "wof:name":"Ban Pu Na",
    "wof:placetype":"locality"
},
  "geometry": {"coordinates":[101.12757999999999,19.42108],"type":"Point"}
}