{
  "type": "Feature",
  "properties": {
    "gn:admin1_code":"81.0",
    "gn:asciiname":"Ban Dong Siat",
    "gn:country_code":"TH",
    "gn:dem":163,
    "gn:feature_class":"P",
    "gn:feature_code":"PPL",
    "gn:name":"Ban Dong Siat",
    "gn:population":0,
    "gn:timezone":"Asia/Bangkok",
    "iso:country":"TH",
    "name:tha_x_preferred":[
        "\u0e1a\u0e49\u0e32\u0e19\u0e14\u0e07\u0e40\u0e2a\u0e35\u0e22\u0e14"
    ],
    "wof:name":"Ban Dong Siat",
    "wof:placetype":"locality"
},
  "geometry": {"coordinates":[103.66727,18.02667000000001],"type":"Point"}
}