{
  "type": "Feature",
  "properties": {
    "gn:admin1_code":"34",
    "gn:asciiname":"Ban Nong Phai",
    "gn:country_code":"TH",
    "gn:dem":39,
    "gn:feature_class":"P",
    "gn:feature_code":"PPL",
    "gn:name":"Ban Nong Phai",
    "gn:population":0,
    "gn:timezone":"Asia/Bangkok",
    "iso:country":"TH",
    "name:tha_x_preferred":[
        "\u0e1a\u0e49\u0e32\u0e19\u0e2b\u0e19\u0e2d\u0e07\u0e44\u0e1c\u0e48"
    ],
    "wof:name":"Ban Nong Phai",
    "wof:placetype":"locality"
},
  "geometry": {"coordinates":[100.70480999999999,15.119],"type":"Point"}
}