{
  "type": "Feature",
  "properties": {
    "gn:admin1_code":"66.0",
    "gn:asciiname":"Ban Sai Khlop",
    "gn:country_code":"TH",
    "gn:dem":14,
    "gn:feature_class":"P",
    "gn:feature_code":"PPL",
    "gn:name":"Ban Sai Khlop",
    "gn:population":0,
    "gn:timezone":"Asia/Bangkok",
    "iso:country":"TH",
    "name:tha_x_preferred":[
        "\u0e1a\u0e49\u0e32\u0e19\u0e44\u0e2a\u0e02\u0e25\u0e1a"
    ],
    "name:und_x_variant":[
        "Ban Zai Krob",
        "Ban Sai Khrop",
        "Ban Sai Khalop",
        "Ban Sai Khlop"
    ],
    "wof:lang_x_official":[
        "tha"
    ],
    "wof:lang_x_spoken":[
        "tha"
    ],
    "wof:name":"Ban Sai Khlop",
    "wof:placetype":"locality"
},
  "geometry": {"coordinates":[100.02207,7.74905],"type":"Point"}
}