{
  "type": "Feature",
  "properties": {
    "gn:admin1_code":"18.0",
    "gn:asciiname":"Ban Huai Pao Yai",
    "gn:country_code":"TH",
    "gn:dem":274,
    "gn:feature_class":"P",
    "gn:feature_code":"PPL",
    "gn:name":"Ban Huai Pao Yai",
    "gn:population":0,
    "gn:timezone":"Asia/Bangkok",
    "iso:country":"TH",
    "name:tha_x_preferred":[
        "\u0e1a\u0e49\u0e32\u0e19\u0e2b\u0e49\u0e27\u0e22\u0e40\u0e1b\u0e49\u0e32\u0e43\u0e2b\u0e0d\u0e48"
    ],
    "wof:name":"Ban Huai Pao Yai",
    "wof:placetype":"locality"
},
  "geometry": {"coordinates":[101.90925,17.9107],"type":"Point"}
}