{
  "type": "Feature",
  "properties": {
    "gn:admin1_code":"50.0",
    "gn:asciiname":"Ban Wang Yai",
    "gn:country_code":"TH",
    "gn:dem":85,
    "gn:feature_class":"P",
    "gn:feature_code":"PPL",
    "gn:name":"Ban Wang Yai",
    "gn:population":0,
    "gn:timezone":"Asia/Bangkok",
    "iso:country":"TH",
    "name:tha_x_preferred":[
        "\u0e1a\u0e49\u0e32\u0e19\u0e27\u0e31\u0e07\u0e43\u0e2b\u0e0d\u0e48"
    ],
    "name:und_x_variant":[
        "Rang",
        "Ban Wan Krai",
        "Ban Wang Yai"
    ],
    "wof:name":"Ban Wang Yai",
    "wof:placetype":"locality"
},
  "geometry": {"coordinates":[99.48967,14.34103],"type":"Point"}
}