{
  "type": "Feature",
  "properties": {
    "gn:admin1_code":"23.0",
    "gn:asciiname":"Ban Na Chan",
    "gn:country_code":"TH",
    "gn:dem":181,
    "gn:feature_class":"P",
    "gn:feature_code":"PPL",
    "gn:name":"Ban Na Chan",
    "gn:population":0,
    "gn:timezone":"Asia/Bangkok",
    "iso:country":"TH",
    "name:tha_x_preferred":[
        "\u0e1a\u0e49\u0e32\u0e19\u0e19\u0e32\u0e08\u0e32\u0e23\u0e22\u0e4c"
    ],
    "wof:name":"Ban Na Chan",
    "wof:placetype":"locality"
},
  "geometry": {"coordinates":[103.61217000000001,16.53025],"type":"Point"}
}