{
  "type": "Feature",
  "properties": {
    "gn:admin1_code":"24",
    "gn:asciiname":"Ban Ruam Chai Song",
    "gn:country_code":"TH",
    "gn:dem":179,
    "gn:feature_class":"P",
    "gn:feature_code":"PPL",
    "gn:name":"Ban Ruam Chai Song",
    "gn:population":0,
    "gn:timezone":"Asia/Bangkok",
    "iso:country":"TH",
    "name:tha_x_preferred":[
        "\u0e1a\u0e49\u0e32\u0e19\u0e23\u0e48\u0e27\u0e21\u0e43\u0e08 \u0e2a\u0e2d\u0e07"
    ],
    "wof:name":"Ban Ruam Chai Song",
    "wof:placetype":"locality"
},
  "geometry": {"coordinates":[103.22799999999999,15.8035],"type":"Point"}
}