{
  "type": "Feature",
  "properties": {
    "gn:admin1_code":"1.0",
    "gn:asciiname":"Ban Mae Kwang Tai",
    "gn:country_code":"TH",
    "gn:dem":747,
    "gn:feature_class":"P",
    "gn:feature_code":"PPL",
    "gn:name":"Ban Mae Kwang Tai",
    "gn:population":0,
    "gn:timezone":"Asia/Bangkok",
    "iso:country":"TH",
    "name:tha_x_preferred":[
        "\u0e1a\u0e49\u0e32\u0e19\u0e41\u0e21\u0e48\u0e01\u0e27\u0e32\u0e07\u0e43\u0e15\u0e49"
    ],
    "name:und_x_variant":[
        "Ban Mae Kwang",
        "Ban Mae Kwang Tai"
    ],
    "wof:name":"Ban Mae Kwang Tai",
    "wof:placetype":"locality"
},
  "geometry": {"coordinates":[98.00039,18.30075],"type":"Point"}
}