{
  "type": "Feature",
  "properties": {
    "gn:admin1_code":"25.0",
    "gn:asciiname":"Ban Sa Phang Thong",
    "gn:country_code":"TH",
    "gn:dem":142,
    "gn:feature_class":"P",
    "gn:feature_code":"PPL",
    "gn:name":"Ban Sa Phang Thong",
    "gn:population":0,
    "gn:timezone":"Asia/Bangkok",
    "iso:country":"TH",
    "name:tha_x_preferred":[
        "\u0e1a\u0e49\u0e32\u0e19\u0e2a\u0e23\u0e30\u0e1e\u0e31\u0e07\u0e17\u0e2d\u0e07"
    ],
    "wof:name":"Ban Sa Phang Thong",
    "wof:placetype":"locality"
},
  "geometry": {"coordinates":[103.50686,15.70528],"type":"Point"}
}