{
  "type": "Feature",
  "properties": {
    "gn:admin1_code":"75.0",
    "gn:asciiname":"Ban Sang Sabaeng",
    "gn:country_code":"TH",
    "gn:dem":155,
    "gn:feature_class":"P",
    "gn:feature_code":"PPL",
    "gn:name":"Ban Sang Sabaeng",
    "gn:population":0,
    "gn:timezone":"Asia/Bangkok",
    "iso:country":"TH",
    "name:tha_x_preferred":[
        "\u0e1a\u0e49\u0e32\u0e19\u0e2a\u0e23\u0e49\u0e32\u0e07\u0e2a\u0e30\u0e41\u0e1a\u0e07"
    ],
    "wof:name":"Ban Sang Sabaeng",
    "wof:placetype":"locality"
},
  "geometry": {"coordinates":[105.24097,15.85308],"type":"Point"}
}