{
  "type": "Feature",
  "properties": {
    "gn:admin1_code":"2.0",
    "gn:asciiname":"Ban Pang Hai",
    "gn:country_code":"TH",
    "gn:dem":923,
    "gn:feature_class":"P",
    "gn:feature_code":"PPL",
    "gn:name":"Ban Pang Hai",
    "gn:population":0,
    "gn:timezone":"Asia/Bangkok",
    "iso:country":"TH",
    "name:tha_x_preferred":[
        "\u0e1a\u0e49\u0e32\u0e19\u0e1b\u0e32\u0e07\u0e44\u0e2e"
    ],
    "wof:name":"Ban Pang Hai",
    "wof:placetype":"locality"
},
  "geometry": {"coordinates":[99.33428000000001,18.92353],"type":"Point"}
}