{
  "type": "Feature",
  "properties": {
    "gn:admin1_code":"51.0",
    "gn:asciiname":"Ban Khlong La-om",
    "gn:country_code":"TH",
    "gn:dem":15,
    "gn:feature_class":"P",
    "gn:feature_code":"PPL",
    "gn:name":"Ban Khlong La-om",
    "gn:population":0,
    "gn:timezone":"Asia/Bangkok",
    "iso:country":"TH",
    "name:tha_x_preferred":[
        "\u0e1a\u0e49\u0e32\u0e19\u0e04\u0e25\u0e2d\u0e07\u0e25\u0e30\u0e2d\u0e2d\u0e21"
    ],
    "wof:name":"Ban Khlong La-om",
    "wof:placetype":"locality"
},
  "geometry": {"coordinates":[100.12227,14.86122],"type":"Point"}
}