{
  "type": "Feature",
  "properties": {
    "gn:admin1_code":"2.0",
    "gn:asciiname":"Ban Buak Pha",
    "gn:country_code":"TH",
    "gn:dem":363,
    "gn:feature_class":"P",
    "gn:feature_code":"PPL",
    "gn:name":"Ban Buak Pha",
    "gn:population":0,
    "gn:timezone":"Asia/Bangkok",
    "iso:country":"TH",
    "name:tha_x_preferred":[
        "\u0e1a\u0e49\u0e32\u0e19\u0e1a\u0e27\u0e01\u0e1c\u0e32"
    ],
    "wof:name":"Ban Buak Pha",
    "wof:placetype":"locality"
},
  "geometry": {"coordinates":[99.187,18.84828],"type":"Point"}
}