{
  "type": "Feature",
  "properties": {
    "gn:admin1_code":"50.0",
    "gn:asciiname":"Ban Tha Yae",
    "gn:country_code":"TH",
    "gn:dem":56,
    "gn:feature_class":"P",
    "gn:feature_code":"PPL",
    "gn:name":"Ban Tha Yae",
    "gn:population":0,
    "gn:timezone":"Asia/Bangkok",
    "iso:country":"TH",
    "name:tha_x_preferred":[
        "\u0e1a\u0e49\u0e32\u0e19\u0e17\u0e48\u0e32\u0e41\u0e22\u0e49"
    ],
    "wof:name":"Ban Tha Yae",
    "wof:placetype":"locality"
},
  "geometry": {"coordinates":[99.408,13.79778],"type":"Point"}
}