{
  "type": "Feature",
  "properties": {
    "gn:admin1_code":"66.0",
    "gn:asciiname":"Ban Khuan Dinso",
    "gn:country_code":"TH",
    "gn:dem":46,
    "gn:feature_class":"P",
    "gn:feature_code":"PPL",
    "gn:name":"Ban Khuan Dinso",
    "gn:population":0,
    "gn:timezone":"Asia/Bangkok",
    "iso:country":"TH",
    "name:tha_x_preferred":[
        "\u0e1a\u0e49\u0e32\u0e19\u0e04\u0e27\u0e19\u0e14\u0e34\u0e19\u0e2a\u0e2d"
    ],
    "wof:name":"Ban Khuan Dinso",
    "wof:placetype":"locality"
},
  "geometry": {"coordinates":[99.93825,7.58292],"type":"Point"}
}