{
  "type": "Feature",
  "properties": {
    "gn:admin1_code":"9.0",
    "gn:asciiname":"Ban Hang Khlong",
    "gn:country_code":"TH",
    "gn:dem":53,
    "gn:feature_class":"P",
    "gn:feature_code":"PPL",
    "gn:name":"Ban Hang Khlong",
    "gn:population":0,
    "gn:timezone":"Asia/Bangkok",
    "iso:country":"TH",
    "name:tha_x_preferred":[
        "\u0e1a\u0e49\u0e32\u0e19\u0e2b\u0e32\u0e07\u0e04\u0e25\u0e2d\u0e07"
    ],
    "wof:name":"Ban Hang Khlong",
    "wof:placetype":"locality"
},
  "geometry": {"coordinates":[99.79111,17.02147],"type":"Point"}
}