{
  "type": "Feature",
  "properties": {
    "gn:admin1_code":"26.0",
    "gn:asciiname":"Ban Khlong Chanla",
    "gn:country_code":"TH",
    "gn:dem":270,
    "gn:feature_class":"P",
    "gn:feature_code":"PPL",
    "gn:name":"Ban Khlong Chanla",
    "gn:population":0,
    "gn:timezone":"Asia/Bangkok",
    "iso:country":"TH",
    "name:tha_x_preferred":[
        "\u0e1a\u0e49\u0e32\u0e19\u0e04\u0e25\u0e2d\u0e07\u0e08\u0e31\u0e19\u0e25\u0e32"
    ],
    "wof:name":"Ban Khlong Chanla",
    "wof:placetype":"locality"
},
  "geometry": {"coordinates":[101.48905999999999,16.05933],"type":"Point"}
}