{
  "type": "Feature",
  "properties": {
    "gn:admin1_code":"47.0",
    "gn:asciiname":"Ban Nikhom Sang Ton-eng Sai Ek",
    "gn:country_code":"TH",
    "gn:dem":69,
    "gn:feature_class":"P",
    "gn:feature_code":"PPL",
    "gn:name":"Ban Nikhom Sang Ton-eng Sai Ek",
    "gn:population":0,
    "gn:timezone":"Asia/Bangkok",
    "iso:country":"TH",
    "name:tha_x_preferred":[
        "\u0e1a\u0e49\u0e32\u0e19\u0e19\u0e34\u0e04\u0e21\u0e2a\u0e23\u0e49\u0e32\u0e07\u0e15\u0e19\u0e40\u0e2d\u0e07\u0e2a\u0e32\u0e22\u0e40\u0e2d\u0e01"
    ],
    "wof:name":"Ban Nikhom Sang Ton-eng Sai Ek",
    "wof:placetype":"locality"
},
  "geometry": {"coordinates":[101.2525,12.92222],"type":"Point"}
}