{
  "type": "Feature",
  "properties": {
    "gn:admin1_code":"29.0",
    "gn:asciiname":"Ban Khok Krachai",
    "gn:country_code":"TH",
    "gn:dem":158,
    "gn:feature_class":"P",
    "gn:feature_code":"PPL",
    "gn:name":"Ban Khok Krachai",
    "gn:population":0,
    "gn:timezone":"Asia/Bangkok",
    "iso:country":"TH",
    "name:tha_x_preferred":[
        "\u0e1a\u0e49\u0e32\u0e19\u0e42\u0e04\u0e01\u0e01\u0e23\u0e30\u0e0a\u0e32\u0e22"
    ],
    "name:und_x_variant":[
        "Ban Khok Kachai"
    ],
    "wof:name":"Ban Khok Krachai",
    "wof:placetype":"locality"
},
  "geometry": {"coordinates":[103.56417,14.82892],"type":"Point"}
}