{
  "type": "Feature",
  "properties": {
    "gn:admin1_code":"1.0",
    "gn:asciiname":"Ban Huai Thi Sa",
    "gn:country_code":"TH",
    "gn:dem":833,
    "gn:feature_class":"P",
    "gn:feature_code":"PPL",
    "gn:name":"Ban Huai Thi Sa",
    "gn:population":0,
    "gn:timezone":"Asia/Bangkok",
    "iso:country":"TH",
    "name:tha_x_preferred":[
        "\u0e1a\u0e49\u0e32\u0e19\u0e2b\u0e49\u0e27\u0e22\u0e17\u0e35\u0e0b\u0e30"
    ],
    "wof:name":"Ban Huai Thi Sa",
    "wof:placetype":"locality"
},
  "geometry": {"coordinates":[97.89915000000001,17.89022000000001],"type":"Point"}
}