{
  "type": "Feature",
  "properties": {
    "gn:admin1_code":"51.0",
    "gn:asciiname":"Ban Wang Wa",
    "gn:country_code":"TH",
    "gn:dem":14,
    "gn:feature_class":"P",
    "gn:feature_code":"PPL",
    "gn:name":"Ban Wang Wa",
    "gn:population":0,
    "gn:timezone":"Asia/Bangkok",
    "iso:country":"TH",
    "name:tha_x_preferred":[
        "\u0e1a\u0e49\u0e32\u0e19\u0e27\u0e31\u0e07\u0e2b\u0e27\u0e49\u0e32"
    ],
    "name:und_x_variant":[
        "Ban Wang Nam Sap",
        "Ban Wang Zab",
        "Ban Wang Wa"
    ],
    "wof:name":"Ban Wang Wa",
    "wof:placetype":"locality"
},
  "geometry": {"coordinates":[100.10711000000001,14.68881],"type":"Point"}
}