{
  "type": "Feature",
  "properties": {
    "gn:admin1_code":"2.0",
    "gn:asciiname":"Ban Pa Sak Noi",
    "gn:country_code":"TH",
    "gn:dem":311,
    "gn:feature_class":"P",
    "gn:feature_code":"PPL",
    "gn:name":"Ban Pa Sak Noi",
    "gn:population":0,
    "gn:timezone":"Asia/Bangkok",
    "iso:country":"TH",
    "name:tha_x_preferred":[
        "\u0e1a\u0e49\u0e32\u0e19\u0e1b\u0e48\u0e32\u0e2a\u0e31\u0e01\u0e19\u0e49\u0e2d\u0e22"
    ],
    "wof:name":"Ban Pa Sak Noi",
    "wof:placetype":"locality"
},
  "geometry": {"coordinates":[99.12242000000001,18.77828],"type":"Point"}
}