{
  "type": "Feature",
  "properties": {
    "gn:admin1_code":"27",
    "gn:asciiname":"Ban Nong Ka To Wa",
    "gn:country_code":"TH",
    "gn:dem":451,
    "gn:feature_class":"P",
    "gn:feature_code":"PPL",
    "gn:name":"Ban Nong Ka To Wa",
    "gn:population":0,
    "gn:timezone":"Asia/Bangkok",
    "iso:country":"TH",
    "name:tha_x_preferred":[
        "\u0e1a\u0e49\u0e32\u0e19\u0e2b\u0e19\u0e2d\u0e07\u0e01\u0e30\u0e42\u0e15\u0e27\u0e32"
    ],
    "wof:name":"Ban Nong Ka To Wa",
    "wof:placetype":"locality"
},
  "geometry": {"coordinates":[101.36647000000001,14.72456],"type":"Point"}
}