{
  "type": "Feature",
  "properties": {
    "gn:admin1_code":"12.0",
    "gn:asciiname":"Ban Phan Tang",
    "gn:country_code":"TH",
    "gn:dem":48,
    "gn:feature_class":"P",
    "gn:feature_code":"PPL",
    "gn:name":"Ban Phan Tang",
    "gn:population":0,
    "gn:timezone":"Asia/Bangkok",
    "iso:country":"TH",
    "name:tha_x_preferred":[
        "\u0e1a\u0e49\u0e32\u0e19\u0e1e\u0e31\u0e19\u0e18\u0e38\u0e4c\u0e15\u0e48\u0e32\u0e07"
    ],
    "wof:name":"Ban Phan Tang",
    "wof:placetype":"locality"
},
  "geometry": {"coordinates":[100.18039,16.62281],"type":"Point"}
}