{
  "type": "Feature",
  "properties": {
    "gn:admin1_code":"18.0",
    "gn:asciiname":"Ban Hua Khua",
    "gn:country_code":"TH",
    "gn:dem":231,
    "gn:feature_class":"P",
    "gn:feature_code":"PPL",
    "gn:name":"Ban Hua Khua",
    "gn:population":0,
    "gn:timezone":"Asia/Bangkok",
    "iso:country":"TH",
    "name:tha_x_preferred":[
        "Ban Hua Khua"
    ],
    "name:tha_x_variant":[
        "\u0e1a\u0e49\u0e32\u0e19\u0e2b\u0e31\u0e27\u0e02\u0e31\u0e27"
    ],
    "wof:name":"Ban Hua Khua",
    "wof:placetype":"locality"
},
  "geometry": {"coordinates":[102.12161,17.04342],"type":"Point"}
}