{
  "type": "Feature",
  "properties": {
    "gn:admin1_code":"23.0",
    "gn:asciiname":"Ban Na Sinuan",
    "gn:country_code":"TH",
    "gn:dem":187,
    "gn:feature_class":"P",
    "gn:feature_code":"PPL",
    "gn:name":"Ban Na Sinuan",
    "gn:population":0,
    "gn:timezone":"Asia/Bangkok",
    "iso:country":"TH",
    "name:tha_x_preferred":[
        "\u0e1a\u0e49\u0e32\u0e19\u0e19\u0e32\u0e2a\u0e35\u0e19\u0e27\u0e25"
    ],
    "name:und_x_variant":[
        "Ban Na Si Nuan"
    ],
    "wof:name":"Ban Na Sinuan",
    "wof:placetype":"locality"
},
  "geometry": {"coordinates":[104.012,16.76392],"type":"Point"}
}