{
  "type": "Feature",
  "properties": {
    "gn:admin1_code":"42.0",
    "gn:asciiname":"Ban Ko Pichit",
    "gn:country_code":"TH",
    "gn:dem":2,
    "gn:feature_class":"P",
    "gn:feature_code":"PPL",
    "gn:name":"Ban Ko Pichit",
    "gn:population":0,
    "gn:timezone":"Asia/Bangkok",
    "iso:country":"TH",
    "name:tha_x_preferred":[
        "\u0e1a\u0e49\u0e32\u0e19\u0e40\u0e01\u0e32\u0e30\u0e1e\u0e34\u0e08\u0e34\u0e15\u0e23"
    ],
    "wof:name":"Ban Ko Pichit",
    "wof:placetype":"locality"
},
  "geometry": {"coordinates":[100.79619,13.61422],"type":"Point"}
}