{
  "type": "Feature",
  "properties": {
    "gn:admin1_code":"15.0",
    "gn:asciiname":"Ban Nong Krathum",
    "gn:country_code":"TH",
    "gn:dem":54,
    "gn:feature_class":"P",
    "gn:feature_code":"PPL",
    "gn:name":"Ban Nong Krathum",
    "gn:population":0,
    "gn:timezone":"Asia/Bangkok",
    "iso:country":"TH",
    "name:tha_x_preferred":[
        "\u0e1a\u0e49\u0e32\u0e19\u0e2b\u0e19\u0e2d\u0e07\u0e01\u0e23\u0e30\u0e17\u0e38\u0e48\u0e21"
    ],
    "name:und_x_variant":[
        "B\u0101n Naung Gathum",
        "Ban Nong Kathum",
        "Ban Nong Krathum"
    ],
    "wof:name":"Ban Nong Krathum",
    "wof:placetype":"locality"
},
  "geometry": {"coordinates":[99.84269,15.46422],"type":"Point"}
}