{
  "type": "Feature",
  "properties": {
    "gn:admin1_code":"80",
    "gn:asciiname":"Ban Song Si",
    "gn:country_code":"TH",
    "gn:dem":81,
    "gn:feature_class":"P",
    "gn:feature_code":"PPL",
    "gn:name":"Ban Song Si",
    "gn:population":0,
    "gn:timezone":"Asia/Bangkok",
    "iso:country":"TH",
    "name:tha_x_preferred":[
        "\u0e1a\u0e49\u0e32\u0e19\u0e2a\u0e2d\u0e07\u0e2a\u0e35"
    ],
    "wof:name":"Ban Song Si",
    "wof:placetype":"locality"
},
  "geometry": {"coordinates":[101.91708,13.58303],"type":"Point"}
}