{
  "type": "Feature",
  "properties": {
    "gn:admin1_code":"3.0",
    "gn:asciiname":"Ban Pa Lo",
    "gn:country_code":"TH",
    "gn:dem":469,
    "gn:feature_class":"P",
    "gn:feature_code":"PPL",
    "gn:name":"Ban Pa Lo",
    "gn:population":0,
    "gn:timezone":"Asia/Bangkok",
    "iso:country":"TH",
    "name:tha_x_preferred":[
        "\u0e1a\u0e49\u0e32\u0e19\u0e1b\u0e48\u0e32\u0e42\u0e2b\u0e25"
    ],
    "wof:name":"Ban Pa Lo",
    "wof:placetype":"locality"
},
  "geometry": {"coordinates":[99.52791999999999,20.06264],"type":"Point"}
}