{
  "type": "Feature",
  "properties": {
    "gn:admin1_code":"63.0",
    "gn:asciiname":"Ban Si Phraya",
    "gn:country_code":"TH",
    "gn:dem":77,
    "gn:feature_class":"P",
    "gn:feature_code":"PPL",
    "gn:name":"Ban Si Phraya",
    "gn:population":0,
    "gn:timezone":"Asia/Bangkok",
    "iso:country":"TH",
    "name:tha_x_preferred":[
        "\u0e1a\u0e49\u0e32\u0e19\u0e28\u0e23\u0e35\u0e1e\u0e23\u0e30\u0e22\u0e32"
    ],
    "wof:name":"Ban Si Phraya",
    "wof:placetype":"locality"
},
  "geometry": {"coordinates":[98.82464,8.50292],"type":"Point"}
}