{
  "type": "Feature",
  "properties": {
    "gn:admin1_code":"0.0",
    "gn:asciiname":"Ban Pha Lae",
    "gn:country_code":"TH",
    "gn:dem":929,
    "gn:feature_class":"P",
    "gn:feature_code":"PPL",
    "gn:name":"Ban Pha Lae",
    "gn:population":0,
    "gn:timezone":"Asia/Bangkok",
    "iso:country":"TH",
    "wof:name":"Ban Pha Lae",
    "wof:placetype":"locality"
},
  "geometry": {"coordinates":[98.05167,18.81889],"type":"Point"}
}