{
  "type": "Feature",
  "properties": {
    "gn:admin1_code":"80.0",
    "gn:asciiname":"Ban Thap Phrik Noi",
    "gn:country_code":"TH",
    "gn:dem":109,
    "gn:feature_class":"P",
    "gn:feature_code":"PPL",
    "gn:name":"Ban Thap Phrik Noi",
    "gn:population":0,
    "gn:timezone":"Asia/Bangkok",
    "iso:country":"TH",
    "wof:name":"Ban Thap Phrik Noi",
    "wof:placetype":"locality"
},
  "geometry": {"coordinates":[102.33139,13.5625],"type":"Point"}
}