{
  "type": "Feature",
  "properties": {
    "gn:admin1_code":"68.0",
    "gn:asciiname":"Ban Laem Yang",
    "gn:country_code":"TH",
    "gn:dem":15,
    "gn:feature_class":"P",
    "gn:feature_code":"PPL",
    "gn:name":"Ban Laem Yang",
    "gn:population":0,
    "gn:timezone":"Asia/Bangkok",
    "iso:country":"TH",
    "name:tha_x_preferred":[
        "\u0e1a\u0e49\u0e32\u0e19\u0e41\u0e2b\u0e25\u0e21\u0e22\u0e32\u0e07"
    ],
    "name:und_x_variant":[
        "Ban Hlem Yang",
        "Ban Laem Ya",
        "Ban Laem Yang"
    ],
    "wof:name":"Ban Laem Yang",
    "wof:placetype":"locality"
},
  "geometry": {"coordinates":[100.27167,7.53864],"type":"Point"}
}