{
  "type": "Feature",
  "properties": {
    "gn:admin1_code":"36",
    "gn:asciiname":"Ban Na Wat",
    "gn:country_code":"TH",
    "gn:dem":7,
    "gn:feature_class":"P",
    "gn:feature_code":"PPL",
    "gn:name":"Ban Na Wat",
    "gn:population":0,
    "gn:timezone":"Asia/Bangkok",
    "iso:country":"TH",
    "name:tha_x_preferred":[
        "\u0e1a\u0e49\u0e32\u0e19\u0e2b\u0e19\u0e49\u0e32\u0e27\u0e31\u0e14"
    ],
    "wof:name":"Ban Na Wat",
    "wof:placetype":"locality"
},
  "geometry": {"coordinates":[100.32966999999999,14.32244],"type":"Point"}
}