{
  "type": "Feature",
  "properties": {
    "gn:admin1_code":"1.0",
    "gn:asciiname":"Ban Phae",
    "gn:country_code":"TH",
    "gn:dem":251,
    "gn:feature_class":"P",
    "gn:feature_code":"PPL",
    "gn:name":"Ban Phae",
    "gn:population":0,
    "gn:timezone":"Asia/Bangkok",
    "iso:country":"TH",
    "name:tha_x_preferred":[
        "\u0e1a\u0e49\u0e32\u0e19\u0e41\u0e1e\u0e30"
    ],
    "wof:name":"Ban Phae",
    "wof:placetype":"locality"
},
  "geometry": {"coordinates":[97.93633,18.16983],"type":"Point"}
}