{
  "type": "Feature",
  "properties": {
    "gn:admin1_code":"50.0",
    "gn:asciiname":"Ban Rang Wan",
    "gn:country_code":"TH",
    "gn:dem":17,
    "gn:feature_class":"P",
    "gn:feature_code":"PPL",
    "gn:name":"Ban Rang Wan",
    "gn:population":0,
    "gn:timezone":"Asia/Bangkok",
    "iso:country":"TH",
    "name:tha_x_preferred":[
        "\u0e1a\u0e49\u0e32\u0e19\u0e23\u0e32\u0e07\u0e27\u0e32\u0e25\u0e22\u0e4c"
    ],
    "wof:name":"Ban Rang Wan",
    "wof:placetype":"locality"
},
  "geometry": {"coordinates":[99.81713999999999,13.86097],"type":"Point"}
}