{
  "type": "Feature",
  "properties": {
    "gn:admin1_code":"44.0",
    "gn:asciiname":"Ban Nong Kha Noi",
    "gn:country_code":"TH",
    "gn:dem":40,
    "gn:feature_class":"P",
    "gn:feature_code":"PPL",
    "gn:name":"Ban Nong Kha Noi",
    "gn:population":0,
    "gn:timezone":"Asia/Bangkok",
    "iso:country":"TH",
    "name:tha_x_preferred":[
        "\u0e1a\u0e49\u0e32\u0e19\u0e2b\u0e19\u0e2d\u0e07\u0e04\u0e48\u0e32\u0e19\u0e49\u0e2d\u0e22"
    ],
    "wof:name":"Ban Nong Kha Noi",
    "wof:placetype":"locality"
},
  "geometry": {"coordinates":[101.50353,13.59656],"type":"Point"}
}