{
  "type": "Feature",
  "properties": {
    "gn:admin1_code":"31.0",
    "gn:asciiname":"Ban Lilanon (Song)",
    "gn:country_code":"TH",
    "gn:dem":100,
    "gn:feature_class":"P",
    "gn:feature_code":"PPL",
    "gn:name":"Ban Lilanon (Song)",
    "gn:population":0,
    "gn:timezone":"Asia/Bangkok",
    "iso:country":"TH",
    "name:tha_x_preferred":[
        "\u0e1a\u0e49\u0e32\u0e19\u0e25\u0e35\u0e25\u0e32\u0e19\u0e19\u0e17\u0e4c (\u0e2a\u0e2d\u0e07)"
    ],
    "name:und_x_variant":[
        "Ban Lilanon (2)",
        "Ban Lilanon (Song)"
    ],
    "wof:name":"Ban Lilanon (Song)",
    "wof:placetype":"locality"
},
  "geometry": {"coordinates":[101.66072,5.96672],"type":"Point"}
}