{
  "type": "Feature",
  "properties": {
    "gn:admin1_code":"65.0",
    "gn:asciiname":"Ban Lang Wat",
    "gn:country_code":"TH",
    "gn:dem":23,
    "gn:feature_class":"P",
    "gn:feature_code":"PPL",
    "gn:name":"Ban Lang Wat",
    "gn:population":0,
    "gn:timezone":"Asia/Bangkok",
    "iso:country":"TH",
    "name:tha_x_preferred":[
        "\u0e1a\u0e49\u0e32\u0e19\u0e2b\u0e25\u0e31\u0e07\u0e27\u0e31\u0e14"
    ],
    "wof:name":"Ban Lang Wat",
    "wof:placetype":"locality"
},
  "geometry": {"coordinates":[99.50852999999999,7.55286],"type":"Point"}
}