{
  "type": "Feature",
  "properties": {
    "gn:admin1_code":"41.0",
    "gn:asciiname":"Ban San Sai Ngoen",
    "gn:country_code":"TH",
    "gn:dem":431,
    "gn:feature_class":"P",
    "gn:feature_code":"PPL",
    "gn:name":"Ban San Sai Ngoen",
    "gn:population":0,
    "gn:timezone":"Asia/Bangkok",
    "iso:country":"TH",
    "name:tha_x_preferred":[
        "\u0e1a\u0e49\u0e32\u0e19\u0e2a\u0e31\u0e19\u0e17\u0e23\u0e32\u0e22\u0e40\u0e07\u0e34\u0e19"
    ],
    "wof:name":"Ban San Sai Ngoen",
    "wof:placetype":"locality"
},
  "geometry": {"coordinates":[100.06310999999999,19.08633],"type":"Point"}
}