{
  "type": "Feature",
  "properties": {
    "gn:admin1_code":"26.0",
    "gn:asciiname":"Ban Prang Makha",
    "gn:country_code":"TH",
    "gn:dem":356,
    "gn:feature_class":"P",
    "gn:feature_code":"PPL",
    "gn:name":"Ban Prang Makha",
    "gn:population":0,
    "gn:timezone":"Asia/Bangkok",
    "iso:country":"TH",
    "name:tha_x_preferred":[
        "\u0e1a\u0e49\u0e32\u0e19\u0e1b\u0e23\u0e32\u0e07\u0e04\u0e4c\u0e21\u0e30\u0e04\u0e48\u0e32"
    ],
    "wof:name":"Ban Prang Makha",
    "wof:placetype":"locality"
},
  "geometry": {"coordinates":[101.34428,15.82158],"type":"Point"}
}