{
  "type": "Feature",
  "properties": {
    "gn:admin1_code":"63.0",
    "gn:asciiname":"Ban Khuan Sian",
    "gn:country_code":"TH",
    "gn:dem":82,
    "gn:feature_class":"P",
    "gn:feature_code":"PPL",
    "gn:name":"Ban Khuan Sian",
    "gn:population":0,
    "gn:timezone":"Asia/Bangkok",
    "iso:country":"TH",
    "name:tha_x_preferred":[
        "\u0e1a\u0e49\u0e32\u0e19\u0e04\u0e27\u0e19\u0e40\u0e28\u0e35\u0e22\u0e23"
    ],
    "wof:name":"Ban Khuan Sian",
    "wof:placetype":"locality"
},
  "geometry": {"coordinates":[98.79831,8.50469],"type":"Point"}
}