{
  "type": "Feature",
  "properties": {
    "gn:admin1_code":"70.0",
    "gn:asciiname":"Ban Ba Yi Klang",
    "gn:country_code":"TH",
    "gn:dem":93,
    "gn:feature_class":"P",
    "gn:feature_code":"PPL",
    "gn:name":"Ban Ba Yi Klang",
    "gn:population":0,
    "gn:timezone":"Asia/Bangkok",
    "iso:country":"TH",
    "name:tha_x_preferred":[
        "\u0e1a\u0e49\u0e32\u0e19\u0e1a\u0e32\u0e22\u0e34\u0e01\u0e25\u0e32\u0e07"
    ],
    "wof:name":"Ban Ba Yi Klang",
    "wof:placetype":"locality"
},
  "geometry": {"coordinates":[101.36194,6.25597],"type":"Point"}
}