{
  "type": "Feature",
  "properties": {
    "gn:admin1_code":"10.0",
    "gn:asciiname":"Ban Nam Mi Mai Charoen",
    "gn:country_code":"TH",
    "gn:dem":110,
    "gn:feature_class":"P",
    "gn:feature_code":"PPL",
    "gn:name":"Ban Nam Mi Mai Charoen",
    "gn:population":0,
    "gn:timezone":"Asia/Bangkok",
    "iso:country":"TH",
    "name:tha_x_preferred":[
        "Ban Nam Mi Mai Charoen"
    ],
    "name:tha_x_variant":[
        "\u0e1a\u0e49\u0e32\u0e19\u0e19\u0e49\u0e33\u0e2b\u0e21\u0e35\u0e43\u0e2b\u0e21\u0e48\u0e40\u0e08\u0e23\u0e34\u0e0d"
    ],
    "wof:name":"Ban Nam Mi Mai Charoen",
    "wof:placetype":"locality"
},
  "geometry": {"coordinates":[100.42744999999999,17.55661],"type":"Point"}
}