{
  "type": "Feature",
  "properties": {
    "gn:admin1_code":"1.0",
    "gn:asciiname":"Ban Huai Phueng Mai",
    "gn:country_code":"TH",
    "gn:dem":1093,
    "gn:feature_class":"P",
    "gn:feature_code":"PPL",
    "gn:name":"Ban Huai Phueng Mai",
    "gn:population":0,
    "gn:timezone":"Asia/Bangkok",
    "iso:country":"TH",
    "name:tha_x_preferred":[
        "\u0e1a\u0e49\u0e32\u0e19\u0e2b\u0e49\u0e27\u0e22\u0e1c\u0e36\u0e49\u0e07\u0e43\u0e2b\u0e21\u0e48"
    ],
    "wof:name":"Ban Huai Phueng Mai",
    "wof:placetype":"locality"
},
  "geometry": {"coordinates":[98.09632999999999,18.61636],"type":"Point"}
}