{
  "type": "Feature",
  "properties": {
    "gn:admin1_code":"50.0",
    "gn:asciiname":"Ban Bo Ong",
    "gn:country_code":"TH",
    "gn:dem":169,
    "gn:feature_class":"P",
    "gn:feature_code":"PPL",
    "gn:name":"Ban Bo Ong",
    "gn:population":0,
    "gn:timezone":"Asia/Bangkok",
    "iso:country":"TH",
    "name:tha_x_preferred":[
        "\u0e1a\u0e49\u0e32\u0e19\u0e42\u0e1a\u0e2d\u0e48\u0e2d\u0e07"
    ],
    "wof:name":"Ban Bo Ong",
    "wof:placetype":"locality"
},
  "geometry": {"coordinates":[98.48425,14.83953],"type":"Point"}
}