{
  "type": "Feature",
  "properties": {
    "gn:admin1_code":"12.0",
    "gn:asciiname":"Ban Fao Rai",
    "gn:country_code":"TH",
    "gn:dem":523,
    "gn:feature_class":"P",
    "gn:feature_code":"PPL",
    "gn:name":"Ban Fao Rai",
    "gn:population":0,
    "gn:timezone":"Asia/Bangkok",
    "iso:country":"TH",
    "name:tha_x_preferred":[
        "\u0e1a\u0e49\u0e32\u0e19\u0e40\u0e1d\u0e49\u0e32\u0e44\u0e23\u0e48"
    ],
    "wof:name":"Ban Fao Rai",
    "wof:placetype":"locality"
},
  "geometry": {"coordinates":[100.72703,16.74639],"type":"Point"}
}