{
  "type": "Feature",
  "properties": {
    "gn:admin1_code":"23.0",
    "gn:asciiname":"Ban Dong Phayung Tai",
    "gn:country_code":"TH",
    "gn:dem":164,
    "gn:feature_class":"P",
    "gn:feature_code":"PPL",
    "gn:name":"Ban Dong Phayung Tai",
    "gn:population":0,
    "gn:timezone":"Asia/Bangkok",
    "iso:country":"TH",
    "name:tha_x_preferred":[
        "\u0e1a\u0e49\u0e32\u0e19\u0e14\u0e07\u0e1e\u0e22\u0e38\u0e07\u0e43\u0e15\u0e49"
    ],
    "name:und_x_variant":[
        "Ban Dong Phayung"
    ],
    "wof:lang_x_official":[
        "tha"
    ],
    "wof:lang_x_spoken":[
        "tha"
    ],
    "wof:name":"Ban Dong Phayung Tai",
    "wof:placetype":"locality"
},
  "geometry": {"coordinates":[103.67968999999999,16.52164],"type":"Point"}
}