{
  "type": "Feature",
  "properties": {
    "gn:admin1_code":"64.0",
    "gn:asciiname":"Ban Sai Liap",
    "gn:country_code":"TH",
    "gn:dem":10,
    "gn:feature_class":"P",
    "gn:feature_code":"PPL",
    "gn:name":"Ban Sai Liap",
    "gn:population":0,
    "gn:timezone":"Asia/Bangkok",
    "iso:country":"TH",
    "name:tha_x_preferred":[
        "\u0e1a\u0e49\u0e32\u0e19\u0e44\u0e2a\u0e40\u0e25\u0e35\u0e22\u0e1a"
    ],
    "wof:name":"Ban Sai Liap",
    "wof:placetype":"locality"
},
  "geometry": {"coordinates":[100.00785999999999,7.88756],"type":"Point"}
}