{
  "type": "Feature",
  "properties": {
    "gn:admin1_code":"29",
    "gn:asciiname":"Ban Kum Phaniang",
    "gn:country_code":"TH",
    "gn:dem":179,
    "gn:feature_class":"P",
    "gn:feature_code":"PPL",
    "gn:name":"Ban Kum Phaniang",
    "gn:population":0,
    "gn:timezone":"Asia/Bangkok",
    "iso:country":"TH",
    "name:tha_x_preferred":[
        "\u0e1a\u0e49\u0e32\u0e19\u0e01\u0e38\u0e21\u0e1e\u0e30\u0e40\u0e19\u0e35\u0e22\u0e07"
    ],
    "wof:name":"Ban Kum Phaniang",
    "wof:placetype":"locality"
},
  "geometry": {"coordinates":[103.42872,14.59625],"type":"Point"}
}