{
  "type": "Feature",
  "properties": {
    "gn:admin1_code":"2.0",
    "gn:asciiname":"Ban Sop Aep",
    "gn:country_code":"TH",
    "gn:dem":590,
    "gn:feature_class":"P",
    "gn:feature_code":"PPL",
    "gn:name":"Ban Sop Aep",
    "gn:population":0,
    "gn:timezone":"Asia/Bangkok",
    "iso:country":"TH",
    "name:tha_x_preferred":[
        "\u0e1a\u0e49\u0e32\u0e19\u0e2a\u0e1a\u0e41\u0e2d\u0e1a"
    ],
    "wof:name":"Ban Sop Aep",
    "wof:placetype":"locality"
},
  "geometry": {"coordinates":[98.61153,18.52939],"type":"Point"}
}