{
  "type": "Feature",
  "properties": {
    "gn:admin1_code":"64.0",
    "gn:asciiname":"Ban Lak Chang",
    "gn:country_code":"TH",
    "gn:dem":39,
    "gn:feature_class":"P",
    "gn:feature_code":"PPL",
    "gn:name":"Ban Lak Chang",
    "gn:population":0,
    "gn:timezone":"Asia/Bangkok",
    "iso:country":"TH",
    "name:tha_x_preferred":[
        "\u0e1a\u0e49\u0e32\u0e19\u0e2b\u0e25\u0e31\u0e01\u0e0a\u0e49\u0e32\u0e07"
    ],
    "name:und_x_variant":[
        "Ban Sathani Lak Chang"
    ],
    "wof:name":"Ban Lak Chang",
    "wof:placetype":"locality"
},
  "geometry": {"coordinates":[99.55036,8.33378],"type":"Point"}
}