{
  "type": "Feature",
  "properties": {
    "gn:admin1_code":"50.0",
    "gn:asciiname":"Ban Daowadueng",
    "gn:country_code":"TH",
    "gn:dem":81,
    "gn:feature_class":"P",
    "gn:feature_code":"PPL",
    "gn:name":"Ban Daowadueng",
    "gn:population":0,
    "gn:timezone":"Asia/Bangkok",
    "iso:country":"TH",
    "name:tha_x_preferred":[
        "\u0e1a\u0e49\u0e32\u0e19\u0e14\u0e32\u0e27\u0e14\u0e36\u0e07\u0e2a\u0e4c"
    ],
    "wof:name":"Ban Daowadueng",
    "wof:placetype":"locality"
},
  "geometry": {"coordinates":[98.83528,14.47995],"type":"Point"}
}