{
  "type": "Feature",
  "properties": {
    "gn:admin1_code":"34",
    "gn:asciiname":"Ban Chong Khae",
    "gn:country_code":"TH",
    "gn:dem":62,
    "gn:feature_class":"P",
    "gn:feature_code":"PPL",
    "gn:name":"Ban Chong Khae",
    "gn:population":0,
    "gn:timezone":"Asia/Bangkok",
    "iso:country":"TH",
    "name:tha_x_preferred":[
        "\u0e1a\u0e49\u0e32\u0e19\u0e0a\u0e48\u0e2d\u0e07\u0e41\u0e04"
    ],
    "wof:name":"Ban Chong Khae",
    "wof:placetype":"locality"
},
  "geometry": {"coordinates":[100.69275,15.15174],"type":"Point"}
}