{
  "type": "Feature",
  "properties": {
    "gn:admin1_code":"26.0",
    "gn:asciiname":"Ban Song Khaen",
    "gn:country_code":"TH",
    "gn:dem":236,
    "gn:feature_class":"P",
    "gn:feature_code":"PPL",
    "gn:name":"Ban Song Khaen",
    "gn:population":0,
    "gn:timezone":"Asia/Bangkok",
    "iso:country":"TH",
    "name:tha_x_preferred":[
        "\u0e1a\u0e49\u0e32\u0e19\u0e2a\u0e07\u0e41\u0e04\u0e19"
    ],
    "wof:name":"Ban Song Khaen",
    "wof:placetype":"locality"
},
  "geometry": {"coordinates":[101.78422,15.85747],"type":"Point"}
}