{
  "type": "Feature",
  "properties": {
    "gn:admin1_code":"18.0",
    "gn:asciiname":"Ban Pa Sakhae",
    "gn:country_code":"TH",
    "gn:dem":322,
    "gn:feature_class":"P",
    "gn:feature_code":"PPL",
    "gn:name":"Ban Pa Sakhae",
    "gn:population":0,
    "gn:timezone":"Asia/Bangkok",
    "iso:country":"TH",
    "name:tha_x_preferred":[
        "Ban Pa Sakhae"
    ],
    "name:tha_x_variant":[
        "\u0e1a\u0e49\u0e32\u0e19\u0e1b\u0e48\u0e32\u0e2a\u0e30\u0e41\u0e02"
    ],
    "wof:name":"Ban Pa Sakhae",
    "wof:placetype":"locality"
},
  "geometry": {"coordinates":[101.27536000000001,17.11508],"type":"Point"}
}