{
  "type": "Feature",
  "properties": {
    "gn:admin1_code":"18.0",
    "gn:asciiname":"Ban Huai Hin So",
    "gn:country_code":"TH",
    "gn:dem":216,
    "gn:feature_class":"P",
    "gn:feature_code":"PPL",
    "gn:name":"Ban Huai Hin So",
    "gn:population":0,
    "gn:timezone":"Asia/Bangkok",
    "iso:country":"TH",
    "name:tha_x_preferred":[
        "\u0e1a\u0e49\u0e32\u0e19\u0e2b\u0e49\u0e27\u0e22\u0e2b\u0e34\u0e19\u0e2a\u0e2d"
    ],
    "wof:name":"Ban Huai Hin So",
    "wof:placetype":"locality"
},
  "geometry": {"coordinates":[101.61617,17.84647],"type":"Point"}
}