{
  "type": "Feature",
  "properties": {
    "gn:admin1_code":"27",
    "gn:asciiname":"Ban Yup I Pun",
    "gn:country_code":"TH",
    "gn:dem":393,
    "gn:feature_class":"P",
    "gn:feature_code":"PPL",
    "gn:name":"Ban Yup I Pun",
    "gn:population":0,
    "gn:timezone":"Asia/Bangkok",
    "iso:country":"TH",
    "name:tha_x_preferred":[
        "\u0e1a\u0e49\u0e32\u0e19\u0e22\u0e38\u0e1a\u0e2d\u0e35\u0e1b\u0e39\u0e19"
    ],
    "wof:name":"Ban Yup I Pun",
    "wof:placetype":"locality"
},
  "geometry": {"coordinates":[101.73824999999999,14.46575],"type":"Point"}
}