{
  "type": "Feature",
  "properties": {
    "gn:admin1_code":"61.0",
    "gn:asciiname":"Ban Lum Kriap",
    "gn:country_code":"TH",
    "gn:dem":33,
    "gn:feature_class":"P",
    "gn:feature_code":"PPL",
    "gn:name":"Ban Lum Kriap",
    "gn:population":0,
    "gn:timezone":"Asia/Bangkok",
    "iso:country":"TH",
    "name:tha_x_preferred":[
        "\u0e1a\u0e49\u0e32\u0e19\u0e25\u0e38\u0e48\u0e21\u0e40\u0e01\u0e23\u0e35\u0e22\u0e1a"
    ],
    "wof:lang_x_official":[
        "tha"
    ],
    "wof:lang_x_spoken":[
        "tha"
    ],
    "wof:name":"Ban Lum Kriap",
    "wof:placetype":"locality"
},
  "geometry": {"coordinates":[98.64111,8.49011],"type":"Point"}
}