{
  "type": "Feature",
  "properties": {
    "gn:admin1_code":"52.0",
    "gn:asciiname":"Ban Thung Kwang",
    "gn:country_code":"TH",
    "gn:dem":93,
    "gn:feature_class":"P",
    "gn:feature_code":"PPL",
    "gn:name":"Ban Thung Kwang",
    "gn:population":0,
    "gn:timezone":"Asia/Bangkok",
    "iso:country":"TH",
    "name:tha_x_preferred":[
        "\u0e1a\u0e49\u0e32\u0e19\u0e17\u0e38\u0e48\u0e07\u0e01\u0e27\u0e49\u0e32\u0e07"
    ],
    "wof:name":"Ban Thung Kwang",
    "wof:placetype":"locality"
},
  "geometry": {"coordinates":[99.50894,13.61853],"type":"Point"}
}