{
  "type": "Feature",
  "properties": {
    "gn:admin1_code":"51.0",
    "gn:asciiname":"Ban Saphang Krang",
    "gn:country_code":"TH",
    "gn:dem":10,
    "gn:feature_class":"P",
    "gn:feature_code":"PPL",
    "gn:name":"Ban Saphang Krang",
    "gn:population":0,
    "gn:timezone":"Asia/Bangkok",
    "iso:country":"TH",
    "name:tha_x_preferred":[
        "\u0e1a\u0e49\u0e32\u0e19\u0e2a\u0e30\u0e1e\u0e31\u0e07\u0e01\u0e23\u0e48\u0e32\u0e07"
    ],
    "name:und_x_variant":[
        "Ban Kaphang Kang",
        "Ban Kraphang Krang",
        "Ban Saphang Krang"
    ],
    "wof:lang_x_official":[
        "tha"
    ],
    "wof:lang_x_spoken":[
        "tha"
    ],
    "wof:name":"Ban Saphang Krang",
    "wof:placetype":"locality"
},
  "geometry": {"coordinates":[99.94261,14.21581],"type":"Point"}
}