{
  "type": "Feature",
  "properties": {
    "gn:admin1_code":"59.0",
    "gn:asciiname":"Ban Ko Sin Hai",
    "gn:country_code":"TH",
    "gn:dem":12,
    "gn:feature_class":"P",
    "gn:feature_code":"PPL",
    "gn:name":"Ban Ko Sin Hai",
    "gn:population":0,
    "gn:timezone":"Asia/Bangkok",
    "iso:country":"TH",
    "name:tha_x_preferred":[
        "\u0e1a\u0e49\u0e32\u0e19\u0e40\u0e01\u0e32\u0e30\u0e2a\u0e34\u0e19\u0e44\u0e2b"
    ],
    "name:und_x_variant":[
        "Ban Sin Hai"
    ],
    "wof:name":"Ban Ko Sin Hai",
    "wof:placetype":"locality"
},
  "geometry": {"coordinates":[98.48554,9.90268],"type":"Point"}
}