{
  "type": "Feature",
  "properties": {
    "gn:admin1_code":"70.0",
    "gn:asciiname":"Ban Khaela",
    "gn:country_code":"TH",
    "gn:dem":45,
    "gn:feature_class":"P",
    "gn:feature_code":"PPL",
    "gn:name":"Ban Khaela",
    "gn:population":0,
    "gn:timezone":"Asia/Bangkok",
    "iso:country":"TH",
    "name:tha_x_preferred":[
        "\u0e1a\u0e49\u0e32\u0e19\u0e41\u0e04\u0e25\u0e30"
    ],
    "name:und_x_variant":[
        "Kampong Kela",
        "Ban Khaela"
    ],
    "wof:name":"Ban Khaela",
    "wof:placetype":"locality"
},
  "geometry": {"coordinates":[101.13572000000001,6.44406],"type":"Point"}
}