{
  "type": "Feature",
  "properties": {
    "gn:admin1_code":"57.0",
    "gn:asciiname":"Ban Rahan",
    "gn:country_code":"TH",
    "gn:dem":15,
    "gn:feature_class":"P",
    "gn:feature_code":"PPL",
    "gn:name":"Ban Rahan",
    "gn:population":0,
    "gn:timezone":"Asia/Bangkok",
    "iso:country":"TH",
    "name:tha_x_preferred":[
        "\u0e1a\u0e49\u0e32\u0e19\u0e23\u0e30\u0e2b\u0e32\u0e19"
    ],
    "wof:name":"Ban Rahan",
    "wof:placetype":"locality"
},
  "geometry": {"coordinates":[99.45864,11.08658],"type":"Point"}
}