{
  "type": "Feature",
  "properties": {
    "gn:admin1_code":"26.0",
    "gn:asciiname":"Ban Sai Ngoen",
    "gn:country_code":"TH",
    "gn:dem":273,
    "gn:feature_class":"P",
    "gn:feature_code":"PPL",
    "gn:name":"Ban Sai Ngoen",
    "gn:population":0,
    "gn:timezone":"Asia/Bangkok",
    "iso:country":"TH",
    "name:tha_x_preferred":[
        "\u0e1a\u0e49\u0e32\u0e19\u0e17\u0e23\u0e32\u0e22\u0e40\u0e07\u0e34\u0e19"
    ],
    "wof:name":"Ban Sai Ngoen",
    "wof:placetype":"locality"
},
  "geometry": {"coordinates":[101.59836,15.5495],"type":"Point"}
}