{
  "type": "Feature",
  "properties": {
    "gn:admin1_code":"11.0",
    "gn:asciiname":"Ban Khlong Yang",
    "gn:country_code":"TH",
    "gn:dem":59,
    "gn:feature_class":"P",
    "gn:feature_code":"PPL",
    "gn:name":"Ban Khlong Yang",
    "gn:population":0,
    "gn:timezone":"Asia/Bangkok",
    "iso:country":"TH",
    "name:tha_x_preferred":[
        "\u0e1a\u0e49\u0e32\u0e19\u0e04\u0e25\u0e2d\u0e07\u0e22\u0e32\u0e07"
    ],
    "wof:name":"Ban Khlong Yang",
    "wof:placetype":"locality"
},
  "geometry": {"coordinates":[99.78028,16.20528],"type":"Point"}
}