{
  "type": "Feature",
  "properties": {
    "gn:admin1_code":"17.0",
    "gn:asciiname":"Ban Pho Si",
    "gn:country_code":"TH",
    "gn:dem":174,
    "gn:feature_class":"P",
    "gn:feature_code":"PPL",
    "gn:name":"Ban Pho Si",
    "gn:population":0,
    "gn:timezone":"Asia/Bangkok",
    "iso:country":"TH",
    "name:tha_x_preferred":[
        "\u0e1a\u0e49\u0e32\u0e19\u0e42\u0e1e\u0e18\u0e34\u0e4c\u0e28\u0e23\u0e35"
    ],
    "wof:name":"Ban Pho Si",
    "wof:placetype":"locality"
},
  "geometry": {"coordinates":[103.13182999999999,17.87625],"type":"Point"}
}