{
  "type": "Feature",
  "properties": {
    "gn:admin1_code":"27",
    "gn:asciiname":"Ban Nong Chao Ruean",
    "gn:country_code":"TH",
    "gn:dem":166,
    "gn:feature_class":"P",
    "gn:feature_code":"PPL",
    "gn:name":"Ban Nong Chao Ruean",
    "gn:population":0,
    "gn:timezone":"Asia/Bangkok",
    "iso:country":"TH",
    "name:tha_x_preferred":[
        "\u0e1a\u0e49\u0e32\u0e19\u0e2b\u0e19\u0e2d\u0e07\u0e40\u0e08\u0e49\u0e32\u0e40\u0e23\u0e37\u0e2d\u0e19"
    ],
    "wof:name":"Ban Nong Chao Ruean",
    "wof:placetype":"locality"
},
  "geometry": {"coordinates":[102.73802999999999,15.11953],"type":"Point"}
}