{
  "type": "Feature",
  "properties": {
    "gn:admin1_code":"41.0",
    "gn:asciiname":"Ban Sak Thung",
    "gn:country_code":"TH",
    "gn:dem":376,
    "gn:feature_class":"P",
    "gn:feature_code":"PPL",
    "gn:name":"Ban Sak Thung",
    "gn:population":0,
    "gn:timezone":"Asia/Bangkok",
    "iso:country":"TH",
    "name:tha_x_preferred":[
        "\u0e1a\u0e49\u0e32\u0e19\u0e2a\u0e31\u0e01\u0e17\u0e38\u0e48\u0e07"
    ],
    "wof:name":"Ban Sak Thung",
    "wof:placetype":"locality"
},
  "geometry": {"coordinates":[100.10906,19.52011],"type":"Point"}
}