{
  "type": "Feature",
  "properties": {
    "gn:admin1_code":"63.0",
    "gn:asciiname":"Ban Nong Lum Pho",
    "gn:country_code":"TH",
    "gn:dem":42,
    "gn:feature_class":"P",
    "gn:feature_code":"PPL",
    "gn:name":"Ban Nong Lum Pho",
    "gn:population":0,
    "gn:timezone":"Asia/Bangkok",
    "iso:country":"TH",
    "name:tha_x_preferred":[
        "\u0e1a\u0e49\u0e32\u0e19\u0e2b\u0e19\u0e2d\u0e07\u0e2b\u0e25\u0e38\u0e21\u0e1e\u0e2d"
    ],
    "name:und_x_variant":[
        "Ban Lum Pho"
    ],
    "wof:name":"Ban Nong Lum Pho",
    "wof:placetype":"locality"
},
  "geometry": {"coordinates":[98.78975,8.31928],"type":"Point"}
}