{
  "type": "Feature",
  "properties": {
    "gn:admin1_code":"79.0",
    "gn:asciiname":"Ban Khok Nam Kliang",
    "gn:country_code":"TH",
    "gn:dem":232,
    "gn:feature_class":"P",
    "gn:feature_code":"PPL",
    "gn:name":"Ban Khok Nam Kliang",
    "gn:population":0,
    "gn:timezone":"Asia/Bangkok",
    "iso:country":"TH",
    "name:tha_x_preferred":[
        "\u0e1a\u0e49\u0e32\u0e19\u0e42\u0e04\u0e01\u0e19\u0e49\u0e33\u0e40\u0e01\u0e25\u0e35\u0e49\u0e22\u0e07"
    ],
    "wof:lang_x_official":[
        "tha"
    ],
    "wof:lang_x_spoken":[
        "tha"
    ],
    "wof:name":"Ban Khok Nam Kliang",
    "wof:placetype":"locality"
},
  "geometry": {"coordinates":[102.41789,17.22247],"type":"Point"}
}