{
  "type": "Feature",
  "properties": {
    "gn:admin1_code":"27",
    "gn:asciiname":"Ban Pho Prue Waeng",
    "gn:country_code":"TH",
    "gn:dem":173,
    "gn:feature_class":"P",
    "gn:feature_code":"PPL",
    "gn:name":"Ban Pho Prue Waeng",
    "gn:population":0,
    "gn:timezone":"Asia/Bangkok",
    "iso:country":"TH",
    "name:tha_x_preferred":[
        "\u0e1a\u0e49\u0e32\u0e19\u0e42\u0e1e\u0e18\u0e34\u0e4c\u0e1b\u0e23\u0e37\u0e2d\u0e41\u0e27\u0e07"
    ],
    "wof:name":"Ban Pho Prue Waeng",
    "wof:placetype":"locality"
},
  "geometry": {"coordinates":[102.2265,15.05333],"type":"Point"}
}