{
  "type": "Feature",
  "properties": {
    "gn:admin1_code":"1.0",
    "gn:asciiname":"Ban Du La Poe",
    "gn:country_code":"TH",
    "gn:dem":1219,
    "gn:feature_class":"P",
    "gn:feature_code":"PPL",
    "gn:name":"Ban Du La Poe",
    "gn:population":0,
    "gn:timezone":"Asia/Bangkok",
    "iso:country":"TH",
    "name:tha_x_preferred":[
        "\u0e1a\u0e49\u0e32\u0e19\u0e14\u0e39\u0e25\u0e32\u0e40\u0e1b\u0e2d"
    ],
    "wof:name":"Ban Du La Poe",
    "wof:placetype":"locality"
},
  "geometry": {"coordinates":[98.08006,18.4075],"type":"Point"}
}