{
  "type": "Feature",
  "properties": {
    "gn:admin1_code":"76.0",
    "gn:asciiname":"Ban Siap",
    "gn:country_code":"TH",
    "gn:dem":177,
    "gn:feature_class":"P",
    "gn:feature_code":"PPL",
    "gn:name":"Ban Siap",
    "gn:population":0,
    "gn:timezone":"Asia/Bangkok",
    "iso:country":"TH",
    "name:tha_x_preferred":[
        "\u0e1a\u0e49\u0e32\u0e19\u0e40\u0e0b\u0e35\u0e22\u0e1a"
    ],
    "wof:name":"Ban Siap",
    "wof:placetype":"locality"
},
  "geometry": {"coordinates":[102.98197,17.16981],"type":"Point"}
}