{
  "type": "Feature",
  "properties": {
    "gn:admin1_code":"66.0",
    "gn:asciiname":"Ban Pai Than Chai",
    "gn:country_code":"TH",
    "gn:dem":64,
    "gn:feature_class":"P",
    "gn:feature_code":"PPL",
    "gn:name":"Ban Pai Than Chai",
    "gn:population":0,
    "gn:timezone":"Asia/Bangkok",
    "iso:country":"TH",
    "name:tha_x_preferred":[
        "\u0e1a\u0e49\u0e32\u0e19\u0e1b\u0e49\u0e32\u0e22\u0e17\u0e31\u0e19\u0e43\u0e08"
    ],
    "wof:name":"Ban Pai Than Chai",
    "wof:placetype":"locality"
},
  "geometry": {"coordinates":[100.17847,7.25222],"type":"Point"}
}