{
  "type": "Feature",
  "properties": {
    "gn:admin1_code":"47.0",
    "gn:asciiname":"U-Tapao",
    "gn:country_code":"TH",
    "gn:dem":21,
    "gn:feature_class":"P",
    "gn:feature_code":"PPL",
    "gn:name":"U-Tapao",
    "gn:population":0,
    "gn:timezone":"Asia/Bangkok",
    "iso:country":"TH",
    "name:deu_x_preferred":[
        "U-Tapao"
    ],
    "name:eng_x_preferred":[
        "U Taphao"
    ],
    "name:eng_x_variant":[
        "U-Tapao",
        "Utapao"
    ],
    "name:fra_x_preferred":[
        "U-Tapao"
    ],
    "name:tha_x_preferred":[
        "Ban U Taphao"
    ],
    "wof:lang_x_official":[
        "tha"
    ],
    "wof:lang_x_spoken":[
        "tha"
    ],
    "wof:name":"U-Tapao",
    "wof:placetype":"locality"
},
  "geometry": {"coordinates":[101.00126,12.70113],"type":"Point"}
}