{
  "type": "Feature",
  "properties": {
    "gn:admin1_code":"6.0",
    "gn:asciiname":"Ban Mae Hit",
    "gn:country_code":"TH",
    "gn:dem":514,
    "gn:feature_class":"P",
    "gn:feature_code":"PPL",
    "gn:name":"Ban Mae Hit",
    "gn:population":0,
    "gn:timezone":"Asia/Bangkok",
    "iso:country":"TH",
    "name:tha_x_preferred":[
        "\u0e1a\u0e49\u0e32\u0e19\u0e41\u0e21\u0e48\u0e2b\u0e35\u0e14"
    ],
    "name:und_x_variant":[
        "B\u0101n Sop Heut",
        "Ban Sop Hit",
        "Ban Mae Hit"
    ],
    "wof:name":"Ban Mae Hit",
    "wof:placetype":"locality"
},
  "geometry": {"coordinates":[99.617,19.33897],"type":"Point"}
}