{
  "type": "Feature",
  "properties": {
    "gn:admin1_code":"34",
    "gn:asciiname":"Ban Khao Tian",
    "gn:country_code":"TH",
    "gn:dem":75,
    "gn:feature_class":"P",
    "gn:feature_code":"PPL",
    "gn:name":"Ban Khao Tian",
    "gn:population":0,
    "gn:timezone":"Asia/Bangkok",
    "iso:country":"TH",
    "name:tha_x_preferred":[
        "\u0e1a\u0e49\u0e32\u0e19\u0e40\u0e02\u0e32\u0e40\u0e15\u0e35\u0e22\u0e19"
    ],
    "wof:name":"Ban Khao Tian",
    "wof:placetype":"locality"
},
  "geometry": {"coordinates":[100.95656,14.98053],"type":"Point"}
}