{
  "type": "Feature",
  "properties": {
    "gn:admin1_code":"4.0",
    "gn:asciiname":"Ban Thung Khon",
    "gn:country_code":"TH",
    "gn:dem":286,
    "gn:feature_class":"P",
    "gn:feature_code":"PPL",
    "gn:name":"Ban Thung Khon",
    "gn:population":0,
    "gn:timezone":"Asia/Bangkok",
    "iso:country":"TH",
    "name:tha_x_preferred":[
        "\u0e1a\u0e49\u0e32\u0e19\u0e17\u0e38\u0e48\u0e07\u0e06\u0e49\u0e2d\u0e19"
    ],
    "wof:name":"Ban Thung Khon",
    "wof:placetype":"locality"
},
  "geometry": {"coordinates":[100.91208,19.08886],"type":"Point"}
}