{
  "type": "Feature",
  "properties": {
    "gn:admin1_code":"46.0",
    "gn:asciiname":"Ban Ko Klang",
    "gn:country_code":"TH",
    "gn:dem":31,
    "gn:feature_class":"P",
    "gn:feature_code":"PPL",
    "gn:name":"Ban Ko Klang",
    "gn:population":0,
    "gn:timezone":"Asia/Bangkok",
    "iso:country":"TH",
    "name:tha_x_preferred":[
        "\u0e1a\u0e49\u0e32\u0e19\u0e40\u0e01\u0e32\u0e30\u0e01\u0e25\u0e32\u0e07"
    ],
    "wof:lang_x_official":[
        "tha"
    ],
    "wof:lang_x_spoken":[
        "tha"
    ],
    "wof:name":"Ban Ko Klang",
    "wof:placetype":"locality"
},
  "geometry": {"coordinates":[101.33253000000001,13.39492],"type":"Point"}
}