{
  "type": "Feature",
  "properties": {
    "gn:admin1_code":"20.0",
    "gn:asciiname":"Ban Khua Kai",
    "gn:country_code":"TH",
    "gn:dem":160,
    "gn:feature_class":"P",
    "gn:feature_code":"PPL",
    "gn:name":"Ban Khua Kai",
    "gn:population":0,
    "gn:timezone":"Asia/Bangkok",
    "iso:country":"TH",
    "name:tha_x_preferred":[
        "\u0e1a\u0e49\u0e32\u0e19\u0e02\u0e31\u0e27\u0e01\u0e48\u0e32\u0e22"
    ],
    "wof:name":"Ban Khua Kai",
    "wof:placetype":"locality"
},
  "geometry": {"coordinates":[103.83045,17.61475],"type":"Point"}
}