{
  "type": "Feature",
  "properties": {
    "gn:admin1_code":"66.0",
    "gn:asciiname":"Ban Sai Yao",
    "gn:country_code":"TH",
    "gn:dem":20,
    "gn:feature_class":"P",
    "gn:feature_code":"PPL",
    "gn:name":"Ban Sai Yao",
    "gn:population":0,
    "gn:timezone":"Asia/Bangkok",
    "iso:country":"TH",
    "name:tha_x_preferred":[
        "\u0e1a\u0e49\u0e32\u0e19\u0e43\u0e2a\u0e22\u0e32\u0e27"
    ],
    "wof:name":"Ban Sai Yao",
    "wof:placetype":"locality"
},
  "geometry": {"coordinates":[99.99021999999999,7.71936],"type":"Point"}
}