{
  "type": "Feature",
  "properties": {
    "gn:admin1_code":"3.0",
    "gn:asciiname":"Ban Phithak Khiri Song",
    "gn:country_code":"TH",
    "gn:dem":626,
    "gn:feature_class":"P",
    "gn:feature_code":"PPL",
    "gn:name":"Ban Phithak Khiri Song",
    "gn:population":0,
    "gn:timezone":"Asia/Bangkok",
    "iso:country":"TH",
    "name:tha_x_preferred":[
        "\u0e1a\u0e49\u0e32\u0e19\u0e1e\u0e34\u0e17\u0e31\u0e01\u0e29\u0e4c\u0e04\u0e35\u0e23\u0e35 \u0e2a\u0e2d\u0e07"
    ],
    "wof:lang_x_official":[
        "tha"
    ],
    "wof:lang_x_spoken":[
        "tha"
    ],
    "wof:name":"Ban Phithak Khiri Song",
    "wof:placetype":"locality"
},
  "geometry": {"coordinates":[100.48419,19.96595],"type":"Point"}
}