{
  "type": "Feature",
  "properties": {
    "gn:admin1_code":"75.0",
    "gn:asciiname":"Ban Loeng Noi",
    "gn:country_code":"TH",
    "gn:dem":130,
    "gn:feature_class":"P",
    "gn:feature_code":"PPL",
    "gn:name":"Ban Loeng Noi",
    "gn:population":0,
    "gn:timezone":"Asia/Bangkok",
    "iso:country":"TH",
    "name:tha_x_preferred":[
        "\u0e1a\u0e49\u0e32\u0e19\u0e40\u0e25\u0e34\u0e07\u0e19\u0e49\u0e2d\u0e22"
    ],
    "wof:name":"Ban Loeng Noi",
    "wof:placetype":"locality"
},
  "geometry": {"coordinates":[104.76022,15.62978],"type":"Point"}
}