{
  "type": "Feature",
  "properties": {
    "gn:admin1_code":"58.0",
    "gn:asciiname":"Ban Duang Di",
    "gn:country_code":"TH",
    "gn:dem":118,
    "gn:feature_class":"P",
    "gn:feature_code":"PPL",
    "gn:name":"Ban Duang Di",
    "gn:population":0,
    "gn:timezone":"Asia/Bangkok",
    "iso:country":"TH",
    "name:tha_x_preferred":[
        "\u0e1a\u0e49\u0e32\u0e19\u0e14\u0e27\u0e07\u0e14\u0e35"
    ],
    "wof:name":"Ban Duang Di",
    "wof:placetype":"locality"
},
  "geometry": {"coordinates":[99.16746999999999,10.92417],"type":"Point"}
}