{
  "type": "Feature",
  "properties": {
    "gn:admin1_code":"23.0",
    "gn:asciiname":"Ban Na Mun Noi",
    "gn:country_code":"TH",
    "gn:dem":215,
    "gn:feature_class":"P",
    "gn:feature_code":"PPL",
    "gn:name":"Ban Na Mun Noi",
    "gn:population":0,
    "gn:timezone":"Asia/Bangkok",
    "iso:country":"TH",
    "name:tha_x_preferred":[
        "\u0e1a\u0e49\u0e32\u0e19\u0e19\u0e32\u0e21\u0e39\u0e25\u0e19\u0e49\u0e2d\u0e22"
    ],
    "wof:name":"Ban Na Mun Noi",
    "wof:placetype":"locality"
},
  "geometry": {"coordinates":[103.26575,16.85742],"type":"Point"}
}