{
  "type": "Feature",
  "properties": {
    "gn:admin1_code":"6.0",
    "gn:asciiname":"Ban Thak",
    "gn:country_code":"TH",
    "gn:dem":335,
    "gn:feature_class":"P",
    "gn:feature_code":"PPL",
    "gn:name":"Ban Thak",
    "gn:population":0,
    "gn:timezone":"Asia/Bangkok",
    "iso:country":"TH",
    "name:tha_x_preferred":[
        "\u0e1a\u0e49\u0e32\u0e19\u0e17\u0e32\u0e01"
    ],
    "wof:name":"Ban Thak",
    "wof:placetype":"locality"
},
  "geometry": {"coordinates":[99.90622,18.61436],"type":"Point"}
}