{
  "type": "Feature",
  "properties": {
    "gn:admin1_code":"35.0",
    "gn:asciiname":"Ban Bang Phlap Song",
    "gn:country_code":"TH",
    "gn:dem":12,
    "gn:feature_class":"P",
    "gn:feature_code":"PPL",
    "gn:name":"Ban Bang Phlap Song",
    "gn:population":0,
    "gn:timezone":"Asia/Bangkok",
    "iso:country":"TH",
    "name:tha_x_preferred":[
        "\u0e1a\u0e49\u0e32\u0e19\u0e1a\u0e32\u0e07\u0e1e\u0e25\u0e31\u0e1a \u0e2a\u0e2d\u0e07"
    ],
    "wof:name":"Ban Bang Phlap Song",
    "wof:placetype":"locality"
},
  "geometry": {"coordinates":[100.41142000000001,14.64106],"type":"Point"}
}