{
  "type": "Feature",
  "properties": {
    "gn:admin1_code":"5.0",
    "gn:asciiname":"Ban Pha Dan",
    "gn:country_code":"TH",
    "gn:dem":441,
    "gn:feature_class":"P",
    "gn:feature_code":"PPL",
    "gn:name":"Ban Pha Dan",
    "gn:population":0,
    "gn:timezone":"Asia/Bangkok",
    "iso:country":"TH",
    "name:tha_x_preferred":[
        "\u0e1a\u0e49\u0e32\u0e19\u0e1c\u0e32\u0e14\u0e48\u0e32\u0e19"
    ],
    "name:und_x_variant":[
        "Ban Yang Pha Dan",
        "Ban Pha Dan"
    ],
    "wof:name":"Ban Pha Dan",
    "wof:placetype":"locality"
},
  "geometry": {"coordinates":[99.04164,18.36256],"type":"Point"}
}