{
  "type": "Feature",
  "properties": {
    "gn:admin1_code":"50.0",
    "gn:asciiname":"Ban Samakkhitham",
    "gn:country_code":"TH",
    "gn:dem":115,
    "gn:feature_class":"P",
    "gn:feature_code":"PPL",
    "gn:name":"Ban Samakkhitham",
    "gn:population":0,
    "gn:timezone":"Asia/Bangkok",
    "iso:country":"TH",
    "name:tha_x_preferred":[
        "\u0e1a\u0e49\u0e32\u0e19\u0e2a\u0e32\u0e21\u0e31\u0e04\u0e04\u0e35\u0e18\u0e23\u0e23\u0e21"
    ],
    "wof:name":"Ban Samakkhitham",
    "wof:placetype":"locality"
},
  "geometry": {"coordinates":[99.08153,14.08656],"type":"Point"}
}