{
  "type": "Feature",
  "properties": {
    "gn:admin1_code":"69.0",
    "gn:asciiname":"Ban Du Song Thu Wo",
    "gn:country_code":"TH",
    "gn:dem":12,
    "gn:feature_class":"P",
    "gn:feature_code":"PPL",
    "gn:name":"Ban Du Song Thu Wo",
    "gn:population":0,
    "gn:timezone":"Asia/Bangkok",
    "iso:country":"TH",
    "name:tha_x_preferred":[
        "\u0e1a\u0e49\u0e32\u0e19\u0e14\u0e39\u0e0b\u0e07\u0e17\u0e39\u0e27\u0e2d"
    ],
    "wof:name":"Ban Du Song Thu Wo",
    "wof:placetype":"locality"
},
  "geometry": {"coordinates":[101.57386,6.62742],"type":"Point"}
}