{
  "type": "Feature",
  "properties": {
    "gn:admin1_code":"12.0",
    "gn:asciiname":"Ban Chai Nam",
    "gn:country_code":"TH",
    "gn:dem":55,
    "gn:feature_class":"P",
    "gn:feature_code":"PPL",
    "gn:name":"Ban Chai Nam",
    "gn:population":0,
    "gn:timezone":"Asia/Bangkok",
    "iso:country":"TH",
    "name:tha_x_preferred":[
        "\u0e1a\u0e49\u0e32\u0e19\u0e0a\u0e31\u0e22\u0e19\u0e32\u0e21"
    ],
    "wof:name":"Ban Chai Nam",
    "wof:placetype":"locality"
},
  "geometry": {"coordinates":[100.47178,16.84778],"type":"Point"}
}