{
  "type": "Feature",
  "properties": {
    "gn:admin1_code":"79.0",
    "gn:asciiname":"Ban Chomphu Thong",
    "gn:country_code":"TH",
    "gn:dem":212,
    "gn:feature_class":"P",
    "gn:feature_code":"PPL",
    "gn:name":"Ban Chomphu Thong",
    "gn:population":0,
    "gn:timezone":"Asia/Bangkok",
    "iso:country":"TH",
    "name:tha_x_preferred":[
        "\u0e1a\u0e49\u0e32\u0e19\u0e0a\u0e21\u0e20\u0e39\u0e17\u0e2d\u0e07"
    ],
    "wof:name":"Ban Chomphu Thong",
    "wof:placetype":"locality"
},
  "geometry": {"coordinates":[102.32142,17.44303],"type":"Point"}
}