{
  "type": "Feature",
  "properties": {
    "gn:admin1_code":"37",
    "gn:asciiname":"Ban Khlong Hua Chang",
    "gn:country_code":"TH",
    "gn:dem":27,
    "gn:feature_class":"P",
    "gn:feature_code":"PPL",
    "gn:name":"Ban Khlong Hua Chang",
    "gn:population":0,
    "gn:timezone":"Asia/Bangkok",
    "iso:country":"TH",
    "name:tha_x_preferred":[
        "\u0e1a\u0e49\u0e32\u0e19\u0e04\u0e25\u0e2d\u0e07\u0e2b\u0e31\u0e27\u0e0a\u0e49\u0e32\u0e07"
    ],
    "wof:name":"Ban Khlong Hua Chang",
    "wof:placetype":"locality"
},
  "geometry": {"coordinates":[101.05316999999999,14.37514],"type":"Point"}
}