{
  "type": "Feature",
  "properties": {
    "iso:country":"TH",
    "qs:name":"Talat Bang Khen",
    "qs:name_adm0":"Thailand",
    "qs:name_adm1":"Bangkok",
    "qs:photos":108,
    "qs:photos_1k":22,
    "qs:photos_9k":1,
    "qs:photos_9r":3,
    "qs:photos_all":108,
    "qs:photos_sr":3,
    "qs:placetype":"Suburb",
    "qs:pop_sr":"0",
    "wof:name":"Talat Bang Khen",
    "wof:placetype":"neighbourhood"
},
  "geometry": {"coordinates":[100.582151,13.880046],"type":"Point"}
}