{
  "type": "Feature",
  "properties": {
    "gn:admin1_code":"10.0",
    "gn:asciiname":"Ban Charim",
    "gn:country_code":"TH",
    "gn:dem":132,
    "gn:feature_class":"P",
    "gn:feature_code":"PPL",
    "gn:name":"Ban Charim",
    "gn:population":0,
    "gn:timezone":"Asia/Bangkok",
    "iso:country":"TH",
    "name:tha_x_preferred":[
        "\u0e1a\u0e49\u0e32\u0e19\u0e08\u0e23\u0e34\u0e21"
    ],
    "name:und_x_variant":[
        "Chalim",
        "B\u0101n Jarim",
        "Ban Charim"
    ],
    "wof:name":"Ban Charim",
    "wof:placetype":"locality"
},
  "geometry": {"coordinates":[100.35858,17.79293999999999],"type":"Point"}
}