{
  "type": "Feature",
  "properties": {
    "gn:admin1_code":"12.0",
    "gn:asciiname":"Ban Tha Khon Ben",
    "gn:country_code":"TH",
    "gn:dem":62,
    "gn:feature_class":"P",
    "gn:feature_code":"PPL",
    "gn:name":"Ban Tha Khon Ben",
    "gn:population":0,
    "gn:timezone":"Asia/Bangkok",
    "iso:country":"TH",
    "name:tha_x_preferred":[
        "\u0e1a\u0e49\u0e32\u0e19\u0e17\u0e48\u0e32\u0e02\u0e2d\u0e19\u0e40\u0e1a\u0e19"
    ],
    "name:und_x_variant":[
        "B\u0101n Tha Kaun Bean",
        "Ban Tha Khon Baen",
        "Ban Tha Khon Ben"
    ],
    "wof:name":"Ban Tha Khon Ben",
    "wof:placetype":"locality"
},
  "geometry": {"coordinates":[100.32867,17.18406],"type":"Point"}
}