{
  "type": "Feature",
  "properties": {
    "gn:admin1_code":"76.0",
    "gn:asciiname":"Ban Dong Phraiwan",
    "gn:country_code":"TH",
    "gn:dem":185,
    "gn:feature_class":"P",
    "gn:feature_code":"PPL",
    "gn:name":"Ban Dong Phraiwan",
    "gn:population":0,
    "gn:timezone":"Asia/Bangkok",
    "iso:country":"TH",
    "name:tha_x_preferred":[
        "\u0e1a\u0e49\u0e32\u0e19\u0e14\u0e07\u0e44\u0e1e\u0e23\u0e27\u0e31\u0e25\u0e22\u0e4c"
    ],
    "wof:name":"Ban Dong Phraiwan",
    "wof:placetype":"locality"
},
  "geometry": {"coordinates":[103.18189,17.65314],"type":"Point"}
}