{
  "type": "Feature",
  "properties": {
    "gn:admin1_code":"61.0",
    "gn:asciiname":"Ban Thung Maphrao",
    "gn:country_code":"TH",
    "gn:dem":24,
    "gn:feature_class":"P",
    "gn:feature_code":"PPL",
    "gn:name":"Ban Thung Maphrao",
    "gn:population":0,
    "gn:timezone":"Asia/Bangkok",
    "iso:country":"TH",
    "name:tha_x_preferred":[
        "\u0e1a\u0e49\u0e32\u0e19\u0e17\u0e38\u0e48\u0e07\u0e21\u0e30\u0e1e\u0e23\u0e49\u0e32\u0e27"
    ],
    "name:und_x_variant":[
        "Thung Maphrao",
        "Ban Tung Ma Prow",
        "Thai Muang",
        "Tung Ma Prow",
        "Ban Thung Maphrao"
    ],
    "wof:lang_x_official":[
        "tha"
    ],
    "wof:lang_x_spoken":[
        "tha"
    ],
    "wof:name":"Ban Thung Maphrao",
    "wof:placetype":"locality"
},
  "geometry": {"coordinates":[98.30307999999999,8.53397],"type":"Point"}
}