{
  "type": "Feature",
  "properties": {
    "gn:admin1_code":"51.0",
    "gn:asciiname":"Ban Khlong Khut Mai",
    "gn:country_code":"TH",
    "gn:dem":4,
    "gn:feature_class":"P",
    "gn:feature_code":"PPL",
    "gn:name":"Ban Khlong Khut Mai",
    "gn:population":0,
    "gn:timezone":"Asia/Bangkok",
    "iso:country":"TH",
    "name:tha_x_preferred":[
        "\u0e1a\u0e49\u0e32\u0e19\u0e04\u0e25\u0e2d\u0e07\u0e02\u0e38\u0e14\u0e43\u0e2b\u0e21\u0e48"
    ],
    "wof:name":"Ban Khlong Khut Mai",
    "wof:placetype":"locality"
},
  "geometry": {"coordinates":[100.08625000000001,14.21792],"type":"Point"}
}