{
  "type": "Feature",
  "properties": {
    "gn:admin1_code":"52.0",
    "gn:asciiname":"Ban Huai Chalok Makha",
    "gn:country_code":"TH",
    "gn:dem":45,
    "gn:feature_class":"P",
    "gn:feature_code":"PPL",
    "gn:name":"Ban Huai Chalok Makha",
    "gn:population":0,
    "gn:timezone":"Asia/Bangkok",
    "iso:country":"TH",
    "name:tha_x_preferred":[
        "\u0e1a\u0e49\u0e32\u0e19\u0e2b\u0e49\u0e27\u0e22\u0e42\u0e09\u0e25\u0e01\u0e21\u0e30\u0e04\u0e48\u0e32"
    ],
    "wof:name":"Ban Huai Chalok Makha",
    "wof:placetype":"locality"
},
  "geometry": {"coordinates":[99.68733,13.45406],"type":"Point"}
}