{
  "type": "Feature",
  "properties": {
    "gn:admin1_code":"29",
    "gn:asciiname":"Ban Non Tae",
    "gn:country_code":"TH",
    "gn:dem":132,
    "gn:feature_class":"P",
    "gn:feature_code":"PPL",
    "gn:name":"Ban Non Tae",
    "gn:population":0,
    "gn:timezone":"Asia/Bangkok",
    "iso:country":"TH",
    "name:tha_x_preferred":[
        "\u0e1a\u0e49\u0e32\u0e19\u0e42\u0e19\u0e19\u0e41\u0e15\u0e49"
    ],
    "wof:name":"Ban Non Tae",
    "wof:placetype":"locality"
},
  "geometry": {"coordinates":[103.28997,15.30606],"type":"Point"}
}