{
  "type": "Feature",
  "properties": {
    "gn:admin1_code":"32.0",
    "gn:asciiname":"Ban Tha Phra",
    "gn:country_code":"TH",
    "gn:dem":22,
    "gn:feature_class":"P",
    "gn:feature_code":"PPL",
    "gn:name":"Ban Tha Phra",
    "gn:population":0,
    "gn:timezone":"Asia/Bangkok",
    "iso:country":"TH",
    "name:tha_x_preferred":[
        "\u0e1a\u0e49\u0e32\u0e19\u0e17\u0e48\u0e32\u0e1e\u0e23\u0e30"
    ],
    "name:und_x_variant":[
        "Ban Khao Tha Phra"
    ],
    "wof:name":"Ban Tha Phra",
    "wof:placetype":"locality"
},
  "geometry": {"coordinates":[100.11514,15.21986],"type":"Point"}
}