{
  "type": "Feature",
  "properties": {
    "gn:admin1_code":"5.0",
    "gn:asciiname":"Ban Doi Chang",
    "gn:country_code":"TH",
    "gn:dem":1104,
    "gn:feature_class":"P",
    "gn:feature_code":"PPL",
    "gn:name":"Ban Doi Chang",
    "gn:population":0,
    "gn:timezone":"Asia/Bangkok",
    "iso:country":"TH",
    "name:tha_x_preferred":[
        "\u0e1a\u0e49\u0e32\u0e19\u0e14\u0e2d\u0e22\u0e0a\u0e49\u0e32\u0e07"
    ],
    "wof:name":"Ban Doi Chang",
    "wof:placetype":"locality"
},
  "geometry": {"coordinates":[98.79339,18.18078],"type":"Point"}
}