{
  "type": "Feature",
  "properties": {
    "gn:admin1_code":"29",
    "gn:asciiname":"Ban Taloe Pring",
    "gn:country_code":"TH",
    "gn:dem":169,
    "gn:feature_class":"P",
    "gn:feature_code":"PPL",
    "gn:name":"Ban Taloe Pring",
    "gn:population":0,
    "gn:timezone":"Asia/Bangkok",
    "iso:country":"TH",
    "name:tha_x_preferred":[
        "\u0e1a\u0e49\u0e32\u0e19\u0e15\u0e30\u0e40\u0e25\u0e4a\u0e2d\u0e30\u0e1b\u0e23\u0e34\u0e07"
    ],
    "wof:name":"Ban Taloe Pring",
    "wof:placetype":"locality"
},
  "geometry": {"coordinates":[103.40119,14.62525],"type":"Point"}
}