{
  "type": "Feature",
  "properties": {
    "gn:admin1_code":"3.0",
    "gn:asciiname":"Ban Mae Kaeo Den Chai",
    "gn:country_code":"TH",
    "gn:dem":404,
    "gn:feature_class":"P",
    "gn:feature_code":"PPL",
    "gn:name":"Ban Mae Kaeo Den Chai",
    "gn:population":0,
    "gn:timezone":"Asia/Bangkok",
    "iso:country":"TH",
    "name:tha_x_preferred":[
        "\u0e1a\u0e49\u0e32\u0e19\u0e41\u0e21\u0e48\u0e41\u0e01\u0e49\u0e27\u0e40\u0e14\u0e48\u0e19\u0e0a\u0e31\u0e22"
    ],
    "wof:name":"Ban Mae Kaeo Den Chai",
    "wof:placetype":"locality"
},
  "geometry": {"coordinates":[99.83475,19.65967],"type":"Point"}
}