{
  "type": "Feature",
  "properties": {
    "gn:admin1_code":"3.0",
    "gn:asciiname":"Ban Mae Phung",
    "gn:country_code":"TH",
    "gn:dem":388,
    "gn:feature_class":"P",
    "gn:feature_code":"PPL",
    "gn:name":"Ban Mae Phung",
    "gn:population":0,
    "gn:timezone":"Asia/Bangkok",
    "iso:country":"TH",
    "name:tha_x_preferred":[
        "\u0e1a\u0e49\u0e32\u0e19\u0e41\u0e21\u0e48\u0e1e\u0e38\u0e07"
    ],
    "wof:name":"Ban Mae Phung",
    "wof:placetype":"locality"
},
  "geometry": {"coordinates":[100.00733,19.53367],"type":"Point"}
}