{
  "type": "Feature",
  "properties": {
    "gn:admin1_code":"27.0",
    "gn:asciiname":"Ban Nong Mai Tai",
    "gn:country_code":"TH",
    "gn:dem":255,
    "gn:feature_class":"P",
    "gn:feature_code":"PPL",
    "gn:name":"Ban Nong Mai Tai",
    "gn:population":0,
    "gn:timezone":"Asia/Bangkok",
    "iso:country":"TH",
    "name:tha_x_preferred":[
        "\u0e1a\u0e49\u0e32\u0e19\u0e2b\u0e19\u0e2d\u0e07\u0e44\u0e21\u0e49\u0e15\u0e32\u0e22"
    ],
    "wof:lang_x_official":[
        "tha"
    ],
    "wof:lang_x_spoken":[
        "tha"
    ],
    "wof:name":"Ban Nong Mai Tai",
    "wof:placetype":"locality"
},
  "geometry": {"coordinates":[101.72411,15.04219],"type":"Point"}
}