{
  "type": "Feature",
  "properties": {
    "gn:admin1_code":"75.0",
    "gn:asciiname":"Ban Nong Kan",
    "gn:country_code":"TH",
    "gn:dem":133,
    "gn:feature_class":"P",
    "gn:feature_code":"PPL",
    "gn:name":"Ban Nong Kan",
    "gn:population":0,
    "gn:timezone":"Asia/Bangkok",
    "iso:country":"TH",
    "name:tha_x_preferred":[
        "\u0e1a\u0e49\u0e32\u0e19\u0e2b\u0e19\u0e2d\u0e07\u0e01\u0e48\u0e32\u0e19"
    ],
    "wof:name":"Ban Nong Kan",
    "wof:placetype":"locality"
},
  "geometry": {"coordinates":[104.80992000000001,15.36314],"type":"Point"}
}