{
  "type": "Feature",
  "properties": {
    "gn:admin1_code":"10.0",
    "gn:asciiname":"Ban Mani Keao",
    "gn:country_code":"TH",
    "gn:dem":398,
    "gn:feature_class":"P",
    "gn:feature_code":"PPL",
    "gn:name":"Ban Mani Keao",
    "gn:population":0,
    "gn:timezone":"Asia/Bangkok",
    "iso:country":"TH",
    "name:tha_x_preferred":[
        "Ban Mani Keao"
    ],
    "name:tha_x_variant":[
        "\u0e1a\u0e49\u0e32\u0e19\u0e21\u0e13\u0e35\u0e41\u0e01\u0e49\u0e27"
    ],
    "wof:name":"Ban Mani Keao",
    "wof:placetype":"locality"
},
  "geometry": {"coordinates":[100.92233,17.76744],"type":"Point"}
}