{
  "type": "Feature",
  "properties": {
    "gn:admin1_code":"57.0",
    "gn:asciiname":"Ban Hin Thoen",
    "gn:country_code":"TH",
    "gn:dem":82,
    "gn:feature_class":"P",
    "gn:feature_code":"PPL",
    "gn:name":"Ban Hin Thoen",
    "gn:population":0,
    "gn:timezone":"Asia/Bangkok",
    "iso:country":"TH",
    "name:tha_x_preferred":[
        "\u0e1a\u0e49\u0e32\u0e19\u0e2b\u0e34\u0e19\u0e40\u0e17\u0e34\u0e19"
    ],
    "wof:name":"Ban Hin Thoen",
    "wof:placetype":"locality"
},
  "geometry": {"coordinates":[99.60021999999999,11.57189],"type":"Point"}
}