{
  "type": "Feature",
  "properties": {
    "gn:admin1_code":"29.0",
    "gn:asciiname":"Ban Phon Thong",
    "gn:country_code":"TH",
    "gn:dem":213,
    "gn:feature_class":"P",
    "gn:feature_code":"PPL",
    "gn:name":"Ban Phon Thong",
    "gn:population":0,
    "gn:timezone":"Asia/Bangkok",
    "iso:country":"TH",
    "name:tha_x_preferred":[
        "\u0e1a\u0e49\u0e32\u0e19\u0e42\u0e1e\u0e19\u0e17\u0e2d\u0e07"
    ],
    "wof:name":"Ban Phon Thong",
    "wof:placetype":"locality"
},
  "geometry": {"coordinates":[103.71567,14.48281],"type":"Point"}
}