{
  "type": "Feature",
  "properties": {
    "gn:admin1_code":"31.0",
    "gn:asciiname":"Bhormi",
    "gn:country_code":"TH",
    "gn:dem":31,
    "gn:feature_class":"P",
    "gn:feature_code":"PPL",
    "gn:name":"Bhormi",
    "gn:population":0,
    "gn:timezone":"Asia/Bangkok",
    "iso:country":"TH",
    "name:tha_x_preferred":[
        "\u0e1a\u0e49\u0e32\u0e19\u0e1a\u0e32\u0e42\u0e25\u0e4a\u0e30"
    ],
    "name:und_x_variant":[
        "Ban Ba Lo"
    ],
    "wof:lang_x_official":[
        "tha"
    ],
    "wof:lang_x_spoken":[
        "tha"
    ],
    "wof:name":"Bhormi",
    "wof:placetype":"locality"
},
  "geometry": {"coordinates":[101.48356,6.37092],"type":"Point"}
}