{
  "type": "Feature",
  "properties": {
    "gn:admin1_code":"37",
    "gn:asciiname":"Ban Khao Song Klong",
    "gn:country_code":"TH",
    "gn:dem":44,
    "gn:feature_class":"P",
    "gn:feature_code":"PPL",
    "gn:name":"Ban Khao Song Klong",
    "gn:population":0,
    "gn:timezone":"Asia/Bangkok",
    "iso:country":"TH",
    "name:tha_x_preferred":[
        "\u0e1a\u0e49\u0e32\u0e19\u0e40\u0e02\u0e32\u0e2a\u0e48\u0e2d\u0e07\u0e01\u0e25\u0e49\u0e2d\u0e07"
    ],
    "wof:name":"Ban Khao Song Klong",
    "wof:placetype":"locality"
},
  "geometry": {"coordinates":[101.12833000000001,14.38442],"type":"Point"}
}