{
  "type": "Feature",
  "properties": {
    "gn:admin1_code":"52.0",
    "gn:asciiname":"Ban Nong Krachoi",
    "gn:country_code":"TH",
    "gn:dem":12,
    "gn:feature_class":"P",
    "gn:feature_code":"PPL",
    "gn:name":"Ban Nong Krachoi",
    "gn:population":0,
    "gn:timezone":"Asia/Bangkok",
    "iso:country":"TH",
    "name:tha_x_preferred":[
        "\u0e1a\u0e49\u0e32\u0e19\u0e2b\u0e19\u0e2d\u0e07\u0e01\u0e23\u0e30\u0e08\u0e2d\u0e22"
    ],
    "name:und_x_variant":[
        "Ban Nong Kachoi"
    ],
    "wof:name":"Ban Nong Krachoi",
    "wof:placetype":"locality"
},
  "geometry": {"coordinates":[99.92144,13.78144],"type":"Point"}
}