{
  "type": "Feature",
  "properties": {
    "gn:admin1_code":"79.0",
    "gn:asciiname":"Ban Phithak Prathum Mueang",
    "gn:country_code":"TH",
    "gn:dem":226,
    "gn:feature_class":"P",
    "gn:feature_code":"PPL",
    "gn:name":"Ban Phithak Prathum Mueang",
    "gn:population":0,
    "gn:timezone":"Asia/Bangkok",
    "iso:country":"TH",
    "name:tha_x_preferred":[
        "\u0e1a\u0e49\u0e32\u0e19\u0e1e\u0e34\u0e17\u0e31\u0e01\u0e29\u0e4c\u0e1b\u0e23\u0e30\u0e17\u0e38\u0e21\u0e40\u0e21\u0e37\u0e2d\u0e07"
    ],
    "wof:name":"Ban Phithak Prathum Mueang",
    "wof:placetype":"locality"
},
  "geometry": {"coordinates":[102.45377999999999,17.21358],"type":"Point"}
}