{
  "type": "Feature",
  "properties": {
    "gn:admin1_code":"29",
    "gn:asciiname":"Ban Pok Po",
    "gn:country_code":"TH",
    "gn:dem":158,
    "gn:feature_class":"P",
    "gn:feature_code":"PPL",
    "gn:name":"Ban Pok Po",
    "gn:population":0,
    "gn:timezone":"Asia/Bangkok",
    "iso:country":"TH",
    "name:tha_x_preferred":[
        "\u0e1a\u0e49\u0e32\u0e19\u0e1b\u0e01\u0e40\u0e1b\u0e32\u0e30"
    ],
    "wof:name":"Ban Pok Po",
    "wof:placetype":"locality"
},
  "geometry": {"coordinates":[103.41844,14.80808],"type":"Point"}
}