{
  "type": "Feature",
  "properties": {
    "gn:admin1_code":"51.0",
    "gn:asciiname":"Ban Don Buppharam",
    "gn:country_code":"TH",
    "gn:dem":12,
    "gn:feature_class":"P",
    "gn:feature_code":"PPL",
    "gn:name":"Ban Don Buppharam",
    "gn:population":0,
    "gn:timezone":"Asia/Bangkok",
    "iso:country":"TH",
    "name:tha_x_preferred":[
        "\u0e1a\u0e49\u0e32\u0e19\u0e14\u0e2d\u0e19\u0e1a\u0e38\u0e1b\u0e1c\u0e32\u0e23\u0e32\u0e21"
    ],
    "wof:name":"Ban Don Buppharam",
    "wof:placetype":"locality"
},
  "geometry": {"coordinates":[100.1245,14.63992],"type":"Point"}
}