{
  "type": "Feature",
  "properties": {
    "gn:admin1_code":"5.0",
    "gn:asciiname":"Ban Wang Sakaeng",
    "gn:country_code":"TH",
    "gn:dem":284,
    "gn:feature_class":"P",
    "gn:feature_code":"PPL",
    "gn:name":"Ban Wang Sakaeng",
    "gn:population":0,
    "gn:timezone":"Asia/Bangkok",
    "iso:country":"TH",
    "name:tha_x_preferred":[
        "\u0e1a\u0e49\u0e32\u0e19\u0e27\u0e31\u0e07\u0e2a\u0e30\u0e41\u0e01\u0e07"
    ],
    "name:und_x_variant":[
        "Ban Wang Takhaeng",
        "Ban Wang Sakhaeng",
        "Ban Wang Sakaeng"
    ],
    "wof:lang_x_official":[
        "tha"
    ],
    "wof:lang_x_spoken":[
        "tha"
    ],
    "wof:name":"Ban Wang Sakaeng",
    "wof:placetype":"locality"
},
  "geometry": {"coordinates":[98.70171999999999,18.42469],"type":"Point"}
}