{
  "type": "Feature",
  "properties": {
    "gn:admin1_code":"29",
    "gn:asciiname":"Ban Non Thua",
    "gn:country_code":"TH",
    "gn:dem":127,
    "gn:feature_class":"P",
    "gn:feature_code":"PPL",
    "gn:name":"Ban Non Thua",
    "gn:population":0,
    "gn:timezone":"Asia/Bangkok",
    "iso:country":"TH",
    "name:tha_x_preferred":[
        "\u0e1a\u0e49\u0e32\u0e19\u0e42\u0e19\u0e19\u0e16\u0e31\u0e48\u0e27"
    ],
    "wof:name":"Ban Non Thua",
    "wof:placetype":"locality"
},
  "geometry": {"coordinates":[103.78842,15.42772],"type":"Point"}
}