{
  "type": "Feature",
  "properties": {
    "gn:admin1_code":"75.0",
    "gn:asciiname":"Ban Rai Nuea",
    "gn:country_code":"TH",
    "gn:dem":120,
    "gn:feature_class":"P",
    "gn:feature_code":"PPL",
    "gn:name":"Ban Rai Nuea",
    "gn:population":0,
    "gn:timezone":"Asia/Bangkok",
    "iso:country":"TH",
    "name:tha_x_preferred":[
        "\u0e1a\u0e49\u0e32\u0e19\u0e44\u0e23\u0e48\u0e40\u0e2b\u0e19\u0e37\u0e2d"
    ],
    "name:und_x_variant":[
        "Ban Rai Nua"
    ],
    "wof:name":"Ban Rai Nuea",
    "wof:placetype":"locality"
},
  "geometry": {"coordinates":[105.13497,15.16881],"type":"Point"}
}