{
  "type": "Feature",
  "properties": {
    "gn:admin1_code":"73.0",
    "gn:asciiname":"Ban Nong Lat Khwai",
    "gn:country_code":"TH",
    "gn:dem":151,
    "gn:feature_class":"P",
    "gn:feature_code":"PPL",
    "gn:name":"Ban Nong Lat Khwai",
    "gn:population":0,
    "gn:timezone":"Asia/Bangkok",
    "iso:country":"TH",
    "name:tha_x_preferred":[
        "Ban Nong Lat Khwai"
    ],
    "name:tha_x_variant":[
        "\u0e1a\u0e49\u0e32\u0e19\u0e2b\u0e19\u0e2d\u0e07\u0e25\u0e32\u0e14\u0e04\u0e27\u0e32\u0e22"
    ],
    "wof:name":"Ban Nong Lat Khwai",
    "wof:placetype":"locality"
},
  "geometry": {"coordinates":[104.70963999999999,17.05083],"type":"Point"}
}