{
  "type": "Feature",
  "properties": {
    "gn:admin1_code":"41.0",
    "gn:asciiname":"Ban Tum Tha",
    "gn:country_code":"TH",
    "gn:dem":399,
    "gn:feature_class":"P",
    "gn:feature_code":"PPL",
    "gn:name":"Ban Tum Tha",
    "gn:population":0,
    "gn:timezone":"Asia/Bangkok",
    "iso:country":"TH",
    "name:tha_x_preferred":[
        "\u0e1a\u0e49\u0e32\u0e19\u0e15\u0e38\u0e49\u0e21\u0e17\u0e48\u0e32"
    ],
    "name:und_x_variant":[
        "Ban Tum"
    ],
    "wof:name":"Ban Tum Tha",
    "wof:placetype":"locality"
},
  "geometry": {"coordinates":[99.82789,19.24772],"type":"Point"}
}