{
  "type": "Feature",
  "properties": {
    "gn:admin1_code":"56.0",
    "gn:asciiname":"Ban Tha Yai",
    "gn:country_code":"TH",
    "gn:dem":6,
    "gn:feature_class":"P",
    "gn:feature_code":"PPL",
    "gn:name":"Ban Tha Yai",
    "gn:population":0,
    "gn:timezone":"Asia/Bangkok",
    "iso:country":"TH",
    "name:tha_x_preferred":[
        "\u0e1a\u0e49\u0e32\u0e19\u0e17\u0e48\u0e32\u0e43\u0e2b\u0e0d\u0e48"
    ],
    "wof:name":"Ban Tha Yai",
    "wof:placetype":"locality"
},
  "geometry": {"coordinates":[100.00194,13.12794],"type":"Point"}
}