{
  "type": "Feature",
  "properties": {
    "gn:admin1_code":"23.0",
    "gn:asciiname":"Ban Kham Hi",
    "gn:country_code":"TH",
    "gn:dem":194,
    "gn:feature_class":"P",
    "gn:feature_code":"PPL",
    "gn:name":"Ban Kham Hi",
    "gn:population":0,
    "gn:timezone":"Asia/Bangkok",
    "iso:country":"TH",
    "name:tha_x_preferred":[
        "\u0e1a\u0e49\u0e32\u0e19\u0e04\u0e33\u0e2e\u0e35"
    ],
    "wof:name":"Ban Kham Hi",
    "wof:placetype":"locality"
},
  "geometry": {"coordinates":[103.49827999999999,16.61092],"type":"Point"}
}