{
  "type": "Feature",
  "properties": {
    "gn:admin1_code":"29",
    "gn:asciiname":"Ban Non Ta Un",
    "gn:country_code":"TH",
    "gn:dem":134,
    "gn:feature_class":"P",
    "gn:feature_code":"PPL",
    "gn:name":"Ban Non Ta Un",
    "gn:population":0,
    "gn:timezone":"Asia/Bangkok",
    "iso:country":"TH",
    "name:tha_x_preferred":[
        "\u0e1a\u0e49\u0e32\u0e19\u0e42\u0e19\u0e19\u0e15\u0e32\u0e2d\u0e38\u0e48\u0e19"
    ],
    "wof:name":"Ban Non Ta Un",
    "wof:placetype":"locality"
},
  "geometry": {"coordinates":[103.56919000000001,15.32608],"type":"Point"}
}