{
  "type": "Feature",
  "properties": {
    "gn:admin1_code":"27",
    "gn:asciiname":"Ban Po Hu",
    "gn:country_code":"TH",
    "gn:dem":485,
    "gn:feature_class":"P",
    "gn:feature_code":"PPL",
    "gn:name":"Ban Po Hu",
    "gn:population":0,
    "gn:timezone":"Asia/Bangkok",
    "iso:country":"TH",
    "name:tha_x_preferred":[
        "\u0e1a\u0e49\u0e32\u0e19\u0e1b\u0e2d\u0e2b\u0e39"
    ],
    "wof:name":"Ban Po Hu",
    "wof:placetype":"locality"
},
  "geometry": {"coordinates":[101.56053,14.48944],"type":"Point"}
}