{
  "type": "Feature",
  "properties": {
    "gn:admin1_code":"22",
    "gn:asciiname":"Ban Non Pho Sai",
    "gn:country_code":"TH",
    "gn:dem":200,
    "gn:feature_class":"P",
    "gn:feature_code":"PPL",
    "gn:name":"Ban Non Pho Sai",
    "gn:population":0,
    "gn:timezone":"Asia/Bangkok",
    "iso:country":"TH",
    "name:tha_x_preferred":[
        "\u0e1a\u0e49\u0e32\u0e19\u0e42\u0e19\u0e19\u0e42\u0e1e\u0e18\u0e34\u0e4c\u0e44\u0e17\u0e23"
    ],
    "wof:name":"Ban Non Pho Sai",
    "wof:placetype":"locality"
},
  "geometry": {"coordinates":[102.36772000000001,16.50381],"type":"Point"}
}