{
  "type": "Feature",
  "properties": {
    "gn:admin1_code":"60.0",
    "gn:asciiname":"Ban Din Kong",
    "gn:country_code":"TH",
    "gn:dem":13,
    "gn:feature_class":"P",
    "gn:feature_code":"PPL",
    "gn:name":"Ban Din Kong",
    "gn:population":0,
    "gn:timezone":"Asia/Bangkok",
    "iso:country":"TH",
    "name:tha_x_preferred":[
        "\u0e1a\u0e49\u0e32\u0e19\u0e14\u0e34\u0e19\u0e01\u0e49\u0e2d\u0e07"
    ],
    "wof:name":"Ban Din Kong",
    "wof:placetype":"locality"
},
  "geometry": {"coordinates":[99.19861,9.50869],"type":"Point"}
}