{
  "type": "Feature",
  "properties": {
    "gn:admin1_code":"50.0",
    "gn:asciiname":"Ban Rang Krachiao",
    "gn:country_code":"TH",
    "gn:dem":58,
    "gn:feature_class":"P",
    "gn:feature_code":"PPL",
    "gn:name":"Ban Rang Krachiao",
    "gn:population":0,
    "gn:timezone":"Asia/Bangkok",
    "iso:country":"TH",
    "name:tha_x_preferred":[
        "\u0e1a\u0e49\u0e32\u0e19\u0e23\u0e32\u0e07\u0e01\u0e23\u0e30\u0e40\u0e08\u0e35\u0e22\u0e27"
    ],
    "name:und_x_variant":[
        "Ban Rang Kachieo"
    ],
    "wof:name":"Ban Rang Krachiao",
    "wof:placetype":"locality"
},
  "geometry": {"coordinates":[99.66664,13.84347],"type":"Point"}
}