{
  "type": "Feature",
  "properties": {
    "gn:admin1_code":"76.0",
    "gn:asciiname":"Ban Kham Kung",
    "gn:country_code":"TH",
    "gn:dem":214,
    "gn:feature_class":"P",
    "gn:feature_code":"PPL",
    "gn:name":"Ban Kham Kung",
    "gn:population":0,
    "gn:timezone":"Asia/Bangkok",
    "iso:country":"TH",
    "name:tha_x_preferred":[
        "\u0e1a\u0e49\u0e32\u0e19\u0e04\u0e33\u0e01\u0e38\u0e07"
    ],
    "name:und_x_variant":[
        "\u0e1a\u0e49\u0e32\u0e19\u0e04\u0e33\u0e01\u0e38\u0e07"
    ],
    "wof:name":"Ban Kham Kung",
    "wof:placetype":"locality"
},
  "geometry": {"coordinates":[103.25091999999999,17.08814],"type":"Point"}
}