{
  "type": "Feature",
  "properties": {
    "gn:admin1_code":"53.0",
    "gn:asciiname":"Ban Don Tao It",
    "gn:country_code":"TH",
    "gn:dem":8,
    "gn:feature_class":"P",
    "gn:feature_code":"PPL",
    "gn:name":"Ban Don Tao It",
    "gn:population":0,
    "gn:timezone":"Asia/Bangkok",
    "iso:country":"TH",
    "name:tha_x_preferred":[
        "Ban Don Tao It"
    ],
    "name:tha_x_variant":[
        "\u0e1a\u0e49\u0e32\u0e19\u0e14\u0e2d\u0e19\u0e40\u0e15\u0e32\u0e2d\u0e34\u0e10"
    ],
    "name:und_x_variant":[
        "Ban Tao It (1)"
    ],
    "wof:name":"Ban Don Tao It",
    "wof:placetype":"locality"
},
  "geometry": {"coordinates":[100.00042999999999,14.04276],"type":"Point"}
}