{
  "type": "Feature",
  "properties": {
    "gn:admin1_code":"4.0",
    "gn:asciiname":"Ban Khueng Tai",
    "gn:country_code":"TH",
    "gn:dem":199,
    "gn:feature_class":"P",
    "gn:feature_code":"PPL",
    "gn:name":"Ban Khueng Tai",
    "gn:population":0,
    "gn:timezone":"Asia/Bangkok",
    "iso:country":"TH",
    "name:tha_x_preferred":[
        "\u0e1a\u0e49\u0e32\u0e19\u0e02\u0e36\u0e48\u0e07\u0e43\u0e15\u0e49"
    ],
    "wof:name":"Ban Khueng Tai",
    "wof:placetype":"locality"
},
  "geometry": {"coordinates":[100.78408,18.54847],"type":"Point"}
}