{
  "type": "Feature",
  "properties": {
    "gn:admin1_code":"64.0",
    "gn:asciiname":"Ban Kong Khong",
    "gn:country_code":"TH",
    "gn:dem":4,
    "gn:feature_class":"P",
    "gn:feature_code":"PPL",
    "gn:name":"Ban Kong Khong",
    "gn:population":0,
    "gn:timezone":"Asia/Bangkok",
    "iso:country":"TH",
    "name:tha_x_preferred":[
        "\u0e1a\u0e49\u0e32\u0e19\u0e42\u0e01\u0e49\u0e07\u0e42\u0e04\u0e49\u0e07"
    ],
    "wof:name":"Ban Kong Khong",
    "wof:placetype":"locality"
},
  "geometry": {"coordinates":[100.21796999999999,8.38167],"type":"Point"}
}