{
  "type": "Feature",
  "properties": {
    "gn:admin1_code":"75.0",
    "gn:asciiname":"Ban Nong Khu",
    "gn:country_code":"TH",
    "gn:dem":180,
    "gn:feature_class":"P",
    "gn:feature_code":"PPL",
    "gn:name":"Ban Nong Khu",
    "gn:population":0,
    "gn:timezone":"Asia/Bangkok",
    "iso:country":"TH",
    "name:tha_x_preferred":[
        "\u0e1a\u0e49\u0e32\u0e19\u0e2b\u0e19\u0e2d\u0e07\u0e04\u0e39"
    ],
    "name:und_x_variant":[
        "Ban Ti Kho",
        "Ban Nong Khu"
    ],
    "wof:name":"Ban Nong Khu",
    "wof:placetype":"locality"
},
  "geometry": {"coordinates":[105.07844,15.8505],"type":"Point"}
}