{
  "type": "Feature",
  "properties": {
    "gn:admin1_code":"65.0",
    "gn:asciiname":"Ban Saphan Dan",
    "gn:country_code":"TH",
    "gn:dem":22,
    "gn:feature_class":"P",
    "gn:feature_code":"PPL",
    "gn:name":"Ban Saphan Dan",
    "gn:population":0,
    "gn:timezone":"Asia/Bangkok",
    "iso:country":"TH",
    "name:tha_x_preferred":[
        "\u0e1a\u0e49\u0e32\u0e19\u0e2a\u0e30\u0e1e\u0e32\u0e19\u0e14\u0e48\u0e32\u0e19"
    ],
    "name:und_x_variant":[
        "Ban Phan Dan",
        "Ban Saphan Dan (1)",
        "Ban Saphan Dan"
    ],
    "wof:lang_x_official":[
        "tha"
    ],
    "wof:lang_x_spoken":[
        "tha"
    ],
    "wof:name":"Ban Saphan Dan",
    "wof:placetype":"locality"
},
  "geometry": {"coordinates":[99.68781,7.41422],"type":"Point"}
}