{
  "type": "Feature",
  "properties": {
    "gn:admin1_code":"63.0",
    "gn:asciiname":"Ban Khuan",
    "gn:country_code":"TH",
    "gn:dem":43,
    "gn:feature_class":"P",
    "gn:feature_code":"PPL",
    "gn:name":"Ban Khuan",
    "gn:population":0,
    "gn:timezone":"Asia/Bangkok",
    "iso:country":"TH",
    "name:tha_x_preferred":[
        "\u0e1a\u0e49\u0e32\u0e19\u0e04\u0e27\u0e19"
    ],
    "wof:name":"Ban Khuan",
    "wof:placetype":"locality"
},
  "geometry": {"coordinates":[99.07719,8.3555],"type":"Point"}
}