{
  "type": "Feature",
  "properties": {
    "gn:admin1_code":"22.0",
    "gn:asciiname":"Ban Nong Saeng",
    "gn:country_code":"TH",
    "gn:dem":193,
    "gn:feature_class":"P",
    "gn:feature_code":"PPL",
    "gn:name":"Ban Nong Saeng",
    "gn:population":0,
    "gn:timezone":"Asia/Bangkok",
    "iso:country":"TH",
    "name:tha_x_preferred":[
        "\u0e1a\u0e49\u0e32\u0e19\u0e2b\u0e19\u0e2d\u0e07\u0e41\u0e2a\u0e07"
    ],
    "name:und_x_variant":[
        "Non Muang",
        "Ban Non Muang",
        "Ban Nong Saeng"
    ],
    "wof:name":"Ban Nong Saeng",
    "wof:placetype":"locality"
},
  "geometry": {"coordinates":[102.56135999999999,16.51608],"type":"Point"}
}