{
  "type": "Feature",
  "properties": {
    "gn:admin1_code":"28",
    "gn:asciiname":"Ban Nong Nam Khun",
    "gn:country_code":"TH",
    "gn:dem":147,
    "gn:feature_class":"P",
    "gn:feature_code":"PPL",
    "gn:name":"Ban Nong Nam Khun",
    "gn:population":0,
    "gn:timezone":"Asia/Bangkok",
    "iso:country":"TH",
    "name:tha_x_preferred":[
        "\u0e1a\u0e49\u0e32\u0e19\u0e2b\u0e19\u0e2d\u0e07\u0e19\u0e49\u0e33\u0e02\u0e38\u0e48\u0e19"
    ],
    "wof:name":"Ban Nong Nam Khun",
    "wof:placetype":"locality"
},
  "geometry": {"coordinates":[103.33739,14.83825],"type":"Point"}
}