{
  "type": "Feature",
  "properties": {
    "gn:admin1_code":"1.0",
    "gn:asciiname":"Ban Huai Ku Pa",
    "gn:country_code":"TH",
    "gn:dem":330,
    "gn:feature_class":"P",
    "gn:feature_code":"PPL",
    "gn:name":"Ban Huai Ku Pa",
    "gn:population":0,
    "gn:timezone":"Asia/Bangkok",
    "iso:country":"TH",
    "name:tha_x_preferred":[
        "\u0e1a\u0e49\u0e32\u0e19\u0e2b\u0e49\u0e27\u0e22\u0e01\u0e39\u0e1b\u0e49\u0e30"
    ],
    "name:und_x_variant":[
        "Ban Kai Pa",
        "Ban Huai Ku Pa"
    ],
    "wof:lang_x_official":[
        "tha"
    ],
    "wof:lang_x_spoken":[
        "tha"
    ],
    "wof:name":"Ban Huai Ku Pa",
    "wof:placetype":"locality"
},
  "geometry": {"coordinates":[97.89561,18.53931],"type":"Point"}
}