{
  "type": "Feature",
  "properties": {
    "gn:admin1_code":"28.0",
    "gn:asciiname":"Ban Krasang",
    "gn:country_code":"TH",
    "gn:dem":202,
    "gn:feature_class":"P",
    "gn:feature_code":"PPL",
    "gn:name":"Ban Krasang",
    "gn:population":0,
    "gn:timezone":"Asia/Bangkok",
    "iso:country":"TH",
    "name:tha_x_preferred":[
        "\u0e1a\u0e49\u0e32\u0e19\u0e01\u0e23\u0e30\u0e2a\u0e31\u0e07"
    ],
    "name:und_x_variant":[
        "Kasang",
        "Ban Krasang",
        "Ban Kasang"
    ],
    "wof:name":"Ban Krasang",
    "wof:placetype":"locality"
},
  "geometry": {"coordinates":[102.51561,14.72603],"type":"Point"}
}