{
  "type": "Feature",
  "properties": {
    "gn:admin1_code":"50.0",
    "gn:asciiname":"Ban Huai Mae Rawang",
    "gn:country_code":"TH",
    "gn:dem":328,
    "gn:feature_class":"P",
    "gn:feature_code":"PPL",
    "gn:name":"Ban Huai Mae Rawang",
    "gn:population":0,
    "gn:timezone":"Asia/Bangkok",
    "iso:country":"TH",
    "name:tha_x_preferred":[
        "\u0e1a\u0e49\u0e32\u0e19\u0e2b\u0e49\u0e27\u0e22\u0e41\u0e21\u0e48\u0e23\u0e30\u0e2b\u0e27\u0e48\u0e32\u0e07"
    ],
    "wof:lang_x_official":[
        "tha"
    ],
    "wof:lang_x_spoken":[
        "tha"
    ],
    "wof:name":"Ban Huai Mae Rawang",
    "wof:placetype":"locality"
},
  "geometry": {"coordinates":[99.32025,14.80303],"type":"Point"}
}