{
  "type": "Feature",
  "properties": {
    "gn:admin1_code":"29",
    "gn:asciiname":"Ban Pang Meng",
    "gn:country_code":"TH",
    "gn:dem":174,
    "gn:feature_class":"P",
    "gn:feature_code":"PPL",
    "gn:name":"Ban Pang Meng",
    "gn:population":0,
    "gn:timezone":"Asia/Bangkok",
    "iso:country":"TH",
    "name:tha_x_preferred":[
        "\u0e1a\u0e49\u0e32\u0e19\u0e1b\u0e31\u0e07\u0e40\u0e21\u0e47\u0e07"
    ],
    "wof:name":"Ban Pang Meng",
    "wof:placetype":"locality"
},
  "geometry": {"coordinates":[103.38800000000001,14.61442],"type":"Point"}
}