{
  "type": "Feature",
  "properties": {
    "gn:admin1_code":"69.0",
    "gn:asciiname":"Ban Tanyong Li Mo",
    "gn:country_code":"TH",
    "gn:dem":9,
    "gn:feature_class":"P",
    "gn:feature_code":"PPL",
    "gn:name":"Ban Tanyong Li Mo",
    "gn:population":0,
    "gn:timezone":"Asia/Bangkok",
    "iso:country":"TH",
    "name:tha_x_preferred":[
        "\u0e1a\u0e49\u0e32\u0e19\u0e15\u0e31\u0e19\u0e2b\u0e22\u0e07\u0e25\u0e34\u0e21\u0e2d"
    ],
    "wof:name":"Ban Tanyong Li Mo",
    "wof:placetype":"locality"
},
  "geometry": {"coordinates":[101.30007999999999,6.83847],"type":"Point"}
}