{
  "type": "Feature",
  "properties": {
    "gn:admin1_code":"63.0",
    "gn:asciiname":"Ban Huai Pritsana",
    "gn:country_code":"TH",
    "gn:dem":75,
    "gn:feature_class":"P",
    "gn:feature_code":"PPL",
    "gn:name":"Ban Huai Pritsana",
    "gn:population":0,
    "gn:timezone":"Asia/Bangkok",
    "iso:country":"TH",
    "name:tha_x_preferred":[
        "\u0e1a\u0e49\u0e32\u0e19\u0e2b\u0e49\u0e27\u0e22\u0e1b\u0e23\u0e34\u0e28\u0e19\u0e32"
    ],
    "name:und_x_variant":[
        "Ban Pritsana"
    ],
    "wof:lang_x_official":[
        "tha"
    ],
    "wof:lang_x_spoken":[
        "tha"
    ],
    "wof:name":"Ban Huai Pritsana",
    "wof:placetype":"locality"
},
  "geometry": {"coordinates":[98.75381,8.44858],"type":"Point"}
}