{
  "type": "Feature",
  "properties": {
    "gn:admin1_code":"50.0",
    "gn:asciiname":"Ban Ton Samrong",
    "gn:country_code":"TH",
    "gn:dem":33,
    "gn:feature_class":"P",
    "gn:feature_code":"PPL",
    "gn:name":"Ban Ton Samrong",
    "gn:population":0,
    "gn:timezone":"Asia/Bangkok",
    "iso:country":"TH",
    "name:tha_x_preferred":[
        "\u0e1a\u0e49\u0e32\u0e19\u0e15\u0e49\u0e19\u0e2a\u0e33\u0e42\u0e23\u0e07"
    ],
    "wof:name":"Ban Ton Samrong",
    "wof:placetype":"locality"
},
  "geometry": {"coordinates":[99.62844,13.95128],"type":"Point"}
}