{
  "type": "Feature",
  "properties": {
    "gn:admin1_code":"6.0",
    "gn:asciiname":"Ban Pa Tan Tai",
    "gn:country_code":"TH",
    "gn:dem":236,
    "gn:feature_class":"P",
    "gn:feature_code":"PPL",
    "gn:name":"Ban Pa Tan Tai",
    "gn:population":0,
    "gn:timezone":"Asia/Bangkok",
    "iso:country":"TH",
    "name:tha_x_preferred":[
        "\u0e1a\u0e49\u0e32\u0e19\u0e1b\u0e48\u0e32\u0e15\u0e31\u0e19\u0e43\u0e15\u0e49"
    ],
    "wof:name":"Ban Pa Tan Tai",
    "wof:placetype":"locality"
},
  "geometry": {"coordinates":[99.47266999999999,18.12969],"type":"Point"}
}