{
  "type": "Feature",
  "properties": {
    "gn:admin1_code":"29",
    "gn:asciiname":"Ban Kalan",
    "gn:country_code":"TH",
    "gn:dem":144,
    "gn:feature_class":"P",
    "gn:feature_code":"PPL",
    "gn:name":"Ban Kalan",
    "gn:population":0,
    "gn:timezone":"Asia/Bangkok",
    "iso:country":"TH",
    "name:tha_x_preferred":[
        "\u0e1a\u0e49\u0e32\u0e19\u0e01\u0e30\u0e25\u0e31\u0e19"
    ],
    "wof:name":"Ban Kalan",
    "wof:placetype":"locality"
},
  "geometry": {"coordinates":[103.78106,14.92328],"type":"Point"}
}