{
  "type": "Feature",
  "properties": {
    "gn:admin1_code":"0.0",
    "gn:asciiname":"Ban Naengmut",
    "gn:country_code":"TH",
    "gn:dem":286,
    "gn:feature_class":"P",
    "gn:feature_code":"PPL",
    "gn:name":"Ban Naengmut",
    "gn:population":0,
    "gn:timezone":"Asia/Bangkok",
    "iso:country":"TH",
    "wof:name":"Ban Naengmut",
    "wof:placetype":"locality"
},
  "geometry": {"coordinates":[103.41667,14.36667],"type":"Point"}
}