{
  "type": "Feature",
  "properties": {
    "gn:admin1_code":"64.0",
    "gn:asciiname":"Ban Wa Yo",
    "gn:country_code":"TH",
    "gn:dem":43,
    "gn:feature_class":"P",
    "gn:feature_code":"PPL",
    "gn:name":"Ban Wa Yo",
    "gn:population":0,
    "gn:timezone":"Asia/Bangkok",
    "iso:country":"TH",
    "name:tha_x_preferred":[
        "\u0e1a\u0e49\u0e32\u0e19\u0e27\u0e32\u0e42\u0e22"
    ],
    "wof:name":"Ban Wa Yo",
    "wof:placetype":"locality"
},
  "geometry": {"coordinates":[99.80571999999999,8.85122],"type":"Point"}
}