{
  "type": "Feature",
  "properties": {
    "gn:admin1_code":"67.0",
    "gn:asciiname":"Ban Ma Nang",
    "gn:country_code":"TH",
    "gn:dem":36,
    "gn:feature_class":"P",
    "gn:feature_code":"PPL",
    "gn:name":"Ban Ma Nang",
    "gn:population":0,
    "gn:timezone":"Asia/Bangkok",
    "iso:country":"TH",
    "name:tha_x_preferred":[
        "Ban Ma Nang"
    ],
    "name:tha_x_variant":[
        "\u0e1a\u0e49\u0e32\u0e19\u0e21\u0e30\u0e19\u0e31\u0e07"
    ],
    "wof:name":"Ban Ma Nang",
    "wof:placetype":"locality"
},
  "geometry": {"coordinates":[99.91242,7.06897],"type":"Point"}
}