{
  "type": "Feature",
  "properties": {
    "gn:admin1_code":"57.0",
    "gn:asciiname":"Ban Samrong Nai",
    "gn:country_code":"TH",
    "gn:dem":10,
    "gn:feature_class":"P",
    "gn:feature_code":"PPL",
    "gn:name":"Ban Samrong Nai",
    "gn:population":0,
    "gn:timezone":"Asia/Bangkok",
    "iso:country":"TH",
    "name:tha_x_preferred":[
        "\u0e1a\u0e49\u0e32\u0e19\u0e2a\u0e33\u0e42\u0e2b\u0e23\u0e07\u0e43\u0e19"
    ],
    "name:und_x_variant":[
        "Samrong",
        "Ban Samrong (1)",
        "Ban Samrong Nai"
    ],
    "wof:lang_x_official":[
        "tha"
    ],
    "wof:lang_x_spoken":[
        "tha"
    ],
    "wof:name":"Ban Samrong Nai",
    "wof:placetype":"locality"
},
  "geometry": {"coordinates":[99.84936,12.12556],"type":"Point"}
}