{
  "type": "Feature",
  "properties": {
    "gn:admin1_code":"80",
    "gn:asciiname":"Ban Wang Burapha",
    "gn:country_code":"TH",
    "gn:dem":120,
    "gn:feature_class":"P",
    "gn:feature_code":"PPL",
    "gn:name":"Ban Wang Burapha",
    "gn:population":0,
    "gn:timezone":"Asia/Bangkok",
    "iso:country":"TH",
    "name:tha_x_preferred":[
        "\u0e1a\u0e49\u0e32\u0e19\u0e27\u0e31\u0e07\u0e1a\u0e39\u0e23\u0e1e\u0e32"
    ],
    "wof:name":"Ban Wang Burapha",
    "wof:placetype":"locality"
},
  "geometry": {"coordinates":[102.19264,13.36028],"type":"Point"}
}