{
  "type": "Feature",
  "properties": {
    "gn:admin1_code":"20.0",
    "gn:asciiname":"Ban Noi Dong I-doi",
    "gn:country_code":"TH",
    "gn:dem":166,
    "gn:feature_class":"P",
    "gn:feature_code":"PPL",
    "gn:name":"Ban Noi Dong I-doi",
    "gn:population":0,
    "gn:timezone":"Asia/Bangkok",
    "iso:country":"TH",
    "name:tha_x_preferred":[
        "\u0e1a\u0e49\u0e32\u0e19\u0e19\u0e49\u0e2d\u0e22\u0e14\u0e07\u0e2d\u0e35\u0e14\u0e48\u0e2d\u0e22"
    ],
    "wof:name":"Ban Noi Dong I-doi",
    "wof:placetype":"locality"
},
  "geometry": {"coordinates":[103.82033,17.72514],"type":"Point"}
}