{
  "type": "Feature",
  "properties": {
    "gn:admin1_code":"80",
    "gn:asciiname":"Ban Pak Dong",
    "gn:country_code":"TH",
    "gn:dem":83,
    "gn:feature_class":"P",
    "gn:feature_code":"PPL",
    "gn:name":"Ban Pak Dong",
    "gn:population":0,
    "gn:timezone":"Asia/Bangkok",
    "iso:country":"TH",
    "name:tha_x_preferred":[
        "\u0e1a\u0e49\u0e32\u0e19\u0e1b\u0e32\u0e01\u0e14\u0e07"
    ],
    "wof:name":"Ban Pak Dong",
    "wof:placetype":"locality"
},
  "geometry": {"coordinates":[101.94374999999999,13.57458],"type":"Point"}
}