{
  "type": "Feature",
  "properties": {
    "gn:admin1_code":"51.0",
    "gn:asciiname":"Ban Rang Hang Ma",
    "gn:country_code":"TH",
    "gn:dem":10,
    "gn:feature_class":"P",
    "gn:feature_code":"PPL",
    "gn:name":"Ban Rang Hang Ma",
    "gn:population":0,
    "gn:timezone":"Asia/Bangkok",
    "iso:country":"TH",
    "name:tha_x_preferred":[
        "\u0e1a\u0e49\u0e32\u0e19\u0e23\u0e32\u0e07\u0e2b\u0e32\u0e07\u0e21\u0e49\u0e32"
    ],
    "wof:name":"Ban Rang Hang Ma",
    "wof:placetype":"locality"
},
  "geometry": {"coordinates":[100.20153000000001,14.6305],"type":"Point"}
}