{
  "type": "Feature",
  "properties": {
    "gn:admin1_code":"3.0",
    "gn:asciiname":"Ban Ton Ngao",
    "gn:country_code":"TH",
    "gn:dem":412,
    "gn:feature_class":"P",
    "gn:feature_code":"PPL",
    "gn:name":"Ban Ton Ngao",
    "gn:population":0,
    "gn:timezone":"Asia/Bangkok",
    "iso:country":"TH",
    "name:tha_x_preferred":[
        "\u0e1a\u0e49\u0e32\u0e19\u0e15\u0e49\u0e19\u0e07\u0e49\u0e32\u0e27"
    ],
    "name:und_x_variant":[
        "B\u0101n Ton Ng\u0101u",
        "Ban Ton Ngao"
    ],
    "wof:name":"Ban Ton Ngao",
    "wof:placetype":"locality"
},
  "geometry": {"coordinates":[99.74172,19.80656],"type":"Point"}
}