{
  "type": "Feature",
  "properties": {
    "gn:admin1_code":"56.0",
    "gn:asciiname":"Ban Rai Sathon",
    "gn:country_code":"TH",
    "gn:dem":14,
    "gn:feature_class":"P",
    "gn:feature_code":"PPL",
    "gn:name":"Ban Rai Sathon",
    "gn:population":0,
    "gn:timezone":"Asia/Bangkok",
    "iso:country":"TH",
    "name:tha_x_preferred":[
        "\u0e1a\u0e49\u0e32\u0e19\u0e44\u0e23\u0e48\u0e2a\u0e30\u0e17\u0e49\u0e2d\u0e19"
    ],
    "name:und_x_variant":[
        "Ban Rai Kathon",
        "Ban Rai Sathon"
    ],
    "wof:lang_x_official":[
        "tha"
    ],
    "wof:lang_x_spoken":[
        "tha"
    ],
    "wof:name":"Ban Rai Sathon",
    "wof:placetype":"locality"
},
  "geometry": {"coordinates":[99.91943999999999,13.02247],"type":"Point"}
}