{
  "type": "Feature",
  "properties": {
    "gn:admin1_code":"30.0",
    "gn:asciiname":"Ban Nong Bua Banlang",
    "gn:country_code":"TH",
    "gn:dem":146,
    "gn:feature_class":"P",
    "gn:feature_code":"PPL",
    "gn:name":"Ban Nong Bua Banlang",
    "gn:population":0,
    "gn:timezone":"Asia/Bangkok",
    "iso:country":"TH",
    "name:tha_x_preferred":[
        "\u0e1a\u0e49\u0e32\u0e19\u0e2b\u0e19\u0e2d\u0e07\u0e1a\u0e31\u0e27\u0e1a\u0e31\u0e25\u0e25\u0e31\u0e07\u0e04\u0e4c"
    ],
    "wof:name":"Ban Nong Bua Banlang",
    "wof:placetype":"locality"
},
  "geometry": {"coordinates":[104.11727999999999,14.77836],"type":"Point"}
}