{
  "type": "Feature",
  "properties": {
    "gn:admin1_code":"76.0",
    "gn:asciiname":"Ban Noi Tan Lian",
    "gn:country_code":"TH",
    "gn:dem":243,
    "gn:feature_class":"P",
    "gn:feature_code":"PPL",
    "gn:name":"Ban Noi Tan Lian",
    "gn:population":0,
    "gn:timezone":"Asia/Bangkok",
    "iso:country":"TH",
    "name:tha_x_preferred":[
        "\u0e1a\u0e49\u0e32\u0e19\u0e19\u0e49\u0e2d\u0e22\u0e15\u0e32\u0e25\u0e40\u0e25\u0e35\u0e22\u0e19"
    ],
    "wof:name":"Ban Noi Tan Lian",
    "wof:placetype":"locality"
},
  "geometry": {"coordinates":[102.41742000000001,17.41778],"type":"Point"}
}