{
  "type": "Feature",
  "properties": {
    "gn:admin1_code":"57.0",
    "gn:asciiname":"Ban Nong Pao Pi",
    "gn:country_code":"TH",
    "gn:dem":86,
    "gn:feature_class":"P",
    "gn:feature_code":"PPL",
    "gn:name":"Ban Nong Pao Pi",
    "gn:population":0,
    "gn:timezone":"Asia/Bangkok",
    "iso:country":"TH",
    "name:tha_x_preferred":[
        "\u0e1a\u0e49\u0e32\u0e19\u0e2b\u0e19\u0e2d\u0e07\u0e40\u0e1b\u0e48\u0e32\u0e1b\u0e35\u0e48"
    ],
    "name:und_x_variant":[
        "Ban Nong Ngam"
    ],
    "wof:name":"Ban Nong Pao Pi",
    "wof:placetype":"locality"
},
  "geometry": {"coordinates":[99.78156,12.26067],"type":"Point"}
}