{
  "type": "Feature",
  "properties": {
    "gn:admin1_code":"75.0",
    "gn:asciiname":"Ban Ba Hoi",
    "gn:country_code":"TH",
    "gn:dem":201,
    "gn:feature_class":"P",
    "gn:feature_code":"PPL",
    "gn:name":"Ban Ba Hoi",
    "gn:population":0,
    "gn:timezone":"Asia/Bangkok",
    "iso:country":"TH",
    "name:tha_x_preferred":[
        "\u0e1a\u0e49\u0e32\u0e19\u0e1a\u0e4b\u0e32\u0e2b\u0e2d\u0e22"
    ],
    "wof:name":"Ban Ba Hoi",
    "wof:placetype":"locality"
},
  "geometry": {"coordinates":[105.18294,15.71303],"type":"Point"}
}