{
  "type": "Feature",
  "properties": {
    "gn:admin1_code":"56.0",
    "gn:asciiname":"Ban Bo Kradan",
    "gn:country_code":"TH",
    "gn:dem":10,
    "gn:feature_class":"P",
    "gn:feature_code":"PPL",
    "gn:name":"Ban Bo Kradan",
    "gn:population":0,
    "gn:timezone":"Asia/Bangkok",
    "iso:country":"TH",
    "name:tha_x_preferred":[
        "\u0e1a\u0e49\u0e32\u0e19\u0e1a\u0e48\u0e2d\u0e01\u0e23\u0e30\u0e14\u0e32\u0e19"
    ],
    "name:und_x_variant":[
        "Ban Bo Kadan",
        "Ban Bo Kradan"
    ],
    "wof:name":"Ban Bo Kradan",
    "wof:placetype":"locality"
},
  "geometry": {"coordinates":[99.97386,13.02858],"type":"Point"}
}