{
  "type": "Feature",
  "properties": {
    "gn:admin1_code":"66.0",
    "gn:asciiname":"Ban Khuan Nai Chang",
    "gn:country_code":"TH",
    "gn:dem":40,
    "gn:feature_class":"P",
    "gn:feature_code":"PPL",
    "gn:name":"Ban Khuan Nai Chang",
    "gn:population":0,
    "gn:timezone":"Asia/Bangkok",
    "iso:country":"TH",
    "name:tha_x_preferred":[
        "\u0e1a\u0e49\u0e32\u0e19\u0e04\u0e27\u0e19\u0e19\u0e32\u0e22\u0e0a\u0e48\u0e32\u0e07"
    ],
    "wof:name":"Ban Khuan Nai Chang",
    "wof:placetype":"locality"
},
  "geometry": {"coordinates":[100.05014,7.37103],"type":"Point"}
}