{
  "type": "Feature",
  "properties": {
    "gn:admin1_code":"60.0",
    "gn:asciiname":"Ban Khao Phanom Baek",
    "gn:country_code":"TH",
    "gn:dem":15,
    "gn:feature_class":"P",
    "gn:feature_code":"PPL",
    "gn:name":"Ban Khao Phanom Baek",
    "gn:population":0,
    "gn:timezone":"Asia/Bangkok",
    "iso:country":"TH",
    "name:tha_x_preferred":[
        "\u0e1a\u0e49\u0e32\u0e19\u0e40\u0e02\u0e32\u0e1e\u0e19\u0e21\u0e41\u0e1a\u0e01"
    ],
    "wof:name":"Ban Khao Phanom Baek",
    "wof:placetype":"locality"
},
  "geometry": {"coordinates":[99.17675,9.46983],"type":"Point"}
}