{
  "type": "Feature",
  "properties": {
    "gn:country":"TH",
    "gn:fcode":"PPL",
    "gn:pop":0,
    "iso:country":"TH",
    "name:tha_x_preferred":[
        "\u0e1a\u0e49\u0e32\u0e19\u0e40\u0e0a\u0e35\u0e22\u0e07\u0e43\u0e2b\u0e21\u0e48"
    ],
    "name:unk_x_variant":[
        "Ban Chiang Mai"
    ],
    "qs:name":"Chiang Mai",
    "qs:name_adm0":"Thailand",
    "qs:name_adm1":"Roi Et",
    "qs:photos":106,
    "qs:photos_1k":21,
    "qs:photos_9k":1,
    "qs:photos_9r":3,
    "qs:photos_all":106,
    "qs:photos_sr":3,
    "qs:placetype":"Town",
    "qs:pop_sr":"0",
    "wd:wordcount":4395,
    "wof:name":"Chiang Mai",
    "wof:placetype":"locality",
    "wof:population":0
},
  "geometry": {"coordinates":[103.83333,16.23333],"type":"Point"}
}