{
  "type": "Feature",
  "properties": {
    "gn:admin1_code":"14.0",
    "gn:asciiname":"Ban Nam Duk",
    "gn:country_code":"TH",
    "gn:dem":146,
    "gn:feature_class":"P",
    "gn:feature_code":"PPL",
    "gn:name":"Ban Nam Duk",
    "gn:population":0,
    "gn:timezone":"Asia/Bangkok",
    "iso:country":"TH",
    "name:tha_x_preferred":[
        "\u0e1a\u0e49\u0e32\u0e19\u0e19\u0e49\u0e33\u0e14\u0e38\u0e01"
    ],
    "wof:name":"Ban Nam Duk",
    "wof:placetype":"locality"
},
  "geometry": {"coordinates":[101.24533,16.72244],"type":"Point"}
}