{
  "type": "Feature",
  "properties": {
    "gn:admin1_code":"53.0",
    "gn:asciiname":"Ban Talat Nong Ngulueam",
    "gn:country_code":"TH",
    "gn:dem":13,
    "gn:feature_class":"P",
    "gn:feature_code":"PPL",
    "gn:name":"Ban Talat Nong Ngulueam",
    "gn:population":0,
    "gn:timezone":"Asia/Bangkok",
    "iso:country":"TH",
    "name:tha_x_preferred":[
        "Ban Talat Nong Ngulueam"
    ],
    "name:tha_x_variant":[
        "\u0e1a\u0e49\u0e32\u0e19\u0e15\u0e25\u0e32\u0e14\u0e2b\u0e19\u0e2d\u0e07\u0e07\u0e39\u0e40\u0e2b\u0e25\u0e37\u0e2d\u0e21"
    ],
    "wof:name":"Ban Talat Nong Ngulueam",
    "wof:placetype":"locality"
},
  "geometry": {"coordinates":[99.93019,13.90125],"type":"Point"}
}