{
  "type": "Feature",
  "properties": {
    "gn:admin1_code":"8.0",
    "gn:asciiname":"Ban Pu Ling",
    "gn:country_code":"TH",
    "gn:dem":272,
    "gn:feature_class":"P",
    "gn:feature_code":"PPL",
    "gn:name":"Ban Pu Ling",
    "gn:population":0,
    "gn:timezone":"Asia/Bangkok",
    "iso:country":"TH",
    "name:tha_x_preferred":[
        "Ban Pu Ling"
    ],
    "name:tha_x_variant":[
        "\u0e1a\u0e49\u0e32\u0e19\u0e1b\u0e39\u0e25\u0e34\u0e07"
    ],
    "name:und_x_variant":[
        "Ban Phu Mia"
    ],
    "wof:name":"Ban Pu Ling",
    "wof:placetype":"locality"
},
  "geometry": {"coordinates":[98.54486,17.05197],"type":"Point"}
}