{
  "type": "Feature",
  "properties": {
    "gn:admin1_code":"66.0",
    "gn:asciiname":"Ban Pak Phaniat",
    "gn:country_code":"TH",
    "gn:dem":6,
    "gn:feature_class":"P",
    "gn:feature_code":"PPL",
    "gn:name":"Ban Pak Phaniat",
    "gn:population":0,
    "gn:timezone":"Asia/Bangkok",
    "iso:country":"TH",
    "name:tha_x_preferred":[
        "\u0e1a\u0e49\u0e32\u0e19\u0e1b\u0e32\u0e01\u0e1e\u0e30\u0e40\u0e19\u0e35\u0e22\u0e14"
    ],
    "name:und_x_variant":[
        "Ban Pak Niad",
        "Ban Pak Niat",
        "Ban Pak Phaniat"
    ],
    "wof:name":"Ban Pak Phaniat",
    "wof:placetype":"locality"
},
  "geometry": {"coordinates":[100.17825000000001,7.51178],"type":"Point"}
}