{
  "type": "Feature",
  "properties": {
    "gn:admin1_code":"11.0",
    "gn:asciiname":"Ban Si Kaset",
    "gn:country_code":"TH",
    "gn:dem":151,
    "gn:feature_class":"P",
    "gn:feature_code":"PPL",
    "gn:name":"Ban Si Kaset",
    "gn:population":0,
    "gn:timezone":"Asia/Bangkok",
    "iso:country":"TH",
    "name:tha_x_preferred":[
        "\u0e1a\u0e49\u0e32\u0e19\u0e28\u0e23\u0e35\u0e40\u0e01\u0e29\u0e15\u0e23"
    ],
    "wof:name":"Ban Si Kaset",
    "wof:placetype":"locality"
},
  "geometry": {"coordinates":[99.38128,15.96228],"type":"Point"}
}