{
  "type": "Feature",
  "properties": {
    "gn:admin1_code":"3.0",
    "gn:asciiname":"Ban San Sai Kong Ngam",
    "gn:country_code":"TH",
    "gn:dem":368,
    "gn:feature_class":"P",
    "gn:feature_code":"PPL",
    "gn:name":"Ban San Sai Kong Ngam",
    "gn:population":0,
    "gn:timezone":"Asia/Bangkok",
    "iso:country":"TH",
    "name:tha_x_preferred":[
        "\u0e1a\u0e49\u0e32\u0e19\u0e2a\u0e31\u0e19\u0e17\u0e23\u0e32\u0e22\u0e01\u0e2d\u0e07\u0e07\u0e32\u0e21"
    ],
    "wof:name":"Ban San Sai Kong Ngam",
    "wof:placetype":"locality"
},
  "geometry": {"coordinates":[100.14397,20.22506],"type":"Point"}
}