{
  "type": "Feature",
  "properties": {
    "gn:admin1_code":"52.0",
    "gn:asciiname":"Ban Thai Prachan",
    "gn:country_code":"TH",
    "gn:dem":164,
    "gn:feature_class":"P",
    "gn:feature_code":"PPL",
    "gn:name":"Ban Thai Prachan",
    "gn:population":0,
    "gn:timezone":"Asia/Bangkok",
    "iso:country":"TH",
    "name:tha_x_preferred":[
        "\u0e1a\u0e49\u0e32\u0e19\u0e44\u0e17\u0e22\u0e1b\u0e23\u0e30\u0e08\u0e31\u0e19"
    ],
    "wof:name":"Ban Thai Prachan",
    "wof:placetype":"locality"
},
  "geometry": {"coordinates":[99.56056,13.27711],"type":"Point"}
}