{
  "type": "Feature",
  "properties": {
    "gn:admin1_code":"28.0",
    "gn:asciiname":"Ban Mai Thawon",
    "gn:country_code":"TH",
    "gn:dem":205,
    "gn:feature_class":"P",
    "gn:feature_code":"PPL",
    "gn:name":"Ban Mai Thawon",
    "gn:population":0,
    "gn:timezone":"Asia/Bangkok",
    "iso:country":"TH",
    "name:tha_x_preferred":[
        "\u0e1a\u0e49\u0e32\u0e19\u0e43\u0e2b\u0e21\u0e48\u0e16\u0e32\u0e27\u0e23"
    ],
    "wof:name":"Ban Mai Thawon",
    "wof:placetype":"locality"
},
  "geometry": {"coordinates":[103.04071999999999,14.45275],"type":"Point"}
}