{
  "type": "Feature",
  "properties": {
    "gn:admin1_code":"60.0",
    "gn:asciiname":"Ban Than Ari",
    "gn:country_code":"TH",
    "gn:dem":82,
    "gn:feature_class":"P",
    "gn:feature_code":"PPL",
    "gn:name":"Ban Than Ari",
    "gn:population":0,
    "gn:timezone":"Asia/Bangkok",
    "iso:country":"TH",
    "name:tha_x_preferred":[
        "\u0e1a\u0e49\u0e32\u0e19\u0e18\u0e32\u0e23\u0e2d\u0e32\u0e23\u0e35\u0e22\u0e4c"
    ],
    "wof:name":"Ban Than Ari",
    "wof:placetype":"locality"
},
  "geometry": {"coordinates":[99.06999999999999,8.7155],"type":"Point"}
}