{
  "type": "Feature",
  "properties": {
    "gn:admin1_code":"7.0",
    "gn:asciiname":"Ban Kio Nak",
    "gn:country_code":"TH",
    "gn:dem":314,
    "gn:feature_class":"P",
    "gn:feature_code":"PPL",
    "gn:name":"Ban Kio Nak",
    "gn:population":0,
    "gn:timezone":"Asia/Bangkok",
    "iso:country":"TH",
    "name:tha_x_preferred":[
        "\u0e1a\u0e49\u0e32\u0e19\u0e01\u0e34\u0e48\u0e27\u0e19\u0e32\u0e04"
    ],
    "wof:name":"Ban Kio Nak",
    "wof:placetype":"locality"
},
  "geometry": {"coordinates":[100.43919,18.42672],"type":"Point"}
}