{
  "type": "Feature",
  "properties": {
    "gn:admin1_code":"0.0",
    "gn:asciiname":"Ban Tha Tum",
    "gn:country_code":"TH",
    "gn:dem":170,
    "gn:feature_class":"P",
    "gn:feature_code":"PPL",
    "gn:name":"Ban Tha Tum",
    "gn:population":0,
    "gn:timezone":"Asia/Bangkok",
    "iso:country":"TH",
    "wof:lang_x_official":[
        "tha"
    ],
    "wof:lang_x_spoken":[
        "tha"
    ],
    "wof:name":"Ban Tha Tum",
    "wof:placetype":"locality"
},
  "geometry": {"coordinates":[103.40000000000001,16.08333],"type":"Point"}
}