{
  "type": "Feature",
  "properties": {
    "gn:admin1_code":"68.0",
    "gn:asciiname":"Ban Na Suan Luang",
    "gn:country_code":"TH",
    "gn:dem":41,
    "gn:feature_class":"P",
    "gn:feature_code":"PPL",
    "gn:name":"Ban Na Suan Luang",
    "gn:population":0,
    "gn:timezone":"Asia/Bangkok",
    "iso:country":"TH",
    "name:tha_x_preferred":[
        "\u0e1a\u0e49\u0e32\u0e19\u0e2b\u0e19\u0e49\u0e32\u0e2a\u0e27\u0e19\u0e2b\u0e25\u0e27\u0e07"
    ],
    "wof:name":"Ban Na Suan Luang",
    "wof:placetype":"locality"
},
  "geometry": {"coordinates":[100.29461000000001,7.00772],"type":"Point"}
}