{
  "type": "Feature",
  "properties": {
    "gn:admin1_code":"3.0",
    "gn:asciiname":"Ban Rong Pao",
    "gn:country_code":"TH",
    "gn:dem":410,
    "gn:feature_class":"P",
    "gn:feature_code":"PPL",
    "gn:name":"Ban Rong Pao",
    "gn:population":0,
    "gn:timezone":"Asia/Bangkok",
    "iso:country":"TH",
    "name:tha_x_preferred":[
        "\u0e1a\u0e49\u0e32\u0e19\u0e23\u0e48\u0e2d\u0e07\u0e40\u0e1b\u0e32"
    ],
    "wof:name":"Ban Rong Pao",
    "wof:placetype":"locality"
},
  "geometry": {"coordinates":[99.93845,19.61061],"type":"Point"}
}