{
  "type": "Feature",
  "properties": {
    "gn:admin1_code":"31.0",
    "gn:asciiname":"Ban Khok Soe Dae",
    "gn:country_code":"TH",
    "gn:dem":5,
    "gn:feature_class":"P",
    "gn:feature_code":"PPL",
    "gn:name":"Ban Khok Soe Dae",
    "gn:population":0,
    "gn:timezone":"Asia/Bangkok",
    "iso:country":"TH",
    "name:tha_x_preferred":[
        "\u0e1a\u0e49\u0e32\u0e19\u0e42\u0e04\u0e01\u0e40\u0e0b\u0e2d\u0e41\u0e14"
    ],
    "wof:name":"Ban Khok Soe Dae",
    "wof:placetype":"locality"
},
  "geometry": {"coordinates":[101.87203,6.29872],"type":"Point"}
}