{
  "type": "Feature",
  "properties": {
    "gn:admin1_code":"14.0",
    "gn:asciiname":"Ban Nong Chok",
    "gn:country_code":"TH",
    "gn:dem":108,
    "gn:feature_class":"P",
    "gn:feature_code":"PPL",
    "gn:name":"Ban Nong Chok",
    "gn:population":0,
    "gn:timezone":"Asia/Bangkok",
    "iso:country":"TH",
    "name:tha_x_preferred":[
        "\u0e1a\u0e49\u0e32\u0e19\u0e2b\u0e19\u0e2d\u0e07\u0e08\u0e2d\u0e01"
    ],
    "wof:name":"Ban Nong Chok",
    "wof:placetype":"locality"
},
  "geometry": {"coordinates":[101.11806,16.13922],"type":"Point"}
}