{
  "type": "Feature",
  "properties": {
    "gn:admin1_code":"75.0",
    "gn:asciiname":"Ban Thung Phiang",
    "gn:country_code":"TH",
    "gn:dem":196,
    "gn:feature_class":"P",
    "gn:feature_code":"PPL",
    "gn:name":"Ban Thung Phiang",
    "gn:population":0,
    "gn:timezone":"Asia/Bangkok",
    "iso:country":"TH",
    "name:tha_x_preferred":[
        "\u0e1a\u0e49\u0e32\u0e19\u0e17\u0e38\u0e48\u0e07\u0e40\u0e1e\u0e35\u0e22\u0e07"
    ],
    "wof:name":"Ban Thung Phiang",
    "wof:placetype":"locality"
},
  "geometry": {"coordinates":[105.30547,14.60628],"type":"Point"}
}