{
  "type": "Feature",
  "properties": {
    "gn:admin1_code":"26.0",
    "gn:asciiname":"Ban Mai Non Mueang",
    "gn:country_code":"TH",
    "gn:dem":285,
    "gn:feature_class":"P",
    "gn:feature_code":"PPL",
    "gn:name":"Ban Mai Non Mueang",
    "gn:population":0,
    "gn:timezone":"Asia/Bangkok",
    "iso:country":"TH",
    "name:tha_x_preferred":[
        "\u0e1a\u0e49\u0e32\u0e19\u0e43\u0e2b\u0e21\u0e48\u0e42\u0e19\u0e19\u0e40\u0e21\u0e37\u0e2d\u0e07"
    ],
    "wof:name":"Ban Mai Non Mueang",
    "wof:placetype":"locality"
},
  "geometry": {"coordinates":[101.52418,15.44042],"type":"Point"}
}