{
  "type": "Feature",
  "properties": {
    "gn:admin1_code":"27",
    "gn:asciiname":"Ban Sap Nam Yen",
    "gn:country_code":"TH",
    "gn:dem":427,
    "gn:feature_class":"P",
    "gn:feature_code":"PPL",
    "gn:name":"Ban Sap Nam Yen",
    "gn:population":0,
    "gn:timezone":"Asia/Bangkok",
    "iso:country":"TH",
    "name:tha_x_preferred":[
        "\u0e1a\u0e49\u0e32\u0e19\u0e0b\u0e31\u0e1a\u0e19\u0e49\u0e33\u0e40\u0e22\u0e47\u0e19"
    ],
    "wof:name":"Ban Sap Nam Yen",
    "wof:placetype":"locality"
},
  "geometry": {"coordinates":[101.32811,14.69514],"type":"Point"}
}