{
  "type": "Feature",
  "properties": {
    "gn:admin1_code":"2.0",
    "gn:asciiname":"Ban Musoe Huai Ngu",
    "gn:country_code":"TH",
    "gn:dem":669,
    "gn:feature_class":"P",
    "gn:feature_code":"PPL",
    "gn:name":"Ban Musoe Huai Ngu",
    "gn:population":0,
    "gn:timezone":"Asia/Bangkok",
    "iso:country":"TH",
    "name:tha_x_preferred":[
        "\u0e1a\u0e49\u0e32\u0e19\u0e21\u0e39\u0e40\u0e0b\u0e2d\u0e2b\u0e49\u0e27\u0e22\u0e07\u0e39"
    ],
    "wof:name":"Ban Musoe Huai Ngu",
    "wof:placetype":"locality"
},
  "geometry": {"coordinates":[98.69083000000001,19.44392],"type":"Point"}
}