{
  "type": "Feature",
  "properties": {
    "gn:admin1_code":"32.0",
    "gn:asciiname":"Ban Thap Sao Ho",
    "gn:country_code":"TH",
    "gn:dem":41,
    "gn:feature_class":"P",
    "gn:feature_code":"PPL",
    "gn:name":"Ban Thap Sao Ho",
    "gn:population":0,
    "gn:timezone":"Asia/Bangkok",
    "iso:country":"TH",
    "name:tha_x_preferred":[
        "\u0e1a\u0e49\u0e32\u0e19\u0e17\u0e31\u0e1a\u0e40\u0e2a\u0e32\u0e2b\u0e2d"
    ],
    "wof:name":"Ban Thap Sao Ho",
    "wof:placetype":"locality"
},
  "geometry": {"coordinates":[99.88739,15.23308],"type":"Point"}
}