{
  "type": "Feature",
  "properties": {
    "gn:admin1_code":"77.0",
    "gn:asciiname":"Ban Kham Noi",
    "gn:country_code":"TH",
    "gn:dem":135,
    "gn:feature_class":"P",
    "gn:feature_code":"PPL",
    "gn:name":"Ban Kham Noi",
    "gn:population":0,
    "gn:timezone":"Asia/Bangkok",
    "iso:country":"TH",
    "name:tha_x_preferred":[
        "Ban Kham Noi"
    ],
    "name:tha_x_variant":[
        "\u0e1a\u0e49\u0e32\u0e19\u0e04\u0e33\u0e19\u0e49\u0e2d\u0e22"
    ],
    "wof:name":"Ban Kham Noi",
    "wof:placetype":"locality"
},
  "geometry": {"coordinates":[104.48972000000001,15.61486],"type":"Point"}
}