{
  "type": "Feature",
  "properties": {
    "gn:admin1_code":"18.0",
    "gn:asciiname":"Ban Na Pa Nat",
    "gn:country_code":"TH",
    "gn:dem":268,
    "gn:feature_class":"P",
    "gn:feature_code":"PPL",
    "gn:name":"Ban Na Pa Nat",
    "gn:population":0,
    "gn:timezone":"Asia/Bangkok",
    "iso:country":"TH",
    "name:tha_x_preferred":[
        "\u0e1a\u0e49\u0e32\u0e19\u0e19\u0e32\u0e1b\u0e48\u0e32\u0e2b\u0e19\u0e32\u0e14"
    ],
    "name:und_x_variant":[
        "Ban Pa Nat",
        "Ban Khok",
        "Ban Na Pa Nat"
    ],
    "wof:name":"Ban Na Pa Nat",
    "wof:placetype":"locality"
},
  "geometry": {"coordinates":[101.73756,17.79758],"type":"Point"}
}