{
  "type": "Feature",
  "properties": {
    "gn:admin1_code":"80.0",
    "gn:asciiname":"Ban Fang Khlong",
    "gn:country_code":"TH",
    "gn:dem":64,
    "gn:feature_class":"P",
    "gn:feature_code":"PPL",
    "gn:name":"Ban Fang Khlong",
    "gn:population":0,
    "gn:timezone":"Asia/Bangkok",
    "iso:country":"TH",
    "name:tha_x_preferred":[
        "\u0e1a\u0e49\u0e32\u0e19\u0e1d\u0e31\u0e48\u0e07\u0e04\u0e25\u0e2d\u0e07"
    ],
    "wof:name":"Ban Fang Khlong",
    "wof:placetype":"locality"
},
  "geometry": {"coordinates":[102.39397,13.67953],"type":"Point"}
}