{
  "type": "Feature",
  "properties": {
    "gn:admin1_code":"6.0",
    "gn:asciiname":"Ban Uthumphon",
    "gn:country_code":"TH",
    "gn:dem":244,
    "gn:feature_class":"P",
    "gn:feature_code":"PPL",
    "gn:name":"Ban Uthumphon",
    "gn:population":0,
    "gn:timezone":"Asia/Bangkok",
    "iso:country":"TH",
    "name:tha_x_preferred":[
        "\u0e1a\u0e49\u0e32\u0e19\u0e2d\u0e38\u0e17\u0e38\u0e21\u0e1e\u0e23"
    ],
    "wof:name":"Ban Uthumphon",
    "wof:placetype":"locality"
},
  "geometry": {"coordinates":[99.54328,18.34508],"type":"Point"}
}