{
  "type": "Feature",
  "properties": {
    "gn:admin1_code":"48.0",
    "gn:asciiname":"Ban Bo Nam Ngoen",
    "gn:country_code":"TH",
    "gn:dem":38,
    "gn:feature_class":"P",
    "gn:feature_code":"PPL",
    "gn:name":"Ban Bo Nam Ngoen",
    "gn:population":0,
    "gn:timezone":"Asia/Bangkok",
    "iso:country":"TH",
    "name:tha_x_preferred":[
        "\u0e1a\u0e49\u0e32\u0e19\u0e1a\u0e48\u0e2d\u0e19\u0e49\u0e33\u0e40\u0e07\u0e34\u0e19"
    ],
    "wof:name":"Ban Bo Nam Ngoen",
    "wof:placetype":"locality"
},
  "geometry": {"coordinates":[102.05431,12.81317],"type":"Point"}
}