{
  "type": "Feature",
  "properties": {
    "gn:admin1_code":"31.0",
    "gn:asciiname":"Ban Chao Pramong Phatthana",
    "gn:country_code":"TH",
    "gn:dem":5,
    "gn:feature_class":"P",
    "gn:feature_code":"PPL",
    "gn:name":"Ban Chao Pramong Phatthana",
    "gn:population":0,
    "gn:timezone":"Asia/Bangkok",
    "iso:country":"TH",
    "name:tha_x_preferred":[
        "\u0e1a\u0e49\u0e32\u0e19\u0e0a\u0e32\u0e27\u0e1b\u0e23\u0e30\u0e21\u0e07\u0e1e\u0e31\u0e12\u0e19\u0e32"
    ],
    "wof:name":"Ban Chao Pramong Phatthana",
    "wof:placetype":"locality"
},
  "geometry": {"coordinates":[101.82496999999999,6.44444],"type":"Point"}
}