{
  "type": "Feature",
  "properties": {
    "gn:admin1_code":"17.0",
    "gn:asciiname":"Ban Knok Maeng-Ngao",
    "gn:country_code":"TH",
    "gn:dem":168,
    "gn:feature_class":"P",
    "gn:feature_code":"PPL",
    "gn:name":"Ban Knok Maeng-Ngao",
    "gn:population":0,
    "gn:timezone":"Asia/Bangkok",
    "iso:country":"TH",
    "name:tha_x_preferred":[
        "\u0e1a\u0e49\u0e32\u0e19\u0e42\u0e04\u0e01\u0e41\u0e21\u0e07\u0e40\u0e07\u0e32"
    ],
    "wof:name":"Ban Knok Maeng-Ngao",
    "wof:placetype":"locality"
},
  "geometry": {"coordinates":[102.71169999999999,17.85206],"type":"Point"}
}