{
  "type": "Feature",
  "properties": {
    "gn:admin1_code":"80",
    "gn:asciiname":"Ban Chet Lang",
    "gn:country_code":"TH",
    "gn:dem":50,
    "gn:feature_class":"P",
    "gn:feature_code":"PPL",
    "gn:name":"Ban Chet Lang",
    "gn:population":0,
    "gn:timezone":"Asia/Bangkok",
    "iso:country":"TH",
    "name:tha_x_preferred":[
        "\u0e1a\u0e49\u0e32\u0e19\u0e40\u0e08\u0e47\u0e14\u0e2b\u0e25\u0e31\u0e07"
    ],
    "wof:name":"Ban Chet Lang",
    "wof:placetype":"locality"
},
  "geometry": {"coordinates":[102.06614,13.96531],"type":"Point"}
}