{
  "type": "Feature",
  "properties": {
    "gn:admin1_code":"70.0",
    "gn:asciiname":"Ban Lako Nako",
    "gn:country_code":"TH",
    "gn:dem":52,
    "gn:feature_class":"P",
    "gn:feature_code":"PPL",
    "gn:name":"Ban Lako Nako",
    "gn:population":0,
    "gn:timezone":"Asia/Bangkok",
    "iso:country":"TH",
    "name:tha_x_preferred":[
        "\u0e1a\u0e49\u0e32\u0e19\u0e25\u0e32\u0e06\u0e2d\u0e19\u0e32\u0e01\u0e2d"
    ],
    "wof:name":"Ban Lako Nako",
    "wof:placetype":"locality"
},
  "geometry": {"coordinates":[101.06083,6.49269],"type":"Point"}
}