{
  "type": "Feature",
  "properties": {
    "gn:admin1_code":"17.0",
    "gn:asciiname":"Ban Bong",
    "gn:country_code":"TH",
    "gn:dem":171,
    "gn:feature_class":"P",
    "gn:feature_code":"PPL",
    "gn:name":"Ban Bong",
    "gn:population":0,
    "gn:timezone":"Asia/Bangkok",
    "iso:country":"TH",
    "name:tha_x_preferred":[
        "\u0e1a\u0e49\u0e32\u0e19\u0e1a\u0e07"
    ],
    "name:und_x_variant":[
        "Muang Bong",
        "Ban Bong"
    ],
    "wof:name":"Ban Bong",
    "wof:placetype":"locality"
},
  "geometry": {"coordinates":[102.88128,17.9535],"type":"Point"}
}