{
  "type": "Feature",
  "properties": {
    "gn:admin1_code":"64.0",
    "gn:asciiname":"Ban Na Mai Dat",
    "gn:country_code":"TH",
    "gn:dem":71,
    "gn:feature_class":"P",
    "gn:feature_code":"PPL",
    "gn:name":"Ban Na Mai Dat",
    "gn:population":0,
    "gn:timezone":"Asia/Bangkok",
    "iso:country":"TH",
    "name:tha_x_preferred":[
        "\u0e1a\u0e49\u0e32\u0e19\u0e19\u0e32\u0e44\u0e21\u0e49\u0e14\u0e31\u0e14"
    ],
    "wof:name":"Ban Na Mai Dat",
    "wof:placetype":"locality"
},
  "geometry": {"coordinates":[99.62282999999999,8.21211],"type":"Point"}
}