{
  "type": "Feature",
  "properties": {
    "gn:admin1_code":"7.0",
    "gn:asciiname":"Ban Pong",
    "gn:country_code":"TH",
    "gn:dem":832,
    "gn:feature_class":"P",
    "gn:feature_code":"PPL",
    "gn:name":"Ban Pong",
    "gn:population":0,
    "gn:timezone":"Asia/Bangkok",
    "iso:country":"TH",
    "name:tha_x_preferred":[
        "\u0e1a\u0e49\u0e32\u0e19\u0e1b\u0e07"
    ],
    "name:und_x_variant":[
        "Ban Bong",
        "B\u0101n Paung",
        "Ban Pong"
    ],
    "wof:name":"Ban Pong",
    "wof:placetype":"locality"
},
  "geometry": {"coordinates":[100.33656000000001,18.12836],"type":"Point"}
}