{
  "type": "Feature",
  "properties": {
    "gn:admin1_code":"70.0",
    "gn:asciiname":"Ban Sa Ta Pae",
    "gn:country_code":"TH",
    "gn:dem":59,
    "gn:feature_class":"P",
    "gn:feature_code":"PPL",
    "gn:name":"Ban Sa Ta Pae",
    "gn:population":0,
    "gn:timezone":"Asia/Bangkok",
    "iso:country":"TH",
    "name:tha_x_preferred":[
        "\u0e1a\u0e49\u0e32\u0e19\u0e2a\u0e30\u0e15\u0e32\u0e41\u0e1b"
    ],
    "wof:name":"Ban Sa Ta Pae",
    "wof:placetype":"locality"
},
  "geometry": {"coordinates":[101.02556,6.44572],"type":"Point"}
}