{
  "type": "Feature",
  "properties": {
    "gn:admin1_code":"3.0",
    "gn:asciiname":"Ban Huai Om Mai",
    "gn:country_code":"TH",
    "gn:dem":400,
    "gn:feature_class":"P",
    "gn:feature_code":"PPL",
    "gn:name":"Ban Huai Om Mai",
    "gn:population":0,
    "gn:timezone":"Asia/Bangkok",
    "iso:country":"TH",
    "name:tha_x_preferred":[
        "\u0e1a\u0e49\u0e32\u0e19\u0e2b\u0e49\u0e27\u0e22\u0e2d\u0e49\u0e21\u0e43\u0e2b\u0e21\u0e48"
    ],
    "wof:name":"Ban Huai Om Mai",
    "wof:placetype":"locality"
},
  "geometry": {"coordinates":[99.97575000000001,20.10861],"type":"Point"}
}