{
  "type": "Feature",
  "properties": {
    "gn:admin1_code":"3.0",
    "gn:asciiname":"Ban Chedi Mai",
    "gn:country_code":"TH",
    "gn:dem":386,
    "gn:feature_class":"P",
    "gn:feature_code":"PPL",
    "gn:name":"Ban Chedi Mai",
    "gn:population":0,
    "gn:timezone":"Asia/Bangkok",
    "iso:country":"TH",
    "name:tha_x_preferred":[
        "\u0e1a\u0e49\u0e32\u0e19\u0e40\u0e08\u0e14\u0e35\u0e22\u0e4c\u0e43\u0e2b\u0e21\u0e48"
    ],
    "wof:name":"Ban Chedi Mai",
    "wof:placetype":"locality"
},
  "geometry": {"coordinates":[100.27307999999999,19.85736],"type":"Point"}
}