{
  "type": "Feature",
  "properties": {
    "gn:admin1_code":"64.0",
    "gn:asciiname":"Ban Chamao",
    "gn:country_code":"TH",
    "gn:dem":11,
    "gn:feature_class":"P",
    "gn:feature_code":"PPL",
    "gn:name":"Ban Chamao",
    "gn:population":0,
    "gn:timezone":"Asia/Bangkok",
    "iso:country":"TH",
    "name:tha_x_preferred":[
        "\u0e1a\u0e49\u0e32\u0e19\u0e0a\u0e30\u0e40\u0e21\u0e32"
    ],
    "name:und_x_variant":[
        "Ban Chama"
    ],
    "wof:name":"Ban Chamao",
    "wof:placetype":"locality"
},
  "geometry": {"coordinates":[100.01508,8.24478],"type":"Point"}
}