{
  "type": "Feature",
  "properties": {
    "gn:admin1_code":"25.0",
    "gn:asciiname":"Phanom Panom Prai Den Maranka",
    "gn:country_code":"TH",
    "gn:dem":124,
    "gn:feature_class":"P",
    "gn:feature_code":"PPL",
    "gn:name":"Phanom Panom Prai Den Maranka",
    "gn:population":0,
    "gn:timezone":"Asia/Bangkok",
    "iso:country":"TH",
    "wof:lang_x_official":[
        "tha"
    ],
    "wof:lang_x_spoken":[
        "tha"
    ],
    "wof:name":"Phanom Panom Prai Den Maranka",
    "wof:placetype":"locality"
},
  "geometry": {"coordinates":[104.11667,15.68333],"type":"Point"}
}