{
  "type": "Feature",
  "properties": {
    "gn:admin1_code":"70.0",
    "gn:asciiname":"Ban Kue Lae",
    "gn:country_code":"TH",
    "gn:dem":18,
    "gn:feature_class":"P",
    "gn:feature_code":"PPL",
    "gn:name":"Ban Kue Lae",
    "gn:population":0,
    "gn:timezone":"Asia/Bangkok",
    "iso:country":"TH",
    "name:tha_x_preferred":[
        "\u0e1a\u0e49\u0e32\u0e19\u0e01\u0e37\u0e2d\u0e41\u0e25"
    ],
    "wof:name":"Ban Kue Lae",
    "wof:placetype":"locality"
},
  "geometry": {"coordinates":[101.33922,6.51197],"type":"Point"}
}