{
  "type": "Feature",
  "properties": {
    "gn:admin1_code":"14.0",
    "gn:asciiname":"Ban Wang Cha-om",
    "gn:country_code":"TH",
    "gn:dem":84,
    "gn:feature_class":"P",
    "gn:feature_code":"PPL",
    "gn:name":"Ban Wang Cha-om",
    "gn:population":0,
    "gn:timezone":"Asia/Bangkok",
    "iso:country":"TH",
    "name:tha_x_preferred":[
        "\u0e1a\u0e49\u0e32\u0e19\u0e27\u0e31\u0e07\u0e0a\u0e30\u0e2d\u0e21"
    ],
    "wof:name":"Ban Wang Cha-om",
    "wof:placetype":"locality"
},
  "geometry": {"coordinates":[100.98189000000001,15.59747],"type":"Point"}
}