{
  "type": "Feature",
  "properties": {
    "gn:admin1_code":"5.0",
    "gn:asciiname":"Ban Pa Pao",
    "gn:country_code":"TH",
    "gn:dem":305,
    "gn:feature_class":"P",
    "gn:feature_code":"PPL",
    "gn:name":"Ban Pa Pao",
    "gn:population":0,
    "gn:timezone":"Asia/Bangkok",
    "iso:country":"TH",
    "name:tha_x_preferred":[
        "\u0e1a\u0e49\u0e32\u0e19\u0e1b\u0e48\u0e32\u0e40\u0e1b\u0e32"
    ],
    "name:und_x_variant":[
        "Ban Pa Pao Nua"
    ],
    "wof:name":"Ban Pa Pao",
    "wof:placetype":"locality"
},
  "geometry": {"coordinates":[99.08056000000001,18.59303],"type":"Point"}
}