{
  "type": "Feature",
  "properties": {
    "gn:admin1_code":"29",
    "gn:asciiname":"Ban Sa Thala",
    "gn:country_code":"TH",
    "gn:dem":134,
    "gn:feature_class":"P",
    "gn:feature_code":"PPL",
    "gn:name":"Ban Sa Thala",
    "gn:population":0,
    "gn:timezone":"Asia/Bangkok",
    "iso:country":"TH",
    "name:tha_x_preferred":[
        "\u0e1a\u0e49\u0e32\u0e19\u0e2a\u0e23\u0e30\u0e17\u0e25\u0e32"
    ],
    "wof:name":"Ban Sa Thala",
    "wof:placetype":"locality"
},
  "geometry": {"coordinates":[103.63261,15.31292],"type":"Point"}
}