{
  "type": "Feature",
  "properties": {
    "gn:admin1_code":"74",
    "gn:asciiname":"Ban Thap Yuan",
    "gn:country_code":"TH",
    "gn:dem":16,
    "gn:feature_class":"P",
    "gn:feature_code":"PPL",
    "gn:name":"Ban Thap Yuan",
    "gn:population":0,
    "gn:timezone":"Asia/Bangkok",
    "iso:country":"TH",
    "name:tha_x_preferred":[
        "\u0e1a\u0e49\u0e32\u0e19\u0e17\u0e31\u0e1a\u0e0d\u0e27\u0e19"
    ],
    "wof:name":"Ban Thap Yuan",
    "wof:placetype":"locality"
},
  "geometry": {"coordinates":[101.58338999999999,13.88933],"type":"Point"}
}