{
  "type": "Feature",
  "properties": {
    "gn:admin1_code":"72.0",
    "gn:asciiname":"Ban Sang Chang",
    "gn:country_code":"TH",
    "gn:dem":150,
    "gn:feature_class":"P",
    "gn:feature_code":"PPL",
    "gn:name":"Ban Sang Chang",
    "gn:population":0,
    "gn:timezone":"Asia/Bangkok",
    "iso:country":"TH",
    "name:tha_x_preferred":[
        "\u0e1a\u0e49\u0e32\u0e19\u0e2a\u0e23\u0e49\u0e32\u0e07\u0e0a\u0e49\u0e32\u0e07"
    ],
    "name:und_x_variant":[
        "Sangsan",
        "Ban Sangsan",
        "Ban Sang Chang"
    ],
    "wof:lang_x_official":[
        "tha"
    ],
    "wof:lang_x_spoken":[
        "tha"
    ],
    "wof:name":"Ban Sang Chang",
    "wof:placetype":"locality"
},
  "geometry": {"coordinates":[104.28531,15.91533],"type":"Point"}
}