{
  "type": "Feature",
  "properties": {
    "gn:admin1_code":"26.0",
    "gn:asciiname":"Ban So Po Ko",
    "gn:country_code":"TH",
    "gn:dem":231,
    "gn:feature_class":"P",
    "gn:feature_code":"PPL",
    "gn:name":"Ban So Po Ko",
    "gn:population":0,
    "gn:timezone":"Asia/Bangkok",
    "iso:country":"TH",
    "name:tha_x_preferred":[
        "\u0e1a\u0e49\u0e32\u0e19 \u0e2a\u0e1b\u0e01."
    ],
    "wof:name":"Ban So Po Ko",
    "wof:placetype":"locality"
},
  "geometry": {"coordinates":[102.25552999999999,16.35878],"type":"Point"}
}