{
  "type": "Feature",
  "properties": {
    "gn:admin1_code":"36.0",
    "gn:asciiname":"Ban Phra Kaeo",
    "gn:country_code":"TH",
    "gn:dem":7,
    "gn:feature_class":"P",
    "gn:feature_code":"PPL",
    "gn:name":"Ban Phra Kaeo",
    "gn:population":0,
    "gn:timezone":"Asia/Bangkok",
    "iso:country":"TH",
    "name:tha_x_preferred":[
        "\u0e1a\u0e49\u0e32\u0e19\u0e1e\u0e23\u0e30\u0e41\u0e01\u0e49\u0e27"
    ],
    "name:und_x_variant":[
        "Ban Pra Kew",
        "Ban Phra Kaeo"
    ],
    "wof:name":"Ban Phra Kaeo",
    "wof:placetype":"locality"
},
  "geometry": {"coordinates":[100.69589000000001,14.45117],"type":"Point"}
}