{
  "type": "Feature",
  "properties": {
    "gn:admin1_code":"28",
    "gn:asciiname":"Ban Thep Samphan",
    "gn:country_code":"TH",
    "gn:dem":142,
    "gn:feature_class":"P",
    "gn:feature_code":"PPL",
    "gn:name":"Ban Thep Samphan",
    "gn:population":0,
    "gn:timezone":"Asia/Bangkok",
    "iso:country":"TH",
    "name:tha_x_preferred":[
        "\u0e1a\u0e49\u0e32\u0e19\u0e40\u0e17\u0e1e\u0e2a\u0e31\u0e21\u0e1e\u0e31\u0e19\u0e18\u0e4c"
    ],
    "wof:name":"Ban Thep Samphan",
    "wof:placetype":"locality"
},
  "geometry": {"coordinates":[103.13806,15.322],"type":"Point"}
}