{
  "type": "Feature",
  "properties": {
    "gn:admin1_code":"43.0",
    "gn:asciiname":"Ban Ko Pho",
    "gn:country_code":"TH",
    "gn:dem":6,
    "gn:feature_class":"P",
    "gn:feature_code":"PPL",
    "gn:name":"Ban Ko Pho",
    "gn:population":0,
    "gn:timezone":"Asia/Bangkok",
    "iso:country":"TH",
    "name:tha_x_preferred":[
        "\u0e1a\u0e49\u0e32\u0e19\u0e40\u0e01\u0e32\u0e30\u0e42\u0e1e\u0e18\u0e34\u0e4c"
    ],
    "name:und_x_variant":[
        "Ban Koh Po",
        "Ban Ko Pho (1)",
        "Ban Ko Pho"
    ],
    "wof:lang_x_official":[
        "tha"
    ],
    "wof:lang_x_spoken":[
        "tha"
    ],
    "wof:name":"Ban Ko Pho",
    "wof:placetype":"locality"
},
  "geometry": {"coordinates":[101.23922,14.162],"type":"Point"}
}