{
  "type": "Feature",
  "properties": {
    "gn:admin1_code":"20.0",
    "gn:asciiname":"Ban Phon Sung",
    "gn:country_code":"TH",
    "gn:dem":165,
    "gn:feature_class":"P",
    "gn:feature_code":"PPL",
    "gn:name":"Ban Phon Sung",
    "gn:population":0,
    "gn:timezone":"Asia/Bangkok",
    "iso:country":"TH",
    "name:tha_x_preferred":[
        "\u0e1a\u0e49\u0e32\u0e19\u0e42\u0e1e\u0e19\u0e2a\u0e39\u0e07"
    ],
    "wof:name":"Ban Phon Sung",
    "wof:placetype":"locality"
},
  "geometry": {"coordinates":[103.43106,17.49233],"type":"Point"}
}