{
  "type": "Feature",
  "properties": {
    "gn:admin1_code":"77.0",
    "gn:asciiname":"Ban Na Ngam",
    "gn:country_code":"TH",
    "gn:dem":166,
    "gn:feature_class":"P",
    "gn:feature_code":"PPL",
    "gn:name":"Ban Na Ngam",
    "gn:population":0,
    "gn:timezone":"Asia/Bangkok",
    "iso:country":"TH",
    "name:tha_x_preferred":[
        "Ban Na Ngam"
    ],
    "name:tha_x_variant":[
        "\u0e1a\u0e49\u0e32\u0e19\u0e19\u0e32\u0e07\u0e32\u0e21"
    ],
    "wof:name":"Ban Na Ngam",
    "wof:placetype":"locality"
},
  "geometry": {"coordinates":[104.928,16.09008],"type":"Point"}
}