{
  "type": "Feature",
  "properties": {
    "gn:admin1_code":"4.0",
    "gn:asciiname":"Ban Sala",
    "gn:country_code":"TH",
    "gn:dem":342,
    "gn:feature_class":"P",
    "gn:feature_code":"PPL",
    "gn:name":"Ban Sala",
    "gn:population":0,
    "gn:timezone":"Asia/Bangkok",
    "iso:country":"TH",
    "name:tha_x_preferred":[
        "\u0e1a\u0e49\u0e32\u0e19\u0e28\u0e32\u0e25\u0e32"
    ],
    "wof:name":"Ban Sala",
    "wof:placetype":"locality"
},
  "geometry": {"coordinates":[100.88236000000001,19.43567],"type":"Point"}
}