{
  "type": "Feature",
  "properties": {
    "gn:admin1_code":"50.0",
    "gn:asciiname":"Ban Phanom Thuan",
    "gn:country_code":"TH",
    "gn:dem":15,
    "gn:feature_class":"P",
    "gn:feature_code":"PPL",
    "gn:name":"Ban Phanom Thuan",
    "gn:population":0,
    "gn:timezone":"Asia/Bangkok",
    "iso:country":"TH",
    "name:tha_x_preferred":[
        "\u0e1a\u0e49\u0e32\u0e19\u0e1e\u0e19\u0e21\u0e17\u0e27\u0e19"
    ],
    "wof:name":"Ban Phanom Thuan",
    "wof:placetype":"locality"
},
  "geometry": {"coordinates":[99.79342,14.22631],"type":"Point"}
}