{
  "type": "Feature",
  "properties": {
    "gn:admin1_code":"1.0",
    "gn:asciiname":"Ban So Khae Tha",
    "gn:country_code":"TH",
    "gn:dem":1041,
    "gn:feature_class":"P",
    "gn:feature_code":"PPL",
    "gn:name":"Ban So Khae Tha",
    "gn:population":0,
    "gn:timezone":"Asia/Bangkok",
    "iso:country":"TH",
    "name:tha_x_preferred":[
        "\u0e1a\u0e49\u0e32\u0e19\u0e0b\u0e2d\u0e41\u0e04\u0e48\u0e16\u0e48\u0e32"
    ],
    "wof:name":"Ban So Khae Tha",
    "wof:placetype":"locality"
},
  "geometry": {"coordinates":[98.09272,18.98758],"type":"Point"}
}