{
  "type": "Feature",
  "properties": {
    "gn:admin1_code":"51.0",
    "gn:asciiname":"Ban Khlong Nguhao",
    "gn:country_code":"TH",
    "gn:dem":7,
    "gn:feature_class":"P",
    "gn:feature_code":"PPL",
    "gn:name":"Ban Khlong Nguhao",
    "gn:population":0,
    "gn:timezone":"Asia/Bangkok",
    "iso:country":"TH",
    "name:tha_x_preferred":[
        "\u0e1a\u0e49\u0e32\u0e19\u0e04\u0e25\u0e2d\u0e07\u0e07\u0e39\u0e40\u0e2b\u0e48\u0e32"
    ],
    "wof:name":"Ban Khlong Nguhao",
    "wof:placetype":"locality"
},
  "geometry": {"coordinates":[100.04481,14.47486],"type":"Point"}
}