{
  "type": "Feature",
  "properties": {
    "gn:admin1_code":"52.0",
    "gn:asciiname":"Ban Rang Phuang",
    "gn:country_code":"TH",
    "gn:dem":36,
    "gn:feature_class":"P",
    "gn:feature_code":"PPL",
    "gn:name":"Ban Rang Phuang",
    "gn:population":0,
    "gn:timezone":"Asia/Bangkok",
    "iso:country":"TH",
    "name:tha_x_preferred":[
        "\u0e1a\u0e49\u0e32\u0e19\u0e23\u0e32\u0e07\u0e1e\u0e27\u0e07"
    ],
    "wof:name":"Ban Rang Phuang",
    "wof:placetype":"locality"
},
  "geometry": {"coordinates":[99.71286000000001,13.37583],"type":"Point"}
}