{
  "type": "Feature",
  "properties": {
    "gn:admin1_code":"16.0",
    "gn:asciiname":"Ban Bo Chumsaeng",
    "gn:country_code":"TH",
    "gn:dem":74,
    "gn:feature_class":"P",
    "gn:feature_code":"PPL",
    "gn:name":"Ban Bo Chumsaeng",
    "gn:population":0,
    "gn:timezone":"Asia/Bangkok",
    "iso:country":"TH",
    "name:tha_x_preferred":[
        "\u0e1a\u0e49\u0e32\u0e19\u0e1a\u0e48\u0e2d\u0e0a\u0e38\u0e21\u0e41\u0e2a\u0e07"
    ],
    "wof:lang_x_official":[
        "tha"
    ],
    "wof:lang_x_spoken":[
        "tha"
    ],
    "wof:name":"Ban Bo Chumsaeng",
    "wof:placetype":"locality"
},
  "geometry": {"coordinates":[99.68407999999999,15.70117],"type":"Point"}
}