{
  "type": "Feature",
  "properties": {
    "gn:admin1_code":"1.0",
    "gn:asciiname":"Ban Pang Mo",
    "gn:cc2":"TH",
    "gn:country_code":"TH",
    "gn:dem":1104,
    "gn:feature_class":"P",
    "gn:feature_code":"PPL",
    "gn:name":"Ban Pang Mo",
    "gn:population":0,
    "gn:timezone":"Asia/Bangkok",
    "iso:country":"TH",
    "name:und_x_variant":[
        "B\u0101n P\u0101ng Mau",
        "Ban Pang Mo"
    ],
    "wof:lang_x_official":[
        "tha"
    ],
    "wof:lang_x_spoken":[
        "tha"
    ],
    "wof:name":"Ban Pang Mo",
    "wof:placetype":"locality"
},
  "geometry": {"coordinates":[97.95,19.56667],"type":"Point"}
}