{
  "type": "Feature",
  "properties": {
    "gn:admin1_code":"52.0",
    "gn:asciiname":"Ban Chae Hai",
    "gn:country_code":"TH",
    "gn:dem":8,
    "gn:feature_class":"P",
    "gn:feature_code":"PPL",
    "gn:name":"Ban Chae Hai",
    "gn:population":0,
    "gn:timezone":"Asia/Bangkok",
    "iso:country":"TH",
    "name:tha_x_preferred":[
        "\u0e1a\u0e49\u0e32\u0e19\u0e41\u0e0a\u0e48\u0e44\u0e2b"
    ],
    "name:und_x_variant":[
        "\u0e1a\u0e49\u0e32\u0e19\u0e41\u0e0a\u0e48\u0e44\u0e2b"
    ],
    "wof:name":"Ban Chae Hai",
    "wof:placetype":"locality"
},
  "geometry": {"coordinates":[100.00466,13.57365],"type":"Point"}
}