{
  "type": "Feature",
  "properties": {
    "gn:admin1_code":"22",
    "gn:asciiname":"Ban Khwao",
    "gn:country_code":"TH",
    "gn:dem":171,
    "gn:feature_class":"P",
    "gn:feature_code":"PPL",
    "gn:name":"Ban Khwao",
    "gn:population":0,
    "gn:timezone":"Asia/Bangkok",
    "iso:country":"TH",
    "name:tha_x_preferred":[
        "\u0e1a\u0e49\u0e32\u0e19\u0e40\u0e02\u0e27\u0e32"
    ],
    "wof:name":"Ban Khwao",
    "wof:placetype":"locality"
},
  "geometry": {"coordinates":[102.52316999999999,16.12814],"type":"Point"}
}