{
  "type": "Feature",
  "properties": {
    "gn:admin1_code":"46.0",
    "gn:asciiname":"Ban Tha Bun Mi",
    "gn:country_code":"TH",
    "gn:dem":24,
    "gn:feature_class":"P",
    "gn:feature_code":"PPL",
    "gn:name":"Ban Tha Bun Mi",
    "gn:population":0,
    "gn:timezone":"Asia/Bangkok",
    "iso:country":"TH",
    "name:tha_x_preferred":[
        "\u0e1a\u0e49\u0e32\u0e19\u0e17\u0e48\u0e32\u0e1a\u0e38\u0e0d\u0e21\u0e35"
    ],
    "name:und_x_variant":[
        "Tha Bun Mi",
        "Ban Tha Bun Mi"
    ],
    "wof:name":"Ban Tha Bun Mi",
    "wof:placetype":"locality"
},
  "geometry": {"coordinates":[101.2855,13.39986],"type":"Point"}
}