{
  "type": "Feature",
  "properties": {
    "gn:admin1_code":"12.0",
    "gn:asciiname":"Ban Tha Ngam Sam",
    "gn:country_code":"TH",
    "gn:dem":50,
    "gn:feature_class":"P",
    "gn:feature_code":"PPL",
    "gn:name":"Ban Tha Ngam Sam",
    "gn:population":0,
    "gn:timezone":"Asia/Bangkok",
    "iso:country":"TH",
    "name:tha_x_preferred":[
        "\u0e1a\u0e49\u0e32\u0e19\u0e17\u0e48\u0e32\u0e07\u0e32\u0e21 \u0e2a\u0e32\u0e21"
    ],
    "wof:name":"Ban Tha Ngam Sam",
    "wof:placetype":"locality"
},
  "geometry": {"coordinates":[100.32256,16.98256],"type":"Point"}
}