{
  "type": "Feature",
  "properties": {
    "gn:admin1_code":"64.0",
    "gn:asciiname":"Ban Sai Yung Pak",
    "gn:country_code":"TH",
    "gn:dem":59,
    "gn:feature_class":"P",
    "gn:feature_code":"PPL",
    "gn:name":"Ban Sai Yung Pak",
    "gn:population":0,
    "gn:timezone":"Asia/Bangkok",
    "iso:country":"TH",
    "name:tha_x_preferred":[
        "\u0e1a\u0e49\u0e32\u0e19\u0e44\u0e2a\u0e22\u0e39\u0e07\u0e1b\u0e31\u0e01"
    ],
    "wof:name":"Ban Sai Yung Pak",
    "wof:placetype":"locality"
},
  "geometry": {"coordinates":[99.48488999999999,8.26475],"type":"Point"}
}