{
  "type": "Feature",
  "properties": {
    "gn:admin1_code":"7.0",
    "gn:asciiname":"Ban Pak Chok",
    "gn:country_code":"TH",
    "gn:dem":122,
    "gn:feature_class":"P",
    "gn:feature_code":"PPL",
    "gn:name":"Ban Pak Chok",
    "gn:population":0,
    "gn:timezone":"Asia/Bangkok",
    "iso:country":"TH",
    "name:tha_x_preferred":[
        "\u0e1a\u0e49\u0e32\u0e19\u0e1b\u0e32\u0e01\u0e08\u0e2d\u0e01"
    ],
    "name:und_x_variant":[
        "Mae Chauk",
        "Ban Mae Chok",
        "B\u0101n Mea Jauk",
        "Ban Pak Chok"
    ],
    "wof:name":"Ban Pak Chok",
    "wof:placetype":"locality"
},
  "geometry": {"coordinates":[99.76031,17.98011],"type":"Point"}
}