{
  "type": "Feature",
  "properties": {
    "gn:admin1_code":"73.0",
    "gn:asciiname":"Ban Siang Sao",
    "gn:country_code":"TH",
    "gn:dem":163,
    "gn:feature_class":"P",
    "gn:feature_code":"PPL",
    "gn:name":"Ban Siang Sao",
    "gn:population":0,
    "gn:timezone":"Asia/Bangkok",
    "iso:country":"TH",
    "name:tha_x_preferred":[
        "\u0e1a\u0e49\u0e32\u0e19\u0e40\u0e0b\u0e35\u0e22\u0e07\u0e40\u0e0b\u0e32"
    ],
    "wof:name":"Ban Siang Sao",
    "wof:placetype":"locality"
},
  "geometry": {"coordinates":[104.21035999999999,17.55928],"type":"Point"}
}