{
  "type": "Feature",
  "properties": {
    "gn:admin1_code":"30.0",
    "gn:asciiname":"Ban Sang Mek Tai",
    "gn:country_code":"TH",
    "gn:dem":146,
    "gn:feature_class":"P",
    "gn:feature_code":"PPL",
    "gn:name":"Ban Sang Mek Tai",
    "gn:population":0,
    "gn:timezone":"Asia/Bangkok",
    "iso:country":"TH",
    "name:tha_x_preferred":[
        "\u0e1a\u0e49\u0e32\u0e19\u0e2a\u0e23\u0e49\u0e32\u0e07\u0e40\u0e21\u0e47\u0e01\u0e43\u0e15\u0e49"
    ],
    "wof:name":"Ban Sang Mek Tai",
    "wof:placetype":"locality"
},
  "geometry": {"coordinates":[104.58647000000001,14.77836],"type":"Point"}
}