{
  "type": "Feature",
  "properties": {
    "gn:admin1_code":"74",
    "gn:asciiname":"Ban Khlong Khuat",
    "gn:country_code":"TH",
    "gn:dem":32,
    "gn:feature_class":"P",
    "gn:feature_code":"PPL",
    "gn:name":"Ban Khlong Khuat",
    "gn:population":0,
    "gn:timezone":"Asia/Bangkok",
    "iso:country":"TH",
    "name:tha_x_preferred":[
        "\u0e1a\u0e49\u0e32\u0e19\u0e04\u0e25\u0e2d\u0e07\u0e02\u0e27\u0e14"
    ],
    "wof:name":"Ban Khlong Khuat",
    "wof:placetype":"locality"
},
  "geometry": {"coordinates":[101.90397,14.08986],"type":"Point"}
}