{
  "type": "Feature",
  "properties": {
    "gn:admin1_code":"52.0",
    "gn:asciiname":"Ban Tao Pun",
    "gn:country_code":"TH",
    "gn:dem":11,
    "gn:feature_class":"P",
    "gn:feature_code":"PPL",
    "gn:name":"Ban Tao Pun",
    "gn:population":0,
    "gn:timezone":"Asia/Bangkok",
    "iso:country":"TH",
    "name:tha_x_preferred":[
        "\u0e1a\u0e49\u0e32\u0e19\u0e40\u0e15\u0e32\u0e1b\u0e39\u0e19"
    ],
    "wof:name":"Ban Tao Pun",
    "wof:placetype":"locality"
},
  "geometry": {"coordinates":[99.78614,13.72272],"type":"Point"}
}