{
  "type": "Feature",
  "properties": {
    "gn:admin1_code":"2.0",
    "gn:asciiname":"Ban Mueang Klang",
    "gn:country_code":"TH",
    "gn:dem":299,
    "gn:feature_class":"P",
    "gn:feature_code":"PPL",
    "gn:name":"Ban Mueang Klang",
    "gn:population":0,
    "gn:timezone":"Asia/Bangkok",
    "iso:country":"TH",
    "name:tha_x_preferred":[
        "\u0e1a\u0e49\u0e32\u0e19\u0e40\u0e21\u0e37\u0e2d\u0e07\u0e01\u0e25\u0e32\u0e07"
    ],
    "name:und_x_variant":[
        "Kang",
        "B\u0101n Muang G\u0101ng",
        "Ban Muang Kang",
        "Ban Muang Klang",
        "Ban Mueang Klang"
    ],
    "wof:lang_x_official":[
        "tha"
    ],
    "wof:lang_x_spoken":[
        "tha"
    ],
    "wof:name":"Ban Mueang Klang",
    "wof:placetype":"locality"
},
  "geometry": {"coordinates":[98.65903,18.47614],"type":"Point"}
}