{
  "type": "Feature",
  "properties": {
    "gn:admin1_code":"7.0",
    "gn:asciiname":"Ban Tho Saman",
    "gn:country_code":"TH",
    "gn:dem":204,
    "gn:feature_class":"P",
    "gn:feature_code":"PPL",
    "gn:name":"Ban Tho Saman",
    "gn:population":0,
    "gn:timezone":"Asia/Bangkok",
    "iso:country":"TH",
    "name:tha_x_preferred":[
        "\u0e1a\u0e49\u0e32\u0e19\u0e17\u0e48\u0e2d\u0e2a\u0e21\u0e32\u0e19"
    ],
    "wof:lang_x_official":[
        "tha"
    ],
    "wof:lang_x_spoken":[
        "tha"
    ],
    "wof:name":"Ban Tho Saman",
    "wof:placetype":"locality"
},
  "geometry": {"coordinates":[100.20594,18.5011],"type":"Point"}
}