{
  "type": "Feature",
  "properties": {
    "gn:admin1_code":"55.0",
    "gn:asciiname":"Muban Rung Napha",
    "gn:country_code":"TH",
    "gn:dem":6,
    "gn:feature_class":"P",
    "gn:feature_code":"PPL",
    "gn:name":"Muban Rung Napha",
    "gn:population":0,
    "gn:timezone":"Asia/Bangkok",
    "iso:country":"TH",
    "name:tha_x_preferred":[
        "\u0e2b\u0e21\u0e39\u0e48\u0e1a\u0e49\u0e32\u0e19\u0e23\u0e38\u0e48\u0e07\u0e19\u0e20\u0e32"
    ],
    "wof:name":"Muban Rung Napha",
    "wof:placetype":"locality"
},
  "geometry": {"coordinates":[100.28111,13.58958],"type":"Point"}
}