{
  "type": "Feature",
  "properties": {
    "gn:admin1_code":"27.0",
    "gn:asciiname":"Ban Non Sa-nga",
    "gn:country_code":"TH",
    "gn:dem":258,
    "gn:feature_class":"P",
    "gn:feature_code":"PPL",
    "gn:name":"Ban Non Sa-nga",
    "gn:population":0,
    "gn:timezone":"Asia/Bangkok",
    "iso:country":"TH",
    "name:tha_x_preferred":[
        "\u0e1a\u0e49\u0e32\u0e19\u0e42\u0e19\u0e19\u0e2a\u0e07\u0e48\u0e32"
    ],
    "name:und_x_variant":[
        "Ban Non Sanga",
        "Ban Khok Mai Ka Sang"
    ],
    "wof:name":"Ban Non Sa-nga",
    "wof:placetype":"locality"
},
  "geometry": {"coordinates":[101.63625,15.30247],"type":"Point"}
}