{
  "type": "Feature",
  "properties": {
    "gn:admin1_code":"75.0",
    "gn:asciiname":"Ban Pha Kaeo Noi",
    "gn:country_code":"TH",
    "gn:dem":128,
    "gn:feature_class":"P",
    "gn:feature_code":"PPL",
    "gn:name":"Ban Pha Kaeo Noi",
    "gn:population":0,
    "gn:timezone":"Asia/Bangkok",
    "iso:country":"TH",
    "name:tha_x_preferred":[
        "\u0e1a\u0e49\u0e32\u0e19\u0e1c\u0e32\u0e41\u0e01\u0e49\u0e27\u0e19\u0e49\u0e2d\u0e22"
    ],
    "name:und_x_variant":[
        "Phra Kaeo Noi",
        "Ban Pa Kaeo Noi",
        "Ban Pha Kaeo Noi"
    ],
    "wof:name":"Ban Pha Kaeo Noi",
    "wof:placetype":"locality"
},
  "geometry": {"coordinates":[105.00931,15.30986],"type":"Point"}
}