{
  "type": "Feature",
  "properties": {
    "gn:admin1_code":"18.0",
    "gn:asciiname":"Ban Pang Khom",
    "gn:country_code":"TH",
    "gn:dem":281,
    "gn:feature_class":"P",
    "gn:feature_code":"PPL",
    "gn:name":"Ban Pang Khom",
    "gn:population":0,
    "gn:timezone":"Asia/Bangkok",
    "iso:country":"TH",
    "name:tha_x_preferred":[
        "\u0e1a\u0e49\u0e32\u0e19\u0e1b\u0e32\u0e07\u0e04\u0e2d\u0e21"
    ],
    "wof:name":"Ban Pang Khom",
    "wof:placetype":"locality"
},
  "geometry": {"coordinates":[101.93208,17.84628],"type":"Point"}
}