{
  "type": "Feature",
  "properties": {
    "gn:admin1_code":"6.0",
    "gn:asciiname":"Ban Tha Sompoi",
    "gn:country_code":"TH",
    "gn:dem":250,
    "gn:feature_class":"P",
    "gn:feature_code":"PPL",
    "gn:name":"Ban Tha Sompoi",
    "gn:population":0,
    "gn:timezone":"Asia/Bangkok",
    "iso:country":"TH",
    "name:tha_x_preferred":[
        "\u0e1a\u0e49\u0e32\u0e19\u0e17\u0e48\u0e32\u0e2a\u0e49\u0e21\u0e1b\u0e2d\u0e22"
    ],
    "wof:name":"Ban Tha Sompoi",
    "wof:placetype":"locality"
},
  "geometry": {"coordinates":[99.58789,18.38156],"type":"Point"}
}