{
  "type": "Feature",
  "properties": {
    "gn:admin1_code":"1.0",
    "gn:asciiname":"Ban Mae Kha",
    "gn:country_code":"TH",
    "gn:dem":944,
    "gn:feature_class":"P",
    "gn:feature_code":"PPL",
    "gn:name":"Ban Mae Kha",
    "gn:population":0,
    "gn:timezone":"Asia/Bangkok",
    "iso:country":"TH",
    "name:tha_x_preferred":[
        "\u0e1a\u0e49\u0e32\u0e19\u0e41\u0e21\u0e48\u0e04\u0e30"
    ],
    "wof:name":"Ban Mae Kha",
    "wof:placetype":"locality"
},
  "geometry": {"coordinates":[98.03308,17.84311],"type":"Point"}
}