{
  "type": "Feature",
  "properties": {
    "gn:admin1_code":"76.0",
    "gn:asciiname":"Ban Na Somnuek",
    "gn:country_code":"TH",
    "gn:dem":189,
    "gn:feature_class":"P",
    "gn:feature_code":"PPL",
    "gn:name":"Ban Na Somnuek",
    "gn:population":0,
    "gn:timezone":"Asia/Bangkok",
    "iso:country":"TH",
    "name:tha_x_preferred":[
        "\u0e1a\u0e49\u0e32\u0e19\u0e19\u0e32\u0e2a\u0e21\u0e19\u0e36\u0e01"
    ],
    "wof:name":"Ban Na Somnuek",
    "wof:placetype":"locality"
},
  "geometry": {"coordinates":[102.23244,17.95056],"type":"Point"}
}