{
  "type": "Feature",
  "properties": {
    "gn:admin1_code":"76.0",
    "gn:asciiname":"Ban Champa Thong Noi",
    "gn:country_code":"TH",
    "gn:dem":264,
    "gn:feature_class":"P",
    "gn:feature_code":"PPL",
    "gn:name":"Ban Champa Thong Noi",
    "gn:population":0,
    "gn:timezone":"Asia/Bangkok",
    "iso:country":"TH",
    "name:tha_x_preferred":[
        "\u0e1a\u0e49\u0e32\u0e19\u0e08\u0e33\u0e1b\u0e32\u0e17\u0e2d\u0e07\u0e19\u0e49\u0e2d\u0e22"
    ],
    "wof:name":"Ban Champa Thong Noi",
    "wof:placetype":"locality"
},
  "geometry": {"coordinates":[102.19070000000001,17.69894],"type":"Point"}
}