{
  "type": "Feature",
  "properties": {
    "gn:admin1_code":"55.0",
    "gn:asciiname":"Ban Lat Pla",
    "gn:cc2":"TH",
    "gn:country_code":"TH",
    "gn:dem":8,
    "gn:feature_class":"P",
    "gn:feature_code":"PPL",
    "gn:name":"Ban Lat Pla",
    "gn:population":0,
    "gn:timezone":"Asia/Bangkok",
    "iso:country":"TH",
    "name:und_x_variant":[
        "Ban Lad Pla",
        "Ban Lat Pla"
    ],
    "wof:name":"Ban Lat Pla",
    "wof:placetype":"locality"
},
  "geometry": {"coordinates":[100.23333,13.56667],"type":"Point"}
}