{
  "type": "Feature",
  "properties": {
    "gn:admin1_code":"22",
    "gn:asciiname":"Ban Nikhom",
    "gn:country_code":"TH",
    "gn:dem":185,
    "gn:feature_class":"P",
    "gn:feature_code":"PPL",
    "gn:name":"Ban Nikhom",
    "gn:population":0,
    "gn:timezone":"Asia/Bangkok",
    "iso:country":"TH",
    "name:tha_x_preferred":[
        "\u0e1a\u0e49\u0e32\u0e19\u0e19\u0e34\u0e04\u0e21"
    ],
    "wof:name":"Ban Nikhom",
    "wof:placetype":"locality"
},
  "geometry": {"coordinates":[102.73475000000001,16.34189],"type":"Point"}
}