{
  "type": "Feature",
  "properties": {
    "gn:admin1_code":"4.0",
    "gn:asciiname":"Ban Pu Lon",
    "gn:country_code":"TH",
    "gn:dem":1089,
    "gn:feature_class":"P",
    "gn:feature_code":"PPL",
    "gn:name":"Ban Pu Lon",
    "gn:population":0,
    "gn:timezone":"Asia/Bangkok",
    "iso:country":"TH",
    "name:tha_x_preferred":[
        "\u0e1a\u0e49\u0e32\u0e19\u0e1b\u0e39\u0e2b\u0e25\u0e48\u0e19"
    ],
    "wof:name":"Ban Pu Lon",
    "wof:placetype":"locality"
},
  "geometry": {"coordinates":[101.02392,19.27322],"type":"Point"}
}