{
  "type": "Feature",
  "properties": {
    "gn:admin1_code":"1.0",
    "gn:asciiname":"Ban Mae U Kho",
    "gn:country_code":"TH",
    "gn:dem":1250,
    "gn:feature_class":"P",
    "gn:feature_code":"PPL",
    "gn:name":"Ban Mae U Kho",
    "gn:population":0,
    "gn:timezone":"Asia/Bangkok",
    "iso:country":"TH",
    "name:tha_x_preferred":[
        "\u0e1a\u0e49\u0e32\u0e19\u0e41\u0e21\u0e48\u0e2d\u0e39\u0e04\u0e2d"
    ],
    "wof:name":"Ban Mae U Kho",
    "wof:placetype":"locality"
},
  "geometry": {"coordinates":[98.07635999999999,18.85556],"type":"Point"}
}