{
  "type": "Feature",
  "properties": {
    "gn:admin1_code":"49.0",
    "gn:asciiname":"Ban Wang Chumsaeng",
    "gn:country_code":"TH",
    "gn:dem":21,
    "gn:feature_class":"P",
    "gn:feature_code":"PPL",
    "gn:name":"Ban Wang Chumsaeng",
    "gn:population":0,
    "gn:timezone":"Asia/Bangkok",
    "iso:country":"TH",
    "name:tha_x_preferred":[
        "\u0e1a\u0e49\u0e32\u0e19\u0e27\u0e31\u0e07\u0e0a\u0e38\u0e21\u0e41\u0e2a\u0e07"
    ],
    "wof:name":"Ban Wang Chumsaeng",
    "wof:placetype":"locality"
},
  "geometry": {"coordinates":[102.38849999999999,12.44567],"type":"Point"}
}