{
  "type": "Feature",
  "properties": {
    "gn:admin1_code":"58.0",
    "gn:asciiname":"Ban Don Rak",
    "gn:country_code":"TH",
    "gn:dem":15,
    "gn:feature_class":"P",
    "gn:feature_code":"PPL",
    "gn:name":"Ban Don Rak",
    "gn:population":0,
    "gn:timezone":"Asia/Bangkok",
    "iso:country":"TH",
    "name:tha_x_preferred":[
        "\u0e1a\u0e49\u0e32\u0e19\u0e14\u0e2d\u0e19\u0e23\u0e31\u0e01\u0e29\u0e4c"
    ],
    "wof:name":"Ban Don Rak",
    "wof:placetype":"locality"
},
  "geometry": {"coordinates":[99.18556,10.57597],"type":"Point"}
}