{
  "type": "Feature",
  "properties": {
    "gn:admin1_code":"3.0",
    "gn:asciiname":"Ban San Ton Muang",
    "gn:country_code":"TH",
    "gn:dem":432,
    "gn:feature_class":"P",
    "gn:feature_code":"PPL",
    "gn:name":"Ban San Ton Muang",
    "gn:population":0,
    "gn:timezone":"Asia/Bangkok",
    "iso:country":"TH",
    "name:tha_x_preferred":[
        "\u0e1a\u0e49\u0e32\u0e19\u0e2a\u0e31\u0e19\u0e15\u0e49\u0e19\u0e21\u0e48\u0e27\u0e07"
    ],
    "wof:name":"Ban San Ton Muang",
    "wof:placetype":"locality"
},
  "geometry": {"coordinates":[99.73828,19.65964],"type":"Point"}
}