{
  "type": "Feature",
  "properties": {
    "gn:admin1_code":"14.0",
    "gn:asciiname":"Ban Pha La Noi",
    "gn:country_code":"TH",
    "gn:dem":946,
    "gn:feature_class":"P",
    "gn:feature_code":"PPL",
    "gn:name":"Ban Pha La Noi",
    "gn:population":0,
    "gn:timezone":"Asia/Bangkok",
    "iso:country":"TH",
    "name:tha_x_preferred":[
        "\u0e1a\u0e49\u0e32\u0e19\u0e1c\u0e32\u0e25\u0e32\u0e19\u0e49\u0e2d\u0e22"
    ],
    "wof:name":"Ban Pha La Noi",
    "wof:placetype":"locality"
},
  "geometry": {"coordinates":[101.57378,16.95794],"type":"Point"}
}