{
  "type": "Feature",
  "properties": {
    "gn:admin1_code":"27.0",
    "gn:asciiname":"Ban Phlai",
    "gn:country_code":"TH",
    "gn:dem":164,
    "gn:feature_class":"P",
    "gn:feature_code":"PPL",
    "gn:name":"Ban Phlai",
    "gn:population":0,
    "gn:timezone":"Asia/Bangkok",
    "iso:country":"TH",
    "name:tha_x_preferred":[
        "\u0e1a\u0e49\u0e32\u0e19\u0e44\u0e1e\u0e25"
    ],
    "name:und_x_variant":[
        "Phlai",
        "Ban Phlai",
        "Ban Pha-lai (1)"
    ],
    "wof:name":"Ban Phlai",
    "wof:placetype":"locality"
},
  "geometry": {"coordinates":[102.33333,15.20544],"type":"Point"}
}