{
  "type": "Feature",
  "properties": {
    "gn:admin1_code":"2.0",
    "gn:asciiname":"Ban Pok Pang Nai",
    "gn:country_code":"TH",
    "gn:dem":1098,
    "gn:feature_class":"P",
    "gn:feature_code":"PPL",
    "gn:name":"Ban Pok Pang Nai",
    "gn:population":0,
    "gn:timezone":"Asia/Bangkok",
    "iso:country":"TH",
    "name:tha_x_preferred":[
        "\u0e1a\u0e49\u0e32\u0e19\u0e1b\u0e4a\u0e2d\u0e01\u0e1b\u0e32\u0e07\u0e43\u0e19"
    ],
    "name:und_x_variant":[
        "Ban Pok Nai"
    ],
    "wof:name":"Ban Pok Pang Nai",
    "wof:placetype":"locality"
},
  "geometry": {"coordinates":[99.35894999999999,18.90089],"type":"Point"}
}