{
  "type": "Feature",
  "properties": {
    "gn:admin1_code":"53.0",
    "gn:asciiname":"Ban Don Yaek",
    "gn:country_code":"TH",
    "gn:dem":7,
    "gn:feature_class":"P",
    "gn:feature_code":"PPL",
    "gn:name":"Ban Don Yaek",
    "gn:population":0,
    "gn:timezone":"Asia/Bangkok",
    "iso:country":"TH",
    "name:und_x_variant":[
        "Ban Don Yek",
        "Ban Don Yaek"
    ],
    "wof:name":"Ban Don Yaek",
    "wof:placetype":"locality"
},
  "geometry": {"coordinates":[100.03333000000001,13.71667],"type":"Point"}
}