{
  "type": "Feature",
  "properties": {
    "gn:admin1_code":"29",
    "gn:asciiname":"Ban Khok Samrong",
    "gn:country_code":"TH",
    "gn:dem":169,
    "gn:feature_class":"P",
    "gn:feature_code":"PPL",
    "gn:name":"Ban Khok Samrong",
    "gn:population":0,
    "gn:timezone":"Asia/Bangkok",
    "iso:country":"TH",
    "name:tha_x_preferred":[
        "\u0e1a\u0e49\u0e32\u0e19\u0e42\u0e04\u0e01\u0e2a\u0e33\u0e42\u0e23\u0e07"
    ],
    "wof:name":"Ban Khok Samrong",
    "wof:placetype":"locality"
},
  "geometry": {"coordinates":[104.02875,14.62975],"type":"Point"}
}