{
  "type": "Feature",
  "properties": {
    "gn:admin1_code":"43",
    "gn:asciiname":"Ban Khok Prasoet",
    "gn:country_code":"TH",
    "gn:dem":10,
    "gn:feature_class":"P",
    "gn:feature_code":"PPL",
    "gn:name":"Ban Khok Prasoet",
    "gn:population":0,
    "gn:timezone":"Asia/Bangkok",
    "iso:country":"TH",
    "name:tha_x_preferred":[
        "\u0e1a\u0e49\u0e32\u0e19\u0e42\u0e04\u0e01\u0e1b\u0e23\u0e30\u0e40\u0e2a\u0e23\u0e34\u0e10"
    ],
    "wof:name":"Ban Khok Prasoet",
    "wof:placetype":"locality"
},
  "geometry": {"coordinates":[101.02408,14.23442],"type":"Point"}
}