{
  "type": "Feature",
  "properties": {
    "gn:admin1_code":"47.0",
    "gn:asciiname":"Ban Laem Son",
    "gn:country_code":"TH",
    "gn:dem":6,
    "gn:feature_class":"P",
    "gn:feature_code":"PPL",
    "gn:name":"Ban Laem Son",
    "gn:population":0,
    "gn:timezone":"Asia/Bangkok",
    "iso:country":"TH",
    "name:tha_x_preferred":[
        "\u0e1a\u0e49\u0e32\u0e19\u0e41\u0e2b\u0e25\u0e21\u0e2a\u0e19"
    ],
    "name:und_x_variant":[
        "Paknam Prasae",
        "Ban Pak Nam Prasae",
        "Ban Pak Nam Krasae",
        "Ban Laem Son"
    ],
    "wof:lang_x_official":[
        "tha"
    ],
    "wof:lang_x_spoken":[
        "tha"
    ],
    "wof:name":"Ban Laem Son",
    "wof:placetype":"locality"
},
  "geometry": {"coordinates":[101.70035,12.69846],"type":"Point"}
}