{
  "type": "Feature",
  "properties": {
    "gn:admin1_code":"30.0",
    "gn:asciiname":"Ban Phue",
    "gn:country_code":"TH",
    "gn:dem":138,
    "gn:feature_class":"P",
    "gn:feature_code":"PPL",
    "gn:name":"Ban Phue",
    "gn:population":0,
    "gn:timezone":"Asia/Bangkok",
    "iso:country":"TH",
    "name:tha_x_preferred":[
        "\u0e1a\u0e49\u0e32\u0e19\u0e1c\u0e37\u0e2d"
    ],
    "name:und_x_variant":[
        "Ban Phu"
    ],
    "wof:name":"Ban Phue",
    "wof:placetype":"locality"
},
  "geometry": {"coordinates":[104.11257999999999,15.23942],"type":"Point"}
}