{
  "type": "Feature",
  "properties": {
    "gn:admin1_code":"13.0",
    "gn:asciiname":"Ban Sai Huai",
    "gn:country_code":"TH",
    "gn:dem":35,
    "gn:feature_class":"P",
    "gn:feature_code":"PPL",
    "gn:name":"Ban Sai Huai",
    "gn:population":0,
    "gn:timezone":"Asia/Bangkok",
    "iso:country":"TH",
    "name:tha_x_preferred":[
        "\u0e1a\u0e49\u0e32\u0e19\u0e2a\u0e32\u0e22\u0e2b\u0e49\u0e27\u0e22"
    ],
    "wof:name":"Ban Sai Huai",
    "wof:placetype":"locality"
},
  "geometry": {"coordinates":[100.43631000000001,15.98133],"type":"Point"}
}