{
  "type": "Feature",
  "properties": {
    "gn:admin1_code":"17.0",
    "gn:asciiname":"Ban Erawan",
    "gn:country_code":"TH",
    "gn:dem":169,
    "gn:feature_class":"P",
    "gn:feature_code":"PPL",
    "gn:name":"Ban Erawan",
    "gn:population":0,
    "gn:timezone":"Asia/Bangkok",
    "iso:country":"TH",
    "name:tha_x_preferred":[
        "\u0e1a\u0e49\u0e32\u0e19\u0e40\u0e2d\u0e23\u0e32\u0e27\u0e31\u0e13"
    ],
    "wof:name":"Ban Erawan",
    "wof:placetype":"locality"
},
  "geometry": {"coordinates":[103.08,17.99675],"type":"Point"}
}