{
  "type": "Feature",
  "properties": {
    "gn:admin1_code":"28.0",
    "gn:asciiname":"Ban Lahan Sai Mai",
    "gn:country_code":"TH",
    "gn:dem":186,
    "gn:feature_class":"P",
    "gn:feature_code":"PPL",
    "gn:name":"Ban Lahan Sai Mai",
    "gn:population":0,
    "gn:timezone":"Asia/Bangkok",
    "iso:country":"TH",
    "name:tha_x_preferred":[
        "\u0e1a\u0e49\u0e32\u0e19\u0e25\u0e30\u0e2b\u0e32\u0e19\u0e17\u0e23\u0e32\u0e22\u0e43\u0e2b\u0e21\u0e48"
    ],
    "wof:name":"Ban Lahan Sai Mai",
    "wof:placetype":"locality"
},
  "geometry": {"coordinates":[103.13881000000001,14.47795],"type":"Point"}
}