{
  "type": "Feature",
  "properties": {
    "gn:admin1_code":"26.0",
    "gn:asciiname":"Ban Nong Phak Bung",
    "gn:country_code":"TH",
    "gn:dem":278,
    "gn:feature_class":"P",
    "gn:feature_code":"PPL",
    "gn:name":"Ban Nong Phak Bung",
    "gn:population":0,
    "gn:timezone":"Asia/Bangkok",
    "iso:country":"TH",
    "name:tha_x_preferred":[
        "\u0e1a\u0e49\u0e32\u0e19\u0e2b\u0e19\u0e2d\u0e07\u0e1c\u0e31\u0e01\u0e1a\u0e38\u0e49\u0e07"
    ],
    "wof:name":"Ban Nong Phak Bung",
    "wof:placetype":"locality"
},
  "geometry": {"coordinates":[101.49003,15.45047],"type":"Point"}
}