{
  "type": "Feature",
  "properties": {
    "gn:admin1_code":"22",
    "gn:asciiname":"Ban Huai Rai Tai",
    "gn:country_code":"TH",
    "gn:dem":176,
    "gn:feature_class":"P",
    "gn:feature_code":"PPL",
    "gn:name":"Ban Huai Rai Tai",
    "gn:population":0,
    "gn:timezone":"Asia/Bangkok",
    "iso:country":"TH",
    "name:tha_x_preferred":[
        "\u0e1a\u0e49\u0e32\u0e19\u0e2b\u0e49\u0e27\u0e22\u0e44\u0e23\u0e48\u0e43\u0e15\u0e49"
    ],
    "wof:name":"Ban Huai Rai Tai",
    "wof:placetype":"locality"
},
  "geometry": {"coordinates":[102.56697,16.06269],"type":"Point"}
}