{
  "type": "Feature",
  "properties": {
    "gn:admin1_code":"74.0",
    "gn:asciiname":"Ban Bang Kung",
    "gn:country_code":"TH",
    "gn:dem":10,
    "gn:feature_class":"P",
    "gn:feature_code":"PPL",
    "gn:name":"Ban Bang Kung",
    "gn:population":0,
    "gn:timezone":"Asia/Bangkok",
    "iso:country":"TH",
    "name:tha_x_preferred":[
        "\u0e1a\u0e49\u0e32\u0e19\u0e1a\u0e32\u0e07\u0e01\u0e38\u0e49\u0e07"
    ],
    "name:und_x_variant":[
        "Bang Kung",
        "Ban Bang Kung"
    ],
    "wof:name":"Ban Bang Kung",
    "wof:placetype":"locality"
},
  "geometry": {"coordinates":[101.47431,13.97811],"type":"Point"}
}