{
  "type": "Feature",
  "properties": {
    "gn:admin1_code":"30.0",
    "gn:asciiname":"Ban Huai Nam Thip",
    "gn:country_code":"TH",
    "gn:dem":167,
    "gn:feature_class":"P",
    "gn:feature_code":"PPL",
    "gn:name":"Ban Huai Nam Thip",
    "gn:population":0,
    "gn:timezone":"Asia/Bangkok",
    "iso:country":"TH",
    "name:tha_x_preferred":[
        "\u0e1a\u0e49\u0e32\u0e19\u0e2b\u0e49\u0e27\u0e22\u0e19\u0e49\u0e33\u0e17\u0e34\u0e1e\u0e22\u0e4c"
    ],
    "wof:name":"Ban Huai Nam Thip",
    "wof:placetype":"locality"
},
  "geometry": {"coordinates":[104.77518999999999,14.72842],"type":"Point"}
}