{
  "type": "Feature",
  "properties": {
    "gn:admin1_code":"2.0",
    "gn:asciiname":"Ban Yang Kaeo",
    "gn:country_code":"TH",
    "gn:dem":916,
    "gn:feature_class":"P",
    "gn:feature_code":"PPL",
    "gn:name":"Ban Yang Kaeo",
    "gn:population":0,
    "gn:timezone":"Asia/Bangkok",
    "iso:country":"TH",
    "name:tha_x_preferred":[
        "\u0e1a\u0e49\u0e32\u0e19\u0e22\u0e32\u0e07\u0e41\u0e01\u0e49\u0e27"
    ],
    "wof:name":"Ban Yang Kaeo",
    "wof:placetype":"locality"
},
  "geometry": {"coordinates":[98.41458,17.86013999999999],"type":"Point"}
}