{
  "type": "Feature",
  "properties": {
    "gn:admin1_code":"70.0",
    "gn:asciiname":"Ban Nam Tok Song Kha",
    "gn:country_code":"TH",
    "gn:dem":566,
    "gn:feature_class":"P",
    "gn:feature_code":"PPL",
    "gn:name":"Ban Nam Tok Song Kha",
    "gn:population":0,
    "gn:timezone":"Asia/Bangkok",
    "iso:country":"TH",
    "name:tha_x_preferred":[
        "\u0e1a\u0e49\u0e32\u0e19\u0e19\u0e49\u0e33\u0e15\u0e01\u0e2a\u0e2d\u0e07\u0e40\u0e02\u0e32"
    ],
    "name:tha_x_variant":[
        "\u0e1a\u0e49\u0e32\u0e19\u0e19\u0e49\u0e33\u0e15\u0e01\u0e2a\u0e2d\u0e07\u0e02\u0e32"
    ],
    "name:und_x_variant":[
        "Ban Nam Tok Song Khao",
        "Ban Nam Tok Song Kha"
    ],
    "wof:name":"Ban Nam Tok Song Kha",
    "wof:placetype":"locality"
},
  "geometry": {"coordinates":[101.14308,6.06131],"type":"Point"}
}