{
  "type": "Feature",
  "properties": {
    "gn:admin1_code":"48.0",
    "gn:asciiname":"Ban Kaphraek On",
    "gn:cc2":"TH",
    "gn:country_code":"TH",
    "gn:dem":26,
    "gn:feature_class":"P",
    "gn:feature_code":"PPL",
    "gn:name":"Ban Kaphraek On",
    "gn:population":0,
    "gn:timezone":"Asia/Bangkok",
    "iso:country":"TH",
    "name:und_x_variant":[
        "Kaphreak On",
        "Ban Kaphraek On"
    ],
    "wof:name":"Ban Kaphraek On",
    "wof:placetype":"locality"
},
  "geometry": {"coordinates":[102.08333,12.78333],"type":"Point"}
}