{
  "type": "Feature",
  "properties": {
    "gn:admin1_code":"7.0",
    "gn:asciiname":"Ban Mae Chong Fai",
    "gn:country_code":"TH",
    "gn:dem":237,
    "gn:feature_class":"P",
    "gn:feature_code":"PPL",
    "gn:name":"Ban Mae Chong Fai",
    "gn:population":0,
    "gn:timezone":"Asia/Bangkok",
    "iso:country":"TH",
    "name:tha_x_preferred":[
        "\u0e1a\u0e49\u0e32\u0e19\u0e41\u0e21\u0e48\u0e08\u0e2d\u0e07\u0e44\u0e1f"
    ],
    "wof:name":"Ban Mae Chong Fai",
    "wof:placetype":"locality"
},
  "geometry": {"coordinates":[99.80164000000001,18.13675],"type":"Point"}
}