{
  "type": "Feature",
  "properties": {
    "gn:admin1_code":"52.0",
    "gn:asciiname":"Ban Chom Prasat",
    "gn:country_code":"TH",
    "gn:dem":10,
    "gn:feature_class":"P",
    "gn:feature_code":"PPL",
    "gn:name":"Ban Chom Prasat",
    "gn:population":0,
    "gn:timezone":"Asia/Bangkok",
    "iso:country":"TH",
    "name:tha_x_preferred":[
        "\u0e1a\u0e49\u0e32\u0e19\u0e08\u0e2d\u0e21\u0e1b\u0e23\u0e32\u0e2a\u0e32\u0e17"
    ],
    "name:und_x_variant":[
        "Ban Chom Prathat"
    ],
    "wof:lang_x_official":[
        "tha"
    ],
    "wof:lang_x_spoken":[
        "tha"
    ],
    "wof:name":"Ban Chom Prasat",
    "wof:placetype":"locality"
},
  "geometry": {"coordinates":[99.82483000000001,13.68011],"type":"Point"}
}