{
  "type": "Feature",
  "properties": {
    "gn:admin1_code":"32.0",
    "gn:asciiname":"Ban Bang Nam Phra",
    "gn:country_code":"TH",
    "gn:dem":21,
    "gn:feature_class":"P",
    "gn:feature_code":"PPL",
    "gn:name":"Ban Bang Nam Phra",
    "gn:population":0,
    "gn:timezone":"Asia/Bangkok",
    "iso:country":"TH",
    "name:tha_x_preferred":[
        "\u0e1a\u0e49\u0e32\u0e19\u0e1a\u0e32\u0e07\u0e19\u0e49\u0e33\u0e1e\u0e23\u0e30"
    ],
    "wof:name":"Ban Bang Nam Phra",
    "wof:placetype":"locality"
},
  "geometry": {"coordinates":[100.17874999999999,15.03847],"type":"Point"}
}