{
  "type": "Feature",
  "properties": {
    "gn:admin1_code":"17.0",
    "gn:asciiname":"Ban Na Kham Mun",
    "gn:country_code":"TH",
    "gn:dem":205,
    "gn:feature_class":"P",
    "gn:feature_code":"PPL",
    "gn:name":"Ban Na Kham Mun",
    "gn:population":0,
    "gn:timezone":"Asia/Bangkok",
    "iso:country":"TH",
    "name:tha_x_preferred":[
        "\u0e1a\u0e49\u0e32\u0e19\u0e19\u0e32\u0e04\u0e33\u0e21\u0e39\u0e25"
    ],
    "wof:name":"Ban Na Kham Mun",
    "wof:placetype":"locality"
},
  "geometry": {"coordinates":[103.30074999999999,18.16622000000001],"type":"Point"}
}