{
  "type": "Feature",
  "properties": {
    "gn:admin1_code":"5.0",
    "gn:asciiname":"Muban Chatsan",
    "gn:country_code":"TH",
    "gn:dem":321,
    "gn:feature_class":"P",
    "gn:feature_code":"PPL",
    "gn:name":"Muban Chatsan",
    "gn:population":0,
    "gn:timezone":"Asia/Bangkok",
    "iso:country":"TH",
    "name:tha_x_preferred":[
        "\u0e2b\u0e21\u0e39\u0e48\u0e1a\u0e49\u0e32\u0e19\u0e08\u0e31\u0e14\u0e2a\u0e23\u0e23"
    ],
    "wof:name":"Muban Chatsan",
    "wof:placetype":"locality"
},
  "geometry": {"coordinates":[99.02275,18.48458],"type":"Point"}
}