{
  "type": "Feature",
  "properties": {
    "gn:admin1_code":"34",
    "gn:asciiname":"Ban Khao Phra Ngam",
    "gn:country_code":"TH",
    "gn:dem":27,
    "gn:feature_class":"P",
    "gn:feature_code":"PPL",
    "gn:name":"Ban Khao Phra Ngam",
    "gn:population":0,
    "gn:timezone":"Asia/Bangkok",
    "iso:country":"TH",
    "name:tha_x_preferred":[
        "\u0e1a\u0e49\u0e32\u0e19\u0e40\u0e02\u0e32\u0e1e\u0e23\u0e30\u0e07\u0e32\u0e21"
    ],
    "wof:name":"Ban Khao Phra Ngam",
    "wof:placetype":"locality"
},
  "geometry": {"coordinates":[100.63052999999999,14.89361],"type":"Point"}
}