{
  "type": "Feature",
  "properties": {
    "gn:admin1_code":"79.0",
    "gn:asciiname":"Ban Khok Pa Kung",
    "gn:country_code":"TH",
    "gn:dem":228,
    "gn:feature_class":"P",
    "gn:feature_code":"PPL",
    "gn:name":"Ban Khok Pa Kung",
    "gn:population":0,
    "gn:timezone":"Asia/Bangkok",
    "iso:country":"TH",
    "name:tha_x_preferred":[
        "\u0e1a\u0e49\u0e32\u0e19\u0e42\u0e04\u0e01\u0e1b\u0e48\u0e32\u0e01\u0e38\u0e07"
    ],
    "wof:name":"Ban Khok Pa Kung",
    "wof:placetype":"locality"
},
  "geometry": {"coordinates":[102.34872,16.99669],"type":"Point"}
}