{
  "type": "Feature",
  "properties": {
    "gn:admin1_code":"37.0",
    "gn:asciiname":"Ban Wihan Daeng",
    "gn:country_code":"TH",
    "gn:dem":11,
    "gn:feature_class":"P",
    "gn:feature_code":"PPL",
    "gn:name":"Ban Wihan Daeng",
    "gn:population":0,
    "gn:timezone":"Asia/Bangkok",
    "iso:country":"TH",
    "name:tha_x_preferred":[
        "\u0e1a\u0e49\u0e32\u0e19\u0e27\u0e34\u0e2b\u0e32\u0e23\u0e41\u0e14\u0e07"
    ],
    "wof:name":"Ban Wihan Daeng",
    "wof:placetype":"locality"
},
  "geometry": {"coordinates":[101.0065,14.33847],"type":"Point"}
}