{
  "type": "Feature",
  "properties": {
    "gn:admin1_code":"27",
    "gn:asciiname":"Ban Nong Prasoet",
    "gn:country_code":"TH",
    "gn:dem":206,
    "gn:feature_class":"P",
    "gn:feature_code":"PPL",
    "gn:name":"Ban Nong Prasoet",
    "gn:population":0,
    "gn:timezone":"Asia/Bangkok",
    "iso:country":"TH",
    "name:tha_x_preferred":[
        "\u0e1a\u0e49\u0e32\u0e19\u0e2b\u0e19\u0e2d\u0e07\u0e1b\u0e23\u0e30\u0e40\u0e2a\u0e23\u0e34\u0e10"
    ],
    "wof:lang_x_official":[
        "tha"
    ],
    "wof:lang_x_spoken":[
        "tha"
    ],
    "wof:name":"Ban Nong Prasoet",
    "wof:placetype":"locality"
},
  "geometry": {"coordinates":[102.34472,14.81175],"type":"Point"}
}