{
  "type": "Feature",
  "properties": {
    "gn:admin1_code":"64.0",
    "gn:asciiname":"Ban Thung Pon",
    "gn:country_code":"TH",
    "gn:dem":36,
    "gn:feature_class":"P",
    "gn:feature_code":"PPL",
    "gn:name":"Ban Thung Pon",
    "gn:population":0,
    "gn:timezone":"Asia/Bangkok",
    "iso:country":"TH",
    "name:tha_x_preferred":[
        "\u0e1a\u0e49\u0e32\u0e19\u0e17\u0e38\u0e48\u0e07\u0e1b\u0e2d\u0e19"
    ],
    "wof:name":"Ban Thung Pon",
    "wof:placetype":"locality"
},
  "geometry": {"coordinates":[99.54197000000001,8.37669],"type":"Point"}
}