{
  "type": "Feature",
  "properties": {
    "gn:admin1_code":"64.0",
    "gn:asciiname":"Ban Phraek Klang",
    "gn:country_code":"TH",
    "gn:dem":38,
    "gn:feature_class":"P",
    "gn:feature_code":"PPL",
    "gn:name":"Ban Phraek Klang",
    "gn:population":0,
    "gn:timezone":"Asia/Bangkok",
    "iso:country":"TH",
    "name:tha_x_preferred":[
        "\u0e1a\u0e49\u0e32\u0e19\u0e41\u0e1e\u0e23\u0e01\u0e01\u0e25\u0e32\u0e07"
    ],
    "wof:name":"Ban Phraek Klang",
    "wof:placetype":"locality"
},
  "geometry": {"coordinates":[99.40617,8.52264],"type":"Point"}
}