{
  "type": "Feature",
  "properties": {
    "gn:admin1_code":"18.0",
    "gn:asciiname":"Ban Kok Kan Luaeng",
    "gn:country_code":"TH",
    "gn:dem":291,
    "gn:feature_class":"P",
    "gn:feature_code":"PPL",
    "gn:name":"Ban Kok Kan Luaeng",
    "gn:population":0,
    "gn:timezone":"Asia/Bangkok",
    "iso:country":"TH",
    "name:tha_x_preferred":[
        "\u0e1a\u0e49\u0e32\u0e19\u0e01\u0e01\u0e01\u0e49\u0e32\u0e19\u0e40\u0e2b\u0e25\u0e37\u0e2d\u0e07"
    ],
    "wof:name":"Ban Kok Kan Luaeng",
    "wof:placetype":"locality"
},
  "geometry": {"coordinates":[101.41656,17.56958],"type":"Point"}
}