{
  "type": "Feature",
  "properties": {
    "gn:admin1_code":"50.0",
    "gn:asciiname":"Ban Ong Thi",
    "gn:country_code":"TH",
    "gn:dem":121,
    "gn:feature_class":"P",
    "gn:feature_code":"PPL",
    "gn:name":"Ban Ong Thi",
    "gn:population":0,
    "gn:timezone":"Asia/Bangkok",
    "iso:country":"TH",
    "name:tha_x_preferred":[
        "\u0e1a\u0e49\u0e32\u0e19\u0e2d\u0e07\u0e17\u0e34"
    ],
    "wof:name":"Ban Ong Thi",
    "wof:placetype":"locality"
},
  "geometry": {"coordinates":[98.68025,14.71342],"type":"Point"}
}