{
  "type": "Feature",
  "properties": {
    "gn:admin1_code":"59.0",
    "gn:asciiname":"Ban Bang Kaeo Yai",
    "gn:country_code":"TH",
    "gn:dem":12,
    "gn:feature_class":"P",
    "gn:feature_code":"PPL",
    "gn:name":"Ban Bang Kaeo Yai",
    "gn:population":0,
    "gn:timezone":"Asia/Bangkok",
    "iso:country":"TH",
    "name:tha_x_preferred":[
        "\u0e1a\u0e49\u0e32\u0e19\u0e1a\u0e32\u0e07\u0e41\u0e01\u0e49\u0e27\u0e43\u0e2b\u0e0d\u0e48"
    ],
    "name:und_x_variant":[
        "B\u0101n B\u0101ng Geo",
        "Ban Bang Kaeo"
    ],
    "wof:lang_x_official":[
        "tha"
    ],
    "wof:lang_x_spoken":[
        "tha"
    ],
    "wof:name":"Ban Bang Kaeo Yai",
    "wof:placetype":"locality"
},
  "geometry": {"coordinates":[98.78364000000001,10.17528],"type":"Point"}
}