{
  "type": "Feature",
  "properties": {
    "gn:admin1_code":"46.0",
    "gn:asciiname":"Ban Map Pong",
    "gn:country_code":"TH",
    "gn:dem":10,
    "gn:feature_class":"P",
    "gn:feature_code":"PPL",
    "gn:name":"Ban Map Pong",
    "gn:population":0,
    "gn:timezone":"Asia/Bangkok",
    "iso:country":"TH",
    "name:tha_x_preferred":[
        "\u0e1a\u0e49\u0e32\u0e19\u0e21\u0e32\u0e1a\u0e42\u0e1b\u0e48\u0e07"
    ],
    "name:tha_x_variant":[
        "Ban Map Pong"
    ],
    "name:und_x_variant":[
        "Map Pong",
        "Ban Huai Map Pong"
    ],
    "wof:name":"Ban Map Pong",
    "wof:placetype":"locality"
},
  "geometry": {"coordinates":[101.11772000000001,13.423],"type":"Point"}
}