{
  "type": "Feature",
  "properties": {
    "gn:admin1_code":"73.0",
    "gn:asciiname":"Ban Lek Nai Pa Yai",
    "gn:country_code":"TH",
    "gn:dem":188,
    "gn:feature_class":"P",
    "gn:feature_code":"PPL",
    "gn:name":"Ban Lek Nai Pa Yai",
    "gn:population":0,
    "gn:timezone":"Asia/Bangkok",
    "iso:country":"TH",
    "name:tha_x_preferred":[
        "Ban Lek Nai Pa Yai"
    ],
    "name:tha_x_variant":[
        "\u0e1a\u0e49\u0e32\u0e19\u0e40\u0e25\u0e47\u0e01\u0e43\u0e19\u0e1b\u0e48\u0e32\u0e43\u0e2b\u0e0d\u0e48"
    ],
    "wof:name":"Ban Lek Nai Pa Yai",
    "wof:placetype":"locality"
},
  "geometry": {"coordinates":[104.46725000000001,17.27175],"type":"Point"}
}