{
  "type": "Feature",
  "properties": {
    "gn:admin1_code":"77.0",
    "gn:asciiname":"Ban Non Samran",
    "gn:country_code":"TH",
    "gn:dem":141,
    "gn:feature_class":"P",
    "gn:feature_code":"PPL",
    "gn:name":"Ban Non Samran",
    "gn:population":0,
    "gn:timezone":"Asia/Bangkok",
    "iso:country":"TH",
    "name:tha_x_preferred":[
        "Ban Non Samran"
    ],
    "name:tha_x_variant":[
        "\u0e1a\u0e49\u0e32\u0e19\u0e42\u0e19\u0e19\u0e2a\u0e33\u0e23\u0e32\u0e0d"
    ],
    "wof:name":"Ban Non Samran",
    "wof:placetype":"locality"
},
  "geometry": {"coordinates":[105.00569,16.20572],"type":"Point"}
}