{
  "type": "Feature",
  "properties": {
    "gn:admin1_code":"58.0",
    "gn:asciiname":"Ban Wang Khrok",
    "gn:country_code":"TH",
    "gn:dem":15,
    "gn:feature_class":"P",
    "gn:feature_code":"PPL",
    "gn:name":"Ban Wang Khrok",
    "gn:population":0,
    "gn:timezone":"Asia/Bangkok",
    "iso:country":"TH",
    "name:tha_x_preferred":[
        "\u0e1a\u0e49\u0e32\u0e19\u0e27\u0e31\u0e07\u0e04\u0e23\u0e01"
    ],
    "name:und_x_variant":[
        "Wang Grok",
        "Ban Wang Khrok"
    ],
    "wof:name":"Ban Wang Khrok",
    "wof:placetype":"locality"
},
  "geometry": {"coordinates":[99.14261,10.59408],"type":"Point"}
}