{
  "type": "Feature",
  "properties": {
    "gn:admin1_code":"31.0",
    "gn:asciiname":"Ban Thop",
    "gn:cc2":"TH",
    "gn:country_code":"TH",
    "gn:dem":7,
    "gn:feature_class":"P",
    "gn:feature_code":"PPL",
    "gn:name":"Ban Thop",
    "gn:population":0,
    "gn:timezone":"Asia/Bangkok",
    "iso:country":"TH",
    "name:und_x_variant":[
        "Ban Thaup",
        "Ban Thob",
        "Ban Thop"
    ],
    "wof:name":"Ban Thop",
    "wof:placetype":"locality"
},
  "geometry": {"coordinates":[101.75,6.53333],"type":"Point"}
}