{
  "type": "Feature",
  "properties": {
    "gn:admin1_code":"33",
    "gn:asciiname":"Ban Wat Yuat",
    "gn:country_code":"TH",
    "gn:dem":11,
    "gn:feature_class":"P",
    "gn:feature_code":"PPL",
    "gn:name":"Ban Wat Yuat",
    "gn:population":0,
    "gn:timezone":"Asia/Bangkok",
    "iso:country":"TH",
    "name:tha_x_preferred":[
        "\u0e1a\u0e49\u0e32\u0e19\u0e27\u0e31\u0e14\u0e22\u0e27\u0e14"
    ],
    "wof:name":"Ban Wat Yuat",
    "wof:placetype":"locality"
},
  "geometry": {"coordinates":[100.37775000000001,14.90069],"type":"Point"}
}