{
  "type": "Feature",
  "properties": {
    "gn:admin1_code":"53.0",
    "gn:asciiname":"Ban Thap Luang",
    "gn:country_code":"TH",
    "gn:dem":9,
    "gn:feature_class":"P",
    "gn:feature_code":"PPL",
    "gn:name":"Ban Thap Luang",
    "gn:population":0,
    "gn:timezone":"Asia/Bangkok",
    "iso:country":"TH",
    "name:tha_x_preferred":[
        "\u0e1a\u0e49\u0e32\u0e19\u0e17\u0e31\u0e1e\u0e2b\u0e25\u0e27\u0e07"
    ],
    "name:und_x_variant":[
        "Ban Tap Luang",
        "Ban Thap Luang",
        "\u0e1a\u0e49\u0e32\u0e19\u0e17\u0e31\u0e1e\u0e2b\u0e25\u0e27\u0e07"
    ],
    "wof:name":"Ban Thap Luang",
    "wof:placetype":"locality"
},
  "geometry": {"coordinates":[100.0115,13.87281],"type":"Point"}
}