{
  "type": "Feature",
  "properties": {
    "gn:admin1_code":"4.0",
    "gn:asciiname":"Ban Song Khwae",
    "gn:country_code":"TH",
    "gn:dem":298,
    "gn:feature_class":"P",
    "gn:feature_code":"PPL",
    "gn:name":"Ban Song Khwae",
    "gn:population":0,
    "gn:timezone":"Asia/Bangkok",
    "iso:country":"TH",
    "name:tha_x_preferred":[
        "\u0e1a\u0e49\u0e32\u0e19\u0e2a\u0e2d\u0e07\u0e41\u0e04\u0e27"
    ],
    "wof:name":"Ban Song Khwae",
    "wof:placetype":"locality"
},
  "geometry": {"coordinates":[100.63556,18.86422],"type":"Point"}
}