{
  "type": "Feature",
  "properties": {
    "gn:admin1_code":"47.0",
    "gn:asciiname":"Ban Talat Ton Klang",
    "gn:country_code":"TH",
    "gn:dem":6,
    "gn:feature_class":"P",
    "gn:feature_code":"PPL",
    "gn:name":"Ban Talat Ton Klang",
    "gn:population":0,
    "gn:timezone":"Asia/Bangkok",
    "iso:country":"TH",
    "name:tha_x_preferred":[
        "\u0e1a\u0e49\u0e32\u0e19\u0e15\u0e25\u0e32\u0e14\u0e15\u0e2d\u0e19\u0e01\u0e25\u0e32\u0e07"
    ],
    "wof:name":"Ban Talat Ton Klang",
    "wof:placetype":"locality"
},
  "geometry": {"coordinates":[101.70444000000001,12.70833],"type":"Point"}
}