{
  "type": "Feature",
  "properties": {
    "gn:admin1_code":"13.0",
    "gn:asciiname":"Ban Tha Phutsa",
    "gn:country_code":"TH",
    "gn:dem":38,
    "gn:feature_class":"P",
    "gn:feature_code":"PPL",
    "gn:name":"Ban Tha Phutsa",
    "gn:population":0,
    "gn:timezone":"Asia/Bangkok",
    "iso:country":"TH",
    "name:tha_x_preferred":[
        "\u0e1a\u0e49\u0e32\u0e19\u0e17\u0e48\u0e32\u0e1e\u0e38\u0e17\u0e23\u0e32"
    ],
    "wof:name":"Ban Tha Phutsa",
    "wof:placetype":"locality"
},
  "geometry": {"coordinates":[100.30800000000001,16.36175],"type":"Point"}
}