{
  "type": "Feature",
  "properties": {
    "gn:admin1_code":"41.0",
    "gn:asciiname":"Ban Pong Sanuk",
    "gn:country_code":"TH",
    "gn:dem":267,
    "gn:feature_class":"P",
    "gn:feature_code":"PPL",
    "gn:name":"Ban Pong Sanuk",
    "gn:population":0,
    "gn:timezone":"Asia/Bangkok",
    "iso:country":"TH",
    "name:tha_x_preferred":[
        "\u0e1a\u0e49\u0e32\u0e19\u0e1b\u0e07\u0e2a\u0e19\u0e38\u0e01"
    ],
    "wof:name":"Ban Pong Sanuk",
    "wof:placetype":"locality"
},
  "geometry": {"coordinates":[100.28574999999999,18.87758],"type":"Point"}
}