{
  "type": "Feature",
  "properties": {
    "gn:admin1_code":"3.0",
    "gn:asciiname":"Ban Pa Sang (1)",
    "gn:country_code":"TH",
    "gn:dem":387,
    "gn:feature_class":"P",
    "gn:feature_code":"PPL",
    "gn:name":"Ban Pa Sang (1)",
    "gn:population":0,
    "gn:timezone":"Asia/Bangkok",
    "iso:country":"TH",
    "name:tha_x_preferred":[
        "\u0e1a\u0e49\u0e32\u0e19\u0e1b\u0e48\u0e32\u0e0b\u0e32\u0e07 (\u0e2b\u0e19\u0e36\u0e48\u0e07)"
    ],
    "name:tha_x_variant":[
        "\u0e1a\u0e49\u0e32\u0e19\u0e1b\u0e48\u0e32\u0e0b\u0e32\u0e07 (1)"
    ],
    "name:und_x_variant":[
        "Ban Pa Sing",
        "Ban Pa Sang (1)",
        "Ban Pa Sang (Nueng)"
    ],
    "wof:name":"Ban Pa Sang (1)",
    "wof:placetype":"locality"
},
  "geometry": {"coordinates":[99.89481000000001,20.00786],"type":"Point"}
}