{
  "type": "Feature",
  "properties": {
    "gn:admin1_code":"23.0",
    "gn:asciiname":"Ban Dong Udom",
    "gn:country_code":"TH",
    "gn:dem":212,
    "gn:feature_class":"P",
    "gn:feature_code":"PPL",
    "gn:name":"Ban Dong Udom",
    "gn:population":0,
    "gn:timezone":"Asia/Bangkok",
    "iso:country":"TH",
    "name:tha_x_preferred":[
        "\u0e1a\u0e49\u0e32\u0e19\u0e14\u0e07\u0e2d\u0e38\u0e14\u0e21"
    ],
    "wof:name":"Ban Dong Udom",
    "wof:placetype":"locality"
},
  "geometry": {"coordinates":[103.84435999999999,16.71786],"type":"Point"}
}