{
  "type": "Feature",
  "properties": {
    "gn:admin1_code":"3.0",
    "gn:asciiname":"Ban Huai Maduea",
    "gn:country_code":"TH",
    "gn:dem":578,
    "gn:feature_class":"P",
    "gn:feature_code":"PPL",
    "gn:name":"Ban Huai Maduea",
    "gn:population":0,
    "gn:timezone":"Asia/Bangkok",
    "iso:country":"TH",
    "name:tha_x_preferred":[
        "\u0e1a\u0e49\u0e32\u0e19\u0e2b\u0e49\u0e27\u0e22\u0e21\u0e30\u0e40\u0e14\u0e37\u0e48\u0e2d"
    ],
    "wof:name":"Ban Huai Maduea",
    "wof:placetype":"locality"
},
  "geometry": {"coordinates":[99.42142,19.39136],"type":"Point"}
}