{
  "type": "Feature",
  "properties": {
    "gn:admin1_code":"3.0",
    "gn:asciiname":"Ban Kralae",
    "gn:country_code":"TH",
    "gn:dem":423,
    "gn:feature_class":"P",
    "gn:feature_code":"PPL",
    "gn:name":"Ban Kralae",
    "gn:population":0,
    "gn:timezone":"Asia/Bangkok",
    "iso:country":"TH",
    "name:tha_x_preferred":[
        "\u0e1a\u0e49\u0e32\u0e19\u0e01\u0e23\u0e30\u0e41\u0e25"
    ],
    "wof:name":"Ban Kralae",
    "wof:placetype":"locality"
},
  "geometry": {"coordinates":[100.14208000000001,19.93247],"type":"Point"}
}