{
  "type": "Feature",
  "properties": {
    "gn:admin1_code":"28.0",
    "gn:asciiname":"Ban Don Yong",
    "gn:country_code":"TH",
    "gn:dem":162,
    "gn:feature_class":"P",
    "gn:feature_code":"PPL",
    "gn:name":"Ban Don Yong",
    "gn:population":0,
    "gn:timezone":"Asia/Bangkok",
    "iso:country":"TH",
    "name:tha_x_preferred":[
        "\u0e1a\u0e49\u0e32\u0e19\u0e14\u0e2d\u0e19\u0e22\u0e2d\u0e07"
    ],
    "name:und_x_variant":[
        "Daun Yong",
        "Ban Don Yong",
        "Ban Don Yang"
    ],
    "wof:name":"Ban Don Yong",
    "wof:placetype":"locality"
},
  "geometry": {"coordinates":[103.28400000000001,15.12344],"type":"Point"}
}