{
  "type": "Feature",
  "properties": {
    "gn:admin1_code":"46.0",
    "gn:asciiname":"Ban Pong Tamuk",
    "gn:country_code":"TH",
    "gn:dem":18,
    "gn:feature_class":"P",
    "gn:feature_code":"PPL",
    "gn:name":"Ban Pong Tamuk",
    "gn:population":0,
    "gn:timezone":"Asia/Bangkok",
    "iso:country":"TH",
    "name:tha_x_preferred":[
        "\u0e1a\u0e49\u0e32\u0e19\u0e42\u0e1b\u0e48\u0e07\u0e15\u0e32\u0e21\u0e38\u0e02"
    ],
    "name:und_x_variant":[
        "Ban Pong Ta Muk"
    ],
    "wof:name":"Ban Pong Tamuk",
    "wof:placetype":"locality"
},
  "geometry": {"coordinates":[101.11572,13.40494],"type":"Point"}
}