{
  "type": "Feature",
  "properties": {
    "gn:admin1_code":"75.0",
    "gn:asciiname":"Ban Nong Mueang",
    "gn:country_code":"TH",
    "gn:dem":142,
    "gn:feature_class":"P",
    "gn:feature_code":"PPL",
    "gn:name":"Ban Nong Mueang",
    "gn:population":0,
    "gn:timezone":"Asia/Bangkok",
    "iso:country":"TH",
    "name:tha_x_preferred":[
        "\u0e1a\u0e49\u0e32\u0e19\u0e2b\u0e19\u0e2d\u0e07\u0e40\u0e21\u0e37\u0e2d\u0e07"
    ],
    "name:und_x_variant":[
        "Ban Nong Muang"
    ],
    "wof:name":"Ban Nong Mueang",
    "wof:placetype":"locality"
},
  "geometry": {"coordinates":[104.74630999999999,15.57825],"type":"Point"}
}