{
  "type": "Feature",
  "properties": {
    "gn:admin1_code":"25.0",
    "gn:asciiname":"Ban Khok Kok Muang",
    "gn:country_code":"TH",
    "gn:dem":147,
    "gn:feature_class":"P",
    "gn:feature_code":"PPL",
    "gn:name":"Ban Khok Kok Muang",
    "gn:population":0,
    "gn:timezone":"Asia/Bangkok",
    "iso:country":"TH",
    "name:tha_x_preferred":[
        "\u0e1a\u0e49\u0e32\u0e19\u0e42\u0e04\u0e01\u0e01\u0e01\u0e21\u0e48\u0e27\u0e07"
    ],
    "wof:name":"Ban Khok Kok Muang",
    "wof:placetype":"locality"
},
  "geometry": {"coordinates":[104.02513999999999,16.16442],"type":"Point"}
}