{
  "type": "Feature",
  "properties": {
    "gn:admin1_code":"4.0",
    "gn:asciiname":"Ban Nam Lan",
    "gn:country_code":"TH",
    "gn:dem":430,
    "gn:feature_class":"P",
    "gn:feature_code":"PPL",
    "gn:name":"Ban Nam Lan",
    "gn:population":0,
    "gn:timezone":"Asia/Bangkok",
    "iso:country":"TH",
    "name:tha_x_preferred":[
        "\u0e1a\u0e49\u0e32\u0e19\u0e19\u0e49\u0e33\u0e25\u0e32\u0e19"
    ],
    "wof:name":"Ban Nam Lan",
    "wof:placetype":"locality"
},
  "geometry": {"coordinates":[101.09392,18.66351],"type":"Point"}
}