{
  "type": "Feature",
  "properties": {
    "gn:admin1_code":"6.0",
    "gn:asciiname":"Ban Pong Wang",
    "gn:country_code":"TH",
    "gn:dem":255,
    "gn:feature_class":"P",
    "gn:feature_code":"PPL",
    "gn:name":"Ban Pong Wang",
    "gn:population":0,
    "gn:timezone":"Asia/Bangkok",
    "iso:country":"TH",
    "name:tha_x_preferred":[
        "\u0e1a\u0e49\u0e32\u0e19\u0e1b\u0e07\u0e27\u0e31\u0e07"
    ],
    "wof:name":"Ban Pong Wang",
    "wof:placetype":"locality"
},
  "geometry": {"coordinates":[99.58356000000001,18.36078],"type":"Point"}
}