{
  "type": "Feature",
  "properties": {
    "gn:admin1_code":"44.0",
    "gn:asciiname":"Ban Lat Nokyung",
    "gn:country_code":"TH",
    "gn:dem":7,
    "gn:feature_class":"P",
    "gn:feature_code":"PPL",
    "gn:name":"Ban Lat Nokyung",
    "gn:population":0,
    "gn:timezone":"Asia/Bangkok",
    "iso:country":"TH",
    "name:tha_x_preferred":[
        "\u0e1a\u0e49\u0e32\u0e19\u0e25\u0e32\u0e14\u0e19\u0e01\u0e22\u0e39\u0e07"
    ],
    "wof:name":"Ban Lat Nokyung",
    "wof:placetype":"locality"
},
  "geometry": {"coordinates":[101.33189,13.70664],"type":"Point"}
}