{
  "type": "Feature",
  "properties": {
    "gn:admin1_code":"55.0",
    "gn:asciiname":"Ban Laem Bang Yang",
    "gn:country_code":"TH",
    "gn:dem":5,
    "gn:feature_class":"P",
    "gn:feature_code":"PPL",
    "gn:name":"Ban Laem Bang Yang",
    "gn:population":0,
    "gn:timezone":"Asia/Bangkok",
    "iso:country":"TH",
    "name:tha_x_preferred":[
        "\u0e1a\u0e49\u0e32\u0e19\u0e41\u0e2b\u0e25\u0e21\u0e1a\u0e32\u0e07\u0e22\u0e32\u0e07"
    ],
    "name:und_x_variant":[
        "Bang Yang",
        "Ban Bang Yang",
        "Ban Laem Bang Yang"
    ],
    "wof:lang_x_official":[
        "tha"
    ],
    "wof:lang_x_spoken":[
        "tha"
    ],
    "wof:name":"Ban Laem Bang Yang",
    "wof:placetype":"locality"
},
  "geometry": {"coordinates":[100.21944999999999,13.64768],"type":"Point"}
}