{
  "type": "Feature",
  "properties": {
    "gn:admin1_code":"44.0",
    "gn:asciiname":"Ban Bang Phutsa",
    "gn:country_code":"TH",
    "gn:dem":6,
    "gn:feature_class":"P",
    "gn:feature_code":"PPL",
    "gn:name":"Ban Bang Phutsa",
    "gn:population":0,
    "gn:timezone":"Asia/Bangkok",
    "iso:country":"TH",
    "name:tha_x_preferred":[
        "\u0e1a\u0e49\u0e32\u0e19\u0e1a\u0e32\u0e07\u0e1e\u0e38\u0e17\u0e23\u0e32"
    ],
    "wof:name":"Ban Bang Phutsa",
    "wof:placetype":"locality"
},
  "geometry": {"coordinates":[101.29069,13.74861],"type":"Point"}
}