{
  "type": "Feature",
  "properties": {
    "gn:admin1_code":"43",
    "gn:asciiname":"Ban Nong Nam Ko",
    "gn:country_code":"TH",
    "gn:dem":9,
    "gn:feature_class":"P",
    "gn:feature_code":"PPL",
    "gn:name":"Ban Nong Nam Ko",
    "gn:population":0,
    "gn:timezone":"Asia/Bangkok",
    "iso:country":"TH",
    "name:tha_x_preferred":[
        "\u0e1a\u0e49\u0e32\u0e19\u0e2b\u0e19\u0e2d\u0e07\u0e19\u0e49\u0e33\u0e42\u0e01\u0e49"
    ],
    "wof:name":"Ban Nong Nam Ko",
    "wof:placetype":"locality"
},
  "geometry": {"coordinates":[101.01443999999999,14.29503],"type":"Point"}
}