{
  "type": "Feature",
  "properties": {
    "gn:admin1_code":"36",
    "gn:asciiname":"Ban Sadang",
    "gn:country_code":"TH",
    "gn:dem":14,
    "gn:feature_class":"P",
    "gn:feature_code":"PPL",
    "gn:name":"Ban Sadang",
    "gn:population":0,
    "gn:timezone":"Asia/Bangkok",
    "iso:country":"TH",
    "name:tha_x_preferred":[
        "\u0e1a\u0e49\u0e32\u0e19\u0e2a\u0e0e\u0e32\u0e07\u0e04\u0e4c"
    ],
    "wof:name":"Ban Sadang",
    "wof:placetype":"locality"
},
  "geometry": {"coordinates":[100.71425000000001,14.54864],"type":"Point"}
}