{
  "type": "Feature",
  "properties": {
    "gn:admin1_code":"50.0",
    "gn:asciiname":"Ban Tha Yai",
    "gn:cc2":"TH",
    "gn:country_code":"TH",
    "gn:dem":172,
    "gn:feature_class":"P",
    "gn:feature_code":"PPL",
    "gn:name":"Ban Tha Yai",
    "gn:population":0,
    "gn:timezone":"Asia/Bangkok",
    "iso:country":"TH",
    "name:und_x_variant":[
        "Ban Tah Yai",
        "Ban Tha Yai"
    ],
    "wof:name":"Ban Tha Yai",
    "wof:placetype":"locality"
},
  "geometry": {"coordinates":[99.02972,14.80389],"type":"Point"}
}