{
  "type": "Feature",
  "properties": {
    "gn:admin1_code":"2.0",
    "gn:asciiname":"Ban La-ang Nuea",
    "gn:country_code":"TH",
    "gn:dem":1053,
    "gn:feature_class":"P",
    "gn:feature_code":"PPL",
    "gn:name":"Ban La-ang Nuea",
    "gn:population":0,
    "gn:timezone":"Asia/Bangkok",
    "iso:country":"TH",
    "name:tha_x_preferred":[
        "\u0e1a\u0e49\u0e32\u0e19\u0e25\u0e30\u0e2d\u0e32\u0e07\u0e40\u0e2b\u0e19\u0e37\u0e2d"
    ],
    "wof:name":"Ban La-ang Nuea",
    "wof:placetype":"locality"
},
  "geometry": {"coordinates":[98.10978,18.41028],"type":"Point"}
}