{
  "type": "Feature",
  "properties": {
    "gn:gn_country":"TH",
    "gn:gn_fcode":"PPLA2",
    "gn:gn_pop":0,
    "gn:population":5094,
    "iso:country":"TH",
    "name:tha_x_preferred":[
        "\u0e41\u0e21\u0e48\u0e43\u0e08"
    ],
    "name:unk_x_variant":[
        "B\u0101n Mea J\u0101i T\u0101i"
    ],
    "name:urd_x_preferred":[
        "\u0645\u0627\u0626\u06d2 \u0686\u0627\u06cc"
    ],
    "qs_pg:aaroncc":"TH",
    "qs_pg:gn_country":"TH",
    "qs_pg:gn_fcode":"PPLA2",
    "qs_pg:gn_pop":0,
    "qs_pg:name":"Mae Chai",
    "qs_pg:name_adm0":"Thailand",
    "qs_pg:name_adm1":"Phayao",
    "qs_pg:photos":11,
    "qs_pg:photos_1k":2,
    "qs_pg:photos_9k":1,
    "qs_pg:photos_9r":1,
    "qs_pg:photos_all":11,
    "qs_pg:photos_sr":1,
    "qs_pg:pop_sr":4,
    "qs_pg:qs_pg_placetype":"locality",
    "qs_pg:qs_pg_placetype_gp":"Town",
    "qs_pg:woe_adm0":23424960,
    "woe:adm0_id":23424960,
    "woe:name_adm0":"Thailand",
    "woe:name_adm1":"Phayao",
    "woe:placetype":"Town",
    "wof:name":"Mae Chai",
    "wof:placetype":"locality",
    "wof:population":5094
},
  "geometry": {"coordinates":[99.81399999999999,19.34597],"type":"Point"}
}