{
  "type": "Feature",
  "properties": {
    "gn:admin1_code":"14.0",
    "gn:asciiname":"Ban Bua Watthana",
    "gn:country_code":"TH",
    "gn:dem":93,
    "gn:feature_class":"P",
    "gn:feature_code":"PPL",
    "gn:name":"Ban Bua Watthana",
    "gn:population":0,
    "gn:timezone":"Asia/Bangkok",
    "iso:country":"TH",
    "name:tha_x_preferred":[
        "\u0e1a\u0e49\u0e32\u0e19\u0e1a\u0e31\u0e27\u0e27\u0e31\u0e12\u0e19\u0e32"
    ],
    "name:und_x_variant":[
        "Ban Lam Bua Watthana",
        "Ban Khlong Wua Nao"
    ],
    "wof:name":"Ban Bua Watthana",
    "wof:placetype":"locality"
},
  "geometry": {"coordinates":[101.02856,15.94131],"type":"Point"}
}