{
  "type": "Feature",
  "properties": {
    "gn:admin1_code":"18.0",
    "gn:asciiname":"Ban Na Wa Noi",
    "gn:country_code":"TH",
    "gn:dem":681,
    "gn:feature_class":"P",
    "gn:feature_code":"PPL",
    "gn:name":"Ban Na Wa Noi",
    "gn:population":0,
    "gn:timezone":"Asia/Bangkok",
    "iso:country":"TH",
    "name:tha_x_preferred":[
        "\u0e1a\u0e49\u0e32\u0e19\u0e19\u0e32\u0e2b\u0e27\u0e49\u0e32\u0e19\u0e49\u0e2d\u0e22"
    ],
    "name:und_x_variant":[
        "Ban Na Wa",
        "Ban Na Wa Noi"
    ],
    "wof:lang_x_official":[
        "tha"
    ],
    "wof:lang_x_spoken":[
        "tha"
    ],
    "wof:name":"Ban Na Wa Noi",
    "wof:placetype":"locality"
},
  "geometry": {"coordinates":[101.13037,17.14002],"type":"Point"}
}