{
  "type": "Feature",
  "properties": {
    "gn:admin1_code":"20.0",
    "gn:asciiname":"Ban Non Hua Chang",
    "gn:country_code":"TH",
    "gn:dem":301,
    "gn:feature_class":"P",
    "gn:feature_code":"PPL",
    "gn:name":"Ban Non Hua Chang",
    "gn:population":0,
    "gn:timezone":"Asia/Bangkok",
    "iso:country":"TH",
    "name:tha_x_preferred":[
        "\u0e1a\u0e49\u0e32\u0e19\u0e42\u0e19\u0e19\u0e2b\u0e31\u0e27\u0e0a\u0e49\u0e32\u0e07"
    ],
    "wof:name":"Ban Non Hua Chang",
    "wof:placetype":"locality"
},
  "geometry": {"coordinates":[103.92932999999999,16.95239],"type":"Point"}
}