{
  "type": "Feature",
  "properties": {
    "gn:admin1_code":"56.0",
    "gn:asciiname":"Ban Han Kancha",
    "gn:country_code":"TH",
    "gn:dem":8,
    "gn:feature_class":"P",
    "gn:feature_code":"PPL",
    "gn:name":"Ban Han Kancha",
    "gn:population":0,
    "gn:timezone":"Asia/Bangkok",
    "iso:country":"TH",
    "name:tha_x_preferred":[
        "\u0e1a\u0e49\u0e32\u0e19\u0e2b\u0e31\u0e19\u0e01\u0e31\u0e0d\u0e0a\u0e32"
    ],
    "wof:name":"Ban Han Kancha",
    "wof:placetype":"locality"
},
  "geometry": {"coordinates":[99.98157999999999,12.88119],"type":"Point"}
}