{
  "type": "Feature",
  "properties": {
    "gn:admin1_code":"41.0",
    "gn:asciiname":"Ban Pa Tum",
    "gn:country_code":"TH",
    "gn:dem":402,
    "gn:feature_class":"P",
    "gn:feature_code":"PPL",
    "gn:name":"Ban Pa Tum",
    "gn:population":0,
    "gn:timezone":"Asia/Bangkok",
    "iso:country":"TH",
    "name:tha_x_preferred":[
        "\u0e1a\u0e49\u0e32\u0e19\u0e1b\u0e48\u0e32\u0e15\u0e38\u0e49\u0e21"
    ],
    "name:und_x_variant":[
        "B\u0101n San Taum Team",
        "Ban San Tom Taem",
        "Ban Pa Tum"
    ],
    "wof:name":"Ban Pa Tum",
    "wof:placetype":"locality"
},
  "geometry": {"coordinates":[99.84428,19.30953],"type":"Point"}
}