{
  "type": "Feature",
  "properties": {
    "gn:admin1_code":"73.0",
    "gn:asciiname":"Ban Na Khu Noi",
    "gn:country_code":"TH",
    "gn:dem":151,
    "gn:feature_class":"P",
    "gn:feature_code":"PPL",
    "gn:name":"Ban Na Khu Noi",
    "gn:population":0,
    "gn:timezone":"Asia/Bangkok",
    "iso:country":"TH",
    "name:tha_x_preferred":[
        "Ban Na Khu Noi"
    ],
    "name:tha_x_variant":[
        "\u0e1a\u0e49\u0e32\u0e19\u0e19\u0e32\u0e04\u0e39\u0e48\u0e19\u0e49\u0e2d\u0e22"
    ],
    "wof:name":"Ban Na Khu Noi",
    "wof:placetype":"locality"
},
  "geometry": {"coordinates":[104.54442,16.97639],"type":"Point"}
}