{
  "type": "Feature",
  "properties": {
    "gn:admin1_code":"6.0",
    "gn:asciiname":"Ban Thung Sakaeng",
    "gn:country_code":"TH",
    "gn:dem":377,
    "gn:feature_class":"P",
    "gn:feature_code":"PPL",
    "gn:name":"Ban Thung Sakaeng",
    "gn:population":0,
    "gn:timezone":"Asia/Bangkok",
    "iso:country":"TH",
    "name:tha_x_preferred":[
        "\u0e1a\u0e49\u0e32\u0e19\u0e17\u0e38\u0e48\u0e07\u0e2a\u0e30\u0e41\u0e01\u0e07"
    ],
    "wof:name":"Ban Thung Sakaeng",
    "wof:placetype":"locality"
},
  "geometry": {"coordinates":[99.48278000000001,18.70722],"type":"Point"}
}