{
  "type": "Feature",
  "properties": {
    "gn:admin1_code":"5.0",
    "gn:asciiname":"Ban Wang Din",
    "gn:country_code":"TH",
    "gn:dem":483,
    "gn:feature_class":"P",
    "gn:feature_code":"PPL",
    "gn:name":"Ban Wang Din",
    "gn:population":0,
    "gn:timezone":"Asia/Bangkok",
    "iso:country":"TH",
    "name:tha_x_preferred":[
        "\u0e1a\u0e49\u0e32\u0e19\u0e27\u0e31\u0e07\u0e14\u0e34\u0e19"
    ],
    "name:und_x_variant":[
        "Wang Din",
        "Ban Wang Din"
    ],
    "wof:name":"Ban Wang Din",
    "wof:placetype":"locality"
},
  "geometry": {"coordinates":[98.94078,17.79697],"type":"Point"}
}