{
  "type": "Feature",
  "properties": {
    "gn:admin1_code":"72.0",
    "gn:asciiname":"Ban Kham Nong Yang",
    "gn:country_code":"TH",
    "gn:dem":182,
    "gn:feature_class":"P",
    "gn:feature_code":"PPL",
    "gn:name":"Ban Kham Nong Yang",
    "gn:population":0,
    "gn:timezone":"Asia/Bangkok",
    "iso:country":"TH",
    "name:tha_x_preferred":[
        "\u0e1a\u0e49\u0e32\u0e19\u0e04\u0e33\u0e2b\u0e19\u0e2d\u0e07\u0e22\u0e32\u0e07"
    ],
    "wof:name":"Ban Kham Nong Yang",
    "wof:placetype":"locality"
},
  "geometry": {"coordinates":[104.26711,16.09944],"type":"Point"}
}