{
  "type": "Feature",
  "properties": {
    "gn:admin1_code":"42.0",
    "gn:asciiname":"Ban Khlong Chorakhe",
    "gn:country_code":"TH",
    "gn:dem":2,
    "gn:feature_class":"P",
    "gn:feature_code":"PPL",
    "gn:name":"Ban Khlong Chorakhe",
    "gn:population":0,
    "gn:timezone":"Asia/Bangkok",
    "iso:country":"TH",
    "name:tha_x_preferred":[
        "\u0e1a\u0e49\u0e32\u0e19\u0e04\u0e25\u0e2d\u0e07\u0e08\u0e23\u0e40\u0e02\u0e49"
    ],
    "name:und_x_variant":[
        "Ban Hua Chake",
        "Ban Hua Chorakhe",
        "Ban Khlong Chorakhe"
    ],
    "wof:name":"Ban Khlong Chorakhe",
    "wof:placetype":"locality"
},
  "geometry": {"coordinates":[100.80056,13.60353],"type":"Point"}
}