{
  "type": "Feature",
  "properties": {
    "gn:admin1_code":"20.0",
    "gn:asciiname":"Ban Rai Na Dieo",
    "gn:country_code":"TH",
    "gn:dem":174,
    "gn:feature_class":"P",
    "gn:feature_code":"PPL",
    "gn:name":"Ban Rai Na Dieo",
    "gn:population":0,
    "gn:timezone":"Asia/Bangkok",
    "iso:country":"TH",
    "wof:name":"Ban Rai Na Dieo",
    "wof:placetype":"locality"
},
  "geometry": {"coordinates":[103.53333000000001,17.71667],"type":"Point"}
}