{
  "type": "Feature",
  "properties": {
    "gn:admin1_code":"6.0",
    "gn:asciiname":"Ban Mae Sai Kham",
    "gn:country_code":"TH",
    "gn:dem":252,
    "gn:feature_class":"P",
    "gn:feature_code":"PPL",
    "gn:name":"Ban Mae Sai Kham",
    "gn:population":0,
    "gn:timezone":"Asia/Bangkok",
    "iso:country":"TH",
    "name:tha_x_preferred":[
        "\u0e1a\u0e49\u0e32\u0e19\u0e41\u0e21\u0e48\u0e17\u0e23\u0e32\u0e22\u0e04\u0e33"
    ],
    "name:und_x_variant":[
        "B\u0101n Mea Sing Kam",
        "Ban Mae Sing Kham",
        "Ban Mae Sai Kham"
    ],
    "wof:name":"Ban Mae Sai Kham",
    "wof:placetype":"locality"
},
  "geometry": {"coordinates":[99.52536000000001,18.36683],"type":"Point"}
}