{
  "type": "Feature",
  "properties": {
    "gn:admin1_code":"41.0",
    "gn:asciiname":"Ban Thung Ton Si",
    "gn:country_code":"TH",
    "gn:dem":274,
    "gn:feature_class":"P",
    "gn:feature_code":"PPL",
    "gn:name":"Ban Thung Ton Si",
    "gn:population":0,
    "gn:timezone":"Asia/Bangkok",
    "iso:country":"TH",
    "name:tha_x_preferred":[
        "\u0e1a\u0e49\u0e32\u0e19\u0e17\u0e38\u0e48\u0e07\u0e15\u0e49\u0e19\u0e28\u0e23\u0e35"
    ],
    "wof:name":"Ban Thung Ton Si",
    "wof:placetype":"locality"
},
  "geometry": {"coordinates":[100.27144,18.87169],"type":"Point"}
}