{
  "type": "Feature",
  "properties": {
    "gn:admin1_code":"3.0",
    "gn:asciiname":"Ban Huai Pu Kaeng",
    "gn:country_code":"TH",
    "gn:dem":391,
    "gn:feature_class":"P",
    "gn:feature_code":"PPL",
    "gn:name":"Ban Huai Pu Kaeng",
    "gn:population":0,
    "gn:timezone":"Asia/Bangkok",
    "iso:country":"TH",
    "name:tha_x_preferred":[
        "\u0e1a\u0e49\u0e32\u0e19\u0e2b\u0e49\u0e27\u0e22\u0e1b\u0e39\u0e41\u0e01\u0e07"
    ],
    "wof:name":"Ban Huai Pu Kaeng",
    "wof:placetype":"locality"
},
  "geometry": {"coordinates":[99.866,20.33056],"type":"Point"}
}