{
  "type": "Feature",
  "properties": {
    "gn:admin1_code":"22",
    "gn:asciiname":"Ban Mai Na Kham",
    "gn:country_code":"TH",
    "gn:dem":243,
    "gn:feature_class":"P",
    "gn:feature_code":"PPL",
    "gn:name":"Ban Mai Na Kham",
    "gn:population":0,
    "gn:timezone":"Asia/Bangkok",
    "iso:country":"TH",
    "name:tha_x_preferred":[
        "\u0e1a\u0e49\u0e32\u0e19\u0e43\u0e2b\u0e21\u0e48\u0e19\u0e32\u0e04\u0e33"
    ],
    "wof:name":"Ban Mai Na Kham",
    "wof:placetype":"locality"
},
  "geometry": {"coordinates":[102.10247,16.58789],"type":"Point"}
}