{
  "type": "Feature",
  "properties": {
    "gn:admin1_code":"43.0",
    "gn:asciiname":"Ban Kut Rang Nai",
    "gn:country_code":"TH",
    "gn:dem":19,
    "gn:feature_class":"P",
    "gn:feature_code":"PPL",
    "gn:name":"Ban Kut Rang Nai",
    "gn:population":0,
    "gn:timezone":"Asia/Bangkok",
    "iso:country":"TH",
    "name:tha_x_preferred":[
        "\u0e1a\u0e49\u0e32\u0e19\u0e01\u0e38\u0e14\u0e23\u0e31\u0e07\u0e43\u0e19"
    ],
    "name:und_x_variant":[
        "Ban Kut Rang",
        "Ban Kut Rang Nai"
    ],
    "wof:name":"Ban Kut Rang Nai",
    "wof:placetype":"locality"
},
  "geometry": {"coordinates":[101.27811,14.25292],"type":"Point"}
}