{
  "type": "Feature",
  "properties": {
    "gn:admin1_code":"12.0",
    "gn:asciiname":"Ban Nam Hak",
    "gn:country_code":"TH",
    "gn:dem":58,
    "gn:feature_class":"P",
    "gn:feature_code":"PPL",
    "gn:name":"Ban Nam Hak",
    "gn:population":0,
    "gn:timezone":"Asia/Bangkok",
    "iso:country":"TH",
    "name:tha_x_preferred":[
        "\u0e1a\u0e49\u0e32\u0e19\u0e19\u0e49\u0e33\u0e2b\u0e31\u0e01"
    ],
    "wof:name":"Ban Nam Hak",
    "wof:placetype":"locality"
},
  "geometry": {"coordinates":[100.39275000000001,17.07607999999999],"type":"Point"}
}