{
  "type": "Feature",
  "properties": {
    "gn:admin1_code":"68.0",
    "gn:asciiname":"Ban Phru Ching",
    "gn:country_code":"TH",
    "gn:dem":28,
    "gn:feature_class":"P",
    "gn:feature_code":"PPL",
    "gn:name":"Ban Phru Ching",
    "gn:population":0,
    "gn:timezone":"Asia/Bangkok",
    "iso:country":"TH",
    "name:tha_x_preferred":[
        "\u0e1a\u0e49\u0e32\u0e19\u0e1e\u0e23\u0e38\u0e0a\u0e34\u0e07"
    ],
    "wof:name":"Ban Phru Ching",
    "wof:placetype":"locality"
},
  "geometry": {"coordinates":[101.041,6.71453],"type":"Point"}
}