{
  "type": "Feature",
  "properties": {
    "gn:admin1_code":"16.0",
    "gn:asciiname":"Ban Chon",
    "gn:country_code":"TH",
    "gn:dem":78,
    "gn:feature_class":"P",
    "gn:feature_code":"PPL",
    "gn:name":"Ban Chon",
    "gn:population":0,
    "gn:timezone":"Asia/Bangkok",
    "iso:country":"TH",
    "name:tha_x_preferred":[
        "\u0e1a\u0e49\u0e32\u0e19\u0e0a\u0e2d\u0e19"
    ],
    "wof:name":"Ban Chon",
    "wof:placetype":"locality"
},
  "geometry": {"coordinates":[100.28344,15.52086],"type":"Point"}
}