{
  "type": "Feature",
  "properties": {
    "gn:admin1_code":"39.0",
    "gn:asciiname":"Ban Khlong Chet",
    "gn:country_code":"TH",
    "gn:dem":8,
    "gn:feature_class":"P",
    "gn:feature_code":"PPL",
    "gn:name":"Ban Khlong Chet",
    "gn:population":0,
    "gn:timezone":"Asia/Bangkok",
    "iso:country":"TH",
    "name:tha_x_preferred":[
        "Ban Khlong Chet"
    ],
    "name:tha_x_variant":[
        "\u0e1a\u0e49\u0e32\u0e19\u0e04\u0e25\u0e2d\u0e07\u0e40\u0e08\u0e47\u0e14"
    ],
    "name:und_x_variant":[
        "Ban Khlong Chet (1)",
        "Ban Khlong 7"
    ],
    "wof:name":"Ban Khlong Chet",
    "wof:placetype":"locality"
},
  "geometry": {"coordinates":[100.77739,14.20022],"type":"Point"}
}