{
  "type": "Feature",
  "properties": {
    "gn:admin1_code":"65.0",
    "gn:asciiname":"Ban Sai Nam Sung",
    "gn:country_code":"TH",
    "gn:dem":20,
    "gn:feature_class":"P",
    "gn:feature_code":"PPL",
    "gn:name":"Ban Sai Nam Sung",
    "gn:population":0,
    "gn:timezone":"Asia/Bangkok",
    "iso:country":"TH",
    "name:tha_x_preferred":[
        "\u0e1a\u0e49\u0e32\u0e19\u0e44\u0e2a\u0e2b\u0e19\u0e33\u0e2a\u0e39\u0e07"
    ],
    "name:und_x_variant":[
        "Ban Thung Sai Nam Sung (1)"
    ],
    "wof:name":"Ban Sai Nam Sung",
    "wof:placetype":"locality"
},
  "geometry": {"coordinates":[99.33911000000001,7.65978],"type":"Point"}
}