{
  "type": "Feature",
  "properties": {
    "gn:admin1_code":"24",
    "gn:asciiname":"Ban Hu Ling",
    "gn:country_code":"TH",
    "gn:dem":148,
    "gn:feature_class":"P",
    "gn:feature_code":"PPL",
    "gn:name":"Ban Hu Ling",
    "gn:population":0,
    "gn:timezone":"Asia/Bangkok",
    "iso:country":"TH",
    "name:tha_x_preferred":[
        "\u0e1a\u0e49\u0e32\u0e19\u0e2b\u0e39\u0e25\u0e34\u0e07"
    ],
    "wof:name":"Ban Hu Ling",
    "wof:placetype":"locality"
},
  "geometry": {"coordinates":[103.09605999999999,15.63792],"type":"Point"}
}