{
  "type": "Feature",
  "properties": {
    "gn:admin1_code":"64.0",
    "gn:asciiname":"Ban Tha Yai",
    "gn:country_code":"TH",
    "gn:dem":4,
    "gn:feature_class":"P",
    "gn:feature_code":"PPL",
    "gn:name":"Ban Tha Yai",
    "gn:population":0,
    "gn:timezone":"Asia/Bangkok",
    "iso:country":"TH",
    "name:tha_x_preferred":[
        "\u0e1a\u0e49\u0e32\u0e19\u0e17\u0e48\u0e32\u0e43\u0e2b\u0e0d\u0e48"
    ],
    "name:und_x_variant":[
        "Ban Tah Yai",
        "Ban Tha Yai"
    ],
    "wof:name":"Ban Tha Yai",
    "wof:placetype":"locality"
},
  "geometry": {"coordinates":[100.12372000000001,8.13594],"type":"Point"}
}