{
  "type": "Feature",
  "properties": {
    "gn:admin1_code":"53.0",
    "gn:asciiname":"Ban Bang Yung",
    "gn:country_code":"TH",
    "gn:dem":5,
    "gn:feature_class":"P",
    "gn:feature_code":"PPL",
    "gn:name":"Ban Bang Yung",
    "gn:population":0,
    "gn:timezone":"Asia/Bangkok",
    "iso:country":"TH",
    "name:tha_x_preferred":[
        "Ban Bang Yung"
    ],
    "name:tha_x_variant":[
        "\u0e1a\u0e49\u0e32\u0e19\u0e1a\u0e32\u0e07\u0e22\u0e38\u0e07"
    ],
    "name:und_x_variant":[
        "B\u0101ng Pl\u0101",
        "Amphoe Bang Pla",
        "Bang Yung",
        "Ban Bang Yung (1)"
    ],
    "wof:name":"Ban Bang Yung",
    "wof:placetype":"locality"
},
  "geometry": {"coordinates":[100.18617,14.00772],"type":"Point"}
}