{
  "type": "Feature",
  "properties": {
    "gn:admin1_code":"3.0",
    "gn:asciiname":"Ban Rai",
    "gn:cc2":"TH",
    "gn:country_code":"TH",
    "gn:dem":404,
    "gn:feature_class":"P",
    "gn:feature_code":"PPL",
    "gn:name":"Ban Rai",
    "gn:population":0,
    "gn:timezone":"Asia/Bangkok",
    "iso:country":"TH",
    "name:und_x_variant":[
        "Ban Meal\u0101i",
        "Ban Mae Lai",
        "Ban Rai"
    ],
    "wof:lang_x_official":[
        "tha"
    ],
    "wof:lang_x_spoken":[
        "tha"
    ],
    "wof:name":"Ban Rai",
    "wof:placetype":"locality"
},
  "geometry": {"coordinates":[99.84999999999999,20.25],"type":"Point"}
}