{
  "type": "Feature",
  "properties": {
    "gn:admin1_code":"57.0",
    "gn:asciiname":"Ban Nong Sai Ting",
    "gn:country_code":"TH",
    "gn:dem":48,
    "gn:feature_class":"P",
    "gn:feature_code":"PPL",
    "gn:name":"Ban Nong Sai Ting",
    "gn:population":0,
    "gn:timezone":"Asia/Bangkok",
    "iso:country":"TH",
    "name:tha_x_preferred":[
        "\u0e1a\u0e49\u0e32\u0e19\u0e2b\u0e19\u0e2d\u0e07\u0e2a\u0e32\u0e22\u0e15\u0e34\u0e48\u0e07"
    ],
    "wof:name":"Ban Nong Sai Ting",
    "wof:placetype":"locality"
},
  "geometry": {"coordinates":[99.55197,11.48531],"type":"Point"}
}