{
  "type": "Feature",
  "properties": {
    "gn:admin1_code":"73.0",
    "gn:asciiname":"Ban Lao Sompoi",
    "gn:country_code":"TH",
    "gn:dem":166,
    "gn:feature_class":"P",
    "gn:feature_code":"PPL",
    "gn:name":"Ban Lao Sompoi",
    "gn:population":0,
    "gn:timezone":"Asia/Bangkok",
    "iso:country":"TH",
    "name:tha_x_preferred":[
        "\u0e1a\u0e49\u0e32\u0e19\u0e40\u0e2b\u0e25\u0e48\u0e32\u0e2a\u0e49\u0e21\u0e1b\u0e48\u0e2d\u0e22"
    ],
    "wof:name":"Ban Lao Sompoi",
    "wof:placetype":"locality"
},
  "geometry": {"coordinates":[104.07091,17.87036],"type":"Point"}
}