{
  "type": "Feature",
  "properties": {
    "gn:admin1_code":"52.0",
    "gn:asciiname":"Ban Khao Sadet",
    "gn:country_code":"TH",
    "gn:dem":44,
    "gn:feature_class":"P",
    "gn:feature_code":"PPL",
    "gn:name":"Ban Khao Sadet",
    "gn:population":0,
    "gn:timezone":"Asia/Bangkok",
    "iso:country":"TH",
    "name:tha_x_preferred":[
        "\u0e1a\u0e49\u0e32\u0e19\u0e40\u0e02\u0e32\u0e40\u0e2a\u0e14\u0e47\u0e08"
    ],
    "wof:name":"Ban Khao Sadet",
    "wof:placetype":"locality"
},
  "geometry": {"coordinates":[99.69964,13.69767],"type":"Point"}
}