{
  "type": "Feature",
  "properties": {
    "gn:admin1_code":"8.0",
    "gn:asciiname":"Ban Wang Wai",
    "gn:country_code":"TH",
    "gn:dem":141,
    "gn:feature_class":"P",
    "gn:feature_code":"PPL",
    "gn:name":"Ban Wang Wai",
    "gn:population":0,
    "gn:timezone":"Asia/Bangkok",
    "iso:country":"TH",
    "name:tha_x_preferred":[
        "Ban Wang Wai"
    ],
    "name:tha_x_variant":[
        "\u0e1a\u0e49\u0e32\u0e19\u0e27\u0e31\u0e07\u0e2b\u0e27\u0e32\u0e22"
    ],
    "wof:name":"Ban Wang Wai",
    "wof:placetype":"locality"
},
  "geometry": {"coordinates":[99.0915,17.19006],"type":"Point"}
}