{
  "type": "Feature",
  "properties": {
    "gn:admin1_code":"44.0",
    "gn:asciiname":"Ban Bang Chueak Khao",
    "gn:country_code":"TH",
    "gn:dem":3,
    "gn:feature_class":"P",
    "gn:feature_code":"PPL",
    "gn:name":"Ban Bang Chueak Khao",
    "gn:population":0,
    "gn:timezone":"Asia/Bangkok",
    "iso:country":"TH",
    "name:tha_x_preferred":[
        "\u0e1a\u0e49\u0e32\u0e19\u0e1a\u0e32\u0e07\u0e40\u0e0a\u0e37\u0e2d\u0e01\u0e40\u0e02\u0e32"
    ],
    "name:und_x_variant":[
        "Ban Bang Chuak",
        "Ban Bang Chuak Khao",
        "Ban Bang Chueak Khao"
    ],
    "wof:name":"Ban Bang Chueak Khao",
    "wof:placetype":"locality"
},
  "geometry": {"coordinates":[101.14039,13.88819],"type":"Point"}
}