{
  "type": "Feature",
  "properties": {
    "gn:admin1_code":"3.0",
    "gn:asciiname":"Ban Pong Pa Kham",
    "gn:country_code":"TH",
    "gn:dem":575,
    "gn:feature_class":"P",
    "gn:feature_code":"PPL",
    "gn:name":"Ban Pong Pa Kham",
    "gn:population":0,
    "gn:timezone":"Asia/Bangkok",
    "iso:country":"TH",
    "name:tha_x_preferred":[
        "\u0e1a\u0e49\u0e32\u0e19\u0e42\u0e1b\u0e48\u0e07\u0e1b\u0e48\u0e32\u0e41\u0e02\u0e21"
    ],
    "wof:name":"Ban Pong Pa Kham",
    "wof:placetype":"locality"
},
  "geometry": {"coordinates":[99.6572,20.10647],"type":"Point"}
}