{
  "type": "Feature",
  "properties": {
    "gn:admin1_code":"27.0",
    "gn:asciiname":"Ban Kut Ta Dam",
    "gn:country_code":"TH",
    "gn:dem":209,
    "gn:feature_class":"P",
    "gn:feature_code":"PPL",
    "gn:name":"Ban Kut Ta Dam",
    "gn:population":0,
    "gn:timezone":"Asia/Bangkok",
    "iso:country":"TH",
    "name:tha_x_preferred":[
        "\u0e1a\u0e49\u0e32\u0e19\u0e01\u0e38\u0e14\u0e15\u0e32\u0e14\u0e33"
    ],
    "name:und_x_variant":[
        "Kut Tadam",
        "B\u0101n Gut Ta Dam",
        "Ban Kut Ta Dam"
    ],
    "wof:name":"Ban Kut Ta Dam",
    "wof:placetype":"locality"
},
  "geometry": {"coordinates":[101.98711,15.37119],"type":"Point"}
}