{
  "type": "Feature",
  "properties": {
    "gn:admin1_code":"20.0",
    "gn:asciiname":"Ban Phak Kham Phu",
    "gn:country_code":"TH",
    "gn:dem":198,
    "gn:feature_class":"P",
    "gn:feature_code":"PPL",
    "gn:name":"Ban Phak Kham Phu",
    "gn:population":0,
    "gn:timezone":"Asia/Bangkok",
    "iso:country":"TH",
    "name:tha_x_preferred":[
        "\u0e1a\u0e49\u0e32\u0e19\u0e1c\u0e31\u0e01\u0e04\u0e33\u0e20\u0e39"
    ],
    "wof:name":"Ban Phak Kham Phu",
    "wof:placetype":"locality"
},
  "geometry": {"coordinates":[103.86783,17.16245],"type":"Point"}
}