{
  "type": "Feature",
  "properties": {
    "gn:admin1_code":"14.0",
    "gn:asciiname":"Ban Huai Makhuea Noi",
    "gn:country_code":"TH",
    "gn:dem":169,
    "gn:feature_class":"P",
    "gn:feature_code":"PPL",
    "gn:name":"Ban Huai Makhuea Noi",
    "gn:population":0,
    "gn:timezone":"Asia/Bangkok",
    "iso:country":"TH",
    "name:tha_x_preferred":[
        "\u0e1a\u0e49\u0e32\u0e19\u0e2b\u0e49\u0e27\u0e22\u0e21\u0e30\u0e40\u0e02\u0e37\u0e2d\u0e19\u0e49\u0e2d\u0e22"
    ],
    "wof:name":"Ban Huai Makhuea Noi",
    "wof:placetype":"locality"
},
  "geometry": {"coordinates":[101.33158,16.87775],"type":"Point"}
}