{
  "type": "Feature",
  "properties": {
    "gn:admin1_code":"36.0",
    "gn:asciiname":"Ban Sakhli",
    "gn:country_code":"TH",
    "gn:dem":7,
    "gn:feature_class":"P",
    "gn:feature_code":"PPL",
    "gn:name":"Ban Sakhli",
    "gn:population":0,
    "gn:timezone":"Asia/Bangkok",
    "iso:country":"TH",
    "name:tha_x_preferred":[
        "\u0e1a\u0e49\u0e32\u0e19\u0e2a\u0e32\u0e04\u0e25\u0e35"
    ],
    "name:und_x_variant":[
        "Ban Pak Khlong Sakhli"
    ],
    "wof:name":"Ban Sakhli",
    "wof:placetype":"locality"
},
  "geometry": {"coordinates":[100.41931,14.27675],"type":"Point"}
}