{
  "type": "Feature",
  "properties": {
    "gn:admin1_code":"32.0",
    "gn:asciiname":"Ban Satue Sing",
    "gn:country_code":"TH",
    "gn:dem":15,
    "gn:feature_class":"P",
    "gn:feature_code":"PPL",
    "gn:name":"Ban Satue Sing",
    "gn:population":0,
    "gn:timezone":"Asia/Bangkok",
    "iso:country":"TH",
    "name:tha_x_preferred":[
        "\u0e1a\u0e49\u0e32\u0e19\u0e2a\u0e30\u0e15\u0e37\u0e2d\u0e2a\u0e34\u0e07\u0e2b\u0e4c"
    ],
    "wof:name":"Ban Satue Sing",
    "wof:placetype":"locality"
},
  "geometry": {"coordinates":[100.06392,14.97017],"type":"Point"}
}