{
  "type": "Feature",
  "properties": {
    "gn:admin1_code":"2.0",
    "gn:asciiname":"Ban Kho Pha To",
    "gn:country_code":"TH",
    "gn:dem":315,
    "gn:feature_class":"P",
    "gn:feature_code":"PPL",
    "gn:name":"Ban Kho Pha To",
    "gn:population":0,
    "gn:timezone":"Asia/Bangkok",
    "iso:country":"TH",
    "name:tha_x_preferred":[
        "\u0e1a\u0e49\u0e32\u0e19\u0e42\u0e04\u0e30\u0e1e\u0e30\u0e42\u0e15\u0e4a\u0e30"
    ],
    "wof:name":"Ban Kho Pha To",
    "wof:placetype":"locality"
},
  "geometry": {"coordinates":[98.11418999999999,17.57783],"type":"Point"}
}