{
  "type": "Feature",
  "properties": {
    "gn:admin1_code":"3.0",
    "gn:asciiname":"Ban Samakkhi Kao",
    "gn:country_code":"TH",
    "gn:dem":733,
    "gn:feature_class":"P",
    "gn:feature_code":"PPL",
    "gn:name":"Ban Samakkhi Kao",
    "gn:population":0,
    "gn:timezone":"Asia/Bangkok",
    "iso:country":"TH",
    "name:tha_x_preferred":[
        "\u0e1a\u0e49\u0e32\u0e19\u0e2a\u0e32\u0e21\u0e31\u0e04\u0e04\u0e35\u0e40\u0e01\u0e48\u0e32"
    ],
    "name:und_x_variant":[
        "Ban Ko Samakkhi"
    ],
    "wof:name":"Ban Samakkhi Kao",
    "wof:placetype":"locality"
},
  "geometry": {"coordinates":[99.73925,20.26339],"type":"Point"}
}