{
  "type": "Feature",
  "properties": {
    "gn:admin1_code":"27.0",
    "gn:asciiname":"Ban Makluea",
    "gn:country_code":"TH",
    "gn:dem":180,
    "gn:feature_class":"P",
    "gn:feature_code":"PPL",
    "gn:name":"Ban Makluea",
    "gn:population":0,
    "gn:timezone":"Asia/Bangkok",
    "iso:country":"TH",
    "name:tha_x_preferred":[
        "\u0e1a\u0e49\u0e32\u0e19\u0e21\u0e30\u0e40\u0e01\u0e25\u0e37\u0e2d"
    ],
    "name:und_x_variant":[
        "Ban Maklua"
    ],
    "wof:lang_x_official":[
        "tha"
    ],
    "wof:lang_x_spoken":[
        "tha"
    ],
    "wof:name":"Ban Makluea",
    "wof:placetype":"locality"
},
  "geometry": {"coordinates":[102.14610999999999,15.29528],"type":"Point"}
}