{
  "type": "Feature",
  "properties": {
    "gn:admin1_code":"27",
    "gn:asciiname":"Ban Yoei Tabaeng",
    "gn:country_code":"TH",
    "gn:dem":155,
    "gn:feature_class":"P",
    "gn:feature_code":"PPL",
    "gn:name":"Ban Yoei Tabaeng",
    "gn:population":0,
    "gn:timezone":"Asia/Bangkok",
    "iso:country":"TH",
    "name:tha_x_preferred":[
        "\u0e1a\u0e49\u0e32\u0e19\u0e40\u0e22\u0e49\u0e22\u0e15\u0e30\u0e41\u0e1a\u0e07"
    ],
    "wof:name":"Ban Yoei Tabaeng",
    "wof:placetype":"locality"
},
  "geometry": {"coordinates":[102.67075,15.48386],"type":"Point"}
}