{
  "type": "Feature",
  "properties": {
    "gn:admin1_code":"12.0",
    "gn:asciiname":"Ban Si Charoen",
    "gn:country_code":"TH",
    "gn:dem":58,
    "gn:feature_class":"P",
    "gn:feature_code":"PPL",
    "gn:name":"Ban Si Charoen",
    "gn:population":0,
    "gn:timezone":"Asia/Bangkok",
    "iso:country":"TH",
    "name:tha_x_preferred":[
        "\u0e1a\u0e49\u0e32\u0e19\u0e28\u0e23\u0e35\u0e40\u0e08\u0e23\u0e34\u0e0d"
    ],
    "wof:name":"Ban Si Charoen",
    "wof:placetype":"locality"
},
  "geometry": {"coordinates":[100.27191999999999,17.13472],"type":"Point"}
}