{
  "type": "Feature",
  "properties": {
    "gn:admin1_code":"25.0",
    "gn:asciiname":"Ban Khui Tae",
    "gn:country_code":"TH",
    "gn:dem":149,
    "gn:feature_class":"P",
    "gn:feature_code":"PPL",
    "gn:name":"Ban Khui Tae",
    "gn:population":0,
    "gn:timezone":"Asia/Bangkok",
    "iso:country":"TH",
    "name:tha_x_preferred":[
        "\u0e1a\u0e49\u0e32\u0e19\u0e04\u0e38\u0e22\u0e41\u0e15\u0e49"
    ],
    "wof:name":"Ban Khui Tae",
    "wof:placetype":"locality"
},
  "geometry": {"coordinates":[103.35424999999999,15.65719],"type":"Point"}
}