{
  "type": "Feature",
  "properties": {
    "gn:admin1_code":"26.0",
    "gn:asciiname":"Ban Thung Prong",
    "gn:country_code":"TH",
    "gn:dem":232,
    "gn:feature_class":"P",
    "gn:feature_code":"PPL",
    "gn:name":"Ban Thung Prong",
    "gn:population":0,
    "gn:timezone":"Asia/Bangkok",
    "iso:country":"TH",
    "name:tha_x_preferred":[
        "\u0e1a\u0e49\u0e32\u0e19\u0e17\u0e38\u0e48\u0e07\u0e42\u0e1b\u0e23\u0e48\u0e07"
    ],
    "wof:name":"Ban Thung Prong",
    "wof:placetype":"locality"
},
  "geometry": {"coordinates":[101.60317999999999,15.40784],"type":"Point"}
}