{
  "type": "Feature",
  "properties": {
    "gn:admin1_code":"65.0",
    "gn:asciiname":"Ban Phru Nai Chang",
    "gn:country_code":"TH",
    "gn:dem":36,
    "gn:feature_class":"P",
    "gn:feature_code":"PPL",
    "gn:name":"Ban Phru Nai Chang",
    "gn:population":0,
    "gn:timezone":"Asia/Bangkok",
    "iso:country":"TH",
    "name:tha_x_preferred":[
        "\u0e1a\u0e49\u0e32\u0e19\u0e1e\u0e23\u0e38\u0e19\u0e32\u0e22\u0e0a\u0e49\u0e32\u0e07"
    ],
    "name:und_x_variant":[
        "Ban Phru Na Chang",
        "Ban Phru Nai Chang"
    ],
    "wof:name":"Ban Phru Nai Chang",
    "wof:placetype":"locality"
},
  "geometry": {"coordinates":[99.70956,7.41511],"type":"Point"}
}