{
  "type": "Feature",
  "properties": {
    "gn:admin1_code":"14.0",
    "gn:asciiname":"Ban Non Sao E",
    "gn:country_code":"TH",
    "gn:dem":159,
    "gn:feature_class":"P",
    "gn:feature_code":"PPL",
    "gn:name":"Ban Non Sao E",
    "gn:population":0,
    "gn:timezone":"Asia/Bangkok",
    "iso:country":"TH",
    "name:tha_x_preferred":[
        "\u0e1a\u0e49\u0e32\u0e19\u0e42\u0e19\u0e19\u0e2a\u0e32\u0e27\u0e40\u0e2d\u0e49"
    ],
    "wof:name":"Ban Non Sao E",
    "wof:placetype":"locality"
},
  "geometry": {"coordinates":[101.28514,16.75903],"type":"Point"}
}