{
  "type": "Feature",
  "properties": {
    "gn:country":"TH",
    "gn:fcode":"PPL",
    "gn:pop":0,
    "iso:country":"TH",
    "name:bpy_x_preferred":[
        "\u0986\u09ae\u09cd\u09ab\u09cb\u09af\u09bc\u09c7 \u09ab\u09be\u09a8\u09af\u09bc\u09be\u09a4 \u09a8\u09bf\u0996\u09cb\u09ae"
    ],
    "name:ceb_x_preferred":[
        "Amphoe Phanat Nikhom"
    ],
    "name:deu_x_preferred":[
        "Amphoe Phanat Nikhom"
    ],
    "name:eng_x_preferred":[
        "Phanat Nikhom"
    ],
    "name:fra_x_preferred":[
        "Phanat Nikhom"
    ],
    "name:jpn_x_preferred":[
        "\u30d1\u30ca\u30c3\u30c8\u30cb\u30b3\u30e0\u90e1"
    ],
    "name:nan_x_preferred":[
        "Phanat Nikhom K\u016bn"
    ],
    "name:ron_x_preferred":[
        "Districtul Phanat Nikhom"
    ],
    "name:tha_x_preferred":[
        "\u0e1a\u0e49\u0e32\u0e19\u0e01\u0e38\u0e0f\u0e42\u0e07\u0e49\u0e07"
    ],
    "name:tha_x_variant":[
        "\u0e2d\u0e33\u0e40\u0e20\u0e2d\u0e1e\u0e19\u0e31\u0e2a\u0e19\u0e34\u0e04\u0e21"
    ],
    "name:unk_x_variant":[
        "Kut Ngong"
    ],
    "name:urd_x_preferred":[
        "\u067e\u06be\u0627\u0646\u0627\u062a \u0646\u06cc\u06a9\u06c1\u0648\u0645 \u0636\u0644\u0639"
    ],
    "name:vie_x_preferred":[
        "Phanat Nikhom"
    ],
    "qs:name":"Ban Kut Ngong",
    "qs:name_adm0":"Thailand",
    "qs:name_adm1":"Chon Buri",
    "qs:photos_9r":0,
    "qs:photos_sr":0,
    "qs:placetype":"Town",
    "qs:pop_sr":"0",
    "wd:wordcount":193,
    "wof:name":"Ban Kut Ngong",
    "wof:placetype":"locality",
    "wof:population":0
},
  "geometry": {"coordinates":[101.16222,13.44342],"type":"Point"}
}