{
  "type": "Feature",
  "properties": {
    "gn:country":"TH",
    "gn:fcode":"PPL",
    "gn:pop":0,
    "iso:country":"TH",
    "name:tha_x_preferred":[
        "\u0e1a\u0e49\u0e32\u0e19\u0e01\u0e38\u0e0f\u0e42\u0e07\u0e49\u0e07"
    ],
    "name:unk_x_variant":[
        "Kut Ngong"
    ],
    "qs:name":"Ban Kut Ngong",
    "qs:name_adm0":"Thailand",
    "qs:name_adm1":"Chon Buri",
    "qs:photos_9r":0,
    "qs:photos_sr":0,
    "qs:placetype":"Town",
    "qs:pop_sr":"0",
    "wd:wordcount":193,
    "wof:name":"Ban Kut Ngong",
    "wof:placetype":"locality",
    "wof:population":0
},
  "geometry": {"coordinates":[101.16222,13.44342],"type":"Point"}
}