{
  "type": "Feature",
  "properties": {
    "gn:admin1_code":"41.0",
    "gn:asciiname":"Ban San Nong Niao",
    "gn:country_code":"TH",
    "gn:dem":398,
    "gn:feature_class":"P",
    "gn:feature_code":"PPL",
    "gn:name":"Ban San Nong Niao",
    "gn:population":0,
    "gn:timezone":"Asia/Bangkok",
    "iso:country":"TH",
    "name:tha_x_preferred":[
        "\u0e1a\u0e49\u0e32\u0e19\u0e2a\u0e31\u0e19\u0e2b\u0e19\u0e2d\u0e07\u0e40\u0e2b\u0e19\u0e35\u0e22\u0e27"
    ],
    "name:und_x_variant":[
        "B\u0101n Naung Nio",
        "Ban Nong Nieo",
        "Ban San Nong Niao"
    ],
    "wof:lang_x_official":[
        "tha"
    ],
    "wof:lang_x_spoken":[
        "tha"
    ],
    "wof:name":"Ban San Nong Niao",
    "wof:placetype":"locality"
},
  "geometry": {"coordinates":[99.84894,19.19528],"type":"Point"}
}