{
  "type": "Feature",
  "properties": {
    "gn:admin1_code":"68.0",
    "gn:asciiname":"Ban Si",
    "gn:cc2":"TH",
    "gn:country_code":"TH",
    "gn:dem":91,
    "gn:feature_class":"P",
    "gn:feature_code":"PPL",
    "gn:name":"Ban Si",
    "gn:population":0,
    "gn:timezone":"Asia/Bangkok",
    "iso:country":"TH",
    "name:und_x_variant":[
        "Ban Chi",
        "Ban Si"
    ],
    "wof:name":"Ban Si",
    "wof:placetype":"locality"
},
  "geometry": {"coordinates":[100.76667,6.85],"type":"Point"}
}