{
  "type": "Feature",
  "properties": {
    "gn:admin1_code":"80",
    "gn:asciiname":"Ban Khlong Malako Tai",
    "gn:country_code":"TH",
    "gn:dem":58,
    "gn:feature_class":"P",
    "gn:feature_code":"PPL",
    "gn:name":"Ban Khlong Malako Tai",
    "gn:population":0,
    "gn:timezone":"Asia/Bangkok",
    "iso:country":"TH",
    "name:tha_x_preferred":[
        "\u0e1a\u0e49\u0e32\u0e19\u0e04\u0e25\u0e2d\u0e07\u0e21\u0e30\u0e25\u0e30\u0e01\u0e2d\u0e43\u0e15\u0e49"
    ],
    "wof:name":"Ban Khlong Malako Tai",
    "wof:placetype":"locality"
},
  "geometry": {"coordinates":[101.95372,13.70814],"type":"Point"}
}