{
  "type": "Feature",
  "properties": {
    "gn:admin1_code":"60.0",
    "gn:asciiname":"Ban Takuk",
    "gn:country_code":"TH",
    "gn:dem":37,
    "gn:feature_class":"P",
    "gn:feature_code":"PPL",
    "gn:name":"Ban Takuk",
    "gn:population":0,
    "gn:timezone":"Asia/Bangkok",
    "iso:country":"TH",
    "name:tha_x_preferred":[
        "\u0e1a\u0e49\u0e32\u0e19\u0e15\u0e30\u0e01\u0e38\u0e01"
    ],
    "name:und_x_variant":[
        "Ban Takuk Nua"
    ],
    "wof:lang_x_official":[
        "tha"
    ],
    "wof:lang_x_spoken":[
        "tha"
    ],
    "wof:name":"Ban Takuk",
    "wof:placetype":"locality"
},
  "geometry": {"coordinates":[98.96086,9.18947],"type":"Point"}
}