{
  "type": "Feature",
  "properties": {
    "gn:admin1_code":"67.0",
    "gn:asciiname":"Ban Pam 5",
    "gn:country_code":"TH",
    "gn:dem":63,
    "gn:feature_class":"P",
    "gn:feature_code":"PPL",
    "gn:name":"Ban Pam 5",
    "gn:population":0,
    "gn:timezone":"Asia/Bangkok",
    "iso:country":"TH",
    "name:tha_x_preferred":[
        "Ban Pam 5"
    ],
    "name:tha_x_variant":[
        "\u0e1a\u0e49\u0e32\u0e19\u0e1b\u0e32\u0e25\u0e4c\u0e21 \u0e2b\u0e49\u0e32",
        "Ban Pam Ha"
    ],
    "wof:name":"Ban Pam 5",
    "wof:placetype":"locality"
},
  "geometry": {"coordinates":[99.92803000000001,7.03442],"type":"Point"}
}