{
  "type": "Feature",
  "properties": {
    "gn:admin1_code":"34.0",
    "gn:asciiname":"Ban Nong Song Ton Tai",
    "gn:country_code":"TH",
    "gn:dem":82,
    "gn:feature_class":"P",
    "gn:feature_code":"PPL",
    "gn:name":"Ban Nong Song Ton Tai",
    "gn:population":0,
    "gn:timezone":"Asia/Bangkok",
    "iso:country":"TH",
    "name:tha_x_preferred":[
        "\u0e1a\u0e49\u0e32\u0e19\u0e2b\u0e19\u0e2d\u0e07\u0e2a\u0e2d\u0e07\u0e15\u0e2d\u0e19\u0e43\u0e15\u0e49"
    ],
    "name:und_x_variant":[
        "Ban Nong Samrong Tai"
    ],
    "wof:name":"Ban Nong Song Ton Tai",
    "wof:placetype":"locality"
},
  "geometry": {"coordinates":[101.07035999999999,15.21264],"type":"Point"}
}