{
  "type": "Feature",
  "properties": {
    "gn:admin1_code":"77.0",
    "gn:asciiname":"Ban Nikhom Amnat Charoen",
    "gn:country_code":"TH",
    "gn:dem":188,
    "gn:feature_class":"P",
    "gn:feature_code":"PPL",
    "gn:name":"Ban Nikhom Amnat Charoen",
    "gn:population":0,
    "gn:timezone":"Asia/Bangkok",
    "iso:country":"TH",
    "name:tha_x_preferred":[
        "Ban Nikhom Amnat Charoen"
    ],
    "name:tha_x_variant":[
        "\u0e1a\u0e49\u0e32\u0e19\u0e19\u0e34\u0e04\u0e21\u0e2d\u0e33\u0e19\u0e32\u0e08\u0e40\u0e08\u0e23\u0e34\u0e0d"
    ],
    "wof:lang_x_official":[
        "tha"
    ],
    "wof:lang_x_spoken":[
        "tha"
    ],
    "wof:name":"Ban Nikhom Amnat Charoen",
    "wof:placetype":"locality"
},
  "geometry": {"coordinates":[104.62304,15.91469],"type":"Point"}
}