{
  "type": "Feature",
  "properties": {
    "gn:admin1_code":"35.0",
    "gn:asciiname":"Ban Bang Nam Won",
    "gn:country_code":"TH",
    "gn:dem":13,
    "gn:feature_class":"P",
    "gn:feature_code":"PPL",
    "gn:name":"Ban Bang Nam Won",
    "gn:population":0,
    "gn:timezone":"Asia/Bangkok",
    "iso:country":"TH",
    "name:tha_x_preferred":[
        "\u0e1a\u0e49\u0e32\u0e19\u0e1a\u0e32\u0e07\u0e19\u0e49\u0e33\u0e27\u0e19"
    ],
    "wof:name":"Ban Bang Nam Won",
    "wof:placetype":"locality"
},
  "geometry": {"coordinates":[100.46814000000001,14.65608],"type":"Point"}
}