{
  "type": "Feature",
  "properties": {
    "gn:admin1_code":"58.0",
    "gn:asciiname":"Ban Huai Ta Sing",
    "gn:country_code":"TH",
    "gn:dem":88,
    "gn:feature_class":"P",
    "gn:feature_code":"PPL",
    "gn:name":"Ban Huai Ta Sing",
    "gn:population":0,
    "gn:timezone":"Asia/Bangkok",
    "iso:country":"TH",
    "name:tha_x_preferred":[
        "\u0e1a\u0e49\u0e32\u0e19\u0e2b\u0e49\u0e27\u0e22\u0e15\u0e32\u0e2a\u0e34\u0e07\u0e2b\u0e4c"
    ],
    "wof:name":"Ban Huai Ta Sing",
    "wof:placetype":"locality"
},
  "geometry": {"coordinates":[99.02097000000001,9.83436],"type":"Point"}
}