{
  "type": "Feature",
  "properties": {
    "gn:admin1_code":"6.0",
    "gn:asciiname":"Ban Mae Ta Nai",
    "gn:country_code":"TH",
    "gn:dem":311,
    "gn:feature_class":"P",
    "gn:feature_code":"PPL",
    "gn:name":"Ban Mae Ta Nai",
    "gn:population":0,
    "gn:timezone":"Asia/Bangkok",
    "iso:country":"TH",
    "name:tha_x_preferred":[
        "\u0e1a\u0e49\u0e32\u0e19\u0e41\u0e21\u0e48\u0e15\u0e32\u0e43\u0e19"
    ],
    "name:und_x_variant":[
        "B\u0101n Mea Ta",
        "Ban Mae Ta",
        "Ban Mae Ta Noi",
        "Ban Mae Ta Nai"
    ],
    "wof:lang_x_official":[
        "tha"
    ],
    "wof:lang_x_spoken":[
        "tha"
    ],
    "wof:name":"Ban Mae Ta Nai",
    "wof:placetype":"locality"
},
  "geometry": {"coordinates":[99.62067,18.74872],"type":"Point"}
}