{
  "type": "Feature",
  "properties": {
    "gn:admin1_code":"2.0",
    "gn:asciiname":"Ban Bo De",
    "gn:country_code":"TH",
    "gn:dem":1052,
    "gn:feature_class":"P",
    "gn:feature_code":"PPL",
    "gn:name":"Ban Bo De",
    "gn:population":0,
    "gn:timezone":"Asia/Bangkok",
    "iso:country":"TH",
    "name:tha_x_preferred":[
        "\u0e1a\u0e49\u0e32\u0e19\u0e1a\u0e2d\u0e40\u0e14"
    ],
    "wof:name":"Ban Bo De",
    "wof:placetype":"locality"
},
  "geometry": {"coordinates":[98.12217,18.41222],"type":"Point"}
}