{
  "type": "Feature",
  "properties": {
    "gn:admin1_code":"32.0",
    "gn:asciiname":"Ban Thung Krathin",
    "gn:country_code":"TH",
    "gn:dem":24,
    "gn:feature_class":"P",
    "gn:feature_code":"PPL",
    "gn:name":"Ban Thung Krathin",
    "gn:population":0,
    "gn:timezone":"Asia/Bangkok",
    "iso:country":"TH",
    "name:tha_x_preferred":[
        "\u0e1a\u0e49\u0e32\u0e19\u0e17\u0e38\u0e48\u0e07\u0e01\u0e23\u0e30\u0e16\u0e34\u0e19"
    ],
    "name:und_x_variant":[
        "Ban Thung Kathin",
        "Ban Thung Krathin"
    ],
    "wof:lang_x_official":[
        "tha"
    ],
    "wof:lang_x_spoken":[
        "tha"
    ],
    "wof:name":"Ban Thung Krathin",
    "wof:placetype":"locality"
},
  "geometry": {"coordinates":[100.05722,15.21381],"type":"Point"}
}