{
  "type": "Feature",
  "properties": {
    "gn:admin1_code":"60.0",
    "gn:asciiname":"Ban Than Nam Ron",
    "gn:country_code":"TH",
    "gn:dem":9,
    "gn:feature_class":"P",
    "gn:feature_code":"PPL",
    "gn:name":"Ban Than Nam Ron",
    "gn:population":0,
    "gn:timezone":"Asia/Bangkok",
    "iso:country":"TH",
    "name:tha_x_preferred":[
        "\u0e1a\u0e49\u0e32\u0e19\u0e18\u0e32\u0e23\u0e19\u0e49\u0e33\u0e23\u0e49\u0e2d\u0e19"
    ],
    "wof:name":"Ban Than Nam Ron",
    "wof:placetype":"locality"
},
  "geometry": {"coordinates":[99.19489,9.34228],"type":"Point"}
}