{
  "type": "Feature",
  "properties": {
    "gn:admin1_code":"23.0",
    "gn:asciiname":"Ban Nong Sarai",
    "gn:country_code":"TH",
    "gn:dem":154,
    "gn:feature_class":"P",
    "gn:feature_code":"PPL",
    "gn:name":"Ban Nong Sarai",
    "gn:population":0,
    "gn:timezone":"Asia/Bangkok",
    "iso:country":"TH",
    "name:tha_x_preferred":[
        "\u0e1a\u0e49\u0e32\u0e19\u0e2b\u0e19\u0e2d\u0e07\u0e2a\u0e32\u0e2b\u0e23\u0e48\u0e32\u0e22"
    ],
    "wof:name":"Ban Nong Sarai",
    "wof:placetype":"locality"
},
  "geometry": {"coordinates":[103.5595,16.43139],"type":"Point"}
}