{
  "type": "Feature",
  "properties": {
    "gn:admin1_code":"53.0",
    "gn:asciiname":"Ban Khlong Bang Krasan",
    "gn:country_code":"TH",
    "gn:dem":4,
    "gn:feature_class":"P",
    "gn:feature_code":"PPL",
    "gn:name":"Ban Khlong Bang Krasan",
    "gn:population":0,
    "gn:timezone":"Asia/Bangkok",
    "iso:country":"TH",
    "name:tha_x_preferred":[
        "\u0e1a\u0e49\u0e32\u0e19\u0e04\u0e25\u0e2d\u0e07\u0e1a\u0e32\u0e07\u0e01\u0e23\u0e30\u0e2a\u0e31\u0e19"
    ],
    "name:und_x_variant":[
        "Ban Bang Krasan"
    ],
    "wof:name":"Ban Khlong Bang Krasan",
    "wof:placetype":"locality"
},
  "geometry": {"coordinates":[100.19749,13.69399],"type":"Point"}
}