{
  "type": "Feature",
  "properties": {
    "gn:admin1_code":"2.0",
    "gn:asciiname":"Ban Nong Krathing",
    "gn:country_code":"TH",
    "gn:dem":1032,
    "gn:feature_class":"P",
    "gn:feature_code":"PPL",
    "gn:name":"Ban Nong Krathing",
    "gn:population":0,
    "gn:timezone":"Asia/Bangkok",
    "iso:country":"TH",
    "name:tha_x_preferred":[
        "\u0e1a\u0e49\u0e32\u0e19\u0e2b\u0e19\u0e2d\u0e07\u0e01\u0e23\u0e30\u0e17\u0e34\u0e07"
    ],
    "name:und_x_variant":[
        "Ban Yang Nong Kathing"
    ],
    "wof:name":"Ban Nong Krathing",
    "wof:placetype":"locality"
},
  "geometry": {"coordinates":[98.35961,17.95786],"type":"Point"}
}