{
  "type": "Feature",
  "properties": {
    "gn:admin1_code":"24",
    "gn:asciiname":"Ban Non Nong Khu",
    "gn:country_code":"TH",
    "gn:dem":162,
    "gn:feature_class":"P",
    "gn:feature_code":"PPL",
    "gn:name":"Ban Non Nong Khu",
    "gn:population":0,
    "gn:timezone":"Asia/Bangkok",
    "iso:country":"TH",
    "name:tha_x_preferred":[
        "\u0e1a\u0e49\u0e32\u0e19\u0e42\u0e19\u0e19\u0e2b\u0e19\u0e2d\u0e07\u0e04\u0e39"
    ],
    "wof:name":"Ban Non Nong Khu",
    "wof:placetype":"locality"
},
  "geometry": {"coordinates":[103.05258000000001,16.17725],"type":"Point"}
}