{
  "type": "Feature",
  "properties": {
    "gn:admin1_code":"22",
    "gn:asciiname":"Ban Hua Fai",
    "gn:country_code":"TH",
    "gn:dem":196,
    "gn:feature_class":"P",
    "gn:feature_code":"PPL",
    "gn:name":"Ban Hua Fai",
    "gn:population":0,
    "gn:timezone":"Asia/Bangkok",
    "iso:country":"TH",
    "name:tha_x_preferred":[
        "\u0e1a\u0e49\u0e32\u0e19\u0e2b\u0e31\u0e27\u0e1d\u0e32\u0e22"
    ],
    "wof:name":"Ban Hua Fai",
    "wof:placetype":"locality"
},
  "geometry": {"coordinates":[102.47081,16.13067],"type":"Point"}
}