{
  "type": "Feature",
  "properties": {
    "gn:admin1_code":"23.0",
    "gn:asciiname":"Ban Non Chai",
    "gn:country_code":"TH",
    "gn:dem":149,
    "gn:feature_class":"P",
    "gn:feature_code":"PPL",
    "gn:name":"Ban Non Chai",
    "gn:population":0,
    "gn:timezone":"Asia/Bangkok",
    "iso:country":"TH",
    "name:tha_x_preferred":[
        "\u0e1a\u0e49\u0e32\u0e19\u0e42\u0e19\u0e19\u0e0a\u0e31\u0e22"
    ],
    "wof:name":"Ban Non Chai",
    "wof:placetype":"locality"
},
  "geometry": {"coordinates":[103.41231000000001,16.26011],"type":"Point"}
}