{
  "type": "Feature",
  "properties": {
    "gn:admin1_code":"49.0",
    "gn:asciiname":"Ban Kasem Suk",
    "gn:country_code":"TH",
    "gn:dem":25,
    "gn:feature_class":"P",
    "gn:feature_code":"PPL",
    "gn:name":"Ban Kasem Suk",
    "gn:population":0,
    "gn:timezone":"Asia/Bangkok",
    "iso:country":"TH",
    "name:tha_x_preferred":[
        "\u0e1a\u0e49\u0e32\u0e19\u0e40\u0e01\u0e29\u0e21\u0e2a\u0e38\u0e02"
    ],
    "wof:name":"Ban Kasem Suk",
    "wof:placetype":"locality"
},
  "geometry": {"coordinates":[102.40085999999999,12.48158],"type":"Point"}
}