{
  "type": "Feature",
  "properties": {
    "gn:admin1_code":"65.0",
    "gn:asciiname":"Ban Sai Thon",
    "gn:country_code":"TH",
    "gn:dem":50,
    "gn:feature_class":"P",
    "gn:feature_code":"PPL",
    "gn:name":"Ban Sai Thon",
    "gn:population":0,
    "gn:timezone":"Asia/Bangkok",
    "iso:country":"TH",
    "name:tha_x_preferred":[
        "\u0e1a\u0e49\u0e32\u0e19\u0e44\u0e2a\u0e17\u0e49\u0e2d\u0e19"
    ],
    "wof:name":"Ban Sai Thon",
    "wof:placetype":"locality"
},
  "geometry": {"coordinates":[99.77231,7.54797],"type":"Point"}
}