{
  "type": "Feature",
  "properties": {
    "gn:admin1_code":"3.0",
    "gn:asciiname":"Ban San Ku",
    "gn:country_code":"TH",
    "gn:dem":588,
    "gn:feature_class":"P",
    "gn:feature_code":"PPL",
    "gn:name":"Ban San Ku",
    "gn:population":0,
    "gn:timezone":"Asia/Bangkok",
    "iso:country":"TH",
    "name:tha_x_preferred":[
        "\u0e1a\u0e49\u0e32\u0e19\u0e2a\u0e31\u0e19\u0e01\u0e39\u0e48"
    ],
    "wof:name":"Ban San Ku",
    "wof:placetype":"locality"
},
  "geometry": {"coordinates":[99.52642,19.18444],"type":"Point"}
}