{
  "type": "Feature",
  "properties": {
    "gn:admin1_code":"70.0",
    "gn:asciiname":"Ban Cha Ro Cha Wa",
    "gn:country_code":"TH",
    "gn:dem":504,
    "gn:feature_class":"P",
    "gn:feature_code":"PPL",
    "gn:name":"Ban Cha Ro Cha Wa",
    "gn:population":0,
    "gn:timezone":"Asia/Bangkok",
    "iso:country":"TH",
    "wof:name":"Ban Cha Ro Cha Wa",
    "wof:placetype":"locality"
},
  "geometry": {"coordinates":[101.05,5.81667],"type":"Point"}
}