{
  "type": "Feature",
  "properties": {
    "gn:admin1_code":"14.0",
    "gn:asciiname":"Ban Sam I Loet",
    "gn:country_code":"TH",
    "gn:dem":147,
    "gn:feature_class":"P",
    "gn:feature_code":"PPL",
    "gn:name":"Ban Sam I Loet",
    "gn:population":0,
    "gn:timezone":"Asia/Bangkok",
    "iso:country":"TH",
    "name:tha_x_preferred":[
        "\u0e1a\u0e49\u0e32\u0e19\u0e0b\u0e33\u0e2d\u0e35\u0e40\u0e25\u0e34\u0e28"
    ],
    "wof:name":"Ban Sam I Loet",
    "wof:placetype":"locality"
},
  "geometry": {"coordinates":[101.13191999999999,16.55558],"type":"Point"}
}