{
  "type": "Feature",
  "properties": {
    "gn:admin1_code":"18.0",
    "gn:asciiname":"Ban Hat Khamphi",
    "gn:country_code":"TH",
    "gn:dem":196,
    "gn:feature_class":"P",
    "gn:feature_code":"PPL",
    "gn:name":"Ban Hat Khamphi",
    "gn:population":0,
    "gn:timezone":"Asia/Bangkok",
    "iso:country":"TH",
    "name:tha_x_preferred":[
        "\u0e1a\u0e49\u0e32\u0e19\u0e2b\u0e32\u0e14\u0e04\u0e33\u0e20\u0e35\u0e23\u0e4c"
    ],
    "name:und_x_variant":[
        "Ban Hat Kam Phi",
        "Ban Hat Khamphi"
    ],
    "wof:lang_x_official":[
        "tha"
    ],
    "wof:lang_x_spoken":[
        "tha"
    ],
    "wof:name":"Ban Hat Khamphi",
    "wof:placetype":"locality"
},
  "geometry": {"coordinates":[102.02245000000001,18.14417000000001],"type":"Point"}
}