{
  "type": "Feature",
  "properties": {
    "gn:admin1_code":"28.0",
    "gn:asciiname":"Ban Nong Mai Ngam Song",
    "gn:country_code":"TH",
    "gn:dem":229,
    "gn:feature_class":"P",
    "gn:feature_code":"PPL",
    "gn:name":"Ban Nong Mai Ngam Song",
    "gn:population":0,
    "gn:timezone":"Asia/Bangkok",
    "iso:country":"TH",
    "name:tha_x_preferred":[
        "\u0e1a\u0e49\u0e32\u0e19\u0e2b\u0e19\u0e2d\u0e07\u0e44\u0e21\u0e49\u0e07\u0e32\u0e21 \u0e2a\u0e2d\u0e07"
    ],
    "name:und_x_variant":[
        "Ban Nong Mai Ngam"
    ],
    "wof:name":"Ban Nong Mai Ngam Song",
    "wof:placetype":"locality"
},
  "geometry": {"coordinates":[103.00620000000001,14.37383],"type":"Point"}
}