{
  "type": "Feature",
  "properties": {
    "gn:admin1_code":"5.0",
    "gn:asciiname":"Ban Pa Sao",
    "gn:country_code":"TH",
    "gn:dem":295,
    "gn:feature_class":"P",
    "gn:feature_code":"PPL",
    "gn:name":"Ban Pa Sao",
    "gn:population":0,
    "gn:timezone":"Asia/Bangkok",
    "iso:country":"TH",
    "name:tha_x_preferred":[
        "\u0e1a\u0e49\u0e32\u0e19\u0e1b\u0e48\u0e32\u0e40\u0e2a\u0e49\u0e32"
    ],
    "wof:name":"Ban Pa Sao",
    "wof:placetype":"locality"
},
  "geometry": {"coordinates":[99.04267,18.64003],"type":"Point"}
}