{
  "type": "Feature",
  "properties": {
    "gn:admin1_code":"75.0",
    "gn:asciiname":"Ban Nong Khi Hen",
    "gn:country_code":"TH",
    "gn:dem":159,
    "gn:feature_class":"P",
    "gn:feature_code":"PPL",
    "gn:name":"Ban Nong Khi Hen",
    "gn:population":0,
    "gn:timezone":"Asia/Bangkok",
    "iso:country":"TH",
    "name:tha_x_preferred":[
        "\u0e1a\u0e49\u0e32\u0e19\u0e2b\u0e19\u0e2d\u0e07\u0e02\u0e35\u0e49\u0e40\u0e2b\u0e47\u0e19"
    ],
    "wof:name":"Ban Nong Khi Hen",
    "wof:placetype":"locality"
},
  "geometry": {"coordinates":[104.89964000000001,14.82072],"type":"Point"}
}