{
  "type": "Feature",
  "properties": {
    "gn:admin1_code":"2.0",
    "gn:asciiname":"Ban Tha Mai I",
    "gn:country_code":"TH",
    "gn:dem":301,
    "gn:feature_class":"P",
    "gn:feature_code":"PPL",
    "gn:name":"Ban Tha Mai I",
    "gn:population":0,
    "gn:timezone":"Asia/Bangkok",
    "iso:country":"TH",
    "name:tha_x_preferred":[
        "\u0e1a\u0e49\u0e32\u0e19\u0e17\u0e48\u0e32\u0e43\u0e2b\u0e21\u0e48\u0e2d\u0e34"
    ],
    "name:und_x_variant":[
        "Ban Pa Daet",
        "B\u0101n Pa Deat",
        "Ban Mai I",
        "Ban Tha Mai I"
    ],
    "wof:name":"Ban Tha Mai I",
    "wof:placetype":"locality"
},
  "geometry": {"coordinates":[98.98578000000001,18.72139],"type":"Point"}
}