{
  "type": "Feature",
  "properties": {
    "gn:admin1_code":"52.0",
    "gn:asciiname":"Ban Nong Ti Uan",
    "gn:country_code":"TH",
    "gn:dem":13,
    "gn:feature_class":"P",
    "gn:feature_code":"PPL",
    "gn:name":"Ban Nong Ti Uan",
    "gn:population":0,
    "gn:timezone":"Asia/Bangkok",
    "iso:country":"TH",
    "name:tha_x_preferred":[
        "\u0e1a\u0e49\u0e32\u0e19\u0e2b\u0e19\u0e2d\u0e07\u0e15\u0e35\u0e2d\u0e27\u0e19"
    ],
    "name:und_x_variant":[
        "Ban Pong Sadao",
        "Ban Nong Tian",
        "Ban Nong Takhian",
        "Ban Nong Ti Uan"
    ],
    "wof:name":"Ban Nong Ti Uan",
    "wof:placetype":"locality"
},
  "geometry": {"coordinates":[99.80956,13.80403],"type":"Point"}
}