{
  "type": "Feature",
  "properties": {
    "gn:admin1_code":"22.0",
    "gn:asciiname":"Ban Pa Du",
    "gn:country_code":"TH",
    "gn:dem":211,
    "gn:feature_class":"P",
    "gn:feature_code":"PPL",
    "gn:name":"Ban Pa Du",
    "gn:population":0,
    "gn:timezone":"Asia/Bangkok",
    "iso:country":"TH",
    "name:tha_x_preferred":[
        "\u0e1a\u0e49\u0e32\u0e19\u0e1b\u0e48\u0e32\u0e14\u0e39\u0e48"
    ],
    "wof:name":"Ban Pa Du",
    "wof:placetype":"locality"
},
  "geometry": {"coordinates":[102.48775000000001,16.26864],"type":"Point"}
}