{
  "type": "Feature",
  "properties": {
    "gn:admin1_code":"23.0",
    "gn:asciiname":"Ban Non Sila Thong",
    "gn:country_code":"TH",
    "gn:dem":170,
    "gn:feature_class":"P",
    "gn:feature_code":"PPL",
    "gn:name":"Ban Non Sila Thong",
    "gn:population":0,
    "gn:timezone":"Asia/Bangkok",
    "iso:country":"TH",
    "name:tha_x_preferred":[
        "\u0e1a\u0e49\u0e32\u0e19\u0e42\u0e19\u0e19\u0e28\u0e34\u0e25\u0e32\u0e17\u0e2d\u0e07"
    ],
    "wof:name":"Ban Non Sila Thong",
    "wof:placetype":"locality"
},
  "geometry": {"coordinates":[103.47281,16.80203],"type":"Point"}
}