{
  "type": "Feature",
  "properties": {
    "gn:admin1_code":"28.0",
    "gn:asciiname":"Ban Hin Khon Dong",
    "gn:country_code":"TH",
    "gn:dem":211,
    "gn:feature_class":"P",
    "gn:feature_code":"PPL",
    "gn:name":"Ban Hin Khon Dong",
    "gn:population":0,
    "gn:timezone":"Asia/Bangkok",
    "iso:country":"TH",
    "wof:name":"Ban Hin Khon Dong",
    "wof:placetype":"locality"
},
  "geometry": {"coordinates":[102.59999999999999,14.41667],"type":"Point"}
}