{
  "type": "Feature",
  "properties": {
    "gn:admin1_code":"75.0",
    "gn:asciiname":"Ban Lin Mai",
    "gn:country_code":"TH",
    "gn:dem":128,
    "gn:feature_class":"P",
    "gn:feature_code":"PPL",
    "gn:name":"Ban Lin Mai",
    "gn:population":0,
    "gn:timezone":"Asia/Bangkok",
    "iso:country":"TH",
    "name:tha_x_preferred":[
        "\u0e1a\u0e49\u0e32\u0e19\u0e25\u0e34\u0e49\u0e19\u0e44\u0e21\u0e49"
    ],
    "wof:name":"Ban Lin Mai",
    "wof:placetype":"locality"
},
  "geometry": {"coordinates":[104.92833,15.11278],"type":"Point"}
}