{
  "type": "Feature",
  "properties": {
    "gn:admin1_code":"23.0",
    "gn:asciiname":"Ban Khao Lam",
    "gn:country_code":"TH",
    "gn:dem":145,
    "gn:feature_class":"P",
    "gn:feature_code":"PPL",
    "gn:name":"Ban Khao Lam",
    "gn:population":0,
    "gn:timezone":"Asia/Bangkok",
    "iso:country":"TH",
    "name:tha_x_preferred":[
        "\u0e1a\u0e49\u0e32\u0e19\u0e02\u0e49\u0e32\u0e27\u0e2b\u0e25\u0e32\u0e21"
    ],
    "wof:name":"Ban Khao Lam",
    "wof:placetype":"locality"
},
  "geometry": {"coordinates":[103.52847,16.32361],"type":"Point"}
}