{
  "type": "Feature",
  "properties": {
    "gn:admin1_code":"28.0",
    "gn:asciiname":"Ban Raboek",
    "gn:country_code":"TH",
    "gn:dem":192,
    "gn:feature_class":"P",
    "gn:feature_code":"PPL",
    "gn:name":"Ban Raboek",
    "gn:population":0,
    "gn:timezone":"Asia/Bangkok",
    "iso:country":"TH",
    "name:tha_x_preferred":[
        "\u0e1a\u0e49\u0e32\u0e19\u0e23\u0e30\u0e40\u0e1a\u0e34\u0e01"
    ],
    "name:und_x_variant":[
        "Ban Nong Raboek",
        "Ban Raboek",
        "Ban Ra Boet"
    ],
    "wof:name":"Ban Raboek",
    "wof:placetype":"locality"
},
  "geometry": {"coordinates":[102.8965,14.60331],"type":"Point"}
}