{
  "type": "Feature",
  "properties": {
    "gn:admin1_code":"2.0",
    "gn:asciiname":"Ban Mut Ka (1)",
    "gn:cc2":"TH",
    "gn:country_code":"TH",
    "gn:dem":241,
    "gn:feature_class":"P",
    "gn:feature_code":"PPL",
    "gn:name":"Ban Mut Ka (1)",
    "gn:population":0,
    "gn:timezone":"Asia/Bangkok",
    "iso:country":"TH",
    "name:und_x_variant":[
        "Moet Ka",
        "M\u0113 K\u0101ng",
        "Ban Mut Ka (1)"
    ],
    "wof:lang_x_official":[
        "tha"
    ],
    "wof:lang_x_spoken":[
        "tha"
    ],
    "wof:name":"Ban Mut Ka (1)",
    "wof:placetype":"locality"
},
  "geometry": {"coordinates":[98.65000000000001,17.88332999999999],"type":"Point"}
}