{
  "type": "Feature",
  "properties": {
    "gn:admin1_code":"75.0",
    "gn:asciiname":"Ban Kut Kasian",
    "gn:country_code":"TH",
    "gn:dem":126,
    "gn:feature_class":"P",
    "gn:feature_code":"PPL",
    "gn:name":"Ban Kut Kasian",
    "gn:population":0,
    "gn:timezone":"Asia/Bangkok",
    "iso:country":"TH",
    "name:tha_x_preferred":[
        "\u0e1a\u0e49\u0e32\u0e19\u0e01\u0e38\u0e14\u0e01\u0e30\u0e40\u0e2a\u0e35\u0e22\u0e19"
    ],
    "name:und_x_variant":[
        "Ban Suk Kasem",
        "Ban Kut Krasian"
    ],
    "wof:lang_x_official":[
        "tha"
    ],
    "wof:lang_x_spoken":[
        "tha"
    ],
    "wof:name":"Ban Kut Kasian",
    "wof:placetype":"locality"
},
  "geometry": {"coordinates":[104.54817,15.33292],"type":"Point"}
}