{
  "type": "Feature",
  "properties": {
    "gn:admin1_code":"66.0",
    "gn:asciiname":"Ban Phraek Yo",
    "gn:country_code":"TH",
    "gn:dem":50,
    "gn:feature_class":"P",
    "gn:feature_code":"PPL",
    "gn:name":"Ban Phraek Yo",
    "gn:population":0,
    "gn:timezone":"Asia/Bangkok",
    "iso:country":"TH",
    "name:tha_x_preferred":[
        "\u0e1a\u0e49\u0e32\u0e19\u0e41\u0e1e\u0e23\u0e01\u0e22\u0e2d"
    ],
    "wof:name":"Ban Phraek Yo",
    "wof:placetype":"locality"
},
  "geometry": {"coordinates":[99.92833,7.61819],"type":"Point"}
}