{
  "type": "Feature",
  "properties": {
    "gn:admin1_code":"72.0",
    "gn:asciiname":"Ban Ko Mo Sam",
    "gn:country_code":"TH",
    "gn:dem":141,
    "gn:feature_class":"P",
    "gn:feature_code":"PPL",
    "gn:name":"Ban Ko Mo Sam",
    "gn:population":0,
    "gn:timezone":"Asia/Bangkok",
    "iso:country":"TH",
    "name:tha_x_preferred":[
        "\u0e1a\u0e49\u0e32\u0e19 \u0e01\u0e21.\u0e2a\u0e32\u0e21"
    ],
    "wof:name":"Ban Ko Mo Sam",
    "wof:placetype":"locality"
},
  "geometry": {"coordinates":[104.18767,15.80108],"type":"Point"}
}