{
  "type": "Feature",
  "properties": {
    "gn:admin1_code":"14.0",
    "gn:asciiname":"Ban Huai Kon Tha",
    "gn:country_code":"TH",
    "gn:dem":586,
    "gn:feature_class":"P",
    "gn:feature_code":"PPL",
    "gn:name":"Ban Huai Kon Tha",
    "gn:population":0,
    "gn:timezone":"Asia/Bangkok",
    "iso:country":"TH",
    "name:tha_x_preferred":[
        "\u0e1a\u0e49\u0e32\u0e19\u0e2b\u0e49\u0e27\u0e22\u0e01\u0e25\u0e17\u0e32"
    ],
    "wof:name":"Ban Huai Kon Tha",
    "wof:placetype":"locality"
},
  "geometry": {"coordinates":[101.39936,16.74689],"type":"Point"}
}