{
  "type": "Feature",
  "properties": {
    "gn:admin1_code":"3.0",
    "gn:asciiname":"Ban Hua Thung",
    "gn:country_code":"TH",
    "gn:dem":476,
    "gn:feature_class":"P",
    "gn:feature_code":"PPL",
    "gn:name":"Ban Hua Thung",
    "gn:population":0,
    "gn:timezone":"Asia/Bangkok",
    "iso:country":"TH",
    "name:tha_x_preferred":[
        "\u0e1a\u0e49\u0e32\u0e19\u0e2b\u0e31\u0e27\u0e17\u0e38\u0e48\u0e07"
    ],
    "wof:name":"Ban Hua Thung",
    "wof:placetype":"locality"
},
  "geometry": {"coordinates":[99.6645,19.8142],"type":"Point"}
}