{
  "type": "Feature",
  "properties": {
    "gn:admin1_code":"39.0",
    "gn:asciiname":"Ban Khlong Hok Wa",
    "gn:country_code":"TH",
    "gn:dem":7,
    "gn:feature_class":"P",
    "gn:feature_code":"PPL",
    "gn:name":"Ban Khlong Hok Wa",
    "gn:population":0,
    "gn:timezone":"Asia/Bangkok",
    "iso:country":"TH",
    "name:tha_x_preferred":[
        "\u0e1a\u0e49\u0e32\u0e19\u0e04\u0e25\u0e2d\u0e07\u0e2b\u0e01\u0e27\u0e32"
    ],
    "wof:name":"Ban Khlong Hok Wa",
    "wof:placetype":"locality"
},
  "geometry": {"coordinates":[100.75681,13.93103],"type":"Point"}
}