{
  "type": "Feature",
  "properties": {
    "gn:admin1_code":"31.0",
    "gn:asciiname":"Ban Kwa Lo Si Ra Paknam",
    "gn:country_code":"TH",
    "gn:dem":12,
    "gn:feature_class":"P",
    "gn:feature_code":"PPL",
    "gn:name":"Ban Kwa Lo Si Ra Paknam",
    "gn:population":0,
    "gn:timezone":"Asia/Bangkok",
    "iso:country":"TH",
    "name:tha_x_preferred":[
        "\u0e1a\u0e49\u0e32\u0e19\u0e01\u0e27\u0e32\u0e25\u0e2d\u0e0b\u0e35\u0e23\u0e32 (\u0e1b\u0e32\u0e01\u0e19\u0e49\u0e33)"
    ],
    "wof:lang_x_official":[
        "tha"
    ],
    "wof:lang_x_spoken":[
        "tha"
    ],
    "wof:name":"Ban Kwa Lo Si Ra Paknam",
    "wof:placetype":"locality"
},
  "geometry": {"coordinates":[102.00339,6.05228],"type":"Point"}
}