{
  "type": "Feature",
  "properties": {
    "gn:admin1_code":"25.0",
    "gn:asciiname":"Ban Dong Man",
    "gn:country_code":"TH",
    "gn:dem":190,
    "gn:feature_class":"P",
    "gn:feature_code":"PPL",
    "gn:name":"Ban Dong Man",
    "gn:population":0,
    "gn:timezone":"Asia/Bangkok",
    "iso:country":"TH",
    "name:tha_x_preferred":[
        "\u0e1a\u0e49\u0e32\u0e19\u0e14\u0e07\u0e21\u0e31\u0e19"
    ],
    "wof:name":"Ban Dong Man",
    "wof:placetype":"locality"
},
  "geometry": {"coordinates":[103.95119,16.38581],"type":"Point"}
}