{
  "type": "Feature",
  "properties": {
    "gn:admin1_code":"61.0",
    "gn:asciiname":"Ban Chao Nam",
    "gn:cc2":"TH",
    "gn:country_code":"TH",
    "gn:dem":12,
    "gn:feature_class":"P",
    "gn:feature_code":"PPL",
    "gn:name":"Ban Chao Nam",
    "gn:population":0,
    "gn:timezone":"Asia/Bangkok",
    "iso:country":"TH",
    "name:und_x_variant":[
        "Ban Chaona",
        "Ban Chao Nam"
    ],
    "wof:name":"Ban Chao Nam",
    "wof:placetype":"locality"
},
  "geometry": {"coordinates":[98.26667,8.85],"type":"Point"}
}