{
  "type": "Feature",
  "properties": {
    "gn:admin1_code":"8.0",
    "gn:asciiname":"Ban Kha Nae Kho Kro",
    "gn:country_code":"TH",
    "gn:dem":281,
    "gn:feature_class":"P",
    "gn:feature_code":"PPL",
    "gn:name":"Ban Kha Nae Kho Kro",
    "gn:population":0,
    "gn:timezone":"Asia/Bangkok",
    "iso:country":"TH",
    "name:tha_x_preferred":[
        "\u0e1a\u0e49\u0e32\u0e19\u0e04\u0e30\u0e41\u0e19\u0e04\u0e2d\u0e42\u0e01\u0e23"
    ],
    "wof:lang_x_official":[
        "tha"
    ],
    "wof:lang_x_spoken":[
        "tha"
    ],
    "wof:name":"Ban Kha Nae Kho Kro",
    "wof:placetype":"locality"
},
  "geometry": {"coordinates":[98.20189000000001,17.4057],"type":"Point"}
}