{
  "type": "Feature",
  "properties": {
    "gn:admin1_code":"76.0",
    "gn:asciiname":"Ban Kong Phan",
    "gn:country_code":"TH",
    "gn:dem":174,
    "gn:feature_class":"P",
    "gn:feature_code":"PPL",
    "gn:name":"Ban Kong Phan",
    "gn:population":0,
    "gn:timezone":"Asia/Bangkok",
    "iso:country":"TH",
    "name:tha_x_preferred":[
        "\u0e1a\u0e49\u0e32\u0e19\u0e01\u0e07\u0e1e\u0e32\u0e19"
    ],
    "wof:name":"Ban Kong Phan",
    "wof:placetype":"locality"
},
  "geometry": {"coordinates":[102.96522,17.11644],"type":"Point"}
}