{
  "type": "Feature",
  "properties": {
    "gn:admin1_code":"50.0",
    "gn:asciiname":"Ban Nong Ya Khao-Nok",
    "gn:country_code":"TH",
    "gn:dem":80,
    "gn:feature_class":"P",
    "gn:feature_code":"PPL",
    "gn:name":"Ban Nong Ya Khao-Nok",
    "gn:population":0,
    "gn:timezone":"Asia/Bangkok",
    "iso:country":"TH",
    "name:tha_x_preferred":[
        "\u0e1a\u0e49\u0e32\u0e19\u0e2b\u0e19\u0e2d\u0e07\u0e2b\u0e0d\u0e49\u0e32\u0e02\u0e49\u0e32\u0e27\u0e19\u0e01"
    ],
    "wof:name":"Ban Nong Ya Khao-Nok",
    "wof:placetype":"locality"
},
  "geometry": {"coordinates":[99.54694000000001,13.78319],"type":"Point"}
}