{
  "type": "Feature",
  "properties": {
    "gn:admin1_code":"0.0",
    "gn:asciiname":"Ban Prong Khe",
    "gn:country_code":"TH",
    "gn:dem":622,
    "gn:feature_class":"P",
    "gn:feature_code":"PPL",
    "gn:name":"Ban Prong Khe",
    "gn:population":0,
    "gn:timezone":"Asia/Bangkok",
    "iso:country":"TH",
    "wof:name":"Ban Prong Khe",
    "wof:placetype":"locality"
},
  "geometry": {"coordinates":[98.98333,14.83333],"type":"Point"}
}