{
  "type": "Feature",
  "properties": {
    "gn:admin1_code":"8.0",
    "gn:asciiname":"Ban Huai Nok Lae",
    "gn:country_code":"TH",
    "gn:dem":577,
    "gn:feature_class":"P",
    "gn:feature_code":"PPL",
    "gn:name":"Ban Huai Nok Lae",
    "gn:population":0,
    "gn:timezone":"Asia/Bangkok",
    "iso:country":"TH",
    "name:tha_x_preferred":[
        "\u0e1a\u0e49\u0e32\u0e19\u0e2b\u0e49\u0e27\u0e22\u0e19\u0e01\u0e41\u0e25"
    ],
    "wof:name":"Ban Huai Nok Lae",
    "wof:placetype":"locality"
},
  "geometry": {"coordinates":[98.70339,16.53195],"type":"Point"}
}