{
  "type": "Feature",
  "properties": {
    "gn:admin1_code":"50.0",
    "gn:asciiname":"Ban Tin Tok",
    "gn:country_code":"TH",
    "gn:dem":316,
    "gn:feature_class":"P",
    "gn:feature_code":"PPL",
    "gn:name":"Ban Tin Tok",
    "gn:population":0,
    "gn:timezone":"Asia/Bangkok",
    "iso:country":"TH",
    "name:tha_x_preferred":[
        "\u0e1a\u0e49\u0e32\u0e19\u0e15\u0e35\u0e19\u0e15\u0e01"
    ],
    "name:und_x_variant":[
        "Ban Din Tok",
        "Ban Tin Tok"
    ],
    "wof:name":"Ban Tin Tok",
    "wof:placetype":"locality"
},
  "geometry": {"coordinates":[99.17031,14.81311],"type":"Point"}
}