{
  "type": "Feature",
  "properties": {
    "gn:admin1_code":"66.0",
    "gn:asciiname":"Ban Tha Khae",
    "gn:country_code":"TH",
    "gn:dem":23,
    "gn:feature_class":"P",
    "gn:feature_code":"PPL",
    "gn:name":"Ban Tha Khae",
    "gn:population":0,
    "gn:timezone":"Asia/Bangkok",
    "iso:country":"TH",
    "name:tha_x_preferred":[
        "\u0e1a\u0e49\u0e32\u0e19\u0e17\u0e48\u0e32\u0e41\u0e04"
    ],
    "name:und_x_variant":[
        "Ban Tah Ke",
        "Ban Tha Khae (1)",
        "Ban Tha Khae"
    ],
    "wof:name":"Ban Tha Khae",
    "wof:placetype":"locality"
},
  "geometry": {"coordinates":[100.04608,7.57272],"type":"Point"}
}