{
  "type": "Feature",
  "properties": {
    "gn:admin1_code":"35.0",
    "gn:asciiname":"Ban Phai Cham Sin",
    "gn:country_code":"TH",
    "gn:dem":12,
    "gn:feature_class":"P",
    "gn:feature_code":"PPL",
    "gn:name":"Ban Phai Cham Sin",
    "gn:population":0,
    "gn:timezone":"Asia/Bangkok",
    "iso:country":"TH",
    "name:tha_x_preferred":[
        "\u0e1a\u0e49\u0e32\u0e19\u0e44\u0e1c\u0e48\u0e08\u0e33\u0e28\u0e35\u0e25"
    ],
    "name:und_x_variant":[
        "Phai Chamsin",
        "B\u0101 Phai Chamsil",
        "Cham Sin",
        "Ban Phai Cham Sin"
    ],
    "wof:name":"Ban Phai Cham Sin",
    "wof:placetype":"locality"
},
  "geometry": {"coordinates":[100.35460999999999,14.61428],"type":"Point"}
}