{
  "type": "Feature",
  "properties": {
    "gn:admin1_code":"68.0",
    "gn:asciiname":"Ban Khuan Mai Phai",
    "gn:country_code":"TH",
    "gn:dem":140,
    "gn:feature_class":"P",
    "gn:feature_code":"PPL",
    "gn:name":"Ban Khuan Mai Phai",
    "gn:population":0,
    "gn:timezone":"Asia/Bangkok",
    "iso:country":"TH",
    "name:tha_x_preferred":[
        "\u0e1a\u0e49\u0e32\u0e19\u0e04\u0e27\u0e19\u0e44\u0e21\u0e49\u0e44\u0e1c\u0e48"
    ],
    "name:und_x_variant":[
        "Khuan Mai Phai",
        "Kuan Mai Pai",
        "Ban Khuan Mai Phai"
    ],
    "wof:lang_x_official":[
        "tha"
    ],
    "wof:lang_x_spoken":[
        "tha"
    ],
    "wof:name":"Ban Khuan Mai Phai",
    "wof:placetype":"locality"
},
  "geometry": {"coordinates":[100.64194999999999,6.92011],"type":"Point"}
}