{
  "type": "Feature",
  "properties": {
    "gn:admin1_code":"5.0",
    "gn:asciiname":"Ban Pa Heo",
    "gn:country_code":"TH",
    "gn:dem":297,
    "gn:feature_class":"P",
    "gn:feature_code":"PPL",
    "gn:name":"Ban Pa Heo",
    "gn:population":0,
    "gn:timezone":"Asia/Bangkok",
    "iso:country":"TH",
    "name:tha_x_preferred":[
        "\u0e1a\u0e49\u0e32\u0e19\u0e1b\u0e48\u0e32\u0e40\u0e2b\u0e47\u0e27"
    ],
    "name:und_x_variant":[
        "Ban Pa Neo"
    ],
    "wof:lang_x_official":[
        "tha"
    ],
    "wof:lang_x_spoken":[
        "tha"
    ],
    "wof:name":"Ban Pa Heo",
    "wof:placetype":"locality"
},
  "geometry": {"coordinates":[99.03888999999999,18.64997],"type":"Point"}
}