{
  "type": "Feature",
  "properties": {
    "gn:admin1_code":"6.0",
    "gn:asciiname":"Ban Huai Kot",
    "gn:country_code":"TH",
    "gn:dem":398,
    "gn:feature_class":"P",
    "gn:feature_code":"PPL",
    "gn:name":"Ban Huai Kot",
    "gn:population":0,
    "gn:timezone":"Asia/Bangkok",
    "iso:country":"TH",
    "name:tha_x_preferred":[
        "\u0e1a\u0e49\u0e32\u0e19\u0e2b\u0e49\u0e27\u0e22\u0e01\u0e49\u0e2d\u0e14"
    ],
    "wof:name":"Ban Huai Kot",
    "wof:placetype":"locality"
},
  "geometry": {"coordinates":[99.60722,19.03381],"type":"Point"}
}