{
  "type": "Feature",
  "properties": {
    "gn:admin1_code":"2.0",
    "gn:asciiname":"Ban Rong Wua",
    "gn:country_code":"TH",
    "gn:dem":314,
    "gn:feature_class":"P",
    "gn:feature_code":"PPL",
    "gn:name":"Ban Rong Wua",
    "gn:population":0,
    "gn:timezone":"Asia/Bangkok",
    "iso:country":"TH",
    "name:tha_x_preferred":[
        "\u0e1a\u0e49\u0e32\u0e19\u0e42\u0e23\u0e07\u0e27\u0e31\u0e27"
    ],
    "name:und_x_variant":[
        "Ban Rong Ngua"
    ],
    "wof:name":"Ban Rong Wua",
    "wof:placetype":"locality"
},
  "geometry": {"coordinates":[98.90611,18.68158],"type":"Point"}
}