{
  "type": "Feature",
  "properties": {
    "gn:admin1_code":"23.0",
    "gn:asciiname":"Ban Dong Sayam",
    "gn:country_code":"TH",
    "gn:dem":226,
    "gn:feature_class":"P",
    "gn:feature_code":"PPL",
    "gn:name":"Ban Dong Sayam",
    "gn:population":0,
    "gn:timezone":"Asia/Bangkok",
    "iso:country":"TH",
    "name:tha_x_preferred":[
        "\u0e1a\u0e49\u0e32\u0e19\u0e14\u0e07\u0e2a\u0e22\u0e32\u0e21"
    ],
    "wof:name":"Ban Dong Sayam",
    "wof:placetype":"locality"
},
  "geometry": {"coordinates":[103.77622,16.51861],"type":"Point"}
}