{
  "type": "Feature",
  "properties": {
    "gn:admin1_code":"75.0",
    "gn:asciiname":"Ban Wang Mon",
    "gn:country_code":"TH",
    "gn:dem":128,
    "gn:feature_class":"P",
    "gn:feature_code":"PPL",
    "gn:name":"Ban Wang Mon",
    "gn:population":0,
    "gn:timezone":"Asia/Bangkok",
    "iso:country":"TH",
    "name:tha_x_preferred":[
        "\u0e1a\u0e49\u0e32\u0e19\u0e27\u0e31\u0e07\u0e21\u0e19"
    ],
    "wof:name":"Ban Wang Mon",
    "wof:placetype":"locality"
},
  "geometry": {"coordinates":[104.66358,15.391],"type":"Point"}
}