{
  "type": "Feature",
  "properties": {
    "gn:admin1_code":"3.0",
    "gn:asciiname":"Ban Chong",
    "gn:country_code":"TH",
    "gn:dem":385,
    "gn:feature_class":"P",
    "gn:feature_code":"PPL",
    "gn:name":"Ban Chong",
    "gn:population":0,
    "gn:timezone":"Asia/Bangkok",
    "iso:country":"TH",
    "name:tha_x_preferred":[
        "\u0e1a\u0e49\u0e32\u0e19\u0e08\u0e49\u0e2d\u0e07"
    ],
    "name:und_x_variant":[
        "Jaung",
        "B\u0101n Jaung",
        "Ban Chong",
        "Ban Chong (1)"
    ],
    "wof:lang_x_official":[
        "tha"
    ],
    "wof:lang_x_spoken":[
        "tha"
    ],
    "wof:name":"Ban Chong",
    "wof:placetype":"locality"
},
  "geometry": {"coordinates":[99.88636,20.37383],"type":"Point"}
}