{
  "type": "Feature",
  "properties": {
    "gn:admin1_code":"4.0",
    "gn:asciiname":"Ban Huak",
    "gn:country_code":"TH",
    "gn:dem":258,
    "gn:feature_class":"P",
    "gn:feature_code":"PPL",
    "gn:name":"Ban Huak",
    "gn:population":0,
    "gn:timezone":"Asia/Bangkok",
    "iso:country":"TH",
    "name:tha_x_preferred":[
        "\u0e1a\u0e49\u0e32\u0e19\u0e2e\u0e27\u0e01"
    ],
    "wof:name":"Ban Huak",
    "wof:placetype":"locality"
},
  "geometry": {"coordinates":[100.75467,19.14164],"type":"Point"}
}