{
  "type": "Feature",
  "properties": {
    "gn:admin1_code":"4.0",
    "gn:asciiname":"Ban Na Hai",
    "gn:country_code":"TH",
    "gn:dem":240,
    "gn:feature_class":"P",
    "gn:feature_code":"PPL",
    "gn:name":"Ban Na Hai",
    "gn:population":0,
    "gn:timezone":"Asia/Bangkok",
    "iso:country":"TH",
    "name:tha_x_preferred":[
        "\u0e1a\u0e49\u0e32\u0e19\u0e19\u0e32\u0e44\u0e2e"
    ],
    "wof:name":"Ban Na Hai",
    "wof:placetype":"locality"
},
  "geometry": {"coordinates":[100.77158,19.05228],"type":"Point"}
}