{
  "type": "Feature",
  "properties": {
    "gn:admin1_code":"64.0",
    "gn:asciiname":"Ban Nong Yai",
    "gn:country_code":"TH",
    "gn:dem":60,
    "gn:feature_class":"P",
    "gn:feature_code":"PPL",
    "gn:name":"Ban Nong Yai",
    "gn:population":0,
    "gn:timezone":"Asia/Bangkok",
    "iso:country":"TH",
    "name:tha_x_preferred":[
        "\u0e1a\u0e49\u0e32\u0e19\u0e2b\u0e19\u0e2d\u0e07\u0e43\u0e2b\u0e0d\u0e48"
    ],
    "wof:name":"Ban Nong Yai",
    "wof:placetype":"locality"
},
  "geometry": {"coordinates":[99.43868999999999,8.37244],"type":"Point"}
}