{
  "type": "Feature",
  "properties": {
    "gn:admin1_code":"51.0",
    "gn:asciiname":"Ban Suan Phlu",
    "gn:country_code":"TH",
    "gn:dem":14,
    "gn:feature_class":"P",
    "gn:feature_code":"PPL",
    "gn:name":"Ban Suan Phlu",
    "gn:population":0,
    "gn:timezone":"Asia/Bangkok",
    "iso:country":"TH",
    "name:tha_x_preferred":[
        "\u0e1a\u0e49\u0e32\u0e19\u0e2a\u0e27\u0e19\u0e1e\u0e25\u0e39"
    ],
    "wof:name":"Ban Suan Phlu",
    "wof:placetype":"locality"
},
  "geometry": {"coordinates":[100.11839000000001,14.52786],"type":"Point"}
}