{
  "type": "Feature",
  "properties": {
    "gn:admin1_code":"58.0",
    "gn:asciiname":"Ban Khao Chan To",
    "gn:country_code":"TH",
    "gn:dem":68,
    "gn:feature_class":"P",
    "gn:feature_code":"PPL",
    "gn:name":"Ban Khao Chan To",
    "gn:population":0,
    "gn:timezone":"Asia/Bangkok",
    "iso:country":"TH",
    "name:tha_x_preferred":[
        "\u0e1a\u0e49\u0e32\u0e19\u0e40\u0e02\u0e32\u0e0a\u0e31\u0e19\u0e42\u0e15\u0e4a\u0e30"
    ],
    "wof:name":"Ban Khao Chan To",
    "wof:placetype":"locality"
},
  "geometry": {"coordinates":[99.07599999999999,10.38092],"type":"Point"}
}