{
  "type": "Feature",
  "properties": {
    "gn:admin1_code":"64.0",
    "gn:asciiname":"Ban Ai Bong",
    "gn:country_code":"TH",
    "gn:dem":6,
    "gn:feature_class":"P",
    "gn:feature_code":"PPL",
    "gn:name":"Ban Ai Bong",
    "gn:population":0,
    "gn:timezone":"Asia/Bangkok",
    "iso:country":"TH",
    "name:tha_x_preferred":[
        "\u0e1a\u0e49\u0e32\u0e19\u0e2d\u0e49\u0e32\u0e22\u0e1a\u0e49\u0e2d\u0e07"
    ],
    "wof:name":"Ban Ai Bong",
    "wof:placetype":"locality"
},
  "geometry": {"coordinates":[100.14969000000001,8.00747],"type":"Point"}
}