{
  "type": "Feature",
  "properties": {
    "gn:admin1_code":"64.0",
    "gn:asciiname":"Ban Sala Ton Sathon",
    "gn:country_code":"TH",
    "gn:dem":16,
    "gn:feature_class":"P",
    "gn:feature_code":"PPL",
    "gn:name":"Ban Sala Ton Sathon",
    "gn:population":0,
    "gn:timezone":"Asia/Bangkok",
    "iso:country":"TH",
    "name:tha_x_preferred":[
        "\u0e1a\u0e49\u0e32\u0e19\u0e28\u0e32\u0e25\u0e32\u0e15\u0e49\u0e19\u0e2a\u0e30\u0e17\u0e49\u0e2d\u0e19"
    ],
    "wof:lang_x_official":[
        "tha"
    ],
    "wof:lang_x_spoken":[
        "tha"
    ],
    "wof:name":"Ban Sala Ton Sathon",
    "wof:placetype":"locality"
},
  "geometry": {"coordinates":[99.86622,8.66569],"type":"Point"}
}