{
  "type": "Feature",
  "properties": {
    "gn:admin1_code":"63.0",
    "gn:asciiname":"Ban Khao Lang Tang",
    "gn:country_code":"TH",
    "gn:dem":22,
    "gn:feature_class":"P",
    "gn:feature_code":"PPL",
    "gn:name":"Ban Khao Lang Tang",
    "gn:population":0,
    "gn:timezone":"Asia/Bangkok",
    "iso:country":"TH",
    "name:tha_x_preferred":[
        "\u0e1a\u0e49\u0e32\u0e19\u0e40\u0e02\u0e32\u0e25\u0e31\u0e07\u0e15\u0e31\u0e07"
    ],
    "wof:name":"Ban Khao Lang Tang",
    "wof:placetype":"locality"
},
  "geometry": {"coordinates":[98.68474999999999,8.46756],"type":"Point"}
}