{
  "type": "Feature",
  "properties": {
    "gn:admin1_code":"3.0",
    "gn:asciiname":"Ban Ko Doi Tung",
    "gn:country_code":"TH",
    "gn:dem":1127,
    "gn:feature_class":"P",
    "gn:feature_code":"PPL",
    "gn:name":"Ban Ko Doi Tung",
    "gn:population":0,
    "gn:timezone":"Asia/Bangkok",
    "iso:country":"TH",
    "name:spa_x_preferred":[
        "Doi Tung"
    ],
    "wof:name":"Ban Ko Doi Tung",
    "wof:placetype":"locality"
},
  "geometry": {"coordinates":[99.82361,20.32028],"type":"Point"}
}