{
  "type": "Feature",
  "properties": {
    "gn:admin1_code":"11.0",
    "gn:asciiname":"Ban Rai",
    "gn:country_code":"TH",
    "gn:dem":72,
    "gn:feature_class":"P",
    "gn:feature_code":"PPL",
    "gn:name":"Ban Rai",
    "gn:population":0,
    "gn:timezone":"Asia/Bangkok",
    "iso:country":"TH",
    "name:tha_x_preferred":[
        "\u0e1a\u0e49\u0e32\u0e19\u0e44\u0e23\u0e48"
    ],
    "wof:name":"Ban Rai",
    "wof:placetype":"locality"
},
  "geometry": {"coordinates":[99.63160999999999,16.22656],"type":"Point"}
}