{
  "type": "Feature",
  "properties": {
    "gn:admin1_code":"2.0",
    "gn:asciiname":"Ban Yang Huai Tian Nua",
    "gn:country_code":"TH",
    "gn:dem":1035,
    "gn:feature_class":"P",
    "gn:feature_code":"PPL",
    "gn:name":"Ban Yang Huai Tian Nua",
    "gn:population":0,
    "gn:timezone":"Asia/Bangkok",
    "iso:country":"TH",
    "wof:name":"Ban Yang Huai Tian Nua",
    "wof:placetype":"locality"
},
  "geometry": {"coordinates":[98.52306,18.76194],"type":"Point"}
}