{
  "type": "Feature",
  "properties": {
    "gn:admin1_code":"29.0",
    "gn:asciiname":"Ban Thung Nak",
    "gn:country_code":"TH",
    "gn:dem":136,
    "gn:feature_class":"P",
    "gn:feature_code":"PPL",
    "gn:name":"Ban Thung Nak",
    "gn:population":0,
    "gn:timezone":"Asia/Bangkok",
    "iso:country":"TH",
    "name:tha_x_preferred":[
        "\u0e1a\u0e49\u0e32\u0e19\u0e17\u0e38\u0e48\u0e07\u0e19\u0e32\u0e04"
    ],
    "wof:name":"Ban Thung Nak",
    "wof:placetype":"locality"
},
  "geometry": {"coordinates":[103.42956,15.19228],"type":"Point"}
}