{
  "type": "Feature",
  "properties": {
    "gn:admin1_code":"14.0",
    "gn:asciiname":"Ban Sap Lin Thong",
    "gn:country_code":"TH",
    "gn:dem":144,
    "gn:feature_class":"P",
    "gn:feature_code":"PPL",
    "gn:name":"Ban Sap Lin Thong",
    "gn:population":0,
    "gn:timezone":"Asia/Bangkok",
    "iso:country":"TH",
    "name:tha_x_preferred":[
        "\u0e1a\u0e49\u0e32\u0e19\u0e0b\u0e31\u0e1a\u0e25\u0e34\u0e49\u0e19\u0e17\u0e2d\u0e07"
    ],
    "wof:name":"Ban Sap Lin Thong",
    "wof:placetype":"locality"
},
  "geometry": {"coordinates":[100.85464,15.90856],"type":"Point"}
}