{
  "type": "Feature",
  "properties": {
    "gn:admin1_code":"6.0",
    "gn:asciiname":"Ban Na Pang",
    "gn:country_code":"TH",
    "gn:dem":460,
    "gn:feature_class":"P",
    "gn:feature_code":"PPL",
    "gn:name":"Ban Na Pang",
    "gn:population":0,
    "gn:timezone":"Asia/Bangkok",
    "iso:country":"TH",
    "wof:name":"Ban Na Pang",
    "wof:placetype":"locality"
},
  "geometry": {"coordinates":[99.95667,18.43778],"type":"Point"}
}