{
  "type": "Feature",
  "properties": {
    "gn:country":"TH",
    "gn:fcode":"PPL",
    "gn:pop":0,
    "iso:country":"TH",
    "name:tha_x_preferred":[
        "\u0e1a\u0e49\u0e32\u0e19\u0e2b\u0e31\u0e19\u0e15\u0e23\u0e32"
    ],
    "name:unk_x_variant":[
        "Ban Han Tra"
    ],
    "qs:name":"Ban Han Tra Fang Nua",
    "qs:name_adm0":"Thailand",
    "qs:name_adm1":"Phra Nakhon Si Ayutthaya",
    "qs:photos":8,
    "qs:photos_1k":2,
    "qs:photos_9k":1,
    "qs:photos_9r":1,
    "qs:photos_all":8,
    "qs:photos_sr":1,
    "qs:placetype":"Town",
    "qs:pop_sr":"0",
    "wof:name":"Ban Han Tra Fang Nua",
    "wof:placetype":"locality",
    "wof:population":0
},
  "geometry": {"coordinates":[100.59999999999999,14.35],"type":"Point"}
}