{
  "type": "Feature",
  "properties": {
    "gn:admin1_code":"12.0",
    "gn:asciiname":"Ban Khlong Mek",
    "gn:country_code":"TH",
    "gn:dem":46,
    "gn:feature_class":"P",
    "gn:feature_code":"PPL",
    "gn:name":"Ban Khlong Mek",
    "gn:population":0,
    "gn:timezone":"Asia/Bangkok",
    "iso:country":"TH",
    "name:tha_x_preferred":[
        "\u0e1a\u0e49\u0e32\u0e19\u0e04\u0e25\u0e2d\u0e07\u0e40\u0e21\u0e06"
    ],
    "name:und_x_variant":[
        "Ban Khlong Mem"
    ],
    "wof:name":"Ban Khlong Mek",
    "wof:placetype":"locality"
},
  "geometry": {"coordinates":[100.12233000000001,16.95394],"type":"Point"}
}