{
  "type": "Feature",
  "properties": {
    "gn:admin1_code":"22.0",
    "gn:asciiname":"Ban Bueng Kae",
    "gn:country_code":"TH",
    "gn:dem":170,
    "gn:feature_class":"P",
    "gn:feature_code":"PPL",
    "gn:name":"Ban Bueng Kae",
    "gn:population":0,
    "gn:timezone":"Asia/Bangkok",
    "iso:country":"TH",
    "name:tha_x_preferred":[
        "\u0e1a\u0e49\u0e32\u0e19\u0e1a\u0e36\u0e07\u0e41\u0e01"
    ],
    "name:und_x_variant":[
        "Ban Bung Kae"
    ],
    "wof:name":"Ban Bueng Kae",
    "wof:placetype":"locality"
},
  "geometry": {"coordinates":[102.84325,16.59961],"type":"Point"}
}