{
  "type": "Feature",
  "properties": {
    "gn:admin1_code":"37.0",
    "gn:asciiname":"Ban Phu Krang",
    "gn:country_code":"TH",
    "gn:dem":19,
    "gn:feature_class":"P",
    "gn:feature_code":"PPL",
    "gn:name":"Ban Phu Krang",
    "gn:population":0,
    "gn:timezone":"Asia/Bangkok",
    "iso:country":"TH",
    "name:tha_x_preferred":[
        "\u0e1a\u0e49\u0e32\u0e19\u0e1e\u0e38\u0e01\u0e23\u0e48\u0e32\u0e07"
    ],
    "name:und_x_variant":[
        "Ban Pukrang",
        "Ban Phu Krang (1)",
        "Ban Phu Krang"
    ],
    "wof:lang_x_official":[
        "tha"
    ],
    "wof:lang_x_spoken":[
        "tha"
    ],
    "wof:name":"Ban Phu Krang",
    "wof:placetype":"locality"
},
  "geometry": {"coordinates":[100.79325,14.67747],"type":"Point"}
}