{
  "type": "Feature",
  "properties": {
    "gn:admin1_code":"36.0",
    "gn:asciiname":"Ban Muang Wan",
    "gn:cc2":"TH",
    "gn:country_code":"TH",
    "gn:dem":9,
    "gn:feature_class":"P",
    "gn:feature_code":"PPL",
    "gn:name":"Ban Muang Wan",
    "gn:population":0,
    "gn:timezone":"Asia/Bangkok",
    "iso:country":"TH",
    "name:und_x_variant":[
        "Ban Nua Wat",
        "Ban Muang Wan"
    ],
    "wof:name":"Ban Muang Wan",
    "wof:placetype":"locality"
},
  "geometry": {"coordinates":[100.51667,14.36667],"type":"Point"}
}