{
  "type": "Feature",
  "properties": {
    "gn:admin1_code":"29.0",
    "gn:asciiname":"Ban Khok Mai Daeng",
    "gn:country_code":"TH",
    "gn:dem":170,
    "gn:feature_class":"P",
    "gn:feature_code":"PPL",
    "gn:name":"Ban Khok Mai Daeng",
    "gn:population":0,
    "gn:timezone":"Asia/Bangkok",
    "iso:country":"TH",
    "name:tha_x_preferred":[
        "\u0e1a\u0e49\u0e32\u0e19\u0e42\u0e04\u0e01\u0e44\u0e21\u0e49\u0e41\u0e14\u0e07"
    ],
    "name:und_x_variant":[
        "Ban Khok Mai"
    ],
    "wof:name":"Ban Khok Mai Daeng",
    "wof:placetype":"locality"
},
  "geometry": {"coordinates":[103.95169,14.624],"type":"Point"}
}