{
  "type": "Feature",
  "properties": {
    "gn:admin1_code":"5.0",
    "gn:asciiname":"Ban San Ton Thong",
    "gn:country_code":"TH",
    "gn:dem":294,
    "gn:feature_class":"P",
    "gn:feature_code":"PPL",
    "gn:name":"Ban San Ton Thong",
    "gn:population":0,
    "gn:timezone":"Asia/Bangkok",
    "iso:country":"TH",
    "name:tha_x_preferred":[
        "\u0e1a\u0e49\u0e32\u0e19\u0e2a\u0e31\u0e19\u0e15\u0e49\u0e19\u0e18\u0e07"
    ],
    "wof:name":"Ban San Ton Thong",
    "wof:placetype":"locality"
},
  "geometry": {"coordinates":[98.99053000000001,18.56322],"type":"Point"}
}