{
  "type": "Feature",
  "properties": {
    "gn:admin1_code":"18.0",
    "gn:asciiname":"Ban Sai Khao",
    "gn:country_code":"TH",
    "gn:dem":264,
    "gn:feature_class":"P",
    "gn:feature_code":"PPL",
    "gn:name":"Ban Sai Khao",
    "gn:population":0,
    "gn:timezone":"Asia/Bangkok",
    "iso:country":"TH",
    "name:tha_x_preferred":[
        "\u0e1a\u0e49\u0e32\u0e19\u0e17\u0e23\u0e32\u0e22\u0e02\u0e32\u0e27"
    ],
    "name:und_x_variant":[
        "B\u0101n Sai K\u0101u",
        "Ban Sai Khao"
    ],
    "wof:lang_x_official":[
        "tha"
    ],
    "wof:lang_x_spoken":[
        "tha"
    ],
    "wof:name":"Ban Sai Khao",
    "wof:placetype":"locality"
},
  "geometry": {"coordinates":[101.69334000000001,17.24208],"type":"Point"}
}