{
  "type": "Feature",
  "properties": {
    "gn:admin1_code":"31.0",
    "gn:asciiname":"Ban La Se",
    "gn:country_code":"TH",
    "gn:dem":50,
    "gn:feature_class":"P",
    "gn:feature_code":"PPL",
    "gn:name":"Ban La Se",
    "gn:population":0,
    "gn:timezone":"Asia/Bangkok",
    "iso:country":"TH",
    "name:tha_x_preferred":[
        "\u0e1a\u0e49\u0e32\u0e19\u0e25\u0e32\u0e40\u0e0b\u0e4a\u0e30"
    ],
    "name:und_x_variant":[
        "Kampong Ma Se",
        "Kampong Lakse",
        "Ban La Se",
        "Kampong Lase"
    ],
    "wof:lang_x_official":[
        "tha"
    ],
    "wof:lang_x_spoken":[
        "tha"
    ],
    "wof:name":"Ban La Se",
    "wof:placetype":"locality"
},
  "geometry": {"coordinates":[101.52131,6.41983],"type":"Point"}
}