{
  "type": "Feature",
  "properties": {
    "gn:admin1_code":"28",
    "gn:asciiname":"Ban Na Saeng",
    "gn:country_code":"TH",
    "gn:dem":139,
    "gn:feature_class":"P",
    "gn:feature_code":"PPL",
    "gn:name":"Ban Na Saeng",
    "gn:population":0,
    "gn:timezone":"Asia/Bangkok",
    "iso:country":"TH",
    "name:tha_x_preferred":[
        "\u0e1a\u0e49\u0e32\u0e19\u0e19\u0e32\u0e41\u0e0b\u0e07"
    ],
    "wof:name":"Ban Na Saeng",
    "wof:placetype":"locality"
},
  "geometry": {"coordinates":[103.13869,15.35636],"type":"Point"}
}