{
  "type": "Feature",
  "properties": {
    "gn:admin1_code":"6.0",
    "gn:asciiname":"Ban Na Sak",
    "gn:country_code":"TH",
    "gn:dem":378,
    "gn:feature_class":"P",
    "gn:feature_code":"PPL",
    "gn:name":"Ban Na Sak",
    "gn:population":0,
    "gn:timezone":"Asia/Bangkok",
    "iso:country":"TH",
    "name:tha_x_preferred":[
        "\u0e1a\u0e49\u0e32\u0e19\u0e19\u0e32\u0e2a\u0e31\u0e01"
    ],
    "wof:name":"Ban Na Sak",
    "wof:placetype":"locality"
},
  "geometry": {"coordinates":[99.84708000000001,18.34894],"type":"Point"}
}