{
  "type": "Feature",
  "properties": {
    "gn:admin1_code":"54.0",
    "gn:asciiname":"Ban Khlong Khoen",
    "gn:country_code":"TH",
    "gn:dem":7,
    "gn:feature_class":"P",
    "gn:feature_code":"PPL",
    "gn:name":"Ban Khlong Khoen",
    "gn:population":0,
    "gn:timezone":"Asia/Bangkok",
    "iso:country":"TH",
    "name:tha_x_preferred":[
        "\u0e1a\u0e49\u0e32\u0e19\u0e04\u0e25\u0e2d\u0e07\u0e40\u0e02\u0e34\u0e19"
    ],
    "wof:lang_x_official":[
        "tha"
    ],
    "wof:lang_x_spoken":[
        "tha"
    ],
    "wof:name":"Ban Khlong Khoen",
    "wof:placetype":"locality"
},
  "geometry": {"coordinates":[99.99397,13.43989],"type":"Point"}
}