{
  "type": "Feature",
  "properties": {
    "gn:admin1_code":"66.0",
    "gn:asciiname":"Ban Nai Lom",
    "gn:country_code":"TH",
    "gn:dem":23,
    "gn:feature_class":"P",
    "gn:feature_code":"PPL",
    "gn:name":"Ban Nai Lom",
    "gn:population":0,
    "gn:timezone":"Asia/Bangkok",
    "iso:country":"TH",
    "name:tha_x_preferred":[
        "\u0e1a\u0e49\u0e32\u0e19\u0e43\u0e19\u0e25\u0e49\u0e2d\u0e21"
    ],
    "wof:name":"Ban Nai Lom",
    "wof:placetype":"locality"
},
  "geometry": {"coordinates":[100.17586,7.30017],"type":"Point"}
}