{
  "type": "Feature",
  "properties": {
    "gn:admin1_code":"53.0",
    "gn:asciiname":"Ban Kho Wang",
    "gn:country_code":"TH",
    "gn:dem":14,
    "gn:feature_class":"P",
    "gn:feature_code":"PPL",
    "gn:name":"Ban Kho Wang",
    "gn:population":0,
    "gn:timezone":"Asia/Bangkok",
    "iso:country":"TH",
    "name:tha_x_preferred":[
        "Ban Kho Wang"
    ],
    "name:tha_x_variant":[
        "\u0e1a\u0e49\u0e32\u0e19\u0e04\u0e2d\u0e27\u0e31\u0e07"
    ],
    "wof:name":"Ban Kho Wang",
    "wof:placetype":"locality"
},
  "geometry": {"coordinates":[99.9115,13.85431],"type":"Point"}
}