{
  "type": "Feature",
  "properties": {
    "gn:admin1_code":"39.0",
    "gn:asciiname":"Ban Tha Kacha",
    "gn:country_code":"TH",
    "gn:dem":5,
    "gn:feature_class":"P",
    "gn:feature_code":"PPL",
    "gn:name":"Ban Tha Kacha",
    "gn:population":0,
    "gn:timezone":"Asia/Bangkok",
    "iso:country":"TH",
    "name:tha_x_preferred":[
        "Ban Tha Kacha"
    ],
    "name:tha_x_variant":[
        "\u0e1a\u0e49\u0e32\u0e19\u0e17\u0e48\u0e32\u0e01\u0e30\u0e0a\u0e30"
    ],
    "name:und_x_variant":[
        "Ban Tha Kacha (1)"
    ],
    "wof:name":"Ban Tha Kacha",
    "wof:placetype":"locality"
},
  "geometry": {"coordinates":[100.58542,14.04067],"type":"Point"}
}