{
  "type": "Feature",
  "properties": {
    "gn:admin1_code":"64.0",
    "gn:asciiname":"Ban Suan Ai Lao",
    "gn:country_code":"TH",
    "gn:dem":43,
    "gn:feature_class":"P",
    "gn:feature_code":"PPL",
    "gn:name":"Ban Suan Ai Lao",
    "gn:population":0,
    "gn:timezone":"Asia/Bangkok",
    "iso:country":"TH",
    "name:tha_x_preferred":[
        "\u0e1a\u0e49\u0e32\u0e19\u0e2a\u0e27\u0e19\u0e2d\u0e32\u0e22\u0e40\u0e25\u0e32"
    ],
    "wof:name":"Ban Suan Ai Lao",
    "wof:placetype":"locality"
},
  "geometry": {"coordinates":[99.80242,8.12314],"type":"Point"}
}