{
  "type": "Feature",
  "properties": {
    "gn:admin1_code":"64.0",
    "gn:asciiname":"Ban Sam Yaek Suan Phak",
    "gn:country_code":"TH",
    "gn:dem":38,
    "gn:feature_class":"P",
    "gn:feature_code":"PPL",
    "gn:name":"Ban Sam Yaek Suan Phak",
    "gn:population":0,
    "gn:timezone":"Asia/Bangkok",
    "iso:country":"TH",
    "name:tha_x_preferred":[
        "\u0e1a\u0e49\u0e32\u0e19\u0e2a\u0e32\u0e21\u0e41\u0e22\u0e01\u0e2a\u0e27\u0e19\u0e1c\u0e31\u0e01"
    ],
    "wof:name":"Ban Sam Yaek Suan Phak",
    "wof:placetype":"locality"
},
  "geometry": {"coordinates":[99.81244,8.14483],"type":"Point"}
}