{
  "type": "Feature",
  "properties": {
    "gn:admin1_code":"26.0",
    "gn:asciiname":"Ban Khao Ki",
    "gn:country_code":"TH",
    "gn:dem":293,
    "gn:feature_class":"P",
    "gn:feature_code":"PPL",
    "gn:name":"Ban Khao Ki",
    "gn:population":0,
    "gn:timezone":"Asia/Bangkok",
    "iso:country":"TH",
    "name:tha_x_preferred":[
        "\u0e1a\u0e49\u0e32\u0e19\u0e40\u0e02\u0e32\u0e01\u0e35\u0e48"
    ],
    "wof:name":"Ban Khao Ki",
    "wof:placetype":"locality"
},
  "geometry": {"coordinates":[101.44089,15.47],"type":"Point"}
}