{
  "type": "Feature",
  "properties": {
    "gn:admin1_code":"68.0",
    "gn:asciiname":"Ban Khao Kloi",
    "gn:country_code":"TH",
    "gn:dem":32,
    "gn:feature_class":"P",
    "gn:feature_code":"PPL",
    "gn:name":"Ban Khao Kloi",
    "gn:population":0,
    "gn:timezone":"Asia/Bangkok",
    "iso:country":"TH",
    "wof:name":"Ban Khao Kloi",
    "wof:placetype":"locality"
},
  "geometry": {"coordinates":[100.58333,7.03333],"type":"Point"}
}