{
  "type": "Feature",
  "properties": {
    "gn:admin1_code":"2.0",
    "gn:asciiname":"Ban Pha Daeng",
    "gn:country_code":"TH",
    "gn:dem":777,
    "gn:feature_class":"P",
    "gn:feature_code":"PPL",
    "gn:name":"Ban Pha Daeng",
    "gn:population":0,
    "gn:timezone":"Asia/Bangkok",
    "iso:country":"TH",
    "name:tha_x_preferred":[
        "\u0e1a\u0e49\u0e32\u0e19\u0e1c\u0e32\u0e41\u0e14\u0e07"
    ],
    "wof:name":"Ban Pha Daeng",
    "wof:placetype":"locality"
},
  "geometry": {"coordinates":[98.23528,17.96761],"type":"Point"}
}