{
  "type": "Feature",
  "properties": {
    "gn:admin1_code":"26.0",
    "gn:asciiname":"Ban Nong Bua Yai",
    "gn:country_code":"TH",
    "gn:dem":191,
    "gn:feature_class":"P",
    "gn:feature_code":"PPL",
    "gn:name":"Ban Nong Bua Yai",
    "gn:population":0,
    "gn:timezone":"Asia/Bangkok",
    "iso:country":"TH",
    "name:tha_x_preferred":[
        "\u0e1a\u0e49\u0e32\u0e19\u0e2b\u0e19\u0e2d\u0e07\u0e1a\u0e31\u0e27\u0e43\u0e2b\u0e0d\u0e48"
    ],
    "name:und_x_variant":[
        "B\u0101n Naung Bua Y\u0101i",
        "Ban Nong Bua Yai"
    ],
    "wof:name":"Ban Nong Bua Yai",
    "wof:placetype":"locality"
},
  "geometry": {"coordinates":[101.85505999999999,15.58336],"type":"Point"}
}