{
  "type": "Feature",
  "properties": {
    "gn:admin1_code":"3.0",
    "gn:asciiname":"Ban Mae Khao Tom",
    "gn:country_code":"TH",
    "gn:dem":384,
    "gn:feature_class":"P",
    "gn:feature_code":"PPL",
    "gn:name":"Ban Mae Khao Tom",
    "gn:population":0,
    "gn:timezone":"Asia/Bangkok",
    "iso:country":"TH",
    "name:tha_x_preferred":[
        "\u0e1a\u0e49\u0e32\u0e19\u0e41\u0e21\u0e48\u0e02\u0e49\u0e32\u0e27\u0e15\u0e49\u0e21"
    ],
    "name:und_x_variant":[
        "B\u0101n Mea K\u0101o Tom Noi",
        "Ban Mae Khao Tom Noi",
        "Ban Mae Khao Tom Luang",
        "Ban Mae Khao Tom"
    ],
    "wof:lang_x_official":[
        "tha"
    ],
    "wof:lang_x_spoken":[
        "tha"
    ],
    "wof:name":"Ban Mae Khao Tom",
    "wof:placetype":"locality"
},
  "geometry": {"coordinates":[99.91539,20.01136],"type":"Point"}
}