{
  "type": "Feature",
  "properties": {
    "gn:admin1_code":"57.0",
    "gn:asciiname":"Ban Bueng Phaknam",
    "gn:country_code":"TH",
    "gn:dem":26,
    "gn:feature_class":"P",
    "gn:feature_code":"PPL",
    "gn:name":"Ban Bueng Phaknam",
    "gn:population":0,
    "gn:timezone":"Asia/Bangkok",
    "iso:country":"TH",
    "name:tha_x_preferred":[
        "\u0e1a\u0e49\u0e32\u0e19\u0e1a\u0e36\u0e07\u0e1c\u0e31\u0e01\u0e2b\u0e19\u0e32\u0e21\u0e1a\u0e36\u0e07\u0e1c\u0e31\u0e01\u0e2b\u0e19\u0e32\u0e21"
    ],
    "name:und_x_variant":[
        "Ban Bung Phak Nam"
    ],
    "wof:name":"Ban Bueng Phaknam",
    "wof:placetype":"locality"
},
  "geometry": {"coordinates":[99.44964,11.23286],"type":"Point"}
}