{
  "type": "Feature",
  "properties": {
    "gn:admin1_code":"75.0",
    "gn:asciiname":"Ban Pho Tok",
    "gn:country_code":"TH",
    "gn:dem":124,
    "gn:feature_class":"P",
    "gn:feature_code":"PPL",
    "gn:name":"Ban Pho Tok",
    "gn:population":0,
    "gn:timezone":"Asia/Bangkok",
    "iso:country":"TH",
    "name:tha_x_preferred":[
        "\u0e1a\u0e49\u0e32\u0e19\u0e42\u0e1e\u0e18\u0e34\u0e4c\u0e15\u0e01"
    ],
    "name:und_x_variant":[
        "Ban Pho",
        "Ban Pho Yai",
        "Ban Pho Tok"
    ],
    "wof:name":"Ban Pho Tok",
    "wof:placetype":"locality"
},
  "geometry": {"coordinates":[104.93486,15.11547],"type":"Point"}
}