{
  "type": "Feature",
  "properties": {
    "gn:admin1_code":"43.0",
    "gn:asciiname":"Ban Khlong Sip Si",
    "gn:country_code":"TH",
    "gn:dem":8,
    "gn:feature_class":"P",
    "gn:feature_code":"PPL",
    "gn:name":"Ban Khlong Sip Si",
    "gn:population":0,
    "gn:timezone":"Asia/Bangkok",
    "iso:country":"TH",
    "name:tha_x_preferred":[
        "\u0e1a\u0e49\u0e32\u0e19\u0e04\u0e25\u0e2d\u0e07\u0e2a\u0e34\u0e1a\u0e2a\u0e35\u0e48"
    ],
    "wof:name":"Ban Khlong Sip Si",
    "wof:placetype":"locality"
},
  "geometry": {"coordinates":[100.9145,13.98136],"type":"Point"}
}