{
  "type": "Feature",
  "properties": {
    "gn:admin1_code":"31.0",
    "gn:asciiname":"Ban Ai Rae Kae",
    "gn:country_code":"TH",
    "gn:dem":78,
    "gn:feature_class":"P",
    "gn:feature_code":"PPL",
    "gn:name":"Ban Ai Rae Kae",
    "gn:population":0,
    "gn:timezone":"Asia/Bangkok",
    "iso:country":"TH",
    "name:tha_x_preferred":[
        "\u0e1a\u0e49\u0e32\u0e19\u0e44\u0e2d\u0e23\u0e4c\u0e41\u0e23\u0e41\u0e01"
    ],
    "name:und_x_variant":[
        "Ban I Rae Kae",
        "Ban Ai Rae Kae"
    ],
    "wof:lang_x_official":[
        "tha"
    ],
    "wof:lang_x_spoken":[
        "tha"
    ],
    "wof:name":"Ban Ai Rae Kae",
    "wof:placetype":"locality"
},
  "geometry": {"coordinates":[101.44232,6.26551],"type":"Point"}
}