{
  "type": "Feature",
  "properties": {
    "gn:admin1_code":"65.0",
    "gn:asciiname":"Ban Chuang",
    "gn:cc2":"TH",
    "gn:country_code":"TH",
    "gn:dem":34,
    "gn:feature_class":"P",
    "gn:feature_code":"PPL",
    "gn:name":"Ban Chuang",
    "gn:population":0,
    "gn:timezone":"Asia/Bangkok",
    "iso:country":"TH",
    "name:und_x_variant":[
        "Ban Chang",
        "Ban Chuang"
    ],
    "wof:name":"Ban Chuang",
    "wof:placetype":"locality"
},
  "geometry": {"coordinates":[99.71666999999999,7.56667],"type":"Point"}
}