{
  "type": "Feature",
  "properties": {
    "gn:admin1_code":"53.0",
    "gn:asciiname":"Ban Tai Pak Khlong Nokkrathung",
    "gn:country_code":"TH",
    "gn:dem":2,
    "gn:feature_class":"P",
    "gn:feature_code":"PPL",
    "gn:name":"Ban Tai Pak Khlong Nokkrathung",
    "gn:population":0,
    "gn:timezone":"Asia/Bangkok",
    "iso:country":"TH",
    "name:tha_x_preferred":[
        "\u0e1a\u0e49\u0e32\u0e19\u0e43\u0e15\u0e49\u0e1b\u0e32\u0e01\u0e04\u0e25\u0e2d\u0e07\u0e19\u0e01\u0e01\u0e23\u0e30\u0e17\u0e38\u0e07"
    ],
    "wof:lang_x_official":[
        "tha"
    ],
    "wof:lang_x_spoken":[
        "tha"
    ],
    "wof:name":"Ban Tai Pak Khlong Nokkrathung",
    "wof:placetype":"locality"
},
  "geometry": {"coordinates":[100.22031,13.98042],"type":"Point"}
}