{
  "type": "Feature",
  "properties": {
    "gn:admin1_code":"40.0",
    "gn:admin2_code":"1001.0",
    "gn:asciiname":"Banglumpoo",
    "gn:country_code":"TH",
    "gn:dem":10,
    "gn:feature_class":"P",
    "gn:feature_code":"PPL",
    "gn:name":"Banglumpoo",
    "gn:population":0,
    "gn:timezone":"Asia/Bangkok",
    "iso:country":"TH",
    "name:tha_x_preferred":[
        "\u0e1a\u0e32\u0e07\u0e25\u0e33\u0e20\u0e39"
    ],
    "wof:name":"Banglumpoo",
    "wof:placetype":"locality"
},
  "geometry": {"coordinates":[100.49984000000001,13.76155],"type":"Point"}
}