{
  "type": "Feature",
  "properties": {
    "gn:admin1_code":"31.0",
    "gn:asciiname":"Ban Kra Yi",
    "gn:country_code":"TH",
    "gn:dem":13,
    "gn:feature_class":"P",
    "gn:feature_code":"PPL",
    "gn:name":"Ban Kra Yi",
    "gn:population":0,
    "gn:timezone":"Asia/Bangkok",
    "iso:country":"TH",
    "name:tha_x_preferred":[
        "\u0e1a\u0e49\u0e32\u0e19\u0e01\u0e23\u0e32\u0e22\u0e35"
    ],
    "wof:name":"Ban Kra Yi",
    "wof:placetype":"locality"
},
  "geometry": {"coordinates":[101.77858000000001,6.38236],"type":"Point"}
}