{
  "type": "Feature",
  "properties": {
    "gn:admin1_code":"11.0",
    "gn:asciiname":"Ban Rai Don Taeng",
    "gn:country_code":"TH",
    "gn:dem":62,
    "gn:feature_class":"P",
    "gn:feature_code":"PPL",
    "gn:name":"Ban Rai Don Taeng",
    "gn:population":0,
    "gn:timezone":"Asia/Bangkok",
    "iso:country":"TH",
    "name:tha_x_preferred":[
        "\u0e1a\u0e49\u0e32\u0e19\u0e44\u0e23\u0e48\u0e14\u0e2d\u0e19\u0e41\u0e15\u0e07"
    ],
    "wof:name":"Ban Rai Don Taeng",
    "wof:placetype":"locality"
},
  "geometry": {"coordinates":[99.71047,16.03919],"type":"Point"}
}