{
  "type": "Feature",
  "properties": {
    "gn:admin1_code":"2.0",
    "gn:asciiname":"Ban San Doi Liam",
    "gn:country_code":"TH",
    "gn:dem":1088,
    "gn:feature_class":"P",
    "gn:feature_code":"PPL",
    "gn:name":"Ban San Doi Liam",
    "gn:population":0,
    "gn:timezone":"Asia/Bangkok",
    "iso:country":"TH",
    "name:tha_x_preferred":[
        "\u0e1a\u0e49\u0e32\u0e19\u0e2a\u0e31\u0e19\u0e14\u0e2d\u0e22\u0e40\u0e2b\u0e25\u0e35\u0e49\u0e22\u0e21"
    ],
    "wof:name":"Ban San Doi Liam",
    "wof:placetype":"locality"
},
  "geometry": {"coordinates":[98.36314,18.09053],"type":"Point"}
}