{
  "type": "Feature",
  "properties": {
    "gn:admin1_code":"64.0",
    "gn:asciiname":"Ban Don Faek",
    "gn:cc2":"TH",
    "gn:country_code":"TH",
    "gn:dem":3,
    "gn:feature_class":"P",
    "gn:feature_code":"PPL",
    "gn:name":"Ban Don Faek",
    "gn:population":0,
    "gn:timezone":"Asia/Bangkok",
    "iso:country":"TH",
    "name:und_x_variant":[
        "Ban Faet",
        "Ban Don Faek"
    ],
    "wof:name":"Ban Don Faek",
    "wof:placetype":"locality"
},
  "geometry": {"coordinates":[100.25,8.06667],"type":"Point"}
}