{
  "type": "Feature",
  "properties": {
    "gn:admin1_code":"5.0",
    "gn:asciiname":"Ban Sai Kham",
    "gn:country_code":"TH",
    "gn:dem":392,
    "gn:feature_class":"P",
    "gn:feature_code":"PPL",
    "gn:name":"Ban Sai Kham",
    "gn:population":0,
    "gn:timezone":"Asia/Bangkok",
    "iso:country":"TH",
    "wof:name":"Ban Sai Kham",
    "wof:placetype":"locality"
},
  "geometry": {"coordinates":[98.89667,18.08444],"type":"Point"}
}