{
  "type": "Feature",
  "properties": {
    "gn:admin1_code":"58.0",
    "gn:asciiname":"Ban Khuan Sao Thong",
    "gn:country_code":"TH",
    "gn:dem":19,
    "gn:feature_class":"P",
    "gn:feature_code":"PPL",
    "gn:name":"Ban Khuan Sao Thong",
    "gn:population":0,
    "gn:timezone":"Asia/Bangkok",
    "iso:country":"TH",
    "name:tha_x_preferred":[
        "\u0e1a\u0e49\u0e32\u0e19\u0e04\u0e27\u0e19\u0e40\u0e2a\u0e32\u0e18\u0e07"
    ],
    "wof:name":"Ban Khuan Sao Thong",
    "wof:placetype":"locality"
},
  "geometry": {"coordinates":[99.11364,10.07314],"type":"Point"}
}