{
  "type": "Feature",
  "properties": {
    "gn:admin1_code":"3.0",
    "gn:asciiname":"Ban Huai Khian",
    "gn:country_code":"TH",
    "gn:dem":358,
    "gn:feature_class":"P",
    "gn:feature_code":"PPL",
    "gn:name":"Ban Huai Khian",
    "gn:population":0,
    "gn:timezone":"Asia/Bangkok",
    "iso:country":"TH",
    "wof:name":"Ban Huai Khian",
    "wof:placetype":"locality"
},
  "geometry": {"coordinates":[100.22705000000001,19.90519],"type":"Point"}
}