{
  "type": "Feature",
  "properties": {
    "gn:admin1_code":"46.0",
    "gn:asciiname":"Ban Map Mahuat",
    "gn:country_code":"TH",
    "gn:dem":88,
    "gn:feature_class":"P",
    "gn:feature_code":"PPL",
    "gn:name":"Ban Map Mahuat",
    "gn:population":0,
    "gn:timezone":"Asia/Bangkok",
    "iso:country":"TH",
    "name:tha_x_preferred":[
        "\u0e1a\u0e49\u0e32\u0e19\u0e21\u0e32\u0e1a\u0e21\u0e30\u0e2b\u0e27\u0e14"
    ],
    "wof:name":"Ban Map Mahuat",
    "wof:placetype":"locality"
},
  "geometry": {"coordinates":[101.22624999999999,13.17539],"type":"Point"}
}