{
  "type": "Feature",
  "properties": {
    "gn:country":"TH",
    "gn:fcode":"PPLA2",
    "gn:pop":0,
    "iso:country":"TH",
    "name:tha_x_preferred":[
        "\u0e40\u0e17\u0e1e\u0e32\u0e23\u0e31\u0e01\u0e29\u0e4c"
    ],
    "name:unk_x_variant":[
        "Ban Takhro"
    ],
    "qs:name":"Thepharak",
    "qs:photos_9r":0,
    "qs:photos_sr":0,
    "qs:pop_sr":"0",
    "wd:wordcount":258,
    "wof:name":"Thepharak",
    "wof:placetype":"locality",
    "wof:population":0
},
  "geometry": {"coordinates":[101.55045,15.30868],"type":"Point"}
}