{
  "type": "Feature",
  "properties": {
    "gn:country":"TH",
    "gn:fcode":"PPLA2",
    "gn:pop":0,
    "iso:country":"TH",
    "name:bpy_x_preferred":[
        "\u0986\u09ae\u09cd\u09ab\u09cb\u09af\u09bc\u09c7 \u09a5\u09c7\u09ab\u09af\u09bc\u09be\u09b0\u09be\u0995"
    ],
    "name:ceb_x_preferred":[
        "Amphoe Thepharak"
    ],
    "name:deu_x_preferred":[
        "Amphoe Thepharak"
    ],
    "name:eng_x_preferred":[
        "Thepharak"
    ],
    "name:fra_x_preferred":[
        "Thepharak"
    ],
    "name:nan_x_preferred":[
        "Thepharak K\u016bn"
    ],
    "name:ron_x_preferred":[
        "Districtul Thepharak"
    ],
    "name:tha_x_preferred":[
        "\u0e40\u0e17\u0e1e\u0e32\u0e23\u0e31\u0e01\u0e29\u0e4c"
    ],
    "name:tha_x_variant":[
        "\u0e2d\u0e33\u0e40\u0e20\u0e2d\u0e40\u0e17\u0e1e\u0e32\u0e23\u0e31\u0e01\u0e29\u0e4c"
    ],
    "name:unk_x_variant":[
        "Ban Takhro"
    ],
    "name:urd_x_preferred":[
        "\u062a\u06be\u06cc\u067e\u06c1\u0627\u0631\u0627\u06a9 \u0636\u0644\u0639"
    ],
    "name:vie_x_preferred":[
        "Thepharak"
    ],
    "qs:name":"Thepharak",
    "qs:photos_9r":0,
    "qs:photos_sr":0,
    "qs:pop_sr":"0",
    "wd:wordcount":258,
    "wof:name":"Thepharak",
    "wof:placetype":"locality",
    "wof:population":0
},
  "geometry": {"coordinates":[101.55045,15.30868],"type":"Point"}
}