{
  "type": "Feature",
  "properties": {
    "gn:admin1_code":"30.0",
    "gn:asciiname":"Ban Thanon Wihan",
    "gn:country_code":"TH",
    "gn:dem":174,
    "gn:feature_class":"P",
    "gn:feature_code":"PPL",
    "gn:name":"Ban Thanon Wihan",
    "gn:population":0,
    "gn:timezone":"Asia/Bangkok",
    "iso:country":"TH",
    "name:tha_x_preferred":[
        "\u0e1a\u0e49\u0e32\u0e19\u0e16\u0e19\u0e19\u0e27\u0e34\u0e2b\u0e32\u0e23"
    ],
    "wof:name":"Ban Thanon Wihan",
    "wof:placetype":"locality"
},
  "geometry": {"coordinates":[104.67511,14.54656],"type":"Point"}
}