{
  "type": "Feature",
  "properties": {
    "gn:admin1_code":"68.0",
    "gn:asciiname":"Ban Ko Yai",
    "gn:country_code":"TH",
    "gn:dem":20,
    "gn:feature_class":"P",
    "gn:feature_code":"PPL",
    "gn:name":"Ban Ko Yai",
    "gn:population":0,
    "gn:timezone":"Asia/Bangkok",
    "iso:country":"TH",
    "name:tha_x_preferred":[
        "\u0e1a\u0e49\u0e32\u0e19\u0e40\u0e01\u0e32\u0e30\u0e43\u0e2b\u0e0d\u0e48"
    ],
    "name:und_x_variant":[
        "Kau Yai",
        "Ban Kok Yai",
        "Ban Ko Yai"
    ],
    "wof:name":"Ban Ko Yai",
    "wof:placetype":"locality"
},
  "geometry": {"coordinates":[100.30439,7.56931],"type":"Point"}
}