{
  "type": "Feature",
  "properties": {
    "gn:admin1_code":"60.0",
    "gn:asciiname":"Ban Tha Lum Pho",
    "gn:country_code":"TH",
    "gn:dem":17,
    "gn:feature_class":"P",
    "gn:feature_code":"PPL",
    "gn:name":"Ban Tha Lum Pho",
    "gn:population":0,
    "gn:timezone":"Asia/Bangkok",
    "iso:country":"TH",
    "name:tha_x_preferred":[
        "\u0e1a\u0e49\u0e32\u0e19\u0e17\u0e48\u0e32\u0e2b\u0e25\u0e38\u0e21\u0e1e\u0e2d"
    ],
    "wof:name":"Ban Tha Lum Pho",
    "wof:placetype":"locality"
},
  "geometry": {"coordinates":[99.09833,9.30794],"type":"Point"}
}