{
  "type": "Feature",
  "properties": {
    "gn:admin1_code":"66.0",
    "gn:asciiname":"Ban Tha Wang",
    "gn:country_code":"TH",
    "gn:dem":29,
    "gn:feature_class":"P",
    "gn:feature_code":"PPL",
    "gn:name":"Ban Tha Wang",
    "gn:population":0,
    "gn:timezone":"Asia/Bangkok",
    "iso:country":"TH",
    "name:tha_x_preferred":[
        "\u0e1a\u0e49\u0e32\u0e19\u0e17\u0e48\u0e32\u0e27\u0e31\u0e07"
    ],
    "wof:name":"Ban Tha Wang",
    "wof:placetype":"locality"
},
  "geometry": {"coordinates":[100.09817,7.37633],"type":"Point"}
}