{
  "type": "Feature",
  "properties": {
    "gn:admin1_code":"57.0",
    "gn:asciiname":"Ban Don Sai Charoen",
    "gn:country_code":"TH",
    "gn:dem":34,
    "gn:feature_class":"P",
    "gn:feature_code":"PPL",
    "gn:name":"Ban Don Sai Charoen",
    "gn:population":0,
    "gn:timezone":"Asia/Bangkok",
    "iso:country":"TH",
    "name:tha_x_preferred":[
        "\u0e1a\u0e49\u0e32\u0e19\u0e14\u0e2d\u0e19\u0e44\u0e17\u0e23\u0e40\u0e08\u0e23\u0e34\u0e0d"
    ],
    "wof:name":"Ban Don Sai Charoen",
    "wof:placetype":"locality"
},
  "geometry": {"coordinates":[99.56467000000001,11.40392],"type":"Point"}
}