{
  "type": "Feature",
  "properties": {
    "gn:admin1_code":"79.0",
    "gn:asciiname":"Ban Kut Du",
    "gn:country_code":"TH",
    "gn:dem":296,
    "gn:feature_class":"P",
    "gn:feature_code":"PPL",
    "gn:name":"Ban Kut Du",
    "gn:population":0,
    "gn:timezone":"Asia/Bangkok",
    "iso:country":"TH",
    "name:tha_x_preferred":[
        "\u0e1a\u0e49\u0e32\u0e19\u0e01\u0e38\u0e14\u0e14\u0e39\u0e48"
    ],
    "wof:name":"Ban Kut Du",
    "wof:placetype":"locality"
},
  "geometry": {"coordinates":[101.99536000000001,17.42958],"type":"Point"}
}