{
  "type": "Feature",
  "properties": {
    "gn:admin1_code":"2.0",
    "gn:asciiname":"Ban Doi Yao",
    "gn:country_code":"TH",
    "gn:dem":332,
    "gn:feature_class":"P",
    "gn:feature_code":"PPL",
    "gn:name":"Ban Doi Yao",
    "gn:population":0,
    "gn:timezone":"Asia/Bangkok",
    "iso:country":"TH",
    "name:tha_x_preferred":[
        "\u0e1a\u0e49\u0e32\u0e19\u0e14\u0e2d\u0e22\u0e22\u0e32\u0e27"
    ],
    "name:und_x_variant":[
        "Doi Yao",
        "B\u0101n Doi Y\u0101u",
        "Ban Doi Yao"
    ],
    "wof:lang_x_official":[
        "tha"
    ],
    "wof:lang_x_spoken":[
        "tha"
    ],
    "wof:name":"Ban Doi Yao",
    "wof:placetype":"locality"
},
  "geometry": {"coordinates":[99.16981,18.72311],"type":"Point"}
}