{
  "type": "Feature",
  "properties": {
    "gn:admin1_code":"74",
    "gn:asciiname":"Ban Noen Mai Hom",
    "gn:country_code":"TH",
    "gn:dem":20,
    "gn:feature_class":"P",
    "gn:feature_code":"PPL",
    "gn:name":"Ban Noen Mai Hom",
    "gn:population":0,
    "gn:timezone":"Asia/Bangkok",
    "iso:country":"TH",
    "name:tha_x_preferred":[
        "\u0e1a\u0e49\u0e32\u0e19\u0e40\u0e19\u0e34\u0e19\u0e44\u0e21\u0e49\u0e2b\u0e2d\u0e21"
    ],
    "wof:name":"Ban Noen Mai Hom",
    "wof:placetype":"locality"
},
  "geometry": {"coordinates":[101.36444,14.1825],"type":"Point"}
}