{
  "type": "Feature",
  "properties": {
    "gn:admin1_code":"2.0",
    "gn:asciiname":"Ban Huai Muang",
    "gn:country_code":"TH",
    "gn:dem":549,
    "gn:feature_class":"P",
    "gn:feature_code":"PPL",
    "gn:name":"Ban Huai Muang",
    "gn:population":0,
    "gn:timezone":"Asia/Bangkok",
    "iso:country":"TH",
    "name:tha_x_preferred":[
        "\u0e1a\u0e49\u0e32\u0e19\u0e2b\u0e49\u0e27\u0e22\u0e21\u0e48\u0e27\u0e07"
    ],
    "wof:name":"Ban Huai Muang",
    "wof:placetype":"locality"
},
  "geometry": {"coordinates":[99.15882000000001,19.6523],"type":"Point"}
}