{
  "type": "Feature",
  "properties": {
    "gn:admin1_code":"31.0",
    "gn:asciiname":"Ban Bae Ta",
    "gn:country_code":"TH",
    "gn:dem":101,
    "gn:feature_class":"P",
    "gn:feature_code":"PPL",
    "gn:name":"Ban Bae Ta",
    "gn:population":0,
    "gn:timezone":"Asia/Bangkok",
    "iso:country":"TH",
    "name:tha_x_preferred":[
        "\u0e1a\u0e49\u0e32\u0e19\u0e41\u0e1a\u0e15\u0e32"
    ],
    "wof:name":"Ban Bae Ta",
    "wof:placetype":"locality"
},
  "geometry": {"coordinates":[101.7775,6.00375],"type":"Point"}
}