{
  "type": "Feature",
  "properties": {
    "gn:admin1_code":"6.0",
    "gn:asciiname":"Ban Mae Wa-Lum",
    "gn:country_code":"TH",
    "gn:dem":174,
    "gn:feature_class":"P",
    "gn:feature_code":"PPL",
    "gn:name":"Ban Mae Wa-Lum",
    "gn:population":0,
    "gn:timezone":"Asia/Bangkok",
    "iso:country":"TH",
    "name:tha_x_preferred":[
        "\u0e1a\u0e49\u0e32\u0e19\u0e41\u0e21\u0e48\u0e27\u0e30-\u0e25\u0e38\u0e48\u0e21"
    ],
    "wof:name":"Ban Mae Wa-Lum",
    "wof:placetype":"locality"
},
  "geometry": {"coordinates":[99.18547,17.50717],"type":"Point"}
}