{
  "type": "Feature",
  "properties": {
    "gn:admin1_code":"30.0",
    "gn:asciiname":"Ban Sadao Tawan Tok",
    "gn:country_code":"TH",
    "gn:dem":152,
    "gn:feature_class":"P",
    "gn:feature_code":"PPL",
    "gn:name":"Ban Sadao Tawan Tok",
    "gn:population":0,
    "gn:timezone":"Asia/Bangkok",
    "iso:country":"TH",
    "name:tha_x_preferred":[
        "\u0e1a\u0e49\u0e32\u0e19\u0e2a\u0e30\u0e40\u0e14\u0e32\u0e15\u0e30\u0e27\u0e31\u0e19\u0e15\u0e01"
    ],
    "name:und_x_variant":[
        "Ban Sadao Yai"
    ],
    "wof:name":"Ban Sadao Tawan Tok",
    "wof:placetype":"locality"
},
  "geometry": {"coordinates":[104.25405000000001,14.70915],"type":"Point"}
}