{
  "type": "Feature",
  "properties": {
    "gn:admin1_code":"4.0",
    "gn:asciiname":"Ban Samun",
    "gn:country_code":"TH",
    "gn:dem":202,
    "gn:feature_class":"P",
    "gn:feature_code":"PPL",
    "gn:name":"Ban Samun",
    "gn:population":0,
    "gn:timezone":"Asia/Bangkok",
    "iso:country":"TH",
    "name:tha_x_preferred":[
        "\u0e1a\u0e49\u0e32\u0e19\u0e2a\u0e21\u0e38\u0e19"
    ],
    "name:und_x_variant":[
        "B\u0101n Daun M\u016bn",
        "Ban Don Mun",
        "Ban Samun"
    ],
    "wof:name":"Ban Samun",
    "wof:placetype":"locality"
},
  "geometry": {"coordinates":[100.75872,18.75289],"type":"Point"}
}