{
  "type": "Feature",
  "properties": {
    "gn:admin1_code":"57.0",
    "gn:asciiname":"Ban Nong Ta Kon",
    "gn:country_code":"TH",
    "gn:dem":6,
    "gn:feature_class":"P",
    "gn:feature_code":"PPL",
    "gn:name":"Ban Nong Ta Kon",
    "gn:population":0,
    "gn:timezone":"Asia/Bangkok",
    "iso:country":"TH",
    "name:tha_x_preferred":[
        "\u0e1a\u0e49\u0e32\u0e19\u0e2b\u0e19\u0e2d\u0e07\u0e15\u0e32\u0e01\u0e49\u0e2d\u0e19"
    ],
    "wof:name":"Ban Nong Ta Kon",
    "wof:placetype":"locality"
},
  "geometry": {"coordinates":[99.89769,12.30339],"type":"Point"}
}