{
  "type": "Feature",
  "properties": {
    "gn:admin1_code":"76.0",
    "gn:asciiname":"Ban Na Chumphon",
    "gn:country_code":"TH",
    "gn:dem":278,
    "gn:feature_class":"P",
    "gn:feature_code":"PPL",
    "gn:name":"Ban Na Chumphon",
    "gn:population":0,
    "gn:timezone":"Asia/Bangkok",
    "iso:country":"TH",
    "name:tha_x_preferred":[
        "\u0e1a\u0e49\u0e32\u0e19\u0e19\u0e32\u0e0a\u0e38\u0e21\u0e1e\u0e23"
    ],
    "wof:name":"Ban Na Chumphon",
    "wof:placetype":"locality"
},
  "geometry": {"coordinates":[103.40103000000001,17.08406],"type":"Point"}
}