{
  "type": "Feature",
  "properties": {
    "gn:admin1_code":"30.0",
    "gn:asciiname":"Ban Yang Ueat",
    "gn:country_code":"TH",
    "gn:dem":155,
    "gn:feature_class":"P",
    "gn:feature_code":"PPL",
    "gn:name":"Ban Yang Ueat",
    "gn:population":0,
    "gn:timezone":"Asia/Bangkok",
    "iso:country":"TH",
    "name:tha_x_preferred":[
        "\u0e1a\u0e49\u0e32\u0e19\u0e22\u0e32\u0e07\u0e40\u0e2d\u0e37\u0e2d\u0e14"
    ],
    "wof:name":"Ban Yang Ueat",
    "wof:placetype":"locality"
},
  "geometry": {"coordinates":[104.14086,15.15725],"type":"Point"}
}