{
  "type": "Feature",
  "properties": {
    "gn:admin1_code":"3.0",
    "gn:asciiname":"Ban Dong Mafueang",
    "gn:country_code":"TH",
    "gn:dem":465,
    "gn:feature_class":"P",
    "gn:feature_code":"PPL",
    "gn:name":"Ban Dong Mafueang",
    "gn:population":0,
    "gn:timezone":"Asia/Bangkok",
    "iso:country":"TH",
    "name:tha_x_preferred":[
        "\u0e1a\u0e49\u0e32\u0e19\u0e14\u0e07\u0e21\u0e30\u0e40\u0e1f\u0e37\u0e2d\u0e07"
    ],
    "wof:name":"Ban Dong Mafueang",
    "wof:placetype":"locality"
},
  "geometry": {"coordinates":[99.67111,19.77464],"type":"Point"}
}