{
  "type": "Feature",
  "properties": {
    "gn:admin1_code":"1.0",
    "gn:asciiname":"Ban Kio No",
    "gn:country_code":"TH",
    "gn:dem":688,
    "gn:feature_class":"P",
    "gn:feature_code":"PPL",
    "gn:name":"Ban Kio No",
    "gn:population":0,
    "gn:timezone":"Asia/Bangkok",
    "iso:country":"TH",
    "name:tha_x_preferred":[
        "\u0e1a\u0e49\u0e32\u0e19\u0e01\u0e34\u0e48\u0e27\u0e2b\u0e19\u0e48\u0e2d"
    ],
    "wof:name":"Ban Kio No",
    "wof:placetype":"locality"
},
  "geometry": {"coordinates":[98.52504999999999,19.52264],"type":"Point"}
}