{
  "type": "Feature",
  "properties": {
    "gn:admin1_code":"22",
    "gn:asciiname":"Ban Nong Ngong",
    "gn:country_code":"TH",
    "gn:dem":167,
    "gn:feature_class":"P",
    "gn:feature_code":"PPL",
    "gn:name":"Ban Nong Ngong",
    "gn:population":0,
    "gn:timezone":"Asia/Bangkok",
    "iso:country":"TH",
    "name:tha_x_preferred":[
        "\u0e1a\u0e49\u0e32\u0e19\u0e2b\u0e19\u0e2d\u0e07\u0e42\u0e07\u0e49\u0e07"
    ],
    "wof:name":"Ban Nong Ngong",
    "wof:placetype":"locality"
},
  "geometry": {"coordinates":[102.75808000000001,16.18314],"type":"Point"}
}