{
  "type": "Feature",
  "properties": {
    "gn:admin1_code":"6.0",
    "gn:asciiname":"Ban Mae Hang Nuea",
    "gn:country_code":"TH",
    "gn:dem":592,
    "gn:feature_class":"P",
    "gn:feature_code":"PPL",
    "gn:name":"Ban Mae Hang Nuea",
    "gn:population":0,
    "gn:timezone":"Asia/Bangkok",
    "iso:country":"TH",
    "name:tha_x_preferred":[
        "\u0e1a\u0e49\u0e32\u0e19\u0e41\u0e21\u0e48\u0e2e\u0e48\u0e32\u0e07\u0e40\u0e2b\u0e19\u0e37\u0e2d"
    ],
    "wof:lang_x_official":[
        "tha"
    ],
    "wof:lang_x_spoken":[
        "tha"
    ],
    "wof:name":"Ban Mae Hang Nuea",
    "wof:placetype":"locality"
},
  "geometry": {"coordinates":[99.85733,18.88028],"type":"Point"}
}