{
  "type": "Feature",
  "properties": {
    "gn:admin1_code":"63.0",
    "gn:asciiname":"Ban Khao Khom",
    "gn:country_code":"TH",
    "gn:dem":26,
    "gn:feature_class":"P",
    "gn:feature_code":"PPL",
    "gn:name":"Ban Khao Khom",
    "gn:population":0,
    "gn:timezone":"Asia/Bangkok",
    "iso:country":"TH",
    "name:tha_x_preferred":[
        "\u0e1a\u0e49\u0e32\u0e19\u0e40\u0e02\u0e32\u0e04\u0e49\u0e2d\u0e21"
    ],
    "name:und_x_variant":[
        "Ban Khao Kom",
        "Ban Khom"
    ],
    "wof:name":"Ban Khao Khom",
    "wof:placetype":"locality"
},
  "geometry": {"coordinates":[98.77392,8.24239],"type":"Point"}
}