{
  "type": "Feature",
  "properties": {
    "gn:admin1_code":"29.0",
    "gn:asciiname":"Khwao Sinarin",
    "gn:country_code":"TH",
    "gn:dem":150,
    "gn:feature_class":"P",
    "gn:feature_code":"PPLA2",
    "gn:name":"Khwao Sinarin",
    "gn:population":0,
    "gn:timezone":"Asia/Bangkok",
    "iso:country":"TH",
    "name:tha_x_preferred":[
        "\u0e40\u0e02\u0e27\u0e32\u0e2a\u0e34\u0e19\u0e23\u0e34\u0e19\u0e17\u0e23\u0e4c"
    ],
    "name:und_x_variant":[
        "King Amphoe Khwao Sinarin",
        "Amphoe Khwao Sinarin"
    ],
    "wof:name":"Khwao Sinarin",
    "wof:placetype":"locality"
},
  "geometry": {"coordinates":[103.59153999999999,15.00244],"type":"Point"}
}