{
  "type": "Feature",
  "properties": {
    "gn:admin1_code":"50.0",
    "gn:asciiname":"Ban Nong Daeng",
    "gn:country_code":"TH",
    "gn:dem":67,
    "gn:feature_class":"P",
    "gn:feature_code":"PPL",
    "gn:name":"Ban Nong Daeng",
    "gn:population":0,
    "gn:timezone":"Asia/Bangkok",
    "iso:country":"TH",
    "name:tha_x_preferred":[
        "\u0e1a\u0e49\u0e32\u0e19\u0e2b\u0e19\u0e2d\u0e07\u0e41\u0e14\u0e07"
    ],
    "name:und_x_variant":[
        "Ban Hnong Den",
        "Ban Nong Daeng"
    ],
    "wof:name":"Ban Nong Daeng",
    "wof:placetype":"locality"
},
  "geometry": {"coordinates":[99.51169,14.24697],"type":"Point"}
}