{
  "type": "Feature",
  "properties": {
    "gn:admin1_code":"64.0",
    "gn:asciiname":"Ban Rai Yao",
    "gn:country_code":"TH",
    "gn:dem":69,
    "gn:feature_class":"P",
    "gn:feature_code":"PPL",
    "gn:name":"Ban Rai Yao",
    "gn:population":0,
    "gn:timezone":"Asia/Bangkok",
    "iso:country":"TH",
    "name:tha_x_preferred":[
        "\u0e1a\u0e49\u0e32\u0e19\u0e44\u0e23\u0e48\u0e22\u0e32\u0e27"
    ],
    "wof:name":"Ban Rai Yao",
    "wof:placetype":"locality"
},
  "geometry": {"coordinates":[99.51442,8.25994],"type":"Point"}
}