{
  "type": "Feature",
  "properties": {
    "gn:admin1_code":"67.0",
    "gn:asciiname":"Ban Kalan Batu",
    "gn:country_code":"TH",
    "gn:dem":7,
    "gn:feature_class":"P",
    "gn:feature_code":"PPL",
    "gn:name":"Ban Kalan Batu",
    "gn:population":0,
    "gn:timezone":"Asia/Bangkok",
    "iso:country":"TH",
    "name:tha_x_preferred":[
        "\u0e1a\u0e49\u0e32\u0e19\u0e01\u0e32\u0e25\u0e31\u0e19\u0e1a\u0e32\u0e15\u0e39"
    ],
    "wof:name":"Ban Kalan Batu",
    "wof:placetype":"locality"
},
  "geometry": {"coordinates":[100.03036,6.5825],"type":"Point"}
}