{
  "type": "Feature",
  "properties": {
    "gn:admin1_code":"17.0",
    "gn:asciiname":"Ban Nam Suai Tai",
    "gn:country_code":"TH",
    "gn:dem":170,
    "gn:feature_class":"P",
    "gn:feature_code":"PPL",
    "gn:name":"Ban Nam Suai Tai",
    "gn:population":0,
    "gn:timezone":"Asia/Bangkok",
    "iso:country":"TH",
    "name:tha_x_preferred":[
        "\u0e1a\u0e49\u0e32\u0e19\u0e19\u0e49\u0e33\u0e2a\u0e27\u0e22\u0e43\u0e15\u0e49"
    ],
    "wof:name":"Ban Nam Suai Tai",
    "wof:placetype":"locality"
},
  "geometry": {"coordinates":[102.78447,17.68667],"type":"Point"}
}