{
  "type": "Feature",
  "properties": {
    "gn:admin1_code":"24",
    "gn:asciiname":"Ban Nong Yang Noi",
    "gn:country_code":"TH",
    "gn:dem":181,
    "gn:feature_class":"P",
    "gn:feature_code":"PPL",
    "gn:name":"Ban Nong Yang Noi",
    "gn:population":0,
    "gn:timezone":"Asia/Bangkok",
    "iso:country":"TH",
    "name:tha_x_preferred":[
        "\u0e1a\u0e49\u0e32\u0e19\u0e2b\u0e19\u0e2d\u0e07\u0e22\u0e32\u0e07\u0e19\u0e49\u0e2d\u0e22"
    ],
    "wof:name":"Ban Nong Yang Noi",
    "wof:placetype":"locality"
},
  "geometry": {"coordinates":[103.17910999999999,15.73714],"type":"Point"}
}