{
  "type": "Feature",
  "properties": {
    "gn:admin1_code":"25.0",
    "gn:asciiname":"Ban Dok Rak Mai",
    "gn:country_code":"TH",
    "gn:dem":140,
    "gn:feature_class":"P",
    "gn:feature_code":"PPL",
    "gn:name":"Ban Dok Rak Mai",
    "gn:population":0,
    "gn:timezone":"Asia/Bangkok",
    "iso:country":"TH",
    "name:tha_x_preferred":[
        "\u0e1a\u0e49\u0e32\u0e19\u0e14\u0e2d\u0e01\u0e23\u0e31\u0e01\u0e43\u0e2b\u0e21\u0e48"
    ],
    "wof:name":"Ban Dok Rak Mai",
    "wof:placetype":"locality"
},
  "geometry": {"coordinates":[103.47338999999999,15.56406],"type":"Point"}
}