{
  "type": "Feature",
  "properties": {
    "gn:admin1_code":"22",
    "gn:asciiname":"Ban Pla Siam",
    "gn:country_code":"TH",
    "gn:dem":163,
    "gn:feature_class":"P",
    "gn:feature_code":"PPL",
    "gn:name":"Ban Pla Siam",
    "gn:population":0,
    "gn:timezone":"Asia/Bangkok",
    "iso:country":"TH",
    "name:tha_x_preferred":[
        "\u0e1a\u0e49\u0e32\u0e19\u0e1b\u0e25\u0e32\u0e40\u0e0b\u0e35\u0e22\u0e21"
    ],
    "wof:name":"Ban Pla Siam",
    "wof:placetype":"locality"
},
  "geometry": {"coordinates":[102.84766999999999,16.54003],"type":"Point"}
}