{
  "type": "Feature",
  "properties": {
    "gn:admin1_code":"9.0",
    "gn:asciiname":"Ban Tha Chum",
    "gn:country_code":"TH",
    "gn:dem":94,
    "gn:feature_class":"P",
    "gn:feature_code":"PPL",
    "gn:name":"Ban Tha Chum",
    "gn:population":0,
    "gn:timezone":"Asia/Bangkok",
    "iso:country":"TH",
    "name:tha_x_preferred":[
        "\u0e1a\u0e49\u0e32\u0e19\u0e17\u0e48\u0e32\u0e0a\u0e38\u0e21"
    ],
    "wof:name":"Ban Tha Chum",
    "wof:placetype":"locality"
},
  "geometry": {"coordinates":[99.54858,17.32007999999999],"type":"Point"}
}