{
  "type": "Feature",
  "properties": {
    "gn:admin1_code":"27.0",
    "gn:asciiname":"Ban Banlang",
    "gn:country_code":"TH",
    "gn:dem":185,
    "gn:feature_class":"P",
    "gn:feature_code":"PPL",
    "gn:name":"Ban Banlang",
    "gn:population":0,
    "gn:timezone":"Asia/Bangkok",
    "iso:country":"TH",
    "name:tha_x_preferred":[
        "\u0e1a\u0e49\u0e32\u0e19\u0e1a\u0e31\u0e25\u0e25\u0e31\u0e07\u0e01\u0e4c"
    ],
    "name:und_x_variant":[
        "Ban Masang",
        "Ban Ma Lang",
        "Ban Banlang"
    ],
    "wof:lang_x_official":[
        "tha"
    ],
    "wof:lang_x_spoken":[
        "tha"
    ],
    "wof:name":"Ban Banlang",
    "wof:placetype":"locality"
},
  "geometry": {"coordinates":[101.94367,15.19386],"type":"Point"}
}