{
  "type": "Feature",
  "properties": {
    "gn:admin1_code":"70.0",
    "gn:asciiname":"Ban Talat Nat",
    "gn:country_code":"TH",
    "gn:dem":38,
    "gn:feature_class":"P",
    "gn:feature_code":"PPL",
    "gn:name":"Ban Talat Nat",
    "gn:population":0,
    "gn:timezone":"Asia/Bangkok",
    "iso:country":"TH",
    "name:tha_x_preferred":[
        "\u0e1a\u0e49\u0e32\u0e19\u0e15\u0e25\u0e32\u0e14\u0e19\u0e31\u0e14"
    ],
    "wof:lang_x_official":[
        "tha"
    ],
    "wof:lang_x_spoken":[
        "tha"
    ],
    "wof:name":"Ban Talat Nat",
    "wof:placetype":"locality"
},
  "geometry": {"coordinates":[101.28036,6.41053],"type":"Point"}
}