{
  "type": "Feature",
  "properties": {
    "gn:admin1_code":"6.0",
    "gn:asciiname":"Ban Wang Kwang",
    "gn:cc2":"TH",
    "gn:country_code":"TH",
    "gn:dem":285,
    "gn:feature_class":"P",
    "gn:feature_code":"PPL",
    "gn:name":"Ban Wang Kwang",
    "gn:population":0,
    "gn:timezone":"Asia/Bangkok",
    "iso:country":"TH",
    "name:und_x_variant":[
        "B\u0101n Wang Gw\u0101ng",
        "Ban Wang Kwang"
    ],
    "wof:name":"Ban Wang Kwang",
    "wof:placetype":"locality"
},
  "geometry": {"coordinates":[99.60583,18.56611],"type":"Point"}
}