{
  "type": "Feature",
  "properties": {
    "gn:admin1_code":"42.0",
    "gn:asciiname":"Ban Khlong Phraya Nakkharat",
    "gn:country_code":"TH",
    "gn:dem":3,
    "gn:feature_class":"P",
    "gn:feature_code":"PPL",
    "gn:name":"Ban Khlong Phraya Nakkharat",
    "gn:population":0,
    "gn:timezone":"Asia/Bangkok",
    "iso:country":"TH",
    "name:tha_x_preferred":[
        "\u0e1a\u0e49\u0e32\u0e19\u0e04\u0e25\u0e2d\u0e07\u0e1e\u0e23\u0e30\u0e22\u0e32\u0e19\u0e32\u0e04\u0e23\u0e32\u0e0a"
    ],
    "wof:name":"Ban Khlong Phraya Nakkharat",
    "wof:placetype":"locality"
},
  "geometry": {"coordinates":[100.94369,13.65125],"type":"Point"}
}