{
  "type": "Feature",
  "properties": {
    "gn:admin1_code":"67.0",
    "gn:asciiname":"Ban Na Phaya",
    "gn:country_code":"TH",
    "gn:dem":13,
    "gn:feature_class":"P",
    "gn:feature_code":"PPL",
    "gn:name":"Ban Na Phaya",
    "gn:population":0,
    "gn:timezone":"Asia/Bangkok",
    "iso:country":"TH",
    "name:tha_x_preferred":[
        "Ban Na Phaya"
    ],
    "name:tha_x_variant":[
        "\u0e1a\u0e49\u0e32\u0e19\u0e19\u0e32\u0e1e\u0e0d\u0e32"
    ],
    "name:und_x_variant":[
        "Ban Na Ya",
        "Ban Nan Ya"
    ],
    "wof:name":"Ban Na Phaya",
    "wof:placetype":"locality"
},
  "geometry": {"coordinates":[99.83060999999999,6.82831],"type":"Point"}
}