{
  "type": "Feature",
  "properties": {
    "gn:admin1_code":"64.0",
    "gn:asciiname":"Ban Thung Kho",
    "gn:country_code":"TH",
    "gn:dem":45,
    "gn:feature_class":"P",
    "gn:feature_code":"PPL",
    "gn:name":"Ban Thung Kho",
    "gn:population":0,
    "gn:timezone":"Asia/Bangkok",
    "iso:country":"TH",
    "name:tha_x_preferred":[
        "\u0e1a\u0e49\u0e32\u0e19\u0e17\u0e38\u0e48\u0e07\u0e04\u0e49\u0e2d"
    ],
    "name:und_x_variant":[
        "Ban Thung Ko"
    ],
    "wof:name":"Ban Thung Kho",
    "wof:placetype":"locality"
},
  "geometry": {"coordinates":[99.65253,8.05106],"type":"Point"}
}