{
  "type": "Feature",
  "properties": {
    "gn:admin1_code":"28",
    "gn:asciiname":"Ban Talong Tong",
    "gn:country_code":"TH",
    "gn:dem":189,
    "gn:feature_class":"P",
    "gn:feature_code":"PPL",
    "gn:name":"Ban Talong Tong",
    "gn:population":0,
    "gn:timezone":"Asia/Bangkok",
    "iso:country":"TH",
    "name:tha_x_preferred":[
        "\u0e1a\u0e49\u0e32\u0e19\u0e15\u0e30\u0e25\u0e2d\u0e07\u0e15\u0e2d\u0e07"
    ],
    "wof:name":"Ban Talong Tong",
    "wof:placetype":"locality"
},
  "geometry": {"coordinates":[102.91764000000001,14.62428],"type":"Point"}
}