{
  "type": "Feature",
  "properties": {
    "gn:admin1_code":"5.0",
    "gn:asciiname":"Ban Huai Duea",
    "gn:country_code":"TH",
    "gn:dem":349,
    "gn:feature_class":"P",
    "gn:feature_code":"PPL",
    "gn:name":"Ban Huai Duea",
    "gn:population":0,
    "gn:timezone":"Asia/Bangkok",
    "iso:country":"TH",
    "name:tha_x_preferred":[
        "\u0e1a\u0e49\u0e32\u0e19\u0e2b\u0e49\u0e27\u0e22\u0e40\u0e14\u0e37\u0e48\u0e2d"
    ],
    "wof:name":"Ban Huai Duea",
    "wof:placetype":"locality"
},
  "geometry": {"coordinates":[98.96119,18.39331],"type":"Point"}
}