{
  "type": "Feature",
  "properties": {
    "gn:admin1_code":"28.0",
    "gn:asciiname":"Ban Mueang Faek",
    "gn:country_code":"TH",
    "gn:dem":183,
    "gn:feature_class":"P",
    "gn:feature_code":"PPL",
    "gn:name":"Ban Mueang Faek",
    "gn:population":0,
    "gn:timezone":"Asia/Bangkok",
    "iso:country":"TH",
    "name:tha_x_preferred":[
        "\u0e1a\u0e49\u0e32\u0e19\u0e40\u0e21\u0e37\u0e2d\u0e07\u0e41\u0e1d\u0e01"
    ],
    "name:und_x_variant":[
        "Ban Muang Faek"
    ],
    "wof:name":"Ban Mueang Faek",
    "wof:placetype":"locality"
},
  "geometry": {"coordinates":[102.97369,15.17869],"type":"Point"}
}