{
  "type": "Feature",
  "properties": {
    "gn:admin1_code":"40.0",
    "gn:admin2_code":"1034",
    "gn:asciiname":"Muban Seri",
    "gn:country_code":"TH",
    "gn:dem":3,
    "gn:feature_class":"P",
    "gn:feature_code":"PPL",
    "gn:name":"Muban Seri",
    "gn:population":0,
    "gn:timezone":"Asia/Bangkok",
    "iso:country":"TH",
    "name:tha_x_preferred":[
        "\u0e2b\u0e21\u0e39\u0e48\u0e1a\u0e49\u0e32\u0e19\u0e40\u0e2a\u0e23\u0e35"
    ],
    "wof:name":"Muban Seri",
    "wof:placetype":"locality"
},
  "geometry": {"coordinates":[100.62961,13.74031],"type":"Point"}
}