{
  "type": "Feature",
  "properties": {
    "gn:admin1_code":"49.0",
    "gn:asciiname":"Ban Thung Ngok",
    "gn:country_code":"TH",
    "gn:dem":27,
    "gn:feature_class":"P",
    "gn:feature_code":"PPL",
    "gn:name":"Ban Thung Ngok",
    "gn:population":0,
    "gn:timezone":"Asia/Bangkok",
    "iso:country":"TH",
    "name:tha_x_preferred":[
        "\u0e1a\u0e49\u0e32\u0e19\u0e17\u0e38\u0e48\u0e07\u0e07\u0e4a\u0e2d\u0e01"
    ],
    "wof:name":"Ban Thung Ngok",
    "wof:placetype":"locality"
},
  "geometry": {"coordinates":[102.50221999999999,12.47447],"type":"Point"}
}