{
  "type": "Feature",
  "properties": {
    "gn:admin1_code":"7.0",
    "gn:asciiname":"Ban Mae Haet",
    "gn:country_code":"TH",
    "gn:dem":158,
    "gn:feature_class":"P",
    "gn:feature_code":"PPL",
    "gn:name":"Ban Mae Haet",
    "gn:population":0,
    "gn:timezone":"Asia/Bangkok",
    "iso:country":"TH",
    "name:tha_x_preferred":[
        "\u0e1a\u0e49\u0e32\u0e19\u0e41\u0e21\u0e48\u0e41\u0e2e\u0e14"
    ],
    "name:und_x_variant":[
        "B\u0101n Mea Heak",
        "Ban Mae Haet"
    ],
    "wof:name":"Ban Mae Haet",
    "wof:placetype":"locality"
},
  "geometry": {"coordinates":[99.52764000000001,17.86022],"type":"Point"}
}