{
  "type": "Feature",
  "properties": {
    "gn:admin1_code":"78.0",
    "gn:asciiname":"Ban Don Sawan",
    "gn:country_code":"TH",
    "gn:dem":191,
    "gn:feature_class":"P",
    "gn:feature_code":"PPL",
    "gn:name":"Ban Don Sawan",
    "gn:population":0,
    "gn:timezone":"Asia/Bangkok",
    "iso:country":"TH",
    "name:tha_x_preferred":[
        "Ban Don Sawan"
    ],
    "name:tha_x_variant":[
        "\u0e1a\u0e49\u0e32\u0e19\u0e14\u0e2d\u0e19\u0e2a\u0e27\u0e23\u0e23\u0e04\u0e4c"
    ],
    "wof:name":"Ban Don Sawan",
    "wof:placetype":"locality"
},
  "geometry": {"coordinates":[104.41372,16.573],"type":"Point"}
}