{
  "type": "Feature",
  "properties": {
    "gn:admin1_code":"27",
    "gn:asciiname":"Ban Sa-nga Phatthana",
    "gn:country_code":"TH",
    "gn:dem":339,
    "gn:feature_class":"P",
    "gn:feature_code":"PPL",
    "gn:name":"Ban Sa-nga Phatthana",
    "gn:population":0,
    "gn:timezone":"Asia/Bangkok",
    "iso:country":"TH",
    "name:tha_x_preferred":[
        "\u0e1a\u0e49\u0e32\u0e19\u0e2a\u0e07\u0e48\u0e32\u0e1e\u0e31\u0e12\u0e19\u0e32"
    ],
    "wof:name":"Ban Sa-nga Phatthana",
    "wof:placetype":"locality"
},
  "geometry": {"coordinates":[101.46186,14.95033],"type":"Point"}
}