{
  "type": "Feature",
  "properties": {
    "gn:admin1_code":"57.0",
    "gn:asciiname":"Ban Talat Rai Kao",
    "gn:country_code":"TH",
    "gn:dem":18,
    "gn:feature_class":"P",
    "gn:feature_code":"PPL",
    "gn:name":"Ban Talat Rai Kao",
    "gn:population":0,
    "gn:timezone":"Asia/Bangkok",
    "iso:country":"TH",
    "name:tha_x_preferred":[
        "\u0e1a\u0e49\u0e32\u0e19\u0e15\u0e25\u0e32\u0e14\u0e44\u0e23\u0e48\u0e40\u0e01\u0e48\u0e32"
    ],
    "name:und_x_variant":[
        "Ban Rai Kao"
    ],
    "wof:name":"Ban Talat Rai Kao",
    "wof:placetype":"locality"
},
  "geometry": {"coordinates":[99.85672,12.22792],"type":"Point"}
}