{
  "type": "Feature",
  "properties": {
    "gn:admin1_code":"11.0",
    "gn:asciiname":"Ban Rai Phatthana",
    "gn:country_code":"TH",
    "gn:dem":98,
    "gn:feature_class":"P",
    "gn:feature_code":"PPL",
    "gn:name":"Ban Rai Phatthana",
    "gn:population":0,
    "gn:timezone":"Asia/Bangkok",
    "iso:country":"TH",
    "name:tha_x_preferred":[
        "\u0e1a\u0e49\u0e32\u0e19\u0e44\u0e23\u0e48\u0e1e\u0e31\u0e12\u0e19\u0e32"
    ],
    "wof:name":"Ban Rai Phatthana",
    "wof:placetype":"locality"
},
  "geometry": {"coordinates":[99.43239,16.69531],"type":"Point"}
}