{
  "type": "Feature",
  "properties": {
    "gn:admin1_code":"14.0",
    "gn:asciiname":"Ban Nam Oi",
    "gn:country_code":"TH",
    "gn:dem":164,
    "gn:feature_class":"P",
    "gn:feature_code":"PPL",
    "gn:name":"Ban Nam Oi",
    "gn:population":0,
    "gn:timezone":"Asia/Bangkok",
    "iso:country":"TH",
    "name:tha_x_preferred":[
        "\u0e1a\u0e49\u0e32\u0e19\u0e19\u0e49\u0e33\u0e2d\u0e49\u0e2d\u0e22"
    ],
    "wof:name":"Ban Nam Oi",
    "wof:placetype":"locality"
},
  "geometry": {"coordinates":[101.19696999999999,16.83769],"type":"Point"}
}