{
  "type": "Feature",
  "properties": {
    "gn:admin1_code":"39.0",
    "gn:asciiname":"Ban Khlong Paet (3)",
    "gn:cc2":"TH",
    "gn:country_code":"TH",
    "gn:dem":6,
    "gn:feature_class":"P",
    "gn:feature_code":"PPL",
    "gn:name":"Ban Khlong Paet (3)",
    "gn:population":0,
    "gn:timezone":"Asia/Bangkok",
    "iso:country":"TH",
    "name:und_x_variant":[
        "Ban Klong Ple",
        "Ban Khlong Paet (3)"
    ],
    "wof:name":"Ban Khlong Paet (3)",
    "wof:placetype":"locality"
},
  "geometry": {"coordinates":[100.78333000000001,14.21667],"type":"Point"}
}