{
  "type": "Feature",
  "properties": {
    "gn:admin1_code":"70.0",
    "gn:asciiname":"Ban Ba Le Ya To",
    "gn:country_code":"TH",
    "gn:dem":47,
    "gn:feature_class":"P",
    "gn:feature_code":"PPL",
    "gn:name":"Ban Ba Le Ya To",
    "gn:population":0,
    "gn:timezone":"Asia/Bangkok",
    "iso:country":"TH",
    "name:tha_x_preferred":[
        "\u0e1a\u0e49\u0e32\u0e19\u0e1a\u0e32\u0e40\u0e25\u0e30\u0e22\u0e32\u0e42\u0e15\u0e30"
    ],
    "wof:name":"Ban Ba Le Ya To",
    "wof:placetype":"locality"
},
  "geometry": {"coordinates":[101.31631,6.46853],"type":"Point"}
}