{
  "type": "Feature",
  "properties": {
    "gn:admin1_code":"31.0",
    "gn:asciiname":"Ban Kua Yi Ma Na",
    "gn:country_code":"TH",
    "gn:dem":23,
    "gn:feature_class":"P",
    "gn:feature_code":"PPL",
    "gn:name":"Ban Kua Yi Ma Na",
    "gn:population":0,
    "gn:timezone":"Asia/Bangkok",
    "iso:country":"TH",
    "name:tha_x_preferred":[
        "\u0e1a\u0e49\u0e32\u0e19\u0e01\u0e31\u0e27\u0e22\u0e35\u0e21\u0e32\u0e19\u0e30"
    ],
    "wof:name":"Ban Kua Yi Ma Na",
    "wof:placetype":"locality"
},
  "geometry": {"coordinates":[101.93264000000001,5.90175],"type":"Point"}
}