{
  "type": "Feature",
  "properties": {
    "gn:admin1_code":"18.0",
    "gn:asciiname":"Ban Pha In Plaeng",
    "gn:country_code":"TH",
    "gn:dem":353,
    "gn:feature_class":"P",
    "gn:feature_code":"PPL",
    "gn:name":"Ban Pha In Plaeng",
    "gn:population":0,
    "gn:timezone":"Asia/Bangkok",
    "iso:country":"TH",
    "name:tha_x_preferred":[
        "Ban Pha In Plaeng"
    ],
    "name:tha_x_variant":[
        "\u0e1a\u0e49\u0e32\u0e19\u0e1c\u0e32\u0e2d\u0e34\u0e19\u0e17\u0e23\u0e4c\u0e41\u0e1b\u0e25\u0e07"
    ],
    "wof:name":"Ban Pha In Plaeng",
    "wof:placetype":"locality"
},
  "geometry": {"coordinates":[101.99061,17.37725],"type":"Point"}
}