{
  "type": "Feature",
  "properties": {
    "gn:admin1_code":"40.0",
    "gn:admin2_code":"1011",
    "gn:asciiname":"Ban Talat Hua Takhe Fang Tai",
    "gn:country_code":"TH",
    "gn:dem":7,
    "gn:feature_class":"P",
    "gn:feature_code":"PPL",
    "gn:name":"Ban Talat Hua Takhe Fang Tai",
    "gn:population":0,
    "gn:timezone":"Asia/Bangkok",
    "iso:country":"TH",
    "name:tha_x_preferred":[
        "\u0e1a\u0e49\u0e32\u0e19\u0e15\u0e25\u0e32\u0e14\u0e2b\u0e31\u0e27\u0e15\u0e30\u0e40\u0e02\u0e49\u0e1d\u0e31\u0e48\u0e07\u0e43\u0e15\u0e49"
    ],
    "name:und_x_variant":[
        "Ban Si Yaek Hua Takhe",
        "Ban Siyek Hua Take",
        "Ban Hua Takhe",
        "Ban Talat Hua Takhe Fang Tai"
    ],
    "wof:name":"Ban Talat Hua Takhe Fang Tai",
    "wof:placetype":"locality"
},
  "geometry": {"coordinates":[100.79772,13.71744],"type":"Point"}
}