{
  "type": "Feature",
  "properties": {
    "gn:admin1_code":"6.0",
    "gn:asciiname":"Ban Nong Ya Pong",
    "gn:cc2":"TH",
    "gn:country_code":"TH",
    "gn:dem":266,
    "gn:feature_class":"P",
    "gn:feature_code":"PPL",
    "gn:name":"Ban Nong Ya Pong",
    "gn:population":0,
    "gn:timezone":"Asia/Bangkok",
    "iso:country":"TH",
    "name:und_x_variant":[
        "Ban Nong Ya Plong",
        "Ban Nong Ya Pong"
    ],
    "wof:lang_x_official":[
        "tha"
    ],
    "wof:lang_x_spoken":[
        "tha"
    ],
    "wof:name":"Ban Nong Ya Pong",
    "wof:placetype":"locality"
},
  "geometry": {"coordinates":[99.41667,18.36667000000001],"type":"Point"}
}