{
  "type": "Feature",
  "properties": {
    "gn:admin1_code":"11.0",
    "gn:asciiname":"Ban Pong Wua Daeng",
    "gn:country_code":"TH",
    "gn:dem":46,
    "gn:feature_class":"P",
    "gn:feature_code":"PPL",
    "gn:name":"Ban Pong Wua Daeng",
    "gn:population":0,
    "gn:timezone":"Asia/Bangkok",
    "iso:country":"TH",
    "name:tha_x_preferred":[
        "\u0e1a\u0e49\u0e32\u0e19\u0e42\u0e1b\u0e48\u0e07\u0e27\u0e31\u0e27\u0e41\u0e14\u0e07"
    ],
    "wof:name":"Ban Pong Wua Daeng",
    "wof:placetype":"locality"
},
  "geometry": {"coordinates":[100.03569,16.2105],"type":"Point"}
}