{
  "type": "Feature",
  "properties": {
    "gn:admin1_code":"14.0",
    "gn:asciiname":"Ban Mai Wang Sima",
    "gn:country_code":"TH",
    "gn:dem":99,
    "gn:feature_class":"P",
    "gn:feature_code":"PPL",
    "gn:name":"Ban Mai Wang Sima",
    "gn:population":0,
    "gn:timezone":"Asia/Bangkok",
    "iso:country":"TH",
    "name:tha_x_preferred":[
        "\u0e1a\u0e49\u0e32\u0e19\u0e43\u0e2b\u0e21\u0e48\u0e27\u0e31\u0e07\u0e2a\u0e35\u0e21\u0e32"
    ],
    "wof:name":"Ban Mai Wang Sima",
    "wof:placetype":"locality"
},
  "geometry": {"coordinates":[101.10011,16.12133],"type":"Point"}
}