{
  "type": "Feature",
  "properties": {
    "gn:admin1_code":"13.0",
    "gn:asciiname":"Ban Mai Kham Wan",
    "gn:country_code":"TH",
    "gn:dem":40,
    "gn:feature_class":"P",
    "gn:feature_code":"PPL",
    "gn:name":"Ban Mai Kham Wan",
    "gn:population":0,
    "gn:timezone":"Asia/Bangkok",
    "iso:country":"TH",
    "name:tha_x_preferred":[
        "\u0e1a\u0e49\u0e32\u0e19\u0e43\u0e2b\u0e21\u0e48\u0e04\u0e33\u0e27\u0e31\u0e19"
    ],
    "wof:name":"Ban Mai Kham Wan",
    "wof:placetype":"locality"
},
  "geometry": {"coordinates":[100.38069,16.31792],"type":"Point"}
}