{
  "type": "Feature",
  "properties": {
    "gn:admin1_code":"3.0",
    "gn:asciiname":"Ban Ko Hae",
    "gn:country_code":"TH",
    "gn:dem":799,
    "gn:feature_class":"P",
    "gn:feature_code":"PPL",
    "gn:name":"Ban Ko Hae",
    "gn:population":0,
    "gn:timezone":"Asia/Bangkok",
    "iso:country":"TH",
    "name:tha_x_preferred":[
        "\u0e1a\u0e49\u0e32\u0e19\u0e01\u0e2d\u0e41\u0e2e"
    ],
    "wof:name":"Ban Ko Hae",
    "wof:placetype":"locality"
},
  "geometry": {"coordinates":[99.53564,20.08519],"type":"Point"}
}