{
  "type": "Feature",
  "properties": {
    "gn:admin1_code":"4.0",
    "gn:asciiname":"Ban Nam Yao",
    "gn:country_code":"TH",
    "gn:dem":297,
    "gn:feature_class":"P",
    "gn:feature_code":"PPL",
    "gn:name":"Ban Nam Yao",
    "gn:population":0,
    "gn:timezone":"Asia/Bangkok",
    "iso:country":"TH",
    "name:tha_x_preferred":[
        "\u0e1a\u0e49\u0e32\u0e19\u0e19\u0e49\u0e33\u0e22\u0e32\u0e27"
    ],
    "wof:name":"Ban Nam Yao",
    "wof:placetype":"locality"
},
  "geometry": {"coordinates":[100.94078,18.99681],"type":"Point"}
}