{
  "type": "Feature",
  "properties": {
    "gn:admin1_code":"54.0",
    "gn:asciiname":"Ban Kradang Nga",
    "gn:country_code":"TH",
    "gn:dem":12,
    "gn:feature_class":"P",
    "gn:feature_code":"PPL",
    "gn:name":"Ban Kradang Nga",
    "gn:population":0,
    "gn:timezone":"Asia/Bangkok",
    "iso:country":"TH",
    "name:tha_x_preferred":[
        "\u0e1a\u0e49\u0e32\u0e19\u0e01\u0e23\u0e30\u0e14\u0e31\u0e07\u0e07\u0e32"
    ],
    "wof:name":"Ban Kradang Nga",
    "wof:placetype":"locality"
},
  "geometry": {"coordinates":[99.95164,13.47983],"type":"Point"}
}