{
  "type": "Feature",
  "properties": {
    "gn:admin1_code":"60.0",
    "gn:asciiname":"Ban Ao Ton Pho",
    "gn:country_code":"TH",
    "gn:dem":132,
    "gn:feature_class":"P",
    "gn:feature_code":"PPL",
    "gn:name":"Ban Ao Ton Pho",
    "gn:population":0,
    "gn:timezone":"Asia/Bangkok",
    "iso:country":"TH",
    "name:tha_x_preferred":[
        "\u0e1a\u0e49\u0e32\u0e19\u0e2d\u0e48\u0e32\u0e27\u0e15\u0e49\u0e19\u0e1e\u0e2d"
    ],
    "wof:lang_x_official":[
        "tha"
    ],
    "wof:lang_x_spoken":[
        "tha"
    ],
    "wof:name":"Ban Ao Ton Pho",
    "wof:placetype":"locality"
},
  "geometry": {"coordinates":[98.92728,8.74356],"type":"Point"}
}