{
  "type": "Feature",
  "properties": {
    "gn:admin1_code":"9.0",
    "gn:asciiname":"Ban Na Phong",
    "gn:country_code":"TH",
    "gn:dem":67,
    "gn:feature_class":"P",
    "gn:feature_code":"PPL",
    "gn:name":"Ban Na Phong",
    "gn:population":0,
    "gn:timezone":"Asia/Bangkok",
    "iso:country":"TH",
    "name:tha_x_preferred":[
        "\u0e1a\u0e49\u0e32\u0e19\u0e19\u0e32\u0e1e\u0e07"
    ],
    "wof:name":"Ban Na Phong",
    "wof:placetype":"locality"
},
  "geometry": {"coordinates":[99.75019,17.35967],"type":"Point"}
}