{
  "type": "Feature",
  "properties": {
    "gn:admin1_code":"5.0",
    "gn:asciiname":"Ban Si Sai Mun",
    "gn:country_code":"TH",
    "gn:dem":412,
    "gn:feature_class":"P",
    "gn:feature_code":"PPL",
    "gn:name":"Ban Si Sai Mun",
    "gn:population":0,
    "gn:timezone":"Asia/Bangkok",
    "iso:country":"TH",
    "name:tha_x_preferred":[
        "\u0e1a\u0e49\u0e32\u0e19\u0e28\u0e23\u0e35\u0e17\u0e23\u0e32\u0e22\u0e21\u0e39\u0e25"
    ],
    "wof:name":"Ban Si Sai Mun",
    "wof:placetype":"locality"
},
  "geometry": {"coordinates":[99.18944,18.48719],"type":"Point"}
}