{
  "type": "Feature",
  "properties": {
    "gn:admin1_code":"38.0",
    "gn:asciiname":"Ban Khlong Na Mon",
    "gn:country_code":"TH",
    "gn:dem":2,
    "gn:feature_class":"P",
    "gn:feature_code":"PPL",
    "gn:name":"Ban Khlong Na Mon",
    "gn:population":0,
    "gn:timezone":"Asia/Bangkok",
    "iso:country":"TH",
    "name:tha_x_preferred":[
        "Ban Khlong Na Mon"
    ],
    "name:tha_x_variant":[
        "\u0e1a\u0e49\u0e32\u0e19\u0e04\u0e25\u0e2d\u0e07\u0e19\u0e32\u0e2b\u0e21\u0e2d\u0e19"
    ],
    "wof:name":"Ban Khlong Na Mon",
    "wof:placetype":"locality"
},
  "geometry": {"coordinates":[100.30467,14.00347],"type":"Point"}
}