{
  "type": "Feature",
  "properties": {
    "gn:admin1_code":"49.0",
    "gn:asciiname":"Ban Muen Dan",
    "gn:country_code":"TH",
    "gn:dem":40,
    "gn:feature_class":"P",
    "gn:feature_code":"PPL",
    "gn:name":"Ban Muen Dan",
    "gn:population":0,
    "gn:timezone":"Asia/Bangkok",
    "iso:country":"TH",
    "name:tha_x_preferred":[
        "\u0e1a\u0e49\u0e32\u0e19\u0e2b\u0e21\u0e37\u0e48\u0e19\u0e14\u0e48\u0e32\u0e19"
    ],
    "name:und_x_variant":[
        "Ban Mun Dan",
        "Ban Muen Dan"
    ],
    "wof:lang_x_official":[
        "tha"
    ],
    "wof:lang_x_spoken":[
        "tha"
    ],
    "wof:name":"Ban Muen Dan",
    "wof:placetype":"locality"
},
  "geometry": {"coordinates":[102.57514,12.5935],"type":"Point"}
}