{
  "type": "Feature",
  "properties": {
    "gn:country":"TH",
    "gn:fcode":"PPL",
    "gn:pop":0,
    "iso:country":"TH",
    "name:tha_x_preferred":[
        "\u0e1a\u0e49\u0e32\u0e19\u0e40\u0e01\u0e48\u0e32"
    ],
    "name:unk_x_variant":[
        "Tha Cham Bon"
    ],
    "qs:name":"Ban Kao",
    "qs:name_adm0":"Thailand",
    "qs:name_adm1":"Chon Buri",
    "qs:photos_9k":1,
    "qs:photos_9r":1,
    "qs:photos_all":1,
    "qs:photos_sr":0,
    "qs:placetype":"Town",
    "qs:pop_sr":"0",
    "wd:wordcount":237,
    "wof:name":"Ban Kao",
    "wof:placetype":"locality",
    "wof:population":0
},
  "geometry": {"coordinates":[101.0562,13.46147],"type":"Point"}
}