{
  "type": "Feature",
  "properties": {
    "gn:admin1_code":"68.0",
    "gn:asciiname":"Ban Nang Son",
    "gn:cc2":"TH",
    "gn:country_code":"TH",
    "gn:dem":25,
    "gn:feature_class":"P",
    "gn:feature_code":"PPL",
    "gn:name":"Ban Nang Son",
    "gn:population":0,
    "gn:timezone":"Asia/Bangkok",
    "iso:country":"TH",
    "name:und_x_variant":[
        "Nang Sin",
        "Nang Son",
        "Ban Nang Son"
    ],
    "wof:name":"Ban Nang Son",
    "wof:placetype":"locality"
},
  "geometry": {"coordinates":[100.33333,6.96667],"type":"Point"}
}