{
  "type": "Feature",
  "properties": {
    "gn:admin1_code":"73.0",
    "gn:asciiname":"Ban Thai Sabai",
    "gn:country_code":"TH",
    "gn:dem":164,
    "gn:feature_class":"P",
    "gn:feature_code":"PPL",
    "gn:name":"Ban Thai Sabai",
    "gn:population":0,
    "gn:timezone":"Asia/Bangkok",
    "iso:country":"TH",
    "name:tha_x_preferred":[
        "\u0e1a\u0e49\u0e32\u0e19\u0e44\u0e17\u0e22\u0e2a\u0e1a\u0e32\u0e22"
    ],
    "wof:name":"Ban Thai Sabai",
    "wof:placetype":"locality"
},
  "geometry": {"coordinates":[104.21722,17.72017],"type":"Point"}
}