{
  "type": "Feature",
  "properties": {
    "gn:admin1_code":"2.0",
    "gn:asciiname":"Ban San Makok Wan",
    "gn:country_code":"TH",
    "gn:dem":601,
    "gn:feature_class":"P",
    "gn:feature_code":"PPL",
    "gn:name":"Ban San Makok Wan",
    "gn:population":0,
    "gn:timezone":"Asia/Bangkok",
    "iso:country":"TH",
    "name:tha_x_preferred":[
        "\u0e1a\u0e49\u0e32\u0e19\u0e2a\u0e31\u0e19\u0e21\u0e30\u0e01\u0e2d\u0e01\u0e2b\u0e27\u0e32\u0e19"
    ],
    "wof:name":"Ban San Makok Wan",
    "wof:placetype":"locality"
},
  "geometry": {"coordinates":[99.09927999999999,19.77242],"type":"Point"}
}