{
  "type": "Feature",
  "properties": {
    "gn:admin1_code":"65.0",
    "gn:asciiname":"Ban Yang Man",
    "gn:country_code":"TH",
    "gn:dem":98,
    "gn:feature_class":"P",
    "gn:feature_code":"PPL",
    "gn:name":"Ban Yang Man",
    "gn:population":0,
    "gn:timezone":"Asia/Bangkok",
    "iso:country":"TH",
    "name:tha_x_preferred":[
        "\u0e1a\u0e49\u0e32\u0e19\u0e22\u0e32\u0e07\u0e21\u0e31\u0e19"
    ],
    "wof:name":"Ban Yang Man",
    "wof:placetype":"locality"
},
  "geometry": {"coordinates":[99.47008,7.48067],"type":"Point"}
}