{
  "type": "Feature",
  "properties": {
    "gn:admin1_code":"3.0",
    "gn:asciiname":"Ban Huai Hia",
    "gn:country_code":"TH",
    "gn:dem":490,
    "gn:feature_class":"P",
    "gn:feature_code":"PPL",
    "gn:name":"Ban Huai Hia",
    "gn:population":0,
    "gn:timezone":"Asia/Bangkok",
    "iso:country":"TH",
    "name:tha_x_preferred":[
        "\u0e1a\u0e49\u0e32\u0e19\u0e2b\u0e49\u0e27\u0e22\u0e40\u0e2e\u0e35\u0e49\u0e22"
    ],
    "wof:name":"Ban Huai Hia",
    "wof:placetype":"locality"
},
  "geometry": {"coordinates":[99.45475,19.59194],"type":"Point"}
}