{
  "type": "Feature",
  "properties": {
    "gn:admin1_code":"60.0",
    "gn:asciiname":"Ban Bang Chum Tho",
    "gn:country_code":"TH",
    "gn:dem":6,
    "gn:feature_class":"P",
    "gn:feature_code":"PPL",
    "gn:name":"Ban Bang Chum Tho",
    "gn:population":0,
    "gn:timezone":"Asia/Bangkok",
    "iso:country":"TH",
    "name:tha_x_preferred":[
        "\u0e1a\u0e49\u0e32\u0e19\u0e1a\u0e32\u0e07\u0e0a\u0e38\u0e21\u0e42\u0e16"
    ],
    "wof:name":"Ban Bang Chum Tho",
    "wof:placetype":"locality"
},
  "geometry": {"coordinates":[99.30853,9.13417],"type":"Point"}
}