{
  "type": "Feature",
  "properties": {
    "gn:admin1_code":"2.0",
    "gn:asciiname":"Ban Lao Manao",
    "gn:cc2":"TH",
    "gn:country_code":"TH",
    "gn:dem":276,
    "gn:feature_class":"P",
    "gn:feature_code":"PPL",
    "gn:name":"Ban Lao Manao",
    "gn:population":0,
    "gn:timezone":"Asia/Bangkok",
    "iso:country":"TH",
    "name:und_x_variant":[
        "B\u0101n Dong",
        "Ban Khong",
        "Ban Lao Manao"
    ],
    "wof:name":"Ban Lao Manao",
    "wof:placetype":"locality"
},
  "geometry": {"coordinates":[98.67278,18.00639],"type":"Point"}
}