{
  "type": "Feature",
  "properties": {
    "gn:admin1_code":"46.0",
    "gn:asciiname":"Ban Khao Kratha",
    "gn:country_code":"TH",
    "gn:dem":100,
    "gn:feature_class":"P",
    "gn:feature_code":"PPL",
    "gn:name":"Ban Khao Kratha",
    "gn:population":0,
    "gn:timezone":"Asia/Bangkok",
    "iso:country":"TH",
    "name:tha_x_preferred":[
        "\u0e1a\u0e49\u0e32\u0e19\u0e40\u0e02\u0e32\u0e01\u0e23\u0e30\u0e17\u0e30"
    ],
    "wof:name":"Ban Khao Kratha",
    "wof:placetype":"locality"
},
  "geometry": {"coordinates":[101.24093999999999,13.06953],"type":"Point"}
}