{
  "type": "Feature",
  "properties": {
    "gn:admin1_code":"41.0",
    "gn:asciiname":"Ban Waen Phatthana",
    "gn:country_code":"TH",
    "gn:dem":398,
    "gn:feature_class":"P",
    "gn:feature_code":"PPL",
    "gn:name":"Ban Waen Phatthana",
    "gn:population":0,
    "gn:timezone":"Asia/Bangkok",
    "iso:country":"TH",
    "name:tha_x_preferred":[
        "\u0e1a\u0e49\u0e32\u0e19\u0e41\u0e27\u0e19\u0e1e\u0e31\u0e12\u0e19\u0e32"
    ],
    "name:und_x_variant":[
        "Ban Waen"
    ],
    "wof:name":"Ban Waen Phatthana",
    "wof:placetype":"locality"
},
  "geometry": {"coordinates":[100.27719999999999,19.49298],"type":"Point"}
}