{
  "type": "Feature",
  "properties": {
    "gn:admin1_code":"24",
    "gn:asciiname":"Ban Nong I Tue Tai",
    "gn:country_code":"TH",
    "gn:dem":155,
    "gn:feature_class":"P",
    "gn:feature_code":"PPL",
    "gn:name":"Ban Nong I Tue Tai",
    "gn:population":0,
    "gn:timezone":"Asia/Bangkok",
    "iso:country":"TH",
    "name:tha_x_preferred":[
        "\u0e1a\u0e49\u0e32\u0e19\u0e2b\u0e19\u0e2d\u0e07\u0e2d\u0e35\u0e15\u0e37\u0e49\u0e2d\u0e43\u0e15\u0e49"
    ],
    "wof:name":"Ban Nong I Tue Tai",
    "wof:placetype":"locality"
},
  "geometry": {"coordinates":[103.28836,16.36042],"type":"Point"}
}