{
  "type": "Feature",
  "properties": {
    "gn:admin1_code":"69.0",
    "gn:asciiname":"Ban Kha Ling",
    "gn:country_code":"TH",
    "gn:dem":27,
    "gn:feature_class":"P",
    "gn:feature_code":"PPL",
    "gn:name":"Ban Kha Ling",
    "gn:population":0,
    "gn:timezone":"Asia/Bangkok",
    "iso:country":"TH",
    "name:tha_x_preferred":[
        "\u0e1a\u0e49\u0e32\u0e19\u0e02\u0e48\u0e32\u0e25\u0e34\u0e07"
    ],
    "wof:name":"Ban Kha Ling",
    "wof:placetype":"locality"
},
  "geometry": {"coordinates":[101.44203,6.64978],"type":"Point"}
}