{
  "type": "Feature",
  "properties": {
    "gn:admin1_code":"22",
    "gn:asciiname":"Ban Sok Nam Khao",
    "gn:country_code":"TH",
    "gn:dem":224,
    "gn:feature_class":"P",
    "gn:feature_code":"PPL",
    "gn:name":"Ban Sok Nam Khao",
    "gn:population":0,
    "gn:timezone":"Asia/Bangkok",
    "iso:country":"TH",
    "name:tha_x_preferred":[
        "\u0e1a\u0e49\u0e32\u0e19\u0e42\u0e2a\u0e01\u0e19\u0e49\u0e33\u0e02\u0e32\u0e27"
    ],
    "wof:name":"Ban Sok Nam Khao",
    "wof:placetype":"locality"
},
  "geometry": {"coordinates":[102.44161,15.85528],"type":"Point"}
}