{
  "type": "Feature",
  "properties": {
    "gn:admin1_code":"76.0",
    "gn:asciiname":"Ban Khok Wichai",
    "gn:country_code":"TH",
    "gn:dem":208,
    "gn:feature_class":"P",
    "gn:feature_code":"PPL",
    "gn:name":"Ban Khok Wichai",
    "gn:population":0,
    "gn:timezone":"Asia/Bangkok",
    "iso:country":"TH",
    "name:tha_x_preferred":[
        "\u0e1a\u0e49\u0e32\u0e19\u0e42\u0e04\u0e01\u0e27\u0e34\u0e0a\u0e31\u0e22"
    ],
    "wof:name":"Ban Khok Wichai",
    "wof:placetype":"locality"
},
  "geometry": {"coordinates":[102.51347,17.43208],"type":"Point"}
}