{
  "type": "Feature",
  "properties": {
    "gn:admin1_code":"22.0",
    "gn:asciiname":"Ban Phra Bu",
    "gn:country_code":"TH",
    "gn:dem":167,
    "gn:feature_class":"P",
    "gn:feature_code":"PPL",
    "gn:name":"Ban Phra Bu",
    "gn:population":0,
    "gn:timezone":"Asia/Bangkok",
    "iso:country":"TH",
    "name:tha_x_preferred":[
        "\u0e1a\u0e49\u0e32\u0e19\u0e1e\u0e23\u0e30\u0e1a\u0e38"
    ],
    "name:und_x_variant":[
        "Ban Phrabuk",
        "Ban Phra Bu"
    ],
    "wof:name":"Ban Phra Bu",
    "wof:placetype":"locality"
},
  "geometry": {"coordinates":[102.69064,16.27275],"type":"Point"}
}