{
  "type": "Feature",
  "properties": {
    "gn:admin1_code":"16.0",
    "gn:asciiname":"Ban Sa Ta Yom",
    "gn:country_code":"TH",
    "gn:dem":68,
    "gn:feature_class":"P",
    "gn:feature_code":"PPL",
    "gn:name":"Ban Sa Ta Yom",
    "gn:population":0,
    "gn:timezone":"Asia/Bangkok",
    "iso:country":"TH",
    "name:tha_x_preferred":[
        "\u0e1a\u0e49\u0e32\u0e19\u0e2a\u0e23\u0e30\u0e15\u0e32\u0e22\u0e21"
    ],
    "wof:name":"Ban Sa Ta Yom",
    "wof:placetype":"locality"
},
  "geometry": {"coordinates":[100.68286000000001,15.97231],"type":"Point"}
}