{
  "type": "Feature",
  "properties": {
    "gn:admin1_code":"80.0",
    "gn:asciiname":"Ban Rongrian",
    "gn:country_code":"TH",
    "gn:dem":52,
    "gn:feature_class":"P",
    "gn:feature_code":"PPL",
    "gn:name":"Ban Rongrian",
    "gn:population":0,
    "gn:timezone":"Asia/Bangkok",
    "iso:country":"TH",
    "name:tha_x_preferred":[
        "\u0e1a\u0e49\u0e32\u0e19\u0e42\u0e23\u0e07\u0e40\u0e23\u0e35\u0e22\u0e19"
    ],
    "wof:name":"Ban Rongrian",
    "wof:placetype":"locality"
},
  "geometry": {"coordinates":[102.45722000000001,13.71944],"type":"Point"}
}