{
  "type": "Feature",
  "properties": {
    "gn:admin1_code":"6.0",
    "gn:asciiname":"Ban Bo Si Liam",
    "gn:country_code":"TH",
    "gn:dem":1013,
    "gn:feature_class":"P",
    "gn:feature_code":"PPL",
    "gn:name":"Ban Bo Si Liam",
    "gn:population":0,
    "gn:timezone":"Asia/Bangkok",
    "iso:country":"TH",
    "name:tha_x_preferred":[
        "\u0e1a\u0e49\u0e32\u0e19\u0e1a\u0e48\u0e2d\u0e2a\u0e35\u0e48\u0e40\u0e2b\u0e25\u0e35\u0e48\u0e22\u0e21"
    ],
    "wof:name":"Ban Bo Si Liam",
    "wof:placetype":"locality"
},
  "geometry": {"coordinates":[99.81227,18.8788],"type":"Point"}
}