{
  "type": "Feature",
  "properties": {
    "gn:admin1_code":"25.0",
    "gn:asciiname":"Ban Hua Nong Waeng",
    "gn:country_code":"TH",
    "gn:dem":136,
    "gn:feature_class":"P",
    "gn:feature_code":"PPL",
    "gn:name":"Ban Hua Nong Waeng",
    "gn:population":0,
    "gn:timezone":"Asia/Bangkok",
    "iso:country":"TH",
    "name:tha_x_preferred":[
        "\u0e1a\u0e49\u0e32\u0e19\u0e2b\u0e31\u0e27\u0e2b\u0e19\u0e2d\u0e07\u0e41\u0e27\u0e07"
    ],
    "wof:name":"Ban Hua Nong Waeng",
    "wof:placetype":"locality"
},
  "geometry": {"coordinates":[103.64581,15.71794],"type":"Point"}
}