{
  "type": "Feature",
  "properties": {
    "gn:admin1_code":"3.0",
    "gn:asciiname":"Ban Patan Mai",
    "gn:country_code":"TH",
    "gn:dem":378,
    "gn:feature_class":"P",
    "gn:feature_code":"PPL",
    "gn:name":"Ban Patan Mai",
    "gn:population":0,
    "gn:timezone":"Asia/Bangkok",
    "iso:country":"TH",
    "name:tha_x_preferred":[
        "\u0e1a\u0e49\u0e32\u0e19\u0e1b\u0e48\u0e32\u0e15\u0e32\u0e25\u0e43\u0e2b\u0e21\u0e48"
    ],
    "name:und_x_variant":[
        "Pa Tan",
        "Ban Patan Mai",
        "Ban Pa Tan"
    ],
    "wof:lang_x_official":[
        "tha"
    ],
    "wof:lang_x_spoken":[
        "tha"
    ],
    "wof:name":"Ban Patan Mai",
    "wof:placetype":"locality"
},
  "geometry": {"coordinates":[100.25864,19.84211],"type":"Point"}
}