{
  "type": "Feature",
  "properties": {
    "gn:admin1_code":"81.0",
    "gn:asciiname":"Ban Si Chom Chun",
    "gn:country_code":"TH",
    "gn:dem":158,
    "gn:feature_class":"P",
    "gn:feature_code":"PPL",
    "gn:name":"Ban Si Chom Chun",
    "gn:population":0,
    "gn:timezone":"Asia/Bangkok",
    "iso:country":"TH",
    "wof:name":"Ban Si Chom Chun",
    "wof:placetype":"locality"
},
  "geometry": {"coordinates":[103.55745,18.08016],"type":"Point"}
}