{
  "type": "Feature",
  "properties": {
    "gn:admin1_code":"69.0",
    "gn:asciiname":"Ban Ba Ngo Yue Ring",
    "gn:country_code":"TH",
    "gn:dem":14,
    "gn:feature_class":"P",
    "gn:feature_code":"PPL",
    "gn:name":"Ban Ba Ngo Yue Ring",
    "gn:population":0,
    "gn:timezone":"Asia/Bangkok",
    "iso:country":"TH",
    "name:tha_x_preferred":[
        "\u0e1a\u0e49\u0e32\u0e19\u0e1a\u0e32\u0e42\u0e07\u0e22\u0e37\u0e2d\u0e23\u0e34\u0e07"
    ],
    "name:und_x_variant":[
        "Ban Ba Ngo Yu Ring"
    ],
    "wof:name":"Ban Ba Ngo Yue Ring",
    "wof:placetype":"locality"
},
  "geometry": {"coordinates":[101.56892000000001,6.716],"type":"Point"}
}