{
  "type": "Feature",
  "properties": {
    "gn:admin1_code":"73.0",
    "gn:asciiname":"Ban Phathai",
    "gn:country_code":"TH",
    "gn:dem":157,
    "gn:feature_class":"P",
    "gn:feature_code":"PPL",
    "gn:name":"Ban Phathai",
    "gn:population":0,
    "gn:timezone":"Asia/Bangkok",
    "iso:country":"TH",
    "name:tha_x_preferred":[
        "\u0e1a\u0e49\u0e32\u0e19\u0e1e\u0e30\u0e17\u0e32\u0e22"
    ],
    "wof:name":"Ban Phathai",
    "wof:placetype":"locality"
},
  "geometry": {"coordinates":[104.31153,17.75214],"type":"Point"}
}