{
  "type": "Feature",
  "properties": {
    "gn:admin1_code":"7.0",
    "gn:asciiname":"Ban Suan Pa",
    "gn:country_code":"TH",
    "gn:dem":384,
    "gn:feature_class":"P",
    "gn:feature_code":"PPL",
    "gn:name":"Ban Suan Pa",
    "gn:population":0,
    "gn:timezone":"Asia/Bangkok",
    "iso:country":"TH",
    "name:tha_x_preferred":[
        "\u0e1a\u0e49\u0e32\u0e19\u0e2a\u0e27\u0e19\u0e1b\u0e48\u0e32"
    ],
    "wof:name":"Ban Suan Pa",
    "wof:placetype":"locality"
},
  "geometry": {"coordinates":[100.47535999999999,18.44722],"type":"Point"}
}