{
  "type": "Feature",
  "properties": {
    "gn:admin1_code":"52.0",
    "gn:asciiname":"Ban Ma Hai",
    "gn:country_code":"TH",
    "gn:dem":8,
    "gn:feature_class":"P",
    "gn:feature_code":"PPL",
    "gn:name":"Ban Ma Hai",
    "gn:population":0,
    "gn:timezone":"Asia/Bangkok",
    "iso:country":"TH",
    "name:tha_x_preferred":[
        "\u0e1a\u0e49\u0e32\u0e19\u0e21\u0e49\u0e32\u0e2e\u0e32\u0e22"
    ],
    "wof:name":"Ban Ma Hai",
    "wof:placetype":"locality"
},
  "geometry": {"coordinates":[99.89917,13.52794],"type":"Point"}
}