{
  "type": "Feature",
  "properties": {
    "gn:admin1_code":"2.0",
    "gn:asciiname":"Ban Nong Yao",
    "gn:country_code":"TH",
    "gn:dem":476,
    "gn:feature_class":"P",
    "gn:feature_code":"PPL",
    "gn:name":"Ban Nong Yao",
    "gn:population":0,
    "gn:timezone":"Asia/Bangkok",
    "iso:country":"TH",
    "name:tha_x_preferred":[
        "\u0e1a\u0e49\u0e32\u0e19\u0e2b\u0e19\u0e2d\u0e07\u0e22\u0e32\u0e27"
    ],
    "name:und_x_variant":[
        "B\u0101n Naung Bua",
        "Ban Nong Bua",
        "Ban Nong Yao"
    ],
    "wof:name":"Ban Nong Yao",
    "wof:placetype":"locality"
},
  "geometry": {"coordinates":[99.17574999999999,19.85278],"type":"Point"}
}