{
  "type": "Feature",
  "properties": {
    "gn:admin1_code":"3.0",
    "gn:asciiname":"Ban Huai Chomphu I-Ko",
    "gn:country_code":"TH",
    "gn:dem":1091,
    "gn:feature_class":"P",
    "gn:feature_code":"PPL",
    "gn:name":"Ban Huai Chomphu I-Ko",
    "gn:population":0,
    "gn:timezone":"Asia/Bangkok",
    "iso:country":"TH",
    "name:tha_x_preferred":[
        "\u0e1a\u0e49\u0e32\u0e19\u0e2b\u0e49\u0e27\u0e22\u0e0a\u0e21\u0e20\u0e39\u0e2d\u0e35\u0e01\u0e49\u0e2d"
    ],
    "wof:name":"Ban Huai Chomphu I-Ko",
    "wof:placetype":"locality"
},
  "geometry": {"coordinates":[99.50675,19.98197],"type":"Point"}
}