{
  "type": "Feature",
  "properties": {
    "gn:admin1_code":"17.0",
    "gn:asciiname":"Ban Pak Suai",
    "gn:country_code":"TH",
    "gn:dem":163,
    "gn:feature_class":"P",
    "gn:feature_code":"PPL",
    "gn:name":"Ban Pak Suai",
    "gn:population":0,
    "gn:timezone":"Asia/Bangkok",
    "iso:country":"TH",
    "name:tha_x_preferred":[
        "\u0e1a\u0e49\u0e32\u0e19\u0e1b\u0e32\u0e01\u0e2a\u0e27\u0e22"
    ],
    "name:und_x_variant":[
        "Ban Pak Soei",
        "Ban Pak Suai"
    ],
    "wof:name":"Ban Pak Suai",
    "wof:placetype":"locality"
},
  "geometry": {"coordinates":[103.00406,17.97514],"type":"Point"}
}