{
  "type": "Feature",
  "properties": {
    "gn:admin1_code":"31.0",
    "gn:asciiname":"Ban Lu Bo Ba Tu",
    "gn:country_code":"TH",
    "gn:dem":37,
    "gn:feature_class":"P",
    "gn:feature_code":"PPL",
    "gn:name":"Ban Lu Bo Ba Tu",
    "gn:population":0,
    "gn:timezone":"Asia/Bangkok",
    "iso:country":"TH",
    "name:tha_x_preferred":[
        "\u0e1a\u0e49\u0e32\u0e19\u0e25\u0e39\u0e42\u0e1a\u0e4a\u0e30\u0e1a\u0e32\u0e15\u0e39"
    ],
    "name:und_x_variant":[
        "Kampong Lubok Batu",
        "Ban Lu Bo Ba Tu",
        "Kampong Lubobatu"
    ],
    "wof:lang_x_official":[
        "tha"
    ],
    "wof:lang_x_spoken":[
        "tha"
    ],
    "wof:name":"Ban Lu Bo Ba Tu",
    "wof:placetype":"locality"
},
  "geometry": {"coordinates":[101.52791999999999,6.29056],"type":"Point"}
}