{
  "type": "Feature",
  "properties": {
    "gn:admin1_code":"6.0",
    "gn:asciiname":"Ban Nong Lom",
    "gn:country_code":"TH",
    "gn:dem":258,
    "gn:feature_class":"P",
    "gn:feature_code":"PPL",
    "gn:name":"Ban Nong Lom",
    "gn:population":0,
    "gn:timezone":"Asia/Bangkok",
    "iso:country":"TH",
    "name:tha_x_preferred":[
        "\u0e1a\u0e49\u0e32\u0e19\u0e2b\u0e19\u0e2d\u0e07\u0e2b\u0e25\u0e48\u0e21"
    ],
    "name:und_x_variant":[
        "B\u0101n Naung Lom",
        "Ban Nong Lom"
    ],
    "wof:name":"Ban Nong Lom",
    "wof:placetype":"locality"
},
  "geometry": {"coordinates":[99.40317,18.33414],"type":"Point"}
}