{
  "type": "Feature",
  "properties": {
    "gn:admin1_code":"2.0",
    "gn:asciiname":"Ban Mai Don Kaeo",
    "gn:country_code":"TH",
    "gn:dem":549,
    "gn:feature_class":"P",
    "gn:feature_code":"PPL",
    "gn:name":"Ban Mai Don Kaeo",
    "gn:population":0,
    "gn:timezone":"Asia/Bangkok",
    "iso:country":"TH",
    "name:tha_x_preferred":[
        "\u0e1a\u0e49\u0e32\u0e19\u0e43\u0e2b\u0e21\u0e48\u0e14\u0e2d\u0e19\u0e41\u0e01\u0e49\u0e27"
    ],
    "name:und_x_variant":[
        "Ban Mai"
    ],
    "wof:name":"Ban Mai Don Kaeo",
    "wof:placetype":"locality"
},
  "geometry": {"coordinates":[99.30164000000001,18.71933],"type":"Point"}
}