{
  "type": "Feature",
  "properties": {
    "gn:admin1_code":"13.0",
    "gn:asciiname":"Ban Khao Phra",
    "gn:country_code":"TH",
    "gn:dem":36,
    "gn:feature_class":"P",
    "gn:feature_code":"PPL",
    "gn:name":"Ban Khao Phra",
    "gn:population":0,
    "gn:timezone":"Asia/Bangkok",
    "iso:country":"TH",
    "name:tha_x_preferred":[
        "\u0e1a\u0e49\u0e32\u0e19\u0e40\u0e02\u0e32\u0e1e\u0e23\u0e30"
    ],
    "name:und_x_variant":[
        "Ban Kao Phra",
        "Ban Khao Phra"
    ],
    "wof:name":"Ban Khao Phra",
    "wof:placetype":"locality"
},
  "geometry": {"coordinates":[100.40328,16.33311],"type":"Point"}
}