{
  "type": "Feature",
  "properties": {
    "gn:admin1_code":"26.0",
    "gn:asciiname":"Ban Dong Pha Suk",
    "gn:country_code":"TH",
    "gn:dem":237,
    "gn:feature_class":"P",
    "gn:feature_code":"PPL",
    "gn:name":"Ban Dong Pha Suk",
    "gn:population":0,
    "gn:timezone":"Asia/Bangkok",
    "iso:country":"TH",
    "name:tha_x_preferred":[
        "\u0e1a\u0e49\u0e32\u0e19\u0e14\u0e07\u0e1c\u0e32\u0e2a\u0e38\u0e02"
    ],
    "wof:name":"Ban Dong Pha Suk",
    "wof:placetype":"locality"
},
  "geometry": {"coordinates":[101.89156,15.46097],"type":"Point"}
}