{
  "type": "Feature",
  "properties": {
    "gn:admin1_code":"20.0",
    "gn:asciiname":"Ban Wang Chomphu",
    "gn:country_code":"TH",
    "gn:dem":164,
    "gn:feature_class":"P",
    "gn:feature_code":"PPL",
    "gn:name":"Ban Wang Chomphu",
    "gn:population":0,
    "gn:timezone":"Asia/Bangkok",
    "iso:country":"TH",
    "name:tha_x_preferred":[
        "\u0e1a\u0e49\u0e32\u0e19\u0e27\u0e31\u0e07\u0e0a\u0e21\u0e20\u0e39"
    ],
    "wof:name":"Ban Wang Chomphu",
    "wof:placetype":"locality"
},
  "geometry": {"coordinates":[103.80717,17.76297000000001],"type":"Point"}
}