{
  "type": "Feature",
  "properties": {
    "gn:admin1_code":"7.0",
    "gn:asciiname":"Ban Nam Phu Noi",
    "gn:country_code":"TH",
    "gn:dem":395,
    "gn:feature_class":"P",
    "gn:feature_code":"PPL",
    "gn:name":"Ban Nam Phu Noi",
    "gn:population":0,
    "gn:timezone":"Asia/Bangkok",
    "iso:country":"TH",
    "name:tha_x_preferred":[
        "\u0e1a\u0e49\u0e32\u0e19\u0e19\u0e49\u0e33\u0e1e\u0e38\u0e19\u0e49\u0e2d\u0e22"
    ],
    "name:und_x_variant":[
        "Ban Nam Phu",
        "Ban Nam Phu Noi"
    ],
    "wof:name":"Ban Nam Phu Noi",
    "wof:placetype":"locality"
},
  "geometry": {"coordinates":[100.45158000000001,18.43656],"type":"Point"}
}