{
  "type": "Feature",
  "properties": {
    "gn:admin1_code":"2.0",
    "gn:asciiname":"Ban San Pa Sak",
    "gn:country_code":"TH",
    "gn:dem":345,
    "gn:feature_class":"P",
    "gn:feature_code":"PPL",
    "gn:name":"Ban San Pa Sak",
    "gn:population":0,
    "gn:timezone":"Asia/Bangkok",
    "iso:country":"TH",
    "name:tha_x_preferred":[
        "\u0e1a\u0e49\u0e32\u0e19\u0e2a\u0e31\u0e19\u0e1b\u0e48\u0e32\u0e2a\u0e31\u0e01"
    ],
    "name:und_x_variant":[
        "B\u0101n Wang Gin",
        "Ban Wang Kin",
        "Ban San Pa Sak"
    ],
    "wof:name":"Ban San Pa Sak",
    "wof:placetype":"locality"
},
  "geometry": {"coordinates":[99.01006,19.13689],"type":"Point"}
}