{
  "type": "Feature",
  "properties": {
    "gn:admin1_code":"2.0",
    "gn:asciiname":"Ban Mai Tae Than",
    "gn:country_code":"TH",
    "gn:dem":310,
    "gn:feature_class":"P",
    "gn:feature_code":"PPL",
    "gn:name":"Ban Mai Tae Than",
    "gn:population":0,
    "gn:timezone":"Asia/Bangkok",
    "iso:country":"TH",
    "name:tha_x_preferred":[
        "\u0e1a\u0e49\u0e32\u0e19\u0e43\u0e2b\u0e21\u0e48\u0e41\u0e15\u0e18\u0e32\u0e23"
    ],
    "wof:name":"Ban Mai Tae Than",
    "wof:placetype":"locality"
},
  "geometry": {"coordinates":[98.819,18.56314],"type":"Point"}
}