{
  "type": "Feature",
  "properties": {
    "gn:admin1_code":"12.0",
    "gn:asciiname":"Ban Wang Ta Bua",
    "gn:country_code":"TH",
    "gn:dem":48,
    "gn:feature_class":"P",
    "gn:feature_code":"PPL",
    "gn:name":"Ban Wang Ta Bua",
    "gn:population":0,
    "gn:timezone":"Asia/Bangkok",
    "iso:country":"TH",
    "name:tha_x_preferred":[
        "\u0e1a\u0e49\u0e32\u0e19\u0e27\u0e31\u0e07\u0e15\u0e32\u0e1a\u0e31\u0e27"
    ],
    "wof:name":"Ban Wang Ta Bua",
    "wof:placetype":"locality"
},
  "geometry": {"coordinates":[100.25400999999999,16.58025],"type":"Point"}
}