{
  "type": "Feature",
  "properties": {
    "gn:admin1_code":"27.0",
    "gn:asciiname":"Ban Phra",
    "gn:country_code":"TH",
    "gn:dem":196,
    "gn:feature_class":"P",
    "gn:feature_code":"PPL",
    "gn:name":"Ban Phra",
    "gn:population":0,
    "gn:timezone":"Asia/Bangkok",
    "iso:country":"TH",
    "name:tha_x_preferred":[
        "\u0e1a\u0e49\u0e32\u0e19\u0e1e\u0e23\u0e30"
    ],
    "name:und_x_variant":[
        "B\u0101n Phra",
        "Ban Phra Mo",
        "Ban Phra"
    ],
    "wof:name":"Ban Phra",
    "wof:placetype":"locality"
},
  "geometry": {"coordinates":[101.89183,15.14306],"type":"Point"}
}