{
  "type": "Feature",
  "properties": {
    "gn:admin1_code":"31.0",
    "gn:asciiname":"Ban Ku Bae Bo Ngo",
    "gn:country_code":"TH",
    "gn:dem":13,
    "gn:feature_class":"P",
    "gn:feature_code":"PPL",
    "gn:name":"Ban Ku Bae Bo Ngo",
    "gn:population":0,
    "gn:timezone":"Asia/Bangkok",
    "iso:country":"TH",
    "name:tha_x_preferred":[
        "\u0e1a\u0e49\u0e32\u0e19\u0e01\u0e39\u0e41\u0e1a\u0e1a\u0e2d\u0e07\u0e2d"
    ],
    "wof:name":"Ban Ku Bae Bo Ngo",
    "wof:placetype":"locality"
},
  "geometry": {"coordinates":[101.80168999999999,6.31536],"type":"Point"}
}