{
  "type": "Feature",
  "properties": {
    "gn:admin1_code":"61.0",
    "gn:asciiname":"Ban Lo Yung",
    "gn:country_code":"TH",
    "gn:dem":29,
    "gn:feature_class":"P",
    "gn:feature_code":"PPL",
    "gn:name":"Ban Lo Yung",
    "gn:population":0,
    "gn:timezone":"Asia/Bangkok",
    "iso:country":"TH",
    "name:tha_x_preferred":[
        "\u0e1a\u0e49\u0e32\u0e19\u0e2b\u0e25\u0e48\u0e2d\u0e22\u0e39\u0e07"
    ],
    "wof:name":"Ban Lo Yung",
    "wof:placetype":"locality"
},
  "geometry": {"coordinates":[98.34711,8.27356],"type":"Point"}
}