{
  "type": "Feature",
  "properties": {
    "gn:admin1_code":"46.0",
    "gn:asciiname":"Ban Khao Thung Na",
    "gn:country_code":"TH",
    "gn:dem":73,
    "gn:feature_class":"P",
    "gn:feature_code":"PPL",
    "gn:name":"Ban Khao Thung Na",
    "gn:population":0,
    "gn:timezone":"Asia/Bangkok",
    "iso:country":"TH",
    "name:tha_x_preferred":[
        "\u0e1a\u0e49\u0e32\u0e19\u0e40\u0e02\u0e32\u0e17\u0e38\u0e48\u0e07\u0e19\u0e32"
    ],
    "name:und_x_variant":[
        "Ban Thung Na"
    ],
    "wof:name":"Ban Khao Thung Na",
    "wof:placetype":"locality"
},
  "geometry": {"coordinates":[101.07436,13.31944],"type":"Point"}
}