{
  "type": "Feature",
  "properties": {
    "gn:admin1_code":"36",
    "gn:asciiname":"Ban Sai Ngam",
    "gn:country_code":"TH",
    "gn:dem":6,
    "gn:feature_class":"P",
    "gn:feature_code":"PPL",
    "gn:name":"Ban Sai Ngam",
    "gn:population":0,
    "gn:timezone":"Asia/Bangkok",
    "iso:country":"TH",
    "name:tha_x_preferred":[
        "\u0e1a\u0e49\u0e32\u0e19\u0e44\u0e17\u0e23\u0e07\u0e32\u0e21"
    ],
    "wof:name":"Ban Sai Ngam",
    "wof:placetype":"locality"
},
  "geometry": {"coordinates":[100.69806,14.36981],"type":"Point"}
}