{
  "type": "Feature",
  "properties": {
    "gn:admin1_code":"33",
    "gn:asciiname":"Ban Pho Samnak",
    "gn:country_code":"TH",
    "gn:dem":19,
    "gn:feature_class":"P",
    "gn:feature_code":"PPL",
    "gn:name":"Ban Pho Samnak",
    "gn:population":0,
    "gn:timezone":"Asia/Bangkok",
    "iso:country":"TH",
    "name:tha_x_preferred":[
        "\u0e1a\u0e49\u0e32\u0e19\u0e42\u0e1e\u0e18\u0e34\u0e4c\u0e2a\u0e33\u0e19\u0e31\u0e01"
    ],
    "wof:name":"Ban Pho Samnak",
    "wof:placetype":"locality"
},
  "geometry": {"coordinates":[100.34237,15.05261],"type":"Point"}
}