{
  "type": "Feature",
  "properties": {
    "gn:admin1_code":"49.0",
    "gn:asciiname":"Ban Khlong Nonsi",
    "gn:country_code":"TH",
    "gn:dem":6,
    "gn:feature_class":"P",
    "gn:feature_code":"PPL",
    "gn:name":"Ban Khlong Nonsi",
    "gn:population":0,
    "gn:timezone":"Asia/Bangkok",
    "iso:country":"TH",
    "name:tha_x_preferred":[
        "\u0e1a\u0e49\u0e32\u0e19\u0e04\u0e25\u0e2d\u0e07\u0e19\u0e19\u0e17\u0e23\u0e35"
    ],
    "name:und_x_variant":[
        "Dan",
        "Khlaung Non Si",
        "Ban Dan",
        "Ban Kaw Chang",
        "Ban Khlong Nonsi"
    ],
    "wof:name":"Ban Khlong Nonsi",
    "wof:placetype":"locality"
},
  "geometry": {"coordinates":[102.35442999999999,12.10877],"type":"Point"}
}