{
  "type": "Feature",
  "properties": {
    "gn:admin1_code":"79.0",
    "gn:asciiname":"Ban Kha Noi",
    "gn:country_code":"TH",
    "gn:dem":203,
    "gn:feature_class":"P",
    "gn:feature_code":"PPL",
    "gn:name":"Ban Kha Noi",
    "gn:population":0,
    "gn:timezone":"Asia/Bangkok",
    "iso:country":"TH",
    "name:tha_x_preferred":[
        "\u0e1a\u0e49\u0e32\u0e19\u0e02\u0e48\u0e32\u0e19\u0e49\u0e2d\u0e22"
    ],
    "wof:name":"Ban Kha Noi",
    "wof:placetype":"locality"
},
  "geometry": {"coordinates":[102.42769,17.04475],"type":"Point"}
}