{
  "type": "Feature",
  "properties": {
    "gn:admin1_code":"34",
    "gn:asciiname":"Ban Khao Nom Nang",
    "gn:country_code":"TH",
    "gn:dem":100,
    "gn:feature_class":"P",
    "gn:feature_code":"PPL",
    "gn:name":"Ban Khao Nom Nang",
    "gn:population":0,
    "gn:timezone":"Asia/Bangkok",
    "iso:country":"TH",
    "name:tha_x_preferred":[
        "\u0e1a\u0e49\u0e32\u0e19\u0e40\u0e02\u0e32\u0e19\u0e21\u0e19\u0e32\u0e07"
    ],
    "wof:name":"Ban Khao Nom Nang",
    "wof:placetype":"locality"
},
  "geometry": {"coordinates":[101.12656,15.24825],"type":"Point"}
}