{
  "type": "Feature",
  "properties": {
    "gn:admin1_code":"2.0",
    "gn:asciiname":"Ban Sam Lang",
    "gn:country_code":"TH",
    "gn:dem":1133,
    "gn:feature_class":"P",
    "gn:feature_code":"PPL",
    "gn:name":"Ban Sam Lang",
    "gn:population":0,
    "gn:timezone":"Asia/Bangkok",
    "iso:country":"TH",
    "name:tha_x_preferred":[
        "\u0e1a\u0e49\u0e32\u0e19\u0e2a\u0e32\u0e21\u0e2b\u0e25\u0e31\u0e07"
    ],
    "wof:name":"Ban Sam Lang",
    "wof:placetype":"locality"
},
  "geometry": {"coordinates":[98.34564,18.14745],"type":"Point"}
}