{
  "type": "Feature",
  "properties": {
    "gn:admin1_code":"80",
    "gn:asciiname":"Ban Thung Setthi",
    "gn:country_code":"TH",
    "gn:dem":106,
    "gn:feature_class":"P",
    "gn:feature_code":"PPL",
    "gn:name":"Ban Thung Setthi",
    "gn:population":0,
    "gn:timezone":"Asia/Bangkok",
    "iso:country":"TH",
    "name:tha_x_preferred":[
        "\u0e1a\u0e49\u0e32\u0e19\u0e17\u0e38\u0e48\u0e07\u0e40\u0e28\u0e23\u0e29\u0e10\u0e35"
    ],
    "wof:name":"Ban Thung Setthi",
    "wof:placetype":"locality"
},
  "geometry": {"coordinates":[102.04819000000001,13.40469],"type":"Point"}
}