{
  "type": "Feature",
  "properties": {
    "gn:admin1_code":"27",
    "gn:asciiname":"Ban Khlong Hin Lat",
    "gn:country_code":"TH",
    "gn:dem":417,
    "gn:feature_class":"P",
    "gn:feature_code":"PPL",
    "gn:name":"Ban Khlong Hin Lat",
    "gn:population":0,
    "gn:timezone":"Asia/Bangkok",
    "iso:country":"TH",
    "name:tha_x_preferred":[
        "\u0e1a\u0e49\u0e32\u0e19\u0e04\u0e25\u0e2d\u0e07\u0e2b\u0e34\u0e19\u0e25\u0e32\u0e14"
    ],
    "wof:name":"Ban Khlong Hin Lat",
    "wof:placetype":"locality"
},
  "geometry": {"coordinates":[101.51478,14.62364],"type":"Point"}
}