{
  "type": "Feature",
  "properties": {
    "gn:admin1_code":"5.0",
    "gn:asciiname":"Ban Pong Phang",
    "gn:country_code":"TH",
    "gn:dem":552,
    "gn:feature_class":"P",
    "gn:feature_code":"PPL",
    "gn:name":"Ban Pong Phang",
    "gn:population":0,
    "gn:timezone":"Asia/Bangkok",
    "iso:country":"TH",
    "name:tha_x_preferred":[
        "\u0e1a\u0e49\u0e32\u0e19\u0e1b\u0e07\u0e1c\u0e32\u0e07"
    ],
    "wof:name":"Ban Pong Phang",
    "wof:placetype":"locality"
},
  "geometry": {"coordinates":[99.06908,18.30111],"type":"Point"}
}