{
  "type": "Feature",
  "properties": {
    "gn:admin1_code":"3.0",
    "gn:asciiname":"Ban Yian Chong Toe",
    "gn:country_code":"TH",
    "gn:dem":1052,
    "gn:feature_class":"P",
    "gn:feature_code":"PPL",
    "gn:name":"Ban Yian Chong Toe",
    "gn:population":0,
    "gn:timezone":"Asia/Bangkok",
    "iso:country":"TH",
    "name:tha_x_preferred":[
        "\u0e1a\u0e49\u0e32\u0e19\u0e40\u0e22\u0e35\u0e22\u0e19\u0e42\u0e0a\u0e49\u0e07\u0e40\u0e15\u0e4b\u0e2d"
    ],
    "wof:name":"Ban Yian Chong Toe",
    "wof:placetype":"locality"
},
  "geometry": {"coordinates":[99.53603,19.95372],"type":"Point"}
}