{
  "type": "Feature",
  "properties": {
    "gn:admin1_code":"18.0",
    "gn:asciiname":"Ban Nong Khon",
    "gn:country_code":"TH",
    "gn:dem":255,
    "gn:feature_class":"P",
    "gn:feature_code":"PPL",
    "gn:name":"Ban Nong Khon",
    "gn:population":0,
    "gn:timezone":"Asia/Bangkok",
    "iso:country":"TH",
    "name:tha_x_preferred":[
        "Ban Nong Khon"
    ],
    "name:tha_x_variant":[
        "\u0e1a\u0e49\u0e32\u0e19\u0e2b\u0e19\u0e2d\u0e07\u0e02\u0e2d\u0e19"
    ],
    "wof:name":"Ban Nong Khon",
    "wof:placetype":"locality"
},
  "geometry": {"coordinates":[101.89481000000001,16.84167],"type":"Point"}
}