{
  "type": "Feature",
  "properties": {
    "gn:admin1_code":"26.0",
    "gn:asciiname":"Ban Don Mo Kaeng",
    "gn:country_code":"TH",
    "gn:dem":233,
    "gn:feature_class":"P",
    "gn:feature_code":"PPL",
    "gn:name":"Ban Don Mo Kaeng",
    "gn:population":0,
    "gn:timezone":"Asia/Bangkok",
    "iso:country":"TH",
    "wof:name":"Ban Don Mo Kaeng",
    "wof:placetype":"locality"
},
  "geometry": {"coordinates":[101.63583,15.44361],"type":"Point"}
}