{
  "type": "Feature",
  "properties": {
    "gn:admin1_code":"58.0",
    "gn:asciiname":"Ban Don Suea Huk",
    "gn:country_code":"TH",
    "gn:dem":12,
    "gn:feature_class":"P",
    "gn:feature_code":"PPL",
    "gn:name":"Ban Don Suea Huk",
    "gn:population":0,
    "gn:timezone":"Asia/Bangkok",
    "iso:country":"TH",
    "name:tha_x_preferred":[
        "\u0e1a\u0e49\u0e32\u0e19\u0e14\u0e2d\u0e19\u0e40\u0e2a\u0e37\u0e2d\u0e2e\u0e39\u0e01"
    ],
    "wof:name":"Ban Don Suea Huk",
    "wof:placetype":"locality"
},
  "geometry": {"coordinates":[99.17819,10.45117],"type":"Point"}
}