{
  "type": "Feature",
  "properties": {
    "gn:admin1_code":"37",
    "gn:asciiname":"Ban Chet Khot",
    "gn:country_code":"TH",
    "gn:dem":131,
    "gn:feature_class":"P",
    "gn:feature_code":"PPL",
    "gn:name":"Ban Chet Khot",
    "gn:population":0,
    "gn:timezone":"Asia/Bangkok",
    "iso:country":"TH",
    "name:tha_x_preferred":[
        "\u0e1a\u0e49\u0e32\u0e19\u0e40\u0e08\u0e47\u0e14\u0e04\u0e15"
    ],
    "wof:name":"Ban Chet Khot",
    "wof:placetype":"locality"
},
  "geometry": {"coordinates":[101.15333,14.47817],"type":"Point"}
}