{
  "type": "Feature",
  "properties": {
    "gn:admin1_code":"27.0",
    "gn:asciiname":"Ban Kut Plakheng",
    "gn:country_code":"TH",
    "gn:dem":210,
    "gn:feature_class":"P",
    "gn:feature_code":"PPL",
    "gn:name":"Ban Kut Plakheng",
    "gn:population":0,
    "gn:timezone":"Asia/Bangkok",
    "iso:country":"TH",
    "name:tha_x_preferred":[
        "\u0e1a\u0e49\u0e32\u0e19\u0e01\u0e38\u0e14\u0e1b\u0e25\u0e32\u0e40\u0e02\u0e47\u0e07"
    ],
    "name:und_x_variant":[
        "Ban Kut Pla Kheng",
        "Ban Kut Pla Khem",
        "Ban Kut Plakheng"
    ],
    "wof:name":"Ban Kut Plakheng",
    "wof:placetype":"locality"
},
  "geometry": {"coordinates":[101.88442000000001,14.93814],"type":"Point"}
}