{
  "type": "Feature",
  "properties": {
    "gn:admin1_code":"31.0",
    "gn:asciiname":"Ban Su-ngai Ba La",
    "gn:country_code":"TH",
    "gn:dem":15,
    "gn:feature_class":"P",
    "gn:feature_code":"PPL",
    "gn:name":"Ban Su-ngai Ba La",
    "gn:population":0,
    "gn:timezone":"Asia/Bangkok",
    "iso:country":"TH",
    "name:tha_x_preferred":[
        "\u0e1a\u0e49\u0e32\u0e19\u0e2a\u0e38\u0e44\u0e2b\u0e07\u0e1a\u0e32\u0e25\u0e32"
    ],
    "wof:name":"Ban Su-ngai Ba La",
    "wof:placetype":"locality"
},
  "geometry": {"coordinates":[101.76958,6.38872],"type":"Point"}
}