{
  "type": "Feature",
  "properties": {
    "gn:admin1_code":"6.0",
    "gn:asciiname":"Ban Saliam Wan",
    "gn:country_code":"TH",
    "gn:dem":175,
    "gn:feature_class":"P",
    "gn:feature_code":"PPL",
    "gn:name":"Ban Saliam Wan",
    "gn:population":0,
    "gn:timezone":"Asia/Bangkok",
    "iso:country":"TH",
    "name:tha_x_preferred":[
        "\u0e1a\u0e49\u0e32\u0e19\u0e2a\u0e30\u0e40\u0e25\u0e35\u0e22\u0e21\u0e2b\u0e27\u0e32\u0e19"
    ],
    "name:und_x_variant":[
        "M\u0113sali\u0113mhwai",
        "Ban Saliam Wan",
        "Saliam Wan",
        "B\u0101n Saliyam W\u0101n",
        "Ban Mae Saliam Wan"
    ],
    "wof:name":"Ban Saliam Wan",
    "wof:placetype":"locality"
},
  "geometry": {"coordinates":[99.35225,17.47286],"type":"Point"}
}