{
  "type": "Feature",
  "properties": {
    "gn:admin1_code":"68.0",
    "gn:asciiname":"Ban Tha Kham",
    "gn:country_code":"TH",
    "gn:dem":18,
    "gn:feature_class":"P",
    "gn:feature_code":"PPL",
    "gn:name":"Ban Tha Kham",
    "gn:population":0,
    "gn:timezone":"Asia/Bangkok",
    "iso:country":"TH",
    "name:tha_x_preferred":[
        "\u0e1a\u0e49\u0e32\u0e19\u0e17\u0e48\u0e32\u0e02\u0e49\u0e32\u0e21"
    ],
    "name:und_x_variant":[
        "Ban Tah Kham",
        "Ban Tha Kham (1)",
        "Ban Tha Kham"
    ],
    "wof:name":"Ban Tha Kham",
    "wof:placetype":"locality"
},
  "geometry": {"coordinates":[100.56811,7.05664],"type":"Point"}
}