{
  "type": "Feature",
  "properties": {
    "gn:admin1_code":"14.0",
    "gn:asciiname":"Ban Maeo Hua Pha",
    "gn:country_code":"TH",
    "gn:dem":1375,
    "gn:feature_class":"P",
    "gn:feature_code":"PPL",
    "gn:name":"Ban Maeo Hua Pha",
    "gn:population":0,
    "gn:timezone":"Asia/Bangkok",
    "iso:country":"TH",
    "wof:name":"Ban Maeo Hua Pha",
    "wof:placetype":"locality"
},
  "geometry": {"coordinates":[101.05,16.88332999999999],"type":"Point"}
}