{
  "type": "Feature",
  "properties": {
    "gn:admin1_code":"47.0",
    "gn:asciiname":"Ban Krahom",
    "gn:country_code":"TH",
    "gn:dem":19,
    "gn:feature_class":"P",
    "gn:feature_code":"PPL",
    "gn:name":"Ban Krahom",
    "gn:population":0,
    "gn:timezone":"Asia/Bangkok",
    "iso:country":"TH",
    "name:und_x_variant":[
        "\u0e1a\u0e49\u0e32\u0e19\u0e01\u0e23\u0e30\u0e42\u0e2b\u0e21",
        "Ban Kahom"
    ],
    "wof:name":"Ban Krahom",
    "wof:placetype":"locality"
},
  "geometry": {"coordinates":[101.28722,12.8025],"type":"Point"}
}