{
  "type": "Feature",
  "properties": {
    "gn:admin1_code":"64.0",
    "gn:asciiname":"Ban Tha Pra Cha",
    "gn:country_code":"TH",
    "gn:dem":9,
    "gn:feature_class":"P",
    "gn:feature_code":"PPL",
    "gn:name":"Ban Tha Pra Cha",
    "gn:population":0,
    "gn:timezone":"Asia/Bangkok",
    "iso:country":"TH",
    "name:tha_x_preferred":[
        "\u0e1a\u0e49\u0e32\u0e19\u0e17\u0e48\u0e32\u0e1b\u0e23\u0e30\u0e08\u0e30"
    ],
    "wof:name":"Ban Tha Pra Cha",
    "wof:placetype":"locality"
},
  "geometry": {"coordinates":[99.97620999999999,7.96383],"type":"Point"}
}