{
  "type": "Feature",
  "properties": {
    "gn:admin1_code":"73.0",
    "gn:asciiname":"Ban Mun On Noi",
    "gn:country_code":"TH",
    "gn:dem":165,
    "gn:feature_class":"P",
    "gn:feature_code":"PPL",
    "gn:name":"Ban Mun On Noi",
    "gn:population":0,
    "gn:timezone":"Asia/Bangkok",
    "iso:country":"TH",
    "name:tha_x_preferred":[
        "Ban Mun On Noi"
    ],
    "name:tha_x_variant":[
        "\u0e1a\u0e49\u0e32\u0e19\u0e21\u0e39\u0e25\u0e2d\u0e49\u0e19\u0e19\u0e49\u0e2d\u0e22"
    ],
    "wof:name":"Ban Mun On Noi",
    "wof:placetype":"locality"
},
  "geometry": {"coordinates":[104.38191999999999,16.97597],"type":"Point"}
}