{
  "type": "Feature",
  "properties": {
    "gn:admin1_code":"37",
    "gn:asciiname":"Ban Pong Mongkhon",
    "gn:country_code":"TH",
    "gn:dem":60,
    "gn:feature_class":"P",
    "gn:feature_code":"PPL",
    "gn:name":"Ban Pong Mongkhon",
    "gn:population":0,
    "gn:timezone":"Asia/Bangkok",
    "iso:country":"TH",
    "name:tha_x_preferred":[
        "\u0e1a\u0e49\u0e32\u0e19\u0e42\u0e1b\u0e48\u0e07\u0e21\u0e07\u0e04\u0e25"
    ],
    "wof:name":"Ban Pong Mongkhon",
    "wof:placetype":"locality"
},
  "geometry": {"coordinates":[101.07436,14.46169],"type":"Point"}
}