{
  "type": "Feature",
  "properties": {
    "gn:admin1_code":"43.0",
    "gn:asciiname":"Ban Khlong Si Ka Phan",
    "gn:cc2":"TH",
    "gn:country_code":"TH",
    "gn:dem":6,
    "gn:feature_class":"P",
    "gn:feature_code":"PPL",
    "gn:name":"Ban Khlong Si Ka Phan",
    "gn:population":0,
    "gn:timezone":"Asia/Bangkok",
    "iso:country":"TH",
    "name:und_x_variant":[
        "Ban Khlong Si Kaphon",
        "Ban Khlong Si Ka Pan",
        "Ban Khlong Si Ka Phan"
    ],
    "wof:name":"Ban Khlong Si Ka Phan",
    "wof:placetype":"locality"
},
  "geometry": {"coordinates":[101.02861,14.10028],"type":"Point"}
}