{
  "type": "Feature",
  "properties": {
    "gn:admin1_code":"43.0",
    "gn:asciiname":"Ban Khok Kradon",
    "gn:country_code":"TH",
    "gn:dem":10,
    "gn:feature_class":"P",
    "gn:feature_code":"PPL",
    "gn:name":"Ban Khok Kradon",
    "gn:population":0,
    "gn:timezone":"Asia/Bangkok",
    "iso:country":"TH",
    "name:tha_x_preferred":[
        "\u0e1a\u0e49\u0e32\u0e19\u0e42\u0e04\u0e01\u0e01\u0e23\u0e30\u0e42\u0e14\u0e19"
    ],
    "name:und_x_variant":[
        "Ban Khok Kadon"
    ],
    "wof:name":"Ban Khok Kradon",
    "wof:placetype":"locality"
},
  "geometry": {"coordinates":[101.27958,14.13289],"type":"Point"}
}