{
  "type": "Feature",
  "properties": {
    "gn:admin1_code":"50.0",
    "gn:asciiname":"Ban Kui Cha Tho",
    "gn:cc2":"TH",
    "gn:country_code":"TH",
    "gn:dem":162,
    "gn:feature_class":"P",
    "gn:feature_code":"PPL",
    "gn:name":"Ban Kui Cha Tho",
    "gn:population":0,
    "gn:timezone":"Asia/Bangkok",
    "iso:country":"TH",
    "name:und_x_variant":[
        "Ban Gui Jathau",
        "Ban Kui Cha Tho"
    ],
    "wof:name":"Ban Kui Cha Tho",
    "wof:placetype":"locality"
},
  "geometry": {"coordinates":[98.40000000000001,15.05],"type":"Point"}
}