{
  "type": "Feature",
  "properties": {
    "gn:admin1_code":"11.0",
    "gn:asciiname":"Ban Bueng Lat",
    "gn:country_code":"TH",
    "gn:dem":49,
    "gn:feature_class":"P",
    "gn:feature_code":"PPL",
    "gn:name":"Ban Bueng Lat",
    "gn:population":0,
    "gn:timezone":"Asia/Bangkok",
    "iso:country":"TH",
    "name:tha_x_preferred":[
        "\u0e1a\u0e49\u0e32\u0e19\u0e1a\u0e36\u0e07\u0e25\u0e32\u0e14"
    ],
    "wof:name":"Ban Bueng Lat",
    "wof:placetype":"locality"
},
  "geometry": {"coordinates":[99.88994,16.14789],"type":"Point"}
}