{
  "type": "Feature",
  "properties": {
    "gn:admin1_code":"12.0",
    "gn:asciiname":"Ban Noen Thong",
    "gn:country_code":"TH",
    "gn:dem":70,
    "gn:feature_class":"P",
    "gn:feature_code":"PPL",
    "gn:name":"Ban Noen Thong",
    "gn:population":0,
    "gn:timezone":"Asia/Bangkok",
    "iso:country":"TH",
    "name:tha_x_preferred":[
        "\u0e1a\u0e49\u0e32\u0e19\u0e40\u0e19\u0e34\u0e19\u0e17\u0e2d\u0e07"
    ],
    "wof:name":"Ban Noen Thong",
    "wof:placetype":"locality"
},
  "geometry": {"coordinates":[100.62264,16.59994],"type":"Point"}
}