{
  "type": "Feature",
  "properties": {
    "gn:admin1_code":"56.0",
    "gn:asciiname":"Ban Don Yang Thon",
    "gn:country_code":"TH",
    "gn:dem":8,
    "gn:feature_class":"P",
    "gn:feature_code":"PPL",
    "gn:name":"Ban Don Yang Thon",
    "gn:population":0,
    "gn:timezone":"Asia/Bangkok",
    "iso:country":"TH",
    "name:tha_x_preferred":[
        "\u0e1a\u0e49\u0e32\u0e19\u0e14\u0e2d\u0e19\u0e22\u0e32\u0e07\u0e42\u0e17\u0e19"
    ],
    "name:und_x_variant":[
        "Ban Don Nang Thon"
    ],
    "wof:name":"Ban Don Yang Thon",
    "wof:placetype":"locality"
},
  "geometry": {"coordinates":[100.00517000000001,13.01668],"type":"Point"}
}