{
  "type": "Feature",
  "properties": {
    "gn:admin1_code":"3.0",
    "gn:asciiname":"Ban Khwae Wua Dam",
    "gn:country_code":"TH",
    "gn:dem":414,
    "gn:feature_class":"P",
    "gn:feature_code":"PPL",
    "gn:name":"Ban Khwae Wua Dam",
    "gn:population":0,
    "gn:timezone":"Asia/Bangkok",
    "iso:country":"TH",
    "name:tha_x_preferred":[
        "\u0e1a\u0e49\u0e32\u0e19\u0e41\u0e04\u0e27\u0e27\u0e31\u0e27\u0e14\u0e33"
    ],
    "wof:name":"Ban Khwae Wua Dam",
    "wof:placetype":"locality"
},
  "geometry": {"coordinates":[99.65264000000001,19.97906],"type":"Point"}
}