{
  "type": "Feature",
  "properties": {
    "gn:admin1_code":"81.0",
    "gn:asciiname":"Ban Nang Wong Sum",
    "gn:country_code":"TH",
    "gn:dem":163,
    "gn:feature_class":"P",
    "gn:feature_code":"PPL",
    "gn:name":"Ban Nang Wong Sum",
    "gn:population":0,
    "gn:timezone":"Asia/Bangkok",
    "iso:country":"TH",
    "name:tha_x_preferred":[
        "\u0e1a\u0e49\u0e32\u0e19\u0e19\u0e32\u0e07\u0e27\u0e07\u0e2a\u0e38\u0e48\u0e21"
    ],
    "wof:name":"Ban Nang Wong Sum",
    "wof:placetype":"locality"
},
  "geometry": {"coordinates":[103.53833,18.17347],"type":"Point"}
}