{
  "type": "Feature",
  "properties": {
    "gn:admin1_code":"32.0",
    "gn:asciiname":"Ban Wat Chan",
    "gn:country_code":"TH",
    "gn:dem":18,
    "gn:feature_class":"P",
    "gn:feature_code":"PPL",
    "gn:name":"Ban Wat Chan",
    "gn:population":0,
    "gn:timezone":"Asia/Bangkok",
    "iso:country":"TH",
    "name:tha_x_preferred":[
        "\u0e1a\u0e49\u0e32\u0e19\u0e27\u0e31\u0e14\u0e08\u0e31\u0e48\u0e19"
    ],
    "wof:name":"Ban Wat Chan",
    "wof:placetype":"locality"
},
  "geometry": {"coordinates":[100.26752999999999,14.96461],"type":"Point"}
}