{
  "type": "Feature",
  "properties": {
    "gn:admin1_code":"3.0",
    "gn:asciiname":"Ban Pha Wi",
    "gn:country_code":"TH",
    "gn:dem":598,
    "gn:feature_class":"P",
    "gn:feature_code":"PPL",
    "gn:name":"Ban Pha Wi",
    "gn:population":0,
    "gn:timezone":"Asia/Bangkok",
    "iso:country":"TH",
    "name:tha_x_preferred":[
        "\u0e1a\u0e49\u0e32\u0e19\u0e1c\u0e32\u0e27\u0e35"
    ],
    "name:und_x_variant":[
        "Pha Wi",
        "Ban Pha Wi"
    ],
    "wof:name":"Ban Pha Wi",
    "wof:placetype":"locality"
},
  "geometry": {"coordinates":[99.62975,19.40978],"type":"Point"}
}