{
  "type": "Feature",
  "properties": {
    "gn:admin1_code":"41.0",
    "gn:asciiname":"Ban Mae Tom Nai",
    "gn:country_code":"TH",
    "gn:dem":457,
    "gn:feature_class":"P",
    "gn:feature_code":"PPL",
    "gn:name":"Ban Mae Tom Nai",
    "gn:population":0,
    "gn:timezone":"Asia/Bangkok",
    "iso:country":"TH",
    "name:tha_x_preferred":[
        "\u0e1a\u0e49\u0e32\u0e19\u0e41\u0e21\u0e48\u0e15\u0e4b\u0e2d\u0e21\u0e43\u0e19"
    ],
    "name:und_x_variant":[
        "Ban Huai Tom Nai",
        "Ban Mae Tom"
    ],
    "wof:name":"Ban Mae Tom Nai",
    "wof:placetype":"locality"
},
  "geometry": {"coordinates":[99.78955999999999,19.17667],"type":"Point"}
}