{
  "type": "Feature",
  "properties": {
    "gn:admin1_code":"3.0",
    "gn:asciiname":"Ban Mae Kham Noi",
    "gn:country_code":"TH",
    "gn:dem":767,
    "gn:feature_class":"P",
    "gn:feature_code":"PPL",
    "gn:name":"Ban Mae Kham Noi",
    "gn:population":0,
    "gn:timezone":"Asia/Bangkok",
    "iso:country":"TH",
    "name:tha_x_preferred":[
        "\u0e1a\u0e49\u0e32\u0e19\u0e41\u0e21\u0e48\u0e04\u0e33\u0e19\u0e49\u0e2d\u0e22"
    ],
    "wof:lang_x_official":[
        "tha"
    ],
    "wof:lang_x_spoken":[
        "tha"
    ],
    "wof:name":"Ban Mae Kham Noi",
    "wof:placetype":"locality"
},
  "geometry": {"coordinates":[99.56605999999999,20.30289],"type":"Point"}
}