{
  "type": "Feature",
  "properties": {
    "gn:admin1_code":"27",
    "gn:asciiname":"Ban Nong Khruea Chut",
    "gn:country_code":"TH",
    "gn:dem":185,
    "gn:feature_class":"P",
    "gn:feature_code":"PPL",
    "gn:name":"Ban Nong Khruea Chut",
    "gn:population":0,
    "gn:timezone":"Asia/Bangkok",
    "iso:country":"TH",
    "name:tha_x_preferred":[
        "\u0e1a\u0e49\u0e32\u0e19\u0e2b\u0e19\u0e2d\u0e07\u0e40\u0e04\u0e23\u0e37\u0e2d\u0e0a\u0e38\u0e14"
    ],
    "wof:name":"Ban Nong Khruea Chut",
    "wof:placetype":"locality"
},
  "geometry": {"coordinates":[102.40083,14.93344],"type":"Point"}
}