{
  "type": "Feature",
  "properties": {
    "gn:admin1_code":"4.0",
    "gn:asciiname":"Ban Mai Din Daen",
    "gn:country_code":"TH",
    "gn:dem":207,
    "gn:feature_class":"P",
    "gn:feature_code":"PPL",
    "gn:name":"Ban Mai Din Daen",
    "gn:population":0,
    "gn:timezone":"Asia/Bangkok",
    "iso:country":"TH",
    "name:tha_x_preferred":[
        "\u0e1a\u0e49\u0e32\u0e19\u0e43\u0e2b\u0e21\u0e48\u0e14\u0e34\u0e19\u0e41\u0e14\u0e19"
    ],
    "wof:name":"Ban Mai Din Daen",
    "wof:placetype":"locality"
},
  "geometry": {"coordinates":[100.73027999999999,18.56614],"type":"Point"}
}