{
  "type": "Feature",
  "properties": {
    "gn:admin1_code":"27",
    "gn:asciiname":"Ban Huai Chong Kho",
    "gn:country_code":"TH",
    "gn:dem":194,
    "gn:feature_class":"P",
    "gn:feature_code":"PPL",
    "gn:name":"Ban Huai Chong Kho",
    "gn:population":0,
    "gn:timezone":"Asia/Bangkok",
    "iso:country":"TH",
    "name:tha_x_preferred":[
        "\u0e1a\u0e49\u0e32\u0e19\u0e2b\u0e49\u0e27\u0e22\u0e0a\u0e07\u0e42\u0e04"
    ],
    "wof:name":"Ban Huai Chong Kho",
    "wof:placetype":"locality"
},
  "geometry": {"coordinates":[102.10786,15.57114],"type":"Point"}
}