{
  "type": "Feature",
  "properties": {
    "gn:admin1_code":"3.0",
    "gn:asciiname":"Ban Saen Charoen Mai",
    "gn:country_code":"TH",
    "gn:dem":809,
    "gn:feature_class":"P",
    "gn:feature_code":"PPL",
    "gn:name":"Ban Saen Charoen Mai",
    "gn:population":0,
    "gn:timezone":"Asia/Bangkok",
    "iso:country":"TH",
    "name:tha_x_preferred":[
        "\u0e1a\u0e49\u0e32\u0e19\u0e41\u0e2a\u0e19\u0e40\u0e08\u0e23\u0e34\u0e0d\u0e43\u0e2b\u0e21\u0e48"
    ],
    "wof:name":"Ban Saen Charoen Mai",
    "wof:placetype":"locality"
},
  "geometry": {"coordinates":[99.53145000000001,19.72758],"type":"Point"}
}