{
  "type": "Feature",
  "properties": {
    "gn:admin1_code":"6.0",
    "gn:asciiname":"Ban Chae Khon",
    "gn:country_code":"TH",
    "gn:dem":364,
    "gn:feature_class":"P",
    "gn:feature_code":"PPL",
    "gn:name":"Ban Chae Khon",
    "gn:population":0,
    "gn:timezone":"Asia/Bangkok",
    "iso:country":"TH",
    "name:tha_x_preferred":[
        "\u0e1a\u0e49\u0e32\u0e19\u0e41\u0e08\u0e49\u0e04\u0e2d\u0e19"
    ],
    "wof:name":"Ban Chae Khon",
    "wof:placetype":"locality"
},
  "geometry": {"coordinates":[99.65808,18.91364],"type":"Point"}
}