{
  "type": "Feature",
  "properties": {
    "gn:admin1_code":"32.0",
    "gn:asciiname":"Ban Tha Kaeo",
    "gn:country_code":"TH",
    "gn:dem":21,
    "gn:feature_class":"P",
    "gn:feature_code":"PPL",
    "gn:name":"Ban Tha Kaeo",
    "gn:population":0,
    "gn:timezone":"Asia/Bangkok",
    "iso:country":"TH",
    "name:tha_x_preferred":[
        "\u0e1a\u0e49\u0e32\u0e19\u0e17\u0e48\u0e32\u0e41\u0e01\u0e49\u0e27"
    ],
    "wof:name":"Ban Tha Kaeo",
    "wof:placetype":"locality"
},
  "geometry": {"coordinates":[100.02469000000001,15.12908],"type":"Point"}
}