{
  "type": "Feature",
  "properties": {
    "gn:admin1_code":"69.0",
    "gn:asciiname":"Ban Thung Naren",
    "gn:country_code":"TH",
    "gn:dem":6,
    "gn:feature_class":"P",
    "gn:feature_code":"PPL",
    "gn:name":"Ban Thung Naren",
    "gn:population":0,
    "gn:timezone":"Asia/Bangkok",
    "iso:country":"TH",
    "name:tha_x_preferred":[
        "\u0e1a\u0e49\u0e32\u0e19\u0e17\u0e38\u0e48\u0e07\u0e19\u0e40\u0e23\u0e19\u0e17\u0e4c"
    ],
    "wof:name":"Ban Thung Naren",
    "wof:placetype":"locality"
},
  "geometry": {"coordinates":[101.11725,6.80767],"type":"Point"}
}