{
  "type": "Feature",
  "properties": {
    "gn:admin1_code":"2.0",
    "gn:asciiname":"Ban Hong Thon Phatthana",
    "gn:country_code":"TH",
    "gn:dem":470,
    "gn:feature_class":"P",
    "gn:feature_code":"PPL",
    "gn:name":"Ban Hong Thon Phatthana",
    "gn:population":0,
    "gn:timezone":"Asia/Bangkok",
    "iso:country":"TH",
    "name:tha_x_preferred":[
        "\u0e1a\u0e49\u0e32\u0e19\u0e2e\u0e48\u0e2d\u0e07\u0e16\u0e48\u0e2d\u0e19\u0e1e\u0e31\u0e12\u0e19\u0e32"
    ],
    "wof:name":"Ban Hong Thon Phatthana",
    "wof:placetype":"locality"
},
  "geometry": {"coordinates":[99.32505999999999,19.9835],"type":"Point"}
}