{
  "type": "Feature",
  "properties": {
    "gn:admin1_code":"56.0",
    "gn:asciiname":"Ban Nong Phutsa",
    "gn:country_code":"TH",
    "gn:dem":8,
    "gn:feature_class":"P",
    "gn:feature_code":"PPL",
    "gn:name":"Ban Nong Phutsa",
    "gn:population":0,
    "gn:timezone":"Asia/Bangkok",
    "iso:country":"TH",
    "name:tha_x_preferred":[
        "\u0e1a\u0e49\u0e32\u0e19\u0e2b\u0e19\u0e2d\u0e07\u0e1e\u0e38\u0e17\u0e23\u0e32"
    ],
    "name:und_x_variant":[
        "Ban Don Phutsa",
        "Ban Nong Phutsa"
    ],
    "wof:name":"Ban Nong Phutsa",
    "wof:placetype":"locality"
},
  "geometry": {"coordinates":[99.98728,13.03667],"type":"Point"}
}