{
  "type": "Feature",
  "properties": {
    "gn:admin1_code":"57.0",
    "gn:asciiname":"Ban Kaeng Krathing",
    "gn:country_code":"TH",
    "gn:dem":14,
    "gn:feature_class":"P",
    "gn:feature_code":"PPL",
    "gn:name":"Ban Kaeng Krathing",
    "gn:population":0,
    "gn:timezone":"Asia/Bangkok",
    "iso:country":"TH",
    "name:tha_x_preferred":[
        "\u0e1a\u0e49\u0e32\u0e19\u0e41\u0e01\u0e48\u0e07\u0e01\u0e23\u0e30\u0e17\u0e34\u0e07"
    ],
    "wof:name":"Ban Kaeng Krathing",
    "wof:placetype":"locality"
},
  "geometry": {"coordinates":[99.92278,12.44203],"type":"Point"}
}