{
  "type": "Feature",
  "properties": {
    "gn:admin1_code":"64.0",
    "gn:asciiname":"Ban Plai Rang",
    "gn:country_code":"TH",
    "gn:dem":30,
    "gn:feature_class":"P",
    "gn:feature_code":"PPL",
    "gn:name":"Ban Plai Rang",
    "gn:population":0,
    "gn:timezone":"Asia/Bangkok",
    "iso:country":"TH",
    "name:tha_x_preferred":[
        "\u0e1a\u0e49\u0e32\u0e19\u0e1b\u0e25\u0e32\u0e22\u0e23\u0e32\u0e07"
    ],
    "wof:name":"Ban Plai Rang",
    "wof:placetype":"locality"
},
  "geometry": {"coordinates":[99.85630999999999,8.28222],"type":"Point"}
}