{
  "type": "Feature",
  "properties": {
    "gn:admin1_code":"43",
    "gn:asciiname":"Ban Khao Lom",
    "gn:country_code":"TH",
    "gn:dem":30,
    "gn:feature_class":"P",
    "gn:feature_code":"PPL",
    "gn:name":"Ban Khao Lom",
    "gn:population":0,
    "gn:timezone":"Asia/Bangkok",
    "iso:country":"TH",
    "name:tha_x_preferred":[
        "\u0e1a\u0e49\u0e32\u0e19\u0e40\u0e02\u0e32\u0e25\u0e49\u0e2d\u0e21"
    ],
    "wof:name":"Ban Khao Lom",
    "wof:placetype":"locality"
},
  "geometry": {"coordinates":[101.0745,14.37767],"type":"Point"}
}