{
  "type": "Feature",
  "properties": {
    "gn:admin1_code":"12.0",
    "gn:asciiname":"Ban Pa Mae Nang",
    "gn:country_code":"TH",
    "gn:dem":200,
    "gn:feature_class":"P",
    "gn:feature_code":"PPL",
    "gn:name":"Ban Pa Mae Nang",
    "gn:population":0,
    "gn:timezone":"Asia/Bangkok",
    "iso:country":"TH",
    "name:tha_x_preferred":[
        "\u0e1a\u0e49\u0e32\u0e19\u0e1b\u0e48\u0e32\u0e41\u0e21\u0e48\u0e19\u0e32\u0e07"
    ],
    "wof:name":"Ban Pa Mae Nang",
    "wof:placetype":"locality"
},
  "geometry": {"coordinates":[100.68942,16.83978],"type":"Point"}
}