{
  "type": "Feature",
  "properties": {
    "gn:admin1_code":"48.0",
    "gn:asciiname":"Ban Tua Chui",
    "gn:country_code":"TH",
    "gn:dem":24,
    "gn:feature_class":"P",
    "gn:feature_code":"PPL",
    "gn:name":"Ban Tua Chui",
    "gn:population":0,
    "gn:timezone":"Asia/Bangkok",
    "iso:country":"TH",
    "name:tha_x_preferred":[
        "\u0e1a\u0e49\u0e32\u0e19\u0e15\u0e31\u0e49\u0e27\u0e08\u0e38\u0e49\u0e22"
    ],
    "wof:name":"Ban Tua Chui",
    "wof:placetype":"locality"
},
  "geometry": {"coordinates":[102.01939,12.65111],"type":"Point"}
}