{
  "type": "Feature",
  "properties": {
    "gn:admin1_code":"1.0",
    "gn:asciiname":"Ban Mae Lai Bon",
    "gn:country_code":"TH",
    "gn:dem":1127,
    "gn:feature_class":"P",
    "gn:feature_code":"PPL",
    "gn:name":"Ban Mae Lai Bon",
    "gn:population":0,
    "gn:timezone":"Asia/Bangkok",
    "iso:country":"TH",
    "name:tha_x_preferred":[
        "\u0e1a\u0e49\u0e32\u0e19\u0e41\u0e21\u0e48\u0e25\u0e32\u0e22\u0e1a\u0e19"
    ],
    "wof:name":"Ban Mae Lai Bon",
    "wof:placetype":"locality"
},
  "geometry": {"coordinates":[98.11353,18.15053],"type":"Point"}
}