{
  "type": "Feature",
  "properties": {
    "gn:admin1_code":"75.0",
    "gn:asciiname":"Ban Phu Mari",
    "gn:country_code":"TH",
    "gn:dem":132,
    "gn:feature_class":"P",
    "gn:feature_code":"PPL",
    "gn:name":"Ban Phu Mari",
    "gn:population":0,
    "gn:timezone":"Asia/Bangkok",
    "iso:country":"TH",
    "name:tha_x_preferred":[
        "\u0e1a\u0e49\u0e32\u0e19\u0e20\u0e39\u0e21\u0e30\u0e2b\u0e23\u0e35\u0e48"
    ],
    "wof:name":"Ban Phu Mari",
    "wof:placetype":"locality"
},
  "geometry": {"coordinates":[105.21781,15.14883],"type":"Point"}
}