{
  "type": "Feature",
  "properties": {
    "gn:admin1_code":"31.0",
    "gn:asciiname":"Ban Na Anamai (Nu Ro)",
    "gn:country_code":"TH",
    "gn:dem":31,
    "gn:feature_class":"P",
    "gn:feature_code":"PPL",
    "gn:name":"Ban Na Anamai (Nu Ro)",
    "gn:population":0,
    "gn:timezone":"Asia/Bangkok",
    "iso:country":"TH",
    "name:tha_x_preferred":[
        "\u0e1a\u0e49\u0e32\u0e19\u0e2b\u0e19\u0e49\u0e32\u0e2d\u0e19\u0e32\u0e21\u0e31\u0e22 (\u0e19\u0e39\u0e42\u0e23\u0e4a\u0e30)"
    ],
    "wof:name":"Ban Na Anamai (Nu Ro)",
    "wof:placetype":"locality"
},
  "geometry": {"coordinates":[101.92025,5.86208],"type":"Point"}
}