{
  "type": "Feature",
  "properties": {
    "gn:admin1_code":"40.0",
    "gn:admin2_code":"1032",
    "gn:asciiname":"Muban Thung Setthi",
    "gn:country_code":"TH",
    "gn:dem":5,
    "gn:feature_class":"P",
    "gn:feature_code":"PPL",
    "gn:name":"Muban Thung Setthi",
    "gn:population":0,
    "gn:timezone":"Asia/Bangkok",
    "iso:country":"TH",
    "name:tha_x_preferred":[
        "\u0e2b\u0e21\u0e39\u0e48\u0e1a\u0e49\u0e32\u0e19\u0e17\u0e38\u0e48\u0e07\u0e40\u0e28\u0e23\u0e29\u0e10\u0e35"
    ],
    "wof:name":"Muban Thung Setthi",
    "wof:placetype":"locality"
},
  "geometry": {"coordinates":[100.69199999999999,13.67389],"type":"Point"}
}