{
  "type": "Feature",
  "properties": {
    "gn:admin1_code":"26.0",
    "gn:asciiname":"Ban Kut Mak Paep",
    "gn:country_code":"TH",
    "gn:dem":191,
    "gn:feature_class":"P",
    "gn:feature_code":"PPL",
    "gn:name":"Ban Kut Mak Paep",
    "gn:population":0,
    "gn:timezone":"Asia/Bangkok",
    "iso:country":"TH",
    "name:tha_x_preferred":[
        "\u0e1a\u0e49\u0e32\u0e19\u0e01\u0e38\u0e14\u0e2b\u0e21\u0e32\u0e01\u0e41\u0e1b\u0e1a"
    ],
    "wof:name":"Ban Kut Mak Paep",
    "wof:placetype":"locality"
},
  "geometry": {"coordinates":[101.85993999999999,15.73456],"type":"Point"}
}