{
  "type": "Feature",
  "properties": {
    "gn:admin1_code":"50.0",
    "gn:asciiname":"Ban Hin Si",
    "gn:country_code":"TH",
    "gn:dem":199,
    "gn:feature_class":"P",
    "gn:feature_code":"PPL",
    "gn:name":"Ban Hin Si",
    "gn:population":0,
    "gn:timezone":"Asia/Bangkok",
    "iso:country":"TH",
    "name:tha_x_preferred":[
        "\u0e1a\u0e49\u0e32\u0e19\u0e2b\u0e34\u0e19\u0e2a\u0e35"
    ],
    "wof:name":"Ban Hin Si",
    "wof:placetype":"locality"
},
  "geometry": {"coordinates":[99.17758000000001,13.78394],"type":"Point"}
}