{
  "type": "Feature",
  "properties": {
    "gn:admin1_code":"24",
    "gn:asciiname":"Ban Kao Noi",
    "gn:country_code":"TH",
    "gn:dem":162,
    "gn:feature_class":"P",
    "gn:feature_code":"PPL",
    "gn:name":"Ban Kao Noi",
    "gn:population":0,
    "gn:timezone":"Asia/Bangkok",
    "iso:country":"TH",
    "name:tha_x_preferred":[
        "\u0e1a\u0e49\u0e32\u0e19\u0e40\u0e01\u0e48\u0e32\u0e19\u0e49\u0e2d\u0e22"
    ],
    "wof:name":"Ban Kao Noi",
    "wof:placetype":"locality"
},
  "geometry": {"coordinates":[103.25239000000001,15.89678],"type":"Point"}
}