{
  "type": "Feature",
  "properties": {
    "gn:admin1_code":"70.0",
    "gn:asciiname":"Ban Tonyong Bae Ro",
    "gn:country_code":"TH",
    "gn:dem":25,
    "gn:feature_class":"P",
    "gn:feature_code":"PPL",
    "gn:name":"Ban Tonyong Bae Ro",
    "gn:population":0,
    "gn:timezone":"Asia/Bangkok",
    "iso:country":"TH",
    "name:tha_x_preferred":[
        "\u0e1a\u0e49\u0e32\u0e19\u0e15\u0e31\u0e19\u0e2b\u0e22\u0e07\u0e41\u0e1a\u0e40\u0e23\u0e32\u0e30"
    ],
    "wof:name":"Ban Tonyong Bae Ro",
    "wof:placetype":"locality"
},
  "geometry": {"coordinates":[101.22660999999999,6.49483],"type":"Point"}
}