{
  "type": "Feature",
  "properties": {
    "gn:admin1_code":"28",
    "gn:asciiname":"Ban Phluang Noi",
    "gn:country_code":"TH",
    "gn:dem":174,
    "gn:feature_class":"P",
    "gn:feature_code":"PPL",
    "gn:name":"Ban Phluang Noi",
    "gn:population":0,
    "gn:timezone":"Asia/Bangkok",
    "iso:country":"TH",
    "name:tha_x_preferred":[
        "\u0e1a\u0e49\u0e32\u0e19\u0e1e\u0e25\u0e27\u0e07\u0e19\u0e49\u0e2d\u0e22"
    ],
    "wof:name":"Ban Phluang Noi",
    "wof:placetype":"locality"
},
  "geometry": {"coordinates":[103.16103,14.95153],"type":"Point"}
}