{
  "type": "Feature",
  "properties": {
    "gn:admin1_code":"35.0",
    "gn:asciiname":"Ban Don Krathum",
    "gn:country_code":"TH",
    "gn:dem":8,
    "gn:feature_class":"P",
    "gn:feature_code":"PPL",
    "gn:name":"Ban Don Krathum",
    "gn:population":0,
    "gn:timezone":"Asia/Bangkok",
    "iso:country":"TH",
    "name:tha_x_preferred":[
        "\u0e1a\u0e49\u0e32\u0e19\u0e14\u0e2d\u0e19\u0e01\u0e23\u0e30\u0e17\u0e38\u0e48\u0e21"
    ],
    "name:und_x_variant":[
        "Ban Don Kathum",
        "Ban Don Krathum"
    ],
    "wof:name":"Ban Don Krathum",
    "wof:placetype":"locality"
},
  "geometry": {"coordinates":[100.2565,14.50275],"type":"Point"}
}