{
  "type": "Feature",
  "properties": {
    "gn:admin1_code":"20.0",
    "gn:asciiname":"Ban Ba Yao Yai",
    "gn:country_code":"TH",
    "gn:dem":173,
    "gn:feature_class":"P",
    "gn:feature_code":"PPL",
    "gn:name":"Ban Ba Yao Yai",
    "gn:population":0,
    "gn:timezone":"Asia/Bangkok",
    "iso:country":"TH",
    "name:tha_x_preferred":[
        "\u0e1a\u0e49\u0e32\u0e19\u0e1a\u0e30\u0e22\u0e32\u0e27\u0e43\u0e2b\u0e0d\u0e48"
    ],
    "name:und_x_variant":[
        "Ban Ba Yao"
    ],
    "wof:name":"Ban Ba Yao Yai",
    "wof:placetype":"locality"
},
  "geometry": {"coordinates":[103.9515,17.48958],"type":"Point"}
}