{
  "type": "Feature",
  "properties": {
    "gn:admin1_code":"53.0",
    "gn:asciiname":"Ban Huai Duan",
    "gn:country_code":"TH",
    "gn:dem":14,
    "gn:feature_class":"P",
    "gn:feature_code":"PPL",
    "gn:name":"Ban Huai Duan",
    "gn:population":0,
    "gn:timezone":"Asia/Bangkok",
    "iso:country":"TH",
    "name:tha_x_preferred":[
        "Ban Huai Duan"
    ],
    "name:tha_x_variant":[
        "\u0e1a\u0e49\u0e32\u0e19\u0e2b\u0e49\u0e27\u0e22\u0e14\u0e49\u0e27\u0e19"
    ],
    "wof:name":"Ban Huai Duan",
    "wof:placetype":"locality"
},
  "geometry": {"coordinates":[99.94314,14.01103],"type":"Point"}
}