{
  "type": "Feature",
  "properties": {
    "iso:country":"TH",
    "qs:name":"Ban Len",
    "qs:name_adm0":"Thailand",
    "qs:name_adm1":"Phra Nakhon Si Ayutthaya",
    "qs:photos":130,
    "qs:photos_1k":26,
    "qs:photos_9k":1,
    "qs:photos_9r":3,
    "qs:photos_all":130,
    "qs:photos_sr":3,
    "qs:placetype":"Town",
    "qs:pop_sr":"0",
    "wof:name":"Ban Len",
    "wof:placetype":"locality"
},
  "geometry": {"coordinates":[100.577049,14.228352],"type":"Point"}
}