{
  "type": "Feature",
  "properties": {
    "gn:admin1_code":"53.0",
    "gn:asciiname":"Ban Wa En",
    "gn:country_code":"TH",
    "gn:dem":11,
    "gn:feature_class":"P",
    "gn:feature_code":"PPL",
    "gn:name":"Ban Wa En",
    "gn:population":0,
    "gn:timezone":"Asia/Bangkok",
    "iso:country":"TH",
    "name:tha_x_preferred":[
        "Ban Wa En"
    ],
    "name:tha_x_variant":[
        "\u0e1a\u0e49\u0e32\u0e19\u0e2b\u0e27\u0e49\u0e32\u0e40\u0e2d\u0e19"
    ],
    "wof:name":"Ban Wa En",
    "wof:placetype":"locality"
},
  "geometry": {"coordinates":[99.96322000000001,13.8315],"type":"Point"}
}