{
  "type": "Feature",
  "properties": {
    "gn:admin1_code":"42.0",
    "gn:asciiname":"Ban Khlong Lum Bua",
    "gn:country_code":"TH",
    "gn:dem":4,
    "gn:feature_class":"P",
    "gn:feature_code":"PPL",
    "gn:name":"Ban Khlong Lum Bua",
    "gn:population":0,
    "gn:timezone":"Asia/Bangkok",
    "iso:country":"TH",
    "name:tha_x_preferred":[
        "\u0e1a\u0e49\u0e32\u0e19\u0e04\u0e25\u0e2d\u0e07\u0e2b\u0e25\u0e38\u0e21\u0e1a\u0e31\u0e27"
    ],
    "wof:name":"Ban Khlong Lum Bua",
    "wof:placetype":"locality"
},
  "geometry": {"coordinates":[100.66775,13.64061],"type":"Point"}
}