{
  "type": "Feature",
  "properties": {
    "gn:admin1_code":"25.0",
    "gn:asciiname":"Ban Thep Prasit",
    "gn:country_code":"TH",
    "gn:dem":171,
    "gn:feature_class":"P",
    "gn:feature_code":"PPL",
    "gn:name":"Ban Thep Prasit",
    "gn:population":0,
    "gn:timezone":"Asia/Bangkok",
    "iso:country":"TH",
    "name:tha_x_preferred":[
        "\u0e1a\u0e49\u0e32\u0e19\u0e40\u0e17\u0e1e\u0e1b\u0e23\u0e30\u0e2a\u0e34\u0e17\u0e18\u0e34\u0e4c"
    ],
    "wof:name":"Ban Thep Prasit",
    "wof:placetype":"locality"
},
  "geometry": {"coordinates":[103.73303,16.38731],"type":"Point"}
}