{
  "type": "Feature",
  "properties": {
    "gn:admin1_code":"58.0",
    "gn:asciiname":"Ban Thong Kho",
    "gn:country_code":"TH",
    "gn:dem":21,
    "gn:feature_class":"P",
    "gn:feature_code":"PPL",
    "gn:name":"Ban Thong Kho",
    "gn:population":0,
    "gn:timezone":"Asia/Bangkok",
    "iso:country":"TH",
    "name:tha_x_preferred":[
        "\u0e1a\u0e49\u0e32\u0e19\u0e17\u0e2d\u0e07\u0e42\u0e02"
    ],
    "name:und_x_variant":[
        "Ban Thong Khok"
    ],
    "wof:name":"Ban Thong Kho",
    "wof:placetype":"locality"
},
  "geometry": {"coordinates":[99.17331,10.03872],"type":"Point"}
}