{
  "type": "Feature",
  "properties": {
    "gn:admin1_code":"18.0",
    "gn:asciiname":"Ban Na I Loet",
    "gn:country_code":"TH",
    "gn:dem":266,
    "gn:feature_class":"P",
    "gn:feature_code":"PPL",
    "gn:name":"Ban Na I Loet",
    "gn:population":0,
    "gn:timezone":"Asia/Bangkok",
    "iso:country":"TH",
    "name:tha_x_preferred":[
        "Ban Na I Loet"
    ],
    "name:tha_x_variant":[
        "\u0e1a\u0e49\u0e32\u0e19\u0e19\u0e32\u0e2d\u0e35\u0e40\u0e25\u0e34\u0e28"
    ],
    "wof:name":"Ban Na I Loet",
    "wof:placetype":"locality"
},
  "geometry": {"coordinates":[101.74206,17.29711],"type":"Point"}
}