{
  "type": "Feature",
  "properties": {
    "gn:admin1_code":"44.0",
    "gn:asciiname":"Ban Phong Krathin",
    "gn:country_code":"TH",
    "gn:dem":5,
    "gn:feature_class":"P",
    "gn:feature_code":"PPL",
    "gn:name":"Ban Phong Krathin",
    "gn:population":0,
    "gn:timezone":"Asia/Bangkok",
    "iso:country":"TH",
    "name:tha_x_preferred":[
        "\u0e1a\u0e49\u0e32\u0e19\u0e1e\u0e07\u0e01\u0e23\u0e30\u0e16\u0e34\u0e19"
    ],
    "name:und_x_variant":[
        "Ban Phrong Kathin"
    ],
    "wof:name":"Ban Phong Krathin",
    "wof:placetype":"locality"
},
  "geometry": {"coordinates":[101.10153,13.78461],"type":"Point"}
}