{
  "type": "Feature",
  "properties": {
    "gn:admin1_code":"30.0",
    "gn:asciiname":"Ban Prue Khan Tai",
    "gn:country_code":"TH",
    "gn:dem":169,
    "gn:feature_class":"P",
    "gn:feature_code":"PPL",
    "gn:name":"Ban Prue Khan Tai",
    "gn:population":0,
    "gn:timezone":"Asia/Bangkok",
    "iso:country":"TH",
    "name:tha_x_preferred":[
        "\u0e1a\u0e49\u0e32\u0e19\u0e1b\u0e23\u0e37\u0e2d\u0e01\u0e31\u0e19\u0e43\u0e15\u0e49"
    ],
    "wof:name":"Ban Prue Khan Tai",
    "wof:placetype":"locality"
},
  "geometry": {"coordinates":[104.22375,14.61872],"type":"Point"}
}