{
  "type": "Feature",
  "properties": {
    "gn:admin1_code":"66.0",
    "gn:asciiname":"Ban Khuan Pring",
    "gn:country_code":"TH",
    "gn:dem":28,
    "gn:feature_class":"P",
    "gn:feature_code":"PPL",
    "gn:name":"Ban Khuan Pring",
    "gn:population":0,
    "gn:timezone":"Asia/Bangkok",
    "iso:country":"TH",
    "name:tha_x_preferred":[
        "\u0e1a\u0e49\u0e32\u0e19\u0e04\u0e27\u0e19\u0e1b\u0e23\u0e34\u0e07"
    ],
    "name:und_x_variant":[
        "Ban Khuan Pling"
    ],
    "wof:name":"Ban Khuan Pring",
    "wof:placetype":"locality"
},
  "geometry": {"coordinates":[99.982,7.69317],"type":"Point"}
}