{
  "type": "Feature",
  "properties": {
    "gn:admin1_code":"49.0",
    "gn:asciiname":"Ban Bang Kradan",
    "gn:country_code":"TH",
    "gn:dem":12,
    "gn:feature_class":"P",
    "gn:feature_code":"PPL",
    "gn:name":"Ban Bang Kradan",
    "gn:population":0,
    "gn:timezone":"Asia/Bangkok",
    "iso:country":"TH",
    "name:tha_x_preferred":[
        "\u0e1a\u0e49\u0e32\u0e19\u0e1a\u0e32\u0e07\u0e01\u0e23\u0e30\u0e14\u0e32\u0e19"
    ],
    "name:und_x_variant":[
        "Kradan",
        "Ban Bang Kadan",
        "Ban Bang Kradan"
    ],
    "wof:name":"Ban Bang Kradan",
    "wof:placetype":"locality"
},
  "geometry": {"coordinates":[102.28653,12.25914],"type":"Point"}
}