{
  "type": "Feature",
  "properties": {
    "gn:admin1_code":"1.0",
    "gn:asciiname":"Ban Pha Khui Hae",
    "gn:country_code":"TH",
    "gn:dem":148,
    "gn:feature_class":"P",
    "gn:feature_code":"PPL",
    "gn:name":"Ban Pha Khui Hae",
    "gn:population":0,
    "gn:timezone":"Asia/Bangkok",
    "iso:country":"TH",
    "name:tha_x_preferred":[
        "\u0e1a\u0e49\u0e32\u0e19\u0e1e\u0e30\u0e04\u0e38\u0e22\u0e41\u0e2e"
    ],
    "wof:name":"Ban Pha Khui Hae",
    "wof:placetype":"locality"
},
  "geometry": {"coordinates":[97.70189000000001,17.85417],"type":"Point"}
}