{
  "type": "Feature",
  "properties": {
    "gn:admin1_code":"22",
    "gn:asciiname":"Ban Samran Hin Lat",
    "gn:country_code":"TH",
    "gn:dem":202,
    "gn:feature_class":"P",
    "gn:feature_code":"PPL",
    "gn:name":"Ban Samran Hin Lat",
    "gn:population":0,
    "gn:timezone":"Asia/Bangkok",
    "iso:country":"TH",
    "name:tha_x_preferred":[
        "\u0e1a\u0e49\u0e32\u0e19\u0e2a\u0e33\u0e23\u0e32\u0e0d\u0e2b\u0e34\u0e19\u0e25\u0e32\u0e14"
    ],
    "wof:name":"Ban Samran Hin Lat",
    "wof:placetype":"locality"
},
  "geometry": {"coordinates":[102.31274999999999,16.48414],"type":"Point"}
}