{
  "type": "Feature",
  "properties": {
    "gn:admin1_code":"0.0",
    "gn:asciiname":"Ban Kaeng Pla Pok",
    "gn:country_code":"TH",
    "gn:dem":344,
    "gn:feature_class":"P",
    "gn:feature_code":"PPL",
    "gn:name":"Ban Kaeng Pla Pok",
    "gn:population":0,
    "gn:timezone":"Asia/Bangkok",
    "iso:country":"TH",
    "wof:name":"Ban Kaeng Pla Pok",
    "wof:placetype":"locality"
},
  "geometry": {"coordinates":[101.81667,17.78333],"type":"Point"}
}