{
  "type": "Feature",
  "properties": {
    "gn:admin1_code":"2.0",
    "gn:asciiname":"Ban Ton Phueng",
    "gn:country_code":"TH",
    "gn:dem":334,
    "gn:feature_class":"P",
    "gn:feature_code":"PPL",
    "gn:name":"Ban Ton Phueng",
    "gn:population":0,
    "gn:timezone":"Asia/Bangkok",
    "iso:country":"TH",
    "name:tha_x_preferred":[
        "\u0e1a\u0e49\u0e32\u0e19\u0e15\u0e49\u0e19\u0e1c\u0e36\u0e49\u0e07"
    ],
    "wof:name":"Ban Ton Phueng",
    "wof:placetype":"locality"
},
  "geometry": {"coordinates":[99.18128,18.80536],"type":"Point"}
}