{
  "type": "Feature",
  "properties": {
    "gn:admin1_code":"14.0",
    "gn:asciiname":"Ban Prong Sawong",
    "gn:country_code":"TH",
    "gn:dem":133,
    "gn:feature_class":"P",
    "gn:feature_code":"PPL",
    "gn:name":"Ban Prong Sawong",
    "gn:population":0,
    "gn:timezone":"Asia/Bangkok",
    "iso:country":"TH",
    "name:tha_x_preferred":[
        "\u0e1a\u0e49\u0e32\u0e19\u0e42\u0e1b\u0e23\u0e48\u0e07\u0e2a\u0e27\u0e2d\u0e07"
    ],
    "wof:name":"Ban Prong Sawong",
    "wof:placetype":"locality"
},
  "geometry": {"coordinates":[100.86944,15.84336],"type":"Point"}
}