{
  "type": "Feature",
  "properties": {
    "gn:admin1_code":"8.0",
    "gn:asciiname":"Ban Mae Ok Pha Ru",
    "gn:country_code":"TH",
    "gn:dem":148,
    "gn:feature_class":"P",
    "gn:feature_code":"PPL",
    "gn:name":"Ban Mae Ok Pha Ru",
    "gn:population":0,
    "gn:timezone":"Asia/Bangkok",
    "iso:country":"TH",
    "name:tha_x_preferred":[
        "\u0e1a\u0e49\u0e32\u0e19\u0e41\u0e21\u0e48\u0e2d\u0e2d\u0e01\u0e1c\u0e32\u0e23\u0e39"
    ],
    "wof:name":"Ban Mae Ok Pha Ru",
    "wof:placetype":"locality"
},
  "geometry": {"coordinates":[98.32167,17.10261],"type":"Point"}
}