{
  "type": "Feature",
  "properties": {
    "gn:admin1_code":"60.0",
    "gn:asciiname":"Ban Nikhom Ha",
    "gn:country_code":"TH",
    "gn:dem":36,
    "gn:feature_class":"P",
    "gn:feature_code":"PPL",
    "gn:name":"Ban Nikhom Ha",
    "gn:population":0,
    "gn:timezone":"Asia/Bangkok",
    "iso:country":"TH",
    "name:tha_x_preferred":[
        "\u0e1a\u0e49\u0e32\u0e19\u0e19\u0e34\u0e04\u0e21 \u0e2b\u0e49\u0e32"
    ],
    "wof:name":"Ban Nikhom Ha",
    "wof:placetype":"locality"
},
  "geometry": {"coordinates":[99.0945,8.54906],"type":"Point"}
}