{
  "type": "Feature",
  "properties": {
    "gn:admin1_code":"30.0",
    "gn:asciiname":"Ban Huai Chan",
    "gn:country_code":"TH",
    "gn:dem":231,
    "gn:feature_class":"P",
    "gn:feature_code":"PPL",
    "gn:name":"Ban Huai Chan",
    "gn:population":0,
    "gn:timezone":"Asia/Bangkok",
    "iso:country":"TH",
    "name:tha_x_preferred":[
        "\u0e1a\u0e49\u0e32\u0e19\u0e2b\u0e49\u0e27\u0e22\u0e08\u0e31\u0e19\u0e17\u0e23\u0e4c"
    ],
    "wof:name":"Ban Huai Chan",
    "wof:placetype":"locality"
},
  "geometry": {"coordinates":[104.37533000000001,14.52722],"type":"Point"}
}