{
  "type": "Feature",
  "properties": {
    "gn:admin1_code":"27",
    "gn:asciiname":"Ban Kham Ngam",
    "gn:country_code":"TH",
    "gn:dem":163,
    "gn:feature_class":"P",
    "gn:feature_code":"PPL",
    "gn:name":"Ban Kham Ngam",
    "gn:population":0,
    "gn:timezone":"Asia/Bangkok",
    "iso:country":"TH",
    "name:tha_x_preferred":[
        "\u0e1a\u0e49\u0e32\u0e19\u0e02\u0e32\u0e21\u0e07\u0e32\u0e21"
    ],
    "wof:name":"Ban Kham Ngam",
    "wof:placetype":"locality"
},
  "geometry": {"coordinates":[102.38417,15.15817],"type":"Point"}
}