{
  "type": "Feature",
  "properties": {
    "iso:country":"TH",
    "qs:name":"Satorn Khwaeng",
    "qs:name_adm0":"Thailand",
    "qs:name_adm1":"Bangkok",
    "qs:photos":1868,
    "qs:photos_1k":379,
    "qs:photos_9k":8,
    "qs:photos_9r":9,
    "qs:photos_all":1868,
    "qs:photos_sr":15,
    "qs:placetype":"Suburb",
    "qs:pop_sr":"0",
    "wof:name":"Satorn Khwaeng",
    "wof:placetype":"neighbourhood"
},
  "geometry": {"coordinates":[100.531082,13.723209],"type":"Point"}
}