{
  "type": "Feature",
  "properties": {
    "gn:admin1_code":"64.0",
    "gn:asciiname":"Ban Plai Mueang",
    "gn:country_code":"TH",
    "gn:dem":7,
    "gn:feature_class":"P",
    "gn:feature_code":"PPL",
    "gn:name":"Ban Plai Mueang",
    "gn:population":0,
    "gn:timezone":"Asia/Bangkok",
    "iso:country":"TH",
    "name:tha_x_preferred":[
        "\u0e1a\u0e49\u0e32\u0e19\u0e1b\u0e25\u0e32\u0e22\u0e40\u0e2b\u0e21\u0e37\u0e2d\u0e07"
    ],
    "wof:name":"Ban Plai Mueang",
    "wof:placetype":"locality"
},
  "geometry": {"coordinates":[100.02236000000001,7.89022],"type":"Point"}
}