{
  "type": "Feature",
  "properties": {
    "gn:admin1_code":"67.0",
    "gn:asciiname":"Ban Phang 34",
    "gn:country_code":"TH",
    "gn:dem":29,
    "gn:feature_class":"P",
    "gn:feature_code":"PPL",
    "gn:name":"Ban Phang 34",
    "gn:population":0,
    "gn:timezone":"Asia/Bangkok",
    "iso:country":"TH",
    "name:tha_x_preferred":[
        "Ban Phang 34"
    ],
    "name:tha_x_variant":[
        "\u0e1a\u0e49\u0e32\u0e19\u0e1c\u0e31\u0e07 \u0e2a\u0e32\u0e21\u0e2a\u0e34\u0e1a \u0e2a\u0e35\u0e48",
        "Ban Phang Sam Sip Si"
    ],
    "wof:name":"Ban Phang 34",
    "wof:placetype":"locality"
},
  "geometry": {"coordinates":[99.91253,6.88022],"type":"Point"}
}