{
  "type": "Feature",
  "properties": {
    "gn:admin1_code":"57.0",
    "gn:asciiname":"Ban Si Yaek Ban Krut",
    "gn:country_code":"TH",
    "gn:dem":54,
    "gn:feature_class":"P",
    "gn:feature_code":"PPL",
    "gn:name":"Ban Si Yaek Ban Krut",
    "gn:population":0,
    "gn:timezone":"Asia/Bangkok",
    "iso:country":"TH",
    "name:tha_x_preferred":[
        "\u0e1a\u0e49\u0e32\u0e19\u0e2a\u0e35\u0e48\u0e41\u0e22\u0e01\u0e1a\u0e49\u0e32\u0e19\u0e01\u0e23\u0e39\u0e14"
    ],
    "wof:name":"Ban Si Yaek Ban Krut",
    "wof:placetype":"locality"
},
  "geometry": {"coordinates":[99.50594,11.38231],"type":"Point"}
}