{
  "type": "Feature",
  "properties": {
    "gn:admin1_code":"8.0",
    "gn:asciiname":"Ban Khun Huai Mae Sot",
    "gn:country_code":"TH",
    "gn:dem":396,
    "gn:feature_class":"P",
    "gn:feature_code":"PPL",
    "gn:name":"Ban Khun Huai Mae Sot",
    "gn:population":0,
    "gn:timezone":"Asia/Bangkok",
    "iso:country":"TH",
    "name:tha_x_preferred":[
        "\u0e1a\u0e49\u0e32\u0e19\u0e02\u0e38\u0e19\u0e2b\u0e49\u0e27\u0e22\u0e41\u0e21\u0e48\u0e2a\u0e2d\u0e14"
    ],
    "wof:name":"Ban Khun Huai Mae Sot",
    "wof:placetype":"locality"
},
  "geometry": {"coordinates":[98.66267000000001,16.71917],"type":"Point"}
}