{
  "type": "Feature",
  "properties": {
    "gn:admin1_code":"33",
    "gn:asciiname":"Ban Tha Choeng Ai",
    "gn:country_code":"TH",
    "gn:dem":12,
    "gn:feature_class":"P",
    "gn:feature_code":"PPL",
    "gn:name":"Ban Tha Choeng Ai",
    "gn:population":0,
    "gn:timezone":"Asia/Bangkok",
    "iso:country":"TH",
    "name:tha_x_preferred":[
        "\u0e1a\u0e49\u0e32\u0e19\u0e17\u0e48\u0e32\u0e40\u0e0a\u0e34\u0e07\u0e2d\u0e49\u0e32\u0e22"
    ],
    "wof:name":"Ban Tha Choeng Ai",
    "wof:placetype":"locality"
},
  "geometry": {"coordinates":[100.32514,14.95794],"type":"Point"}
}