{
  "type": "Feature",
  "properties": {
    "gn:admin1_code":"16.0",
    "gn:asciiname":"Ban Ta Khli",
    "gn:country_code":"TH",
    "gn:dem":83,
    "gn:feature_class":"P",
    "gn:feature_code":"PPL",
    "gn:name":"Ban Ta Khli",
    "gn:population":0,
    "gn:timezone":"Asia/Bangkok",
    "iso:country":"TH",
    "name:tha_x_preferred":[
        "\u0e1a\u0e49\u0e32\u0e19\u0e15\u0e32\u0e04\u0e25\u0e35"
    ],
    "wof:name":"Ban Ta Khli",
    "wof:placetype":"locality"
},
  "geometry": {"coordinates":[99.66933,15.75817],"type":"Point"}
}