{
  "type": "Feature",
  "properties": {
    "gn:admin1_code":"2.0",
    "gn:asciiname":"Ban Phra That",
    "gn:country_code":"TH",
    "gn:dem":348,
    "gn:feature_class":"P",
    "gn:feature_code":"PPL",
    "gn:name":"Ban Phra That",
    "gn:population":0,
    "gn:timezone":"Asia/Bangkok",
    "iso:country":"TH",
    "name:tha_x_preferred":[
        "\u0e1a\u0e49\u0e32\u0e19\u0e1e\u0e23\u0e30\u0e18\u0e32\u0e15\u0e38"
    ],
    "wof:name":"Ban Phra That",
    "wof:placetype":"locality"
},
  "geometry": {"coordinates":[98.98560999999999,19.04158],"type":"Point"}
}