{
  "type": "Feature",
  "properties": {
    "gn:admin1_code":"26.0",
    "gn:asciiname":"Ban Nong Pla",
    "gn:country_code":"TH",
    "gn:dem":224,
    "gn:feature_class":"P",
    "gn:feature_code":"PPL",
    "gn:name":"Ban Nong Pla",
    "gn:population":0,
    "gn:timezone":"Asia/Bangkok",
    "iso:country":"TH",
    "name:tha_x_preferred":[
        "\u0e1a\u0e49\u0e32\u0e19\u0e2b\u0e19\u0e2d\u0e07\u0e1b\u0e25\u0e32"
    ],
    "wof:name":"Ban Nong Pla",
    "wof:placetype":"locality"
},
  "geometry": {"coordinates":[102.10863999999999,16.48864],"type":"Point"}
}