{
  "type": "Feature",
  "properties": {
    "gn:admin1_code":"78.0",
    "gn:asciiname":"Ban Kham Chiang Sa",
    "gn:country_code":"TH",
    "gn:dem":181,
    "gn:feature_class":"P",
    "gn:feature_code":"PPL",
    "gn:name":"Ban Kham Chiang Sa",
    "gn:population":0,
    "gn:timezone":"Asia/Bangkok",
    "iso:country":"TH",
    "name:tha_x_preferred":[
        "Ban Kham Chiang Sa"
    ],
    "name:tha_x_variant":[
        "\u0e1a\u0e49\u0e32\u0e19\u0e04\u0e33\u0e40\u0e0a\u0e35\u0e22\u0e07\u0e2a\u0e32"
    ],
    "wof:lang_x_official":[
        "tha"
    ],
    "wof:lang_x_spoken":[
        "tha"
    ],
    "wof:name":"Ban Kham Chiang Sa",
    "wof:placetype":"locality"
},
  "geometry": {"coordinates":[104.63030999999999,16.27508],"type":"Point"}
}