{
  "type": "Feature",
  "properties": {
    "gn:admin1_code":"70.0",
    "gn:asciiname":"Ban Lam Phaya",
    "gn:country_code":"TH",
    "gn:dem":468,
    "gn:feature_class":"P",
    "gn:feature_code":"PPL",
    "gn:name":"Ban Lam Phaya",
    "gn:population":0,
    "gn:timezone":"Asia/Bangkok",
    "iso:country":"TH",
    "name:tha_x_preferred":[
        "\u0e1a\u0e49\u0e32\u0e19\u0e25\u0e33\u0e1e\u0e0d\u0e32"
    ],
    "wof:name":"Ban Lam Phaya",
    "wof:placetype":"locality"
},
  "geometry": {"coordinates":[101.15136,6.09878],"type":"Point"}
}