{
  "type": "Feature",
  "properties": {
    "gn:admin1_code":"6.0",
    "gn:asciiname":"Ban Na Bon Lai Tha",
    "gn:country_code":"TH",
    "gn:dem":237,
    "gn:feature_class":"P",
    "gn:feature_code":"PPL",
    "gn:name":"Ban Na Bon Lai Tha",
    "gn:population":0,
    "gn:timezone":"Asia/Bangkok",
    "iso:country":"TH",
    "name:tha_x_preferred":[
        "\u0e1a\u0e49\u0e32\u0e19\u0e19\u0e32\u0e1a\u0e2d\u0e19\u0e2b\u0e25\u0e48\u0e32\u0e22\u0e17\u0e48\u0e32"
    ],
    "wof:name":"Ban Na Bon Lai Tha",
    "wof:placetype":"locality"
},
  "geometry": {"coordinates":[99.25418999999999,18.06594],"type":"Point"}
}