{
  "type": "Feature",
  "properties": {
    "gn:admin1_code":"78.0",
    "gn:asciiname":"Ban Pong Daeng",
    "gn:country_code":"TH",
    "gn:dem":177,
    "gn:feature_class":"P",
    "gn:feature_code":"PPL",
    "gn:name":"Ban Pong Daeng",
    "gn:population":0,
    "gn:timezone":"Asia/Bangkok",
    "iso:country":"TH",
    "name:tha_x_preferred":[
        "\u0e1a\u0e49\u0e32\u0e19\u0e1b\u0e48\u0e07\u0e41\u0e14\u0e07"
    ],
    "name:und_x_variant":[
        "Ban Pong Taeng",
        "Ban Pong Daeng"
    ],
    "wof:name":"Ban Pong Daeng",
    "wof:placetype":"locality"
},
  "geometry": {"coordinates":[104.57758,16.42233],"type":"Point"}
}