{
  "type": "Feature",
  "properties": {
    "gn:admin1_code":"72.0",
    "gn:asciiname":"Ban Tat Hai",
    "gn:country_code":"TH",
    "gn:dem":171,
    "gn:feature_class":"P",
    "gn:feature_code":"PPL",
    "gn:name":"Ban Tat Hai",
    "gn:population":0,
    "gn:timezone":"Asia/Bangkok",
    "iso:country":"TH",
    "name:tha_x_preferred":[
        "\u0e1a\u0e49\u0e32\u0e19\u0e15\u0e32\u0e14\u0e44\u0e2e"
    ],
    "wof:name":"Ban Tat Hai",
    "wof:placetype":"locality"
},
  "geometry": {"coordinates":[104.46789,16.03339],"type":"Point"}
}