{
  "type": "Feature",
  "properties": {
    "gn:admin1_code":"68.0",
    "gn:asciiname":"Ban Lam Pao Tok",
    "gn:country_code":"TH",
    "gn:dem":18,
    "gn:feature_class":"P",
    "gn:feature_code":"PPL",
    "gn:name":"Ban Lam Pao Tok",
    "gn:population":0,
    "gn:timezone":"Asia/Bangkok",
    "iso:country":"TH",
    "name:tha_x_preferred":[
        "\u0e1a\u0e49\u0e32\u0e19\u0e25\u0e33\u0e40\u0e1b\u0e32\u0e15\u0e01"
    ],
    "wof:name":"Ban Lam Pao Tok",
    "wof:placetype":"locality"
},
  "geometry": {"coordinates":[100.93431,6.70075],"type":"Point"}
}