{
  "type": "Feature",
  "properties": {
    "gn:admin1_code":"23.0",
    "gn:asciiname":"Ban Kham Plafa",
    "gn:country_code":"TH",
    "gn:dem":197,
    "gn:feature_class":"P",
    "gn:feature_code":"PPL",
    "gn:name":"Ban Kham Plafa",
    "gn:population":0,
    "gn:timezone":"Asia/Bangkok",
    "iso:country":"TH",
    "name:tha_x_preferred":[
        "\u0e1a\u0e49\u0e32\u0e19\u0e04\u0e33\u0e1b\u0e25\u0e32\u0e1d\u0e32"
    ],
    "wof:name":"Ban Kham Plafa",
    "wof:placetype":"locality"
},
  "geometry": {"coordinates":[103.55806,16.62747],"type":"Point"}
}