{
  "type": "Feature",
  "properties": {
    "gn:admin1_code":"30.0",
    "gn:asciiname":"Ban Non Wan Fai",
    "gn:country_code":"TH",
    "gn:dem":144,
    "gn:feature_class":"P",
    "gn:feature_code":"PPL",
    "gn:name":"Ban Non Wan Fai",
    "gn:population":0,
    "gn:timezone":"Asia/Bangkok",
    "iso:country":"TH",
    "name:tha_x_preferred":[
        "\u0e1a\u0e49\u0e32\u0e19\u0e42\u0e19\u0e19\u0e2b\u0e27\u0e48\u0e32\u0e19\u0e44\u0e1f"
    ],
    "wof:name":"Ban Non Wan Fai",
    "wof:placetype":"locality"
},
  "geometry": {"coordinates":[104.71517,14.82036],"type":"Point"}
}