{
  "type": "Feature",
  "properties": {
    "gn:admin1_code":"29",
    "gn:asciiname":"Ban Nong Phak Waen",
    "gn:country_code":"TH",
    "gn:dem":142,
    "gn:feature_class":"P",
    "gn:feature_code":"PPL",
    "gn:name":"Ban Nong Phak Waen",
    "gn:population":0,
    "gn:timezone":"Asia/Bangkok",
    "iso:country":"TH",
    "name:tha_x_preferred":[
        "\u0e1a\u0e49\u0e32\u0e19\u0e2b\u0e19\u0e2d\u0e07\u0e1c\u0e31\u0e01\u0e41\u0e27\u0e48\u0e19"
    ],
    "wof:name":"Ban Nong Phak Waen",
    "wof:placetype":"locality"
},
  "geometry": {"coordinates":[103.86133,14.86494],"type":"Point"}
}