{
  "type": "Feature",
  "properties": {
    "gn:admin1_code":"2.0",
    "gn:asciiname":"Ban Pa Kluai",
    "gn:country_code":"TH",
    "gn:dem":299,
    "gn:feature_class":"P",
    "gn:feature_code":"PPL",
    "gn:name":"Ban Pa Kluai",
    "gn:population":0,
    "gn:timezone":"Asia/Bangkok",
    "iso:country":"TH",
    "name:tha_x_preferred":[
        "\u0e1a\u0e49\u0e32\u0e19\u0e1b\u0e48\u0e32\u0e01\u0e25\u0e49\u0e27\u0e22"
    ],
    "wof:name":"Ban Pa Kluai",
    "wof:placetype":"locality"
},
  "geometry": {"coordinates":[99.06072,18.72408],"type":"Point"}
}