{
  "type": "Feature",
  "properties": {
    "gn:admin1_code":"8.0",
    "gn:asciiname":"Ban Pre Lu",
    "gn:country_code":"TH",
    "gn:dem":669,
    "gn:feature_class":"P",
    "gn:feature_code":"PPL",
    "gn:name":"Ban Pre Lu",
    "gn:population":0,
    "gn:timezone":"Asia/Bangkok",
    "iso:country":"TH",
    "name:tha_x_preferred":[
        "\u0e1a\u0e49\u0e32\u0e19\u0e40\u0e1b\u0e23\u0e49\u0e25\u0e39\u0e48"
    ],
    "wof:name":"Ban Pre Lu",
    "wof:placetype":"locality"
},
  "geometry": {"coordinates":[98.27131,17.45747],"type":"Point"}
}