{
  "type": "Feature",
  "properties": {
    "gn:admin1_code":"37.0",
    "gn:asciiname":"Ban Nong Krot",
    "gn:country_code":"TH",
    "gn:dem":37,
    "gn:feature_class":"P",
    "gn:feature_code":"PPL",
    "gn:name":"Ban Nong Krot",
    "gn:population":0,
    "gn:timezone":"Asia/Bangkok",
    "iso:country":"TH",
    "name:tha_x_preferred":[
        "\u0e1a\u0e49\u0e32\u0e19\u0e2b\u0e19\u0e2d\u0e07\u0e01\u0e23\u0e14"
    ],
    "name:und_x_variant":[
        "Ban Hnong Krod",
        "Ban Nong Krot",
        "B\u0101n Hnong Kro",
        "Ban Nong Kot"
    ],
    "wof:lang_x_official":[
        "tha"
    ],
    "wof:lang_x_spoken":[
        "tha"
    ],
    "wof:name":"Ban Nong Krot",
    "wof:placetype":"locality"
},
  "geometry": {"coordinates":[101.07919,14.77883],"type":"Point"}
}