{
  "type": "Feature",
  "properties": {
    "gn:admin1_code":"60.0",
    "gn:asciiname":"Ban Thang Kham",
    "gn:country_code":"TH",
    "gn:dem":31,
    "gn:feature_class":"P",
    "gn:feature_code":"PPL",
    "gn:name":"Ban Thang Kham",
    "gn:population":0,
    "gn:timezone":"Asia/Bangkok",
    "iso:country":"TH",
    "name:tha_x_preferred":[
        "\u0e1a\u0e49\u0e32\u0e19\u0e17\u0e32\u0e07\u0e02\u0e49\u0e32\u0e21"
    ],
    "wof:name":"Ban Thang Kham",
    "wof:placetype":"locality"
},
  "geometry": {"coordinates":[99.34094,8.74883],"type":"Point"}
}