{
  "type": "Feature",
  "properties": {
    "gn:admin1_code":"37",
    "gn:asciiname":"Ban Lam Som Phung",
    "gn:country_code":"TH",
    "gn:dem":212,
    "gn:feature_class":"P",
    "gn:feature_code":"PPL",
    "gn:name":"Ban Lam Som Phung",
    "gn:population":0,
    "gn:timezone":"Asia/Bangkok",
    "iso:country":"TH",
    "name:tha_x_preferred":[
        "\u0e1a\u0e49\u0e32\u0e19\u0e25\u0e33\u0e2a\u0e21\u0e1e\u0e38\u0e07"
    ],
    "wof:name":"Ban Lam Som Phung",
    "wof:placetype":"locality"
},
  "geometry": {"coordinates":[101.42353,14.97061],"type":"Point"}
}