{
  "type": "Feature",
  "properties": {
    "gn:admin1_code":"48.0",
    "gn:asciiname":"Ban Pak Thang Thraektoe",
    "gn:country_code":"TH",
    "gn:dem":22,
    "gn:feature_class":"P",
    "gn:feature_code":"PPL",
    "gn:name":"Ban Pak Thang Thraektoe",
    "gn:population":0,
    "gn:timezone":"Asia/Bangkok",
    "iso:country":"TH",
    "name:tha_x_preferred":[
        "\u0e1a\u0e49\u0e32\u0e19\u0e1b\u0e32\u0e01\u0e17\u0e32\u0e07\u0e41\u0e17\u0e23\u0e01\u0e40\u0e15\u0e2d\u0e23\u0e4c"
    ],
    "wof:name":"Ban Pak Thang Thraektoe",
    "wof:placetype":"locality"
},
  "geometry": {"coordinates":[101.89239000000001,12.73881],"type":"Point"}
}