{
  "type": "Feature",
  "properties": {
    "gn:admin1_code":"3.0",
    "gn:asciiname":"Ban San Makhet",
    "gn:country_code":"TH",
    "gn:dem":563,
    "gn:feature_class":"P",
    "gn:feature_code":"PPL",
    "gn:name":"Ban San Makhet",
    "gn:population":0,
    "gn:timezone":"Asia/Bangkok",
    "iso:country":"TH",
    "name:tha_x_preferred":[
        "\u0e1a\u0e49\u0e32\u0e19\u0e2a\u0e31\u0e19\u0e21\u0e30\u0e40\u0e04\u0e47\u0e14"
    ],
    "wof:name":"Ban San Makhet",
    "wof:placetype":"locality"
},
  "geometry": {"coordinates":[99.52727,19.25125],"type":"Point"}
}