{
  "type": "Feature",
  "properties": {
    "gn:admin1_code":"66.0",
    "gn:asciiname":"Ban Sala Klang Khuan",
    "gn:country_code":"TH",
    "gn:dem":21,
    "gn:feature_class":"P",
    "gn:feature_code":"PPL",
    "gn:name":"Ban Sala Klang Khuan",
    "gn:population":0,
    "gn:timezone":"Asia/Bangkok",
    "iso:country":"TH",
    "name:tha_x_preferred":[
        "\u0e1a\u0e49\u0e32\u0e19\u0e28\u0e32\u0e25\u0e32\u0e01\u0e25\u0e32\u0e07\u0e04\u0e27\u0e19"
    ],
    "wof:name":"Ban Sala Klang Khuan",
    "wof:placetype":"locality"
},
  "geometry": {"coordinates":[100.15183,7.46572],"type":"Point"}
}