{
  "type": "Feature",
  "properties": {
    "gn:admin1_code":"5.0",
    "gn:asciiname":"Ban Wang Pan",
    "gn:country_code":"TH",
    "gn:dem":575,
    "gn:feature_class":"P",
    "gn:feature_code":"PPL",
    "gn:name":"Ban Wang Pan",
    "gn:population":0,
    "gn:timezone":"Asia/Bangkok",
    "iso:country":"TH",
    "name:tha_x_preferred":[
        "\u0e1a\u0e49\u0e32\u0e19\u0e27\u0e31\u0e07\u0e1b\u0e32\u0e19"
    ],
    "wof:name":"Ban Wang Pan",
    "wof:placetype":"locality"
},
  "geometry": {"coordinates":[99.03214,18.039],"type":"Point"}
}