{
  "type": "Feature",
  "properties": {
    "gn:admin1_code":"22",
    "gn:asciiname":"Ban Huai Tham Tao",
    "gn:country_code":"TH",
    "gn:dem":253,
    "gn:feature_class":"P",
    "gn:feature_code":"PPL",
    "gn:name":"Ban Huai Tham Tao",
    "gn:population":0,
    "gn:timezone":"Asia/Bangkok",
    "iso:country":"TH",
    "name:tha_x_preferred":[
        "\u0e1a\u0e49\u0e32\u0e19\u0e2b\u0e49\u0e27\u0e22\u0e16\u0e49\u0e33\u0e40\u0e15\u0e48\u0e32"
    ],
    "wof:name":"Ban Huai Tham Tao",
    "wof:placetype":"locality"
},
  "geometry": {"coordinates":[101.94103,16.67667],"type":"Point"}
}