{
  "type": "Feature",
  "properties": {
    "gn:admin1_code":"30.0",
    "gn:asciiname":"Ban Non I Pang",
    "gn:country_code":"TH",
    "gn:dem":148,
    "gn:feature_class":"P",
    "gn:feature_code":"PPL",
    "gn:name":"Ban Non I Pang",
    "gn:population":0,
    "gn:timezone":"Asia/Bangkok",
    "iso:country":"TH",
    "name:tha_x_preferred":[
        "\u0e1a\u0e49\u0e32\u0e19\u0e42\u0e19\u0e19\u0e2d\u0e35\u0e1b\u0e31\u0e07"
    ],
    "wof:name":"Ban Non I Pang",
    "wof:placetype":"locality"
},
  "geometry": {"coordinates":[104.40075,15.08033],"type":"Point"}
}