{
  "type": "Feature",
  "properties": {
    "gn:admin1_code":"50.0",
    "gn:asciiname":"Ban Ko Sa Doeng",
    "gn:country_code":"TH",
    "gn:dem":230,
    "gn:feature_class":"P",
    "gn:feature_code":"PPL",
    "gn:name":"Ban Ko Sa Doeng",
    "gn:population":0,
    "gn:timezone":"Asia/Bangkok",
    "iso:country":"TH",
    "name:tha_x_preferred":[
        "\u0e1a\u0e49\u0e32\u0e19\u0e40\u0e01\u0e32\u0e30\u0e2a\u0e30\u0e40\u0e14\u0e34\u0e48\u0e07"
    ],
    "name:und_x_variant":[
        "Ban Ko Satoeng"
    ],
    "wof:name":"Ban Ko Sa Doeng",
    "wof:placetype":"locality"
},
  "geometry": {"coordinates":[98.55394,15.20961],"type":"Point"}
}