{
  "type": "Feature",
  "properties": {
    "gn:admin1_code":"46.0",
    "gn:asciiname":"Ban Nong Chek",
    "gn:country_code":"TH",
    "gn:dem":36,
    "gn:feature_class":"P",
    "gn:feature_code":"PPL",
    "gn:name":"Ban Nong Chek",
    "gn:population":0,
    "gn:timezone":"Asia/Bangkok",
    "iso:country":"TH",
    "name:tha_x_preferred":[
        "\u0e1a\u0e49\u0e32\u0e19\u0e2b\u0e19\u0e2d\u0e07\u0e40\u0e08\u0e47\u0e01"
    ],
    "wof:name":"Ban Nong Chek",
    "wof:placetype":"locality"
},
  "geometry": {"coordinates":[101.26192,13.34406],"type":"Point"}
}