{
  "type": "Feature",
  "properties": {
    "gn:admin1_code":"20.0",
    "gn:asciiname":"Ban Klang Mai",
    "gn:country_code":"TH",
    "gn:dem":177,
    "gn:feature_class":"P",
    "gn:feature_code":"PPL",
    "gn:name":"Ban Klang Mai",
    "gn:population":0,
    "gn:timezone":"Asia/Bangkok",
    "iso:country":"TH",
    "name:tha_x_preferred":[
        "\u0e1a\u0e49\u0e32\u0e19\u0e01\u0e25\u0e32\u0e07\u0e43\u0e2b\u0e21\u0e48"
    ],
    "wof:name":"Ban Klang Mai",
    "wof:placetype":"locality"
},
  "geometry": {"coordinates":[104.28180999999999,17.22975],"type":"Point"}
}