{
  "type": "Feature",
  "properties": {
    "gn:admin1_code":"0.0",
    "gn:asciiname":"Ban Phayi Khoe",
    "gn:country_code":"TH",
    "gn:dem":475,
    "gn:feature_class":"P",
    "gn:feature_code":"PPL",
    "gn:name":"Ban Phayi Khoe",
    "gn:population":0,
    "gn:timezone":"Asia/Bangkok",
    "iso:country":"TH",
    "name:und_x_variant":[
        "Ban Phawi Khu"
    ],
    "wof:lang_x_official":[
        "tha"
    ],
    "wof:lang_x_spoken":[
        "tha"
    ],
    "wof:name":"Ban Phayi Khoe",
    "wof:placetype":"locality"
},
  "geometry": {"coordinates":[98.71666999999999,17.08333],"type":"Point"}
}