{
  "type": "Feature",
  "properties": {
    "gn:admin1_code":"63.0",
    "gn:asciiname":"Ban Khlong Yang",
    "gn:country_code":"TH",
    "gn:dem":17,
    "gn:feature_class":"P",
    "gn:feature_code":"PPL",
    "gn:name":"Ban Khlong Yang",
    "gn:population":0,
    "gn:timezone":"Asia/Bangkok",
    "iso:country":"TH",
    "name:tha_x_preferred":[
        "\u0e1a\u0e49\u0e32\u0e19\u0e04\u0e25\u0e2d\u0e07\u0e22\u0e32\u0e07"
    ],
    "name:und_x_variant":[
        "Ban Khlong Yan"
    ],
    "wof:name":"Ban Khlong Yang",
    "wof:placetype":"locality"
},
  "geometry": {"coordinates":[99.12063999999999,7.80192],"type":"Point"}
}