{
  "type": "Feature",
  "properties": {
    "gn:admin1_code":"2.0",
    "gn:asciiname":"Ban Ta Ko Kha",
    "gn:country_code":"TH",
    "gn:dem":1184,
    "gn:feature_class":"P",
    "gn:feature_code":"PPL",
    "gn:name":"Ban Ta Ko Kha",
    "gn:population":0,
    "gn:timezone":"Asia/Bangkok",
    "iso:country":"TH",
    "name:tha_x_preferred":[
        "\u0e1a\u0e49\u0e32\u0e19\u0e15\u0e30\u0e01\u0e2d\u0e04\u0e30"
    ],
    "wof:name":"Ban Ta Ko Kha",
    "wof:placetype":"locality"
},
  "geometry": {"coordinates":[98.23053,17.59478],"type":"Point"}
}