{
  "type": "Feature",
  "properties": {
    "gn:admin1_code":"41.0",
    "gn:asciiname":"Ban Pha Lat",
    "gn:country_code":"TH",
    "gn:dem":447,
    "gn:feature_class":"P",
    "gn:feature_code":"PPL",
    "gn:name":"Ban Pha Lat",
    "gn:population":0,
    "gn:timezone":"Asia/Bangkok",
    "iso:country":"TH",
    "name:tha_x_preferred":[
        "\u0e1a\u0e49\u0e32\u0e19\u0e1c\u0e32\u0e25\u0e32\u0e14 \u0e2a\u0e2d\u0e07"
    ],
    "name:und_x_variant":[
        "B\u0101n M\u0101l\u0101d",
        "Ban Pha Lat Luang",
        "Ban Pha Lat",
        "Ban Pha Lat Song"
    ],
    "wof:lang_x_official":[
        "tha"
    ],
    "wof:lang_x_spoken":[
        "tha"
    ],
    "wof:name":"Ban Pha Lat",
    "wof:placetype":"locality"
},
  "geometry": {"coordinates":[100.33363,19.65076],"type":"Point"}
}