{
  "type": "Feature",
  "properties": {
    "gn:admin1_code":"42.0",
    "gn:asciiname":"Muban Krin Lek",
    "gn:country_code":"TH",
    "gn:dem":6,
    "gn:feature_class":"P",
    "gn:feature_code":"PPL",
    "gn:name":"Muban Krin Lek",
    "gn:population":0,
    "gn:timezone":"Asia/Bangkok",
    "iso:country":"TH",
    "name:tha_x_preferred":[
        "\u0e2b\u0e21\u0e39\u0e48\u0e1a\u0e49\u0e32\u0e19\u0e01\u0e23\u0e35\u0e19\u0e40\u0e25\u0e04"
    ],
    "wof:name":"Muban Krin Lek",
    "wof:placetype":"locality"
},
  "geometry": {"coordinates":[100.71017000000001,13.62947],"type":"Point"}
}