{
  "type": "Feature",
  "properties": {
    "gn:admin1_code":"9.0",
    "gn:asciiname":"Ban Pa Muang Song",
    "gn:country_code":"TH",
    "gn:dem":69,
    "gn:feature_class":"P",
    "gn:feature_code":"PPL",
    "gn:name":"Ban Pa Muang Song",
    "gn:population":0,
    "gn:timezone":"Asia/Bangkok",
    "iso:country":"TH",
    "name:tha_x_preferred":[
        "\u0e1a\u0e49\u0e32\u0e19\u0e1b\u0e48\u0e32\u0e21\u0e48\u0e27\u0e07 \u0e2a\u0e2d\u0e07"
    ],
    "wof:name":"Ban Pa Muang Song",
    "wof:placetype":"locality"
},
  "geometry": {"coordinates":[99.83286,17.32772000000001],"type":"Point"}
}