{
  "type": "Feature",
  "properties": {
    "gn:admin1_code":"51.0",
    "gn:asciiname":"Ban Khui Pho",
    "gn:country_code":"TH",
    "gn:dem":16,
    "gn:feature_class":"P",
    "gn:feature_code":"PPL",
    "gn:name":"Ban Khui Pho",
    "gn:population":0,
    "gn:timezone":"Asia/Bangkok",
    "iso:country":"TH",
    "name:tha_x_preferred":[
        "\u0e1a\u0e49\u0e32\u0e19\u0e02\u0e38\u0e22\u0e42\u0e1e\u0e18\u0e34\u0e4c"
    ],
    "wof:name":"Ban Khui Pho",
    "wof:placetype":"locality"
},
  "geometry": {"coordinates":[100.21767,14.86453],"type":"Point"}
}