{
  "type": "Feature",
  "properties": {
    "gn:admin1_code":"74.0",
    "gn:asciiname":"Ban Phraya Wang",
    "gn:country_code":"TH",
    "gn:dem":9,
    "gn:feature_class":"P",
    "gn:feature_code":"PPL",
    "gn:name":"Ban Phraya Wang",
    "gn:population":0,
    "gn:timezone":"Asia/Bangkok",
    "iso:country":"TH",
    "name:tha_x_preferred":[
        "\u0e1a\u0e49\u0e32\u0e19\u0e1e\u0e23\u0e30\u0e22\u0e32\u0e27\u0e31\u0e07"
    ],
    "wof:name":"Ban Phraya Wang",
    "wof:placetype":"locality"
},
  "geometry": {"coordinates":[101.52978,13.97483],"type":"Point"}
}