{
  "type": "Feature",
  "properties": {
    "gn:admin1_code":"80",
    "gn:asciiname":"Ban Mai Udom Phon",
    "gn:country_code":"TH",
    "gn:dem":47,
    "gn:feature_class":"P",
    "gn:feature_code":"PPL",
    "gn:name":"Ban Mai Udom Phon",
    "gn:population":0,
    "gn:timezone":"Asia/Bangkok",
    "iso:country":"TH",
    "name:tha_x_preferred":[
        "\u0e1a\u0e49\u0e32\u0e19\u0e43\u0e2b\u0e21\u0e48\u0e2d\u0e38\u0e14\u0e21\u0e1e\u0e23"
    ],
    "wof:name":"Ban Mai Udom Phon",
    "wof:placetype":"locality"
},
  "geometry": {"coordinates":[101.99131,13.82914],"type":"Point"}
}