{
  "type": "Feature",
  "properties": {
    "gn:admin1_code":"48.0",
    "gn:asciiname":"Ban Khlong Nam Khem",
    "gn:cc2":"TH",
    "gn:country_code":"TH",
    "gn:dem":21,
    "gn:feature_class":"P",
    "gn:feature_code":"PPL",
    "gn:name":"Ban Khlong Nam Khem",
    "gn:population":0,
    "gn:timezone":"Asia/Bangkok",
    "iso:country":"TH",
    "name:und_x_variant":[
        "B\u0101n Gl\u014dhng Nam",
        "Ban Klong Namkhem",
        "Ban Khlong Nam Khem"
    ],
    "wof:name":"Ban Khlong Nam Khem",
    "wof:placetype":"locality"
},
  "geometry": {"coordinates":[101.83333,12.78333],"type":"Point"}
}