{
  "type": "Feature",
  "properties": {
    "gn:admin1_code":"26.0",
    "gn:asciiname":"Ban Ran Ya",
    "gn:country_code":"TH",
    "gn:dem":203,
    "gn:feature_class":"P",
    "gn:feature_code":"PPL",
    "gn:name":"Ban Ran Ya",
    "gn:population":0,
    "gn:timezone":"Asia/Bangkok",
    "iso:country":"TH",
    "name:tha_x_preferred":[
        "\u0e1a\u0e49\u0e32\u0e19\u0e23\u0e49\u0e32\u0e19\u0e2b\u0e0d\u0e49\u0e32"
    ],
    "name:und_x_variant":[
        "B\u0101n L\u0101m Ya",
        "Ban Lan Ya",
        "Ban Ran Ya"
    ],
    "wof:name":"Ban Ran Ya",
    "wof:placetype":"locality"
},
  "geometry": {"coordinates":[101.80036,15.53575],"type":"Point"}
}