{
  "type": "Feature",
  "properties": {
    "gn:admin1_code":"30.0",
    "gn:asciiname":"Ban Hai Noi",
    "gn:country_code":"TH",
    "gn:dem":144,
    "gn:feature_class":"P",
    "gn:feature_code":"PPL",
    "gn:name":"Ban Hai Noi",
    "gn:population":0,
    "gn:timezone":"Asia/Bangkok",
    "iso:country":"TH",
    "name:tha_x_preferred":[
        "\u0e1a\u0e49\u0e32\u0e19\u0e44\u0e2e\u0e19\u0e49\u0e2d\u0e22"
    ],
    "wof:name":"Ban Hai Noi",
    "wof:placetype":"locality"
},
  "geometry": {"coordinates":[103.97678000000001,14.823],"type":"Point"}
}