{
  "type": "Feature",
  "properties": {
    "gn:admin1_code":"28",
    "gn:asciiname":"Ban Pang Ku",
    "gn:country_code":"TH",
    "gn:dem":178,
    "gn:feature_class":"P",
    "gn:feature_code":"PPL",
    "gn:name":"Ban Pang Ku",
    "gn:population":0,
    "gn:timezone":"Asia/Bangkok",
    "iso:country":"TH",
    "name:tha_x_preferred":[
        "\u0e1a\u0e49\u0e32\u0e19\u0e1b\u0e31\u0e07\u0e01\u0e39"
    ],
    "wof:name":"Ban Pang Ku",
    "wof:placetype":"locality"
},
  "geometry": {"coordinates":[103.04181,14.55592],"type":"Point"}
}