{
  "type": "Feature",
  "properties": {
    "gn:admin1_code":"52.0",
    "gn:asciiname":"Ban Noen Thong",
    "gn:country_code":"TH",
    "gn:dem":72,
    "gn:feature_class":"P",
    "gn:feature_code":"PPL",
    "gn:name":"Ban Noen Thong",
    "gn:population":0,
    "gn:timezone":"Asia/Bangkok",
    "iso:country":"TH",
    "name:tha_x_preferred":[
        "\u0e1a\u0e49\u0e32\u0e19\u0e40\u0e19\u0e34\u0e19\u0e17\u0e2d\u0e07"
    ],
    "wof:name":"Ban Noen Thong",
    "wof:placetype":"locality"
},
  "geometry": {"coordinates":[99.6615,13.38053],"type":"Point"}
}