{
  "type": "Feature",
  "properties": {
    "gn:admin1_code":"65.0",
    "gn:asciiname":"Ban Nong Khla",
    "gn:country_code":"TH",
    "gn:dem":45,
    "gn:feature_class":"P",
    "gn:feature_code":"PPL",
    "gn:name":"Ban Nong Khla",
    "gn:population":0,
    "gn:timezone":"Asia/Bangkok",
    "iso:country":"TH",
    "name:tha_x_preferred":[
        "\u0e1a\u0e49\u0e32\u0e19\u0e2b\u0e19\u0e2d\u0e07\u0e04\u0e25\u0e49\u0e32"
    ],
    "name:und_x_variant":[
        "Ban Nong Khla (1)"
    ],
    "wof:name":"Ban Nong Khla",
    "wof:placetype":"locality"
},
  "geometry": {"coordinates":[99.62692,7.91453],"type":"Point"}
}