{
  "type": "Feature",
  "properties": {
    "gn:admin1_code":"2.0",
    "gn:asciiname":"Ban Hin Lek Fai",
    "gn:country_code":"TH",
    "gn:dem":1193,
    "gn:feature_class":"P",
    "gn:feature_code":"PPL",
    "gn:name":"Ban Hin Lek Fai",
    "gn:population":0,
    "gn:timezone":"Asia/Bangkok",
    "iso:country":"TH",
    "name:tha_x_preferred":[
        "\u0e1a\u0e49\u0e32\u0e19\u0e2b\u0e34\u0e19\u0e40\u0e2b\u0e25\u0e47\u0e01\u0e44\u0e1f"
    ],
    "wof:lang_x_official":[
        "tha"
    ],
    "wof:lang_x_spoken":[
        "tha"
    ],
    "wof:name":"Ban Hin Lek Fai",
    "wof:placetype":"locality"
},
  "geometry": {"coordinates":[98.49518999999999,18.36433],"type":"Point"}
}