{
  "type": "Feature",
  "properties": {
    "gn:admin1_code":"23.0",
    "gn:asciiname":"Ban Tha Ngam",
    "gn:country_code":"TH",
    "gn:dem":191,
    "gn:feature_class":"P",
    "gn:feature_code":"PPL",
    "gn:name":"Ban Tha Ngam",
    "gn:population":0,
    "gn:timezone":"Asia/Bangkok",
    "iso:country":"TH",
    "name:tha_x_preferred":[
        "\u0e1a\u0e49\u0e32\u0e19\u0e17\u0e48\u0e32\u0e07\u0e32\u0e21"
    ],
    "wof:name":"Ban Tha Ngam",
    "wof:placetype":"locality"
},
  "geometry": {"coordinates":[103.50203,16.95694],"type":"Point"}
}