{
  "type": "Feature",
  "properties": {
    "gn:admin1_code":"41.0",
    "gn:asciiname":"Ban Pa Kha",
    "gn:country_code":"TH",
    "gn:dem":308,
    "gn:feature_class":"P",
    "gn:feature_code":"PPL",
    "gn:name":"Ban Pa Kha",
    "gn:population":0,
    "gn:timezone":"Asia/Bangkok",
    "iso:country":"TH",
    "name:tha_x_preferred":[
        "\u0e1a\u0e49\u0e32\u0e19\u0e1b\u0e48\u0e32\u0e04\u0e32"
    ],
    "name:und_x_variant":[
        "B\u0101n Pa Ka",
        "Ban Pa Kha"
    ],
    "wof:name":"Ban Pa Kha",
    "wof:placetype":"locality"
},
  "geometry": {"coordinates":[100.31814,19.15767],"type":"Point"}
}