{
  "type": "Feature",
  "properties": {
    "gn:admin1_code":"24",
    "gn:asciiname":"Ban Don Sai Thong",
    "gn:country_code":"TH",
    "gn:dem":176,
    "gn:feature_class":"P",
    "gn:feature_code":"PPL",
    "gn:name":"Ban Don Sai Thong",
    "gn:population":0,
    "gn:timezone":"Asia/Bangkok",
    "iso:country":"TH",
    "name:tha_x_preferred":[
        "\u0e1a\u0e49\u0e32\u0e19\u0e14\u0e2d\u0e19\u0e44\u0e17\u0e23\u0e17\u0e2d\u0e07"
    ],
    "wof:name":"Ban Don Sai Thong",
    "wof:placetype":"locality"
},
  "geometry": {"coordinates":[103.35953000000001,16.03983],"type":"Point"}
}