{
  "type": "Feature",
  "properties": {
    "gn:admin1_code":"51.0",
    "gn:asciiname":"Ban Nong Khai Nao",
    "gn:country_code":"TH",
    "gn:dem":28,
    "gn:feature_class":"P",
    "gn:feature_code":"PPL",
    "gn:name":"Ban Nong Khai Nao",
    "gn:population":0,
    "gn:timezone":"Asia/Bangkok",
    "iso:country":"TH",
    "wof:name":"Ban Nong Khai Nao",
    "wof:placetype":"locality"
},
  "geometry": {"coordinates":[99.88889,14.6575],"type":"Point"}
}