{
  "type": "Feature",
  "properties": {
    "gn:admin1_code":"14.0",
    "gn:asciiname":"Ban Huai Na",
    "gn:country_code":"TH",
    "gn:dem":709,
    "gn:feature_class":"P",
    "gn:feature_code":"PPL",
    "gn:name":"Ban Huai Na",
    "gn:population":0,
    "gn:timezone":"Asia/Bangkok",
    "iso:country":"TH",
    "name:tha_x_preferred":[
        "\u0e1a\u0e49\u0e32\u0e19\u0e2b\u0e49\u0e27\u0e22\u0e19\u0e32"
    ],
    "wof:name":"Ban Huai Na",
    "wof:placetype":"locality"
},
  "geometry": {"coordinates":[101.01488999999999,16.74197],"type":"Point"}
}