{
  "type": "Feature",
  "properties": {
    "gn:admin1_code":"39.0",
    "gn:asciiname":"Ban Tong Poe",
    "gn:country_code":"TH",
    "gn:dem":6,
    "gn:feature_class":"P",
    "gn:feature_code":"PPL",
    "gn:name":"Ban Tong Poe",
    "gn:population":0,
    "gn:timezone":"Asia/Bangkok",
    "iso:country":"TH",
    "name:tha_x_preferred":[
        "Ban Tong Poe"
    ],
    "name:tha_x_variant":[
        "\u0e1a\u0e49\u0e32\u0e19\u0e15\u0e2d\u0e07\u0e40\u0e1b\u0e2d\u0e30"
    ],
    "wof:name":"Ban Tong Poe",
    "wof:placetype":"locality"
},
  "geometry": {"coordinates":[100.52258,14.05917],"type":"Point"}
}