{
  "type": "Feature",
  "properties": {
    "gn:admin1_code":"4.0",
    "gn:asciiname":"Ban Pang Yang",
    "gn:country_code":"TH",
    "gn:dem":879,
    "gn:feature_class":"P",
    "gn:feature_code":"PPL",
    "gn:name":"Ban Pang Yang",
    "gn:population":0,
    "gn:timezone":"Asia/Bangkok",
    "iso:country":"TH",
    "name:tha_x_preferred":[
        "\u0e1a\u0e49\u0e32\u0e19\u0e1b\u0e32\u0e07\u0e22\u0e32\u0e07"
    ],
    "wof:name":"Ban Pang Yang",
    "wof:placetype":"locality"
},
  "geometry": {"coordinates":[100.99594,19.13282],"type":"Point"}
}