{
  "type": "Feature",
  "properties": {
    "gn:admin1_code":"22",
    "gn:asciiname":"Ban Non Daeng",
    "gn:country_code":"TH",
    "gn:dem":187,
    "gn:feature_class":"P",
    "gn:feature_code":"PPL",
    "gn:name":"Ban Non Daeng",
    "gn:population":0,
    "gn:timezone":"Asia/Bangkok",
    "iso:country":"TH",
    "name:tha_x_preferred":[
        "\u0e1a\u0e49\u0e32\u0e19\u0e42\u0e19\u0e19\u0e41\u0e14\u0e07"
    ],
    "wof:name":"Ban Non Daeng",
    "wof:placetype":"locality"
},
  "geometry": {"coordinates":[102.97497,16.72561],"type":"Point"}
}