{
  "type": "Feature",
  "properties": {
    "gn:admin1_code":"10.0",
    "gn:asciiname":"Ban Khom",
    "gn:country_code":"TH",
    "gn:dem":54,
    "gn:feature_class":"P",
    "gn:feature_code":"PPL",
    "gn:name":"Ban Khom",
    "gn:population":0,
    "gn:timezone":"Asia/Bangkok",
    "iso:country":"TH",
    "name:tha_x_preferred":[
        "\u0e1a\u0e49\u0e32\u0e19\u0e02\u0e2d\u0e21"
    ],
    "name:und_x_variant":[
        "B\u0101n Kuam",
        "Ban Khuam",
        "Ban Khom"
    ],
    "wof:name":"Ban Khom",
    "wof:placetype":"locality"
},
  "geometry": {"coordinates":[100.03239000000001,17.165],"type":"Point"}
}