{
  "type": "Feature",
  "properties": {
    "gn:admin1_code":"67.0",
    "gn:asciiname":"Ban Khao Noi Tok",
    "gn:country_code":"TH",
    "gn:dem":24,
    "gn:feature_class":"P",
    "gn:feature_code":"PPL",
    "gn:name":"Ban Khao Noi Tok",
    "gn:population":0,
    "gn:timezone":"Asia/Bangkok",
    "iso:country":"TH",
    "name:tha_x_preferred":[
        "\u0e1a\u0e49\u0e32\u0e19\u0e40\u0e02\u0e32\u0e19\u0e49\u0e2d\u0e22\u0e15\u0e01"
    ],
    "wof:name":"Ban Khao Noi Tok",
    "wof:placetype":"locality"
},
  "geometry": {"coordinates":[100.01588,6.74568],"type":"Point"}
}