{
  "type": "Feature",
  "properties": {
    "gn:admin1_code":"17.0",
    "gn:asciiname":"Ban Putdu",
    "gn:country_code":"TH",
    "gn:dem":224,
    "gn:feature_class":"P",
    "gn:feature_code":"PPL",
    "gn:name":"Ban Putdu",
    "gn:population":0,
    "gn:timezone":"Asia/Bangkok",
    "iso:country":"TH",
    "name:tha_x_preferred":[
        "\u0e1a\u0e49\u0e32\u0e19\u0e1b\u0e38\u0e14\u0e14\u0e39\u0e48"
    ],
    "wof:name":"Ban Putdu",
    "wof:placetype":"locality"
},
  "geometry": {"coordinates":[102.39858,17.97458],"type":"Point"}
}