{
  "type": "Feature",
  "properties": {
    "gn:admin1_code":"68.0",
    "gn:asciiname":"Ban Mo La Tae",
    "gn:country_code":"TH",
    "gn:dem":25,
    "gn:feature_class":"P",
    "gn:feature_code":"PPL",
    "gn:name":"Ban Mo La Tae",
    "gn:population":0,
    "gn:timezone":"Asia/Bangkok",
    "iso:country":"TH",
    "name:tha_x_preferred":[
        "\u0e1a\u0e49\u0e32\u0e19\u0e40\u0e21\u0e32\u0e30\u0e25\u0e32\u0e41\u0e15"
    ],
    "wof:name":"Ban Mo La Tae",
    "wof:placetype":"locality"
},
  "geometry": {"coordinates":[100.95180999999999,6.56161],"type":"Point"}
}