{
  "type": "Feature",
  "properties": {
    "gn:admin1_code":"64.0",
    "gn:asciiname":"Ban Phatthasima",
    "gn:country_code":"TH",
    "gn:dem":12,
    "gn:feature_class":"P",
    "gn:feature_code":"PPL",
    "gn:name":"Ban Phatthasima",
    "gn:population":0,
    "gn:timezone":"Asia/Bangkok",
    "iso:country":"TH",
    "name:tha_x_preferred":[
        "\u0e1a\u0e49\u0e32\u0e19\u0e1e\u0e31\u0e17\u0e18\u0e2a\u0e35\u0e21\u0e32"
    ],
    "name:und_x_variant":[
        "Ban Phat Sema",
        "Pat Samau",
        "Ban Bang Phatthasima",
        "Ban Phatthasima"
    ],
    "wof:name":"Ban Phatthasima",
    "wof:placetype":"locality"
},
  "geometry": {"coordinates":[100.24924,8.13866],"type":"Point"}
}