{
  "type": "Feature",
  "properties": {
    "gn:admin1_code":"35.0",
    "gn:asciiname":"Ban Wat Bot",
    "gn:country_code":"TH",
    "gn:dem":12,
    "gn:feature_class":"P",
    "gn:feature_code":"PPL",
    "gn:name":"Ban Wat Bot",
    "gn:population":0,
    "gn:timezone":"Asia/Bangkok",
    "iso:country":"TH",
    "name:tha_x_preferred":[
        "\u0e1a\u0e49\u0e32\u0e19\u0e27\u0e31\u0e14\u0e42\u0e1a\u0e2a\u0e16\u0e4c"
    ],
    "name:und_x_variant":[
        "Ban Na Wat Bot"
    ],
    "wof:name":"Ban Wat Bot",
    "wof:placetype":"locality"
},
  "geometry": {"coordinates":[100.27556,14.58761],"type":"Point"}
}