{
  "type": "Feature",
  "properties": {
    "gn:admin1_code":"8.0",
    "gn:asciiname":"Ban Kio Hang",
    "gn:country_code":"TH",
    "gn:dem":474,
    "gn:feature_class":"P",
    "gn:feature_code":"PPL",
    "gn:name":"Ban Kio Hang",
    "gn:population":0,
    "gn:timezone":"Asia/Bangkok",
    "iso:country":"TH",
    "name:tha_x_preferred":[
        "\u0e1a\u0e49\u0e32\u0e19\u0e01\u0e34\u0e48\u0e27\u0e2b\u0e49\u0e32\u0e07"
    ],
    "name:und_x_variant":[
        "Ban Kiu Hang"
    ],
    "wof:lang_x_official":[
        "tha"
    ],
    "wof:lang_x_spoken":[
        "tha"
    ],
    "wof:name":"Ban Kio Hang",
    "wof:placetype":"locality"
},
  "geometry": {"coordinates":[98.87544,15.98853],"type":"Point"}
}