{
  "type": "Feature",
  "properties": {
    "gn:admin1_code":"12.0",
    "gn:asciiname":"Ban Rong Kok",
    "gn:country_code":"TH",
    "gn:dem":216,
    "gn:feature_class":"P",
    "gn:feature_code":"PPL",
    "gn:name":"Ban Rong Kok",
    "gn:population":0,
    "gn:timezone":"Asia/Bangkok",
    "iso:country":"TH",
    "name:tha_x_preferred":[
        "\u0e1a\u0e49\u0e32\u0e19\u0e23\u0e49\u0e2d\u0e07\u0e01\u0e2d\u0e01"
    ],
    "wof:name":"Ban Rong Kok",
    "wof:placetype":"locality"
},
  "geometry": {"coordinates":[100.87555999999999,17.15803],"type":"Point"}
}