{
  "type": "Feature",
  "properties": {
    "gn:admin1_code":"48.0",
    "gn:asciiname":"Ban Hin Dat",
    "gn:country_code":"TH",
    "gn:dem":14,
    "gn:feature_class":"P",
    "gn:feature_code":"PPL",
    "gn:name":"Ban Hin Dat",
    "gn:population":0,
    "gn:timezone":"Asia/Bangkok",
    "iso:country":"TH",
    "name:tha_x_preferred":[
        "\u0e1a\u0e49\u0e32\u0e19\u0e2b\u0e34\u0e19\u0e14\u0e32\u0e29"
    ],
    "name:und_x_variant":[
        "Ban Hin Dat (2)"
    ],
    "wof:name":"Ban Hin Dat",
    "wof:placetype":"locality"
},
  "geometry": {"coordinates":[101.93114,12.74786],"type":"Point"}
}