{
  "type": "Feature",
  "properties": {
    "gn:admin1_code":"47.0",
    "gn:asciiname":"Ban Khlong Thuea Raet",
    "gn:country_code":"TH",
    "gn:dem":47,
    "gn:feature_class":"P",
    "gn:feature_code":"PPL",
    "gn:name":"Ban Khlong Thuea Raet",
    "gn:population":0,
    "gn:timezone":"Asia/Bangkok",
    "iso:country":"TH",
    "name:tha_x_preferred":[
        "\u0e1a\u0e49\u0e32\u0e19\u0e04\u0e25\u0e2d\u0e07\u0e40\u0e16\u0e37\u0e2d\u0e41\u0e23\u0e14"
    ],
    "wof:name":"Ban Khlong Thuea Raet",
    "wof:placetype":"locality"
},
  "geometry": {"coordinates":[101.36028,12.81694],"type":"Point"}
}