{
  "type": "Feature",
  "properties": {
    "gn:admin1_code":"66.0",
    "gn:asciiname":"Ban Hua Rang Nueng",
    "gn:country_code":"TH",
    "gn:dem":33,
    "gn:feature_class":"P",
    "gn:feature_code":"PPL",
    "gn:name":"Ban Hua Rang Nueng",
    "gn:population":0,
    "gn:timezone":"Asia/Bangkok",
    "iso:country":"TH",
    "name:tha_x_preferred":[
        "\u0e1a\u0e49\u0e32\u0e19\u0e2b\u0e31\u0e27\u0e2b\u0e23\u0e31\u0e48\u0e07 \u0e2b\u0e19\u0e36\u0e48\u0e07"
    ],
    "wof:name":"Ban Hua Rang Nueng",
    "wof:placetype":"locality"
},
  "geometry": {"coordinates":[100.00506,7.47333],"type":"Point"}
}