{
  "type": "Feature",
  "properties": {
    "gn:admin1_code":"24",
    "gn:asciiname":"Ban Dong Nam Kin",
    "gn:country_code":"TH",
    "gn:dem":140,
    "gn:feature_class":"P",
    "gn:feature_code":"PPL",
    "gn:name":"Ban Dong Nam Kin",
    "gn:population":0,
    "gn:timezone":"Asia/Bangkok",
    "iso:country":"TH",
    "name:tha_x_preferred":[
        "\u0e1a\u0e49\u0e32\u0e19\u0e14\u0e07\u0e19\u0e49\u0e33\u0e01\u0e34\u0e19"
    ],
    "wof:name":"Ban Dong Nam Kin",
    "wof:placetype":"locality"
},
  "geometry": {"coordinates":[103.22897,15.47456],"type":"Point"}
}