{
  "type": "Feature",
  "properties": {
    "gn:admin1_code":"25.0",
    "gn:asciiname":"Ban Sa-at Charoen",
    "gn:country_code":"TH",
    "gn:dem":177,
    "gn:feature_class":"P",
    "gn:feature_code":"PPL",
    "gn:name":"Ban Sa-at Charoen",
    "gn:population":0,
    "gn:timezone":"Asia/Bangkok",
    "iso:country":"TH",
    "name:tha_x_preferred":[
        "\u0e1a\u0e49\u0e32\u0e19\u0e2a\u0e30\u0e2d\u0e32\u0e14\u0e40\u0e08\u0e23\u0e34\u0e0d"
    ],
    "wof:name":"Ban Sa-at Charoen",
    "wof:placetype":"locality"
},
  "geometry": {"coordinates":[103.82156000000001,16.30467],"type":"Point"}
}