{
  "type": "Feature",
  "properties": {
    "gn:admin1_code":"80",
    "gn:asciiname":"Ban Chan Chu",
    "gn:country_code":"TH",
    "gn:dem":42,
    "gn:feature_class":"P",
    "gn:feature_code":"PPL",
    "gn:name":"Ban Chan Chu",
    "gn:population":0,
    "gn:timezone":"Asia/Bangkok",
    "iso:country":"TH",
    "name:tha_x_preferred":[
        "\u0e1a\u0e49\u0e32\u0e19\u0e08\u0e32\u0e23\u0e22\u0e4c\u0e08\u0e39"
    ],
    "wof:name":"Ban Chan Chu",
    "wof:placetype":"locality"
},
  "geometry": {"coordinates":[102.56413999999999,13.61844],"type":"Point"}
}