{
  "type": "Feature",
  "properties": {
    "gn:admin1_code":"27",
    "gn:asciiname":"Ban Bung Takhrong",
    "gn:country_code":"TH",
    "gn:dem":178,
    "gn:feature_class":"P",
    "gn:feature_code":"PPL",
    "gn:name":"Ban Bung Takhrong",
    "gn:population":0,
    "gn:timezone":"Asia/Bangkok",
    "iso:country":"TH",
    "name:tha_x_preferred":[
        "\u0e1a\u0e49\u0e32\u0e19\u0e1a\u0e38\u0e48\u0e07\u0e15\u0e30\u0e04\u0e23\u0e2d\u0e07"
    ],
    "wof:name":"Ban Bung Takhrong",
    "wof:placetype":"locality"
},
  "geometry": {"coordinates":[102.38606,15.38131],"type":"Point"}
}