{
  "type": "Feature",
  "properties": {
    "gn:admin1_code":"77.0",
    "gn:asciiname":"Ban Hin Sio",
    "gn:country_code":"TH",
    "gn:dem":179,
    "gn:feature_class":"P",
    "gn:feature_code":"PPL",
    "gn:name":"Ban Hin Sio",
    "gn:population":0,
    "gn:timezone":"Asia/Bangkok",
    "iso:country":"TH",
    "name:tha_x_preferred":[
        "Ban Hin Sio"
    ],
    "name:tha_x_variant":[
        "\u0e1a\u0e49\u0e32\u0e19\u0e2b\u0e34\u0e19\u0e2a\u0e34\u0e48\u0e27"
    ],
    "wof:name":"Ban Hin Sio",
    "wof:placetype":"locality"
},
  "geometry": {"coordinates":[104.90831,16.22294],"type":"Point"}
}