{
  "type": "Feature",
  "properties": {
    "gn:admin1_code":"68.0",
    "gn:asciiname":"Ban Chalung",
    "gn:country_code":"TH",
    "gn:dem":33,
    "gn:feature_class":"P",
    "gn:feature_code":"PPL",
    "gn:name":"Ban Chalung",
    "gn:population":0,
    "gn:timezone":"Asia/Bangkok",
    "iso:country":"TH",
    "name:und_x_variant":[
        "Chalung",
        "Ban Chalung",
        "\u0e1a\u0e49\u0e32\u0e19\u0e09\u0e25\u0e38\u0e07"
    ],
    "wof:name":"Ban Chalung",
    "wof:placetype":"locality"
},
  "geometry": {"coordinates":[100.30025999999999,6.99686],"type":"Point"}
}