{
  "type": "Feature",
  "properties": {
    "gn:admin1_code":"39.0",
    "gn:asciiname":"Ban Charoen Suk Phatthana",
    "gn:country_code":"TH",
    "gn:dem":7,
    "gn:feature_class":"P",
    "gn:feature_code":"PPL",
    "gn:name":"Ban Charoen Suk Phatthana",
    "gn:population":0,
    "gn:timezone":"Asia/Bangkok",
    "iso:country":"TH",
    "name:tha_x_preferred":[
        "Ban Charoen Suk Phatthana"
    ],
    "name:tha_x_variant":[
        "\u0e1a\u0e49\u0e32\u0e19\u0e40\u0e08\u0e23\u0e34\u0e0d\u0e2a\u0e38\u0e02\u0e1e\u0e31\u0e12\u0e19\u0e32"
    ],
    "wof:name":"Ban Charoen Suk Phatthana",
    "wof:placetype":"locality"
},
  "geometry": {"coordinates":[100.80016999999999,14.15306],"type":"Point"}
}