{
  "type": "Feature",
  "properties": {
    "gn:admin1_code":"63.0",
    "gn:asciiname":"Ban Thap Khwai",
    "gn:country_code":"TH",
    "gn:dem":97,
    "gn:feature_class":"P",
    "gn:feature_code":"PPL",
    "gn:name":"Ban Thap Khwai",
    "gn:population":0,
    "gn:timezone":"Asia/Bangkok",
    "iso:country":"TH",
    "name:tha_x_preferred":[
        "\u0e1a\u0e49\u0e32\u0e19\u0e17\u0e31\u0e1a\u0e04\u0e27\u0e32\u0e22"
    ],
    "wof:name":"Ban Thap Khwai",
    "wof:placetype":"locality"
},
  "geometry": {"coordinates":[98.79197000000001,8.42961],"type":"Point"}
}