{
  "type": "Feature",
  "properties": {
    "gn:admin1_code":"37",
    "gn:asciiname":"Ban Sap Mai Lom",
    "gn:country_code":"TH",
    "gn:dem":265,
    "gn:feature_class":"P",
    "gn:feature_code":"PPL",
    "gn:name":"Ban Sap Mai Lom",
    "gn:population":0,
    "gn:timezone":"Asia/Bangkok",
    "iso:country":"TH",
    "name:tha_x_preferred":[
        "\u0e1a\u0e49\u0e32\u0e19\u0e0b\u0e31\u0e1a\u0e44\u0e21\u0e49\u0e25\u0e49\u0e21"
    ],
    "wof:name":"Ban Sap Mai Lom",
    "wof:placetype":"locality"
},
  "geometry": {"coordinates":[101.45294,14.86008],"type":"Point"}
}