{
  "type": "Feature",
  "properties": {
    "gn:admin1_code":"70.0",
    "gn:asciiname":"Ban Bu Ke Kue Long",
    "gn:country_code":"TH",
    "gn:dem":160,
    "gn:feature_class":"P",
    "gn:feature_code":"PPL",
    "gn:name":"Ban Bu Ke Kue Long",
    "gn:population":0,
    "gn:timezone":"Asia/Bangkok",
    "iso:country":"TH",
    "name:tha_x_preferred":[
        "\u0e1a\u0e49\u0e32\u0e19\u0e1a\u0e38\u0e40\u0e01\u0e4a\u0e30\u0e01\u0e37\u0e2d\u0e25\u0e2d\u0e07"
    ],
    "wof:name":"Ban Bu Ke Kue Long",
    "wof:placetype":"locality"
},
  "geometry": {"coordinates":[101.35789,6.24164],"type":"Point"}
}