{
  "type": "Feature",
  "properties": {
    "gn:admin1_code":"20.0",
    "gn:asciiname":"Ban Noi Chom Si",
    "gn:country_code":"TH",
    "gn:dem":172,
    "gn:feature_class":"P",
    "gn:feature_code":"PPL",
    "gn:name":"Ban Noi Chom Si",
    "gn:population":0,
    "gn:timezone":"Asia/Bangkok",
    "iso:country":"TH",
    "name:tha_x_preferred":[
        "\u0e1a\u0e49\u0e32\u0e19\u0e19\u0e49\u0e2d\u0e22\u0e08\u0e2d\u0e21\u0e28\u0e23\u0e35"
    ],
    "wof:name":"Ban Noi Chom Si",
    "wof:placetype":"locality"
},
  "geometry": {"coordinates":[104.09331,17.21745],"type":"Point"}
}