{
  "type": "Feature",
  "properties": {
    "gn:admin1_code":"5.0",
    "gn:asciiname":"Ban San Ma Ko",
    "gn:country_code":"TH",
    "gn:dem":298,
    "gn:feature_class":"P",
    "gn:feature_code":"PPL",
    "gn:name":"Ban San Ma Ko",
    "gn:population":0,
    "gn:timezone":"Asia/Bangkok",
    "iso:country":"TH",
    "name:tha_x_preferred":[
        "\u0e1a\u0e49\u0e32\u0e19\u0e2a\u0e31\u0e19\u0e21\u0e30\u0e42\u0e01"
    ],
    "wof:name":"Ban San Ma Ko",
    "wof:placetype":"locality"
},
  "geometry": {"coordinates":[98.95358,18.52164],"type":"Point"}
}