{
  "type": "Feature",
  "properties": {
    "gn:admin1_code":"29",
    "gn:asciiname":"Ban Wang Nam Yen",
    "gn:country_code":"TH",
    "gn:dem":144,
    "gn:feature_class":"P",
    "gn:feature_code":"PPL",
    "gn:name":"Ban Wang Nam Yen",
    "gn:population":0,
    "gn:timezone":"Asia/Bangkok",
    "iso:country":"TH",
    "name:tha_x_preferred":[
        "\u0e1a\u0e49\u0e32\u0e19\u0e27\u0e31\u0e07\u0e19\u0e49\u0e33\u0e40\u0e22\u0e47\u0e19"
    ],
    "wof:name":"Ban Wang Nam Yen",
    "wof:placetype":"locality"
},
  "geometry": {"coordinates":[103.77782999999999,14.8365],"type":"Point"}
}