{
  "type": "Feature",
  "properties": {
    "gn:admin1_code":"26.0",
    "gn:asciiname":"Ban Kut Chik",
    "gn:country_code":"TH",
    "gn:dem":281,
    "gn:feature_class":"P",
    "gn:feature_code":"PPL",
    "gn:name":"Ban Kut Chik",
    "gn:population":0,
    "gn:timezone":"Asia/Bangkok",
    "iso:country":"TH",
    "name:tha_x_preferred":[
        "\u0e1a\u0e49\u0e32\u0e19\u0e01\u0e38\u0e14\u0e08\u0e34\u0e01"
    ],
    "wof:name":"Ban Kut Chik",
    "wof:placetype":"locality"
},
  "geometry": {"coordinates":[101.84989,16.14514],"type":"Point"}
}