{
  "type": "Feature",
  "properties": {
    "gn:admin1_code":"58.0",
    "gn:asciiname":"Ban Tham Ta Thong",
    "gn:country_code":"TH",
    "gn:dem":120,
    "gn:feature_class":"P",
    "gn:feature_code":"PPL",
    "gn:name":"Ban Tham Ta Thong",
    "gn:population":0,
    "gn:timezone":"Asia/Bangkok",
    "iso:country":"TH",
    "name:tha_x_preferred":[
        "\u0e1a\u0e49\u0e32\u0e19\u0e16\u0e49\u0e33\u0e15\u0e32\u0e17\u0e2d\u0e07"
    ],
    "wof:name":"Ban Tham Ta Thong",
    "wof:placetype":"locality"
},
  "geometry": {"coordinates":[98.87358,10.09762],"type":"Point"}
}