{
  "type": "Feature",
  "properties": {
    "gn:admin1_code":"28.0",
    "gn:asciiname":"Ban Kwang Ngoi",
    "gn:country_code":"TH",
    "gn:dem":173,
    "gn:feature_class":"P",
    "gn:feature_code":"PPL",
    "gn:name":"Ban Kwang Ngoi",
    "gn:population":0,
    "gn:timezone":"Asia/Bangkok",
    "iso:country":"TH",
    "name:tha_x_preferred":[
        "\u0e1a\u0e49\u0e32\u0e19\u0e01\u0e27\u0e32\u0e07\u0e07\u0e2d\u0e22"
    ],
    "name:und_x_variant":[
        "Ban Kwang Ngoi (1)"
    ],
    "wof:name":"Ban Kwang Ngoi",
    "wof:placetype":"locality"
},
  "geometry": {"coordinates":[102.83394,14.92169],"type":"Point"}
}