{
  "type": "Feature",
  "properties": {
    "gn:admin1_code":"27",
    "gn:asciiname":"Ban Khok Sa Daeng",
    "gn:country_code":"TH",
    "gn:dem":195,
    "gn:feature_class":"P",
    "gn:feature_code":"PPL",
    "gn:name":"Ban Khok Sa Daeng",
    "gn:population":0,
    "gn:timezone":"Asia/Bangkok",
    "iso:country":"TH",
    "name:tha_x_preferred":[
        "\u0e1a\u0e49\u0e32\u0e19\u0e42\u0e04\u0e01\u0e2a\u0e23\u0e30\u0e41\u0e14\u0e07"
    ],
    "wof:name":"Ban Khok Sa Daeng",
    "wof:placetype":"locality"
},
  "geometry": {"coordinates":[102.12003,15.56678],"type":"Point"}
}