{
  "type": "Feature",
  "properties": {
    "gn:admin1_code":"29.0",
    "gn:asciiname":"Ban Si Tawan",
    "gn:country_code":"TH",
    "gn:dem":146,
    "gn:feature_class":"P",
    "gn:feature_code":"PPL",
    "gn:name":"Ban Si Tawan",
    "gn:population":0,
    "gn:timezone":"Asia/Bangkok",
    "iso:country":"TH",
    "name:tha_x_preferred":[
        "\u0e1a\u0e49\u0e32\u0e19\u0e28\u0e23\u0e35\u0e15\u0e30\u0e27\u0e31\u0e19"
    ],
    "wof:name":"Ban Si Tawan",
    "wof:placetype":"locality"
},
  "geometry": {"coordinates":[103.84039,14.95614],"type":"Point"}
}