{
  "type": "Feature",
  "properties": {
    "gn:admin1_code":"78.0",
    "gn:asciiname":"Ban Nong Yaplong",
    "gn:country_code":"TH",
    "gn:dem":186,
    "gn:feature_class":"P",
    "gn:feature_code":"PPL",
    "gn:name":"Ban Nong Yaplong",
    "gn:population":0,
    "gn:timezone":"Asia/Bangkok",
    "iso:country":"TH",
    "name:tha_x_preferred":[
        "Ban Nong Yaplong"
    ],
    "name:tha_x_variant":[
        "\u0e1a\u0e49\u0e32\u0e19\u0e2b\u0e19\u0e2d\u0e07\u0e2b\u0e0d\u0e49\u0e32\u0e1b\u0e25\u0e49\u0e2d\u0e07"
    ],
    "wof:name":"Ban Nong Yaplong",
    "wof:placetype":"locality"
},
  "geometry": {"coordinates":[104.38795,16.616],"type":"Point"}
}