{
  "type": "Feature",
  "properties": {
    "gn:admin1_code":"11.0",
    "gn:asciiname":"Ban Salok Bat",
    "gn:country_code":"TH",
    "gn:dem":45,
    "gn:feature_class":"P",
    "gn:feature_code":"PPL",
    "gn:name":"Ban Salok Bat",
    "gn:population":0,
    "gn:timezone":"Asia/Bangkok",
    "iso:country":"TH",
    "name:tha_x_preferred":[
        "\u0e1a\u0e49\u0e32\u0e19\u0e2a\u0e25\u0e01\u0e1a\u0e32\u0e15\u0e23\u0e4c"
    ],
    "name:und_x_variant":[
        "B\u0101n Wat Gut",
        "Ban Wat Kut",
        "Ban Wat Thut",
        "Ban Salok Bat"
    ],
    "wof:name":"Ban Salok Bat",
    "wof:placetype":"locality"
},
  "geometry": {"coordinates":[99.81775,15.98636],"type":"Point"}
}