{
  "type": "Feature",
  "properties": {
    "gn:admin1_code":"28",
    "gn:asciiname":"Ban Ron Thong",
    "gn:country_code":"TH",
    "gn:dem":198,
    "gn:feature_class":"P",
    "gn:feature_code":"PPL",
    "gn:name":"Ban Ron Thong",
    "gn:population":0,
    "gn:timezone":"Asia/Bangkok",
    "iso:country":"TH",
    "name:tha_x_preferred":[
        "\u0e1a\u0e49\u0e32\u0e19\u0e23\u0e48\u0e2d\u0e19\u0e17\u0e2d\u0e07"
    ],
    "wof:name":"Ban Ron Thong",
    "wof:placetype":"locality"
},
  "geometry": {"coordinates":[102.62925,14.86275],"type":"Point"}
}