{
  "type": "Feature",
  "properties": {
    "gn:admin1_code":"42.0",
    "gn:asciiname":"Ban Khlong Bang Chaman",
    "gn:country_code":"TH",
    "gn:dem":5,
    "gn:feature_class":"P",
    "gn:feature_code":"PPL",
    "gn:name":"Ban Khlong Bang Chaman",
    "gn:population":0,
    "gn:timezone":"Asia/Bangkok",
    "iso:country":"TH",
    "name:tha_x_preferred":[
        "\u0e1a\u0e49\u0e32\u0e19\u0e04\u0e25\u0e2d\u0e07\u0e1a\u0e32\u0e07\u0e09\u0e30\u0e21\u0e32\u0e19"
    ],
    "wof:name":"Ban Khlong Bang Chaman",
    "wof:placetype":"locality"
},
  "geometry": {"coordinates":[100.81492,13.64681],"type":"Point"}
}