{
  "type": "Feature",
  "properties": {
    "gn:admin1_code":"27.0",
    "gn:asciiname":"Ban Khok Nang Phloen",
    "gn:country_code":"TH",
    "gn:dem":206,
    "gn:feature_class":"P",
    "gn:feature_code":"PPL",
    "gn:name":"Ban Khok Nang Phloen",
    "gn:population":0,
    "gn:timezone":"Asia/Bangkok",
    "iso:country":"TH",
    "wof:name":"Ban Khok Nang Phloen",
    "wof:placetype":"locality"
},
  "geometry": {"coordinates":[102.05,14.66667],"type":"Point"}
}