{
  "type": "Feature",
  "properties": {
    "gn:admin1_code":"13.0",
    "gn:asciiname":"Ban Si Yaek Bueng Na Rang",
    "gn:country_code":"TH",
    "gn:dem":42,
    "gn:feature_class":"P",
    "gn:feature_code":"PPL",
    "gn:name":"Ban Si Yaek Bueng Na Rang",
    "gn:population":0,
    "gn:timezone":"Asia/Bangkok",
    "iso:country":"TH",
    "name:tha_x_preferred":[
        "\u0e1a\u0e49\u0e32\u0e19\u0e2a\u0e35\u0e48\u0e41\u0e22\u0e01\u0e1a\u0e36\u0e07\u0e19\u0e32\u0e23\u0e32\u0e07"
    ],
    "wof:lang_x_official":[
        "tha"
    ],
    "wof:lang_x_spoken":[
        "tha"
    ],
    "wof:name":"Ban Si Yaek Bueng Na Rang",
    "wof:placetype":"locality"
},
  "geometry": {"coordinates":[100.12822,16.19106],"type":"Point"}
}