{
  "type": "Feature",
  "properties": {
    "gn:admin1_code":"24",
    "gn:asciiname":"Ban Nong Khuean Chang Tai",
    "gn:country_code":"TH",
    "gn:dem":163,
    "gn:feature_class":"P",
    "gn:feature_code":"PPL",
    "gn:name":"Ban Nong Khuean Chang Tai",
    "gn:population":0,
    "gn:timezone":"Asia/Bangkok",
    "iso:country":"TH",
    "name:tha_x_preferred":[
        "\u0e1a\u0e49\u0e32\u0e19\u0e2b\u0e19\u0e2d\u0e07\u0e40\u0e02\u0e37\u0e48\u0e2d\u0e19\u0e0a\u0e49\u0e32\u0e07\u0e43\u0e15\u0e49"
    ],
    "wof:name":"Ban Nong Khuean Chang Tai",
    "wof:placetype":"locality"
},
  "geometry": {"coordinates":[103.18922000000001,16.17097],"type":"Point"}
}