{
  "type": "Feature",
  "properties": {
    "gn:admin1_code":"26.0",
    "gn:asciiname":"Ban Prong Ngam",
    "gn:country_code":"TH",
    "gn:dem":205,
    "gn:feature_class":"P",
    "gn:feature_code":"PPL",
    "gn:name":"Ban Prong Ngam",
    "gn:population":0,
    "gn:timezone":"Asia/Bangkok",
    "iso:country":"TH",
    "name:tha_x_preferred":[
        "\u0e1a\u0e49\u0e32\u0e19\u0e42\u0e1b\u0e23\u0e48\u0e07\u0e07\u0e32\u0e21"
    ],
    "wof:name":"Ban Prong Ngam",
    "wof:placetype":"locality"
},
  "geometry": {"coordinates":[102.16647,16.43706],"type":"Point"}
}