{
  "type": "Feature",
  "properties": {
    "gn:admin1_code":"51.0",
    "gn:asciiname":"Ban Amphoe Kao",
    "gn:country_code":"TH",
    "gn:dem":6,
    "gn:feature_class":"P",
    "gn:feature_code":"PPL",
    "gn:name":"Ban Amphoe Kao",
    "gn:population":0,
    "gn:timezone":"Asia/Bangkok",
    "iso:country":"TH",
    "name:tha_x_preferred":[
        "\u0e1a\u0e49\u0e32\u0e19\u0e2d\u0e33\u0e40\u0e20\u0e2d\u0e40\u0e01\u0e48\u0e32"
    ],
    "wof:name":"Ban Amphoe Kao",
    "wof:placetype":"locality"
},
  "geometry": {"coordinates":[100.05831999999999,14.21179],"type":"Point"}
}