{
  "type": "Feature",
  "properties": {
    "gn:admin1_code":"4.0",
    "gn:asciiname":"Ban Nam Pho",
    "gn:country_code":"TH",
    "gn:dem":358,
    "gn:feature_class":"P",
    "gn:feature_code":"PPL",
    "gn:name":"Ban Nam Pho",
    "gn:population":0,
    "gn:timezone":"Asia/Bangkok",
    "iso:country":"TH",
    "name:tha_x_preferred":[
        "\u0e1a\u0e49\u0e32\u0e19\u0e19\u0e49\u0e33\u0e40\u0e1e\u0e32\u0e30"
    ],
    "wof:name":"Ban Nam Pho",
    "wof:placetype":"locality"
},
  "geometry": {"coordinates":[100.83189,19.41828],"type":"Point"}
}