{
  "type": "Feature",
  "properties": {
    "gn:admin1_code":"27",
    "gn:asciiname":"Ban Mo Din Daeng",
    "gn:country_code":"TH",
    "gn:dem":295,
    "gn:feature_class":"P",
    "gn:feature_code":"PPL",
    "gn:name":"Ban Mo Din Daeng",
    "gn:population":0,
    "gn:timezone":"Asia/Bangkok",
    "iso:country":"TH",
    "name:tha_x_preferred":[
        "\u0e1a\u0e49\u0e32\u0e19\u0e21\u0e2d\u0e14\u0e34\u0e19\u0e41\u0e14\u0e07"
    ],
    "wof:name":"Ban Mo Din Daeng",
    "wof:placetype":"locality"
},
  "geometry": {"coordinates":[101.64664,14.94014],"type":"Point"}
}