{
  "type": "Feature",
  "properties": {
    "gn:admin1_code":"75.0",
    "gn:asciiname":"Ban Kham Klang",
    "gn:country_code":"TH",
    "gn:dem":173,
    "gn:feature_class":"P",
    "gn:feature_code":"PPL",
    "gn:name":"Ban Kham Klang",
    "gn:population":0,
    "gn:timezone":"Asia/Bangkok",
    "iso:country":"TH",
    "name:tha_x_preferred":[
        "\u0e1a\u0e49\u0e32\u0e19\u0e04\u0e33\u0e01\u0e25\u0e32\u0e07"
    ],
    "name:und_x_variant":[
        "Ban Kham"
    ],
    "wof:name":"Ban Kham Klang",
    "wof:placetype":"locality"
},
  "geometry": {"coordinates":[105.00514,14.60547],"type":"Point"}
}