{
  "type": "Feature",
  "properties": {
    "gn:admin1_code":"3.0",
    "gn:asciiname":"Ban Kosin Nimit",
    "gn:country_code":"TH",
    "gn:dem":390,
    "gn:feature_class":"P",
    "gn:feature_code":"PPL",
    "gn:name":"Ban Kosin Nimit",
    "gn:population":0,
    "gn:timezone":"Asia/Bangkok",
    "iso:country":"TH",
    "name:tha_x_preferred":[
        "\u0e1a\u0e49\u0e32\u0e19\u0e42\u0e01\u0e2a\u0e34\u0e19\u0e17\u0e23\u0e4c\u0e19\u0e34\u0e21\u0e34\u0e15"
    ],
    "wof:name":"Ban Kosin Nimit",
    "wof:placetype":"locality"
},
  "geometry": {"coordinates":[99.93241999999999,20.02045],"type":"Point"}
}