{
  "type": "Feature",
  "properties": {
    "gn:admin1_code":"14.0",
    "gn:asciiname":"Ban Wang Sung",
    "gn:country_code":"TH",
    "gn:dem":103,
    "gn:feature_class":"P",
    "gn:feature_code":"PPL",
    "gn:name":"Ban Wang Sung",
    "gn:population":0,
    "gn:timezone":"Asia/Bangkok",
    "iso:country":"TH",
    "name:tha_x_preferred":[
        "\u0e1a\u0e49\u0e32\u0e19\u0e27\u0e31\u0e07\u0e2a\u0e38\u0e48\u0e07"
    ],
    "wof:name":"Ban Wang Sung",
    "wof:placetype":"locality"
},
  "geometry": {"coordinates":[100.84403,16.02519],"type":"Point"}
}