{
  "type": "Feature",
  "properties": {
    "gn:admin1_code":"81.0",
    "gn:asciiname":"Ban Chai Si",
    "gn:country_code":"TH",
    "gn:dem":180,
    "gn:feature_class":"P",
    "gn:feature_code":"PPL",
    "gn:name":"Ban Chai Si",
    "gn:population":0,
    "gn:timezone":"Asia/Bangkok",
    "iso:country":"TH",
    "name:tha_x_preferred":[
        "\u0e1a\u0e49\u0e32\u0e19\u0e44\u0e0a\u0e22\u0e28\u0e23\u0e35"
    ],
    "wof:name":"Ban Chai Si",
    "wof:placetype":"locality"
},
  "geometry": {"coordinates":[103.73985999999999,18.07106],"type":"Point"}
}