{
  "type": "Feature",
  "properties": {
    "gn:admin1_code":"2.0",
    "gn:asciiname":"Ban Mae Khan",
    "gn:country_code":"TH",
    "gn:dem":286,
    "gn:feature_class":"P",
    "gn:feature_code":"PPL",
    "gn:name":"Ban Mae Khan",
    "gn:population":0,
    "gn:timezone":"Asia/Bangkok",
    "iso:country":"TH",
    "name:tha_x_preferred":[
        "\u0e1a\u0e49\u0e32\u0e19\u0e41\u0e21\u0e48\u0e02\u0e32\u0e19"
    ],
    "name:und_x_variant":[
        "Ban Sop Wang",
        "Ban Sop Khan",
        "Ban Mae Khan"
    ],
    "wof:name":"Ban Mae Khan",
    "wof:placetype":"locality"
},
  "geometry": {"coordinates":[98.85505999999999,18.52158],"type":"Point"}
}