{
  "type": "Feature",
  "properties": {
    "gn:admin1_code":"1.0",
    "gn:asciiname":"Ban Nam Bo Sape",
    "gn:country_code":"TH",
    "gn:dem":960,
    "gn:feature_class":"P",
    "gn:feature_code":"PPL",
    "gn:name":"Ban Nam Bo Sape",
    "gn:population":0,
    "gn:timezone":"Asia/Bangkok",
    "iso:country":"TH",
    "name:tha_x_preferred":[
        "\u0e1a\u0e49\u0e32\u0e19\u0e19\u0e49\u0e33\u0e1a\u0e48\u0e2d\u0e2a\u0e30\u0e40\u0e1b\u0e48"
    ],
    "wof:name":"Ban Nam Bo Sape",
    "wof:placetype":"locality"
},
  "geometry": {"coordinates":[98.19186000000001,19.50586],"type":"Point"}
}