{
  "type": "Feature",
  "properties": {
    "gn:admin1_code":"30.0",
    "gn:asciiname":"Ban Thang Sai Luat",
    "gn:country_code":"TH",
    "gn:dem":241,
    "gn:feature_class":"P",
    "gn:feature_code":"PPL",
    "gn:name":"Ban Thang Sai Luat",
    "gn:population":0,
    "gn:timezone":"Asia/Bangkok",
    "iso:country":"TH",
    "name:tha_x_preferred":[
        "\u0e1a\u0e49\u0e32\u0e19\u0e17\u0e32\u0e07\u0e2a\u0e32\u0e22\u0e25\u0e27\u0e14"
    ],
    "wof:lang_x_official":[
        "tha"
    ],
    "wof:lang_x_spoken":[
        "tha"
    ],
    "wof:name":"Ban Thang Sai Luat",
    "wof:placetype":"locality"
},
  "geometry": {"coordinates":[104.08928,14.48331],"type":"Point"}
}