{
  "type": "Feature",
  "properties": {
    "gn:admin1_code":"1.0",
    "gn:asciiname":"Ban Khon Phueng",
    "gn:country_code":"TH",
    "gn:dem":193,
    "gn:feature_class":"P",
    "gn:feature_code":"PPL",
    "gn:name":"Ban Khon Phueng",
    "gn:population":0,
    "gn:timezone":"Asia/Bangkok",
    "iso:country":"TH",
    "name:tha_x_preferred":[
        "\u0e1a\u0e49\u0e32\u0e19\u0e04\u0e2d\u0e19\u0e1c\u0e36\u0e49\u0e07"
    ],
    "name:und_x_variant":[
        "Ban Kon Phung",
        "Ban Khon Phueng"
    ],
    "wof:name":"Ban Khon Phueng",
    "wof:placetype":"locality"
},
  "geometry": {"coordinates":[97.93232999999999,18.04961],"type":"Point"}
}