{
  "type": "Feature",
  "properties": {
    "gn:admin1_code":"7.0",
    "gn:asciiname":"Ban Mae Pan",
    "gn:cc2":"TH",
    "gn:country_code":"TH",
    "gn:dem":137,
    "gn:feature_class":"P",
    "gn:feature_code":"PPL",
    "gn:name":"Ban Mae Pan",
    "gn:population":0,
    "gn:timezone":"Asia/Bangkok",
    "iso:country":"TH",
    "name:und_x_variant":[
        "B\u0101n Mea P\u0101n",
        "Ban Mae Pan"
    ],
    "wof:name":"Ban Mae Pan",
    "wof:placetype":"locality"
},
  "geometry": {"coordinates":[99.84999999999999,18.01667],"type":"Point"}
}