{
  "type": "Feature",
  "properties": {
    "gn:admin1_code":"52.0",
    "gn:asciiname":"Ban Tham Sarika",
    "gn:country_code":"TH",
    "gn:dem":36,
    "gn:feature_class":"P",
    "gn:feature_code":"PPL",
    "gn:name":"Ban Tham Sarika",
    "gn:population":0,
    "gn:timezone":"Asia/Bangkok",
    "iso:country":"TH",
    "name:tha_x_preferred":[
        "\u0e1a\u0e49\u0e32\u0e19\u0e16\u0e49\u0e33\u0e2a\u0e32\u0e23\u0e34\u0e01\u0e32"
    ],
    "wof:name":"Ban Tham Sarika",
    "wof:placetype":"locality"
},
  "geometry": {"coordinates":[99.73703,13.65061],"type":"Point"}
}