{
  "type": "Feature",
  "properties": {
    "gn:admin1_code":"10.0",
    "gn:asciiname":"Ban Wang Hom",
    "gn:country_code":"TH",
    "gn:dem":79,
    "gn:feature_class":"P",
    "gn:feature_code":"PPL",
    "gn:name":"Ban Wang Hom",
    "gn:population":0,
    "gn:timezone":"Asia/Bangkok",
    "iso:country":"TH",
    "name:tha_x_preferred":[
        "Ban Wang Hom"
    ],
    "name:tha_x_variant":[
        "\u0e1a\u0e49\u0e32\u0e19\u0e27\u0e31\u0e07\u0e2b\u0e2d\u0e21"
    ],
    "wof:name":"Ban Wang Hom",
    "wof:placetype":"locality"
},
  "geometry": {"coordinates":[100.04433,17.61322000000001],"type":"Point"}
}