{
  "type": "Feature",
  "properties": {
    "gn:admin1_code":"1.0",
    "gn:asciiname":"Ban Pu Kham Noi",
    "gn:country_code":"TH",
    "gn:dem":855,
    "gn:feature_class":"P",
    "gn:feature_code":"PPL",
    "gn:name":"Ban Pu Kham Noi",
    "gn:population":0,
    "gn:timezone":"Asia/Bangkok",
    "iso:country":"TH",
    "name:tha_x_preferred":[
        "\u0e1a\u0e49\u0e32\u0e19\u0e1b\u0e39\u0e48\u0e04\u0e33\u0e19\u0e49\u0e2d\u0e22"
    ],
    "name:und_x_variant":[
        "Ban Pu Kham"
    ],
    "wof:name":"Ban Pu Kham Noi",
    "wof:placetype":"locality"
},
  "geometry": {"coordinates":[97.73663000000001,17.88853],"type":"Point"}
}