{
  "type": "Feature",
  "properties": {
    "gn:admin1_code":"36",
    "gn:asciiname":"Ban Khan Hak",
    "gn:country_code":"TH",
    "gn:dem":6,
    "gn:feature_class":"P",
    "gn:feature_code":"PPL",
    "gn:name":"Ban Khan Hak",
    "gn:population":0,
    "gn:timezone":"Asia/Bangkok",
    "iso:country":"TH",
    "name:tha_x_preferred":[
        "\u0e1a\u0e49\u0e32\u0e19\u0e04\u0e32\u0e19\u0e2b\u0e31\u0e01"
    ],
    "wof:name":"Ban Khan Hak",
    "wof:placetype":"locality"
},
  "geometry": {"coordinates":[100.67478,14.2335],"type":"Point"}
}