{
  "type": "Feature",
  "properties": {
    "gn:admin1_code":"10.0",
    "gn:asciiname":"Ban Hat Song Khwae",
    "gn:cc2":"TH",
    "gn:country_code":"TH",
    "gn:dem":151,
    "gn:feature_class":"P",
    "gn:feature_code":"PPL",
    "gn:name":"Ban Hat Song Khwae",
    "gn:population":0,
    "gn:timezone":"Asia/Bangkok",
    "iso:country":"TH",
    "name:und_x_variant":[
        "B\u0101n H\u0101t Saung Keo",
        "Ban Hat Song Khwae"
    ],
    "wof:lang_x_official":[
        "tha"
    ],
    "wof:lang_x_spoken":[
        "tha"
    ],
    "wof:name":"Ban Hat Song Khwae",
    "wof:placetype":"locality"
},
  "geometry": {"coordinates":[100.37694,17.84],"type":"Point"}
}