{
  "type": "Feature",
  "properties": {
    "gn:admin1_code":"4.0",
    "gn:asciiname":"Ban Kom",
    "gn:country_code":"TH",
    "gn:dem":316,
    "gn:feature_class":"P",
    "gn:feature_code":"PPL",
    "gn:name":"Ban Kom",
    "gn:population":0,
    "gn:timezone":"Asia/Bangkok",
    "iso:country":"TH",
    "name:tha_x_preferred":[
        "\u0e1a\u0e49\u0e32\u0e19\u0e01\u0e2d\u0e21"
    ],
    "name:und_x_variant":[
        "B\u0101n Huai Grom",
        "Ban Huai Krom",
        "Ban Huai Kom",
        "Ban Kom"
    ],
    "wof:lang_x_official":[
        "tha"
    ],
    "wof:lang_x_spoken":[
        "tha"
    ],
    "wof:name":"Ban Kom",
    "wof:placetype":"locality"
},
  "geometry": {"coordinates":[100.95511,18.67686],"type":"Point"}
}