{
  "type": "Feature",
  "properties": {
    "gn:admin1_code":"65.0",
    "gn:asciiname":"Ban Na Khuan",
    "gn:country_code":"TH",
    "gn:dem":58,
    "gn:feature_class":"P",
    "gn:feature_code":"PPL",
    "gn:name":"Ban Na Khuan",
    "gn:population":0,
    "gn:timezone":"Asia/Bangkok",
    "iso:country":"TH",
    "name:tha_x_preferred":[
        "\u0e1a\u0e49\u0e32\u0e19\u0e2b\u0e19\u0e49\u0e32\u0e04\u0e27\u0e19"
    ],
    "wof:name":"Ban Na Khuan",
    "wof:placetype":"locality"
},
  "geometry": {"coordinates":[99.40183,7.82617],"type":"Point"}
}