{
  "type": "Feature",
  "properties": {
    "gn:admin1_code":"11.0",
    "gn:asciiname":"Ban Noen Samran",
    "gn:country_code":"TH",
    "gn:dem":56,
    "gn:feature_class":"P",
    "gn:feature_code":"PPL",
    "gn:name":"Ban Noen Samran",
    "gn:population":0,
    "gn:timezone":"Asia/Bangkok",
    "iso:country":"TH",
    "name:tha_x_preferred":[
        "\u0e1a\u0e49\u0e32\u0e19\u0e40\u0e19\u0e34\u0e19\u0e2a\u0e33\u0e23\u0e32\u0e0d"
    ],
    "wof:name":"Ban Noen Samran",
    "wof:placetype":"locality"
},
  "geometry": {"coordinates":[99.89583,16.51486],"type":"Point"}
}