{
  "type": "Feature",
  "properties": {
    "gn:admin1_code":"26.0",
    "gn:asciiname":"Ban Khok Krabueang Hai",
    "gn:country_code":"TH",
    "gn:dem":671,
    "gn:feature_class":"P",
    "gn:feature_code":"PPL",
    "gn:name":"Ban Khok Krabueang Hai",
    "gn:population":0,
    "gn:timezone":"Asia/Bangkok",
    "iso:country":"TH",
    "name:tha_x_preferred":[
        "\u0e1a\u0e49\u0e32\u0e19\u0e42\u0e04\u0e01\u0e01\u0e23\u0e30\u0e40\u0e1a\u0e37\u0e49\u0e2d\u0e07\u0e44\u0e2b"
    ],
    "wof:lang_x_official":[
        "tha"
    ],
    "wof:lang_x_spoken":[
        "tha"
    ],
    "wof:name":"Ban Khok Krabueang Hai",
    "wof:placetype":"locality"
},
  "geometry": {"coordinates":[101.41489,15.63561],"type":"Point"}
}