{
  "type": "Feature",
  "properties": {
    "gn:admin1_code":"76.0",
    "gn:asciiname":"Ban Kham Ta Na",
    "gn:country_code":"TH",
    "gn:dem":199,
    "gn:feature_class":"P",
    "gn:feature_code":"PPL",
    "gn:name":"Ban Kham Ta Na",
    "gn:population":0,
    "gn:timezone":"Asia/Bangkok",
    "iso:country":"TH",
    "name:tha_x_preferred":[
        "\u0e1a\u0e49\u0e32\u0e19\u0e04\u0e33\u0e15\u0e32\u0e19\u0e32"
    ],
    "wof:name":"Ban Kham Ta Na",
    "wof:placetype":"locality"
},
  "geometry": {"coordinates":[103.18389000000001,17.44861],"type":"Point"}
}