{
  "type": "Feature",
  "properties": {
    "gn:admin1_code":"28",
    "gn:asciiname":"Ban Khok Ta Chu",
    "gn:country_code":"TH",
    "gn:dem":188,
    "gn:feature_class":"P",
    "gn:feature_code":"PPL",
    "gn:name":"Ban Khok Ta Chu",
    "gn:population":0,
    "gn:timezone":"Asia/Bangkok",
    "iso:country":"TH",
    "name:tha_x_preferred":[
        "\u0e1a\u0e49\u0e32\u0e19\u0e42\u0e04\u0e01\u0e15\u0e32\u0e0a\u0e39"
    ],
    "wof:name":"Ban Khok Ta Chu",
    "wof:placetype":"locality"
},
  "geometry": {"coordinates":[102.89803000000001,14.63586],"type":"Point"}
}