{
  "type": "Feature",
  "properties": {
    "gn:admin1_code":"29",
    "gn:asciiname":"Ban Ang Kan",
    "gn:country_code":"TH",
    "gn:dem":171,
    "gn:feature_class":"P",
    "gn:feature_code":"PPL",
    "gn:name":"Ban Ang Kan",
    "gn:population":0,
    "gn:timezone":"Asia/Bangkok",
    "iso:country":"TH",
    "name:tha_x_preferred":[
        "\u0e1a\u0e49\u0e32\u0e19\u0e2d\u0e31\u0e07\u0e01\u0e31\u0e0d"
    ],
    "wof:name":"Ban Ang Kan",
    "wof:placetype":"locality"
},
  "geometry": {"coordinates":[103.41213999999999,14.64314],"type":"Point"}
}