{
  "type": "Feature",
  "properties": {
    "gn:admin1_code":"9.0",
    "gn:asciiname":"Ban Lan Krabue",
    "gn:country_code":"TH",
    "gn:dem":108,
    "gn:feature_class":"P",
    "gn:feature_code":"PPL",
    "gn:name":"Ban Lan Krabue",
    "gn:population":0,
    "gn:timezone":"Asia/Bangkok",
    "iso:country":"TH",
    "name:tha_x_preferred":[
        "\u0e1a\u0e49\u0e32\u0e19\u0e25\u0e32\u0e19\u0e01\u0e23\u0e30\u0e1a\u0e37\u0e2d"
    ],
    "name:und_x_variant":[
        "Ban Lan Krabu"
    ],
    "wof:name":"Ban Lan Krabue",
    "wof:placetype":"locality"
},
  "geometry": {"coordinates":[99.47469,17.10472],"type":"Point"}
}