{
  "type": "Feature",
  "properties": {
    "gn:admin1_code":"6.0",
    "gn:asciiname":"Ban I Thuk",
    "gn:cc2":"TH",
    "gn:country_code":"TH",
    "gn:dem":158,
    "gn:feature_class":"P",
    "gn:feature_code":"PPL",
    "gn:name":"Ban I Thuk",
    "gn:population":0,
    "gn:timezone":"Asia/Bangkok",
    "iso:country":"TH",
    "name:und_x_variant":[
        "B\u0101n Wang-i-Tuk",
        "Ban Wang-i-Thuk",
        "Ban I Thuk"
    ],
    "wof:name":"Ban I Thuk",
    "wof:placetype":"locality"
},
  "geometry": {"coordinates":[99.15000000000001,17.46667],"type":"Point"}
}