{
  "type": "Feature",
  "properties": {
    "gn:admin1_code":"60.0",
    "gn:asciiname":"Ban Mae Mok",
    "gn:country_code":"TH",
    "gn:dem":24,
    "gn:feature_class":"P",
    "gn:feature_code":"PPL",
    "gn:name":"Ban Mae Mok",
    "gn:population":0,
    "gn:timezone":"Asia/Bangkok",
    "iso:country":"TH",
    "name:tha_x_preferred":[
        "\u0e1a\u0e49\u0e32\u0e19\u0e41\u0e21\u0e48\u0e42\u0e21\u0e01\u0e02\u0e4c"
    ],
    "wof:name":"Ban Mae Mok",
    "wof:placetype":"locality"
},
  "geometry": {"coordinates":[99.53242,9.12578],"type":"Point"}
}