{
  "type": "Feature",
  "properties": {
    "gn:admin1_code":"68.0",
    "gn:asciiname":"Ban Khlong Thurian",
    "gn:country_code":"TH",
    "gn:dem":99,
    "gn:feature_class":"P",
    "gn:feature_code":"PPL",
    "gn:name":"Ban Khlong Thurian",
    "gn:population":0,
    "gn:timezone":"Asia/Bangkok",
    "iso:country":"TH",
    "name:tha_x_preferred":[
        "\u0e1a\u0e49\u0e32\u0e19\u0e04\u0e25\u0e2d\u0e07\u0e17\u0e38\u0e40\u0e23\u0e35\u0e22\u0e19"
    ],
    "wof:name":"Ban Khlong Thurian",
    "wof:placetype":"locality"
},
  "geometry": {"coordinates":[100.79900000000001,6.73147],"type":"Point"}
}