{
  "type": "Feature",
  "properties": {
    "gn:admin1_code":"70.0",
    "gn:asciiname":"Ban Kho Ka Po",
    "gn:country_code":"TH",
    "gn:dem":65,
    "gn:feature_class":"P",
    "gn:feature_code":"PPL",
    "gn:name":"Ban Kho Ka Po",
    "gn:population":0,
    "gn:timezone":"Asia/Bangkok",
    "iso:country":"TH",
    "name:tha_x_preferred":[
        "\u0e1a\u0e49\u0e32\u0e19\u0e40\u0e06\u0e32\u0e30\u0e01\u0e32\u0e42\u0e1b"
    ],
    "wof:name":"Ban Kho Ka Po",
    "wof:placetype":"locality"
},
  "geometry": {"coordinates":[101.27285999999999,6.21761],"type":"Point"}
}