{
  "type": "Feature",
  "properties": {
    "gn:admin1_code":"51.0",
    "gn:asciiname":"Ban Rang Krang",
    "gn:country_code":"TH",
    "gn:dem":12,
    "gn:feature_class":"P",
    "gn:feature_code":"PPL",
    "gn:name":"Ban Rang Krang",
    "gn:population":0,
    "gn:timezone":"Asia/Bangkok",
    "iso:country":"TH",
    "name:tha_x_preferred":[
        "\u0e1a\u0e49\u0e32\u0e19\u0e23\u0e32\u0e07\u0e01\u0e23\u0e48\u0e32\u0e07"
    ],
    "name:und_x_variant":[
        "Ban Nong Krang"
    ],
    "wof:name":"Ban Rang Krang",
    "wof:placetype":"locality"
},
  "geometry": {"coordinates":[99.84650000000001,14.29483],"type":"Point"}
}