{
  "type": "Feature",
  "properties": {
    "gn:admin1_code":"18.0",
    "gn:asciiname":"Ban Mueang Phrae",
    "gn:country_code":"TH",
    "gn:dem":474,
    "gn:feature_class":"P",
    "gn:feature_code":"PPL",
    "gn:name":"Ban Mueang Phrae",
    "gn:population":0,
    "gn:timezone":"Asia/Bangkok",
    "iso:country":"TH",
    "name:tha_x_preferred":[
        "\u0e1a\u0e49\u0e32\u0e19\u0e40\u0e2b\u0e21\u0e37\u0e2d\u0e07\u0e41\u0e1e\u0e23\u0e48"
    ],
    "name:und_x_variant":[
        "B\u0101n Muang Phrea",
        "Ban Muang Phrae",
        "Ban Mueang Phrae"
    ],
    "wof:name":"Ban Mueang Phrae",
    "wof:placetype":"locality"
},
  "geometry": {"coordinates":[101.07678,17.50389],"type":"Point"}
}