{
  "type": "Feature",
  "properties": {
    "gn:admin1_code":"29",
    "gn:asciiname":"Ban Laboek",
    "gn:country_code":"TH",
    "gn:dem":173,
    "gn:feature_class":"P",
    "gn:feature_code":"PPL",
    "gn:name":"Ban Laboek",
    "gn:population":0,
    "gn:timezone":"Asia/Bangkok",
    "iso:country":"TH",
    "name:tha_x_preferred":[
        "\u0e1a\u0e49\u0e32\u0e19\u0e25\u0e30\u0e40\u0e1a\u0e34\u0e01"
    ],
    "wof:name":"Ban Laboek",
    "wof:placetype":"locality"
},
  "geometry": {"coordinates":[103.30871999999999,14.58194],"type":"Point"}
}