{
  "type": "Feature",
  "properties": {
    "gn:country":"TH",
    "gn:fcode":"PPL",
    "gn:population":0,
    "iso:country":"TH",
    "name:deu_x_preferred":[
        "Song Dao"
    ],
    "name:eng_x_preferred":[
        "Song Dao"
    ],
    "name:tha_x_preferred":[
        "\u0e40\u0e17\u0e28\u0e1a\u0e32\u0e25\u0e15\u0e33\u0e1a\u0e25\u0e2a\u0e48\u0e2d\u0e07\u0e14\u0e32\u0e27"
    ],
    "qs:name":"Song Dao",
    "qs:name_adm0":"Thailand",
    "qs:name_adm1":"Sakon Nakhon",
    "qs:photos":2,
    "qs:photos_1k":1,
    "qs:photos_9k":1,
    "qs:photos_9r":1,
    "qs:photos_all":2,
    "qs:photos_sr":1,
    "qs:placetype":"Town",
    "qs:pop_sr":"0",
    "wd:wordcount":251,
    "wof:name":"Song Dao",
    "wof:placetype":"locality",
    "wof:population":0
},
  "geometry": {"coordinates":[103.53333000000001,17.41667],"type":"Point"}
}