{
  "type": "Feature",
  "properties": {
    "gn:admin1_code":"55.0",
    "gn:asciiname":"Ban San Phanom",
    "gn:country_code":"TH",
    "gn:dem":3,
    "gn:feature_class":"P",
    "gn:feature_code":"PPL",
    "gn:name":"Ban San Phanom",
    "gn:population":0,
    "gn:timezone":"Asia/Bangkok",
    "iso:country":"TH",
    "name:tha_x_preferred":[
        "\u0e1a\u0e49\u0e32\u0e19\u0e2a\u0e31\u0e19\u0e1e\u0e30\u0e19\u0e2d\u0e21"
    ],
    "wof:name":"Ban San Phanom",
    "wof:placetype":"locality"
},
  "geometry": {"coordinates":[100.26925,13.61856],"type":"Point"}
}