{
  "type": "Feature",
  "properties": {
    "gn:admin1_code":"64.0",
    "gn:asciiname":"Ban Phrong Tum",
    "gn:country_code":"TH",
    "gn:dem":0,
    "gn:feature_class":"P",
    "gn:feature_code":"PPL",
    "gn:name":"Ban Phrong Tum",
    "gn:population":0,
    "gn:timezone":"Asia/Bangkok",
    "iso:country":"TH",
    "name:tha_x_preferred":[
        "\u0e1a\u0e49\u0e32\u0e19\u0e42\u0e1e\u0e23\u0e07\u0e15\u0e38\u0e21"
    ],
    "wof:name":"Ban Phrong Tum",
    "wof:placetype":"locality"
},
  "geometry": {"coordinates":[100.22874,8.17898],"type":"Point"}
}