{
  "type": "Feature",
  "properties": {
    "gn:admin1_code":"61.0",
    "gn:asciiname":"Ban Ko Tang Len",
    "gn:country_code":"TH",
    "gn:dem":1,
    "gn:feature_class":"P",
    "gn:feature_code":"PPL",
    "gn:name":"Ban Ko Tang Len",
    "gn:population":0,
    "gn:timezone":"Asia/Bangkok",
    "iso:country":"TH",
    "wof:name":"Ban Ko Tang Len",
    "wof:placetype":"locality"
},
  "geometry": {"coordinates":[98.59999999999999,8.36667],"type":"Point"}
}