{
  "type": "Feature",
  "properties": {
    "gn:admin1_code":"27",
    "gn:asciiname":"Ban Burana Phanit",
    "gn:country_code":"TH",
    "gn:dem":181,
    "gn:feature_class":"P",
    "gn:feature_code":"PPL",
    "gn:name":"Ban Burana Phanit",
    "gn:population":0,
    "gn:timezone":"Asia/Bangkok",
    "iso:country":"TH",
    "name:tha_x_preferred":[
        "\u0e1a\u0e49\u0e32\u0e19\u0e1a\u0e39\u0e23\u0e13\u0e1e\u0e32\u0e13\u0e34\u0e0a\u0e22\u0e4c"
    ],
    "wof:name":"Ban Burana Phanit",
    "wof:placetype":"locality"
},
  "geometry": {"coordinates":[102.18083,15.06181],"type":"Point"}
}