{
  "type": "Feature",
  "properties": {
    "gn:admin1_code":"64.0",
    "gn:asciiname":"Ban Chang",
    "gn:country_code":"TH",
    "gn:dem":13,
    "gn:feature_class":"P",
    "gn:feature_code":"PPL",
    "gn:name":"Ban Chang",
    "gn:population":0,
    "gn:timezone":"Asia/Bangkok",
    "iso:country":"TH",
    "name:ceb_x_preferred":[
        "Ban Chang"
    ],
    "name:tha_x_preferred":[
        "\u0e1a\u0e49\u0e32\u0e19\u0e09\u0e32\u0e07"
    ],
    "name:und_x_variant":[
        "Ban Chang Sai"
    ],
    "wof:lang_x_official":[
        "tha"
    ],
    "wof:lang_x_spoken":[
        "tha"
    ],
    "wof:name":"Ban Chang",
    "wof:placetype":"locality"
},
  "geometry": {"coordinates":[99.91414,8.55975],"type":"Point"}
}