{
  "type": "Feature",
  "properties": {
    "gn:admin1_code":"30.0",
    "gn:asciiname":"Ban That Thong",
    "gn:country_code":"TH",
    "gn:dem":174,
    "gn:feature_class":"P",
    "gn:feature_code":"PPL",
    "gn:name":"Ban That Thong",
    "gn:population":0,
    "gn:timezone":"Asia/Bangkok",
    "iso:country":"TH",
    "name:tha_x_preferred":[
        "\u0e1a\u0e49\u0e32\u0e19\u0e18\u0e32\u0e15\u0e38\u0e17\u0e2d\u0e07"
    ],
    "name:und_x_variant":[
        "Ban That"
    ],
    "wof:name":"Ban That Thong",
    "wof:placetype":"locality"
},
  "geometry": {"coordinates":[104.08842,14.56581],"type":"Point"}
}