{
  "type": "Feature",
  "properties": {
    "gn:admin1_code":"8.0",
    "gn:asciiname":"Ban Nong Ta Chuen",
    "gn:country_code":"TH",
    "gn:dem":118,
    "gn:feature_class":"P",
    "gn:feature_code":"PPL",
    "gn:name":"Ban Nong Ta Chuen",
    "gn:population":0,
    "gn:timezone":"Asia/Bangkok",
    "iso:country":"TH",
    "name:tha_x_preferred":[
        "Ban Nong Ta Chuen"
    ],
    "name:tha_x_variant":[
        "\u0e1a\u0e49\u0e32\u0e19\u0e2b\u0e19\u0e2d\u0e07\u0e15\u0e32\u0e0a\u0e37\u0e48\u0e19"
    ],
    "wof:name":"Ban Nong Ta Chuen",
    "wof:placetype":"locality"
},
  "geometry": {"coordinates":[99.13703,16.80692],"type":"Point"}
}