{
  "type": "Feature",
  "properties": {
    "gn:admin1_code":"53.0",
    "gn:asciiname":"Ban Khlong Sawit Chat",
    "gn:country_code":"TH",
    "gn:dem":4,
    "gn:feature_class":"P",
    "gn:feature_code":"PPL",
    "gn:name":"Ban Khlong Sawit Chat",
    "gn:population":0,
    "gn:timezone":"Asia/Bangkok",
    "iso:country":"TH",
    "name:tha_x_preferred":[
        "\u0e1a\u0e49\u0e32\u0e19\u0e04\u0e25\u0e2d\u0e07\u0e2a\u0e27\u0e34\u0e15\u0e0a\u0e32\u0e15\u0e34"
    ],
    "wof:name":"Ban Khlong Sawit Chat",
    "wof:placetype":"locality"
},
  "geometry": {"coordinates":[100.22002999999999,13.93069],"type":"Point"}
}