{
  "type": "Feature",
  "properties": {
    "gn:admin1_code":"11.0",
    "gn:asciiname":"Ban Bueng Kio",
    "gn:country_code":"TH",
    "gn:dem":56,
    "gn:feature_class":"P",
    "gn:feature_code":"PPL",
    "gn:name":"Ban Bueng Kio",
    "gn:population":0,
    "gn:timezone":"Asia/Bangkok",
    "iso:country":"TH",
    "name:tha_x_preferred":[
        "\u0e1a\u0e49\u0e32\u0e19\u0e1a\u0e36\u0e07\u0e01\u0e34\u0e48\u0e27"
    ],
    "wof:name":"Ban Bueng Kio",
    "wof:placetype":"locality"
},
  "geometry": {"coordinates":[99.87111,16.64331],"type":"Point"}
}