{
  "type": "Feature",
  "properties": {
    "gn:admin1_code":"2.0",
    "gn:asciiname":"Ban Mae Tae Lae Kui",
    "gn:country_code":"TH",
    "gn:dem":1025,
    "gn:feature_class":"P",
    "gn:feature_code":"PPL",
    "gn:name":"Ban Mae Tae Lae Kui",
    "gn:population":0,
    "gn:timezone":"Asia/Bangkok",
    "iso:country":"TH",
    "name:tha_x_preferred":[
        "\u0e1a\u0e49\u0e32\u0e19\u0e41\u0e21\u0e30\u0e41\u0e15\u0e30\u0e41\u0e25\u0e30\u0e01\u0e38\u0e22"
    ],
    "wof:name":"Ban Mae Tae Lae Kui",
    "wof:placetype":"locality"
},
  "geometry": {"coordinates":[98.34489000000001,17.33592],"type":"Point"}
}