{
  "type": "Feature",
  "properties": {
    "gn:admin1_code":"11.0",
    "gn:asciiname":"Ban Pho Thale Klang",
    "gn:country_code":"TH",
    "gn:dem":69,
    "gn:feature_class":"P",
    "gn:feature_code":"PPL",
    "gn:name":"Ban Pho Thale Klang",
    "gn:population":0,
    "gn:timezone":"Asia/Bangkok",
    "iso:country":"TH",
    "name:tha_x_preferred":[
        "\u0e1a\u0e49\u0e32\u0e19\u0e42\u0e1e\u0e18\u0e34\u0e4c\u0e17\u0e30\u0e40\u0e25\u0e01\u0e25\u0e32\u0e07"
    ],
    "wof:name":"Ban Pho Thale Klang",
    "wof:placetype":"locality"
},
  "geometry": {"coordinates":[99.68767,16.47136],"type":"Point"}
}