{
  "type": "Feature",
  "properties": {
    "gn:admin1_code":"52.0",
    "gn:asciiname":"Ban Chaloem Phra Kiat",
    "gn:country_code":"TH",
    "gn:dem":10,
    "gn:feature_class":"P",
    "gn:feature_code":"PPL",
    "gn:name":"Ban Chaloem Phra Kiat",
    "gn:population":0,
    "gn:timezone":"Asia/Bangkok",
    "iso:country":"TH",
    "name:tha_x_preferred":[
        "\u0e1a\u0e49\u0e32\u0e19\u0e40\u0e09\u0e25\u0e34\u0e21\u0e1e\u0e23\u0e30\u0e40\u0e01\u0e35\u0e22\u0e23\u0e15\u0e34"
    ],
    "wof:name":"Ban Chaloem Phra Kiat",
    "wof:placetype":"locality"
},
  "geometry": {"coordinates":[99.91583,13.77744],"type":"Point"}
}