{
  "type": "Feature",
  "properties": {
    "gn:admin1_code":"33.0",
    "gn:asciiname":"Ban Long Kabao",
    "gn:country_code":"TH",
    "gn:dem":18,
    "gn:feature_class":"P",
    "gn:feature_code":"PPL",
    "gn:name":"Ban Long Kabao",
    "gn:population":0,
    "gn:timezone":"Asia/Bangkok",
    "iso:country":"TH",
    "name:tha_x_preferred":[
        "\u0e1a\u0e49\u0e32\u0e19\u0e25\u0e48\u0e2d\u0e07\u0e01\u0e30\u0e40\u0e1a\u0e32"
    ],
    "name:und_x_variant":[
        "Ban Rong Krabao",
        "Ban Rong Kabao",
        "Ban Long Kabao"
    ],
    "wof:lang_x_official":[
        "tha"
    ],
    "wof:lang_x_spoken":[
        "tha"
    ],
    "wof:name":"Ban Long Kabao",
    "wof:placetype":"locality"
},
  "geometry": {"coordinates":[100.35709,15.04997],"type":"Point"}
}