{
  "type": "Feature",
  "properties": {
    "gn:admin1_code":"23.0",
    "gn:asciiname":"Ban Som Hong",
    "gn:country_code":"TH",
    "gn:dem":149,
    "gn:feature_class":"P",
    "gn:feature_code":"PPL",
    "gn:name":"Ban Som Hong",
    "gn:population":0,
    "gn:timezone":"Asia/Bangkok",
    "iso:country":"TH",
    "name:tha_x_preferred":[
        "\u0e1a\u0e49\u0e32\u0e19\u0e2a\u0e49\u0e21\u0e42\u0e2e\u0e07"
    ],
    "wof:name":"Ban Som Hong",
    "wof:placetype":"locality"
},
  "geometry": {"coordinates":[103.57013999999999,16.25792],"type":"Point"}
}