{
  "type": "Feature",
  "properties": {
    "gn:admin1_code":"49.0",
    "gn:asciiname":"Ban Tak Waeng Bon",
    "gn:country_code":"TH",
    "gn:dem":34,
    "gn:feature_class":"P",
    "gn:feature_code":"PPL",
    "gn:name":"Ban Tak Waeng Bon",
    "gn:population":0,
    "gn:timezone":"Asia/Bangkok",
    "iso:country":"TH",
    "name:tha_x_preferred":[
        "\u0e1a\u0e49\u0e32\u0e19\u0e15\u0e32\u0e01\u0e41\u0e27\u0e49\u0e07\u0e1a\u0e19"
    ],
    "wof:name":"Ban Tak Waeng Bon",
    "wof:placetype":"locality"
},
  "geometry": {"coordinates":[102.54642,12.56433],"type":"Point"}
}