{
  "type": "Feature",
  "properties": {
    "gn:admin1_code":"3.0",
    "gn:asciiname":"Ban Pa Sak Luang",
    "gn:country_code":"TH",
    "gn:dem":387,
    "gn:feature_class":"P",
    "gn:feature_code":"PPL",
    "gn:name":"Ban Pa Sak Luang",
    "gn:population":0,
    "gn:timezone":"Asia/Bangkok",
    "iso:country":"TH",
    "wof:name":"Ban Pa Sak Luang",
    "wof:placetype":"locality"
},
  "geometry": {"coordinates":[99.95056,20.22611],"type":"Point"}
}