{
  "type": "Feature",
  "properties": {
    "gn:admin1_code":"30.0",
    "gn:asciiname":"Ban Non Suan",
    "gn:country_code":"TH",
    "gn:dem":141,
    "gn:feature_class":"P",
    "gn:feature_code":"PPL",
    "gn:name":"Ban Non Suan",
    "gn:population":0,
    "gn:timezone":"Asia/Bangkok",
    "iso:country":"TH",
    "name:tha_x_preferred":[
        "\u0e1a\u0e49\u0e32\u0e19\u0e42\u0e19\u0e19\u0e2a\u0e27\u0e19"
    ],
    "wof:name":"Ban Non Suan",
    "wof:placetype":"locality"
},
  "geometry": {"coordinates":[104.48811000000001,14.86047],"type":"Point"}
}