{
  "type": "Feature",
  "properties": {
    "gn:admin1_code":"3.0",
    "gn:asciiname":"Ban San Ngon Thai",
    "gn:country_code":"TH",
    "gn:dem":388,
    "gn:feature_class":"P",
    "gn:feature_code":"PPL",
    "gn:name":"Ban San Ngon Thai",
    "gn:population":0,
    "gn:timezone":"Asia/Bangkok",
    "iso:country":"TH",
    "name:tha_x_preferred":[
        "\u0e1a\u0e49\u0e32\u0e19\u0e2a\u0e31\u0e19\u0e07\u0e49\u0e2d\u0e19\u0e44\u0e16"
    ],
    "wof:name":"Ban San Ngon Thai",
    "wof:placetype":"locality"
},
  "geometry": {"coordinates":[100.01447,19.85703],"type":"Point"}
}