{
  "type": "Feature",
  "properties": {
    "gn:admin1_code":"39.0",
    "gn:asciiname":"Ban Mu Thai",
    "gn:country_code":"TH",
    "gn:dem":7,
    "gn:feature_class":"P",
    "gn:feature_code":"PPL",
    "gn:name":"Ban Mu Thai",
    "gn:population":0,
    "gn:timezone":"Asia/Bangkok",
    "iso:country":"TH",
    "name:tha_x_preferred":[
        "\u0e1a\u0e49\u0e32\u0e19\u0e2b\u0e21\u0e39\u0e48\u0e44\u0e17\u0e22"
    ],
    "wof:name":"Ban Mu Thai",
    "wof:placetype":"locality"
},
  "geometry": {"coordinates":[100.47311000000001,13.99619],"type":"Point"}
}