{
  "type": "Feature",
  "properties": {
    "gn:admin1_code":"43.0",
    "gn:asciiname":"Ban Sabok Khiao",
    "gn:country_code":"TH",
    "gn:dem":9,
    "gn:feature_class":"P",
    "gn:feature_code":"PPL",
    "gn:name":"Ban Sabok Khiao",
    "gn:population":0,
    "gn:timezone":"Asia/Bangkok",
    "iso:country":"TH",
    "name:tha_x_preferred":[
        "\u0e1a\u0e49\u0e32\u0e19\u0e2a\u0e1a\u0e01\u0e40\u0e0a\u0e35\u0e22\u0e27"
    ],
    "name:und_x_variant":[
        "Ban Sabok Khieo",
        "Ban Sabok Khiao"
    ],
    "wof:name":"Ban Sabok Khiao",
    "wof:placetype":"locality"
},
  "geometry": {"coordinates":[101.27200000000001,14.19839],"type":"Point"}
}