{
  "type": "Feature",
  "properties": {
    "gn:admin1_code":"30.0",
    "gn:asciiname":"Ban Phu Ngoen",
    "gn:country_code":"TH",
    "gn:dem":196,
    "gn:feature_class":"P",
    "gn:feature_code":"PPL",
    "gn:name":"Ban Phu Ngoen",
    "gn:population":0,
    "gn:timezone":"Asia/Bangkok",
    "iso:country":"TH",
    "name:tha_x_preferred":[
        "\u0e1a\u0e49\u0e32\u0e19\u0e20\u0e39\u0e40\u0e07\u0e34\u0e19"
    ],
    "wof:name":"Ban Phu Ngoen",
    "wof:placetype":"locality"
},
  "geometry": {"coordinates":[104.53456,14.74072],"type":"Point"}
}