{
  "type": "Feature",
  "properties": {
    "gn:admin1_code":"52.0",
    "gn:asciiname":"Muban Lam Plathio Winla",
    "gn:country_code":"TH",
    "gn:dem":9,
    "gn:feature_class":"P",
    "gn:feature_code":"PPL",
    "gn:name":"Muban Lam Plathio Winla",
    "gn:population":0,
    "gn:timezone":"Asia/Bangkok",
    "iso:country":"TH",
    "name:tha_x_preferred":[
        "\u0e2b\u0e21\u0e39\u0e48\u0e1a\u0e49\u0e32\u0e19\u0e25\u0e33\u0e1b\u0e25\u0e32\u0e17\u0e34\u0e27\u0e27\u0e34\u0e25\u0e25\u0e48\u0e32"
    ],
    "wof:name":"Muban Lam Plathio Winla",
    "wof:placetype":"locality"
},
  "geometry": {"coordinates":[99.84283000000001,13.53628],"type":"Point"}
}