{
  "type": "Feature",
  "properties": {
    "gn:admin1_code":"2.0",
    "gn:asciiname":"Ban Mae Na Poe",
    "gn:country_code":"TH",
    "gn:dem":920,
    "gn:feature_class":"P",
    "gn:feature_code":"PPL",
    "gn:name":"Ban Mae Na Poe",
    "gn:population":0,
    "gn:timezone":"Asia/Bangkok",
    "iso:country":"TH",
    "name:tha_x_preferred":[
        "\u0e1a\u0e49\u0e32\u0e19\u0e41\u0e21\u0e48\u0e19\u0e32\u0e40\u0e1b\u0e2d\u0e30"
    ],
    "name:und_x_variant":[
        "Ban Nam Poe",
        "Ban Mae Na Poe"
    ],
    "wof:name":"Ban Mae Na Poe",
    "wof:placetype":"locality"
},
  "geometry": {"coordinates":[98.53942000000001,18.90894],"type":"Point"}
}