{
  "type": "Feature",
  "properties": {
    "gn:admin1_code":"18.0",
    "gn:asciiname":"Ban Nam Man",
    "gn:country_code":"TH",
    "gn:dem":675,
    "gn:feature_class":"P",
    "gn:feature_code":"PPL",
    "gn:name":"Ban Nam Man",
    "gn:population":0,
    "gn:timezone":"Asia/Bangkok",
    "iso:country":"TH",
    "name:tha_x_preferred":[
        "\u0e1a\u0e49\u0e32\u0e19\u0e19\u0e49\u0e33\u0e2b\u0e21\u0e31\u0e19"
    ],
    "name:und_x_variant":[
        "Ban Na Chiang Kum",
        "B\u0101n Na Chiang Gum",
        "Ban Nam Man"
    ],
    "wof:lang_x_official":[
        "tha"
    ],
    "wof:lang_x_spoken":[
        "tha"
    ],
    "wof:name":"Ban Nam Man",
    "wof:placetype":"locality"
},
  "geometry": {"coordinates":[101.12648,17.09773],"type":"Point"}
}