{
  "type": "Feature",
  "properties": {
    "gn:admin1_code":"37",
    "gn:asciiname":"Ban Nong Mi",
    "gn:country_code":"TH",
    "gn:dem":229,
    "gn:feature_class":"P",
    "gn:feature_code":"PPL",
    "gn:name":"Ban Nong Mi",
    "gn:population":0,
    "gn:timezone":"Asia/Bangkok",
    "iso:country":"TH",
    "name:tha_x_preferred":[
        "\u0e1a\u0e49\u0e32\u0e19\u0e2b\u0e19\u0e2d\u0e07\u0e2b\u0e21\u0e35"
    ],
    "wof:name":"Ban Nong Mi",
    "wof:placetype":"locality"
},
  "geometry": {"coordinates":[101.44203,14.92253],"type":"Point"}
}