{
  "type": "Feature",
  "properties": {
    "gn:admin1_code":"57.0",
    "gn:asciiname":"Ban Mak Phu",
    "gn:country_code":"TH",
    "gn:dem":104,
    "gn:feature_class":"P",
    "gn:feature_code":"PPL",
    "gn:name":"Ban Mak Phu",
    "gn:population":0,
    "gn:timezone":"Asia/Bangkok",
    "iso:country":"TH",
    "name:tha_x_preferred":[
        "\u0e1a\u0e49\u0e32\u0e19\u0e2b\u0e21\u0e32\u0e01\u0e1c\u0e39\u0e49"
    ],
    "wof:name":"Ban Mak Phu",
    "wof:placetype":"locality"
},
  "geometry": {"coordinates":[99.28742,10.98467],"type":"Point"}
}