{
  "type": "Feature",
  "properties": {
    "gn:admin1_code":"8.0",
    "gn:asciiname":"Ban Mae Salit",
    "gn:country_code":"TH",
    "gn:dem":135,
    "gn:feature_class":"P",
    "gn:feature_code":"PPL",
    "gn:name":"Ban Mae Salit",
    "gn:population":0,
    "gn:timezone":"Asia/Bangkok",
    "iso:country":"TH",
    "name:tha_x_preferred":[
        "Ban Mae Salit"
    ],
    "name:tha_x_variant":[
        "\u0e1a\u0e49\u0e32\u0e19\u0e41\u0e21\u0e48\u0e2a\u0e25\u0e34\u0e14"
    ],
    "name:und_x_variant":[
        "Ban Mae Salit Noi"
    ],
    "wof:name":"Ban Mae Salit",
    "wof:placetype":"locality"
},
  "geometry": {"coordinates":[99.11111,17.14756],"type":"Point"}
}