{
  "type": "Feature",
  "properties": {
    "gn:admin1_code":"75.0",
    "gn:asciiname":"Ban Phu Lon",
    "gn:country_code":"TH",
    "gn:dem":179,
    "gn:feature_class":"P",
    "gn:feature_code":"PPL",
    "gn:name":"Ban Phu Lon",
    "gn:population":0,
    "gn:timezone":"Asia/Bangkok",
    "iso:country":"TH",
    "name:tha_x_preferred":[
        "\u0e1a\u0e49\u0e32\u0e19\u0e20\u0e39\u0e2b\u0e25\u0e48\u0e19"
    ],
    "wof:name":"Ban Phu Lon",
    "wof:placetype":"locality"
},
  "geometry": {"coordinates":[105.27592,15.64022],"type":"Point"}
}