{
  "type": "Feature",
  "properties": {
    "gn:admin1_code":"66.0",
    "gn:asciiname":"Ban Taphaen",
    "gn:country_code":"TH",
    "gn:dem":85,
    "gn:feature_class":"P",
    "gn:feature_code":"PPL",
    "gn:name":"Ban Taphaen",
    "gn:population":0,
    "gn:timezone":"Asia/Bangkok",
    "iso:country":"TH",
    "name:tha_x_preferred":[
        "\u0e1a\u0e49\u0e32\u0e19\u0e15\u0e30\u0e41\u0e1e\u0e19"
    ],
    "wof:name":"Ban Taphaen",
    "wof:placetype":"locality"
},
  "geometry": {"coordinates":[99.87582999999999,7.65269],"type":"Point"}
}