{
  "type": "Feature",
  "properties": {
    "gn:admin1_code":"80.0",
    "gn:asciiname":"Ban Bu Yai",
    "gn:country_code":"TH",
    "gn:dem":45,
    "gn:feature_class":"P",
    "gn:feature_code":"PPL",
    "gn:name":"Ban Bu Yai",
    "gn:population":0,
    "gn:timezone":"Asia/Bangkok",
    "iso:country":"TH",
    "name:und_x_variant":[
        "Bu Yai",
        "Ban Bu Yai"
    ],
    "wof:name":"Ban Bu Yai",
    "wof:placetype":"locality"
},
  "geometry": {"coordinates":[102.08333,13.71667],"type":"Point"}
}