{
  "type": "Feature",
  "properties": {
    "gn:admin1_code":"47.0",
    "gn:asciiname":"Ban Khao Phai",
    "gn:country_code":"TH",
    "gn:dem":71,
    "gn:feature_class":"P",
    "gn:feature_code":"PPL",
    "gn:name":"Ban Khao Phai",
    "gn:population":0,
    "gn:timezone":"Asia/Bangkok",
    "iso:country":"TH",
    "name:tha_x_preferred":[
        "\u0e1a\u0e49\u0e32\u0e19\u0e40\u0e02\u0e32\u0e44\u0e1c\u0e48"
    ],
    "wof:name":"Ban Khao Phai",
    "wof:placetype":"locality"
},
  "geometry": {"coordinates":[101.60138999999999,13.085],"type":"Point"}
}