{
  "type": "Feature",
  "properties": {
    "gn:admin1_code":"51.0",
    "gn:asciiname":"Ban Nong Po",
    "gn:country_code":"TH",
    "gn:dem":79,
    "gn:feature_class":"P",
    "gn:feature_code":"PPL",
    "gn:name":"Ban Nong Po",
    "gn:population":0,
    "gn:timezone":"Asia/Bangkok",
    "iso:country":"TH",
    "name:tha_x_preferred":[
        "\u0e1a\u0e49\u0e32\u0e19\u0e2b\u0e19\u0e2d\u0e07\u0e40\u0e1b\u0e32\u0e30"
    ],
    "name:und_x_variant":[
        "Ban Nong I Po"
    ],
    "wof:name":"Ban Nong Po",
    "wof:placetype":"locality"
},
  "geometry": {"coordinates":[99.65703000000001,14.80714],"type":"Point"}
}