{
  "type": "Feature",
  "properties": {
    "gn:admin1_code":"3.0",
    "gn:asciiname":"Ban Pa Hat",
    "gn:country_code":"TH",
    "gn:dem":404,
    "gn:feature_class":"P",
    "gn:feature_code":"PPL",
    "gn:name":"Ban Pa Hat",
    "gn:population":0,
    "gn:timezone":"Asia/Bangkok",
    "iso:country":"TH",
    "name:tha_x_preferred":[
        "\u0e1a\u0e49\u0e32\u0e19\u0e1b\u0e48\u0e32\u0e2b\u0e31\u0e14"
    ],
    "wof:name":"Ban Pa Hat",
    "wof:placetype":"locality"
},
  "geometry": {"coordinates":[99.83719000000001,19.84736],"type":"Point"}
}