{
  "type": "Feature",
  "properties": {
    "gn:admin1_code":"47.0",
    "gn:asciiname":"Ban Chak Luk Ya",
    "gn:country_code":"TH",
    "gn:dem":52,
    "gn:feature_class":"P",
    "gn:feature_code":"PPL",
    "gn:name":"Ban Chak Luk Ya",
    "gn:population":0,
    "gn:timezone":"Asia/Bangkok",
    "iso:country":"TH",
    "name:tha_x_preferred":[
        "\u0e1a\u0e49\u0e32\u0e19\u0e0a\u0e32\u0e01\u0e25\u0e39\u0e01\u0e2b\u0e0d\u0e49\u0e32"
    ],
    "wof:name":"Ban Chak Luk Ya",
    "wof:placetype":"locality"
},
  "geometry": {"coordinates":[101.12306,12.74056],"type":"Point"}
}