{
  "type": "Feature",
  "properties": {
    "gn:admin1_code":"75.0",
    "gn:asciiname":"Ban Khok Chan",
    "gn:country_code":"TH",
    "gn:dem":133,
    "gn:feature_class":"P",
    "gn:feature_code":"PPL",
    "gn:name":"Ban Khok Chan",
    "gn:population":0,
    "gn:timezone":"Asia/Bangkok",
    "iso:country":"TH",
    "name:tha_x_preferred":[
        "\u0e1a\u0e49\u0e32\u0e19\u0e42\u0e04\u0e01\u0e08\u0e32\u0e19"
    ],
    "wof:name":"Ban Khok Chan",
    "wof:placetype":"locality"
},
  "geometry": {"coordinates":[105.07181,15.54131],"type":"Point"}
}