{
  "type": "Feature",
  "properties": {
    "gn:admin1_code":"25.0",
    "gn:asciiname":"Ban Chi Lon",
    "gn:country_code":"TH",
    "gn:dem":142,
    "gn:feature_class":"P",
    "gn:feature_code":"PPL",
    "gn:name":"Ban Chi Lon",
    "gn:population":0,
    "gn:timezone":"Asia/Bangkok",
    "iso:country":"TH",
    "name:tha_x_preferred":[
        "\u0e1a\u0e49\u0e32\u0e19\u0e0a\u0e35\u0e42\u0e2b\u0e25\u0e48\u0e19"
    ],
    "wof:name":"Ban Chi Lon",
    "wof:placetype":"locality"
},
  "geometry": {"coordinates":[103.93380000000001,15.87794],"type":"Point"}
}