{
  "type": "Feature",
  "properties": {
    "gn:admin1_code":"43",
    "gn:asciiname":"Ban Kut Rang Nok",
    "gn:country_code":"TH",
    "gn:dem":17,
    "gn:feature_class":"P",
    "gn:feature_code":"PPL",
    "gn:name":"Ban Kut Rang Nok",
    "gn:population":0,
    "gn:timezone":"Asia/Bangkok",
    "iso:country":"TH",
    "name:tha_x_preferred":[
        "\u0e1a\u0e49\u0e32\u0e19\u0e01\u0e38\u0e14\u0e23\u0e31\u0e07\u0e19\u0e2d\u0e01"
    ],
    "wof:name":"Ban Kut Rang Nok",
    "wof:placetype":"locality"
},
  "geometry": {"coordinates":[101.27269,14.26742],"type":"Point"}
}