{
  "type": "Feature",
  "properties": {
    "gn:admin1_code":"2.0",
    "gn:asciiname":"Ban Phet Phaithun",
    "gn:country_code":"TH",
    "gn:dem":546,
    "gn:feature_class":"P",
    "gn:feature_code":"PPL",
    "gn:name":"Ban Phet Phaithun",
    "gn:population":0,
    "gn:timezone":"Asia/Bangkok",
    "iso:country":"TH",
    "name:tha_x_preferred":[
        "\u0e1a\u0e49\u0e32\u0e19\u0e40\u0e1e\u0e0a\u0e23\u0e44\u0e1e\u0e11\u0e39\u0e23\u0e22\u0e4c"
    ],
    "wof:name":"Ban Phet Phaithun",
    "wof:placetype":"locality"
},
  "geometry": {"coordinates":[99.13753,19.85461],"type":"Point"}
}