{
  "type": "Feature",
  "properties": {
    "gn:admin1_code":"34.0",
    "gn:asciiname":"Ban Dong Phlap",
    "gn:country_code":"TH",
    "gn:dem":24,
    "gn:feature_class":"P",
    "gn:feature_code":"PPL",
    "gn:name":"Ban Dong Phlap",
    "gn:population":0,
    "gn:timezone":"Asia/Bangkok",
    "iso:country":"TH",
    "name:tha_x_preferred":[
        "\u0e1a\u0e49\u0e32\u0e19\u0e14\u0e07\u0e1e\u0e25\u0e31\u0e1a"
    ],
    "name:und_x_variant":[
        "Ban Dong Phlab",
        "Ban Dong Phlap"
    ],
    "wof:name":"Ban Dong Phlap",
    "wof:placetype":"locality"
},
  "geometry": {"coordinates":[100.63467,15.07164],"type":"Point"}
}