{
  "type": "Feature",
  "properties": {
    "gn:admin1_code":"20.0",
    "gn:asciiname":"Ban Khok",
    "gn:country_code":"TH",
    "gn:dem":183,
    "gn:feature_class":"P",
    "gn:feature_code":"PPL",
    "gn:name":"Ban Khok",
    "gn:population":0,
    "gn:timezone":"Asia/Bangkok",
    "iso:country":"TH",
    "name:tha_x_preferred":[
        "\u0e1a\u0e49\u0e32\u0e19\u0e42\u0e04\u0e01"
    ],
    "wof:name":"Ban Khok",
    "wof:placetype":"locality"
},
  "geometry": {"coordinates":[103.83356000000001,17.30367],"type":"Point"}
}