{
  "type": "Feature",
  "properties": {
    "gn:admin1_code":"6.0",
    "gn:asciiname":"Ban San Pa Lan",
    "gn:country_code":"TH",
    "gn:dem":259,
    "gn:feature_class":"P",
    "gn:feature_code":"PPL",
    "gn:name":"Ban San Pa Lan",
    "gn:population":0,
    "gn:timezone":"Asia/Bangkok",
    "iso:country":"TH",
    "name:tha_x_preferred":[
        "\u0e1a\u0e49\u0e32\u0e19\u0e2a\u0e31\u0e19\u0e1b\u0e48\u0e32\u0e25\u0e32\u0e19"
    ],
    "wof:name":"Ban San Pa Lan",
    "wof:placetype":"locality"
},
  "geometry": {"coordinates":[99.19374999999999,18.08769],"type":"Point"}
}