{
  "type": "Feature",
  "properties": {
    "gn:admin1_code":"6.0",
    "gn:asciiname":"Ban Thung Charoen",
    "gn:country_code":"TH",
    "gn:dem":237,
    "gn:feature_class":"P",
    "gn:feature_code":"PPL",
    "gn:name":"Ban Thung Charoen",
    "gn:population":0,
    "gn:timezone":"Asia/Bangkok",
    "iso:country":"TH",
    "name:tha_x_preferred":[
        "\u0e1a\u0e49\u0e32\u0e19\u0e17\u0e38\u0e48\u0e07\u0e40\u0e08\u0e23\u0e34\u0e0d"
    ],
    "wof:name":"Ban Thung Charoen",
    "wof:placetype":"locality"
},
  "geometry": {"coordinates":[99.34425,18.205],"type":"Point"}
}