{
  "type": "Feature",
  "properties": {
    "gn:admin1_code":"12.0",
    "gn:asciiname":"Ban Mai Rak Thai",
    "gn:country_code":"TH",
    "gn:dem":554,
    "gn:feature_class":"P",
    "gn:feature_code":"PPL",
    "gn:name":"Ban Mai Rak Thai",
    "gn:population":0,
    "gn:timezone":"Asia/Bangkok",
    "iso:country":"TH",
    "name:tha_x_preferred":[
        "\u0e1a\u0e49\u0e32\u0e19\u0e43\u0e2b\u0e21\u0e48\u0e23\u0e31\u0e01\u0e44\u0e17\u0e22"
    ],
    "wof:name":"Ban Mai Rak Thai",
    "wof:placetype":"locality"
},
  "geometry": {"coordinates":[100.91394,17.68711],"type":"Point"}
}