{
  "type": "Feature",
  "properties": {
    "gn:admin1_code":"72.0",
    "gn:asciiname":"Ban Non Pho",
    "gn:country_code":"TH",
    "gn:dem":142,
    "gn:feature_class":"P",
    "gn:feature_code":"PPL",
    "gn:name":"Ban Non Pho",
    "gn:population":0,
    "gn:timezone":"Asia/Bangkok",
    "iso:country":"TH",
    "name:tha_x_preferred":[
        "\u0e1a\u0e49\u0e32\u0e19\u0e42\u0e19\u0e19\u0e42\u0e1e\u0e18\u0e34\u0e4c"
    ],
    "wof:lang_x_official":[
        "tha"
    ],
    "wof:lang_x_spoken":[
        "tha"
    ],
    "wof:name":"Ban Non Pho",
    "wof:placetype":"locality"
},
  "geometry": {"coordinates":[104.14055999999999,15.90306],"type":"Point"}
}