{
  "type": "Feature",
  "properties": {
    "gn:admin1_code":"28.0",
    "gn:asciiname":"Ban Pan Ro",
    "gn:country_code":"TH",
    "gn:dem":184,
    "gn:feature_class":"P",
    "gn:feature_code":"PPL",
    "gn:name":"Ban Pan Ro",
    "gn:population":0,
    "gn:timezone":"Asia/Bangkok",
    "iso:country":"TH",
    "name:tha_x_preferred":[
        "\u0e1a\u0e49\u0e32\u0e19\u0e1b\u0e31\u0e19\u0e40\u0e23\u0e32\u0e30"
    ],
    "wof:name":"Ban Pan Ro",
    "wof:placetype":"locality"
},
  "geometry": {"coordinates":[103.11288999999999,14.47142],"type":"Point"}
}