{
  "type": "Feature",
  "properties": {
    "gn:admin1_code":"4.0",
    "gn:asciiname":"Ban Rong Ngae",
    "gn:country_code":"TH",
    "gn:dem":270,
    "gn:feature_class":"P",
    "gn:feature_code":"PPL",
    "gn:name":"Ban Rong Ngae",
    "gn:population":0,
    "gn:timezone":"Asia/Bangkok",
    "iso:country":"TH",
    "name:tha_x_preferred":[
        "\u0e1a\u0e49\u0e32\u0e19\u0e23\u0e49\u0e2d\u0e07\u0e41\u0e07"
    ],
    "wof:name":"Ban Rong Ngae",
    "wof:placetype":"locality"
},
  "geometry": {"coordinates":[100.93733,19.17519],"type":"Point"}
}