{
  "type": "Feature",
  "properties": {
    "gn:admin1_code":"60.0",
    "gn:asciiname":"Ban Chalok Lam",
    "gn:country_code":"TH",
    "gn:dem":10,
    "gn:feature_class":"P",
    "gn:feature_code":"PPL",
    "gn:name":"Ban Chalok Lam",
    "gn:population":0,
    "gn:timezone":"Asia/Bangkok",
    "iso:country":"TH",
    "name:tha_x_preferred":[
        "\u0e1a\u0e49\u0e32\u0e19\u0e42\u0e09\u0e25\u0e01\u0e2b\u0e25\u0e33"
    ],
    "wof:name":"Ban Chalok Lam",
    "wof:placetype":"locality"
},
  "geometry": {"coordinates":[100.00481000000001,9.78586],"type":"Point"}
}