{
  "type": "Feature",
  "properties": {
    "gn:admin1_code":"53.0",
    "gn:asciiname":"Ban Cham Churi",
    "gn:country_code":"TH",
    "gn:dem":7,
    "gn:feature_class":"P",
    "gn:feature_code":"PPL",
    "gn:name":"Ban Cham Churi",
    "gn:population":0,
    "gn:timezone":"Asia/Bangkok",
    "iso:country":"TH",
    "name:tha_x_preferred":[
        "Ban Cham Churi"
    ],
    "name:tha_x_variant":[
        "\u0e1a\u0e49\u0e32\u0e19\u0e08\u0e32\u0e21\u0e08\u0e38\u0e23\u0e35"
    ],
    "wof:name":"Ban Cham Churi",
    "wof:placetype":"locality"
},
  "geometry": {"coordinates":[100.08992000000001,14.0145],"type":"Point"}
}