{
  "type": "Feature",
  "properties": {
    "gn:admin1_code":"68.0",
    "gn:asciiname":"Ban Di Luang",
    "gn:country_code":"TH",
    "gn:dem":8,
    "gn:feature_class":"P",
    "gn:feature_code":"PPL",
    "gn:name":"Ban Di Luang",
    "gn:population":0,
    "gn:timezone":"Asia/Bangkok",
    "iso:country":"TH",
    "name:tha_x_preferred":[
        "\u0e1a\u0e49\u0e32\u0e19\u0e14\u0e35\u0e2b\u0e25\u0e27\u0e07"
    ],
    "name:und_x_variant":[
        "Ban Khadi Luang",
        "Ban Di Luang"
    ],
    "wof:name":"Ban Di Luang",
    "wof:placetype":"locality"
},
  "geometry": {"coordinates":[100.50461,7.29014],"type":"Point"}
}