{
  "type": "Feature",
  "properties": {
    "gn:admin1_code":"58.0",
    "gn:asciiname":"Ban Wang Maprang",
    "gn:country_code":"TH",
    "gn:dem":42,
    "gn:feature_class":"P",
    "gn:feature_code":"PPL",
    "gn:name":"Ban Wang Maprang",
    "gn:population":0,
    "gn:timezone":"Asia/Bangkok",
    "iso:country":"TH",
    "name:tha_x_preferred":[
        "\u0e1a\u0e49\u0e32\u0e19\u0e27\u0e31\u0e07\u0e21\u0e30\u0e1b\u0e23\u0e32\u0e07"
    ],
    "name:und_x_variant":[
        "Wang Ma Pr\u0101ng",
        "Ban Wang Maprang"
    ],
    "wof:name":"Ban Wang Maprang",
    "wof:placetype":"locality"
},
  "geometry": {"coordinates":[99.15913999999999,10.72611],"type":"Point"}
}