{
  "type": "Feature",
  "properties": {
    "gn:admin1_code":"53.0",
    "gn:asciiname":"Ban Thung Phakkut",
    "gn:country_code":"TH",
    "gn:dem":8,
    "gn:feature_class":"P",
    "gn:feature_code":"PPL",
    "gn:name":"Ban Thung Phakkut",
    "gn:population":0,
    "gn:timezone":"Asia/Bangkok",
    "iso:country":"TH",
    "name:tha_x_preferred":[
        "\u0e1a\u0e49\u0e32\u0e19\u0e17\u0e38\u0e48\u0e07\u0e1c\u0e31\u0e01\u0e01\u0e39\u0e14"
    ],
    "wof:name":"Ban Thung Phakkut",
    "wof:placetype":"locality"
},
  "geometry": {"coordinates":[100.09775,13.90869],"type":"Point"}
}