{
  "type": "Feature",
  "properties": {
    "gn:admin1_code":"43.0",
    "gn:asciiname":"Ban Hup Moei",
    "gn:country_code":"TH",
    "gn:dem":28,
    "gn:feature_class":"P",
    "gn:feature_code":"PPL",
    "gn:name":"Ban Hup Moei",
    "gn:population":0,
    "gn:timezone":"Asia/Bangkok",
    "iso:country":"TH",
    "name:tha_x_preferred":[
        "\u0e1a\u0e49\u0e32\u0e19\u0e2b\u0e38\u0e1a\u0e40\u0e21\u0e22"
    ],
    "name:und_x_variant":[
        "Ban Hum Moei"
    ],
    "wof:name":"Ban Hup Moei",
    "wof:placetype":"locality"
},
  "geometry": {"coordinates":[101.30647,14.26439],"type":"Point"}
}