{
  "type": "Feature",
  "properties": {
    "gn:admin1_code":"8.0",
    "gn:asciiname":"Ban Samuen",
    "gn:country_code":"TH",
    "gn:dem":588,
    "gn:feature_class":"P",
    "gn:feature_code":"PPL",
    "gn:name":"Ban Samuen",
    "gn:population":0,
    "gn:timezone":"Asia/Bangkok",
    "iso:country":"TH",
    "name:tha_x_preferred":[
        "\u0e1a\u0e49\u0e32\u0e19\u0e2a\u0e30\u0e21\u0e36\u0e19"
    ],
    "name:und_x_variant":[
        "Ban Sam Mun"
    ],
    "wof:name":"Ban Samuen",
    "wof:placetype":"locality"
},
  "geometry": {"coordinates":[98.74639000000001,16.96183],"type":"Point"}
}