{
  "type": "Feature",
  "properties": {
    "gn:admin1_code":"37.0",
    "gn:asciiname":"Ban Makrut",
    "gn:country_code":"TH",
    "gn:dem":17,
    "gn:feature_class":"P",
    "gn:feature_code":"PPL",
    "gn:name":"Ban Makrut",
    "gn:population":0,
    "gn:timezone":"Asia/Bangkok",
    "iso:country":"TH",
    "name:tha_x_preferred":[
        "\u0e1a\u0e49\u0e32\u0e19\u0e21\u0e30\u0e01\u0e23\u0e39\u0e14"
    ],
    "name:und_x_variant":[
        "Ban Makrut (2)"
    ],
    "wof:name":"Ban Makrut",
    "wof:placetype":"locality"
},
  "geometry": {"coordinates":[100.81641999999999,14.56189],"type":"Point"}
}