{
  "type": "Feature",
  "properties": {
    "gn:admin1_code":"18.0",
    "gn:asciiname":"Ban Khua Tae",
    "gn:country_code":"TH",
    "gn:dem":297,
    "gn:feature_class":"P",
    "gn:feature_code":"PPL",
    "gn:name":"Ban Khua Tae",
    "gn:population":0,
    "gn:timezone":"Asia/Bangkok",
    "iso:country":"TH",
    "name:tha_x_preferred":[
        "Ban Khua Tae"
    ],
    "name:tha_x_variant":[
        "\u0e1a\u0e49\u0e32\u0e19\u0e02\u0e31\u0e27\u0e41\u0e15\u0e30"
    ],
    "wof:name":"Ban Khua Tae",
    "wof:placetype":"locality"
},
  "geometry": {"coordinates":[101.90106,17.31158],"type":"Point"}
}