{
  "type": "Feature",
  "properties": {
    "gn:admin1_code":"1.0",
    "gn:asciiname":"Ban Kung Lom",
    "gn:country_code":"TH",
    "gn:dem":901,
    "gn:feature_class":"P",
    "gn:feature_code":"PPL",
    "gn:name":"Ban Kung Lom",
    "gn:population":0,
    "gn:timezone":"Asia/Bangkok",
    "iso:country":"TH",
    "name:tha_x_preferred":[
        "\u0e1a\u0e49\u0e32\u0e19\u0e01\u0e38\u0e07\u0e25\u0e21"
    ],
    "name:und_x_variant":[
        "Ban Kung Hoi"
    ],
    "wof:name":"Ban Kung Lom",
    "wof:placetype":"locality"
},
  "geometry": {"coordinates":[98.13214000000001,19.62486],"type":"Point"}
}