{
  "type": "Feature",
  "properties": {
    "gn:admin1_code":"37",
    "gn:asciiname":"Ban Heo Lat",
    "gn:country_code":"TH",
    "gn:dem":189,
    "gn:feature_class":"P",
    "gn:feature_code":"PPL",
    "gn:name":"Ban Heo Lat",
    "gn:population":0,
    "gn:timezone":"Asia/Bangkok",
    "iso:country":"TH",
    "name:tha_x_preferred":[
        "\u0e1a\u0e49\u0e32\u0e19\u0e40\u0e2b\u0e27\u0e25\u0e32\u0e14"
    ],
    "wof:name":"Ban Heo Lat",
    "wof:placetype":"locality"
},
  "geometry": {"coordinates":[101.18742,14.71503],"type":"Point"}
}