{
  "type": "Feature",
  "properties": {
    "gn:country":"TH",
    "gn:fcode":"PPL",
    "gn:population":0,
    "iso:country":"TH",
    "name:tha_x_preferred":[
        "\u0e1a\u0e49\u0e32\u0e19\u0e17\u0e38\u0e48\u0e07\u0e17\u0e2d\u0e07"
    ],
    "name:und_x_variant":[
        "Ban Tung Tong"
    ],
    "qs:name":"Ban Thung Thong (1)",
    "qs:name_adm0":"Thailand",
    "qs:name_adm1":"Kanchanaburi",
    "qs:photos":48,
    "qs:photos_1k":10,
    "qs:photos_9k":1,
    "qs:photos_9r":2,
    "qs:photos_all":48,
    "qs:photos_sr":2,
    "qs:placetype":"Town",
    "qs:pop_sr":"0",
    "wof:name":"Ban Thung Thong (1)",
    "wof:placetype":"locality",
    "wof:population":0
},
  "geometry": {"coordinates":[99.63531,13.99603],"type":"Point"}
}