{
  "type": "Feature",
  "properties": {
    "gn:admin1_code":"81.0",
    "gn:asciiname":"Ban Wisit",
    "gn:country_code":"TH",
    "gn:dem":161,
    "gn:feature_class":"P",
    "gn:feature_code":"PPL",
    "gn:name":"Ban Wisit",
    "gn:population":0,
    "gn:timezone":"Asia/Bangkok",
    "iso:country":"TH",
    "name:tha_x_preferred":[
        "\u0e1a\u0e49\u0e32\u0e19\u0e27\u0e34\u0e28\u0e34\u0e29\u0e10\u0e4c"
    ],
    "wof:name":"Ban Wisit",
    "wof:placetype":"locality"
},
  "geometry": {"coordinates":[103.63611,18.37711],"type":"Point"}
}