{
  "type": "Feature",
  "properties": {
    "gn:admin1_code":"68.0",
    "gn:asciiname":"Ban Khai Nao",
    "gn:cc2":"TH",
    "gn:country_code":"TH",
    "gn:dem":23,
    "gn:feature_class":"P",
    "gn:feature_code":"PPL",
    "gn:name":"Ban Khai Nao",
    "gn:population":0,
    "gn:timezone":"Asia/Bangkok",
    "iso:country":"TH",
    "name:und_x_variant":[
        "Khai Nao",
        "Ban Khai Nao"
    ],
    "wof:name":"Ban Khai Nao",
    "wof:placetype":"locality"
},
  "geometry": {"coordinates":[100.38333,6.91667],"type":"Point"}
}