{
  "type": "Feature",
  "properties": {
    "gn:admin1_code":"4.0",
    "gn:asciiname":"Ban Nam Khong",
    "gn:country_code":"TH",
    "gn:dem":268,
    "gn:feature_class":"P",
    "gn:feature_code":"PPL",
    "gn:name":"Ban Nam Khong",
    "gn:population":0,
    "gn:timezone":"Asia/Bangkok",
    "iso:country":"TH",
    "name:tha_x_preferred":[
        "\u0e1a\u0e49\u0e32\u0e19\u0e19\u0e49\u0e33\u0e42\u0e04\u0e49\u0e07"
    ],
    "wof:name":"Ban Nam Khong",
    "wof:placetype":"locality"
},
  "geometry": {"coordinates":[100.65533000000001,18.84689],"type":"Point"}
}