{
  "type": "Feature",
  "properties": {
    "gn:admin1_code":"6.0",
    "gn:asciiname":"Ban Thung Man Nua",
    "gn:country_code":"TH",
    "gn:dem":246,
    "gn:feature_class":"P",
    "gn:feature_code":"PPL",
    "gn:name":"Ban Thung Man Nua",
    "gn:population":0,
    "gn:timezone":"Asia/Bangkok",
    "iso:country":"TH",
    "wof:name":"Ban Thung Man Nua",
    "wof:placetype":"locality"
},
  "geometry": {"coordinates":[99.45,18.35],"type":"Point"}
}