{
  "type": "Feature",
  "properties": {
    "gn:admin1_code":"2.0",
    "gn:asciiname":"Ban Wiang Chai",
    "gn:country_code":"TH",
    "gn:dem":502,
    "gn:feature_class":"P",
    "gn:feature_code":"PPL",
    "gn:name":"Ban Wiang Chai",
    "gn:population":0,
    "gn:timezone":"Asia/Bangkok",
    "iso:country":"TH",
    "name:tha_x_preferred":[
        "\u0e1a\u0e49\u0e32\u0e19\u0e40\u0e27\u0e35\u0e22\u0e07\u0e44\u0e0a\u0e22"
    ],
    "wof:name":"Ban Wiang Chai",
    "wof:placetype":"locality"
},
  "geometry": {"coordinates":[99.16894000000001,19.75247],"type":"Point"}
}