{
  "type": "Feature",
  "properties": {
    "gn:admin1_code":"9.0",
    "gn:asciiname":"Ban Tha Din Daeng",
    "gn:country_code":"TH",
    "gn:dem":60,
    "gn:feature_class":"P",
    "gn:feature_code":"PPL",
    "gn:name":"Ban Tha Din Daeng",
    "gn:population":0,
    "gn:timezone":"Asia/Bangkok",
    "iso:country":"TH",
    "name:und_x_variant":[
        "Dh\u0101dind\u0113ng",
        "Tha Din Daeng",
        "B\u0101n Tha Din Deang",
        "Ban Tha Din Daeng"
    ],
    "wof:name":"Ban Tha Din Daeng",
    "wof:placetype":"locality"
},
  "geometry": {"coordinates":[99.75,16.85],"type":"Point"}
}