{
  "type": "Feature",
  "properties": {
    "gn:admin1_code":"34.0",
    "gn:asciiname":"Ban Khok Salut (1)",
    "gn:cc2":"TH",
    "gn:country_code":"TH",
    "gn:dem":10,
    "gn:feature_class":"P",
    "gn:feature_code":"PPL",
    "gn:name":"Ban Khok Salut (1)",
    "gn:population":0,
    "gn:timezone":"Asia/Bangkok",
    "iso:country":"TH",
    "name:und_x_variant":[
        "Ban Kok Salud",
        "Ban Khok Salut (1)"
    ],
    "wof:name":"Ban Khok Salut (1)",
    "wof:placetype":"locality"
},
  "geometry": {"coordinates":[100.51667,14.86667],"type":"Point"}
}