{
  "type": "Feature",
  "properties": {
    "gn:admin1_code":"14.0",
    "gn:asciiname":"Ban Ko Boraphet",
    "gn:country_code":"TH",
    "gn:dem":87,
    "gn:feature_class":"P",
    "gn:feature_code":"PPL",
    "gn:name":"Ban Ko Boraphet",
    "gn:population":0,
    "gn:timezone":"Asia/Bangkok",
    "iso:country":"TH",
    "name:tha_x_preferred":[
        "\u0e1a\u0e49\u0e32\u0e19\u0e40\u0e01\u0e32\u0e30\u0e1a\u0e23\u0e40\u0e1e\u0e47\u0e14"
    ],
    "wof:name":"Ban Ko Boraphet",
    "wof:placetype":"locality"
},
  "geometry": {"coordinates":[101.09983,15.73733],"type":"Point"}
}