{
  "type": "Feature",
  "properties": {
    "gn:admin1_code":"37.0",
    "gn:asciiname":"Ban Nong Khruea Ta Pla",
    "gn:country_code":"TH",
    "gn:dem":13,
    "gn:feature_class":"P",
    "gn:feature_code":"PPL",
    "gn:name":"Ban Nong Khruea Ta Pla",
    "gn:population":0,
    "gn:timezone":"Asia/Bangkok",
    "iso:country":"TH",
    "name:tha_x_preferred":[
        "\u0e1a\u0e49\u0e32\u0e19\u0e2b\u0e19\u0e2d\u0e07\u0e40\u0e04\u0e23\u0e37\u0e2d\u0e15\u0e32\u0e1b\u0e25\u0e32"
    ],
    "name:und_x_variant":[
        "Ban Nong Khrua Ta Pa"
    ],
    "wof:name":"Ban Nong Khruea Ta Pla",
    "wof:placetype":"locality"
},
  "geometry": {"coordinates":[100.73764,14.68947],"type":"Point"}
}