{
  "type": "Feature",
  "properties": {
    "gn:admin1_code":"30.0",
    "gn:asciiname":"Ban Phak Khaya Noi",
    "gn:country_code":"TH",
    "gn:dem":136,
    "gn:feature_class":"P",
    "gn:feature_code":"PPL",
    "gn:name":"Ban Phak Khaya Noi",
    "gn:population":0,
    "gn:timezone":"Asia/Bangkok",
    "iso:country":"TH",
    "name:tha_x_preferred":[
        "\u0e1a\u0e49\u0e32\u0e19\u0e1c\u0e31\u0e01\u0e02\u0e22\u0e48\u0e32\u0e19\u0e49\u0e2d\u0e22"
    ],
    "wof:name":"Ban Phak Khaya Noi",
    "wof:placetype":"locality"
},
  "geometry": {"coordinates":[104.62367,14.96064],"type":"Point"}
}