{
  "type": "Feature",
  "properties": {
    "gn:admin1_code":"68.0",
    "gn:asciiname":"Ban Sanam Chai",
    "gn:country_code":"TH",
    "gn:dem":9,
    "gn:feature_class":"P",
    "gn:feature_code":"PPL",
    "gn:name":"Ban Sanam Chai",
    "gn:population":0,
    "gn:timezone":"Asia/Bangkok",
    "iso:country":"TH",
    "name:tha_x_preferred":[
        "\u0e1a\u0e49\u0e32\u0e19\u0e2a\u0e19\u0e32\u0e21\u0e0a\u0e31\u0e22"
    ],
    "name:und_x_variant":[
        "Sanam Chai",
        "Ban Snam Chai",
        "Ban Sanam Chai"
    ],
    "wof:lang_x_official":[
        "tha"
    ],
    "wof:lang_x_spoken":[
        "tha"
    ],
    "wof:name":"Ban Sanam Chai",
    "wof:placetype":"locality"
},
  "geometry": {"coordinates":[100.41307999999999,7.55811],"type":"Point"}
}