{
  "type": "Feature",
  "properties": {
    "gn:admin1_code":"23.0",
    "gn:asciiname":"Ban Noi Santi Suk",
    "gn:country_code":"TH",
    "gn:dem":175,
    "gn:feature_class":"P",
    "gn:feature_code":"PPL",
    "gn:name":"Ban Noi Santi Suk",
    "gn:population":0,
    "gn:timezone":"Asia/Bangkok",
    "iso:country":"TH",
    "name:tha_x_preferred":[
        "\u0e1a\u0e49\u0e32\u0e19\u0e19\u0e49\u0e2d\u0e22\u0e2a\u0e31\u0e19\u0e15\u0e34\u0e2a\u0e38\u0e02"
    ],
    "wof:lang_x_official":[
        "tha"
    ],
    "wof:lang_x_spoken":[
        "tha"
    ],
    "wof:name":"Ban Noi Santi Suk",
    "wof:placetype":"locality"
},
  "geometry": {"coordinates":[103.72889000000001,16.44783],"type":"Point"}
}