{
  "type": "Feature",
  "properties": {
    "gn:admin1_code":"5.0",
    "gn:asciiname":"Ban San Pa Hiang",
    "gn:country_code":"TH",
    "gn:dem":311,
    "gn:feature_class":"P",
    "gn:feature_code":"PPL",
    "gn:name":"Ban San Pa Hiang",
    "gn:population":0,
    "gn:timezone":"Asia/Bangkok",
    "iso:country":"TH",
    "name:tha_x_preferred":[
        "\u0e1a\u0e49\u0e32\u0e19\u0e2a\u0e31\u0e19\u0e1b\u0e48\u0e32\u0e40\u0e2b\u0e35\u0e22\u0e07"
    ],
    "wof:name":"Ban San Pa Hiang",
    "wof:placetype":"locality"
},
  "geometry": {"coordinates":[99.09956,18.62467],"type":"Point"}
}