{
  "type": "Feature",
  "properties": {
    "gn:admin1_code":"66.0",
    "gn:asciiname":"Ban Ao Chat",
    "gn:country_code":"TH",
    "gn:dem":11,
    "gn:feature_class":"P",
    "gn:feature_code":"PPL",
    "gn:name":"Ban Ao Chat",
    "gn:population":0,
    "gn:timezone":"Asia/Bangkok",
    "iso:country":"TH",
    "name:tha_x_preferred":[
        "\u0e1a\u0e49\u0e32\u0e19\u0e2d\u0e48\u0e32\u0e27\u0e08\u0e32\u0e14"
    ],
    "name:und_x_variant":[
        "Ban Chat"
    ],
    "wof:name":"Ban Ao Chat",
    "wof:placetype":"locality"
},
  "geometry": {"coordinates":[100.36091999999999,7.41657],"type":"Point"}
}