{
  "type": "Feature",
  "properties": {
    "gn:admin1_code":"34",
    "gn:asciiname":"Ban Wang Takhian",
    "gn:country_code":"TH",
    "gn:dem":61,
    "gn:feature_class":"P",
    "gn:feature_code":"PPL",
    "gn:name":"Ban Wang Takhian",
    "gn:population":0,
    "gn:timezone":"Asia/Bangkok",
    "iso:country":"TH",
    "name:tha_x_preferred":[
        "\u0e1a\u0e49\u0e32\u0e19\u0e27\u0e31\u0e07\u0e15\u0e30\u0e40\u0e04\u0e35\u0e22\u0e19"
    ],
    "wof:name":"Ban Wang Takhian",
    "wof:placetype":"locality"
},
  "geometry": {"coordinates":[101.11439,15.14897],"type":"Point"}
}