{
  "type": "Feature",
  "properties": {
    "gn:admin1_code":"37",
    "gn:asciiname":"Ban Khao Din",
    "gn:country_code":"TH",
    "gn:dem":50,
    "gn:feature_class":"P",
    "gn:feature_code":"PPL",
    "gn:name":"Ban Khao Din",
    "gn:population":0,
    "gn:timezone":"Asia/Bangkok",
    "iso:country":"TH",
    "name:tha_x_preferred":[
        "\u0e1a\u0e49\u0e32\u0e19\u0e40\u0e02\u0e32\u0e14\u0e34\u0e19"
    ],
    "wof:name":"Ban Khao Din",
    "wof:placetype":"locality"
},
  "geometry": {"coordinates":[101.04044,14.40417],"type":"Point"}
}