{
  "type": "Feature",
  "properties": {
    "gn:admin1_code":"70.0",
    "gn:asciiname":"Ban Phayap",
    "gn:country_code":"TH",
    "gn:dem":120,
    "gn:feature_class":"P",
    "gn:feature_code":"PPL",
    "gn:name":"Ban Phayap",
    "gn:population":0,
    "gn:timezone":"Asia/Bangkok",
    "iso:country":"TH",
    "name:tha_x_preferred":[
        "\u0e1a\u0e49\u0e32\u0e19\u0e1e\u0e32\u0e22\u0e31\u0e1a"
    ],
    "name:und_x_variant":[
        "Ban Pha Yai",
        "Ban Phayap"
    ],
    "wof:lang_x_official":[
        "tha"
    ],
    "wof:lang_x_spoken":[
        "tha"
    ],
    "wof:name":"Ban Phayap",
    "wof:placetype":"locality"
},
  "geometry": {"coordinates":[101.17794000000001,6.19903],"type":"Point"}
}