{
  "type": "Feature",
  "properties": {
    "gn:admin1_code":"8.0",
    "gn:asciiname":"Ban Rom Klao Sahamit",
    "gn:country_code":"TH",
    "gn:dem":845,
    "gn:feature_class":"P",
    "gn:feature_code":"PPL",
    "gn:name":"Ban Rom Klao Sahamit",
    "gn:population":0,
    "gn:timezone":"Asia/Bangkok",
    "iso:country":"TH",
    "name:tha_x_preferred":[
        "\u0e1a\u0e49\u0e32\u0e19\u0e23\u0e48\u0e21\u0e40\u0e01\u0e25\u0e49\u0e32\u0e2a\u0e2b\u0e21\u0e34\u0e15\u0e23"
    ],
    "wof:name":"Ban Rom Klao Sahamit",
    "wof:placetype":"locality"
},
  "geometry": {"coordinates":[98.84014000000001,16.47792],"type":"Point"}
}