{
  "type": "Feature",
  "properties": {
    "iso:country":"TH",
    "qs:name":"Kuet Chang",
    "qs:name_adm0":"Thailand",
    "qs:name_adm1":"Chiang Mai",
    "qs:photos":920,
    "qs:photos_1k":186,
    "qs:photos_9k":4,
    "qs:photos_9r":6,
    "qs:photos_all":920,
    "qs:photos_sr":10,
    "qs:placetype":"Town",
    "qs:pop_sr":"0",
    "wd:wordcount":58,
    "wof:name":"Kuet Chang",
    "wof:placetype":"locality"
},
  "geometry": {"coordinates":[98.85879749999999,19.214333],"type":"Point"}
}