{
  "type": "Feature",
  "properties": {
    "gn:admin1_code":"27.0",
    "gn:asciiname":"Ban Nong Tho",
    "gn:cc2":"TH",
    "gn:country_code":"TH",
    "gn:dem":199,
    "gn:feature_class":"P",
    "gn:feature_code":"PPL",
    "gn:name":"Ban Nong Tho",
    "gn:population":0,
    "gn:timezone":"Asia/Bangkok",
    "iso:country":"TH",
    "name:und_x_variant":[
        "Ban Ai Cha",
        "B\u0101n \u0100i Ja",
        "Ban Nong Tho"
    ],
    "wof:name":"Ban Nong Tho",
    "wof:placetype":"locality"
},
  "geometry": {"coordinates":[101.90833000000001,15.11306],"type":"Point"}
}