{
  "type": "Feature",
  "properties": {
    "gn:admin1_code":"70.0",
    "gn:asciiname":"Ban Na To",
    "gn:country_code":"TH",
    "gn:dem":61,
    "gn:feature_class":"P",
    "gn:feature_code":"PPL",
    "gn:name":"Ban Na To",
    "gn:population":0,
    "gn:timezone":"Asia/Bangkok",
    "iso:country":"TH",
    "name:tha_x_preferred":[
        "\u0e1a\u0e49\u0e32\u0e19\u0e19\u0e32\u0e40\u0e15\u0e4a\u0e32\u0e30"
    ],
    "name:und_x_variant":[
        "Na Tao",
        "Ban Natau",
        "Ban Bu Na To",
        "Ban Natao",
        "Ban Na To"
    ],
    "wof:lang_x_official":[
        "tha"
    ],
    "wof:lang_x_spoken":[
        "tha"
    ],
    "wof:name":"Ban Na To",
    "wof:placetype":"locality"
},
  "geometry": {"coordinates":[101.34650000000001,6.41211],"type":"Point"}
}