{
  "type": "Feature",
  "properties": {
    "gn:admin1_code":"8.0",
    "gn:asciiname":"Ban Nong Nam Khiao",
    "gn:country_code":"TH",
    "gn:dem":558,
    "gn:feature_class":"P",
    "gn:feature_code":"PPL",
    "gn:name":"Ban Nong Nam Khiao",
    "gn:population":0,
    "gn:timezone":"Asia/Bangkok",
    "iso:country":"TH",
    "name:tha_x_preferred":[
        "\u0e1a\u0e49\u0e32\u0e19\u0e2b\u0e19\u0e2d\u0e07\u0e19\u0e49\u0e33\u0e40\u0e02\u0e35\u0e22\u0e27"
    ],
    "wof:lang_x_official":[
        "tha"
    ],
    "wof:lang_x_spoken":[
        "tha"
    ],
    "wof:name":"Ban Nong Nam Khiao",
    "wof:placetype":"locality"
},
  "geometry": {"coordinates":[98.68519000000001,16.62978],"type":"Point"}
}