{
  "type": "Feature",
  "properties": {
    "gn:admin1_code":"80",
    "gn:asciiname":"Ban Khao Lueam Tai",
    "gn:country_code":"TH",
    "gn:dem":184,
    "gn:feature_class":"P",
    "gn:feature_code":"PPL",
    "gn:name":"Ban Khao Lueam Tai",
    "gn:population":0,
    "gn:timezone":"Asia/Bangkok",
    "iso:country":"TH",
    "name:tha_x_preferred":[
        "\u0e1a\u0e49\u0e32\u0e19\u0e40\u0e02\u0e32\u0e40\u0e25\u0e37\u0e48\u0e2d\u0e21\u0e43\u0e15\u0e49"
    ],
    "wof:name":"Ban Khao Lueam Tai",
    "wof:placetype":"locality"
},
  "geometry": {"coordinates":[102.30378,13.40214],"type":"Point"}
}