{
  "type": "Feature",
  "properties": {
    "gn:admin1_code":"76.0",
    "gn:asciiname":"Ban Dong Kham Bon",
    "gn:country_code":"TH",
    "gn:dem":173,
    "gn:feature_class":"P",
    "gn:feature_code":"PPL",
    "gn:name":"Ban Dong Kham Bon",
    "gn:population":0,
    "gn:timezone":"Asia/Bangkok",
    "iso:country":"TH",
    "name:tha_x_preferred":[
        "\u0e1a\u0e49\u0e32\u0e19\u0e14\u0e07\u0e04\u0e33\u0e1a\u0e48\u0e2d\u0e19"
    ],
    "wof:name":"Ban Dong Kham Bon",
    "wof:placetype":"locality"
},
  "geometry": {"coordinates":[102.95092,17.55206],"type":"Point"}
}