{
  "type": "Feature",
  "properties": {
    "gn:admin1_code":"3.0",
    "gn:asciiname":"Ban Huai Khom Nok",
    "gn:country_code":"TH",
    "gn:dem":437,
    "gn:feature_class":"P",
    "gn:feature_code":"PPL",
    "gn:name":"Ban Huai Khom Nok",
    "gn:population":0,
    "gn:timezone":"Asia/Bangkok",
    "iso:country":"TH",
    "name:tha_x_preferred":[
        "\u0e1a\u0e49\u0e32\u0e19\u0e2b\u0e49\u0e27\u0e22\u0e02\u0e21\u0e19\u0e2d\u0e01"
    ],
    "wof:name":"Ban Huai Khom Nok",
    "wof:placetype":"locality"
},
  "geometry": {"coordinates":[99.76342,19.98578],"type":"Point"}
}