{
  "type": "Feature",
  "properties": {
    "gn:admin1_code":"28",
    "gn:asciiname":"Ban Sam Sila",
    "gn:country_code":"TH",
    "gn:dem":176,
    "gn:feature_class":"P",
    "gn:feature_code":"PPL",
    "gn:name":"Ban Sam Sila",
    "gn:population":0,
    "gn:timezone":"Asia/Bangkok",
    "iso:country":"TH",
    "name:tha_x_preferred":[
        "\u0e1a\u0e49\u0e32\u0e19\u0e2a\u0e32\u0e21\u0e28\u0e34\u0e25\u0e32"
    ],
    "wof:name":"Ban Sam Sila",
    "wof:placetype":"locality"
},
  "geometry": {"coordinates":[103.08078,15.27453],"type":"Point"}
}