{
  "type": "Feature",
  "properties": {
    "gn:admin1_code":"77.0",
    "gn:asciiname":"Ban Siao Sawat",
    "gn:country_code":"TH",
    "gn:dem":137,
    "gn:feature_class":"P",
    "gn:feature_code":"PPL",
    "gn:name":"Ban Siao Sawat",
    "gn:population":0,
    "gn:timezone":"Asia/Bangkok",
    "iso:country":"TH",
    "name:tha_x_preferred":[
        "Ban Siao Sawat"
    ],
    "name:tha_x_variant":[
        "\u0e1a\u0e49\u0e32\u0e19\u0e40\u0e2a\u0e35\u0e22\u0e27\u0e2a\u0e27\u0e32\u0e2a\u0e14\u0e34\u0e4c"
    ],
    "wof:name":"Ban Siao Sawat",
    "wof:placetype":"locality"
},
  "geometry": {"coordinates":[104.85509,15.66265],"type":"Point"}
}