{
  "type": "Feature",
  "properties": {
    "gn:admin1_code":"47.0",
    "gn:asciiname":"Ban Khao Wang Man",
    "gn:country_code":"TH",
    "gn:dem":46,
    "gn:feature_class":"P",
    "gn:feature_code":"PPL",
    "gn:name":"Ban Khao Wang Man",
    "gn:population":0,
    "gn:timezone":"Asia/Bangkok",
    "iso:country":"TH",
    "name:tha_x_preferred":[
        "\u0e1a\u0e49\u0e32\u0e19\u0e40\u0e02\u0e32\u0e27\u0e31\u0e07\u0e21\u0e48\u0e32\u0e19"
    ],
    "wof:name":"Ban Khao Wang Man",
    "wof:placetype":"locality"
},
  "geometry": {"coordinates":[101.37860999999999,12.75306],"type":"Point"}
}