{
  "type": "Feature",
  "properties": {
    "gn:admin1_code":"31.0",
    "gn:asciiname":"Ban Lu Bo Lue Song",
    "gn:country_code":"TH",
    "gn:dem":6,
    "gn:feature_class":"P",
    "gn:feature_code":"PPL",
    "gn:name":"Ban Lu Bo Lue Song",
    "gn:population":0,
    "gn:timezone":"Asia/Bangkok",
    "iso:country":"TH",
    "name:tha_x_preferred":[
        "\u0e1a\u0e49\u0e32\u0e19\u0e25\u0e39\u0e42\u0e1a\u0e4a\u0e30\u0e25\u0e37\u0e2d\u0e0b\u0e07"
    ],
    "wof:name":"Ban Lu Bo Lue Song",
    "wof:placetype":"locality"
},
  "geometry": {"coordinates":[102.03303,6.09754],"type":"Point"}
}