{
  "type": "Feature",
  "properties": {
    "gn:admin1_code":"26.0",
    "gn:asciiname":"Ban Lup Chang Phlai",
    "gn:country_code":"TH",
    "gn:dem":470,
    "gn:feature_class":"P",
    "gn:feature_code":"PPL",
    "gn:name":"Ban Lup Chang Phlai",
    "gn:population":0,
    "gn:timezone":"Asia/Bangkok",
    "iso:country":"TH",
    "name:tha_x_preferred":[
        "\u0e1a\u0e49\u0e32\u0e19\u0e2b\u0e25\u0e38\u0e1a\u0e0a\u0e49\u0e32\u0e07\u0e1e\u0e25\u0e32\u0e22"
    ],
    "wof:name":"Ban Lup Chang Phlai",
    "wof:placetype":"locality"
},
  "geometry": {"coordinates":[102.04572,16.06425],"type":"Point"}
}