{
  "type": "Feature",
  "properties": {
    "gn:admin1_code":"4.0",
    "gn:asciiname":"Ban Pang San",
    "gn:country_code":"TH",
    "gn:dem":450,
    "gn:feature_class":"P",
    "gn:feature_code":"PPL",
    "gn:name":"Ban Pang San",
    "gn:population":0,
    "gn:timezone":"Asia/Bangkok",
    "iso:country":"TH",
    "wof:name":"Ban Pang San",
    "wof:placetype":"locality"
},
  "geometry": {"coordinates":[100.59999999999999,19.43333],"type":"Point"}
}