{
  "type": "Feature",
  "properties": {
    "gn:admin1_code":"31.0",
    "gn:asciiname":"Ban Ai Sue Do",
    "gn:country_code":"TH",
    "gn:dem":191,
    "gn:feature_class":"P",
    "gn:feature_code":"PPL",
    "gn:name":"Ban Ai Sue Do",
    "gn:population":0,
    "gn:timezone":"Asia/Bangkok",
    "iso:country":"TH",
    "name:tha_x_preferred":[
        "\u0e1a\u0e49\u0e32\u0e19\u0e44\u0e2d\u0e23\u0e4c\u0e0b\u0e37\u0e2d\u0e14\u0e2d"
    ],
    "wof:name":"Ban Ai Sue Do",
    "wof:placetype":"locality"
},
  "geometry": {"coordinates":[101.57706,6.18367],"type":"Point"}
}