{
  "type": "Feature",
  "properties": {
    "gn:admin1_code":"68.0",
    "gn:asciiname":"Ban Thai-Changlon",
    "gn:country_code":"TH",
    "gn:dem":88,
    "gn:feature_class":"P",
    "gn:feature_code":"PPL",
    "gn:name":"Ban Thai-Changlon",
    "gn:population":0,
    "gn:timezone":"Asia/Bangkok",
    "iso:country":"TH",
    "name:tha_x_preferred":[
        "\u0e1a\u0e49\u0e32\u0e19\u0e44\u0e17\u0e22-\u0e08\u0e31\u0e07\u0e42\u0e2b\u0e25\u0e19"
    ],
    "wof:name":"Ban Thai-Changlon",
    "wof:placetype":"locality"
},
  "geometry": {"coordinates":[100.419,6.52264],"type":"Point"}
}