{
  "type": "Feature",
  "properties": {
    "gn:admin1_code":"75.0",
    "gn:asciiname":"Ban Fa Huan",
    "gn:country_code":"TH",
    "gn:dem":159,
    "gn:feature_class":"P",
    "gn:feature_code":"PPL",
    "gn:name":"Ban Fa Huan",
    "gn:population":0,
    "gn:timezone":"Asia/Bangkok",
    "iso:country":"TH",
    "name:tha_x_preferred":[
        "\u0e1a\u0e49\u0e32\u0e19\u0e1f\u0e49\u0e32\u0e2b\u0e48\u0e27\u0e19"
    ],
    "wof:name":"Ban Fa Huan",
    "wof:placetype":"locality"
},
  "geometry": {"coordinates":[105.31456,15.53261],"type":"Point"}
}