{
  "type": "Feature",
  "properties": {
    "gn:admin1_code":"79.0",
    "gn:asciiname":"Ban Nong Nokkhian",
    "gn:country_code":"TH",
    "gn:dem":203,
    "gn:feature_class":"P",
    "gn:feature_code":"PPL",
    "gn:name":"Ban Nong Nokkhian",
    "gn:population":0,
    "gn:timezone":"Asia/Bangkok",
    "iso:country":"TH",
    "name:tha_x_preferred":[
        "\u0e1a\u0e49\u0e32\u0e19\u0e2b\u0e19\u0e2d\u0e07\u0e19\u0e01\u0e40\u0e02\u0e35\u0e22\u0e19"
    ],
    "wof:name":"Ban Nong Nokkhian",
    "wof:placetype":"locality"
},
  "geometry": {"coordinates":[102.62094,16.92147000000001],"type":"Point"}
}