{
  "type": "Feature",
  "properties": {
    "gn:admin1_code":"64.0",
    "gn:asciiname":"Ban Na",
    "gn:country_code":"TH",
    "gn:dem":19,
    "gn:feature_class":"P",
    "gn:feature_code":"PPL",
    "gn:name":"Ban Na",
    "gn:population":0,
    "gn:timezone":"Asia/Bangkok",
    "iso:country":"TH",
    "name:tha_x_preferred":[
        "\u0e1a\u0e49\u0e32\u0e19\u0e19\u0e32"
    ],
    "name:und_x_variant":[
        "Na",
        "Ban Na",
        "Ban Na San"
    ],
    "wof:name":"Ban Na",
    "wof:placetype":"locality"
},
  "geometry": {"coordinates":[99.87683,8.53],"type":"Point"}
}