{
  "type": "Feature",
  "properties": {
    "gn:admin1_code":"31.0",
    "gn:asciiname":"Ban Luk Suea",
    "gn:country_code":"TH",
    "gn:dem":13,
    "gn:feature_class":"P",
    "gn:feature_code":"PPL",
    "gn:name":"Ban Luk Suea",
    "gn:population":0,
    "gn:timezone":"Asia/Bangkok",
    "iso:country":"TH",
    "name:tha_x_preferred":[
        "\u0e1a\u0e49\u0e32\u0e19\u0e25\u0e39\u0e01\u0e40\u0e2a\u0e37\u0e2d"
    ],
    "wof:name":"Ban Luk Suea",
    "wof:placetype":"locality"
},
  "geometry": {"coordinates":[102.03533,6.07233],"type":"Point"}
}