{
  "type": "Feature",
  "properties": {
    "gn:admin1_code":"50.0",
    "gn:asciiname":"Ban Nong Kai",
    "gn:cc2":"TH",
    "gn:country_code":"TH",
    "gn:dem":151,
    "gn:feature_class":"P",
    "gn:feature_code":"PPL",
    "gn:name":"Ban Nong Kai",
    "gn:population":0,
    "gn:timezone":"Asia/Bangkok",
    "iso:country":"TH",
    "name:und_x_variant":[
        "B\u0101n Naung Gai",
        "Ban Nong Kai"
    ],
    "wof:name":"Ban Nong Kai",
    "wof:placetype":"locality"
},
  "geometry": {"coordinates":[98.40000000000001,15.08333],"type":"Point"}
}