{
  "type": "Feature",
  "properties": {
    "gn:admin1_code":"65.0",
    "gn:asciiname":"Ban Khao Kaeo",
    "gn:country_code":"TH",
    "gn:dem":50,
    "gn:feature_class":"P",
    "gn:feature_code":"PPL",
    "gn:name":"Ban Khao Kaeo",
    "gn:population":0,
    "gn:timezone":"Asia/Bangkok",
    "iso:country":"TH",
    "name:tha_x_preferred":[
        "\u0e1a\u0e49\u0e32\u0e19\u0e40\u0e02\u0e32\u0e41\u0e01\u0e49\u0e27"
    ],
    "name:und_x_variant":[
        "B\u0101n K\u0101o K\u0101u",
        "Ban Khao Khao (2)",
        "Ban Khao Kaeo"
    ],
    "wof:name":"Ban Khao Kaeo",
    "wof:placetype":"locality"
},
  "geometry": {"coordinates":[99.45625,7.81161],"type":"Point"}
}