{
  "type": "Feature",
  "properties": {
    "gn:admin1_code":"5.0",
    "gn:asciiname":"Ban Ling Loe",
    "gn:country_code":"TH",
    "gn:dem":474,
    "gn:feature_class":"P",
    "gn:feature_code":"PPL",
    "gn:name":"Ban Ling Loe",
    "gn:population":0,
    "gn:timezone":"Asia/Bangkok",
    "iso:country":"TH",
    "name:tha_x_preferred":[
        "\u0e1a\u0e49\u0e32\u0e19\u0e2b\u0e25\u0e34\u0e48\u0e07\u0e40\u0e25\u0e2d\u0e30"
    ],
    "wof:name":"Ban Ling Loe",
    "wof:placetype":"locality"
},
  "geometry": {"coordinates":[98.94607999999999,18.26044],"type":"Point"}
}