{
  "type": "Feature",
  "properties": {
    "gn:admin1_code":"24.0",
    "gn:asciiname":"Ban Ku Thong",
    "gn:country_code":"TH",
    "gn:dem":161,
    "gn:feature_class":"P",
    "gn:feature_code":"PPL",
    "gn:name":"Ban Ku Thong",
    "gn:population":0,
    "gn:timezone":"Asia/Bangkok",
    "iso:country":"TH",
    "name:tha_x_preferred":[
        "\u0e1a\u0e49\u0e32\u0e19\u0e01\u0e39\u0e48\u0e17\u0e2d\u0e07"
    ],
    "wof:name":"Ban Ku Thong",
    "wof:placetype":"locality"
},
  "geometry": {"coordinates":[102.96389000000001,16.44269],"type":"Point"}
}