{
  "type": "Feature",
  "properties": {
    "gn:admin1_code":"0.0",
    "gn:asciiname":"Ban Lo Khang Khao",
    "gn:country_code":"TH",
    "gn:dem":1061,
    "gn:feature_class":"P",
    "gn:feature_code":"PPL",
    "gn:name":"Ban Lo Khang Khao",
    "gn:population":0,
    "gn:timezone":"Asia/Bangkok",
    "iso:country":"TH",
    "wof:name":"Ban Lo Khang Khao",
    "wof:placetype":"locality"
},
  "geometry": {"coordinates":[98.47833,18.32111],"type":"Point"}
}