{
  "type": "Feature",
  "properties": {
    "gn:admin1_code":"64.0",
    "gn:asciiname":"Ban Sa Chu",
    "gn:country_code":"TH",
    "gn:dem":6,
    "gn:feature_class":"P",
    "gn:feature_code":"PPL",
    "gn:name":"Ban Sa Chu",
    "gn:population":0,
    "gn:timezone":"Asia/Bangkok",
    "iso:country":"TH",
    "name:tha_x_preferred":[
        "\u0e1a\u0e49\u0e32\u0e19\u0e2a\u0e23\u0e30\u0e0a\u0e39"
    ],
    "wof:name":"Ban Sa Chu",
    "wof:placetype":"locality"
},
  "geometry": {"coordinates":[100.18628,8.10683],"type":"Point"}
}