{
  "type": "Feature",
  "properties": {
    "gn:admin1_code":"0.0",
    "gn:asciiname":"Ban Si Che",
    "gn:country_code":"TH",
    "gn:dem":1049,
    "gn:feature_class":"P",
    "gn:feature_code":"PPL",
    "gn:name":"Ban Si Che",
    "gn:population":0,
    "gn:timezone":"Asia/Bangkok",
    "iso:country":"TH",
    "wof:name":"Ban Si Che",
    "wof:placetype":"locality"
},
  "geometry": {"coordinates":[98.18805999999999,18.20111],"type":"Point"}
}