{
  "type": "Feature",
  "properties": {
    "gn:admin1_code":"14.0",
    "gn:asciiname":"Ban Lam Phat",
    "gn:country_code":"TH",
    "gn:dem":148,
    "gn:feature_class":"P",
    "gn:feature_code":"PPL",
    "gn:name":"Ban Lam Phat",
    "gn:population":0,
    "gn:timezone":"Asia/Bangkok",
    "iso:country":"TH",
    "name:tha_x_preferred":[
        "\u0e1a\u0e49\u0e32\u0e19\u0e25\u0e33\u0e1e\u0e32\u0e14"
    ],
    "wof:name":"Ban Lam Phat",
    "wof:placetype":"locality"
},
  "geometry": {"coordinates":[101.00266999999999,16.00572],"type":"Point"}
}