{
  "type": "Feature",
  "properties": {
    "gn:admin1_code":"22",
    "gn:asciiname":"Ban Nong Waeng Pracha",
    "gn:country_code":"TH",
    "gn:dem":179,
    "gn:feature_class":"P",
    "gn:feature_code":"PPL",
    "gn:name":"Ban Nong Waeng Pracha",
    "gn:population":0,
    "gn:timezone":"Asia/Bangkok",
    "iso:country":"TH",
    "name:tha_x_preferred":[
        "\u0e1a\u0e49\u0e32\u0e19\u0e2b\u0e19\u0e2d\u0e07\u0e41\u0e27\u0e07\u0e1b\u0e23\u0e30\u0e0a\u0e32"
    ],
    "wof:name":"Ban Nong Waeng Pracha",
    "wof:placetype":"locality"
},
  "geometry": {"coordinates":[102.742,16.84425],"type":"Point"}
}