{
  "type": "Feature",
  "properties": {
    "gn:admin1_code":"60.0",
    "gn:asciiname":"Ban Nok Yang",
    "gn:country_code":"TH",
    "gn:dem":21,
    "gn:feature_class":"P",
    "gn:feature_code":"PPL",
    "gn:name":"Ban Nok Yang",
    "gn:population":0,
    "gn:timezone":"Asia/Bangkok",
    "iso:country":"TH",
    "name:tha_x_preferred":[
        "\u0e1a\u0e49\u0e32\u0e19\u0e19\u0e01\u0e22\u0e32\u0e07"
    ],
    "wof:name":"Ban Nok Yang",
    "wof:placetype":"locality"
},
  "geometry": {"coordinates":[99.01728,9.03028],"type":"Point"}
}