{
  "type": "Feature",
  "properties": {
    "gn:admin1_code":"27",
    "gn:asciiname":"Ban Sap Udom",
    "gn:country_code":"TH",
    "gn:dem":221,
    "gn:feature_class":"P",
    "gn:feature_code":"PPL",
    "gn:name":"Ban Sap Udom",
    "gn:population":0,
    "gn:timezone":"Asia/Bangkok",
    "iso:country":"TH",
    "name:tha_x_preferred":[
        "\u0e1a\u0e49\u0e32\u0e19\u0e17\u0e23\u0e31\u0e1e\u0e22\u0e4c\u0e2d\u0e38\u0e14\u0e21"
    ],
    "wof:name":"Ban Sap Udom",
    "wof:placetype":"locality"
},
  "geometry": {"coordinates":[102.24583,14.49489],"type":"Point"}
}