{
  "type": "Feature",
  "properties": {
    "gn:admin1_code":"27.0",
    "gn:asciiname":"Ban Takhong Kao",
    "gn:country_code":"TH",
    "gn:dem":184,
    "gn:feature_class":"P",
    "gn:feature_code":"PPL",
    "gn:name":"Ban Takhong Kao",
    "gn:population":0,
    "gn:timezone":"Asia/Bangkok",
    "iso:country":"TH",
    "name:tha_x_preferred":[
        "\u0e1a\u0e49\u0e32\u0e19\u0e15\u0e30\u0e04\u0e2d\u0e07\u0e40\u0e01\u0e48\u0e32"
    ],
    "name:und_x_variant":[
        "Ban Takho",
        "Ban Takhlong Kao (1)",
        "Ban Takhong Kao"
    ],
    "wof:name":"Ban Takhong Kao",
    "wof:placetype":"locality"
},
  "geometry": {"coordinates":[102.06289,14.98894],"type":"Point"}
}