{
  "type": "Feature",
  "properties": {
    "gn:admin1_code":"17.0",
    "gn:asciiname":"Ban Sok Kla Nua",
    "gn:country_code":"TH",
    "gn:dem":198,
    "gn:feature_class":"P",
    "gn:feature_code":"PPL",
    "gn:name":"Ban Sok Kla Nua",
    "gn:population":0,
    "gn:timezone":"Asia/Bangkok",
    "iso:country":"TH",
    "wof:name":"Ban Sok Kla Nua",
    "wof:placetype":"locality"
},
  "geometry": {"coordinates":[102.22944,18.04306],"type":"Point"}
}