{
  "type": "Feature",
  "properties": {
    "gn:admin1_code":"29",
    "gn:asciiname":"Ban Ra-ngaeng Tai",
    "gn:country_code":"TH",
    "gn:dem":141,
    "gn:feature_class":"P",
    "gn:feature_code":"PPL",
    "gn:name":"Ban Ra-ngaeng Tai",
    "gn:population":0,
    "gn:timezone":"Asia/Bangkok",
    "iso:country":"TH",
    "name:tha_x_preferred":[
        "\u0e1a\u0e49\u0e32\u0e19\u0e23\u0e30\u0e41\u0e07\u0e07\u0e43\u0e15\u0e49"
    ],
    "wof:name":"Ban Ra-ngaeng Tai",
    "wof:placetype":"locality"
},
  "geometry": {"coordinates":[103.78655999999999,14.9405],"type":"Point"}
}