{
  "type": "Feature",
  "properties": {
    "gn:admin1_code":"18.0",
    "gn:asciiname":"Ban Nam Thaeng",
    "gn:country_code":"TH",
    "gn:dem":363,
    "gn:feature_class":"P",
    "gn:feature_code":"PPL",
    "gn:name":"Ban Nam Thaeng",
    "gn:population":0,
    "gn:timezone":"Asia/Bangkok",
    "iso:country":"TH",
    "name:tha_x_preferred":[
        "\u0e1a\u0e49\u0e32\u0e19\u0e2b\u0e19\u0e32\u0e21\u0e41\u0e17\u0e07"
    ],
    "name:und_x_variant":[
        "B\u0101n N\u0101m Theang",
        "Ban Nam Thaeng"
    ],
    "wof:name":"Ban Nam Thaeng",
    "wof:placetype":"locality"
},
  "geometry": {"coordinates":[101.12972000000001,17.29194],"type":"Point"}
}