{
  "type": "Feature",
  "properties": {
    "gn:admin1_code":"36",
    "gn:asciiname":"Ban Tamru",
    "gn:country_code":"TH",
    "gn:dem":10,
    "gn:feature_class":"P",
    "gn:feature_code":"PPL",
    "gn:name":"Ban Tamru",
    "gn:population":0,
    "gn:timezone":"Asia/Bangkok",
    "iso:country":"TH",
    "name:tha_x_preferred":[
        "\u0e1a\u0e49\u0e32\u0e19\u0e15\u0e33\u0e2b\u0e23\u0e38"
    ],
    "wof:name":"Ban Tamru",
    "wof:placetype":"locality"
},
  "geometry": {"coordinates":[100.65447,14.49394],"type":"Point"}
}