{
  "type": "Feature",
  "properties": {
    "gn:admin1_code":"65.0",
    "gn:asciiname":"Ban Khok Wan",
    "gn:country_code":"TH",
    "gn:dem":20,
    "gn:feature_class":"P",
    "gn:feature_code":"PPL",
    "gn:name":"Ban Khok Wan",
    "gn:population":0,
    "gn:timezone":"Asia/Bangkok",
    "iso:country":"TH",
    "name:tha_x_preferred":[
        "\u0e1a\u0e49\u0e32\u0e19\u0e42\u0e04\u0e01\u0e2b\u0e27\u0e49\u0e32\u0e19"
    ],
    "wof:name":"Ban Khok Wan",
    "wof:placetype":"locality"
},
  "geometry": {"coordinates":[99.51578000000001,7.54653],"type":"Point"}
}