{
  "type": "Feature",
  "properties": {
    "gn:admin1_code":"4.0",
    "gn:asciiname":"Ban Thung Hao",
    "gn:country_code":"TH",
    "gn:dem":318,
    "gn:feature_class":"P",
    "gn:feature_code":"PPL",
    "gn:name":"Ban Thung Hao",
    "gn:population":0,
    "gn:timezone":"Asia/Bangkok",
    "iso:country":"TH",
    "name:tha_x_preferred":[
        "\u0e1a\u0e49\u0e32\u0e19\u0e17\u0e38\u0e48\u0e07\u0e40\u0e2e\u0e49\u0e32"
    ],
    "name:und_x_variant":[
        "Ban Don Kaeo"
    ],
    "wof:name":"Ban Thung Hao",
    "wof:placetype":"locality"
},
  "geometry": {"coordinates":[100.92949,19.0401],"type":"Point"}
}