{
  "type": "Feature",
  "properties": {
    "gn:admin1_code":"75.0",
    "gn:asciiname":"Ban Don Ngio",
    "gn:country_code":"TH",
    "gn:dem":115,
    "gn:feature_class":"P",
    "gn:feature_code":"PPL",
    "gn:name":"Ban Don Ngio",
    "gn:population":0,
    "gn:timezone":"Asia/Bangkok",
    "iso:country":"TH",
    "name:tha_x_preferred":[
        "\u0e1a\u0e49\u0e32\u0e19\u0e14\u0e2d\u0e19\u0e07\u0e34\u0e49\u0e27"
    ],
    "wof:name":"Ban Don Ngio",
    "wof:placetype":"locality"
},
  "geometry": {"coordinates":[104.85644000000001,15.20598],"type":"Point"}
}