{
  "type": "Feature",
  "properties": {
    "gn:admin1_code":"70.0",
    "gn:asciiname":"Ban Sa Ke Nok",
    "gn:country_code":"TH",
    "gn:dem":40,
    "gn:feature_class":"P",
    "gn:feature_code":"PPL",
    "gn:name":"Ban Sa Ke Nok",
    "gn:population":0,
    "gn:timezone":"Asia/Bangkok",
    "iso:country":"TH",
    "name:tha_x_preferred":[
        "\u0e1a\u0e49\u0e32\u0e19\u0e2a\u0e32\u0e40\u0e01\u0e19\u0e2d\u0e01"
    ],
    "wof:name":"Ban Sa Ke Nok",
    "wof:placetype":"locality"
},
  "geometry": {"coordinates":[101.28125,6.42486],"type":"Point"}
}