{
  "type": "Feature",
  "properties": {
    "gn:admin1_code":"26.0",
    "gn:asciiname":"Ban Nong Khai Nam",
    "gn:country_code":"TH",
    "gn:dem":196,
    "gn:feature_class":"P",
    "gn:feature_code":"PPL",
    "gn:name":"Ban Nong Khai Nam",
    "gn:population":0,
    "gn:timezone":"Asia/Bangkok",
    "iso:country":"TH",
    "name:tha_x_preferred":[
        "\u0e1a\u0e49\u0e32\u0e19\u0e2b\u0e19\u0e2d\u0e07\u0e44\u0e02\u0e48\u0e19\u0e49\u0e33"
    ],
    "wof:name":"Ban Nong Khai Nam",
    "wof:placetype":"locality"
},
  "geometry": {"coordinates":[102.01443999999999,15.65297],"type":"Point"}
}