{
  "type": "Feature",
  "properties": {
    "gn:admin1_code":"3.0",
    "gn:asciiname":"Ban Patan Doi",
    "gn:country_code":"TH",
    "gn:dem":386,
    "gn:feature_class":"P",
    "gn:feature_code":"PPL",
    "gn:name":"Ban Patan Doi",
    "gn:population":0,
    "gn:timezone":"Asia/Bangkok",
    "iso:country":"TH",
    "name:tha_x_preferred":[
        "\u0e1a\u0e49\u0e32\u0e19\u0e1b\u0e48\u0e32\u0e15\u0e32\u0e25\u0e14\u0e2d\u0e22"
    ],
    "wof:name":"Ban Patan Doi",
    "wof:placetype":"locality"
},
  "geometry": {"coordinates":[100.27110999999999,19.84925],"type":"Point"}
}