{
  "type": "Feature",
  "properties": {
    "gn:admin1_code":"26.0",
    "gn:asciiname":"Ban Hua Khu",
    "gn:country_code":"TH",
    "gn:dem":257,
    "gn:feature_class":"P",
    "gn:feature_code":"PPL",
    "gn:name":"Ban Hua Khu",
    "gn:population":0,
    "gn:timezone":"Asia/Bangkok",
    "iso:country":"TH",
    "name:tha_x_preferred":[
        "\u0e1a\u0e49\u0e32\u0e19\u0e2b\u0e31\u0e27\u0e04\u0e39"
    ],
    "wof:name":"Ban Hua Khu",
    "wof:placetype":"locality"
},
  "geometry": {"coordinates":[101.70281,15.62683],"type":"Point"}
}