{
  "type": "Feature",
  "properties": {
    "gn:admin1_code":"29",
    "gn:asciiname":"Ban Kut Wai",
    "gn:country_code":"TH",
    "gn:dem":146,
    "gn:feature_class":"P",
    "gn:feature_code":"PPL",
    "gn:name":"Ban Kut Wai",
    "gn:population":0,
    "gn:timezone":"Asia/Bangkok",
    "iso:country":"TH",
    "name:tha_x_preferred":[
        "\u0e1a\u0e49\u0e32\u0e19\u0e01\u0e38\u0e14\u0e2b\u0e27\u0e32\u0e22"
    ],
    "wof:name":"Ban Kut Wai",
    "wof:placetype":"locality"
},
  "geometry": {"coordinates":[103.90013999999999,14.90853],"type":"Point"}
}