{
  "type": "Feature",
  "properties": {
    "gn:admin1_code":"36.0",
    "gn:asciiname":"Ban Lam Daeng",
    "gn:country_code":"TH",
    "gn:dem":5,
    "gn:feature_class":"P",
    "gn:feature_code":"PPL",
    "gn:name":"Ban Lam Daeng",
    "gn:population":0,
    "gn:timezone":"Asia/Bangkok",
    "iso:country":"TH",
    "name:tha_x_preferred":[
        "\u0e1a\u0e49\u0e32\u0e19\u0e25\u0e33\u0e41\u0e14\u0e07"
    ],
    "name:und_x_variant":[
        "Ban Lamdeng",
        "Ban Lam Daeng"
    ],
    "wof:name":"Ban Lam Daeng",
    "wof:placetype":"locality"
},
  "geometry": {"coordinates":[100.75272,14.30706],"type":"Point"}
}