{
  "type": "Feature",
  "properties": {
    "gn:admin1_code":"16.0",
    "gn:asciiname":"Ban Ko Ta Thep",
    "gn:country_code":"TH",
    "gn:dem":29,
    "gn:feature_class":"P",
    "gn:feature_code":"PPL",
    "gn:name":"Ban Ko Ta Thep",
    "gn:population":0,
    "gn:timezone":"Asia/Bangkok",
    "iso:country":"TH",
    "name:tha_x_preferred":[
        "\u0e1a\u0e49\u0e32\u0e19\u0e40\u0e01\u0e32\u0e30\u0e15\u0e32\u0e40\u0e17\u0e1e"
    ],
    "wof:name":"Ban Ko Ta Thep",
    "wof:placetype":"locality"
},
  "geometry": {"coordinates":[100.11353,15.73286],"type":"Point"}
}