{
  "type": "Feature",
  "properties": {
    "gn:admin1_code":"13.0",
    "gn:asciiname":"Ban Phai Luang",
    "gn:country_code":"TH",
    "gn:dem":37,
    "gn:feature_class":"P",
    "gn:feature_code":"PPL",
    "gn:name":"Ban Phai Luang",
    "gn:population":0,
    "gn:timezone":"Asia/Bangkok",
    "iso:country":"TH",
    "name:tha_x_preferred":[
        "\u0e1a\u0e49\u0e32\u0e19\u0e44\u0e1c\u0e48\u0e2b\u0e25\u0e27\u0e07"
    ],
    "wof:name":"Ban Phai Luang",
    "wof:placetype":"locality"
},
  "geometry": {"coordinates":[100.40786,16.18939],"type":"Point"}
}