{
  "type": "Feature",
  "properties": {
    "gn:admin1_code":"25.0",
    "gn:asciiname":"Ban Phue Hi",
    "gn:country_code":"TH",
    "gn:dem":148,
    "gn:feature_class":"P",
    "gn:feature_code":"PPL",
    "gn:name":"Ban Phue Hi",
    "gn:population":0,
    "gn:timezone":"Asia/Bangkok",
    "iso:country":"TH",
    "name:tha_x_preferred":[
        "\u0e1a\u0e49\u0e32\u0e19\u0e1c\u0e37\u0e2d\u0e2e\u0e35"
    ],
    "wof:name":"Ban Phue Hi",
    "wof:placetype":"locality"
},
  "geometry": {"coordinates":[103.65510999999999,15.8635],"type":"Point"}
}