{
  "type": "Feature",
  "properties": {
    "gn:admin1_code":"18.0",
    "gn:asciiname":"Ban Mak Khaeng",
    "gn:country_code":"TH",
    "gn:dem":706,
    "gn:feature_class":"P",
    "gn:feature_code":"PPL",
    "gn:name":"Ban Mak Khaeng",
    "gn:population":0,
    "gn:timezone":"Asia/Bangkok",
    "iso:country":"TH",
    "name:tha_x_preferred":[
        "Ban Mak Khaeng"
    ],
    "name:tha_x_variant":[
        "\u0e1a\u0e49\u0e32\u0e19\u0e2b\u0e21\u0e32\u0e01\u0e41\u0e02\u0e49\u0e07"
    ],
    "wof:name":"Ban Mak Khaeng",
    "wof:placetype":"locality"
},
  "geometry": {"coordinates":[101.11049,17.00814],"type":"Point"}
}