{
  "type": "Feature",
  "properties": {
    "gn:admin1_code":"51.0",
    "gn:asciiname":"Ban Luang",
    "gn:country_code":"TH",
    "gn:dem":8,
    "gn:feature_class":"P",
    "gn:feature_code":"PPL",
    "gn:name":"Ban Luang",
    "gn:population":0,
    "gn:timezone":"Asia/Bangkok",
    "iso:country":"TH",
    "name:tha_x_preferred":[
        "\u0e1a\u0e49\u0e32\u0e19\u0e2b\u0e25\u0e27\u0e07"
    ],
    "name:und_x_variant":[
        "Ban Luango",
        "Ban Luang"
    ],
    "wof:name":"Ban Luang",
    "wof:placetype":"locality"
},
  "geometry": {"coordinates":[99.95192,14.44903],"type":"Point"}
}