{
  "type": "Feature",
  "properties": {
    "gn:admin1_code":"53.0",
    "gn:asciiname":"Ban Ko Klang",
    "gn:country_code":"TH",
    "gn:dem":9,
    "gn:feature_class":"P",
    "gn:feature_code":"PPL",
    "gn:name":"Ban Ko Klang",
    "gn:population":0,
    "gn:timezone":"Asia/Bangkok",
    "iso:country":"TH",
    "name:tha_x_preferred":[
        "\u0e1a\u0e49\u0e32\u0e19\u0e40\u0e01\u0e32\u0e30\u0e01\u0e25\u0e32\u0e07"
    ],
    "name:und_x_variant":[
        "Ban Don Klang"
    ],
    "wof:name":"Ban Ko Klang",
    "wof:placetype":"locality"
},
  "geometry": {"coordinates":[100.10429999999999,13.95324],"type":"Point"}
}