{
  "type": "Feature",
  "properties": {
    "gn:admin1_code":"2.0",
    "gn:asciiname":"Ban San Khong Kao",
    "gn:country_code":"TH",
    "gn:dem":317,
    "gn:feature_class":"P",
    "gn:feature_code":"PPL",
    "gn:name":"Ban San Khong Kao",
    "gn:population":0,
    "gn:timezone":"Asia/Bangkok",
    "iso:country":"TH",
    "name:tha_x_preferred":[
        "\u0e1a\u0e49\u0e32\u0e19\u0e2a\u0e31\u0e19\u0e42\u0e04\u0e49\u0e07\u0e40\u0e01\u0e48\u0e32"
    ],
    "wof:name":"Ban San Khong Kao",
    "wof:placetype":"locality"
},
  "geometry": {"coordinates":[99.13755999999999,18.7367],"type":"Point"}
}