{
  "type": "Feature",
  "properties": {
    "gn:admin1_code":"65.0",
    "gn:asciiname":"Ban Huai Mai Phai",
    "gn:country_code":"TH",
    "gn:dem":19,
    "gn:feature_class":"P",
    "gn:feature_code":"PPL",
    "gn:name":"Ban Huai Mai Phai",
    "gn:population":0,
    "gn:timezone":"Asia/Bangkok",
    "iso:country":"TH",
    "name:tha_x_preferred":[
        "\u0e1a\u0e49\u0e32\u0e19\u0e2b\u0e49\u0e27\u0e22\u0e44\u0e21\u0e49\u0e44\u0e1c\u0e48"
    ],
    "wof:name":"Ban Huai Mai Phai",
    "wof:placetype":"locality"
},
  "geometry": {"coordinates":[99.69419000000001,7.21756],"type":"Point"}
}