{
  "type": "Feature",
  "properties": {
    "gn:admin1_code":"29",
    "gn:asciiname":"Ban Riang Phanom",
    "gn:country_code":"TH",
    "gn:dem":131,
    "gn:feature_class":"P",
    "gn:feature_code":"PPL",
    "gn:name":"Ban Riang Phanom",
    "gn:population":0,
    "gn:timezone":"Asia/Bangkok",
    "iso:country":"TH",
    "name:tha_x_preferred":[
        "\u0e1a\u0e49\u0e32\u0e19\u0e40\u0e23\u0e35\u0e22\u0e07\u0e1e\u0e19\u0e21"
    ],
    "wof:name":"Ban Riang Phanom",
    "wof:placetype":"locality"
},
  "geometry": {"coordinates":[103.67422000000001,15.36108],"type":"Point"}
}