{
  "type": "Feature",
  "properties": {
    "gn:admin1_code":"27",
    "gn:asciiname":"Ban Thanon Hak",
    "gn:country_code":"TH",
    "gn:dem":175,
    "gn:feature_class":"P",
    "gn:feature_code":"PPL",
    "gn:name":"Ban Thanon Hak",
    "gn:population":0,
    "gn:timezone":"Asia/Bangkok",
    "iso:country":"TH",
    "name:tha_x_preferred":[
        "\u0e1a\u0e49\u0e32\u0e19\u0e16\u0e19\u0e19\u0e2b\u0e31\u0e01"
    ],
    "wof:name":"Ban Thanon Hak",
    "wof:placetype":"locality"
},
  "geometry": {"coordinates":[102.25169,15.32677],"type":"Point"}
}