{
  "type": "Feature",
  "properties": {
    "gn:admin1_code":"64.0",
    "gn:asciiname":"Ban Pian",
    "gn:country_code":"TH",
    "gn:dem":111,
    "gn:feature_class":"P",
    "gn:feature_code":"PPL",
    "gn:name":"Ban Pian",
    "gn:population":0,
    "gn:timezone":"Asia/Bangkok",
    "iso:country":"TH",
    "name:tha_x_preferred":[
        "\u0e1a\u0e49\u0e32\u0e19\u0e40\u0e1b\u0e35\u0e22\u0e19"
    ],
    "name:und_x_variant":[
        "Ban Bien",
        "Pian",
        "Ban Pian"
    ],
    "wof:name":"Ban Pian",
    "wof:placetype":"locality"
},
  "geometry": {"coordinates":[99.63467,8.79547],"type":"Point"}
}