{
  "type": "Feature",
  "properties": {
    "gn:admin1_code":"44.0",
    "gn:asciiname":"Ban Pa I Thaen",
    "gn:country_code":"TH",
    "gn:dem":37,
    "gn:feature_class":"P",
    "gn:feature_code":"PPL",
    "gn:name":"Ban Pa I Thaen",
    "gn:population":0,
    "gn:timezone":"Asia/Bangkok",
    "iso:country":"TH",
    "name:tha_x_preferred":[
        "\u0e1a\u0e49\u0e32\u0e19\u0e1b\u0e48\u0e32\u0e2d\u0e35\u0e41\u0e17\u0e19"
    ],
    "wof:lang_x_official":[
        "tha"
    ],
    "wof:lang_x_spoken":[
        "tha"
    ],
    "wof:name":"Ban Pa I Thaen",
    "wof:placetype":"locality"
},
  "geometry": {"coordinates":[101.54317,13.58803],"type":"Point"}
}