{
  "type": "Feature",
  "properties": {
    "gn:admin1_code":"2.0",
    "gn:asciiname":"Ban Mu Soe Pa Khli",
    "gn:country_code":"TH",
    "gn:dem":530,
    "gn:feature_class":"P",
    "gn:feature_code":"PPL",
    "gn:name":"Ban Mu Soe Pa Khli",
    "gn:population":0,
    "gn:timezone":"Asia/Bangkok",
    "iso:country":"TH",
    "name:tha_x_preferred":[
        "\u0e1a\u0e49\u0e32\u0e19\u0e21\u0e39\u0e40\u0e0b\u0e2d\u0e23\u0e4c\u0e1b\u0e48\u0e32\u0e04\u0e25\u0e35"
    ],
    "wof:name":"Ban Mu Soe Pa Khli",
    "wof:placetype":"locality"
},
  "geometry": {"coordinates":[99.18781,19.95806],"type":"Point"}
}