{
  "type": "Feature",
  "properties": {
    "gn:admin1_code":"69.0",
    "gn:asciiname":"Ban Chamao Sam Ton",
    "gn:country_code":"TH",
    "gn:dem":12,
    "gn:feature_class":"P",
    "gn:feature_code":"PPL",
    "gn:name":"Ban Chamao Sam Ton",
    "gn:population":0,
    "gn:timezone":"Asia/Bangkok",
    "iso:country":"TH",
    "name:tha_x_preferred":[
        "\u0e1a\u0e49\u0e32\u0e19\u0e0a\u0e30\u0e40\u0e21\u0e32\u0e2a\u0e32\u0e21\u0e15\u0e49\u0e19"
    ],
    "wof:name":"Ban Chamao Sam Ton",
    "wof:placetype":"locality"
},
  "geometry": {"coordinates":[101.56881,6.69703],"type":"Point"}
}