{
  "type": "Feature",
  "properties": {
    "gn:admin1_code":"28",
    "gn:asciiname":"Ban Kut Yai",
    "gn:country_code":"TH",
    "gn:dem":147,
    "gn:feature_class":"P",
    "gn:feature_code":"PPL",
    "gn:name":"Ban Kut Yai",
    "gn:population":0,
    "gn:timezone":"Asia/Bangkok",
    "iso:country":"TH",
    "name:tha_x_preferred":[
        "\u0e1a\u0e49\u0e32\u0e19\u0e01\u0e38\u0e14\u0e43\u0e2b\u0e0d\u0e48"
    ],
    "wof:name":"Ban Kut Yai",
    "wof:placetype":"locality"
},
  "geometry": {"coordinates":[103.35947,14.86461],"type":"Point"}
}