{
  "type": "Feature",
  "properties": {
    "gn:admin1_code":"50.0",
    "gn:asciiname":"Ban Kaeng Pralom",
    "gn:country_code":"TH",
    "gn:dem":71,
    "gn:feature_class":"P",
    "gn:feature_code":"PPL",
    "gn:name":"Ban Kaeng Pralom",
    "gn:population":0,
    "gn:timezone":"Asia/Bangkok",
    "iso:country":"TH",
    "name:tha_x_preferred":[
        "\u0e1a\u0e49\u0e32\u0e19\u0e41\u0e01\u0e48\u0e07\u0e1b\u0e23\u0e30\u0e25\u0e2d\u0e21"
    ],
    "wof:name":"Ban Kaeng Pralom",
    "wof:placetype":"locality"
},
  "geometry": {"coordinates":[98.87675,14.3842],"type":"Point"}
}