{
  "type": "Feature",
  "properties": {
    "gn:admin1_code":"7.0",
    "gn:asciiname":"Ban Huai Yuak",
    "gn:country_code":"TH",
    "gn:dem":446,
    "gn:feature_class":"P",
    "gn:feature_code":"PPL",
    "gn:name":"Ban Huai Yuak",
    "gn:population":0,
    "gn:timezone":"Asia/Bangkok",
    "iso:country":"TH",
    "name:tha_x_preferred":[
        "\u0e1a\u0e49\u0e32\u0e19\u0e2b\u0e49\u0e27\u0e22\u0e2b\u0e22\u0e27\u0e01"
    ],
    "wof:name":"Ban Huai Yuak",
    "wof:placetype":"locality"
},
  "geometry": {"coordinates":[100.32261,18.03267],"type":"Point"}
}