{
  "type": "Feature",
  "properties": {
    "gn:admin1_code":"1.0",
    "gn:asciiname":"Ban Don Tan",
    "gn:country_code":"TH",
    "gn:dem":456,
    "gn:feature_class":"P",
    "gn:feature_code":"PPL",
    "gn:name":"Ban Don Tan",
    "gn:population":0,
    "gn:timezone":"Asia/Bangkok",
    "iso:country":"TH",
    "name:tha_x_preferred":[
        "\u0e1a\u0e49\u0e32\u0e19\u0e14\u0e2d\u0e19\u0e15\u0e31\u0e19"
    ],
    "wof:name":"Ban Don Tan",
    "wof:placetype":"locality"
},
  "geometry": {"coordinates":[98.37689,19.21289],"type":"Point"}
}