{
  "type": "Feature",
  "properties": {
    "gn:admin1_code":"58.0",
    "gn:asciiname":"Ban Don Sathon",
    "gn:country_code":"TH",
    "gn:dem":11,
    "gn:feature_class":"P",
    "gn:feature_code":"PPL",
    "gn:name":"Ban Don Sathon",
    "gn:population":0,
    "gn:timezone":"Asia/Bangkok",
    "iso:country":"TH",
    "name:tha_x_preferred":[
        "\u0e1a\u0e49\u0e32\u0e19\u0e14\u0e2d\u0e19\u0e2a\u0e30\u0e17\u0e49\u0e2d\u0e19"
    ],
    "name:und_x_variant":[
        "Ban Don Kathon",
        "Ban Don Sathon"
    ],
    "wof:name":"Ban Don Sathon",
    "wof:placetype":"locality"
},
  "geometry": {"coordinates":[99.10594,10.25792],"type":"Point"}
}