{
  "type": "Feature",
  "properties": {
    "gn:admin1_code":"18.0",
    "gn:asciiname":"Ban Kam Phi",
    "gn:country_code":"TH",
    "gn:dem":345,
    "gn:feature_class":"P",
    "gn:feature_code":"PPL",
    "gn:name":"Ban Kam Phi",
    "gn:population":0,
    "gn:timezone":"Asia/Bangkok",
    "iso:country":"TH",
    "name:tha_x_preferred":[
        "\u0e1a\u0e49\u0e32\u0e19\u0e01\u0e33\u0e1e\u0e35\u0e49"
    ],
    "name:und_x_variant":[
        "B\u0101n Hua Kam Pi",
        "Ban Hua Kham Pi",
        "Ban Kam Phi"
    ],
    "wof:name":"Ban Kam Phi",
    "wof:placetype":"locality"
},
  "geometry": {"coordinates":[101.57545,17.60389],"type":"Point"}
}