{
  "type": "Feature",
  "properties": {
    "gn:admin1_code":"59.0",
    "gn:asciiname":"Ban Nuea",
    "gn:country_code":"TH",
    "gn:dem":45,
    "gn:feature_class":"P",
    "gn:feature_code":"PPL",
    "gn:name":"Ban Nuea",
    "gn:population":0,
    "gn:timezone":"Asia/Bangkok",
    "iso:country":"TH",
    "name:tha_x_preferred":[
        "\u0e1a\u0e49\u0e32\u0e19\u0e40\u0e2b\u0e19\u0e37\u0e2d"
    ],
    "wof:name":"Ban Nuea",
    "wof:placetype":"locality"
},
  "geometry": {"coordinates":[98.82289,10.18886],"type":"Point"}
}