{
  "type": "Feature",
  "properties": {
    "gn:admin1_code":"9.0",
    "gn:asciiname":"Ban Khlong Tan",
    "gn:country_code":"TH",
    "gn:dem":60,
    "gn:feature_class":"P",
    "gn:feature_code":"PPL",
    "gn:name":"Ban Khlong Tan",
    "gn:population":0,
    "gn:timezone":"Asia/Bangkok",
    "iso:country":"TH",
    "name:tha_x_preferred":[
        "\u0e1a\u0e49\u0e32\u0e19\u0e04\u0e25\u0e2d\u0e07\u0e15\u0e32\u0e25"
    ],
    "name:und_x_variant":[
        "B\u0101n Klaung Trang",
        "Ban Khlong Trang",
        "Ban Khlong Tan"
    ],
    "wof:name":"Ban Khlong Tan",
    "wof:placetype":"locality"
},
  "geometry": {"coordinates":[99.86039,17.17575],"type":"Point"}
}