{
  "type": "Feature",
  "properties": {
    "gn:admin1_code":"61.0",
    "gn:asciiname":"Ban Bang Nae",
    "gn:country_code":"TH",
    "gn:dem":21,
    "gn:feature_class":"P",
    "gn:feature_code":"PPL",
    "gn:name":"Ban Bang Nae",
    "gn:population":0,
    "gn:timezone":"Asia/Bangkok",
    "iso:country":"TH",
    "name:tha_x_preferred":[
        "\u0e1a\u0e49\u0e32\u0e19\u0e1a\u0e32\u0e07\u0e41\u0e19\u0e30"
    ],
    "name:und_x_variant":[
        "Ban Bang Na"
    ],
    "wof:name":"Ban Bang Nae",
    "wof:placetype":"locality"
},
  "geometry": {"coordinates":[98.5197,8.4953],"type":"Point"}
}