{
  "type": "Feature",
  "properties": {
    "gn:admin1_code":"31.0",
    "gn:asciiname":"Ban Ta Ba",
    "gn:country_code":"TH",
    "gn:dem":5,
    "gn:feature_class":"P",
    "gn:feature_code":"PPL",
    "gn:name":"Ban Ta Ba",
    "gn:population":0,
    "gn:timezone":"Asia/Bangkok",
    "iso:country":"TH",
    "name:tha_x_preferred":[
        "\u0e1a\u0e49\u0e32\u0e19\u0e15\u0e32\u0e1a\u0e32"
    ],
    "name:und_x_variant":[
        "Kampong Tabalamo",
        "Kampong Tabar Lama",
        "Ban Ta Ba"
    ],
    "wof:name":"Ban Ta Ba",
    "wof:placetype":"locality"
},
  "geometry": {"coordinates":[102.08660999999999,6.23712],"type":"Point"}
}