{
  "type": "Feature",
  "properties": {
    "gn:admin1_code":"77.0",
    "gn:asciiname":"Ban Bung Sombat",
    "gn:country_code":"TH",
    "gn:dem":154,
    "gn:feature_class":"P",
    "gn:feature_code":"PPL",
    "gn:name":"Ban Bung Sombat",
    "gn:population":0,
    "gn:timezone":"Asia/Bangkok",
    "iso:country":"TH",
    "name:tha_x_preferred":[
        "Ban Bung Sombat"
    ],
    "name:tha_x_variant":[
        "\u0e1a\u0e49\u0e32\u0e19\u0e1a\u0e38\u0e48\u0e07\u0e2a\u0e21\u0e1a\u0e31\u0e15\u0e34"
    ],
    "wof:name":"Ban Bung Sombat",
    "wof:placetype":"locality"
},
  "geometry": {"coordinates":[105.04358000000001,16.09689],"type":"Point"}
}