{
  "type": "Feature",
  "properties": {
    "gn:admin1_code":"52.0",
    "gn:asciiname":"Ban Ko Ta Phut",
    "gn:country_code":"TH",
    "gn:dem":36,
    "gn:feature_class":"P",
    "gn:feature_code":"PPL",
    "gn:name":"Ban Ko Ta Phut",
    "gn:population":0,
    "gn:timezone":"Asia/Bangkok",
    "iso:country":"TH",
    "name:tha_x_preferred":[
        "\u0e1a\u0e49\u0e32\u0e19\u0e40\u0e01\u0e32\u0e30\u0e15\u0e32\u0e1e\u0e38\u0e14"
    ],
    "wof:name":"Ban Ko Ta Phut",
    "wof:placetype":"locality"
},
  "geometry": {"coordinates":[99.70131000000001,13.682],"type":"Point"}
}