{
  "type": "Feature",
  "properties": {
    "gn:admin1_code":"76.0",
    "gn:asciiname":"Ban Si Sawang Wong",
    "gn:country_code":"TH",
    "gn:dem":175,
    "gn:feature_class":"P",
    "gn:feature_code":"PPL",
    "gn:name":"Ban Si Sawang Wong",
    "gn:population":0,
    "gn:timezone":"Asia/Bangkok",
    "iso:country":"TH",
    "name:tha_x_preferred":[
        "\u0e1a\u0e49\u0e32\u0e19\u0e28\u0e23\u0e35\u0e2a\u0e27\u0e48\u0e32\u0e07\u0e27\u0e07\u0e28\u0e4c"
    ],
    "wof:name":"Ban Si Sawang Wong",
    "wof:placetype":"locality"
},
  "geometry": {"coordinates":[102.91153,17.70161000000001],"type":"Point"}
}