{
  "type": "Feature",
  "properties": {
    "gn:admin1_code":"40.0",
    "gn:admin2_code":"1011",
    "gn:asciiname":"Ban Khlong Chek",
    "gn:country_code":"TH",
    "gn:dem":2,
    "gn:feature_class":"P",
    "gn:feature_code":"PPL",
    "gn:name":"Ban Khlong Chek",
    "gn:population":0,
    "gn:timezone":"Asia/Bangkok",
    "iso:country":"TH",
    "name:tha_x_preferred":[
        "\u0e1a\u0e49\u0e32\u0e19\u0e04\u0e25\u0e2d\u0e07\u0e40\u0e08\u0e47\u0e01"
    ],
    "wof:name":"Ban Khlong Chek",
    "wof:placetype":"locality"
},
  "geometry": {"coordinates":[100.82013999999999,13.74619],"type":"Point"}
}