{
  "type": "Feature",
  "properties": {
    "gn:admin1_code":"46.0",
    "gn:asciiname":"Ban Phatthaya Tai",
    "gn:country_code":"TH",
    "gn:dem":18,
    "gn:feature_class":"P",
    "gn:feature_code":"PPL",
    "gn:name":"Ban Phatthaya Tai",
    "gn:population":0,
    "gn:timezone":"Asia/Bangkok",
    "iso:country":"TH",
    "name:tha_x_preferred":[
        "\u0e1a\u0e49\u0e32\u0e19\u0e1e\u0e31\u0e17\u0e22\u0e32\u0e43\u0e15\u0e49"
    ],
    "wof:name":"Ban Phatthaya Tai",
    "wof:placetype":"locality"
},
  "geometry": {"coordinates":[100.879,12.92992],"type":"Point"}
}