{
  "type": "Feature",
  "properties": {
    "gn:admin1_code":"27.0",
    "gn:asciiname":"Ban Takhian",
    "gn:country_code":"TH",
    "gn:dem":226,
    "gn:feature_class":"P",
    "gn:feature_code":"PPL",
    "gn:name":"Ban Takhian",
    "gn:population":0,
    "gn:timezone":"Asia/Bangkok",
    "iso:country":"TH",
    "name:tha_x_preferred":[
        "\u0e1a\u0e49\u0e32\u0e19\u0e15\u0e30\u0e40\u0e04\u0e35\u0e22\u0e19"
    ],
    "name:und_x_variant":[
        "Ban Takhian Yai"
    ],
    "wof:name":"Ban Takhian",
    "wof:placetype":"locality"
},
  "geometry": {"coordinates":[101.69956000000001,15.15989],"type":"Point"}
}