{
  "type": "Feature",
  "properties": {
    "gn:admin1_code":"76.0",
    "gn:asciiname":"Ban Narai",
    "gn:country_code":"TH",
    "gn:dem":175,
    "gn:feature_class":"P",
    "gn:feature_code":"PPL",
    "gn:name":"Ban Narai",
    "gn:population":0,
    "gn:timezone":"Asia/Bangkok",
    "iso:country":"TH",
    "name:tha_x_preferred":[
        "\u0e1a\u0e49\u0e32\u0e19\u0e19\u0e32\u0e23\u0e32\u0e22\u0e13\u0e4c"
    ],
    "wof:name":"Ban Narai",
    "wof:placetype":"locality"
},
  "geometry": {"coordinates":[102.89086,17.86942],"type":"Point"}
}