{
  "type": "Feature",
  "properties": {
    "gn:admin1_code":"80",
    "gn:asciiname":"Ban Noen Kham",
    "gn:country_code":"TH",
    "gn:dem":119,
    "gn:feature_class":"P",
    "gn:feature_code":"PPL",
    "gn:name":"Ban Noen Kham",
    "gn:population":0,
    "gn:timezone":"Asia/Bangkok",
    "iso:country":"TH",
    "name:tha_x_preferred":[
        "\u0e1a\u0e49\u0e32\u0e19\u0e40\u0e19\u0e34\u0e19\u0e02\u0e32\u0e21"
    ],
    "wof:name":"Ban Noen Kham",
    "wof:placetype":"locality"
},
  "geometry": {"coordinates":[102.58060999999999,14.03558],"type":"Point"}
}