{
  "type": "Feature",
  "properties": {
    "gn:admin1_code":"79.0",
    "gn:asciiname":"Ban Wang Hin Sa",
    "gn:country_code":"TH",
    "gn:dem":212,
    "gn:feature_class":"P",
    "gn:feature_code":"PPL",
    "gn:name":"Ban Wang Hin Sa",
    "gn:population":0,
    "gn:timezone":"Asia/Bangkok",
    "iso:country":"TH",
    "name:und_x_variant":[
        "\u0e1a\u0e49\u0e32\u0e19\u0e27\u0e31\u0e07\u0e2b\u0e34\u0e19\u0e0b\u0e32"
    ],
    "wof:name":"Ban Wang Hin Sa",
    "wof:placetype":"locality"
},
  "geometry": {"coordinates":[102.24578,17.60761],"type":"Point"}
}