{
  "type": "Feature",
  "properties": {
    "gn:admin1_code":"43.0",
    "gn:asciiname":"Ban Pak Khlong Sip Hok",
    "gn:country_code":"TH",
    "gn:dem":8,
    "gn:feature_class":"P",
    "gn:feature_code":"PPL",
    "gn:name":"Ban Pak Khlong Sip Hok",
    "gn:population":0,
    "gn:timezone":"Asia/Bangkok",
    "iso:country":"TH",
    "name:tha_x_preferred":[
        "Ban Pak Khlong Sip Hok"
    ],
    "name:tha_x_variant":[
        "\u0e1a\u0e49\u0e32\u0e19\u0e1b\u0e32\u0e01\u0e04\u0e25\u0e2d\u0e07\u0e2a\u0e34\u0e1a\u0e2b\u0e01"
    ],
    "wof:name":"Ban Pak Khlong Sip Hok",
    "wof:placetype":"locality"
},
  "geometry": {"coordinates":[100.94694,14.09497],"type":"Point"}
}