{
  "type": "Feature",
  "properties": {
    "gn:admin1_code":"15.0",
    "gn:asciiname":"Ban Thap Tae",
    "gn:country_code":"TH",
    "gn:dem":39,
    "gn:feature_class":"P",
    "gn:feature_code":"PPL",
    "gn:name":"Ban Thap Tae",
    "gn:population":0,
    "gn:timezone":"Asia/Bangkok",
    "iso:country":"TH",
    "wof:name":"Ban Thap Tae",
    "wof:placetype":"locality"
},
  "geometry": {"coordinates":[99.88333,15.36667],"type":"Point"}
}