{
  "type": "Feature",
  "properties": {
    "gn:admin1_code":"26.0",
    "gn:asciiname":"Ban Khok Kung",
    "gn:country_code":"TH",
    "gn:dem":227,
    "gn:feature_class":"P",
    "gn:feature_code":"PPL",
    "gn:name":"Ban Khok Kung",
    "gn:population":0,
    "gn:timezone":"Asia/Bangkok",
    "iso:country":"TH",
    "name:tha_x_preferred":[
        "\u0e1a\u0e49\u0e32\u0e19\u0e42\u0e04\u0e01\u0e01\u0e38\u0e07"
    ],
    "name:und_x_variant":[
        "Ban Kut Kung"
    ],
    "wof:lang_x_official":[
        "tha"
    ],
    "wof:lang_x_spoken":[
        "tha"
    ],
    "wof:name":"Ban Khok Kung",
    "wof:placetype":"locality"
},
  "geometry": {"coordinates":[102.16803,16.13456],"type":"Point"}
}