{
  "type": "Feature",
  "properties": {
    "gn:admin1_code":"47.0",
    "gn:asciiname":"Ban Chak Khanun",
    "gn:country_code":"TH",
    "gn:dem":17,
    "gn:feature_class":"P",
    "gn:feature_code":"PPL",
    "gn:name":"Ban Chak Khanun",
    "gn:population":0,
    "gn:timezone":"Asia/Bangkok",
    "iso:country":"TH",
    "wof:name":"Ban Chak Khanun",
    "wof:placetype":"locality"
},
  "geometry": {"coordinates":[101.34999999999999,12.71667],"type":"Point"}
}