{
  "type": "Feature",
  "properties": {
    "gn:admin1_code":"80",
    "gn:asciiname":"Ban Khao Maka",
    "gn:country_code":"TH",
    "gn:dem":51,
    "gn:feature_class":"P",
    "gn:feature_code":"PPL",
    "gn:name":"Ban Khao Maka",
    "gn:population":0,
    "gn:timezone":"Asia/Bangkok",
    "iso:country":"TH",
    "name:tha_x_preferred":[
        "\u0e1a\u0e49\u0e32\u0e19\u0e40\u0e02\u0e32\u0e21\u0e30\u0e01\u0e32"
    ],
    "wof:name":"Ban Khao Maka",
    "wof:placetype":"locality"
},
  "geometry": {"coordinates":[101.96406,13.79469],"type":"Point"}
}