{
  "type": "Feature",
  "properties": {
    "gn:admin1_code":"60.0",
    "gn:asciiname":"Ban Nai Siat",
    "gn:country_code":"TH",
    "gn:dem":8,
    "gn:feature_class":"P",
    "gn:feature_code":"PPL",
    "gn:name":"Ban Nai Siat",
    "gn:population":0,
    "gn:timezone":"Asia/Bangkok",
    "iso:country":"TH",
    "name:tha_x_preferred":[
        "\u0e1a\u0e49\u0e32\u0e19\u0e43\u0e19\u0e40\u0e0b\u0e35\u0e22\u0e14"
    ],
    "name:und_x_variant":[
        "Bang Siat"
    ],
    "wof:name":"Ban Nai Siat",
    "wof:placetype":"locality"
},
  "geometry": {"coordinates":[99.21108,8.98861],"type":"Point"}
}