{
  "type": "Feature",
  "properties": {
    "gn:admin1_code":"3.0",
    "gn:asciiname":"Ban Mae Pha Tan",
    "gn:country_code":"TH",
    "gn:dem":667,
    "gn:feature_class":"P",
    "gn:feature_code":"PPL",
    "gn:name":"Ban Mae Pha Tan",
    "gn:population":0,
    "gn:timezone":"Asia/Bangkok",
    "iso:country":"TH",
    "name:tha_x_preferred":[
        "\u0e1a\u0e49\u0e32\u0e19\u0e41\u0e21\u0e48\u0e1c\u0e32\u0e15\u0e31\u0e19"
    ],
    "name:und_x_variant":[
        "Ban Mae Fai Tan"
    ],
    "wof:name":"Ban Mae Pha Tan",
    "wof:placetype":"locality"
},
  "geometry": {"coordinates":[99.50069000000001,19.11061],"type":"Point"}
}