{
  "type": "Feature",
  "properties": {
    "gn:admin1_code":"50.0",
    "gn:asciiname":"Ban Kaeng Sian",
    "gn:country_code":"TH",
    "gn:dem":40,
    "gn:feature_class":"P",
    "gn:feature_code":"PPL",
    "gn:name":"Ban Kaeng Sian",
    "gn:population":0,
    "gn:timezone":"Asia/Bangkok",
    "iso:country":"TH",
    "name:tha_x_preferred":[
        "\u0e1a\u0e49\u0e32\u0e19\u0e41\u0e01\u0e48\u0e07\u0e40\u0e2a\u0e35\u0e49\u0e22\u0e19"
    ],
    "wof:name":"Ban Kaeng Sian",
    "wof:placetype":"locality"
},
  "geometry": {"coordinates":[99.48442,14.06167],"type":"Point"}
}