{
  "type": "Feature",
  "properties": {
    "gn:admin1_code":"60.0",
    "gn:asciiname":"Ban Ang Thong",
    "gn:country_code":"TH",
    "gn:dem":63,
    "gn:feature_class":"P",
    "gn:feature_code":"PPL",
    "gn:name":"Ban Ang Thong",
    "gn:population":0,
    "gn:timezone":"Asia/Bangkok",
    "iso:country":"TH",
    "name:tha_x_preferred":[
        "\u0e1a\u0e49\u0e32\u0e19\u0e2d\u0e48\u0e32\u0e07\u0e17\u0e2d\u0e07"
    ],
    "wof:name":"Ban Ang Thong",
    "wof:placetype":"locality"
},
  "geometry": {"coordinates":[98.99908000000001,9.44003],"type":"Point"}
}