{
  "type": "Feature",
  "properties": {
    "gn:admin1_code":"14.0",
    "gn:asciiname":"Ban Sam Bun",
    "gn:country_code":"TH",
    "gn:dem":481,
    "gn:feature_class":"P",
    "gn:feature_code":"PPL",
    "gn:name":"Ban Sam Bun",
    "gn:population":0,
    "gn:timezone":"Asia/Bangkok",
    "iso:country":"TH",
    "name:tha_x_preferred":[
        "\u0e1a\u0e49\u0e32\u0e19\u0e0b\u0e33\u0e1a\u0e38\u0e48\u0e19"
    ],
    "wof:lang_x_official":[
        "tha"
    ],
    "wof:lang_x_spoken":[
        "tha"
    ],
    "wof:name":"Ban Sam Bun",
    "wof:placetype":"locality"
},
  "geometry": {"coordinates":[101.33302999999999,17.06925],"type":"Point"}
}