{
  "type": "Feature",
  "properties": {
    "gn:admin1_code":"8.0",
    "gn:asciiname":"Ban Ya Ka Toe Kho",
    "gn:country_code":"TH",
    "gn:dem":563,
    "gn:feature_class":"P",
    "gn:feature_code":"PPL",
    "gn:name":"Ban Ya Ka Toe Kho",
    "gn:population":0,
    "gn:timezone":"Asia/Bangkok",
    "iso:country":"TH",
    "name:tha_x_preferred":[
        "\u0e1a\u0e49\u0e32\u0e19\u0e22\u0e30\u0e01\u0e30\u0e40\u0e15\u0e49\u0e2d\u0e42\u0e04\u0e4a\u0e30"
    ],
    "wof:name":"Ban Ya Ka Toe Kho",
    "wof:placetype":"locality"
},
  "geometry": {"coordinates":[98.17856,17.43481],"type":"Point"}
}