{
  "type": "Feature",
  "properties": {
    "gn:admin1_code":"23.0",
    "gn:asciiname":"Ban Nong Pham",
    "gn:country_code":"TH",
    "gn:dem":192,
    "gn:feature_class":"P",
    "gn:feature_code":"PPL",
    "gn:name":"Ban Nong Pham",
    "gn:population":0,
    "gn:timezone":"Asia/Bangkok",
    "iso:country":"TH",
    "name:tha_x_preferred":[
        "\u0e1a\u0e49\u0e32\u0e19\u0e2b\u0e19\u0e2d\u0e07\u0e1c\u0e33"
    ],
    "wof:name":"Ban Nong Pham",
    "wof:placetype":"locality"
},
  "geometry": {"coordinates":[103.72478,16.50567],"type":"Point"}
}