{
  "type": "Feature",
  "properties": {
    "gn:admin1_code":"15.0",
    "gn:asciiname":"Ban Chong Nok Tha",
    "gn:country_code":"TH",
    "gn:dem":131,
    "gn:feature_class":"P",
    "gn:feature_code":"PPL",
    "gn:name":"Ban Chong Nok Tha",
    "gn:population":0,
    "gn:timezone":"Asia/Bangkok",
    "iso:country":"TH",
    "name:tha_x_preferred":[
        "\u0e1a\u0e49\u0e32\u0e19\u0e0a\u0e48\u0e2d\u0e07\u0e19\u0e01\u0e17\u0e32"
    ],
    "wof:name":"Ban Chong Nok Tha",
    "wof:placetype":"locality"
},
  "geometry": {"coordinates":[99.65980999999999,15.11],"type":"Point"}
}