{
  "type": "Feature",
  "properties": {
    "gn:admin1_code":"69.0",
    "gn:asciiname":"Ban Bli Ku",
    "gn:country_code":"TH",
    "gn:dem":11,
    "gn:feature_class":"P",
    "gn:feature_code":"PPL",
    "gn:name":"Ban Bli Ku",
    "gn:population":0,
    "gn:timezone":"Asia/Bangkok",
    "iso:country":"TH",
    "name:tha_x_preferred":[
        "\u0e1a\u0e49\u0e32\u0e19\u0e1a\u0e25\u0e35\u0e01\u0e39"
    ],
    "wof:name":"Ban Bli Ku",
    "wof:placetype":"locality"
},
  "geometry": {"coordinates":[101.63633,6.64425],"type":"Point"}
}