{
  "type": "Feature",
  "properties": {
    "gn:admin1_code":"33",
    "gn:asciiname":"Ban Khlong Sam Yaek",
    "gn:country_code":"TH",
    "gn:dem":15,
    "gn:feature_class":"P",
    "gn:feature_code":"PPL",
    "gn:name":"Ban Khlong Sam Yaek",
    "gn:population":0,
    "gn:timezone":"Asia/Bangkok",
    "iso:country":"TH",
    "name:tha_x_preferred":[
        "\u0e1a\u0e49\u0e32\u0e19\u0e04\u0e25\u0e2d\u0e07\u0e2a\u0e32\u0e21\u0e41\u0e22\u0e01"
    ],
    "wof:name":"Ban Khlong Sam Yaek",
    "wof:placetype":"locality"
},
  "geometry": {"coordinates":[100.36461,14.87997],"type":"Point"}
}