{
  "type": "Feature",
  "properties": {
    "gn:admin1_code":"44.0",
    "gn:asciiname":"Ban To Krathum",
    "gn:country_code":"TH",
    "gn:dem":5,
    "gn:feature_class":"P",
    "gn:feature_code":"PPL",
    "gn:name":"Ban To Krathum",
    "gn:population":0,
    "gn:timezone":"Asia/Bangkok",
    "iso:country":"TH",
    "name:tha_x_preferred":[
        "\u0e1a\u0e49\u0e32\u0e19\u0e15\u0e2d\u0e01\u0e23\u0e30\u0e17\u0e38\u0e48\u0e21"
    ],
    "wof:name":"Ban To Krathum",
    "wof:placetype":"locality"
},
  "geometry": {"coordinates":[101.07619,13.84808],"type":"Point"}
}