{
  "type": "Feature",
  "properties": {
    "gn:admin1_code":"64.0",
    "gn:asciiname":"Ban Thung Chai Sai",
    "gn:country_code":"TH",
    "gn:dem":52,
    "gn:feature_class":"P",
    "gn:feature_code":"PPL",
    "gn:name":"Ban Thung Chai Sai",
    "gn:population":0,
    "gn:timezone":"Asia/Bangkok",
    "iso:country":"TH",
    "name:tha_x_preferred":[
        "\u0e1a\u0e49\u0e32\u0e19\u0e17\u0e38\u0e48\u0e07\u0e0a\u0e32\u0e22\u0e44\u0e2a"
    ],
    "wof:name":"Ban Thung Chai Sai",
    "wof:placetype":"locality"
},
  "geometry": {"coordinates":[99.50597,8.28908],"type":"Point"}
}