{
  "type": "Feature",
  "properties": {
    "gn:admin1_code":"8.0",
    "gn:asciiname":"Ban Mo Ko Khi",
    "gn:country_code":"TH",
    "gn:dem":807,
    "gn:feature_class":"P",
    "gn:feature_code":"PPL",
    "gn:name":"Ban Mo Ko Khi",
    "gn:population":0,
    "gn:timezone":"Asia/Bangkok",
    "iso:country":"TH",
    "name:tha_x_preferred":[
        "\u0e1a\u0e49\u0e32\u0e19\u0e21\u0e2d\u0e42\u0e01\u0e49\u0e04\u0e35"
    ],
    "wof:name":"Ban Mo Ko Khi",
    "wof:placetype":"locality"
},
  "geometry": {"coordinates":[98.25714000000001,17.42289],"type":"Point"}
}