{
  "type": "Feature",
  "properties": {
    "gn:admin1_code":"3.0",
    "gn:asciiname":"Ban Ngio Thao",
    "gn:country_code":"TH",
    "gn:dem":386,
    "gn:feature_class":"P",
    "gn:feature_code":"PPL",
    "gn:name":"Ban Ngio Thao",
    "gn:population":0,
    "gn:timezone":"Asia/Bangkok",
    "iso:country":"TH",
    "name:tha_x_preferred":[
        "\u0e1a\u0e49\u0e32\u0e19\u0e07\u0e34\u0e49\u0e27\u0e40\u0e12\u0e48\u0e32"
    ],
    "name:und_x_variant":[
        "Ban Ngiu Thao",
        "Ban Ngio Thao"
    ],
    "wof:name":"Ban Ngio Thao",
    "wof:placetype":"locality"
},
  "geometry": {"coordinates":[100.00208000000001,20.3407],"type":"Point"}
}