{
  "type": "Feature",
  "properties": {
    "gn:admin1_code":"63.0",
    "gn:asciiname":"Ban Pak Chong",
    "gn:country_code":"TH",
    "gn:dem":121,
    "gn:feature_class":"P",
    "gn:feature_code":"PPL",
    "gn:name":"Ban Pak Chong",
    "gn:population":0,
    "gn:timezone":"Asia/Bangkok",
    "iso:country":"TH",
    "name:tha_x_preferred":[
        "\u0e1a\u0e49\u0e32\u0e19\u0e1b\u0e32\u0e01\u0e0a\u0e48\u0e2d\u0e07"
    ],
    "wof:name":"Ban Pak Chong",
    "wof:placetype":"locality"
},
  "geometry": {"coordinates":[98.91733000000001,8.38353],"type":"Point"}
}