{
  "type": "Feature",
  "properties": {
    "gn:admin1_code":"46.0",
    "gn:asciiname":"Ban Pong Saket",
    "gn:country_code":"TH",
    "gn:dem":142,
    "gn:feature_class":"P",
    "gn:feature_code":"PPL",
    "gn:name":"Ban Pong Saket",
    "gn:population":0,
    "gn:timezone":"Asia/Bangkok",
    "iso:country":"TH",
    "name:tha_x_preferred":[
        "\u0e1a\u0e49\u0e32\u0e19\u0e42\u0e1b\u0e48\u0e07\u0e2a\u0e30\u0e40\u0e01\u0e47\u0e15"
    ],
    "wof:name":"Ban Pong Saket",
    "wof:placetype":"locality"
},
  "geometry": {"coordinates":[101.06345,13.00683],"type":"Point"}
}