{
  "type": "Feature",
  "properties": {
    "gn:admin1_code":"75.0",
    "gn:asciiname":"Ban Nong Tae",
    "gn:country_code":"TH",
    "gn:dem":161,
    "gn:feature_class":"P",
    "gn:feature_code":"PPL",
    "gn:name":"Ban Nong Tae",
    "gn:population":0,
    "gn:timezone":"Asia/Bangkok",
    "iso:country":"TH",
    "name:tha_x_preferred":[
        "\u0e1a\u0e49\u0e32\u0e19\u0e2b\u0e19\u0e2d\u0e07\u0e41\u0e15\u0e49"
    ],
    "wof:name":"Ban Nong Tae",
    "wof:placetype":"locality"
},
  "geometry": {"coordinates":[104.92936,14.83881],"type":"Point"}
}