{
  "type": "Feature",
  "properties": {
    "gn:admin1_code":"8.0",
    "gn:asciiname":"Ban Rang Raeng",
    "gn:country_code":"TH",
    "gn:dem":147,
    "gn:feature_class":"P",
    "gn:feature_code":"PPL",
    "gn:name":"Ban Rang Raeng",
    "gn:population":0,
    "gn:timezone":"Asia/Bangkok",
    "iso:country":"TH",
    "name:tha_x_preferred":[
        "Ban Rang Raeng"
    ],
    "name:tha_x_variant":[
        "\u0e1a\u0e49\u0e32\u0e19\u0e23\u0e31\u0e07\u0e41\u0e23\u0e49\u0e07"
    ],
    "wof:name":"Ban Rang Raeng",
    "wof:placetype":"locality"
},
  "geometry": {"coordinates":[99.01605000000001,17.03372],"type":"Point"}
}