{
  "type": "Feature",
  "properties": {
    "gn:admin1_code":"58.0",
    "gn:asciiname":"Ban Khung Yang",
    "gn:country_code":"TH",
    "gn:dem":13,
    "gn:feature_class":"P",
    "gn:feature_code":"PPL",
    "gn:name":"Ban Khung Yang",
    "gn:population":0,
    "gn:timezone":"Asia/Bangkok",
    "iso:country":"TH",
    "name:tha_x_preferred":[
        "\u0e1a\u0e49\u0e32\u0e19\u0e04\u0e38\u0e49\u0e07\u0e22\u0e32\u0e07"
    ],
    "wof:name":"Ban Khung Yang",
    "wof:placetype":"locality"
},
  "geometry": {"coordinates":[99.50739,10.89033],"type":"Point"}
}