{
  "type": "Feature",
  "properties": {
    "gn:admin1_code":"56.0",
    "gn:asciiname":"Ban Nong Chumphon",
    "gn:country_code":"TH",
    "gn:dem":22,
    "gn:feature_class":"P",
    "gn:feature_code":"PPL",
    "gn:name":"Ban Nong Chumphon",
    "gn:population":0,
    "gn:timezone":"Asia/Bangkok",
    "iso:country":"TH",
    "name:tha_x_preferred":[
        "\u0e1a\u0e49\u0e32\u0e19\u0e2b\u0e19\u0e2d\u0e07\u0e0a\u0e38\u0e21\u0e1e\u0e25"
    ],
    "wof:name":"Ban Nong Chumphon",
    "wof:placetype":"locality"
},
  "geometry": {"coordinates":[99.78753,13.29325],"type":"Point"}
}