{
  "type": "Feature",
  "properties": {
    "gn:admin1_code":"63.0",
    "gn:asciiname":"Ban Chang Tai",
    "gn:country_code":"TH",
    "gn:dem":62,
    "gn:feature_class":"P",
    "gn:feature_code":"PPL",
    "gn:name":"Ban Chang Tai",
    "gn:population":0,
    "gn:timezone":"Asia/Bangkok",
    "iso:country":"TH",
    "name:tha_x_preferred":[
        "\u0e1a\u0e49\u0e32\u0e19\u0e0a\u0e49\u0e32\u0e07\u0e15\u0e32\u0e22"
    ],
    "wof:name":"Ban Chang Tai",
    "wof:placetype":"locality"
},
  "geometry": {"coordinates":[99.06358,8.28767],"type":"Point"}
}