{
  "type": "Feature",
  "properties": {
    "gn:admin1_code":"52.0",
    "gn:asciiname":"Ban Choeng Saphan",
    "gn:country_code":"TH",
    "gn:dem":16,
    "gn:feature_class":"P",
    "gn:feature_code":"PPL",
    "gn:name":"Ban Choeng Saphan",
    "gn:population":0,
    "gn:timezone":"Asia/Bangkok",
    "iso:country":"TH",
    "name:tha_x_preferred":[
        "\u0e1a\u0e49\u0e32\u0e19\u0e40\u0e0a\u0e34\u0e07\u0e2a\u0e30\u0e1e\u0e32\u0e19"
    ],
    "wof:name":"Ban Choeng Saphan",
    "wof:placetype":"locality"
},
  "geometry": {"coordinates":[99.75881,13.55917],"type":"Point"}
}