{
  "type": "Feature",
  "properties": {
    "gn:admin1_code":"80",
    "gn:asciiname":"Ban Sap Mon",
    "gn:country_code":"TH",
    "gn:dem":89,
    "gn:feature_class":"P",
    "gn:feature_code":"PPL",
    "gn:name":"Ban Sap Mon",
    "gn:population":0,
    "gn:timezone":"Asia/Bangkok",
    "iso:country":"TH",
    "name:tha_x_preferred":[
        "\u0e1a\u0e49\u0e32\u0e19\u0e0b\u0e31\u0e1a\u0e21\u0e25"
    ],
    "wof:name":"Ban Sap Mon",
    "wof:placetype":"locality"
},
  "geometry": {"coordinates":[102.47836,13.90806],"type":"Point"}
}