{
  "type": "Feature",
  "properties": {
    "gn:admin1_code":"57.0",
    "gn:asciiname":"Ban Pak Khlong Kliao",
    "gn:country_code":"TH",
    "gn:dem":3,
    "gn:feature_class":"P",
    "gn:feature_code":"PPL",
    "gn:name":"Ban Pak Khlong Kliao",
    "gn:population":0,
    "gn:timezone":"Asia/Bangkok",
    "iso:country":"TH",
    "name:tha_x_preferred":[
        "\u0e1a\u0e49\u0e32\u0e19\u0e1b\u0e32\u0e01\u0e04\u0e25\u0e2d\u0e07\u0e40\u0e01\u0e25\u0e35\u0e22\u0e27"
    ],
    "name:und_x_variant":[
        "Ban Klieo",
        "Ban Pak Khlong Klieo",
        "Ban Pak Khlong Kliao"
    ],
    "wof:name":"Ban Pak Khlong Kliao",
    "wof:placetype":"locality"
},
  "geometry": {"coordinates":[99.90786,12.04336],"type":"Point"}
}