{
  "type": "Feature",
  "properties": {
    "gn:admin1_code":"68.0",
    "gn:asciiname":"Ban Kho Lo Mudo",
    "gn:country_code":"TH",
    "gn:dem":33,
    "gn:feature_class":"P",
    "gn:feature_code":"PPL",
    "gn:name":"Ban Kho Lo Mudo",
    "gn:population":0,
    "gn:timezone":"Asia/Bangkok",
    "iso:country":"TH",
    "name:tha_x_preferred":[
        "\u0e1a\u0e49\u0e32\u0e19\u0e04\u0e2d\u0e25\u0e2d\u0e21\u0e38\u0e14\u0e2d"
    ],
    "wof:name":"Ban Kho Lo Mudo",
    "wof:placetype":"locality"
},
  "geometry": {"coordinates":[100.95574999999999,6.54353],"type":"Point"}
}