{
  "type": "Feature",
  "properties": {
    "gn:admin1_code":"4.0",
    "gn:asciiname":"Ban Chae Phlang",
    "gn:country_code":"TH",
    "gn:dem":203,
    "gn:feature_class":"P",
    "gn:feature_code":"PPL",
    "gn:name":"Ban Chae Phlang",
    "gn:population":0,
    "gn:timezone":"Asia/Bangkok",
    "iso:country":"TH",
    "name:tha_x_preferred":[
        "\u0e1a\u0e49\u0e32\u0e19\u0e41\u0e0a\u0e48\u0e1e\u0e25\u0e32\u0e07"
    ],
    "name:und_x_variant":[
        "B\u0101n Paung Kam",
        "Ban Pong Kham",
        "Ban Chae Phang (1)",
        "Ban Chae Phlang"
    ],
    "wof:name":"Ban Chae Phlang",
    "wof:placetype":"locality"
},
  "geometry": {"coordinates":[100.77285999999999,18.74461],"type":"Point"}
}