{
  "type": "Feature",
  "properties": {
    "gn:admin1_code":"18.0",
    "gn:asciiname":"Ban Pong Pa Tio",
    "gn:country_code":"TH",
    "gn:dem":307,
    "gn:feature_class":"P",
    "gn:feature_code":"PPL",
    "gn:name":"Ban Pong Pa Tio",
    "gn:population":0,
    "gn:timezone":"Asia/Bangkok",
    "iso:country":"TH",
    "name:tha_x_preferred":[
        "\u0e1a\u0e49\u0e32\u0e19\u0e42\u0e1b\u0e48\u0e07\u0e1b\u0e48\u0e32\u0e15\u0e34\u0e49\u0e27"
    ],
    "name:und_x_variant":[
        "Ban Pong Pa Tiu"
    ],
    "wof:name":"Ban Pong Pa Tio",
    "wof:placetype":"locality"
},
  "geometry": {"coordinates":[101.59703,17.57222],"type":"Point"}
}