{
  "type": "Feature",
  "properties": {
    "gn:admin1_code":"31.0",
    "gn:asciiname":"Ban Khok Ma Chae",
    "gn:country_code":"TH",
    "gn:dem":18,
    "gn:feature_class":"P",
    "gn:feature_code":"PPL",
    "gn:name":"Ban Khok Ma Chae",
    "gn:population":0,
    "gn:timezone":"Asia/Bangkok",
    "iso:country":"TH",
    "name:tha_x_preferred":[
        "\u0e1a\u0e49\u0e32\u0e19\u0e42\u0e04\u0e01\u0e21\u0e32\u0e41\u0e08"
    ],
    "wof:name":"Ban Khok Ma Chae",
    "wof:placetype":"locality"
},
  "geometry": {"coordinates":[101.72008,6.42153],"type":"Point"}
}