{
  "type": "Feature",
  "properties": {
    "gn:admin1_code":"22",
    "gn:asciiname":"Ban Haeo Kham",
    "gn:country_code":"TH",
    "gn:dem":167,
    "gn:feature_class":"P",
    "gn:feature_code":"PPL",
    "gn:name":"Ban Haeo Kham",
    "gn:population":0,
    "gn:timezone":"Asia/Bangkok",
    "iso:country":"TH",
    "name:tha_x_preferred":[
        "\u0e1a\u0e49\u0e32\u0e19\u0e41\u0e2b\u0e49\u0e27\u0e04\u0e33"
    ],
    "wof:name":"Ban Haeo Kham",
    "wof:placetype":"locality"
},
  "geometry": {"coordinates":[103.02658,16.53728],"type":"Point"}
}