{
  "type": "Feature",
  "properties": {
    "gn:admin1_code":"25.0",
    "gn:asciiname":"Ban Chum Saeng Chai",
    "gn:country_code":"TH",
    "gn:dem":187,
    "gn:feature_class":"P",
    "gn:feature_code":"PPL",
    "gn:name":"Ban Chum Saeng Chai",
    "gn:population":0,
    "gn:timezone":"Asia/Bangkok",
    "iso:country":"TH",
    "name:tha_x_preferred":[
        "\u0e1a\u0e49\u0e32\u0e19\u0e0a\u0e38\u0e21\u0e41\u0e2a\u0e07\u0e0a\u0e31\u0e22"
    ],
    "wof:name":"Ban Chum Saeng Chai",
    "wof:placetype":"locality"
},
  "geometry": {"coordinates":[103.93444,16.36853],"type":"Point"}
}