{
  "type": "Feature",
  "properties": {
    "gn:admin1_code":"49.0",
    "gn:asciiname":"Ban Ta Pon",
    "gn:country_code":"TH",
    "gn:dem":7,
    "gn:feature_class":"P",
    "gn:feature_code":"PPL",
    "gn:name":"Ban Ta Pon",
    "gn:population":0,
    "gn:timezone":"Asia/Bangkok",
    "iso:country":"TH",
    "name:tha_x_preferred":[
        "\u0e1a\u0e49\u0e32\u0e19\u0e15\u0e32\u0e42\u0e1b\u0e19"
    ],
    "wof:name":"Ban Ta Pon",
    "wof:placetype":"locality"
},
  "geometry": {"coordinates":[102.50747,12.31008],"type":"Point"}
}