{
  "type": "Feature",
  "properties": {
    "gn:admin1_code":"12.0",
    "gn:asciiname":"Ban Sam Bon",
    "gn:country_code":"TH",
    "gn:dem":576,
    "gn:feature_class":"P",
    "gn:feature_code":"PPL",
    "gn:name":"Ban Sam Bon",
    "gn:population":0,
    "gn:timezone":"Asia/Bangkok",
    "iso:country":"TH",
    "name:tha_x_preferred":[
        "\u0e1a\u0e49\u0e32\u0e19\u0e0b\u0e33\u0e1a\u0e2d\u0e19"
    ],
    "wof:name":"Ban Sam Bon",
    "wof:placetype":"locality"
},
  "geometry": {"coordinates":[100.64703,17.03803],"type":"Point"}
}