{
  "type": "Feature",
  "properties": {
    "gn:admin1_code":"18.0",
    "gn:asciiname":"Ban Phet Charoen",
    "gn:country_code":"TH",
    "gn:dem":330,
    "gn:feature_class":"P",
    "gn:feature_code":"PPL",
    "gn:name":"Ban Phet Charoen",
    "gn:population":0,
    "gn:timezone":"Asia/Bangkok",
    "iso:country":"TH",
    "name:tha_x_preferred":[
        "Ban Phet Charoen"
    ],
    "name:tha_x_variant":[
        "\u0e1a\u0e49\u0e32\u0e19\u0e40\u0e1e\u0e0a\u0e23\u0e40\u0e08\u0e23\u0e34\u0e0d"
    ],
    "wof:name":"Ban Phet Charoen",
    "wof:placetype":"locality"
},
  "geometry": {"coordinates":[101.97217000000001,17.07539],"type":"Point"}
}