{
  "type": "Feature",
  "properties": {
    "gn:admin1_code":"40.0",
    "gn:admin2_code":"1026.0",
    "gn:asciiname":"Din Daeng",
    "gn:country_code":"TH",
    "gn:dem":5,
    "gn:feature_class":"P",
    "gn:feature_code":"PPLA2",
    "gn:name":"Din Daeng",
    "gn:population":0,
    "gn:timezone":"Asia/Bangkok",
    "iso:country":"TH",
    "name:tha_x_preferred":[
        "\u0e14\u0e34\u0e19\u0e41\u0e14\u0e07"
    ],
    "wof:name":"Din Daeng",
    "wof:placetype":"locality"
},
  "geometry": {"coordinates":[100.55298999999999,13.76994],"type":"Point"}
}