{
  "type": "Feature",
  "properties": {
    "gn:admin1_code":"73.0",
    "gn:asciiname":"Ban Klang Rung Rueang",
    "gn:country_code":"TH",
    "gn:dem":165,
    "gn:feature_class":"P",
    "gn:feature_code":"PPL",
    "gn:name":"Ban Klang Rung Rueang",
    "gn:population":0,
    "gn:timezone":"Asia/Bangkok",
    "iso:country":"TH",
    "name:tha_x_preferred":[
        "Ban Klang Rung Rueang"
    ],
    "name:tha_x_variant":[
        "\u0e1a\u0e49\u0e32\u0e19\u0e01\u0e25\u0e32\u0e07\u0e23\u0e38\u0e48\u0e07\u0e40\u0e23\u0e37\u0e2d\u0e07"
    ],
    "wof:name":"Ban Klang Rung Rueang",
    "wof:placetype":"locality"
},
  "geometry": {"coordinates":[104.08369999999999,17.39203],"type":"Point"}
}