{
  "type": "Feature",
  "properties": {
    "gn:admin1_code":"60.0",
    "gn:asciiname":"Ban Thong Mai",
    "gn:country_code":"TH",
    "gn:dem":18,
    "gn:feature_class":"P",
    "gn:feature_code":"PPL",
    "gn:name":"Ban Thong Mai",
    "gn:population":0,
    "gn:timezone":"Asia/Bangkok",
    "iso:country":"TH",
    "name:tha_x_preferred":[
        "\u0e1a\u0e49\u0e32\u0e19\u0e17\u0e49\u0e2d\u0e07\u0e44\u0e21"
    ],
    "wof:name":"Ban Thong Mai",
    "wof:placetype":"locality"
},
  "geometry": {"coordinates":[99.68661,9.33353],"type":"Point"}
}