{
  "type": "Feature",
  "properties": {
    "gn:admin1_code":"13.0",
    "gn:asciiname":"Ban Nong Ping Kluea",
    "gn:country_code":"TH",
    "gn:dem":51,
    "gn:feature_class":"P",
    "gn:feature_code":"PPL",
    "gn:name":"Ban Nong Ping Kluea",
    "gn:population":0,
    "gn:timezone":"Asia/Bangkok",
    "iso:country":"TH",
    "name:tha_x_preferred":[
        "\u0e1a\u0e49\u0e32\u0e19\u0e2b\u0e19\u0e2d\u0e07\u0e1b\u0e34\u0e49\u0e07\u0e40\u0e01\u0e25\u0e37\u0e2d"
    ],
    "wof:name":"Ban Nong Ping Kluea",
    "wof:placetype":"locality"
},
  "geometry": {"coordinates":[100.01658,16.28641],"type":"Point"}
}