{
  "type": "Feature",
  "properties": {
    "gn:admin1_code":"31.0",
    "gn:asciiname":"Ban Balu Ka Hu Lu",
    "gn:country_code":"TH",
    "gn:dem":24,
    "gn:feature_class":"P",
    "gn:feature_code":"PPL",
    "gn:name":"Ban Balu Ka Hu Lu",
    "gn:population":0,
    "gn:timezone":"Asia/Bangkok",
    "iso:country":"TH",
    "name:tha_x_preferred":[
        "\u0e1a\u0e49\u0e32\u0e19\u0e1a\u0e25\u0e39\u0e01\u0e32\u0e2e\u0e39\u0e25\u0e39"
    ],
    "wof:name":"Ban Balu Ka Hu Lu",
    "wof:placetype":"locality"
},
  "geometry": {"coordinates":[101.67506,6.45247],"type":"Point"}
}