{
  "type": "Feature",
  "properties": {
    "gn:admin1_code":"41.0",
    "gn:asciiname":"Ban Mae Ka Rai Diao",
    "gn:country_code":"TH",
    "gn:dem":497,
    "gn:feature_class":"P",
    "gn:feature_code":"PPL",
    "gn:name":"Ban Mae Ka Rai Diao",
    "gn:population":0,
    "gn:timezone":"Asia/Bangkok",
    "iso:country":"TH",
    "name:tha_x_preferred":[
        "\u0e1a\u0e49\u0e32\u0e19\u0e41\u0e21\u0e48\u0e01\u0e32\u0e44\u0e23\u0e48\u0e40\u0e14\u0e35\u0e48\u0e22\u0e27"
    ],
    "wof:name":"Ban Mae Ka Rai Diao",
    "wof:placetype":"locality"
},
  "geometry": {"coordinates":[99.89700000000001,19.00281],"type":"Point"}
}