{
  "type": "Feature",
  "properties": {
    "gn:admin1_code":"48.0",
    "gn:asciiname":"Ban Tha Luang Bon",
    "gn:country_code":"TH",
    "gn:dem":15,
    "gn:feature_class":"P",
    "gn:feature_code":"PPL",
    "gn:name":"Ban Tha Luang Bon",
    "gn:population":0,
    "gn:timezone":"Asia/Bangkok",
    "iso:country":"TH",
    "name:tha_x_preferred":[
        "\u0e1a\u0e49\u0e32\u0e19\u0e17\u0e48\u0e32\u0e2b\u0e25\u0e27\u0e07\u0e1a\u0e19"
    ],
    "wof:name":"Ban Tha Luang Bon",
    "wof:placetype":"locality"
},
  "geometry": {"coordinates":[102.15958000000001,12.69872],"type":"Point"}
}