{
  "type": "Feature",
  "properties": {
    "gn:admin1_code":"12.0",
    "gn:asciiname":"Ban Nong Chum Saeng",
    "gn:country_code":"TH",
    "gn:dem":196,
    "gn:feature_class":"P",
    "gn:feature_code":"PPL",
    "gn:name":"Ban Nong Chum Saeng",
    "gn:population":0,
    "gn:timezone":"Asia/Bangkok",
    "iso:country":"TH",
    "name:tha_x_preferred":[
        "\u0e1a\u0e49\u0e32\u0e19\u0e2b\u0e19\u0e2d\u0e07\u0e0a\u0e38\u0e21\u0e41\u0e2a\u0e07"
    ],
    "wof:name":"Ban Nong Chum Saeng",
    "wof:placetype":"locality"
},
  "geometry": {"coordinates":[100.52625,17.20253],"type":"Point"}
}