{
  "type": "Feature",
  "properties": {
    "gn:admin1_code":"9.0",
    "gn:asciiname":"Ban Sok Krabak",
    "gn:country_code":"TH",
    "gn:dem":62,
    "gn:feature_class":"P",
    "gn:feature_code":"PPL",
    "gn:name":"Ban Sok Krabak",
    "gn:population":0,
    "gn:timezone":"Asia/Bangkok",
    "iso:country":"TH",
    "name:tha_x_preferred":[
        "\u0e1a\u0e49\u0e32\u0e19\u0e42\u0e0b\u0e01\u0e01\u0e23\u0e30\u0e1a\u0e32\u0e01"
    ],
    "wof:name":"Ban Sok Krabak",
    "wof:placetype":"locality"
},
  "geometry": {"coordinates":[99.73406,16.84903],"type":"Point"}
}