{
  "type": "Feature",
  "properties": {
    "gn:admin1_code":"10.0",
    "gn:asciiname":"Ban Hin Kon Diao",
    "gn:country_code":"TH",
    "gn:dem":69,
    "gn:feature_class":"P",
    "gn:feature_code":"PPL",
    "gn:name":"Ban Hin Kon Diao",
    "gn:population":0,
    "gn:timezone":"Asia/Bangkok",
    "iso:country":"TH",
    "name:tha_x_preferred":[
        "Ban Hin Kon Diao"
    ],
    "name:tha_x_variant":[
        "\u0e1a\u0e49\u0e32\u0e19\u0e2b\u0e34\u0e19\u0e01\u0e49\u0e2d\u0e19\u0e40\u0e14\u0e35\u0e22\u0e27"
    ],
    "wof:name":"Ban Hin Kon Diao",
    "wof:placetype":"locality"
},
  "geometry": {"coordinates":[100.08222000000001,17.64193999999999],"type":"Point"}
}