{
  "type": "Feature",
  "properties": {
    "gn:admin1_code":"27",
    "gn:asciiname":"Ban Dan Mamuang",
    "gn:country_code":"TH",
    "gn:dem":268,
    "gn:feature_class":"P",
    "gn:feature_code":"PPL",
    "gn:name":"Ban Dan Mamuang",
    "gn:population":0,
    "gn:timezone":"Asia/Bangkok",
    "iso:country":"TH",
    "name:tha_x_preferred":[
        "\u0e1a\u0e49\u0e32\u0e19\u0e14\u0e48\u0e32\u0e19\u0e21\u0e30\u0e21\u0e48\u0e27\u0e07"
    ],
    "wof:name":"Ban Dan Mamuang",
    "wof:placetype":"locality"
},
  "geometry": {"coordinates":[102.28389,14.57675],"type":"Point"}
}