{
  "type": "Feature",
  "properties": {
    "gn:admin1_code":"69.0",
    "gn:asciiname":"Ban Bue Nae La Mo",
    "gn:country_code":"TH",
    "gn:dem":14,
    "gn:feature_class":"P",
    "gn:feature_code":"PPL",
    "gn:name":"Ban Bue Nae La Mo",
    "gn:population":0,
    "gn:timezone":"Asia/Bangkok",
    "iso:country":"TH",
    "name:tha_x_preferred":[
        "\u0e1a\u0e49\u0e32\u0e19\u0e1a\u0e37\u0e2d\u0e41\u0e19\u0e25\u0e32\u0e40\u0e21\u0e32\u0e30"
    ],
    "wof:name":"Ban Bue Nae La Mo",
    "wof:placetype":"locality"
},
  "geometry": {"coordinates":[101.57931000000001,6.631],"type":"Point"}
}