{
  "type": "Feature",
  "properties": {
    "gn:admin1_code":"51.0",
    "gn:asciiname":"Ban Lam Bua",
    "gn:country_code":"TH",
    "gn:dem":6,
    "gn:feature_class":"P",
    "gn:feature_code":"PPL",
    "gn:name":"Ban Lam Bua",
    "gn:population":0,
    "gn:timezone":"Asia/Bangkok",
    "iso:country":"TH",
    "name:tha_x_preferred":[
        "\u0e1a\u0e49\u0e32\u0e19\u0e25\u0e33\u0e1a\u0e31\u0e27"
    ],
    "wof:name":"Ban Lam Bua",
    "wof:placetype":"locality"
},
  "geometry": {"coordinates":[100.22869,14.42289],"type":"Point"}
}