{
  "type": "Feature",
  "properties": {
    "gn:admin1_code":"3.0",
    "gn:asciiname":"Ban San Ton Haen",
    "gn:country_code":"TH",
    "gn:dem":425,
    "gn:feature_class":"P",
    "gn:feature_code":"PPL",
    "gn:name":"Ban San Ton Haen",
    "gn:population":0,
    "gn:timezone":"Asia/Bangkok",
    "iso:country":"TH",
    "name:tha_x_preferred":[
        "\u0e1a\u0e49\u0e32\u0e19\u0e2a\u0e31\u0e19\u0e15\u0e49\u0e19\u0e41\u0e2b\u0e19"
    ],
    "wof:name":"Ban San Ton Haen",
    "wof:placetype":"locality"
},
  "geometry": {"coordinates":[99.73025,19.46386],"type":"Point"}
}