{
  "type": "Feature",
  "properties": {
    "gn:admin1_code":"65.0",
    "gn:asciiname":"Ban Na Mueang Phet",
    "gn:country_code":"TH",
    "gn:dem":16,
    "gn:feature_class":"P",
    "gn:feature_code":"PPL",
    "gn:name":"Ban Na Mueang Phet",
    "gn:population":0,
    "gn:timezone":"Asia/Bangkok",
    "iso:country":"TH",
    "name:tha_x_preferred":[
        "\u0e1a\u0e49\u0e32\u0e19\u0e19\u0e32\u0e40\u0e21\u0e37\u0e2d\u0e07\u0e40\u0e1e\u0e0a\u0e23"
    ],
    "name:und_x_variant":[
        "Ban Na Muang Phet"
    ],
    "wof:name":"Ban Na Mueang Phet",
    "wof:placetype":"locality"
},
  "geometry": {"coordinates":[99.50217000000001,7.54292],"type":"Point"}
}