{
  "type": "Feature",
  "properties": {
    "gn:admin1_code":"0.0",
    "gn:asciiname":"Ban Huai Khrai",
    "gn:country_code":"TH",
    "gn:dem":1057,
    "gn:feature_class":"P",
    "gn:feature_code":"PPL",
    "gn:name":"Ban Huai Khrai",
    "gn:population":0,
    "gn:timezone":"Asia/Bangkok",
    "iso:country":"TH",
    "wof:name":"Ban Huai Khrai",
    "wof:placetype":"locality"
},
  "geometry": {"coordinates":[101.43333,17.43333],"type":"Point"}
}