{
  "type": "Feature",
  "properties": {
    "gn:admin1_code":"6.0",
    "gn:asciiname":"Ban Phae",
    "gn:country_code":"TH",
    "gn:dem":428,
    "gn:feature_class":"P",
    "gn:feature_code":"PPL",
    "gn:name":"Ban Phae",
    "gn:population":0,
    "gn:timezone":"Asia/Bangkok",
    "iso:country":"TH",
    "name:tha_x_preferred":[
        "\u0e1a\u0e49\u0e32\u0e19\u0e41\u0e1e\u0e30"
    ],
    "name:und_x_variant":[
        "Bhe\u0101k\u0113bhak",
        "Phae Kae Phak",
        "Ban Phae Kae Phak",
        "Phae Kae Phek",
        "B\u0101n Phea Gea Phak",
        "Ban Phae"
    ],
    "wof:lang_x_official":[
        "tha"
    ],
    "wof:lang_x_spoken":[
        "tha"
    ],
    "wof:name":"Ban Phae",
    "wof:placetype":"locality"
},
  "geometry": {"coordinates":[99.61319,19.14383],"type":"Point"}
}