{
  "type": "Feature",
  "properties": {
    "gn:admin1_code":"53.0",
    "gn:asciiname":"Muban Suan Ariyawat",
    "gn:country_code":"TH",
    "gn:dem":8,
    "gn:feature_class":"P",
    "gn:feature_code":"PPL",
    "gn:name":"Muban Suan Ariyawat",
    "gn:population":0,
    "gn:timezone":"Asia/Bangkok",
    "iso:country":"TH",
    "name:tha_x_preferred":[
        "\u0e2b\u0e21\u0e39\u0e48\u0e1a\u0e49\u0e32\u0e19\u0e2a\u0e27\u0e19\u0e2d\u0e32\u0e23\u0e34\u0e22\u0e27\u0e31\u0e12\u0e19\u0e4c"
    ],
    "wof:name":"Muban Suan Ariyawat",
    "wof:placetype":"locality"
},
  "geometry": {"coordinates":[100.04631000000001,13.78506],"type":"Point"}
}