{
  "type": "Feature",
  "properties": {
    "gn:admin1_code":"12.0",
    "gn:asciiname":"Ban Yan Khat",
    "gn:country_code":"TH",
    "gn:dem":43,
    "gn:feature_class":"P",
    "gn:feature_code":"PPL",
    "gn:name":"Ban Yan Khat",
    "gn:population":0,
    "gn:timezone":"Asia/Bangkok",
    "iso:country":"TH",
    "name:tha_x_preferred":[
        "\u0e1a\u0e49\u0e32\u0e19\u0e22\u0e48\u0e32\u0e19\u0e02\u0e32\u0e14"
    ],
    "wof:name":"Ban Yan Khat",
    "wof:placetype":"locality"
},
  "geometry": {"coordinates":[100.17922,17.04128],"type":"Point"}
}