{
  "type": "Feature",
  "properties": {
    "gn:admin1_code":"64.0",
    "gn:asciiname":"Ban Fai Tha",
    "gn:country_code":"TH",
    "gn:dem":5,
    "gn:feature_class":"P",
    "gn:feature_code":"PPL",
    "gn:name":"Ban Fai Tha",
    "gn:population":0,
    "gn:timezone":"Asia/Bangkok",
    "iso:country":"TH",
    "name:tha_x_preferred":[
        "\u0e1a\u0e49\u0e32\u0e19\u0e1d\u0e32\u0e22\u0e17\u0e48\u0e32"
    ],
    "wof:name":"Ban Fai Tha",
    "wof:placetype":"locality"
},
  "geometry": {"coordinates":[99.91072,9.021],"type":"Point"}
}