{
  "type": "Feature",
  "properties": {
    "gn:admin1_code":"24",
    "gn:asciiname":"Ban Hua Na Thai",
    "gn:country_code":"TH",
    "gn:dem":179,
    "gn:feature_class":"P",
    "gn:feature_code":"PPL",
    "gn:name":"Ban Hua Na Thai",
    "gn:population":0,
    "gn:timezone":"Asia/Bangkok",
    "iso:country":"TH",
    "name:tha_x_preferred":[
        "\u0e1a\u0e49\u0e32\u0e19\u0e2b\u0e31\u0e27\u0e19\u0e32\u0e44\u0e17\u0e22"
    ],
    "wof:name":"Ban Hua Na Thai",
    "wof:placetype":"locality"
},
  "geometry": {"coordinates":[103.27444,15.94033],"type":"Point"}
}