{
  "type": "Feature",
  "properties": {
    "gn:admin1_code":"17.0",
    "gn:asciiname":"Ban Kut Khaen",
    "gn:country_code":"TH",
    "gn:dem":167,
    "gn:feature_class":"P",
    "gn:feature_code":"PPL",
    "gn:name":"Ban Kut Khaen",
    "gn:population":0,
    "gn:timezone":"Asia/Bangkok",
    "iso:country":"TH",
    "name:tha_x_preferred":[
        "\u0e1a\u0e49\u0e32\u0e19\u0e01\u0e38\u0e14\u0e41\u0e04\u0e19"
    ],
    "wof:name":"Ban Kut Khaen",
    "wof:placetype":"locality"
},
  "geometry": {"coordinates":[103.20283000000001,18.02742000000001],"type":"Point"}
}