{
  "type": "Feature",
  "properties": {
    "gn:admin1_code":"64.0",
    "gn:asciiname":"Ban Hu Dan",
    "gn:country_code":"TH",
    "gn:dem":32,
    "gn:feature_class":"P",
    "gn:feature_code":"PPL",
    "gn:name":"Ban Hu Dan",
    "gn:population":0,
    "gn:timezone":"Asia/Bangkok",
    "iso:country":"TH",
    "name:tha_x_preferred":[
        "\u0e1a\u0e49\u0e32\u0e19\u0e2b\u0e39\u0e14\u0e48\u0e32\u0e19"
    ],
    "wof:name":"Ban Hu Dan",
    "wof:placetype":"locality"
},
  "geometry": {"coordinates":[99.86878,8.18089],"type":"Point"}
}