{
  "type": "Feature",
  "properties": {
    "gn:admin1_code":"24",
    "gn:asciiname":"Ban Mueang Udom",
    "gn:country_code":"TH",
    "gn:dem":137,
    "gn:feature_class":"P",
    "gn:feature_code":"PPL",
    "gn:name":"Ban Mueang Udom",
    "gn:population":0,
    "gn:timezone":"Asia/Bangkok",
    "iso:country":"TH",
    "name:tha_x_preferred":[
        "\u0e1a\u0e49\u0e32\u0e19\u0e40\u0e21\u0e37\u0e2d\u0e07\u0e2d\u0e38\u0e14\u0e21"
    ],
    "wof:name":"Ban Mueang Udom",
    "wof:placetype":"locality"
},
  "geometry": {"coordinates":[103.22633,15.45556],"type":"Point"}
}