{
  "type": "Feature",
  "properties": {
    "gn:admin1_code":"26.0",
    "gn:asciiname":"Ban Sima Thong",
    "gn:country_code":"TH",
    "gn:dem":194,
    "gn:feature_class":"P",
    "gn:feature_code":"PPL",
    "gn:name":"Ban Sima Thong",
    "gn:population":0,
    "gn:timezone":"Asia/Bangkok",
    "iso:country":"TH",
    "name:tha_x_preferred":[
        "\u0e1a\u0e49\u0e32\u0e19\u0e28\u0e23\u0e35\u0e21\u0e32\u0e17\u0e2d\u0e07"
    ],
    "wof:name":"Ban Sima Thong",
    "wof:placetype":"locality"
},
  "geometry": {"coordinates":[102.37917,16.41725],"type":"Point"}
}