{
  "type": "Feature",
  "properties": {
    "gn:admin1_code":"2.0",
    "gn:asciiname":"Ban Mae Sun",
    "gn:country_code":"TH",
    "gn:dem":754,
    "gn:feature_class":"P",
    "gn:feature_code":"PPL",
    "gn:name":"Ban Mae Sun",
    "gn:population":0,
    "gn:timezone":"Asia/Bangkok",
    "iso:country":"TH",
    "name:tha_x_preferred":[
        "\u0e1a\u0e49\u0e32\u0e19\u0e41\u0e21\u0e48\u0e2a\u0e39\u0e19"
    ],
    "wof:name":"Ban Mae Sun",
    "wof:placetype":"locality"
},
  "geometry": {"coordinates":[99.26875,19.15528],"type":"Point"}
}