{
  "type": "Feature",
  "properties": {
    "gn:admin1_code":"50.0",
    "gn:asciiname":"Ban Na Kan",
    "gn:country_code":"TH",
    "gn:dem":39,
    "gn:feature_class":"P",
    "gn:feature_code":"PPL",
    "gn:name":"Ban Na Kan",
    "gn:population":0,
    "gn:timezone":"Asia/Bangkok",
    "iso:country":"TH",
    "name:tha_x_preferred":[
        "\u0e1a\u0e49\u0e32\u0e19\u0e19\u0e32\u0e01\u0e32\u0e0d\u0e08\u0e19\u0e4c"
    ],
    "wof:name":"Ban Na Kan",
    "wof:placetype":"locality"
},
  "geometry": {"coordinates":[99.44714,13.93244],"type":"Point"}
}