{
  "type": "Feature",
  "properties": {
    "gn:admin1_code":"30.0",
    "gn:asciiname":"Ban Hua Suea",
    "gn:country_code":"TH",
    "gn:dem":145,
    "gn:feature_class":"P",
    "gn:feature_code":"PPL",
    "gn:name":"Ban Hua Suea",
    "gn:population":0,
    "gn:timezone":"Asia/Bangkok",
    "iso:country":"TH",
    "name:tha_x_preferred":[
        "\u0e1a\u0e49\u0e32\u0e19\u0e2b\u0e31\u0e27\u0e40\u0e2a\u0e37\u0e2d"
    ],
    "name:und_x_variant":[
        "Ban Hua Sua"
    ],
    "wof:name":"Ban Hua Suea",
    "wof:placetype":"locality"
},
  "geometry": {"coordinates":[104.18589,14.81931],"type":"Point"}
}