{
  "type": "Feature",
  "properties": {
    "gn:admin1_code":"3.0",
    "gn:asciiname":"Ban Mueang Daeng Tai",
    "gn:country_code":"TH",
    "gn:dem":393,
    "gn:feature_class":"P",
    "gn:feature_code":"PPL",
    "gn:name":"Ban Mueang Daeng Tai",
    "gn:population":0,
    "gn:timezone":"Asia/Bangkok",
    "iso:country":"TH",
    "name:tha_x_preferred":[
        "\u0e1a\u0e49\u0e32\u0e19\u0e40\u0e2b\u0e21\u0e37\u0e2d\u0e07\u0e41\u0e14\u0e07\u0e43\u0e15\u0e49"
    ],
    "wof:name":"Ban Mueang Daeng Tai",
    "wof:placetype":"locality"
},
  "geometry": {"coordinates":[99.89633000000001,20.44156],"type":"Point"}
}