{
  "type": "Feature",
  "properties": {
    "gn:admin1_code":"10.0",
    "gn:asciiname":"Ban Yan Du",
    "gn:country_code":"TH",
    "gn:dem":92,
    "gn:feature_class":"P",
    "gn:feature_code":"PPL",
    "gn:name":"Ban Yan Du",
    "gn:population":0,
    "gn:timezone":"Asia/Bangkok",
    "iso:country":"TH",
    "name:tha_x_preferred":[
        "\u0e1a\u0e49\u0e32\u0e19\u0e22\u0e48\u0e32\u0e19\u0e14\u0e39\u0e48"
    ],
    "name:und_x_variant":[
        "Ban Yan",
        "Ban Yan Du"
    ],
    "wof:name":"Ban Yan Du",
    "wof:placetype":"locality"
},
  "geometry": {"coordinates":[100.52178000000001,17.73325],"type":"Point"}
}