{
  "type": "Feature",
  "properties": {
    "gn:admin1_code":"11.0",
    "gn:asciiname":"Ban Lan Thong",
    "gn:country_code":"TH",
    "gn:dem":117,
    "gn:feature_class":"P",
    "gn:feature_code":"PPL",
    "gn:name":"Ban Lan Thong",
    "gn:population":0,
    "gn:timezone":"Asia/Bangkok",
    "iso:country":"TH",
    "name:tha_x_preferred":[
        "Ban Lan Thong"
    ],
    "name:tha_x_variant":[
        "\u0e1a\u0e49\u0e32\u0e19\u0e25\u0e32\u0e19\u0e17\u0e2d\u0e07"
    ],
    "wof:name":"Ban Lan Thong",
    "wof:placetype":"locality"
},
  "geometry": {"coordinates":[99.38011,16.8075],"type":"Point"}
}