{
  "type": "Feature",
  "properties": {
    "gn:admin1_code":"74",
    "gn:asciiname":"Ban Doi Lamphu",
    "gn:country_code":"TH",
    "gn:dem":41,
    "gn:feature_class":"P",
    "gn:feature_code":"PPL",
    "gn:name":"Ban Doi Lamphu",
    "gn:population":0,
    "gn:timezone":"Asia/Bangkok",
    "iso:country":"TH",
    "name:tha_x_preferred":[
        "\u0e1a\u0e49\u0e32\u0e19\u0e14\u0e2d\u0e22\u0e25\u0e33\u0e20\u0e39"
    ],
    "wof:name":"Ban Doi Lamphu",
    "wof:placetype":"locality"
},
  "geometry": {"coordinates":[101.81544,13.81],"type":"Point"}
}