{
  "type": "Feature",
  "properties": {
    "gn:admin1_code":"2.0",
    "gn:asciiname":"Ban Yang Khun Usu",
    "gn:country_code":"TH",
    "gn:dem":626,
    "gn:feature_class":"P",
    "gn:feature_code":"PPL",
    "gn:name":"Ban Yang Khun Usu",
    "gn:population":0,
    "gn:timezone":"Asia/Bangkok",
    "iso:country":"TH",
    "name:und_x_variant":[
        "Ban Yang Usu"
    ],
    "wof:name":"Ban Yang Khun Usu",
    "wof:placetype":"locality"
},
  "geometry": {"coordinates":[98.26434,17.37575],"type":"Point"}
}