{
  "type": "Feature",
  "properties": {
    "gn:admin1_code":"8.0",
    "gn:asciiname":"Ban Loe Mae Bo Tha",
    "gn:country_code":"TH",
    "gn:dem":220,
    "gn:feature_class":"P",
    "gn:feature_code":"PPL",
    "gn:name":"Ban Loe Mae Bo Tha",
    "gn:population":0,
    "gn:timezone":"Asia/Bangkok",
    "iso:country":"TH",
    "name:tha_x_preferred":[
        "\u0e1a\u0e49\u0e32\u0e19\u0e40\u0e25\u0e49\u0e2d\u0e41\u0e2b\u0e21\u0e30\u0e1a\u0e2d\u0e17\u0e30"
    ],
    "wof:name":"Ban Loe Mae Bo Tha",
    "wof:placetype":"locality"
},
  "geometry": {"coordinates":[98.17411,17.40914],"type":"Point"}
}