{
  "type": "Feature",
  "properties": {
    "gn:admin1_code":"1.0",
    "gn:asciiname":"Ban Mae La Noi",
    "gn:country_code":"TH",
    "gn:dem":340,
    "gn:feature_class":"P",
    "gn:feature_code":"PPL",
    "gn:name":"Ban Mae La Noi",
    "gn:population":0,
    "gn:timezone":"Asia/Bangkok",
    "iso:country":"TH",
    "name:tha_x_preferred":[
        "\u0e1a\u0e49\u0e32\u0e19\u0e41\u0e21\u0e48\u0e25\u0e32\u0e19\u0e49\u0e2d\u0e22"
    ],
    "wof:name":"Ban Mae La Noi",
    "wof:placetype":"locality"
},
  "geometry": {"coordinates":[97.94071,18.38149],"type":"Point"}
}