{
  "type": "Feature",
  "properties": {
    "gn:admin1_code":"66.0",
    "gn:asciiname":"Ban Nok Thung",
    "gn:country_code":"TH",
    "gn:dem":5,
    "gn:feature_class":"P",
    "gn:feature_code":"PPL",
    "gn:name":"Ban Nok Thung",
    "gn:population":0,
    "gn:timezone":"Asia/Bangkok",
    "iso:country":"TH",
    "name:tha_x_preferred":[
        "\u0e1a\u0e49\u0e32\u0e19\u0e19\u0e2d\u0e01\u0e17\u0e38\u0e48\u0e07"
    ],
    "wof:name":"Ban Nok Thung",
    "wof:placetype":"locality"
},
  "geometry": {"coordinates":[100.15582999999999,7.60228],"type":"Point"}
}