{
  "type": "Feature",
  "properties": {
    "gn:admin1_code":"24",
    "gn:asciiname":"Ban Khi Tun",
    "gn:country_code":"TH",
    "gn:dem":177,
    "gn:feature_class":"P",
    "gn:feature_code":"PPL",
    "gn:name":"Ban Khi Tun",
    "gn:population":0,
    "gn:timezone":"Asia/Bangkok",
    "iso:country":"TH",
    "name:tha_x_preferred":[
        "\u0e1a\u0e49\u0e32\u0e19\u0e02\u0e35\u0e49\u0e15\u0e38\u0e48\u0e19"
    ],
    "wof:name":"Ban Khi Tun",
    "wof:placetype":"locality"
},
  "geometry": {"coordinates":[103.00181000000001,15.83678],"type":"Point"}
}