{
  "type": "Feature",
  "properties": {
    "gn:admin1_code":"70.0",
    "gn:asciiname":"Ban Cham Pun",
    "gn:country_code":"TH",
    "gn:dem":19,
    "gn:feature_class":"P",
    "gn:feature_code":"PPL",
    "gn:name":"Ban Cham Pun",
    "gn:population":0,
    "gn:timezone":"Asia/Bangkok",
    "iso:country":"TH",
    "name:tha_x_preferred":[
        "\u0e1a\u0e49\u0e32\u0e19\u0e08\u0e33\u0e1b\u0e39\u0e19"
    ],
    "wof:name":"Ban Cham Pun",
    "wof:placetype":"locality"
},
  "geometry": {"coordinates":[101.42794000000001,6.5405],"type":"Point"}
}