{
  "type": "Feature",
  "properties": {
    "gn:admin1_code":"46.0",
    "gn:asciiname":"Ban Ko Mo Ha",
    "gn:country_code":"TH",
    "gn:dem":25,
    "gn:feature_class":"P",
    "gn:feature_code":"PPL",
    "gn:name":"Ban Ko Mo Ha",
    "gn:population":0,
    "gn:timezone":"Asia/Bangkok",
    "iso:country":"TH",
    "name:tha_x_preferred":[
        "\u0e1a\u0e49\u0e32\u0e19 \u0e01\u0e21.\u0e2b\u0e49\u0e32"
    ],
    "wof:lang_x_official":[
        "tha"
    ],
    "wof:lang_x_spoken":[
        "tha"
    ],
    "wof:name":"Ban Ko Mo Ha",
    "wof:placetype":"locality"
},
  "geometry": {"coordinates":[100.93931000000001,12.67267],"type":"Point"}
}