{
  "type": "Feature",
  "properties": {
    "gn:admin1_code":"14.0",
    "gn:asciiname":"Ban Wang Mai Chueak",
    "gn:country_code":"TH",
    "gn:dem":65,
    "gn:feature_class":"P",
    "gn:feature_code":"PPL",
    "gn:name":"Ban Wang Mai Chueak",
    "gn:population":0,
    "gn:timezone":"Asia/Bangkok",
    "iso:country":"TH",
    "name:tha_x_preferred":[
        "\u0e1a\u0e49\u0e32\u0e19\u0e27\u0e31\u0e07\u0e44\u0e21\u0e49\u0e40\u0e0a\u0e37\u0e2d\u0e01"
    ],
    "wof:name":"Ban Wang Mai Chueak",
    "wof:placetype":"locality"
},
  "geometry": {"coordinates":[100.69110999999999,16.06172],"type":"Point"}
}