{
  "type": "Feature",
  "properties": {
    "gn:admin1_code":"29",
    "gn:asciiname":"Ban Dueai Kai Kaeo",
    "gn:country_code":"TH",
    "gn:dem":159,
    "gn:feature_class":"P",
    "gn:feature_code":"PPL",
    "gn:name":"Ban Dueai Kai Kaeo",
    "gn:population":0,
    "gn:timezone":"Asia/Bangkok",
    "iso:country":"TH",
    "name:tha_x_preferred":[
        "\u0e1a\u0e49\u0e32\u0e19\u0e40\u0e14\u0e37\u0e2d\u0e22\u0e44\u0e01\u0e48\u0e41\u0e01\u0e49\u0e27"
    ],
    "wof:name":"Ban Dueai Kai Kaeo",
    "wof:placetype":"locality"
},
  "geometry": {"coordinates":[103.77889,14.65028],"type":"Point"}
}