{
  "type": "Feature",
  "properties": {
    "gn:admin1_code":"52.0",
    "gn:asciiname":"Ban Phra Yueang",
    "gn:country_code":"TH",
    "gn:dem":36,
    "gn:feature_class":"P",
    "gn:feature_code":"PPL",
    "gn:name":"Ban Phra Yueang",
    "gn:population":0,
    "gn:timezone":"Asia/Bangkok",
    "iso:country":"TH",
    "name:tha_x_preferred":[
        "\u0e1a\u0e49\u0e32\u0e19\u0e1e\u0e23\u0e30\u0e40\u0e22\u0e37\u0e49\u0e2d\u0e07"
    ],
    "wof:name":"Ban Phra Yueang",
    "wof:placetype":"locality"
},
  "geometry": {"coordinates":[99.73564,13.46047],"type":"Point"}
}