{
  "type": "Feature",
  "properties": {
    "gn:admin1_code":"1.0",
    "gn:asciiname":"Ban Mae Um Phai Nuea",
    "gn:country_code":"TH",
    "gn:dem":799,
    "gn:feature_class":"P",
    "gn:feature_code":"PPL",
    "gn:name":"Ban Mae Um Phai Nuea",
    "gn:population":0,
    "gn:timezone":"Asia/Bangkok",
    "iso:country":"TH",
    "name:tha_x_preferred":[
        "\u0e1a\u0e49\u0e32\u0e19\u0e41\u0e21\u0e48\u0e2d\u0e39\u0e21\u0e1e\u0e32\u0e22\u0e40\u0e2b\u0e19\u0e37\u0e2d"
    ],
    "name:und_x_variant":[
        "Ban Yang Mae Om Phai",
        "Ban Mae Um Phai Nuea"
    ],
    "wof:name":"Ban Mae Um Phai Nuea",
    "wof:placetype":"locality"
},
  "geometry": {"coordinates":[98.02583,18.60075],"type":"Point"}
}