{
  "type": "Feature",
  "properties": {
    "gn:admin1_code":"28",
    "gn:asciiname":"Ban Nong Ta Pheng",
    "gn:country_code":"TH",
    "gn:dem":137,
    "gn:feature_class":"P",
    "gn:feature_code":"PPL",
    "gn:name":"Ban Nong Ta Pheng",
    "gn:population":0,
    "gn:timezone":"Asia/Bangkok",
    "iso:country":"TH",
    "name:tha_x_preferred":[
        "\u0e1a\u0e49\u0e32\u0e19\u0e2b\u0e19\u0e2d\u0e07\u0e15\u0e32\u0e40\u0e1e\u0e47\u0e07"
    ],
    "wof:name":"Ban Nong Ta Pheng",
    "wof:placetype":"locality"
},
  "geometry": {"coordinates":[103.36933000000001,15.28042],"type":"Point"}
}