{
  "type": "Feature",
  "properties": {
    "gn:admin1_code":"2.0",
    "gn:asciiname":"Ban Khong Khao",
    "gn:country_code":"TH",
    "gn:dem":317,
    "gn:feature_class":"P",
    "gn:feature_code":"PPL",
    "gn:name":"Ban Khong Khao",
    "gn:population":0,
    "gn:timezone":"Asia/Bangkok",
    "iso:country":"TH",
    "name:tha_x_preferred":[
        "\u0e1a\u0e49\u0e32\u0e19\u0e42\u0e02\u0e07\u0e02\u0e48\u0e32\u0e27"
    ],
    "wof:name":"Ban Khong Khao",
    "wof:placetype":"locality"
},
  "geometry": {"coordinates":[98.92413999999999,18.706],"type":"Point"}
}