{
  "type": "Feature",
  "properties": {
    "gn:admin1_code":"66.0",
    "gn:asciiname":"Ban Khuan In Nimit",
    "gn:country_code":"TH",
    "gn:dem":17,
    "gn:feature_class":"P",
    "gn:feature_code":"PPL",
    "gn:name":"Ban Khuan In Nimit",
    "gn:population":0,
    "gn:timezone":"Asia/Bangkok",
    "iso:country":"TH",
    "name:tha_x_preferred":[
        "\u0e1a\u0e49\u0e32\u0e19\u0e04\u0e27\u0e19\u0e2d\u0e34\u0e19\u0e17\u0e23\u0e4c\u0e19\u0e34\u0e21\u0e34\u0e15\u0e23"
    ],
    "wof:name":"Ban Khuan In Nimit",
    "wof:placetype":"locality"
},
  "geometry": {"coordinates":[100.05883,7.59531],"type":"Point"}
}