{
  "type": "Feature",
  "properties": {
    "gn:admin1_code":"14.0",
    "gn:asciiname":"Ban Wang Satue",
    "gn:country_code":"TH",
    "gn:dem":94,
    "gn:feature_class":"P",
    "gn:feature_code":"PPL",
    "gn:name":"Ban Wang Satue",
    "gn:population":0,
    "gn:timezone":"Asia/Bangkok",
    "iso:country":"TH",
    "name:tha_x_preferred":[
        "\u0e1a\u0e49\u0e32\u0e19\u0e27\u0e31\u0e07\u0e2a\u0e30\u0e15\u0e37\u0e2d"
    ],
    "wof:name":"Ban Wang Satue",
    "wof:placetype":"locality"
},
  "geometry": {"coordinates":[101.11185999999999,16.08372],"type":"Point"}
}