{
  "type": "Feature",
  "properties": {
    "gn:admin1_code":"16.0",
    "gn:asciiname":"Ban Taluk Khoi Nam",
    "gn:country_code":"TH",
    "gn:dem":102,
    "gn:feature_class":"P",
    "gn:feature_code":"PPL",
    "gn:name":"Ban Taluk Khoi Nam",
    "gn:population":0,
    "gn:timezone":"Asia/Bangkok",
    "iso:country":"TH",
    "name:tha_x_preferred":[
        "\u0e1a\u0e49\u0e32\u0e19\u0e15\u0e25\u0e38\u0e01\u0e02\u0e48\u0e2d\u0e22\u0e19\u0e49\u0e33"
    ],
    "wof:lang_x_official":[
        "tha"
    ],
    "wof:lang_x_spoken":[
        "tha"
    ],
    "wof:name":"Ban Taluk Khoi Nam",
    "wof:placetype":"locality"
},
  "geometry": {"coordinates":[99.55678,15.89861],"type":"Point"}
}