{
  "type": "Feature",
  "properties": {
    "gn:admin1_code":"76.0",
    "gn:asciiname":"Ban Lao Kok Kheng",
    "gn:country_code":"TH",
    "gn:dem":200,
    "gn:feature_class":"P",
    "gn:feature_code":"PPL",
    "gn:name":"Ban Lao Kok Kheng",
    "gn:population":0,
    "gn:timezone":"Asia/Bangkok",
    "iso:country":"TH",
    "name:tha_x_preferred":[
        "\u0e1a\u0e49\u0e32\u0e19\u0e40\u0e2b\u0e25\u0e48\u0e32\u0e01\u0e01\u0e40\u0e04\u0e47\u0e07"
    ],
    "wof:name":"Ban Lao Kok Kheng",
    "wof:placetype":"locality"
},
  "geometry": {"coordinates":[103.08717,17.16142],"type":"Point"}
}