{
  "type": "Feature",
  "properties": {
    "gn:admin1_code":"10.0",
    "gn:asciiname":"Ban Wang Pha Chan",
    "gn:country_code":"TH",
    "gn:dem":145,
    "gn:feature_class":"P",
    "gn:feature_code":"PPL",
    "gn:name":"Ban Wang Pha Chan",
    "gn:population":0,
    "gn:timezone":"Asia/Bangkok",
    "iso:country":"TH",
    "name:tha_x_preferred":[
        "Ban Wang Pha Chan"
    ],
    "name:tha_x_variant":[
        "\u0e1a\u0e49\u0e32\u0e19\u0e27\u0e31\u0e07\u0e1c\u0e32\u0e0a\u0e31\u0e19"
    ],
    "name:und_x_variant":[
        "Ban Wang Pha Khan"
    ],
    "wof:name":"Ban Wang Pha Chan",
    "wof:placetype":"locality"
},
  "geometry": {"coordinates":[100.50878,17.59395],"type":"Point"}
}