{
  "type": "Feature",
  "properties": {
    "gn:admin1_code":"43.0",
    "gn:asciiname":"Ban Nong Hu Ling Nai",
    "gn:country_code":"TH",
    "gn:dem":16,
    "gn:feature_class":"P",
    "gn:feature_code":"PPL",
    "gn:name":"Ban Nong Hu Ling Nai",
    "gn:population":0,
    "gn:timezone":"Asia/Bangkok",
    "iso:country":"TH",
    "name:tha_x_preferred":[
        "\u0e1a\u0e49\u0e32\u0e19\u0e2b\u0e19\u0e2d\u0e07\u0e2b\u0e39\u0e25\u0e34\u0e07\u0e43\u0e19"
    ],
    "name:und_x_variant":[
        "Ban Hnong Huling",
        "Ban Nong Hu Ling (1)",
        "Ban Nong Hu Ling Nai"
    ],
    "wof:lang_x_official":[
        "tha"
    ],
    "wof:lang_x_spoken":[
        "tha"
    ],
    "wof:name":"Ban Nong Hu Ling Nai",
    "wof:placetype":"locality"
},
  "geometry": {"coordinates":[101.30561,14.19817],"type":"Point"}
}