{
  "type": "Feature",
  "properties": {
    "gn:admin1_code":"76.0",
    "gn:asciiname":"Ban Huai Khum Pun",
    "gn:country_code":"TH",
    "gn:dem":210,
    "gn:feature_class":"P",
    "gn:feature_code":"PPL",
    "gn:name":"Ban Huai Khum Pun",
    "gn:population":0,
    "gn:timezone":"Asia/Bangkok",
    "iso:country":"TH",
    "name:tha_x_preferred":[
        "\u0e1a\u0e49\u0e32\u0e19\u0e2b\u0e49\u0e27\u0e22\u0e02\u0e38\u0e21\u0e1b\u0e39\u0e19"
    ],
    "wof:name":"Ban Huai Khum Pun",
    "wof:placetype":"locality"
},
  "geometry": {"coordinates":[102.85957999999999,17.03731],"type":"Point"}
}