{
  "type": "Feature",
  "properties": {
    "gn:admin1_code":"60.0",
    "gn:asciiname":"Ban Khok Mamuang",
    "gn:country_code":"TH",
    "gn:dem":37,
    "gn:feature_class":"P",
    "gn:feature_code":"PPL",
    "gn:name":"Ban Khok Mamuang",
    "gn:population":0,
    "gn:timezone":"Asia/Bangkok",
    "iso:country":"TH",
    "name:tha_x_preferred":[
        "\u0e1a\u0e49\u0e32\u0e19\u0e42\u0e04\u0e01\u0e21\u0e30\u0e21\u0e48\u0e27\u0e07"
    ],
    "wof:name":"Ban Khok Mamuang",
    "wof:placetype":"locality"
},
  "geometry": {"coordinates":[99.26353,8.55081],"type":"Point"}
}