{
  "type": "Feature",
  "properties": {
    "gn:admin1_code":"47.0",
    "gn:asciiname":"Ban Noen Phutsa",
    "gn:country_code":"TH",
    "gn:dem":7,
    "gn:feature_class":"P",
    "gn:feature_code":"PPL",
    "gn:name":"Ban Noen Phutsa",
    "gn:population":0,
    "gn:timezone":"Asia/Bangkok",
    "iso:country":"TH",
    "name:tha_x_preferred":[
        "\u0e1a\u0e49\u0e32\u0e19\u0e40\u0e19\u0e34\u0e19\u0e1e\u0e38\u0e17\u0e2a\u0e32"
    ],
    "wof:name":"Ban Noen Phutsa",
    "wof:placetype":"locality"
},
  "geometry": {"coordinates":[101.29083,12.66694],"type":"Point"}
}