{
  "type": "Feature",
  "properties": {
    "gn:admin1_code":"68.0",
    "gn:asciiname":"Ban Lo Yao",
    "gn:country_code":"TH",
    "gn:dem":23,
    "gn:feature_class":"P",
    "gn:feature_code":"PPL",
    "gn:name":"Ban Lo Yao",
    "gn:population":0,
    "gn:timezone":"Asia/Bangkok",
    "iso:country":"TH",
    "name:tha_x_preferred":[
        "\u0e1a\u0e49\u0e32\u0e19\u0e42\u0e2b\u0e25\u0e4a\u0e30\u0e22\u0e32\u0e27"
    ],
    "name:und_x_variant":[
        "Ban Lo Yao (1)"
    ],
    "wof:name":"Ban Lo Yao",
    "wof:placetype":"locality"
},
  "geometry": {"coordinates":[100.30197,7.18683],"type":"Point"}
}