{
  "type": "Feature",
  "properties": {
    "gn:admin1_code":"14.0",
    "gn:asciiname":"Ban Nam Ron",
    "gn:country_code":"TH",
    "gn:dem":122,
    "gn:feature_class":"P",
    "gn:feature_code":"PPL",
    "gn:name":"Ban Nam Ron",
    "gn:population":0,
    "gn:timezone":"Asia/Bangkok",
    "iso:country":"TH",
    "name:tha_x_preferred":[
        "\u0e1a\u0e49\u0e32\u0e19\u0e19\u0e49\u0e33\u0e23\u0e49\u0e2d\u0e19"
    ],
    "name:und_x_variant":[
        "B\u0101n Nam Raun",
        "B\u0101n Nam R\u014dhn",
        "Ban Nam Ron"
    ],
    "wof:name":"Ban Nam Ron",
    "wof:placetype":"locality"
},
  "geometry": {"coordinates":[101.27194,15.69314],"type":"Point"}
}