{
  "type": "Feature",
  "properties": {
    "gn:admin1_code":"2.0",
    "gn:asciiname":"Ban Huai Din Dam",
    "gn:country_code":"TH",
    "gn:dem":753,
    "gn:feature_class":"P",
    "gn:feature_code":"PPL",
    "gn:name":"Ban Huai Din Dam",
    "gn:population":0,
    "gn:timezone":"Asia/Bangkok",
    "iso:country":"TH",
    "name:tha_x_preferred":[
        "\u0e1a\u0e49\u0e32\u0e19\u0e2b\u0e49\u0e27\u0e22\u0e14\u0e34\u0e19\u0e14\u0e33"
    ],
    "wof:name":"Ban Huai Din Dam",
    "wof:placetype":"locality"
},
  "geometry": {"coordinates":[98.68789,19.38411],"type":"Point"}
}