{
  "type": "Feature",
  "properties": {
    "gn:admin1_code":"6.0",
    "gn:asciiname":"Ban Huai Hok",
    "gn:country_code":"TH",
    "gn:dem":681,
    "gn:feature_class":"P",
    "gn:feature_code":"PPL",
    "gn:name":"Ban Huai Hok",
    "gn:population":0,
    "gn:timezone":"Asia/Bangkok",
    "iso:country":"TH",
    "name:tha_x_preferred":[
        "\u0e1a\u0e49\u0e32\u0e19\u0e2b\u0e49\u0e27\u0e22\u0e2b\u0e01"
    ],
    "wof:name":"Ban Huai Hok",
    "wof:placetype":"locality"
},
  "geometry": {"coordinates":[99.80446999999999,18.74767],"type":"Point"}
}