{
  "type": "Feature",
  "properties": {
    "gn:admin1_code":"53.0",
    "gn:asciiname":"Ban Muang Sam Sip",
    "gn:country_code":"TH",
    "gn:dem":10,
    "gn:feature_class":"P",
    "gn:feature_code":"PPL",
    "gn:name":"Ban Muang Sam Sip",
    "gn:population":0,
    "gn:timezone":"Asia/Bangkok",
    "iso:country":"TH",
    "name:tha_x_preferred":[
        "\u0e1a\u0e49\u0e32\u0e19\u0e21\u0e48\u0e27\u0e07\u0e2a\u0e32\u0e21\u0e2a\u0e34\u0e1a"
    ],
    "name:und_x_variant":[
        "Ban Mamuang Sam Sip",
        "Ban Muang Sam Sip"
    ],
    "wof:name":"Ban Muang Sam Sip",
    "wof:placetype":"locality"
},
  "geometry": {"coordinates":[99.97572,13.94264],"type":"Point"}
}