{
  "type": "Feature",
  "properties": {
    "gn:admin1_code":"68.0",
    "gn:asciiname":"Ban Bang Klam Bon",
    "gn:country_code":"TH",
    "gn:dem":10,
    "gn:feature_class":"P",
    "gn:feature_code":"PPL",
    "gn:name":"Ban Bang Klam Bon",
    "gn:population":0,
    "gn:timezone":"Asia/Bangkok",
    "iso:country":"TH",
    "name:tha_x_preferred":[
        "\u0e1a\u0e49\u0e32\u0e19\u0e1a\u0e32\u0e07\u0e01\u0e25\u0e48\u0e33\u0e1a\u0e19"
    ],
    "wof:name":"Ban Bang Klam Bon",
    "wof:placetype":"locality"
},
  "geometry": {"coordinates":[100.42428,7.08511],"type":"Point"}
}