{
  "type": "Feature",
  "properties": {
    "gn:admin1_code":"48.0",
    "gn:asciiname":"Ban Bo Cha-om Nai",
    "gn:country_code":"TH",
    "gn:dem":107,
    "gn:feature_class":"P",
    "gn:feature_code":"PPL",
    "gn:name":"Ban Bo Cha-om Nai",
    "gn:population":0,
    "gn:timezone":"Asia/Bangkok",
    "iso:country":"TH",
    "name:tha_x_preferred":[
        "\u0e1a\u0e49\u0e32\u0e19\u0e1a\u0e48\u0e2d\u0e0a\u0e30\u0e2d\u0e21\u0e43\u0e19"
    ],
    "wof:lang_x_official":[
        "tha"
    ],
    "wof:lang_x_spoken":[
        "tha"
    ],
    "wof:name":"Ban Bo Cha-om Nai",
    "wof:placetype":"locality"
},
  "geometry": {"coordinates":[101.77628,13.058],"type":"Point"}
}