{
  "type": "Feature",
  "properties": {
    "gn:admin1_code":"37",
    "gn:asciiname":"Ban Rong Lao",
    "gn:country_code":"TH",
    "gn:dem":17,
    "gn:feature_class":"P",
    "gn:feature_code":"PPL",
    "gn:name":"Ban Rong Lao",
    "gn:population":0,
    "gn:timezone":"Asia/Bangkok",
    "iso:country":"TH",
    "name:tha_x_preferred":[
        "\u0e1a\u0e49\u0e32\u0e19\u0e42\u0e23\u0e07\u0e40\u0e2b\u0e25\u0e49\u0e32"
    ],
    "wof:name":"Ban Rong Lao",
    "wof:placetype":"locality"
},
  "geometry": {"coordinates":[100.84608,14.55803],"type":"Point"}
}