{
  "type": "Feature",
  "properties": {
    "gn:admin1_code":"57.0",
    "gn:asciiname":"Ban Khiri Lom",
    "gn:country_code":"TH",
    "gn:dem":266,
    "gn:feature_class":"P",
    "gn:feature_code":"PPL",
    "gn:name":"Ban Khiri Lom",
    "gn:population":0,
    "gn:timezone":"Asia/Bangkok",
    "iso:country":"TH",
    "name:tha_x_preferred":[
        "\u0e1a\u0e49\u0e32\u0e19\u0e04\u0e35\u0e23\u0e35\u0e25\u0e49\u0e2d\u0e21"
    ],
    "wof:name":"Ban Khiri Lom",
    "wof:placetype":"locality"
},
  "geometry": {"coordinates":[99.30481,11.16042],"type":"Point"}
}