{
  "type": "Feature",
  "properties": {
    "gn:admin1_code":"5.0",
    "gn:asciiname":"Ban Mae Rong Noi",
    "gn:country_code":"TH",
    "gn:dem":294,
    "gn:feature_class":"P",
    "gn:feature_code":"PPL",
    "gn:name":"Ban Mae Rong Noi",
    "gn:population":0,
    "gn:timezone":"Asia/Bangkok",
    "iso:country":"TH",
    "name:tha_x_preferred":[
        "\u0e1a\u0e49\u0e32\u0e19\u0e41\u0e21\u0e48\u0e23\u0e48\u0e2d\u0e07\u0e19\u0e49\u0e2d\u0e22"
    ],
    "wof:name":"Ban Mae Rong Noi",
    "wof:placetype":"locality"
},
  "geometry": {"coordinates":[99.04836,18.62647],"type":"Point"}
}