{
  "type": "Feature",
  "properties": {
    "gn:admin1_code":"32.0",
    "gn:asciiname":"Ban Nong Phlap",
    "gn:cc2":"TH",
    "gn:country_code":"TH",
    "gn:dem":21,
    "gn:feature_class":"P",
    "gn:feature_code":"PPL",
    "gn:name":"Ban Nong Phlap",
    "gn:population":0,
    "gn:timezone":"Asia/Bangkok",
    "iso:country":"TH",
    "name:und_x_variant":[
        "Ban Nong Yai",
        "Ban Nong Phlap"
    ],
    "wof:name":"Ban Nong Phlap",
    "wof:placetype":"locality"
},
  "geometry": {"coordinates":[99.96666999999999,14.98333],"type":"Point"}
}