{
  "type": "Feature",
  "properties": {
    "gn:admin1_code":"46.0",
    "gn:asciiname":"Ban Thung Na Phon",
    "gn:country_code":"TH",
    "gn:dem":41,
    "gn:feature_class":"P",
    "gn:feature_code":"PPL",
    "gn:name":"Ban Thung Na Phon",
    "gn:population":0,
    "gn:timezone":"Asia/Bangkok",
    "iso:country":"TH",
    "name:tha_x_preferred":[
        "\u0e1a\u0e49\u0e32\u0e19\u0e17\u0e38\u0e48\u0e07\u0e19\u0e32\u0e1e\u0e23"
    ],
    "wof:name":"Ban Thung Na Phon",
    "wof:placetype":"locality"
},
  "geometry": {"coordinates":[100.95667,13.1992],"type":"Point"}
}