{
  "type": "Feature",
  "properties": {
    "gn:admin1_code":"27.0",
    "gn:asciiname":"Ban Sadao En",
    "gn:country_code":"TH",
    "gn:dem":174,
    "gn:feature_class":"P",
    "gn:feature_code":"PPL",
    "gn:name":"Ban Sadao En",
    "gn:population":0,
    "gn:timezone":"Asia/Bangkok",
    "iso:country":"TH",
    "name:tha_x_preferred":[
        "\u0e1a\u0e49\u0e32\u0e19\u0e2a\u0e30\u0e40\u0e14\u0e32\u0e40\u0e2d\u0e19"
    ],
    "name:und_x_variant":[
        "Ban Mai Sadao En",
        "Ban Mai Sadao",
        "Ban Sadao En"
    ],
    "wof:lang_x_official":[
        "tha"
    ],
    "wof:lang_x_spoken":[
        "tha"
    ],
    "wof:name":"Ban Sadao En",
    "wof:placetype":"locality"
},
  "geometry": {"coordinates":[102.26064,15.07272],"type":"Point"}
}