{
  "type": "Feature",
  "properties": {
    "gn:admin1_code":"34",
    "gn:asciiname":"Ban Wang Saen Di",
    "gn:country_code":"TH",
    "gn:dem":77,
    "gn:feature_class":"P",
    "gn:feature_code":"PPL",
    "gn:name":"Ban Wang Saen Di",
    "gn:population":0,
    "gn:timezone":"Asia/Bangkok",
    "iso:country":"TH",
    "name:tha_x_preferred":[
        "\u0e1a\u0e49\u0e32\u0e19\u0e27\u0e31\u0e07\u0e41\u0e2a\u0e19\u0e14\u0e35"
    ],
    "wof:name":"Ban Wang Saen Di",
    "wof:placetype":"locality"
},
  "geometry": {"coordinates":[101.35469000000001,15.25953],"type":"Point"}
}