{
  "type": "Feature",
  "properties": {
    "gn:admin1_code":"1.0",
    "gn:asciiname":"Ban Bun Loe",
    "gn:country_code":"TH",
    "gn:dem":818,
    "gn:feature_class":"P",
    "gn:feature_code":"PPL",
    "gn:name":"Ban Bun Loe",
    "gn:population":0,
    "gn:timezone":"Asia/Bangkok",
    "iso:country":"TH",
    "name:tha_x_preferred":[
        "\u0e1a\u0e49\u0e32\u0e19\u0e1a\u0e38\u0e0d\u0e40\u0e25\u0e2d"
    ],
    "wof:name":"Ban Bun Loe",
    "wof:placetype":"locality"
},
  "geometry": {"coordinates":[97.72197,17.87283],"type":"Point"}
}