{
  "type": "Feature",
  "properties": {
    "gn:admin1_code":"25",
    "gn:asciiname":"Ban Makhuea",
    "gn:country_code":"TH",
    "gn:dem":131,
    "gn:feature_class":"P",
    "gn:feature_code":"PPL",
    "gn:name":"Ban Makhuea",
    "gn:population":0,
    "gn:timezone":"Asia/Bangkok",
    "iso:country":"TH",
    "name:tha_x_preferred":[
        "\u0e1a\u0e49\u0e32\u0e19\u0e21\u0e30\u0e40\u0e02\u0e37\u0e2d"
    ],
    "wof:lang_x_official":[
        "tha"
    ],
    "wof:lang_x_spoken":[
        "tha"
    ],
    "wof:name":"Ban Makhuea",
    "wof:placetype":"locality"
},
  "geometry": {"coordinates":[104.12514,15.58028],"type":"Point"}
}