{
  "type": "Feature",
  "properties": {
    "gn:admin1_code":"20.0",
    "gn:asciiname":"Ban Thit Thai",
    "gn:country_code":"TH",
    "gn:dem":205,
    "gn:feature_class":"P",
    "gn:feature_code":"PPL",
    "gn:name":"Ban Thit Thai",
    "gn:population":0,
    "gn:timezone":"Asia/Bangkok",
    "iso:country":"TH",
    "name:tha_x_preferred":[
        "\u0e1a\u0e49\u0e32\u0e19\u0e17\u0e34\u0e14\u0e44\u0e17\u0e22"
    ],
    "wof:name":"Ban Thit Thai",
    "wof:placetype":"locality"
},
  "geometry": {"coordinates":[103.80708,17.2747],"type":"Point"}
}