{
  "type": "Feature",
  "properties": {
    "gn:admin1_code":"69.0",
    "gn:asciiname":"Ban Sa Pae Nong",
    "gn:country_code":"TH",
    "gn:dem":13,
    "gn:feature_class":"P",
    "gn:feature_code":"PPL",
    "gn:name":"Ban Sa Pae Nong",
    "gn:population":0,
    "gn:timezone":"Asia/Bangkok",
    "iso:country":"TH",
    "name:tha_x_preferred":[
        "\u0e1a\u0e49\u0e32\u0e19\u0e2a\u0e30\u0e41\u0e1b\u0e19\u0e2d\u0e07"
    ],
    "wof:name":"Ban Sa Pae Nong",
    "wof:placetype":"locality"
},
  "geometry": {"coordinates":[101.44571999999999,6.84408],"type":"Point"}
}