{
  "type": "Feature",
  "properties": {
    "gn:country":"TH",
    "gn:fcode":"ADM3",
    "gn:pop":2485,
    "iso:country":"TH",
    "name:rus_x_preferred":[
        "\u0421\u0430\u043e-\u0425\u0438\u043d"
    ],
    "name:tha_x_preferred":[
        "\u0e40\u0e2a\u0e32\u0e2b\u0e34\u0e19"
    ],
    "name:unk_x_variant":[
        "Tambon Sao Hin"
    ],
    "qs:name":"Sao Hin",
    "qs:photos_9r":0,
    "qs:photos_sr":0,
    "qs:pop_sr":"4",
    "wd:wordcount":54,
    "wof:name":"Sao Hin",
    "wof:placetype":"localadmin",
    "wof:population":2485
},
  "geometry": {"coordinates":[97.68665,18.36137],"type":"Point"}
}