{
  "type": "Feature",
  "properties": {
    "gn:admin1_code":"60.0",
    "gn:asciiname":"Ban Tham Non",
    "gn:country_code":"TH",
    "gn:dem":68,
    "gn:feature_class":"P",
    "gn:feature_code":"PPL",
    "gn:name":"Ban Tham Non",
    "gn:population":0,
    "gn:timezone":"Asia/Bangkok",
    "iso:country":"TH",
    "name:tha_x_preferred":[
        "\u0e1a\u0e49\u0e32\u0e19\u0e16\u0e49\u0e33\u0e19\u0e2d\u0e19"
    ],
    "wof:name":"Ban Tham Non",
    "wof:placetype":"locality"
},
  "geometry": {"coordinates":[98.93089000000001,8.90908],"type":"Point"}
}