{
  "type": "Feature",
  "properties": {
    "gn:admin1_code":"5.0",
    "gn:asciiname":"Ban Yang He",
    "gn:country_code":"TH",
    "gn:dem":599,
    "gn:feature_class":"P",
    "gn:feature_code":"PPL",
    "gn:name":"Ban Yang He",
    "gn:population":0,
    "gn:timezone":"Asia/Bangkok",
    "iso:country":"TH",
    "wof:name":"Ban Yang He",
    "wof:placetype":"locality"
},
  "geometry": {"coordinates":[98.98193999999999,18.21556],"type":"Point"}
}