{
  "type": "Feature",
  "properties": {
    "gn:admin1_code":"43",
    "gn:asciiname":"Ban Khlong Maduea",
    "gn:country_code":"TH",
    "gn:dem":95,
    "gn:feature_class":"P",
    "gn:feature_code":"PPL",
    "gn:name":"Ban Khlong Maduea",
    "gn:population":0,
    "gn:timezone":"Asia/Bangkok",
    "iso:country":"TH",
    "name:tha_x_preferred":[
        "\u0e1a\u0e49\u0e32\u0e19\u0e04\u0e25\u0e2d\u0e07\u0e21\u0e30\u0e40\u0e14\u0e37\u0e48\u0e2d"
    ],
    "wof:name":"Ban Khlong Maduea",
    "wof:placetype":"locality"
},
  "geometry": {"coordinates":[101.27081,14.35733],"type":"Point"}
}