{
  "type": "Feature",
  "properties": {
    "gn:admin1_code":"11.0",
    "gn:asciiname":"Ban Lam Makrok",
    "gn:country_code":"TH",
    "gn:dem":77,
    "gn:feature_class":"P",
    "gn:feature_code":"PPL",
    "gn:name":"Ban Lam Makrok",
    "gn:population":0,
    "gn:timezone":"Asia/Bangkok",
    "iso:country":"TH",
    "name:tha_x_preferred":[
        "\u0e1a\u0e49\u0e32\u0e19\u0e25\u0e33\u0e21\u0e30\u0e42\u0e01\u0e23\u0e01"
    ],
    "wof:name":"Ban Lam Makrok",
    "wof:placetype":"locality"
},
  "geometry": {"coordinates":[99.55286,16.51333],"type":"Point"}
}