{
  "type": "Feature",
  "properties": {
    "gn:admin1_code":"2.0",
    "gn:asciiname":"Ban Wang Lung Mai",
    "gn:country_code":"TH",
    "gn:dem":285,
    "gn:feature_class":"P",
    "gn:feature_code":"PPL",
    "gn:name":"Ban Wang Lung Mai",
    "gn:population":0,
    "gn:timezone":"Asia/Bangkok",
    "iso:country":"TH",
    "name:tha_x_preferred":[
        "\u0e1a\u0e49\u0e32\u0e19\u0e27\u0e31\u0e07\u0e25\u0e38\u0e07\u0e43\u0e2b\u0e21\u0e48"
    ],
    "wof:name":"Ban Wang Lung Mai",
    "wof:placetype":"locality"
},
  "geometry": {"coordinates":[98.61230999999999,18.18231],"type":"Point"}
}