{
  "type": "Feature",
  "properties": {
    "gn:admin1_code":"26.0",
    "gn:asciiname":"Ban Khok Phraiwan",
    "gn:country_code":"TH",
    "gn:dem":224,
    "gn:feature_class":"P",
    "gn:feature_code":"PPL",
    "gn:name":"Ban Khok Phraiwan",
    "gn:population":0,
    "gn:timezone":"Asia/Bangkok",
    "iso:country":"TH",
    "name:tha_x_preferred":[
        "\u0e1a\u0e49\u0e32\u0e19\u0e42\u0e04\u0e01\u0e44\u0e1e\u0e23\u0e27\u0e31\u0e25\u0e22\u0e4c"
    ],
    "wof:name":"Ban Khok Phraiwan",
    "wof:placetype":"locality"
},
  "geometry": {"coordinates":[102.27417,16.19464],"type":"Point"}
}