{
  "type": "Feature",
  "properties": {
    "gn:admin1_code":"31.0",
    "gn:asciiname":"Ban Ta Lo Ta",
    "gn:country_code":"TH",
    "gn:dem":22,
    "gn:feature_class":"P",
    "gn:feature_code":"PPL",
    "gn:name":"Ban Ta Lo Ta",
    "gn:population":0,
    "gn:timezone":"Asia/Bangkok",
    "iso:country":"TH",
    "name:tha_x_preferred":[
        "\u0e1a\u0e49\u0e32\u0e19\u0e15\u0e30\u0e42\u0e25\u0e4a\u0e15\u0e32"
    ],
    "wof:name":"Ban Ta Lo Ta",
    "wof:placetype":"locality"
},
  "geometry": {"coordinates":[101.59003,6.60295],"type":"Point"}
}