{
  "type": "Feature",
  "properties": {
    "gn:admin1_code":"60.0",
    "gn:asciiname":"Ban Bok Hun",
    "gn:country_code":"TH",
    "gn:dem":85,
    "gn:feature_class":"P",
    "gn:feature_code":"PPL",
    "gn:name":"Ban Bok Hun",
    "gn:population":0,
    "gn:timezone":"Asia/Bangkok",
    "iso:country":"TH",
    "name:tha_x_preferred":[
        "\u0e1a\u0e49\u0e32\u0e19\u0e1a\u0e01\u0e2b\u0e38\u0e49\u0e19"
    ],
    "wof:name":"Ban Bok Hun",
    "wof:placetype":"locality"
},
  "geometry": {"coordinates":[99.10181,8.69197],"type":"Point"}
}