{
  "type": "Feature",
  "properties": {
    "gn:admin1_code":"26.0",
    "gn:asciiname":"Ban Chot",
    "gn:country_code":"TH",
    "gn:dem":205,
    "gn:feature_class":"P",
    "gn:feature_code":"PPL",
    "gn:name":"Ban Chot",
    "gn:population":0,
    "gn:timezone":"Asia/Bangkok",
    "iso:country":"TH",
    "name:tha_x_preferred":[
        "\u0e1a\u0e49\u0e32\u0e19\u0e42\u0e08\u0e14"
    ],
    "name:und_x_variant":[
        "Ban Non Chot"
    ],
    "wof:name":"Ban Chot",
    "wof:placetype":"locality"
},
  "geometry": {"coordinates":[102.25533,16.43914],"type":"Point"}
}