{
  "type": "Feature",
  "properties": {
    "gn:admin1_code":"27",
    "gn:asciiname":"Ban Thep Phu Thong",
    "gn:country_code":"TH",
    "gn:dem":322,
    "gn:feature_class":"P",
    "gn:feature_code":"PPL",
    "gn:name":"Ban Thep Phu Thong",
    "gn:population":0,
    "gn:timezone":"Asia/Bangkok",
    "iso:country":"TH",
    "name:tha_x_preferred":[
        "\u0e1a\u0e49\u0e32\u0e19\u0e40\u0e17\u0e1e\u0e20\u0e39\u0e17\u0e2d\u0e07"
    ],
    "wof:name":"Ban Thep Phu Thong",
    "wof:placetype":"locality"
},
  "geometry": {"coordinates":[101.44168999999999,15.35947],"type":"Point"}
}