{
  "type": "Feature",
  "properties": {
    "gn:admin1_code":"8.0",
    "gn:asciiname":"Ban Chatsan",
    "gn:country_code":"TH",
    "gn:dem":142,
    "gn:feature_class":"P",
    "gn:feature_code":"PPL",
    "gn:name":"Ban Chatsan",
    "gn:population":0,
    "gn:timezone":"Asia/Bangkok",
    "iso:country":"TH",
    "name:tha_x_preferred":[
        "Ban Chatsan"
    ],
    "name:tha_x_variant":[
        "\u0e1a\u0e49\u0e32\u0e19\u0e08\u0e31\u0e14\u0e2a\u0e23\u0e23"
    ],
    "wof:name":"Ban Chatsan",
    "wof:placetype":"locality"
},
  "geometry": {"coordinates":[99.05086,17.21503],"type":"Point"}
}