{
  "type": "Feature",
  "properties": {
    "gn:admin1_code":"55.0",
    "gn:asciiname":"Ban Plai Na",
    "gn:country_code":"TH",
    "gn:dem":6,
    "gn:feature_class":"P",
    "gn:feature_code":"PPL",
    "gn:name":"Ban Plai Na",
    "gn:population":0,
    "gn:timezone":"Asia/Bangkok",
    "iso:country":"TH",
    "name:tha_x_preferred":[
        "\u0e1a\u0e49\u0e32\u0e19\u0e1b\u0e25\u0e32\u0e22\u0e19\u0e32"
    ],
    "wof:name":"Ban Plai Na",
    "wof:placetype":"locality"
},
  "geometry": {"coordinates":[100.13736,13.67886],"type":"Point"}
}