{
  "type": "Feature",
  "properties": {
    "iso:country":"TH",
    "name:deu_x_preferred":[
        "Phutthamonthon"
    ],
    "name:eng_x_preferred":[
        "Phutthamonthon"
    ],
    "name:jpn_x_preferred":[
        "\u30d7\u30c3\u30bf\u30e2\u30f3\u30c8\u30f3"
    ],
    "name:tha_x_preferred":[
        "\u0e1e\u0e38\u0e17\u0e18\u0e21\u0e13\u0e11\u0e25"
    ],
    "qs:name":"Phutthamonthon",
    "qs:name_adm0":"Thailand",
    "qs:name_adm1":"Nathon Pathon",
    "qs:photos":166,
    "qs:photos_1k":34,
    "qs:photos_9k":1,
    "qs:photos_9r":4,
    "qs:photos_all":166,
    "qs:photos_sr":4,
    "qs:placetype":"Town",
    "qs:pop_sr":"0",
    "wd:wordcount":347,
    "wof:name":"Phutthamonthon",
    "wof:placetype":"locality"
},
  "geometry": {"coordinates":[100.309473,13.7916],"type":"Point"}
}