{
  "type": "Feature",
  "properties": {
    "iso:country":"TH",
    "qs:name":"Phutthamonthon",
    "qs:name_adm0":"Thailand",
    "qs:name_adm1":"Nathon Pathon",
    "qs:photos":166,
    "qs:photos_1k":34,
    "qs:photos_9k":1,
    "qs:photos_9r":4,
    "qs:photos_all":166,
    "qs:photos_sr":4,
    "qs:placetype":"Town",
    "qs:pop_sr":"0",
    "wd:wordcount":347,
    "wof:name":"Phutthamonthon",
    "wof:placetype":"locality"
},
  "geometry": {"coordinates":[100.309473,13.7916],"type":"Point"}
}