{
  "type": "Feature",
  "properties": {
    "gn:admin1_code":"17.0",
    "gn:asciiname":"Ban Chai Phatthana",
    "gn:country_code":"TH",
    "gn:dem":175,
    "gn:feature_class":"P",
    "gn:feature_code":"PPL",
    "gn:name":"Ban Chai Phatthana",
    "gn:population":0,
    "gn:timezone":"Asia/Bangkok",
    "iso:country":"TH",
    "name:tha_x_preferred":[
        "\u0e1a\u0e49\u0e32\u0e19\u0e44\u0e0a\u0e22\u0e1e\u0e31\u0e12\u0e19\u0e32"
    ],
    "wof:name":"Ban Chai Phatthana",
    "wof:placetype":"locality"
},
  "geometry": {"coordinates":[103.26447,18.08642],"type":"Point"}
}