{
  "type": "Feature",
  "properties": {
    "gn:admin1_code":"7.0",
    "gn:asciiname":"Ban Mae Yang Lai Thung",
    "gn:country_code":"TH",
    "gn:dem":204,
    "gn:feature_class":"P",
    "gn:feature_code":"PPL",
    "gn:name":"Ban Mae Yang Lai Thung",
    "gn:population":0,
    "gn:timezone":"Asia/Bangkok",
    "iso:country":"TH",
    "name:tha_x_preferred":[
        "\u0e1a\u0e49\u0e32\u0e19\u0e41\u0e21\u0e48\u0e22\u0e32\u0e07\u0e2b\u0e25\u0e32\u0e22\u0e17\u0e38\u0e48\u0e07"
    ],
    "wof:name":"Ban Mae Yang Lai Thung",
    "wof:placetype":"locality"
},
  "geometry": {"coordinates":[100.26716999999999,18.33125],"type":"Point"}
}