{
  "type": "Feature",
  "properties": {
    "gn:admin1_code":"61.0",
    "gn:asciiname":"Ban Pak Wip",
    "gn:country_code":"TH",
    "gn:dem":15,
    "gn:feature_class":"P",
    "gn:feature_code":"PPL",
    "gn:name":"Ban Pak Wip",
    "gn:population":0,
    "gn:timezone":"Asia/Bangkok",
    "iso:country":"TH",
    "name:tha_x_preferred":[
        "\u0e1a\u0e49\u0e32\u0e19\u0e1b\u0e32\u0e01\u0e27\u0e35\u0e1b"
    ],
    "name:und_x_variant":[
        "Ban Kamnan Pak Wit",
        "Ban Pak Wit",
        "Ban Pak Wip"
    ],
    "wof:lang_x_official":[
        "tha"
    ],
    "wof:lang_x_spoken":[
        "tha"
    ],
    "wof:name":"Ban Pak Wip",
    "wof:placetype":"locality"
},
  "geometry": {"coordinates":[98.26213,8.74902],"type":"Point"}
}