{
  "type": "Feature",
  "properties": {
    "gn:admin1_code":"46.0",
    "gn:asciiname":"Ban Khao Cha-ang",
    "gn:country_code":"TH",
    "gn:dem":99,
    "gn:feature_class":"P",
    "gn:feature_code":"PPL",
    "gn:name":"Ban Khao Cha-ang",
    "gn:population":0,
    "gn:timezone":"Asia/Bangkok",
    "iso:country":"TH",
    "name:tha_x_preferred":[
        "\u0e1a\u0e49\u0e32\u0e19\u0e40\u0e02\u0e32\u0e0a\u0e30\u0e2d\u0e32\u0e07\u0e04\u0e4c"
    ],
    "wof:name":"Ban Khao Cha-ang",
    "wof:placetype":"locality"
},
  "geometry": {"coordinates":[101.58817000000001,13.21986],"type":"Point"}
}