{
  "type": "Feature",
  "properties": {
    "gn:admin1_code":"36.0",
    "gn:asciiname":"Ban Khu Makmao",
    "gn:country_code":"TH",
    "gn:dem":5,
    "gn:feature_class":"P",
    "gn:feature_code":"PPL",
    "gn:name":"Ban Khu Makmao",
    "gn:population":0,
    "gn:timezone":"Asia/Bangkok",
    "iso:country":"TH",
    "name:tha_x_preferred":[
        "Ban Khu Makmao"
    ],
    "name:tha_x_variant":[
        "\u0e1a\u0e49\u0e32\u0e19\u0e04\u0e39\u0e49\u0e21\u0e31\u0e01\u0e40\u0e21\u0e48\u0e32"
    ],
    "wof:name":"Ban Khu Makmao",
    "wof:placetype":"locality"
},
  "geometry": {"coordinates":[100.37157999999999,14.20289],"type":"Point"}
}