{
  "type": "Feature",
  "properties": {
    "gn:admin1_code":"25",
    "gn:asciiname":"Ban Sawang Arom",
    "gn:country_code":"TH",
    "gn:dem":159,
    "gn:feature_class":"P",
    "gn:feature_code":"PPL",
    "gn:name":"Ban Sawang Arom",
    "gn:population":0,
    "gn:timezone":"Asia/Bangkok",
    "iso:country":"TH",
    "name:tha_x_preferred":[
        "\u0e1a\u0e49\u0e32\u0e19\u0e2a\u0e27\u0e48\u0e32\u0e07\u0e2d\u0e32\u0e23\u0e21\u0e13\u0e4c"
    ],
    "wof:lang_x_official":[
        "tha"
    ],
    "wof:lang_x_spoken":[
        "tha"
    ],
    "wof:name":"Ban Sawang Arom",
    "wof:placetype":"locality"
},
  "geometry": {"coordinates":[104.08831000000001,16.19397],"type":"Point"}
}