{
  "type": "Feature",
  "properties": {
    "gn:admin1_code":"27.0",
    "gn:asciiname":"Ban Huai",
    "gn:country_code":"TH",
    "gn:dem":213,
    "gn:feature_class":"P",
    "gn:feature_code":"PPL",
    "gn:name":"Ban Huai",
    "gn:population":0,
    "gn:timezone":"Asia/Bangkok",
    "iso:country":"TH",
    "name:tha_x_preferred":[
        "\u0e1a\u0e49\u0e32\u0e19\u0e2b\u0e49\u0e27\u0e22"
    ],
    "name:und_x_variant":[
        "Sakae Rat",
        "Ban Huai",
        "Ban Sakae Rat",
        "King Sakae Rat",
        "Ban Huai Sakae Rat"
    ],
    "wof:name":"Ban Huai",
    "wof:placetype":"locality"
},
  "geometry": {"coordinates":[102.03086,14.61106],"type":"Point"}
}