{
  "type": "Feature",
  "properties": {
    "gn:admin1_code":"27",
    "gn:asciiname":"Ban Sap Tai",
    "gn:country_code":"TH",
    "gn:dem":424,
    "gn:feature_class":"P",
    "gn:feature_code":"PPL",
    "gn:name":"Ban Sap Tai",
    "gn:population":0,
    "gn:timezone":"Asia/Bangkok",
    "iso:country":"TH",
    "name:tha_x_preferred":[
        "\u0e1a\u0e49\u0e32\u0e19\u0e0b\u0e31\u0e1a\u0e43\u0e15\u0e49"
    ],
    "wof:name":"Ban Sap Tai",
    "wof:placetype":"locality"
},
  "geometry": {"coordinates":[101.25485999999999,14.52147],"type":"Point"}
}