{
  "type": "Feature",
  "properties": {
    "gn:admin1_code":"68.0",
    "gn:asciiname":"Ban Wang Chang",
    "gn:country_code":"TH",
    "gn:dem":40,
    "gn:feature_class":"P",
    "gn:feature_code":"PPL",
    "gn:name":"Ban Wang Chang",
    "gn:population":0,
    "gn:timezone":"Asia/Bangkok",
    "iso:country":"TH",
    "name:tha_x_preferred":[
        "\u0e1a\u0e49\u0e32\u0e19\u0e27\u0e31\u0e07\u0e0a\u0e49\u0e32\u0e07"
    ],
    "wof:name":"Ban Wang Chang",
    "wof:placetype":"locality"
},
  "geometry": {"coordinates":[100.57472,6.98992],"type":"Point"}
}