{
  "type": "Feature",
  "properties": {
    "gn:admin1_code":"30.0",
    "gn:asciiname":"Ban Nam Om Noi",
    "gn:country_code":"TH",
    "gn:dem":127,
    "gn:feature_class":"P",
    "gn:feature_code":"PPL",
    "gn:name":"Ban Nam Om Noi",
    "gn:population":0,
    "gn:timezone":"Asia/Bangkok",
    "iso:country":"TH",
    "name:tha_x_preferred":[
        "\u0e1a\u0e49\u0e32\u0e19\u0e19\u0e49\u0e33\u0e2d\u0e49\u0e2d\u0e21\u0e19\u0e49\u0e2d\u0e22"
    ],
    "wof:name":"Ban Nam Om Noi",
    "wof:placetype":"locality"
},
  "geometry": {"coordinates":[104.20139,15.39706],"type":"Point"}
}