{
  "type": "Feature",
  "properties": {
    "gn:admin1_code":"47.0",
    "gn:asciiname":"Ban Cham Kho",
    "gn:country_code":"TH",
    "gn:dem":57,
    "gn:feature_class":"P",
    "gn:feature_code":"PPL",
    "gn:name":"Ban Cham Kho",
    "gn:population":0,
    "gn:timezone":"Asia/Bangkok",
    "iso:country":"TH",
    "name:tha_x_preferred":[
        "\u0e1a\u0e49\u0e32\u0e19\u0e0a\u0e33\u0e06\u0e49\u0e2d"
    ],
    "wof:name":"Ban Cham Kho",
    "wof:placetype":"locality"
},
  "geometry": {"coordinates":[101.67556,12.93972],"type":"Point"}
}