{
  "type": "Feature",
  "properties": {
    "gn:admin1_code":"26.0",
    "gn:asciiname":"Ban Sap Plakang",
    "gn:country_code":"TH",
    "gn:dem":274,
    "gn:feature_class":"P",
    "gn:feature_code":"PPL",
    "gn:name":"Ban Sap Plakang",
    "gn:population":0,
    "gn:timezone":"Asia/Bangkok",
    "iso:country":"TH",
    "name:tha_x_preferred":[
        "\u0e1a\u0e49\u0e32\u0e19\u0e0b\u0e31\u0e1a\u0e1b\u0e25\u0e32\u0e01\u0e31\u0e49\u0e07"
    ],
    "wof:name":"Ban Sap Plakang",
    "wof:placetype":"locality"
},
  "geometry": {"coordinates":[101.76828,15.91953],"type":"Point"}
}