{
  "type": "Feature",
  "properties": {
    "gn:admin1_code":"29",
    "gn:asciiname":"Ban A-wuek",
    "gn:country_code":"TH",
    "gn:dem":167,
    "gn:feature_class":"P",
    "gn:feature_code":"PPL",
    "gn:name":"Ban A-wuek",
    "gn:population":0,
    "gn:timezone":"Asia/Bangkok",
    "iso:country":"TH",
    "name:tha_x_preferred":[
        "\u0e1a\u0e49\u0e32\u0e19\u0e2d\u0e32\u0e27\u0e36\u0e01"
    ],
    "wof:name":"Ban A-wuek",
    "wof:placetype":"locality"
},
  "geometry": {"coordinates":[103.37822,14.71844],"type":"Point"}
}