{
  "type": "Feature",
  "properties": {
    "gn:admin1_code":"38.0",
    "gn:asciiname":"Muban Nanthicha",
    "gn:country_code":"TH",
    "gn:dem":10,
    "gn:feature_class":"P",
    "gn:feature_code":"PPL",
    "gn:name":"Muban Nanthicha",
    "gn:population":0,
    "gn:timezone":"Asia/Bangkok",
    "iso:country":"TH",
    "name:tha_x_preferred":[
        "\u0e2b\u0e21\u0e39\u0e48\u0e1a\u0e49\u0e32\u0e19\u0e19\u0e31\u0e19\u0e17\u0e34\u0e0a\u0e32"
    ],
    "wof:name":"Muban Nanthicha",
    "wof:placetype":"locality"
},
  "geometry": {"coordinates":[100.39506,13.94558],"type":"Point"}
}