{
  "type": "Feature",
  "properties": {
    "gn:admin1_code":"4.0",
    "gn:asciiname":"Ban Sakat Tai",
    "gn:country_code":"TH",
    "gn:dem":921,
    "gn:feature_class":"P",
    "gn:feature_code":"PPL",
    "gn:name":"Ban Sakat Tai",
    "gn:population":0,
    "gn:timezone":"Asia/Bangkok",
    "iso:country":"TH",
    "name:tha_x_preferred":[
        "\u0e1a\u0e49\u0e32\u0e19\u0e2a\u0e01\u0e32\u0e14\u0e43\u0e15\u0e49"
    ],
    "name:und_x_variant":[
        "B\u0101n Sakat D\u0101i",
        "Ban Sakat Tai"
    ],
    "wof:name":"Ban Sakat Tai",
    "wof:placetype":"locality"
},
  "geometry": {"coordinates":[101.00375,19.259],"type":"Point"}
}