{
  "type": "Feature",
  "properties": {
    "gn:admin1_code":"59.0",
    "gn:asciiname":"Ban Chiao Khlai",
    "gn:country_code":"TH",
    "gn:dem":58,
    "gn:feature_class":"P",
    "gn:feature_code":"PPL",
    "gn:name":"Ban Chiao Khlai",
    "gn:population":0,
    "gn:timezone":"Asia/Bangkok",
    "iso:country":"TH",
    "name:tha_x_preferred":[
        "\u0e1a\u0e49\u0e32\u0e19\u0e40\u0e0a\u0e35\u0e48\u0e22\u0e27\u0e04\u0e25\u0e49\u0e32\u0e22"
    ],
    "wof:name":"Ban Chiao Khlai",
    "wof:placetype":"locality"
},
  "geometry": {"coordinates":[98.73175000000001,9.98258],"type":"Point"}
}