{
  "type": "Feature",
  "properties": {
    "gn:admin1_code":"66.0",
    "gn:asciiname":"Ban Sai O",
    "gn:country_code":"TH",
    "gn:dem":18,
    "gn:feature_class":"P",
    "gn:feature_code":"PPL",
    "gn:name":"Ban Sai O",
    "gn:population":0,
    "gn:timezone":"Asia/Bangkok",
    "iso:country":"TH",
    "name:tha_x_preferred":[
        "\u0e1a\u0e49\u0e32\u0e19\u0e44\u0e2a\u0e2d\u0e49\u0e2d"
    ],
    "wof:name":"Ban Sai O",
    "wof:placetype":"locality"
},
  "geometry": {"coordinates":[99.97186000000001,7.84441],"type":"Point"}
}