{
  "type": "Feature",
  "properties": {
    "gn:admin1_code":"20.0",
    "gn:asciiname":"Ban Si Wicha",
    "gn:country_code":"TH",
    "gn:dem":178,
    "gn:feature_class":"P",
    "gn:feature_code":"PPL",
    "gn:name":"Ban Si Wicha",
    "gn:population":0,
    "gn:timezone":"Asia/Bangkok",
    "iso:country":"TH",
    "name:tha_x_preferred":[
        "\u0e1a\u0e49\u0e32\u0e19\u0e28\u0e23\u0e35\u0e27\u0e34\u0e0a\u0e32"
    ],
    "wof:name":"Ban Si Wicha",
    "wof:placetype":"locality"
},
  "geometry": {"coordinates":[104.09814,17.13242],"type":"Point"}
}