{
  "type": "Feature",
  "properties": {
    "gn:admin1_code":"2.0",
    "gn:asciiname":"Ban Mae Tala",
    "gn:country_code":"TH",
    "gn:dem":1323,
    "gn:feature_class":"P",
    "gn:feature_code":"PPL",
    "gn:name":"Ban Mae Tala",
    "gn:population":0,
    "gn:timezone":"Asia/Bangkok",
    "iso:country":"TH",
    "name:tha_x_preferred":[
        "\u0e1a\u0e49\u0e32\u0e19\u0e41\u0e21\u0e48\u0e15\u0e30\u0e25\u0e30"
    ],
    "name:und_x_variant":[
        "Ban Khun Mae Tala"
    ],
    "wof:name":"Ban Mae Tala",
    "wof:placetype":"locality"
},
  "geometry": {"coordinates":[98.4575,18.93492],"type":"Point"}
}