{
  "type": "Feature",
  "properties": {
    "gn:admin1_code":"9.0",
    "gn:asciiname":"Ban Pak Khlong Chang",
    "gn:country_code":"TH",
    "gn:dem":65,
    "gn:feature_class":"P",
    "gn:feature_code":"PPL",
    "gn:name":"Ban Pak Khlong Chang",
    "gn:population":0,
    "gn:timezone":"Asia/Bangkok",
    "iso:country":"TH",
    "name:tha_x_preferred":[
        "\u0e1a\u0e49\u0e32\u0e19\u0e1b\u0e32\u0e01\u0e04\u0e25\u0e2d\u0e07\u0e0a\u0e49\u0e32\u0e07"
    ],
    "name:und_x_variant":[
        "B\u0101n P\u0101k Klaung Ch\u0101ng",
        "Ban Pak Khlong Chang"
    ],
    "wof:lang_x_official":[
        "tha"
    ],
    "wof:lang_x_spoken":[
        "tha"
    ],
    "wof:name":"Ban Pak Khlong Chang",
    "wof:placetype":"locality"
},
  "geometry": {"coordinates":[99.72044,17.21697],"type":"Point"}
}