{
  "type": "Feature",
  "properties": {
    "gn:admin1_code":"31.0",
    "gn:asciiname":"Ban Ai Chu Cho",
    "gn:country_code":"TH",
    "gn:dem":64,
    "gn:feature_class":"P",
    "gn:feature_code":"PPL",
    "gn:name":"Ban Ai Chu Cho",
    "gn:population":0,
    "gn:timezone":"Asia/Bangkok",
    "iso:country":"TH",
    "name:tha_x_preferred":[
        "\u0e1a\u0e49\u0e32\u0e19\u0e44\u0e2d\u0e23\u0e4c\u0e08\u0e39\u0e42\u0e08\u0e4a\u0e30"
    ],
    "name:und_x_variant":[
        "Ban Al Chu Cho",
        "Ban Ai Chu Cho"
    ],
    "wof:lang_x_official":[
        "tha"
    ],
    "wof:lang_x_spoken":[
        "tha"
    ],
    "wof:name":"Ban Ai Chu Cho",
    "wof:placetype":"locality"
},
  "geometry": {"coordinates":[101.48839,6.14253],"type":"Point"}
}