{
  "type": "Feature",
  "properties": {
    "gn:admin1_code":"74",
    "gn:asciiname":"Ban Nong Lakhon",
    "gn:country_code":"TH",
    "gn:dem":21,
    "gn:feature_class":"P",
    "gn:feature_code":"PPL",
    "gn:name":"Ban Nong Lakhon",
    "gn:population":0,
    "gn:timezone":"Asia/Bangkok",
    "iso:country":"TH",
    "name:tha_x_preferred":[
        "\u0e1a\u0e49\u0e32\u0e19\u0e2b\u0e19\u0e2d\u0e07\u0e25\u0e30\u0e04\u0e23"
    ],
    "wof:name":"Ban Nong Lakhon",
    "wof:placetype":"locality"
},
  "geometry": {"coordinates":[101.55208,14.06944],"type":"Point"}
}