{
  "type": "Feature",
  "properties": {
    "gn:admin1_code":"51.0",
    "gn:asciiname":"Ban Yom Buea",
    "gn:country_code":"TH",
    "gn:dem":37,
    "gn:feature_class":"P",
    "gn:feature_code":"PPL",
    "gn:name":"Ban Yom Buea",
    "gn:population":0,
    "gn:timezone":"Asia/Bangkok",
    "iso:country":"TH",
    "name:tha_x_preferred":[
        "\u0e1a\u0e49\u0e32\u0e19\u0e22\u0e21\u0e40\u0e1a\u0e37\u0e2d"
    ],
    "wof:name":"Ban Yom Buea",
    "wof:placetype":"locality"
},
  "geometry": {"coordinates":[99.84892000000001,14.68267],"type":"Point"}
}