{
  "type": "Feature",
  "properties": {
    "gn:admin1_code":"27.0",
    "gn:asciiname":"Ban Prasat",
    "gn:country_code":"TH",
    "gn:dem":262,
    "gn:feature_class":"P",
    "gn:feature_code":"PPL",
    "gn:name":"Ban Prasat",
    "gn:population":0,
    "gn:timezone":"Asia/Bangkok",
    "iso:country":"TH",
    "name:tha_x_preferred":[
        "\u0e1a\u0e49\u0e32\u0e19\u0e1b\u0e23\u0e30\u0e2a\u0e32\u0e17"
    ],
    "name:und_x_variant":[
        "Ban Noi",
        "Ban Prasat"
    ],
    "wof:name":"Ban Prasat",
    "wof:placetype":"locality"
},
  "geometry": {"coordinates":[101.58575,15.13142],"type":"Point"}
}