{
  "type": "Feature",
  "properties": {
    "gn:admin1_code":"54.0",
    "gn:asciiname":"Ban Khlong Kao",
    "gn:country_code":"TH",
    "gn:dem":4,
    "gn:feature_class":"P",
    "gn:feature_code":"PPL",
    "gn:name":"Ban Khlong Kao",
    "gn:population":0,
    "gn:timezone":"Asia/Bangkok",
    "iso:country":"TH",
    "name:tha_x_preferred":[
        "\u0e1a\u0e49\u0e32\u0e19\u0e04\u0e25\u0e2d\u0e07\u0e40\u0e01\u0e48\u0e32"
    ],
    "wof:name":"Ban Khlong Kao",
    "wof:placetype":"locality"
},
  "geometry": {"coordinates":[99.94938999999999,13.37589],"type":"Point"}
}