{
  "type": "Feature",
  "properties": {
    "gn:admin1_code":"10.0",
    "gn:asciiname":"Ban Nam Mi Yai",
    "gn:country_code":"TH",
    "gn:dem":106,
    "gn:feature_class":"P",
    "gn:feature_code":"PPL",
    "gn:name":"Ban Nam Mi Yai",
    "gn:population":0,
    "gn:timezone":"Asia/Bangkok",
    "iso:country":"TH",
    "name:tha_x_preferred":[
        "Ban Nam Mi Yai"
    ],
    "name:tha_x_variant":[
        "\u0e1a\u0e49\u0e32\u0e19\u0e19\u0e49\u0e33\u0e2b\u0e21\u0e35\u0e43\u0e2b\u0e0d\u0e48"
    ],
    "wof:name":"Ban Nam Mi Yai",
    "wof:placetype":"locality"
},
  "geometry": {"coordinates":[100.43597,17.56197],"type":"Point"}
}