{
  "type": "Feature",
  "properties": {
    "gn:admin1_code":"29.0",
    "gn:asciiname":"Ban Khok Lamduan",
    "gn:country_code":"TH",
    "gn:dem":152,
    "gn:feature_class":"P",
    "gn:feature_code":"PPL",
    "gn:name":"Ban Khok Lamduan",
    "gn:population":0,
    "gn:timezone":"Asia/Bangkok",
    "iso:country":"TH",
    "name:tha_x_preferred":[
        "\u0e1a\u0e49\u0e32\u0e19\u0e42\u0e04\u0e01\u0e25\u0e33\u0e14\u0e27\u0e19"
    ],
    "wof:name":"Ban Khok Lamduan",
    "wof:placetype":"locality"
},
  "geometry": {"coordinates":[103.76742,14.78942],"type":"Point"}
}