{
  "type": "Feature",
  "properties": {
    "gn:admin1_code":"24",
    "gn:asciiname":"Ban Pa Chik",
    "gn:country_code":"TH",
    "gn:dem":168,
    "gn:feature_class":"P",
    "gn:feature_code":"PPL",
    "gn:name":"Ban Pa Chik",
    "gn:population":0,
    "gn:timezone":"Asia/Bangkok",
    "iso:country":"TH",
    "name:tha_x_preferred":[
        "\u0e1a\u0e49\u0e32\u0e19\u0e1b\u0e48\u0e32\u0e08\u0e34\u0e01"
    ],
    "wof:name":"Ban Pa Chik",
    "wof:placetype":"locality"
},
  "geometry": {"coordinates":[103.26897,15.92403],"type":"Point"}
}