{
  "type": "Feature",
  "properties": {
    "gn:admin1_code":"34",
    "gn:asciiname":"Ban Khok Na Chat",
    "gn:country_code":"TH",
    "gn:dem":53,
    "gn:feature_class":"P",
    "gn:feature_code":"PPL",
    "gn:name":"Ban Khok Na Chat",
    "gn:population":0,
    "gn:timezone":"Asia/Bangkok",
    "iso:country":"TH",
    "name:tha_x_preferred":[
        "\u0e1a\u0e49\u0e32\u0e19\u0e42\u0e04\u0e01\u0e19\u0e32\u0e0a\u0e31\u0e14"
    ],
    "wof:name":"Ban Khok Na Chat",
    "wof:placetype":"locality"
},
  "geometry": {"coordinates":[101.20456,15.23214],"type":"Point"}
}