{
  "type": "Feature",
  "properties": {
    "gn:admin1_code":"76.0",
    "gn:asciiname":"Ban Mae Non",
    "gn:country_code":"TH",
    "gn:dem":193,
    "gn:feature_class":"P",
    "gn:feature_code":"PPL",
    "gn:name":"Ban Mae Non",
    "gn:population":0,
    "gn:timezone":"Asia/Bangkok",
    "iso:country":"TH",
    "name:tha_x_preferred":[
        "\u0e1a\u0e49\u0e32\u0e19\u0e41\u0e21\u0e48\u0e19\u0e19\u0e17\u0e4c"
    ],
    "wof:name":"Ban Mae Non",
    "wof:placetype":"locality"
},
  "geometry": {"coordinates":[102.89653,17.23897],"type":"Point"}
}