{
  "type": "Feature",
  "properties": {
    "gn:admin1_code":"29",
    "gn:asciiname":"Ban Sae Kraban",
    "gn:country_code":"TH",
    "gn:dem":154,
    "gn:feature_class":"P",
    "gn:feature_code":"PPL",
    "gn:name":"Ban Sae Kraban",
    "gn:population":0,
    "gn:timezone":"Asia/Bangkok",
    "iso:country":"TH",
    "name:tha_x_preferred":[
        "\u0e1a\u0e49\u0e32\u0e19\u0e41\u0e0b\u0e30\u0e01\u0e23\u0e30\u0e1a\u0e32\u0e25"
    ],
    "wof:name":"Ban Sae Kraban",
    "wof:placetype":"locality"
},
  "geometry": {"coordinates":[103.65058000000001,14.82675],"type":"Point"}
}