{
  "type": "Feature",
  "properties": {
    "gn:admin1_code":"27",
    "gn:asciiname":"Ban Thewa Nimit",
    "gn:country_code":"TH",
    "gn:dem":220,
    "gn:feature_class":"P",
    "gn:feature_code":"PPL",
    "gn:name":"Ban Thewa Nimit",
    "gn:population":0,
    "gn:timezone":"Asia/Bangkok",
    "iso:country":"TH",
    "name:tha_x_preferred":[
        "\u0e1a\u0e49\u0e32\u0e19\u0e40\u0e17\u0e27\u0e19\u0e34\u0e21\u0e34\u0e15"
    ],
    "wof:name":"Ban Thewa Nimit",
    "wof:placetype":"locality"
},
  "geometry": {"coordinates":[101.70011,15.34867],"type":"Point"}
}