{
  "type": "Feature",
  "properties": {
    "gn:admin1_code":"2.0",
    "gn:asciiname":"Ban Bo Luang",
    "gn:country_code":"TH",
    "gn:dem":1112,
    "gn:feature_class":"P",
    "gn:feature_code":"PPL",
    "gn:name":"Ban Bo Luang",
    "gn:population":0,
    "gn:timezone":"Asia/Bangkok",
    "iso:country":"TH",
    "name:tha_x_preferred":[
        "\u0e1a\u0e49\u0e32\u0e19\u0e1a\u0e48\u0e2d\u0e2b\u0e25\u0e27\u0e07"
    ],
    "name:und_x_variant":[
        "Bau Luang",
        "B\u0101n Bau Luang",
        "Bohhluang",
        "Ban Bo Luang"
    ],
    "wof:name":"Ban Bo Luang",
    "wof:placetype":"locality"
},
  "geometry": {"coordinates":[98.35081,18.1505],"type":"Point"}
}