{
  "type": "Feature",
  "properties": {
    "gn:admin1_code":"75.0",
    "gn:asciiname":"Ban Don Chiang Tho",
    "gn:country_code":"TH",
    "gn:dem":126,
    "gn:feature_class":"P",
    "gn:feature_code":"PPL",
    "gn:name":"Ban Don Chiang Tho",
    "gn:population":0,
    "gn:timezone":"Asia/Bangkok",
    "iso:country":"TH",
    "name:tha_x_preferred":[
        "\u0e1a\u0e49\u0e32\u0e19\u0e14\u0e2d\u0e19\u0e40\u0e0a\u0e35\u0e22\u0e07\u0e42\u0e17"
    ],
    "wof:name":"Ban Don Chiang Tho",
    "wof:placetype":"locality"
},
  "geometry": {"coordinates":[104.51258,15.40969],"type":"Point"}
}