{
  "type": "Feature",
  "properties": {
    "gn:admin1_code":"9.0",
    "gn:asciiname":"Ban Bang Sanim",
    "gn:country_code":"TH",
    "gn:dem":45,
    "gn:feature_class":"P",
    "gn:feature_code":"PPL",
    "gn:name":"Ban Bang Sanim",
    "gn:population":0,
    "gn:timezone":"Asia/Bangkok",
    "iso:country":"TH",
    "name:tha_x_preferred":[
        "\u0e1a\u0e49\u0e32\u0e19\u0e1a\u0e32\u0e07\u0e2a\u0e19\u0e34\u0e21"
    ],
    "name:und_x_variant":[
        "Ban Wang Sanim"
    ],
    "wof:name":"Ban Bang Sanim",
    "wof:placetype":"locality"
},
  "geometry": {"coordinates":[99.94319,16.90603],"type":"Point"}
}