{
  "type": "Feature",
  "properties": {
    "gn:admin1_code":"27",
    "gn:asciiname":"Ban Som Kop Ngam",
    "gn:country_code":"TH",
    "gn:dem":253,
    "gn:feature_class":"P",
    "gn:feature_code":"PPL",
    "gn:name":"Ban Som Kop Ngam",
    "gn:population":0,
    "gn:timezone":"Asia/Bangkok",
    "iso:country":"TH",
    "name:tha_x_preferred":[
        "\u0e1a\u0e49\u0e32\u0e19\u0e2a\u0e49\u0e21\u0e01\u0e1a\u0e07\u0e32\u0e21"
    ],
    "wof:name":"Ban Som Kop Ngam",
    "wof:placetype":"locality"
},
  "geometry": {"coordinates":[101.80967,15.00285],"type":"Point"}
}