{
  "type": "Feature",
  "properties": {
    "gn:admin1_code":"9.0",
    "gn:asciiname":"Ban Tha Makluea",
    "gn:country_code":"TH",
    "gn:dem":67,
    "gn:feature_class":"P",
    "gn:feature_code":"PPL",
    "gn:name":"Ban Tha Makluea",
    "gn:population":0,
    "gn:timezone":"Asia/Bangkok",
    "iso:country":"TH",
    "name:tha_x_preferred":[
        "\u0e1a\u0e49\u0e32\u0e19\u0e17\u0e48\u0e32\u0e21\u0e30\u0e40\u0e01\u0e25\u0e37\u0e2d"
    ],
    "name:und_x_variant":[
        "Ban Tha Maklua"
    ],
    "wof:name":"Ban Tha Makluea",
    "wof:placetype":"locality"
},
  "geometry": {"coordinates":[99.80128000000001,17.42094],"type":"Point"}
}