{
  "type": "Feature",
  "properties": {
    "iso:country":"TH",
    "name:bpy_x_preferred":[
        "\u0986\u09ae\u09cd\u09ab\u09cb\u09af\u09bc\u09c7 \u09ac\u09cd\u09af\u09be\u0982 \u09ac\u09be\u09a8"
    ],
    "name:ceb_x_preferred":[
        "Amphoe Bang Ban"
    ],
    "name:deu_x_preferred":[
        "Amphoe Bang Ban"
    ],
    "name:eng_x_preferred":[
        "Bang Ban"
    ],
    "name:fra_x_preferred":[
        "Bang Ban"
    ],
    "name:jpn_x_preferred":[
        "\u30d0\u30fc\u30f3\u30d0\u30fc\u30f3\u90e1"
    ],
    "name:nan_x_preferred":[
        "Bang Ban K\u016bn"
    ],
    "name:ron_x_preferred":[
        "Districtul Bang Ban"
    ],
    "name:tha_x_preferred":[
        "\u0e2d\u0e33\u0e40\u0e20\u0e2d\u0e1a\u0e32\u0e07\u0e1a\u0e32\u0e25"
    ],
    "name:urd_x_preferred":[
        "\u0628\u0627\u0646\u06af \u0628\u0627\u0646 \u0636\u0644\u0639"
    ],
    "name:vie_x_preferred":[
        "Bang Ban"
    ],
    "qs:name":"Maha Phram",
    "qs:name_adm0":"Thailand",
    "qs:name_adm1":"Phra Nakhon Si Ayutthaya",
    "qs:photos":127,
    "qs:photos_1k":26,
    "qs:photos_9k":1,
    "qs:photos_9r":3,
    "qs:photos_all":127,
    "qs:photos_sr":3,
    "qs:placetype":"Town",
    "qs:pop_sr":"0",
    "wd:wordcount":269,
    "wof:name":"Maha Phram",
    "wof:placetype":"locality"
},
  "geometry": {"coordinates":[100.540013,14.368953],"type":"Point"}
}