{
  "type": "Feature",
  "properties": {
    "iso:country":"TH",
    "qs:name":"Maha Phram",
    "qs:name_adm0":"Thailand",
    "qs:name_adm1":"Phra Nakhon Si Ayutthaya",
    "qs:photos":127,
    "qs:photos_1k":26,
    "qs:photos_9k":1,
    "qs:photos_9r":3,
    "qs:photos_all":127,
    "qs:photos_sr":3,
    "qs:placetype":"Town",
    "qs:pop_sr":"0",
    "wd:wordcount":269,
    "wof:name":"Maha Phram",
    "wof:placetype":"locality"
},
  "geometry": {"coordinates":[100.540013,14.368953],"type":"Point"}
}