{
  "type": "Feature",
  "properties": {
    "gn:admin1_code":"25",
    "gn:asciiname":"Ban Pa Mao Tai",
    "gn:country_code":"TH",
    "gn:dem":168,
    "gn:feature_class":"P",
    "gn:feature_code":"PPL",
    "gn:name":"Ban Pa Mao Tai",
    "gn:population":0,
    "gn:timezone":"Asia/Bangkok",
    "iso:country":"TH",
    "name:tha_x_preferred":[
        "\u0e1a\u0e49\u0e32\u0e19\u0e1b\u0e48\u0e32\u0e40\u0e21\u0e49\u0e32\u0e43\u0e15\u0e49"
    ],
    "wof:name":"Ban Pa Mao Tai",
    "wof:placetype":"locality"
},
  "geometry": {"coordinates":[103.55425,15.99844],"type":"Point"}
}