{
  "type": "Feature",
  "properties": {
    "gn:admin1_code":"7.0",
    "gn:asciiname":"Ban Daen Chon",
    "gn:country_code":"TH",
    "gn:dem":177,
    "gn:feature_class":"P",
    "gn:feature_code":"PPL",
    "gn:name":"Ban Daen Chon",
    "gn:population":0,
    "gn:timezone":"Asia/Bangkok",
    "iso:country":"TH",
    "name:tha_x_preferred":[
        "\u0e1a\u0e49\u0e32\u0e19\u0e41\u0e14\u0e19\u0e0a\u0e25"
    ],
    "wof:name":"Ban Daen Chon",
    "wof:placetype":"locality"
},
  "geometry": {"coordinates":[100.18164,18.14022000000001],"type":"Point"}
}