{
  "type": "Feature",
  "properties": {
    "gn:admin1_code":"57.0",
    "gn:asciiname":"Ban Don Tao Lao",
    "gn:country_code":"TH",
    "gn:dem":9,
    "gn:feature_class":"P",
    "gn:feature_code":"PPL",
    "gn:name":"Ban Don Tao Lao",
    "gn:population":0,
    "gn:timezone":"Asia/Bangkok",
    "iso:country":"TH",
    "name:tha_x_preferred":[
        "\u0e1a\u0e49\u0e32\u0e19\u0e14\u0e2d\u0e19\u0e40\u0e15\u0e32\u0e40\u0e2b\u0e25\u0e49\u0e32"
    ],
    "wof:name":"Ban Don Tao Lao",
    "wof:placetype":"locality"
},
  "geometry": {"coordinates":[99.97075,12.22606],"type":"Point"}
}