{
  "type": "Feature",
  "properties": {
    "gn:admin1_code":"46.0",
    "gn:asciiname":"Ban Pak Ruam",
    "gn:country_code":"TH",
    "gn:dem":97,
    "gn:feature_class":"P",
    "gn:feature_code":"PPL",
    "gn:name":"Ban Pak Ruam",
    "gn:population":0,
    "gn:timezone":"Asia/Bangkok",
    "iso:country":"TH",
    "name:tha_x_preferred":[
        "\u0e1a\u0e49\u0e32\u0e19\u0e1b\u0e32\u0e01\u0e23\u0e48\u0e27\u0e21"
    ],
    "wof:name":"Ban Pak Ruam",
    "wof:placetype":"locality"
},
  "geometry": {"coordinates":[101.08489,13.0365],"type":"Point"}
}