{
  "type": "Feature",
  "properties": {
    "gn:admin1_code":"76.0",
    "gn:asciiname":"Ban Na Phen",
    "gn:country_code":"TH",
    "gn:dem":177,
    "gn:feature_class":"P",
    "gn:feature_code":"PPL",
    "gn:name":"Ban Na Phen",
    "gn:population":0,
    "gn:timezone":"Asia/Bangkok",
    "iso:country":"TH",
    "name:tha_x_preferred":[
        "\u0e1a\u0e49\u0e32\u0e19\u0e19\u0e32\u0e40\u0e1e\u0e47\u0e0d"
    ],
    "name:und_x_variant":[
        "Naphaen",
        "Ban Na Phaen",
        "Ban Napaen",
        "Ban Nong Paen",
        "Ban Na Phen"
    ],
    "wof:name":"Ban Na Phen",
    "wof:placetype":"locality"
},
  "geometry": {"coordinates":[103.06814,16.97047],"type":"Point"}
}