{
  "type": "Feature",
  "properties": {
    "gn:admin1_code":"33.0",
    "gn:asciiname":"Ban Chak Si",
    "gn:country_code":"TH",
    "gn:dem":15,
    "gn:feature_class":"P",
    "gn:feature_code":"PPL",
    "gn:name":"Ban Chak Si",
    "gn:population":0,
    "gn:timezone":"Asia/Bangkok",
    "iso:country":"TH",
    "name:tha_x_preferred":[
        "\u0e1a\u0e49\u0e32\u0e19\u0e08\u0e31\u0e01\u0e23\u0e2a\u0e35\u0e2b\u0e4c"
    ],
    "wof:name":"Ban Chak Si",
    "wof:placetype":"locality"
},
  "geometry": {"coordinates":[100.40706,14.83272],"type":"Point"}
}