{
  "type": "Feature",
  "properties": {
    "gn:admin1_code":"28",
    "gn:asciiname":"Ban Suk Sawat",
    "gn:country_code":"TH",
    "gn:dem":150,
    "gn:feature_class":"P",
    "gn:feature_code":"PPL",
    "gn:name":"Ban Suk Sawat",
    "gn:population":0,
    "gn:timezone":"Asia/Bangkok",
    "iso:country":"TH",
    "name:tha_x_preferred":[
        "\u0e1a\u0e49\u0e32\u0e19\u0e2a\u0e38\u0e02\u0e2a\u0e27\u0e31\u0e2a\u0e14\u0e34\u0e4c"
    ],
    "wof:name":"Ban Suk Sawat",
    "wof:placetype":"locality"
},
  "geometry": {"coordinates":[103.16819,15.0665],"type":"Point"}
}