{
  "type": "Feature",
  "properties": {
    "gn:admin1_code":"16.0",
    "gn:asciiname":"Ban Phai Ko",
    "gn:country_code":"TH",
    "gn:dem":26,
    "gn:feature_class":"P",
    "gn:feature_code":"PPL",
    "gn:name":"Ban Phai Ko",
    "gn:population":0,
    "gn:timezone":"Asia/Bangkok",
    "iso:country":"TH",
    "name:tha_x_preferred":[
        "\u0e1a\u0e49\u0e32\u0e19\u0e44\u0e1c\u0e48\u0e40\u0e01\u0e32\u0e30"
    ],
    "wof:name":"Ban Phai Ko",
    "wof:placetype":"locality"
},
  "geometry": {"coordinates":[100.32178,15.82614],"type":"Point"}
}