{
  "type": "Feature",
  "properties": {
    "gn:admin1_code":"60.0",
    "gn:asciiname":"Ban Yan Yao",
    "gn:country_code":"TH",
    "gn:dem":16,
    "gn:feature_class":"P",
    "gn:feature_code":"PPL",
    "gn:name":"Ban Yan Yao",
    "gn:population":0,
    "gn:timezone":"Asia/Bangkok",
    "iso:country":"TH",
    "name:tha_x_preferred":[
        "\u0e1a\u0e49\u0e32\u0e19\u0e22\u0e48\u0e32\u0e19\u0e22\u0e32\u0e27"
    ],
    "wof:name":"Ban Yan Yao",
    "wof:placetype":"locality"
},
  "geometry": {"coordinates":[99.0021,9.03483],"type":"Point"}
}