{
  "type": "Feature",
  "properties": {
    "gn:admin1_code":"49.0",
    "gn:asciiname":"Ban Hat Taphao",
    "gn:country_code":"TH",
    "gn:dem":12,
    "gn:feature_class":"P",
    "gn:feature_code":"PPL",
    "gn:name":"Ban Hat Taphao",
    "gn:population":0,
    "gn:timezone":"Asia/Bangkok",
    "iso:country":"TH",
    "name:tha_x_preferred":[
        "\u0e1a\u0e49\u0e32\u0e19\u0e2b\u0e32\u0e14\u0e15\u0e30\u0e40\u0e20\u0e32"
    ],
    "wof:name":"Ban Hat Taphao",
    "wof:placetype":"locality"
},
  "geometry": {"coordinates":[102.53519,11.65061],"type":"Point"}
}