{
  "type": "Feature",
  "properties": {
    "gn:admin1_code":"72.0",
    "gn:asciiname":"Ban Lao Fai",
    "gn:country_code":"TH",
    "gn:dem":188,
    "gn:feature_class":"P",
    "gn:feature_code":"PPL",
    "gn:name":"Ban Lao Fai",
    "gn:population":0,
    "gn:timezone":"Asia/Bangkok",
    "iso:country":"TH",
    "name:tha_x_preferred":[
        "\u0e1a\u0e49\u0e32\u0e19\u0e40\u0e2b\u0e25\u0e48\u0e32\u0e1d\u0e49\u0e32\u0e22"
    ],
    "wof:name":"Ban Lao Fai",
    "wof:placetype":"locality"
},
  "geometry": {"coordinates":[104.30503,16.11153],"type":"Point"}
}