{
  "type": "Feature",
  "properties": {
    "gn:admin1_code":"23.0",
    "gn:asciiname":"Ban Song Yang",
    "gn:country_code":"TH",
    "gn:dem":147,
    "gn:feature_class":"P",
    "gn:feature_code":"PPL",
    "gn:name":"Ban Song Yang",
    "gn:population":0,
    "gn:timezone":"Asia/Bangkok",
    "iso:country":"TH",
    "name:tha_x_preferred":[
        "\u0e1a\u0e49\u0e32\u0e19\u0e2a\u0e07\u0e22\u0e32\u0e07"
    ],
    "wof:name":"Ban Song Yang",
    "wof:placetype":"locality"
},
  "geometry": {"coordinates":[103.52864,16.30011],"type":"Point"}
}