{
  "type": "Feature",
  "properties": {
    "gn:admin1_code":"60.0",
    "gn:asciiname":"Ban Ya Plong",
    "gn:country_code":"TH",
    "gn:dem":61,
    "gn:feature_class":"P",
    "gn:feature_code":"PPL",
    "gn:name":"Ban Ya Plong",
    "gn:population":0,
    "gn:timezone":"Asia/Bangkok",
    "iso:country":"TH",
    "name:tha_x_preferred":[
        "\u0e1a\u0e49\u0e32\u0e19\u0e2b\u0e0d\u0e49\u0e32\u0e1b\u0e25\u0e49\u0e2d\u0e07"
    ],
    "name:und_x_variant":[
        "Ya Plaung",
        "Ban Hya Plohng",
        "Ban Ya Plong"
    ],
    "wof:name":"Ban Ya Plong",
    "wof:placetype":"locality"
},
  "geometry": {"coordinates":[98.55706000000001,8.89525],"type":"Point"}
}