{
  "type": "Feature",
  "properties": {
    "gn:admin1_code":"74",
    "gn:asciiname":"Ban Pa Pao",
    "gn:country_code":"TH",
    "gn:dem":21,
    "gn:feature_class":"P",
    "gn:feature_code":"PPL",
    "gn:name":"Ban Pa Pao",
    "gn:population":0,
    "gn:timezone":"Asia/Bangkok",
    "iso:country":"TH",
    "name:tha_x_preferred":[
        "\u0e1a\u0e49\u0e32\u0e19\u0e1b\u0e48\u0e32\u0e40\u0e1b\u0e49\u0e32"
    ],
    "wof:name":"Ban Pa Pao",
    "wof:placetype":"locality"
},
  "geometry": {"coordinates":[101.61508000000001,14.07419],"type":"Point"}
}