{
  "type": "Feature",
  "properties": {
    "gn:admin1_code":"50.0",
    "gn:asciiname":"Ban Rang Phayom",
    "gn:country_code":"TH",
    "gn:dem":29,
    "gn:feature_class":"P",
    "gn:feature_code":"PPL",
    "gn:name":"Ban Rang Phayom",
    "gn:population":0,
    "gn:timezone":"Asia/Bangkok",
    "iso:country":"TH",
    "name:tha_x_preferred":[
        "\u0e1a\u0e49\u0e32\u0e19\u0e23\u0e32\u0e07\u0e1e\u0e22\u0e2d\u0e21"
    ],
    "wof:name":"Ban Rang Phayom",
    "wof:placetype":"locality"
},
  "geometry": {"coordinates":[99.68261,13.88053],"type":"Point"}
}