{
  "type": "Feature",
  "properties": {
    "gn:admin1_code":"3.0",
    "gn:asciiname":"Ban I-Ko Cha Li",
    "gn:country_code":"TH",
    "gn:dem":1165,
    "gn:feature_class":"P",
    "gn:feature_code":"PPL",
    "gn:name":"Ban I-Ko Cha Li",
    "gn:population":0,
    "gn:timezone":"Asia/Bangkok",
    "iso:country":"TH",
    "name:tha_x_preferred":[
        "\u0e1a\u0e49\u0e32\u0e19\u0e2d\u0e35\u0e01\u0e49\u0e2d\u0e08\u0e32\u0e25\u0e35\u0e49"
    ],
    "wof:name":"Ban I-Ko Cha Li",
    "wof:placetype":"locality"
},
  "geometry": {"coordinates":[99.79846999999999,20.05169],"type":"Point"}
}