{
  "type": "Feature",
  "properties": {
    "gn:admin1_code":"64.0",
    "gn:asciiname":"Ban Thep Rattana",
    "gn:country_code":"TH",
    "gn:dem":50,
    "gn:feature_class":"P",
    "gn:feature_code":"PPL",
    "gn:name":"Ban Thep Rattana",
    "gn:population":0,
    "gn:timezone":"Asia/Bangkok",
    "iso:country":"TH",
    "name:tha_x_preferred":[
        "\u0e1a\u0e49\u0e32\u0e19\u0e40\u0e17\u0e1e\u0e23\u0e31\u0e15\u0e19\u0e32"
    ],
    "wof:name":"Ban Thep Rattana",
    "wof:placetype":"locality"
},
  "geometry": {"coordinates":[99.58803,8.41708],"type":"Point"}
}