{
  "type": "Feature",
  "properties": {
    "gn:admin1_code":"26.0",
    "gn:asciiname":"Ban Na Yang Klak",
    "gn:country_code":"TH",
    "gn:dem":293,
    "gn:feature_class":"P",
    "gn:feature_code":"PPL",
    "gn:name":"Ban Na Yang Klak",
    "gn:population":0,
    "gn:timezone":"Asia/Bangkok",
    "iso:country":"TH",
    "name:tha_x_preferred":[
        "\u0e1a\u0e49\u0e32\u0e19\u0e19\u0e32\u0e22\u0e32\u0e07\u0e01\u0e25\u0e31\u0e01"
    ],
    "name:und_x_variant":[
        "Na Phang Hak",
        "B\u0101n Na Y\u0101ng Glak",
        "Ban Na Yang Klak"
    ],
    "wof:name":"Ban Na Yang Klak",
    "wof:placetype":"locality"
},
  "geometry": {"coordinates":[101.51117000000001,15.658],"type":"Point"}
}