{
  "type": "Feature",
  "properties": {
    "gn:admin1_code":"68.0",
    "gn:asciiname":"Ban Plak Lam Phan Daeng",
    "gn:country_code":"TH",
    "gn:dem":62,
    "gn:feature_class":"P",
    "gn:feature_code":"PPL",
    "gn:name":"Ban Plak Lam Phan Daeng",
    "gn:population":0,
    "gn:timezone":"Asia/Bangkok",
    "iso:country":"TH",
    "name:tha_x_preferred":[
        "\u0e1a\u0e49\u0e32\u0e19\u0e1b\u0e25\u0e31\u0e01\u0e25\u0e33\u0e1e\u0e31\u0e19\u0e41\u0e14\u0e07"
    ],
    "wof:name":"Ban Plak Lam Phan Daeng",
    "wof:placetype":"locality"
},
  "geometry": {"coordinates":[100.82478,6.50389],"type":"Point"}
}