{
  "type": "Feature",
  "properties": {
    "gn:admin1_code":"6.0",
    "gn:asciiname":"Ban Huai Sala",
    "gn:country_code":"TH",
    "gn:dem":250,
    "gn:feature_class":"P",
    "gn:feature_code":"PPL",
    "gn:name":"Ban Huai Sala",
    "gn:population":0,
    "gn:timezone":"Asia/Bangkok",
    "iso:country":"TH",
    "name:tha_x_preferred":[
        "\u0e1a\u0e49\u0e32\u0e19\u0e2b\u0e49\u0e27\u0e22\u0e28\u0e32\u0e25\u0e32"
    ],
    "wof:name":"Ban Huai Sala",
    "wof:placetype":"locality"
},
  "geometry": {"coordinates":[100.01553,18.66622000000001],"type":"Point"}
}