{
  "type": "Feature",
  "properties": {
    "gn:admin1_code":"3.0",
    "gn:asciiname":"Ban Khrae Yao",
    "gn:country_code":"TH",
    "gn:dem":658,
    "gn:feature_class":"P",
    "gn:feature_code":"PPL",
    "gn:name":"Ban Khrae Yao",
    "gn:population":0,
    "gn:timezone":"Asia/Bangkok",
    "iso:country":"TH",
    "wof:name":"Ban Khrae Yao",
    "wof:placetype":"locality"
},
  "geometry": {"coordinates":[99.56667,19.98333],"type":"Point"}
}