{
  "type": "Feature",
  "properties": {
    "gn:admin1_code":"46.0",
    "gn:asciiname":"Ban Nong Ngulueam",
    "gn:country_code":"TH",
    "gn:dem":34,
    "gn:feature_class":"P",
    "gn:feature_code":"PPL",
    "gn:name":"Ban Nong Ngulueam",
    "gn:population":0,
    "gn:timezone":"Asia/Bangkok",
    "iso:country":"TH",
    "name:tha_x_preferred":[
        "\u0e1a\u0e49\u0e32\u0e19\u0e2b\u0e19\u0e2d\u0e07\u0e07\u0e39\u0e40\u0e2b\u0e25\u0e37\u0e2d\u0e21"
    ],
    "name:und_x_variant":[
        "Ban Nong Ngu Luam"
    ],
    "wof:name":"Ban Nong Ngulueam",
    "wof:placetype":"locality"
},
  "geometry": {"coordinates":[101.28972,13.35825],"type":"Point"}
}