{
  "type": "Feature",
  "properties": {
    "gn:admin1_code":"5.0",
    "gn:asciiname":"Ban San Wilai",
    "gn:country_code":"TH",
    "gn:dem":437,
    "gn:feature_class":"P",
    "gn:feature_code":"PPL",
    "gn:name":"Ban San Wilai",
    "gn:population":0,
    "gn:timezone":"Asia/Bangkok",
    "iso:country":"TH",
    "name:tha_x_preferred":[
        "\u0e1a\u0e49\u0e32\u0e19\u0e2a\u0e31\u0e19\u0e27\u0e34\u0e44\u0e25"
    ],
    "wof:name":"Ban San Wilai",
    "wof:placetype":"locality"
},
  "geometry": {"coordinates":[98.91789,17.956],"type":"Point"}
}