{
  "type": "Feature",
  "properties": {
    "gn:admin1_code":"2.0",
    "gn:asciiname":"Ban Pa Phai",
    "gn:country_code":"TH",
    "gn:dem":734,
    "gn:feature_class":"P",
    "gn:feature_code":"PPL",
    "gn:name":"Ban Pa Phai",
    "gn:population":0,
    "gn:timezone":"Asia/Bangkok",
    "iso:country":"TH",
    "name:tha_x_preferred":[
        "\u0e1a\u0e49\u0e32\u0e19\u0e1b\u0e48\u0e32\u0e44\u0e1c\u0e48"
    ],
    "wof:name":"Ban Pa Phai",
    "wof:placetype":"locality"
},
  "geometry": {"coordinates":[98.63678,19.55881],"type":"Point"}
}