{
  "type": "Feature",
  "properties": {
    "gn:admin1_code":"75.0",
    "gn:asciiname":"Ban Wari Udom",
    "gn:country_code":"TH",
    "gn:dem":142,
    "gn:feature_class":"P",
    "gn:feature_code":"PPL",
    "gn:name":"Ban Wari Udom",
    "gn:population":0,
    "gn:timezone":"Asia/Bangkok",
    "iso:country":"TH",
    "name:tha_x_preferred":[
        "\u0e1a\u0e49\u0e32\u0e19\u0e27\u0e32\u0e23\u0e35\u0e2d\u0e38\u0e14\u0e21"
    ],
    "wof:name":"Ban Wari Udom",
    "wof:placetype":"locality"
},
  "geometry": {"coordinates":[105.06317,14.85217],"type":"Point"}
}