{
  "type": "Feature",
  "properties": {
    "iso:country":"TH",
    "qs:name":"Sateng",
    "qs:name_adm0":"Thailand",
    "qs:name_adm1":"Yala",
    "qs:photos":244,
    "qs:photos_1k":49,
    "qs:photos_9k":1,
    "qs:photos_9r":4,
    "qs:photos_all":244,
    "qs:photos_sr":4,
    "qs:placetype":"Town",
    "qs:pop_sr":"0",
    "wof:name":"Sateng",
    "wof:placetype":"locality"
},
  "geometry": {"coordinates":[101.28699899999999,6.555833],"type":"Point"}
}