{
  "type": "Feature",
  "properties": {
    "gn:admin1_code":"68.0",
    "gn:asciiname":"Ban Phang Luek",
    "gn:country_code":"TH",
    "gn:dem":10,
    "gn:feature_class":"P",
    "gn:feature_code":"PPL",
    "gn:name":"Ban Phang Luek",
    "gn:population":0,
    "gn:timezone":"Asia/Bangkok",
    "iso:country":"TH",
    "name:tha_x_preferred":[
        "\u0e1a\u0e49\u0e32\u0e19\u0e1e\u0e31\u0e07\u0e25\u0e36\u0e01"
    ],
    "wof:name":"Ban Phang Luek",
    "wof:placetype":"locality"
},
  "geometry": {"coordinates":[100.43553,7.4875],"type":"Point"}
}