{
  "type": "Feature",
  "properties": {
    "gn:admin1_code":"73.0",
    "gn:asciiname":"Ban Hua Bueng Tha",
    "gn:country_code":"TH",
    "gn:dem":144,
    "gn:feature_class":"P",
    "gn:feature_code":"PPL",
    "gn:name":"Ban Hua Bueng Tha",
    "gn:population":0,
    "gn:timezone":"Asia/Bangkok",
    "iso:country":"TH",
    "name:tha_x_preferred":[
        "Ban Hua Bueng Tha"
    ],
    "name:tha_x_variant":[
        "\u0e1a\u0e49\u0e32\u0e19\u0e2b\u0e31\u0e27\u0e1a\u0e36\u0e07\u0e17\u0e48\u0e32"
    ],
    "wof:name":"Ban Hua Bueng Tha",
    "wof:placetype":"locality"
},
  "geometry": {"coordinates":[104.72761,16.95683],"type":"Point"}
}