{
  "type": "Feature",
  "properties": {
    "gn:admin1_code":"0.0",
    "gn:asciiname":"Ban Nam Om",
    "gn:country_code":"TH",
    "gn:dem":306,
    "gn:feature_class":"P",
    "gn:feature_code":"PPL",
    "gn:name":"Ban Nam Om",
    "gn:population":0,
    "gn:timezone":"Asia/Bangkok",
    "iso:country":"TH",
    "wof:name":"Ban Nam Om",
    "wof:placetype":"locality"
},
  "geometry": {"coordinates":[101.71666999999999,17.16667],"type":"Point"}
}