{
  "type": "Feature",
  "properties": {
    "gn:admin1_code":"63.0",
    "gn:asciiname":"Ban Khuan Muang",
    "gn:country_code":"TH",
    "gn:dem":41,
    "gn:feature_class":"P",
    "gn:feature_code":"PPL",
    "gn:name":"Ban Khuan Muang",
    "gn:population":0,
    "gn:timezone":"Asia/Bangkok",
    "iso:country":"TH",
    "name:tha_x_preferred":[
        "\u0e1a\u0e49\u0e32\u0e19\u0e04\u0e27\u0e19\u0e21\u0e48\u0e27\u0e07"
    ],
    "name:und_x_variant":[
        "Ban Hu Khanan",
        "Ban Hua Khuan",
        "Ban Khuan Muang"
    ],
    "wof:name":"Ban Khuan Muang",
    "wof:placetype":"locality"
},
  "geometry": {"coordinates":[99.059,8.04253],"type":"Point"}
}