{
  "type": "Feature",
  "properties": {
    "gn:admin1_code":"16.0",
    "gn:asciiname":"Ban Lam Charoen",
    "gn:country_code":"TH",
    "gn:dem":70,
    "gn:feature_class":"P",
    "gn:feature_code":"PPL",
    "gn:name":"Ban Lam Charoen",
    "gn:population":0,
    "gn:timezone":"Asia/Bangkok",
    "iso:country":"TH",
    "name:tha_x_preferred":[
        "\u0e1a\u0e49\u0e32\u0e19\u0e25\u0e49\u0e33\u0e40\u0e08\u0e23\u0e34\u0e0d"
    ],
    "wof:name":"Ban Lam Charoen",
    "wof:placetype":"locality"
},
  "geometry": {"coordinates":[100.44683000000001,15.48867],"type":"Point"}
}