{
  "type": "Feature",
  "properties": {
    "gn:admin1_code":"14.0",
    "gn:asciiname":"Ban Rai Ruang Thong",
    "gn:country_code":"TH",
    "gn:dem":95,
    "gn:feature_class":"P",
    "gn:feature_code":"PPL",
    "gn:name":"Ban Rai Ruang Thong",
    "gn:population":0,
    "gn:timezone":"Asia/Bangkok",
    "iso:country":"TH",
    "wof:name":"Ban Rai Ruang Thong",
    "wof:placetype":"locality"
},
  "geometry": {"coordinates":[101.08333,16.03333],"type":"Point"}
}