{
  "type": "Feature",
  "properties": {
    "gn:admin1_code":"27",
    "gn:asciiname":"Ban Kraton",
    "gn:country_code":"TH",
    "gn:dem":157,
    "gn:feature_class":"P",
    "gn:feature_code":"PPL",
    "gn:name":"Ban Kraton",
    "gn:population":0,
    "gn:timezone":"Asia/Bangkok",
    "iso:country":"TH",
    "name:tha_x_preferred":[
        "\u0e1a\u0e49\u0e32\u0e19\u0e01\u0e23\u0e30\u0e42\u0e15\u0e19"
    ],
    "wof:name":"Ban Kraton",
    "wof:placetype":"locality"
},
  "geometry": {"coordinates":[102.71669,15.54125],"type":"Point"}
}