{
  "type": "Feature",
  "properties": {
    "gn:admin1_code":"2.0",
    "gn:asciiname":"Ban Mai Nong Hoi",
    "gn:country_code":"TH",
    "gn:dem":337,
    "gn:feature_class":"P",
    "gn:feature_code":"PPL",
    "gn:name":"Ban Mai Nong Hoi",
    "gn:population":0,
    "gn:timezone":"Asia/Bangkok",
    "iso:country":"TH",
    "name:tha_x_preferred":[
        "\u0e1a\u0e49\u0e32\u0e19\u0e43\u0e2b\u0e21\u0e48\u0e2b\u0e19\u0e2d\u0e07\u0e2b\u0e2d\u0e22"
    ],
    "name:und_x_variant":[
        "Ban Nong Hoi",
        "Ban Nong Ho",
        "Ban Mai Nong Hoi"
    ],
    "wof:lang_x_official":[
        "tha"
    ],
    "wof:lang_x_spoken":[
        "tha"
    ],
    "wof:name":"Ban Mai Nong Hoi",
    "wof:placetype":"locality"
},
  "geometry": {"coordinates":[98.79628,18.536],"type":"Point"}
}