{
  "type": "Feature",
  "properties": {
    "gn:admin1_code":"12.0",
    "gn:asciiname":"Ban Pa Khanun",
    "gn:country_code":"TH",
    "gn:dem":168,
    "gn:feature_class":"P",
    "gn:feature_code":"PPL",
    "gn:name":"Ban Pa Khanun",
    "gn:population":0,
    "gn:timezone":"Asia/Bangkok",
    "iso:country":"TH",
    "name:tha_x_preferred":[
        "\u0e1a\u0e49\u0e32\u0e19\u0e1b\u0e48\u0e32\u0e02\u0e19\u0e38\u0e19"
    ],
    "wof:name":"Ban Pa Khanun",
    "wof:placetype":"locality"
},
  "geometry": {"coordinates":[100.47169,17.08002999999999],"type":"Point"}
}