{
  "type": "Feature",
  "properties": {
    "gn:admin1_code":"3.0",
    "gn:asciiname":"Ban Khrai",
    "gn:country_code":"TH",
    "gn:dem":419,
    "gn:feature_class":"P",
    "gn:feature_code":"PPL",
    "gn:name":"Ban Khrai",
    "gn:population":0,
    "gn:timezone":"Asia/Bangkok",
    "iso:country":"TH",
    "name:nld_x_preferred":[
        "Huai Khrai"
    ],
    "name:tha_x_preferred":[
        "\u0e1a\u0e49\u0e32\u0e19\u0e44\u0e04\u0e23\u0e49"
    ],
    "name:und_x_variant":[
        "B\u0101n Kr\u0101i",
        "Ban Huai Khrai",
        "Ban Khrai"
    ],
    "wof:name":"Ban Khrai",
    "wof:placetype":"locality"
},
  "geometry": {"coordinates":[100.294,19.72531],"type":"Point"}
}