{
  "type": "Feature",
  "properties": {
    "gn:admin1_code":"73.0",
    "gn:asciiname":"Ban Phon Sawang",
    "gn:country_code":"TH",
    "gn:dem":169,
    "gn:feature_class":"P",
    "gn:feature_code":"PPL",
    "gn:name":"Ban Phon Sawang",
    "gn:population":0,
    "gn:timezone":"Asia/Bangkok",
    "iso:country":"TH",
    "name:tha_x_preferred":[
        "\u0e1a\u0e49\u0e32\u0e19\u0e42\u0e1e\u0e19\u0e2a\u0e27\u0e48\u0e32\u0e07"
    ],
    "wof:name":"Ban Phon Sawang",
    "wof:placetype":"locality"
},
  "geometry": {"coordinates":[104.48678,17.05331],"type":"Point"}
}