{
  "type": "Feature",
  "properties": {
    "gn:admin1_code":"26.0",
    "gn:asciiname":"Ban Lat Nuea",
    "gn:country_code":"TH",
    "gn:dem":273,
    "gn:feature_class":"P",
    "gn:feature_code":"PPL",
    "gn:name":"Ban Lat Nuea",
    "gn:population":0,
    "gn:timezone":"Asia/Bangkok",
    "iso:country":"TH",
    "name:tha_x_preferred":[
        "\u0e1a\u0e49\u0e32\u0e19\u0e25\u0e32\u0e14\u0e40\u0e2b\u0e19\u0e37\u0e2d"
    ],
    "name:und_x_variant":[
        "Ban Lat Nua"
    ],
    "wof:name":"Ban Lat Nuea",
    "wof:placetype":"locality"
},
  "geometry": {"coordinates":[101.80097000000001,16.1205],"type":"Point"}
}