{
  "type": "Feature",
  "properties": {
    "gn:admin1_code":"26.0",
    "gn:asciiname":"Ban Lae On Son",
    "gn:country_code":"TH",
    "gn:dem":483,
    "gn:feature_class":"P",
    "gn:feature_code":"PPL",
    "gn:name":"Ban Lae On Son",
    "gn:population":0,
    "gn:timezone":"Asia/Bangkok",
    "iso:country":"TH",
    "name:tha_x_preferred":[
        "\u0e1a\u0e49\u0e32\u0e19\u0e41\u0e2b\u0e25\u0e2d\u0e2d\u0e19\u0e0b\u0e2d\u0e19"
    ],
    "wof:name":"Ban Lae On Son",
    "wof:placetype":"locality"
},
  "geometry": {"coordinates":[102.03456,16.12461],"type":"Point"}
}