{
  "type": "Feature",
  "properties": {
    "gn:admin1_code":"61.0",
    "gn:asciiname":"Ban Ko Pan Yi",
    "gn:country_code":"TH",
    "gn:dem":6,
    "gn:feature_class":"P",
    "gn:feature_code":"PPL",
    "gn:name":"Ban Ko Pan Yi",
    "gn:population":0,
    "gn:timezone":"Asia/Bangkok",
    "iso:country":"TH",
    "name:tha_x_preferred":[
        "\u0e1a\u0e49\u0e32\u0e19\u0e40\u0e01\u0e32\u0e30\u0e1b\u0e31\u0e19\u0e2b\u0e22\u0e35"
    ],
    "wof:name":"Ban Ko Pan Yi",
    "wof:placetype":"locality"
},
  "geometry": {"coordinates":[98.50322,8.33619],"type":"Point"}
}