{
  "type": "Feature",
  "properties": {
    "gn:admin1_code":"64.0",
    "gn:asciiname":"Ban Khan Bet",
    "gn:country_code":"TH",
    "gn:dem":68,
    "gn:feature_class":"P",
    "gn:feature_code":"PPL",
    "gn:name":"Ban Khan Bet",
    "gn:population":0,
    "gn:timezone":"Asia/Bangkok",
    "iso:country":"TH",
    "name:tha_x_preferred":[
        "\u0e1a\u0e49\u0e32\u0e19\u0e04\u0e31\u0e19\u0e40\u0e1a\u0e47\u0e14"
    ],
    "wof:name":"Ban Khan Bet",
    "wof:placetype":"locality"
},
  "geometry": {"coordinates":[99.75839000000001,8.36744],"type":"Point"}
}