{
  "type": "Feature",
  "properties": {
    "gn:admin1_code":"5.0",
    "gn:asciiname":"Ban Chiwit Mai",
    "gn:country_code":"TH",
    "gn:dem":442,
    "gn:feature_class":"P",
    "gn:feature_code":"PPL",
    "gn:name":"Ban Chiwit Mai",
    "gn:population":0,
    "gn:timezone":"Asia/Bangkok",
    "iso:country":"TH",
    "name:tha_x_preferred":[
        "\u0e1a\u0e49\u0e32\u0e19\u0e0a\u0e35\u0e27\u0e34\u0e15\u0e43\u0e2b\u0e21\u0e48"
    ],
    "wof:name":"Ban Chiwit Mai",
    "wof:placetype":"locality"
},
  "geometry": {"coordinates":[98.93853,17.86117],"type":"Point"}
}