{
  "type": "Feature",
  "properties": {
    "gn:admin1_code":"68.0",
    "gn:asciiname":"Ban Bo Daeng",
    "gn:country_code":"TH",
    "gn:dem":9,
    "gn:feature_class":"P",
    "gn:feature_code":"PPL",
    "gn:name":"Ban Bo Daeng",
    "gn:population":0,
    "gn:timezone":"Asia/Bangkok",
    "iso:country":"TH",
    "name:tha_x_preferred":[
        "\u0e1a\u0e49\u0e32\u0e19\u0e1a\u0e48\u0e2d\u0e41\u0e14\u0e07"
    ],
    "name:und_x_variant":[
        "Ban Bodeng",
        "Ban Bo Daeng"
    ],
    "wof:name":"Ban Bo Daeng",
    "wof:placetype":"locality"
},
  "geometry": {"coordinates":[100.46333,7.40511],"type":"Point"}
}