{
  "type": "Feature",
  "properties": {
    "gn:admin1_code":"75.0",
    "gn:asciiname":"Ban Na Khae",
    "gn:country_code":"TH",
    "gn:dem":126,
    "gn:feature_class":"P",
    "gn:feature_code":"PPL",
    "gn:name":"Ban Na Khae",
    "gn:population":0,
    "gn:timezone":"Asia/Bangkok",
    "iso:country":"TH",
    "name:tha_x_preferred":[
        "\u0e1a\u0e49\u0e32\u0e19\u0e19\u0e32\u0e41\u0e04"
    ],
    "wof:name":"Ban Na Khae",
    "wof:placetype":"locality"
},
  "geometry": {"coordinates":[105.00561,15.53319],"type":"Point"}
}