{
  "type": "Feature",
  "properties": {
    "gn:admin1_code":"27",
    "gn:asciiname":"Ban Laen Aen Hao",
    "gn:country_code":"TH",
    "gn:dem":264,
    "gn:feature_class":"P",
    "gn:feature_code":"PPL",
    "gn:name":"Ban Laen Aen Hao",
    "gn:population":0,
    "gn:timezone":"Asia/Bangkok",
    "iso:country":"TH",
    "name:tha_x_preferred":[
        "\u0e1a\u0e49\u0e32\u0e19\u0e41\u0e25\u0e19\u0e14\u0e4c\u0e41\u0e2d\u0e19\u0e14\u0e4c\u0e40\u0e2e\u0e32\u0e2a\u0e4c"
    ],
    "wof:name":"Ban Laen Aen Hao",
    "wof:placetype":"locality"
},
  "geometry": {"coordinates":[102.06341999999999,14.8815],"type":"Point"}
}