{
  "type": "Feature",
  "properties": {
    "gn:admin1_code":"60.0",
    "gn:asciiname":"Ban Boet Bang Yang",
    "gn:country_code":"TH",
    "gn:dem":9,
    "gn:feature_class":"P",
    "gn:feature_code":"PPL",
    "gn:name":"Ban Boet Bang Yang",
    "gn:population":0,
    "gn:timezone":"Asia/Bangkok",
    "iso:country":"TH",
    "name:tha_x_preferred":[
        "\u0e1a\u0e49\u0e32\u0e19\u0e40\u0e1a\u0e34\u0e14\u0e1a\u0e32\u0e07\u0e22\u0e32\u0e07"
    ],
    "wof:name":"Ban Boet Bang Yang",
    "wof:placetype":"locality"
},
  "geometry": {"coordinates":[99.29128,9.1595],"type":"Point"}
}