{
  "type": "Feature",
  "properties": {
    "iso:country":"TH",
    "name:ceb_x_preferred":[
        "Kao"
    ],
    "name:fas_x_preferred":[
        "\u06a9\u0627\u0626\u0648"
    ],
    "name:fra_x_preferred":[
        "Kao"
    ],
    "name:heb_x_preferred":[
        "\u05e7\u05d0\u05d5"
    ],
    "name:rus_x_preferred":[
        "\u041a\u0430\u043e"
    ],
    "name:slk_x_preferred":[
        "Kao"
    ],
    "name:swa_x_preferred":[
        "Mto Kao"
    ],
    "name:swe_x_preferred":[
        "Kao"
    ],
    "qs:name":"Kao",
    "qs:name_adm0":"Thailand",
    "qs:name_adm1":"Chachoengsao",
    "qs:photos":10,
    "qs:photos_1k":2,
    "qs:photos_9k":1,
    "qs:photos_9r":1,
    "qs:photos_all":10,
    "qs:photos_sr":1,
    "qs:placetype":"Town",
    "qs:pop_sr":"0",
    "wd:wordcount":207,
    "wof:name":"Kao",
    "wof:placetype":"locality"
},
  "geometry": {"coordinates":[101.3139245,13.719182],"type":"Point"}
}