{
  "type": "Feature",
  "properties": {
    "gn:admin1_code":"23.0",
    "gn:asciiname":"Ban Kham Maho",
    "gn:country_code":"TH",
    "gn:dem":187,
    "gn:feature_class":"P",
    "gn:feature_code":"PPL",
    "gn:name":"Ban Kham Maho",
    "gn:population":0,
    "gn:timezone":"Asia/Bangkok",
    "iso:country":"TH",
    "name:tha_x_preferred":[
        "\u0e1a\u0e49\u0e32\u0e19\u0e04\u0e33\u0e21\u0e30\u0e42\u0e2e"
    ],
    "wof:name":"Ban Kham Maho",
    "wof:placetype":"locality"
},
  "geometry": {"coordinates":[103.19369,16.49867],"type":"Point"}
}