{
  "type": "Feature",
  "properties": {
    "gn:admin1_code":"70.0",
    "gn:asciiname":"Ban Ru Beng",
    "gn:country_code":"TH",
    "gn:dem":85,
    "gn:feature_class":"P",
    "gn:feature_code":"PPL",
    "gn:name":"Ban Ru Beng",
    "gn:population":0,
    "gn:timezone":"Asia/Bangkok",
    "iso:country":"TH",
    "wof:name":"Ban Ru Beng",
    "wof:placetype":"locality"
},
  "geometry": {"coordinates":[101.13333,6.38333],"type":"Point"}
}