{
  "type": "Feature",
  "properties": {
    "gn:admin1_code":"50.0",
    "gn:asciiname":"Ban Khao Chang",
    "gn:country_code":"TH",
    "gn:dem":77,
    "gn:feature_class":"P",
    "gn:feature_code":"PPL",
    "gn:name":"Ban Khao Chang",
    "gn:population":0,
    "gn:timezone":"Asia/Bangkok",
    "iso:country":"TH",
    "name:tha_x_preferred":[
        "\u0e1a\u0e49\u0e32\u0e19\u0e40\u0e02\u0e32\u0e0a\u0e49\u0e32\u0e07"
    ],
    "wof:name":"Ban Khao Chang",
    "wof:placetype":"locality"
},
  "geometry": {"coordinates":[99.06764,14.16522],"type":"Point"}
}