{
  "type": "Feature",
  "properties": {
    "gn:admin1_code":"57.0",
    "gn:asciiname":"Ban Thung Suea Non",
    "gn:country_code":"TH",
    "gn:dem":18,
    "gn:feature_class":"P",
    "gn:feature_code":"PPL",
    "gn:name":"Ban Thung Suea Non",
    "gn:population":0,
    "gn:timezone":"Asia/Bangkok",
    "iso:country":"TH",
    "name:tha_x_preferred":[
        "\u0e1a\u0e49\u0e32\u0e19\u0e17\u0e38\u0e48\u0e07\u0e40\u0e2a\u0e37\u0e2d\u0e19\u0e2d\u0e19"
    ],
    "wof:name":"Ban Thung Suea Non",
    "wof:placetype":"locality"
},
  "geometry": {"coordinates":[99.90919,12.45556],"type":"Point"}
}