{
  "type": "Feature",
  "properties": {
    "gn:admin1_code":"66.0",
    "gn:asciiname":"Ban Khuan Mai",
    "gn:country_code":"TH",
    "gn:dem":24,
    "gn:feature_class":"P",
    "gn:feature_code":"PPL",
    "gn:name":"Ban Khuan Mai",
    "gn:population":0,
    "gn:timezone":"Asia/Bangkok",
    "iso:country":"TH",
    "name:tha_x_preferred":[
        "\u0e1a\u0e49\u0e32\u0e19\u0e04\u0e27\u0e19\u0e43\u0e2b\u0e21\u0e48"
    ],
    "wof:name":"Ban Khuan Mai",
    "wof:placetype":"locality"
},
  "geometry": {"coordinates":[99.98547000000001,7.62803],"type":"Point"}
}