{
  "type": "Feature",
  "properties": {
    "gn:admin1_code":"67.0",
    "gn:asciiname":"Ban Thung Sa Bo",
    "gn:country_code":"TH",
    "gn:dem":5,
    "gn:feature_class":"P",
    "gn:feature_code":"PPL",
    "gn:name":"Ban Thung Sa Bo",
    "gn:population":0,
    "gn:timezone":"Asia/Bangkok",
    "iso:country":"TH",
    "name:tha_x_preferred":[
        "Ban Thung Sa Bo"
    ],
    "name:tha_x_variant":[
        "\u0e1a\u0e49\u0e32\u0e19\u0e17\u0e38\u0e48\u0e07\u0e2a\u0e30\u0e42\u0e1a\u0e4a\u0e30"
    ],
    "wof:name":"Ban Thung Sa Bo",
    "wof:placetype":"locality"
},
  "geometry": {"coordinates":[99.68047,7.02678],"type":"Point"}
}