{
  "type": "Feature",
  "properties": {
    "gn:admin1_code":"73.0",
    "gn:asciiname":"Ban Phanom Thung",
    "gn:country_code":"TH",
    "gn:dem":157,
    "gn:feature_class":"P",
    "gn:feature_code":"PPL",
    "gn:name":"Ban Phanom Thung",
    "gn:population":0,
    "gn:timezone":"Asia/Bangkok",
    "iso:country":"TH",
    "name:tha_x_preferred":[
        "\u0e1a\u0e49\u0e32\u0e19\u0e1e\u0e19\u0e2d\u0e21\u0e17\u0e38\u0e48\u0e07"
    ],
    "name:und_x_variant":[
        "Ban Phanom"
    ],
    "wof:name":"Ban Phanom Thung",
    "wof:placetype":"locality"
},
  "geometry": {"coordinates":[104.42279000000001,17.68481],"type":"Point"}
}