{
  "type": "Feature",
  "properties": {
    "gn:admin1_code":"36",
    "gn:asciiname":"Ban Chawat Khok",
    "gn:country_code":"TH",
    "gn:dem":5,
    "gn:feature_class":"P",
    "gn:feature_code":"PPL",
    "gn:name":"Ban Chawat Khok",
    "gn:population":0,
    "gn:timezone":"Asia/Bangkok",
    "iso:country":"TH",
    "name:tha_x_preferred":[
        "\u0e1a\u0e49\u0e32\u0e19\u0e0a\u0e30\u0e27\u0e32\u0e14\u0e42\u0e04\u0e01"
    ],
    "wof:name":"Ban Chawat Khok",
    "wof:placetype":"locality"
},
  "geometry": {"coordinates":[100.47696999999999,14.16519],"type":"Point"}
}