{
  "type": "Feature",
  "properties": {
    "gn:admin1_code":"51.0",
    "gn:asciiname":"Ban Don Kha",
    "gn:country_code":"TH",
    "gn:dem":13,
    "gn:feature_class":"P",
    "gn:feature_code":"PPL",
    "gn:name":"Ban Don Kha",
    "gn:population":0,
    "gn:timezone":"Asia/Bangkok",
    "iso:country":"TH",
    "name:und_x_variant":[
        "Ban Don Ka",
        "Ban Don Kha"
    ],
    "wof:name":"Ban Don Kha",
    "wof:placetype":"locality"
},
  "geometry": {"coordinates":[99.93333,14.46667],"type":"Point"}
}