{
  "type": "Feature",
  "properties": {
    "gn:admin1_code":"54.0",
    "gn:asciiname":"Ban Tanot Rai",
    "gn:country_code":"TH",
    "gn:dem":6,
    "gn:feature_class":"P",
    "gn:feature_code":"PPL",
    "gn:name":"Ban Tanot Rai",
    "gn:population":0,
    "gn:timezone":"Asia/Bangkok",
    "iso:country":"TH",
    "name:tha_x_preferred":[
        "\u0e1a\u0e49\u0e32\u0e19\u0e15\u0e30\u0e42\u0e2b\u0e19\u0e14\u0e23\u0e32\u0e22"
    ],
    "wof:name":"Ban Tanot Rai",
    "wof:placetype":"locality"
},
  "geometry": {"coordinates":[99.96731,13.47075],"type":"Point"}
}