{
  "type": "Feature",
  "properties": {
    "gn:admin1_code":"18.0",
    "gn:asciiname":"Ban Tha Sawan",
    "gn:country_code":"TH",
    "gn:dem":306,
    "gn:feature_class":"P",
    "gn:feature_code":"PPL",
    "gn:name":"Ban Tha Sawan",
    "gn:population":0,
    "gn:timezone":"Asia/Bangkok",
    "iso:country":"TH",
    "name:tha_x_preferred":[
        "Ban Tha Sawan"
    ],
    "name:tha_x_variant":[
        "\u0e1a\u0e49\u0e32\u0e19\u0e17\u0e48\u0e32\u0e2a\u0e27\u0e23\u0e23\u0e04\u0e4c"
    ],
    "name:und_x_variant":[
        "Ban Nam Suai Tha Sawan"
    ],
    "wof:lang_x_official":[
        "tha"
    ],
    "wof:lang_x_spoken":[
        "tha"
    ],
    "wof:name":"Ban Tha Sawan",
    "wof:placetype":"locality"
},
  "geometry": {"coordinates":[101.93697,17.42272],"type":"Point"}
}