{
  "type": "Feature",
  "properties": {
    "gn:admin1_code":"46.0",
    "gn:asciiname":"Ban Nong Plalai 2",
    "gn:country_code":"TH",
    "gn:dem":31,
    "gn:feature_class":"P",
    "gn:feature_code":"PPL",
    "gn:name":"Ban Nong Plalai 2",
    "gn:population":0,
    "gn:timezone":"Asia/Bangkok",
    "iso:country":"TH",
    "name:tha_x_preferred":[
        "\u0e1a\u0e49\u0e32\u0e19\u0e2b\u0e19\u0e2d\u0e07\u0e1b\u0e25\u0e32\u0e44\u0e2b\u0e25 \u0e2a\u0e2d\u0e07"
    ],
    "name:und_x_variant":[
        "Ban Nong Plalai Song"
    ],
    "wof:name":"Ban Nong Plalai 2",
    "wof:placetype":"locality"
},
  "geometry": {"coordinates":[101.26511000000001,13.391],"type":"Point"}
}