{
  "type": "Feature",
  "properties": {
    "gn:admin1_code":"18.0",
    "gn:asciiname":"Ban Pak Phu",
    "gn:country_code":"TH",
    "gn:dem":243,
    "gn:feature_class":"P",
    "gn:feature_code":"PPL",
    "gn:name":"Ban Pak Phu",
    "gn:population":0,
    "gn:timezone":"Asia/Bangkok",
    "iso:country":"TH",
    "name:tha_x_preferred":[
        "\u0e1a\u0e49\u0e32\u0e19\u0e1b\u0e32\u0e01\u0e20\u0e39"
    ],
    "name:und_x_variant":[
        "Ban Pa Phu",
        "B\u0101n P\u0101p",
        "Ban Pak Phu"
    ],
    "wof:name":"Ban Pak Phu",
    "wof:placetype":"locality"
},
  "geometry": {"coordinates":[101.72592,17.54658],"type":"Point"}
}