{
  "type": "Feature",
  "properties": {
    "gn:admin1_code":"9.0",
    "gn:asciiname":"Ban Song Krasa",
    "gn:country_code":"TH",
    "gn:dem":55,
    "gn:feature_class":"P",
    "gn:feature_code":"PPL",
    "gn:name":"Ban Song Krasa",
    "gn:population":0,
    "gn:timezone":"Asia/Bangkok",
    "iso:country":"TH",
    "name:tha_x_preferred":[
        "\u0e1a\u0e49\u0e32\u0e19\u0e2a\u0e07\u0e01\u0e23\u0e30\u0e2a\u0e32"
    ],
    "wof:name":"Ban Song Krasa",
    "wof:placetype":"locality"
},
  "geometry": {"coordinates":[99.83038999999999,16.76461],"type":"Point"}
}