{
  "type": "Feature",
  "properties": {
    "gn:admin1_code":"0.0",
    "gn:asciiname":"Ban Wa Thon",
    "gn:country_code":"TH",
    "gn:dem":-9999,
    "gn:feature_class":"P",
    "gn:feature_code":"PPL",
    "gn:name":"Ban Wa Thon",
    "gn:population":0,
    "gn:timezone":"Asia/Bangkok",
    "iso:country":"TH",
    "wof:name":"Ban Wa Thon",
    "wof:placetype":"locality"
},
  "geometry": {"coordinates":[99.73333,11.66667],"type":"Point"}
}