{
  "type": "Feature",
  "properties": {
    "gn:admin1_code":"16.0",
    "gn:asciiname":"Ban Noen Tan Sian",
    "gn:country_code":"TH",
    "gn:dem":30,
    "gn:feature_class":"P",
    "gn:feature_code":"PPL",
    "gn:name":"Ban Noen Tan Sian",
    "gn:population":0,
    "gn:timezone":"Asia/Bangkok",
    "iso:country":"TH",
    "name:tha_x_preferred":[
        "\u0e1a\u0e49\u0e32\u0e19\u0e40\u0e19\u0e34\u0e19\u0e15\u0e32\u0e25\u0e40\u0e2a\u0e35\u0e49\u0e22\u0e19"
    ],
    "name:und_x_variant":[
        "Ban Noen Ta Sian",
        "B\u0101n Narn Ta Sian",
        "Ban Noen Tak Sian",
        "Ban Noen Tan Sian"
    ],
    "wof:name":"Ban Noen Tan Sian",
    "wof:placetype":"locality"
},
  "geometry": {"coordinates":[100.44808,15.74889],"type":"Point"}
}