{
  "type": "Feature",
  "properties": {
    "gn:admin1_code":"49.0",
    "gn:asciiname":"Ban Thai Itsalam",
    "gn:country_code":"TH",
    "gn:dem":3,
    "gn:feature_class":"P",
    "gn:feature_code":"PPL",
    "gn:name":"Ban Thai Itsalam",
    "gn:population":0,
    "gn:timezone":"Asia/Bangkok",
    "iso:country":"TH",
    "name:tha_x_preferred":[
        "\u0e1a\u0e49\u0e32\u0e19\u0e44\u0e17\u0e22\u0e2d\u0e34\u0e2a\u0e25\u0e32\u0e21"
    ],
    "wof:name":"Ban Thai Itsalam",
    "wof:placetype":"locality"
},
  "geometry": {"coordinates":[102.46263999999999,12.19222],"type":"Point"}
}