{
  "type": "Feature",
  "properties": {
    "gn:admin1_code":"74",
    "gn:asciiname":"Ban Khlong Hua Suea",
    "gn:country_code":"TH",
    "gn:dem":4,
    "gn:feature_class":"P",
    "gn:feature_code":"PPL",
    "gn:name":"Ban Khlong Hua Suea",
    "gn:population":0,
    "gn:timezone":"Asia/Bangkok",
    "iso:country":"TH",
    "name:tha_x_preferred":[
        "\u0e1a\u0e49\u0e32\u0e19\u0e04\u0e25\u0e2d\u0e07\u0e2b\u0e31\u0e27\u0e40\u0e2a\u0e37\u0e2d"
    ],
    "wof:name":"Ban Khlong Hua Suea",
    "wof:placetype":"locality"
},
  "geometry": {"coordinates":[101.1895,13.89772],"type":"Point"}
}