{
  "type": "Feature",
  "properties": {
    "gn:admin1_code":"25.0",
    "gn:asciiname":"Ban Wang Yao",
    "gn:country_code":"TH",
    "gn:dem":158,
    "gn:feature_class":"P",
    "gn:feature_code":"PPL",
    "gn:name":"Ban Wang Yao",
    "gn:population":0,
    "gn:timezone":"Asia/Bangkok",
    "iso:country":"TH",
    "name:tha_x_preferred":[
        "\u0e1a\u0e49\u0e32\u0e19\u0e27\u0e31\u0e07\u0e22\u0e32\u0e27"
    ],
    "wof:name":"Ban Wang Yao",
    "wof:placetype":"locality"
},
  "geometry": {"coordinates":[104.05094,16.28594],"type":"Point"}
}