{
  "type": "Feature",
  "properties": {
    "gn:admin1_code":"29",
    "gn:asciiname":"Ban Non Khwao",
    "gn:country_code":"TH",
    "gn:dem":134,
    "gn:feature_class":"P",
    "gn:feature_code":"PPL",
    "gn:name":"Ban Non Khwao",
    "gn:population":0,
    "gn:timezone":"Asia/Bangkok",
    "iso:country":"TH",
    "name:tha_x_preferred":[
        "\u0e1a\u0e49\u0e32\u0e19\u0e42\u0e19\u0e19\u0e02\u0e27\u0e32\u0e27"
    ],
    "wof:name":"Ban Non Khwao",
    "wof:placetype":"locality"
},
  "geometry": {"coordinates":[103.77128,15.33272],"type":"Point"}
}