{
  "type": "Feature",
  "properties": {
    "gn:admin1_code":"0.0",
    "gn:asciiname":"Ban Mae Hong Khi",
    "gn:country_code":"TH",
    "gn:dem":649,
    "gn:feature_class":"P",
    "gn:feature_code":"PPL",
    "gn:name":"Ban Mae Hong Khi",
    "gn:population":0,
    "gn:timezone":"Asia/Bangkok",
    "iso:country":"TH",
    "wof:name":"Ban Mae Hong Khi",
    "wof:placetype":"locality"
},
  "geometry": {"coordinates":[98.05,17.81667000000001],"type":"Point"}
}