{
  "type": "Feature",
  "properties": {
    "gn:admin1_code":"32.0",
    "gn:asciiname":"Ban Khok Suk",
    "gn:country_code":"TH",
    "gn:dem":25,
    "gn:feature_class":"P",
    "gn:feature_code":"PPL",
    "gn:name":"Ban Khok Suk",
    "gn:population":0,
    "gn:timezone":"Asia/Bangkok",
    "iso:country":"TH",
    "name:tha_x_preferred":[
        "\u0e1a\u0e49\u0e32\u0e19\u0e42\u0e04\u0e01\u0e2a\u0e38\u0e01"
    ],
    "name:und_x_variant":[
        "Ban Kauk Suk",
        "Ban Khok Suk (1)",
        "Ban Khok Suk"
    ],
    "wof:name":"Ban Khok Suk",
    "wof:placetype":"locality"
},
  "geometry": {"coordinates":[100.01797000000001,15.18689],"type":"Point"}
}