{
  "type": "Feature",
  "properties": {
    "gn:admin1_code":"44.0",
    "gn:asciiname":"Ban Ang Ta Phueng",
    "gn:country_code":"TH",
    "gn:dem":37,
    "gn:feature_class":"P",
    "gn:feature_code":"PPL",
    "gn:name":"Ban Ang Ta Phueng",
    "gn:population":0,
    "gn:timezone":"Asia/Bangkok",
    "iso:country":"TH",
    "name:tha_x_preferred":[
        "\u0e1a\u0e49\u0e32\u0e19\u0e2d\u0e48\u0e32\u0e07\u0e15\u0e32\u0e1c\u0e36\u0e49\u0e07"
    ],
    "wof:name":"Ban Ang Ta Phueng",
    "wof:placetype":"locality"
},
  "geometry": {"coordinates":[101.55672,13.5617],"type":"Point"}
}