{
  "type": "Feature",
  "properties": {
    "gn:admin1_code":"64.0",
    "gn:asciiname":"Ban Thung Na Bon",
    "gn:country_code":"TH",
    "gn:dem":29,
    "gn:feature_class":"P",
    "gn:feature_code":"PPL",
    "gn:name":"Ban Thung Na Bon",
    "gn:population":0,
    "gn:timezone":"Asia/Bangkok",
    "iso:country":"TH",
    "name:tha_x_preferred":[
        "\u0e1a\u0e49\u0e32\u0e19\u0e17\u0e38\u0e48\u0e07\u0e19\u0e32\u0e1a\u0e19"
    ],
    "name:und_x_variant":[
        "Ban Thung Na Nua"
    ],
    "wof:name":"Ban Thung Na Bon",
    "wof:placetype":"locality"
},
  "geometry": {"coordinates":[99.93528000000001,7.88681],"type":"Point"}
}