{
  "type": "Feature",
  "properties": {
    "gn:admin1_code":"72.0",
    "gn:asciiname":"Ban Muang Khai",
    "gn:country_code":"TH",
    "gn:dem":136,
    "gn:feature_class":"P",
    "gn:feature_code":"PPL",
    "gn:name":"Ban Muang Khai",
    "gn:population":0,
    "gn:timezone":"Asia/Bangkok",
    "iso:country":"TH",
    "name:tha_x_preferred":[
        "\u0e1a\u0e49\u0e32\u0e19\u0e21\u0e48\u0e27\u0e07\u0e44\u0e02\u0e48"
    ],
    "wof:name":"Ban Muang Khai",
    "wof:placetype":"locality"
},
  "geometry": {"coordinates":[104.36405999999999,15.83242],"type":"Point"}
}