{
  "type": "Feature",
  "properties": {
    "gn:admin1_code":"0.0",
    "gn:asciiname":"Ban Yang Thi Kayae",
    "gn:country_code":"TH",
    "gn:dem":1319,
    "gn:feature_class":"P",
    "gn:feature_code":"PPL",
    "gn:name":"Ban Yang Thi Kayae",
    "gn:population":0,
    "gn:timezone":"Asia/Bangkok",
    "iso:country":"TH",
    "wof:lang_x_official":[
        "tha"
    ],
    "wof:lang_x_spoken":[
        "tha"
    ],
    "wof:name":"Ban Yang Thi Kayae",
    "wof:placetype":"locality"
},
  "geometry": {"coordinates":[98.15000000000001,17.81667000000001],"type":"Point"}
}