{
  "type": "Feature",
  "properties": {
    "gn:admin1_code":"11.0",
    "gn:asciiname":"Ban Khok Matum",
    "gn:country_code":"TH",
    "gn:dem":57,
    "gn:feature_class":"P",
    "gn:feature_code":"PPL",
    "gn:name":"Ban Khok Matum",
    "gn:population":0,
    "gn:timezone":"Asia/Bangkok",
    "iso:country":"TH",
    "name:tha_x_preferred":[
        "\u0e1a\u0e49\u0e32\u0e19\u0e42\u0e04\u0e01\u0e21\u0e30\u0e15\u0e39\u0e21"
    ],
    "wof:name":"Ban Khok Matum",
    "wof:placetype":"locality"
},
  "geometry": {"coordinates":[99.84667,16.62714],"type":"Point"}
}