{
  "type": "Feature",
  "properties": {
    "gn:admin1_code":"48.0",
    "gn:asciiname":"Ban Thung Anong",
    "gn:country_code":"TH",
    "gn:dem":8,
    "gn:feature_class":"P",
    "gn:feature_code":"PPL",
    "gn:name":"Ban Thung Anong",
    "gn:population":0,
    "gn:timezone":"Asia/Bangkok",
    "iso:country":"TH",
    "name:tha_x_preferred":[
        "\u0e1a\u0e49\u0e32\u0e19\u0e17\u0e38\u0e48\u0e07\u0e2d\u0e19\u0e07\u0e04\u0e4c"
    ],
    "wof:name":"Ban Thung Anong",
    "wof:placetype":"locality"
},
  "geometry": {"coordinates":[101.99422,12.63561],"type":"Point"}
}