{
  "type": "Feature",
  "properties": {
    "gn:admin1_code":"26.0",
    "gn:asciiname":"Ban Nokiang Mai",
    "gn:country_code":"TH",
    "gn:dem":231,
    "gn:feature_class":"P",
    "gn:feature_code":"PPL",
    "gn:name":"Ban Nokiang Mai",
    "gn:population":0,
    "gn:timezone":"Asia/Bangkok",
    "iso:country":"TH",
    "name:tha_x_preferred":[
        "\u0e1a\u0e49\u0e32\u0e19\u0e19\u0e01\u0e40\u0e2d\u0e35\u0e49\u0e22\u0e07\u0e43\u0e2b\u0e21\u0e48"
    ],
    "wof:name":"Ban Nokiang Mai",
    "wof:placetype":"locality"
},
  "geometry": {"coordinates":[101.9905,16.29944],"type":"Point"}
}