{
  "type": "Feature",
  "properties": {
    "gn:admin1_code":"31.0",
    "gn:asciiname":"Ban Pa Lu Ka Na Ko",
    "gn:country_code":"TH",
    "gn:dem":16,
    "gn:feature_class":"P",
    "gn:feature_code":"PPL",
    "gn:name":"Ban Pa Lu Ka Na Ko",
    "gn:population":0,
    "gn:timezone":"Asia/Bangkok",
    "iso:country":"TH",
    "name:tha_x_preferred":[
        "\u0e1a\u0e49\u0e32\u0e19\u0e1b\u0e30\u0e25\u0e38\u0e01\u0e32\u0e19\u0e32\u0e01\u0e2d"
    ],
    "name:und_x_variant":[
        "Ban Pa Lu Kha"
    ],
    "wof:name":"Ban Pa Lu Ka Na Ko",
    "wof:placetype":"locality"
},
  "geometry": {"coordinates":[101.669,6.50042],"type":"Point"}
}