{
  "type": "Feature",
  "properties": {
    "gn:admin1_code":"1.0",
    "gn:asciiname":"Ban Tha Song Khwae",
    "gn:country_code":"TH",
    "gn:dem":297,
    "gn:feature_class":"P",
    "gn:feature_code":"PPL",
    "gn:name":"Ban Tha Song Khwae",
    "gn:population":0,
    "gn:timezone":"Asia/Bangkok",
    "iso:country":"TH",
    "name:tha_x_preferred":[
        "\u0e1a\u0e49\u0e32\u0e19\u0e17\u0e48\u0e32\u0e2a\u0e2d\u0e07\u0e41\u0e04\u0e27"
    ],
    "name:und_x_variant":[
        "Ban Tha Song Khae",
        "Ban Tha Song Khwae"
    ],
    "wof:name":"Ban Tha Song Khwae",
    "wof:placetype":"locality"
},
  "geometry": {"coordinates":[97.90824000000001,18.34298],"type":"Point"}
}