{
  "type": "Feature",
  "properties": {
    "gn:admin1_code":"27",
    "gn:asciiname":"Ban Pa Oi",
    "gn:country_code":"TH",
    "gn:dem":316,
    "gn:feature_class":"P",
    "gn:feature_code":"PPL",
    "gn:name":"Ban Pa Oi",
    "gn:population":0,
    "gn:timezone":"Asia/Bangkok",
    "iso:country":"TH",
    "name:tha_x_preferred":[
        "\u0e1a\u0e49\u0e32\u0e19\u0e1b\u0e48\u0e32\u0e2d\u0e49\u0e2d\u0e22"
    ],
    "wof:name":"Ban Pa Oi",
    "wof:placetype":"locality"
},
  "geometry": {"coordinates":[101.59144000000001,14.71403],"type":"Point"}
}