{
  "type": "Feature",
  "properties": {
    "gn:admin1_code":"70.0",
    "gn:asciiname":"Ban Phong Bue Ra Ngae",
    "gn:country_code":"TH",
    "gn:dem":67,
    "gn:feature_class":"P",
    "gn:feature_code":"PPL",
    "gn:name":"Ban Phong Bue Ra Ngae",
    "gn:population":0,
    "gn:timezone":"Asia/Bangkok",
    "iso:country":"TH",
    "name:tha_x_preferred":[
        "\u0e1a\u0e49\u0e32\u0e19\u0e1e\u0e07\u0e1a\u0e37\u0e2d\u0e23\u0e32\u0e41\u0e07"
    ],
    "wof:name":"Ban Phong Bue Ra Ngae",
    "wof:placetype":"locality"
},
  "geometry": {"coordinates":[101.36153,6.39764],"type":"Point"}
}