{
  "type": "Feature",
  "properties": {
    "gn:admin1_code":"29",
    "gn:asciiname":"Ban Na Nuan",
    "gn:country_code":"TH",
    "gn:dem":158,
    "gn:feature_class":"P",
    "gn:feature_code":"PPL",
    "gn:name":"Ban Na Nuan",
    "gn:population":0,
    "gn:timezone":"Asia/Bangkok",
    "iso:country":"TH",
    "name:tha_x_preferred":[
        "\u0e1a\u0e49\u0e32\u0e19\u0e19\u0e32\u0e19\u0e27\u0e19"
    ],
    "wof:name":"Ban Na Nuan",
    "wof:placetype":"locality"
},
  "geometry": {"coordinates":[103.77616999999999,15.13297],"type":"Point"}
}