{
  "type": "Feature",
  "properties": {
    "gn:admin1_code":"30.0",
    "gn:asciiname":"Ban Saithai Ruam Sap",
    "gn:country_code":"TH",
    "gn:dem":200,
    "gn:feature_class":"P",
    "gn:feature_code":"PPL",
    "gn:name":"Ban Saithai Ruam Sap",
    "gn:population":0,
    "gn:timezone":"Asia/Bangkok",
    "iso:country":"TH",
    "name:tha_x_preferred":[
        "\u0e1a\u0e49\u0e32\u0e19\u0e2a\u0e32\u0e22\u0e17\u0e31\u0e22\u0e23\u0e27\u0e21\u0e17\u0e23\u0e31\u0e1e\u0e22\u0e4c"
    ],
    "wof:name":"Ban Saithai Ruam Sap",
    "wof:placetype":"locality"
},
  "geometry": {"coordinates":[104.73421999999999,14.47328],"type":"Point"}
}