{
  "type": "Feature",
  "properties": {
    "gn:admin1_code":"22",
    "gn:asciiname":"Ban Khuem Chat",
    "gn:country_code":"TH",
    "gn:dem":205,
    "gn:feature_class":"P",
    "gn:feature_code":"PPL",
    "gn:name":"Ban Khuem Chat",
    "gn:population":0,
    "gn:timezone":"Asia/Bangkok",
    "iso:country":"TH",
    "name:tha_x_preferred":[
        "\u0e1a\u0e49\u0e32\u0e19\u0e04\u0e36\u0e21\u0e0a\u0e32\u0e15\u0e34"
    ],
    "wof:name":"Ban Khuem Chat",
    "wof:placetype":"locality"
},
  "geometry": {"coordinates":[102.41128999999999,16.75147999999999],"type":"Point"}
}