{
  "type": "Feature",
  "properties": {
    "gn:admin1_code":"16.0",
    "gn:asciiname":"Ban Nong Ai Sa",
    "gn:country_code":"TH",
    "gn:dem":102,
    "gn:feature_class":"P",
    "gn:feature_code":"PPL",
    "gn:name":"Ban Nong Ai Sa",
    "gn:population":0,
    "gn:timezone":"Asia/Bangkok",
    "iso:country":"TH",
    "name:tha_x_preferred":[
        "\u0e1a\u0e49\u0e32\u0e19\u0e2b\u0e19\u0e2d\u0e07\u0e2d\u0e49\u0e32\u0e22\u0e2a\u0e32"
    ],
    "wof:name":"Ban Nong Ai Sa",
    "wof:placetype":"locality"
},
  "geometry": {"coordinates":[99.56283000000001,15.72683],"type":"Point"}
}