{
  "type": "Feature",
  "properties": {
    "gn:admin1_code":"74",
    "gn:asciiname":"Ban Na Lom",
    "gn:country_code":"TH",
    "gn:dem":31,
    "gn:feature_class":"P",
    "gn:feature_code":"PPL",
    "gn:name":"Ban Na Lom",
    "gn:population":0,
    "gn:timezone":"Asia/Bangkok",
    "iso:country":"TH",
    "name:tha_x_preferred":[
        "\u0e1a\u0e49\u0e32\u0e19\u0e19\u0e32\u0e25\u0e49\u0e2d\u0e21"
    ],
    "wof:name":"Ban Na Lom",
    "wof:placetype":"locality"
},
  "geometry": {"coordinates":[101.92780999999999,13.85203],"type":"Point"}
}