{
  "type": "Feature",
  "properties": {
    "gn:admin1_code":"28.0",
    "gn:asciiname":"Ban Nong Yang",
    "gn:country_code":"TH",
    "gn:dem":189,
    "gn:feature_class":"P",
    "gn:feature_code":"PPL",
    "gn:name":"Ban Nong Yang",
    "gn:population":0,
    "gn:timezone":"Asia/Bangkok",
    "iso:country":"TH",
    "name:tha_x_preferred":[
        "\u0e1a\u0e49\u0e32\u0e19\u0e2b\u0e19\u0e2d\u0e07\u0e22\u0e32\u0e07"
    ],
    "name:und_x_variant":[
        "Ban Yang",
        "Ban Nong Yang (1)",
        "Ban Nong Yang"
    ],
    "wof:name":"Ban Nong Yang",
    "wof:placetype":"locality"
},
  "geometry": {"coordinates":[102.73202999999999,14.62617],"type":"Point"}
}