{
  "type": "Feature",
  "properties": {
    "gn:admin1_code":"3.0",
    "gn:asciiname":"Ban I Ko Pa Mai",
    "gn:country_code":"TH",
    "gn:dem":492,
    "gn:feature_class":"P",
    "gn:feature_code":"PPL",
    "gn:name":"Ban I Ko Pa Mai",
    "gn:population":0,
    "gn:timezone":"Asia/Bangkok",
    "iso:country":"TH",
    "name:tha_x_preferred":[
        "\u0e1a\u0e49\u0e32\u0e19\u0e2d\u0e35\u0e01\u0e49\u0e2d\u0e1b\u0e48\u0e32\u0e44\u0e21\u0e49"
    ],
    "name:und_x_variant":[
        "Ban Phak Pa Ma",
        "Ban I Ko Pa Mai"
    ],
    "wof:name":"Ban I Ko Pa Mai",
    "wof:placetype":"locality"
},
  "geometry": {"coordinates":[99.755,20.15758],"type":"Point"}
}