{
  "type": "Feature",
  "properties": {
    "gn:admin1_code":"75.0",
    "gn:asciiname":"Ban Don Suea",
    "gn:country_code":"TH",
    "gn:dem":160,
    "gn:feature_class":"P",
    "gn:feature_code":"PPL",
    "gn:name":"Ban Don Suea",
    "gn:population":0,
    "gn:timezone":"Asia/Bangkok",
    "iso:country":"TH",
    "name:tha_x_preferred":[
        "\u0e1a\u0e49\u0e32\u0e19\u0e14\u0e2d\u0e19\u0e40\u0e2a\u0e37\u0e2d"
    ],
    "wof:name":"Ban Don Suea",
    "wof:placetype":"locality"
},
  "geometry": {"coordinates":[105.02894000000001,15.75106],"type":"Point"}
}