{
  "type": "Feature",
  "properties": {
    "gn:admin1_code":"16.0",
    "gn:asciiname":"Ban Dong Pa Khlak",
    "gn:country_code":"TH",
    "gn:dem":19,
    "gn:feature_class":"P",
    "gn:feature_code":"PPL",
    "gn:name":"Ban Dong Pa Khlak",
    "gn:population":0,
    "gn:timezone":"Asia/Bangkok",
    "iso:country":"TH",
    "name:tha_x_preferred":[
        "\u0e1a\u0e49\u0e32\u0e19\u0e14\u0e07\u0e1b\u0e48\u0e32\u0e04\u0e25\u0e31\u0e01"
    ],
    "wof:name":"Ban Dong Pa Khlak",
    "wof:placetype":"locality"
},
  "geometry": {"coordinates":[100.37961,15.18992],"type":"Point"}
}