{
  "type": "Feature",
  "properties": {
    "gn:admin1_code":"16.0",
    "gn:asciiname":"Ban Takhro Lat",
    "gn:country_code":"TH",
    "gn:dem":61,
    "gn:feature_class":"P",
    "gn:feature_code":"PPL",
    "gn:name":"Ban Takhro Lat",
    "gn:population":0,
    "gn:timezone":"Asia/Bangkok",
    "iso:country":"TH",
    "name:tha_x_preferred":[
        "\u0e1a\u0e49\u0e32\u0e19\u0e15\u0e30\u0e04\u0e23\u0e49\u0e2d\u0e25\u0e32\u0e14"
    ],
    "wof:name":"Ban Takhro Lat",
    "wof:placetype":"locality"
},
  "geometry": {"coordinates":[100.5608,15.49863],"type":"Point"}
}