{
  "type": "Feature",
  "properties": {
    "gn:admin1_code":"3.0",
    "gn:asciiname":"Ban Pha Bue",
    "gn:country_code":"TH",
    "gn:dem":827,
    "gn:feature_class":"P",
    "gn:feature_code":"PPL",
    "gn:name":"Ban Pha Bue",
    "gn:population":0,
    "gn:timezone":"Asia/Bangkok",
    "iso:country":"TH",
    "name:tha_x_preferred":[
        "\u0e1a\u0e49\u0e32\u0e19\u0e1c\u0e48\u0e32\u0e1a\u0e37\u0e2d"
    ],
    "name:und_x_variant":[
        "Ban Pa Bu"
    ],
    "wof:name":"Ban Pha Bue",
    "wof:placetype":"locality"
},
  "geometry": {"coordinates":[99.79597,20.30831],"type":"Point"}
}