{
  "type": "Feature",
  "properties": {
    "gn:admin1_code":"20.0",
    "gn:asciiname":"Ban Sung Noen",
    "gn:country_code":"TH",
    "gn:dem":209,
    "gn:feature_class":"P",
    "gn:feature_code":"PPL",
    "gn:name":"Ban Sung Noen",
    "gn:population":0,
    "gn:timezone":"Asia/Bangkok",
    "iso:country":"TH",
    "name:tha_x_preferred":[
        "\u0e1a\u0e49\u0e32\u0e19\u0e2a\u0e39\u0e07\u0e40\u0e19\u0e34\u0e19"
    ],
    "wof:name":"Ban Sung Noen",
    "wof:placetype":"locality"
},
  "geometry": {"coordinates":[103.69256,17.19522000000001],"type":"Point"}
}