{
  "type": "Feature",
  "properties": {
    "gn:admin1_code":"20.0",
    "gn:asciiname":"Ban Chaiyanon",
    "gn:country_code":"TH",
    "gn:dem":181,
    "gn:feature_class":"P",
    "gn:feature_code":"PPL",
    "gn:name":"Ban Chaiyanon",
    "gn:population":0,
    "gn:timezone":"Asia/Bangkok",
    "iso:country":"TH",
    "name:tha_x_preferred":[
        "\u0e1a\u0e49\u0e32\u0e19\u0e44\u0e0a\u0e22\u0e22\u0e32\u0e19\u0e19\u0e17\u0e4c"
    ],
    "wof:name":"Ban Chaiyanon",
    "wof:placetype":"locality"
},
  "geometry": {"coordinates":[103.41383,17.76472],"type":"Point"}
}