{
  "type": "Feature",
  "properties": {
    "gn:admin1_code":"2.0",
    "gn:asciiname":"Ban Pa Khaem",
    "gn:country_code":"TH",
    "gn:dem":726,
    "gn:feature_class":"P",
    "gn:feature_code":"PPL",
    "gn:name":"Ban Pa Khaem",
    "gn:population":0,
    "gn:timezone":"Asia/Bangkok",
    "iso:country":"TH",
    "name:tha_x_preferred":[
        "\u0e1a\u0e49\u0e32\u0e19\u0e1b\u0e48\u0e32\u0e41\u0e02\u0e21"
    ],
    "wof:name":"Ban Pa Khaem",
    "wof:placetype":"locality"
},
  "geometry": {"coordinates":[98.59260999999999,18.52031],"type":"Point"}
}