{
  "type": "Feature",
  "properties": {
    "gn:admin1_code":"6.0",
    "gn:asciiname":"Ban Pong Tham",
    "gn:country_code":"TH",
    "gn:dem":537,
    "gn:feature_class":"P",
    "gn:feature_code":"PPL",
    "gn:name":"Ban Pong Tham",
    "gn:population":0,
    "gn:timezone":"Asia/Bangkok",
    "iso:country":"TH",
    "name:tha_x_preferred":[
        "\u0e1a\u0e49\u0e32\u0e19\u0e1b\u0e07\u0e16\u0e49\u0e33"
    ],
    "name:und_x_variant":[
        "B\u0101n Paung Tham",
        "Ban Pong Tham"
    ],
    "wof:name":"Ban Pong Tham",
    "wof:placetype":"locality"
},
  "geometry": {"coordinates":[99.70122000000001,19.11964],"type":"Point"}
}