{
  "type": "Feature",
  "properties": {
    "gn:admin1_code":"26.0",
    "gn:asciiname":"Ban Sap Chomphu",
    "gn:country_code":"TH",
    "gn:dem":337,
    "gn:feature_class":"P",
    "gn:feature_code":"PPL",
    "gn:name":"Ban Sap Chomphu",
    "gn:population":0,
    "gn:timezone":"Asia/Bangkok",
    "iso:country":"TH",
    "name:tha_x_preferred":[
        "\u0e1a\u0e49\u0e32\u0e19\u0e0b\u0e31\u0e1a\u0e0a\u0e21\u0e20\u0e39"
    ],
    "wof:name":"Ban Sap Chomphu",
    "wof:placetype":"locality"
},
  "geometry": {"coordinates":[101.37555999999999,15.78328],"type":"Point"}
}