{
  "type": "Feature",
  "properties": {
    "gn:admin1_code":"65.0",
    "gn:asciiname":"Ban Bang Mak",
    "gn:country_code":"TH",
    "gn:dem":16,
    "gn:feature_class":"P",
    "gn:feature_code":"PPL",
    "gn:name":"Ban Bang Mak",
    "gn:population":0,
    "gn:timezone":"Asia/Bangkok",
    "iso:country":"TH",
    "name:tha_x_preferred":[
        "\u0e1a\u0e49\u0e32\u0e19\u0e1a\u0e32\u0e07\u0e2b\u0e21\u0e32\u0e01"
    ],
    "name:und_x_variant":[
        "Ban Bang Mak (1)"
    ],
    "wof:name":"Ban Bang Mak",
    "wof:placetype":"locality"
},
  "geometry": {"coordinates":[99.56103,7.48497],"type":"Point"}
}