{
  "type": "Feature",
  "properties": {
    "gn:admin1_code":"76.0",
    "gn:asciiname":"Ban Dong Saen Suk",
    "gn:country_code":"TH",
    "gn:dem":165,
    "gn:feature_class":"P",
    "gn:feature_code":"PPL",
    "gn:name":"Ban Dong Saen Suk",
    "gn:population":0,
    "gn:timezone":"Asia/Bangkok",
    "iso:country":"TH",
    "name:tha_x_preferred":[
        "\u0e1a\u0e49\u0e32\u0e19\u0e14\u0e07\u0e41\u0e2a\u0e19\u0e2a\u0e38\u0e02"
    ],
    "wof:name":"Ban Dong Saen Suk",
    "wof:placetype":"locality"
},
  "geometry": {"coordinates":[103.39319,17.67982],"type":"Point"}
}