{
  "type": "Feature",
  "properties": {
    "gn:admin1_code":"36",
    "gn:asciiname":"Ban Si Yaek Wang Noi",
    "gn:country_code":"TH",
    "gn:dem":8,
    "gn:feature_class":"P",
    "gn:feature_code":"PPL",
    "gn:name":"Ban Si Yaek Wang Noi",
    "gn:population":0,
    "gn:timezone":"Asia/Bangkok",
    "iso:country":"TH",
    "name:tha_x_preferred":[
        "\u0e1a\u0e49\u0e32\u0e19\u0e2a\u0e35\u0e48\u0e41\u0e22\u0e01\u0e27\u0e31\u0e07\u0e19\u0e49\u0e2d\u0e22"
    ],
    "wof:name":"Ban Si Yaek Wang Noi",
    "wof:placetype":"locality"
},
  "geometry": {"coordinates":[100.71232999999999,14.23458],"type":"Point"}
}