{
  "type": "Feature",
  "properties": {
    "gn:admin1_code":"24",
    "gn:asciiname":"Ban Lao Rat Phatthana",
    "gn:country_code":"TH",
    "gn:dem":148,
    "gn:feature_class":"P",
    "gn:feature_code":"PPL",
    "gn:name":"Ban Lao Rat Phatthana",
    "gn:population":0,
    "gn:timezone":"Asia/Bangkok",
    "iso:country":"TH",
    "name:tha_x_preferred":[
        "\u0e1a\u0e49\u0e32\u0e19\u0e40\u0e2b\u0e25\u0e48\u0e32\u0e23\u0e32\u0e29\u0e0e\u0e23\u0e4c\u0e1e\u0e31\u0e12\u0e19\u0e32"
    ],
    "wof:name":"Ban Lao Rat Phatthana",
    "wof:placetype":"locality"
},
  "geometry": {"coordinates":[103.43335999999999,15.80147],"type":"Point"}
}