{
  "type": "Feature",
  "properties": {
    "gn:admin1_code":"29",
    "gn:asciiname":"Ban Thap Khai",
    "gn:country_code":"TH",
    "gn:dem":135,
    "gn:feature_class":"P",
    "gn:feature_code":"PPL",
    "gn:name":"Ban Thap Khai",
    "gn:population":0,
    "gn:timezone":"Asia/Bangkok",
    "iso:country":"TH",
    "name:tha_x_preferred":[
        "\u0e1a\u0e49\u0e32\u0e19\u0e17\u0e31\u0e1e\u0e04\u0e48\u0e32\u0e22"
    ],
    "wof:name":"Ban Thap Khai",
    "wof:placetype":"locality"
},
  "geometry": {"coordinates":[103.38186,15.34469],"type":"Point"}
}