{
  "type": "Feature",
  "properties": {
    "gn:admin1_code":"36",
    "gn:asciiname":"Ban Hua Malaengwan",
    "gn:country_code":"TH",
    "gn:dem":5,
    "gn:feature_class":"P",
    "gn:feature_code":"PPL",
    "gn:name":"Ban Hua Malaengwan",
    "gn:population":0,
    "gn:timezone":"Asia/Bangkok",
    "iso:country":"TH",
    "name:tha_x_preferred":[
        "\u0e1a\u0e49\u0e32\u0e19\u0e2b\u0e31\u0e27\u0e41\u0e21\u0e25\u0e07\u0e27\u0e31\u0e19"
    ],
    "wof:name":"Ban Hua Malaengwan",
    "wof:placetype":"locality"
},
  "geometry": {"coordinates":[100.3355,14.20942],"type":"Point"}
}