{
  "type": "Feature",
  "properties": {
    "gn:admin1_code":"36",
    "gn:asciiname":"Ban Khok Krayo",
    "gn:country_code":"TH",
    "gn:dem":5,
    "gn:feature_class":"P",
    "gn:feature_code":"PPL",
    "gn:name":"Ban Khok Krayo",
    "gn:population":0,
    "gn:timezone":"Asia/Bangkok",
    "iso:country":"TH",
    "name:tha_x_preferred":[
        "\u0e1a\u0e49\u0e32\u0e19\u0e42\u0e04\u0e01\u0e01\u0e23\u0e30\u0e22\u0e2d"
    ],
    "wof:name":"Ban Khok Krayo",
    "wof:placetype":"locality"
},
  "geometry": {"coordinates":[100.58694,14.52153],"type":"Point"}
}