{
  "type": "Feature",
  "properties": {
    "gn:admin1_code":"28",
    "gn:asciiname":"Ban Nong Thanon",
    "gn:country_code":"TH",
    "gn:dem":191,
    "gn:feature_class":"P",
    "gn:feature_code":"PPL",
    "gn:name":"Ban Nong Thanon",
    "gn:population":0,
    "gn:timezone":"Asia/Bangkok",
    "iso:country":"TH",
    "name:tha_x_preferred":[
        "\u0e1a\u0e49\u0e32\u0e19\u0e2b\u0e19\u0e2d\u0e07\u0e16\u0e19\u0e19"
    ],
    "wof:name":"Ban Nong Thanon",
    "wof:placetype":"locality"
},
  "geometry": {"coordinates":[102.72711,14.74178],"type":"Point"}
}