{
  "type": "Feature",
  "properties": {
    "gn:admin1_code":"31.0",
    "gn:asciiname":"Ban Bue Nae Chi Cha",
    "gn:country_code":"TH",
    "gn:dem":52,
    "gn:feature_class":"P",
    "gn:feature_code":"PPL",
    "gn:name":"Ban Bue Nae Chi Cha",
    "gn:population":0,
    "gn:timezone":"Asia/Bangkok",
    "iso:country":"TH",
    "name:tha_x_preferred":[
        "\u0e1a\u0e49\u0e32\u0e19\u0e1a\u0e37\u0e2d\u0e41\u0e19\u0e08\u0e35\u0e08\u0e32"
    ],
    "wof:name":"Ban Bue Nae Chi Cha",
    "wof:placetype":"locality"
},
  "geometry": {"coordinates":[101.68994000000001,6.18222],"type":"Point"}
}