{
  "type": "Feature",
  "properties": {
    "gn:admin1_code":"4.0",
    "gn:asciiname":"Ban Chiang Rai",
    "gn:country_code":"TH",
    "gn:dem":202,
    "gn:feature_class":"P",
    "gn:feature_code":"PPL",
    "gn:name":"Ban Chiang Rai",
    "gn:population":0,
    "gn:timezone":"Asia/Bangkok",
    "iso:country":"TH",
    "name:tha_x_preferred":[
        "\u0e1a\u0e49\u0e32\u0e19\u0e40\u0e0a\u0e35\u0e22\u0e07\u0e23\u0e32\u0e22"
    ],
    "wof:name":"Ban Chiang Rai",
    "wof:placetype":"locality"
},
  "geometry": {"coordinates":[100.75172000000001,18.71772],"type":"Point"}
}