{
  "type": "Feature",
  "properties": {
    "gn:admin1_code":"30.0",
    "gn:asciiname":"Ban Sang Pi",
    "gn:country_code":"TH",
    "gn:dem":128,
    "gn:feature_class":"P",
    "gn:feature_code":"PPL",
    "gn:name":"Ban Sang Pi",
    "gn:population":0,
    "gn:timezone":"Asia/Bangkok",
    "iso:country":"TH",
    "name:tha_x_preferred":[
        "\u0e1a\u0e49\u0e32\u0e19\u0e2a\u0e23\u0e49\u0e32\u0e07\u0e1b\u0e35\u0e48"
    ],
    "wof:name":"Ban Sang Pi",
    "wof:placetype":"locality"
},
  "geometry": {"coordinates":[104.30322,15.31242],"type":"Point"}
}