{
  "type": "Feature",
  "properties": {
    "gn:admin1_code":"16.0",
    "gn:asciiname":"Ban Prathap Ron",
    "gn:country_code":"TH",
    "gn:dem":26,
    "gn:feature_class":"P",
    "gn:feature_code":"PPL",
    "gn:name":"Ban Prathap Ron",
    "gn:population":0,
    "gn:timezone":"Asia/Bangkok",
    "iso:country":"TH",
    "name:tha_x_preferred":[
        "\u0e1a\u0e49\u0e32\u0e19\u0e1b\u0e23\u0e30\u0e17\u0e31\u0e1a\u0e23\u0e49\u0e2d\u0e19"
    ],
    "name:und_x_variant":[
        "Ban Thap Ron",
        "Ban Prathap Ron"
    ],
    "wof:lang_x_official":[
        "tha"
    ],
    "wof:lang_x_spoken":[
        "tha"
    ],
    "wof:name":"Ban Prathap Ron",
    "wof:placetype":"locality"
},
  "geometry": {"coordinates":[100.32881,15.83197],"type":"Point"}
}