{
  "type": "Feature",
  "properties": {
    "gn:admin1_code":"9.0",
    "gn:asciiname":"Ban Hat Sai Phan",
    "gn:country_code":"TH",
    "gn:dem":85,
    "gn:feature_class":"P",
    "gn:feature_code":"PPL",
    "gn:name":"Ban Hat Sai Phan",
    "gn:population":0,
    "gn:timezone":"Asia/Bangkok",
    "iso:country":"TH",
    "name:tha_x_preferred":[
        "\u0e1a\u0e49\u0e32\u0e19\u0e2b\u0e32\u0e14\u0e17\u0e23\u0e32\u0e22\u0e1c\u0e31\u0e19"
    ],
    "wof:name":"Ban Hat Sai Phan",
    "wof:placetype":"locality"
},
  "geometry": {"coordinates":[99.68919,17.65544],"type":"Point"}
}