{
  "type": "Feature",
  "properties": {
    "gn:admin1_code":"25.0",
    "gn:asciiname":"Ban Bua Ngoen",
    "gn:country_code":"TH",
    "gn:dem":142,
    "gn:feature_class":"P",
    "gn:feature_code":"PPL",
    "gn:name":"Ban Bua Ngoen",
    "gn:population":0,
    "gn:timezone":"Asia/Bangkok",
    "iso:country":"TH",
    "name:tha_x_preferred":[
        "\u0e1a\u0e49\u0e32\u0e19\u0e1a\u0e31\u0e27\u0e40\u0e07\u0e34\u0e19"
    ],
    "wof:name":"Ban Bua Ngoen",
    "wof:placetype":"locality"
},
  "geometry": {"coordinates":[103.76778,15.76386],"type":"Point"}
}