{
  "type": "Feature",
  "properties": {
    "gn:admin1_code":"18.0",
    "gn:asciiname":"Ban Na Lueng",
    "gn:country_code":"TH",
    "gn:dem":775,
    "gn:feature_class":"P",
    "gn:feature_code":"PPL",
    "gn:name":"Ban Na Lueng",
    "gn:population":0,
    "gn:timezone":"Asia/Bangkok",
    "iso:country":"TH",
    "name:tha_x_preferred":[
        "Ban Na Lueng"
    ],
    "name:tha_x_variant":[
        "\u0e1a\u0e49\u0e32\u0e19\u0e19\u0e32\u0e25\u0e36\u0e48\u0e07"
    ],
    "wof:name":"Ban Na Lueng",
    "wof:placetype":"locality"
},
  "geometry": {"coordinates":[100.8627,17.46895],"type":"Point"}
}