{
  "type": "Feature",
  "properties": {
    "gn:admin1_code":"23.0",
    "gn:asciiname":"Ban Non Tao Hai",
    "gn:country_code":"TH",
    "gn:dem":216,
    "gn:feature_class":"P",
    "gn:feature_code":"PPL",
    "gn:name":"Ban Non Tao Hai",
    "gn:population":0,
    "gn:timezone":"Asia/Bangkok",
    "iso:country":"TH",
    "name:tha_x_preferred":[
        "\u0e1a\u0e49\u0e32\u0e19\u0e42\u0e19\u0e19\u0e40\u0e15\u0e48\u0e32\u0e44\u0e2b"
    ],
    "wof:name":"Ban Non Tao Hai",
    "wof:placetype":"locality"
},
  "geometry": {"coordinates":[103.16158,16.72464],"type":"Point"}
}