{
  "type": "Feature",
  "properties": {
    "gn:admin1_code":"20.0",
    "gn:asciiname":"Ban Nong Din Dam",
    "gn:country_code":"TH",
    "gn:dem":189,
    "gn:feature_class":"P",
    "gn:feature_code":"PPL",
    "gn:name":"Ban Nong Din Dam",
    "gn:population":0,
    "gn:timezone":"Asia/Bangkok",
    "iso:country":"TH",
    "name:tha_x_preferred":[
        "\u0e1a\u0e49\u0e32\u0e19\u0e2b\u0e19\u0e2d\u0e07\u0e14\u0e34\u0e19\u0e14\u0e33"
    ],
    "wof:name":"Ban Nong Din Dam",
    "wof:placetype":"locality"
},
  "geometry": {"coordinates":[103.96657,17.25326],"type":"Point"}
}