{
  "type": "Feature",
  "properties": {
    "gn:admin1_code":"27",
    "gn:asciiname":"Ban Takrut Khruea Plok",
    "gn:country_code":"TH",
    "gn:dem":177,
    "gn:feature_class":"P",
    "gn:feature_code":"PPL",
    "gn:name":"Ban Takrut Khruea Plok",
    "gn:population":0,
    "gn:timezone":"Asia/Bangkok",
    "iso:country":"TH",
    "name:tha_x_preferred":[
        "\u0e1a\u0e49\u0e32\u0e19\u0e15\u0e23\u0e30\u0e01\u0e23\u0e38\u0e14\u0e40\u0e04\u0e23\u0e37\u0e2d\u0e1b\u0e25\u0e2d\u0e01"
    ],
    "wof:name":"Ban Takrut Khruea Plok",
    "wof:placetype":"locality"
},
  "geometry": {"coordinates":[102.39046999999999,15.02275],"type":"Point"}
}