{
  "type": "Feature",
  "properties": {
    "gn:admin1_code":"65.0",
    "gn:asciiname":"Ban Hua Thanon",
    "gn:country_code":"TH",
    "gn:dem":39,
    "gn:feature_class":"P",
    "gn:feature_code":"PPL",
    "gn:name":"Ban Hua Thanon",
    "gn:population":0,
    "gn:timezone":"Asia/Bangkok",
    "iso:country":"TH",
    "name:tha_x_preferred":[
        "\u0e1a\u0e49\u0e32\u0e19\u0e2b\u0e31\u0e27\u0e16\u0e19\u0e19"
    ],
    "wof:name":"Ban Hua Thanon",
    "wof:placetype":"locality"
},
  "geometry": {"coordinates":[99.63549999999999,7.59792],"type":"Point"}
}