{
  "type": "Feature",
  "properties": {
    "gn:admin1_code":"43",
    "gn:asciiname":"Ban Talat Ban Phrik",
    "gn:country_code":"TH",
    "gn:dem":15,
    "gn:feature_class":"P",
    "gn:feature_code":"PPL",
    "gn:name":"Ban Talat Ban Phrik",
    "gn:population":0,
    "gn:timezone":"Asia/Bangkok",
    "iso:country":"TH",
    "name:tha_x_preferred":[
        "\u0e1a\u0e49\u0e32\u0e19\u0e15\u0e25\u0e32\u0e14\u0e1a\u0e49\u0e32\u0e19\u0e1e\u0e23\u0e34\u0e01"
    ],
    "wof:name":"Ban Talat Ban Phrik",
    "wof:placetype":"locality"
},
  "geometry": {"coordinates":[101.02567000000001,14.30758],"type":"Point"}
}