{
  "type": "Feature",
  "properties": {
    "gn:admin1_code":"51.0",
    "gn:asciiname":"Ban Tha Nang Roeng",
    "gn:country_code":"TH",
    "gn:dem":19,
    "gn:feature_class":"P",
    "gn:feature_code":"PPL",
    "gn:name":"Ban Tha Nang Roeng",
    "gn:population":0,
    "gn:timezone":"Asia/Bangkok",
    "iso:country":"TH",
    "name:tha_x_preferred":[
        "\u0e1a\u0e49\u0e32\u0e19\u0e17\u0e48\u0e32\u0e19\u0e32\u0e07\u0e40\u0e23\u0e34\u0e07"
    ],
    "wof:name":"Ban Tha Nang Roeng",
    "wof:placetype":"locality"
},
  "geometry": {"coordinates":[100.11242,14.81806],"type":"Point"}
}