{
  "type": "Feature",
  "properties": {
    "gn:admin1_code":"2.0",
    "gn:asciiname":"Ban Kong Khak Luang",
    "gn:country_code":"TH",
    "gn:dem":555,
    "gn:feature_class":"P",
    "gn:feature_code":"PPL",
    "gn:name":"Ban Kong Khak Luang",
    "gn:population":0,
    "gn:timezone":"Asia/Bangkok",
    "iso:country":"TH",
    "name:tha_x_preferred":[
        "\u0e1a\u0e49\u0e32\u0e19\u0e01\u0e2d\u0e07\u0e02\u0e32\u0e01\u0e2b\u0e25\u0e27\u0e07"
    ],
    "name:und_x_variant":[
        "B\u0101n Gaung K\u0101t",
        "Ban Kong Khat",
        "Ban Kong Khak Luang"
    ],
    "wof:name":"Ban Kong Khak Luang",
    "wof:placetype":"locality"
},
  "geometry": {"coordinates":[98.72141999999999,18.91725],"type":"Point"}
}