{
  "type": "Feature",
  "properties": {
    "gn:admin1_code":"46.0",
    "gn:asciiname":"Ban Na Ta Thok",
    "gn:country_code":"TH",
    "gn:dem":31,
    "gn:feature_class":"P",
    "gn:feature_code":"PPL",
    "gn:name":"Ban Na Ta Thok",
    "gn:population":0,
    "gn:timezone":"Asia/Bangkok",
    "iso:country":"TH",
    "name:tha_x_preferred":[
        "\u0e1a\u0e49\u0e32\u0e19\u0e19\u0e32\u0e15\u0e32\u0e17\u0e2d\u0e01"
    ],
    "wof:name":"Ban Na Ta Thok",
    "wof:placetype":"locality"
},
  "geometry": {"coordinates":[101.23058,13.34975],"type":"Point"}
}