{
  "type": "Feature",
  "properties": {
    "gn:admin1_code":"51.0",
    "gn:asciiname":"Ban Noi Plai Kradon",
    "gn:country_code":"TH",
    "gn:dem":40,
    "gn:feature_class":"P",
    "gn:feature_code":"PPL",
    "gn:name":"Ban Noi Plai Kradon",
    "gn:population":0,
    "gn:timezone":"Asia/Bangkok",
    "iso:country":"TH",
    "wof:name":"Ban Noi Plai Kradon",
    "wof:placetype":"locality"
},
  "geometry": {"coordinates":[99.83105,14.84107],"type":"Point"}
}