{
  "type": "Feature",
  "properties": {
    "gn:admin1_code":"61.0",
    "gn:asciiname":"Ban Ao Ku Ning",
    "gn:country_code":"TH",
    "gn:dem":0,
    "gn:feature_class":"P",
    "gn:feature_code":"PPL",
    "gn:name":"Ban Ao Ku Ning",
    "gn:population":0,
    "gn:timezone":"Asia/Bangkok",
    "iso:country":"TH",
    "wof:name":"Ban Ao Ku Ning",
    "wof:placetype":"locality"
},
  "geometry": {"coordinates":[98.26667,9.18333],"type":"Point"}
}