{
  "type": "Feature",
  "properties": {
    "gn:admin1_code":"26.0",
    "gn:asciiname":"Ban Non Phra Kham",
    "gn:country_code":"TH",
    "gn:dem":206,
    "gn:feature_class":"P",
    "gn:feature_code":"PPL",
    "gn:name":"Ban Non Phra Kham",
    "gn:population":0,
    "gn:timezone":"Asia/Bangkok",
    "iso:country":"TH",
    "name:tha_x_preferred":[
        "\u0e1a\u0e49\u0e32\u0e19\u0e42\u0e19\u0e19\u0e1e\u0e23\u0e30\u0e04\u0e33"
    ],
    "wof:name":"Ban Non Phra Kham",
    "wof:placetype":"locality"
},
  "geometry": {"coordinates":[102.00722,15.95356],"type":"Point"}
}