{
  "type": "Feature",
  "properties": {
    "gn:admin1_code":"29.0",
    "gn:asciiname":"Ban Sangkae",
    "gn:country_code":"TH",
    "gn:dem":171,
    "gn:feature_class":"P",
    "gn:feature_code":"PPL",
    "gn:name":"Ban Sangkae",
    "gn:population":0,
    "gn:timezone":"Asia/Bangkok",
    "iso:country":"TH",
    "name:tha_x_preferred":[
        "\u0e1a\u0e49\u0e32\u0e19\u0e2a\u0e31\u0e07\u0e41\u0e01"
    ],
    "name:und_x_variant":[
        "Song Ke",
        "Ban Sangkae"
    ],
    "wof:name":"Ban Sangkae",
    "wof:placetype":"locality"
},
  "geometry": {"coordinates":[104.00857999999999,14.56911],"type":"Point"}
}