{
  "type": "Feature",
  "properties": {
    "gn:admin1_code":"31.0",
    "gn:asciiname":"Ban Pong Mu Su",
    "gn:country_code":"TH",
    "gn:dem":29,
    "gn:feature_class":"P",
    "gn:feature_code":"PPL",
    "gn:name":"Ban Pong Mu Su",
    "gn:population":0,
    "gn:timezone":"Asia/Bangkok",
    "iso:country":"TH",
    "name:tha_x_preferred":[
        "\u0e1a\u0e49\u0e32\u0e19\u0e1e\u0e07\u0e21\u0e39\u0e0b\u0e39"
    ],
    "wof:name":"Ban Pong Mu Su",
    "wof:placetype":"locality"
},
  "geometry": {"coordinates":[101.47989,6.34275],"type":"Point"}
}