{
  "type": "Feature",
  "properties": {
    "gn:admin1_code":"22",
    "gn:asciiname":"Ban Kai Na",
    "gn:country_code":"TH",
    "gn:dem":165,
    "gn:feature_class":"P",
    "gn:feature_code":"PPL",
    "gn:name":"Ban Kai Na",
    "gn:population":0,
    "gn:timezone":"Asia/Bangkok",
    "iso:country":"TH",
    "name:tha_x_preferred":[
        "\u0e1a\u0e49\u0e32\u0e19\u0e44\u0e01\u0e48\u0e19\u0e32"
    ],
    "wof:name":"Ban Kai Na",
    "wof:placetype":"locality"
},
  "geometry": {"coordinates":[102.84103,16.54539],"type":"Point"}
}