{
  "type": "Feature",
  "properties": {
    "gn:admin1_code":"66.0",
    "gn:asciiname":"Ban Ko Mo Si Sip Song",
    "gn:country_code":"TH",
    "gn:dem":27,
    "gn:feature_class":"P",
    "gn:feature_code":"PPL",
    "gn:name":"Ban Ko Mo Si Sip Song",
    "gn:population":0,
    "gn:timezone":"Asia/Bangkok",
    "iso:country":"TH",
    "name:tha_x_preferred":[
        "\u0e1a\u0e49\u0e32\u0e19 \u0e01\u0e21.\u0e2a\u0e35\u0e48\u0e2a\u0e34\u0e1a\u0e2a\u0e2d\u0e07"
    ],
    "wof:name":"Ban Ko Mo Si Sip Song",
    "wof:placetype":"locality"
},
  "geometry": {"coordinates":[100.07292,7.42794],"type":"Point"}
}