{
  "type": "Feature",
  "properties": {
    "gn:admin1_code":"80",
    "gn:asciiname":"Ban Si Wilai",
    "gn:country_code":"TH",
    "gn:dem":60,
    "gn:feature_class":"P",
    "gn:feature_code":"PPL",
    "gn:name":"Ban Si Wilai",
    "gn:population":0,
    "gn:timezone":"Asia/Bangkok",
    "iso:country":"TH",
    "name:tha_x_preferred":[
        "\u0e1a\u0e49\u0e32\u0e19\u0e28\u0e23\u0e35\u0e27\u0e34\u0e44\u0e25"
    ],
    "wof:name":"Ban Si Wilai",
    "wof:placetype":"locality"
},
  "geometry": {"coordinates":[102.52422,13.59411],"type":"Point"}
}