{
  "type": "Feature",
  "properties": {
    "gn:admin1_code":"2.0",
    "gn:asciiname":"Ban Huai Hian",
    "gn:country_code":"TH",
    "gn:dem":521,
    "gn:feature_class":"P",
    "gn:feature_code":"PPL",
    "gn:name":"Ban Huai Hian",
    "gn:population":0,
    "gn:timezone":"Asia/Bangkok",
    "iso:country":"TH",
    "name:tha_x_preferred":[
        "\u0e1a\u0e49\u0e32\u0e19\u0e2b\u0e49\u0e27\u0e22\u0e40\u0e2e\u0e35\u0e48\u0e22\u0e19"
    ],
    "wof:name":"Ban Huai Hian",
    "wof:placetype":"locality"
},
  "geometry": {"coordinates":[99.18781,19.95397],"type":"Point"}
}