{
  "type": "Feature",
  "properties": {
    "gn:admin1_code":"60.0",
    "gn:asciiname":"Ban Amrat",
    "gn:country_code":"TH",
    "gn:dem":16,
    "gn:feature_class":"P",
    "gn:feature_code":"PPL",
    "gn:name":"Ban Amrat",
    "gn:population":0,
    "gn:timezone":"Asia/Bangkok",
    "iso:country":"TH",
    "name:tha_x_preferred":[
        "\u0e1a\u0e49\u0e32\u0e19\u0e2d\u0e33\u0e23\u0e31\u0e15\u0e19\u0e4c"
    ],
    "name:und_x_variant":[
        "Ban Ammarat"
    ],
    "wof:name":"Ban Amrat",
    "wof:placetype":"locality"
},
  "geometry": {"coordinates":[99.21093999999999,8.79144],"type":"Point"}
}