{
  "type": "Feature",
  "properties": {
    "gn:admin1_code":"13.0",
    "gn:asciiname":"Ban Wang Sai Phun",
    "gn:country_code":"TH",
    "gn:dem":48,
    "gn:feature_class":"P",
    "gn:feature_code":"PPL",
    "gn:name":"Ban Wang Sai Phun",
    "gn:population":0,
    "gn:timezone":"Asia/Bangkok",
    "iso:country":"TH",
    "name:tha_x_preferred":[
        "\u0e1a\u0e49\u0e32\u0e19\u0e27\u0e31\u0e07\u0e17\u0e23\u0e32\u0e22\u0e1e\u0e39\u0e19"
    ],
    "wof:name":"Ban Wang Sai Phun",
    "wof:placetype":"locality"
},
  "geometry": {"coordinates":[100.52553,16.40547],"type":"Point"}
}