{
  "type": "Feature",
  "properties": {
    "gn:admin1_code":"69.0",
    "gn:asciiname":"Ban Manang Yong",
    "gn:country_code":"TH",
    "gn:dem":24,
    "gn:feature_class":"P",
    "gn:feature_code":"PPL",
    "gn:name":"Ban Manang Yong",
    "gn:population":0,
    "gn:timezone":"Asia/Bangkok",
    "iso:country":"TH",
    "name:tha_x_preferred":[
        "\u0e1a\u0e49\u0e32\u0e19\u0e21\u0e30\u0e19\u0e31\u0e07\u0e22\u0e07"
    ],
    "wof:name":"Ban Manang Yong",
    "wof:placetype":"locality"
},
  "geometry": {"coordinates":[101.48269999999999,6.64867],"type":"Point"}
}