{
  "type": "Feature",
  "properties": {
    "gn:admin1_code":"32.0",
    "gn:asciiname":"Ban Bueng Thap Pla",
    "gn:country_code":"TH",
    "gn:dem":23,
    "gn:feature_class":"P",
    "gn:feature_code":"PPL",
    "gn:name":"Ban Bueng Thap Pla",
    "gn:population":0,
    "gn:timezone":"Asia/Bangkok",
    "iso:country":"TH",
    "name:tha_x_preferred":[
        "\u0e1a\u0e49\u0e32\u0e19\u0e1a\u0e36\u0e07\u0e17\u0e31\u0e1a\u0e1b\u0e25\u0e32"
    ],
    "wof:name":"Ban Bueng Thap Pla",
    "wof:placetype":"locality"
},
  "geometry": {"coordinates":[100.13542,15.30067],"type":"Point"}
}