{
  "type": "Feature",
  "properties": {
    "gn:admin1_code":"41.0",
    "gn:asciiname":"Ban Nun",
    "gn:country_code":"TH",
    "gn:dem":305,
    "gn:feature_class":"P",
    "gn:feature_code":"PPL",
    "gn:name":"Ban Nun",
    "gn:population":0,
    "gn:timezone":"Asia/Bangkok",
    "iso:country":"TH",
    "name:tha_x_preferred":[
        "\u0e1a\u0e49\u0e32\u0e19\u0e2b\u0e19\u0e38\u0e19"
    ],
    "wof:name":"Ban Nun",
    "wof:placetype":"locality"
},
  "geometry": {"coordinates":[100.26311,19.13422000000001],"type":"Point"}
}