{
  "type": "Feature",
  "properties": {
    "gn:admin1_code":"60.0",
    "gn:asciiname":"Ban Rong Krabueang",
    "gn:country_code":"TH",
    "gn:dem":17,
    "gn:feature_class":"P",
    "gn:feature_code":"PPL",
    "gn:name":"Ban Rong Krabueang",
    "gn:population":0,
    "gn:timezone":"Asia/Bangkok",
    "iso:country":"TH",
    "name:tha_x_preferred":[
        "\u0e1a\u0e49\u0e32\u0e19\u0e42\u0e23\u0e07\u0e01\u0e23\u0e30\u0e40\u0e1a\u0e37\u0e49\u0e2d\u0e07"
    ],
    "name:und_x_variant":[
        "Ban Rong Krabuang"
    ],
    "wof:name":"Ban Rong Krabueang",
    "wof:placetype":"locality"
},
  "geometry": {"coordinates":[99.0355,9.04567],"type":"Point"}
}