{
  "type": "Feature",
  "properties": {
    "gn:admin1_code":"6.0",
    "gn:asciiname":"Ban Phae Sop Huak",
    "gn:country_code":"TH",
    "gn:dem":239,
    "gn:feature_class":"P",
    "gn:feature_code":"PPL",
    "gn:name":"Ban Phae Sop Huak",
    "gn:population":0,
    "gn:timezone":"Asia/Bangkok",
    "iso:country":"TH",
    "name:tha_x_preferred":[
        "\u0e1a\u0e49\u0e32\u0e19\u0e41\u0e1e\u0e30\u0e2a\u0e1a\u0e2e\u0e27\u0e01"
    ],
    "wof:name":"Ban Phae Sop Huak",
    "wof:placetype":"locality"
},
  "geometry": {"coordinates":[99.34233,18.20047000000001],"type":"Point"}
}