{
  "type": "Feature",
  "properties": {
    "gn:admin1_code":"77.0",
    "gn:asciiname":"Ban Khan Sung",
    "gn:country_code":"TH",
    "gn:dem":143,
    "gn:feature_class":"P",
    "gn:feature_code":"PPL",
    "gn:name":"Ban Khan Sung",
    "gn:population":0,
    "gn:timezone":"Asia/Bangkok",
    "iso:country":"TH",
    "name:tha_x_preferred":[
        "Ban Khan Sung"
    ],
    "name:tha_x_variant":[
        "\u0e1a\u0e49\u0e32\u0e19\u0e04\u0e31\u0e19\u0e2a\u0e39\u0e07"
    ],
    "wof:name":"Ban Khan Sung",
    "wof:placetype":"locality"
},
  "geometry": {"coordinates":[105.00817000000001,16.18442000000001],"type":"Point"}
}