{
  "type": "Feature",
  "properties": {
    "gn:admin1_code":"4.0",
    "gn:asciiname":"Ban Maeo",
    "gn:country_code":"TH",
    "gn:dem":1384,
    "gn:feature_class":"P",
    "gn:feature_code":"PPL",
    "gn:name":"Ban Maeo",
    "gn:population":0,
    "gn:timezone":"Asia/Bangkok",
    "iso:country":"TH",
    "name:tha_x_preferred":[
        "\u0e1a\u0e49\u0e32\u0e19\u0e41\u0e21\u0e49\u0e27"
    ],
    "wof:name":"Ban Maeo",
    "wof:placetype":"locality"
},
  "geometry": {"coordinates":[101.08396999999999,19.20842],"type":"Point"}
}