{
  "type": "Feature",
  "properties": {
    "gn:admin1_code":"36",
    "gn:asciiname":"Ban Don Ta Chang",
    "gn:country_code":"TH",
    "gn:dem":4,
    "gn:feature_class":"P",
    "gn:feature_code":"PPL",
    "gn:name":"Ban Don Ta Chang",
    "gn:population":0,
    "gn:timezone":"Asia/Bangkok",
    "iso:country":"TH",
    "name:tha_x_preferred":[
        "\u0e1a\u0e49\u0e32\u0e19\u0e14\u0e2d\u0e19\u0e15\u0e32\u0e0a\u0e49\u0e32\u0e07"
    ],
    "wof:name":"Ban Don Ta Chang",
    "wof:placetype":"locality"
},
  "geometry": {"coordinates":[100.43335999999999,14.15372],"type":"Point"}
}