{
  "type": "Feature",
  "properties": {
    "gn:admin1_code":"79.0",
    "gn:asciiname":"Ban Han Na Ngam",
    "gn:country_code":"TH",
    "gn:dem":212,
    "gn:feature_class":"P",
    "gn:feature_code":"PPL",
    "gn:name":"Ban Han Na Ngam",
    "gn:population":0,
    "gn:timezone":"Asia/Bangkok",
    "iso:country":"TH",
    "name:tha_x_preferred":[
        "\u0e1a\u0e49\u0e32\u0e19\u0e2b\u0e31\u0e19\u0e19\u0e32\u0e07\u0e32\u0e21"
    ],
    "wof:name":"Ban Han Na Ngam",
    "wof:placetype":"locality"
},
  "geometry": {"coordinates":[102.25678000000001,16.99458],"type":"Point"}
}