{
  "type": "Feature",
  "properties": {
    "gn:admin1_code":"36",
    "gn:asciiname":"Ban Tha Chang",
    "gn:country_code":"TH",
    "gn:dem":9,
    "gn:feature_class":"P",
    "gn:feature_code":"PPL",
    "gn:name":"Ban Tha Chang",
    "gn:population":0,
    "gn:timezone":"Asia/Bangkok",
    "iso:country":"TH",
    "name:tha_x_preferred":[
        "\u0e1a\u0e49\u0e32\u0e19\u0e17\u0e48\u0e32\u0e0a\u0e49\u0e32\u0e07"
    ],
    "wof:name":"Ban Tha Chang",
    "wof:placetype":"locality"
},
  "geometry": {"coordinates":[100.47711,14.32881],"type":"Point"}
}