{
  "type": "Feature",
  "properties": {
    "gn:admin1_code":"3.0",
    "gn:asciiname":"Ban Pa Tueng Ngam",
    "gn:country_code":"TH",
    "gn:dem":484,
    "gn:feature_class":"P",
    "gn:feature_code":"PPL",
    "gn:name":"Ban Pa Tueng Ngam",
    "gn:population":0,
    "gn:timezone":"Asia/Bangkok",
    "iso:country":"TH",
    "name:tha_x_preferred":[
        "\u0e1a\u0e49\u0e32\u0e19\u0e1b\u0e48\u0e32\u0e15\u0e36\u0e07\u0e07\u0e32\u0e21"
    ],
    "wof:name":"Ban Pa Tueng Ngam",
    "wof:placetype":"locality"
},
  "geometry": {"coordinates":[99.50847,19.60544],"type":"Point"}
}