{
  "type": "Feature",
  "properties": {
    "gn:admin1_code":"53.0",
    "gn:asciiname":"Ban Huai Phakchi",
    "gn:country_code":"TH",
    "gn:dem":13,
    "gn:feature_class":"P",
    "gn:feature_code":"PPL",
    "gn:name":"Ban Huai Phakchi",
    "gn:population":0,
    "gn:timezone":"Asia/Bangkok",
    "iso:country":"TH",
    "name:tha_x_preferred":[
        "Ban Huai Phakchi"
    ],
    "name:tha_x_variant":[
        "\u0e1a\u0e49\u0e32\u0e19\u0e2b\u0e49\u0e27\u0e22\u0e1c\u0e31\u0e01\u0e0a\u0e35"
    ],
    "name:und_x_variant":[
        "Naung Phak Chi",
        "Ban Nong Phak Chi"
    ],
    "wof:name":"Ban Huai Phakchi",
    "wof:placetype":"locality"
},
  "geometry": {"coordinates":[99.88142000000001,13.97375],"type":"Point"}
}