{
  "type": "Feature",
  "properties": {
    "gn:admin1_code":"29.0",
    "gn:asciiname":"Ban Akhun",
    "gn:country_code":"TH",
    "gn:dem":152,
    "gn:feature_class":"P",
    "gn:feature_code":"PPL",
    "gn:name":"Ban Akhun",
    "gn:population":0,
    "gn:timezone":"Asia/Bangkok",
    "iso:country":"TH",
    "name:tha_x_preferred":[
        "\u0e1a\u0e49\u0e32\u0e19\u0e2d\u0e32\u0e04\u0e38\u0e13"
    ],
    "name:und_x_variant":[
        "Ban A Khun"
    ],
    "wof:name":"Ban Akhun",
    "wof:placetype":"locality"
},
  "geometry": {"coordinates":[103.51133,15.21092],"type":"Point"}
}