{
  "type": "Feature",
  "properties": {
    "gn:admin1_code":"4.0",
    "gn:asciiname":"Ban Huai Win",
    "gn:country_code":"TH",
    "gn:dem":810,
    "gn:feature_class":"P",
    "gn:feature_code":"PPL",
    "gn:name":"Ban Huai Win",
    "gn:population":0,
    "gn:timezone":"Asia/Bangkok",
    "iso:country":"TH",
    "name:tha_x_preferred":[
        "\u0e1a\u0e49\u0e32\u0e19\u0e2b\u0e49\u0e27\u0e22\u0e27\u0e35\u0e19"
    ],
    "wof:name":"Ban Huai Win",
    "wof:placetype":"locality"
},
  "geometry": {"coordinates":[101.11903,19.04995],"type":"Point"}
}