{
  "type": "Feature",
  "properties": {
    "gn:admin1_code":"56.0",
    "gn:asciiname":"Ban Hua Saphan",
    "gn:country_code":"TH",
    "gn:dem":5,
    "gn:feature_class":"P",
    "gn:feature_code":"PPL",
    "gn:name":"Ban Hua Saphan",
    "gn:population":0,
    "gn:timezone":"Asia/Bangkok",
    "iso:country":"TH",
    "name:tha_x_preferred":[
        "\u0e1a\u0e49\u0e32\u0e19\u0e2b\u0e31\u0e27\u0e2a\u0e30\u0e1e\u0e32\u0e19"
    ],
    "name:und_x_variant":[
        "Hua Taphan",
        "Ban Hua Saphan"
    ],
    "wof:name":"Ban Hua Saphan",
    "wof:placetype":"locality"
},
  "geometry": {"coordinates":[99.87278000000001,13.12661],"type":"Point"}
}