{
  "type": "Feature",
  "properties": {
    "gn:country":"TH",
    "gn:fcode":"PPL",
    "gn:population":0,
    "iso:country":"TH",
    "name:ara_x_preferred":[
        "\u0643\u0647\u0641 \u062b\u0627\u0645 \u0644\u0648\u062a"
    ],
    "name:arz_x_preferred":[
        "\u0643\u0647\u0641 \u062b\u0627\u0645 \u0644\u0648\u062a"
    ],
    "name:eng_x_preferred":[
        "Tham Lot"
    ],
    "name:spa_x_preferred":[
        "Tham Lot"
    ],
    "name:tha_x_preferred":[
        "\u0e1a\u0e49\u0e32\u0e19\u0e16\u0e49\u0e33\u0e25\u0e2d\u0e14"
    ],
    "name:tha_x_variant":[
        "\u0e16\u0e49\u0e33\u0e25\u0e2d\u0e14"
    ],
    "name:und_x_variant":[
        "Ban Tham Lot"
    ],
    "qs:name":"Tham Lot",
    "qs:name_adm0":"Thailand",
    "qs:name_adm1":"Mae Hong Son",
    "qs:photos":343,
    "qs:photos_1k":70,
    "qs:photos_9k":2,
    "qs:photos_9r":5,
    "qs:photos_all":343,
    "qs:photos_sr":5,
    "qs:placetype":"Town",
    "qs:pop_sr":"0",
    "wd:wordcount":312,
    "wof:name":"Tham Lot",
    "wof:placetype":"locality",
    "wof:population":0
},
  "geometry": {"coordinates":[98.27733000000001,19.57217],"type":"Point"}
}