{
  "type": "Feature",
  "properties": {
    "gn:admin1_code":"65.0",
    "gn:asciiname":"Ban Thon Chao Ngu",
    "gn:country_code":"TH",
    "gn:dem":14,
    "gn:feature_class":"P",
    "gn:feature_code":"PPL",
    "gn:name":"Ban Thon Chao Ngu",
    "gn:population":0,
    "gn:timezone":"Asia/Bangkok",
    "iso:country":"TH",
    "name:tha_x_preferred":[
        "\u0e1a\u0e49\u0e32\u0e19\u0e17\u0e2d\u0e19\u0e0a\u0e32\u0e27\u0e07\u0e39"
    ],
    "wof:name":"Ban Thon Chao Ngu",
    "wof:placetype":"locality"
},
  "geometry": {"coordinates":[99.69906,7.17703],"type":"Point"}
}