{
  "type": "Feature",
  "properties": {
    "gn:admin1_code":"31.0",
    "gn:asciiname":"Ban Ku Ching Rue Pa",
    "gn:country_code":"TH",
    "gn:dem":39,
    "gn:feature_class":"P",
    "gn:feature_code":"PPL",
    "gn:name":"Ban Ku Ching Rue Pa",
    "gn:population":0,
    "gn:timezone":"Asia/Bangkok",
    "iso:country":"TH",
    "name:tha_x_preferred":[
        "\u0e1a\u0e49\u0e32\u0e19\u0e01\u0e39\u0e08\u0e34\u0e07\u0e23\u0e37\u0e2d\u0e1b\u0e4a\u0e30"
    ],
    "name:und_x_variant":[
        "Ban Ku Ching Ru Pa"
    ],
    "wof:name":"Ban Ku Ching Rue Pa",
    "wof:placetype":"locality"
},
  "geometry": {"coordinates":[101.63630999999999,6.29453],"type":"Point"}
}