{
  "type": "Feature",
  "properties": {
    "gn:admin1_code":"27.0",
    "gn:asciiname":"Ban Non Rang",
    "gn:country_code":"TH",
    "gn:dem":179,
    "gn:feature_class":"P",
    "gn:feature_code":"PPL",
    "gn:name":"Ban Non Rang",
    "gn:population":0,
    "gn:timezone":"Asia/Bangkok",
    "iso:country":"TH",
    "name:tha_x_preferred":[
        "\u0e1a\u0e49\u0e32\u0e19\u0e42\u0e19\u0e19\u0e23\u0e31\u0e07"
    ],
    "name:und_x_variant":[
        "Noen Rang",
        "Ban Noen Rang",
        "Ban Non Rang (1)",
        "Ban Non Rang"
    ],
    "wof:name":"Ban Non Rang",
    "wof:placetype":"locality"
},
  "geometry": {"coordinates":[102.81411,15.226],"type":"Point"}
}