{
  "type": "Feature",
  "properties": {
    "gn:admin1_code":"74",
    "gn:asciiname":"Ban Wang Hua Khu",
    "gn:country_code":"TH",
    "gn:dem":7,
    "gn:feature_class":"P",
    "gn:feature_code":"PPL",
    "gn:name":"Ban Wang Hua Khu",
    "gn:population":0,
    "gn:timezone":"Asia/Bangkok",
    "iso:country":"TH",
    "name:tha_x_preferred":[
        "\u0e1a\u0e49\u0e32\u0e19\u0e27\u0e31\u0e07\u0e2b\u0e31\u0e27\u0e04\u0e39\u0e49"
    ],
    "wof:name":"Ban Wang Hua Khu",
    "wof:placetype":"locality"
},
  "geometry": {"coordinates":[101.25389,13.95675],"type":"Point"}
}