{
  "type": "Feature",
  "properties": {
    "gn:admin1_code":"16.0",
    "gn:asciiname":"Ban Bang Plong",
    "gn:country_code":"TH",
    "gn:dem":25,
    "gn:feature_class":"P",
    "gn:feature_code":"PPL",
    "gn:name":"Ban Bang Plong",
    "gn:population":0,
    "gn:timezone":"Asia/Bangkok",
    "iso:country":"TH",
    "name:tha_x_preferred":[
        "\u0e1a\u0e49\u0e32\u0e19\u0e1a\u0e32\u0e07\u0e1b\u0e25\u0e2d\u0e07"
    ],
    "name:und_x_variant":[
        "Ban Bang Prong",
        "Ban Bang Plung",
        "Ban Bang Plong"
    ],
    "wof:name":"Ban Bang Plong",
    "wof:placetype":"locality"
},
  "geometry": {"coordinates":[100.13472,15.68844],"type":"Point"}
}