{
  "type": "Feature",
  "properties": {
    "gn:admin1_code":"17.0",
    "gn:asciiname":"Ban Dong Muai",
    "gn:country_code":"TH",
    "gn:dem":172,
    "gn:feature_class":"P",
    "gn:feature_code":"PPL",
    "gn:name":"Ban Dong Muai",
    "gn:population":0,
    "gn:timezone":"Asia/Bangkok",
    "iso:country":"TH",
    "name:tha_x_preferred":[
        "\u0e1a\u0e49\u0e32\u0e19\u0e14\u0e07\u0e21\u0e48\u0e27\u0e22"
    ],
    "wof:name":"Ban Dong Muai",
    "wof:placetype":"locality"
},
  "geometry": {"coordinates":[103.02417,17.92731000000001],"type":"Point"}
}