{
  "type": "Feature",
  "properties": {
    "gn:admin1_code":"57.0",
    "gn:asciiname":"Ban Ta Mong Lai",
    "gn:country_code":"TH",
    "gn:dem":7,
    "gn:feature_class":"P",
    "gn:feature_code":"PPL",
    "gn:name":"Ban Ta Mong Lai",
    "gn:population":0,
    "gn:timezone":"Asia/Bangkok",
    "iso:country":"TH",
    "name:tha_x_preferred":[
        "\u0e1a\u0e49\u0e32\u0e19\u0e15\u0e32\u0e21\u0e48\u0e2d\u0e07\u0e25\u0e48\u0e32\u0e22"
    ],
    "name:und_x_variant":[
        "M\u014dhng L\u0101i",
        "Ban Mong Lai",
        "Ban Mong Rai",
        "Ban Ta Mong Lai"
    ],
    "wof:name":"Ban Ta Mong Lai",
    "wof:placetype":"locality"
},
  "geometry": {"coordinates":[99.82467,11.84178],"type":"Point"}
}