{
  "type": "Feature",
  "properties": {
    "gn:admin1_code":"75.0",
    "gn:asciiname":"Ban Non Nari",
    "gn:country_code":"TH",
    "gn:dem":139,
    "gn:feature_class":"P",
    "gn:feature_code":"PPL",
    "gn:name":"Ban Non Nari",
    "gn:population":0,
    "gn:timezone":"Asia/Bangkok",
    "iso:country":"TH",
    "name:tha_x_preferred":[
        "\u0e1a\u0e49\u0e32\u0e19\u0e42\u0e19\u0e19\u0e19\u0e32\u0e23\u0e35"
    ],
    "wof:name":"Ban Non Nari",
    "wof:placetype":"locality"
},
  "geometry": {"coordinates":[105.22693999999998,16.03372],"type":"Point"}
}