{
  "type": "Feature",
  "properties": {
    "gn:admin1_code":"46.0",
    "gn:asciiname":"Ban Nong Kai Ploi",
    "gn:country_code":"TH",
    "gn:dem":135,
    "gn:feature_class":"P",
    "gn:feature_code":"PPL",
    "gn:name":"Ban Nong Kai Ploi",
    "gn:population":0,
    "gn:timezone":"Asia/Bangkok",
    "iso:country":"TH",
    "name:tha_x_preferred":[
        "\u0e1a\u0e49\u0e32\u0e19\u0e2b\u0e19\u0e2d\u0e07\u0e44\u0e01\u0e48\u0e1b\u0e25\u0e48\u0e2d\u0e22"
    ],
    "wof:name":"Ban Nong Kai Ploi",
    "wof:placetype":"locality"
},
  "geometry": {"coordinates":[101.08844000000001,13.12956],"type":"Point"}
}