{
  "type": "Feature",
  "properties": {
    "gn:admin1_code":"65.0",
    "gn:asciiname":"Ban Thung Na Haeng",
    "gn:country_code":"TH",
    "gn:dem":20,
    "gn:feature_class":"P",
    "gn:feature_code":"PPL",
    "gn:name":"Ban Thung Na Haeng",
    "gn:population":0,
    "gn:timezone":"Asia/Bangkok",
    "iso:country":"TH",
    "name:tha_x_preferred":[
        "\u0e1a\u0e49\u0e32\u0e19\u0e17\u0e38\u0e48\u0e07\u0e19\u0e32\u0e41\u0e2b\u0e49\u0e07"
    ],
    "wof:name":"Ban Thung Na Haeng",
    "wof:placetype":"locality"
},
  "geometry": {"coordinates":[99.35928,7.4565],"type":"Point"}
}