{
  "type": "Feature",
  "properties": {
    "gn:admin1_code":"29",
    "gn:asciiname":"Ban Ta Mok",
    "gn:country_code":"TH",
    "gn:dem":145,
    "gn:feature_class":"P",
    "gn:feature_code":"PPL",
    "gn:name":"Ban Ta Mok",
    "gn:population":0,
    "gn:timezone":"Asia/Bangkok",
    "iso:country":"TH",
    "name:tha_x_preferred":[
        "\u0e1a\u0e49\u0e32\u0e19\u0e15\u0e32\u0e42\u0e2b\u0e21\u0e01"
    ],
    "wof:name":"Ban Ta Mok",
    "wof:placetype":"locality"
},
  "geometry": {"coordinates":[103.59896999999999,15.05058],"type":"Point"}
}