{
  "type": "Feature",
  "properties": {
    "gn:admin1_code":"76.0",
    "gn:asciiname":"Ban Don Mak Kaeo",
    "gn:country_code":"TH",
    "gn:dem":177,
    "gn:feature_class":"P",
    "gn:feature_code":"PPL",
    "gn:name":"Ban Don Mak Kaeo",
    "gn:population":0,
    "gn:timezone":"Asia/Bangkok",
    "iso:country":"TH",
    "name:tha_x_preferred":[
        "\u0e1a\u0e49\u0e32\u0e19\u0e14\u0e2d\u0e19\u0e2b\u0e21\u0e32\u0e01\u0e41\u0e01\u0e49\u0e27"
    ],
    "wof:name":"Ban Don Mak Kaeo",
    "wof:placetype":"locality"
},
  "geometry": {"coordinates":[102.764,17.58886],"type":"Point"}
}