{
  "type": "Feature",
  "properties": {
    "gn:admin1_code":"44.0",
    "gn:asciiname":"Ban Krok Kaeo Wong Phrachan",
    "gn:country_code":"TH",
    "gn:dem":46,
    "gn:feature_class":"P",
    "gn:feature_code":"PPL",
    "gn:name":"Ban Krok Kaeo Wong Phrachan",
    "gn:population":0,
    "gn:timezone":"Asia/Bangkok",
    "iso:country":"TH",
    "name:tha_x_preferred":[
        "\u0e1a\u0e49\u0e32\u0e19\u0e42\u0e01\u0e23\u0e01\u0e41\u0e01\u0e49\u0e27\u0e27\u0e07\u0e1e\u0e23\u0e30\u0e08\u0e31\u0e19\u0e17\u0e23\u0e4c"
    ],
    "wof:name":"Ban Krok Kaeo Wong Phrachan",
    "wof:placetype":"locality"
},
  "geometry": {"coordinates":[101.32808,13.50789],"type":"Point"}
}