{
  "type": "Feature",
  "properties": {
    "gn:admin1_code":"37.0",
    "gn:asciiname":"Ban Khlong Khai Nao",
    "gn:cc2":"TH",
    "gn:country_code":"TH",
    "gn:dem":9,
    "gn:feature_class":"P",
    "gn:feature_code":"PPL",
    "gn:name":"Ban Khlong Khai Nao",
    "gn:population":0,
    "gn:timezone":"Asia/Bangkok",
    "iso:country":"TH",
    "name:und_x_variant":[
        "Ban Klong Khai Nao",
        "Ban Khlong Khai Nao"
    ],
    "wof:name":"Ban Khlong Khai Nao",
    "wof:placetype":"locality"
},
  "geometry": {"coordinates":[100.68333,14.71667],"type":"Point"}
}