{
  "type": "Feature",
  "properties": {
    "gn:admin1_code":"26.0",
    "gn:asciiname":"Ban Phanang Suea",
    "gn:country_code":"TH",
    "gn:dem":214,
    "gn:feature_class":"P",
    "gn:feature_code":"PPL",
    "gn:name":"Ban Phanang Suea",
    "gn:population":0,
    "gn:timezone":"Asia/Bangkok",
    "iso:country":"TH",
    "name:tha_x_preferred":[
        "\u0e1a\u0e49\u0e32\u0e19\u0e1e\u0e19\u0e31\u0e07\u0e40\u0e2a\u0e37\u0e2d"
    ],
    "wof:name":"Ban Phanang Suea",
    "wof:placetype":"locality"
},
  "geometry": {"coordinates":[101.77494,15.72392],"type":"Point"}
}