{
  "type": "Feature",
  "properties": {
    "gn:admin1_code":"76.0",
    "gn:asciiname":"Ban Phukhao Khoen",
    "gn:country_code":"TH",
    "gn:dem":256,
    "gn:feature_class":"P",
    "gn:feature_code":"PPL",
    "gn:name":"Ban Phukhao Khoen",
    "gn:population":0,
    "gn:timezone":"Asia/Bangkok",
    "iso:country":"TH",
    "name:tha_x_preferred":[
        "\u0e1a\u0e49\u0e32\u0e19\u0e20\u0e39\u0e40\u0e02\u0e32\u0e40\u0e02\u0e34\u0e19"
    ],
    "wof:name":"Ban Phukhao Khoen",
    "wof:placetype":"locality"
},
  "geometry": {"coordinates":[102.47292,17.35717],"type":"Point"}
}