{
  "type": "Feature",
  "properties": {
    "gn:admin1_code":"12.0",
    "gn:asciiname":"Ban Bang Ma",
    "gn:cc2":"TH",
    "gn:country_code":"TH",
    "gn:dem":45,
    "gn:feature_class":"P",
    "gn:feature_code":"PPL",
    "gn:name":"Ban Bang Ma",
    "gn:population":0,
    "gn:timezone":"Asia/Bangkok",
    "iso:country":"TH",
    "name:und_x_variant":[
        "Ban Bang Ba",
        "B\u0101n B\u0101ng Pa",
        "Bang Ba",
        "Ban Bang Ma"
    ],
    "wof:name":"Ban Bang Ma",
    "wof:placetype":"locality"
},
  "geometry": {"coordinates":[100.06667,16.83333],"type":"Point"}
}