{
  "type": "Feature",
  "properties": {
    "gn:admin1_code":"67.0",
    "gn:asciiname":"Ban Soi 9",
    "gn:country_code":"TH",
    "gn:dem":36,
    "gn:feature_class":"P",
    "gn:feature_code":"PPL",
    "gn:name":"Ban Soi 9",
    "gn:population":0,
    "gn:timezone":"Asia/Bangkok",
    "iso:country":"TH",
    "name:tha_x_preferred":[
        "\u0e1a\u0e49\u0e32\u0e19\u0e0b\u0e2d\u0e22 \u0e40\u0e01\u0e49\u0e32"
    ],
    "name:tha_x_variant":[
        "Ban Soi 9"
    ],
    "name:und_x_variant":[
        "Ban Soi Kao"
    ],
    "wof:name":"Ban Soi 9",
    "wof:placetype":"locality"
},
  "geometry": {"coordinates":[100.00736000000001,6.87006],"type":"Point"}
}