{
  "type": "Feature",
  "properties": {
    "gn:admin1_code":"75.0",
    "gn:asciiname":"Ban Kao Ko",
    "gn:country_code":"TH",
    "gn:dem":144,
    "gn:feature_class":"P",
    "gn:feature_code":"PPL",
    "gn:name":"Ban Kao Ko",
    "gn:population":0,
    "gn:timezone":"Asia/Bangkok",
    "iso:country":"TH",
    "name:tha_x_preferred":[
        "\u0e1a\u0e49\u0e32\u0e19\u0e40\u0e01\u0e48\u0e32\u0e42\u0e01"
    ],
    "wof:name":"Ban Kao Ko",
    "wof:placetype":"locality"
},
  "geometry": {"coordinates":[105.25694,15.54031],"type":"Point"}
}