{
  "type": "Feature",
  "properties": {
    "gn:admin1_code":"29",
    "gn:asciiname":"Ban Piam",
    "gn:country_code":"TH",
    "gn:dem":152,
    "gn:feature_class":"P",
    "gn:feature_code":"PPL",
    "gn:name":"Ban Piam",
    "gn:population":0,
    "gn:timezone":"Asia/Bangkok",
    "iso:country":"TH",
    "name:tha_x_preferred":[
        "\u0e1a\u0e49\u0e32\u0e19\u0e40\u0e1b\u0e35\u0e48\u0e22\u0e21"
    ],
    "wof:name":"Ban Piam",
    "wof:placetype":"locality"
},
  "geometry": {"coordinates":[103.47718999999999,14.77414],"type":"Point"}
}