{
  "type": "Feature",
  "properties": {
    "gn:admin1_code":"80.0",
    "gn:asciiname":"Ban Sala Lamduan",
    "gn:country_code":"TH",
    "gn:dem":40,
    "gn:feature_class":"P",
    "gn:feature_code":"PPL",
    "gn:name":"Ban Sala Lamduan",
    "gn:population":0,
    "gn:timezone":"Asia/Bangkok",
    "iso:country":"TH",
    "name:tha_x_preferred":[
        "\u0e1a\u0e49\u0e32\u0e19\u0e28\u0e32\u0e25\u0e32\u0e25\u0e33\u0e14\u0e27\u0e19"
    ],
    "name:und_x_variant":[
        "Ban Sala Lamdwan",
        "Ban Sala Lamduan"
    ],
    "wof:lang_x_official":[
        "tha"
    ],
    "wof:lang_x_spoken":[
        "tha"
    ],
    "wof:name":"Ban Sala Lamduan",
    "wof:placetype":"locality"
},
  "geometry": {"coordinates":[102.00745999999999,13.87958],"type":"Point"}
}