{
  "type": "Feature",
  "properties": {
    "gn:admin1_code":"66.0",
    "gn:asciiname":"Ban Khuan Kai Khieo (1)",
    "gn:cc2":"TH",
    "gn:country_code":"TH",
    "gn:dem":6,
    "gn:feature_class":"P",
    "gn:feature_code":"PPL",
    "gn:name":"Ban Khuan Kai Khieo (1)",
    "gn:population":0,
    "gn:timezone":"Asia/Bangkok",
    "iso:country":"TH",
    "name:und_x_variant":[
        "Ban Khuan Ke Khieo",
        "Ban Khuan Kai Khieo (1)"
    ],
    "wof:name":"Ban Khuan Kai Khieo (1)",
    "wof:placetype":"locality"
},
  "geometry": {"coordinates":[100.26667,7.36667],"type":"Point"}
}