{
  "type": "Feature",
  "properties": {
    "gn:admin1_code":"78.0",
    "gn:asciiname":"Ban Det Chamnong",
    "gn:country_code":"TH",
    "gn:dem":177,
    "gn:feature_class":"P",
    "gn:feature_code":"PPL",
    "gn:name":"Ban Det Chamnong",
    "gn:population":0,
    "gn:timezone":"Asia/Bangkok",
    "iso:country":"TH",
    "name:tha_x_preferred":[
        "Ban Det Chamnong"
    ],
    "name:tha_x_variant":[
        "\u0e1a\u0e49\u0e32\u0e19\u0e40\u0e14\u0e0a\u0e08\u0e33\u0e19\u0e07\u0e04\u0e4c"
    ],
    "wof:lang_x_official":[
        "tha"
    ],
    "wof:lang_x_spoken":[
        "tha"
    ],
    "wof:name":"Ban Det Chamnong",
    "wof:placetype":"locality"
},
  "geometry": {"coordinates":[104.56178,16.36717],"type":"Point"}
}