{
  "type": "Feature",
  "properties": {
    "gn:admin1_code":"36.0",
    "gn:asciiname":"Ban Phit Phian",
    "gn:country_code":"TH",
    "gn:dem":12,
    "gn:feature_class":"P",
    "gn:feature_code":"PPL",
    "gn:name":"Ban Phit Phian",
    "gn:population":0,
    "gn:timezone":"Asia/Bangkok",
    "iso:country":"TH",
    "name:tha_x_preferred":[
        "\u0e1a\u0e49\u0e32\u0e19\u0e1e\u0e34\u0e15\u0e40\u0e1e\u0e35\u0e22\u0e19"
    ],
    "name:und_x_variant":[
        "Ban Pita Pian",
        "Ban Phittaphian",
        "Ban Phit Phian"
    ],
    "wof:lang_x_official":[
        "tha"
    ],
    "wof:lang_x_spoken":[
        "tha"
    ],
    "wof:name":"Ban Phit Phian",
    "wof:placetype":"locality"
},
  "geometry": {"coordinates":[100.54577999999999,14.60497],"type":"Point"}
}