{
  "type": "Feature",
  "properties": {
    "gn:admin1_code":"70.0",
    "gn:asciiname":"Ban Bu Ke Bue Lo",
    "gn:country_code":"TH",
    "gn:dem":113,
    "gn:feature_class":"P",
    "gn:feature_code":"PPL",
    "gn:name":"Ban Bu Ke Bue Lo",
    "gn:population":0,
    "gn:timezone":"Asia/Bangkok",
    "iso:country":"TH",
    "name:tha_x_preferred":[
        "\u0e1a\u0e49\u0e32\u0e19\u0e1a\u0e39\u0e40\u0e01\u0e4a\u0e30\u0e1a\u0e37\u0e2d\u0e40\u0e25\u0e32\u0e30"
    ],
    "wof:name":"Ban Bu Ke Bue Lo",
    "wof:placetype":"locality"
},
  "geometry": {"coordinates":[101.37544,6.25597],"type":"Point"}
}