{
  "type": "Feature",
  "properties": {
    "gn:admin1_code":"44.0",
    "gn:asciiname":"Ban Talat Rongsi Lang",
    "gn:country_code":"TH",
    "gn:dem":4,
    "gn:feature_class":"P",
    "gn:feature_code":"PPL",
    "gn:name":"Ban Talat Rongsi Lang",
    "gn:population":0,
    "gn:timezone":"Asia/Bangkok",
    "iso:country":"TH",
    "name:tha_x_preferred":[
        "\u0e1a\u0e49\u0e32\u0e19\u0e15\u0e25\u0e32\u0e14\u0e42\u0e23\u0e07\u0e2a\u0e35\u0e25\u0e48\u0e32\u0e07"
    ],
    "wof:name":"Ban Talat Rongsi Lang",
    "wof:placetype":"locality"
},
  "geometry": {"coordinates":[101.09269999999999,13.62203],"type":"Point"}
}