{
  "type": "Feature",
  "properties": {
    "gn:admin1_code":"3.0",
    "gn:asciiname":"Ban Ngam Mueang",
    "gn:country_code":"TH",
    "gn:dem":375,
    "gn:feature_class":"P",
    "gn:feature_code":"PPL",
    "gn:name":"Ban Ngam Mueang",
    "gn:population":0,
    "gn:timezone":"Asia/Bangkok",
    "iso:country":"TH",
    "name:tha_x_preferred":[
        "\u0e1a\u0e49\u0e32\u0e19\u0e07\u0e32\u0e21\u0e40\u0e21\u0e37\u0e2d\u0e07"
    ],
    "wof:name":"Ban Ngam Mueang",
    "wof:placetype":"locality"
},
  "geometry": {"coordinates":[100.31844,19.97042],"type":"Point"}
}