{
  "type": "Feature",
  "properties": {
    "gn:admin1_code":"2.0",
    "gn:asciiname":"Ban Pang Mo",
    "gn:country_code":"TH",
    "gn:dem":553,
    "gn:feature_class":"P",
    "gn:feature_code":"PPL",
    "gn:name":"Ban Pang Mo",
    "gn:population":0,
    "gn:timezone":"Asia/Bangkok",
    "iso:country":"TH",
    "name:tha_x_preferred":[
        "\u0e1a\u0e49\u0e32\u0e19\u0e1b\u0e32\u0e07\u0e42\u0e21\u0e48"
    ],
    "wof:name":"Ban Pang Mo",
    "wof:placetype":"locality"
},
  "geometry": {"coordinates":[99.05114,19.50467],"type":"Point"}
}