{
  "type": "Feature",
  "properties": {
    "gn:admin1_code":"18.0",
    "gn:asciiname":"Ban Nong Pokkati",
    "gn:country_code":"TH",
    "gn:dem":274,
    "gn:feature_class":"P",
    "gn:feature_code":"PPL",
    "gn:name":"Ban Nong Pokkati",
    "gn:population":0,
    "gn:timezone":"Asia/Bangkok",
    "iso:country":"TH",
    "name:tha_x_preferred":[
        "\u0e1a\u0e49\u0e32\u0e19\u0e2b\u0e19\u0e2d\u0e07\u0e1b\u0e01\u0e15\u0e34"
    ],
    "wof:name":"Ban Nong Pokkati",
    "wof:placetype":"locality"
},
  "geometry": {"coordinates":[101.31286,17.63494],"type":"Point"}
}