{
  "type": "Feature",
  "properties": {
    "gn:admin1_code":"3.0",
    "gn:asciiname":"Ban Dong",
    "gn:country_code":"TH",
    "gn:dem":388,
    "gn:feature_class":"P",
    "gn:feature_code":"PPL",
    "gn:name":"Ban Dong",
    "gn:population":0,
    "gn:timezone":"Asia/Bangkok",
    "iso:country":"TH",
    "name:tha_x_preferred":[
        "\u0e1a\u0e49\u0e32\u0e19\u0e14\u0e07"
    ],
    "wof:name":"Ban Dong",
    "wof:placetype":"locality"
},
  "geometry": {"coordinates":[99.97214,20.23523],"type":"Point"}
}