{
  "type": "Feature",
  "properties": {
    "gn:admin1_code":"41.0",
    "gn:asciiname":"Ban Huai Kang Pla",
    "gn:country_code":"TH",
    "gn:dem":579,
    "gn:feature_class":"P",
    "gn:feature_code":"PPL",
    "gn:name":"Ban Huai Kang Pla",
    "gn:population":0,
    "gn:timezone":"Asia/Bangkok",
    "iso:country":"TH",
    "name:tha_x_preferred":[
        "\u0e1a\u0e49\u0e32\u0e19\u0e2b\u0e49\u0e27\u0e22\u0e01\u0e49\u0e32\u0e07\u0e1b\u0e25\u0e32"
    ],
    "wof:name":"Ban Huai Kang Pla",
    "wof:placetype":"locality"
},
  "geometry": {"coordinates":[100.15752000000001,18.92506],"type":"Point"}
}