{
  "type": "Feature",
  "properties": {
    "gn:admin1_code":"3.0",
    "gn:asciiname":"Ban San Mana",
    "gn:country_code":"TH",
    "gn:dem":384,
    "gn:feature_class":"P",
    "gn:feature_code":"PPL",
    "gn:name":"Ban San Mana",
    "gn:population":0,
    "gn:timezone":"Asia/Bangkok",
    "iso:country":"TH",
    "name:tha_x_preferred":[
        "\u0e1a\u0e49\u0e32\u0e19\u0e2a\u0e31\u0e19\u0e21\u0e30\u0e19\u0e30"
    ],
    "name:und_x_variant":[
        "Ban Sam Mana"
    ],
    "wof:name":"Ban San Mana",
    "wof:placetype":"locality"
},
  "geometry": {"coordinates":[99.93753,20.43592],"type":"Point"}
}