{
  "type": "Feature",
  "properties": {
    "gn:admin1_code":"14.0",
    "gn:asciiname":"Ban Huai Pun",
    "gn:country_code":"TH",
    "gn:dem":169,
    "gn:feature_class":"P",
    "gn:feature_code":"PPL",
    "gn:name":"Ban Huai Pun",
    "gn:population":0,
    "gn:timezone":"Asia/Bangkok",
    "iso:country":"TH",
    "name:tha_x_preferred":[
        "\u0e1a\u0e49\u0e32\u0e19\u0e2b\u0e49\u0e27\u0e22\u0e1b\u0e39\u0e19"
    ],
    "name:und_x_variant":[
        "H\u016bip\u016bn",
        "B\u0101n Huai Pui",
        "Ban Huai Pun"
    ],
    "wof:name":"Ban Huai Pun",
    "wof:placetype":"locality"
},
  "geometry": {"coordinates":[101.18161000000001,16.80894],"type":"Point"}
}