{
  "type": "Feature",
  "properties": {
    "gn:admin1_code":"23.0",
    "gn:asciiname":"Ban Kham Nam Sai",
    "gn:country_code":"TH",
    "gn:dem":179,
    "gn:feature_class":"P",
    "gn:feature_code":"PPL",
    "gn:name":"Ban Kham Nam Sai",
    "gn:population":0,
    "gn:timezone":"Asia/Bangkok",
    "iso:country":"TH",
    "name:tha_x_preferred":[
        "\u0e1a\u0e49\u0e32\u0e19\u0e04\u0e33\u0e19\u0e49\u0e33\u0e43\u0e2a"
    ],
    "wof:name":"Ban Kham Nam Sai",
    "wof:placetype":"locality"
},
  "geometry": {"coordinates":[103.49469000000001,16.87692],"type":"Point"}
}