{
  "type": "Feature",
  "properties": {
    "gn:admin1_code":"46.0",
    "gn:asciiname":"Ban Na Wang Hin",
    "gn:country_code":"TH",
    "gn:dem":12,
    "gn:feature_class":"P",
    "gn:feature_code":"PPL",
    "gn:name":"Ban Na Wang Hin",
    "gn:population":0,
    "gn:timezone":"Asia/Bangkok",
    "iso:country":"TH",
    "name:tha_x_preferred":[
        "\u0e1a\u0e49\u0e32\u0e19\u0e19\u0e32\u0e27\u0e31\u0e07\u0e2b\u0e34\u0e19"
    ],
    "wof:name":"Ban Na Wang Hin",
    "wof:placetype":"locality"
},
  "geometry": {"coordinates":[101.22331,13.46186],"type":"Point"}
}