{
  "type": "Feature",
  "properties": {
    "gn:admin1_code":"11.0",
    "gn:asciiname":"Ban Nong Tha Mai",
    "gn:country_code":"TH",
    "gn:dem":57,
    "gn:feature_class":"P",
    "gn:feature_code":"PPL",
    "gn:name":"Ban Nong Tha Mai",
    "gn:population":0,
    "gn:timezone":"Asia/Bangkok",
    "iso:country":"TH",
    "name:tha_x_preferred":[
        "\u0e1a\u0e49\u0e32\u0e19\u0e2b\u0e19\u0e2d\u0e07\u0e17\u0e48\u0e32\u0e44\u0e21\u0e49"
    ],
    "wof:name":"Ban Nong Tha Mai",
    "wof:placetype":"locality"
},
  "geometry": {"coordinates":[99.89843999999999,16.67483],"type":"Point"}
}