{
  "type": "Feature",
  "properties": {
    "gn:admin1_code":"31.0",
    "gn:asciiname":"Ban Ba Ngo Cha Ma Kae",
    "gn:country_code":"TH",
    "gn:dem":29,
    "gn:feature_class":"P",
    "gn:feature_code":"PPL",
    "gn:name":"Ban Ba Ngo Cha Ma Kae",
    "gn:population":0,
    "gn:timezone":"Asia/Bangkok",
    "iso:country":"TH",
    "name:tha_x_preferred":[
        "\u0e1a\u0e49\u0e32\u0e19\u0e1a\u0e32\u0e42\u0e07\u0e08\u0e30\u0e21\u0e32\u0e41\u0e01\u0e4a\u0e30"
    ],
    "wof:name":"Ban Ba Ngo Cha Ma Kae",
    "wof:placetype":"locality"
},
  "geometry": {"coordinates":[101.88625,5.92008],"type":"Point"}
}