{
  "type": "Feature",
  "properties": {
    "gn:admin1_code":"28",
    "gn:asciiname":"Ban Ku Ruesi",
    "gn:country_code":"TH",
    "gn:dem":151,
    "gn:feature_class":"P",
    "gn:feature_code":"PPL",
    "gn:name":"Ban Ku Ruesi",
    "gn:population":0,
    "gn:timezone":"Asia/Bangkok",
    "iso:country":"TH",
    "name:tha_x_preferred":[
        "\u0e1a\u0e49\u0e32\u0e19\u0e01\u0e39\u0e48\u0e24\u0e32\u0e29\u0e35"
    ],
    "wof:name":"Ban Ku Ruesi",
    "wof:placetype":"locality"
},
  "geometry": {"coordinates":[102.80333,15.54394],"type":"Point"}
}