{
  "type": "Feature",
  "properties": {
    "gn:admin1_code":"36",
    "gn:asciiname":"Ban Tha Kwian",
    "gn:country_code":"TH",
    "gn:dem":7,
    "gn:feature_class":"P",
    "gn:feature_code":"PPL",
    "gn:name":"Ban Tha Kwian",
    "gn:population":0,
    "gn:timezone":"Asia/Bangkok",
    "iso:country":"TH",
    "name:tha_x_preferred":[
        "\u0e1a\u0e49\u0e32\u0e19\u0e17\u0e48\u0e32\u0e40\u0e01\u0e27\u0e35\u0e22\u0e19"
    ],
    "wof:name":"Ban Tha Kwian",
    "wof:placetype":"locality"
},
  "geometry": {"coordinates":[100.46781,14.17972],"type":"Point"}
}