{
  "type": "Feature",
  "properties": {
    "gn:admin1_code":"66.0",
    "gn:asciiname":"Ban Pak Khriao",
    "gn:country_code":"TH",
    "gn:dem":7,
    "gn:feature_class":"P",
    "gn:feature_code":"PPL",
    "gn:name":"Ban Pak Khriao",
    "gn:population":0,
    "gn:timezone":"Asia/Bangkok",
    "iso:country":"TH",
    "name:tha_x_preferred":[
        "\u0e1a\u0e49\u0e32\u0e19\u0e1b\u0e32\u0e01\u0e40\u0e04\u0e23\u0e35\u0e22\u0e27"
    ],
    "wof:name":"Ban Pak Khriao",
    "wof:placetype":"locality"
},
  "geometry": {"coordinates":[100.29378,7.35139],"type":"Point"}
}