{
  "type": "Feature",
  "properties": {
    "gn:admin1_code":"56.0",
    "gn:asciiname":"Ban Nong Faep",
    "gn:country_code":"TH",
    "gn:dem":16,
    "gn:feature_class":"P",
    "gn:feature_code":"PPL",
    "gn:name":"Ban Nong Faep",
    "gn:population":0,
    "gn:timezone":"Asia/Bangkok",
    "iso:country":"TH",
    "name:tha_x_preferred":[
        "\u0e1a\u0e49\u0e32\u0e19\u0e2b\u0e19\u0e2d\u0e07\u0e41\u0e1f\u0e1a"
    ],
    "name:und_x_variant":[
        "Hn\u014dngfep",
        "Ban Nong Faep"
    ],
    "wof:name":"Ban Nong Faep",
    "wof:placetype":"locality"
},
  "geometry": {"coordinates":[99.90911,12.97458],"type":"Point"}
}