{
  "type": "Feature",
  "properties": {
    "gn:admin1_code":"3.0",
    "gn:asciiname":"Ban I Ko Pa Miang",
    "gn:country_code":"TH",
    "gn:dem":460,
    "gn:feature_class":"P",
    "gn:feature_code":"PPL",
    "gn:name":"Ban I Ko Pa Miang",
    "gn:population":0,
    "gn:timezone":"Asia/Bangkok",
    "iso:country":"TH",
    "name:tha_x_preferred":[
        "\u0e1a\u0e49\u0e32\u0e19\u0e2d\u0e35\u0e01\u0e49\u0e2d\u0e1b\u0e48\u0e32\u0e40\u0e21\u0e35\u0e48\u0e22\u0e07"
    ],
    "wof:lang_x_official":[
        "tha"
    ],
    "wof:lang_x_spoken":[
        "tha"
    ],
    "wof:name":"Ban I Ko Pa Miang",
    "wof:placetype":"locality"
},
  "geometry": {"coordinates":[99.77719,20.19456],"type":"Point"}
}