{
  "type": "Feature",
  "properties": {
    "gn:admin1_code":"10.0",
    "gn:asciiname":"Ban Khum",
    "gn:country_code":"TH",
    "gn:dem":80,
    "gn:feature_class":"P",
    "gn:feature_code":"PPL",
    "gn:name":"Ban Khum",
    "gn:population":0,
    "gn:timezone":"Asia/Bangkok",
    "iso:country":"TH",
    "name:tha_x_preferred":[
        "\u0e1a\u0e49\u0e32\u0e19\u0e04\u0e38\u0e49\u0e21"
    ],
    "name:und_x_variant":[
        "B\u0101n Kum",
        "Ban Khum"
    ],
    "wof:name":"Ban Khum",
    "wof:placetype":"locality"
},
  "geometry": {"coordinates":[100.03516,17.6446],"type":"Point"}
}