{
  "type": "Feature",
  "properties": {
    "gn:admin1_code":"50.0",
    "gn:asciiname":"Ban Thung Rakhang",
    "gn:country_code":"TH",
    "gn:dem":23,
    "gn:feature_class":"P",
    "gn:feature_code":"PPL",
    "gn:name":"Ban Thung Rakhang",
    "gn:population":0,
    "gn:timezone":"Asia/Bangkok",
    "iso:country":"TH",
    "name:tha_x_preferred":[
        "\u0e1a\u0e49\u0e32\u0e19\u0e17\u0e38\u0e48\u0e07\u0e23\u0e30\u0e06\u0e31\u0e07"
    ],
    "wof:name":"Ban Thung Rakhang",
    "wof:placetype":"locality"
},
  "geometry": {"coordinates":[99.68728,14.06297],"type":"Point"}
}