{
  "type": "Feature",
  "properties": {
    "gn:admin1_code":"43.0",
    "gn:asciiname":"Ban Khlong Yi Sip Sam",
    "gn:country_code":"TH",
    "gn:dem":9,
    "gn:feature_class":"P",
    "gn:feature_code":"PPL",
    "gn:name":"Ban Khlong Yi Sip Sam",
    "gn:population":0,
    "gn:timezone":"Asia/Bangkok",
    "iso:country":"TH",
    "name:tha_x_preferred":[
        "\u0e1a\u0e49\u0e32\u0e19\u0e04\u0e25\u0e2d\u0e07 \u0e22\u0e35\u0e48\u0e2a\u0e34\u0e1a\u0e2a\u0e32\u0e21"
    ],
    "wof:name":"Ban Khlong Yi Sip Sam",
    "wof:placetype":"locality"
},
  "geometry": {"coordinates":[101.00921,14.03028],"type":"Point"}
}