{
  "type": "Feature",
  "properties": {
    "gn:admin1_code":"55.0",
    "gn:asciiname":"Ban Nai Tha Nuea",
    "gn:country_code":"TH",
    "gn:dem":3,
    "gn:feature_class":"P",
    "gn:feature_code":"PPL",
    "gn:name":"Ban Nai Tha Nuea",
    "gn:population":0,
    "gn:timezone":"Asia/Bangkok",
    "iso:country":"TH",
    "name:tha_x_preferred":[
        "\u0e1a\u0e49\u0e32\u0e19\u0e43\u0e19\u0e17\u0e48\u0e32\u0e40\u0e19\u0e37\u0e49\u0e2d"
    ],
    "wof:name":"Ban Nai Tha Nuea",
    "wof:placetype":"locality"
},
  "geometry": {"coordinates":[100.20632999999999,13.60803],"type":"Point"}
}