{
  "type": "Feature",
  "properties": {
    "gn:admin1_code":"15.0",
    "gn:asciiname":"Ban Pang Rai",
    "gn:country_code":"TH",
    "gn:dem":483,
    "gn:feature_class":"P",
    "gn:feature_code":"PPL",
    "gn:name":"Ban Pang Rai",
    "gn:population":0,
    "gn:timezone":"Asia/Bangkok",
    "iso:country":"TH",
    "wof:name":"Ban Pang Rai",
    "wof:placetype":"locality"
},
  "geometry": {"coordinates":[99.30786000000001,15.13582],"type":"Point"}
}