{
  "type": "Feature",
  "properties": {
    "gn:admin1_code":"68.0",
    "gn:asciiname":"Ban Sai Khrop",
    "gn:country_code":"TH",
    "gn:dem":21,
    "gn:feature_class":"P",
    "gn:feature_code":"PPL",
    "gn:name":"Ban Sai Khrop",
    "gn:population":0,
    "gn:timezone":"Asia/Bangkok",
    "iso:country":"TH",
    "name:tha_x_preferred":[
        "\u0e1a\u0e49\u0e32\u0e19\u0e44\u0e17\u0e23\u0e04\u0e23\u0e2d\u0e1a"
    ],
    "wof:name":"Ban Sai Khrop",
    "wof:placetype":"locality"
},
  "geometry": {"coordinates":[100.63594000000001,7.04103],"type":"Point"}
}