{
  "type": "Feature",
  "properties": {
    "gn:admin1_code":"72.0",
    "gn:asciiname":"Ban Mek Ta Ha",
    "gn:country_code":"TH",
    "gn:dem":172,
    "gn:feature_class":"P",
    "gn:feature_code":"PPL",
    "gn:name":"Ban Mek Ta Ha",
    "gn:population":0,
    "gn:timezone":"Asia/Bangkok",
    "iso:country":"TH",
    "name:tha_x_preferred":[
        "\u0e1a\u0e49\u0e32\u0e19\u0e40\u0e21\u0e06\u0e15\u0e32\u0e2b\u0e32"
    ],
    "wof:name":"Ban Mek Ta Ha",
    "wof:placetype":"locality"
},
  "geometry": {"coordinates":[104.41658,16.09364],"type":"Point"}
}