{
  "type": "Feature",
  "properties": {
    "gn:admin1_code":"52.0",
    "gn:asciiname":"Ban Tha I Pa",
    "gn:country_code":"TH",
    "gn:dem":94,
    "gn:feature_class":"P",
    "gn:feature_code":"PPL",
    "gn:name":"Ban Tha I Pa",
    "gn:population":0,
    "gn:timezone":"Asia/Bangkok",
    "iso:country":"TH",
    "name:tha_x_preferred":[
        "\u0e1a\u0e49\u0e32\u0e19\u0e17\u0e48\u0e32\u0e2d\u0e35\u0e1b\u0e30"
    ],
    "wof:name":"Ban Tha I Pa",
    "wof:placetype":"locality"
},
  "geometry": {"coordinates":[99.42897000000001,13.62867],"type":"Point"}
}