{
  "type": "Feature",
  "properties": {
    "gn:admin1_code":"43.0",
    "gn:asciiname":"Ban Ko Kraphi",
    "gn:country_code":"TH",
    "gn:dem":9,
    "gn:feature_class":"P",
    "gn:feature_code":"PPL",
    "gn:name":"Ban Ko Kraphi",
    "gn:population":0,
    "gn:timezone":"Asia/Bangkok",
    "iso:country":"TH",
    "name:tha_x_preferred":[
        "\u0e1a\u0e49\u0e32\u0e19\u0e40\u0e01\u0e32\u0e30\u0e01\u0e23\u0e30\u0e1e\u0e35\u0e49"
    ],
    "name:und_x_variant":[
        "Ban Ko Kaphi"
    ],
    "wof:name":"Ban Ko Kraphi",
    "wof:placetype":"locality"
},
  "geometry": {"coordinates":[101.10003,14.23194],"type":"Point"}
}