{
  "type": "Feature",
  "properties": {
    "gn:admin1_code":"38.0",
    "gn:asciiname":"Ban Surao Suan",
    "gn:country_code":"TH",
    "gn:dem":7,
    "gn:feature_class":"P",
    "gn:feature_code":"PPL",
    "gn:name":"Ban Surao Suan",
    "gn:population":0,
    "gn:timezone":"Asia/Bangkok",
    "iso:country":"TH",
    "name:tha_x_preferred":[
        "\u0e1a\u0e49\u0e32\u0e19\u0e2a\u0e38\u0e40\u0e2b\u0e23\u0e48\u0e32\u0e2a\u0e27\u0e19"
    ],
    "wof:name":"Ban Surao Suan",
    "wof:placetype":"locality"
},
  "geometry": {"coordinates":[100.46505999999999,13.89408],"type":"Point"}
}