{
  "type": "Feature",
  "properties": {
    "gn:admin1_code":"2.0",
    "gn:asciiname":"Ban Tha Lo",
    "gn:country_code":"TH",
    "gn:dem":279,
    "gn:feature_class":"P",
    "gn:feature_code":"PPL",
    "gn:name":"Ban Tha Lo",
    "gn:population":0,
    "gn:timezone":"Asia/Bangkok",
    "iso:country":"TH",
    "name:tha_x_preferred":[
        "\u0e1a\u0e49\u0e32\u0e19\u0e17\u0e48\u0e32\u0e25\u0e49\u0e2d"
    ],
    "wof:name":"Ban Tha Lo",
    "wof:placetype":"locality"
},
  "geometry": {"coordinates":[98.75758,18.43653],"type":"Point"}
}