{
  "type": "Feature",
  "properties": {
    "gn:admin1_code":"20.0",
    "gn:asciiname":"Ban Dong Tong",
    "gn:country_code":"TH",
    "gn:dem":178,
    "gn:feature_class":"P",
    "gn:feature_code":"PPL",
    "gn:name":"Ban Dong Tong",
    "gn:population":0,
    "gn:timezone":"Asia/Bangkok",
    "iso:country":"TH",
    "name:tha_x_preferred":[
        "\u0e1a\u0e49\u0e32\u0e19\u0e14\u0e07\u0e15\u0e49\u0e2d\u0e07"
    ],
    "wof:name":"Ban Dong Tong",
    "wof:placetype":"locality"
},
  "geometry": {"coordinates":[103.39472000000001,17.55772],"type":"Point"}
}