{
  "type": "Feature",
  "properties": {
    "gn:admin1_code":"64.0",
    "gn:asciiname":"Ban Kasom Tai",
    "gn:country_code":"TH",
    "gn:dem":43,
    "gn:feature_class":"P",
    "gn:feature_code":"PPL",
    "gn:name":"Ban Kasom Tai",
    "gn:population":0,
    "gn:timezone":"Asia/Bangkok",
    "iso:country":"TH",
    "name:tha_x_preferred":[
        "\u0e1a\u0e49\u0e32\u0e19\u0e01\u0e30\u0e42\u0e2a\u0e21\u0e43\u0e15\u0e49"
    ],
    "wof:name":"Ban Kasom Tai",
    "wof:placetype":"locality"
},
  "geometry": {"coordinates":[99.66974999999999,8.04381],"type":"Point"}
}