{
  "type": "Feature",
  "properties": {
    "gn:admin1_code":"20.0",
    "gn:asciiname":"Ban Huai Nam Thiang",
    "gn:country_code":"TH",
    "gn:dem":179,
    "gn:feature_class":"P",
    "gn:feature_code":"PPL",
    "gn:name":"Ban Huai Nam Thiang",
    "gn:population":0,
    "gn:timezone":"Asia/Bangkok",
    "iso:country":"TH",
    "name:tha_x_preferred":[
        "\u0e1a\u0e49\u0e32\u0e19\u0e2b\u0e49\u0e27\u0e22\u0e19\u0e49\u0e33\u0e40\u0e17\u0e35\u0e48\u0e22\u0e07"
    ],
    "name:und_x_variant":[
        "Ban Nam Thiang"
    ],
    "wof:lang_x_official":[
        "tha"
    ],
    "wof:lang_x_spoken":[
        "tha"
    ],
    "wof:name":"Ban Huai Nam Thiang",
    "wof:placetype":"locality"
},
  "geometry": {"coordinates":[103.63686,17.80362000000001],"type":"Point"}
}