{
  "type": "Feature",
  "properties": {
    "gn:admin1_code":"5.0",
    "gn:asciiname":"Ban Tha Thung Phai",
    "gn:country_code":"TH",
    "gn:dem":442,
    "gn:feature_class":"P",
    "gn:feature_code":"PPL",
    "gn:name":"Ban Tha Thung Phai",
    "gn:population":0,
    "gn:timezone":"Asia/Bangkok",
    "iso:country":"TH",
    "name:tha_x_preferred":[
        "\u0e1a\u0e49\u0e32\u0e19\u0e17\u0e32\u0e17\u0e38\u0e48\u0e07\u0e44\u0e1c\u0e48"
    ],
    "name:und_x_variant":[
        "Ban Thung",
        "Ban Tha Thung Phai"
    ],
    "wof:name":"Ban Tha Thung Phai",
    "wof:placetype":"locality"
},
  "geometry": {"coordinates":[99.23214,18.52692],"type":"Point"}
}