{
  "type": "Feature",
  "properties": {
    "gn:admin1_code":"69.0",
    "gn:asciiname":"Ban Bin Ya Si Mo",
    "gn:country_code":"TH",
    "gn:dem":14,
    "gn:feature_class":"P",
    "gn:feature_code":"PPL",
    "gn:name":"Ban Bin Ya Si Mo",
    "gn:population":0,
    "gn:timezone":"Asia/Bangkok",
    "iso:country":"TH",
    "name:tha_x_preferred":[
        "\u0e1a\u0e49\u0e32\u0e19\u0e1a\u0e34\u0e19\u0e22\u0e32\u0e2a\u0e35\u0e21\u0e2d"
    ],
    "wof:name":"Ban Bin Ya Si Mo",
    "wof:placetype":"locality"
},
  "geometry": {"coordinates":[101.30789,6.76792],"type":"Point"}
}