{
  "type": "Feature",
  "properties": {
    "gn:admin1_code":"2.0",
    "gn:asciiname":"Ban Si Blae",
    "gn:country_code":"TH",
    "gn:dem":957,
    "gn:feature_class":"P",
    "gn:feature_code":"PPL",
    "gn:name":"Ban Si Blae",
    "gn:population":0,
    "gn:timezone":"Asia/Bangkok",
    "iso:country":"TH",
    "name:tha_x_preferred":[
        "\u0e1a\u0e49\u0e32\u0e19\u0e0b\u0e34\u0e41\u0e1a\u0e25"
    ],
    "wof:name":"Ban Si Blae",
    "wof:placetype":"locality"
},
  "geometry": {"coordinates":[98.36185999999999,17.44825],"type":"Point"}
}