{
  "type": "Feature",
  "properties": {
    "gn:admin1_code":"75.0",
    "gn:asciiname":"Ban Huai Mak Yai",
    "gn:country_code":"TH",
    "gn:dem":132,
    "gn:feature_class":"P",
    "gn:feature_code":"PPL",
    "gn:name":"Ban Huai Mak Yai",
    "gn:population":0,
    "gn:timezone":"Asia/Bangkok",
    "iso:country":"TH",
    "name:tha_x_preferred":[
        "\u0e1a\u0e49\u0e32\u0e19\u0e2b\u0e49\u0e27\u0e22\u0e2b\u0e21\u0e32\u0e01\u0e43\u0e2b\u0e0d\u0e48"
    ],
    "wof:name":"Ban Huai Mak Yai",
    "wof:placetype":"locality"
},
  "geometry": {"coordinates":[105.3535,15.42781],"type":"Point"}
}