{
  "type": "Feature",
  "properties": {
    "gn:admin1_code":"12.0",
    "gn:asciiname":"Ban Nong Ya Ma",
    "gn:country_code":"TH",
    "gn:dem":50,
    "gn:feature_class":"P",
    "gn:feature_code":"PPL",
    "gn:name":"Ban Nong Ya Ma",
    "gn:population":0,
    "gn:timezone":"Asia/Bangkok",
    "iso:country":"TH",
    "name:tha_x_preferred":[
        "\u0e1a\u0e49\u0e32\u0e19\u0e2b\u0e19\u0e2d\u0e07\u0e2b\u0e0d\u0e49\u0e32\u0e21\u0e49\u0e32"
    ],
    "wof:name":"Ban Nong Ya Ma",
    "wof:placetype":"locality"
},
  "geometry": {"coordinates":[100.28728,16.90325],"type":"Point"}
}