{
  "type": "Feature",
  "properties": {
    "gn:admin1_code":"20.0",
    "gn:asciiname":"Ban Kok Plasio",
    "gn:country_code":"TH",
    "gn:dem":202,
    "gn:feature_class":"P",
    "gn:feature_code":"PPL",
    "gn:name":"Ban Kok Plasio",
    "gn:population":0,
    "gn:timezone":"Asia/Bangkok",
    "iso:country":"TH",
    "name:tha_x_preferred":[
        "\u0e1a\u0e49\u0e32\u0e19\u0e01\u0e01\u0e1b\u0e25\u0e32\u0e0b\u0e34\u0e27"
    ],
    "wof:name":"Ban Kok Plasio",
    "wof:placetype":"locality"
},
  "geometry": {"coordinates":[104.0185,16.96097],"type":"Point"}
}