{
  "type": "Feature",
  "properties": {
    "gn:admin1_code":"29",
    "gn:asciiname":"Ban Rattana",
    "gn:country_code":"TH",
    "gn:dem":158,
    "gn:feature_class":"P",
    "gn:feature_code":"PPL",
    "gn:name":"Ban Rattana",
    "gn:population":0,
    "gn:timezone":"Asia/Bangkok",
    "iso:country":"TH",
    "name:tha_x_preferred":[
        "\u0e1a\u0e49\u0e32\u0e19\u0e23\u0e31\u0e15\u0e19\u0e30"
    ],
    "wof:name":"Ban Rattana",
    "wof:placetype":"locality"
},
  "geometry": {"coordinates":[103.61581,14.888],"type":"Point"}
}