{
  "type": "Feature",
  "properties": {
    "gn:admin1_code":"22",
    "gn:asciiname":"Ban Sawong",
    "gn:country_code":"TH",
    "gn:dem":182,
    "gn:feature_class":"P",
    "gn:feature_code":"PPL",
    "gn:name":"Ban Sawong",
    "gn:population":0,
    "gn:timezone":"Asia/Bangkok",
    "iso:country":"TH",
    "name:tha_x_preferred":[
        "\u0e1a\u0e49\u0e32\u0e19\u0e2a\u0e27\u0e2d\u0e07"
    ],
    "wof:name":"Ban Sawong",
    "wof:placetype":"locality"
},
  "geometry": {"coordinates":[102.83978999999999,15.75245],"type":"Point"}
}