{
  "type": "Feature",
  "properties": {
    "gn:admin1_code":"23.0",
    "gn:asciiname":"Ban Kham Chiang Yuen",
    "gn:country_code":"TH",
    "gn:dem":191,
    "gn:feature_class":"P",
    "gn:feature_code":"PPL",
    "gn:name":"Ban Kham Chiang Yuen",
    "gn:population":0,
    "gn:timezone":"Asia/Bangkok",
    "iso:country":"TH",
    "name:tha_x_preferred":[
        "\u0e1a\u0e49\u0e32\u0e19\u0e04\u0e33\u0e40\u0e0a\u0e35\u0e22\u0e07\u0e22\u0e37\u0e19"
    ],
    "wof:name":"Ban Kham Chiang Yuen",
    "wof:placetype":"locality"
},
  "geometry": {"coordinates":[103.51730999999999,16.68367000000001],"type":"Point"}
}