{
  "type": "Feature",
  "properties": {
    "gn:admin1_code":"27.0",
    "gn:asciiname":"Ban Pun",
    "gn:country_code":"TH",
    "gn:dem":177,
    "gn:feature_class":"P",
    "gn:feature_code":"PPL",
    "gn:name":"Ban Pun",
    "gn:population":0,
    "gn:timezone":"Asia/Bangkok",
    "iso:country":"TH",
    "name:tha_x_preferred":[
        "\u0e1a\u0e49\u0e32\u0e19\u0e1b\u0e39\u0e19"
    ],
    "name:und_x_variant":[
        "Ban Nong Pun",
        "Ban Pun"
    ],
    "wof:name":"Ban Pun",
    "wof:placetype":"locality"
},
  "geometry": {"coordinates":[102.15411,15.04889],"type":"Point"}
}