{
  "type": "Feature",
  "properties": {
    "gn:admin1_code":"14.0",
    "gn:asciiname":"Ban Kaeng Ton Mai",
    "gn:country_code":"TH",
    "gn:dem":213,
    "gn:feature_class":"P",
    "gn:feature_code":"PPL",
    "gn:name":"Ban Kaeng Ton Mai",
    "gn:population":0,
    "gn:timezone":"Asia/Bangkok",
    "iso:country":"TH",
    "name:tha_x_preferred":[
        "Ban Kaeng Ton Mai"
    ],
    "name:tha_x_variant":[
        "\u0e1a\u0e49\u0e32\u0e19\u0e41\u0e01\u0e48\u0e07\u0e42\u0e15\u0e19\u0e43\u0e2b\u0e21\u0e48"
    ],
    "name:und_x_variant":[
        "Ban Kaeng Ton"
    ],
    "wof:name":"Ban Kaeng Ton Mai",
    "wof:placetype":"locality"
},
  "geometry": {"coordinates":[101.20492,17.03611],"type":"Point"}
}