{
  "type": "Feature",
  "properties": {
    "gn:admin1_code":"6.0",
    "gn:asciiname":"Ban Mae Chiang Rai Lum",
    "gn:country_code":"TH",
    "gn:dem":154,
    "gn:feature_class":"P",
    "gn:feature_code":"PPL",
    "gn:name":"Ban Mae Chiang Rai Lum",
    "gn:population":0,
    "gn:timezone":"Asia/Bangkok",
    "iso:country":"TH",
    "name:tha_x_preferred":[
        "\u0e1a\u0e49\u0e32\u0e19\u0e41\u0e21\u0e48\u0e40\u0e0a\u0e35\u0e22\u0e07\u0e23\u0e32\u0e22\u0e25\u0e38\u0e48\u0e21"
    ],
    "name:und_x_variant":[
        "M\u0113chienghab",
        "Ban Mea Chiyan Gh\u0101i",
        "Mae Chiang Hai",
        "Ban Mae Chiang Hai",
        "Ban Mae Chiang Rai Lum"
    ],
    "wof:name":"Ban Mae Chiang Rai Lum",
    "wof:placetype":"locality"
},
  "geometry": {"coordinates":[99.11014,17.3755],"type":"Point"}
}