{
  "type": "Feature",
  "properties": {
    "gn:admin1_code":"8.0",
    "gn:asciiname":"Ban Pha Rong",
    "gn:country_code":"TH",
    "gn:dem":227,
    "gn:feature_class":"P",
    "gn:feature_code":"PPL",
    "gn:name":"Ban Pha Rong",
    "gn:population":0,
    "gn:timezone":"Asia/Bangkok",
    "iso:country":"TH",
    "name:tha_x_preferred":[
        "Ban Pha Rong"
    ],
    "name:tha_x_variant":[
        "\u0e1a\u0e49\u0e32\u0e19\u0e1c\u0e32\u0e23\u0e48\u0e2d\u0e07"
    ],
    "wof:name":"Ban Pha Rong",
    "wof:placetype":"locality"
},
  "geometry": {"coordinates":[99.27272000000001,17.18914],"type":"Point"}
}