{
  "type": "Feature",
  "properties": {
    "gn:admin1_code":"10.0",
    "gn:asciiname":"Ban Huai Khai Khiat",
    "gn:country_code":"TH",
    "gn:dem":224,
    "gn:feature_class":"P",
    "gn:feature_code":"PPL",
    "gn:name":"Ban Huai Khai Khiat",
    "gn:population":0,
    "gn:timezone":"Asia/Bangkok",
    "iso:country":"TH",
    "name:tha_x_preferred":[
        "Ban Huai Khai Khiat"
    ],
    "name:tha_x_variant":[
        "\u0e1a\u0e49\u0e32\u0e19\u0e2b\u0e49\u0e27\u0e22\u0e44\u0e02\u0e48\u0e40\u0e02\u0e35\u0e22\u0e14"
    ],
    "name:und_x_variant":[
        "Ban Huai Khai Khieo"
    ],
    "wof:name":"Ban Huai Khai Khiat",
    "wof:placetype":"locality"
},
  "geometry": {"coordinates":[100.86656000000001,17.96917000000001],"type":"Point"}
}