{
  "type": "Feature",
  "properties": {
    "gn:admin1_code":"69.0",
    "gn:asciiname":"Mae Lan",
    "gn:cc2":"TH",
    "gn:country_code":"TH",
    "gn:dem":16,
    "gn:feature_class":"P",
    "gn:feature_code":"PPL",
    "gn:name":"Mae Lan",
    "gn:population":0,
    "gn:timezone":"Asia/Bangkok",
    "iso:country":"TH",
    "name:und_x_variant":[
        "King Amphoe Mae Lan",
        "Mae Lan"
    ],
    "wof:name":"Mae Lan",
    "wof:placetype":"locality"
},
  "geometry": {"coordinates":[101.27139,6.68194],"type":"Point"}
}