{
  "type": "Feature",
  "properties": {
    "gn:admin1_code":"57.0",
    "gn:asciiname":"Ban Tha Fueak",
    "gn:country_code":"TH",
    "gn:dem":10,
    "gn:feature_class":"P",
    "gn:feature_code":"PPL",
    "gn:name":"Ban Tha Fueak",
    "gn:population":0,
    "gn:timezone":"Asia/Bangkok",
    "iso:country":"TH",
    "name:tha_x_preferred":[
        "\u0e1a\u0e49\u0e32\u0e19\u0e17\u0e48\u0e32\u0e40\u0e1d\u0e37\u0e2d\u0e01"
    ],
    "name:und_x_variant":[
        "Ban Tha Fuak"
    ],
    "wof:name":"Ban Tha Fueak",
    "wof:placetype":"locality"
},
  "geometry": {"coordinates":[99.86789,12.07086],"type":"Point"}
}