{
  "type": "Feature",
  "properties": {
    "gn:admin1_code":"25",
    "gn:asciiname":"Ban Phon Pha-ung",
    "gn:country_code":"TH",
    "gn:dem":130,
    "gn:feature_class":"P",
    "gn:feature_code":"PPL",
    "gn:name":"Ban Phon Pha-ung",
    "gn:population":0,
    "gn:timezone":"Asia/Bangkok",
    "iso:country":"TH",
    "name:tha_x_preferred":[
        "\u0e1a\u0e49\u0e32\u0e19\u0e42\u0e1e\u0e19\u0e1e\u0e2d\u0e38\u0e07"
    ],
    "wof:name":"Ban Phon Pha-ung",
    "wof:placetype":"locality"
},
  "geometry": {"coordinates":[103.69219,15.61608],"type":"Point"}
}