{
  "type": "Feature",
  "properties": {
    "gn:admin1_code":"27",
    "gn:asciiname":"Ban Sa Tamok",
    "gn:country_code":"TH",
    "gn:dem":185,
    "gn:feature_class":"P",
    "gn:feature_code":"PPL",
    "gn:name":"Ban Sa Tamok",
    "gn:population":0,
    "gn:timezone":"Asia/Bangkok",
    "iso:country":"TH",
    "name:tha_x_preferred":[
        "\u0e1a\u0e49\u0e32\u0e19\u0e2a\u0e23\u0e30\u0e15\u0e30\u0e2b\u0e21\u0e01"
    ],
    "wof:name":"Ban Sa Tamok",
    "wof:placetype":"locality"
},
  "geometry": {"coordinates":[102.2255,14.84286],"type":"Point"}
}