{
  "type": "Feature",
  "properties": {
    "gn:admin1_code":"16.0",
    "gn:asciiname":"Ban Noen Ya Kha",
    "gn:country_code":"TH",
    "gn:dem":32,
    "gn:feature_class":"P",
    "gn:feature_code":"PPL",
    "gn:name":"Ban Noen Ya Kha",
    "gn:population":0,
    "gn:timezone":"Asia/Bangkok",
    "iso:country":"TH",
    "name:tha_x_preferred":[
        "\u0e1a\u0e49\u0e32\u0e19\u0e40\u0e19\u0e34\u0e19\u0e2b\u0e0d\u0e49\u0e32\u0e04\u0e32"
    ],
    "wof:name":"Ban Noen Ya Kha",
    "wof:placetype":"locality"
},
  "geometry": {"coordinates":[99.99760999999999,15.50472],"type":"Point"}
}