{
  "type": "Feature",
  "properties": {
    "gn:admin1_code":"64.0",
    "gn:asciiname":"Ban Hua Thanon Chai Thale",
    "gn:country_code":"TH",
    "gn:dem":6,
    "gn:feature_class":"P",
    "gn:feature_code":"PPL",
    "gn:name":"Ban Hua Thanon Chai Thale",
    "gn:population":0,
    "gn:timezone":"Asia/Bangkok",
    "iso:country":"TH",
    "name:tha_x_preferred":[
        "\u0e1a\u0e49\u0e32\u0e19\u0e2b\u0e31\u0e27\u0e16\u0e19\u0e19\u0e0a\u0e32\u0e22\u0e17\u0e30\u0e40\u0e25"
    ],
    "wof:lang_x_official":[
        "tha"
    ],
    "wof:lang_x_spoken":[
        "tha"
    ],
    "wof:name":"Ban Hua Thanon Chai Thale",
    "wof:placetype":"locality"
},
  "geometry": {"coordinates":[100.24061,8.36894],"type":"Point"}
}