{
  "type": "Feature",
  "properties": {
    "gn:admin1_code":"53.0",
    "gn:asciiname":"Ban Bang Phikun",
    "gn:country_code":"TH",
    "gn:dem":4,
    "gn:feature_class":"P",
    "gn:feature_code":"PPL",
    "gn:name":"Ban Bang Phikun",
    "gn:population":0,
    "gn:timezone":"Asia/Bangkok",
    "iso:country":"TH",
    "name:tha_x_preferred":[
        "\u0e1a\u0e49\u0e32\u0e19\u0e1a\u0e32\u0e07\u0e1e\u0e34\u0e01\u0e38\u0e25"
    ],
    "name:und_x_variant":[
        "\u0e1a\u0e49\u0e32\u0e19\u0e1a\u0e32\u0e07\u0e1e\u0e34\u0e01\u0e38\u0e25"
    ],
    "wof:name":"Ban Bang Phikun",
    "wof:placetype":"locality"
},
  "geometry": {"coordinates":[100.2368,13.79415],"type":"Point"}
}