{
  "type": "Feature",
  "properties": {
    "gn:admin1_code":"23.0",
    "gn:asciiname":"Ban Noi",
    "gn:country_code":"TH",
    "gn:dem":168,
    "gn:feature_class":"P",
    "gn:feature_code":"PPL",
    "gn:name":"Ban Noi",
    "gn:population":0,
    "gn:timezone":"Asia/Bangkok",
    "iso:country":"TH",
    "name:tha_x_preferred":[
        "\u0e1a\u0e49\u0e32\u0e19\u0e19\u0e49\u0e2d\u0e22"
    ],
    "wof:name":"Ban Noi",
    "wof:placetype":"locality"
},
  "geometry": {"coordinates":[104.04881,16.53178],"type":"Point"}
}