{
  "type": "Feature",
  "properties": {
    "gn:admin1_code":"23.0",
    "gn:asciiname":"Ban Chat Phatthana",
    "gn:country_code":"TH",
    "gn:dem":199,
    "gn:feature_class":"P",
    "gn:feature_code":"PPL",
    "gn:name":"Ban Chat Phatthana",
    "gn:population":0,
    "gn:timezone":"Asia/Bangkok",
    "iso:country":"TH",
    "name:tha_x_preferred":[
        "\u0e1a\u0e49\u0e32\u0e19\u0e0a\u0e32\u0e14\u0e1e\u0e31\u0e12\u0e19\u0e32"
    ],
    "name:und_x_variant":[
        "Ban Chat"
    ],
    "wof:name":"Ban Chat Phatthana",
    "wof:placetype":"locality"
},
  "geometry": {"coordinates":[104.04186,16.79658],"type":"Point"}
}