{
  "type": "Feature",
  "properties": {
    "gn:admin1_code":"9.0",
    "gn:asciiname":"Ban Rai Pla Kang",
    "gn:country_code":"TH",
    "gn:dem":53,
    "gn:feature_class":"P",
    "gn:feature_code":"PPL",
    "gn:name":"Ban Rai Pla Kang",
    "gn:population":0,
    "gn:timezone":"Asia/Bangkok",
    "iso:country":"TH",
    "name:tha_x_preferred":[
        "\u0e1a\u0e49\u0e32\u0e19\u0e2b\u0e23\u0e32\u0e22\u0e1b\u0e25\u0e32\u0e01\u0e49\u0e32\u0e07"
    ],
    "wof:name":"Ban Rai Pla Kang",
    "wof:placetype":"locality"
},
  "geometry": {"coordinates":[99.82406,16.82339],"type":"Point"}
}