{
  "type": "Feature",
  "properties": {
    "gn:admin1_code":"75.0",
    "gn:asciiname":"Ban Na Hang Tai",
    "gn:country_code":"TH",
    "gn:dem":158,
    "gn:feature_class":"P",
    "gn:feature_code":"PPL",
    "gn:name":"Ban Na Hang Tai",
    "gn:population":0,
    "gn:timezone":"Asia/Bangkok",
    "iso:country":"TH",
    "name:tha_x_preferred":[
        "\u0e1a\u0e49\u0e32\u0e19\u0e19\u0e32\u0e2b\u0e49\u0e32\u0e07\u0e43\u0e15\u0e49"
    ],
    "wof:name":"Ban Na Hang Tai",
    "wof:placetype":"locality"
},
  "geometry": {"coordinates":[105.41203,15.70589],"type":"Point"}
}