{
  "type": "Feature",
  "properties": {
    "gn:admin1_code":"75.0",
    "gn:asciiname":"Ban Bua Thong",
    "gn:country_code":"TH",
    "gn:dem":157,
    "gn:feature_class":"P",
    "gn:feature_code":"PPL",
    "gn:name":"Ban Bua Thong",
    "gn:population":0,
    "gn:timezone":"Asia/Bangkok",
    "iso:country":"TH",
    "name:tha_x_preferred":[
        "\u0e1a\u0e49\u0e32\u0e19\u0e1a\u0e31\u0e27\u0e17\u0e2d\u0e07"
    ],
    "wof:name":"Ban Bua Thong",
    "wof:placetype":"locality"
},
  "geometry": {"coordinates":[105.17867,14.78003],"type":"Point"}
}