{
  "type": "Feature",
  "properties": {
    "gn:admin1_code":"6.0",
    "gn:asciiname":"Ban Na Fan",
    "gn:country_code":"TH",
    "gn:dem":280,
    "gn:feature_class":"P",
    "gn:feature_code":"PPL",
    "gn:name":"Ban Na Fan",
    "gn:population":0,
    "gn:timezone":"Asia/Bangkok",
    "iso:country":"TH",
    "name:tha_x_preferred":[
        "\u0e1a\u0e49\u0e32\u0e19\u0e19\u0e32\u0e1f\u0e32\u0e19"
    ],
    "wof:name":"Ban Na Fan",
    "wof:placetype":"locality"
},
  "geometry": {"coordinates":[99.63806,18.12019],"type":"Point"}
}