{
  "type": "Feature",
  "properties": {
    "gn:admin1_code":"26.0",
    "gn:asciiname":"Ban Lup Phek",
    "gn:country_code":"TH",
    "gn:dem":217,
    "gn:feature_class":"P",
    "gn:feature_code":"PPL",
    "gn:name":"Ban Lup Phek",
    "gn:population":0,
    "gn:timezone":"Asia/Bangkok",
    "iso:country":"TH",
    "name:tha_x_preferred":[
        "\u0e1a\u0e49\u0e32\u0e19\u0e2b\u0e25\u0e38\u0e1a\u0e40\u0e1e\u0e47\u0e01"
    ],
    "wof:name":"Ban Lup Phek",
    "wof:placetype":"locality"
},
  "geometry": {"coordinates":[102.23508,16.01442],"type":"Point"}
}