{
  "type": "Feature",
  "properties": {
    "gn:admin1_code":"76.0",
    "gn:asciiname":"Ban Nam Suem Noi",
    "gn:country_code":"TH",
    "gn:dem":208,
    "gn:feature_class":"P",
    "gn:feature_code":"PPL",
    "gn:name":"Ban Nam Suem Noi",
    "gn:population":0,
    "gn:timezone":"Asia/Bangkok",
    "iso:country":"TH",
    "name:tha_x_preferred":[
        "\u0e1a\u0e49\u0e32\u0e19\u0e19\u0e49\u0e33\u0e0b\u0e36\u0e21\u0e19\u0e49\u0e2d\u0e22"
    ],
    "name:und_x_variant":[
        "Ban Noi Nam Sum"
    ],
    "wof:name":"Ban Nam Suem Noi",
    "wof:placetype":"locality"
},
  "geometry": {"coordinates":[102.29083,17.80453],"type":"Point"}
}