{
  "type": "Feature",
  "properties": {
    "gn:admin1_code":"37.0",
    "gn:asciiname":"Ban Tha Tum",
    "gn:country_code":"TH",
    "gn:dem":27,
    "gn:feature_class":"P",
    "gn:feature_code":"PPL",
    "gn:name":"Ban Tha Tum",
    "gn:population":0,
    "gn:timezone":"Asia/Bangkok",
    "iso:country":"TH",
    "name:tha_x_preferred":[
        "\u0e1a\u0e49\u0e32\u0e19\u0e17\u0e48\u0e32\u0e15\u0e39\u0e21"
    ],
    "name:und_x_variant":[
        "Ban Tah Tum",
        "Ban Tha Tum"
    ],
    "wof:name":"Ban Tha Tum",
    "wof:placetype":"locality"
},
  "geometry": {"coordinates":[101.01872,14.6655],"type":"Point"}
}