{
  "type": "Feature",
  "properties": {
    "gn:admin1_code":"10.0",
    "gn:asciiname":"Ban Mon",
    "gn:country_code":"TH",
    "gn:dem":92,
    "gn:feature_class":"P",
    "gn:feature_code":"PPL",
    "gn:name":"Ban Mon",
    "gn:population":0,
    "gn:timezone":"Asia/Bangkok",
    "iso:country":"TH",
    "name:tha_x_preferred":[
        "\u0e1a\u0e49\u0e32\u0e19\u0e21\u0e48\u0e2d\u0e19"
    ],
    "name:und_x_variant":[
        "B\u0101n Maun",
        "B\u0101n Maun Mai",
        "Ban Mon"
    ],
    "wof:name":"Ban Mon",
    "wof:placetype":"locality"
},
  "geometry": {"coordinates":[100.13261,17.71394],"type":"Point"}
}