{
  "type": "Feature",
  "properties": {
    "gn:admin1_code":"29",
    "gn:asciiname":"Ban Don Ok",
    "gn:country_code":"TH",
    "gn:dem":186,
    "gn:feature_class":"P",
    "gn:feature_code":"PPL",
    "gn:name":"Ban Don Ok",
    "gn:population":0,
    "gn:timezone":"Asia/Bangkok",
    "iso:country":"TH",
    "name:tha_x_preferred":[
        "\u0e1a\u0e49\u0e32\u0e19\u0e42\u0e14\u0e19\u0e42\u0e2d\u0e01"
    ],
    "wof:name":"Ban Don Ok",
    "wof:placetype":"locality"
},
  "geometry": {"coordinates":[103.52383,14.58417],"type":"Point"}
}