{
  "type": "Feature",
  "properties": {
    "gn:admin1_code":"29",
    "gn:asciiname":"Ban Phrai Khala Noi",
    "gn:country_code":"TH",
    "gn:dem":133,
    "gn:feature_class":"P",
    "gn:feature_code":"PPL",
    "gn:name":"Ban Phrai Khala Noi",
    "gn:population":0,
    "gn:timezone":"Asia/Bangkok",
    "iso:country":"TH",
    "name:tha_x_preferred":[
        "\u0e1a\u0e49\u0e32\u0e19\u0e44\u0e1e\u0e23\u0e02\u0e25\u0e32\u0e19\u0e49\u0e2d\u0e22"
    ],
    "wof:name":"Ban Phrai Khala Noi",
    "wof:placetype":"locality"
},
  "geometry": {"coordinates":[103.54489,15.34219],"type":"Point"}
}