{
  "type": "Feature",
  "properties": {
    "gn:admin1_code":"69.0",
    "gn:asciiname":"Ban Chakhe",
    "gn:country_code":"TH",
    "gn:dem":27,
    "gn:feature_class":"P",
    "gn:feature_code":"PPL",
    "gn:name":"Ban Chakhe",
    "gn:population":0,
    "gn:timezone":"Asia/Bangkok",
    "iso:country":"TH",
    "name:tha_x_preferred":[
        "\u0e1a\u0e49\u0e32\u0e19\u0e08\u0e30\u0e40\u0e06\u0e48"
    ],
    "name:und_x_variant":[
        "Kampong Tauk Ha",
        "Kampong Chokha",
        "Ban Chakhe"
    ],
    "wof:name":"Ban Chakhe",
    "wof:placetype":"locality"
},
  "geometry": {"coordinates":[101.54546000000001,6.75815],"type":"Point"}
}