{
  "type": "Feature",
  "properties": {
    "gn:admin1_code":"79.0",
    "gn:asciiname":"Ban Khok Kratho",
    "gn:country_code":"TH",
    "gn:dem":271,
    "gn:feature_class":"P",
    "gn:feature_code":"PPL",
    "gn:name":"Ban Khok Kratho",
    "gn:population":0,
    "gn:timezone":"Asia/Bangkok",
    "iso:country":"TH",
    "name:tha_x_preferred":[
        "\u0e1a\u0e49\u0e32\u0e19\u0e42\u0e04\u0e01\u0e01\u0e23\u0e30\u0e17\u0e2d"
    ],
    "wof:name":"Ban Khok Kratho",
    "wof:placetype":"locality"
},
  "geometry": {"coordinates":[102.06999999999999,17.34142],"type":"Point"}
}