{
  "type": "Feature",
  "properties": {
    "gn:admin1_code":"76.0",
    "gn:asciiname":"Ban Pa Kham",
    "gn:country_code":"TH",
    "gn:dem":242,
    "gn:feature_class":"P",
    "gn:feature_code":"PPL",
    "gn:name":"Ban Pa Kham",
    "gn:population":0,
    "gn:timezone":"Asia/Bangkok",
    "iso:country":"TH",
    "name:tha_x_preferred":[
        "\u0e1a\u0e49\u0e32\u0e19\u0e1b\u0e48\u0e32\u0e02\u0e32\u0e21"
    ],
    "wof:name":"Ban Pa Kham",
    "wof:placetype":"locality"
},
  "geometry": {"coordinates":[102.73063999999999,17.23003],"type":"Point"}
}