{
  "type": "Feature",
  "properties": {
    "gn:admin1_code":"81.0",
    "gn:asciiname":"Ban Na Kham Khaen",
    "gn:country_code":"TH",
    "gn:dem":172,
    "gn:feature_class":"P",
    "gn:feature_code":"PPL",
    "gn:name":"Ban Na Kham Khaen",
    "gn:population":0,
    "gn:timezone":"Asia/Bangkok",
    "iso:country":"TH",
    "name:tha_x_preferred":[
        "\u0e1a\u0e49\u0e32\u0e19\u0e19\u0e32\u0e04\u0e33\u0e41\u0e04\u0e19"
    ],
    "wof:name":"Ban Na Kham Khaen",
    "wof:placetype":"locality"
},
  "geometry": {"coordinates":[103.86686,18.11822],"type":"Point"}
}