{
  "type": "Feature",
  "properties": {
    "gn:admin1_code":"24.0",
    "gn:asciiname":"Ban Yang Yai",
    "gn:country_code":"TH",
    "gn:dem":152,
    "gn:feature_class":"P",
    "gn:feature_code":"PPL",
    "gn:name":"Ban Yang Yai",
    "gn:population":0,
    "gn:timezone":"Asia/Bangkok",
    "iso:country":"TH",
    "name:tha_x_preferred":[
        "\u0e1a\u0e49\u0e32\u0e19\u0e22\u0e32\u0e07\u0e43\u0e2b\u0e0d\u0e48"
    ],
    "wof:name":"Ban Yang Yai",
    "wof:placetype":"locality"
},
  "geometry": {"coordinates":[103.09389,16.27856],"type":"Point"}
}