{
  "type": "Feature",
  "properties": {
    "gn:admin1_code":"67.0",
    "gn:asciiname":"Ban Wang Rat Charoen",
    "gn:country_code":"TH",
    "gn:dem":16,
    "gn:feature_class":"P",
    "gn:feature_code":"PPL",
    "gn:name":"Ban Wang Rat Charoen",
    "gn:population":0,
    "gn:timezone":"Asia/Bangkok",
    "iso:country":"TH",
    "name:tha_x_preferred":[
        "Ban Wang Rat Charoen"
    ],
    "name:tha_x_variant":[
        "\u0e1a\u0e49\u0e32\u0e19\u0e27\u0e31\u0e07\u0e23\u0e32\u0e29\u0e0e\u0e23\u0e4c\u0e40\u0e08\u0e23\u0e34\u0e0d"
    ],
    "wof:name":"Ban Wang Rat Charoen",
    "wof:placetype":"locality"
},
  "geometry": {"coordinates":[99.75922,6.9912],"type":"Point"}
}