{
  "type": "Feature",
  "properties": {
    "gn:admin1_code":"63.0",
    "gn:asciiname":"Ban Na Thung Klang",
    "gn:country_code":"TH",
    "gn:dem":30,
    "gn:feature_class":"P",
    "gn:feature_code":"PPL",
    "gn:name":"Ban Na Thung Klang",
    "gn:population":0,
    "gn:timezone":"Asia/Bangkok",
    "iso:country":"TH",
    "name:tha_x_preferred":[
        "\u0e1a\u0e49\u0e32\u0e19\u0e19\u0e32\u0e17\u0e38\u0e48\u0e07\u0e01\u0e25\u0e32\u0e07"
    ],
    "wof:name":"Ban Na Thung Klang",
    "wof:placetype":"locality"
},
  "geometry": {"coordinates":[99.05441999999999,7.78653],"type":"Point"}
}