{
  "type": "Feature",
  "properties": {
    "gn:admin1_code":"27.0",
    "gn:admin2_code":"3005",
    "gn:asciiname":"Ban Lueam",
    "gn:country_code":"TH",
    "gn:dem":194,
    "gn:feature_class":"P",
    "gn:feature_code":"PPLA2",
    "gn:name":"Ban Lueam",
    "gn:population":0,
    "gn:timezone":"Asia/Bangkok",
    "iso:country":"TH",
    "name:tha_x_preferred":[
        "\u0e1a\u0e49\u0e32\u0e19\u0e40\u0e2b\u0e25\u0e37\u0e48\u0e2d\u0e21"
    ],
    "name:und_x_variant":[
        "Luam",
        "Ban Luam",
        "Ban Lueam",
        "King Amphoe Ban Lueam",
        "Amphoe Ban Lueam"
    ],
    "wof:name":"Ban Lueam",
    "wof:placetype":"locality"
},
  "geometry": {"coordinates":[102.12927999999999,15.60916],"type":"Point"}
}