{
  "type": "Feature",
  "properties": {
    "gn:admin1_code":"7.0",
    "gn:asciiname":"Ban Pha Wua Rua Tai",
    "gn:cc2":"TH",
    "gn:country_code":"TH",
    "gn:dem":106,
    "gn:feature_class":"P",
    "gn:feature_code":"PPL",
    "gn:name":"Ban Pha Wua Rua Tai",
    "gn:population":0,
    "gn:timezone":"Asia/Bangkok",
    "iso:country":"TH",
    "name:und_x_variant":[
        "Ph\u0101ng\u016baro\u0113a",
        "Ban Pha Ngua Rua Tai",
        "Pha Ngua Rua Tai",
        "Ban Pha Wua Rua Tai"
    ],
    "wof:lang_x_official":[
        "tha"
    ],
    "wof:lang_x_spoken":[
        "tha"
    ],
    "wof:name":"Ban Pha Wua Rua Tai",
    "wof:placetype":"locality"
},
  "geometry": {"coordinates":[99.61667,17.88332999999999],"type":"Point"}
}