{
  "type": "Feature",
  "properties": {
    "gn:admin1_code":"75.0",
    "gn:asciiname":"Ban Nam Thaeng",
    "gn:country_code":"TH",
    "gn:dem":159,
    "gn:feature_class":"P",
    "gn:feature_code":"PPL",
    "gn:name":"Ban Nam Thaeng",
    "gn:population":0,
    "gn:timezone":"Asia/Bangkok",
    "iso:country":"TH",
    "name:tha_x_preferred":[
        "\u0e1a\u0e49\u0e32\u0e19\u0e2b\u0e19\u0e32\u0e21\u0e41\u0e17\u0e48\u0e07"
    ],
    "name:und_x_variant":[
        "Namtaeng",
        "Ban Nam Teng",
        "Ban Nam Taeng",
        "Ban Nam Thaeng"
    ],
    "wof:name":"Ban Nam Thaeng",
    "wof:placetype":"locality"
},
  "geometry": {"coordinates":[105.48881000000002,15.57436],"type":"Point"}
}