{
  "type": "Feature",
  "properties": {
    "gn:admin1_code":"27.0",
    "gn:asciiname":"Ban Nong San",
    "gn:country_code":"TH",
    "gn:dem":162,
    "gn:feature_class":"P",
    "gn:feature_code":"PPL",
    "gn:name":"Ban Nong San",
    "gn:population":0,
    "gn:timezone":"Asia/Bangkok",
    "iso:country":"TH",
    "name:tha_x_preferred":[
        "\u0e1a\u0e49\u0e32\u0e19\u0e2b\u0e19\u0e2d\u0e07\u0e2a\u0e32\u0e19\u0e15\u0e4c"
    ],
    "name:und_x_variant":[
        "Ban Mai Nong San"
    ],
    "wof:name":"Ban Nong San",
    "wof:placetype":"locality"
},
  "geometry": {"coordinates":[102.5445,15.20694],"type":"Point"}
}