{
  "type": "Feature",
  "properties": {
    "gn:admin1_code":"2.0",
    "gn:asciiname":"Ban Thung Din Daeng",
    "gn:country_code":"TH",
    "gn:dem":388,
    "gn:feature_class":"P",
    "gn:feature_code":"PPL",
    "gn:name":"Ban Thung Din Daeng",
    "gn:population":0,
    "gn:timezone":"Asia/Bangkok",
    "iso:country":"TH",
    "name:tha_x_preferred":[
        "\u0e1a\u0e49\u0e32\u0e19\u0e17\u0e38\u0e48\u0e07\u0e14\u0e34\u0e19\u0e41\u0e14\u0e07"
    ],
    "wof:name":"Ban Thung Din Daeng",
    "wof:placetype":"locality"
},
  "geometry": {"coordinates":[98.96983,19.37833],"type":"Point"}
}