{
  "type": "Feature",
  "properties": {
    "gn:admin1_code":"44.0",
    "gn:asciiname":"Ban Tha Pao",
    "gn:country_code":"TH",
    "gn:dem":25,
    "gn:feature_class":"P",
    "gn:feature_code":"PPL",
    "gn:name":"Ban Tha Pao",
    "gn:population":0,
    "gn:timezone":"Asia/Bangkok",
    "iso:country":"TH",
    "name:tha_x_preferred":[
        "\u0e1a\u0e49\u0e32\u0e19\u0e17\u0e48\u0e32\u0e40\u0e1b\u0e49\u0e32"
    ],
    "wof:name":"Ban Tha Pao",
    "wof:placetype":"locality"
},
  "geometry": {"coordinates":[101.48917,13.63736],"type":"Point"}
}