{
  "type": "Feature",
  "properties": {
    "gn:admin1_code":"36",
    "gn:asciiname":"Ban Mu Sakae",
    "gn:country_code":"TH",
    "gn:dem":6,
    "gn:feature_class":"P",
    "gn:feature_code":"PPL",
    "gn:name":"Ban Mu Sakae",
    "gn:population":0,
    "gn:timezone":"Asia/Bangkok",
    "iso:country":"TH",
    "name:tha_x_preferred":[
        "\u0e1a\u0e49\u0e32\u0e19\u0e2b\u0e21\u0e39\u0e48\u0e2a\u0e30\u0e41\u0e01"
    ],
    "wof:name":"Ban Mu Sakae",
    "wof:placetype":"locality"
},
  "geometry": {"coordinates":[100.41106000000001,14.29397],"type":"Point"}
}