{
  "type": "Feature",
  "properties": {
    "gn:admin1_code":"70.0",
    "gn:asciiname":"Ban Thong Lon",
    "gn:country_code":"TH",
    "gn:dem":59,
    "gn:feature_class":"P",
    "gn:feature_code":"PPL",
    "gn:name":"Ban Thong Lon",
    "gn:population":0,
    "gn:timezone":"Asia/Bangkok",
    "iso:country":"TH",
    "name:tha_x_preferred":[
        "\u0e1a\u0e49\u0e32\u0e19\u0e17\u0e2d\u0e07\u0e25\u0e49\u0e19"
    ],
    "wof:name":"Ban Thong Lon",
    "wof:placetype":"locality"
},
  "geometry": {"coordinates":[101.1485,6.58592],"type":"Point"}
}