{
  "type": "Feature",
  "properties": {
    "gn:admin1_code":"24",
    "gn:asciiname":"Ban Kham Thao Phatthana",
    "gn:country_code":"TH",
    "gn:dem":153,
    "gn:feature_class":"P",
    "gn:feature_code":"PPL",
    "gn:name":"Ban Kham Thao Phatthana",
    "gn:population":0,
    "gn:timezone":"Asia/Bangkok",
    "iso:country":"TH",
    "name:tha_x_preferred":[
        "\u0e1a\u0e49\u0e32\u0e19\u0e02\u0e32\u0e21\u0e40\u0e12\u0e48\u0e32\u0e1e\u0e31\u0e12\u0e19\u0e32"
    ],
    "wof:name":"Ban Kham Thao Phatthana",
    "wof:placetype":"locality"
},
  "geometry": {"coordinates":[103.30911,16.26444],"type":"Point"}
}