{
  "type": "Feature",
  "properties": {
    "gn:admin1_code":"79.0",
    "gn:asciiname":"Ban Phek Thong",
    "gn:country_code":"TH",
    "gn:dem":237,
    "gn:feature_class":"P",
    "gn:feature_code":"PPL",
    "gn:name":"Ban Phek Thong",
    "gn:population":0,
    "gn:timezone":"Asia/Bangkok",
    "iso:country":"TH",
    "name:tha_x_preferred":[
        "\u0e1a\u0e49\u0e32\u0e19\u0e40\u0e1e\u0e47\u0e01\u0e17\u0e2d\u0e07"
    ],
    "wof:name":"Ban Phek Thong",
    "wof:placetype":"locality"
},
  "geometry": {"coordinates":[102.19344,17.5825],"type":"Point"}
}