{
  "type": "Feature",
  "properties": {
    "gn:admin1_code":"31.0",
    "gn:asciiname":"Ban Phan Suek",
    "gn:country_code":"TH",
    "gn:dem":30,
    "gn:feature_class":"P",
    "gn:feature_code":"PPL",
    "gn:name":"Ban Phan Suek",
    "gn:population":0,
    "gn:timezone":"Asia/Bangkok",
    "iso:country":"TH",
    "name:tha_x_preferred":[
        "\u0e1a\u0e49\u0e32\u0e19\u0e1c\u0e48\u0e32\u0e19\u0e28\u0e36\u0e01"
    ],
    "wof:lang_x_official":[
        "tha"
    ],
    "wof:lang_x_spoken":[
        "tha"
    ],
    "wof:name":"Ban Phan Suek",
    "wof:placetype":"locality"
},
  "geometry": {"coordinates":[101.89243999999999,5.89475],"type":"Point"}
}