{
  "type": "Feature",
  "properties": {
    "gn:admin1_code":"68.0",
    "gn:asciiname":"Ban Khlong Chang",
    "gn:country_code":"TH",
    "gn:dem":7,
    "gn:feature_class":"P",
    "gn:feature_code":"PPL",
    "gn:name":"Ban Khlong Chang",
    "gn:population":0,
    "gn:timezone":"Asia/Bangkok",
    "iso:country":"TH",
    "name:tha_x_preferred":[
        "\u0e1a\u0e49\u0e32\u0e19\u0e04\u0e25\u0e49\u0e2d\u0e07\u0e0a\u0e49\u0e32\u0e07"
    ],
    "wof:name":"Ban Khlong Chang",
    "wof:placetype":"locality"
},
  "geometry": {"coordinates":[100.67136000000001,7.07436],"type":"Point"}
}