{
  "type": "Feature",
  "properties": {
    "gn:admin1_code":"54.0",
    "gn:asciiname":"Ban Bang Chakreng",
    "gn:country_code":"TH",
    "gn:dem":6,
    "gn:feature_class":"P",
    "gn:feature_code":"PPL",
    "gn:name":"Ban Bang Chakreng",
    "gn:population":0,
    "gn:timezone":"Asia/Bangkok",
    "iso:country":"TH",
    "name:tha_x_preferred":[
        "\u0e1a\u0e49\u0e32\u0e19\u0e1a\u0e32\u0e07\u0e08\u0e30\u0e40\u0e01\u0e23\u0e47\u0e07"
    ],
    "name:und_x_variant":[
        "Bang Dha Krang"
    ],
    "wof:lang_x_official":[
        "tha"
    ],
    "wof:lang_x_spoken":[
        "tha"
    ],
    "wof:name":"Ban Bang Chakreng",
    "wof:placetype":"locality"
},
  "geometry": {"coordinates":[100.00207,13.38749],"type":"Point"}
}