{
  "type": "Feature",
  "properties": {
    "gn:admin1_code":"38.0",
    "gn:asciiname":"Ban Khlong Ha Roi",
    "gn:cc2":"TH",
    "gn:country_code":"TH",
    "gn:dem":5,
    "gn:feature_class":"P",
    "gn:feature_code":"PPL",
    "gn:name":"Ban Khlong Ha Roi",
    "gn:population":0,
    "gn:timezone":"Asia/Bangkok",
    "iso:country":"TH",
    "name:tha_x_preferred":[
        "\u0e1a\u0e49\u0e32\u0e19\u0e04\u0e25\u0e2d\u0e07\u0e2b\u0e49\u0e32\u0e23\u0e49\u0e2d\u0e22"
    ],
    "name:und_x_variant":[
        "Ban Khlong Ha Roi (5)",
        "Ban Khlong Ha Roi"
    ],
    "wof:name":"Ban Khlong Ha Roi",
    "wof:placetype":"locality"
},
  "geometry": {"coordinates":[100.32314,13.99797],"type":"Point"}
}