{
  "type": "Feature",
  "properties": {
    "gn:admin1_code":"31.0",
    "gn:asciiname":"Ban Si Yaek Bang Phrao",
    "gn:country_code":"TH",
    "gn:dem":29,
    "gn:feature_class":"P",
    "gn:feature_code":"PPL",
    "gn:name":"Ban Si Yaek Bang Phrao",
    "gn:population":0,
    "gn:timezone":"Asia/Bangkok",
    "iso:country":"TH",
    "name:tha_x_preferred":[
        "\u0e1a\u0e49\u0e32\u0e19\u0e2a\u0e35\u0e48\u0e41\u0e22\u0e01\u0e1a\u0e32\u0e07\u0e1e\u0e23\u0e49\u0e32\u0e27"
    ],
    "wof:name":"Ban Si Yaek Bang Phrao",
    "wof:placetype":"locality"
},
  "geometry": {"coordinates":[101.88285999999999,6.1315],"type":"Point"}
}