{
  "type": "Feature",
  "properties": {
    "gn:admin1_code":"16.0",
    "gn:asciiname":"Ban Hua Plik",
    "gn:country_code":"TH",
    "gn:dem":30,
    "gn:feature_class":"P",
    "gn:feature_code":"PPL",
    "gn:name":"Ban Hua Plik",
    "gn:population":0,
    "gn:timezone":"Asia/Bangkok",
    "iso:country":"TH",
    "name:tha_x_preferred":[
        "\u0e1a\u0e49\u0e32\u0e19\u0e2b\u0e31\u0e27\u0e1b\u0e25\u0e34\u0e01"
    ],
    "wof:name":"Ban Hua Plik",
    "wof:placetype":"locality"
},
  "geometry": {"coordinates":[100.34614000000001,15.76861],"type":"Point"}
}