{
  "type": "Feature",
  "properties": {
    "gn:admin1_code":"60.0",
    "gn:asciiname":"Ban Khuan Sung",
    "gn:country_code":"TH",
    "gn:dem":122,
    "gn:feature_class":"P",
    "gn:feature_code":"PPL",
    "gn:name":"Ban Khuan Sung",
    "gn:population":0,
    "gn:timezone":"Asia/Bangkok",
    "iso:country":"TH",
    "name:tha_x_preferred":[
        "\u0e1a\u0e49\u0e32\u0e19\u0e04\u0e27\u0e19\u0e2a\u0e39\u0e07"
    ],
    "wof:lang_x_official":[
        "tha"
    ],
    "wof:lang_x_spoken":[
        "tha"
    ],
    "wof:name":"Ban Khuan Sung",
    "wof:placetype":"locality"
},
  "geometry": {"coordinates":[98.76094000000001,8.67744],"type":"Point"}
}