{
  "type": "Feature",
  "properties": {
    "gn:admin1_code":"22",
    "gn:asciiname":"Ban Maliwan",
    "gn:country_code":"TH",
    "gn:dem":174,
    "gn:feature_class":"P",
    "gn:feature_code":"PPL",
    "gn:name":"Ban Maliwan",
    "gn:population":0,
    "gn:timezone":"Asia/Bangkok",
    "iso:country":"TH",
    "name:tha_x_preferred":[
        "\u0e1a\u0e49\u0e32\u0e19\u0e21\u0e30\u0e25\u0e34\u0e27\u0e31\u0e25\u0e22\u0e4c"
    ],
    "wof:name":"Ban Maliwan",
    "wof:placetype":"locality"
},
  "geometry": {"coordinates":[102.76047,16.46503],"type":"Point"}
}