{
  "type": "Feature",
  "properties": {
    "gn:admin1_code":"2.0",
    "gn:asciiname":"Ban Mo-Ro-Tu",
    "gn:country_code":"TH",
    "gn:dem":1011,
    "gn:feature_class":"P",
    "gn:feature_code":"PPL",
    "gn:name":"Ban Mo-Ro-Tu",
    "gn:population":0,
    "gn:timezone":"Asia/Bangkok",
    "iso:country":"TH",
    "name:tha_x_preferred":[
        "\u0e1a\u0e49\u0e32\u0e19\u0e42\u0e21\u0e42\u0e23\u0e15\u0e39"
    ],
    "wof:name":"Ban Mo-Ro-Tu",
    "wof:placetype":"locality"
},
  "geometry": {"coordinates":[98.11575000000001,18.44761],"type":"Point"}
}