{
  "type": "Feature",
  "properties": {
    "gn:admin1_code":"47.0",
    "gn:asciiname":"Ban Noen Khao Din",
    "gn:country_code":"TH",
    "gn:dem":13,
    "gn:feature_class":"P",
    "gn:feature_code":"PPL",
    "gn:name":"Ban Noen Khao Din",
    "gn:population":0,
    "gn:timezone":"Asia/Bangkok",
    "iso:country":"TH",
    "name:tha_x_preferred":[
        "\u0e1a\u0e49\u0e32\u0e19\u0e40\u0e19\u0e34\u0e19\u0e40\u0e02\u0e32\u0e14\u0e34\u0e19"
    ],
    "wof:name":"Ban Noen Khao Din",
    "wof:placetype":"locality"
},
  "geometry": {"coordinates":[101.71250000000001,12.77694],"type":"Point"}
}