{
  "type": "Feature",
  "properties": {
    "gn:admin1_code":"73.0",
    "gn:asciiname":"Ban Dong Khwang",
    "gn:country_code":"TH",
    "gn:dem":148,
    "gn:feature_class":"P",
    "gn:feature_code":"PPL",
    "gn:name":"Ban Dong Khwang",
    "gn:population":0,
    "gn:timezone":"Asia/Bangkok",
    "iso:country":"TH",
    "name:tha_x_preferred":[
        "Ban Dong Khwang"
    ],
    "name:tha_x_variant":[
        "\u0e1a\u0e49\u0e32\u0e19\u0e14\u0e07\u0e02\u0e27\u0e32\u0e07"
    ],
    "wof:name":"Ban Dong Khwang",
    "wof:placetype":"locality"
},
  "geometry": {"coordinates":[104.78483,17.20097],"type":"Point"}
}