{
  "type": "Feature",
  "properties": {
    "gn:admin1_code":"50.0",
    "gn:asciiname":"Ban Nong Rong",
    "gn:country_code":"TH",
    "gn:dem":37,
    "gn:feature_class":"P",
    "gn:feature_code":"PPL",
    "gn:name":"Ban Nong Rong",
    "gn:population":0,
    "gn:timezone":"Asia/Bangkok",
    "iso:country":"TH",
    "name:tha_x_preferred":[
        "\u0e1a\u0e49\u0e32\u0e19\u0e2b\u0e19\u0e2d\u0e07\u0e42\u0e23\u0e07"
    ],
    "name:und_x_variant":[
        "Ban Hnong Rong",
        "Ban Nong Rong"
    ],
    "wof:name":"Ban Nong Rong",
    "wof:placetype":"locality"
},
  "geometry": {"coordinates":[99.63742000000001,14.11736],"type":"Point"}
}