{
  "type": "Feature",
  "properties": {
    "gn:admin1_code":"74.0",
    "gn:asciiname":"Ban Non Klang",
    "gn:country_code":"TH",
    "gn:dem":23,
    "gn:feature_class":"P",
    "gn:feature_code":"PPL",
    "gn:name":"Ban Non Klang",
    "gn:population":0,
    "gn:timezone":"Asia/Bangkok",
    "iso:country":"TH",
    "name:tha_x_preferred":[
        "\u0e1a\u0e49\u0e32\u0e19\u0e42\u0e19\u0e19\u0e01\u0e25\u0e32\u0e07"
    ],
    "name:und_x_variant":[
        "Ban Klang",
        "Ban Hae",
        "Ban Non Klang"
    ],
    "wof:name":"Ban Non Klang",
    "wof:placetype":"locality"
},
  "geometry": {"coordinates":[101.73522,14.06111],"type":"Point"}
}