{
  "type": "Feature",
  "properties": {
    "gn:admin1_code":"8.0",
    "gn:asciiname":"Ban Thi Cho Chi",
    "gn:country_code":"TH",
    "gn:dem":547,
    "gn:feature_class":"P",
    "gn:feature_code":"PPL",
    "gn:name":"Ban Thi Cho Chi",
    "gn:population":0,
    "gn:timezone":"Asia/Bangkok",
    "iso:country":"TH",
    "name:tha_x_preferred":[
        "\u0e1a\u0e49\u0e32\u0e19\u0e17\u0e35\u0e08\u0e2d\u0e0a\u0e35"
    ],
    "name:und_x_variant":[
        "Pule",
        "Ban Thi Cho Chui",
        "B\u0101n Thi Jau Ch\u0101i",
        "Ban Thi Lo Chui",
        "Ban Kui Chokae",
        "Ban Thi Cho Chi",
        "Ban Chi Cho Chi"
    ],
    "wof:name":"Ban Thi Cho Chi",
    "wof:placetype":"locality"
},
  "geometry": {"coordinates":[98.63153,15.93772],"type":"Point"}
}