{
  "type": "Feature",
  "properties": {
    "gn:admin1_code":"16.0",
    "gn:asciiname":"Ban Nong Pradu Thao",
    "gn:country_code":"TH",
    "gn:dem":31,
    "gn:feature_class":"P",
    "gn:feature_code":"PPL",
    "gn:name":"Ban Nong Pradu Thao",
    "gn:population":0,
    "gn:timezone":"Asia/Bangkok",
    "iso:country":"TH",
    "name:tha_x_preferred":[
        "\u0e1a\u0e49\u0e32\u0e19\u0e2b\u0e19\u0e2d\u0e07\u0e1b\u0e23\u0e30\u0e14\u0e39\u0e48\u0e40\u0e12\u0e48\u0e32"
    ],
    "wof:lang_x_official":[
        "tha"
    ],
    "wof:lang_x_spoken":[
        "tha"
    ],
    "wof:name":"Ban Nong Pradu Thao",
    "wof:placetype":"locality"
},
  "geometry": {"coordinates":[100.19867000000001,15.45219],"type":"Point"}
}