{
  "type": "Feature",
  "properties": {
    "gn:admin1_code":"34",
    "gn:asciiname":"Ban Nong Raroeng",
    "gn:country_code":"TH",
    "gn:dem":97,
    "gn:feature_class":"P",
    "gn:feature_code":"PPL",
    "gn:name":"Ban Nong Raroeng",
    "gn:population":0,
    "gn:timezone":"Asia/Bangkok",
    "iso:country":"TH",
    "name:tha_x_preferred":[
        "\u0e1a\u0e49\u0e32\u0e19\u0e2b\u0e19\u0e2d\u0e07\u0e23\u0e48\u0e32\u0e40\u0e23\u0e34\u0e07"
    ],
    "wof:name":"Ban Nong Raroeng",
    "wof:placetype":"locality"
},
  "geometry": {"coordinates":[100.81377999999999,15.48217],"type":"Point"}
}