{
  "type": "Feature",
  "properties": {
    "gn:admin1_code":"81.0",
    "gn:asciiname":"Ban Nong Tin Phueak",
    "gn:country_code":"TH",
    "gn:dem":160,
    "gn:feature_class":"P",
    "gn:feature_code":"PPL",
    "gn:name":"Ban Nong Tin Phueak",
    "gn:population":0,
    "gn:timezone":"Asia/Bangkok",
    "iso:country":"TH",
    "name:tha_x_preferred":[
        "\u0e1a\u0e49\u0e32\u0e19\u0e2b\u0e19\u0e2d\u0e07\u0e15\u0e35\u0e19\u0e40\u0e1c\u0e37\u0e2d\u0e01"
    ],
    "name:und_x_variant":[
        "Ban Nong Tin Phuak"
    ],
    "wof:name":"Ban Nong Tin Phueak",
    "wof:placetype":"locality"
},
  "geometry": {"coordinates":[103.82253,18.03082],"type":"Point"}
}