{
  "type": "Feature",
  "properties": {
    "gn:admin1_code":"26.0",
    "gn:asciiname":"Ban Tha Wa",
    "gn:country_code":"TH",
    "gn:dem":186,
    "gn:feature_class":"P",
    "gn:feature_code":"PPL",
    "gn:name":"Ban Tha Wa",
    "gn:population":0,
    "gn:timezone":"Asia/Bangkok",
    "iso:country":"TH",
    "name:tha_x_preferred":[
        "\u0e1a\u0e49\u0e32\u0e19\u0e17\u0e48\u0e32\u0e2b\u0e27\u0e49\u0e32"
    ],
    "name:und_x_variant":[
        "Ban Khong Yang Khai Tha Wa"
    ],
    "wof:name":"Ban Tha Wa",
    "wof:placetype":"locality"
},
  "geometry": {"coordinates":[102.02911,15.67031],"type":"Point"}
}