{
  "type": "Feature",
  "properties": {
    "gn:admin1_code":"24",
    "gn:asciiname":"Ban Nong Bua Noi",
    "gn:country_code":"TH",
    "gn:dem":158,
    "gn:feature_class":"P",
    "gn:feature_code":"PPL",
    "gn:name":"Ban Nong Bua Noi",
    "gn:population":0,
    "gn:timezone":"Asia/Bangkok",
    "iso:country":"TH",
    "name:tha_x_preferred":[
        "\u0e1a\u0e49\u0e32\u0e19\u0e2b\u0e19\u0e2d\u0e07\u0e1a\u0e31\u0e27\u0e19\u0e49\u0e2d\u0e22"
    ],
    "wof:name":"Ban Nong Bua Noi",
    "wof:placetype":"locality"
},
  "geometry": {"coordinates":[103.307,15.73183],"type":"Point"}
}