{
  "type": "Feature",
  "properties": {
    "gn:admin1_code":"16.0",
    "gn:asciiname":"Ban Wang Pla Ra",
    "gn:country_code":"TH",
    "gn:dem":36,
    "gn:feature_class":"P",
    "gn:feature_code":"PPL",
    "gn:name":"Ban Wang Pla Ra",
    "gn:population":0,
    "gn:timezone":"Asia/Bangkok",
    "iso:country":"TH",
    "name:tha_x_preferred":[
        "\u0e1a\u0e49\u0e32\u0e19\u0e27\u0e31\u0e07\u0e1b\u0e25\u0e32\u0e23\u0e49\u0e32"
    ],
    "wof:name":"Ban Wang Pla Ra",
    "wof:placetype":"locality"
},
  "geometry": {"coordinates":[100.05231000000001,15.80547],"type":"Point"}
}