{
  "type": "Feature",
  "properties": {
    "gn:admin1_code":"16.0",
    "gn:asciiname":"Ban Phu Kham",
    "gn:country_code":"TH",
    "gn:dem":109,
    "gn:feature_class":"P",
    "gn:feature_code":"PPL",
    "gn:name":"Ban Phu Kham",
    "gn:population":0,
    "gn:timezone":"Asia/Bangkok",
    "iso:country":"TH",
    "name:tha_x_preferred":[
        "\u0e1a\u0e49\u0e32\u0e19\u0e1e\u0e38\u0e02\u0e32\u0e21"
    ],
    "wof:name":"Ban Phu Kham",
    "wof:placetype":"locality"
},
  "geometry": {"coordinates":[100.51906,15.42492],"type":"Point"}
}