{
  "type": "Feature",
  "properties": {
    "gn:admin1_code":"18.0",
    "gn:asciiname":"Ban Si Than",
    "gn:country_code":"TH",
    "gn:dem":255,
    "gn:feature_class":"P",
    "gn:feature_code":"PPL",
    "gn:name":"Ban Si Than",
    "gn:population":0,
    "gn:timezone":"Asia/Bangkok",
    "iso:country":"TH",
    "name:tha_x_preferred":[
        "\u0e1a\u0e49\u0e32\u0e19\u0e28\u0e23\u0e35\u0e10\u0e32\u0e19"
    ],
    "name:und_x_variant":[
        "S\u012bgan",
        "Ban Si Dun",
        "Si Khan",
        "Ban Si Khan",
        "B\u0101n Si Kan",
        "Ban Si Than"
    ],
    "wof:name":"Ban Si Than",
    "wof:placetype":"locality"
},
  "geometry": {"coordinates":[101.86077,16.88234],"type":"Point"}
}