{
  "type": "Feature",
  "properties": {
    "gn:admin1_code":"28",
    "gn:asciiname":"Ban Bu Sa-nga",
    "gn:country_code":"TH",
    "gn:dem":189,
    "gn:feature_class":"P",
    "gn:feature_code":"PPL",
    "gn:name":"Ban Bu Sa-nga",
    "gn:population":0,
    "gn:timezone":"Asia/Bangkok",
    "iso:country":"TH",
    "name:tha_x_preferred":[
        "\u0e1a\u0e49\u0e32\u0e19\u0e1a\u0e38\u0e2a\u0e07\u0e48\u0e32"
    ],
    "wof:name":"Ban Bu Sa-nga",
    "wof:placetype":"locality"
},
  "geometry": {"coordinates":[102.88482999999999,14.65653],"type":"Point"}
}