{
  "type": "Feature",
  "properties": {
    "gn:admin1_code":"65.0",
    "gn:asciiname":"Ban Khuan A-ri",
    "gn:country_code":"TH",
    "gn:dem":50,
    "gn:feature_class":"P",
    "gn:feature_code":"PPL",
    "gn:name":"Ban Khuan A-ri",
    "gn:population":0,
    "gn:timezone":"Asia/Bangkok",
    "iso:country":"TH",
    "name:tha_x_preferred":[
        "\u0e1a\u0e49\u0e32\u0e19\u0e04\u0e27\u0e19\u0e2d\u0e32\u0e23\u0e35"
    ],
    "wof:name":"Ban Khuan A-ri",
    "wof:placetype":"locality"
},
  "geometry": {"coordinates":[99.47167,7.80981],"type":"Point"}
}