{
  "type": "Feature",
  "properties": {
    "gn:admin1_code":"60.0",
    "gn:asciiname":"Ban Thap Paet",
    "gn:country_code":"TH",
    "gn:dem":29,
    "gn:feature_class":"P",
    "gn:feature_code":"PPL",
    "gn:name":"Ban Thap Paet",
    "gn:population":0,
    "gn:timezone":"Asia/Bangkok",
    "iso:country":"TH",
    "name:tha_x_preferred":[
        "\u0e1a\u0e49\u0e32\u0e19\u0e17\u0e31\u0e1a\u0e41\u0e1b\u0e14"
    ],
    "wof:name":"Ban Thap Paet",
    "wof:placetype":"locality"
},
  "geometry": {"coordinates":[99.10275,8.83217],"type":"Point"}
}