{
  "type": "Feature",
  "properties": {
    "gn:admin1_code":"36.0",
    "gn:asciiname":"Ban Sao Wang Kha",
    "gn:country_code":"TH",
    "gn:dem":6,
    "gn:feature_class":"P",
    "gn:feature_code":"PPL",
    "gn:name":"Ban Sao Wang Kha",
    "gn:population":0,
    "gn:timezone":"Asia/Bangkok",
    "iso:country":"TH",
    "name:tha_x_preferred":[
        "\u0e1a\u0e49\u0e32\u0e19\u0e40\u0e2a\u0e32\u0e27\u0e31\u0e07\u0e04\u0e32"
    ],
    "wof:name":"Ban Sao Wang Kha",
    "wof:placetype":"locality"
},
  "geometry": {"coordinates":[100.64422,14.23642],"type":"Point"}
}