{
  "type": "Feature",
  "properties": {
    "gn:admin1_code":"68.0",
    "gn:asciiname":"Ban Tha Riang",
    "gn:country_code":"TH",
    "gn:dem":14,
    "gn:feature_class":"P",
    "gn:feature_code":"PPL",
    "gn:name":"Ban Tha Riang",
    "gn:population":0,
    "gn:timezone":"Asia/Bangkok",
    "iso:country":"TH",
    "name:und_x_variant":[
        "Tha Riang",
        "Ban Tah Riang",
        "Ban Tha Riang",
        "\u0e1a\u0e49\u0e32\u0e19\u0e17\u0e48\u0e32\u0e2b\u0e23\u0e31\u0e48\u0e07"
    ],
    "wof:name":"Ban Tha Riang",
    "wof:placetype":"locality"
},
  "geometry": {"coordinates":[100.4209,6.92498],"type":"Point"}
}