{
  "type": "Feature",
  "properties": {
    "gn:admin1_code":"46.0",
    "gn:asciiname":"Ban Plaeng Krathin",
    "gn:country_code":"TH",
    "gn:dem":31,
    "gn:feature_class":"P",
    "gn:feature_code":"PPL",
    "gn:name":"Ban Plaeng Krathin",
    "gn:population":0,
    "gn:timezone":"Asia/Bangkok",
    "iso:country":"TH",
    "name:tha_x_preferred":[
        "\u0e1a\u0e49\u0e32\u0e19\u0e41\u0e1b\u0e25\u0e07\u0e01\u0e23\u0e30\u0e16\u0e34\u0e19"
    ],
    "wof:name":"Ban Plaeng Krathin",
    "wof:placetype":"locality"
},
  "geometry": {"coordinates":[101.23878000000001,13.53672],"type":"Point"}
}