{
  "type": "Feature",
  "properties": {
    "gn:admin1_code":"27.0",
    "gn:asciiname":"Ban Nong Plaen",
    "gn:country_code":"TH",
    "gn:dem":195,
    "gn:feature_class":"P",
    "gn:feature_code":"PPL",
    "gn:name":"Ban Nong Plaen",
    "gn:population":0,
    "gn:timezone":"Asia/Bangkok",
    "iso:country":"TH",
    "name:tha_x_preferred":[
        "\u0e1a\u0e49\u0e32\u0e19\u0e2b\u0e19\u0e2d\u0e07\u0e41\u0e1b\u0e25\u0e19"
    ],
    "name:und_x_variant":[
        "Ban Nong Paen"
    ],
    "wof:name":"Ban Nong Plaen",
    "wof:placetype":"locality"
},
  "geometry": {"coordinates":[102.13686,14.66297],"type":"Point"}
}