{
  "type": "Feature",
  "properties": {
    "gn:admin1_code":"23.0",
    "gn:asciiname":"Ban Wang Saen Kham",
    "gn:country_code":"TH",
    "gn:dem":163,
    "gn:feature_class":"P",
    "gn:feature_code":"PPL",
    "gn:name":"Ban Wang Saen Kham",
    "gn:population":0,
    "gn:timezone":"Asia/Bangkok",
    "iso:country":"TH",
    "name:tha_x_preferred":[
        "\u0e1a\u0e49\u0e32\u0e19\u0e27\u0e31\u0e07\u0e41\u0e2a\u0e19\u0e04\u0e33"
    ],
    "wof:name":"Ban Wang Saen Kham",
    "wof:placetype":"locality"
},
  "geometry": {"coordinates":[103.70097,16.56336],"type":"Point"}
}