{
  "type": "Feature",
  "properties": {
    "gn:admin1_code":"49.0",
    "gn:asciiname":"Ban Thap Makok",
    "gn:country_code":"TH",
    "gn:dem":36,
    "gn:feature_class":"P",
    "gn:feature_code":"PPL",
    "gn:name":"Ban Thap Makok",
    "gn:population":0,
    "gn:timezone":"Asia/Bangkok",
    "iso:country":"TH",
    "name:tha_x_preferred":[
        "\u0e1a\u0e49\u0e32\u0e19\u0e17\u0e31\u0e1a\u0e21\u0e30\u0e01\u0e2d\u0e01"
    ],
    "wof:name":"Ban Thap Makok",
    "wof:placetype":"locality"
},
  "geometry": {"coordinates":[102.66378,12.40183],"type":"Point"}
}