{
  "type": "Feature",
  "properties": {
    "gn:admin1_code":"1.0",
    "gn:asciiname":"Ban Kong",
    "gn:country_code":"TH",
    "gn:dem":313,
    "gn:feature_class":"P",
    "gn:feature_code":"PPL",
    "gn:name":"Ban Kong",
    "gn:population":0,
    "gn:timezone":"Asia/Bangkok",
    "iso:country":"TH",
    "name:tha_x_preferred":[
        "\u0e1a\u0e49\u0e32\u0e19\u0e01\u0e2d\u0e07"
    ],
    "name:und_x_variant":[
        "Pak Baung",
        "B\u0101n P\u0101k Baung",
        "P\u0101kb\u014dhng",
        "Ban Pak Pong",
        "Pak Bong",
        "Ban Pak Bong",
        "Ban Kong"
    ],
    "wof:name":"Ban Kong",
    "wof:placetype":"locality"
},
  "geometry": {"coordinates":[98.90895,18.69244],"type":"Point"}
}