{
  "type": "Feature",
  "properties": {
    "gn:admin1_code":"44.0",
    "gn:asciiname":"Ban Nong Chang Tai",
    "gn:country_code":"TH",
    "gn:dem":5,
    "gn:feature_class":"P",
    "gn:feature_code":"PPL",
    "gn:name":"Ban Nong Chang Tai",
    "gn:population":0,
    "gn:timezone":"Asia/Bangkok",
    "iso:country":"TH",
    "name:tha_x_preferred":[
        "\u0e1a\u0e49\u0e32\u0e19\u0e2b\u0e19\u0e2d\u0e07\u0e0a\u0e49\u0e32\u0e07\u0e15\u0e32\u0e22"
    ],
    "wof:name":"Ban Nong Chang Tai",
    "wof:placetype":"locality"
},
  "geometry": {"coordinates":[101.26383,13.74253],"type":"Point"}
}