{
  "type": "Feature",
  "properties": {
    "gn:admin1_code":"70.0",
    "gn:asciiname":"Ban Talat Khok Chang",
    "gn:country_code":"TH",
    "gn:dem":153,
    "gn:feature_class":"P",
    "gn:feature_code":"PPL",
    "gn:name":"Ban Talat Khok Chang",
    "gn:population":0,
    "gn:timezone":"Asia/Bangkok",
    "iso:country":"TH",
    "name:tha_x_preferred":[
        "\u0e1a\u0e49\u0e32\u0e19\u0e15\u0e25\u0e32\u0e14\u0e04\u0e2d\u0e01\u0e0a\u0e49\u0e32\u0e07"
    ],
    "wof:name":"Ban Talat Khok Chang",
    "wof:placetype":"locality"
},
  "geometry": {"coordinates":[101.17733,6.04897],"type":"Point"}
}