{
  "type": "Feature",
  "properties": {
    "gn:admin1_code":"22",
    "gn:asciiname":"Ban Sompoi Yai",
    "gn:country_code":"TH",
    "gn:dem":191,
    "gn:feature_class":"P",
    "gn:feature_code":"PPL",
    "gn:name":"Ban Sompoi Yai",
    "gn:population":0,
    "gn:timezone":"Asia/Bangkok",
    "iso:country":"TH",
    "name:tha_x_preferred":[
        "\u0e1a\u0e49\u0e32\u0e19\u0e2a\u0e49\u0e21\u0e1b\u0e48\u0e2d\u0e22\u0e43\u0e2b\u0e0d\u0e48"
    ],
    "wof:name":"Ban Sompoi Yai",
    "wof:placetype":"locality"
},
  "geometry": {"coordinates":[102.89456,15.91889],"type":"Point"}
}