{
  "type": "Feature",
  "properties": {
    "gn:admin1_code":"63.0",
    "gn:asciiname":"Ban Bang Sai",
    "gn:country_code":"TH",
    "gn:dem":49,
    "gn:feature_class":"P",
    "gn:feature_code":"PPL",
    "gn:name":"Ban Bang Sai",
    "gn:population":0,
    "gn:timezone":"Asia/Bangkok",
    "iso:country":"TH",
    "name:tha_x_preferred":[
        "\u0e1a\u0e49\u0e32\u0e19\u0e1a\u0e32\u0e07\u0e44\u0e17\u0e23"
    ],
    "name:und_x_variant":[
        "Ban Bang Thai"
    ],
    "wof:name":"Ban Bang Sai",
    "wof:placetype":"locality"
},
  "geometry": {"coordinates":[98.74831,8.53272],"type":"Point"}
}