{
  "type": "Feature",
  "properties": {
    "gn:admin1_code":"75.0",
    "gn:asciiname":"Ban Kaset Udom",
    "gn:country_code":"TH",
    "gn:dem":205,
    "gn:feature_class":"P",
    "gn:feature_code":"PPL",
    "gn:name":"Ban Kaset Udom",
    "gn:population":0,
    "gn:timezone":"Asia/Bangkok",
    "iso:country":"TH",
    "name:tha_x_preferred":[
        "\u0e1a\u0e49\u0e32\u0e19\u0e40\u0e01\u0e29\u0e15\u0e23\u0e2d\u0e38\u0e14\u0e21"
    ],
    "wof:name":"Ban Kaset Udom",
    "wof:placetype":"locality"
},
  "geometry": {"coordinates":[105.05333,14.55222],"type":"Point"}
}