{
  "type": "Feature",
  "properties": {
    "gn:admin1_code":"6.0",
    "gn:asciiname":"Ban Huai Khoi",
    "gn:country_code":"TH",
    "gn:dem":425,
    "gn:feature_class":"P",
    "gn:feature_code":"PPL",
    "gn:name":"Ban Huai Khoi",
    "gn:population":0,
    "gn:timezone":"Asia/Bangkok",
    "iso:country":"TH",
    "name:tha_x_preferred":[
        "\u0e1a\u0e49\u0e32\u0e19\u0e2b\u0e49\u0e27\u0e22\u0e02\u0e48\u0e2d\u0e22"
    ],
    "wof:name":"Ban Huai Khoi",
    "wof:placetype":"locality"
},
  "geometry": {"coordinates":[99.61597,19.12117000000001],"type":"Point"}
}