{
  "type": "Feature",
  "properties": {
    "gn:admin1_code":"20.0",
    "gn:asciiname":"Ban Choeng Chum",
    "gn:country_code":"TH",
    "gn:dem":170,
    "gn:feature_class":"P",
    "gn:feature_code":"PPL",
    "gn:name":"Ban Choeng Chum",
    "gn:population":0,
    "gn:timezone":"Asia/Bangkok",
    "iso:country":"TH",
    "name:tha_x_preferred":[
        "\u0e1a\u0e49\u0e32\u0e19\u0e40\u0e0a\u0e34\u0e07\u0e0a\u0e38\u0e21"
    ],
    "wof:name":"Ban Choeng Chum",
    "wof:placetype":"locality"
},
  "geometry": {"coordinates":[104.01458,17.4035],"type":"Point"}
}