{
  "type": "Feature",
  "properties": {
    "gn:admin1_code":"42.0",
    "gn:asciiname":"Muban Likhit Chet",
    "gn:country_code":"TH",
    "gn:dem":3,
    "gn:feature_class":"P",
    "gn:feature_code":"PPL",
    "gn:name":"Muban Likhit Chet",
    "gn:population":0,
    "gn:timezone":"Asia/Bangkok",
    "iso:country":"TH",
    "name:tha_x_preferred":[
        "\u0e2b\u0e21\u0e39\u0e48\u0e1a\u0e49\u0e32\u0e19\u0e25\u0e34\u0e02\u0e34\u0e15 \u0e40\u0e08\u0e47\u0e14"
    ],
    "name:und_x_variant":[
        "Muban Likhit 7",
        "Muban Likhit Chet"
    ],
    "wof:name":"Muban Likhit Chet",
    "wof:placetype":"locality"
},
  "geometry": {"coordinates":[100.70456,13.61778],"type":"Point"}
}