{
  "type": "Feature",
  "properties": {
    "gn:admin1_code":"17.0",
    "gn:asciiname":"Ban Sam Chiang",
    "gn:country_code":"TH",
    "gn:dem":249,
    "gn:feature_class":"P",
    "gn:feature_code":"PPL",
    "gn:name":"Ban Sam Chiang",
    "gn:population":0,
    "gn:timezone":"Asia/Bangkok",
    "iso:country":"TH",
    "name:tha_x_preferred":[
        "\u0e1a\u0e49\u0e32\u0e19\u0e0b\u0e33\u0e40\u0e08\u0e35\u0e22\u0e07"
    ],
    "wof:name":"Ban Sam Chiang",
    "wof:placetype":"locality"
},
  "geometry": {"coordinates":[102.14381,18.11419],"type":"Point"}
}