{
  "type": "Feature",
  "properties": {
    "gn:admin1_code":"27.0",
    "gn:asciiname":"Ban Nong Chaeng Yai",
    "gn:country_code":"TH",
    "gn:dem":176,
    "gn:feature_class":"P",
    "gn:feature_code":"PPL",
    "gn:name":"Ban Nong Chaeng Yai",
    "gn:population":0,
    "gn:timezone":"Asia/Bangkok",
    "iso:country":"TH",
    "name:tha_x_preferred":[
        "\u0e1a\u0e49\u0e32\u0e19\u0e2b\u0e19\u0e2d\u0e07\u0e41\u0e08\u0e49\u0e07\u0e43\u0e2b\u0e0d\u0e48"
    ],
    "name:und_x_variant":[
        "Ban Chaeng",
        "Chaeng",
        "Ban Nong Chaeng Yai"
    ],
    "wof:name":"Ban Nong Chaeng Yai",
    "wof:placetype":"locality"
},
  "geometry": {"coordinates":[102.38753,15.55928],"type":"Point"}
}