{
  "type": "Feature",
  "properties": {
    "gn:admin1_code":"26.0",
    "gn:asciiname":"Ban Khong Nam Tap",
    "gn:country_code":"TH",
    "gn:dem":189,
    "gn:feature_class":"P",
    "gn:feature_code":"PPL",
    "gn:name":"Ban Khong Nam Tap",
    "gn:population":0,
    "gn:timezone":"Asia/Bangkok",
    "iso:country":"TH",
    "name:tha_x_preferred":[
        "\u0e1a\u0e49\u0e32\u0e19\u0e42\u0e04\u0e49\u0e07\u0e19\u0e49\u0e33\u0e15\u0e31\u0e1a"
    ],
    "wof:name":"Ban Khong Nam Tap",
    "wof:placetype":"locality"
},
  "geometry": {"coordinates":[102.03682999999999,15.65144],"type":"Point"}
}