{
  "type": "Feature",
  "properties": {
    "gn:admin1_code":"81.0",
    "gn:asciiname":"Ban Na Sing",
    "gn:country_code":"TH",
    "gn:dem":162,
    "gn:feature_class":"P",
    "gn:feature_code":"PPL",
    "gn:name":"Ban Na Sing",
    "gn:population":0,
    "gn:timezone":"Asia/Bangkok",
    "iso:country":"TH",
    "name:tha_x_preferred":[
        "\u0e1a\u0e49\u0e32\u0e19\u0e19\u0e32\u0e2a\u0e34\u0e07\u0e2b\u0e4c"
    ],
    "wof:name":"Ban Na Sing",
    "wof:placetype":"locality"
},
  "geometry": {"coordinates":[103.79076999999999,18.16219],"type":"Point"}
}