{
  "type": "Feature",
  "properties": {
    "gn:admin1_code":"36.0",
    "gn:asciiname":"Ban Rat Niyom",
    "gn:country_code":"TH",
    "gn:dem":6,
    "gn:feature_class":"P",
    "gn:feature_code":"PPL",
    "gn:name":"Ban Rat Niyom",
    "gn:population":0,
    "gn:timezone":"Asia/Bangkok",
    "iso:country":"TH",
    "name:tha_x_preferred":[
        "Ban Rat Niyom"
    ],
    "name:tha_x_variant":[
        "\u0e1a\u0e49\u0e32\u0e19\u0e23\u0e32\u0e29\u0e0e\u0e23\u0e4c\u0e19\u0e34\u0e22\u0e21"
    ],
    "wof:name":"Ban Rat Niyom",
    "wof:placetype":"locality"
},
  "geometry": {"coordinates":[100.33038999999999,14.13081],"type":"Point"}
}