{
  "type": "Feature",
  "properties": {
    "gn:admin1_code":"2.0",
    "gn:asciiname":"Ban Phrabat",
    "gn:country_code":"TH",
    "gn:dem":296,
    "gn:feature_class":"P",
    "gn:feature_code":"PPL",
    "gn:name":"Ban Phrabat",
    "gn:population":0,
    "gn:timezone":"Asia/Bangkok",
    "iso:country":"TH",
    "name:tha_x_preferred":[
        "\u0e1a\u0e49\u0e32\u0e19\u0e1e\u0e23\u0e30\u0e1a\u0e32\u0e17"
    ],
    "wof:name":"Ban Phrabat",
    "wof:placetype":"locality"
},
  "geometry": {"coordinates":[98.89575000000001,18.57767],"type":"Point"}
}