{
  "type": "Feature",
  "properties": {
    "gn:admin1_code":"2.0",
    "gn:asciiname":"Ban Rong Than",
    "gn:country_code":"TH",
    "gn:dem":530,
    "gn:feature_class":"P",
    "gn:feature_code":"PPL",
    "gn:name":"Ban Rong Than",
    "gn:population":0,
    "gn:timezone":"Asia/Bangkok",
    "iso:country":"TH",
    "name:tha_x_preferred":[
        "\u0e1a\u0e49\u0e32\u0e19\u0e23\u0e49\u0e2d\u0e07\u0e18\u0e32\u0e23"
    ],
    "wof:name":"Ban Rong Than",
    "wof:placetype":"locality"
},
  "geometry": {"coordinates":[99.14731,19.67428],"type":"Point"}
}