{
  "type": "Feature",
  "properties": {
    "gn:admin1_code":"58.0",
    "gn:asciiname":"Ban Tha Mai Lai",
    "gn:country_code":"TH",
    "gn:dem":59,
    "gn:feature_class":"P",
    "gn:feature_code":"PPL",
    "gn:name":"Ban Tha Mai Lai",
    "gn:population":0,
    "gn:timezone":"Asia/Bangkok",
    "iso:country":"TH",
    "name:tha_x_preferred":[
        "\u0e1a\u0e49\u0e32\u0e19\u0e17\u0e48\u0e32\u0e44\u0e21\u0e49\u0e25\u0e32\u0e22"
    ],
    "name:und_x_variant":[
        "Ban Tha Mai Luak"
    ],
    "wof:name":"Ban Tha Mai Lai",
    "wof:placetype":"locality"
},
  "geometry": {"coordinates":[98.95658,10.49958],"type":"Point"}
}