{
  "type": "Feature",
  "properties": {
    "gn:admin1_code":"75.0",
    "gn:asciiname":"Ban Ang Hin Tai",
    "gn:country_code":"TH",
    "gn:dem":155,
    "gn:feature_class":"P",
    "gn:feature_code":"PPL",
    "gn:name":"Ban Ang Hin Tai",
    "gn:population":0,
    "gn:timezone":"Asia/Bangkok",
    "iso:country":"TH",
    "name:tha_x_preferred":[
        "\u0e1a\u0e49\u0e32\u0e19\u0e2d\u0e48\u0e32\u0e07\u0e2b\u0e34\u0e19\u0e43\u0e15\u0e49"
    ],
    "name:und_x_variant":[
        "Ban Ang Hin Yai"
    ],
    "wof:name":"Ban Ang Hin Tai",
    "wof:placetype":"locality"
},
  "geometry": {"coordinates":[105.27567000000001,15.051],"type":"Point"}
}