{
  "type": "Feature",
  "properties": {
    "gn:admin1_code":"27",
    "gn:asciiname":"Ban Taraeng",
    "gn:country_code":"TH",
    "gn:dem":298,
    "gn:feature_class":"P",
    "gn:feature_code":"PPL",
    "gn:name":"Ban Taraeng",
    "gn:population":0,
    "gn:timezone":"Asia/Bangkok",
    "iso:country":"TH",
    "name:tha_x_preferred":[
        "\u0e1a\u0e49\u0e32\u0e19\u0e15\u0e30\u0e41\u0e23\u0e07"
    ],
    "wof:name":"Ban Taraeng",
    "wof:placetype":"locality"
},
  "geometry": {"coordinates":[102.25414000000001,14.63142],"type":"Point"}
}