{
  "type": "Feature",
  "properties": {
    "gn:admin1_code":"51.0",
    "gn:asciiname":"Ban Thung Samae",
    "gn:country_code":"TH",
    "gn:dem":73,
    "gn:feature_class":"P",
    "gn:feature_code":"PPL",
    "gn:name":"Ban Thung Samae",
    "gn:population":0,
    "gn:timezone":"Asia/Bangkok",
    "iso:country":"TH",
    "name:tha_x_preferred":[
        "\u0e1a\u0e49\u0e32\u0e19\u0e17\u0e38\u0e48\u0e07\u0e41\u0e2a\u0e21"
    ],
    "wof:name":"Ban Thung Samae",
    "wof:placetype":"locality"
},
  "geometry": {"coordinates":[99.67564,14.81253],"type":"Point"}
}