{
  "type": "Feature",
  "properties": {
    "gn:admin1_code":"2.0",
    "gn:asciiname":"Ban Ku Ho",
    "gn:country_code":"TH",
    "gn:dem":306,
    "gn:feature_class":"P",
    "gn:feature_code":"PPL",
    "gn:name":"Ban Ku Ho",
    "gn:population":0,
    "gn:timezone":"Asia/Bangkok",
    "iso:country":"TH",
    "name:tha_x_preferred":[
        "\u0e1a\u0e49\u0e32\u0e19\u0e01\u0e39\u0e48\u0e2e\u0e49\u0e2d"
    ],
    "wof:name":"Ban Ku Ho",
    "wof:placetype":"locality"
},
  "geometry": {"coordinates":[98.65239,18.47253],"type":"Point"}
}