{
  "type": "Feature",
  "properties": {
    "gn:admin1_code":"55.0",
    "gn:asciiname":"Ban Mu Thot",
    "gn:country_code":"TH",
    "gn:dem":6,
    "gn:feature_class":"P",
    "gn:feature_code":"PPL",
    "gn:name":"Ban Mu Thot",
    "gn:population":0,
    "gn:timezone":"Asia/Bangkok",
    "iso:country":"TH",
    "name:tha_x_preferred":[
        "\u0e1a\u0e49\u0e32\u0e19\u0e2b\u0e21\u0e39\u0e17\u0e2d\u0e14"
    ],
    "name:und_x_variant":[
        "Ban Mu Tok",
        "Ban Mu Thok",
        "Ban Mu Thot"
    ],
    "wof:lang_x_official":[
        "tha"
    ],
    "wof:lang_x_spoken":[
        "tha"
    ],
    "wof:name":"Ban Mu Thot",
    "wof:placetype":"locality"
},
  "geometry": {"coordinates":[100.08143,13.56977],"type":"Point"}
}