{
  "type": "Feature",
  "properties": {
    "gn:admin1_code":"48.0",
    "gn:asciiname":"Ban Wung Sarika",
    "gn:country_code":"TH",
    "gn:dem":13,
    "gn:feature_class":"P",
    "gn:feature_code":"PPL",
    "gn:name":"Ban Wung Sarika",
    "gn:population":0,
    "gn:timezone":"Asia/Bangkok",
    "iso:country":"TH",
    "name:tha_x_preferred":[
        "\u0e1a\u0e49\u0e32\u0e19\u0e27\u0e38\u0e49\u0e07\u0e2a\u0e32\u0e23\u0e34\u0e01\u0e32"
    ],
    "name:und_x_variant":[
        "Ban Wang Sarika",
        "Ban Wung Sarika"
    ],
    "wof:name":"Ban Wung Sarika",
    "wof:placetype":"locality"
},
  "geometry": {"coordinates":[101.93797000000001,12.70128],"type":"Point"}
}