{
  "type": "Feature",
  "properties": {
    "gn:admin1_code":"77.0",
    "gn:asciiname":"Ban Na Dok Mai",
    "gn:country_code":"TH",
    "gn:dem":150,
    "gn:feature_class":"P",
    "gn:feature_code":"PPL",
    "gn:name":"Ban Na Dok Mai",
    "gn:population":0,
    "gn:timezone":"Asia/Bangkok",
    "iso:country":"TH",
    "name:tha_x_preferred":[
        "Ban Na Dok Mai"
    ],
    "name:tha_x_variant":[
        "\u0e1a\u0e49\u0e32\u0e19\u0e19\u0e32\u0e14\u0e2d\u0e01\u0e44\u0e21\u0e49"
    ],
    "wof:name":"Ban Na Dok Mai",
    "wof:placetype":"locality"
},
  "geometry": {"coordinates":[104.49011,15.83636],"type":"Point"}
}