{
  "type": "Feature",
  "properties": {
    "gn:admin1_code":"69.0",
    "gn:asciiname":"Ban Bango Na Ko",
    "gn:country_code":"TH",
    "gn:dem":11,
    "gn:feature_class":"P",
    "gn:feature_code":"PPL",
    "gn:name":"Ban Bango Na Ko",
    "gn:population":0,
    "gn:timezone":"Asia/Bangkok",
    "iso:country":"TH",
    "name:tha_x_preferred":[
        "\u0e1a\u0e49\u0e32\u0e19\u0e1a\u0e32\u0e42\u0e07\u0e19\u0e32\u0e01\u0e2d"
    ],
    "wof:name":"Ban Bango Na Ko",
    "wof:placetype":"locality"
},
  "geometry": {"coordinates":[101.21311,6.721],"type":"Point"}
}