{
  "type": "Feature",
  "properties": {
    "gn:admin1_code":"29",
    "gn:asciiname":"Ban Khun In",
    "gn:country_code":"TH",
    "gn:dem":149,
    "gn:feature_class":"P",
    "gn:feature_code":"PPL",
    "gn:name":"Ban Khun In",
    "gn:population":0,
    "gn:timezone":"Asia/Bangkok",
    "iso:country":"TH",
    "name:tha_x_preferred":[
        "\u0e1a\u0e49\u0e32\u0e19\u0e02\u0e38\u0e19\u0e2d\u0e34\u0e19\u0e17\u0e23\u0e4c"
    ],
    "wof:name":"Ban Khun In",
    "wof:placetype":"locality"
},
  "geometry": {"coordinates":[103.45860999999999,15.16628],"type":"Point"}
}