{
  "type": "Feature",
  "properties": {
    "gn:admin1_code":"14.0",
    "gn:asciiname":"Ban Wang To",
    "gn:country_code":"TH",
    "gn:dem":76,
    "gn:feature_class":"P",
    "gn:feature_code":"PPL",
    "gn:name":"Ban Wang To",
    "gn:population":0,
    "gn:timezone":"Asia/Bangkok",
    "iso:country":"TH",
    "name:tha_x_preferred":[
        "\u0e1a\u0e49\u0e32\u0e19\u0e27\u0e31\u0e07\u0e15\u0e2d"
    ],
    "wof:name":"Ban Wang To",
    "wof:placetype":"locality"
},
  "geometry": {"coordinates":[100.74491999999999,16.12272],"type":"Point"}
}