{
  "type": "Feature",
  "properties": {
    "gn:admin1_code":"25.0",
    "gn:asciiname":"Ban Non Sathian",
    "gn:country_code":"TH",
    "gn:dem":149,
    "gn:feature_class":"P",
    "gn:feature_code":"PPL",
    "gn:name":"Ban Non Sathian",
    "gn:population":0,
    "gn:timezone":"Asia/Bangkok",
    "iso:country":"TH",
    "name:tha_x_preferred":[
        "\u0e1a\u0e49\u0e32\u0e19\u0e42\u0e19\u0e19\u0e40\u0e2a\u0e16\u0e35\u0e22\u0e23"
    ],
    "wof:name":"Ban Non Sathian",
    "wof:placetype":"locality"
},
  "geometry": {"coordinates":[103.66386,16.09586],"type":"Point"}
}