{
  "type": "Feature",
  "properties": {
    "gn:admin1_code":"40.0",
    "gn:admin2_code":"1023.0",
    "gn:asciiname":"Muban Phut Tan",
    "gn:country_code":"TH",
    "gn:dem":5,
    "gn:feature_class":"P",
    "gn:feature_code":"PPL",
    "gn:name":"Muban Phut Tan",
    "gn:population":0,
    "gn:timezone":"Asia/Bangkok",
    "iso:country":"TH",
    "name:tha_x_preferred":[
        "\u0e2b\u0e21\u0e39\u0e48\u0e1a\u0e49\u0e32\u0e19\u0e1e\u0e38\u0e14\u0e15\u0e32\u0e19"
    ],
    "wof:name":"Muban Phut Tan",
    "wof:placetype":"locality"
},
  "geometry": {"coordinates":[100.33892,13.68058],"type":"Point"}
}