{
  "type": "Feature",
  "properties": {
    "gn:admin1_code":"28",
    "gn:asciiname":"Ban Suan Sawan",
    "gn:country_code":"TH",
    "gn:dem":215,
    "gn:feature_class":"P",
    "gn:feature_code":"PPL",
    "gn:name":"Ban Suan Sawan",
    "gn:population":0,
    "gn:timezone":"Asia/Bangkok",
    "iso:country":"TH",
    "name:tha_x_preferred":[
        "\u0e1a\u0e49\u0e32\u0e19\u0e2a\u0e27\u0e19\u0e2a\u0e27\u0e23\u0e23\u0e04\u0e4c"
    ],
    "wof:name":"Ban Suan Sawan",
    "wof:placetype":"locality"
},
  "geometry": {"coordinates":[102.53031,14.65844],"type":"Point"}
}