{
  "type": "Feature",
  "properties": {
    "gn:admin1_code":"8.0",
    "gn:asciiname":"Ban Nong Khaem",
    "gn:country_code":"TH",
    "gn:dem":135,
    "gn:feature_class":"P",
    "gn:feature_code":"PPL",
    "gn:name":"Ban Nong Khaem",
    "gn:population":0,
    "gn:timezone":"Asia/Bangkok",
    "iso:country":"TH",
    "name:tha_x_preferred":[
        "Ban Nong Khaem"
    ],
    "name:tha_x_variant":[
        "\u0e1a\u0e49\u0e32\u0e19\u0e2b\u0e19\u0e2d\u0e07\u0e41\u0e02\u0e21"
    ],
    "name:und_x_variant":[
        "Ban Naung Keam",
        "Ban Nong Khaem (2)"
    ],
    "wof:name":"Ban Nong Khaem",
    "wof:placetype":"locality"
},
  "geometry": {"coordinates":[99.07886000000001,16.83225],"type":"Point"}
}