{
  "type": "Feature",
  "properties": {
    "gn:admin1_code":"27.0",
    "gn:asciiname":"Ban Kum Phaya",
    "gn:country_code":"TH",
    "gn:dem":203,
    "gn:feature_class":"P",
    "gn:feature_code":"PPL",
    "gn:name":"Ban Kum Phaya",
    "gn:population":0,
    "gn:timezone":"Asia/Bangkok",
    "iso:country":"TH",
    "name:tha_x_preferred":[
        "\u0e1a\u0e49\u0e32\u0e19\u0e01\u0e38\u0e48\u0e21\u0e1e\u0e23\u0e30\u0e22\u0e32"
    ],
    "name:und_x_variant":[
        "Ban Kum Phraya"
    ],
    "wof:name":"Ban Kum Phaya",
    "wof:placetype":"locality"
},
  "geometry": {"coordinates":[101.91733000000001,15.03708],"type":"Point"}
}