{
  "type": "Feature",
  "properties": {
    "gn:admin1_code":"70.0",
    "gn:asciiname":"Ban Bu Ka Ba Ti Yo",
    "gn:country_code":"TH",
    "gn:dem":22,
    "gn:feature_class":"P",
    "gn:feature_code":"PPL",
    "gn:name":"Ban Bu Ka Ba Ti Yo",
    "gn:population":0,
    "gn:timezone":"Asia/Bangkok",
    "iso:country":"TH",
    "name:tha_x_preferred":[
        "\u0e1a\u0e49\u0e32\u0e19\u0e1a\u0e39\u0e40\u0e01\u0e30\u0e1a\u0e32\u0e15\u0e35\u0e22\u0e2d"
    ],
    "wof:name":"Ban Bu Ka Ba Ti Yo",
    "wof:placetype":"locality"
},
  "geometry": {"coordinates":[101.36814,6.50642],"type":"Point"}
}