{
  "type": "Feature",
  "properties": {
    "gn:admin1_code":"28.0",
    "gn:asciiname":"Ban Khok Fueang",
    "gn:country_code":"TH",
    "gn:dem":221,
    "gn:feature_class":"P",
    "gn:feature_code":"PPL",
    "gn:name":"Ban Khok Fueang",
    "gn:population":0,
    "gn:timezone":"Asia/Bangkok",
    "iso:country":"TH",
    "name:tha_x_preferred":[
        "\u0e1a\u0e49\u0e32\u0e19\u0e42\u0e04\u0e01\u0e40\u0e1f\u0e37\u0e2d\u0e07"
    ],
    "name:und_x_variant":[
        "Ban Khok Phiang",
        "Ban Khok Fuang",
        "Ban Khok Fueang"
    ],
    "wof:name":"Ban Khok Fueang",
    "wof:placetype":"locality"
},
  "geometry": {"coordinates":[102.86628,14.36539],"type":"Point"}
}