{
  "type": "Feature",
  "properties": {
    "gn:admin1_code":"22",
    "gn:asciiname":"Ban Nong Thum",
    "gn:country_code":"TH",
    "gn:dem":242,
    "gn:feature_class":"P",
    "gn:feature_code":"PPL",
    "gn:name":"Ban Nong Thum",
    "gn:population":0,
    "gn:timezone":"Asia/Bangkok",
    "iso:country":"TH",
    "name:tha_x_preferred":[
        "\u0e1a\u0e49\u0e32\u0e19\u0e2b\u0e19\u0e2d\u0e07\u0e17\u0e38\u0e48\u0e21"
    ],
    "wof:name":"Ban Nong Thum",
    "wof:placetype":"locality"
},
  "geometry": {"coordinates":[102.07969,16.60833],"type":"Point"}
}