{
  "type": "Feature",
  "properties": {
    "gn:admin1_code":"23.0",
    "gn:asciiname":"Ban Thap Pla",
    "gn:country_code":"TH",
    "gn:dem":169,
    "gn:feature_class":"P",
    "gn:feature_code":"PPL",
    "gn:name":"Ban Thap Pla",
    "gn:population":0,
    "gn:timezone":"Asia/Bangkok",
    "iso:country":"TH",
    "name:tha_x_preferred":[
        "\u0e1a\u0e49\u0e32\u0e19\u0e17\u0e31\u0e1a\u0e1b\u0e25\u0e32"
    ],
    "wof:name":"Ban Thap Pla",
    "wof:placetype":"locality"
},
  "geometry": {"coordinates":[103.42658,16.79133],"type":"Point"}
}