{
  "type": "Feature",
  "properties": {
    "gn:admin1_code":"41.0",
    "gn:asciiname":"Ban Huai Kaeo Phatthana",
    "gn:country_code":"TH",
    "gn:dem":419,
    "gn:feature_class":"P",
    "gn:feature_code":"PPL",
    "gn:name":"Ban Huai Kaeo Phatthana",
    "gn:population":0,
    "gn:timezone":"Asia/Bangkok",
    "iso:country":"TH",
    "name:tha_x_preferred":[
        "\u0e1a\u0e49\u0e32\u0e19\u0e2b\u0e49\u0e27\u0e22\u0e41\u0e01\u0e49\u0e27\u0e1e\u0e31\u0e12\u0e19\u0e32"
    ],
    "wof:name":"Ban Huai Kaeo Phatthana",
    "wof:placetype":"locality"
},
  "geometry": {"coordinates":[100.08358,19.36797],"type":"Point"}
}