{
  "type": "Feature",
  "properties": {
    "gn:admin1_code":"51.0",
    "gn:asciiname":"Ban Bo Wa",
    "gn:country_code":"TH",
    "gn:dem":31,
    "gn:feature_class":"P",
    "gn:feature_code":"PPL",
    "gn:name":"Ban Bo Wa",
    "gn:population":0,
    "gn:timezone":"Asia/Bangkok",
    "iso:country":"TH",
    "name:tha_x_preferred":[
        "\u0e1a\u0e49\u0e32\u0e19\u0e1a\u0e48\u0e2d\u0e2b\u0e27\u0e49\u0e32"
    ],
    "name:und_x_variant":[
        "Ban Bo Wa (1)"
    ],
    "wof:name":"Ban Bo Wa",
    "wof:placetype":"locality"
},
  "geometry": {"coordinates":[99.90788999999999,14.79636],"type":"Point"}
}