{
  "type": "Feature",
  "properties": {
    "gn:admin1_code":"52.0",
    "gn:asciiname":"Ban Thung Faek",
    "gn:country_code":"TH",
    "gn:dem":131,
    "gn:feature_class":"P",
    "gn:feature_code":"PPL",
    "gn:name":"Ban Thung Faek",
    "gn:population":0,
    "gn:timezone":"Asia/Bangkok",
    "iso:country":"TH",
    "name:tha_x_preferred":[
        "\u0e1a\u0e49\u0e32\u0e19\u0e17\u0e38\u0e48\u0e07\u0e41\u0e1d\u0e01"
    ],
    "name:und_x_variant":[
        "Thung Faek",
        "Ban Thung Faek"
    ],
    "wof:name":"Ban Thung Faek",
    "wof:placetype":"locality"
},
  "geometry": {"coordinates":[99.32438999999999,13.5357],"type":"Point"}
}