{
  "type": "Feature",
  "properties": {
    "gn:admin1_code":"41.0",
    "gn:asciiname":"Ban Pha Lat",
    "gn:country_code":"TH",
    "gn:dem":386,
    "gn:feature_class":"P",
    "gn:feature_code":"PPL",
    "gn:name":"Ban Pha Lat",
    "gn:population":0,
    "gn:timezone":"Asia/Bangkok",
    "iso:country":"TH",
    "name:tha_x_preferred":[
        "\u0e1a\u0e49\u0e32\u0e19\u0e1c\u0e32\u0e25\u0e32\u0e14"
    ],
    "wof:name":"Ban Pha Lat",
    "wof:placetype":"locality"
},
  "geometry": {"coordinates":[100.22225,19.51045],"type":"Point"}
}