{
  "type": "Feature",
  "properties": {
    "gn:admin1_code":"11.0",
    "gn:asciiname":"Ban Mae Lat Yai",
    "gn:country_code":"TH",
    "gn:dem":60,
    "gn:feature_class":"P",
    "gn:feature_code":"PPL",
    "gn:name":"Ban Mae Lat Yai",
    "gn:population":0,
    "gn:timezone":"Asia/Bangkok",
    "iso:country":"TH",
    "name:tha_x_preferred":[
        "\u0e1a\u0e49\u0e32\u0e19\u0e41\u0e21\u0e48\u0e25\u0e32\u0e14\u0e43\u0e2b\u0e0d\u0e48"
    ],
    "wof:name":"Ban Mae Lat Yai",
    "wof:placetype":"locality"
},
  "geometry": {"coordinates":[99.75955999999999,16.16467],"type":"Point"}
}