{
  "type": "Feature",
  "properties": {
    "gn:admin1_code":"13.0",
    "gn:asciiname":"Ban Khok Nong Cha Prap",
    "gn:country_code":"TH",
    "gn:dem":76,
    "gn:feature_class":"P",
    "gn:feature_code":"PPL",
    "gn:name":"Ban Khok Nong Cha Prap",
    "gn:population":0,
    "gn:timezone":"Asia/Bangkok",
    "iso:country":"TH",
    "name:tha_x_preferred":[
        "\u0e1a\u0e49\u0e32\u0e19\u0e42\u0e04\u0e01\u0e2b\u0e19\u0e2d\u0e07\u0e08\u0e30\u0e1b\u0e23\u0e32\u0e1a"
    ],
    "wof:name":"Ban Khok Nong Cha Prap",
    "wof:placetype":"locality"
},
  "geometry": {"coordinates":[100.70381,16.23692],"type":"Point"}
}