{
  "type": "Feature",
  "properties": {
    "gn:admin1_code":"51.0",
    "gn:asciiname":"Ban Thai Wat Dong Tan",
    "gn:country_code":"TH",
    "gn:dem":8,
    "gn:feature_class":"P",
    "gn:feature_code":"PPL",
    "gn:name":"Ban Thai Wat Dong Tan",
    "gn:population":0,
    "gn:timezone":"Asia/Bangkok",
    "iso:country":"TH",
    "name:tha_x_preferred":[
        "\u0e1a\u0e49\u0e32\u0e19\u0e17\u0e49\u0e32\u0e22\u0e27\u0e31\u0e14\u0e14\u0e07\u0e15\u0e32\u0e25"
    ],
    "wof:lang_x_official":[
        "tha"
    ],
    "wof:lang_x_spoken":[
        "tha"
    ],
    "wof:name":"Ban Thai Wat Dong Tan",
    "wof:placetype":"locality"
},
  "geometry": {"coordinates":[100.03536,14.23261],"type":"Point"}
}