{
  "type": "Feature",
  "properties": {
    "gn:admin1_code":"70.0",
    "gn:asciiname":"Ban Phan Suek Nai",
    "gn:country_code":"TH",
    "gn:dem":634,
    "gn:feature_class":"P",
    "gn:feature_code":"PPL",
    "gn:name":"Ban Phan Suek Nai",
    "gn:population":0,
    "gn:timezone":"Asia/Bangkok",
    "iso:country":"TH",
    "name:tha_x_preferred":[
        "\u0e1a\u0e49\u0e32\u0e19\u0e1c\u0e48\u0e32\u0e19\u0e28\u0e36\u0e01\u0e43\u0e19"
    ],
    "wof:name":"Ban Phan Suek Nai",
    "wof:placetype":"locality"
},
  "geometry": {"coordinates":[101.139,6.17433],"type":"Point"}
}