{
  "type": "Feature",
  "properties": {
    "gn:admin1_code":"66.0",
    "gn:asciiname":"Ban Ko Rian",
    "gn:country_code":"TH",
    "gn:dem":46,
    "gn:feature_class":"P",
    "gn:feature_code":"PPL",
    "gn:name":"Ban Ko Rian",
    "gn:population":0,
    "gn:timezone":"Asia/Bangkok",
    "iso:country":"TH",
    "name:tha_x_preferred":[
        "\u0e1a\u0e49\u0e32\u0e19\u0e40\u0e01\u0e32\u0e30\u0e40\u0e23\u0e35\u0e22\u0e19"
    ],
    "wof:name":"Ban Ko Rian",
    "wof:placetype":"locality"
},
  "geometry": {"coordinates":[100.06171999999999,7.28689],"type":"Point"}
}