{
  "type": "Feature",
  "properties": {
    "gn:admin1_code":"50.0",
    "gn:asciiname":"Ban Phu Krang",
    "gn:country_code":"TH",
    "gn:dem":168,
    "gn:feature_class":"P",
    "gn:feature_code":"PPL",
    "gn:name":"Ban Phu Krang",
    "gn:population":0,
    "gn:timezone":"Asia/Bangkok",
    "iso:country":"TH",
    "name:tha_x_preferred":[
        "\u0e1a\u0e49\u0e32\u0e19\u0e1e\u0e38\u0e01\u0e23\u0e48\u0e32\u0e07"
    ],
    "wof:name":"Ban Phu Krang",
    "wof:placetype":"locality"
},
  "geometry": {"coordinates":[99.28077999999999,13.78531],"type":"Point"}
}