{
  "type": "Feature",
  "properties": {
    "gn:admin1_code":"68.0",
    "gn:asciiname":"Ban Chai Khlong",
    "gn:country_code":"TH",
    "gn:dem":12,
    "gn:feature_class":"P",
    "gn:feature_code":"PPL",
    "gn:name":"Ban Chai Khlong",
    "gn:population":0,
    "gn:timezone":"Asia/Bangkok",
    "iso:country":"TH",
    "name:tha_x_preferred":[
        "\u0e1a\u0e49\u0e32\u0e19\u0e0a\u0e32\u0e22\u0e04\u0e25\u0e2d\u0e07"
    ],
    "wof:name":"Ban Chai Khlong",
    "wof:placetype":"locality"
},
  "geometry": {"coordinates":[100.37106,7.14497],"type":"Point"}
}