{
  "type": "Feature",
  "properties": {
    "gn:admin1_code":"26.0",
    "gn:asciiname":"Ban Saliang Thong",
    "gn:country_code":"TH",
    "gn:dem":318,
    "gn:feature_class":"P",
    "gn:feature_code":"PPL",
    "gn:name":"Ban Saliang Thong",
    "gn:population":0,
    "gn:timezone":"Asia/Bangkok",
    "iso:country":"TH",
    "name:tha_x_preferred":[
        "\u0e1a\u0e49\u0e32\u0e19\u0e40\u0e2a\u0e25\u0e35\u0e48\u0e22\u0e07\u0e17\u0e2d\u0e07"
    ],
    "wof:name":"Ban Saliang Thong",
    "wof:placetype":"locality"
},
  "geometry": {"coordinates":[101.46811,15.64358],"type":"Point"}
}