{
  "type": "Feature",
  "properties": {
    "gn:admin1_code":"74",
    "gn:asciiname":"Ban Laem Ling",
    "gn:country_code":"TH",
    "gn:dem":4,
    "gn:feature_class":"P",
    "gn:feature_code":"PPL",
    "gn:name":"Ban Laem Ling",
    "gn:population":0,
    "gn:timezone":"Asia/Bangkok",
    "iso:country":"TH",
    "name:tha_x_preferred":[
        "\u0e1a\u0e49\u0e32\u0e19\u0e41\u0e2b\u0e25\u0e21\u0e25\u0e34\u0e07"
    ],
    "wof:name":"Ban Laem Ling",
    "wof:placetype":"locality"
},
  "geometry": {"coordinates":[101.21792000000001,13.96975],"type":"Point"}
}