{
  "type": "Feature",
  "properties": {
    "gn:admin1_code":"36.0",
    "gn:asciiname":"Ban Rang Ai Thuem",
    "gn:country_code":"TH",
    "gn:dem":7,
    "gn:feature_class":"P",
    "gn:feature_code":"PPL",
    "gn:name":"Ban Rang Ai Thuem",
    "gn:population":0,
    "gn:timezone":"Asia/Bangkok",
    "iso:country":"TH",
    "name:tha_x_preferred":[
        "\u0e1a\u0e49\u0e32\u0e19\u0e23\u0e32\u0e07\u0e2d\u0e49\u0e32\u0e22\u0e17\u0e36\u0e21"
    ],
    "name:und_x_variant":[
        "Ban Ai Thum",
        "Ban Ai Toem",
        "Ban Nai Thum",
        "Ban Rang Ai Thuem"
    ],
    "wof:name":"Ban Rang Ai Thuem",
    "wof:placetype":"locality"
},
  "geometry": {"coordinates":[100.26058,14.23786],"type":"Point"}
}