{
  "type": "Feature",
  "properties": {
    "gn:admin1_code":"6.0",
    "gn:asciiname":"Ban Huai Nam Khem",
    "gn:country_code":"TH",
    "gn:dem":262,
    "gn:feature_class":"P",
    "gn:feature_code":"PPL",
    "gn:name":"Ban Huai Nam Khem",
    "gn:population":0,
    "gn:timezone":"Asia/Bangkok",
    "iso:country":"TH",
    "name:tha_x_preferred":[
        "\u0e1a\u0e49\u0e32\u0e19\u0e2b\u0e49\u0e27\u0e22\u0e19\u0e49\u0e33\u0e40\u0e04\u0e47\u0e21"
    ],
    "wof:lang_x_official":[
        "tha"
    ],
    "wof:lang_x_spoken":[
        "tha"
    ],
    "wof:name":"Ban Huai Nam Khem",
    "wof:placetype":"locality"
},
  "geometry": {"coordinates":[99.61391999999999,18.38417],"type":"Point"}
}