{
  "type": "Feature",
  "properties": {
    "gn:admin1_code":"14.0",
    "gn:asciiname":"Ban Sam Phu",
    "gn:country_code":"TH",
    "gn:dem":233,
    "gn:feature_class":"P",
    "gn:feature_code":"PPL",
    "gn:name":"Ban Sam Phu",
    "gn:population":0,
    "gn:timezone":"Asia/Bangkok",
    "iso:country":"TH",
    "name:tha_x_preferred":[
        "\u0e1a\u0e49\u0e32\u0e19\u0e0b\u0e33\u0e20\u0e39"
    ],
    "wof:name":"Ban Sam Phu",
    "wof:placetype":"locality"
},
  "geometry": {"coordinates":[101.3395,16.60394],"type":"Point"}
}