{
  "type": "Feature",
  "properties": {
    "gn:admin1_code":"3.0",
    "gn:asciiname":"Ban Doi Lan",
    "gn:country_code":"TH",
    "gn:dem":1228,
    "gn:feature_class":"P",
    "gn:feature_code":"PPL",
    "gn:name":"Ban Doi Lan",
    "gn:population":0,
    "gn:timezone":"Asia/Bangkok",
    "iso:country":"TH",
    "name:tha_x_preferred":[
        "\u0e1a\u0e49\u0e32\u0e19\u0e14\u0e2d\u0e22\u0e25\u0e49\u0e32\u0e19"
    ],
    "wof:name":"Ban Doi Lan",
    "wof:placetype":"locality"
},
  "geometry": {"coordinates":[99.5615,19.76565],"type":"Point"}
}