{
  "type": "Feature",
  "properties": {
    "gn:admin1_code":"62.0",
    "gn:asciiname":"Ban Ao Kung",
    "gn:country_code":"TH",
    "gn:dem":15,
    "gn:feature_class":"P",
    "gn:feature_code":"PPL",
    "gn:name":"Ban Ao Kung",
    "gn:population":0,
    "gn:timezone":"Asia/Bangkok",
    "iso:country":"TH",
    "name:tha_x_preferred":[
        "\u0e1a\u0e49\u0e32\u0e19\u0e2d\u0e48\u0e32\u0e27\u0e01\u0e38\u0e49\u0e07"
    ],
    "name:und_x_variant":[
        "Ban Bang Kung",
        "Ban Ao Kung"
    ],
    "wof:name":"Ban Ao Kung",
    "wof:placetype":"locality"
},
  "geometry": {"coordinates":[98.40461000000001,8.07647],"type":"Point"}
}