{
  "type": "Feature",
  "properties": {
    "gn:admin1_code":"24",
    "gn:asciiname":"Ban Nong Khu Khat",
    "gn:country_code":"TH",
    "gn:dem":191,
    "gn:feature_class":"P",
    "gn:feature_code":"PPL",
    "gn:name":"Ban Nong Khu Khat",
    "gn:population":0,
    "gn:timezone":"Asia/Bangkok",
    "iso:country":"TH",
    "name:tha_x_preferred":[
        "\u0e1a\u0e49\u0e32\u0e19\u0e2b\u0e19\u0e2d\u0e07\u0e04\u0e39\u0e02\u0e32\u0e14"
    ],
    "wof:name":"Ban Nong Khu Khat",
    "wof:placetype":"locality"
},
  "geometry": {"coordinates":[102.98786,15.92611],"type":"Point"}
}