{
  "type": "Feature",
  "properties": {
    "gn:admin1_code":"64.0",
    "gn:asciiname":"Ban Suan Mak",
    "gn:country_code":"TH",
    "gn:dem":37,
    "gn:feature_class":"P",
    "gn:feature_code":"PPL",
    "gn:name":"Ban Suan Mak",
    "gn:population":0,
    "gn:timezone":"Asia/Bangkok",
    "iso:country":"TH",
    "name:tha_x_preferred":[
        "\u0e1a\u0e49\u0e32\u0e19\u0e2a\u0e27\u0e19\u0e2b\u0e21\u0e32\u0e01"
    ],
    "wof:name":"Ban Suan Mak",
    "wof:placetype":"locality"
},
  "geometry": {"coordinates":[99.83696999999999,8.58886],"type":"Point"}
}