{
  "type": "Feature",
  "properties": {
    "gn:admin1_code":"68.0",
    "gn:asciiname":"Ban Khok Mao Tok",
    "gn:country_code":"TH",
    "gn:dem":13,
    "gn:feature_class":"P",
    "gn:feature_code":"PPL",
    "gn:name":"Ban Khok Mao Tok",
    "gn:population":0,
    "gn:timezone":"Asia/Bangkok",
    "iso:country":"TH",
    "name:tha_x_preferred":[
        "\u0e1a\u0e49\u0e32\u0e19\u0e42\u0e04\u0e01\u0e40\u0e21\u0e32\u0e15\u0e01"
    ],
    "wof:name":"Ban Khok Mao Tok",
    "wof:placetype":"locality"
},
  "geometry": {"coordinates":[100.43313999999999,7.0245],"type":"Point"}
}