{
  "type": "Feature",
  "properties": {
    "gn:admin1_code":"0.0",
    "gn:asciiname":"Ban Sop Mae Salit Luang",
    "gn:country_code":"TH",
    "gn:dem":1000,
    "gn:feature_class":"P",
    "gn:feature_code":"PPL",
    "gn:name":"Ban Sop Mae Salit Luang",
    "gn:population":0,
    "gn:timezone":"Asia/Bangkok",
    "iso:country":"TH",
    "wof:name":"Ban Sop Mae Salit Luang",
    "wof:placetype":"locality"
},
  "geometry": {"coordinates":[97.95,17.35],"type":"Point"}
}