{
  "type": "Feature",
  "properties": {
    "gn:admin1_code":"22",
    "gn:asciiname":"Ban Pracham Kong Thi Yi Sip",
    "gn:country_code":"TH",
    "gn:dem":193,
    "gn:feature_class":"P",
    "gn:feature_code":"PPL",
    "gn:name":"Ban Pracham Kong Thi Yi Sip",
    "gn:population":0,
    "gn:timezone":"Asia/Bangkok",
    "iso:country":"TH",
    "name:tha_x_preferred":[
        "\u0e1a\u0e49\u0e32\u0e19\u0e1b\u0e23\u0e30\u0e08\u0e33\u0e01\u0e2d\u0e07\u0e17\u0e35\u0e48 \u0e22\u0e35\u0e48\u0e2a\u0e34\u0e1a"
    ],
    "wof:name":"Ban Pracham Kong Thi Yi Sip",
    "wof:placetype":"locality"
},
  "geometry": {"coordinates":[102.62447,15.85917],"type":"Point"}
}