{
  "type": "Feature",
  "properties": {
    "gn:admin1_code":"52.0",
    "gn:asciiname":"Ban Phu Wai",
    "gn:country_code":"TH",
    "gn:dem":215,
    "gn:feature_class":"P",
    "gn:feature_code":"PPL",
    "gn:name":"Ban Phu Wai",
    "gn:population":0,
    "gn:timezone":"Asia/Bangkok",
    "iso:country":"TH",
    "name:tha_x_preferred":[
        "\u0e1a\u0e49\u0e32\u0e19\u0e1e\u0e39\u0e2b\u0e27\u0e32\u0e22"
    ],
    "wof:name":"Ban Phu Wai",
    "wof:placetype":"locality"
},
  "geometry": {"coordinates":[99.54694000000001,13.30375],"type":"Point"}
}