{
  "type": "Feature",
  "properties": {
    "gn:admin1_code":"76.0",
    "gn:asciiname":"Ban Dong Samphan",
    "gn:country_code":"TH",
    "gn:dem":198,
    "gn:feature_class":"P",
    "gn:feature_code":"PPL",
    "gn:name":"Ban Dong Samphan",
    "gn:population":0,
    "gn:timezone":"Asia/Bangkok",
    "iso:country":"TH",
    "name:tha_x_preferred":[
        "\u0e1a\u0e49\u0e32\u0e19\u0e14\u0e07\u0e2a\u0e31\u0e21\u0e1e\u0e31\u0e19\u0e18\u0e4c"
    ],
    "wof:name":"Ban Dong Samphan",
    "wof:placetype":"locality"
},
  "geometry": {"coordinates":[102.96903,17.70218999999999],"type":"Point"}
}