{
  "type": "Feature",
  "properties": {
    "gn:admin1_code":"2.0",
    "gn:asciiname":"Ban Yang Khram",
    "gn:cc2":"TH",
    "gn:country_code":"TH",
    "gn:dem":503,
    "gn:feature_class":"P",
    "gn:feature_code":"PPL",
    "gn:name":"Ban Yang Khram",
    "gn:population":0,
    "gn:timezone":"Asia/Bangkok",
    "iso:country":"TH",
    "name:und_x_variant":[
        "Ban Yang Kram",
        "Ban Yang Khram"
    ],
    "wof:name":"Ban Yang Khram",
    "wof:placetype":"locality"
},
  "geometry": {"coordinates":[98.68333,18.58333],"type":"Point"}
}