{
  "type": "Feature",
  "properties": {
    "gn:admin1_code":"3.0",
    "gn:asciiname":"Ban Hong Long",
    "gn:country_code":"TH",
    "gn:dem":415,
    "gn:feature_class":"P",
    "gn:feature_code":"PPL",
    "gn:name":"Ban Hong Long",
    "gn:population":0,
    "gn:timezone":"Asia/Bangkok",
    "iso:country":"TH",
    "name:tha_x_preferred":[
        "\u0e1a\u0e49\u0e32\u0e19\u0e2e\u0e48\u0e2d\u0e07\u0e2b\u0e25\u0e07"
    ],
    "name:und_x_variant":[
        "Ban Haung Long",
        "Ban Hong Long",
        "Ban Hong Long (1)"
    ],
    "wof:name":"Ban Hong Long",
    "wof:placetype":"locality"
},
  "geometry": {"coordinates":[99.73786,19.558],"type":"Point"}
}