{
  "type": "Feature",
  "properties": {
    "gn:admin1_code":"79.0",
    "gn:asciiname":"Ban Non Wa Thong",
    "gn:country_code":"TH",
    "gn:dem":263,
    "gn:feature_class":"P",
    "gn:feature_code":"PPL",
    "gn:name":"Ban Non Wa Thong",
    "gn:population":0,
    "gn:timezone":"Asia/Bangkok",
    "iso:country":"TH",
    "name:tha_x_preferred":[
        "\u0e1a\u0e49\u0e32\u0e19\u0e42\u0e19\u0e19\u0e2b\u0e27\u0e49\u0e32\u0e17\u0e2d\u0e07"
    ],
    "wof:name":"Ban Non Wa Thong",
    "wof:placetype":"locality"
},
  "geometry": {"coordinates":[102.18894,17.14011],"type":"Point"}
}