{
  "type": "Feature",
  "properties": {
    "gn:admin1_code":"41.0",
    "gn:asciiname":"Ban Phra Nang Din",
    "gn:country_code":"TH",
    "gn:dem":404,
    "gn:feature_class":"P",
    "gn:feature_code":"PPL",
    "gn:name":"Ban Phra Nang Din",
    "gn:population":0,
    "gn:timezone":"Asia/Bangkok",
    "iso:country":"TH",
    "name:tha_x_preferred":[
        "\u0e1a\u0e49\u0e32\u0e19\u0e1e\u0e23\u0e30\u0e19\u0e31\u0e48\u0e07\u0e14\u0e34\u0e19"
    ],
    "wof:name":"Ban Phra Nang Din",
    "wof:placetype":"locality"
},
  "geometry": {"coordinates":[100.32553,19.49828],"type":"Point"}
}