{
  "type": "Feature",
  "properties": {
    "gn:admin1_code":"66.0",
    "gn:asciiname":"Ban Thung Sai Han",
    "gn:country_code":"TH",
    "gn:dem":6,
    "gn:feature_class":"P",
    "gn:feature_code":"PPL",
    "gn:name":"Ban Thung Sai Han",
    "gn:population":0,
    "gn:timezone":"Asia/Bangkok",
    "iso:country":"TH",
    "name:tha_x_preferred":[
        "\u0e1a\u0e49\u0e32\u0e19\u0e17\u0e38\u0e48\u0e07\u0e43\u0e2a\u0e2b\u0e32\u0e19"
    ],
    "wof:name":"Ban Thung Sai Han",
    "wof:placetype":"locality"
},
  "geometry": {"coordinates":[100.03852999999999,7.81872],"type":"Point"}
}