{
  "type": "Feature",
  "properties": {
    "gn:admin1_code":"16.0",
    "gn:asciiname":"Ban Thung Thai Noen",
    "gn:country_code":"TH",
    "gn:dem":38,
    "gn:feature_class":"P",
    "gn:feature_code":"PPL",
    "gn:name":"Ban Thung Thai Noen",
    "gn:population":0,
    "gn:timezone":"Asia/Bangkok",
    "iso:country":"TH",
    "name:tha_x_preferred":[
        "\u0e1a\u0e49\u0e32\u0e19\u0e17\u0e38\u0e48\u0e07\u0e17\u0e49\u0e32\u0e22\u0e40\u0e19\u0e34\u0e19"
    ],
    "wof:name":"Ban Thung Thai Noen",
    "wof:placetype":"locality"
},
  "geometry": {"coordinates":[100.57275,15.86558],"type":"Point"}
}