{
  "type": "Feature",
  "properties": {
    "gn:admin1_code":"28",
    "gn:asciiname":"Ban Rong Kuli",
    "gn:country_code":"TH",
    "gn:dem":188,
    "gn:feature_class":"P",
    "gn:feature_code":"PPL",
    "gn:name":"Ban Rong Kuli",
    "gn:population":0,
    "gn:timezone":"Asia/Bangkok",
    "iso:country":"TH",
    "name:tha_x_preferred":[
        "\u0e1a\u0e49\u0e32\u0e19\u0e42\u0e23\u0e07\u0e01\u0e38\u0e25\u0e35"
    ],
    "wof:name":"Ban Rong Kuli",
    "wof:placetype":"locality"
},
  "geometry": {"coordinates":[102.96025,15.02858],"type":"Point"}
}