{
  "type": "Feature",
  "properties": {
    "gn:admin1_code":"74.0",
    "gn:asciiname":"Ban Non Takhian",
    "gn:country_code":"TH",
    "gn:dem":33,
    "gn:feature_class":"P",
    "gn:feature_code":"PPL",
    "gn:name":"Ban Non Takhian",
    "gn:population":0,
    "gn:timezone":"Asia/Bangkok",
    "iso:country":"TH",
    "name:und_x_variant":[
        "Ban Hnong Bua",
        "Ban Non Takhian"
    ],
    "wof:name":"Ban Non Takhian",
    "wof:placetype":"locality"
},
  "geometry": {"coordinates":[101.65000000000001,14.06667],"type":"Point"}
}