{
  "type": "Feature",
  "properties": {
    "gn:admin1_code":"53.0",
    "gn:asciiname":"Ban Suea I Dang",
    "gn:country_code":"TH",
    "gn:dem":7,
    "gn:feature_class":"P",
    "gn:feature_code":"PPL",
    "gn:name":"Ban Suea I Dang",
    "gn:population":0,
    "gn:timezone":"Asia/Bangkok",
    "iso:country":"TH",
    "name:tha_x_preferred":[
        "Ban Suea I Dang"
    ],
    "name:tha_x_variant":[
        "\u0e1a\u0e49\u0e32\u0e19\u0e40\u0e2a\u0e37\u0e2d\u0e2d\u0e35\u0e14\u0e48\u0e32\u0e07"
    ],
    "name:und_x_variant":[
        "Ban Sua I Dang"
    ],
    "wof:lang_x_official":[
        "tha"
    ],
    "wof:lang_x_spoken":[
        "tha"
    ],
    "wof:name":"Ban Suea I Dang",
    "wof:placetype":"locality"
},
  "geometry": {"coordinates":[100.02249999999999,14.05095],"type":"Point"}
}