{
  "type": "Feature",
  "properties": {
    "gn:admin1_code":"44.0",
    "gn:asciiname":"Ban Mai Hua Samrong",
    "gn:country_code":"TH",
    "gn:dem":10,
    "gn:feature_class":"P",
    "gn:feature_code":"PPL",
    "gn:name":"Ban Mai Hua Samrong",
    "gn:population":0,
    "gn:timezone":"Asia/Bangkok",
    "iso:country":"TH",
    "name:tha_x_preferred":[
        "\u0e1a\u0e49\u0e32\u0e19\u0e43\u0e2b\u0e21\u0e48\u0e2b\u0e31\u0e27\u0e2a\u0e33\u0e42\u0e23\u0e07"
    ],
    "wof:name":"Ban Mai Hua Samrong",
    "wof:placetype":"locality"
},
  "geometry": {"coordinates":[101.29246999999999,13.64647],"type":"Point"}
}