{
  "type": "Feature",
  "properties": {
    "gn:admin1_code":"75.0",
    "gn:asciiname":"Ban Kutsakon",
    "gn:country_code":"TH",
    "gn:dem":132,
    "gn:feature_class":"P",
    "gn:feature_code":"PPL",
    "gn:name":"Ban Kutsakon",
    "gn:population":0,
    "gn:timezone":"Asia/Bangkok",
    "iso:country":"TH",
    "name:tha_x_preferred":[
        "\u0e1a\u0e49\u0e32\u0e19\u0e01\u0e38\u0e28\u0e01\u0e23"
    ],
    "name:und_x_variant":[
        "Ban Khok Sakhu",
        "Ban Kutsakon"
    ],
    "wof:name":"Ban Kutsakon",
    "wof:placetype":"locality"
},
  "geometry": {"coordinates":[105.07275,15.57114],"type":"Point"}
}