{
  "type": "Feature",
  "properties": {
    "gn:admin1_code":"30.0",
    "gn:asciiname":"Ban Sayao",
    "gn:country_code":"TH",
    "gn:dem":187,
    "gn:feature_class":"P",
    "gn:feature_code":"PPL",
    "gn:name":"Ban Sayao",
    "gn:population":0,
    "gn:timezone":"Asia/Bangkok",
    "iso:country":"TH",
    "wof:name":"Ban Sayao",
    "wof:placetype":"locality"
},
  "geometry": {"coordinates":[104.51667,14.75],"type":"Point"}
}