{
  "type": "Feature",
  "properties": {
    "gn:admin1_code":"31.0",
    "gn:asciiname":"Ban Lilanon (Sam)",
    "gn:country_code":"TH",
    "gn:dem":120,
    "gn:feature_class":"P",
    "gn:feature_code":"PPL",
    "gn:name":"Ban Lilanon (Sam)",
    "gn:population":0,
    "gn:timezone":"Asia/Bangkok",
    "iso:country":"TH",
    "name:tha_x_preferred":[
        "\u0e1a\u0e49\u0e32\u0e19\u0e25\u0e35\u0e25\u0e32\u0e19\u0e19\u0e17\u0e4c (\u0e2a\u0e32\u0e21)"
    ],
    "name:und_x_variant":[
        "Ban Lilanon (3)",
        "Ban Lilanon (Sam)"
    ],
    "wof:name":"Ban Lilanon (Sam)",
    "wof:placetype":"locality"
},
  "geometry": {"coordinates":[101.65658000000001,5.95889],"type":"Point"}
}