{
  "type": "Feature",
  "properties": {
    "gn:admin1_code":"24.0",
    "gn:asciiname":"Ban Tio",
    "gn:country_code":"TH",
    "gn:dem":148,
    "gn:feature_class":"P",
    "gn:feature_code":"PPL",
    "gn:name":"Ban Tio",
    "gn:population":0,
    "gn:timezone":"Asia/Bangkok",
    "iso:country":"TH",
    "name:tha_x_preferred":[
        "\u0e1a\u0e49\u0e32\u0e19\u0e15\u0e34\u0e49\u0e27"
    ],
    "name:und_x_variant":[
        "Ban Tiu"
    ],
    "wof:name":"Ban Tio",
    "wof:placetype":"locality"
},
  "geometry": {"coordinates":[103.35539,16.17289],"type":"Point"}
}