{
  "type": "Feature",
  "properties": {
    "gn:admin1_code":"36.0",
    "gn:asciiname":"Ban Don Krasang",
    "gn:country_code":"TH",
    "gn:dem":13,
    "gn:feature_class":"P",
    "gn:feature_code":"PPL",
    "gn:name":"Ban Don Krasang",
    "gn:population":0,
    "gn:timezone":"Asia/Bangkok",
    "iso:country":"TH",
    "name:tha_x_preferred":[
        "\u0e1a\u0e49\u0e32\u0e19\u0e14\u0e2d\u0e19\u0e01\u0e23\u0e30\u0e2a\u0e31\u0e07\u0e02\u0e4c"
    ],
    "name:und_x_variant":[
        "Ban Don Kasang",
        "Ban Don Krasang"
    ],
    "wof:name":"Ban Don Krasang",
    "wof:placetype":"locality"
},
  "geometry": {"coordinates":[100.70793999999999,14.57311],"type":"Point"}
}