{
  "type": "Feature",
  "properties": {
    "gn:admin1_code":"66.0",
    "gn:asciiname":"Ban Phoeng",
    "gn:country_code":"TH",
    "gn:dem":15,
    "gn:feature_class":"P",
    "gn:feature_code":"PPL",
    "gn:name":"Ban Phoeng",
    "gn:population":0,
    "gn:timezone":"Asia/Bangkok",
    "iso:country":"TH",
    "name:tha_x_preferred":[
        "\u0e1a\u0e49\u0e32\u0e19\u0e40\u0e1e\u0e34\u0e07"
    ],
    "name:und_x_variant":[
        "Ban Ploeng",
        "Ban Phloeng",
        "Ban Phoeng"
    ],
    "wof:name":"Ban Phoeng",
    "wof:placetype":"locality"
},
  "geometry": {"coordinates":[100.02200000000001,7.73739],"type":"Point"}
}