{
  "type": "Feature",
  "properties": {
    "gn:admin1_code":"12.0",
    "gn:asciiname":"Ban Wang Pradu",
    "gn:country_code":"TH",
    "gn:dem":51,
    "gn:feature_class":"P",
    "gn:feature_code":"PPL",
    "gn:name":"Ban Wang Pradu",
    "gn:population":0,
    "gn:timezone":"Asia/Bangkok",
    "iso:country":"TH",
    "name:tha_x_preferred":[
        "\u0e1a\u0e49\u0e32\u0e19\u0e27\u0e31\u0e07\u0e1b\u0e23\u0e30\u0e14\u0e39\u0e48"
    ],
    "name:und_x_variant":[
        "Ban Wang Phikun (1)",
        "Ban Wang Phikun"
    ],
    "wof:name":"Ban Wang Pradu",
    "wof:placetype":"locality"
},
  "geometry": {"coordinates":[100.40458,16.77325],"type":"Point"}
}