{
  "type": "Feature",
  "properties": {
    "gn:admin1_code":"28",
    "gn:asciiname":"Ban Lako",
    "gn:country_code":"TH",
    "gn:dem":146,
    "gn:feature_class":"P",
    "gn:feature_code":"PPL",
    "gn:name":"Ban Lako",
    "gn:population":0,
    "gn:timezone":"Asia/Bangkok",
    "iso:country":"TH",
    "name:tha_x_preferred":[
        "\u0e1a\u0e49\u0e32\u0e19\u0e25\u0e30\u0e01\u0e2d"
    ],
    "wof:name":"Ban Lako",
    "wof:placetype":"locality"
},
  "geometry": {"coordinates":[103.19235999999999,15.17875],"type":"Point"}
}