{
  "type": "Feature",
  "properties": {
    "gn:admin1_code":"64.0",
    "gn:asciiname":"Ban Tha Len",
    "gn:country_code":"TH",
    "gn:dem":37,
    "gn:feature_class":"P",
    "gn:feature_code":"PPL",
    "gn:name":"Ban Tha Len",
    "gn:population":0,
    "gn:timezone":"Asia/Bangkok",
    "iso:country":"TH",
    "name:tha_x_preferred":[
        "\u0e1a\u0e49\u0e32\u0e19\u0e17\u0e48\u0e32\u0e40\u0e25\u0e19"
    ],
    "wof:name":"Ban Tha Len",
    "wof:placetype":"locality"
},
  "geometry": {"coordinates":[99.65069,8.03931],"type":"Point"}
}