{
  "type": "Feature",
  "properties": {
    "gn:admin1_code":"0.0",
    "gn:asciiname":"Ban Wiang Tai",
    "gn:country_code":"TH",
    "gn:dem":719,
    "gn:feature_class":"P",
    "gn:feature_code":"PPL",
    "gn:name":"Ban Wiang Tai",
    "gn:population":0,
    "gn:timezone":"Asia/Bangkok",
    "iso:country":"TH",
    "wof:name":"Ban Wiang Tai",
    "wof:placetype":"locality"
},
  "geometry": {"coordinates":[98.41667,19.25],"type":"Point"}
}