{
  "type": "Feature",
  "properties": {
    "gn:admin1_code":"64.0",
    "gn:asciiname":"Ban Na Khliang",
    "gn:country_code":"TH",
    "gn:dem":54,
    "gn:feature_class":"P",
    "gn:feature_code":"PPL",
    "gn:name":"Ban Na Khliang",
    "gn:population":0,
    "gn:timezone":"Asia/Bangkok",
    "iso:country":"TH",
    "name:tha_x_preferred":[
        "\u0e1a\u0e49\u0e32\u0e19\u0e19\u0e32\u0e40\u0e02\u0e25\u0e35\u0e22\u0e07"
    ],
    "wof:name":"Ban Na Khliang",
    "wof:placetype":"locality"
},
  "geometry": {"coordinates":[99.50886,8.53247],"type":"Point"}
}