{
  "type": "Feature",
  "properties": {
    "gn:admin1_code":"2.0",
    "gn:asciiname":"Ban Mae Khom Tai",
    "gn:country_code":"TH",
    "gn:dem":1002,
    "gn:feature_class":"P",
    "gn:feature_code":"PPL",
    "gn:name":"Ban Mae Khom Tai",
    "gn:population":0,
    "gn:timezone":"Asia/Bangkok",
    "iso:country":"TH",
    "name:tha_x_preferred":[
        "\u0e1a\u0e49\u0e32\u0e19\u0e41\u0e21\u0e48\u0e02\u0e2d\u0e21\u0e43\u0e15\u0e49"
    ],
    "wof:name":"Ban Mae Khom Tai",
    "wof:placetype":"locality"
},
  "geometry": {"coordinates":[98.26025,18.60495],"type":"Point"}
}