{
  "type": "Feature",
  "properties": {
    "gn:admin1_code":"56.0",
    "gn:asciiname":"Ban Nong Khuean",
    "gn:country_code":"TH",
    "gn:dem":54,
    "gn:feature_class":"P",
    "gn:feature_code":"PPL",
    "gn:name":"Ban Nong Khuean",
    "gn:population":0,
    "gn:timezone":"Asia/Bangkok",
    "iso:country":"TH",
    "name:tha_x_preferred":[
        "\u0e1a\u0e49\u0e32\u0e19\u0e2b\u0e19\u0e2d\u0e07\u0e40\u0e02\u0e37\u0e48\u0e2d\u0e19"
    ],
    "wof:name":"Ban Nong Khuean",
    "wof:placetype":"locality"
},
  "geometry": {"coordinates":[99.84627999999999,12.65561],"type":"Point"}
}