{
  "type": "Feature",
  "properties": {
    "gn:admin1_code":"9.0",
    "gn:asciiname":"Ban Chetuphon",
    "gn:country_code":"TH",
    "gn:dem":62,
    "gn:feature_class":"P",
    "gn:feature_code":"PPL",
    "gn:name":"Ban Chetuphon",
    "gn:population":0,
    "gn:timezone":"Asia/Bangkok",
    "iso:country":"TH",
    "name:tha_x_preferred":[
        "\u0e1a\u0e49\u0e32\u0e19\u0e40\u0e0a\u0e15\u0e38\u0e1e\u0e19"
    ],
    "wof:name":"Ban Chetuphon",
    "wof:placetype":"locality"
},
  "geometry": {"coordinates":[99.70744000000001,17.00731],"type":"Point"}
}