{
  "type": "Feature",
  "properties": {
    "gn:admin1_code":"41.0",
    "gn:asciiname":"Ban Thung Nong",
    "gn:country_code":"TH",
    "gn:dem":282,
    "gn:feature_class":"P",
    "gn:feature_code":"PPL",
    "gn:name":"Ban Thung Nong",
    "gn:population":0,
    "gn:timezone":"Asia/Bangkok",
    "iso:country":"TH",
    "name:tha_x_preferred":[
        "\u0e1a\u0e49\u0e32\u0e19\u0e17\u0e38\u0e48\u0e07\u0e2b\u0e19\u0e2d\u0e07"
    ],
    "wof:name":"Ban Thung Nong",
    "wof:placetype":"locality"
},
  "geometry": {"coordinates":[100.26327999999999,18.94239],"type":"Point"}
}