{
  "type": "Feature",
  "properties": {
    "gn:admin1_code":"49.0",
    "gn:asciiname":"Ban Takang",
    "gn:country_code":"TH",
    "gn:dem":9,
    "gn:feature_class":"P",
    "gn:feature_code":"PPL",
    "gn:name":"Ban Takang",
    "gn:population":0,
    "gn:timezone":"Asia/Bangkok",
    "iso:country":"TH",
    "name:tha_x_preferred":[
        "\u0e1a\u0e49\u0e32\u0e19\u0e15\u0e30\u0e01\u0e32\u0e07"
    ],
    "name:und_x_variant":[
        "Takang",
        "Ban Takang"
    ],
    "wof:name":"Ban Takang",
    "wof:placetype":"locality"
},
  "geometry": {"coordinates":[102.63120000000001,12.22824],"type":"Point"}
}