{
  "type": "Feature",
  "properties": {
    "gn:admin1_code":"16.0",
    "gn:asciiname":"Ban Thap Krit Klang",
    "gn:country_code":"TH",
    "gn:dem":26,
    "gn:feature_class":"P",
    "gn:feature_code":"PPL",
    "gn:name":"Ban Thap Krit Klang",
    "gn:population":0,
    "gn:timezone":"Asia/Bangkok",
    "iso:country":"TH",
    "name:tha_x_preferred":[
        "\u0e1a\u0e49\u0e32\u0e19\u0e17\u0e31\u0e1a\u0e01\u0e24\u0e29\u0e01\u0e25\u0e32\u0e07"
    ],
    "wof:name":"Ban Thap Krit Klang",
    "wof:placetype":"locality"
},
  "geometry": {"coordinates":[100.25843999999999,15.77817],"type":"Point"}
}