{
  "type": "Feature",
  "properties": {
    "gn:admin1_code":"22.0",
    "gn:asciiname":"Ban Na Nam Sam",
    "gn:country_code":"TH",
    "gn:dem":264,
    "gn:feature_class":"P",
    "gn:feature_code":"PPL",
    "gn:name":"Ban Na Nam Sam",
    "gn:population":0,
    "gn:timezone":"Asia/Bangkok",
    "iso:country":"TH",
    "name:tha_x_preferred":[
        "\u0e1a\u0e49\u0e32\u0e19\u0e19\u0e32\u0e19\u0e49\u0e33\u0e0b\u0e33"
    ],
    "name:und_x_variant":[
        "Ban Nam Sam"
    ],
    "wof:name":"Ban Na Nam Sam",
    "wof:placetype":"locality"
},
  "geometry": {"coordinates":[101.92261000000001,16.66719],"type":"Point"}
}