{
  "type": "Feature",
  "properties": {
    "gn:admin1_code":"78.0",
    "gn:asciiname":"Ban Dong Phu",
    "gn:country_code":"TH",
    "gn:dem":180,
    "gn:feature_class":"P",
    "gn:feature_code":"PPL",
    "gn:name":"Ban Dong Phu",
    "gn:population":0,
    "gn:timezone":"Asia/Bangkok",
    "iso:country":"TH",
    "name:tha_x_preferred":[
        "Ban Dong Phu"
    ],
    "name:tha_x_variant":[
        "\u0e1a\u0e49\u0e32\u0e19\u0e14\u0e07\u0e20\u0e39\u0e48"
    ],
    "wof:name":"Ban Dong Phu",
    "wof:placetype":"locality"
},
  "geometry": {"coordinates":[104.41828,16.58695],"type":"Point"}
}