{
  "type": "Feature",
  "properties": {
    "gn:admin1_code":"28",
    "gn:asciiname":"Ban Phalai Phatthana",
    "gn:country_code":"TH",
    "gn:dem":159,
    "gn:feature_class":"P",
    "gn:feature_code":"PPL",
    "gn:name":"Ban Phalai Phatthana",
    "gn:population":0,
    "gn:timezone":"Asia/Bangkok",
    "iso:country":"TH",
    "name:tha_x_preferred":[
        "\u0e1a\u0e49\u0e32\u0e19\u0e1e\u0e30\u0e44\u0e25\u0e1e\u0e31\u0e12\u0e19\u0e32"
    ],
    "wof:name":"Ban Phalai Phatthana",
    "wof:placetype":"locality"
},
  "geometry": {"coordinates":[103.09981000000001,15.12286],"type":"Point"}
}