{
  "type": "Feature",
  "properties": {
    "gn:admin1_code":"9.0",
    "gn:asciiname":"Ban Na Khao Bao",
    "gn:country_code":"TH",
    "gn:dem":48,
    "gn:feature_class":"P",
    "gn:feature_code":"PPL",
    "gn:name":"Ban Na Khao Bao",
    "gn:population":0,
    "gn:timezone":"Asia/Bangkok",
    "iso:country":"TH",
    "name:tha_x_preferred":[
        "\u0e1a\u0e49\u0e32\u0e19\u0e19\u0e32\u0e02\u0e49\u0e32\u0e27\u0e40\u0e1a\u0e32"
    ],
    "wof:name":"Ban Na Khao Bao",
    "wof:placetype":"locality"
},
  "geometry": {"coordinates":[99.95142,16.95208],"type":"Point"}
}