{
  "type": "Feature",
  "properties": {
    "gn:admin1_code":"15.0",
    "gn:asciiname":"Ban Pa Sa Kae",
    "gn:country_code":"TH",
    "gn:dem":25,
    "gn:feature_class":"P",
    "gn:feature_code":"PPL",
    "gn:name":"Ban Pa Sa Kae",
    "gn:population":0,
    "gn:timezone":"Asia/Bangkok",
    "iso:country":"TH",
    "name:tha_x_preferred":[
        "\u0e1a\u0e49\u0e32\u0e19\u0e1b\u0e48\u0e32\u0e2a\u0e30\u0e41\u0e01"
    ],
    "wof:name":"Ban Pa Sa Kae",
    "wof:placetype":"locality"
},
  "geometry": {"coordinates":[100.07983,15.35969],"type":"Point"}
}