{
  "type": "Feature",
  "properties": {
    "gn:admin1_code":"14.0",
    "gn:asciiname":"Ban Dong Mafai",
    "gn:country_code":"TH",
    "gn:dem":713,
    "gn:feature_class":"P",
    "gn:feature_code":"PPL",
    "gn:name":"Ban Dong Mafai",
    "gn:population":0,
    "gn:timezone":"Asia/Bangkok",
    "iso:country":"TH",
    "name:tha_x_preferred":[
        "\u0e1a\u0e49\u0e32\u0e19\u0e14\u0e07\u0e21\u0e30\u0e44\u0e1f"
    ],
    "wof:name":"Ban Dong Mafai",
    "wof:placetype":"locality"
},
  "geometry": {"coordinates":[101.76846999999999,16.73053],"type":"Point"}
}