{
  "type": "Feature",
  "properties": {
    "gn:admin1_code":"69.0",
    "gn:asciiname":"Kampong Ko Laka",
    "gn:cc2":"TH",
    "gn:country_code":"TH",
    "gn:dem":7,
    "gn:feature_class":"P",
    "gn:feature_code":"PPL",
    "gn:name":"Kampong Ko Laka",
    "gn:population":0,
    "gn:timezone":"Asia/Bangkok",
    "iso:country":"TH",
    "name:und_x_variant":[
        "Kampong Kok Laka",
        "Kampong Kau La Sa",
        "Kampong Ko Laka"
    ],
    "wof:name":"Kampong Ko Laka",
    "wof:placetype":"locality"
},
  "geometry": {"coordinates":[101.33333,6.83333],"type":"Point"}
}