{
  "type": "Feature",
  "properties": {
    "gn:admin1_code":"60.0",
    "gn:asciiname":"Ban Bo Nam Phut",
    "gn:country_code":"TH",
    "gn:dem":47,
    "gn:feature_class":"P",
    "gn:feature_code":"PPL",
    "gn:name":"Ban Bo Nam Phut",
    "gn:population":0,
    "gn:timezone":"Asia/Bangkok",
    "iso:country":"TH",
    "name:tha_x_preferred":[
        "\u0e1a\u0e49\u0e32\u0e19\u0e1a\u0e48\u0e2d\u0e19\u0e49\u0e33\u0e1c\u0e38\u0e14"
    ],
    "wof:name":"Ban Bo Nam Phut",
    "wof:placetype":"locality"
},
  "geometry": {"coordinates":[99.06186,8.92444],"type":"Point"}
}