{
  "type": "Feature",
  "properties": {
    "gn:admin1_code":"50.0",
    "gn:asciiname":"Ban Pa Nawakan",
    "gn:country_code":"TH",
    "gn:dem":153,
    "gn:feature_class":"P",
    "gn:feature_code":"PPL",
    "gn:name":"Ban Pa Nawakan",
    "gn:population":0,
    "gn:timezone":"Asia/Bangkok",
    "iso:country":"TH",
    "name:tha_x_preferred":[
        "\u0e1a\u0e49\u0e32\u0e19\u0e1b\u0e48\u0e32\u0e19\u0e27\u0e01\u0e32\u0e0d\u0e08\u0e19\u0e4c"
    ],
    "wof:name":"Ban Pa Nawakan",
    "wof:placetype":"locality"
},
  "geometry": {"coordinates":[99.0065,14.23306],"type":"Point"}
}