{
  "type": "Feature",
  "properties": {
    "gn:admin1_code":"0.0",
    "gn:asciiname":"Ban Huai Dua",
    "gn:country_code":"TH",
    "gn:dem":766,
    "gn:feature_class":"P",
    "gn:feature_code":"PPL",
    "gn:name":"Ban Huai Dua",
    "gn:population":0,
    "gn:timezone":"Asia/Bangkok",
    "iso:country":"TH",
    "wof:name":"Ban Huai Dua",
    "wof:placetype":"locality"
},
  "geometry": {"coordinates":[98.51667,19.08333],"type":"Point"}
}