{
  "type": "Feature",
  "properties": {
    "gn:admin1_code":"52.0",
    "gn:asciiname":"Ban Don Pho",
    "gn:country_code":"TH",
    "gn:dem":8,
    "gn:feature_class":"P",
    "gn:feature_code":"PPL",
    "gn:name":"Ban Don Pho",
    "gn:population":0,
    "gn:timezone":"Asia/Bangkok",
    "iso:country":"TH",
    "name:tha_x_preferred":[
        "\u0e1a\u0e49\u0e32\u0e19\u0e14\u0e2d\u0e19\u0e42\u0e1e\u0e18\u0e34\u0e4c"
    ],
    "wof:name":"Ban Don Pho",
    "wof:placetype":"locality"
},
  "geometry": {"coordinates":[99.88381,13.61933],"type":"Point"}
}