{
  "type": "Feature",
  "properties": {
    "gn:admin1_code":"50.0",
    "gn:asciiname":"Ban Choeng Khao",
    "gn:country_code":"TH",
    "gn:dem":233,
    "gn:feature_class":"P",
    "gn:feature_code":"PPL",
    "gn:name":"Ban Choeng Khao",
    "gn:population":0,
    "gn:timezone":"Asia/Bangkok",
    "iso:country":"TH",
    "name:tha_x_preferred":[
        "\u0e1a\u0e49\u0e32\u0e19\u0e40\u0e0a\u0e34\u0e07\u0e40\u0e02\u0e32"
    ],
    "wof:name":"Ban Choeng Khao",
    "wof:placetype":"locality"
},
  "geometry": {"coordinates":[98.50547,14.69339],"type":"Point"}
}