{
  "type": "Feature",
  "properties": {
    "gn:admin1_code":"73.0",
    "gn:asciiname":"Ban Na Phra",
    "gn:country_code":"TH",
    "gn:dem":155,
    "gn:feature_class":"P",
    "gn:feature_code":"PPL",
    "gn:name":"Ban Na Phra",
    "gn:population":0,
    "gn:timezone":"Asia/Bangkok",
    "iso:country":"TH",
    "name:tha_x_preferred":[
        "Ban Na Phra"
    ],
    "name:tha_x_variant":[
        "\u0e1a\u0e49\u0e32\u0e19\u0e19\u0e32\u0e1e\u0e23\u0e30"
    ],
    "wof:name":"Ban Na Phra",
    "wof:placetype":"locality"
},
  "geometry": {"coordinates":[104.07339,17.48561],"type":"Point"}
}