{
  "type": "Feature",
  "properties": {
    "gn:admin1_code":"44.0",
    "gn:asciiname":"Ban Bueng Phan Thong",
    "gn:country_code":"TH",
    "gn:dem":3,
    "gn:feature_class":"P",
    "gn:feature_code":"PPL",
    "gn:name":"Ban Bueng Phan Thong",
    "gn:population":0,
    "gn:timezone":"Asia/Bangkok",
    "iso:country":"TH",
    "name:tha_x_preferred":[
        "\u0e1a\u0e49\u0e32\u0e19\u0e1a\u0e36\u0e07\u0e1e\u0e32\u0e19\u0e17\u0e2d\u0e07"
    ],
    "wof:name":"Ban Bueng Phan Thong",
    "wof:placetype":"locality"
},
  "geometry": {"coordinates":[101.28294,13.85347],"type":"Point"}
}