{
  "type": "Feature",
  "properties": {
    "gn:admin1_code":"35.0",
    "gn:asciiname":"Ban Bang Chao Cha",
    "gn:country_code":"TH",
    "gn:dem":12,
    "gn:feature_class":"P",
    "gn:feature_code":"PPL",
    "gn:name":"Ban Bang Chao Cha",
    "gn:population":0,
    "gn:timezone":"Asia/Bangkok",
    "iso:country":"TH",
    "name:tha_x_preferred":[
        "\u0e1a\u0e49\u0e32\u0e19\u0e1a\u0e32\u0e07\u0e40\u0e08\u0e49\u0e32\u0e09\u0e48\u0e32"
    ],
    "name:und_x_variant":[
        "Ban Bang Chao Cha Tok",
        "Ban Bang Chao Cha"
    ],
    "wof:name":"Ban Bang Chao Cha",
    "wof:placetype":"locality"
},
  "geometry": {"coordinates":[100.41364,14.70161],"type":"Point"}
}