{
  "type": "Feature",
  "properties": {
    "gn:admin1_code":"2.0",
    "gn:asciiname":"Ban Pang Puk",
    "gn:cc2":"TH",
    "gn:country_code":"TH",
    "gn:dem":413,
    "gn:feature_class":"P",
    "gn:feature_code":"PPL",
    "gn:name":"Ban Pang Puk",
    "gn:population":0,
    "gn:timezone":"Asia/Bangkok",
    "iso:country":"TH",
    "name:und_x_variant":[
        "P\u0101ngfhakpok",
        "Ban Pang Phak Puk",
        "Pang Phak Puk",
        "Ban Pang Puk"
    ],
    "wof:name":"Ban Pang Puk",
    "wof:placetype":"locality"
},
  "geometry": {"coordinates":[98.83333,19.11667000000001],"type":"Point"}
}