{
  "type": "Feature",
  "properties": {
    "gn:admin1_code":"63.0",
    "gn:asciiname":"Ban Khuan Yung",
    "gn:country_code":"TH",
    "gn:dem":21,
    "gn:feature_class":"P",
    "gn:feature_code":"PPL",
    "gn:name":"Ban Khuan Yung",
    "gn:population":0,
    "gn:timezone":"Asia/Bangkok",
    "iso:country":"TH",
    "name:tha_x_preferred":[
        "\u0e1a\u0e49\u0e32\u0e19\u0e04\u0e27\u0e19\u0e22\u0e39\u0e07"
    ],
    "name:und_x_variant":[
        "Ban Khuan Yang",
        "Ban Khuan Yung"
    ],
    "wof:name":"Ban Khuan Yung",
    "wof:placetype":"locality"
},
  "geometry": {"coordinates":[99.03086,8.02083],"type":"Point"}
}