{
  "type": "Feature",
  "properties": {
    "gn:admin1_code":"11.0",
    "gn:asciiname":"Ban Mo Fai",
    "gn:country_code":"TH",
    "gn:dem":110,
    "gn:feature_class":"P",
    "gn:feature_code":"PPL",
    "gn:name":"Ban Mo Fai",
    "gn:population":0,
    "gn:timezone":"Asia/Bangkok",
    "iso:country":"TH",
    "name:tha_x_preferred":[
        "\u0e1a\u0e49\u0e32\u0e19\u0e21\u0e2d\u0e1d\u0e49\u0e32\u0e22"
    ],
    "wof:name":"Ban Mo Fai",
    "wof:placetype":"locality"
},
  "geometry": {"coordinates":[99.39886,16.35369],"type":"Point"}
}