{
  "type": "Feature",
  "properties": {
    "gn:admin1_code":"22.0",
    "gn:asciiname":"Ban Nong Waeng Mai",
    "gn:country_code":"TH",
    "gn:dem":190,
    "gn:feature_class":"P",
    "gn:feature_code":"PPL",
    "gn:name":"Ban Nong Waeng Mai",
    "gn:population":0,
    "gn:timezone":"Asia/Bangkok",
    "iso:country":"TH",
    "name:tha_x_preferred":[
        "\u0e1a\u0e49\u0e32\u0e19\u0e2b\u0e19\u0e2d\u0e07\u0e41\u0e27\u0e07\u0e43\u0e2b\u0e21\u0e48"
    ],
    "name:und_x_variant":[
        "Ban Nong Waeng"
    ],
    "wof:name":"Ban Nong Waeng Mai",
    "wof:placetype":"locality"
},
  "geometry": {"coordinates":[102.71494,16.83042],"type":"Point"}
}