{
  "type": "Feature",
  "properties": {
    "gn:admin1_code":"20.0",
    "gn:asciiname":"Ban Mai Thai Sueksa",
    "gn:country_code":"TH",
    "gn:dem":162,
    "gn:feature_class":"P",
    "gn:feature_code":"PPL",
    "gn:name":"Ban Mai Thai Sueksa",
    "gn:population":0,
    "gn:timezone":"Asia/Bangkok",
    "iso:country":"TH",
    "name:tha_x_preferred":[
        "\u0e1a\u0e49\u0e32\u0e19\u0e43\u0e2b\u0e21\u0e48\u0e44\u0e17\u0e22\u0e28\u0e36\u0e01\u0e29\u0e32"
    ],
    "wof:name":"Ban Mai Thai Sueksa",
    "wof:placetype":"locality"
},
  "geometry": {"coordinates":[103.80922,17.76961],"type":"Point"}
}