{
  "type": "Feature",
  "properties": {
    "gn:admin1_code":"63.0",
    "gn:asciiname":"Ban Sai Yai",
    "gn:country_code":"TH",
    "gn:dem":76,
    "gn:feature_class":"P",
    "gn:feature_code":"PPL",
    "gn:name":"Ban Sai Yai",
    "gn:population":0,
    "gn:timezone":"Asia/Bangkok",
    "iso:country":"TH",
    "name:tha_x_preferred":[
        "\u0e1a\u0e49\u0e32\u0e19\u0e44\u0e2a\u0e43\u0e2b\u0e0d\u0e48"
    ],
    "wof:name":"Ban Sai Yai",
    "wof:placetype":"locality"
},
  "geometry": {"coordinates":[99.19525,8.29033],"type":"Point"}
}