{
  "type": "Feature",
  "properties": {
    "gn:admin1_code":"27",
    "gn:asciiname":"Ban Nong Bot",
    "gn:country_code":"TH",
    "gn:dem":201,
    "gn:feature_class":"P",
    "gn:feature_code":"PPL",
    "gn:name":"Ban Nong Bot",
    "gn:population":0,
    "gn:timezone":"Asia/Bangkok",
    "iso:country":"TH",
    "name:tha_x_preferred":[
        "\u0e1a\u0e49\u0e32\u0e19\u0e2b\u0e19\u0e2d\u0e07\u0e42\u0e1a\u0e2a\u0e16\u0e4c"
    ],
    "wof:name":"Ban Nong Bot",
    "wof:placetype":"locality"
},
  "geometry": {"coordinates":[102.14386,15.39278],"type":"Point"}
}