{
  "type": "Feature",
  "properties": {
    "gn:admin1_code":"27",
    "gn:asciiname":"Ban Nong Lahan Plakhao",
    "gn:country_code":"TH",
    "gn:dem":140,
    "gn:feature_class":"P",
    "gn:feature_code":"PPL",
    "gn:name":"Ban Nong Lahan Plakhao",
    "gn:population":0,
    "gn:timezone":"Asia/Bangkok",
    "iso:country":"TH",
    "name:tha_x_preferred":[
        "\u0e1a\u0e49\u0e32\u0e19\u0e2b\u0e19\u0e2d\u0e07\u0e25\u0e30\u0e2b\u0e32\u0e19\u0e1b\u0e25\u0e32\u0e40\u0e04\u0e49\u0e32"
    ],
    "wof:name":"Ban Nong Lahan Plakhao",
    "wof:placetype":"locality"
},
  "geometry": {"coordinates":[102.88569,15.5095],"type":"Point"}
}