{
  "type": "Feature",
  "properties": {
    "gn:admin1_code":"53.0",
    "gn:asciiname":"Ban Bang Rathuek",
    "gn:country_code":"TH",
    "gn:dem":6,
    "gn:feature_class":"P",
    "gn:feature_code":"PPL",
    "gn:name":"Ban Bang Rathuek",
    "gn:population":0,
    "gn:timezone":"Asia/Bangkok",
    "iso:country":"TH",
    "name:tha_x_preferred":[
        "\u0e1a\u0e49\u0e32\u0e19\u0e1a\u0e32\u0e07\u0e23\u0e30\u0e17\u0e36\u0e01"
    ],
    "name:und_x_variant":[
        "Ban Bang Thuk",
        "Ban Bang Toek",
        "Ban Bang Rathuek",
        "Ban Bang Rathuk"
    ],
    "wof:name":"Ban Bang Rathuek",
    "wof:placetype":"locality"
},
  "geometry": {"coordinates":[100.30136,13.74406],"type":"Point"}
}