{
  "type": "Feature",
  "properties": {
    "gn:admin1_code":"16.0",
    "gn:asciiname":"Ban Bang Pha Luang",
    "gn:cc2":"TH",
    "gn:country_code":"TH",
    "gn:dem":27,
    "gn:feature_class":"P",
    "gn:feature_code":"PPL",
    "gn:name":"Ban Bang Pha Luang",
    "gn:population":0,
    "gn:timezone":"Asia/Bangkok",
    "iso:country":"TH",
    "name:und_x_variant":[
        "Ban Bang Phra Luang",
        "B\u0101n B\u0101ng Pa Luang",
        "Ban Bang Pha Luang"
    ],
    "wof:name":"Ban Bang Pha Luang",
    "wof:placetype":"locality"
},
  "geometry": {"coordinates":[100.18333,15.78333],"type":"Point"}
}