{
  "type": "Feature",
  "properties": {
    "gn:admin1_code":"22.0",
    "gn:asciiname":"Ban Thang Phat",
    "gn:country_code":"TH",
    "gn:dem":162,
    "gn:feature_class":"P",
    "gn:feature_code":"PPL",
    "gn:name":"Ban Thang Phat",
    "gn:population":0,
    "gn:timezone":"Asia/Bangkok",
    "iso:country":"TH",
    "wof:name":"Ban Thang Phat",
    "wof:placetype":"locality"
},
  "geometry": {"coordinates":[102.71666999999999,16.15],"type":"Point"}
}