{
  "type": "Feature",
  "properties": {
    "gn:admin1_code":"80",
    "gn:asciiname":"Ban Noen Din Daeng",
    "gn:country_code":"TH",
    "gn:dem":43,
    "gn:feature_class":"P",
    "gn:feature_code":"PPL",
    "gn:name":"Ban Noen Din Daeng",
    "gn:population":0,
    "gn:timezone":"Asia/Bangkok",
    "iso:country":"TH",
    "name:tha_x_preferred":[
        "\u0e1a\u0e49\u0e32\u0e19\u0e40\u0e19\u0e34\u0e19\u0e14\u0e34\u0e19\u0e41\u0e14\u0e07"
    ],
    "wof:name":"Ban Noen Din Daeng",
    "wof:placetype":"locality"
},
  "geometry": {"coordinates":[101.98442,14.01392],"type":"Point"}
}