{
  "type": "Feature",
  "properties": {
    "gn:admin1_code":"28.0",
    "gn:asciiname":"Ban Nong Karako",
    "gn:country_code":"TH",
    "gn:dem":168,
    "gn:feature_class":"P",
    "gn:feature_code":"PPL",
    "gn:name":"Ban Nong Karako",
    "gn:population":0,
    "gn:timezone":"Asia/Bangkok",
    "iso:country":"TH",
    "name:tha_x_preferred":[
        "\u0e1a\u0e49\u0e32\u0e19\u0e2b\u0e19\u0e2d\u0e07\u0e01\u0e32\u0e23\u0e30\u0e42\u0e01"
    ],
    "wof:name":"Ban Nong Karako",
    "wof:placetype":"locality"
},
  "geometry": {"coordinates":[103.10867,15.27658],"type":"Point"}
}