{
  "type": "Feature",
  "properties": {
    "gn:admin1_code":"26.0",
    "gn:asciiname":"Ban Tat Pun",
    "gn:country_code":"TH",
    "gn:dem":284,
    "gn:feature_class":"P",
    "gn:feature_code":"PPL",
    "gn:name":"Ban Tat Pun",
    "gn:population":0,
    "gn:timezone":"Asia/Bangkok",
    "iso:country":"TH",
    "name:tha_x_preferred":[
        "\u0e1a\u0e49\u0e32\u0e19\u0e15\u0e32\u0e14\u0e1b\u0e39\u0e19"
    ],
    "wof:name":"Ban Tat Pun",
    "wof:placetype":"locality"
},
  "geometry": {"coordinates":[101.87869000000001,16.58056],"type":"Point"}
}