{
  "type": "Feature",
  "properties": {
    "gn:admin1_code":"22.0",
    "gn:asciiname":"Ban Hua Na Klang",
    "gn:country_code":"TH",
    "gn:dem":203,
    "gn:feature_class":"P",
    "gn:feature_code":"PPL",
    "gn:name":"Ban Hua Na Klang",
    "gn:population":0,
    "gn:timezone":"Asia/Bangkok",
    "iso:country":"TH",
    "name:tha_x_preferred":[
        "\u0e1a\u0e49\u0e32\u0e19\u0e2b\u0e31\u0e27\u0e19\u0e32\u0e01\u0e25\u0e32\u0e07"
    ],
    "wof:name":"Ban Hua Na Klang",
    "wof:placetype":"locality"
},
  "geometry": {"coordinates":[102.62897,15.95317],"type":"Point"}
}