{
  "type": "Feature",
  "properties": {
    "gn:admin1_code":"30.0",
    "gn:asciiname":"Ban O Pang Ko",
    "gn:country_code":"TH",
    "gn:dem":203,
    "gn:feature_class":"P",
    "gn:feature_code":"PPL",
    "gn:name":"Ban O Pang Ko",
    "gn:population":0,
    "gn:timezone":"Asia/Bangkok",
    "iso:country":"TH",
    "name:tha_x_preferred":[
        "\u0e1a\u0e49\u0e32\u0e19\u0e42\u0e2d\u0e1b\u0e31\u0e07\u0e42\u0e01\u0e27\u0e4c"
    ],
    "wof:name":"Ban O Pang Ko",
    "wof:placetype":"locality"
},
  "geometry": {"coordinates":[104.12092,14.47172],"type":"Point"}
}