{
  "type": "Feature",
  "properties": {
    "gn:admin1_code":"6.0",
    "gn:asciiname":"Ban Kio Huai Boek",
    "gn:country_code":"TH",
    "gn:dem":365,
    "gn:feature_class":"P",
    "gn:feature_code":"PPL",
    "gn:name":"Ban Kio Huai Boek",
    "gn:population":0,
    "gn:timezone":"Asia/Bangkok",
    "iso:country":"TH",
    "name:tha_x_preferred":[
        "\u0e1a\u0e49\u0e32\u0e19\u0e01\u0e34\u0e48\u0e27\u0e2b\u0e49\u0e27\u0e22\u0e40\u0e1a\u0e34\u0e01"
    ],
    "name:und_x_variant":[
        "Ban Sop Huai Boek"
    ],
    "wof:name":"Ban Kio Huai Boek",
    "wof:placetype":"locality"
},
  "geometry": {"coordinates":[99.121,18.12031],"type":"Point"}
}