{
  "type": "Feature",
  "properties": {
    "gn:admin1_code":"36",
    "gn:asciiname":"Ban Suan Thapthim",
    "gn:country_code":"TH",
    "gn:dem":15,
    "gn:feature_class":"P",
    "gn:feature_code":"PPL",
    "gn:name":"Ban Suan Thapthim",
    "gn:population":0,
    "gn:timezone":"Asia/Bangkok",
    "iso:country":"TH",
    "name:tha_x_preferred":[
        "\u0e1a\u0e49\u0e32\u0e19\u0e2a\u0e27\u0e19\u0e17\u0e31\u0e1a\u0e17\u0e34\u0e21"
    ],
    "wof:name":"Ban Suan Thapthim",
    "wof:placetype":"locality"
},
  "geometry": {"coordinates":[100.75706,14.56506],"type":"Point"}
}