{
  "type": "Feature",
  "properties": {
    "gn:admin1_code":"53.0",
    "gn:asciiname":"Ban Khlong Bang Luang",
    "gn:country_code":"TH",
    "gn:dem":5,
    "gn:feature_class":"P",
    "gn:feature_code":"PPL",
    "gn:name":"Ban Khlong Bang Luang",
    "gn:population":0,
    "gn:timezone":"Asia/Bangkok",
    "iso:country":"TH",
    "name:tha_x_preferred":[
        "\u0e1a\u0e49\u0e32\u0e19\u0e04\u0e25\u0e2d\u0e07\u0e1a\u0e32\u0e07\u0e2b\u0e25\u0e27\u0e07"
    ],
    "wof:name":"Ban Khlong Bang Luang",
    "wof:placetype":"locality"
},
  "geometry": {"coordinates":[100.22092000000001,13.74628],"type":"Point"}
}