{
  "type": "Feature",
  "properties": {
    "gn:admin1_code":"60.0",
    "gn:asciiname":"Ban Hua Wiang",
    "gn:country_code":"TH",
    "gn:dem":13,
    "gn:feature_class":"P",
    "gn:feature_code":"PPL",
    "gn:name":"Ban Hua Wiang",
    "gn:population":0,
    "gn:timezone":"Asia/Bangkok",
    "iso:country":"TH",
    "name:tha_x_preferred":[
        "\u0e1a\u0e49\u0e32\u0e19\u0e2b\u0e31\u0e27\u0e40\u0e27\u0e35\u0e22\u0e07"
    ],
    "wof:name":"Ban Hua Wiang",
    "wof:placetype":"locality"
},
  "geometry": {"coordinates":[99.98833,9.44767],"type":"Point"}
}