{
  "type": "Feature",
  "properties": {
    "gn:admin1_code":"27",
    "gn:asciiname":"Ban Phang Thiam",
    "gn:country_code":"TH",
    "gn:dem":195,
    "gn:feature_class":"P",
    "gn:feature_code":"PPL",
    "gn:name":"Ban Phang Thiam",
    "gn:population":0,
    "gn:timezone":"Asia/Bangkok",
    "iso:country":"TH",
    "name:tha_x_preferred":[
        "\u0e1a\u0e49\u0e32\u0e19\u0e1e\u0e31\u0e07\u0e40\u0e17\u0e35\u0e22\u0e21"
    ],
    "wof:name":"Ban Phang Thiam",
    "wof:placetype":"locality"
},
  "geometry": {"coordinates":[102.00856,15.28536],"type":"Point"}
}