{
  "type": "Feature",
  "properties": {
    "gn:admin1_code":"36.0",
    "gn:asciiname":"Ban Krasong",
    "gn:cc2":"TH",
    "gn:country_code":"TH",
    "gn:dem":10,
    "gn:feature_class":"P",
    "gn:feature_code":"PPL",
    "gn:name":"Ban Krasong",
    "gn:population":0,
    "gn:timezone":"Asia/Bangkok",
    "iso:country":"TH",
    "name:und_x_variant":[
        "Ban Kra Zong",
        "Ban Krasong"
    ],
    "wof:name":"Ban Krasong",
    "wof:placetype":"locality"
},
  "geometry": {"coordinates":[100.53333000000001,14.58333],"type":"Point"}
}