{
  "type": "Feature",
  "properties": {
    "gn:admin1_code":"36.0",
    "gn:asciiname":"Ban Khlong Yi Sip Paet (1)",
    "gn:country_code":"TH",
    "gn:dem":2,
    "gn:feature_class":"P",
    "gn:feature_code":"PPL",
    "gn:name":"Ban Khlong Yi Sip Paet (1)",
    "gn:population":0,
    "gn:timezone":"Asia/Bangkok",
    "iso:country":"TH",
    "name:tha_x_preferred":[
        "Ban Khlong Yi Sip Paet (1)"
    ],
    "wof:name":"Ban Khlong Yi Sip Paet (1)",
    "wof:placetype":"locality"
},
  "geometry": {"coordinates":[100.78333000000001,14.31667],"type":"Point"}
}