{
  "type": "Feature",
  "properties": {
    "gn:admin1_code":"52.0",
    "gn:asciiname":"Ban Bang Kado",
    "gn:country_code":"TH",
    "gn:dem":8,
    "gn:feature_class":"P",
    "gn:feature_code":"PPL",
    "gn:name":"Ban Bang Kado",
    "gn:population":0,
    "gn:timezone":"Asia/Bangkok",
    "iso:country":"TH",
    "name:tha_x_preferred":[
        "\u0e1a\u0e49\u0e32\u0e19\u0e1a\u0e32\u0e07\u0e01\u0e30\u0e42\u0e14"
    ],
    "name:und_x_variant":[
        "Bang Krado",
        "Ban Bang Krado",
        "Ban Bang Kado"
    ],
    "wof:name":"Ban Bang Kado",
    "wof:placetype":"locality"
},
  "geometry": {"coordinates":[99.89899,13.65306],"type":"Point"}
}