{
  "type": "Feature",
  "properties": {
    "gn:admin1_code":"46.0",
    "gn:asciiname":"Ban Huai Kra Soem",
    "gn:country_code":"TH",
    "gn:dem":60,
    "gn:feature_class":"P",
    "gn:feature_code":"PPL",
    "gn:name":"Ban Huai Kra Soem",
    "gn:population":0,
    "gn:timezone":"Asia/Bangkok",
    "iso:country":"TH",
    "name:tha_x_preferred":[
        "\u0e1a\u0e49\u0e32\u0e19\u0e2b\u0e49\u0e27\u0e22\u0e01\u0e23\u0e30\u0e40\u0e2a\u0e23\u0e34\u0e21"
    ],
    "wof:name":"Ban Huai Kra Soem",
    "wof:placetype":"locality"
},
  "geometry": {"coordinates":[100.99366999999999,13.15381],"type":"Point"}
}