{
  "type": "Feature",
  "properties": {
    "gn:admin1_code":"53.0",
    "gn:asciiname":"Ban Phai Rong Wua",
    "gn:country_code":"TH",
    "gn:dem":10,
    "gn:feature_class":"P",
    "gn:feature_code":"PPL",
    "gn:name":"Ban Phai Rong Wua",
    "gn:population":0,
    "gn:timezone":"Asia/Bangkok",
    "iso:country":"TH",
    "name:tha_x_preferred":[
        "Ban Phai Rong Wua"
    ],
    "name:tha_x_variant":[
        "\u0e1a\u0e49\u0e32\u0e19\u0e44\u0e1c\u0e48\u0e42\u0e23\u0e07\u0e27\u0e31\u0e27"
    ],
    "wof:name":"Ban Phai Rong Wua",
    "wof:placetype":"locality"
},
  "geometry": {"coordinates":[100.16011,14.16422],"type":"Point"}
}