{
  "type": "Feature",
  "properties": {
    "gn:admin1_code":"1.0",
    "gn:asciiname":"Ban Mae Sakua",
    "gn:country_code":"TH",
    "gn:dem":839,
    "gn:feature_class":"P",
    "gn:feature_code":"PPL",
    "gn:name":"Ban Mae Sakua",
    "gn:population":0,
    "gn:timezone":"Asia/Bangkok",
    "iso:country":"TH",
    "name:tha_x_preferred":[
        "\u0e1a\u0e49\u0e32\u0e19\u0e41\u0e21\u0e48\u0e2a\u0e30\u0e01\u0e31\u0e4a\u0e27\u0e30"
    ],
    "wof:name":"Ban Mae Sakua",
    "wof:placetype":"locality"
},
  "geometry": {"coordinates":[98.00922,18.34961],"type":"Point"}
}