{
  "type": "Feature",
  "properties": {
    "gn:admin1_code":"7.0",
    "gn:asciiname":"Ban Dok Kham Tai",
    "gn:country_code":"TH",
    "gn:dem":152,
    "gn:feature_class":"P",
    "gn:feature_code":"PPL",
    "gn:name":"Ban Dok Kham Tai",
    "gn:population":0,
    "gn:timezone":"Asia/Bangkok",
    "iso:country":"TH",
    "name:tha_x_preferred":[
        "\u0e1a\u0e49\u0e32\u0e19\u0e14\u0e2d\u0e01\u0e04\u0e33\u0e43\u0e15\u0e49"
    ],
    "wof:name":"Ban Dok Kham Tai",
    "wof:placetype":"locality"
},
  "geometry": {"coordinates":[99.85208,18.01272],"type":"Point"}
}