{
  "type": "Feature",
  "properties": {
    "gn:admin1_code":"44.0",
    "gn:asciiname":"Ban Hua Sai",
    "gn:country_code":"TH",
    "gn:dem":6,
    "gn:feature_class":"P",
    "gn:feature_code":"PPL",
    "gn:name":"Ban Hua Sai",
    "gn:population":0,
    "gn:timezone":"Asia/Bangkok",
    "iso:country":"TH",
    "name:tha_x_preferred":[
        "\u0e1a\u0e49\u0e32\u0e19\u0e2b\u0e31\u0e27\u0e44\u0e17\u0e23"
    ],
    "name:und_x_variant":[
        "Hua Sai",
        "Ban Hua Sai"
    ],
    "wof:name":"Ban Hua Sai",
    "wof:placetype":"locality"
},
  "geometry": {"coordinates":[101.20778,13.77828],"type":"Point"}
}