{
  "type": "Feature",
  "properties": {
    "gn:admin1_code":"6.0",
    "gn:asciiname":"Ban Bo Si Nga",
    "gn:country_code":"TH",
    "gn:dem":226,
    "gn:feature_class":"P",
    "gn:feature_code":"PPL",
    "gn:name":"Ban Bo Si Nga",
    "gn:population":0,
    "gn:timezone":"Asia/Bangkok",
    "iso:country":"TH",
    "name:tha_x_preferred":[
        "\u0e1a\u0e49\u0e32\u0e19\u0e1a\u0e48\u0e2d\u0e28\u0e23\u0e35\u0e07\u0e32"
    ],
    "wof:name":"Ban Bo Si Nga",
    "wof:placetype":"locality"
},
  "geometry": {"coordinates":[99.39156,18.22028],"type":"Point"}
}