{
  "type": "Feature",
  "properties": {
    "gn:admin1_code":"32.0",
    "gn:asciiname":"Ban Don Makok",
    "gn:country_code":"TH",
    "gn:dem":17,
    "gn:feature_class":"P",
    "gn:feature_code":"PPL",
    "gn:name":"Ban Don Makok",
    "gn:population":0,
    "gn:timezone":"Asia/Bangkok",
    "iso:country":"TH",
    "name:tha_x_preferred":[
        "\u0e1a\u0e49\u0e32\u0e19\u0e14\u0e2d\u0e19\u0e21\u0e30\u0e01\u0e2d\u0e01"
    ],
    "wof:name":"Ban Don Makok",
    "wof:placetype":"locality"
},
  "geometry": {"coordinates":[100.15069,15.02461],"type":"Point"}
}