{
  "type": "Feature",
  "properties": {
    "gn:admin1_code":"50.0",
    "gn:asciiname":"Ban Krok Mo",
    "gn:country_code":"TH",
    "gn:dem":103,
    "gn:feature_class":"P",
    "gn:feature_code":"PPL",
    "gn:name":"Ban Krok Mo",
    "gn:population":0,
    "gn:timezone":"Asia/Bangkok",
    "iso:country":"TH",
    "name:tha_x_preferred":[
        "\u0e1a\u0e49\u0e32\u0e19\u0e42\u0e01\u0e23\u0e01\u0e2b\u0e21\u0e49\u0e2d"
    ],
    "wof:name":"Ban Krok Mo",
    "wof:placetype":"locality"
},
  "geometry": {"coordinates":[99.5355,14.11942],"type":"Point"}
}