{
  "type": "Feature",
  "properties": {
    "gn:country":"TH",
    "gn:fcode":"PPL",
    "gn:population":0,
    "iso:country":"TH",
    "name:ceb_x_preferred":[
        "Nong Bua"
    ],
    "name:tha_x_preferred":[
        "\u0e1a\u0e49\u0e32\u0e19\u0e2b\u0e19\u0e2d\u0e07\u0e1a\u0e31\u0e27"
    ],
    "name:tha_x_variant":[
        "\u0e2b\u0e19\u0e2d\u0e07\u0e1a\u0e31\u0e27"
    ],
    "name:und_x_variant":[
        "Ban Hnong Bua"
    ],
    "qs:name":"Nong Bua",
    "qs:name_adm0":"Thailand",
    "qs:name_adm1":"Kanchanaburi",
    "qs:photos":838,
    "qs:photos_1k":170,
    "qs:photos_9k":4,
    "qs:photos_9r":6,
    "qs:photos_all":838,
    "qs:photos_sr":9,
    "qs:placetype":"Town",
    "qs:pop_sr":"0",
    "wof:lang_x_official":[
        "tha"
    ],
    "wof:lang_x_spoken":[
        "tha"
    ],
    "wof:name":"Nong Bua",
    "wof:placetype":"locality",
    "wof:population":0
},
  "geometry": {"coordinates":[99.44739,14.05992],"type":"Point"}
}