{
  "type": "Feature",
  "properties": {
    "gn:admin1_code":"3.0",
    "gn:asciiname":"Ban Rom Fa Pha Mon",
    "gn:country_code":"TH",
    "gn:dem":1188,
    "gn:feature_class":"P",
    "gn:feature_code":"PPL",
    "gn:name":"Ban Rom Fa Pha Mon",
    "gn:population":0,
    "gn:timezone":"Asia/Bangkok",
    "iso:country":"TH",
    "name:tha_x_preferred":[
        "\u0e1a\u0e49\u0e32\u0e19\u0e23\u0e48\u0e21\u0e1f\u0e49\u0e32\u0e1c\u0e32\u0e2b\u0e21\u0e48\u0e19"
    ],
    "wof:name":"Ban Rom Fa Pha Mon",
    "wof:placetype":"locality"
},
  "geometry": {"coordinates":[100.50175,19.90347],"type":"Point"}
}