{
  "type": "Feature",
  "properties": {
    "gn:admin1_code":"36",
    "gn:asciiname":"Ban Lam Mae Lek",
    "gn:country_code":"TH",
    "gn:dem":7,
    "gn:feature_class":"P",
    "gn:feature_code":"PPL",
    "gn:name":"Ban Lam Mae Lek",
    "gn:population":0,
    "gn:timezone":"Asia/Bangkok",
    "iso:country":"TH",
    "name:tha_x_preferred":[
        "\u0e1a\u0e49\u0e32\u0e19\u0e25\u0e33\u0e41\u0e21\u0e48\u0e40\u0e2b\u0e25\u0e47\u0e01"
    ],
    "wof:name":"Ban Lam Mae Lek",
    "wof:placetype":"locality"
},
  "geometry": {"coordinates":[100.30235999999999,14.413],"type":"Point"}
}