{
  "type": "Feature",
  "properties": {
    "gn:country":"TH",
    "gn:fcode":"PPL",
    "gn:population":325,
    "iso:country":"TH",
    "name:rus_x_preferred":[
        "\u0410\u043e-\u0421\u0430\u043b\u0430\u0434"
    ],
    "qs:name":"Ban Ao Salad",
    "qs:photos_9r":0,
    "qs:photos_sr":0,
    "qs:pop_sr":"2",
    "wof:name":"Ban Ao Salad",
    "wof:placetype":"locality",
    "wof:population":325
},
  "geometry": {"coordinates":[102.56667,11.71667],"type":"Point"}
}