{
  "type": "Feature",
  "properties": {
    "gn:admin1_code":"14.0",
    "gn:asciiname":"Ban Tat Kha",
    "gn:country_code":"TH",
    "gn:dem":330,
    "gn:feature_class":"P",
    "gn:feature_code":"PPL",
    "gn:name":"Ban Tat Kha",
    "gn:population":0,
    "gn:timezone":"Asia/Bangkok",
    "iso:country":"TH",
    "name:tha_x_preferred":[
        "\u0e1a\u0e49\u0e32\u0e19\u0e15\u0e32\u0e14\u0e02\u0e48\u0e32"
    ],
    "wof:name":"Ban Tat Kha",
    "wof:placetype":"locality"
},
  "geometry": {"coordinates":[101.46232999999999,17.04786],"type":"Point"}
}