{
  "type": "Feature",
  "properties": {
    "gn:admin1_code":"42.0",
    "gn:asciiname":"Muban Ratchathani Song",
    "gn:country_code":"TH",
    "gn:dem":6,
    "gn:feature_class":"P",
    "gn:feature_code":"PPL",
    "gn:name":"Muban Ratchathani Song",
    "gn:population":0,
    "gn:timezone":"Asia/Bangkok",
    "iso:country":"TH",
    "name:tha_x_preferred":[
        "\u0e2b\u0e21\u0e39\u0e48\u0e1a\u0e49\u0e32\u0e19\u0e23\u0e31\u0e0a\u0e18\u0e32\u0e19\u0e35 \u0e2a\u0e2d\u0e07"
    ],
    "name:und_x_variant":[
        "Muban Ratchathani 2",
        "Muban Ratchathani Song"
    ],
    "wof:name":"Muban Ratchathani Song",
    "wof:placetype":"locality"
},
  "geometry": {"coordinates":[100.71819000000001,13.58875],"type":"Point"}
}