{
  "type": "Feature",
  "properties": {
    "gn:admin1_code":"9.0",
    "gn:asciiname":"Ban Sam Ruean",
    "gn:country_code":"TH",
    "gn:dem":60,
    "gn:feature_class":"P",
    "gn:feature_code":"PPL",
    "gn:name":"Ban Sam Ruean",
    "gn:population":0,
    "gn:timezone":"Asia/Bangkok",
    "iso:country":"TH",
    "name:tha_x_preferred":[
        "\u0e1a\u0e49\u0e32\u0e19\u0e2a\u0e32\u0e21\u0e40\u0e23\u0e37\u0e2d\u0e19"
    ],
    "wof:name":"Ban Sam Ruean",
    "wof:placetype":"locality"
},
  "geometry": {"coordinates":[99.86696999999999,17.17392000000001],"type":"Point"}
}