{
  "type": "Feature",
  "properties": {
    "gn:admin1_code":"24",
    "gn:asciiname":"Ban San Phatthana",
    "gn:country_code":"TH",
    "gn:dem":165,
    "gn:feature_class":"P",
    "gn:feature_code":"PPL",
    "gn:name":"Ban San Phatthana",
    "gn:population":0,
    "gn:timezone":"Asia/Bangkok",
    "iso:country":"TH",
    "name:tha_x_preferred":[
        "\u0e1a\u0e49\u0e32\u0e19\u0e2a\u0e32\u0e23\u0e1e\u0e31\u0e12\u0e19\u0e32"
    ],
    "wof:name":"Ban San Phatthana",
    "wof:placetype":"locality"
},
  "geometry": {"coordinates":[103.36844000000001,16.06628],"type":"Point"}
}