{
  "type": "Feature",
  "properties": {
    "gn:admin1_code":"64.0",
    "gn:asciiname":"xngkhkar thorsaphth rxnphibuly",
    "gn:country_code":"TH",
    "gn:dem":21,
    "gn:feature_class":"P",
    "gn:feature_code":"PPL",
    "gn:name":"\u0e2d\u0e07\u0e04\u0e4c\u0e01\u0e32\u0e23\u0e42\u0e17\u0e23\u0e28\u0e31\u0e1e\u0e17\u0e4c\u0e23\u0e48\u0e2d\u0e19\u0e1e\u0e34\u0e1a\u0e39\u0e25\u0e22\u0e4c",
    "gn:population":0,
    "gn:timezone":"Asia/Bangkok",
    "iso:country":"TH",
    "wof:lang_x_official":[
        "tha"
    ],
    "wof:lang_x_spoken":[
        "tha"
    ],
    "wof:name":"xngkhkar thorsaphth rxnphibuly",
    "wof:placetype":"locality"
},
  "geometry": {"coordinates":[99.85098000000001,8.16761],"type":"Point"}
}