{
  "type": "Feature",
  "properties": {
    "gn:admin1_code":"40.0",
    "gn:admin2_code":"1023.0",
    "gn:asciiname":"Muban Phong Siri Chai Si",
    "gn:country_code":"TH",
    "gn:dem":5,
    "gn:feature_class":"P",
    "gn:feature_code":"PPL",
    "gn:name":"Muban Phong Siri Chai Si",
    "gn:population":0,
    "gn:timezone":"Asia/Bangkok",
    "iso:country":"TH",
    "name:tha_x_preferred":[
        "\u0e2b\u0e21\u0e39\u0e48\u0e1a\u0e49\u0e32\u0e19\u0e1e\u0e07\u0e29\u0e4c\u0e28\u0e34\u0e23\u0e34\u0e0a\u0e31\u0e22 \u0e2a\u0e35\u0e48"
    ],
    "wof:name":"Muban Phong Siri Chai Si",
    "wof:placetype":"locality"
},
  "geometry": {"coordinates":[100.34456,13.69411],"type":"Point"}
}