{
  "type": "Feature",
  "properties": {
    "gn:admin1_code":"37.0",
    "gn:asciiname":"Ban Nong Cham Raet",
    "gn:country_code":"TH",
    "gn:dem":11,
    "gn:feature_class":"P",
    "gn:feature_code":"PPL",
    "gn:name":"Ban Nong Cham Raet",
    "gn:population":0,
    "gn:timezone":"Asia/Bangkok",
    "iso:country":"TH",
    "name:tha_x_preferred":[
        "\u0e1a\u0e49\u0e32\u0e19\u0e2b\u0e19\u0e2d\u0e07\u0e0a\u0e33\u0e41\u0e23\u0e14"
    ],
    "name:und_x_variant":[
        "Ban Nong Sam Raet (1)"
    ],
    "wof:name":"Ban Nong Cham Raet",
    "wof:placetype":"locality"
},
  "geometry": {"coordinates":[100.86391999999999,14.46933],"type":"Point"}
}