{
  "type": "Feature",
  "properties": {
    "gn:admin1_code":"29",
    "gn:asciiname":"Ban Rawiang",
    "gn:country_code":"TH",
    "gn:dem":144,
    "gn:feature_class":"P",
    "gn:feature_code":"PPL",
    "gn:name":"Ban Rawiang",
    "gn:population":0,
    "gn:timezone":"Asia/Bangkok",
    "iso:country":"TH",
    "name:tha_x_preferred":[
        "\u0e1a\u0e49\u0e32\u0e19\u0e23\u0e30\u0e40\u0e27\u0e35\u0e22\u0e07"
    ],
    "wof:name":"Ban Rawiang",
    "wof:placetype":"locality"
},
  "geometry": {"coordinates":[103.78525,14.92422],"type":"Point"}
}