{
  "type": "Feature",
  "properties": {
    "gn:admin1_code":"55.0",
    "gn:asciiname":"Ban Sahakon 1",
    "gn:country_code":"TH",
    "gn:dem":5,
    "gn:feature_class":"P",
    "gn:feature_code":"PPL",
    "gn:name":"Ban Sahakon 1",
    "gn:population":0,
    "gn:timezone":"Asia/Bangkok",
    "iso:country":"TH",
    "name:tha_x_preferred":[
        "\u0e1a\u0e49\u0e32\u0e19\u0e2a\u0e2b\u0e01\u0e23\u0e13\u0e4c \u0e2b\u0e19\u0e36\u0e48\u0e07"
    ],
    "name:tha_x_variant":[
        "Ban Sahakon 1"
    ],
    "name:und_x_variant":[
        "Ban Sahakon Nueng"
    ],
    "wof:name":"Ban Sahakon 1",
    "wof:placetype":"locality"
},
  "geometry": {"coordinates":[100.33396999999999,13.49894],"type":"Point"}
}