{
  "type": "Feature",
  "properties": {
    "gn:admin1_code":"3.0",
    "gn:asciiname":"Ban Mae Tam Song Sop",
    "gn:country_code":"TH",
    "gn:dem":591,
    "gn:feature_class":"P",
    "gn:feature_code":"PPL",
    "gn:name":"Ban Mae Tam Song Sop",
    "gn:population":0,
    "gn:timezone":"Asia/Bangkok",
    "iso:country":"TH",
    "name:tha_x_preferred":[
        "\u0e1a\u0e49\u0e32\u0e19\u0e41\u0e21\u0e48\u0e15\u0e4b\u0e33\u0e2a\u0e2d\u0e07\u0e2a\u0e1a"
    ],
    "wof:name":"Ban Mae Tam Song Sop",
    "wof:placetype":"locality"
},
  "geometry": {"coordinates":[99.40036000000001,19.50033],"type":"Point"}
}