{
  "type": "Feature",
  "properties": {
    "gn:admin1_code":"70.0",
    "gn:asciiname":"Ban Cha Rong Tue Ngo",
    "gn:country_code":"TH",
    "gn:dem":44,
    "gn:feature_class":"P",
    "gn:feature_code":"PPL",
    "gn:name":"Ban Cha Rong Tue Ngo",
    "gn:population":0,
    "gn:timezone":"Asia/Bangkok",
    "iso:country":"TH",
    "name:tha_x_preferred":[
        "\u0e1a\u0e49\u0e32\u0e19\u0e08\u0e32\u0e23\u0e07\u0e15\u0e37\u0e2d\u0e42\u0e07\u0e30"
    ],
    "wof:name":"Ban Cha Rong Tue Ngo",
    "wof:placetype":"locality"
},
  "geometry": {"coordinates":[101.35319,6.44328],"type":"Point"}
}