{
  "type": "Feature",
  "properties": {
    "gn:admin1_code":"1.0",
    "gn:asciiname":"Ban Doi Khu",
    "gn:country_code":"TH",
    "gn:dem":887,
    "gn:feature_class":"P",
    "gn:feature_code":"PPL",
    "gn:name":"Ban Doi Khu",
    "gn:population":0,
    "gn:timezone":"Asia/Bangkok",
    "iso:country":"TH",
    "name:tha_x_preferred":[
        "\u0e1a\u0e49\u0e32\u0e19\u0e14\u0e2d\u0e22\u0e04\u0e39"
    ],
    "wof:name":"Ban Doi Khu",
    "wof:placetype":"locality"
},
  "geometry": {"coordinates":[98.04103000000001,19.71114],"type":"Point"}
}