{
  "type": "Feature",
  "properties": {
    "gn:admin1_code":"22",
    "gn:asciiname":"Ban Kut Kranuan",
    "gn:country_code":"TH",
    "gn:dem":181,
    "gn:feature_class":"P",
    "gn:feature_code":"PPL",
    "gn:name":"Ban Kut Kranuan",
    "gn:population":0,
    "gn:timezone":"Asia/Bangkok",
    "iso:country":"TH",
    "name:tha_x_preferred":[
        "\u0e1a\u0e49\u0e32\u0e19\u0e01\u0e38\u0e14\u0e01\u0e23\u0e30\u0e2b\u0e19\u0e27\u0e19"
    ],
    "wof:name":"Ban Kut Kranuan",
    "wof:placetype":"locality"
},
  "geometry": {"coordinates":[102.68025,16.83002999999999],"type":"Point"}
}