{
  "type": "Feature",
  "properties": {
    "gn:admin1_code":"50.0",
    "gn:asciiname":"Ban Huai Somchit",
    "gn:country_code":"TH",
    "gn:dem":334,
    "gn:feature_class":"P",
    "gn:feature_code":"PPL",
    "gn:name":"Ban Huai Somchit",
    "gn:population":0,
    "gn:timezone":"Asia/Bangkok",
    "iso:country":"TH",
    "name:tha_x_preferred":[
        "\u0e1a\u0e49\u0e32\u0e19\u0e2b\u0e49\u0e27\u0e22\u0e2a\u0e21\u0e08\u0e34\u0e15\u0e23"
    ],
    "wof:name":"Ban Huai Somchit",
    "wof:placetype":"locality"
},
  "geometry": {"coordinates":[98.75382999999999,14.72025],"type":"Point"}
}