{
  "type": "Feature",
  "properties": {
    "gn:admin1_code":"58.0",
    "gn:asciiname":"Ban Pang Wan",
    "gn:country_code":"TH",
    "gn:dem":45,
    "gn:feature_class":"P",
    "gn:feature_code":"PPL",
    "gn:name":"Ban Pang Wan",
    "gn:population":0,
    "gn:timezone":"Asia/Bangkok",
    "iso:country":"TH",
    "name:tha_x_preferred":[
        "\u0e1a\u0e49\u0e32\u0e19\u0e1b\u0e31\u0e07\u0e2b\u0e27\u0e32\u0e19"
    ],
    "name:und_x_variant":[
        "Pang Wan",
        "Pang Hwan",
        "Ban Pang Hwan",
        "Ban Pang Wan"
    ],
    "wof:name":"Ban Pang Wan",
    "wof:placetype":"locality"
},
  "geometry": {"coordinates":[98.92332,9.91323],"type":"Point"}
}