{
  "type": "Feature",
  "properties": {
    "gn:admin1_code":"27",
    "gn:asciiname":"Ban Kao Ta Dam",
    "gn:country_code":"TH",
    "gn:dem":157,
    "gn:feature_class":"P",
    "gn:feature_code":"PPL",
    "gn:name":"Ban Kao Ta Dam",
    "gn:population":0,
    "gn:timezone":"Asia/Bangkok",
    "iso:country":"TH",
    "name:tha_x_preferred":[
        "\u0e1a\u0e49\u0e32\u0e19\u0e40\u0e01\u0e48\u0e32\u0e15\u0e32\u0e14\u0e33"
    ],
    "wof:name":"Ban Kao Ta Dam",
    "wof:placetype":"locality"
},
  "geometry": {"coordinates":[102.68822,15.16511],"type":"Point"}
}