{
  "type": "Feature",
  "properties": {
    "gn:admin1_code":"26.0",
    "gn:asciiname":"Ban Huai Bong Nuea",
    "gn:country_code":"TH",
    "gn:dem":205,
    "gn:feature_class":"P",
    "gn:feature_code":"PPL",
    "gn:name":"Ban Huai Bong Nuea",
    "gn:population":0,
    "gn:timezone":"Asia/Bangkok",
    "iso:country":"TH",
    "name:tha_x_preferred":[
        "\u0e1a\u0e49\u0e32\u0e19\u0e2b\u0e49\u0e27\u0e22\u0e1a\u0e07\u0e40\u0e2b\u0e19\u0e37\u0e2d"
    ],
    "name:und_x_variant":[
        "Ban Huai Bong Nua"
    ],
    "wof:name":"Ban Huai Bong Nuea",
    "wof:placetype":"locality"
},
  "geometry": {"coordinates":[102.17017,15.84919],"type":"Point"}
}