{
  "type": "Feature",
  "properties": {
    "gn:admin1_code":"9.0",
    "gn:asciiname":"Ban Nong Pa Taeo",
    "gn:country_code":"TH",
    "gn:dem":88,
    "gn:feature_class":"P",
    "gn:feature_code":"PPL",
    "gn:name":"Ban Nong Pa Taeo",
    "gn:population":0,
    "gn:timezone":"Asia/Bangkok",
    "iso:country":"TH",
    "name:tha_x_preferred":[
        "\u0e1a\u0e49\u0e32\u0e19\u0e2b\u0e19\u0e2d\u0e07\u0e1b\u0e48\u0e32\u0e41\u0e15\u0e49\u0e27"
    ],
    "wof:name":"Ban Nong Pa Taeo",
    "wof:placetype":"locality"
},
  "geometry": {"coordinates":[99.50924999999999,17.01967],"type":"Point"}
}