{
  "type": "Feature",
  "properties": {
    "gn:admin1_code":"24",
    "gn:asciiname":"Ban Khon Kaen",
    "gn:country_code":"TH",
    "gn:dem":167,
    "gn:feature_class":"P",
    "gn:feature_code":"PPL",
    "gn:name":"Ban Khon Kaen",
    "gn:population":0,
    "gn:timezone":"Asia/Bangkok",
    "iso:country":"TH",
    "name:tha_x_preferred":[
        "\u0e1a\u0e49\u0e32\u0e19\u0e02\u0e2d\u0e19\u0e41\u0e01\u0e48\u0e19"
    ],
    "wof:name":"Ban Khon Kaen",
    "wof:placetype":"locality"
},
  "geometry": {"coordinates":[103.37922,16.05336],"type":"Point"}
}