{
  "type": "Feature",
  "properties": {
    "gn:admin1_code":"41.0",
    "gn:asciiname":"Ban Pa Faek Nuea",
    "gn:country_code":"TH",
    "gn:dem":424,
    "gn:feature_class":"P",
    "gn:feature_code":"PPL",
    "gn:name":"Ban Pa Faek Nuea",
    "gn:population":0,
    "gn:timezone":"Asia/Bangkok",
    "iso:country":"TH",
    "name:tha_x_preferred":[
        "\u0e1a\u0e49\u0e32\u0e19\u0e1b\u0e48\u0e32\u0e41\u0e1d\u0e01\u0e40\u0e2b\u0e19\u0e37\u0e2d"
    ],
    "name:und_x_variant":[
        "Pa Faek",
        "Ban Pa Faek",
        "P\u0101fh\u0113k",
        "B\u0101n Pa Feak",
        "Ban Pa Faek Nua",
        "Ban Pa Faek Nuea"
    ],
    "wof:lang_x_official":[
        "tha"
    ],
    "wof:lang_x_spoken":[
        "tha"
    ],
    "wof:name":"Ban Pa Faek Nuea",
    "wof:placetype":"locality"
},
  "geometry": {"coordinates":[99.75972,19.41967],"type":"Point"}
}