{
  "type": "Feature",
  "properties": {
    "gn:admin1_code":"8.0",
    "gn:asciiname":"Ban Thi Chue Khi",
    "gn:country_code":"TH",
    "gn:dem":788,
    "gn:feature_class":"P",
    "gn:feature_code":"PPL",
    "gn:name":"Ban Thi Chue Khi",
    "gn:population":0,
    "gn:timezone":"Asia/Bangkok",
    "iso:country":"TH",
    "name:tha_x_preferred":[
        "\u0e1a\u0e49\u0e32\u0e19\u0e17\u0e34\u0e08\u0e36\u0e2d\u0e04\u0e35"
    ],
    "wof:name":"Ban Thi Chue Khi",
    "wof:placetype":"locality"
},
  "geometry": {"coordinates":[97.93297,17.65151000000001],"type":"Point"}
}