{
  "type": "Feature",
  "properties": {
    "gn:admin1_code":"60.0",
    "gn:asciiname":"Ban Huai Khun Rat",
    "gn:country_code":"TH",
    "gn:dem":38,
    "gn:feature_class":"P",
    "gn:feature_code":"PPL",
    "gn:name":"Ban Huai Khun Rat",
    "gn:population":0,
    "gn:timezone":"Asia/Bangkok",
    "iso:country":"TH",
    "name:tha_x_preferred":[
        "\u0e1a\u0e49\u0e32\u0e19\u0e2b\u0e49\u0e27\u0e22\u0e02\u0e38\u0e19\u0e23\u0e32\u0e29\u0e0e\u0e23\u0e4c"
    ],
    "wof:name":"Ban Huai Khun Rat",
    "wof:placetype":"locality"
},
  "geometry": {"coordinates":[99.36478,8.94328],"type":"Point"}
}