{
  "type": "Feature",
  "properties": {
    "gn:admin1_code":"2.0",
    "gn:asciiname":"Ban Mae Ngat",
    "gn:country_code":"TH",
    "gn:dem":435,
    "gn:feature_class":"P",
    "gn:feature_code":"PPL",
    "gn:name":"Ban Mae Ngat",
    "gn:population":0,
    "gn:timezone":"Asia/Bangkok",
    "iso:country":"TH",
    "name:tha_x_preferred":[
        "\u0e1a\u0e49\u0e32\u0e19\u0e41\u0e21\u0e48\u0e07\u0e31\u0e14"
    ],
    "wof:name":"Ban Mae Ngat",
    "wof:placetype":"locality"
},
  "geometry": {"coordinates":[99.17556,19.35875],"type":"Point"}
}