{
  "type": "Feature",
  "properties": {
    "gn:admin1_code":"10.0",
    "gn:asciiname":"Ban Ngom Sak",
    "gn:country_code":"TH",
    "gn:dem":237,
    "gn:feature_class":"P",
    "gn:feature_code":"PPL",
    "gn:name":"Ban Ngom Sak",
    "gn:population":0,
    "gn:timezone":"Asia/Bangkok",
    "iso:country":"TH",
    "name:tha_x_preferred":[
        "Ban Ngom Sak"
    ],
    "name:tha_x_variant":[
        "\u0e1a\u0e49\u0e32\u0e19\u0e07\u0e2d\u0e21\u0e2a\u0e31\u0e01"
    ],
    "wof:name":"Ban Ngom Sak",
    "wof:placetype":"locality"
},
  "geometry": {"coordinates":[100.67158000000001,17.97756],"type":"Point"}
}