{
  "type": "Feature",
  "properties": {
    "gn:admin1_code":"2.0",
    "gn:asciiname":"Ban Pang Haeo",
    "gn:country_code":"TH",
    "gn:dem":357,
    "gn:feature_class":"P",
    "gn:feature_code":"PPL",
    "gn:name":"Ban Pang Haeo",
    "gn:population":0,
    "gn:timezone":"Asia/Bangkok",
    "iso:country":"TH",
    "name:tha_x_preferred":[
        "\u0e1a\u0e49\u0e32\u0e19\u0e1b\u0e32\u0e07\u0e41\u0e2b\u0e27"
    ],
    "name:und_x_variant":[
        "Ban Thung Pa Haeo"
    ],
    "wof:name":"Ban Pang Haeo",
    "wof:placetype":"locality"
},
  "geometry": {"coordinates":[98.88889,18.94278],"type":"Point"}
}