{
  "type": "Feature",
  "properties": {
    "gn:admin1_code":"29",
    "gn:asciiname":"Ban Phatthana",
    "gn:country_code":"TH",
    "gn:dem":180,
    "gn:feature_class":"P",
    "gn:feature_code":"PPL",
    "gn:name":"Ban Phatthana",
    "gn:population":0,
    "gn:timezone":"Asia/Bangkok",
    "iso:country":"TH",
    "name:tha_x_preferred":[
        "\u0e1a\u0e49\u0e32\u0e19\u0e1e\u0e31\u0e12\u0e19\u0e32"
    ],
    "wof:name":"Ban Phatthana",
    "wof:placetype":"locality"
},
  "geometry": {"coordinates":[103.61396999999999,14.62303],"type":"Point"}
}