{
  "type": "Feature",
  "properties": {
    "gn:admin1_code":"14.0",
    "gn:asciiname":"Ban Mu But",
    "gn:cc2":"TH",
    "gn:country_code":"TH",
    "gn:dem":172,
    "gn:feature_class":"P",
    "gn:feature_code":"PPL",
    "gn:name":"Ban Mu But",
    "gn:population":0,
    "gn:timezone":"Asia/Bangkok",
    "iso:country":"TH",
    "name:und_x_variant":[
        "Ban Mu Khut",
        "Ban Mu But"
    ],
    "wof:name":"Ban Mu But",
    "wof:placetype":"locality"
},
  "geometry": {"coordinates":[101.13333,16.66667],"type":"Point"}
}