{
  "type": "Feature",
  "properties": {
    "gn:admin1_code":"70.0",
    "gn:asciiname":"Ban Pho Maeng",
    "gn:country_code":"TH",
    "gn:dem":21,
    "gn:feature_class":"P",
    "gn:feature_code":"PPL",
    "gn:name":"Ban Pho Maeng",
    "gn:population":0,
    "gn:timezone":"Asia/Bangkok",
    "iso:country":"TH",
    "name:tha_x_preferred":[
        "\u0e1a\u0e49\u0e32\u0e19\u0e1e\u0e2d\u0e41\u0e21\u0e4a\u0e07"
    ],
    "wof:name":"Ban Pho Maeng",
    "wof:placetype":"locality"
},
  "geometry": {"coordinates":[101.42131000000001,6.49214],"type":"Point"}
}