{
  "type": "Feature",
  "properties": {
    "gn:admin1_code":"57.0",
    "gn:asciiname":"Ban Tabaek Phrong",
    "gn:country_code":"TH",
    "gn:dem":75,
    "gn:feature_class":"P",
    "gn:feature_code":"PPL",
    "gn:name":"Ban Tabaek Phrong",
    "gn:population":0,
    "gn:timezone":"Asia/Bangkok",
    "iso:country":"TH",
    "name:tha_x_preferred":[
        "\u0e1a\u0e49\u0e32\u0e19\u0e15\u0e30\u0e41\u0e1a\u0e01\u0e42\u0e1e\u0e23\u0e07"
    ],
    "wof:name":"Ban Tabaek Phrong",
    "wof:placetype":"locality"
},
  "geometry": {"coordinates":[99.48130999999999,11.44928],"type":"Point"}
}