{
  "type": "Feature",
  "properties": {
    "gn:admin1_code":"9.0",
    "gn:asciiname":"Ban Nong Hua Rao",
    "gn:country_code":"TH",
    "gn:dem":64,
    "gn:feature_class":"P",
    "gn:feature_code":"PPL",
    "gn:name":"Ban Nong Hua Rao",
    "gn:population":0,
    "gn:timezone":"Asia/Bangkok",
    "iso:country":"TH",
    "name:tha_x_preferred":[
        "\u0e1a\u0e49\u0e32\u0e19\u0e2b\u0e19\u0e2d\u0e07\u0e2b\u0e31\u0e27\u0e23\u0e32\u0e27"
    ],
    "wof:name":"Ban Nong Hua Rao",
    "wof:placetype":"locality"
},
  "geometry": {"coordinates":[99.65917,17.17108],"type":"Point"}
}