{
  "type": "Feature",
  "properties": {
    "gn:admin1_code":"59.0",
    "gn:asciiname":"Ban Thung Ngao",
    "gn:country_code":"TH",
    "gn:dem":29,
    "gn:feature_class":"P",
    "gn:feature_code":"PPL",
    "gn:name":"Ban Thung Ngao",
    "gn:population":0,
    "gn:timezone":"Asia/Bangkok",
    "iso:country":"TH",
    "name:tha_x_preferred":[
        "\u0e1a\u0e49\u0e32\u0e19\u0e17\u0e38\u0e48\u0e07\u0e2b\u0e07\u0e32\u0e27"
    ],
    "name:und_x_variant":[
        "Klong Hwau",
        "Ban Khlong Ngao",
        "Ban Klong Hwau",
        "Ban Ngao",
        "Ban Thung Ngao"
    ],
    "wof:name":"Ban Thung Ngao",
    "wof:placetype":"locality"
},
  "geometry": {"coordinates":[98.62425,9.86039],"type":"Point"}
}