{
  "type": "Feature",
  "properties": {
    "gn:admin1_code":"52.0",
    "gn:asciiname":"Ban Khlong Mayom",
    "gn:country_code":"TH",
    "gn:dem":8,
    "gn:feature_class":"P",
    "gn:feature_code":"PPL",
    "gn:name":"Ban Khlong Mayom",
    "gn:population":0,
    "gn:timezone":"Asia/Bangkok",
    "iso:country":"TH",
    "name:tha_x_preferred":[
        "\u0e1a\u0e49\u0e32\u0e19\u0e04\u0e25\u0e2d\u0e07\u0e21\u0e30\u0e22\u0e21"
    ],
    "wof:name":"Ban Khlong Mayom",
    "wof:placetype":"locality"
},
  "geometry": {"coordinates":[99.97297,13.49603],"type":"Point"}
}