{
  "type": "Feature",
  "properties": {
    "gn:admin1_code":"25.0",
    "gn:asciiname":"Ban Um Mao",
    "gn:country_code":"TH",
    "gn:dem":143,
    "gn:feature_class":"P",
    "gn:feature_code":"PPL",
    "gn:name":"Ban Um Mao",
    "gn:population":0,
    "gn:timezone":"Asia/Bangkok",
    "iso:country":"TH",
    "name:tha_x_preferred":[
        "\u0e1a\u0e49\u0e32\u0e19\u0e2d\u0e38\u0e48\u0e21\u0e40\u0e21\u0e32"
    ],
    "name:und_x_variant":[
        "Ma-oe",
        "Saeng Badan",
        "Ban Maee",
        "Amphoe Zengbadan",
        "Ban Mau",
        "Amphoe Saengbadan",
        "Ban Um Mao"
    ],
    "wof:lang_x_official":[
        "tha"
    ],
    "wof:lang_x_spoken":[
        "tha"
    ],
    "wof:name":"Ban Um Mao",
    "wof:placetype":"locality"
},
  "geometry": {"coordinates":[103.78861000000001,16.027],"type":"Point"}
}