{
  "type": "Feature",
  "properties": {
    "gn:admin1_code":"14.0",
    "gn:asciiname":"Ban Khok Hin",
    "gn:country_code":"TH",
    "gn:dem":66,
    "gn:feature_class":"P",
    "gn:feature_code":"PPL",
    "gn:name":"Ban Khok Hin",
    "gn:population":0,
    "gn:timezone":"Asia/Bangkok",
    "iso:country":"TH",
    "name:tha_x_preferred":[
        "\u0e1a\u0e49\u0e32\u0e19\u0e42\u0e04\u0e01\u0e2b\u0e34\u0e19"
    ],
    "wof:name":"Ban Khok Hin",
    "wof:placetype":"locality"
},
  "geometry": {"coordinates":[101.06483,15.40697],"type":"Point"}
}