{
  "type": "Feature",
  "properties": {
    "gn:admin1_code":"77.0",
    "gn:asciiname":"Ban I Pe",
    "gn:country_code":"TH",
    "gn:dem":161,
    "gn:feature_class":"P",
    "gn:feature_code":"PPL",
    "gn:name":"Ban I Pe",
    "gn:population":0,
    "gn:timezone":"Asia/Bangkok",
    "iso:country":"TH",
    "name:tha_x_preferred":[
        "Ban I Pe"
    ],
    "name:tha_x_variant":[
        "\u0e1a\u0e49\u0e32\u0e19\u0e2d\u0e35\u0e40\u0e1b\u0e4b"
    ],
    "wof:name":"Ban I Pe",
    "wof:placetype":"locality"
},
  "geometry": {"coordinates":[104.67428,15.821],"type":"Point"}
}