{
  "type": "Feature",
  "properties": {
    "gn:admin1_code":"3.0",
    "gn:asciiname":"Ban Mae Yang Min",
    "gn:country_code":"TH",
    "gn:dem":550,
    "gn:feature_class":"P",
    "gn:feature_code":"PPL",
    "gn:name":"Ban Mae Yang Min",
    "gn:population":0,
    "gn:timezone":"Asia/Bangkok",
    "iso:country":"TH",
    "name:tha_x_preferred":[
        "\u0e1a\u0e49\u0e32\u0e19\u0e41\u0e21\u0e48\u0e22\u0e32\u0e07\u0e21\u0e34\u0e49\u0e19"
    ],
    "wof:name":"Ban Mae Yang Min",
    "wof:placetype":"locality"
},
  "geometry": {"coordinates":[99.38531,19.60308],"type":"Point"}
}