{
  "type": "Feature",
  "properties": {
    "gn:admin1_code":"36.0",
    "gn:asciiname":"Ban Nong Lamchiak",
    "gn:country_code":"TH",
    "gn:dem":5,
    "gn:feature_class":"P",
    "gn:feature_code":"PPL",
    "gn:name":"Ban Nong Lamchiak",
    "gn:population":0,
    "gn:timezone":"Asia/Bangkok",
    "iso:country":"TH",
    "name:tha_x_preferred":[
        "\u0e1a\u0e49\u0e32\u0e19\u0e2b\u0e19\u0e2d\u0e07\u0e25\u0e33\u0e40\u0e08\u0e35\u0e22\u0e01"
    ],
    "wof:name":"Ban Nong Lamchiak",
    "wof:placetype":"locality"
},
  "geometry": {"coordinates":[100.33168999999999,14.27589],"type":"Point"}
}