{
  "type": "Feature",
  "properties": {
    "gn:admin1_code":"22",
    "gn:asciiname":"Ban Nong Ya Plong",
    "gn:country_code":"TH",
    "gn:dem":185,
    "gn:feature_class":"P",
    "gn:feature_code":"PPL",
    "gn:name":"Ban Nong Ya Plong",
    "gn:population":0,
    "gn:timezone":"Asia/Bangkok",
    "iso:country":"TH",
    "name:tha_x_preferred":[
        "\u0e1a\u0e49\u0e32\u0e19\u0e2b\u0e19\u0e2d\u0e07\u0e2b\u0e0d\u0e49\u0e32\u0e1b\u0e25\u0e49\u0e2d\u0e07"
    ],
    "wof:name":"Ban Nong Ya Plong",
    "wof:placetype":"locality"
},
  "geometry": {"coordinates":[102.45464,15.78408],"type":"Point"}
}