{
  "type": "Feature",
  "properties": {
    "gn:admin1_code":"27",
    "gn:asciiname":"Ban Sap Langka",
    "gn:country_code":"TH",
    "gn:dem":241,
    "gn:feature_class":"P",
    "gn:feature_code":"PPL",
    "gn:name":"Ban Sap Langka",
    "gn:population":0,
    "gn:timezone":"Asia/Bangkok",
    "iso:country":"TH",
    "name:tha_x_preferred":[
        "\u0e1a\u0e49\u0e32\u0e19\u0e0b\u0e31\u0e1a\u0e25\u0e31\u0e07\u0e01\u0e32"
    ],
    "wof:name":"Ban Sap Langka",
    "wof:placetype":"locality"
},
  "geometry": {"coordinates":[102.45856000000001,14.57469],"type":"Point"}
}