{
  "type": "Feature",
  "properties": {
    "gn:admin1_code":"72.0",
    "gn:asciiname":"Ban Du Lat",
    "gn:country_code":"TH",
    "gn:dem":151,
    "gn:feature_class":"P",
    "gn:feature_code":"PPL",
    "gn:name":"Ban Du Lat",
    "gn:population":0,
    "gn:timezone":"Asia/Bangkok",
    "iso:country":"TH",
    "name:tha_x_preferred":[
        "\u0e1a\u0e49\u0e32\u0e19\u0e14\u0e39\u0e48\u0e25\u0e32\u0e14"
    ],
    "wof:name":"Ban Du Lat",
    "wof:placetype":"locality"
},
  "geometry": {"coordinates":[104.18472,16.00103],"type":"Point"}
}