{
  "type": "Feature",
  "properties": {
    "gn:admin1_code":"43.0",
    "gn:asciiname":"Ban Dong (2)",
    "gn:cc2":"TH",
    "gn:country_code":"TH",
    "gn:dem":25,
    "gn:feature_class":"P",
    "gn:feature_code":"PPL",
    "gn:name":"Ban Dong (2)",
    "gn:population":0,
    "gn:timezone":"Asia/Bangkok",
    "iso:country":"TH",
    "name:und_x_variant":[
        "Ban Ko Krabao",
        "Ban Ko Kabao",
        "Ban Kok Kabau",
        "Ban Dong (2)"
    ],
    "wof:lang_x_official":[
        "tha"
    ],
    "wof:lang_x_spoken":[
        "tha"
    ],
    "wof:name":"Ban Dong (2)",
    "wof:placetype":"locality"
},
  "geometry": {"coordinates":[101.08750000000001,14.34806],"type":"Point"}
}