{
  "type": "Feature",
  "properties": {
    "gn:admin1_code":"9.0",
    "gn:asciiname":"Ban Na Pa Khae",
    "gn:country_code":"TH",
    "gn:dem":52,
    "gn:feature_class":"P",
    "gn:feature_code":"PPL",
    "gn:name":"Ban Na Pa Khae",
    "gn:population":0,
    "gn:timezone":"Asia/Bangkok",
    "iso:country":"TH",
    "name:tha_x_preferred":[
        "\u0e1a\u0e49\u0e32\u0e19\u0e19\u0e32\u0e1b\u0e48\u0e32\u0e41\u0e04"
    ],
    "wof:name":"Ban Na Pa Khae",
    "wof:placetype":"locality"
},
  "geometry": {"coordinates":[99.81392,16.86772],"type":"Point"}
}