{
  "type": "Feature",
  "properties": {
    "gn:admin1_code":"66.0",
    "gn:asciiname":"Ban Han Kong",
    "gn:country_code":"TH",
    "gn:dem":54,
    "gn:feature_class":"P",
    "gn:feature_code":"PPL",
    "gn:name":"Ban Han Kong",
    "gn:population":0,
    "gn:timezone":"Asia/Bangkok",
    "iso:country":"TH",
    "name:tha_x_preferred":[
        "\u0e1a\u0e49\u0e32\u0e19\u0e2b\u0e32\u0e23\u0e01\u0e07"
    ],
    "wof:name":"Ban Han Kong",
    "wof:placetype":"locality"
},
  "geometry": {"coordinates":[100.12558,7.21178],"type":"Point"}
}