{
  "type": "Feature",
  "properties": {
    "gn:admin1_code":"64.0",
    "gn:asciiname":"Ban Lum Toei",
    "gn:country_code":"TH",
    "gn:dem":44,
    "gn:feature_class":"P",
    "gn:feature_code":"PPL",
    "gn:name":"Ban Lum Toei",
    "gn:population":0,
    "gn:timezone":"Asia/Bangkok",
    "iso:country":"TH",
    "name:tha_x_preferred":[
        "\u0e1a\u0e49\u0e32\u0e19\u0e25\u0e38\u0e21\u0e40\u0e15\u0e22"
    ],
    "wof:name":"Ban Lum Toei",
    "wof:placetype":"locality"
},
  "geometry": {"coordinates":[99.81375,8.34381],"type":"Point"}
}