{
  "type": "Feature",
  "properties": {
    "gn:admin1_code":"2.0",
    "gn:asciiname":"Ban Maecha Noi",
    "gn:country_code":"TH",
    "gn:dem":810,
    "gn:feature_class":"P",
    "gn:feature_code":"PPL",
    "gn:name":"Ban Maecha Noi",
    "gn:population":0,
    "gn:timezone":"Asia/Bangkok",
    "iso:country":"TH",
    "name:tha_x_preferred":[
        "\u0e1a\u0e49\u0e32\u0e19\u0e41\u0e21\u0e48\u0e08\u0e32\u0e19\u0e49\u0e2d\u0e22"
    ],
    "wof:name":"Ban Maecha Noi",
    "wof:placetype":"locality"
},
  "geometry": {"coordinates":[98.86557999999999,19.54014],"type":"Point"}
}