{
  "type": "Feature",
  "properties": {
    "gn:admin1_code":"5.0",
    "gn:asciiname":"Ban Khua Khrae",
    "gn:country_code":"TH",
    "gn:dem":315,
    "gn:feature_class":"P",
    "gn:feature_code":"PPL",
    "gn:name":"Ban Khua Khrae",
    "gn:population":0,
    "gn:timezone":"Asia/Bangkok",
    "iso:country":"TH",
    "name:tha_x_preferred":[
        "\u0e1a\u0e49\u0e32\u0e19\u0e02\u0e31\u0e27\u0e41\u0e04\u0e23\u0e48"
    ],
    "wof:name":"Ban Khua Khrae",
    "wof:placetype":"locality"
},
  "geometry": {"coordinates":[99.06917,18.53789],"type":"Point"}
}