{
  "type": "Feature",
  "properties": {
    "gn:admin1_code":"26.0",
    "gn:asciiname":"Ban Lat Sala Thong",
    "gn:country_code":"TH",
    "gn:dem":220,
    "gn:feature_class":"P",
    "gn:feature_code":"PPL",
    "gn:name":"Ban Lat Sala Thong",
    "gn:population":0,
    "gn:timezone":"Asia/Bangkok",
    "iso:country":"TH",
    "name:tha_x_preferred":[
        "\u0e1a\u0e49\u0e32\u0e19\u0e25\u0e32\u0e14\u0e28\u0e32\u0e25\u0e32\u0e17\u0e2d\u0e07"
    ],
    "wof:name":"Ban Lat Sala Thong",
    "wof:placetype":"locality"
},
  "geometry": {"coordinates":[101.70131000000001,16.00528],"type":"Point"}
}