{
  "type": "Feature",
  "properties": {
    "gn:admin1_code":"3.0",
    "gn:asciiname":"Ban San Sali",
    "gn:country_code":"TH",
    "gn:dem":435,
    "gn:feature_class":"P",
    "gn:feature_code":"PPL",
    "gn:name":"Ban San Sali",
    "gn:population":0,
    "gn:timezone":"Asia/Bangkok",
    "iso:country":"TH",
    "name:tha_x_preferred":[
        "\u0e1a\u0e49\u0e32\u0e19\u0e2a\u0e31\u0e19\u0e2a\u0e25\u0e35"
    ],
    "wof:name":"Ban San Sali",
    "wof:placetype":"locality"
},
  "geometry": {"coordinates":[99.69647000000001,19.78214],"type":"Point"}
}