{
  "type": "Feature",
  "properties": {
    "gn:admin1_code":"20.0",
    "gn:asciiname":"Ban Khlong Phai Phatthana",
    "gn:country_code":"TH",
    "gn:dem":186,
    "gn:feature_class":"P",
    "gn:feature_code":"PPL",
    "gn:name":"Ban Khlong Phai Phatthana",
    "gn:population":0,
    "gn:timezone":"Asia/Bangkok",
    "iso:country":"TH",
    "name:tha_x_preferred":[
        "\u0e1a\u0e49\u0e32\u0e19\u0e04\u0e25\u0e2d\u0e07\u0e44\u0e1c\u0e48\u0e1e\u0e31\u0e12\u0e19\u0e32"
    ],
    "wof:name":"Ban Khlong Phai Phatthana",
    "wof:placetype":"locality"
},
  "geometry": {"coordinates":[104.07383,17.11836],"type":"Point"}
}