{
  "type": "Feature",
  "properties": {
    "gn:admin1_code":"10.0",
    "gn:asciiname":"Ban Huai Kan Lueang",
    "gn:country_code":"TH",
    "gn:dem":165,
    "gn:feature_class":"P",
    "gn:feature_code":"PPL",
    "gn:name":"Ban Huai Kan Lueang",
    "gn:population":0,
    "gn:timezone":"Asia/Bangkok",
    "iso:country":"TH",
    "name:tha_x_preferred":[
        "Ban Huai Kan Lueang"
    ],
    "name:tha_x_variant":[
        "\u0e1a\u0e49\u0e32\u0e19\u0e2b\u0e49\u0e27\u0e22\u0e01\u0e49\u0e32\u0e19\u0e40\u0e2b\u0e25\u0e37\u0e2d\u0e07"
    ],
    "name:und_x_variant":[
        "Ban Huai Kan Luang"
    ],
    "wof:name":"Ban Huai Kan Lueang",
    "wof:placetype":"locality"
},
  "geometry": {"coordinates":[100.52778000000001,17.61097000000001],"type":"Point"}
}