{
  "type": "Feature",
  "properties": {
    "gn:admin1_code":"68.0",
    "gn:asciiname":"Ban Ya Sam",
    "gn:cc2":"TH",
    "gn:country_code":"TH",
    "gn:dem":82,
    "gn:feature_class":"P",
    "gn:feature_code":"PPL",
    "gn:name":"Ban Ya Sam",
    "gn:population":0,
    "gn:timezone":"Asia/Bangkok",
    "iso:country":"TH",
    "name:und_x_variant":[
        "Ya Sam",
        "Ban Ya Sam"
    ],
    "wof:name":"Ban Ya Sam",
    "wof:placetype":"locality"
},
  "geometry": {"coordinates":[100.56667,6.73333],"type":"Point"}
}