{
  "type": "Feature",
  "properties": {
    "gn:admin1_code":"2.0",
    "gn:asciiname":"Ban Nong Sae",
    "gn:country_code":"TH",
    "gn:dem":327,
    "gn:feature_class":"P",
    "gn:feature_code":"PPL",
    "gn:name":"Ban Nong Sae",
    "gn:population":0,
    "gn:timezone":"Asia/Bangkok",
    "iso:country":"TH",
    "name:tha_x_preferred":[
        "\u0e1a\u0e49\u0e32\u0e19\u0e2b\u0e19\u0e2d\u0e07\u0e41\u0e2a\u0e30"
    ],
    "wof:name":"Ban Nong Sae",
    "wof:placetype":"locality"
},
  "geometry": {"coordinates":[98.96886000000001,19.01583],"type":"Point"}
}