{
  "type": "Feature",
  "properties": {
    "gn:admin1_code":"11.0",
    "gn:asciiname":"Ban Tha Ranae",
    "gn:country_code":"TH",
    "gn:dem":117,
    "gn:feature_class":"P",
    "gn:feature_code":"PPL",
    "gn:name":"Ban Tha Ranae",
    "gn:population":0,
    "gn:timezone":"Asia/Bangkok",
    "iso:country":"TH",
    "name:tha_x_preferred":[
        "\u0e1a\u0e49\u0e32\u0e19\u0e17\u0e48\u0e32\u0e23\u0e30\u0e41\u0e19\u0e30"
    ],
    "wof:name":"Ban Tha Ranae",
    "wof:placetype":"locality"
},
  "geometry": {"coordinates":[99.38778000000001,16.41969],"type":"Point"}
}