{
  "type": "Feature",
  "properties": {
    "gn:admin1_code":"76.0",
    "gn:asciiname":"Ban Chiang",
    "gn:country_code":"TH",
    "gn:dem":176,
    "gn:feature_class":"P",
    "gn:feature_code":"PPL",
    "gn:name":"Ban Chiang",
    "gn:population":0,
    "gn:timezone":"Asia/Bangkok",
    "iso:country":"TH",
    "name:tha_x_preferred":[
        "\u0e1a\u0e49\u0e32\u0e19\u0e40\u0e0a\u0e35\u0e22\u0e07"
    ],
    "name:und_x_variant":[
        "Ban Chieng",
        "Ban Chiang"
    ],
    "wof:name":"Ban Chiang",
    "wof:placetype":"locality"
},
  "geometry": {"coordinates":[103.23895,17.40645],"type":"Point"}
}