{
  "type": "Feature",
  "properties": {
    "gn:admin1_code":"31.0",
    "gn:asciiname":"Ban Che Yo",
    "gn:country_code":"TH",
    "gn:dem":41,
    "gn:feature_class":"P",
    "gn:feature_code":"PPL",
    "gn:name":"Ban Che Yo",
    "gn:population":0,
    "gn:timezone":"Asia/Bangkok",
    "iso:country":"TH",
    "name:tha_x_preferred":[
        "\u0e1a\u0e49\u0e32\u0e19\u0e40\u0e08\u0e4a\u0e30\u0e22\u0e2d"
    ],
    "name:und_x_variant":[
        "Kampong Leyong",
        "Kampong Chayo",
        "Kampong Cheyo",
        "Ban Che Yo"
    ],
    "wof:name":"Ban Che Yo",
    "wof:placetype":"locality"
},
  "geometry": {"coordinates":[101.86469,5.85153],"type":"Point"}
}