{
  "type": "Feature",
  "properties": {
    "gn:admin1_code":"61.0",
    "gn:asciiname":"Ban Ko Ping",
    "gn:country_code":"TH",
    "gn:dem":503,
    "gn:feature_class":"P",
    "gn:feature_code":"PPL",
    "gn:name":"Ban Ko Ping",
    "gn:population":0,
    "gn:timezone":"Asia/Bangkok",
    "iso:country":"TH",
    "wof:name":"Ban Ko Ping",
    "wof:placetype":"locality"
},
  "geometry": {"coordinates":[98.48333,8.58333],"type":"Point"}
}