{
  "type": "Feature",
  "properties": {
    "gn:admin1_code":"22",
    "gn:asciiname":"Ban Non Thong Tai",
    "gn:country_code":"TH",
    "gn:dem":188,
    "gn:feature_class":"P",
    "gn:feature_code":"PPL",
    "gn:name":"Ban Non Thong Tai",
    "gn:population":0,
    "gn:timezone":"Asia/Bangkok",
    "iso:country":"TH",
    "name:tha_x_preferred":[
        "\u0e1a\u0e49\u0e32\u0e19\u0e42\u0e19\u0e19\u0e17\u0e2d\u0e07\u0e43\u0e15\u0e49"
    ],
    "wof:name":"Ban Non Thong Tai",
    "wof:placetype":"locality"
},
  "geometry": {"coordinates":[102.39133,15.91881],"type":"Point"}
}