{
  "type": "Feature",
  "properties": {
    "gn:admin1_code":"6.0",
    "gn:asciiname":"Ban Sop Run",
    "gn:cc2":"TH",
    "gn:country_code":"TH",
    "gn:dem":407,
    "gn:feature_class":"P",
    "gn:feature_code":"PPL",
    "gn:name":"Ban Sop Run",
    "gn:population":0,
    "gn:timezone":"Asia/Bangkok",
    "iso:country":"TH",
    "name:und_x_variant":[
        "Sop Rin",
        "Ban Sop Rin",
        "Ban Sop Run"
    ],
    "wof:name":"Ban Sop Run",
    "wof:placetype":"locality"
},
  "geometry": {"coordinates":[99.59999999999999,18.98333],"type":"Point"}
}