{
  "type": "Feature",
  "properties": {
    "gn:admin1_code":"66.0",
    "gn:asciiname":"Ban Khuan Rit",
    "gn:country_code":"TH",
    "gn:dem":59,
    "gn:feature_class":"P",
    "gn:feature_code":"PPL",
    "gn:name":"Ban Khuan Rit",
    "gn:population":0,
    "gn:timezone":"Asia/Bangkok",
    "iso:country":"TH",
    "name:tha_x_preferred":[
        "\u0e1a\u0e49\u0e32\u0e19\u0e04\u0e27\u0e19\u0e24\u0e17\u0e18\u0e34\u0e4c"
    ],
    "wof:name":"Ban Khuan Rit",
    "wof:placetype":"locality"
},
  "geometry": {"coordinates":[99.86969000000001,7.754],"type":"Point"}
}