{
  "type": "Feature",
  "properties": {
    "gn:admin1_code":"14.0",
    "gn:asciiname":"Ban Khao Khui",
    "gn:country_code":"TH",
    "gn:dem":132,
    "gn:feature_class":"P",
    "gn:feature_code":"PPL",
    "gn:name":"Ban Khao Khui",
    "gn:population":0,
    "gn:timezone":"Asia/Bangkok",
    "iso:country":"TH",
    "name:tha_x_preferred":[
        "\u0e1a\u0e49\u0e32\u0e19\u0e40\u0e02\u0e32\u0e02\u0e38\u0e22"
    ],
    "wof:name":"Ban Khao Khui",
    "wof:placetype":"locality"
},
  "geometry": {"coordinates":[100.84238999999999,15.53364],"type":"Point"}
}