{
  "type": "Feature",
  "properties": {
    "gn:admin1_code":"11.0",
    "gn:asciiname":"Ban Fak Thung",
    "gn:country_code":"TH",
    "gn:dem":51,
    "gn:feature_class":"P",
    "gn:feature_code":"PPL",
    "gn:name":"Ban Fak Thung",
    "gn:population":0,
    "gn:timezone":"Asia/Bangkok",
    "iso:country":"TH",
    "name:tha_x_preferred":[
        "\u0e1a\u0e49\u0e32\u0e19\u0e1f\u0e32\u0e01\u0e17\u0e38\u0e48\u0e07"
    ],
    "wof:name":"Ban Fak Thung",
    "wof:placetype":"locality"
},
  "geometry": {"coordinates":[99.85117,16.58556],"type":"Point"}
}