{
  "type": "Feature",
  "properties": {
    "gn:admin1_code":"58.0",
    "gn:asciiname":"Ban Doi Charoen",
    "gn:country_code":"TH",
    "gn:dem":134,
    "gn:feature_class":"P",
    "gn:feature_code":"PPL",
    "gn:name":"Ban Doi Charoen",
    "gn:population":0,
    "gn:timezone":"Asia/Bangkok",
    "iso:country":"TH",
    "name:tha_x_preferred":[
        "\u0e1a\u0e49\u0e32\u0e19\u0e14\u0e2d\u0e22\u0e40\u0e08\u0e23\u0e34\u0e0d"
    ],
    "wof:name":"Ban Doi Charoen",
    "wof:placetype":"locality"
},
  "geometry": {"coordinates":[98.77661000000001,9.77642],"type":"Point"}
}