{
  "type": "Feature",
  "properties": {
    "gn:admin1_code":"8.0",
    "gn:asciiname":"Ban Samakkhi",
    "gn:country_code":"TH",
    "gn:dem":475,
    "gn:feature_class":"P",
    "gn:feature_code":"PPL",
    "gn:name":"Ban Samakkhi",
    "gn:population":0,
    "gn:timezone":"Asia/Bangkok",
    "iso:country":"TH",
    "name:tha_x_preferred":[
        "\u0e1a\u0e49\u0e32\u0e19\u0e2a\u0e32\u0e21\u0e31\u0e04\u0e04\u0e35"
    ],
    "name:und_x_variant":[
        "Ban Kariang Samakkhi"
    ],
    "wof:name":"Ban Samakkhi",
    "wof:placetype":"locality"
},
  "geometry": {"coordinates":[98.86960999999999,15.99589],"type":"Point"}
}