{
  "type": "Feature",
  "properties": {
    "gn:admin1_code":"20.0",
    "gn:asciiname":"Ban Sang Paen",
    "gn:country_code":"TH",
    "gn:dem":170,
    "gn:feature_class":"P",
    "gn:feature_code":"PPL",
    "gn:name":"Ban Sang Paen",
    "gn:population":0,
    "gn:timezone":"Asia/Bangkok",
    "iso:country":"TH",
    "name:tha_x_preferred":[
        "\u0e1a\u0e49\u0e32\u0e19\u0e2a\u0e23\u0e49\u0e32\u0e07\u0e41\u0e1b\u0e49\u0e19"
    ],
    "wof:name":"Ban Sang Paen",
    "wof:placetype":"locality"
},
  "geometry": {"coordinates":[103.61011000000001,17.41247000000001],"type":"Point"}
}