{
  "type": "Feature",
  "properties": {
    "gn:admin1_code":"41.0",
    "gn:asciiname":"Ban Phaen Din Haeng",
    "gn:country_code":"TH",
    "gn:dem":385,
    "gn:feature_class":"P",
    "gn:feature_code":"PPL",
    "gn:name":"Ban Phaen Din Haeng",
    "gn:population":0,
    "gn:timezone":"Asia/Bangkok",
    "iso:country":"TH",
    "name:tha_x_preferred":[
        "\u0e1a\u0e49\u0e32\u0e19\u0e41\u0e1c\u0e48\u0e19\u0e14\u0e34\u0e19\u0e41\u0e2b\u0e07"
    ],
    "wof:name":"Ban Phaen Din Haeng",
    "wof:placetype":"locality"
},
  "geometry": {"coordinates":[100.12381000000001,19.40025],"type":"Point"}
}