{
  "type": "Feature",
  "properties": {
    "gn:admin1_code":"70.0",
    "gn:asciiname":"Ban Cha Ro Kue La Di",
    "gn:country_code":"TH",
    "gn:dem":25,
    "gn:feature_class":"P",
    "gn:feature_code":"PPL",
    "gn:name":"Ban Cha Ro Kue La Di",
    "gn:population":0,
    "gn:timezone":"Asia/Bangkok",
    "iso:country":"TH",
    "name:tha_x_preferred":[
        "\u0e1a\u0e49\u0e32\u0e19\u0e08\u0e32\u0e40\u0e23\u0e32\u0e30\u0e01\u0e37\u0e2d\u0e25\u0e32\u0e14\u0e35"
    ],
    "wof:name":"Ban Cha Ro Kue La Di",
    "wof:placetype":"locality"
},
  "geometry": {"coordinates":[101.40011,6.49667],"type":"Point"}
}