{
  "type": "Feature",
  "properties": {
    "gn:admin1_code":"18.0",
    "gn:asciiname":"Ban Khon Kaen",
    "gn:country_code":"TH",
    "gn:dem":251,
    "gn:feature_class":"P",
    "gn:feature_code":"PPL",
    "gn:name":"Ban Khon Kaen",
    "gn:population":0,
    "gn:timezone":"Asia/Bangkok",
    "iso:country":"TH",
    "name:tha_x_preferred":[
        "Ban Khon Kaen"
    ],
    "name:tha_x_variant":[
        "\u0e1a\u0e49\u0e32\u0e19\u0e02\u0e2d\u0e19\u0e41\u0e01\u0e48\u0e19"
    ],
    "name:und_x_variant":[
        "B\u0101n Wang Thean",
        "Ban Wang Thaen",
        "Ban Khon Kaen Nai"
    ],
    "wof:lang_x_official":[
        "tha"
    ],
    "wof:lang_x_spoken":[
        "tha"
    ],
    "wof:name":"Ban Khon Kaen",
    "wof:placetype":"locality"
},
  "geometry": {"coordinates":[101.72939,17.42467000000001],"type":"Point"}
}