{
  "type": "Feature",
  "properties": {
    "gn:admin1_code":"70.0",
    "gn:asciiname":"Ban Ta Lo Due Long",
    "gn:country_code":"TH",
    "gn:dem":46,
    "gn:feature_class":"P",
    "gn:feature_code":"PPL",
    "gn:name":"Ban Ta Lo Due Long",
    "gn:population":0,
    "gn:timezone":"Asia/Bangkok",
    "iso:country":"TH",
    "name:tha_x_preferred":[
        "\u0e1a\u0e49\u0e32\u0e19\u0e15\u0e30\u0e42\u0e25\u0e30\u0e14\u0e37\u0e2d\u0e2b\u0e25\u0e07"
    ],
    "wof:name":"Ban Ta Lo Due Long",
    "wof:placetype":"locality"
},
  "geometry": {"coordinates":[101.27903000000001,6.29294],"type":"Point"}
}