{
  "type": "Feature",
  "properties": {
    "gn:admin1_code":"30.0",
    "gn:asciiname":"Ban Chiang Wong Noi",
    "gn:country_code":"TH",
    "gn:dem":135,
    "gn:feature_class":"P",
    "gn:feature_code":"PPL",
    "gn:name":"Ban Chiang Wong Noi",
    "gn:population":0,
    "gn:timezone":"Asia/Bangkok",
    "iso:country":"TH",
    "name:tha_x_preferred":[
        "\u0e1a\u0e49\u0e32\u0e19\u0e40\u0e08\u0e35\u0e22\u0e07\u0e27\u0e07\u0e29\u0e4c\u0e19\u0e49\u0e2d\u0e22"
    ],
    "wof:name":"Ban Chiang Wong Noi",
    "wof:placetype":"locality"
},
  "geometry": {"coordinates":[104.06574999999999,15.09186],"type":"Point"}
}