{
  "type": "Feature",
  "properties": {
    "gn:admin1_code":"30.0",
    "gn:asciiname":"Ban I Thum",
    "gn:country_code":"TH",
    "gn:dem":136,
    "gn:feature_class":"P",
    "gn:feature_code":"PPL",
    "gn:name":"Ban I Thum",
    "gn:population":0,
    "gn:timezone":"Asia/Bangkok",
    "iso:country":"TH",
    "name:tha_x_preferred":[
        "\u0e1a\u0e49\u0e32\u0e19\u0e2d\u0e35\u0e17\u0e38\u0e48\u0e21"
    ],
    "wof:name":"Ban I Thum",
    "wof:placetype":"locality"
},
  "geometry": {"coordinates":[104.15877999999999,15.09675],"type":"Point"}
}