{
  "type": "Feature",
  "properties": {
    "gn:admin1_code":"2.0",
    "gn:asciiname":"Ban Mai Na Hi",
    "gn:cc2":"TH",
    "gn:country_code":"TH",
    "gn:dem":345,
    "gn:feature_class":"P",
    "gn:feature_code":"PPL",
    "gn:name":"Ban Mai Na Hi",
    "gn:population":0,
    "gn:timezone":"Asia/Bangkok",
    "iso:country":"TH",
    "name:und_x_variant":[
        "Ban Nari",
        "Ban Mai Na Hi"
    ],
    "wof:name":"Ban Mai Na Hi",
    "wof:placetype":"locality"
},
  "geometry": {"coordinates":[98.91667,18.91667],"type":"Point"}
}