{
  "type": "Feature",
  "properties": {
    "gn:admin1_code":"2.0",
    "gn:asciiname":"Ban Mae Hia Nai",
    "gn:country_code":"TH",
    "gn:dem":361,
    "gn:feature_class":"P",
    "gn:feature_code":"PPL",
    "gn:name":"Ban Mae Hia Nai",
    "gn:population":0,
    "gn:timezone":"Asia/Bangkok",
    "iso:country":"TH",
    "name:tha_x_preferred":[
        "\u0e1a\u0e49\u0e32\u0e19\u0e41\u0e21\u0e48\u0e40\u0e2b\u0e35\u0e22\u0e30\u0e43\u0e19"
    ],
    "name:und_x_variant":[
        "M\u0113hie",
        "Ban Mea Hia",
        "Ban Mae Hia",
        "Ban Mae Hia Nai"
    ],
    "wof:lang_x_official":[
        "tha"
    ],
    "wof:lang_x_spoken":[
        "tha"
    ],
    "wof:name":"Ban Mae Hia Nai",
    "wof:placetype":"locality"
},
  "geometry": {"coordinates":[98.90985999999999,18.76022],"type":"Point"}
}