{
  "type": "Feature",
  "properties": {
    "gn:admin1_code":"26.0",
    "gn:asciiname":"Ban Sila Thong",
    "gn:country_code":"TH",
    "gn:dem":367,
    "gn:feature_class":"P",
    "gn:feature_code":"PPL",
    "gn:name":"Ban Sila Thong",
    "gn:population":0,
    "gn:timezone":"Asia/Bangkok",
    "iso:country":"TH",
    "name:tha_x_preferred":[
        "\u0e1a\u0e49\u0e32\u0e19\u0e28\u0e34\u0e25\u0e32\u0e17\u0e2d\u0e07"
    ],
    "wof:name":"Ban Sila Thong",
    "wof:placetype":"locality"
},
  "geometry": {"coordinates":[101.48908,15.83531],"type":"Point"}
}