{
  "type": "Feature",
  "properties": {
    "gn:admin1_code":"68.0",
    "gn:asciiname":"Ban Khuan Hin Lek Fai",
    "gn:country_code":"TH",
    "gn:dem":25,
    "gn:feature_class":"P",
    "gn:feature_code":"PPL",
    "gn:name":"Ban Khuan Hin Lek Fai",
    "gn:population":0,
    "gn:timezone":"Asia/Bangkok",
    "iso:country":"TH",
    "name:tha_x_preferred":[
        "\u0e1a\u0e49\u0e32\u0e19\u0e04\u0e27\u0e19\u0e2b\u0e34\u0e19\u0e40\u0e2b\u0e25\u0e47\u0e01\u0e44\u0e1f"
    ],
    "wof:name":"Ban Khuan Hin Lek Fai",
    "wof:placetype":"locality"
},
  "geometry": {"coordinates":[100.27719999999999,7.16014],"type":"Point"}
}