{
  "type": "Feature",
  "properties": {
    "gn:admin1_code":"34",
    "gn:asciiname":"Ban Nong Thong",
    "gn:country_code":"TH",
    "gn:dem":105,
    "gn:feature_class":"P",
    "gn:feature_code":"PPL",
    "gn:name":"Ban Nong Thong",
    "gn:population":0,
    "gn:timezone":"Asia/Bangkok",
    "iso:country":"TH",
    "name:tha_x_preferred":[
        "\u0e1a\u0e49\u0e32\u0e19\u0e2b\u0e19\u0e2d\u0e07\u0e17\u0e2d\u0e07"
    ],
    "wof:name":"Ban Nong Thong",
    "wof:placetype":"locality"
},
  "geometry": {"coordinates":[100.67561000000001,15.19244],"type":"Point"}
}