{
  "type": "Feature",
  "properties": {
    "gn:admin1_code":"34",
    "gn:asciiname":"Ban Khao Wong Kot",
    "gn:country_code":"TH",
    "gn:dem":16,
    "gn:feature_class":"P",
    "gn:feature_code":"PPL",
    "gn:name":"Ban Khao Wong Kot",
    "gn:population":0,
    "gn:timezone":"Asia/Bangkok",
    "iso:country":"TH",
    "name:tha_x_preferred":[
        "\u0e1a\u0e49\u0e32\u0e19\u0e40\u0e02\u0e32\u0e27\u0e07\u0e01\u0e0e"
    ],
    "wof:name":"Ban Khao Wong Kot",
    "wof:placetype":"locality"
},
  "geometry": {"coordinates":[100.54494,15.01169],"type":"Point"}
}