{
  "type": "Feature",
  "properties": {
    "gn:admin1_code":"72.0",
    "gn:asciiname":"Ban Maphrik",
    "gn:country_code":"TH",
    "gn:dem":141,
    "gn:feature_class":"P",
    "gn:feature_code":"PPL",
    "gn:name":"Ban Maphrik",
    "gn:population":0,
    "gn:timezone":"Asia/Bangkok",
    "iso:country":"TH",
    "name:tha_x_preferred":[
        "\u0e1a\u0e49\u0e32\u0e19\u0e21\u0e30\u0e1e\u0e23\u0e34\u0e01"
    ],
    "wof:name":"Ban Maphrik",
    "wof:placetype":"locality"
},
  "geometry": {"coordinates":[104.34383,15.73019],"type":"Point"}
}