{
  "type": "Feature",
  "properties": {
    "gn:admin1_code":"2.0",
    "gn:asciiname":"Ban Sahakon Plaeng Song",
    "gn:country_code":"TH",
    "gn:dem":473,
    "gn:feature_class":"P",
    "gn:feature_code":"PPL",
    "gn:name":"Ban Sahakon Plaeng Song",
    "gn:population":0,
    "gn:timezone":"Asia/Bangkok",
    "iso:country":"TH",
    "name:tha_x_preferred":[
        "\u0e1a\u0e49\u0e32\u0e19\u0e2a\u0e2b\u0e01\u0e23\u0e13\u0e4c\u0e41\u0e1b\u0e25\u0e07 \u0e2a\u0e2d\u0e07"
    ],
    "name:und_x_variant":[
        "Ban Sahakon Plaeng 2"
    ],
    "wof:lang_x_official":[
        "tha"
    ],
    "wof:lang_x_spoken":[
        "tha"
    ],
    "wof:name":"Ban Sahakon Plaeng Song",
    "wof:placetype":"locality"
},
  "geometry": {"coordinates":[99.22075,19.33431],"type":"Point"}
}