{
  "type": "Feature",
  "properties": {
    "gn:admin1_code":"59.0",
    "gn:asciiname":"Ban Bang Mut Phatthana",
    "gn:country_code":"TH",
    "gn:dem":63,
    "gn:feature_class":"P",
    "gn:feature_code":"PPL",
    "gn:name":"Ban Bang Mut Phatthana",
    "gn:population":0,
    "gn:timezone":"Asia/Bangkok",
    "iso:country":"TH",
    "name:tha_x_preferred":[
        "\u0e1a\u0e49\u0e32\u0e19\u0e1a\u0e32\u0e07\u0e21\u0e38\u0e14\u0e1e\u0e31\u0e12\u0e19\u0e32"
    ],
    "wof:name":"Ban Bang Mut Phatthana",
    "wof:placetype":"locality"
},
  "geometry": {"coordinates":[98.93603,10.57872],"type":"Point"}
}