{
  "type": "Feature",
  "properties": {
    "gn:admin1_code":"4.0",
    "gn:asciiname":"Ban Ton Kok",
    "gn:country_code":"TH",
    "gn:dem":253,
    "gn:feature_class":"P",
    "gn:feature_code":"PPL",
    "gn:name":"Ban Ton Kok",
    "gn:population":0,
    "gn:timezone":"Asia/Bangkok",
    "iso:country":"TH",
    "name:tha_x_preferred":[
        "\u0e1a\u0e49\u0e32\u0e19\u0e15\u0e49\u0e19\u0e01\u0e2d\u0e01"
    ],
    "wof:name":"Ban Ton Kok",
    "wof:placetype":"locality"
},
  "geometry": {"coordinates":[100.83728000000001,18.73767],"type":"Point"}
}