{
  "type": "Feature",
  "properties": {
    "gn:admin1_code":"51.0",
    "gn:asciiname":"Doem Bang Nang Buat",
    "gn:country_code":"TH",
    "gn:dem":17,
    "gn:feature_class":"P",
    "gn:feature_code":"PPLA2",
    "gn:name":"Doem Bang Nang Buat",
    "gn:population":0,
    "gn:timezone":"Asia/Bangkok",
    "iso:country":"TH",
    "name:und_x_variant":[
        "\u0e40\u0e14\u0e34\u0e21\u0e1a\u0e32\u0e07\u0e19\u0e32\u0e07\u0e1a\u0e27\u0e0a"
    ],
    "wof:name":"Doem Bang Nang Buat",
    "wof:placetype":"locality"
},
  "geometry": {"coordinates":[100.09772,14.85428],"type":"Point"}
}