{
  "type": "Feature",
  "properties": {
    "gn:admin1_code":"3.0",
    "gn:asciiname":"Ban Pang Chomphu",
    "gn:country_code":"TH",
    "gn:dem":863,
    "gn:feature_class":"P",
    "gn:feature_code":"PPL",
    "gn:name":"Ban Pang Chomphu",
    "gn:population":0,
    "gn:timezone":"Asia/Bangkok",
    "iso:country":"TH",
    "name:tha_x_preferred":[
        "\u0e1a\u0e49\u0e32\u0e19\u0e1b\u0e32\u0e07\u0e0a\u0e21\u0e1e\u0e39"
    ],
    "wof:name":"Ban Pang Chomphu",
    "wof:placetype":"locality"
},
  "geometry": {"coordinates":[99.57733,19.51022],"type":"Point"}
}