{
  "type": "Feature",
  "properties": {
    "gn:admin1_code":"9.0",
    "gn:asciiname":"Ban Wang Phai Sung",
    "gn:country_code":"TH",
    "gn:dem":45,
    "gn:feature_class":"P",
    "gn:feature_code":"PPL",
    "gn:name":"Ban Wang Phai Sung",
    "gn:population":0,
    "gn:timezone":"Asia/Bangkok",
    "iso:country":"TH",
    "name:tha_x_preferred":[
        "\u0e1a\u0e49\u0e32\u0e19\u0e27\u0e31\u0e07\u0e44\u0e1c\u0e48\u0e2a\u0e39\u0e07"
    ],
    "name:und_x_variant":[
        "Ban Wang I Sung"
    ],
    "wof:name":"Ban Wang Phai Sung",
    "wof:placetype":"locality"
},
  "geometry": {"coordinates":[100.04428,16.93267],"type":"Point"}
}