{
  "type": "Feature",
  "properties": {
    "gn:admin1_code":"28",
    "gn:asciiname":"Ban Phrom Nimit",
    "gn:country_code":"TH",
    "gn:dem":159,
    "gn:feature_class":"P",
    "gn:feature_code":"PPL",
    "gn:name":"Ban Phrom Nimit",
    "gn:population":0,
    "gn:timezone":"Asia/Bangkok",
    "iso:country":"TH",
    "name:tha_x_preferred":[
        "\u0e1a\u0e49\u0e32\u0e19\u0e1e\u0e23\u0e2b\u0e21\u0e19\u0e34\u0e21\u0e34\u0e15\u0e23"
    ],
    "wof:name":"Ban Phrom Nimit",
    "wof:placetype":"locality"
},
  "geometry": {"coordinates":[103.12039,15.00467],"type":"Point"}
}