{
  "type": "Feature",
  "properties": {
    "gn:admin1_code":"64.0",
    "gn:asciiname":"Ban Khu Ra",
    "gn:country_code":"TH",
    "gn:dem":5,
    "gn:feature_class":"P",
    "gn:feature_code":"PPL",
    "gn:name":"Ban Khu Ra",
    "gn:population":0,
    "gn:timezone":"Asia/Bangkok",
    "iso:country":"TH",
    "name:tha_x_preferred":[
        "\u0e1a\u0e49\u0e32\u0e19\u0e04\u0e39\u0e23\u0e30"
    ],
    "wof:name":"Ban Khu Ra",
    "wof:placetype":"locality"
},
  "geometry": {"coordinates":[100.24903,8.15186],"type":"Point"}
}