{
  "type": "Feature",
  "properties": {
    "gn:admin1_code":"25.0",
    "gn:asciiname":"Ban Saeng Laem",
    "gn:country_code":"TH",
    "gn:dem":137,
    "gn:feature_class":"P",
    "gn:feature_code":"PPL",
    "gn:name":"Ban Saeng Laem",
    "gn:population":0,
    "gn:timezone":"Asia/Bangkok",
    "iso:country":"TH",
    "name:tha_x_preferred":[
        "\u0e1a\u0e49\u0e32\u0e19\u0e41\u0e0b\u0e07\u0e41\u0e2b\u0e25\u0e21"
    ],
    "name:und_x_variant":[
        "Ban Chiang Laem",
        "Ban Saeng Laem"
    ],
    "wof:lang_x_official":[
        "tha"
    ],
    "wof:lang_x_spoken":[
        "tha"
    ],
    "wof:name":"Ban Saeng Laem",
    "wof:placetype":"locality"
},
  "geometry": {"coordinates":[103.61819,16.20944],"type":"Point"}
}