{
  "type": "Feature",
  "properties": {
    "gn:admin1_code":"46.0",
    "gn:asciiname":"Ban Rom Ruedi",
    "gn:country_code":"TH",
    "gn:dem":12,
    "gn:feature_class":"P",
    "gn:feature_code":"PPL",
    "gn:name":"Ban Rom Ruedi",
    "gn:population":0,
    "gn:timezone":"Asia/Bangkok",
    "iso:country":"TH",
    "name:tha_x_preferred":[
        "\u0e1a\u0e49\u0e32\u0e19\u0e23\u0e48\u0e21\u0e24\u0e14\u0e35"
    ],
    "wof:name":"Ban Rom Ruedi",
    "wof:placetype":"locality"
},
  "geometry": {"coordinates":[100.89464,12.67958],"type":"Point"}
}