{
  "type": "Feature",
  "properties": {
    "gn:admin1_code":"30.0",
    "gn:asciiname":"Ban Sung Ngu Noi",
    "gn:country_code":"TH",
    "gn:dem":134,
    "gn:feature_class":"P",
    "gn:feature_code":"PPL",
    "gn:name":"Ban Sung Ngu Noi",
    "gn:population":0,
    "gn:timezone":"Asia/Bangkok",
    "iso:country":"TH",
    "name:tha_x_preferred":[
        "\u0e1a\u0e49\u0e32\u0e19\u0e0b\u0e38\u0e07\u0e07\u0e39\u0e19\u0e49\u0e2d\u0e22"
    ],
    "wof:name":"Ban Sung Ngu Noi",
    "wof:placetype":"locality"
},
  "geometry": {"coordinates":[104.1895,15.09597],"type":"Point"}
}