{
  "type": "Feature",
  "properties": {
    "gn:admin1_code":"7.0",
    "gn:asciiname":"Ban Pa Lao",
    "gn:cc2":"TH",
    "gn:country_code":"TH",
    "gn:dem":387,
    "gn:feature_class":"P",
    "gn:feature_code":"PPL",
    "gn:name":"Ban Pa Lao",
    "gn:population":0,
    "gn:timezone":"Asia/Bangkok",
    "iso:country":"TH",
    "name:und_x_variant":[
        "Ban Pa Lao Nai",
        "Ban Pa Lao"
    ],
    "wof:name":"Ban Pa Lao",
    "wof:placetype":"locality"
},
  "geometry": {"coordinates":[100.25,18.63333],"type":"Point"}
}