{
  "type": "Feature",
  "properties": {
    "gn:admin1_code":"28",
    "gn:asciiname":"Ban Khok Yakha",
    "gn:country_code":"TH",
    "gn:dem":199,
    "gn:feature_class":"P",
    "gn:feature_code":"PPL",
    "gn:name":"Ban Khok Yakha",
    "gn:population":0,
    "gn:timezone":"Asia/Bangkok",
    "iso:country":"TH",
    "name:tha_x_preferred":[
        "\u0e1a\u0e49\u0e32\u0e19\u0e42\u0e04\u0e01\u0e2b\u0e0d\u0e49\u0e32\u0e04\u0e32"
    ],
    "wof:name":"Ban Khok Yakha",
    "wof:placetype":"locality"
},
  "geometry": {"coordinates":[102.89261,14.52286],"type":"Point"}
}