{
  "type": "Feature",
  "properties": {
    "gn:admin1_code":"70.0",
    "gn:asciiname":"Ban Pa Deng Klang",
    "gn:country_code":"TH",
    "gn:dem":443,
    "gn:feature_class":"P",
    "gn:feature_code":"PPL",
    "gn:name":"Ban Pa Deng Klang",
    "gn:population":0,
    "gn:timezone":"Asia/Bangkok",
    "iso:country":"TH",
    "name:tha_x_preferred":[
        "\u0e1a\u0e49\u0e32\u0e19\u0e1b\u0e30\u0e40\u0e14\u0e47\u0e07\u0e01\u0e25\u0e32\u0e07"
    ],
    "wof:name":"Ban Pa Deng Klang",
    "wof:placetype":"locality"
},
  "geometry": {"coordinates":[101.23766999999999,6.00669],"type":"Point"}
}