{
  "type": "Feature",
  "properties": {
    "gn:admin1_code":"54.0",
    "gn:asciiname":"Ban Khlong Wat Ket",
    "gn:country_code":"TH",
    "gn:dem":7,
    "gn:feature_class":"P",
    "gn:feature_code":"PPL",
    "gn:name":"Ban Khlong Wat Ket",
    "gn:population":0,
    "gn:timezone":"Asia/Bangkok",
    "iso:country":"TH",
    "name:tha_x_preferred":[
        "\u0e1a\u0e49\u0e32\u0e19\u0e04\u0e25\u0e2d\u0e07\u0e27\u0e31\u0e14\u0e40\u0e01\u0e15\u0e38"
    ],
    "wof:name":"Ban Khlong Wat Ket",
    "wof:placetype":"locality"
},
  "geometry": {"coordinates":[99.93667000000001,13.46918],"type":"Point"}
}