{
  "type": "Feature",
  "properties": {
    "gn:admin1_code":"22.0",
    "gn:asciiname":"Ban Sawang",
    "gn:country_code":"TH",
    "gn:dem":186,
    "gn:feature_class":"P",
    "gn:feature_code":"PPL",
    "gn:name":"Ban Sawang",
    "gn:population":0,
    "gn:timezone":"Asia/Bangkok",
    "iso:country":"TH",
    "name:tha_x_preferred":[
        "\u0e1a\u0e49\u0e32\u0e19\u0e2a\u0e27\u0e48\u0e32\u0e07"
    ],
    "name:und_x_variant":[
        "Sakhang",
        "Ban Sakhang",
        "Ban Saklang",
        "Ban Sawang"
    ],
    "wof:name":"Ban Sawang",
    "wof:placetype":"locality"
},
  "geometry": {"coordinates":[102.554,16.20617],"type":"Point"}
}