{
  "type": "Feature",
  "properties": {
    "gn:admin1_code":"60.0",
    "gn:asciiname":"Ban Khlong Lam Phla",
    "gn:country_code":"TH",
    "gn:dem":41,
    "gn:feature_class":"P",
    "gn:feature_code":"PPL",
    "gn:name":"Ban Khlong Lam Phla",
    "gn:population":0,
    "gn:timezone":"Asia/Bangkok",
    "iso:country":"TH",
    "name:tha_x_preferred":[
        "\u0e1a\u0e49\u0e32\u0e19\u0e04\u0e25\u0e2d\u0e07\u0e25\u0e33\u0e1e\u0e25\u0e32"
    ],
    "wof:name":"Ban Khlong Lam Phla",
    "wof:placetype":"locality"
},
  "geometry": {"coordinates":[99.38621999999999,8.56517],"type":"Point"}
}