{
  "type": "Feature",
  "properties": {
    "gn:admin1_code":"11.0",
    "gn:asciiname":"Ban Yang",
    "gn:country_code":"TH",
    "gn:dem":102,
    "gn:feature_class":"P",
    "gn:feature_code":"PPL",
    "gn:name":"Ban Yang",
    "gn:population":0,
    "gn:timezone":"Asia/Bangkok",
    "iso:country":"TH",
    "wof:name":"Ban Yang",
    "wof:placetype":"locality"
},
  "geometry": {"coordinates":[99.43333,16.36667000000001],"type":"Point"}
}