{
  "type": "Feature",
  "properties": {
    "gn:admin1_code":"25",
    "gn:asciiname":"Ban Khang Hung",
    "gn:country_code":"TH",
    "gn:dem":139,
    "gn:feature_class":"P",
    "gn:feature_code":"PPL",
    "gn:name":"Ban Khang Hung",
    "gn:population":0,
    "gn:timezone":"Asia/Bangkok",
    "iso:country":"TH",
    "name:tha_x_preferred":[
        "\u0e1a\u0e49\u0e32\u0e19\u0e04\u0e32\u0e07\u0e2e\u0e38\u0e07"
    ],
    "wof:name":"Ban Khang Hung",
    "wof:placetype":"locality"
},
  "geometry": {"coordinates":[103.80036,16.09214],"type":"Point"}
}