{
  "type": "Feature",
  "properties": {
    "gn:admin1_code":"4.0",
    "gn:asciiname":"Ban Kaem",
    "gn:country_code":"TH",
    "gn:dem":283,
    "gn:feature_class":"P",
    "gn:feature_code":"PPL",
    "gn:name":"Ban Kaem",
    "gn:population":0,
    "gn:timezone":"Asia/Bangkok",
    "iso:country":"TH",
    "name:tha_x_preferred":[
        "\u0e1a\u0e49\u0e32\u0e19\u0e41\u0e01\u0e49\u0e21"
    ],
    "wof:name":"Ban Kaem",
    "wof:placetype":"locality"
},
  "geometry": {"coordinates":[100.91839,19.17489],"type":"Point"}
}