{
  "type": "Feature",
  "properties": {
    "gn:admin1_code":"26.0",
    "gn:asciiname":"Ban Non Lueam",
    "gn:country_code":"TH",
    "gn:dem":234,
    "gn:feature_class":"P",
    "gn:feature_code":"PPL",
    "gn:name":"Ban Non Lueam",
    "gn:population":0,
    "gn:timezone":"Asia/Bangkok",
    "iso:country":"TH",
    "name:tha_x_preferred":[
        "\u0e1a\u0e49\u0e32\u0e19\u0e42\u0e19\u0e19\u0e40\u0e2b\u0e25\u0e37\u0e48\u0e2d\u0e21"
    ],
    "wof:name":"Ban Non Lueam",
    "wof:placetype":"locality"
},
  "geometry": {"coordinates":[101.83711,15.90147],"type":"Point"}
}