{
  "type": "Feature",
  "properties": {
    "gn:admin1_code":"53.0",
    "gn:asciiname":"Ban Welu Wanaram",
    "gn:country_code":"TH",
    "gn:dem":6,
    "gn:feature_class":"P",
    "gn:feature_code":"PPL",
    "gn:name":"Ban Welu Wanaram",
    "gn:population":0,
    "gn:timezone":"Asia/Bangkok",
    "iso:country":"TH",
    "name:tha_x_preferred":[
        "\u0e1a\u0e49\u0e32\u0e19\u0e40\u0e27\u0e2c\u0e38\u0e27\u0e19\u0e32\u0e23\u0e32\u0e21"
    ],
    "wof:name":"Ban Welu Wanaram",
    "wof:placetype":"locality"
},
  "geometry": {"coordinates":[100.23596999999999,13.96858],"type":"Point"}
}