{
  "type": "Feature",
  "properties": {
    "gn:admin1_code":"15.0",
    "gn:asciiname":"Ban Thap Luang",
    "gn:country_code":"TH",
    "gn:dem":132,
    "gn:feature_class":"P",
    "gn:feature_code":"PPL",
    "gn:name":"Ban Thap Luang",
    "gn:population":0,
    "gn:timezone":"Asia/Bangkok",
    "iso:country":"TH",
    "name:tha_x_preferred":[
        "\u0e1a\u0e49\u0e32\u0e19\u0e17\u0e31\u0e1e\u0e2b\u0e25\u0e27\u0e07"
    ],
    "name:und_x_variant":[
        "B\u0101n Dhabh Hlu\u0101ng",
        "Ban Thap Luang"
    ],
    "wof:lang_x_official":[
        "tha"
    ],
    "wof:lang_x_spoken":[
        "tha"
    ],
    "wof:name":"Ban Thap Luang",
    "wof:placetype":"locality"
},
  "geometry": {"coordinates":[99.56856000000001,15.08767],"type":"Point"}
}