{
  "type": "Feature",
  "properties": {
    "gn:admin1_code":"76.0",
    "gn:asciiname":"Ban Saphan Luean Lam",
    "gn:country_code":"TH",
    "gn:dem":213,
    "gn:feature_class":"P",
    "gn:feature_code":"PPL",
    "gn:name":"Ban Saphan Luean Lam",
    "gn:population":0,
    "gn:timezone":"Asia/Bangkok",
    "iso:country":"TH",
    "name:tha_x_preferred":[
        "\u0e1a\u0e49\u0e32\u0e19\u0e2a\u0e30\u0e1e\u0e32\u0e19\u0e40\u0e25\u0e37\u0e2d\u0e19\u0e25\u0e33"
    ],
    "wof:name":"Ban Saphan Luean Lam",
    "wof:placetype":"locality"
},
  "geometry": {"coordinates":[103.35853,17.08997],"type":"Point"}
}