{
  "type": "Feature",
  "properties": {
    "gn:admin1_code":"44.0",
    "gn:asciiname":"Ban Ko Mamuang",
    "gn:country_code":"TH",
    "gn:dem":12,
    "gn:feature_class":"P",
    "gn:feature_code":"PPL",
    "gn:name":"Ban Ko Mamuang",
    "gn:population":0,
    "gn:timezone":"Asia/Bangkok",
    "iso:country":"TH",
    "name:tha_x_preferred":[
        "\u0e1a\u0e49\u0e32\u0e19\u0e40\u0e01\u0e32\u0e30\u0e21\u0e30\u0e21\u0e48\u0e27\u0e07"
    ],
    "wof:name":"Ban Ko Mamuang",
    "wof:placetype":"locality"
},
  "geometry": {"coordinates":[101.36792,13.70631],"type":"Point"}
}