{
  "type": "Feature",
  "properties": {
    "gn:admin1_code":"37",
    "gn:asciiname":"Ban Khok Khwit",
    "gn:country_code":"TH",
    "gn:dem":13,
    "gn:feature_class":"P",
    "gn:feature_code":"PPL",
    "gn:name":"Ban Khok Khwit",
    "gn:population":0,
    "gn:timezone":"Asia/Bangkok",
    "iso:country":"TH",
    "name:tha_x_preferred":[
        "\u0e1a\u0e49\u0e32\u0e19\u0e42\u0e04\u0e01\u0e02\u0e27\u0e34\u0e14"
    ],
    "wof:name":"Ban Khok Khwit",
    "wof:placetype":"locality"
},
  "geometry": {"coordinates":[100.72228,14.62542],"type":"Point"}
}