{
  "type": "Feature",
  "properties": {
    "gn:admin1_code":"14.0",
    "gn:asciiname":"Ban Huai Mak",
    "gn:country_code":"TH",
    "gn:dem":727,
    "gn:feature_class":"P",
    "gn:feature_code":"PPL",
    "gn:name":"Ban Huai Mak",
    "gn:population":0,
    "gn:timezone":"Asia/Bangkok",
    "iso:country":"TH",
    "name:tha_x_preferred":[
        "\u0e1a\u0e49\u0e32\u0e19\u0e2b\u0e49\u0e27\u0e22\u0e2b\u0e21\u0e32\u0e01"
    ],
    "wof:name":"Ban Huai Mak",
    "wof:placetype":"locality"
},
  "geometry": {"coordinates":[101.04980999999999,16.76242],"type":"Point"}
}