{
  "type": "Feature",
  "properties": {
    "gn:admin1_code":"50.0",
    "gn:asciiname":"Ban Khao Pu Khong",
    "gn:country_code":"TH",
    "gn:dem":38,
    "gn:feature_class":"P",
    "gn:feature_code":"PPL",
    "gn:name":"Ban Khao Pu Khong",
    "gn:population":0,
    "gn:timezone":"Asia/Bangkok",
    "iso:country":"TH",
    "name:tha_x_preferred":[
        "\u0e1a\u0e49\u0e32\u0e19\u0e40\u0e02\u0e32\u0e1b\u0e39\u0e48\u0e04\u0e07"
    ],
    "wof:name":"Ban Khao Pu Khong",
    "wof:placetype":"locality"
},
  "geometry": {"coordinates":[99.48872,13.8962],"type":"Point"}
}