{
  "type": "Feature",
  "properties": {
    "gn:admin1_code":"65.0",
    "gn:asciiname":"Ban Tae Ram",
    "gn:country_code":"TH",
    "gn:dem":11,
    "gn:feature_class":"P",
    "gn:feature_code":"PPL",
    "gn:name":"Ban Tae Ram",
    "gn:population":0,
    "gn:timezone":"Asia/Bangkok",
    "iso:country":"TH",
    "name:tha_x_preferred":[
        "\u0e1a\u0e49\u0e32\u0e19\u0e41\u0e15\u0e30\u0e2b\u0e23\u0e33"
    ],
    "name:und_x_variant":[
        "Ban Tae Lam"
    ],
    "wof:name":"Ban Tae Ram",
    "wof:placetype":"locality"
},
  "geometry": {"coordinates":[99.53006000000001,7.34842],"type":"Point"}
}