{
  "type": "Feature",
  "properties": {
    "gn:admin1_code":"75.0",
    "gn:asciiname":"Ban Kho Laen Noi",
    "gn:country_code":"TH",
    "gn:dem":159,
    "gn:feature_class":"P",
    "gn:feature_code":"PPL",
    "gn:name":"Ban Kho Laen Noi",
    "gn:population":0,
    "gn:timezone":"Asia/Bangkok",
    "iso:country":"TH",
    "name:tha_x_preferred":[
        "\u0e1a\u0e49\u0e32\u0e19\u0e04\u0e2d\u0e41\u0e25\u0e19\u0e19\u0e49\u0e2d\u0e22"
    ],
    "name:und_x_variant":[
        "Ban Kho Laen"
    ],
    "wof:name":"Ban Kho Laen Noi",
    "wof:placetype":"locality"
},
  "geometry": {"coordinates":[105.40219,14.881],"type":"Point"}
}