{
  "type": "Feature",
  "properties": {
    "gn:admin1_code":"5.0",
    "gn:asciiname":"Ban Mae Tut",
    "gn:country_code":"TH",
    "gn:dem":396,
    "gn:feature_class":"P",
    "gn:feature_code":"PPL",
    "gn:name":"Ban Mae Tut",
    "gn:population":0,
    "gn:timezone":"Asia/Bangkok",
    "iso:country":"TH",
    "wof:name":"Ban Mae Tut",
    "wof:placetype":"locality"
},
  "geometry": {"coordinates":[99.12194,18.47111],"type":"Point"}
}