{
  "type": "Feature",
  "properties": {
    "gn:admin1_code":"14.0",
    "gn:asciiname":"Ban Wang Kamphaeng",
    "gn:country_code":"TH",
    "gn:dem":77,
    "gn:feature_class":"P",
    "gn:feature_code":"PPL",
    "gn:name":"Ban Wang Kamphaeng",
    "gn:population":0,
    "gn:timezone":"Asia/Bangkok",
    "iso:country":"TH",
    "name:tha_x_preferred":[
        "\u0e1a\u0e49\u0e32\u0e19\u0e27\u0e31\u0e07\u0e01\u0e33\u0e41\u0e1e\u0e07"
    ],
    "wof:name":"Ban Wang Kamphaeng",
    "wof:placetype":"locality"
},
  "geometry": {"coordinates":[101.00339,15.41114],"type":"Point"}
}