{
  "type": "Feature",
  "properties": {
    "gn:admin1_code":"24",
    "gn:asciiname":"Ban Lao Som Lom",
    "gn:country_code":"TH",
    "gn:dem":174,
    "gn:feature_class":"P",
    "gn:feature_code":"PPL",
    "gn:name":"Ban Lao Som Lom",
    "gn:population":0,
    "gn:timezone":"Asia/Bangkok",
    "iso:country":"TH",
    "name:tha_x_preferred":[
        "\u0e1a\u0e49\u0e32\u0e19\u0e40\u0e2b\u0e25\u0e48\u0e32\u0e2a\u0e49\u0e21\u0e25\u0e21"
    ],
    "wof:name":"Ban Lao Som Lom",
    "wof:placetype":"locality"
},
  "geometry": {"coordinates":[103.15953,15.73606],"type":"Point"}
}