{
  "type": "Feature",
  "properties": {
    "gn:admin1_code":"55.0",
    "gn:asciiname":"Ban Khung Samphao",
    "gn:country_code":"TH",
    "gn:dem":3,
    "gn:feature_class":"P",
    "gn:feature_code":"PPL",
    "gn:name":"Ban Khung Samphao",
    "gn:population":0,
    "gn:timezone":"Asia/Bangkok",
    "iso:country":"TH",
    "name:tha_x_preferred":[
        "\u0e1a\u0e49\u0e32\u0e19\u0e04\u0e38\u0e49\u0e07\u0e2a\u0e33\u0e40\u0e20\u0e32"
    ],
    "wof:name":"Ban Khung Samphao",
    "wof:placetype":"locality"
},
  "geometry": {"coordinates":[100.25244000000001,13.58431],"type":"Point"}
}