{
  "type": "Feature",
  "properties": {
    "gn:admin1_code":"31.0",
    "gn:asciiname":"Ban Sai Wari",
    "gn:country_code":"TH",
    "gn:dem":188,
    "gn:feature_class":"P",
    "gn:feature_code":"PPL",
    "gn:name":"Ban Sai Wari",
    "gn:population":0,
    "gn:timezone":"Asia/Bangkok",
    "iso:country":"TH",
    "name:tha_x_preferred":[
        "\u0e1a\u0e49\u0e32\u0e19\u0e2a\u0e32\u0e22\u0e27\u0e32\u0e23\u0e35"
    ],
    "wof:name":"Ban Sai Wari",
    "wof:placetype":"locality"
},
  "geometry": {"coordinates":[101.56802999999999,6.18372],"type":"Point"}
}