{
  "type": "Feature",
  "properties": {
    "gn:admin1_code":"10.0",
    "gn:asciiname":"Ban Ruam Chit",
    "gn:country_code":"TH",
    "gn:dem":105,
    "gn:feature_class":"P",
    "gn:feature_code":"PPL",
    "gn:name":"Ban Ruam Chit",
    "gn:population":0,
    "gn:timezone":"Asia/Bangkok",
    "iso:country":"TH",
    "name:tha_x_preferred":[
        "Ban Ruam Chit"
    ],
    "name:tha_x_variant":[
        "\u0e1a\u0e49\u0e32\u0e19\u0e23\u0e48\u0e27\u0e21\u0e08\u0e34\u0e15"
    ],
    "wof:name":"Ban Ruam Chit",
    "wof:placetype":"locality"
},
  "geometry": {"coordinates":[100.34757999999999,17.70988999999999],"type":"Point"}
}