{
  "type": "Feature",
  "properties": {
    "gn:admin1_code":"53.0",
    "gn:asciiname":"Ban Huai Pla Kot",
    "gn:country_code":"TH",
    "gn:dem":14,
    "gn:feature_class":"P",
    "gn:feature_code":"PPL",
    "gn:name":"Ban Huai Pla Kot",
    "gn:population":0,
    "gn:timezone":"Asia/Bangkok",
    "iso:country":"TH",
    "name:tha_x_preferred":[
        "\u0e1a\u0e49\u0e32\u0e19\u0e2b\u0e49\u0e27\u0e22\u0e1b\u0e25\u0e32\u0e01\u0e14"
    ],
    "name:und_x_variant":[
        "Huai Pla Kot",
        "Ban Huai Pla Kot"
    ],
    "wof:name":"Ban Huai Pla Kot",
    "wof:placetype":"locality"
},
  "geometry": {"coordinates":[99.84814,13.98561],"type":"Point"}
}