{
  "type": "Feature",
  "properties": {
    "gn:admin1_code":"18.0",
    "gn:asciiname":"Ban Pha Nang",
    "gn:country_code":"TH",
    "gn:dem":332,
    "gn:feature_class":"P",
    "gn:feature_code":"PPL",
    "gn:name":"Ban Pha Nang",
    "gn:population":0,
    "gn:timezone":"Asia/Bangkok",
    "iso:country":"TH",
    "name:tha_x_preferred":[
        "Ban Pha Nang"
    ],
    "name:tha_x_variant":[
        "\u0e1a\u0e49\u0e32\u0e19\u0e1c\u0e32\u0e19\u0e32\u0e07"
    ],
    "wof:name":"Ban Pha Nang",
    "wof:placetype":"locality"
},
  "geometry": {"coordinates":[101.99044000000001,17.34017],"type":"Point"}
}