{
  "type": "Feature",
  "properties": {
    "gn:admin1_code":"81.0",
    "gn:asciiname":"Ban Na Saeng Sakhon",
    "gn:country_code":"TH",
    "gn:dem":159,
    "gn:feature_class":"P",
    "gn:feature_code":"PPL",
    "gn:name":"Ban Na Saeng Sakhon",
    "gn:population":0,
    "gn:timezone":"Asia/Bangkok",
    "iso:country":"TH",
    "name:tha_x_preferred":[
        "\u0e1a\u0e49\u0e32\u0e19\u0e19\u0e32\u0e41\u0e2a\u0e07\u0e2a\u0e32\u0e04\u0e23"
    ],
    "wof:name":"Ban Na Saeng Sakhon",
    "wof:placetype":"locality"
},
  "geometry": {"coordinates":[103.82056,18.09328],"type":"Point"}
}