{
  "type": "Feature",
  "properties": {
    "gn:admin1_code":"16.0",
    "gn:asciiname":"Ban Bo Nam Yen",
    "gn:country_code":"TH",
    "gn:dem":51,
    "gn:feature_class":"P",
    "gn:feature_code":"PPL",
    "gn:name":"Ban Bo Nam Yen",
    "gn:population":0,
    "gn:timezone":"Asia/Bangkok",
    "iso:country":"TH",
    "name:tha_x_preferred":[
        "\u0e1a\u0e49\u0e32\u0e19\u0e1a\u0e48\u0e2d\u0e19\u0e49\u0e33\u0e40\u0e22\u0e47\u0e19"
    ],
    "wof:name":"Ban Bo Nam Yen",
    "wof:placetype":"locality"
},
  "geometry": {"coordinates":[100.60492000000001,15.91867],"type":"Point"}
}