{
  "type": "Feature",
  "properties": {
    "gn:admin1_code":"8.0",
    "gn:asciiname":"Ban Mai Sairung",
    "gn:country_code":"TH",
    "gn:dem":411,
    "gn:feature_class":"P",
    "gn:feature_code":"PPL",
    "gn:name":"Ban Mai Sairung",
    "gn:population":0,
    "gn:timezone":"Asia/Bangkok",
    "iso:country":"TH",
    "name:tha_x_preferred":[
        "\u0e1a\u0e49\u0e32\u0e19\u0e43\u0e2b\u0e21\u0e48\u0e2a\u0e32\u0e22\u0e23\u0e38\u0e49\u0e07"
    ],
    "wof:name":"Ban Mai Sairung",
    "wof:placetype":"locality"
},
  "geometry": {"coordinates":[98.68928,16.42486],"type":"Point"}
}