{
  "type": "Feature",
  "properties": {
    "gn:admin1_code":"18.0",
    "gn:asciiname":"Ban Kut Ngong",
    "gn:country_code":"TH",
    "gn:dem":251,
    "gn:feature_class":"P",
    "gn:feature_code":"PPL",
    "gn:name":"Ban Kut Ngong",
    "gn:population":0,
    "gn:timezone":"Asia/Bangkok",
    "iso:country":"TH",
    "name:tha_x_preferred":[
        "Ban Kut Ngong"
    ],
    "name:tha_x_variant":[
        "\u0e1a\u0e49\u0e32\u0e19\u0e01\u0e38\u0e14\u0e42\u0e07\u0e49\u0e07"
    ],
    "wof:name":"Ban Kut Ngong",
    "wof:placetype":"locality"
},
  "geometry": {"coordinates":[101.76083,17.36997],"type":"Point"}
}