{
  "type": "Feature",
  "properties": {
    "gn:admin1_code":"56.0",
    "gn:asciiname":"Ban Nong khao On",
    "gn:country_code":"TH",
    "gn:dem":46,
    "gn:feature_class":"P",
    "gn:feature_code":"PPL",
    "gn:name":"Ban Nong khao On",
    "gn:population":0,
    "gn:timezone":"Asia/Bangkok",
    "iso:country":"TH",
    "name:tha_x_preferred":[
        "\u0e1a\u0e49\u0e32\u0e19\u0e2b\u0e19\u0e2d\u0e07\u0e40\u0e02\u0e32\u0e2d\u0e48\u0e2d\u0e19"
    ],
    "wof:name":"Ban Nong khao On",
    "wof:placetype":"locality"
},
  "geometry": {"coordinates":[99.74275,12.82861],"type":"Point"}
}