{
  "type": "Feature",
  "properties": {
    "gn:admin1_code":"55.0",
    "gn:asciiname":"Ban Hup Sanchao",
    "gn:country_code":"TH",
    "gn:dem":4,
    "gn:feature_class":"P",
    "gn:feature_code":"PPL",
    "gn:name":"Ban Hup Sanchao",
    "gn:population":0,
    "gn:timezone":"Asia/Bangkok",
    "iso:country":"TH",
    "name:tha_x_preferred":[
        "\u0e1a\u0e49\u0e32\u0e19\u0e2b\u0e38\u0e1a\u0e28\u0e32\u0e25\u0e40\u0e08\u0e49\u0e32"
    ],
    "wof:name":"Ban Hup Sanchao",
    "wof:placetype":"locality"
},
  "geometry": {"coordinates":[100.27218999999999,13.652],"type":"Point"}
}