{
  "type": "Feature",
  "properties": {
    "gn:admin1_code":"73.0",
    "gn:asciiname":"Ban Nong Saeng",
    "gn:cc2":"TH",
    "gn:country_code":"TH",
    "gn:dem":148,
    "gn:feature_class":"P",
    "gn:feature_code":"PPL",
    "gn:name":"Ban Nong Saeng",
    "gn:population":0,
    "gn:timezone":"Asia/Bangkok",
    "iso:country":"TH",
    "name:und_x_variant":[
        "Ban Nong Waeng",
        "Ban Nong Saeng"
    ],
    "wof:name":"Ban Nong Saeng",
    "wof:placetype":"locality"
},
  "geometry": {"coordinates":[104.76667,17.41667],"type":"Point"}
}