{
  "type": "Feature",
  "properties": {
    "gn:admin1_code":"27",
    "gn:asciiname":"Ban Bun Bandan",
    "gn:country_code":"TH",
    "gn:dem":381,
    "gn:feature_class":"P",
    "gn:feature_code":"PPL",
    "gn:name":"Ban Bun Bandan",
    "gn:population":0,
    "gn:timezone":"Asia/Bangkok",
    "iso:country":"TH",
    "name:tha_x_preferred":[
        "\u0e1a\u0e49\u0e32\u0e19\u0e1a\u0e38\u0e0d\u0e1a\u0e31\u0e19\u0e14\u0e32\u0e25"
    ],
    "wof:name":"Ban Bun Bandan",
    "wof:placetype":"locality"
},
  "geometry": {"coordinates":[101.28389,14.63867],"type":"Point"}
}