{
  "type": "Feature",
  "properties": {
    "gn:admin1_code":"40.0",
    "gn:admin2_code":"1046",
    "gn:asciiname":"Ban Bang Chan",
    "gn:country_code":"TH",
    "gn:dem":1,
    "gn:feature_class":"P",
    "gn:feature_code":"PPL",
    "gn:name":"Ban Bang Chan",
    "gn:population":0,
    "gn:timezone":"Asia/Bangkok",
    "iso:country":"TH",
    "name:und_x_variant":[
        "Ban Ta Chan",
        "Ban Bang Chan"
    ],
    "wof:name":"Ban Bang Chan",
    "wof:placetype":"locality"
},
  "geometry": {"coordinates":[100.68333,13.85],"type":"Point"}
}