{
  "type": "Feature",
  "properties": {
    "gn:admin1_code":"44.0",
    "gn:asciiname":"Ban Na Lao Nam",
    "gn:country_code":"TH",
    "gn:dem":9,
    "gn:feature_class":"P",
    "gn:feature_code":"PPL",
    "gn:name":"Ban Na Lao Nam",
    "gn:population":0,
    "gn:timezone":"Asia/Bangkok",
    "iso:country":"TH",
    "name:tha_x_preferred":[
        "\u0e1a\u0e49\u0e32\u0e19\u0e19\u0e32\u0e40\u0e2b\u0e25\u0e48\u0e32\u0e19\u0e49\u0e33"
    ],
    "wof:name":"Ban Na Lao Nam",
    "wof:placetype":"locality"
},
  "geometry": {"coordinates":[101.31553,13.73392],"type":"Point"}
}