{
  "type": "Feature",
  "properties": {
    "gn:admin1_code":"27.0",
    "gn:asciiname":"Ban Tako Thung",
    "gn:country_code":"TH",
    "gn:dem":160,
    "gn:feature_class":"P",
    "gn:feature_code":"PPL",
    "gn:name":"Ban Tako Thung",
    "gn:population":0,
    "gn:timezone":"Asia/Bangkok",
    "iso:country":"TH",
    "name:tha_x_preferred":[
        "\u0e1a\u0e49\u0e32\u0e19\u0e15\u0e30\u0e42\u0e01\u0e17\u0e38\u0e48\u0e07"
    ],
    "wof:name":"Ban Tako Thung",
    "wof:placetype":"locality"
},
  "geometry": {"coordinates":[102.41522000000001,15.28003],"type":"Point"}
}