{
  "type": "Feature",
  "properties": {
    "gn:admin1_code":"26.0",
    "gn:asciiname":"Ban Non Si Thong",
    "gn:country_code":"TH",
    "gn:dem":250,
    "gn:feature_class":"P",
    "gn:feature_code":"PPL",
    "gn:name":"Ban Non Si Thong",
    "gn:population":0,
    "gn:timezone":"Asia/Bangkok",
    "iso:country":"TH",
    "name:tha_x_preferred":[
        "\u0e1a\u0e49\u0e32\u0e19\u0e42\u0e19\u0e19\u0e28\u0e23\u0e35\u0e17\u0e2d\u0e07"
    ],
    "wof:name":"Ban Non Si Thong",
    "wof:placetype":"locality"
},
  "geometry": {"coordinates":[101.62058,16.04603],"type":"Point"}
}