{
  "type": "Feature",
  "properties": {
    "gn:admin1_code":"57.0",
    "gn:asciiname":"Ban Khlong Nam Khem",
    "gn:country_code":"TH",
    "gn:dem":10,
    "gn:feature_class":"P",
    "gn:feature_code":"PPL",
    "gn:name":"Ban Khlong Nam Khem",
    "gn:population":0,
    "gn:timezone":"Asia/Bangkok",
    "iso:country":"TH",
    "name:tha_x_preferred":[
        "\u0e1a\u0e49\u0e32\u0e19\u0e04\u0e25\u0e2d\u0e07\u0e19\u0e49\u0e33\u0e40\u0e04\u0e47\u0e21"
    ],
    "wof:name":"Ban Khlong Nam Khem",
    "wof:placetype":"locality"
},
  "geometry": {"coordinates":[99.45975,11.09767],"type":"Point"}
}