{
  "type": "Feature",
  "properties": {
    "gn:admin1_code":"42.0",
    "gn:asciiname":"Muban Happi Laen Siwio",
    "gn:country_code":"TH",
    "gn:dem":7,
    "gn:feature_class":"P",
    "gn:feature_code":"PPL",
    "gn:name":"Muban Happi Laen Siwio",
    "gn:population":0,
    "gn:timezone":"Asia/Bangkok",
    "iso:country":"TH",
    "name:tha_x_preferred":[
        "\u0e2b\u0e21\u0e39\u0e48\u0e1a\u0e49\u0e32\u0e19\u0e41\u0e2e\u0e1b\u0e1b\u0e35\u0e49\u0e41\u0e25\u0e19\u0e14\u0e4c\u0e0b\u0e35\u0e27\u0e34\u0e27"
    ],
    "wof:name":"Muban Happi Laen Siwio",
    "wof:placetype":"locality"
},
  "geometry": {"coordinates":[100.71758,13.50289],"type":"Point"}
}