{
  "type": "Feature",
  "properties": {
    "gn:admin1_code":"23.0",
    "gn:asciiname":"Ban Non Khi Khuang",
    "gn:country_code":"TH",
    "gn:dem":180,
    "gn:feature_class":"P",
    "gn:feature_code":"PPL",
    "gn:name":"Ban Non Khi Khuang",
    "gn:population":0,
    "gn:timezone":"Asia/Bangkok",
    "iso:country":"TH",
    "name:tha_x_preferred":[
        "\u0e1a\u0e49\u0e32\u0e19\u0e42\u0e19\u0e19\u0e02\u0e35\u0e49\u0e04\u0e27\u0e07"
    ],
    "wof:name":"Ban Non Khi Khuang",
    "wof:placetype":"locality"
},
  "geometry": {"coordinates":[103.32669,16.55542],"type":"Point"}
}