{
  "type": "Feature",
  "properties": {
    "gn:admin1_code":"22.0",
    "gn:asciiname":"Ban Kao Ngio",
    "gn:country_code":"TH",
    "gn:dem":192,
    "gn:feature_class":"P",
    "gn:feature_code":"PPL",
    "gn:name":"Ban Kao Ngio",
    "gn:population":0,
    "gn:timezone":"Asia/Bangkok",
    "iso:country":"TH",
    "name:tha_x_preferred":[
        "\u0e1a\u0e49\u0e32\u0e19\u0e40\u0e01\u0e48\u0e32\u0e07\u0e34\u0e49\u0e27"
    ],
    "name:und_x_variant":[
        "Ban Kao Ngiu"
    ],
    "wof:name":"Ban Kao Ngio",
    "wof:placetype":"locality"
},
  "geometry": {"coordinates":[102.58822000000001,15.84794],"type":"Point"}
}