{
  "type": "Feature",
  "properties": {
    "gn:admin1_code":"50.0",
    "gn:asciiname":"Ban Thi Kai",
    "gn:country_code":"TH",
    "gn:dem":534,
    "gn:feature_class":"P",
    "gn:feature_code":"PPL",
    "gn:name":"Ban Thi Kai",
    "gn:population":0,
    "gn:timezone":"Asia/Bangkok",
    "iso:country":"TH",
    "wof:name":"Ban Thi Kai",
    "wof:placetype":"locality"
},
  "geometry": {"coordinates":[98.69732,14.94864],"type":"Point"}
}