{
  "type": "Feature",
  "properties": {
    "gn:admin1_code":"60.0",
    "gn:asciiname":"Ban Phra Saeng Nuea",
    "gn:country_code":"TH",
    "gn:dem":31,
    "gn:feature_class":"P",
    "gn:feature_code":"PPL",
    "gn:name":"Ban Phra Saeng Nuea",
    "gn:population":0,
    "gn:timezone":"Asia/Bangkok",
    "iso:country":"TH",
    "name:tha_x_preferred":[
        "\u0e1a\u0e49\u0e32\u0e19\u0e1e\u0e23\u0e30\u0e41\u0e2a\u0e07\u0e40\u0e2b\u0e19\u0e37\u0e2d"
    ],
    "name:und_x_variant":[
        "Ban Phra Saeng Nua",
        "Ban Pha Saeng Nua"
    ],
    "wof:name":"Ban Phra Saeng Nuea",
    "wof:placetype":"locality"
},
  "geometry": {"coordinates":[98.82625,8.93436],"type":"Point"}
}