{
  "type": "Feature",
  "properties": {
    "gn:admin1_code":"44.0",
    "gn:asciiname":"Ban Pak Lat Yai Mut",
    "gn:country_code":"TH",
    "gn:dem":3,
    "gn:feature_class":"P",
    "gn:feature_code":"PPL",
    "gn:name":"Ban Pak Lat Yai Mut",
    "gn:population":0,
    "gn:timezone":"Asia/Bangkok",
    "iso:country":"TH",
    "name:tha_x_preferred":[
        "\u0e1a\u0e49\u0e32\u0e19\u0e1b\u0e32\u0e01\u0e25\u0e31\u0e14\u0e22\u0e32\u0e22\u0e21\u0e38\u0e14"
    ],
    "wof:name":"Ban Pak Lat Yai Mut",
    "wof:placetype":"locality"
},
  "geometry": {"coordinates":[100.97928,13.65144],"type":"Point"}
}