{
  "type": "Feature",
  "properties": {
    "gn:admin1_code":"4.0",
    "gn:asciiname":"Ban Sa Kiang",
    "gn:country_code":"TH",
    "gn:dem":1369,
    "gn:feature_class":"P",
    "gn:feature_code":"PPL",
    "gn:name":"Ban Sa Kiang",
    "gn:population":0,
    "gn:timezone":"Asia/Bangkok",
    "iso:country":"TH",
    "name:tha_x_preferred":[
        "\u0e1a\u0e49\u0e32\u0e19\u0e2a\u0e30\u0e40\u0e01\u0e35\u0e49\u0e22\u0e07"
    ],
    "wof:name":"Ban Sa Kiang",
    "wof:placetype":"locality"
},
  "geometry": {"coordinates":[101.19242,19.35708],"type":"Point"}
}