{
  "type": "Feature",
  "properties": {
    "gn:admin1_code":"34",
    "gn:asciiname":"Ban Khao Phraya Chon",
    "gn:country_code":"TH",
    "gn:dem":102,
    "gn:feature_class":"P",
    "gn:feature_code":"PPL",
    "gn:name":"Ban Khao Phraya Chon",
    "gn:population":0,
    "gn:timezone":"Asia/Bangkok",
    "iso:country":"TH",
    "name:tha_x_preferred":[
        "\u0e1a\u0e49\u0e32\u0e19\u0e40\u0e02\u0e32\u0e1e\u0e23\u0e30\u0e22\u0e32\u0e42\u0e08\u0e23"
    ],
    "wof:name":"Ban Khao Phraya Chon",
    "wof:placetype":"locality"
},
  "geometry": {"coordinates":[100.88603000000001,14.99375],"type":"Point"}
}