{
  "type": "Feature",
  "properties": {
    "gn:admin1_code":"48.0",
    "gn:asciiname":"Ban Chong Kaphat",
    "gn:country_code":"TH",
    "gn:dem":36,
    "gn:feature_class":"P",
    "gn:feature_code":"PPL",
    "gn:name":"Ban Chong Kaphat",
    "gn:population":0,
    "gn:timezone":"Asia/Bangkok",
    "iso:country":"TH",
    "name:tha_x_preferred":[
        "\u0e1a\u0e49\u0e32\u0e19\u0e0a\u0e48\u0e2d\u0e07\u0e01\u0e30\u0e1e\u0e31\u0e14"
    ],
    "name:und_x_variant":[
        "Chaung Kaphat",
        "Ban Chong Kaphat"
    ],
    "wof:lang_x_official":[
        "tha"
    ],
    "wof:lang_x_spoken":[
        "tha"
    ],
    "wof:name":"Ban Chong Kaphat",
    "wof:placetype":"locality"
},
  "geometry": {"coordinates":[101.90947,13.02314],"type":"Point"}
}