{
  "type": "Feature",
  "properties": {
    "gn:admin1_code":"24",
    "gn:asciiname":"Ban Lat Khum Nok",
    "gn:country_code":"TH",
    "gn:dem":144,
    "gn:feature_class":"P",
    "gn:feature_code":"PPL",
    "gn:name":"Ban Lat Khum Nok",
    "gn:population":0,
    "gn:timezone":"Asia/Bangkok",
    "iso:country":"TH",
    "name:tha_x_preferred":[
        "\u0e1a\u0e49\u0e32\u0e19\u0e25\u0e32\u0e14\u0e04\u0e38\u0e49\u0e21\u0e19\u0e2d\u0e01"
    ],
    "wof:name":"Ban Lat Khum Nok",
    "wof:placetype":"locality"
},
  "geometry": {"coordinates":[103.3755,16.21572],"type":"Point"}
}