{
  "type": "Feature",
  "properties": {
    "gn:admin1_code":"67.0",
    "gn:asciiname":"Ban Thung To Kat",
    "gn:country_code":"TH",
    "gn:dem":34,
    "gn:feature_class":"P",
    "gn:feature_code":"PPL",
    "gn:name":"Ban Thung To Kat",
    "gn:population":0,
    "gn:timezone":"Asia/Bangkok",
    "iso:country":"TH",
    "name:tha_x_preferred":[
        "\u0e1a\u0e49\u0e32\u0e19\u0e17\u0e38\u0e48\u0e07\u0e42\u0e15\u0e4a\u0e30\u0e01\u0e32\u0e14"
    ],
    "wof:name":"Ban Thung To Kat",
    "wof:placetype":"locality"
},
  "geometry": {"coordinates":[100.07868999999999,6.79933],"type":"Point"}
}