{
  "type": "Feature",
  "properties": {
    "gn:admin1_code":"73.0",
    "gn:asciiname":"Ban Bueng Lom",
    "gn:country_code":"TH",
    "gn:dem":150,
    "gn:feature_class":"P",
    "gn:feature_code":"PPL",
    "gn:name":"Ban Bueng Lom",
    "gn:population":0,
    "gn:timezone":"Asia/Bangkok",
    "iso:country":"TH",
    "name:tha_x_preferred":[
        "Ban Bueng Lom"
    ],
    "name:tha_x_variant":[
        "\u0e1a\u0e49\u0e32\u0e19\u0e1a\u0e36\u0e07\u0e2b\u0e25\u0e48\u0e21"
    ],
    "name:und_x_variant":[
        "Ban Bung Lom"
    ],
    "wof:name":"Ban Bueng Lom",
    "wof:placetype":"locality"
},
  "geometry": {"coordinates":[104.79232,17.18638],"type":"Point"}
}