{
  "type": "Feature",
  "properties": {
    "gn:admin1_code":"70.0",
    "gn:asciiname":"Ban Bo Pla",
    "gn:country_code":"TH",
    "gn:dem":326,
    "gn:feature_class":"P",
    "gn:feature_code":"PPL",
    "gn:name":"Ban Bo Pla",
    "gn:population":0,
    "gn:timezone":"Asia/Bangkok",
    "iso:country":"TH",
    "name:tha_x_preferred":[
        "\u0e1a\u0e49\u0e32\u0e19\u0e1a\u0e48\u0e2d\u0e1b\u0e25\u0e32"
    ],
    "wof:name":"Ban Bo Pla",
    "wof:placetype":"locality"
},
  "geometry": {"coordinates":[101.07619,5.73033],"type":"Point"}
}