{
  "type": "Feature",
  "properties": {
    "gn:admin1_code":"75.0",
    "gn:asciiname":"Ban Pa Kung",
    "gn:country_code":"TH",
    "gn:dem":147,
    "gn:feature_class":"P",
    "gn:feature_code":"PPL",
    "gn:name":"Ban Pa Kung",
    "gn:population":0,
    "gn:timezone":"Asia/Bangkok",
    "iso:country":"TH",
    "name:tha_x_preferred":[
        "\u0e1a\u0e49\u0e32\u0e19\u0e1b\u0e48\u0e32\u0e01\u0e38\u0e07"
    ],
    "wof:name":"Ban Pa Kung",
    "wof:placetype":"locality"
},
  "geometry": {"coordinates":[105.33806,15.18567],"type":"Point"}
}