{
  "type": "Feature",
  "properties": {
    "gn:admin1_code":"69.0",
    "gn:asciiname":"Ban Bang Pla Mo",
    "gn:country_code":"TH",
    "gn:dem":4,
    "gn:feature_class":"P",
    "gn:feature_code":"PPL",
    "gn:name":"Ban Bang Pla Mo",
    "gn:population":0,
    "gn:timezone":"Asia/Bangkok",
    "iso:country":"TH",
    "name:tha_x_preferred":[
        "\u0e1a\u0e49\u0e32\u0e19\u0e1a\u0e32\u0e07\u0e1b\u0e25\u0e32\u0e2b\u0e21\u0e2d"
    ],
    "wof:name":"Ban Bang Pla Mo",
    "wof:placetype":"locality"
},
  "geometry": {"coordinates":[101.19711,6.86245],"type":"Point"}
}