{
  "type": "Feature",
  "properties": {
    "gn:admin1_code":"0.0",
    "gn:asciiname":"Amphoe Tha Song Yang",
    "gn:country_code":"TH",
    "gn:dem":209,
    "gn:feature_class":"P",
    "gn:feature_code":"PPL",
    "gn:name":"Amphoe Tha Song Yang",
    "gn:population":0,
    "gn:timezone":"Asia/Bangkok",
    "iso:country":"TH",
    "wof:name":"Amphoe Tha Song Yang",
    "wof:placetype":"locality"
},
  "geometry": {"coordinates":[98.15000000000001,17.18333],"type":"Point"}
}