{
  "type": "Feature",
  "properties": {
    "gn:admin1_code":"30.0",
    "gn:asciiname":"Ban Khok Kae Lae",
    "gn:country_code":"TH",
    "gn:dem":202,
    "gn:feature_class":"P",
    "gn:feature_code":"PPL",
    "gn:name":"Ban Khok Kae Lae",
    "gn:population":0,
    "gn:timezone":"Asia/Bangkok",
    "iso:country":"TH",
    "name:tha_x_preferred":[
        "\u0e1a\u0e49\u0e32\u0e19\u0e42\u0e04\u0e01\u0e41\u0e01\u0e41\u0e25"
    ],
    "name:und_x_variant":[
        "Ban Kra Lek",
        "Ban Khok Kaelae",
        "Ban Khok Kae Lae"
    ],
    "wof:lang_x_official":[
        "tha"
    ],
    "wof:lang_x_spoken":[
        "tha"
    ],
    "wof:name":"Ban Khok Kae Lae",
    "wof:placetype":"locality"
},
  "geometry": {"coordinates":[104.54522,14.52283],"type":"Point"}
}