{
  "type": "Feature",
  "properties": {
    "gn:admin1_code":"35.0",
    "gn:asciiname":"Ban Nong Sam Krai",
    "gn:country_code":"TH",
    "gn:dem":8,
    "gn:feature_class":"P",
    "gn:feature_code":"PPL",
    "gn:name":"Ban Nong Sam Krai",
    "gn:population":0,
    "gn:timezone":"Asia/Bangkok",
    "iso:country":"TH",
    "name:tha_x_preferred":[
        "\u0e1a\u0e49\u0e32\u0e19\u0e2b\u0e19\u0e2d\u0e07\u0e2a\u0e32\u0e21\u0e44\u0e01\u0e23"
    ],
    "wof:name":"Ban Nong Sam Krai",
    "wof:placetype":"locality"
},
  "geometry": {"coordinates":[100.3475,14.66403],"type":"Point"}
}