{
  "type": "Feature",
  "properties": {
    "gn:admin1_code":"75.0",
    "gn:asciiname":"Ban Kut Yai Luan",
    "gn:country_code":"TH",
    "gn:dem":147,
    "gn:feature_class":"P",
    "gn:feature_code":"PPL",
    "gn:name":"Ban Kut Yai Luan",
    "gn:population":0,
    "gn:timezone":"Asia/Bangkok",
    "iso:country":"TH",
    "name:tha_x_preferred":[
        "\u0e1a\u0e49\u0e32\u0e19\u0e01\u0e38\u0e14\u0e22\u0e32\u0e22\u0e25\u0e27\u0e19"
    ],
    "wof:name":"Ban Kut Yai Luan",
    "wof:placetype":"locality"
},
  "geometry": {"coordinates":[105.02518999999999,15.71942],"type":"Point"}
}