{
  "type": "Feature",
  "properties": {
    "gn:admin1_code":"12.0",
    "gn:asciiname":"Ban Kaeng Khan Na",
    "gn:country_code":"TH",
    "gn:dem":153,
    "gn:feature_class":"P",
    "gn:feature_code":"PPL",
    "gn:name":"Ban Kaeng Khan Na",
    "gn:population":0,
    "gn:timezone":"Asia/Bangkok",
    "iso:country":"TH",
    "name:tha_x_preferred":[
        "\u0e1a\u0e49\u0e32\u0e19\u0e41\u0e01\u0e48\u0e07\u0e04\u0e31\u0e19\u0e19\u0e32"
    ],
    "wof:name":"Ban Kaeng Khan Na",
    "wof:placetype":"locality"
},
  "geometry": {"coordinates":[100.51606,17.10319],"type":"Point"}
}