{
  "type": "Feature",
  "properties": {
    "gn:admin1_code":"5.0",
    "gn:asciiname":"Ban San Ton Kha",
    "gn:country_code":"TH",
    "gn:dem":304,
    "gn:feature_class":"P",
    "gn:feature_code":"PPL",
    "gn:name":"Ban San Ton Kha",
    "gn:population":0,
    "gn:timezone":"Asia/Bangkok",
    "iso:country":"TH",
    "name:tha_x_preferred":[
        "\u0e1a\u0e49\u0e32\u0e19\u0e2a\u0e31\u0e19\u0e15\u0e49\u0e19\u0e04\u0e48\u0e32"
    ],
    "name:und_x_variant":[
        "B\u0101n Sam Pa Ka",
        "Ban Sam Pa Kha",
        "Ban San Pa Kha",
        "Ban San Ton Kha"
    ],
    "wof:name":"Ban San Ton Kha",
    "wof:placetype":"locality"
},
  "geometry": {"coordinates":[99.10906,18.66081],"type":"Point"}
}