{
  "type": "Feature",
  "properties": {
    "gn:admin1_code":"4.0",
    "gn:asciiname":"Ban Nam Khoem",
    "gn:country_code":"TH",
    "gn:dem":256,
    "gn:feature_class":"P",
    "gn:feature_code":"PPL",
    "gn:name":"Ban Nam Khoem",
    "gn:population":0,
    "gn:timezone":"Asia/Bangkok",
    "iso:country":"TH",
    "name:tha_x_preferred":[
        "\u0e1a\u0e49\u0e32\u0e19\u0e19\u0e49\u0e33\u0e40\u0e04\u0e34\u0e21"
    ],
    "wof:name":"Ban Nam Khoem",
    "wof:placetype":"locality"
},
  "geometry": {"coordinates":[100.44314,18.10139],"type":"Point"}
}