{
  "type": "Feature",
  "properties": {
    "gn:admin1_code":"44.0",
    "gn:asciiname":"Ban Tha Khan",
    "gn:country_code":"TH",
    "gn:dem":82,
    "gn:feature_class":"P",
    "gn:feature_code":"PPL",
    "gn:name":"Ban Tha Khan",
    "gn:population":0,
    "gn:timezone":"Asia/Bangkok",
    "iso:country":"TH",
    "name:tha_x_preferred":[
        "\u0e1a\u0e49\u0e32\u0e19\u0e17\u0e48\u0e32\u0e04\u0e32\u0e19"
    ],
    "name:und_x_variant":[
        "Tha Khan",
        "Ban Tha Dan",
        "Ban Tha Khan"
    ],
    "wof:name":"Ban Tha Khan",
    "wof:placetype":"locality"
},
  "geometry": {"coordinates":[101.71217,13.46928],"type":"Point"}
}