{
  "type": "Feature",
  "properties": {
    "gn:admin1_code":"41.0",
    "gn:asciiname":"Ban Thung Ban Yen",
    "gn:country_code":"TH",
    "gn:dem":396,
    "gn:feature_class":"P",
    "gn:feature_code":"PPL",
    "gn:name":"Ban Thung Ban Yen",
    "gn:population":0,
    "gn:timezone":"Asia/Bangkok",
    "iso:country":"TH",
    "name:tha_x_preferred":[
        "\u0e1a\u0e49\u0e32\u0e19\u0e17\u0e38\u0e48\u0e07\u0e1a\u0e32\u0e19\u0e40\u0e22\u0e47\u0e19"
    ],
    "name:und_x_variant":[
        "Ban Thung",
        "Ban Thung Ban Yen"
    ],
    "wof:lang_x_official":[
        "tha"
    ],
    "wof:lang_x_spoken":[
        "tha"
    ],
    "wof:name":"Ban Thung Ban Yen",
    "wof:placetype":"locality"
},
  "geometry": {"coordinates":[100.31095000000001,19.52189],"type":"Point"}
}