{
  "type": "Feature",
  "properties": {
    "gn:admin1_code":"16.0",
    "gn:asciiname":"Ban Don Phoem",
    "gn:country_code":"TH",
    "gn:dem":44,
    "gn:feature_class":"P",
    "gn:feature_code":"PPL",
    "gn:name":"Ban Don Phoem",
    "gn:population":0,
    "gn:timezone":"Asia/Bangkok",
    "iso:country":"TH",
    "name:tha_x_preferred":[
        "\u0e1a\u0e49\u0e32\u0e19\u0e14\u0e2d\u0e19\u0e40\u0e1e\u0e34\u0e48\u0e21"
    ],
    "wof:name":"Ban Don Phoem",
    "wof:placetype":"locality"
},
  "geometry": {"coordinates":[99.88357999999999,15.87131],"type":"Point"}
}