{
  "type": "Feature",
  "properties": {
    "gn:admin1_code":"44.0",
    "gn:asciiname":"Ban Nong Falami",
    "gn:country_code":"TH",
    "gn:dem":63,
    "gn:feature_class":"P",
    "gn:feature_code":"PPL",
    "gn:name":"Ban Nong Falami",
    "gn:population":0,
    "gn:timezone":"Asia/Bangkok",
    "iso:country":"TH",
    "name:tha_x_preferred":[
        "\u0e1a\u0e49\u0e32\u0e19\u0e2b\u0e19\u0e2d\u0e07\u0e1d\u0e32\u0e25\u0e30\u0e21\u0e35"
    ],
    "wof:name":"Ban Nong Falami",
    "wof:placetype":"locality"
},
  "geometry": {"coordinates":[101.50261,13.44553],"type":"Point"}
}