{
  "type": "Feature",
  "properties": {
    "gn:admin1_code":"29",
    "gn:asciiname":"Ban Ta Kae",
    "gn:country_code":"TH",
    "gn:dem":155,
    "gn:feature_class":"P",
    "gn:feature_code":"PPL",
    "gn:name":"Ban Ta Kae",
    "gn:population":0,
    "gn:timezone":"Asia/Bangkok",
    "iso:country":"TH",
    "name:tha_x_preferred":[
        "\u0e1a\u0e49\u0e32\u0e19\u0e15\u0e32\u0e41\u0e01"
    ],
    "wof:name":"Ban Ta Kae",
    "wof:placetype":"locality"
},
  "geometry": {"coordinates":[103.47056000000001,14.79308],"type":"Point"}
}