{
  "type": "Feature",
  "properties": {
    "gn:admin1_code":"9.0",
    "gn:asciiname":"Ban Pa Faek",
    "gn:country_code":"TH",
    "gn:dem":49,
    "gn:feature_class":"P",
    "gn:feature_code":"PPL",
    "gn:name":"Ban Pa Faek",
    "gn:population":0,
    "gn:timezone":"Asia/Bangkok",
    "iso:country":"TH",
    "name:tha_x_preferred":[
        "\u0e1a\u0e49\u0e32\u0e19\u0e1b\u0e48\u0e32\u0e41\u0e1d\u0e01"
    ],
    "name:und_x_variant":[
        "B\u0101n Pa Feak",
        "Ban Pa Faek"
    ],
    "wof:name":"Ban Pa Faek",
    "wof:placetype":"locality"
},
  "geometry": {"coordinates":[99.97869,16.96189],"type":"Point"}
}