{
  "type": "Feature",
  "properties": {
    "gn:admin1_code":"38.0",
    "gn:asciiname":"Ban Bang Phraek",
    "gn:country_code":"TH",
    "gn:dem":6,
    "gn:feature_class":"P",
    "gn:feature_code":"PPL",
    "gn:name":"Ban Bang Phraek",
    "gn:population":0,
    "gn:timezone":"Asia/Bangkok",
    "iso:country":"TH",
    "name:tha_x_preferred":[
        "Ban Bang Phraek"
    ],
    "name:tha_x_variant":[
        "\u0e1a\u0e49\u0e32\u0e19\u0e1a\u0e32\u0e07\u0e41\u0e1e\u0e23\u0e01"
    ],
    "name:und_x_variant":[
        "Ban Bang Phraek (1)"
    ],
    "wof:name":"Ban Bang Phraek",
    "wof:placetype":"locality"
},
  "geometry": {"coordinates":[100.41365,13.88784],"type":"Point"}
}