{
  "type": "Feature",
  "properties": {
    "gn:admin1_code":"39.0",
    "gn:asciiname":"Ban Lat Phak Khuang",
    "gn:country_code":"TH",
    "gn:dem":3,
    "gn:feature_class":"P",
    "gn:feature_code":"PPL",
    "gn:name":"Ban Lat Phak Khuang",
    "gn:population":0,
    "gn:timezone":"Asia/Bangkok",
    "iso:country":"TH",
    "name:tha_x_preferred":[
        "Ban Lat Phak Khuang"
    ],
    "name:tha_x_variant":[
        "\u0e1a\u0e49\u0e32\u0e19\u0e25\u0e32\u0e14\u0e1c\u0e31\u0e01\u0e02\u0e27\u0e07"
    ],
    "wof:name":"Ban Lat Phak Khuang",
    "wof:placetype":"locality"
},
  "geometry": {"coordinates":[100.91271999999999,14.21003],"type":"Point"}
}