{
  "type": "Feature",
  "properties": {
    "gn:admin1_code":"68.0",
    "gn:asciiname":"Ban Phrao",
    "gn:country_code":"TH",
    "gn:dem":21,
    "gn:feature_class":"P",
    "gn:feature_code":"PPL",
    "gn:name":"Ban Phrao",
    "gn:population":0,
    "gn:timezone":"Asia/Bangkok",
    "iso:country":"TH",
    "name:und_x_variant":[
        "\u0e1a\u0e49\u0e32\u0e19\u0e1e\u0e23\u0e49\u0e32\u0e27"
    ],
    "wof:name":"Ban Phrao",
    "wof:placetype":"locality"
},
  "geometry": {"coordinates":[100.43424,6.87683],"type":"Point"}
}