{
  "type": "Feature",
  "properties": {
    "gn:admin1_code":"56.0",
    "gn:asciiname":"Ban Sam Ruean",
    "gn:country_code":"TH",
    "gn:dem":7,
    "gn:feature_class":"P",
    "gn:feature_code":"PPL",
    "gn:name":"Ban Sam Ruean",
    "gn:population":0,
    "gn:timezone":"Asia/Bangkok",
    "iso:country":"TH",
    "name:tha_x_preferred":[
        "\u0e1a\u0e49\u0e32\u0e19\u0e2a\u0e32\u0e21\u0e40\u0e23\u0e37\u0e2d\u0e19"
    ],
    "name:und_x_variant":[
        "Ban Sam Ruan"
    ],
    "wof:name":"Ban Sam Ruean",
    "wof:placetype":"locality"
},
  "geometry": {"coordinates":[99.89310999999999,13.13558],"type":"Point"}
}