{
  "type": "Feature",
  "properties": {
    "gn:admin1_code":"46.0",
    "gn:asciiname":"Ban Khet Thetsaban Saen Suk",
    "gn:country_code":"TH",
    "gn:dem":6,
    "gn:feature_class":"P",
    "gn:feature_code":"PPL",
    "gn:name":"Ban Khet Thetsaban Saen Suk",
    "gn:population":0,
    "gn:timezone":"Asia/Bangkok",
    "iso:country":"TH",
    "name:tha_x_preferred":[
        "\u0e1a\u0e49\u0e32\u0e19\u0e40\u0e02\u0e15\u0e40\u0e17\u0e28\u0e1a\u0e32\u0e25\u0e41\u0e2a\u0e19\u0e2a\u0e38\u0e02"
    ],
    "wof:name":"Ban Khet Thetsaban Saen Suk",
    "wof:placetype":"locality"
},
  "geometry": {"coordinates":[100.91275,13.30356],"type":"Point"}
}