{
  "type": "Feature",
  "properties": {
    "gn:admin1_code":"65.0",
    "gn:asciiname":"Ban Na Ok",
    "gn:country_code":"TH",
    "gn:dem":29,
    "gn:feature_class":"P",
    "gn:feature_code":"PPL",
    "gn:name":"Ban Na Ok",
    "gn:population":0,
    "gn:timezone":"Asia/Bangkok",
    "iso:country":"TH",
    "name:tha_x_preferred":[
        "\u0e1a\u0e49\u0e32\u0e19\u0e19\u0e32\u0e2d\u0e2d\u0e01"
    ],
    "wof:name":"Ban Na Ok",
    "wof:placetype":"locality"
},
  "geometry": {"coordinates":[99.34905999999999,7.61092],"type":"Point"}
}