{
  "type": "Feature",
  "properties": {
    "gn:admin1_code":"73.0",
    "gn:asciiname":"Ban Na Kradao",
    "gn:country_code":"TH",
    "gn:dem":158,
    "gn:feature_class":"P",
    "gn:feature_code":"PPL",
    "gn:name":"Ban Na Kradao",
    "gn:population":0,
    "gn:timezone":"Asia/Bangkok",
    "iso:country":"TH",
    "name:tha_x_preferred":[
        "Ban Na Kradao"
    ],
    "name:tha_x_variant":[
        "\u0e1a\u0e49\u0e32\u0e19\u0e19\u0e32\u0e01\u0e23\u0e30\u0e40\u0e14\u0e32"
    ],
    "wof:name":"Ban Na Kradao",
    "wof:placetype":"locality"
},
  "geometry": {"coordinates":[104.55725,17.10931],"type":"Point"}
}