{
  "type": "Feature",
  "properties": {
    "gn:admin1_code":"3.0",
    "gn:asciiname":"Ban Pa Bong Luang",
    "gn:country_code":"TH",
    "gn:dem":390,
    "gn:feature_class":"P",
    "gn:feature_code":"PPL",
    "gn:name":"Ban Pa Bong Luang",
    "gn:population":0,
    "gn:timezone":"Asia/Bangkok",
    "iso:country":"TH",
    "name:tha_x_preferred":[
        "\u0e1a\u0e49\u0e32\u0e19\u0e1b\u0e48\u0e32\u0e1a\u0e07\u0e2b\u0e25\u0e27\u0e07"
    ],
    "name:und_x_variant":[
        "Ban Pa Bong",
        "Ban Pa Bong Luang"
    ],
    "wof:name":"Ban Pa Bong Luang",
    "wof:placetype":"locality"
},
  "geometry": {"coordinates":[99.943,20.23078],"type":"Point"}
}