{
  "type": "Feature",
  "properties": {
    "gn:admin1_code":"69.0",
    "gn:asciiname":"Ban Kra So",
    "gn:country_code":"TH",
    "gn:dem":11,
    "gn:feature_class":"P",
    "gn:feature_code":"PPL",
    "gn:name":"Ban Kra So",
    "gn:population":0,
    "gn:timezone":"Asia/Bangkok",
    "iso:country":"TH",
    "name:und_x_variant":[
        "Kampong Kra Sau",
        "Kampong Krasok",
        "Kampong Kraso",
        "Ban Kra So",
        "\u0e1a\u0e49\u0e32\u0e19\u0e01\u0e23\u0e30\u0e40\u0e2a\u0e32\u0e30"
    ],
    "wof:name":"Ban Kra So",
    "wof:placetype":"locality"
},
  "geometry": {"coordinates":[101.38101,6.74847],"type":"Point"}
}