{
  "type": "Feature",
  "properties": {
    "gn:admin1_code":"31.0",
    "gn:asciiname":"Ban Pu Yu Hi Le",
    "gn:country_code":"TH",
    "gn:dem":8,
    "gn:feature_class":"P",
    "gn:feature_code":"PPL",
    "gn:name":"Ban Pu Yu Hi Le",
    "gn:population":0,
    "gn:timezone":"Asia/Bangkok",
    "iso:country":"TH",
    "name:tha_x_preferred":[
        "\u0e1a\u0e49\u0e32\u0e19\u0e1b\u0e39\u0e22\u0e39\u0e2e\u0e35\u0e40\u0e25"
    ],
    "wof:name":"Ban Pu Yu Hi Le",
    "wof:placetype":"locality"
},
  "geometry": {"coordinates":[102.03888999999999,6.24175],"type":"Point"}
}